{
  "type": "Feature",
  "properties": {
    "iso:country":"GB",
    "wof:name":"DE7 6JF",
    "wof:placetype":"postalcode"
},
  "geometry": {"coordinates":[-1.35555978046579,52.97185287994682],"type":"Point"}
}