{
  "type": "Feature",
  "properties": {
    "iso:country":"GB",
    "wof:name":"SO40 7AF",
    "wof:placetype":"postalcode"
},
  "geometry": {"coordinates":[-1.53181929568286,50.89417696605511],"type":"Point"}
}