{
  "type": "Feature",
  "properties": {
    "iso:country": "GB",
    "wof:name": "W4 5QL",
    "wof:placetype": "postalcode"
  },
  "geometry": {"coordinates":[-0.283482,51.493226],"type":"Point"}
}
