{
  "type": "Feature",
  "properties": {
    "iso:country":"GB",
    "wof:name":"W4 5QL",
    "wof:placetype":"postalcode"
},
  "geometry": {"coordinates":[-0.28348226716791,51.49322596431625],"type":"Point"}
}