{
  "type": "Feature",
  "properties": {
    "date:inception_lower": "1983-07-01",
    "date:inception_upper": "1983-07-01",
    "iso:country": "GB",
    "wof:name": "HD4 7SP",
    "wof:placetype": "postalcode"
  },
  "geometry": {"coordinates":[-1.803575,53.614863],"type":"Point"}
}
