{
  "type": "Feature",
  "properties": {
    "date:inception_lower": "2018-05-01",
    "date:inception_upper": "2018-05-01",
    "iso:country": "GB",
    "wof:name": "TN34 1DP",
    "wof:placetype": "postalcode"
  },
  "geometry": {"coordinates":[0.565981,50.860143],"type":"Point"}
}
