{
  "type": "Feature",
  "properties": {
    "iso:country":"GB",
    "wof:name":"WR3 8SL",
    "wof:placetype":"postalcode"
},
  "geometry": {"coordinates":[-2.18188004695713,52.22466318720955],"type":"Point"}
}