{
  "type": "Feature",
  "properties": {
    "date:inception_lower": "1994-12-01",
    "date:inception_upper": "1994-12-01",
    "iso:country": "GB",
    "wof:name": "SO40 8FJ",
    "wof:placetype": "postalcode"
  },
  "geometry": {"coordinates":[-1.522335,50.916467],"type":"Point"}
}
