{
  "type": "Feature",
  "properties": {
    "iso:country":"GB",
    "wof:name":"SO40 8FJ",
    "wof:placetype":"postalcode"
},
  "geometry": {"coordinates":[-1.52233510686471,50.91646681490605],"type":"Point"}
}