{
  "type": "Feature",
  "properties": {
    "iso:country":"GB",
    "wof:name":"M9 4BU",
    "wof:placetype":"postalcode"
},
  "geometry": {"coordinates":[-2.20839382589061,53.51609640218023],"type":"Point"}
}