{
  "type": "Feature",
  "properties": {
    "date:inception_lower": "1984-10-01",
    "date:inception_upper": "1984-10-01",
    "iso:country": "GB",
    "wof:name": "GU9 9HY",
    "wof:placetype": "postalcode"
  },
  "geometry": {"coordinates":[-0.76479,51.224858],"type":"Point"}
}
