{
  "type": "Feature",
  "properties": {
    "iso:country":"GB",
    "wof:name":"GU9 9HY",
    "wof:placetype":"postalcode"
},
  "geometry": {"coordinates":[-0.7641671181447,51.22469181280259],"type":"Point"}
}