{
  "type": "Feature",
  "properties": {
    "iso:country":"GB",
    "wof:name":"M45 7EF",
    "wof:placetype":"postalcode"
},
  "geometry": {"coordinates":[-2.29143756032368,53.54147664756644],"type":"Point"}
}