{
  "type": "Feature",
  "properties": {
    "date:inception_lower": "1994-05-01",
    "date:inception_upper": "1994-05-01",
    "iso:country": "GB",
    "wof:name": "M45 7EF",
    "wof:placetype": "postalcode"
  },
  "geometry": {"coordinates":[-2.291438,53.541477],"type":"Point"}
}
