{
  "type": "Feature",
  "properties": {
    "iso:country": "GB",
    "wof:name": "YO13 9DU",
    "wof:placetype": "postalcode"
  },
  "geometry": {"coordinates":[-0.552846,54.245783],"type":"Point"}
}
