{
  "type": "Feature",
  "properties": {
    "iso:country":"GB",
    "wof:name":"YO13 9DU",
    "wof:placetype":"postalcode"
},
  "geometry": {"coordinates":[-0.55284599047197,54.24578302905711],"type":"Point"}
}