{
  "type": "Feature",
  "properties": {
    "iso:country":"GB",
    "wof:name":"FY1 6RR",
    "wof:placetype":"postalcode"
},
  "geometry": {"coordinates":[-3.0349032263461,53.80709943475577],"type":"Point"}
}