{
  "type": "Feature",
  "properties": {
    "iso:country":"GB",
    "wof:name":"KT10 9DP",
    "wof:placetype":"postalcode"
},
  "geometry": {"coordinates":[-0.36422979187481,51.36780322458348],"type":"Point"}
}