{
  "type": "Feature",
  "properties": {
    "iso:country":"GB",
    "wof:name":"GL52 2ET",
    "wof:placetype":"postalcode"
},
  "geometry": {"coordinates":[-2.06586504647104,51.90080896907571],"type":"Point"}
}