{
  "type": "Feature",
  "properties": {
    "date:inception_lower": "1980-01-01",
    "date:inception_upper": "1980-01-01",
    "iso:country": "GB",
    "wof:name": "WA8 8AD",
    "wof:placetype": "postalcode"
  },
  "geometry": {"coordinates":[-2.763164,53.366606],"type":"Point"}
}
