{
  "type": "Feature",
  "properties": {
    "iso:country":"GB",
    "wof:name":"B23 5DN",
    "wof:placetype":"postalcode"
},
  "geometry": {"coordinates":[-1.86406179536265,52.53926287704882],"type":"Point"}
}