{
  "type": "Feature",
  "properties": {
    "iso:country":"GB",
    "wof:name":"UB7 7FL",
    "wof:placetype":"postalcode"
},
  "geometry": {"coordinates":[-0.47888159634007,51.51425802414894],"type":"Point"}
}