{
  "type": "Feature",
  "properties": {
    "iso:country":"GB",
    "wof:name":"PO5 3PS",
    "wof:placetype":"postalcode"
},
  "geometry": {"coordinates":[-1.08862541132493,50.78322404385236],"type":"Point"}
}