{
  "type": "Feature",
  "properties": {
    "iso:country": "GB",
    "wof:name": "PO5 3PS",
    "wof:placetype": "postalcode"
  },
  "geometry": {"coordinates":[-1.088625,50.783224],"type":"Point"}
}
