{
  "type": "Feature",
  "properties": {
    "iso:country": "GB",
    "wof:name": "PL13 2DL",
    "wof:placetype": "postalcode"
  },
  "geometry": {"coordinates":[-4.45372,50.345657],"type":"Point"}
}
