{
  "type": "Feature",
  "properties": {
    "iso:country":"GB",
    "wof:name":"PL13 2DL",
    "wof:placetype":"postalcode"
},
  "geometry": {"coordinates":[-4.45372036153584,50.34565715325411],"type":"Point"}
}