{
  "type": "Feature",
  "properties": {
    "date:inception_lower": "1980-01-01",
    "date:inception_upper": "1980-01-01",
    "iso:country": "GB",
    "wof:name": "ST15 8JT",
    "wof:placetype": "postalcode"
  },
  "geometry": {"coordinates":[-2.149641,52.9031],"type":"Point"}
}
