{
  "type": "Feature",
  "properties": {
    "iso:country":"GB",
    "wof:name":"HD6 3QG",
    "wof:placetype":"postalcode"
},
  "geometry": {"coordinates":[-1.8025555140779,53.68112257275511],"type":"Point"}
}