{
  "type": "Feature",
  "properties": {
    "iso:country":"GB",
    "wof:name":"IP31 3FE",
    "wof:placetype":"postalcode"
},
  "geometry": {"coordinates":[0.94106971187275,52.30205633424992],"type":"Point"}
}