{
  "type": "Feature",
  "properties": {
    "date:inception_lower": "2009-06-01",
    "date:inception_upper": "2009-06-01",
    "iso:country": "GB",
    "wof:name": "IP31 3FE",
    "wof:placetype": "postalcode"
  },
  "geometry": {"coordinates":[0.941102,52.302083],"type":"Point"}
}
