{
  "type": "Feature",
  "properties": {
    "date:inception_lower":"1995-12-01",
    "date:inception_upper":"1995-12-31",
    "iso:country":"GB",
    "wof:name":"SY4 5EU",
    "wof:placetype":"postalcode"
},
  "geometry": {"coordinates":[-2.721207,52.860703],"type":"Point"}
}