{
  "type": "Feature",
  "properties": {
    "iso:country":"GB",
    "wof:name":"SY4 5EU",
    "wof:placetype":"postalcode"
},
  "geometry": {"coordinates":[-2.72120692098391,52.86070339920526],"type":"Point"}
}