{
  "type": "Feature",
  "properties": {
    "date:inception_lower": "1995-12-01",
    "date:inception_upper": "1995-12-01",
    "iso:country": "GB",
    "wof:name": "SY4 5EU",
    "wof:placetype": "postalcode"
  },
  "geometry": {"coordinates":[-2.721144,52.860718],"type":"Point"}
}
