{
  "type": "Feature",
  "properties": {
    "iso:country":"GB",
    "wof:name":"LU1 5QP",
    "wof:placetype":"postalcode"
},
  "geometry": {"coordinates":[-0.44178919052386,51.87647864924165],"type":"Point"}
}