{
  "type": "Feature",
  "properties": {
    "iso:country":"GB",
    "wof:name":"DL2 3TY",
    "wof:placetype":"postalcode"
},
  "geometry": {"coordinates":[-1.66436762369462,54.56508790743956],"type":"Point"}
}