{
  "type": "Feature",
  "properties": {
    "date:inception_lower": "1980-01-01",
    "date:inception_upper": "1980-01-01",
    "iso:country": "GB",
    "wof:name": "OX4 4LH",
    "wof:placetype": "postalcode"
  },
  "geometry": {"coordinates":[-1.2212,51.722156],"type":"Point"}
}
