{
  "type": "Feature",
  "properties": {
    "iso:country": "GB",
    "wof:name": "OX4 4LH",
    "wof:placetype": "postalcode"
  },
  "geometry": {"coordinates":[-1.220638,51.722291],"type":"Point"}
}
