{
  "type": "Feature",
  "properties": {
    "iso:country": "GB",
    "wof:name": "CF23 6BP",
    "wof:placetype": "postalcode"
  },
  "geometry": {"coordinates":[-3.16414,51.512224],"type":"Point"}
}
