{
  "type": "Feature",
  "properties": {
    "iso:country":"GB",
    "wof:name":"CF23 6BP",
    "wof:placetype":"postalcode"
},
  "geometry": {"coordinates":[-3.16413974900493,51.51222371578324],"type":"Point"}
}