{
  "type": "Feature",
  "properties": {
    "iso:country": "GB",
    "wof:name": "CH66 4TF",
    "wof:placetype": "postalcode"
  },
  "geometry": {"coordinates":[-2.95018,53.278888],"type":"Point"}
}
