{
  "type": "Feature",
  "properties": {
    "date:inception_lower": "2019-04-01",
    "date:inception_upper": "2019-04-01",
    "iso:country": "GB",
    "wof:name": "HP27 9FE",
    "wof:placetype": "postalcode"
  },
  "geometry": {"coordinates":[-0.860214,51.735206],"type":"Point"}
}
