{
  "type": "Feature",
  "properties": {
    "iso:country": "GB",
    "wof:name": "HP27 9FE",
    "wof:placetype": "postalcode"
  },
  "geometry": {"coordinates":[-0.860214,51.735206],"type":"Point"}
}
