{
  "type": "Feature",
  "properties": {
    "iso:country":"GB",
    "wof:name":"HX6 2RR",
    "wof:placetype":"postalcode"
},
  "geometry": {"coordinates":[-1.91797927241356,53.71319172568184],"type":"Point"}
}