{
  "type": "Feature",
  "properties": {
    "iso:country":"GB",
    "wof:name":"NN4 8HB",
    "wof:placetype":"postalcode"
},
  "geometry": {"coordinates":[-0.90594982266085,52.22559750881786],"type":"Point"}
}