{
  "type": "Feature",
  "properties": {
    "iso:country": "GB",
    "wof:name": "NN4 8HB",
    "wof:placetype": "postalcode"
  },
  "geometry": {"coordinates":[-0.905934,52.225675],"type":"Point"}
}
