{
  "type": "Feature",
  "properties": {
    "iso:country":"GB",
    "wof:name":"EX13 7BB",
    "wof:placetype":"postalcode"
},
  "geometry": {"coordinates":[-2.97412028730373,50.8164176558483],"type":"Point"}
}