{
  "type": "Feature",
  "properties": {
    "iso:country":"GB",
    "wof:name":"CO3 0PW",
    "wof:placetype":"postalcode"
},
  "geometry": {"coordinates":[0.83104003155128,51.88841400417262],"type":"Point"}
}