{
  "type": "Feature",
  "properties": {
    "iso:country":"GB",
    "wof:name":"NP20 6GQ",
    "wof:placetype":"postalcode"
},
  "geometry": {"coordinates":[-3.00825346669244,51.60516699740842],"type":"Point"}
}