{
  "type": "Feature",
  "properties": {
    "iso:country": "GB",
    "wof:name": "NP20 6GQ",
    "wof:placetype": "postalcode"
  },
  "geometry": {"coordinates":[-3.008253,51.605167],"type":"Point"}
}
