{
  "type": "Feature",
  "properties": {
    "iso:country":"GB",
    "wof:name":"BD10 8JZ",
    "wof:placetype":"postalcode"
},
  "geometry": {"coordinates":[-1.73585484468792,53.84241936661836],"type":"Point"}
}