{
  "type": "Feature",
  "properties": {
    "iso:country":"GB",
    "wof:name":"SO21 2LX",
    "wof:placetype":"postalcode"
},
  "geometry": {"coordinates":[-1.37247849754186,51.09027236401334],"type":"Point"}
}