{
  "type": "Feature",
  "properties": {
    "date:inception_lower": "1980-01-01",
    "date:inception_upper": "1980-01-01",
    "iso:country": "GB",
    "wof:name": "KY12 0TP",
    "wof:placetype": "postalcode"
  },
  "geometry": {"coordinates":[-3.405715,56.099016],"type":"Point"}
}
