{
  "type": "Feature",
  "properties": {
    "iso:country":"GB",
    "wof:name":"KY12 0TP",
    "wof:placetype":"postalcode"
},
  "geometry": {"coordinates":[-3.40571748150856,56.09902102616618],"type":"Point"}
}