{
  "type": "Feature",
  "properties": {
    "iso:country":"GB",
    "wof:name":"B90 1BF",
    "wof:placetype":"postalcode"
},
  "geometry": {"coordinates":[-1.84922775829271,52.40596853639926],"type":"Point"}
}