{
  "type": "Feature",
  "properties": {
    "iso:country":"GB",
    "wof:name":"G14 9BE",
    "wof:placetype":"postalcode"
},
  "geometry": {"coordinates":[-4.34708650066104,55.88281438548444],"type":"Point"}
}