{
  "type": "Feature",
  "properties": {
    "iso:country": "GB",
    "wof:name": "DD8 4ET",
    "wof:placetype": "postalcode"
  },
  "geometry": {"coordinates":[-3.004756,56.672984],"type":"Point"}
}
