{
  "type": "Feature",
  "properties": {
    "iso:country":"GB",
    "wof:name":"SN14 6QF",
    "wof:placetype":"postalcode"
},
  "geometry": {"coordinates":[-2.13973990482223,51.46887967591231],"type":"Point"}
}