{
  "type": "Feature",
  "properties": {
    "iso:country": "GB",
    "wof:name": "SN14 6QF",
    "wof:placetype": "postalcode"
  },
  "geometry": {"coordinates":[-2.13974,51.46888],"type":"Point"}
}
