{
  "type": "Feature",
  "properties": {
    "iso:country": "GB",
    "wof:name": "WA5 2TQ",
    "wof:placetype": "postalcode"
  },
  "geometry": {"coordinates":[-2.643093,53.38794],"type":"Point"}
}
