{
  "type": "Feature",
  "properties": {
    "iso:country":"GB",
    "wof:name":"WA5 2TQ",
    "wof:placetype":"postalcode"
},
  "geometry": {"coordinates":[-2.64306281502223,53.38791566818207],"type":"Point"}
}