{
  "type": "Feature",
  "properties": {
    "date:inception_lower": "1980-01-01",
    "date:inception_upper": "1980-01-01",
    "iso:country": "GB",
    "wof:name": "WA5 2TQ",
    "wof:placetype": "postalcode"
  },
  "geometry": {"coordinates":[-2.643093,53.38794],"type":"Point"}
}
