{
  "type": "Feature",
  "properties": {
    "iso:country":"GB",
    "wof:name":"NG34 8PN",
    "wof:placetype":"postalcode"
},
  "geometry": {"coordinates":[-0.45493391139282,52.9811356507748],"type":"Point"}
}