{
  "type": "Feature",
  "properties": {
    "iso:country":"GB",
    "wof:name":"WA5 3SQ",
    "wof:placetype":"postalcode"
},
  "geometry": {"coordinates":[-2.63625136511074,53.39495439589723],"type":"Point"}
}