{
  "type": "Feature",
  "properties": {
    "iso:country": "GB",
    "wof:name": "WA5 3SQ",
    "wof:placetype": "postalcode"
  },
  "geometry": {"coordinates":[-2.636251,53.394954],"type":"Point"}
}
