{
  "type": "Feature",
  "properties": {
    "iso:country":"GB",
    "wof:name":"WN5 9XR",
    "wof:placetype":"postalcode"
},
  "geometry": {"coordinates":[-2.67911617359273,53.54248239399715],"type":"Point"}
}