{
  "type": "Feature",
  "properties": {
    "iso:country": "GB",
    "wof:name": "WN5 9XR",
    "wof:placetype": "postalcode"
  },
  "geometry": {"coordinates":[-2.679116,53.542482],"type":"Point"}
}
