{
  "type": "Feature",
  "properties": {
    "date:inception_lower": "1986-07-01",
    "date:inception_upper": "1986-07-01",
    "iso:country": "GB",
    "wof:name": "ST7 2XF",
    "wof:placetype": "postalcode"
  },
  "geometry": {"coordinates":[-2.314958,53.094714],"type":"Point"}
}
