{
  "type": "Feature",
  "properties": {
    "iso:country":"GB",
    "wof:name":"ST7 2XF",
    "wof:placetype":"postalcode"
},
  "geometry": {"coordinates":[-2.31495827727694,53.09471353357224],"type":"Point"}
}