{
  "type": "Feature",
  "properties": {
    "iso:country":"GB",
    "wof:name":"TR1 1HR",
    "wof:placetype":"postalcode"
},
  "geometry": {"coordinates":[-5.04804726727287,50.26655643224138],"type":"Point"}
}