{
  "type": "Feature",
  "properties": {
    "iso:country": "GB",
    "wof:name": "SE24 0PL",
    "wof:placetype": "postalcode"
  },
  "geometry": {"coordinates":[-0.109165,51.458981],"type":"Point"}
}
