{
  "type": "Feature",
  "properties": {
    "iso:country":"GB",
    "wof:name":"SG18 0BX",
    "wof:placetype":"postalcode"
},
  "geometry": {"coordinates":[-0.26573136231527,52.09057166169269],"type":"Point"}
}