{
  "type": "Feature",
  "properties": {
    "date:inception_lower":"1980-01-01",
    "date:inception_upper":"1980-01-31",
    "iso:country":"GB",
    "wof:name":"SG18 0BX",
    "wof:placetype":"postalcode"
},
  "geometry": {"coordinates":[-0.265731,52.090572],"type":"Point"}
}