{
  "type": "Feature",
  "properties": {
    "iso:country":"GB",
    "wof:name":"FK10 2BZ",
    "wof:placetype":"postalcode"
},
  "geometry": {"coordinates":[-3.80915397140035,56.12063659117282],"type":"Point"}
}