{
  "type": "Feature",
  "properties": {
    "date:inception_lower": "2013-12-01",
    "date:inception_upper": "2013-12-01",
    "iso:country": "GB",
    "wof:name": "CT15 4FE",
    "wof:placetype": "postalcode"
  },
  "geometry": {"coordinates":[1.273774,51.206652],"type":"Point"}
}
