{
  "type": "Feature",
  "properties": {
    "iso:country":"GB",
    "wof:name":"CT15 4FE",
    "wof:placetype":"postalcode"
},
  "geometry": {"coordinates":[1.2737739185344,51.20665169455816],"type":"Point"}
}