{
  "type": "Feature",
  "properties": {
    "iso:country":"GB",
    "wof:name":"NW1 8DS",
    "wof:placetype":"postalcode"
},
  "geometry": {"coordinates":[-0.1473468238223,51.54550494795055],"type":"Point"}
}