{
  "type": "Feature",
  "properties": {
    "iso:country":"GB",
    "wof:name":"NR31 0BA",
    "wof:placetype":"postalcode"
},
  "geometry": {"coordinates":[1.71515213500237,52.6076160917484],"type":"Point"}
}