{
  "type": "Feature",
  "properties": {
    "iso:country": "GB",
    "wof:name": "CV23 0GA",
    "wof:placetype": "postalcode"
  },
  "geometry": {"coordinates":[-1.300029,52.409325],"type":"Point"}
}
