{
  "type": "Feature",
  "properties": {
    "iso:country":"GB",
    "wof:name":"CV23 0GA",
    "wof:placetype":"postalcode"
},
  "geometry": {"coordinates":[-1.30002864329882,52.40932505431607],"type":"Point"}
}