{
  "type": "Feature",
  "properties": {
    "date:inception_lower":"1999-06-01",
    "date:inception_upper":"1999-06-30",
    "iso:country":"GB",
    "wof:name":"CV23 0GA",
    "wof:placetype":"postalcode"
},
  "geometry": {"coordinates":[-1.300029,52.409325],"type":"Point"}
}