{
  "type": "Feature",
  "properties": {
    "iso:country": "GB",
    "wof:name": "LL18 4GF",
    "wof:placetype": "postalcode"
  },
  "geometry": {"coordinates":[-3.465274,53.322608],"type":"Point"}
}
