{
  "type": "Feature",
  "properties": {
    "iso:country":"GB",
    "wof:name":"CO15 3TD",
    "wof:placetype":"postalcode"
},
  "geometry": {"coordinates":[1.15590114120975,51.79747822013621],"type":"Point"}
}