{
  "type": "Feature",
  "properties": {
    "iso:country":"GB",
    "wof:name":"NP24 6BZ",
    "wof:placetype":"postalcode"
},
  "geometry": {"coordinates":[-3.24141803637674,51.72473370915611],"type":"Point"}
}