{
  "type": "Feature",
  "properties": {
    "iso:country": "GB",
    "wof:name": "RM15 4SP",
    "wof:placetype": "postalcode"
  },
  "geometry": {"coordinates":[0.250207,51.50125],"type":"Point"}
}
