{
  "type": "Feature",
  "properties": {
    "date:inception_lower":"1991-09-01",
    "date:inception_upper":"1991-09-30",
    "iso:country":"GB",
    "wof:name":"NP44 6EZ",
    "wof:placetype":"postalcode"
},
  "geometry": {"coordinates":[-3.060863,51.64067],"type":"Point"}
}