{
  "type": "Feature",
  "properties": {
    "iso:country":"GB",
    "wof:name":"NP44 6EZ",
    "wof:placetype":"postalcode"
},
  "geometry": {"coordinates":[-3.06086299423536,51.64066973250359],"type":"Point"}
}