{
  "type": "Feature",
  "properties": {
    "date:inception_lower":"2018-03-01",
    "date:inception_upper":"2018-03-31",
    "iso:country":"GB",
    "wof:name":"WA1 2JT",
    "wof:placetype":"postalcode"
},
  "geometry": {"coordinates":[-2.58363,53.388201],"type":"Point"}
}