{
  "type": "Feature",
  "properties": {
    "iso:country": "GB",
    "wof:name": "WA1 2JT",
    "wof:placetype": "postalcode"
  },
  "geometry": {"coordinates":[-2.58363,53.388201],"type":"Point"}
}
