{
  "type": "Feature",
  "properties": {
    "date:inception_lower": "2002-08-01",
    "date:inception_upper": "2002-08-01",
    "iso:country": "GB",
    "wof:name": "BN27 2GA",
    "wof:placetype": "postalcode"
  },
  "geometry": {"coordinates":[0.263665,50.858129],"type":"Point"}
}
