{
  "type": "Feature",
  "properties": {
    "iso:country":"GB",
    "wof:name":"CT21 5JQ",
    "wof:placetype":"postalcode"
},
  "geometry": {"coordinates":[1.08481291431253,51.07174122531739],"type":"Point"}
}