{
  "type": "Feature",
  "properties": {
    "iso:country":"GB",
    "wof:name":"EH33 2EA",
    "wof:placetype":"postalcode"
},
  "geometry": {"coordinates":[-2.94868526819196,55.93958021096987],"type":"Point"}
}