{
  "type": "Feature",
  "properties": {
    "iso:country": "GB",
    "wof:name": "MK4 1AY",
    "wof:placetype": "postalcode"
  },
  "geometry": {"coordinates":[-0.757174,52.013348],"type":"Point"}
}
