{
  "type": "Feature",
  "properties": {
    "iso:country": "GB",
    "wof:name": "NN10 0AH",
    "wof:placetype": "postalcode"
  },
  "geometry": {"coordinates":[-0.597994,52.293101],"type":"Point"}
}
