{
  "type": "Feature",
  "properties": {
    "iso:country":"GB",
    "wof:name":"NN10 0AH",
    "wof:placetype":"postalcode"
},
  "geometry": {"coordinates":[-0.59799383596671,52.29310050793189],"type":"Point"}
}