{
  "type": "Feature",
  "properties": {
    "iso:country":"GB",
    "wof:name":"NG5 8UD",
    "wof:placetype":"postalcode"
},
  "geometry": {"coordinates":[-1.12590705784087,53.01405742331397],"type":"Point"}
}