{
  "type": "Feature",
  "properties": {
    "date:inception_lower": "2014-06-01",
    "date:inception_upper": "2014-06-01",
    "iso:country": "GB",
    "wof:name": "NG5 8UD",
    "wof:placetype": "postalcode"
  },
  "geometry": {"coordinates":[-1.125784,53.014094],"type":"Point"}
}
