{
  "type": "Feature",
  "properties": {
    "iso:country": "GB",
    "wof:name": "W5 1EW",
    "wof:placetype": "postalcode"
  },
  "geometry": {"coordinates":[-0.292955,51.526555],"type":"Point"}
}
