{
  "type": "Feature",
  "properties": {
    "date:inception_lower": "2023-05-01",
    "date:inception_upper": "2023-05-01",
    "iso:country": "GB",
    "wof:name": "DN11 8GR",
    "wof:placetype": "postalcode"
  },
  "geometry": {"coordinates":[-1.055002,53.412206],"type":"Point"}
}
