{
  "type": "Feature",
  "properties": {
    "date:inception_lower":"1980-01-01",
    "date:inception_upper":"1980-01-31",
    "iso:country":"GB",
    "wof:name":"SG1 4PJ",
    "wof:placetype":"postalcode"
},
  "geometry": {"coordinates":[-0.174124,51.926976],"type":"Point"}
}