{
  "type": "Feature",
  "properties": {
    "iso:country":"GB",
    "wof:name":"TQ5 8PU",
    "wof:placetype":"postalcode"
},
  "geometry": {"coordinates":[-3.53414304395745,50.39310752158108],"type":"Point"}
}