{
  "type": "Feature",
  "properties": {
    "iso:country":"GB",
    "wof:name":"NN13 5LU",
    "wof:placetype":"postalcode"
},
  "geometry": {"coordinates":[-1.21366327464421,51.99622207538118],"type":"Point"}
}