{
  "type": "Feature",
  "properties": {
    "iso:country":"GB",
    "wof:name":"NG3 3JL",
    "wof:placetype":"postalcode"
},
  "geometry": {"coordinates":[-1.13118345472918,52.96505855111593],"type":"Point"}
}