{
  "type": "Feature",
  "properties": {
    "iso:country": "GB",
    "wof:name": "DN9 1RZ",
    "wof:placetype": "postalcode"
  },
  "geometry": {"coordinates":[-0.813987,53.553269],"type":"Point"}
}
