{
  "type": "Feature",
  "properties": {
    "iso:country":"GB",
    "wof:name":"BR5 3DN",
    "wof:placetype":"postalcode"
},
  "geometry": {"coordinates":[0.1073184026255,51.41008178678283],"type":"Point"}
}