{
  "type": "Feature",
  "properties": {
    "iso:country":"GB",
    "wof:name":"S11 9JF",
    "wof:placetype":"postalcode"
},
  "geometry": {"coordinates":[-1.51033023065297,53.34972473806883],"type":"Point"}
}