{
  "type": "Feature",
  "properties": {
    "iso:country":"GB",
    "wof:name":"FK3 8PF",
    "wof:placetype":"postalcode"
},
  "geometry": {"coordinates":[-3.73406813499103,56.0070148238285],"type":"Point"}
}