{
  "type": "Feature",
  "properties": {
    "iso:country":"GB",
    "wof:name":"SY11 1BS",
    "wof:placetype":"postalcode"
},
  "geometry": {"coordinates":[-3.05991493187237,52.8666936676774],"type":"Point"}
}