{
  "type": "Feature",
  "properties": {
    "iso:country":"GB",
    "wof:name":"NE24 4BG",
    "wof:placetype":"postalcode"
},
  "geometry": {"coordinates":[-1.53414869388771,55.10881632301272],"type":"Point"}
}