{
  "type": "Feature",
  "properties": {
    "date:inception_lower": "1999-12-01",
    "date:inception_upper": "1999-12-01",
    "iso:country": "GB",
    "wof:name": "OX1 3TJ",
    "wof:placetype": "postalcode"
  },
  "geometry": {"coordinates":[-1.248166,51.757627],"type":"Point"}
}
