{
  "type": "Feature",
  "properties": {
    "iso:country":"GB",
    "wof:name":"NW9 5GJ",
    "wof:placetype":"postalcode"
},
  "geometry": {"coordinates":[-0.24959967533475,51.60335786073942],"type":"Point"}
}