{
  "type": "Feature",
  "properties": {
    "iso:country":"GB",
    "wof:name":"HU5 4HQ",
    "wof:placetype":"postalcode"
},
  "geometry": {"coordinates":[-0.38197015688065,53.75908971696919],"type":"Point"}
}