{
  "type": "Feature",
  "properties": {
    "iso:country": "GB",
    "wof:name": "HU5 4HQ",
    "wof:placetype": "postalcode"
  },
  "geometry": {"coordinates":[-0.38197,53.75909],"type":"Point"}
}
