{
  "type": "Feature",
  "properties": {
    "iso:country":"GB",
    "wof:name":"SN4 9AR",
    "wof:placetype":"postalcode"
},
  "geometry": {"coordinates":[-1.79176534744152,51.525901720545],"type":"Point"}
}