{
  "type": "Feature",
  "properties": {
    "iso:country": "GB",
    "wof:name": "AL5 3LR",
    "wof:placetype": "postalcode"
  },
  "geometry": {"coordinates":[-0.37759,51.829312],"type":"Point"}
}
