{
  "type": "Feature",
  "properties": {
    "iso:country":"GB",
    "wof:name":"AL5 3LR",
    "wof:placetype":"postalcode"
},
  "geometry": {"coordinates":[-0.37758969069366,51.82931229802261],"type":"Point"}
}