{
  "type": "Feature",
  "properties": {
    "iso:country": "GB",
    "wof:name": "NP4 7JL",
    "wof:placetype": "postalcode"
  },
  "geometry": {"coordinates":[-3.069913,51.732238],"type":"Point"}
}
