{
  "type": "Feature",
  "properties": {
    "iso:country":"GB",
    "wof:name":"NP4 7JL",
    "wof:placetype":"postalcode"
},
  "geometry": {"coordinates":[-3.06991331237007,51.7322383412533],"type":"Point"}
}