{
  "type": "Feature",
  "properties": {
    "iso:country": "GB",
    "wof:name": "RG12 9JD",
    "wof:placetype": "postalcode"
  },
  "geometry": {"coordinates":[-0.730346,51.40546],"type":"Point"}
}
