{
  "type": "Feature",
  "properties": {
    "iso:country":"GB",
    "wof:name":"RG12 9JD",
    "wof:placetype":"postalcode"
},
  "geometry": {"coordinates":[-0.73034555204685,51.40546031634079],"type":"Point"}
}