{
  "type": "Feature",
  "properties": {
    "iso:country": "GB",
    "wof:name": "PH7 3BT",
    "wof:placetype": "postalcode"
  },
  "geometry": {"coordinates":[-3.838367,56.372813],"type":"Point"}
}
