{
  "type": "Feature",
  "properties": {
    "date:inception_lower":"1980-01-01",
    "date:inception_upper":"1980-01-31",
    "iso:country":"GB",
    "wof:name":"PH7 3BT",
    "wof:placetype":"postalcode"
},
  "geometry": {"coordinates":[-3.838367,56.372813],"type":"Point"}
}