{
  "type": "Feature",
  "properties": {
    "date:inception_lower": "1980-01-01",
    "date:inception_upper": "1980-01-01",
    "iso:country": "GB",
    "wof:name": "G82 1RH",
    "wof:placetype": "postalcode"
  },
  "geometry": {"coordinates":[-4.554892,55.942295],"type":"Point"}
}
