{
  "type": "Feature",
  "properties": {
    "iso:country":"GB",
    "wof:name":"NR9 3JW",
    "wof:placetype":"postalcode"
},
  "geometry": {"coordinates":[1.1894160431839,52.60041650036615],"type":"Point"}
}