{
  "type": "Feature",
  "properties": {
    "iso:country":"GB",
    "wof:name":"SA6 5SR",
    "wof:placetype":"postalcode"
},
  "geometry": {"coordinates":[-3.90925835339402,51.69123718023706],"type":"Point"}
}