{
  "type": "Feature",
  "properties": {
    "date:inception_lower":"1980-01-01",
    "date:inception_upper":"1980-01-31",
    "iso:country":"GB",
    "wof:name":"SA6 5SR",
    "wof:placetype":"postalcode"
},
  "geometry": {"coordinates":[-3.909277,51.691242],"type":"Point"}
}