{
  "type": "Feature",
  "properties": {
    "iso:country": "GB",
    "wof:name": "SA6 5SR",
    "wof:placetype": "postalcode"
  },
  "geometry": {"coordinates":[-3.909377,51.691223],"type":"Point"}
}
