{
  "type": "Feature",
  "properties": {
    "iso:country": "GB",
    "wof:name": "SA6 5SR",
    "wof:placetype": "postalcode"
  },
  "geometry": {"coordinates":[-3.909277,51.691242],"type":"Point"}
}
