{
  "type": "Feature",
  "properties": {
    "date:inception_lower": "2001-06-01",
    "date:inception_upper": "2001-06-01",
    "iso:country": "GB",
    "wof:name": "PR26 8LL",
    "wof:placetype": "postalcode"
  },
  "geometry": {"coordinates":[-2.727587,53.669932],"type":"Point"}
}
