{
  "type": "Feature",
  "properties": {
    "iso:country":"GB",
    "wof:name":"PR26 8LL",
    "wof:placetype":"postalcode"
},
  "geometry": {"coordinates":[-2.72758698822924,53.66993220767917],"type":"Point"}
}