{
  "type": "Feature",
  "properties": {
    "date:inception_lower": "1980-01-01",
    "date:inception_upper": "1980-01-01",
    "iso:country": "GB",
    "wof:name": "BA8 0RE",
    "wof:placetype": "postalcode"
  },
  "geometry": {"coordinates":[-2.392376,50.97499],"type":"Point"}
}
