{
  "type": "Feature",
  "properties": {
    "iso:country":"GB",
    "wof:name":"BA8 0RE",
    "wof:placetype":"postalcode"
},
  "geometry": {"coordinates":[-2.39237588103902,50.97499015860642],"type":"Point"}
}