{
  "type": "Feature",
  "properties": {
    "iso:country":"GB",
    "wof:name":"E17 3DE",
    "wof:placetype":"postalcode"
},
  "geometry": {"coordinates":[-0.01027198803333,51.58923927236754],"type":"Point"}
}