{
  "type": "Feature",
  "properties": {
    "iso:country":"GB",
    "wof:name":"W1T 5DD",
    "wof:placetype":"postalcode"
},
  "geometry": {"coordinates":[-0.13757980464373,51.52332771991433],"type":"Point"}
}