{
  "type": "Feature",
  "properties": {
    "iso:country":"GB",
    "wof:name":"HU8 9SL",
    "wof:placetype":"postalcode"
},
  "geometry": {"coordinates":[-0.26163416544161,53.77989602354289],"type":"Point"}
}