{
  "type": "Feature",
  "properties": {
    "date:inception_lower": "1980-01-01",
    "date:inception_upper": "1980-01-01",
    "iso:country": "GB",
    "wof:name": "HU8 9SL",
    "wof:placetype": "postalcode"
  },
  "geometry": {"coordinates":[-0.261634,53.779896],"type":"Point"}
}
