{
  "type": "Feature",
  "properties": {
    "iso:country": "GB",
    "wof:name": "TN21 0SY",
    "wof:placetype": "postalcode"
  },
  "geometry": {"coordinates":[0.218622,50.973931],"type":"Point"}
}
