{
  "type": "Feature",
  "properties": {
    "iso:country":"GB",
    "wof:name":"BN6 8AW",
    "wof:placetype":"postalcode"
},
  "geometry": {"coordinates":[-0.14334869725548,50.92426694558676],"type":"Point"}
}