{
  "type": "Feature",
  "properties": {
    "iso:country": "GB",
    "wof:name": "HA3 8QW",
    "wof:placetype": "postalcode"
  },
  "geometry": {"coordinates":[-0.319613,51.597691],"type":"Point"}
}
