{
  "type": "Feature",
  "properties": {
    "iso:country":"GB",
    "wof:name":"HA3 8QW",
    "wof:placetype":"postalcode"
},
  "geometry": {"coordinates":[-0.31961333362648,51.59769082191593],"type":"Point"}
}