{
  "type": "Feature",
  "properties": {
    "iso:country": "GB",
    "wof:name": "CR2 7DF",
    "wof:placetype": "postalcode"
  },
  "geometry": {"coordinates":[-0.094423,51.360092],"type":"Point"}
}
