{
  "type": "Feature",
  "properties": {
    "iso:country":"GB",
    "wof:name":"CR2 7DF",
    "wof:placetype":"postalcode"
},
  "geometry": {"coordinates":[-0.09442327844447,51.36009223847513],"type":"Point"}
}