{
  "type": "Feature",
  "properties": {
    "iso:country":"GB",
    "wof:name":"S63 7BN",
    "wof:placetype":"postalcode"
},
  "geometry": {"coordinates":[-1.33883841484839,53.49705894394097],"type":"Point"}
}