{
  "type": "Feature",
  "properties": {
    "iso:country":"GB",
    "wof:name":"BN14 9HB",
    "wof:placetype":"postalcode"
},
  "geometry": {"coordinates":[-0.36870324284799,50.83318682074179],"type":"Point"}
}