{
  "type": "Feature",
  "properties": {
    "iso:country":"GB",
    "wof:name":"BA12 0LF",
    "wof:placetype":"postalcode"
},
  "geometry": {"coordinates":[-2.0078790873053,51.19994870333783],"type":"Point"}
}