{
  "type": "Feature",
  "properties": {
    "date:inception_lower":"1980-01-01",
    "date:inception_upper":"1980-01-31",
    "iso:country":"GB",
    "wof:name":"BA12 0LF",
    "wof:placetype":"postalcode"
},
  "geometry": {"coordinates":[-2.007879,51.199949],"type":"Point"}
}