{
  "type": "Feature",
  "properties": {
    "iso:country":"GB",
    "wof:name":"ST6 1RB",
    "wof:placetype":"postalcode"
},
  "geometry": {"coordinates":[-2.17732220583912,53.04816540274511],"type":"Point"}
}