{
  "type": "Feature",
  "properties": {
    "date:inception_lower":"1980-01-01",
    "date:inception_upper":"1980-01-31",
    "iso:country":"GB",
    "wof:name":"ST6 1RB",
    "wof:placetype":"postalcode"
},
  "geometry": {"coordinates":[-2.177322,53.048165],"type":"Point"}
}