{
  "type": "Feature",
  "properties": {
    "iso:country":"GB",
    "wof:name":"CH7 2AA",
    "wof:placetype":"postalcode"
},
  "geometry": {"coordinates":[-3.0710731418951,53.16645867780682],"type":"Point"}
}