{
  "type": "Feature",
  "properties": {
    "date:inception_lower": "1980-01-01",
    "date:inception_upper": "1980-01-01",
    "iso:country": "GB",
    "wof:name": "CH7 2AA",
    "wof:placetype": "postalcode"
  },
  "geometry": {"coordinates":[-3.071073,53.166459],"type":"Point"}
}
