{
  "type": "Feature",
  "properties": {
    "date:inception_lower":"1994-12-01",
    "date:inception_upper":"1994-12-31",
    "iso:country":"GB",
    "wof:name":"GL51 0QW",
    "wof:placetype":"postalcode"
},
  "geometry": {"coordinates":[-2.119314,51.914595],"type":"Point"}
}