{
  "type": "Feature",
  "properties": {
    "iso:country": "GB",
    "wof:name": "GL51 0QW",
    "wof:placetype": "postalcode"
  },
  "geometry": {"coordinates":[-2.119314,51.914595],"type":"Point"}
}
