{
  "type": "Feature",
  "properties": {
    "iso:country":"GB",
    "wof:name":"GL51 0QW",
    "wof:placetype":"postalcode"
},
  "geometry": {"coordinates":[-2.11931410768948,51.91459471421083],"type":"Point"}
}