{
  "type": "Feature",
  "properties": {
    "iso:country":"GB",
    "wof:name":"SE9 4SB",
    "wof:placetype":"postalcode"
},
  "geometry": {"coordinates":[0.04947935372537,51.43188118286093],"type":"Point"}
}