{
  "type": "Feature",
  "properties": {
    "iso:country": "GB",
    "wof:name": "OX16 2LY",
    "wof:placetype": "postalcode"
  },
  "geometry": {"coordinates":[-1.343634,52.066534],"type":"Point"}
}
