{
  "type": "Feature",
  "properties": {
    "iso:country":"GB",
    "wof:name":"NE21 4HH",
    "wof:placetype":"postalcode"
},
  "geometry": {"coordinates":[-1.72839006182891,54.96071910512379],"type":"Point"}
}