{
  "type": "Feature",
  "properties": {
    "iso:country": "GB",
    "wof:name": "NE21 4HH",
    "wof:placetype": "postalcode"
  },
  "geometry": {"coordinates":[-1.72839,54.960719],"type":"Point"}
}
