{
  "type": "Feature",
  "properties": {
    "iso:country": "GB",
    "wof:name": "TR15 2AT",
    "wof:placetype": "postalcode"
  },
  "geometry": {"coordinates":[-5.227209,50.233198],"type":"Point"}
}
