{
  "type": "Feature",
  "properties": {
    "iso:country":"GB",
    "wof:name":"TR15 2AT",
    "wof:placetype":"postalcode"
},
  "geometry": {"coordinates":[-5.2273059773685,50.23307792155956],"type":"Point"}
}