{
  "type": "Feature",
  "properties": {
    "iso:country":"GB",
    "wof:name":"L30 8RR",
    "wof:placetype":"postalcode"
},
  "geometry": {"coordinates":[-2.95258439590335,53.4911870428537],"type":"Point"}
}