{
  "type": "Feature",
  "properties": {
    "iso:country": "GB",
    "wof:name": "RH13 0SL",
    "wof:placetype": "postalcode"
  },
  "geometry": {"coordinates":[-0.410967,51.061527],"type":"Point"}
}
