{
  "type": "Feature",
  "properties": {
    "iso:country":"GB",
    "wof:name":"NR31 6NS",
    "wof:placetype":"postalcode"
},
  "geometry": {"coordinates":[1.72432222736018,52.58546149387041],"type":"Point"}
}