{
  "type": "Feature",
  "properties": {
    "iso:country":"GB",
    "wof:name":"BN27 3GN",
    "wof:placetype":"postalcode"
},
  "geometry": {"coordinates":[0.24120741462837,50.87519249320946],"type":"Point"}
}