{
  "type": "Feature",
  "properties": {
    "iso:country": "GB",
    "wof:name": "S66 2TJ",
    "wof:placetype": "postalcode"
  },
  "geometry": {"coordinates":[-1.2679,53.422498],"type":"Point"}
}
