{
  "type": "Feature",
  "properties": {
    "date:inception_lower": "1997-06-01",
    "date:inception_upper": "1997-06-01",
    "iso:country": "GB",
    "wof:name": "S66 2TJ",
    "wof:placetype": "postalcode"
  },
  "geometry": {"coordinates":[-1.2679,53.422498],"type":"Point"}
}
