{
  "type": "Feature",
  "properties": {
    "iso:country": "GB",
    "wof:name": "PE9 2HD",
    "wof:placetype": "postalcode"
  },
  "geometry": {"coordinates":[-0.459948,52.656372],"type":"Point"}
}
