{
  "type": "Feature",
  "properties": {
    "iso:country":"GB",
    "wof:name":"PE9 2HD",
    "wof:placetype":"postalcode"
},
  "geometry": {"coordinates":[-0.45994840387572,52.6563717148961],"type":"Point"}
}