{
  "type": "Feature",
  "properties": {
    "iso:country":"GB",
    "wof:name":"CA4 0PN",
    "wof:placetype":"postalcode"
},
  "geometry": {"coordinates":[-2.93107980743128,54.78282496140297],"type":"Point"}
}