{
  "type": "Feature",
  "properties": {
    "date:inception_lower": "1980-01-01",
    "date:inception_upper": "1980-01-01",
    "iso:country": "GB",
    "wof:name": "CA4 0PN",
    "wof:placetype": "postalcode"
  },
  "geometry": {"coordinates":[-2.93108,54.782825],"type":"Point"}
}
