{
  "type": "Feature",
  "properties": {
    "iso:country":"GB",
    "wof:name":"BR3 3AW",
    "wof:placetype":"postalcode"
},
  "geometry": {"coordinates":[-0.01171437888008,51.39393352841308],"type":"Point"}
}