{
  "type": "Feature",
  "properties": {
    "iso:country":"GB",
    "wof:name":"BL1 8DT",
    "wof:placetype":"postalcode"
},
  "geometry": {"coordinates":[-2.43072730258637,53.59291874023416],"type":"Point"}
}