{
  "type": "Feature",
  "properties": {
    "date:inception_lower":"1980-01-01",
    "date:inception_upper":"1980-01-31",
    "iso:country":"GB",
    "wof:name":"BA12 6QZ",
    "wof:placetype":"postalcode"
},
  "geometry": {"coordinates":[-2.325444,51.120986],"type":"Point"}
}