{
  "type": "Feature",
  "properties": {
    "date:inception_lower": "2001-12-01",
    "date:inception_upper": "2001-12-01",
    "iso:country": "GB",
    "wof:name": "CH45 8QS",
    "wof:placetype": "postalcode"
  },
  "geometry": {"coordinates":[-3.068878,53.425644],"type":"Point"}
}
