{
  "type": "Feature",
  "properties": {
    "iso:country": "GB",
    "wof:name": "CH45 8QS",
    "wof:placetype": "postalcode"
  },
  "geometry": {"coordinates":[-3.068878,53.425644],"type":"Point"}
}
