{
  "type": "Feature",
  "properties": {
    "iso:country":"GB",
    "wof:name":"NG9 5AQ",
    "wof:placetype":"postalcode"
},
  "geometry": {"coordinates":[-1.23820621007581,52.90645281521976],"type":"Point"}
}