{
  "type": "Feature",
  "properties": {
    "iso:country":"GB",
    "wof:name":"SE23 1NJ",
    "wof:placetype":"postalcode"
},
  "geometry": {"coordinates":[-0.04109919474082,51.44835800048843],"type":"Point"}
}