{
  "type": "Feature",
  "properties": {
    "iso:country":"GB",
    "wof:name":"NR30 1BH",
    "wof:placetype":"postalcode"
},
  "geometry": {"coordinates":[1.72648150434971,52.6131423309406],"type":"Point"}
}