{
  "type": "Feature",
  "properties": {
    "iso:country":"GB",
    "wof:name":"RG1 6EY",
    "wof:placetype":"postalcode"
},
  "geometry": {"coordinates":[-0.9857219623637,51.44395167447323],"type":"Point"}
}