{
  "type": "Feature",
  "properties": {
    "iso:country": "GB",
    "wof:name": "BA22 9EP",
    "wof:placetype": "postalcode"
  },
  "geometry": {"coordinates":[-2.730068,50.921346],"type":"Point"}
}
