{
  "type": "Feature",
  "properties": {
    "iso:country":"GB",
    "wof:name":"BA22 9EP",
    "wof:placetype":"postalcode"
},
  "geometry": {"coordinates":[-2.73006852553549,50.92134554688909],"type":"Point"}
}