{
  "type": "Feature",
  "properties": {
    "date:inception_lower": "1980-01-01",
    "date:inception_upper": "1980-01-01",
    "iso:country": "GB",
    "wof:name": "FK2 7XF",
    "wof:placetype": "postalcode"
  },
  "geometry": {"coordinates":[-3.780385,56.01229],"type":"Point"}
}
