{
  "type": "Feature",
  "properties": {
    "iso:country": "GB",
    "wof:name": "KY16 0BX",
    "wof:placetype": "postalcode"
  },
  "geometry": {"coordinates":[-2.917798,56.414502],"type":"Point"}
}
