{
  "type": "Feature",
  "properties": {
    "iso:country": "GB",
    "wof:name": "BL9 5BE",
    "wof:placetype": "postalcode"
  },
  "geometry": {"coordinates":[-2.295763,53.601551],"type":"Point"}
}
