{
  "type": "Feature",
  "properties": {
    "iso:country":"GB",
    "wof:name":"BL9 5BE",
    "wof:placetype":"postalcode"
},
  "geometry": {"coordinates":[-2.2955704396799,53.60180517004038],"type":"Point"}
}