{
  "type": "Feature",
  "properties": {
    "iso:country": "GB",
    "wof:name": "NG12 2HX",
    "wof:placetype": "postalcode"
  },
  "geometry": {"coordinates":[-1.01692,52.948266],"type":"Point"}
}
