{
  "type": "Feature",
  "properties": {
    "date:inception_lower": "2001-06-01",
    "date:inception_upper": "2001-06-01",
    "iso:country": "GB",
    "wof:name": "G2 2AA",
    "wof:placetype": "postalcode"
  },
  "geometry": {"coordinates":[-4.25862,55.862787],"type":"Point"}
}
