{
  "type": "Feature",
  "properties": {
    "iso:country":"GB",
    "wof:name":"G32 0HP",
    "wof:placetype":"postalcode"
},
  "geometry": {"coordinates":[-4.15047620181568,55.85619243687854],"type":"Point"}
}