{
  "type": "Feature",
  "properties": {
    "iso:country":"GB",
    "wof:name":"KY2 5JU",
    "wof:placetype":"postalcode"
},
  "geometry": {"coordinates":[-3.16240137879084,56.12180429111684],"type":"Point"}
}