{
  "type": "Feature",
  "properties": {
    "iso:country":"GB",
    "wof:name":"HP4 1AZ",
    "wof:placetype":"postalcode"
},
  "geometry": {"coordinates":[-0.56564582027918,51.76098257732911],"type":"Point"}
}