{
  "type": "Feature",
  "properties": {
    "date:inception_lower": "1980-01-01",
    "date:inception_upper": "1980-01-01",
    "iso:country": "GB",
    "wof:name": "HP4 1AZ",
    "wof:placetype": "postalcode"
  },
  "geometry": {"coordinates":[-0.565646,51.760983],"type":"Point"}
}
