{
  "type": "Feature",
  "properties": {
    "iso:country":"GB",
    "wof:name":"YO17 8QQ",
    "wof:placetype":"postalcode"
},
  "geometry": {"coordinates":[-0.53241738448969,54.17531075494232],"type":"Point"}
}