{
  "type": "Feature",
  "properties": {
    "iso:country":"GB",
    "wof:name":"WN7 2XZ",
    "wof:placetype":"postalcode"
},
  "geometry": {"coordinates":[-2.48159603886768,53.50514150161838],"type":"Point"}
}