{
  "type": "Feature",
  "properties": {
    "iso:country": "GB",
    "wof:name": "NE10 8XU",
    "wof:placetype": "postalcode"
  },
  "geometry": {"coordinates":[-1.544028,54.931915],"type":"Point"}
}
