{
  "type": "Feature",
  "properties": {
    "date:inception_lower": "2015-04-01",
    "date:inception_upper": "2015-04-01",
    "iso:country": "GB",
    "wof:name": "NE10 8XU",
    "wof:placetype": "postalcode"
  },
  "geometry": {"coordinates":[-1.544028,54.931915],"type":"Point"}
}
