{
  "type": "Feature",
  "properties": {
    "iso:country":"GB",
    "wof:name":"NE10 8XU",
    "wof:placetype":"postalcode"
},
  "geometry": {"coordinates":[-1.54402843026935,54.93191498094885],"type":"Point"}
}