{
  "type": "Feature",
  "properties": {
    "iso:country":"GB",
    "wof:name":"PE3 9UP",
    "wof:placetype":"postalcode"
},
  "geometry": {"coordinates":[-0.27667463238629,52.58229028569727],"type":"Point"}
}