{
  "type": "Feature",
  "properties": {
    "date:inception_lower": "2022-12-01",
    "date:inception_upper": "2022-12-01",
    "iso:country": "GB",
    "wof:name": "L30 4UJ",
    "wof:placetype": "postalcode"
  },
  "geometry": {"coordinates":[-2.966043,53.469971],"type":"Point"}
}
