{
  "type": "Feature",
  "properties": {
    "iso:country":"GB",
    "wof:name":"L30 4UJ",
    "wof:placetype":"postalcode"
},
  "geometry": {"coordinates":[-2.96496032844776,53.47066517183247],"type":"Point"}
}