{
  "type": "Feature",
  "properties": {
    "iso:country":"GB",
    "wof:name":"SK14 6AU",
    "wof:placetype":"postalcode"
},
  "geometry": {"coordinates":[-2.01141722504493,53.44033458567869],"type":"Point"}
}