{
  "type": "Feature",
  "properties": {
    "iso:country":"GB",
    "wof:name":"N10 3TR",
    "wof:placetype":"postalcode"
},
  "geometry": {"coordinates":[-0.13663912044008,51.58836417945756],"type":"Point"}
}