{
  "type": "Feature",
  "properties": {
    "date:inception_lower":"1994-12-01",
    "date:inception_upper":"1994-12-31",
    "iso:country":"GB",
    "wof:name":"SO23 0NT",
    "wof:placetype":"postalcode"
},
  "geometry": {"coordinates":[-1.294263,51.064693],"type":"Point"}
}