{
  "type": "Feature",
  "properties": {
    "date:inception_lower":"1980-01-01",
    "date:inception_upper":"1980-01-31",
    "iso:country":"GB",
    "wof:name":"BB1 1DB",
    "wof:placetype":"postalcode"
},
  "geometry": {"coordinates":[-2.477564,53.744175],"type":"Point"}
}