{
  "type": "Feature",
  "properties": {
    "iso:country":"GB",
    "wof:name":"PR1 8PX",
    "wof:placetype":"postalcode"
},
  "geometry": {"coordinates":[-2.7141074332413,53.75707396193609],"type":"Point"}
}