{
  "type": "Feature",
  "properties": {
    "iso:country":"GB",
    "wof:name":"CH4 0JE",
    "wof:placetype":"postalcode"
},
  "geometry": {"coordinates":[-3.04411108094332,53.15078700438153],"type":"Point"}
}