{
  "type": "Feature",
  "properties": {
    "iso:country": "GB",
    "wof:name": "CH4 0JE",
    "wof:placetype": "postalcode"
  },
  "geometry": {"coordinates":[-3.044111,53.150787],"type":"Point"}
}
