{
  "type": "Feature",
  "properties": {
    "iso:country":"GB",
    "wof:name":"AL1 3SQ",
    "wof:placetype":"postalcode"
},
  "geometry": {"coordinates":[-0.33385578103902,51.75713432259854],"type":"Point"}
}