{
  "type": "Feature",
  "properties": {
    "iso:country":"GB",
    "wof:name":"ME1 1PU",
    "wof:placetype":"postalcode"
},
  "geometry": {"coordinates":[0.50237304104079,51.39102320596638],"type":"Point"}
}