{
  "type": "Feature",
  "properties": {
    "iso:country": "GB",
    "wof:name": "ME10 1SN",
    "wof:placetype": "postalcode"
  },
  "geometry": {"coordinates":[0.718934,51.329166],"type":"Point"}
}
