{
  "type": "Feature",
  "properties": {
    "iso:country":"GB",
    "wof:name":"ME10 1SN",
    "wof:placetype":"postalcode"
},
  "geometry": {"coordinates":[0.71893407649581,51.32916581110521],"type":"Point"}
}