{
  "type": "Feature",
  "properties": {
    "date:inception_lower":"1980-01-01",
    "date:inception_upper":"1980-01-31",
    "iso:country":"GB",
    "wof:name":"ME10 1SN",
    "wof:placetype":"postalcode"
},
  "geometry": {"coordinates":[0.718934,51.329166],"type":"Point"}
}