{
  "type": "Feature",
  "properties": {
    "iso:country":"GB",
    "wof:name":"NG9 3NG",
    "wof:placetype":"postalcode"
},
  "geometry": {"coordinates":[-1.2390147822685,52.93922471357484],"type":"Point"}
}