{
  "type": "Feature",
  "properties": {
    "iso:country": "GB",
    "wof:name": "NG9 3NG",
    "wof:placetype": "postalcode"
  },
  "geometry": {"coordinates":[-1.239015,52.939225],"type":"Point"}
}
