{
  "type": "Feature",
  "properties": {
    "iso:country":"GB",
    "wof:name":"TN4 0HL",
    "wof:placetype":"postalcode"
},
  "geometry": {"coordinates":[0.25794043002052,51.15697411522797],"type":"Point"}
}