{
  "type": "Feature",
  "properties": {
    "date:inception_lower":"1980-01-01",
    "date:inception_upper":"1980-01-31",
    "iso:country":"GB",
    "wof:name":"TN4 0HL",
    "wof:placetype":"postalcode"
},
  "geometry": {"coordinates":[0.25794,51.156974],"type":"Point"}
}