{
  "type": "Feature",
  "properties": {
    "iso:country":"GB",
    "wof:name":"BH5 2AJ",
    "wof:placetype":"postalcode"
},
  "geometry": {"coordinates":[-1.82600901051638,50.72722060339765],"type":"Point"}
}