{
  "type": "Feature",
  "properties": {
    "iso:country":"GB",
    "wof:name":"SY10 7RX",
    "wof:placetype":"postalcode"
},
  "geometry": {"coordinates":[-3.06587641478023,52.91412417063418],"type":"Point"}
}