{
  "type": "Feature",
  "properties": {
    "iso:country": "GB",
    "wof:name": "SY10 7RX",
    "wof:placetype": "postalcode"
  },
  "geometry": {"coordinates":[-3.066201,52.914073],"type":"Point"}
}
