{
  "type": "Feature",
  "properties": {
    "iso:country":"GB",
    "wof:name":"SW3 3NA",
    "wof:placetype":"postalcode"
},
  "geometry": {"coordinates":[-0.16234622734598,51.49106660530163],"type":"Point"}
}