{
  "type": "Feature",
  "properties": {
    "date:inception_lower": "1980-01-01",
    "date:inception_upper": "1980-01-01",
    "iso:country": "GB",
    "wof:name": "SW3 3NA",
    "wof:placetype": "postalcode"
  },
  "geometry": {"coordinates":[-0.162346,51.491067],"type":"Point"}
}
