{
  "type": "Feature",
  "properties": {
    "iso:country":"GB",
    "wof:name":"N18 1PU",
    "wof:placetype":"postalcode"
},
  "geometry": {"coordinates":[-0.07757309122084,51.61831857141988],"type":"Point"}
}