{
  "type": "Feature",
  "properties": {
    "iso:country": "GB",
    "wof:name": "DL16 6QY",
    "wof:placetype": "postalcode"
  },
  "geometry": {"coordinates":[-1.600604,54.704243],"type":"Point"}
}
