{
  "type": "Feature",
  "properties": {
    "iso:country":"GB",
    "wof:name":"DL16 6QY",
    "wof:placetype":"postalcode"
},
  "geometry": {"coordinates":[-1.60060392279276,54.70424326387631],"type":"Point"}
}