{
  "type": "Feature",
  "properties": {
    "iso:country":"GB",
    "wof:name":"SO30 3EW",
    "wof:placetype":"postalcode"
},
  "geometry": {"coordinates":[-1.33411193684126,50.92194818739132],"type":"Point"}
}