{
  "type": "Feature",
  "properties": {
    "date:inception_lower": "1983-01-01",
    "date:inception_upper": "1983-01-01",
    "iso:country": "GB",
    "wof:name": "NE38 9DX",
    "wof:placetype": "postalcode"
  },
  "geometry": {"coordinates":[-1.551805,54.88091],"type":"Point"}
}
