{
  "type": "Feature",
  "properties": {
    "iso:country": "GB",
    "wof:name": "NE38 9DX",
    "wof:placetype": "postalcode"
  },
  "geometry": {"coordinates":[-1.551805,54.88091],"type":"Point"}
}
