{
  "type": "Feature",
  "properties": {
    "iso:country": "GB",
    "wof:name": "LL31 9SW",
    "wof:placetype": "postalcode"
  },
  "geometry": {"coordinates":[-3.813644,53.29378],"type":"Point"}
}
