{
  "type": "Feature",
  "properties": {
    "date:inception_lower":"1986-07-01",
    "date:inception_upper":"1986-07-31",
    "iso:country":"GB",
    "wof:name":"LL31 9SW",
    "wof:placetype":"postalcode"
},
  "geometry": {"coordinates":[-3.813644,53.29378],"type":"Point"}
}