{
  "type": "Feature",
  "properties": {
    "iso:country":"GB",
    "wof:name":"LL31 9SW",
    "wof:placetype":"postalcode"
},
  "geometry": {"coordinates":[-3.81364386226202,53.29378019953956],"type":"Point"}
}