{
  "type": "Feature",
  "properties": {
    "iso:country":"GB",
    "wof:name":"DY1 2SZ",
    "wof:placetype":"postalcode"
},
  "geometry": {"coordinates":[-2.11258548533628,52.51632665806208],"type":"Point"}
}