{
  "type": "Feature",
  "properties": {
    "iso:country":"GB",
    "wof:name":"LE9 6SE",
    "wof:placetype":"postalcode"
},
  "geometry": {"coordinates":[-1.2331956809108,52.53658012370934],"type":"Point"}
}