{
  "type": "Feature",
  "properties": {
    "date:inception_lower":"1980-01-01",
    "date:inception_upper":"1980-01-31",
    "iso:country":"GB",
    "wof:name":"LE9 6SE",
    "wof:placetype":"postalcode"
},
  "geometry": {"coordinates":[-1.233196,52.53658],"type":"Point"}
}