{
  "type": "Feature",
  "properties": {
    "date:inception_lower": "2023-12-01",
    "date:inception_upper": "2023-12-01",
    "iso:country": "GB",
    "wof:name": "SA16 0FJ",
    "wof:placetype": "postalcode"
  },
  "geometry": {"coordinates":[-4.279054,51.689541],"type":"Point"}
}
