{
  "type": "Feature",
  "properties": {
    "iso:country": "GB",
    "wof:name": "NR29 5EJ",
    "wof:placetype": "postalcode"
  },
  "geometry": {"coordinates":[1.632947,52.684104],"type":"Point"}
}
