{
  "type": "Feature",
  "properties": {
    "iso:country":"GB",
    "wof:name":"NR29 5EJ",
    "wof:placetype":"postalcode"
},
  "geometry": {"coordinates":[1.6329472342453,52.68410353096959],"type":"Point"}
}