{
  "type": "Feature",
  "properties": {
    "iso:country":"GB",
    "wof:name":"BS5 0ES",
    "wof:placetype":"postalcode"
},
  "geometry": {"coordinates":[-2.56663663504354,51.461883303945],"type":"Point"}
}