{
  "type": "Feature",
  "properties": {
    "iso:country":"GB",
    "wof:name":"OL7 9SA",
    "wof:placetype":"postalcode"
},
  "geometry": {"coordinates":[-2.11349975385128,53.49719590612359],"type":"Point"}
}