{
  "type": "Feature",
  "properties": {
    "iso:country":"GB",
    "wof:name":"DT4 8AA",
    "wof:placetype":"postalcode"
},
  "geometry": {"coordinates":[-2.45548553325886,50.60858162714413],"type":"Point"}
}