{
  "type": "Feature",
  "properties": {
    "date:inception_lower": "2017-11-01",
    "date:inception_upper": "2017-11-01",
    "iso:country": "GB",
    "wof:name": "BH14 0BW",
    "wof:placetype": "postalcode"
  },
  "geometry": {"coordinates":[-1.94385,50.725887],"type":"Point"}
}
