{
  "type": "Feature",
  "properties": {
    "iso:country":"GB",
    "wof:name":"DT8 3JN",
    "wof:placetype":"postalcode"
},
  "geometry": {"coordinates":[-2.77414125100493,50.80454424383644],"type":"Point"}
}