{
  "type": "Feature",
  "properties": {
    "date:inception_lower": "1980-01-01",
    "date:inception_upper": "1980-01-01",
    "iso:country": "GB",
    "wof:name": "DT8 3JN",
    "wof:placetype": "postalcode"
  },
  "geometry": {"coordinates":[-2.774141,50.804544],"type":"Point"}
}
