{
  "type": "Feature",
  "properties": {
    "iso:country": "GB",
    "wof:name": "KT22 9XB",
    "wof:placetype": "postalcode"
  },
  "geometry": {"coordinates":[-0.357512,51.284474],"type":"Point"}
}
