{
  "type": "Feature",
  "properties": {
    "iso:country":"GB",
    "wof:name":"AB31 4QW",
    "wof:placetype":"postalcode"
},
  "geometry": {"coordinates":[-2.68928208298617,57.13104890164599],"type":"Point"}
}