{
  "type": "Feature",
  "properties": {
    "iso:country":"GB",
    "wof:name":"YO62 5BX",
    "wof:placetype":"postalcode"
},
  "geometry": {"coordinates":[-1.05756690509805,54.24530233035846],"type":"Point"}
}