{
  "type": "Feature",
  "properties": {
    "date:inception_lower": "1998-06-01",
    "date:inception_upper": "1998-06-01",
    "iso:country": "GB",
    "wof:name": "YO62 5BX",
    "wof:placetype": "postalcode"
  },
  "geometry": {"coordinates":[-1.057567,54.245302],"type":"Point"}
}
