{
  "type": "Feature",
  "properties": {
    "iso:country":"GB",
    "wof:name":"GU27 1LT",
    "wof:placetype":"postalcode"
},
  "geometry": {"coordinates":[-0.7471859901996,51.08886017575342],"type":"Point"}
}