{
  "type": "Feature",
  "properties": {
    "date:inception_lower": "2021-04-01",
    "date:inception_upper": "2021-04-01",
    "iso:country": "GB",
    "wof:name": "TN13 1FH",
    "wof:placetype": "postalcode"
  },
  "geometry": {"coordinates":[0.188421,51.274453],"type":"Point"}
}
