{
  "type": "Feature",
  "properties": {
    "iso:country": "GB",
    "wof:name": "SP11 0QX",
    "wof:placetype": "postalcode"
  },
  "geometry": {"coordinates":[-1.524269,51.213609],"type":"Point"}
}
