{
  "type": "Feature",
  "properties": {
    "iso:country": "GB",
    "wof:name": "SP11 0QX",
    "wof:placetype": "postalcode"
  },
  "geometry": {"coordinates":[-1.523746,51.214335],"type":"Point"}
}
