{
  "type": "Feature",
  "properties": {
    "iso:country":"GB",
    "wof:name":"SP11 0QX",
    "wof:placetype":"postalcode"
},
  "geometry": {"coordinates":[-1.52375677287324,51.21433926086893],"type":"Point"}
}