{
  "type": "Feature",
  "properties": {
    "iso:country":"GB",
    "wof:name":"BB4 5RJ",
    "wof:placetype":"postalcode"
},
  "geometry": {"coordinates":[-2.32289761656588,53.70741791783932],"type":"Point"}
}