{
  "type": "Feature",
  "properties": {
    "date:inception_lower": "1980-01-01",
    "date:inception_upper": "1980-01-01",
    "iso:country": "GB",
    "wof:name": "WF2 6HR",
    "wof:placetype": "postalcode"
  },
  "geometry": {"coordinates":[-1.482358,53.650677],"type":"Point"}
}
