{
  "type": "Feature",
  "properties": {
    "iso:country": "GB",
    "wof:name": "E2 6BT",
    "wof:placetype": "postalcode"
  },
  "geometry": {"coordinates":[-0.068817,51.526092],"type":"Point"}
}
