{
  "type": "Feature",
  "properties": {
    "iso:country":"GB",
    "wof:name":"HS7 5QL",
    "wof:placetype":"postalcode"
},
  "geometry": {"coordinates":[-7.23121612303409,57.417820312164],"type":"Point"}
}