{
  "type": "Feature",
  "properties": {
    "iso:country":"GB",
    "wof:name":"DN2 6QA",
    "wof:placetype":"postalcode"
},
  "geometry": {"coordinates":[-1.09380243305472,53.5331246401467],"type":"Point"}
}