{
  "type": "Feature",
  "properties": {
    "date:inception_lower": "2023-05-01",
    "date:inception_upper": "2023-05-01",
    "iso:country": "GB",
    "wof:name": "PR1 9LW",
    "wof:placetype": "postalcode"
  },
  "geometry": {"coordinates":[-2.697017,53.731835],"type":"Point"}
}
