{
  "type": "Feature",
  "properties": {
    "iso:country":"GB",
    "wof:name":"DA17 6DU",
    "wof:placetype":"postalcode"
},
  "geometry": {"coordinates":[0.16427094079329,51.48935989416649],"type":"Point"}
}