{
  "type": "Feature",
  "properties": {
    "date:inception_lower": "1980-01-01",
    "date:inception_upper": "1980-01-01",
    "iso:country": "GB",
    "wof:name": "CA6 5UF",
    "wof:placetype": "postalcode"
  },
  "geometry": {"coordinates":[-2.96756,55.009721],"type":"Point"}
}
