{
  "type": "Feature",
  "properties": {
    "iso:country":"GB",
    "wof:name":"NP4 7SW",
    "wof:placetype":"postalcode"
},
  "geometry": {"coordinates":[-3.06777295927676,51.73849788922133],"type":"Point"}
}