{
  "type": "Feature",
  "properties": {
    "iso:country": "GB",
    "wof:name": "DE7 8QQ",
    "wof:placetype": "postalcode"
  },
  "geometry": {"coordinates":[-1.311669,52.989163],"type":"Point"}
}
