{
  "type": "Feature",
  "properties": {
    "iso:country":"GB",
    "wof:name":"DE7 8QQ",
    "wof:placetype":"postalcode"
},
  "geometry": {"coordinates":[-1.31166914586962,52.98916319118281],"type":"Point"}
}