{
  "type": "Feature",
  "properties": {
    "iso:country":"GB",
    "wof:name":"SN3 6DR",
    "wof:placetype":"postalcode"
},
  "geometry": {"coordinates":[-1.73722615327683,51.55264975277502],"type":"Point"}
}