{
  "type": "Feature",
  "properties": {
    "iso:country":"GB",
    "wof:name":"G64 2QR",
    "wof:placetype":"postalcode"
},
  "geometry": {"coordinates":[-4.19939269004818,55.91452686884573],"type":"Point"}
}