{
  "type": "Feature",
  "properties": {
    "iso:country": "GB",
    "wof:name": "G64 2QR",
    "wof:placetype": "postalcode"
  },
  "geometry": {"coordinates":[-4.199393,55.914527],"type":"Point"}
}
