{
  "type": "Feature",
  "properties": {
    "iso:country": "GB",
    "wof:name": "B64 5RF",
    "wof:placetype": "postalcode"
  },
  "geometry": {"coordinates":[-2.065058,52.488113],"type":"Point"}
}
