{
  "type": "Feature",
  "properties": {
    "iso:country":"GB",
    "wof:name":"BR4 0AE",
    "wof:placetype":"postalcode"
},
  "geometry": {"coordinates":[-0.00610515597836,51.37912592465931],"type":"Point"}
}