{
  "type": "Feature",
  "properties": {
    "iso:country":"GB",
    "wof:name":"CH5 4XU",
    "wof:placetype":"postalcode"
},
  "geometry": {"coordinates":[-3.0713214419167,53.2226396377061],"type":"Point"}
}