{
  "type": "Feature",
  "properties": {
    "iso:country": "GB",
    "wof:name": "CH5 4XU",
    "wof:placetype": "postalcode"
  },
  "geometry": {"coordinates":[-3.071321,53.22264],"type":"Point"}
}
