{
  "type": "Feature",
  "properties": {
    "date:inception_lower": "1985-10-01",
    "date:inception_upper": "1985-10-01",
    "iso:country": "GB",
    "wof:name": "L14 3PA",
    "wof:placetype": "postalcode"
  },
  "geometry": {"coordinates":[-2.89972,53.40621],"type":"Point"}
}
