{
  "type": "Feature",
  "properties": {
    "iso:country":"GB",
    "wof:name":"L14 3PA",
    "wof:placetype":"postalcode"
},
  "geometry": {"coordinates":[-2.89848621226689,53.40617649363827],"type":"Point"}
}