{
  "type": "Feature",
  "properties": {
    "date:inception_lower": "1990-02-01",
    "date:inception_upper": "1990-02-01",
    "iso:country": "GB",
    "wof:name": "PO21 4RB",
    "wof:placetype": "postalcode"
  },
  "geometry": {"coordinates":[-0.712494,50.778348],"type":"Point"}
}
