{
  "type": "Feature",
  "properties": {
    "iso:country": "GB",
    "wof:name": "PO21 4RB",
    "wof:placetype": "postalcode"
  },
  "geometry": {"coordinates":[-0.712494,50.778348],"type":"Point"}
}
