{
  "type": "Feature",
  "properties": {
    "iso:country":"GB",
    "wof:name":"CF5 4PZ",
    "wof:placetype":"postalcode"
},
  "geometry": {"coordinates":[-3.25844346455163,51.4766575656252],"type":"Point"}
}