{
  "type": "Feature",
  "properties": {
    "date:inception_lower": "1980-01-01",
    "date:inception_upper": "1980-01-01",
    "iso:country": "GB",
    "wof:name": "DN22 6LB",
    "wof:placetype": "postalcode"
  },
  "geometry": {"coordinates":[-0.939175,53.32315],"type":"Point"}
}
