{
  "type": "Feature",
  "properties": {
    "iso:country":"GB",
    "wof:name":"DN22 6LB",
    "wof:placetype":"postalcode"
},
  "geometry": {"coordinates":[-0.93920547436133,53.32312076066558],"type":"Point"}
}