{
  "type": "Feature",
  "properties": {
    "iso:country": "GB",
    "wof:name": "B37 5DJ",
    "wof:placetype": "postalcode"
  },
  "geometry": {"coordinates":[-1.748075,52.481879],"type":"Point"}
}
