{
  "type": "Feature",
  "properties": {
    "date:inception_lower": "1980-01-01",
    "date:inception_upper": "1980-01-01",
    "iso:country": "GB",
    "wof:name": "B37 5DJ",
    "wof:placetype": "postalcode"
  },
  "geometry": {"coordinates":[-1.748075,52.481879],"type":"Point"}
}
