{
  "type": "Feature",
  "properties": {
    "iso:country":"GB",
    "wof:name":"DL2 1GD",
    "wof:placetype":"postalcode"
},
  "geometry": {"coordinates":[-1.46282500152542,54.51648794803136],"type":"Point"}
}