{
  "type": "Feature",
  "properties": {
    "iso:country":"GB",
    "wof:name":"KA8 0PH",
    "wof:placetype":"postalcode"
},
  "geometry": {"coordinates":[-4.59382838563161,55.47189396604758],"type":"Point"}
}