{
  "type": "Feature",
  "properties": {
    "iso:country":"GB",
    "wof:name":"N21 1QE",
    "wof:placetype":"postalcode"
},
  "geometry": {"coordinates":[-0.11336819589256,51.63888038426956],"type":"Point"}
}