{
  "type": "Feature",
  "properties": {
    "date:inception_lower": "1980-01-01",
    "date:inception_upper": "1980-01-01",
    "iso:country": "GB",
    "wof:name": "N21 1QE",
    "wof:placetype": "postalcode"
  },
  "geometry": {"coordinates":[-0.113368,51.63888],"type":"Point"}
}
