{
  "type": "Feature",
  "properties": {
    "date:inception_lower": "2012-07-01",
    "date:inception_upper": "2012-07-01",
    "iso:country": "GB",
    "wof:name": "LA2 6FD",
    "wof:placetype": "postalcode"
  },
  "geometry": {"coordinates":[-2.751962,54.075396],"type":"Point"}
}
