{
  "type": "Feature",
  "properties": {
    "iso:country":"GB",
    "wof:name":"LA2 6FD",
    "wof:placetype":"postalcode"
},
  "geometry": {"coordinates":[-2.75196206601375,54.07539557310258],"type":"Point"}
}