{
  "type": "Feature",
  "properties": {
    "iso:country": "GB",
    "wof:name": "RG7 1BL",
    "wof:placetype": "postalcode"
  },
  "geometry": {"coordinates":[-0.9767,51.404039],"type":"Point"}
}
