{
  "type": "Feature",
  "properties": {
    "iso:country":"GB",
    "wof:name":"DL10 5HZ",
    "wof:placetype":"postalcode"
},
  "geometry": {"coordinates":[-1.7158977536604,54.43150308693581],"type":"Point"}
}