{
  "type": "Feature",
  "properties": {
    "iso:country":"GB",
    "wof:name":"CM1 7PD",
    "wof:placetype":"postalcode"
},
  "geometry": {"coordinates":[0.48495406476738,51.74561216080718],"type":"Point"}
}