{
  "type": "Feature",
  "properties": {
    "date:inception_lower": "1980-01-01",
    "date:inception_upper": "1980-01-01",
    "iso:country": "GB",
    "wof:name": "EH52 5QW",
    "wof:placetype": "postalcode"
  },
  "geometry": {"coordinates":[-3.471209,55.932781],"type":"Point"}
}
