{
  "type": "Feature",
  "properties": {
    "iso:country":"GB",
    "wof:name":"EH52 5QW",
    "wof:placetype":"postalcode"
},
  "geometry": {"coordinates":[-3.47121223434999,55.93278505380319],"type":"Point"}
}