{
  "type": "Feature",
  "properties": {
    "date:inception_lower": "1980-01-01",
    "date:inception_upper": "1980-01-01",
    "iso:country": "GB",
    "wof:name": "TF4 2QZ",
    "wof:placetype": "postalcode"
  },
  "geometry": {"coordinates":[-2.468023,52.669855],"type":"Point"}
}
