{
  "type": "Feature",
  "properties": {
    "iso:country":"GB",
    "wof:name":"TF4 2QZ",
    "wof:placetype":"postalcode"
},
  "geometry": {"coordinates":[-2.46802306640982,52.66985495591369],"type":"Point"}
}