{
  "type": "Feature",
  "properties": {
    "date:inception_lower":"1980-01-01",
    "date:inception_upper":"1980-01-31",
    "iso:country":"GB",
    "wof:name":"TN22 3AE",
    "wof:placetype":"postalcode"
},
  "geometry": {"coordinates":[0.102152,50.990875],"type":"Point"}
}