{
  "type": "Feature",
  "properties": {
    "iso:country":"GB",
    "wof:name":"HA0 1YJ",
    "wof:placetype":"postalcode"
},
  "geometry": {"coordinates":[-0.3038879791389,51.53647919255693],"type":"Point"}
}