{
  "type": "Feature",
  "properties": {
    "iso:country": "GB",
    "wof:name": "PL21 0RH",
    "wof:placetype": "postalcode"
  },
  "geometry": {"coordinates":[-3.885569,50.352098],"type":"Point"}
}
