{
  "type": "Feature",
  "properties": {
    "iso:country":"GB",
    "wof:name":"AB24 3BQ",
    "wof:placetype":"postalcode"
},
  "geometry": {"coordinates":[-2.0952176306561,57.15758406748706],"type":"Point"}
}