{
  "type": "Feature",
  "properties": {
    "iso:country": "GB",
    "wof:name": "G22 6NG",
    "wof:placetype": "postalcode"
  },
  "geometry": {"coordinates":[-4.261938,55.894559],"type":"Point"}
}
