{
  "type": "Feature",
  "properties": {
    "date:inception_lower": "2016-11-01",
    "date:inception_upper": "2016-11-01",
    "iso:country": "GB",
    "wof:name": "G22 6NG",
    "wof:placetype": "postalcode"
  },
  "geometry": {"coordinates":[-4.262348,55.894723],"type":"Point"}
}
