{
  "type": "Feature",
  "properties": {
    "date:inception_lower": "1980-01-01",
    "date:inception_upper": "1980-01-01",
    "iso:country": "GB",
    "wof:name": "SP1 3LG",
    "wof:placetype": "postalcode"
  },
  "geometry": {"coordinates":[-1.810684,51.087774],"type":"Point"}
}
