{
  "type": "Feature",
  "properties": {
    "iso:country":"GB",
    "wof:name":"SP1 3LG",
    "wof:placetype":"postalcode"
},
  "geometry": {"coordinates":[-1.81068392821638,51.0877736336284],"type":"Point"}
}