{
  "type": "Feature",
  "properties": {
    "iso:country":"GB",
    "wof:name":"LU1 3FS",
    "wof:placetype":"postalcode"
},
  "geometry": {"coordinates":[-0.40833939011157,51.87628268405278],"type":"Point"}
}