{
  "type": "Feature",
  "properties": {
    "date:inception_lower":"2013-10-01",
    "date:inception_upper":"2013-10-31",
    "iso:country":"GB",
    "wof:name":"LU1 3FS",
    "wof:placetype":"postalcode"
},
  "geometry": {"coordinates":[-0.408339,51.876283],"type":"Point"}
}