{
  "type": "Feature",
  "properties": {
    "iso:country":"GB",
    "wof:name":"S6 5BU",
    "wof:placetype":"postalcode"
},
  "geometry": {"coordinates":[-1.50364732446168,53.39482938742396],"type":"Point"}
}