{
  "type": "Feature",
  "properties": {
    "date:inception_lower":"1997-06-01",
    "date:inception_upper":"1997-06-30",
    "iso:country":"GB",
    "wof:name":"S6 5BU",
    "wof:placetype":"postalcode"
},
  "geometry": {"coordinates":[-1.503647,53.394829],"type":"Point"}
}