{
  "type": "Feature",
  "properties": {
    "date:inception_lower": "1980-01-01",
    "date:inception_upper": "1980-01-01",
    "iso:country": "GB",
    "wof:name": "BD15 0LA",
    "wof:placetype": "postalcode"
  },
  "geometry": {"coordinates":[-1.850984,53.815222],"type":"Point"}
}
