{
  "type": "Feature",
  "properties": {
    "iso:country": "GB",
    "wof:name": "DE4 3EJ",
    "wof:placetype": "postalcode"
  },
  "geometry": {"coordinates":[-1.548026,53.135749],"type":"Point"}
}
