{
  "type": "Feature",
  "properties": {
    "date:inception_lower":"1980-01-01",
    "date:inception_upper":"1980-01-31",
    "iso:country":"GB",
    "wof:name":"DE4 3EJ",
    "wof:placetype":"postalcode"
},
  "geometry": {"coordinates":[-1.548026,53.135749],"type":"Point"}
}