{
  "type": "Feature",
  "properties": {
    "iso:country": "GB",
    "wof:name": "WR12 7NW",
    "wof:placetype": "postalcode"
  },
  "geometry": {"coordinates":[-1.902682,52.006402],"type":"Point"}
}
