{
  "type": "Feature",
  "properties": {
    "iso:country":"GB",
    "wof:name":"WR12 7NW",
    "wof:placetype":"postalcode"
},
  "geometry": {"coordinates":[-1.90268215317794,52.00640208592606],"type":"Point"}
}