{
  "type": "Feature",
  "properties": {
    "iso:country":"GB",
    "wof:name":"IP8 4AG",
    "wof:placetype":"postalcode"
},
  "geometry": {"coordinates":[1.09460861050705,52.07337864789346],"type":"Point"}
}