{
  "type": "Feature",
  "properties": {
    "iso:country":"GB",
    "wof:name":"LS8 2RX",
    "wof:placetype":"postalcode"
},
  "geometry": {"coordinates":[-1.50192746091915,53.82068091200644],"type":"Point"}
}