{
  "type": "Feature",
  "properties": {
    "iso:country":"GB",
    "wof:name":"DH3 1GN",
    "wof:placetype":"postalcode"
},
  "geometry": {"coordinates":[-1.56981639234635,54.9063888018671],"type":"Point"}
}