{
  "type": "Feature",
  "properties": {
    "date:inception_lower": "2014-02-01",
    "date:inception_upper": "2014-02-01",
    "iso:country": "GB",
    "wof:name": "DH3 1GN",
    "wof:placetype": "postalcode"
  },
  "geometry": {"coordinates":[-1.569828,54.906397],"type":"Point"}
}
