{
  "type": "Feature",
  "properties": {
    "date:inception_lower":"2015-10-01",
    "date:inception_upper":"2015-10-31",
    "iso:country":"GB",
    "wof:name":"FK5 4XY",
    "wof:placetype":"postalcode"
},
  "geometry": {"coordinates":[-3.84586,56.019899],"type":"Point"}
}