{
  "type": "Feature",
  "properties": {
    "iso:country":"GB",
    "wof:name":"AB24 5HT",
    "wof:placetype":"postalcode"
},
  "geometry": {"coordinates":[-2.09175859311155,57.14928635514539],"type":"Point"}
}