{
  "type": "Feature",
  "properties": {
    "iso:country": "GB",
    "wof:name": "BA11 2LD",
    "wof:placetype": "postalcode"
  },
  "geometry": {"coordinates":[-2.291002,51.244654],"type":"Point"}
}
