{
  "type": "Feature",
  "properties": {
    "iso:country":"GB",
    "wof:name":"B75 7EZ",
    "wof:placetype":"postalcode"
},
  "geometry": {"coordinates":[-1.78684675223318,52.56081478113316],"type":"Point"}
}