{
  "type": "Feature",
  "properties": {
    "iso:country": "GB",
    "wof:name": "PL20 7ES",
    "wof:placetype": "postalcode"
  },
  "geometry": {"coordinates":[-4.199975,50.485579],"type":"Point"}
}
