{
  "type": "Feature",
  "properties": {
    "iso:country":"GB",
    "wof:name":"PL20 7ES",
    "wof:placetype":"postalcode"
},
  "geometry": {"coordinates":[-4.19994552152898,50.48559064038342],"type":"Point"}
}