{
  "type": "Feature",
  "properties": {
    "iso:country": "GB",
    "wof:name": "SA73 1QY",
    "wof:placetype": "postalcode"
  },
  "geometry": {"coordinates":[-4.962234,51.718325],"type":"Point"}
}
