{
  "type": "Feature",
  "properties": {
    "iso:country":"GB",
    "wof:name":"SA73 1QY",
    "wof:placetype":"postalcode"
},
  "geometry": {"coordinates":[-4.9622338993408,51.71832460317426],"type":"Point"}
}