{
  "type": "Feature",
  "properties": {
    "iso:country": "GB",
    "wof:name": "G64 3NW",
    "wof:placetype": "postalcode"
  },
  "geometry": {"coordinates":[-4.218449,55.915326],"type":"Point"}
}
