{
  "type": "Feature",
  "properties": {
    "iso:country":"GB",
    "wof:name":"G64 3NW",
    "wof:placetype":"postalcode"
},
  "geometry": {"coordinates":[-4.21844941133212,55.91532631739291],"type":"Point"}
}