{
  "type": "Feature",
  "properties": {
    "iso:country": "GB",
    "wof:name": "CM5 0PJ",
    "wof:placetype": "postalcode"
  },
  "geometry": {"coordinates":[0.296852,51.758424],"type":"Point"}
}
