{
  "type": "Feature",
  "properties": {
    "iso:country":"GB",
    "wof:name":"CM5 0PJ",
    "wof:placetype":"postalcode"
},
  "geometry": {"coordinates":[0.29685197120266,51.7584238708458],"type":"Point"}
}