{
  "type": "Feature",
  "properties": {
    "date:inception_lower":"1992-01-01",
    "date:inception_upper":"1992-01-31",
    "iso:country":"GB",
    "wof:name":"MK11 1JX",
    "wof:placetype":"postalcode"
},
  "geometry": {"coordinates":[-0.847944,52.053391],"type":"Point"}
}