{
  "type": "Feature",
  "properties": {
    "iso:country":"GB",
    "wof:name":"EH11 1TP",
    "wof:placetype":"postalcode"
},
  "geometry": {"coordinates":[-3.23213453839823,55.93655887034474],"type":"Point"}
}