{
  "type": "Feature",
  "properties": {
    "iso:country":"GB",
    "wof:name":"NG33 4RU",
    "wof:placetype":"postalcode"
},
  "geometry": {"coordinates":[-0.535488058569,52.7543715588132],"type":"Point"}
}