{
  "type": "Feature",
  "properties": {
    "iso:country":"GB",
    "wof:name":"PE34 4SQ",
    "wof:placetype":"postalcode"
},
  "geometry": {"coordinates":[0.34560150485058,52.7196449613592],"type":"Point"}
}