{
  "type": "Feature",
  "properties": {
    "date:inception_lower": "1980-01-01",
    "date:inception_upper": "1980-01-01",
    "iso:country": "GB",
    "wof:name": "PE34 4SQ",
    "wof:placetype": "postalcode"
  },
  "geometry": {"coordinates":[0.344673,52.71973],"type":"Point"}
}
