{
  "type": "Feature",
  "properties": {
    "iso:country":"GB",
    "wof:name":"PL6 5WE",
    "wof:placetype":"postalcode"
},
  "geometry": {"coordinates":[-4.11711111825702,50.40485709509435],"type":"Point"}
}