{
  "type": "Feature",
  "properties": {
    "date:inception_lower": "1998-06-01",
    "date:inception_upper": "1998-06-01",
    "iso:country": "GB",
    "wof:name": "PL6 5WE",
    "wof:placetype": "postalcode"
  },
  "geometry": {"coordinates":[-4.117111,50.404857],"type":"Point"}
}
