{
  "type": "Feature",
  "properties": {
    "iso:country":"GB",
    "wof:name":"PA47 7SW",
    "wof:placetype":"postalcode"
},
  "geometry": {"coordinates":[-6.50562017142014,55.68024324062092],"type":"Point"}
}