{
  "type": "Feature",
  "properties": {
    "iso:country": "GB",
    "wof:name": "EH12 5RB",
    "wof:placetype": "postalcode"
  },
  "geometry": {"coordinates":[-3.248991,55.942508],"type":"Point"}
}
