{
  "type": "Feature",
  "properties": {
    "date:inception_lower": "2021-09-01",
    "date:inception_upper": "2021-09-01",
    "iso:country": "GB",
    "wof:name": "KT12 1FW",
    "wof:placetype": "postalcode"
  },
  "geometry": {"coordinates":[-0.412286,51.374174],"type":"Point"}
}
