{
  "type": "Feature",
  "properties": {
    "iso:country": "GB",
    "wof:name": "CO10 8EA",
    "wof:placetype": "postalcode"
  },
  "geometry": {"coordinates":[0.536723,52.106979],"type":"Point"}
}
