{
  "type": "Feature",
  "properties": {
    "date:inception_lower":"1980-01-01",
    "date:inception_upper":"1980-01-31",
    "iso:country":"GB",
    "wof:name":"CO10 8EA",
    "wof:placetype":"postalcode"
},
  "geometry": {"coordinates":[0.536723,52.106979],"type":"Point"}
}