{
  "type": "Feature",
  "properties": {
    "iso:country":"GB",
    "wof:name":"CO10 8EA",
    "wof:placetype":"postalcode"
},
  "geometry": {"coordinates":[0.5366917494767,52.10696572901675],"type":"Point"}
}