{
  "type": "Feature",
  "properties": {
    "iso:country": "GB",
    "wof:name": "SY10 7EU",
    "wof:placetype": "postalcode"
  },
  "geometry": {"coordinates":[-3.065689,52.899901],"type":"Point"}
}
