{
  "type": "Feature",
  "properties": {
    "iso:country":"GB",
    "wof:name":"SY10 7EU",
    "wof:placetype":"postalcode"
},
  "geometry": {"coordinates":[-3.06569042579182,52.89988610930996],"type":"Point"}
}