{
  "type": "Feature",
  "properties": {
    "date:inception_lower": "1980-01-01",
    "date:inception_upper": "1980-01-01",
    "iso:country": "GB",
    "wof:name": "SY10 7EU",
    "wof:placetype": "postalcode"
  },
  "geometry": {"coordinates":[-3.065671,52.899748],"type":"Point"}
}
