{
  "type": "Feature",
  "properties": {
    "date:inception_lower":"1980-01-01",
    "date:inception_upper":"1980-01-31",
    "iso:country":"GB",
    "wof:name":"SY10 7EU",
    "wof:placetype":"postalcode"
},
  "geometry": {"coordinates":[-3.065689,52.899901],"type":"Point"}
}