{
  "type": "Feature",
  "properties": {
    "iso:country": "GB",
    "wof:name": "OX28 5BJ",
    "wof:placetype": "postalcode"
  },
  "geometry": {"coordinates":[-1.505059,51.787895],"type":"Point"}
}
