{
  "type": "Feature",
  "properties": {
    "iso:country":"GB",
    "wof:name":"OX28 5BJ",
    "wof:placetype":"postalcode"
},
  "geometry": {"coordinates":[-1.50505856906174,51.78789482251703],"type":"Point"}
}