{
  "type": "Feature",
  "properties": {
    "iso:country":"GB",
    "wof:name":"IP2 9BW",
    "wof:placetype":"postalcode"
},
  "geometry": {"coordinates":[1.1390337297232,52.04089516564606],"type":"Point"}
}