{
  "type": "Feature",
  "properties": {
    "date:inception_lower":"2006-01-01",
    "date:inception_upper":"2006-01-31",
    "iso:country":"GB",
    "wof:name":"DH8 5RZ",
    "wof:placetype":"postalcode"
},
  "geometry": {"coordinates":[-1.831943,54.849009],"type":"Point"}
}