{
  "type": "Feature",
  "properties": {
    "iso:country":"GB",
    "wof:name":"DH8 5RZ",
    "wof:placetype":"postalcode"
},
  "geometry": {"coordinates":[-1.83194312083227,54.84900855161499],"type":"Point"}
}