{
  "type": "Feature",
  "properties": {
    "iso:country": "GB",
    "wof:name": "M6 7HR",
    "wof:placetype": "postalcode"
  },
  "geometry": {"coordinates":[-2.30385,53.500566],"type":"Point"}
}
