{
  "type": "Feature",
  "properties": {
    "date:inception_lower": "1980-01-01",
    "date:inception_upper": "1980-01-01",
    "iso:country": "GB",
    "wof:name": "TR18 5AW",
    "wof:placetype": "postalcode"
  },
  "geometry": {"coordinates":[-5.552666,50.101761],"type":"Point"}
}
