{
  "type": "Feature",
  "properties": {
    "iso:country":"GB",
    "wof:name":"WV12 5HU",
    "wof:placetype":"postalcode"
},
  "geometry": {"coordinates":[-2.02832644658078,52.61138152586319],"type":"Point"}
}