{
  "type": "Feature",
  "properties": {
    "date:inception_lower": "1990-07-01",
    "date:inception_upper": "1990-07-01",
    "iso:country": "GB",
    "wof:name": "PO12 4XW",
    "wof:placetype": "postalcode"
  },
  "geometry": {"coordinates":[-1.141395,50.804083],"type":"Point"}
}
