{
  "type": "Feature",
  "properties": {
    "iso:country": "GB",
    "wof:name": "DY10 3QX",
    "wof:placetype": "postalcode"
  },
  "geometry": {"coordinates":[-2.229303,52.39028],"type":"Point"}
}
