{
  "type": "Feature",
  "properties": {
    "iso:country":"GB",
    "wof:name":"WA15 6SH",
    "wof:placetype":"postalcode"
},
  "geometry": {"coordinates":[-2.3406221921014,53.39940922099539],"type":"Point"}
}