{
  "type": "Feature",
  "properties": {
    "iso:country":"GB",
    "wof:name":"NP19 7TH",
    "wof:placetype":"postalcode"
},
  "geometry": {"coordinates":[-2.97190720253869,51.59632916701629],"type":"Point"}
}