{
  "type": "Feature",
  "properties": {
    "iso:country": "GB",
    "wof:name": "NP19 7TH",
    "wof:placetype": "postalcode"
  },
  "geometry": {"coordinates":[-2.971907,51.596329],"type":"Point"}
}
