{
  "type": "Feature",
  "properties": {
    "iso:country":"GB",
    "wof:name":"CA12 5EG",
    "wof:placetype":"postalcode"
},
  "geometry": {"coordinates":[-3.14386533660706,54.60065865636287],"type":"Point"}
}