{
  "type": "Feature",
  "properties": {
    "iso:country": "GB",
    "wof:name": "CA12 5EG",
    "wof:placetype": "postalcode"
  },
  "geometry": {"coordinates":[-3.143865,54.600659],"type":"Point"}
}
