{
  "type": "Feature",
  "properties": {
    "iso:country":"GB",
    "wof:name":"CM4 0LU",
    "wof:placetype":"postalcode"
},
  "geometry": {"coordinates":[0.35090852442139,51.72671612839536],"type":"Point"}
}