{
  "type": "Feature",
  "properties": {
    "iso:country":"GB",
    "wof:name":"SK13 5DG",
    "wof:placetype":"postalcode"
},
  "geometry": {"coordinates":[-1.99719198045523,53.42733775047631],"type":"Point"}
}