{
  "type": "Feature",
  "properties": {
    "date:inception_lower":"1997-12-01",
    "date:inception_upper":"1997-12-31",
    "iso:country":"GB",
    "wof:name":"SK13 5DG",
    "wof:placetype":"postalcode"
},
  "geometry": {"coordinates":[-1.997327,53.427383],"type":"Point"}
}