{
  "type": "Feature",
  "properties": {
    "iso:country": "GB",
    "wof:name": "SK13 5DG",
    "wof:placetype": "postalcode"
  },
  "geometry": {"coordinates":[-1.997327,53.427383],"type":"Point"}
}
