{
  "type": "Feature",
  "properties": {
    "iso:country":"GB",
    "wof:name":"LS11 5LE",
    "wof:placetype":"postalcode"
},
  "geometry": {"coordinates":[-1.55631812455626,53.76648067734778],"type":"Point"}
}