{
  "type": "Feature",
  "properties": {
    "date:inception_lower": "1980-01-01",
    "date:inception_upper": "1980-01-01",
    "iso:country": "GB",
    "wof:name": "LS11 5LE",
    "wof:placetype": "postalcode"
  },
  "geometry": {"coordinates":[-1.556318,53.766481],"type":"Point"}
}
