{
  "type": "Feature",
  "properties": {
    "date:inception_lower": "2016-07-01",
    "date:inception_upper": "2016-07-01",
    "iso:country": "GB",
    "wof:name": "E15 1LA",
    "wof:placetype": "postalcode"
  },
  "geometry": {"coordinates":[-0.00146,51.540026],"type":"Point"}
}
