{
  "type": "Feature",
  "properties": {
    "iso:country":"GB",
    "wof:name":"WN6 7RR",
    "wof:placetype":"postalcode"
},
  "geometry": {"coordinates":[-2.65518501219835,53.55826492860503],"type":"Point"}
}