{
  "type": "Feature",
  "properties": {
    "iso:country":"GB",
    "wof:name":"BA1 2UD",
    "wof:placetype":"postalcode"
},
  "geometry": {"coordinates":[-2.36858317691848,51.39185556161093],"type":"Point"}
}