{
  "type": "Feature",
  "properties": {
    "iso:country":"GB",
    "wof:name":"NG24 3DQ",
    "wof:placetype":"postalcode"
},
  "geometry": {"coordinates":[-0.7912125037049,53.059824120862],"type":"Point"}
}