{
  "type": "Feature",
  "properties": {
    "date:inception_lower":"1980-01-01",
    "date:inception_upper":"1980-01-31",
    "iso:country":"GB",
    "wof:name":"BB4 8RB",
    "wof:placetype":"postalcode"
},
  "geometry": {"coordinates":[-2.282511,53.739203],"type":"Point"}
}