{
  "type": "Feature",
  "properties": {
    "iso:country":"GB",
    "wof:name":"BB4 8RB",
    "wof:placetype":"postalcode"
},
  "geometry": {"coordinates":[-2.28251086269489,53.73920309647043],"type":"Point"}
}