{
  "type": "Feature",
  "properties": {
    "date:inception_lower": "2006-09-01",
    "date:inception_upper": "2006-09-01",
    "iso:country": "GB",
    "wof:name": "CB22 4UD",
    "wof:placetype": "postalcode"
  },
  "geometry": {"coordinates":[0.148143,52.114625],"type":"Point"}
}
