{
  "type": "Feature",
  "properties": {
    "iso:country":"GB",
    "wof:name":"M8 0RR",
    "wof:placetype":"postalcode"
},
  "geometry": {"coordinates":[-2.22940638712246,53.50306064167793],"type":"Point"}
}