{
  "type": "Feature",
  "properties": {
    "date:inception_lower": "1994-05-01",
    "date:inception_upper": "1994-05-01",
    "iso:country": "GB",
    "wof:name": "M8 0RR",
    "wof:placetype": "postalcode"
  },
  "geometry": {"coordinates":[-2.229406,53.503061],"type":"Point"}
}
