{
  "type": "Feature",
  "properties": {
    "iso:country":"GB",
    "wof:name":"SW1P 1QE",
    "wof:placetype":"postalcode"
},
  "geometry": {"coordinates":[-0.13876337615133,51.49606322044608],"type":"Point"}
}