{
  "type": "Feature",
  "properties": {
    "iso:country":"GB",
    "wof:name":"B33 0ED",
    "wof:placetype":"postalcode"
},
  "geometry": {"coordinates":[-1.77529187574097,52.48076523434842],"type":"Point"}
}