{
  "type": "Feature",
  "properties": {
    "iso:country":"GB",
    "wof:name":"PO30 3DY",
    "wof:placetype":"postalcode"
},
  "geometry": {"coordinates":[-1.30834485804475,50.67878034291109],"type":"Point"}
}