{
  "type": "Feature",
  "properties": {
    "iso:country":"GB",
    "wof:name":"B60 3BW",
    "wof:placetype":"postalcode"
},
  "geometry": {"coordinates":[-2.04420353401384,52.32056875602174],"type":"Point"}
}