{
  "type": "Feature",
  "properties": {
    "date:inception_lower":"2000-10-01",
    "date:inception_upper":"2000-10-31",
    "iso:country":"GB",
    "wof:name":"WD18 0EG",
    "wof:placetype":"postalcode"
},
  "geometry": {"coordinates":[-0.395821,51.65458],"type":"Point"}
}