{
  "type": "Feature",
  "properties": {
    "iso:country":"GB",
    "wof:name":"OX26 3ZN",
    "wof:placetype":"postalcode"
},
  "geometry": {"coordinates":[-1.16208640394946,51.91274483802533],"type":"Point"}
}