{
  "type": "Feature",
  "properties": {
    "iso:country":"GB",
    "wof:name":"SA4 8QX",
    "wof:placetype":"postalcode"
},
  "geometry": {"coordinates":[-4.04123053126573,51.71186706966915],"type":"Point"}
}