{
  "type": "Feature",
  "properties": {
    "iso:country":"GB",
    "wof:name":"S18 8NB",
    "wof:placetype":"postalcode"
},
  "geometry": {"coordinates":[-1.49128777334072,53.2999911561628],"type":"Point"}
}