{
  "type": "Feature",
  "properties": {
    "iso:country": "GB",
    "wof:name": "S18 8NB",
    "wof:placetype": "postalcode"
  },
  "geometry": {"coordinates":[-1.491288,53.299991],"type":"Point"}
}
