{
  "type": "Feature",
  "properties": {
    "iso:country":"GB",
    "wof:name":"CW3 9HG",
    "wof:placetype":"postalcode"
},
  "geometry": {"coordinates":[-2.33671364502014,53.00645258538944],"type":"Point"}
}