{
  "type": "Feature",
  "properties": {
    "date:inception_lower": "1993-08-01",
    "date:inception_upper": "1993-08-01",
    "iso:country": "GB",
    "wof:name": "CW3 9HG",
    "wof:placetype": "postalcode"
  },
  "geometry": {"coordinates":[-2.336714,53.006453],"type":"Point"}
}
