{
  "type": "Feature",
  "properties": {
    "iso:country":"GB",
    "wof:name":"KW17 2HS",
    "wof:placetype":"postalcode"
},
  "geometry": {"coordinates":[-3.24381433071939,59.07414465532958],"type":"Point"}
}