{
  "type": "Feature",
  "properties": {
    "iso:country":"GB",
    "wof:name":"HA4 7JD",
    "wof:placetype":"postalcode"
},
  "geometry": {"coordinates":[-0.43297557555549,51.57525901427555],"type":"Point"}
}