{
  "type": "Feature",
  "properties": {
    "iso:country":"GB",
    "wof:name":"GU11 3AE",
    "wof:placetype":"postalcode"
},
  "geometry": {"coordinates":[-0.77572384464565,51.24628690460781],"type":"Point"}
}