{
  "type": "Feature",
  "properties": {
    "date:inception_lower":"1997-12-01",
    "date:inception_upper":"1997-12-31",
    "iso:country":"GB",
    "wof:name":"BS22 6QR",
    "wof:placetype":"postalcode"
},
  "geometry": {"coordinates":[-2.926593,51.36139],"type":"Point"}
}