{
  "type": "Feature",
  "properties": {
    "iso:country":"GB",
    "wof:name":"BB12 7PJ",
    "wof:placetype":"postalcode"
},
  "geometry": {"coordinates":[-2.35297596512341,53.80768478710699],"type":"Point"}
}