{
  "type": "Feature",
  "properties": {
    "iso:country": "GB",
    "wof:name": "NN14 3ET",
    "wof:placetype": "postalcode"
  },
  "geometry": {"coordinates":[-0.612192,52.458411],"type":"Point"}
}
