{
  "type": "Feature",
  "properties": {
    "iso:country":"GB",
    "wof:name":"NN14 3ET",
    "wof:placetype":"postalcode"
},
  "geometry": {"coordinates":[-0.6121916033826,52.45841094899769],"type":"Point"}
}