{
  "type": "Feature",
  "properties": {
    "iso:country":"GB",
    "wof:name":"HU14 3QW",
    "wof:placetype":"postalcode"
},
  "geometry": {"coordinates":[-0.48265440244725,53.74086442429294],"type":"Point"}
}