{
  "type": "Feature",
  "properties": {
    "date:inception_lower":"1994-05-01",
    "date:inception_upper":"1994-05-31",
    "iso:country":"GB",
    "wof:name":"M7 2EX",
    "wof:placetype":"postalcode"
},
  "geometry": {"coordinates":[-2.267922,53.504832],"type":"Point"}
}