{
  "type": "Feature",
  "properties": {
    "iso:country":"GB",
    "wof:name":"M7 2EX",
    "wof:placetype":"postalcode"
},
  "geometry": {"coordinates":[-2.26792229677665,53.50483205729028],"type":"Point"}
}