{
  "type": "Feature",
  "properties": {
    "iso:country":"GB",
    "wof:name":"HR2 0RE",
    "wof:placetype":"postalcode"
},
  "geometry": {"coordinates":[-2.95855587150221,52.01959580123454],"type":"Point"}
}