{
  "type": "Feature",
  "properties": {
    "iso:country": "GB",
    "wof:name": "HR2 0RE",
    "wof:placetype": "postalcode"
  },
  "geometry": {"coordinates":[-2.958546,52.019613],"type":"Point"}
}
