{
  "type": "Feature",
  "properties": {
    "iso:country":"GB",
    "wof:name":"UB5 4NT",
    "wof:placetype":"postalcode"
},
  "geometry": {"coordinates":[-0.3606111928218,51.55296796641688],"type":"Point"}
}