{
  "type": "Feature",
  "properties": {
    "iso:country": "GB",
    "wof:name": "S35 7EU",
    "wof:placetype": "postalcode"
  },
  "geometry": {"coordinates":[-1.528982,53.479685],"type":"Point"}
}
