{
  "type": "Feature",
  "properties": {
    "iso:country":"GB",
    "wof:name":"S35 7EU",
    "wof:placetype":"postalcode"
},
  "geometry": {"coordinates":[-1.51760419968991,53.47448956704682],"type":"Point"}
}