{
  "type": "Feature",
  "properties": {
    "date:inception_lower": "1980-01-01",
    "date:inception_upper": "1980-01-01",
    "iso:country": "GB",
    "wof:name": "WS1 4LJ",
    "wof:placetype": "postalcode"
  },
  "geometry": {"coordinates":[-1.990454,52.57209],"type":"Point"}
}
