{
  "type": "Feature",
  "properties": {
    "iso:country":"GB",
    "wof:name":"WS1 4LJ",
    "wof:placetype":"postalcode"
},
  "geometry": {"coordinates":[-1.99045450343768,52.57209025325545],"type":"Point"}
}