{
  "type": "Feature",
  "properties": {
    "date:inception_lower": "1992-08-01",
    "date:inception_upper": "1992-08-01",
    "iso:country": "GB",
    "wof:name": "DE72 3JS",
    "wof:placetype": "postalcode"
  },
  "geometry": {"coordinates":[-1.371752,52.905697],"type":"Point"}
}
