{
  "type": "Feature",
  "properties": {
    "iso:country":"GB",
    "wof:name":"B46 1AT",
    "wof:placetype":"postalcode"
},
  "geometry": {"coordinates":[-1.70658191193867,52.51045263383268],"type":"Point"}
}