{
  "type": "Feature",
  "properties": {
    "date:inception_lower":"2008-11-01",
    "date:inception_upper":"2008-11-30",
    "iso:country":"GB",
    "wof:name":"B46 1AT",
    "wof:placetype":"postalcode"
},
  "geometry": {"coordinates":[-1.706582,52.510453],"type":"Point"}
}