{
  "type": "Feature",
  "properties": {
    "iso:country": "GB",
    "wof:name": "B46 1AT",
    "wof:placetype": "postalcode"
  },
  "geometry": {"coordinates":[-1.706582,52.510453],"type":"Point"}
}
