{
  "type": "Feature",
  "properties": {
    "iso:country":"GB",
    "wof:name":"WA7 2TE",
    "wof:placetype":"postalcode"
},
  "geometry": {"coordinates":[-2.69342397155876,53.32075690254487],"type":"Point"}
}