{
  "type": "Feature",
  "properties": {
    "iso:country":"GB",
    "wof:name":"LS25 2GY",
    "wof:placetype":"postalcode"
},
  "geometry": {"coordinates":[-1.37453547181918,53.79971759181891],"type":"Point"}
}