{
  "type": "Feature",
  "properties": {
    "date:inception_lower":"1980-01-01",
    "date:inception_upper":"1980-01-31",
    "iso:country":"GB",
    "wof:name":"DT2 7RJ",
    "wof:placetype":"postalcode"
},
  "geometry": {"coordinates":[-2.405298,50.818433],"type":"Point"}
}