{
  "type": "Feature",
  "properties": {
    "iso:country":"GB",
    "wof:name":"DT2 7RJ",
    "wof:placetype":"postalcode"
},
  "geometry": {"coordinates":[-2.40531364462038,50.81840550892263],"type":"Point"}
}