{
  "type": "Feature",
  "properties": {
    "date:inception_lower":"2015-05-01",
    "date:inception_upper":"2015-05-31",
    "iso:country":"GB",
    "wof:name":"LS29 7BX",
    "wof:placetype":"postalcode"
},
  "geometry": {"coordinates":[-1.757817,53.908014],"type":"Point"}
}