{
  "type": "Feature",
  "properties": {
    "iso:country": "GB",
    "wof:name": "LS29 7BX",
    "wof:placetype": "postalcode"
  },
  "geometry": {"coordinates":[-1.757817,53.908014],"type":"Point"}
}
