{
  "type": "Feature",
  "properties": {
    "iso:country":"GB",
    "wof:name":"LS29 7BX",
    "wof:placetype":"postalcode"
},
  "geometry": {"coordinates":[-1.75781746141909,53.90801413925467],"type":"Point"}
}