{
  "type": "Feature",
  "properties": {
    "iso:country":"GB",
    "wof:name":"NW3 1BP",
    "wof:placetype":"postalcode"
},
  "geometry": {"coordinates":[-0.17125276016452,51.55968337933954],"type":"Point"}
}