{
  "type": "Feature",
  "properties": {
    "iso:country":"GB",
    "wof:name":"SK6 5NQ",
    "wof:placetype":"postalcode"
},
  "geometry": {"coordinates":[-2.00842660934232,53.39167092490503],"type":"Point"}
}