{
  "type": "Feature",
  "properties": {
    "iso:country":"GB",
    "wof:name":"BS5 8AF",
    "wof:placetype":"postalcode"
},
  "geometry": {"coordinates":[-2.54826765028377,51.45932713598692],"type":"Point"}
}