{
  "type": "Feature",
  "properties": {
    "iso:country":"GB",
    "wof:name":"TN4 8ES",
    "wof:placetype":"postalcode"
},
  "geometry": {"coordinates":[0.25411389398665,51.13509483914476],"type":"Point"}
}