{
  "type": "Feature",
  "properties": {
    "iso:country": "GB",
    "wof:name": "TN4 8ES",
    "wof:placetype": "postalcode"
  },
  "geometry": {"coordinates":[0.254114,51.135095],"type":"Point"}
}
