{
  "type": "Feature",
  "properties": {
    "date:inception_lower": "1980-01-01",
    "date:inception_upper": "1980-01-01",
    "iso:country": "GB",
    "wof:name": "DH9 9RT",
    "wof:placetype": "postalcode"
  },
  "geometry": {"coordinates":[-1.730659,54.884618],"type":"Point"}
}
