{
  "type": "Feature",
  "properties": {
    "iso:country":"GB",
    "wof:name":"DH9 9RT",
    "wof:placetype":"postalcode"
},
  "geometry": {"coordinates":[-1.73061619104951,54.88463702563246],"type":"Point"}
}