{
  "type": "Feature",
  "properties": {
    "iso:country": "GB",
    "wof:name": "PE14 7SL",
    "wof:placetype": "postalcode"
  },
  "geometry": {"coordinates":[0.274988,52.679905],"type":"Point"}
}
