{
  "type": "Feature",
  "properties": {
    "iso:country": "GB",
    "wof:name": "PE14 7SL",
    "wof:placetype": "postalcode"
  },
  "geometry": {"coordinates":[0.274941,52.679859],"type":"Point"}
}
