{
  "type": "Feature",
  "properties": {
    "iso:country":"GB",
    "wof:name":"SP2 0FT",
    "wof:placetype":"postalcode"
},
  "geometry": {"coordinates":[-1.85281978183188,51.08255580309697],"type":"Point"}
}