{
  "type": "Feature",
  "properties": {
    "iso:country":"GB",
    "wof:name":"NE17 7JX",
    "wof:placetype":"postalcode"
},
  "geometry": {"coordinates":[-1.82212262098197,54.91484651833955],"type":"Point"}
}