{
  "type": "Feature",
  "properties": {
    "iso:country": "GB",
    "wof:name": "NE17 7JX",
    "wof:placetype": "postalcode"
  },
  "geometry": {"coordinates":[-1.822123,54.914847],"type":"Point"}
}
