{
  "type": "Feature",
  "properties": {
    "iso:country": "GB",
    "wof:name": "S5 6HF",
    "wof:placetype": "postalcode"
  },
  "geometry": {"coordinates":[-1.444298,53.415161],"type":"Point"}
}
