{
  "type": "Feature",
  "properties": {
    "date:inception_lower": "2001-06-01",
    "date:inception_upper": "2001-06-01",
    "iso:country": "GB",
    "wof:name": "PR25 4QN",
    "wof:placetype": "postalcode"
  },
  "geometry": {"coordinates":[-2.684517,53.703973],"type":"Point"}
}
