{
  "type": "Feature",
  "properties": {
    "date:inception_lower": "1980-01-01",
    "date:inception_upper": "1980-01-01",
    "iso:country": "GB",
    "wof:name": "SN6 8DX",
    "wof:placetype": "postalcode"
  },
  "geometry": {"coordinates":[-1.654007,51.596357],"type":"Point"}
}
