{
  "type": "Feature",
  "properties": {
    "iso:country":"GB",
    "wof:name":"DN9 1NG",
    "wof:placetype":"postalcode"
},
  "geometry": {"coordinates":[-0.79208507738892,53.54513690653579],"type":"Point"}
}