{
  "type": "Feature",
  "properties": {
    "iso:country":"GB",
    "wof:name":"EN8 8UQ",
    "wof:placetype":"postalcode"
},
  "geometry": {"coordinates":[-0.02638118014581,51.69977686939604],"type":"Point"}
}