{
  "type": "Feature",
  "properties": {
    "iso:country":"GB",
    "wof:name":"SA2 9EL",
    "wof:placetype":"postalcode"
},
  "geometry": {"coordinates":[-3.98902040972006,51.62347686058826],"type":"Point"}
}