{
  "type": "Feature",
  "properties": {
    "iso:country": "GB",
    "wof:name": "IP26 5AU",
    "wof:placetype": "postalcode"
  },
  "geometry": {"coordinates":[0.613288,52.546181],"type":"Point"}
}
