{
  "type": "Feature",
  "properties": {
    "iso:country":"GB",
    "wof:name":"IP26 5AU",
    "wof:placetype":"postalcode"
},
  "geometry": {"coordinates":[0.61326611222703,52.54616151370951],"type":"Point"}
}