{
  "type": "Feature",
  "properties": {
    "iso:country":"GB",
    "wof:name":"HP1 3QN",
    "wof:placetype":"postalcode"
},
  "geometry": {"coordinates":[-0.49150570782281,51.75732103442003],"type":"Point"}
}