{
  "type": "Feature",
  "properties": {
    "date:inception_lower":"1980-01-01",
    "date:inception_upper":"1980-01-31",
    "iso:country":"GB",
    "wof:name":"ME3 7SL",
    "wof:placetype":"postalcode"
},
  "geometry": {"coordinates":[0.494709,51.454366],"type":"Point"}
}