{
  "type": "Feature",
  "properties": {
    "iso:country": "GB",
    "wof:name": "ME3 7SL",
    "wof:placetype": "postalcode"
  },
  "geometry": {"coordinates":[0.494709,51.454366],"type":"Point"}
}
