{
  "type": "Feature",
  "properties": {
    "iso:country":"GB",
    "wof:name":"ME3 7SL",
    "wof:placetype":"postalcode"
},
  "geometry": {"coordinates":[0.49470928709403,51.45436582356837],"type":"Point"}
}