{
  "type": "Feature",
  "properties": {
    "iso:country":"GB",
    "wof:name":"BA14 6BT",
    "wof:placetype":"postalcode"
},
  "geometry": {"coordinates":[-2.13227182037133,51.33086693062899],"type":"Point"}
}