{
  "type": "Feature",
  "properties": {
    "date:inception_lower": "1980-01-01",
    "date:inception_upper": "1980-01-01",
    "iso:country": "GB",
    "wof:name": "BA14 6BT",
    "wof:placetype": "postalcode"
  },
  "geometry": {"coordinates":[-2.132272,51.330867],"type":"Point"}
}
