{
  "type": "Feature",
  "properties": {
    "iso:country":"GB",
    "wof:name":"EX4 5SR",
    "wof:placetype":"postalcode"
},
  "geometry": {"coordinates":[-3.51989289492914,50.75773845048602],"type":"Point"}
}