{
  "type": "Feature",
  "properties": {
    "date:inception_lower":"2004-08-01",
    "date:inception_upper":"2004-08-31",
    "iso:country":"GB",
    "wof:name":"EX4 5SR",
    "wof:placetype":"postalcode"
},
  "geometry": {"coordinates":[-3.519893,50.757738],"type":"Point"}
}