{
  "type": "Feature",
  "properties": {
    "iso:country":"GB",
    "wof:name":"G46 7AW",
    "wof:placetype":"postalcode"
},
  "geometry": {"coordinates":[-4.30601727702524,55.80556961562112],"type":"Point"}
}