{
  "type": "Feature",
  "properties": {
    "iso:country": "GB",
    "wof:name": "SP2 8PH",
    "wof:placetype": "postalcode"
  },
  "geometry": {"coordinates":[-1.8508,51.075791],"type":"Point"}
}
