{
  "type": "Feature",
  "properties": {
    "iso:country":"GB",
    "wof:name":"SP2 8PH",
    "wof:placetype":"postalcode"
},
  "geometry": {"coordinates":[-1.8508000150319,51.07579117284384],"type":"Point"}
}