{
  "type": "Feature",
  "properties": {
    "iso:country": "GB",
    "wof:name": "GU22 0PX",
    "wof:placetype": "postalcode"
  },
  "geometry": {"coordinates":[-0.58311,51.300173],"type":"Point"}
}
