{
  "type": "Feature",
  "properties": {
    "date:inception_lower": "1980-01-01",
    "date:inception_upper": "1980-01-01",
    "iso:country": "GB",
    "wof:name": "RG7 3SQ",
    "wof:placetype": "postalcode"
  },
  "geometry": {"coordinates":[-1.068541,51.377595],"type":"Point"}
}
