{
  "type": "Feature",
  "properties": {
    "iso:country": "GB",
    "wof:name": "RG7 3SQ",
    "wof:placetype": "postalcode"
  },
  "geometry": {"coordinates":[-1.068541,51.377595],"type":"Point"}
}
