{
  "type": "Feature",
  "properties": {
    "iso:country":"GB",
    "wof:name":"RG7 3SQ",
    "wof:placetype":"postalcode"
},
  "geometry": {"coordinates":[-1.06854135125109,51.37759542173185],"type":"Point"}
}