{
  "type": "Feature",
  "properties": {
    "date:inception_lower": "2020-10-01",
    "date:inception_upper": "2020-10-01",
    "iso:country": "GB",
    "wof:name": "WV5 0NR",
    "wof:placetype": "postalcode"
  },
  "geometry": {"coordinates":[-2.180921,52.52922],"type":"Point"}
}
