{
  "type": "Feature",
  "properties": {
    "date:inception_lower": "1984-09-01",
    "date:inception_upper": "1984-09-01",
    "iso:country": "GB",
    "wof:name": "DD1 5EU",
    "wof:placetype": "postalcode"
  },
  "geometry": {"coordinates":[-2.980223,56.459513],"type":"Point"}
}
