{
  "type": "Feature",
  "properties": {
    "iso:country":"GB",
    "wof:name":"BD2 4AS",
    "wof:placetype":"postalcode"
},
  "geometry": {"coordinates":[-1.74756203685473,53.81379100165253],"type":"Point"}
}