{
  "type": "Feature",
  "properties": {
    "iso:country":"GB",
    "wof:name":"SA62 6UD",
    "wof:placetype":"postalcode"
},
  "geometry": {"coordinates":[-5.19809199966289,51.88447549932553],"type":"Point"}
}