{
  "type": "Feature",
  "properties": {
    "iso:country": "GB",
    "wof:name": "SA62 6UD",
    "wof:placetype": "postalcode"
  },
  "geometry": {"coordinates":[-5.198067,51.884483],"type":"Point"}
}
