{
  "type": "Feature",
  "properties": {
    "iso:country":"GB",
    "wof:name":"PE28 2QX",
    "wof:placetype":"postalcode"
},
  "geometry": {"coordinates":[-0.16018450286849,52.41544254678961],"type":"Point"}
}