{
  "type": "Feature",
  "properties": {
    "date:inception_lower": "2018-06-01",
    "date:inception_upper": "2018-06-01",
    "iso:country": "GB",
    "wof:name": "IP3 8XS",
    "wof:placetype": "postalcode"
  },
  "geometry": {"coordinates":[1.192549,52.048708],"type":"Point"}
}
