{
  "type": "Feature",
  "properties": {
    "date:inception_lower":"1980-01-01",
    "date:inception_upper":"1980-01-31",
    "iso:country":"GB",
    "wof:name":"TR26 3EY",
    "wof:placetype":"postalcode"
},
  "geometry": {"coordinates":[-5.470036,50.181075],"type":"Point"}
}