{
  "type": "Feature",
  "properties": {
    "iso:country": "GB",
    "wof:name": "TR26 3EY",
    "wof:placetype": "postalcode"
  },
  "geometry": {"coordinates":[-5.470036,50.181075],"type":"Point"}
}
