{
  "type": "Feature",
  "properties": {
    "iso:country":"GB",
    "wof:name":"TR26 3EY",
    "wof:placetype":"postalcode"
},
  "geometry": {"coordinates":[-5.47003625521757,50.18107455933878],"type":"Point"}
}