{
  "type": "Feature",
  "properties": {
    "iso:country": "GB",
    "wof:name": "NR34 7EJ",
    "wof:placetype": "postalcode"
  },
  "geometry": {"coordinates":[1.581303,52.451283],"type":"Point"}
}
