{
  "type": "Feature",
  "properties": {
    "iso:country": "GB",
    "wof:name": "NR20 5HS",
    "wof:placetype": "postalcode"
  },
  "geometry": {"coordinates":[0.964913,52.738889],"type":"Point"}
}
