{
  "type": "Feature",
  "properties": {
    "iso:country":"GB",
    "wof:name":"WA8 9ER",
    "wof:placetype":"postalcode"
},
  "geometry": {"coordinates":[-2.73679860291587,53.38719402076243],"type":"Point"}
}