{
  "type": "Feature",
  "properties": {
    "iso:country":"GB",
    "wof:name":"E17 6DG",
    "wof:placetype":"postalcode"
},
  "geometry": {"coordinates":[-0.03528833758497,51.59296100650789],"type":"Point"}
}