{
  "type": "Feature",
  "properties": {
    "iso:country":"GB",
    "wof:name":"CF33 4NU",
    "wof:placetype":"postalcode"
},
  "geometry": {"coordinates":[-3.69791056853481,51.5238652642161],"type":"Point"}
}