{
  "type": "Feature",
  "properties": {
    "iso:country": "GB",
    "wof:name": "DE12 8DZ",
    "wof:placetype": "postalcode"
  },
  "geometry": {"coordinates":[-1.61925,52.727963],"type":"Point"}
}
