{
  "type": "Feature",
  "properties": {
    "date:inception_lower": "1980-01-01",
    "date:inception_upper": "1980-01-01",
    "iso:country": "GB",
    "wof:name": "DE12 8DZ",
    "wof:placetype": "postalcode"
  },
  "geometry": {"coordinates":[-1.61925,52.727963],"type":"Point"}
}
