{
  "type": "Feature",
  "properties": {
    "iso:country":"GB",
    "wof:name":"PO15 5BF",
    "wof:placetype":"postalcode"
},
  "geometry": {"coordinates":[-1.24859081905733,50.86725819123433],"type":"Point"}
}