{
  "type": "Feature",
  "properties": {
    "date:inception_lower":"2007-04-01",
    "date:inception_upper":"2007-04-30",
    "iso:country":"GB",
    "wof:name":"PO15 5BF",
    "wof:placetype":"postalcode"
},
  "geometry": {"coordinates":[-1.248591,50.867258],"type":"Point"}
}