{
  "type": "Feature",
  "properties": {
    "iso:country":"GB",
    "wof:name":"OL9 7RY",
    "wof:placetype":"postalcode"
},
  "geometry": {"coordinates":[-2.14030528663019,53.53477481053991],"type":"Point"}
}