{
  "type": "Feature",
  "properties": {
    "date:inception_lower":"1992-01-01",
    "date:inception_upper":"1992-01-31",
    "iso:country":"GB",
    "wof:name":"LN7 6JP",
    "wof:placetype":"postalcode"
},
  "geometry": {"coordinates":[-0.429306,53.504821],"type":"Point"}
}