{
  "type": "Feature",
  "properties": {
    "iso:country": "GB",
    "wof:name": "CH44 7HN",
    "wof:placetype": "postalcode"
  },
  "geometry": {"coordinates":[-3.028582,53.410879],"type":"Point"}
}
