{
  "type": "Feature",
  "properties": {
    "iso:country":"GB",
    "wof:name":"SM6 8QD",
    "wof:placetype":"postalcode"
},
  "geometry": {"coordinates":[-0.14626300056934,51.35972802252898],"type":"Point"}
}