{
  "type": "Feature",
  "properties": {
    "iso:country": "GB",
    "wof:name": "SM6 8QD",
    "wof:placetype": "postalcode"
  },
  "geometry": {"coordinates":[-0.146263,51.359728],"type":"Point"}
}
