{
  "type": "Feature",
  "properties": {
    "iso:country": "GB",
    "wof:name": "KT21 2FD",
    "wof:placetype": "postalcode"
  },
  "geometry": {"coordinates":[-0.307323,51.305908],"type":"Point"}
}
