{
  "type": "Feature",
  "properties": {
    "date:inception_lower": "1999-06-01",
    "date:inception_upper": "1999-06-01",
    "iso:country": "GB",
    "wof:name": "NP20 6LF",
    "wof:placetype": "postalcode"
  },
  "geometry": {"coordinates":[-2.997678,51.611516],"type":"Point"}
}
