{
  "type": "Feature",
  "properties": {
    "iso:country":"GB",
    "wof:name":"NR3 1NG",
    "wof:placetype":"postalcode"
},
  "geometry": {"coordinates":[1.29804714704949,52.63823396703952],"type":"Point"}
}