{
  "type": "Feature",
  "properties": {
    "date:inception_lower":"1980-01-01",
    "date:inception_upper":"1980-01-31",
    "iso:country":"GB",
    "wof:name":"WN5 7TS",
    "wof:placetype":"postalcode"
},
  "geometry": {"coordinates":[-2.708745,53.493179],"type":"Point"}
}