{
  "type": "Feature",
  "properties": {
    "date:inception_lower": "2002-06-01",
    "date:inception_upper": "2002-06-01",
    "iso:country": "GB",
    "wof:name": "BD13 5DB",
    "wof:placetype": "postalcode"
  },
  "geometry": {"coordinates":[-1.899446,53.822885],"type":"Point"}
}
