{
  "type": "Feature",
  "properties": {
    "iso:country": "GB",
    "wof:name": "CV1 4DR",
    "wof:placetype": "postalcode"
  },
  "geometry": {"coordinates":[-1.506501,52.421747],"type":"Point"}
}
