{
  "type": "Feature",
  "properties": {
    "iso:country":"GB",
    "wof:name":"WA3 4AN",
    "wof:placetype":"postalcode"
},
  "geometry": {"coordinates":[-2.51414812923086,53.45910139756885],"type":"Point"}
}