{
  "type": "Feature",
  "properties": {
    "iso:country": "GB",
    "wof:name": "WA3 4AN",
    "wof:placetype": "postalcode"
  },
  "geometry": {"coordinates":[-2.514148,53.459101],"type":"Point"}
}
