{
  "type": "Feature",
  "properties": {
    "date:inception_lower": "1980-01-01",
    "date:inception_upper": "1980-01-01",
    "iso:country": "GB",
    "wof:name": "LL21 0PP",
    "wof:placetype": "postalcode"
  },
  "geometry": {"coordinates":[-3.488373,52.989566],"type":"Point"}
}
