{
  "type": "Feature",
  "properties": {
    "iso:country":"GB",
    "wof:name":"MK7 7HP",
    "wof:placetype":"postalcode"
},
  "geometry": {"coordinates":[-0.7002314647578,52.01580878706498],"type":"Point"}
}