{
  "type": "Feature",
  "properties": {
    "date:inception_lower": "1992-08-01",
    "date:inception_upper": "1992-08-01",
    "iso:country": "GB",
    "wof:name": "MK7 7HP",
    "wof:placetype": "postalcode"
  },
  "geometry": {"coordinates":[-0.700231,52.015809],"type":"Point"}
}
