{
  "type": "Feature",
  "properties": {
    "iso:country":"GB",
    "wof:name":"LL11 2LH",
    "wof:placetype":"postalcode"
},
  "geometry": {"coordinates":[-3.00020466327292,53.0630859761198],"type":"Point"}
}