{
  "type": "Feature",
  "properties": {
    "date:inception_lower": "1980-01-01",
    "date:inception_upper": "1980-01-01",
    "iso:country": "GB",
    "wof:name": "DL12 9TX",
    "wof:placetype": "postalcode"
  },
  "geometry": {"coordinates":[-1.8338,54.513513],"type":"Point"}
}
