{
  "type": "Feature",
  "properties": {
    "iso:country":"GB",
    "wof:name":"DL12 9TX",
    "wof:placetype":"postalcode"
},
  "geometry": {"coordinates":[-1.83379986002884,54.51351280788888],"type":"Point"}
}