{
  "type": "Feature",
  "properties": {
    "date:inception_lower": "1980-01-01",
    "date:inception_upper": "1980-01-01",
    "iso:country": "GB",
    "wof:name": "DH4 4LX",
    "wof:placetype": "postalcode"
  },
  "geometry": {"coordinates":[-1.468073,54.870472],"type":"Point"}
}
