{
  "type": "Feature",
  "properties": {
    "iso:country":"GB",
    "wof:name":"DH4 4LX",
    "wof:placetype":"postalcode"
},
  "geometry": {"coordinates":[-1.4680726075593,54.87047182374109],"type":"Point"}
}