{
  "type": "Feature",
  "properties": {
    "iso:country":"GB",
    "wof:name":"CW1 4NL",
    "wof:placetype":"postalcode"
},
  "geometry": {"coordinates":[-2.44274230939165,53.11223976547539],"type":"Point"}
}