{
  "type": "Feature",
  "properties": {
    "iso:country": "GB",
    "wof:name": "WA2 9DU",
    "wof:placetype": "postalcode"
  },
  "geometry": {"coordinates":[-2.585467,53.411367],"type":"Point"}
}
