{
  "type": "Feature",
  "properties": {
    "date:inception_lower": "1992-01-01",
    "date:inception_upper": "1992-01-01",
    "iso:country": "GB",
    "wof:name": "EC1V 7JA",
    "wof:placetype": "postalcode"
  },
  "geometry": {"coordinates":[-0.102604,51.52863],"type":"Point"}
}
