{
  "type": "Feature",
  "properties": {
    "iso:country": "GB",
    "wof:name": "NR4 6DE",
    "wof:placetype": "postalcode"
  },
  "geometry": {"coordinates":[1.281268,52.60921],"type":"Point"}
}
