{
  "type": "Feature",
  "properties": {
    "iso:country": "GB",
    "wof:name": "BB12 8XB",
    "wof:placetype": "postalcode"
  },
  "geometry": {"coordinates":[-2.276285,53.799986],"type":"Point"}
}
