{
  "type": "Feature",
  "properties": {
    "date:inception_lower":"1990-02-01",
    "date:inception_upper":"1990-02-28",
    "iso:country":"GB",
    "wof:name":"BB12 8XB",
    "wof:placetype":"postalcode"
},
  "geometry": {"coordinates":[-2.276285,53.799986],"type":"Point"}
}