{
  "type": "Feature",
  "properties": {
    "iso:country":"GB",
    "wof:name":"CT12 6SH",
    "wof:placetype":"postalcode"
},
  "geometry": {"coordinates":[1.40007992285693,51.35442728910494],"type":"Point"}
}