{
  "type": "Feature",
  "properties": {
    "iso:country": "GB",
    "wof:name": "CT12 6SH",
    "wof:placetype": "postalcode"
  },
  "geometry": {"coordinates":[1.40008,51.354427],"type":"Point"}
}
