{
  "type": "Feature",
  "properties": {
    "iso:country":"GB",
    "wof:name":"DE24 0SH",
    "wof:placetype":"postalcode"
},
  "geometry": {"coordinates":[-1.41149463553276,52.89032131060427],"type":"Point"}
}