{
  "type": "Feature",
  "properties": {
    "iso:country": "GB",
    "wof:name": "DE24 0SH",
    "wof:placetype": "postalcode"
  },
  "geometry": {"coordinates":[-1.411495,52.890321],"type":"Point"}
}
