{
  "type": "Feature",
  "properties": {
    "iso:country":"GB",
    "wof:name":"S62 7NR",
    "wof:placetype":"postalcode"
},
  "geometry": {"coordinates":[-1.36333462328331,53.47286874956756],"type":"Point"}
}