{
  "type": "Feature",
  "properties": {
    "date:inception_lower":"1980-01-01",
    "date:inception_upper":"1980-01-31",
    "iso:country":"GB",
    "wof:name":"S62 7NR",
    "wof:placetype":"postalcode"
},
  "geometry": {"coordinates":[-1.363335,53.472869],"type":"Point"}
}