{
  "type": "Feature",
  "properties": {
    "iso:country":"GB",
    "wof:name":"BL7 0AA",
    "wof:placetype":"postalcode"
},
  "geometry": {"coordinates":[-2.39525989196585,53.64055334011105],"type":"Point"}
}