{
  "type": "Feature",
  "properties": {
    "iso:country": "GB",
    "wof:name": "BL7 0AA",
    "wof:placetype": "postalcode"
  },
  "geometry": {"coordinates":[-2.39526,53.640553],"type":"Point"}
}
