{
  "type": "Feature",
  "properties": {
    "iso:country":"GB",
    "wof:name":"NW11 0PH",
    "wof:placetype":"postalcode"
},
  "geometry": {"coordinates":[-0.20015529360484,51.57780027337297],"type":"Point"}
}