{
  "type": "Feature",
  "properties": {
    "iso:country":"GB",
    "wof:name":"DD4 8LX",
    "wof:placetype":"postalcode"
},
  "geometry": {"coordinates":[-2.93021534099204,56.48227839615537],"type":"Point"}
}