{
  "type": "Feature",
  "properties": {
    "iso:country":"GB",
    "wof:name":"CA25 5RE",
    "wof:placetype":"postalcode"
},
  "geometry": {"coordinates":[-3.54056205715097,54.5292813142363],"type":"Point"}
}