{
  "type": "Feature",
  "properties": {
    "date:inception_lower": "1980-01-01",
    "date:inception_upper": "1980-01-01",
    "iso:country": "GB",
    "wof:name": "CA25 5RE",
    "wof:placetype": "postalcode"
  },
  "geometry": {"coordinates":[-3.540563,54.52929],"type":"Point"}
}
