{
  "type": "Feature",
  "properties": {
    "iso:country":"GB",
    "wof:name":"LL68 9PF",
    "wof:placetype":"postalcode"
},
  "geometry": {"coordinates":[-4.35437457846928,53.39736854060654],"type":"Point"}
}