{
  "type": "Feature",
  "properties": {
    "date:inception_lower": "1980-01-01",
    "date:inception_upper": "1980-01-01",
    "iso:country": "GB",
    "wof:name": "LL68 9PF",
    "wof:placetype": "postalcode"
  },
  "geometry": {"coordinates":[-4.354375,53.397369],"type":"Point"}
}
