{
  "type": "Feature",
  "properties": {
    "iso:country":"GB",
    "wof:name":"LA13 9RF",
    "wof:placetype":"postalcode"
},
  "geometry": {"coordinates":[-3.19695846371492,54.11368361914894],"type":"Point"}
}