{
  "type": "Feature",
  "properties": {
    "iso:country": "GB",
    "wof:name": "LA13 9RF",
    "wof:placetype": "postalcode"
  },
  "geometry": {"coordinates":[-3.196958,54.113684],"type":"Point"}
}
