{
  "type": "Feature",
  "properties": {
    "iso:country":"GB",
    "wof:name":"TW12 1HL",
    "wof:placetype":"postalcode"
},
  "geometry": {"coordinates":[-0.35980789605654,51.42841335396933],"type":"Point"}
}