{
  "type": "Feature",
  "properties": {
    "iso:country":"GB",
    "wof:name":"EH32 9RH",
    "wof:placetype":"postalcode"
},
  "geometry": {"coordinates":[-2.96502048424891,55.96040686672286],"type":"Point"}
}