{
  "type": "Feature",
  "properties": {
    "iso:country": "GB",
    "wof:name": "EH32 9RH",
    "wof:placetype": "postalcode"
  },
  "geometry": {"coordinates":[-2.96502,55.960407],"type":"Point"}
}
