{
  "type": "Feature",
  "properties": {
    "iso:country":"GB",
    "wof:name":"N20 0QB",
    "wof:placetype":"postalcode"
},
  "geometry": {"coordinates":[-0.17688851792563,51.62435418157946],"type":"Point"}
}