{
  "type": "Feature",
  "properties": {
    "iso:country": "GB",
    "wof:name": "NE61 1TT",
    "wof:placetype": "postalcode"
  },
  "geometry": {"coordinates":[-1.68166,55.166523],"type":"Point"}
}
