{
  "type": "Feature",
  "properties": {
    "iso:country":"GB",
    "wof:name":"NE61 1TT",
    "wof:placetype":"postalcode"
},
  "geometry": {"coordinates":[-1.68166027012932,55.16652251162854],"type":"Point"}
}