{
  "type": "Feature",
  "properties": {
    "date:inception_lower": "2005-07-01",
    "date:inception_upper": "2005-07-01",
    "iso:country": "GB",
    "wof:name": "WS9 8AR",
    "wof:placetype": "postalcode"
  },
  "geometry": {"coordinates":[-1.926446,52.608351],"type":"Point"}
}
