{
  "type": "Feature",
  "properties": {
    "iso:country":"GB",
    "wof:name":"WS9 8AR",
    "wof:placetype":"postalcode"
},
  "geometry": {"coordinates":[-1.92644618608055,52.6083507349925],"type":"Point"}
}