{
  "type": "Feature",
  "properties": {
    "iso:country":"GB",
    "wof:name":"KT3 6PB",
    "wof:placetype":"postalcode"
},
  "geometry": {"coordinates":[-0.24229946180528,51.39496650240802],"type":"Point"}
}