{
  "type": "Feature",
  "properties": {
    "iso:country":"GB",
    "wof:name":"DG1 3AY",
    "wof:placetype":"postalcode"
},
  "geometry": {"coordinates":[-3.59571332565774,55.07317080040038],"type":"Point"}
}