{
  "type": "Feature",
  "properties": {
    "iso:country":"GB",
    "wof:name":"LU4 9XB",
    "wof:placetype":"postalcode"
},
  "geometry": {"coordinates":[-0.4660059674064,51.89655147260767],"type":"Point"}
}