{
  "type": "Feature",
  "properties": {
    "date:inception_lower":"2016-01-01",
    "date:inception_upper":"2016-01-31",
    "iso:country":"GB",
    "wof:name":"HG1 9UU",
    "wof:placetype":"postalcode"
},
  "geometry": {"coordinates":[-1.546009,53.994843],"type":"Point"}
}