{
  "type": "Feature",
  "properties": {
    "iso:country":"GB",
    "wof:name":"CT1 1JF",
    "wof:placetype":"postalcode"
},
  "geometry": {"coordinates":[1.09376701388854,51.28603844969111],"type":"Point"}
}