{
  "type": "Feature",
  "properties": {
    "iso:country": "GB",
    "wof:name": "L18 2HE",
    "wof:placetype": "postalcode"
  },
  "geometry": {"coordinates":[-2.897244,53.387165],"type":"Point"}
}
