{
  "type": "Feature",
  "properties": {
    "iso:country":"GB",
    "wof:name":"PE30 3YD",
    "wof:placetype":"postalcode"
},
  "geometry": {"coordinates":[0.44270223187303,52.76738998632154],"type":"Point"}
}