{
  "type": "Feature",
  "properties": {
    "iso:country": "GB",
    "wof:name": "PE30 3YD",
    "wof:placetype": "postalcode"
  },
  "geometry": {"coordinates":[0.442702,52.76739],"type":"Point"}
}
