{
  "type": "Feature",
  "properties": {
    "iso:country":"GB",
    "wof:name":"FY5 4DT",
    "wof:placetype":"postalcode"
},
  "geometry": {"coordinates":[-2.99967436767608,53.87416345558553],"type":"Point"}
}