{
  "type": "Feature",
  "properties": {
    "iso:country": "GB",
    "wof:name": "ML4 1RD",
    "wof:placetype": "postalcode"
  },
  "geometry": {"coordinates":[-4.02524,55.817805],"type":"Point"}
}
