{
  "type": "Feature",
  "properties": {
    "iso:country":"GB",
    "wof:name":"ML4 1RD",
    "wof:placetype":"postalcode"
},
  "geometry": {"coordinates":[-4.0252399298319,55.81780469280487],"type":"Point"}
}