{
  "type": "Feature",
  "properties": {
    "iso:country":"GB",
    "wof:name":"IP13 7DP",
    "wof:placetype":"postalcode"
},
  "geometry": {"coordinates":[1.25127851385438,52.18554055420891],"type":"Point"}
}