{
  "type": "Feature",
  "properties": {
    "iso:country": "GB",
    "wof:name": "IP13 7DP",
    "wof:placetype": "postalcode"
  },
  "geometry": {"coordinates":[1.251279,52.185541],"type":"Point"}
}
