{
  "type": "Feature",
  "properties": {
    "date:inception_lower": "1980-01-01",
    "date:inception_upper": "1980-01-01",
    "iso:country": "GB",
    "wof:name": "LS7 1BA",
    "wof:placetype": "postalcode"
  },
  "geometry": {"coordinates":[-1.53112,53.805031],"type":"Point"}
}
