{
  "type": "Feature",
  "properties": {
    "iso:country":"GB",
    "wof:name":"BD12 0PT",
    "wof:placetype":"postalcode"
},
  "geometry": {"coordinates":[-1.75365431273478,53.7589678818528],"type":"Point"}
}