{
  "type": "Feature",
  "properties": {
    "iso:country":"GB",
    "wof:name":"CT15 5HW",
    "wof:placetype":"postalcode"
},
  "geometry": {"coordinates":[1.34989555376837,51.1851374612563],"type":"Point"}
}