{
  "type": "Feature",
  "properties": {
    "iso:country":"GB",
    "wof:name":"SA62 5SH",
    "wof:placetype":"postalcode"
},
  "geometry": {"coordinates":[-4.99528175245253,51.92850005965344],"type":"Point"}
}