{
  "type": "Feature",
  "properties": {
    "iso:country": "GB",
    "wof:name": "SA62 5SH",
    "wof:placetype": "postalcode"
  },
  "geometry": {"coordinates":[-4.995282,51.9285],"type":"Point"}
}
