{
  "type": "Feature",
  "properties": {
    "iso:country": "GB",
    "wof:name": "NN6 7QR",
    "wof:placetype": "postalcode"
  },
  "geometry": {"coordinates":[-1.092451,52.304668],"type":"Point"}
}
