{
  "type": "Feature",
  "properties": {
    "iso:country":"GB",
    "wof:name":"PR4 6SX",
    "wof:placetype":"postalcode"
},
  "geometry": {"coordinates":[-2.83673259784842,53.69660680891663],"type":"Point"}
}