{
  "type": "Feature",
  "properties": {
    "date:inception_lower":"1980-01-01",
    "date:inception_upper":"1980-01-31",
    "iso:country":"GB",
    "wof:name":"PR4 6SX",
    "wof:placetype":"postalcode"
},
  "geometry": {"coordinates":[-2.836733,53.696607],"type":"Point"}
}