{
  "type": "Feature",
  "properties": {
    "iso:country": "GB",
    "wof:name": "DH6 2XF",
    "wof:placetype": "postalcode"
  },
  "geometry": {"coordinates":[-1.384488,54.760962],"type":"Point"}
}
