{
  "type": "Feature",
  "properties": {
    "iso:country":"GB",
    "wof:name":"DH6 2XF",
    "wof:placetype":"postalcode"
},
  "geometry": {"coordinates":[-1.38448823692962,54.7609619000573],"type":"Point"}
}