{
  "type": "Feature",
  "properties": {
    "date:inception_lower": "1980-01-01",
    "date:inception_upper": "1980-01-01",
    "iso:country": "GB",
    "wof:name": "BN22 9PR",
    "wof:placetype": "postalcode"
  },
  "geometry": {"coordinates":[0.272464,50.796791],"type":"Point"}
}
