{
  "type": "Feature",
  "properties": {
    "iso:country":"GB",
    "wof:name":"WA14 3DD",
    "wof:placetype":"postalcode"
},
  "geometry": {"coordinates":[-2.36385948879806,53.36957926215019],"type":"Point"}
}