{
  "type": "Feature",
  "properties": {
    "date:inception_lower": "1980-01-01",
    "date:inception_upper": "1980-01-01",
    "iso:country": "GB",
    "wof:name": "NN1 4AW",
    "wof:placetype": "postalcode"
  },
  "geometry": {"coordinates":[-0.886201,52.241938],"type":"Point"}
}
