{
  "type": "Feature",
  "properties": {
    "iso:country": "GB",
    "wof:name": "WA10 3XX",
    "wof:placetype": "postalcode"
  },
  "geometry": {"coordinates":[-2.745884,53.448468],"type":"Point"}
}
