{
  "type": "Feature",
  "properties": {
    "iso:country":"GB",
    "wof:name":"WA10 3XX",
    "wof:placetype":"postalcode"
},
  "geometry": {"coordinates":[-2.74588443836732,53.44846782553024],"type":"Point"}
}