{
  "type": "Feature",
  "properties": {
    "date:inception_lower": "2000-06-01",
    "date:inception_upper": "2000-06-01",
    "iso:country": "GB",
    "wof:name": "WA10 3XX",
    "wof:placetype": "postalcode"
  },
  "geometry": {"coordinates":[-2.745884,53.448468],"type":"Point"}
}
