{
  "type": "Feature",
  "properties": {
    "iso:country":"GB",
    "wof:name":"NG34 9UL",
    "wof:placetype":"postalcode"
},
  "geometry": {"coordinates":[-0.29353925493792,52.97588081908012],"type":"Point"}
}