{
  "type": "Feature",
  "properties": {
    "iso:country": "GB",
    "wof:name": "NG34 9UL",
    "wof:placetype": "postalcode"
  },
  "geometry": {"coordinates":[-0.293539,52.975881],"type":"Point"}
}
