{
  "type": "Feature",
  "properties": {
    "iso:country":"GB",
    "wof:name":"TW19 5JS",
    "wof:placetype":"postalcode"
},
  "geometry": {"coordinates":[-0.57218932047017,51.45825898547443],"type":"Point"}
}