{
  "type": "Feature",
  "properties": {
    "date:inception_lower": "1980-01-01",
    "date:inception_upper": "1980-01-01",
    "iso:country": "GB",
    "wof:name": "HA3 5PJ",
    "wof:placetype": "postalcode"
  },
  "geometry": {"coordinates":[-0.344763,51.598947],"type":"Point"}
}
