{
  "type": "Feature",
  "properties": {
    "iso:country":"GB",
    "wof:name":"HA3 5PJ",
    "wof:placetype":"postalcode"
},
  "geometry": {"coordinates":[-0.34476271258574,51.59894737633548],"type":"Point"}
}