{
  "type": "Feature",
  "properties": {
    "date:inception_lower": "1980-01-01",
    "date:inception_upper": "1980-01-01",
    "iso:country": "GB",
    "wof:name": "PO6 1ND",
    "wof:placetype": "postalcode"
  },
  "geometry": {"coordinates":[-1.040497,50.84549],"type":"Point"}
}
