{
  "type": "Feature",
  "properties": {
    "iso:country":"GB",
    "wof:name":"PO6 1ND",
    "wof:placetype":"postalcode"
},
  "geometry": {"coordinates":[-1.04051120743596,50.84549997148304],"type":"Point"}
}