{
  "type": "Feature",
  "properties": {
    "date:inception_lower":"1980-01-01",
    "date:inception_upper":"1980-01-31",
    "iso:country":"GB",
    "wof:name":"M30 0RD",
    "wof:placetype":"postalcode"
},
  "geometry": {"coordinates":[-2.356228,53.483362],"type":"Point"}
}