{
  "type": "Feature",
  "properties": {
    "iso:country":"GB",
    "wof:name":"AB24 2YP",
    "wof:placetype":"postalcode"
},
  "geometry": {"coordinates":[-2.11914488908482,57.17514329286626],"type":"Point"}
}