{
  "type": "Feature",
  "properties": {
    "iso:country":"GB",
    "wof:name":"SS1 1NB",
    "wof:placetype":"postalcode"
},
  "geometry": {"coordinates":[0.71033343049971,51.53861503422915],"type":"Point"}
}