{
  "type": "Feature",
  "properties": {
    "date:inception_lower": "1980-01-01",
    "date:inception_upper": "1980-01-01",
    "iso:country": "GB",
    "wof:name": "LL55 2RB",
    "wof:placetype": "postalcode"
  },
  "geometry": {"coordinates":[-4.271402,53.138352],"type":"Point"}
}
