{
  "type": "Feature",
  "properties": {
    "iso:country":"GB",
    "wof:name":"OX4 4EJ",
    "wof:placetype":"postalcode"
},
  "geometry": {"coordinates":[-1.23875728213091,51.72866809943802],"type":"Point"}
}