{
  "type": "Feature",
  "properties": {
    "iso:country": "GB",
    "wof:name": "RH11 7QL",
    "wof:placetype": "postalcode"
  },
  "geometry": {"coordinates":[-0.1931,51.115221],"type":"Point"}
}
