{
  "type": "Feature",
  "properties": {
    "date:inception_lower":"2019-01-01",
    "date:inception_upper":"2019-01-31",
    "iso:country":"GB",
    "wof:name":"DN22 7ZW",
    "wof:placetype":"postalcode"
},
  "geometry": {"coordinates":[-0.931094,53.308228],"type":"Point"}
}