{
  "type": "Feature",
  "properties": {
    "iso:country": "GB",
    "wof:name": "DN22 7ZW",
    "wof:placetype": "postalcode"
  },
  "geometry": {"coordinates":[-0.931094,53.308228],"type":"Point"}
}
