{
  "type": "Feature",
  "properties": {
    "date:inception_lower":"1999-06-01",
    "date:inception_upper":"1999-06-30",
    "iso:country":"GB",
    "wof:name":"CH42 2BL",
    "wof:placetype":"postalcode"
},
  "geometry": {"coordinates":[-3.009618,53.373683],"type":"Point"}
}