{
  "type": "Feature",
  "properties": {
    "date:inception_lower": "1980-01-01",
    "date:inception_upper": "1980-01-01",
    "iso:country": "GB",
    "wof:name": "EH41 3AL",
    "wof:placetype": "postalcode"
  },
  "geometry": {"coordinates":[-2.786068,55.957721],"type":"Point"}
}
