{
  "type": "Feature",
  "properties": {
    "iso:country": "GB",
    "wof:name": "AB53 4FH",
    "wof:placetype": "postalcode"
  },
  "geometry": {"coordinates":[-2.449145,57.538014],"type":"Point"}
}
