{
  "type": "Feature",
  "properties": {
    "iso:country":"GB",
    "wof:name":"SN12 7DW",
    "wof:placetype":"postalcode"
},
  "geometry": {"coordinates":[-2.12882262290231,51.37527177559502],"type":"Point"}
}