{
  "type": "Feature",
  "properties": {
    "date:inception_lower": "1998-12-01",
    "date:inception_upper": "1998-12-01",
    "iso:country": "GB",
    "wof:name": "LS13 4QP",
    "wof:placetype": "postalcode"
  },
  "geometry": {"coordinates":[-1.64191,53.798656],"type":"Point"}
}
