{
  "type": "Feature",
  "properties": {
    "iso:country":"GB",
    "wof:name":"LS13 4QP",
    "wof:placetype":"postalcode"
},
  "geometry": {"coordinates":[-1.64190963198463,53.79865622064062],"type":"Point"}
}