{
  "type": "Feature",
  "properties": {
    "iso:country": "GB",
    "wof:name": "LS13 4QP",
    "wof:placetype": "postalcode"
  },
  "geometry": {"coordinates":[-1.64191,53.798656],"type":"Point"}
}
