{
  "type": "Feature",
  "properties": {
    "date:inception_lower": "1980-01-01",
    "date:inception_upper": "1980-01-01",
    "iso:country": "GB",
    "wof:name": "L40 1SD",
    "wof:placetype": "postalcode"
  },
  "geometry": {"coordinates":[-2.815834,53.639636],"type":"Point"}
}
