{
  "type": "Feature",
  "properties": {
    "date:inception_lower": "2007-03-01",
    "date:inception_upper": "2007-03-01",
    "iso:country": "GB",
    "wof:name": "SO32 2EN",
    "wof:placetype": "postalcode"
  },
  "geometry": {"coordinates":[-1.279093,50.927656],"type":"Point"}
}
