{
  "type": "Feature",
  "properties": {
    "iso:country":"GB",
    "wof:name":"SO32 2EN",
    "wof:placetype":"postalcode"
},
  "geometry": {"coordinates":[-1.27909283349262,50.92765555853546],"type":"Point"}
}