{
  "type": "Feature",
  "properties": {
    "iso:country":"GB",
    "wof:name":"LE3 0QN",
    "wof:placetype":"postalcode"
},
  "geometry": {"coordinates":[-1.1516597947276,52.62935881765966],"type":"Point"}
}