{
  "type": "Feature",
  "properties": {
    "iso:country":"GB",
    "wof:name":"SR4 9HX",
    "wof:placetype":"postalcode"
},
  "geometry": {"coordinates":[-1.43893586461552,54.89500867318549],"type":"Point"}
}