{
  "type": "Feature",
  "properties": {
    "iso:country": "GB",
    "wof:name": "SR4 9HX",
    "wof:placetype": "postalcode"
  },
  "geometry": {"coordinates":[-1.438936,54.895009],"type":"Point"}
}
