{
  "type": "Feature",
  "properties": {
    "date:inception_lower": "2002-07-01",
    "date:inception_upper": "2002-07-01",
    "iso:country": "GB",
    "wof:name": "OX4 2EW",
    "wof:placetype": "postalcode"
  },
  "geometry": {"coordinates":[-1.218022,51.737946],"type":"Point"}
}
