{
  "type": "Feature",
  "properties": {
    "iso:country":"GB",
    "wof:name":"OX4 2EW",
    "wof:placetype":"postalcode"
},
  "geometry": {"coordinates":[-1.21802253046258,51.73794589150686],"type":"Point"}
}