{
  "type": "Feature",
  "properties": {
    "iso:country":"GB",
    "wof:name":"GL1 1GG",
    "wof:placetype":"postalcode"
},
  "geometry": {"coordinates":[-2.24414973288523,51.86256026085871],"type":"Point"}
}