{
  "type": "Feature",
  "properties": {
    "iso:country": "GB",
    "wof:name": "GL1 1GG",
    "wof:placetype": "postalcode"
  },
  "geometry": {"coordinates":[-2.244205,51.862594],"type":"Point"}
}
