{
  "type": "Feature",
  "properties": {
    "date:inception_lower":"2014-08-01",
    "date:inception_upper":"2014-08-31",
    "iso:country":"GB",
    "wof:name":"GL1 1GG",
    "wof:placetype":"postalcode"
},
  "geometry": {"coordinates":[-2.244205,51.862594],"type":"Point"}
}