{
  "type": "Feature",
  "properties": {
    "iso:country":"GB",
    "wof:name":"SW18 3PA",
    "wof:placetype":"postalcode"
},
  "geometry": {"coordinates":[-0.18562223851848,51.44249174649698],"type":"Point"}
}