{
  "type": "Feature",
  "properties": {
    "iso:country":"GB",
    "wof:name":"SY5 8AE",
    "wof:placetype":"postalcode"
},
  "geometry": {"coordinates":[-2.83179800796996,52.63495625247362],"type":"Point"}
}