{
  "type": "Feature",
  "properties": {
    "date:inception_lower":"1980-01-01",
    "date:inception_upper":"1980-01-31",
    "iso:country":"GB",
    "wof:name":"PA5 0JN",
    "wof:placetype":"postalcode"
},
  "geometry": {"coordinates":[-4.525764,55.823001],"type":"Point"}
}