{
  "type": "Feature",
  "properties": {
    "iso:country": "GB",
    "wof:name": "DN22 0LA",
    "wof:placetype": "postalcode"
  },
  "geometry": {"coordinates":[-0.836221,53.283624],"type":"Point"}
}
