{
  "type": "Feature",
  "properties": {
    "iso:country":"GB",
    "wof:name":"DN22 0LA",
    "wof:placetype":"postalcode"
},
  "geometry": {"coordinates":[-0.83622104609996,53.28362399546542],"type":"Point"}
}