{
  "type": "Feature",
  "properties": {
    "date:inception_lower":"2014-06-01",
    "date:inception_upper":"2014-06-30",
    "iso:country":"GB",
    "wof:name":"EH48 2FB",
    "wof:placetype":"postalcode"
},
  "geometry": {"coordinates":[-3.647321,55.879747],"type":"Point"}
}