{
  "type": "Feature",
  "properties": {
    "date:inception_lower": "2016-02-01",
    "date:inception_upper": "2016-02-01",
    "iso:country": "GB",
    "wof:name": "SW15 2FJ",
    "wof:placetype": "postalcode"
  },
  "geometry": {"coordinates":[-0.20823,51.459494],"type":"Point"}
}
