{
  "type": "Feature",
  "properties": {
    "iso:country": "GB",
    "wof:name": "LN11 9UR",
    "wof:placetype": "postalcode"
  },
  "geometry": {"coordinates":[-0.121269,53.295666],"type":"Point"}
}
