{
  "type": "Feature",
  "properties": {
    "iso:country":"GB",
    "wof:name":"LN11 9UR",
    "wof:placetype":"postalcode"
},
  "geometry": {"coordinates":[-0.12126913778138,53.29566642030056],"type":"Point"}
}