{
  "type": "Feature",
  "properties": {
    "iso:country":"GB",
    "wof:name":"DA2 6ES",
    "wof:placetype":"postalcode"
},
  "geometry": {"coordinates":[0.25483282854376,51.43876685631005],"type":"Point"}
}