{
  "type": "Feature",
  "properties": {
    "date:inception_lower": "1980-01-01",
    "date:inception_upper": "1980-01-01",
    "iso:country": "GB",
    "wof:name": "DA2 6ES",
    "wof:placetype": "postalcode"
  },
  "geometry": {"coordinates":[0.254833,51.438767],"type":"Point"}
}
