{
  "type": "Feature",
  "properties": {
    "iso:country": "GB",
    "wof:name": "HD8 0AF",
    "wof:placetype": "postalcode"
  },
  "geometry": {"coordinates":[-1.71799,53.633035],"type":"Point"}
}
