{
  "type": "Feature",
  "properties": {
    "iso:country":"GB",
    "wof:name":"HD8 0AF",
    "wof:placetype":"postalcode"
},
  "geometry": {"coordinates":[-1.71797294548834,53.63298344232263],"type":"Point"}
}