{
  "type": "Feature",
  "properties": {
    "iso:country":"GB",
    "wof:name":"CF39 0PU",
    "wof:placetype":"postalcode"
},
  "geometry": {"coordinates":[-3.41729966082124,51.63483036070893],"type":"Point"}
}