{
  "type": "Feature",
  "properties": {
    "iso:country":"GB",
    "wof:name":"WV10 7EY",
    "wof:placetype":"postalcode"
},
  "geometry": {"coordinates":[-2.12794645078958,52.6397231793671],"type":"Point"}
}