{
  "type": "Feature",
  "properties": {
    "date:inception_lower":"1980-01-01",
    "date:inception_upper":"1980-01-31",
    "iso:country":"GB",
    "wof:name":"WV10 7EY",
    "wof:placetype":"postalcode"
},
  "geometry": {"coordinates":[-2.127946,52.639723],"type":"Point"}
}