{
  "type": "Feature",
  "properties": {
    "iso:country":"GB",
    "wof:name":"NE48 3PY",
    "wof:placetype":"postalcode"
},
  "geometry": {"coordinates":[-2.24577964127959,55.12138188967211],"type":"Point"}
}