{
  "type": "Feature",
  "properties": {
    "iso:country": "GB",
    "wof:name": "TQ13 8RP",
    "wof:placetype": "postalcode"
  },
  "geometry": {"coordinates":[-3.811019,50.636195],"type":"Point"}
}
