{
  "type": "Feature",
  "properties": {
    "date:inception_lower": "1980-01-01",
    "date:inception_upper": "1980-01-01",
    "iso:country": "GB",
    "wof:name": "DG9 0AA",
    "wof:placetype": "postalcode"
  },
  "geometry": {"coordinates":[-5.034954,54.905104],"type":"Point"}
}
