{
  "type": "Feature",
  "properties": {
    "iso:country":"GB",
    "wof:name":"DG9 0AA",
    "wof:placetype":"postalcode"
},
  "geometry": {"coordinates":[-5.03601704656253,54.90583981441893],"type":"Point"}
}