{
  "type": "Feature",
  "properties": {
    "iso:country": "GB",
    "wof:name": "BA3 2QY",
    "wof:placetype": "postalcode"
  },
  "geometry": {"coordinates":[-2.492165,51.286854],"type":"Point"}
}
