{
  "type": "Feature",
  "properties": {
    "date:inception_lower": "1980-01-01",
    "date:inception_upper": "1980-01-01",
    "iso:country": "GB",
    "wof:name": "DT6 3XN",
    "wof:placetype": "postalcode"
  },
  "geometry": {"coordinates":[-2.738249,50.744048],"type":"Point"}
}
