{
  "type": "Feature",
  "properties": {
    "date:inception_lower":"2002-07-01",
    "date:inception_upper":"2002-07-31",
    "iso:country":"GB",
    "wof:name":"TS4 3GD",
    "wof:placetype":"postalcode"
},
  "geometry": {"coordinates":[-1.219527,54.556288],"type":"Point"}
}