{
  "type": "Feature",
  "properties": {
    "iso:country":"GB",
    "wof:name":"SA31 3AN",
    "wof:placetype":"postalcode"
},
  "geometry": {"coordinates":[-4.31031444393086,51.8558463039357],"type":"Point"}
}