{
  "type": "Feature",
  "properties": {
    "date:inception_lower": "2018-08-01",
    "date:inception_upper": "2018-08-01",
    "iso:country": "GB",
    "wof:name": "IP30 9XH",
    "wof:placetype": "postalcode"
  },
  "geometry": {"coordinates":[0.830927,52.215978],"type":"Point"}
}
