{
  "type": "Feature",
  "properties": {
    "iso:country":"GB",
    "wof:name":"RH15 8NY",
    "wof:placetype":"postalcode"
},
  "geometry": {"coordinates":[-0.14258817576636,50.96121728933269],"type":"Point"}
}