{
  "type": "Feature",
  "properties": {
    "date:inception_lower": "1980-01-01",
    "date:inception_upper": "1980-01-01",
    "iso:country": "GB",
    "wof:name": "NG9 5BS",
    "wof:placetype": "postalcode"
  },
  "geometry": {"coordinates":[-1.233667,52.92185],"type":"Point"}
}
