{
  "type": "Feature",
  "properties": {
    "iso:country":"GB",
    "wof:name":"LE4 7YA",
    "wof:placetype":"postalcode"
},
  "geometry": {"coordinates":[-1.1029778178251,52.66329716384556],"type":"Point"}
}