{
  "type": "Feature",
  "properties": {
    "date:inception_lower": "1992-01-01",
    "date:inception_upper": "1992-01-01",
    "iso:country": "GB",
    "wof:name": "NG22 9ZB",
    "wof:placetype": "postalcode"
  },
  "geometry": {"coordinates":[-0.98101,53.20288],"type":"Point"}
}
