{
  "type": "Feature",
  "properties": {
    "date:inception_lower": "2015-04-01",
    "date:inception_upper": "2015-04-01",
    "iso:country": "GB",
    "wof:name": "SK1 2AF",
    "wof:placetype": "postalcode"
  },
  "geometry": {"coordinates":[-2.14492,53.419277],"type":"Point"}
}
