{
  "type": "Feature",
  "properties": {
    "iso:country":"GB",
    "wof:name":"ST16 3SY",
    "wof:placetype":"postalcode"
},
  "geometry": {"coordinates":[-2.09816170479713,52.81384395140005],"type":"Point"}
}