{
  "type": "Feature",
  "properties": {
    "iso:country":"GB",
    "wof:name":"CF24 3RJ",
    "wof:placetype":"postalcode"
},
  "geometry": {"coordinates":[-3.16152643420106,51.48766583481949],"type":"Point"}
}