{
  "type": "Feature",
  "properties": {
    "iso:country":"GB",
    "wof:name":"NE12 8SZ",
    "wof:placetype":"postalcode"
},
  "geometry": {"coordinates":[-1.59041373595854,55.01289356601343],"type":"Point"}
}