{
  "type": "Feature",
  "properties": {
    "iso:country":"GB",
    "wof:name":"PA35 1HT",
    "wof:placetype":"postalcode"
},
  "geometry": {"coordinates":[-5.19009856019895,56.41789591778998],"type":"Point"}
}