{
  "type": "Feature",
  "properties": {
    "iso:country":"GB",
    "wof:name":"PE2 6SS",
    "wof:placetype":"postalcode"
},
  "geometry": {"coordinates":[-0.31242391994195,52.54730032068746],"type":"Point"}
}