{
  "type": "Feature",
  "properties": {
    "date:inception_lower": "1999-06-01",
    "date:inception_upper": "1999-06-01",
    "iso:country": "GB",
    "wof:name": "PE2 6SS",
    "wof:placetype": "postalcode"
  },
  "geometry": {"coordinates":[-0.312424,52.5473],"type":"Point"}
}
