{
  "type": "Feature",
  "properties": {
    "iso:country":"GB",
    "wof:name":"W14 0TJ",
    "wof:placetype":"postalcode"
},
  "geometry": {"coordinates":[-0.20853837449584,51.49228492993138],"type":"Point"}
}