{
  "type": "Feature",
  "properties": {
    "date:inception_lower":"1989-10-01",
    "date:inception_upper":"1989-10-31",
    "iso:country":"GB",
    "wof:name":"KA9 2QF",
    "wof:placetype":"postalcode"
},
  "geometry": {"coordinates":[-4.603921,55.509019],"type":"Point"}
}