{
  "type": "Feature",
  "properties": {
    "iso:country": "GB",
    "wof:name": "KA9 2QF",
    "wof:placetype": "postalcode"
  },
  "geometry": {"coordinates":[-4.603921,55.509019],"type":"Point"}
}
