{
  "type": "Feature",
  "properties": {
    "date:inception_lower": "1980-01-01",
    "date:inception_upper": "1980-01-01",
    "iso:country": "GB",
    "wof:name": "TN12 7BB",
    "wof:placetype": "postalcode"
  },
  "geometry": {"coordinates":[0.400043,51.146813],"type":"Point"}
}
