{
  "type": "Feature",
  "properties": {
    "iso:country": "GB",
    "wof:name": "DL14 6LT",
    "wof:placetype": "postalcode"
  },
  "geometry": {"coordinates":[-1.68639,54.653802],"type":"Point"}
}
