{
  "type": "Feature",
  "properties": {
    "iso:country":"GB",
    "wof:name":"WA14 3LH",
    "wof:placetype":"postalcode"
},
  "geometry": {"coordinates":[-2.37570380337933,53.37485484127358],"type":"Point"}
}