{
  "type": "Feature",
  "properties": {
    "iso:country": "GB",
    "wof:name": "BH24 2DD",
    "wof:placetype": "postalcode"
  },
  "geometry": {"coordinates":[-1.80674,50.844543],"type":"Point"}
}
