{
  "type": "Feature",
  "properties": {
    "date:inception_lower": "1980-01-01",
    "date:inception_upper": "1980-01-01",
    "iso:country": "GB",
    "wof:name": "BH24 2DD",
    "wof:placetype": "postalcode"
  },
  "geometry": {"coordinates":[-1.80674,50.844543],"type":"Point"}
}
