{
  "type": "Feature",
  "properties": {
    "iso:country":"GB",
    "wof:name":"G42 9SY",
    "wof:placetype":"postalcode"
},
  "geometry": {"coordinates":[-4.27100907300757,55.82453804665726],"type":"Point"}
}