{
  "type": "Feature",
  "properties": {
    "iso:country":"GB",
    "wof:name":"OX15 4NL",
    "wof:placetype":"postalcode"
},
  "geometry": {"coordinates":[-1.37011507743353,52.02266918206038],"type":"Point"}
}