{
  "type": "Feature",
  "properties": {
    "date:inception_lower": "1980-01-01",
    "date:inception_upper": "1980-01-01",
    "iso:country": "GB",
    "wof:name": "OX15 4NL",
    "wof:placetype": "postalcode"
  },
  "geometry": {"coordinates":[-1.370115,52.022669],"type":"Point"}
}
