{
  "type": "Feature",
  "properties": {
    "iso:country": "GB",
    "wof:name": "OX15 4NL",
    "wof:placetype": "postalcode"
  },
  "geometry": {"coordinates":[-1.370115,52.022669],"type":"Point"}
}
