{
  "type": "Feature",
  "properties": {
    "iso:country": "GB",
    "wof:name": "PO16 9AX",
    "wof:placetype": "postalcode"
  },
  "geometry": {"coordinates":[-1.133464,50.842315],"type":"Point"}
}
