{
  "type": "Feature",
  "properties": {
    "iso:country":"GB",
    "wof:name":"PO16 9AX",
    "wof:placetype":"postalcode"
},
  "geometry": {"coordinates":[-1.13346443639182,50.84231518746331],"type":"Point"}
}