{
  "type": "Feature",
  "properties": {
    "iso:country": "GB",
    "wof:name": "SN7 7AH",
    "wof:placetype": "postalcode"
  },
  "geometry": {"coordinates":[-1.580463,51.657861],"type":"Point"}
}
