{
  "type": "Feature",
  "properties": {
    "date:inception_lower":"1980-01-01",
    "date:inception_upper":"1980-01-31",
    "iso:country":"GB",
    "wof:name":"SN7 7AH",
    "wof:placetype":"postalcode"
},
  "geometry": {"coordinates":[-1.580463,51.657861],"type":"Point"}
}