{
  "type": "Feature",
  "properties": {
    "iso:country":"GB",
    "wof:name":"BN22 0NJ",
    "wof:placetype":"postalcode"
},
  "geometry": {"coordinates":[0.25418303012074,50.80381886870945],"type":"Point"}
}