{
  "type": "Feature",
  "properties": {
    "iso:country":"GB",
    "wof:name":"EX8 5SU",
    "wof:placetype":"postalcode"
},
  "geometry": {"coordinates":[-3.40002399902998,50.64288511968545],"type":"Point"}
}