{
  "type": "Feature",
  "properties": {
    "iso:country": "GB",
    "wof:name": "SN14 6YW",
    "wof:placetype": "postalcode"
  },
  "geometry": {"coordinates":[-2.136758,51.473226],"type":"Point"}
}
