{
  "type": "Feature",
  "properties": {
    "date:inception_lower":"1997-12-01",
    "date:inception_upper":"1997-12-31",
    "iso:country":"GB",
    "wof:name":"SN14 6YW",
    "wof:placetype":"postalcode"
},
  "geometry": {"coordinates":[-2.136758,51.473226],"type":"Point"}
}