{
  "type": "Feature",
  "properties": {
    "iso:country":"GB",
    "wof:name":"G83 7BA",
    "wof:placetype":"postalcode"
},
  "geometry": {"coordinates":[-4.57779473420145,55.99408124900371],"type":"Point"}
}