{
  "type": "Feature",
  "properties": {
    "iso:country":"GB",
    "wof:name":"DY10 4HS",
    "wof:placetype":"postalcode"
},
  "geometry": {"coordinates":[-2.22932998672796,52.36141222092737],"type":"Point"}
}