{
  "type": "Feature",
  "properties": {
    "date:inception_lower": "1980-01-01",
    "date:inception_upper": "1980-01-01",
    "iso:country": "GB",
    "wof:name": "NG24 2PQ",
    "wof:placetype": "postalcode"
  },
  "geometry": {"coordinates":[-0.779284,53.102241],"type":"Point"}
}
