{
  "type": "Feature",
  "properties": {
    "iso:country": "GB",
    "wof:name": "NG24 2PQ",
    "wof:placetype": "postalcode"
  },
  "geometry": {"coordinates":[-0.779284,53.102241],"type":"Point"}
}
