{
  "type": "Feature",
  "properties": {
    "date:inception_lower": "1980-01-01",
    "date:inception_upper": "1980-01-01",
    "iso:country": "GB",
    "wof:name": "NE17 7AR",
    "wof:placetype": "postalcode"
  },
  "geometry": {"coordinates":[-1.806296,54.932074],"type":"Point"}
}
