{
  "type": "Feature",
  "properties": {
    "date:inception_lower": "2000-10-01",
    "date:inception_upper": "2000-10-01",
    "iso:country": "GB",
    "wof:name": "OX25 2LY",
    "wof:placetype": "postalcode"
  },
  "geometry": {"coordinates":[-1.126217,51.86948],"type":"Point"}
}
