{
  "type": "Feature",
  "properties": {
    "iso:country":"GB",
    "wof:name":"EH4 4HZ",
    "wof:placetype":"postalcode"
},
  "geometry": {"coordinates":[-3.2434443174683,55.97376213197784],"type":"Point"}
}