{
  "type": "Feature",
  "properties": {
    "iso:country": "GB",
    "wof:name": "EH4 4HZ",
    "wof:placetype": "postalcode"
  },
  "geometry": {"coordinates":[-3.243444,55.973762],"type":"Point"}
}
