{
  "type": "Feature",
  "properties": {
    "iso:country": "GB",
    "wof:name": "MK45 1NH",
    "wof:placetype": "postalcode"
  },
  "geometry": {"coordinates":[-0.499235,51.999285],"type":"Point"}
}
