{
  "type": "Feature",
  "properties": {
    "iso:country": "GB",
    "wof:name": "KT19 9EX",
    "wof:placetype": "postalcode"
  },
  "geometry": {"coordinates":[-0.279175,51.361126],"type":"Point"}
}
