{
  "type": "Feature",
  "properties": {
    "date:inception_lower": "2008-10-01",
    "date:inception_upper": "2008-10-01",
    "iso:country": "GB",
    "wof:name": "SE28 8GS",
    "wof:placetype": "postalcode"
  },
  "geometry": {"coordinates":[0.120545,51.502569],"type":"Point"}
}
