{
  "type": "Feature",
  "properties": {
    "iso:country":"GB",
    "wof:name":"GL7 3LG",
    "wof:placetype":"postalcode"
},
  "geometry": {"coordinates":[-1.64137712963301,51.72067724322154],"type":"Point"}
}