{
  "type": "Feature",
  "properties": {
    "iso:country":"GB",
    "wof:name":"TR13 8GR",
    "wof:placetype":"postalcode"
},
  "geometry": {"coordinates":[-5.26354786615143,50.11292874421352],"type":"Point"}
}