{
  "type": "Feature",
  "properties": {
    "date:inception_lower": "2005-03-01",
    "date:inception_upper": "2005-03-01",
    "iso:country": "GB",
    "wof:name": "IP27 9QG",
    "wof:placetype": "postalcode"
  },
  "geometry": {"coordinates":[0.527793,52.41113],"type":"Point"}
}
