{
  "type": "Feature",
  "properties": {
    "iso:country":"GB",
    "wof:name":"BD2 1JG",
    "wof:placetype":"postalcode"
},
  "geometry": {"coordinates":[-1.73687815232516,53.81977201979875],"type":"Point"}
}