{
  "type": "Feature",
  "properties": {
    "iso:country":"GB",
    "wof:name":"IV17 0UA",
    "wof:placetype":"postalcode"
},
  "geometry": {"coordinates":[-4.24708706689877,57.69556262941767],"type":"Point"}
}