{
  "type": "Feature",
  "properties": {
    "iso:country":"GB",
    "wof:name":"HA4 7EE",
    "wof:placetype":"postalcode"
},
  "geometry": {"coordinates":[-0.42416008614293,51.57228148515318],"type":"Point"}
}