{
  "type": "Feature",
  "properties": {
    "iso:country":"GB",
    "wof:name":"PL6 8TR",
    "wof:placetype":"postalcode"
},
  "geometry": {"coordinates":[-4.10452013878417,50.40781992854572],"type":"Point"}
}