{
  "type": "Feature",
  "properties": {
    "iso:country":"GB",
    "wof:name":"BR5 4ED",
    "wof:placetype":"postalcode"
},
  "geometry": {"coordinates":[0.11683896197237,51.38145639561878],"type":"Point"}
}