{
  "type": "Feature",
  "properties": {
    "iso:country":"GB",
    "wof:name":"KA8 0QD",
    "wof:placetype":"postalcode"
},
  "geometry": {"coordinates":[-4.6020379030024,55.46848367224666],"type":"Point"}
}