{
  "type": "Feature",
  "properties": {
    "iso:country":"GB",
    "wof:name":"CO2 8YS",
    "wof:placetype":"postalcode"
},
  "geometry": {"coordinates":[0.92739948663801,51.88143197493784],"type":"Point"}
}