{
  "type": "Feature",
  "properties": {
    "iso:country": "GB",
    "wof:name": "TQ1 2PS",
    "wof:placetype": "postalcode"
  },
  "geometry": {"coordinates":[-3.514319,50.463671],"type":"Point"}
}
