{
  "type": "Feature",
  "properties": {
    "iso:country":"GB",
    "wof:name":"CO4 5UT",
    "wof:placetype":"postalcode"
},
  "geometry": {"coordinates":[0.87513003074583,51.90787658274919],"type":"Point"}
}