{
  "type": "Feature",
  "properties": {
    "iso:country": "GB",
    "wof:name": "BD23 2RH",
    "wof:placetype": "postalcode"
  },
  "geometry": {"coordinates":[-2.019453,53.952413],"type":"Point"}
}
