{
  "type": "Feature",
  "properties": {
    "date:inception_lower":"1980-01-01",
    "date:inception_upper":"1980-01-31",
    "iso:country":"GB",
    "wof:name":"BD23 2RH",
    "wof:placetype":"postalcode"
},
  "geometry": {"coordinates":[-2.019453,53.952413],"type":"Point"}
}