{
  "type": "Feature",
  "properties": {
    "iso:country":"GB",
    "wof:name":"NN4 8QQ",
    "wof:placetype":"postalcode"
},
  "geometry": {"coordinates":[-0.89926554426909,52.22119283421141],"type":"Point"}
}