{
  "type": "Feature",
  "properties": {
    "iso:country": "GB",
    "wof:name": "NN4 8QQ",
    "wof:placetype": "postalcode"
  },
  "geometry": {"coordinates":[-0.899266,52.221193],"type":"Point"}
}
