{
  "type": "Feature",
  "properties": {
    "iso:country":"GB",
    "wof:name":"PO36 9AG",
    "wof:placetype":"postalcode"
},
  "geometry": {"coordinates":[-1.1554806285255,50.66019216042913],"type":"Point"}
}