{
  "type": "Feature",
  "properties": {
    "iso:country": "GB",
    "wof:name": "GL16 8FB",
    "wof:placetype": "postalcode"
  },
  "geometry": {"coordinates":[-2.615686,51.795159],"type":"Point"}
}
