{
  "type": "Feature",
  "properties": {
    "iso:country":"GB",
    "wof:name":"M11 2DZ",
    "wof:placetype":"postalcode"
},
  "geometry": {"coordinates":[-2.20084510768855,53.47292892066469],"type":"Point"}
}