{
  "type": "Feature",
  "properties": {
    "date:inception_lower": "1998-12-01",
    "date:inception_upper": "1998-12-01",
    "iso:country": "GB",
    "wof:name": "LS7 4RL",
    "wof:placetype": "postalcode"
  },
  "geometry": {"coordinates":[-1.534675,53.826823],"type":"Point"}
}
