{
  "type": "Feature",
  "properties": {
    "iso:country":"GB",
    "wof:name":"LS7 4RL",
    "wof:placetype":"postalcode"
},
  "geometry": {"coordinates":[-1.5347310897636,53.82680755231301],"type":"Point"}
}