{
  "type": "Feature",
  "properties": {
    "iso:country": "GB",
    "wof:name": "G60 5HP",
    "wof:placetype": "postalcode"
  },
  "geometry": {"coordinates":[-4.446025,55.919499],"type":"Point"}
}
