{
  "type": "Feature",
  "properties": {
    "iso:country": "GB",
    "wof:name": "BB7 9QA",
    "wof:placetype": "postalcode"
  },
  "geometry": {"coordinates":[-2.480552,53.839936],"type":"Point"}
}
