{
  "type": "Feature",
  "properties": {
    "iso:country":"GB",
    "wof:name":"WD4 8PL",
    "wof:placetype":"postalcode"
},
  "geometry": {"coordinates":[-0.43355518979976,51.69766614922591],"type":"Point"}
}