{
  "type": "Feature",
  "properties": {
    "iso:country":"GB",
    "wof:name":"SP2 0FS",
    "wof:placetype":"postalcode"
},
  "geometry": {"coordinates":[-1.85410414833312,51.08271027594192],"type":"Point"}
}