{
  "type": "Feature",
  "properties": {
    "date:inception_lower": "2015-10-01",
    "date:inception_upper": "2015-10-01",
    "iso:country": "GB",
    "wof:name": "SP2 0FS",
    "wof:placetype": "postalcode"
  },
  "geometry": {"coordinates":[-1.854439,51.0823],"type":"Point"}
}
