{
  "type": "Feature",
  "properties": {
    "iso:country":"GB",
    "wof:name":"SE15 5EY",
    "wof:placetype":"postalcode"
},
  "geometry": {"coordinates":[-0.06933664027294,51.47187466894795],"type":"Point"}
}