{
  "type": "Feature",
  "properties": {
    "iso:country":"GB",
    "wof:name":"CR4 3RZ",
    "wof:placetype":"postalcode"
},
  "geometry": {"coordinates":[-0.17301129521359,51.41378037941953],"type":"Point"}
}