{
  "type": "Feature",
  "properties": {
    "date:inception_lower":"1992-01-01",
    "date:inception_upper":"1992-01-31",
    "iso:country":"GB",
    "wof:name":"CR4 3RZ",
    "wof:placetype":"postalcode"
},
  "geometry": {"coordinates":[-0.173011,51.41378],"type":"Point"}
}