{
  "type": "Feature",
  "properties": {
    "iso:country": "GB",
    "wof:name": "CR4 3RZ",
    "wof:placetype": "postalcode"
  },
  "geometry": {"coordinates":[-0.173011,51.41378],"type":"Point"}
}
