{
  "type": "Feature",
  "properties": {
    "iso:country": "GB",
    "wof:name": "EX17 4ET",
    "wof:placetype": "postalcode"
  },
  "geometry": {"coordinates":[-3.669739,50.817779],"type":"Point"}
}
