{
  "type": "Feature",
  "properties": {
    "iso:country":"GB",
    "wof:name":"TD8 6HN",
    "wof:placetype":"postalcode"
},
  "geometry": {"coordinates":[-2.54658460152311,55.48246122036608],"type":"Point"}
}