{
  "type": "Feature",
  "properties": {
    "date:inception_lower":"2012-02-01",
    "date:inception_upper":"2012-02-29",
    "iso:country":"GB",
    "wof:name":"TR14 8FN",
    "wof:placetype":"postalcode"
},
  "geometry": {"coordinates":[-5.289041,50.214504],"type":"Point"}
}