{
  "type": "Feature",
  "properties": {
    "iso:country": "GB",
    "wof:name": "TR14 8FN",
    "wof:placetype": "postalcode"
  },
  "geometry": {"coordinates":[-5.289041,50.214504],"type":"Point"}
}
