{
  "type": "Feature",
  "properties": {
    "iso:country":"GB",
    "wof:name":"BH31 6TN",
    "wof:placetype":"postalcode"
},
  "geometry": {"coordinates":[-1.86447385515174,50.87009131070818],"type":"Point"}
}