{
  "type": "Feature",
  "properties": {
    "iso:country":"GB",
    "wof:name":"NR13 5FH",
    "wof:placetype":"postalcode"
},
  "geometry": {"coordinates":[1.4063840224607,52.65003273325754],"type":"Point"}
}