{
  "type": "Feature",
  "properties": {
    "date:inception_lower":"2009-02-01",
    "date:inception_upper":"2009-02-28",
    "iso:country":"GB",
    "wof:name":"NR13 5FH",
    "wof:placetype":"postalcode"
},
  "geometry": {"coordinates":[1.406384,52.650033],"type":"Point"}
}