{
  "type": "Feature",
  "properties": {
    "iso:country":"GB",
    "wof:name":"SW4 9QR",
    "wof:placetype":"postalcode"
},
  "geometry": {"coordinates":[-0.13964323574794,51.45887497320671],"type":"Point"}
}