{
  "type": "Feature",
  "properties": {
    "iso:country": "GB",
    "wof:name": "TR11 4FQ",
    "wof:placetype": "postalcode"
  },
  "geometry": {"coordinates":[-5.100827,50.160094],"type":"Point"}
}
