{
  "type": "Feature",
  "properties": {
    "date:inception_lower": "1980-01-01",
    "date:inception_upper": "1980-01-01",
    "iso:country": "GB",
    "wof:name": "LA19 5UD",
    "wof:placetype": "postalcode"
  },
  "geometry": {"coordinates":[-3.378485,54.282175],"type":"Point"}
}
