{
  "type": "Feature",
  "properties": {
    "iso:country": "GB",
    "wof:name": "LA19 5UD",
    "wof:placetype": "postalcode"
  },
  "geometry": {"coordinates":[-3.378485,54.282175],"type":"Point"}
}
