{
  "type": "Feature",
  "properties": {
    "date:inception_lower": "2000-06-01",
    "date:inception_upper": "2000-06-01",
    "iso:country": "GB",
    "wof:name": "CA8 7NH",
    "wof:placetype": "postalcode"
  },
  "geometry": {"coordinates":[-2.504726,54.865859],"type":"Point"}
}
