{
  "type": "Feature",
  "properties": {
    "iso:country":"GB",
    "wof:name":"CA8 7NH",
    "wof:placetype":"postalcode"
},
  "geometry": {"coordinates":[-2.50472569284872,54.86585877962029],"type":"Point"}
}