{
  "type": "Feature",
  "properties": {
    "date:inception_lower": "2013-07-01",
    "date:inception_upper": "2013-07-01",
    "iso:country": "GB",
    "wof:name": "BA14 6GJ",
    "wof:placetype": "postalcode"
  },
  "geometry": {"coordinates":[-2.182659,51.31848],"type":"Point"}
}
