{
  "type": "Feature",
  "properties": {
    "iso:country":"GB",
    "wof:name":"BA14 6GJ",
    "wof:placetype":"postalcode"
},
  "geometry": {"coordinates":[-2.18265934354295,51.31848039298131],"type":"Point"}
}