{
  "type": "Feature",
  "properties": {
    "iso:country":"GB",
    "wof:name":"N2 9LH",
    "wof:placetype":"postalcode"
},
  "geometry": {"coordinates":[-0.15711576954733,51.58784221883012],"type":"Point"}
}