{
  "type": "Feature",
  "properties": {
    "date:inception_lower": "1983-01-01",
    "date:inception_upper": "1983-01-01",
    "iso:country": "GB",
    "wof:name": "TS12 2YW",
    "wof:placetype": "postalcode"
  },
  "geometry": {"coordinates":[-0.96957,54.56008],"type":"Point"}
}
