{
  "type": "Feature",
  "properties": {
    "iso:country":"GB",
    "wof:name":"TS12 2YW",
    "wof:placetype":"postalcode"
},
  "geometry": {"coordinates":[-0.96956991314936,54.56008007783883],"type":"Point"}
}