{
  "type": "Feature",
  "properties": {
    "iso:country": "GB",
    "wof:name": "GU24 8HL",
    "wof:placetype": "postalcode"
  },
  "geometry": {"coordinates":[-0.579943,51.365886],"type":"Point"}
}
