{
  "type": "Feature",
  "properties": {
    "iso:country":"GB",
    "wof:name":"BR1 5RQ",
    "wof:placetype":"postalcode"
},
  "geometry": {"coordinates":[-0.003108233793,51.4301360969168],"type":"Point"}
}