{
  "type": "Feature",
  "properties": {
    "iso:country": "GB",
    "wof:name": "BR1 5RQ",
    "wof:placetype": "postalcode"
  },
  "geometry": {"coordinates":[-0.003108,51.430136],"type":"Point"}
}
