{
  "type": "Feature",
  "properties": {
    "iso:country":"GB",
    "wof:name":"MK40 4NN",
    "wof:placetype":"postalcode"
},
  "geometry": {"coordinates":[-0.48625747464326,52.13169681596771],"type":"Point"}
}