{
  "type": "Feature",
  "properties": {
    "date:inception_lower": "2022-10-01",
    "date:inception_upper": "2022-10-01",
    "iso:country": "GB",
    "wof:name": "DD4 0FL",
    "wof:placetype": "postalcode"
  },
  "geometry": {"coordinates":[-2.916712,56.49042],"type":"Point"}
}
