{
  "type": "Feature",
  "properties": {
    "iso:country":"GB",
    "wof:name":"DG2 7TN",
    "wof:placetype":"postalcode"
},
  "geometry": {"coordinates":[-3.61939731923548,55.06856213253498],"type":"Point"}
}