{
  "type": "Feature",
  "properties": {
    "iso:country":"GB",
    "wof:name":"SO31 6RN",
    "wof:placetype":"postalcode"
},
  "geometry": {"coordinates":[-1.26161062728129,50.85806988282498],"type":"Point"}
}