{
  "type": "Feature",
  "properties": {
    "date:inception_lower": "1980-01-01",
    "date:inception_upper": "1980-01-01",
    "iso:country": "GB",
    "wof:name": "TF1 3HJ",
    "wof:placetype": "postalcode"
  },
  "geometry": {"coordinates":[-2.525612,52.705959],"type":"Point"}
}
