{
  "type": "Feature",
  "properties": {
    "iso:country":"GB",
    "wof:name":"TF1 3HJ",
    "wof:placetype":"postalcode"
},
  "geometry": {"coordinates":[-2.52561216736805,52.70595896071497],"type":"Point"}
}