{
  "type": "Feature",
  "properties": {
    "iso:country":"GB",
    "wof:name":"NG8 5HR",
    "wof:placetype":"postalcode"
},
  "geometry": {"coordinates":[-1.19420473733008,52.97643350015114],"type":"Point"}
}