{
  "type": "Feature",
  "properties": {
    "date:inception_lower": "1980-01-01",
    "date:inception_upper": "1980-01-01",
    "iso:country": "GB",
    "wof:name": "NG8 5HR",
    "wof:placetype": "postalcode"
  },
  "geometry": {"coordinates":[-1.194205,52.976433],"type":"Point"}
}
