{
  "type": "Feature",
  "properties": {
    "iso:country":"GB",
    "wof:name":"B33 9TB",
    "wof:placetype":"postalcode"
},
  "geometry": {"coordinates":[-1.77490479688814,52.48448634767729],"type":"Point"}
}