{
  "type": "Feature",
  "properties": {
    "iso:country":"GB",
    "wof:name":"HA8 5SA",
    "wof:placetype":"postalcode"
},
  "geometry": {"coordinates":[-0.27873820919776,51.599976051194],"type":"Point"}
}