{
  "type": "Feature",
  "properties": {
    "date:inception_lower":"1980-01-01",
    "date:inception_upper":"1980-01-31",
    "iso:country":"GB",
    "wof:name":"SK11 8HF",
    "wof:placetype":"postalcode"
},
  "geometry": {"coordinates":[-2.137358,53.253589],"type":"Point"}
}