{
  "type": "Feature",
  "properties": {
    "iso:country": "GB",
    "wof:name": "SK11 8HF",
    "wof:placetype": "postalcode"
  },
  "geometry": {"coordinates":[-2.137358,53.253589],"type":"Point"}
}
