{
  "type": "Feature",
  "properties": {
    "iso:country": "GB",
    "wof:name": "CV35 8DD",
    "wof:placetype": "postalcode"
  },
  "geometry": {"coordinates":[-1.573475,52.240028],"type":"Point"}
}
