{
  "type": "Feature",
  "properties": {
    "iso:country":"GB",
    "wof:name":"CV35 8DD",
    "wof:placetype":"postalcode"
},
  "geometry": {"coordinates":[-1.57347541186072,52.24002796886758],"type":"Point"}
}