{
  "type": "Feature",
  "properties": {
    "iso:country":"GB",
    "wof:name":"BH16 5JT",
    "wof:placetype":"postalcode"
},
  "geometry": {"coordinates":[-2.03315112895148,50.73844215834676],"type":"Point"}
}