{
  "type": "Feature",
  "properties": {
    "date:inception_lower":"1980-01-01",
    "date:inception_upper":"1980-01-31",
    "iso:country":"GB",
    "wof:name":"PL24 2PX",
    "wof:placetype":"postalcode"
},
  "geometry": {"coordinates":[-4.693211,50.359441],"type":"Point"}
}