{
  "type": "Feature",
  "properties": {
    "iso:country":"GB",
    "wof:name":"PL24 2PX",
    "wof:placetype":"postalcode"
},
  "geometry": {"coordinates":[-4.69321060026615,50.35944100205165],"type":"Point"}
}