{
  "type": "Feature",
  "properties": {
    "iso:country":"GB",
    "wof:name":"RM3 9AD",
    "wof:placetype":"postalcode"
},
  "geometry": {"coordinates":[0.22081141503223,51.61285440096427],"type":"Point"}
}