{
  "type": "Feature",
  "properties": {
    "iso:country":"GB",
    "wof:name":"BS13 8HU",
    "wof:placetype":"postalcode"
},
  "geometry": {"coordinates":[-2.63054029353587,51.41123049381707],"type":"Point"}
}