{
  "type": "Feature",
  "properties": {
    "iso:country": "GB",
    "wof:name": "BL5 3ZE",
    "wof:placetype": "postalcode"
  },
  "geometry": {"coordinates":[-2.509504,53.556673],"type":"Point"}
}
