{
  "type": "Feature",
  "properties": {
    "iso:country":"GB",
    "wof:name":"BL5 3ZE",
    "wof:placetype":"postalcode"
},
  "geometry": {"coordinates":[-2.50950407349027,53.5566734617264],"type":"Point"}
}