{
  "type": "Feature",
  "properties": {
    "date:inception_lower":"2006-03-01",
    "date:inception_upper":"2006-03-31",
    "iso:country":"GB",
    "wof:name":"BL5 3ZE",
    "wof:placetype":"postalcode"
},
  "geometry": {"coordinates":[-2.509504,53.556673],"type":"Point"}
}