{
  "type": "Feature",
  "properties": {
    "iso:country":"GB",
    "wof:name":"OX4 3PP",
    "wof:placetype":"postalcode"
},
  "geometry": {"coordinates":[-1.21306935505664,51.73379482756891],"type":"Point"}
}