{
  "type": "Feature",
  "properties": {
    "iso:country":"GB",
    "wof:name":"BS8 4TN",
    "wof:placetype":"postalcode"
},
  "geometry": {"coordinates":[-2.61136563715547,51.45155191804338],"type":"Point"}
}