{
  "type": "Feature",
  "properties": {
    "iso:country": "GB",
    "wof:name": "BS8 4TN",
    "wof:placetype": "postalcode"
  },
  "geometry": {"coordinates":[-2.611366,51.451552],"type":"Point"}
}
