{
  "type": "Feature",
  "properties": {
    "iso:country":"GB",
    "wof:name":"CV33 9TP",
    "wof:placetype":"postalcode"
},
  "geometry": {"coordinates":[-1.48658543932849,52.19965678093639],"type":"Point"}
}