{
  "type": "Feature",
  "properties": {
    "iso:country": "GB",
    "wof:name": "CV33 9TP",
    "wof:placetype": "postalcode"
  },
  "geometry": {"coordinates":[-1.486585,52.199657],"type":"Point"}
}
