{
  "type": "Feature",
  "properties": {
    "iso:country": "GB",
    "wof:name": "WV5 9HY",
    "wof:placetype": "postalcode"
  },
  "geometry": {"coordinates":[-2.186487,52.533413],"type":"Point"}
}
