{
  "type": "Feature",
  "properties": {
    "date:inception_lower": "1981-06-01",
    "date:inception_upper": "1981-06-01",
    "iso:country": "GB",
    "wof:name": "WV5 9HY",
    "wof:placetype": "postalcode"
  },
  "geometry": {"coordinates":[-2.186487,52.533413],"type":"Point"}
}
