{
  "type": "Feature",
  "properties": {
    "date:inception_lower":"1980-01-01",
    "date:inception_upper":"1980-01-31",
    "iso:country":"GB",
    "wof:name":"RG22 4BB",
    "wof:placetype":"postalcode"
},
  "geometry": {"coordinates":[-1.101858,51.249845],"type":"Point"}
}