{
  "type": "Feature",
  "properties": {
    "iso:country":"GB",
    "wof:name":"RG22 4BB",
    "wof:placetype":"postalcode"
},
  "geometry": {"coordinates":[-1.10185809841591,51.24984546570736],"type":"Point"}
}