{
  "type": "Feature",
  "properties": {
    "iso:country": "GB",
    "wof:name": "RG22 4BB",
    "wof:placetype": "postalcode"
  },
  "geometry": {"coordinates":[-1.101858,51.249845],"type":"Point"}
}
