{
  "type": "Feature",
  "properties": {
    "iso:country": "GB",
    "wof:name": "LS25 2EN",
    "wof:placetype": "postalcode"
  },
  "geometry": {"coordinates":[-1.373206,53.794183],"type":"Point"}
}
