{
  "type": "Feature",
  "properties": {
    "iso:country": "GB",
    "wof:name": "OL4 4PS",
    "wof:placetype": "postalcode"
  },
  "geometry": {"coordinates":[-2.066101,53.542075],"type":"Point"}
}
