{
  "type": "Feature",
  "properties": {
    "date:inception_lower": "1985-04-01",
    "date:inception_upper": "1985-04-01",
    "iso:country": "GB",
    "wof:name": "OL4 4PS",
    "wof:placetype": "postalcode"
  },
  "geometry": {"coordinates":[-2.066101,53.542075],"type":"Point"}
}
