{
  "type": "Feature",
  "properties": {
    "iso:country":"GB",
    "wof:name":"BS15 8BG",
    "wof:placetype":"postalcode"
},
  "geometry": {"coordinates":[-2.51356935003442,51.45971810228952],"type":"Point"}
}