{
  "type": "Feature",
  "properties": {
    "iso:country":"GB",
    "wof:name":"EX39 2AU",
    "wof:placetype":"postalcode"
},
  "geometry": {"coordinates":[-4.20681444803749,51.01604959379086],"type":"Point"}
}