{
  "type": "Feature",
  "properties": {
    "iso:country": "GB",
    "wof:name": "EX39 2AU",
    "wof:placetype": "postalcode"
  },
  "geometry": {"coordinates":[-4.206799,51.0161],"type":"Point"}
}
