{
  "type": "Feature",
  "properties": {
    "iso:country":"GB",
    "wof:name":"G46 8LJ",
    "wof:placetype":"postalcode"
},
  "geometry": {"coordinates":[-4.31459934643176,55.8098122582407],"type":"Point"}
}