{
  "type": "Feature",
  "properties": {
    "date:inception_lower":"1980-01-01",
    "date:inception_upper":"1980-01-31",
    "iso:country":"GB",
    "wof:name":"BD5 9LN",
    "wof:placetype":"postalcode"
},
  "geometry": {"coordinates":[-1.772333,53.780127],"type":"Point"}
}