{
  "type": "Feature",
  "properties": {
    "date:inception_lower": "2004-11-01",
    "date:inception_upper": "2004-11-01",
    "iso:country": "GB",
    "wof:name": "WR10 3DL",
    "wof:placetype": "postalcode"
  },
  "geometry": {"coordinates":[-2.08622,52.067377],"type":"Point"}
}
