{
  "type": "Feature",
  "properties": {
    "iso:country": "GB",
    "wof:name": "DN22 9HJ",
    "wof:placetype": "postalcode"
  },
  "geometry": {"coordinates":[-0.821084,53.345807],"type":"Point"}
}
