{
  "type": "Feature",
  "properties": {
    "iso:country":"GB",
    "wof:name":"PE19 7SL",
    "wof:placetype":"postalcode"
},
  "geometry": {"coordinates":[-0.28006261045031,52.22528472983578],"type":"Point"}
}