{
  "type": "Feature",
  "properties": {
    "date:inception_lower": "2000-06-01",
    "date:inception_upper": "2000-06-01",
    "iso:country": "GB",
    "wof:name": "PE19 7SL",
    "wof:placetype": "postalcode"
  },
  "geometry": {"coordinates":[-0.280063,52.225285],"type":"Point"}
}
