{
  "type": "Feature",
  "properties": {
    "iso:country":"GB",
    "wof:name":"GL13 9HD",
    "wof:placetype":"postalcode"
},
  "geometry": {"coordinates":[-2.40862169668927,51.69887049052349],"type":"Point"}
}