{
  "type": "Feature",
  "properties": {
    "iso:country": "GB",
    "wof:name": "SA6 5LY",
    "wof:placetype": "postalcode"
  },
  "geometry": {"coordinates":[-3.892962,51.698047],"type":"Point"}
}
