{
  "type": "Feature",
  "properties": {
    "iso:country":"GB",
    "wof:name":"SA6 5LY",
    "wof:placetype":"postalcode"
},
  "geometry": {"coordinates":[-3.89296154445862,51.69804741282902],"type":"Point"}
}