{
  "type": "Feature",
  "properties": {
    "iso:country": "GB",
    "wof:name": "NR5 9NF",
    "wof:placetype": "postalcode"
  },
  "geometry": {"coordinates":[1.208465,52.64093],"type":"Point"}
}
