{
  "type": "Feature",
  "properties": {
    "date:inception_lower":"1980-01-01",
    "date:inception_upper":"1980-01-31",
    "iso:country":"GB",
    "wof:name":"LL68 0UE",
    "wof:placetype":"postalcode"
},
  "geometry": {"coordinates":[-4.492267,53.394469],"type":"Point"}
}