{
  "type": "Feature",
  "properties": {
    "iso:country":"GB",
    "wof:name":"LL68 0UE",
    "wof:placetype":"postalcode"
},
  "geometry": {"coordinates":[-4.49226703868477,53.39446924711574],"type":"Point"}
}