{
  "type": "Feature",
  "properties": {
    "iso:country":"GB",
    "wof:name":"SG18 8UN",
    "wof:placetype":"postalcode"
},
  "geometry": {"coordinates":[-0.24575448348287,52.08109564091843],"type":"Point"}
}