{
  "type": "Feature",
  "properties": {
    "iso:country":"GB",
    "wof:name":"SK2 6QX",
    "wof:placetype":"postalcode"
},
  "geometry": {"coordinates":[-2.15755654501588,53.3983802831084],"type":"Point"}
}