{
  "type": "Feature",
  "properties": {
    "iso:country": "GB",
    "wof:name": "TW20 9LU",
    "wof:placetype": "postalcode"
  },
  "geometry": {"coordinates":[-0.546575,51.42765],"type":"Point"}
}
