{
  "type": "Feature",
  "properties": {
    "iso:country":"GB",
    "wof:name":"TW20 9LU",
    "wof:placetype":"postalcode"
},
  "geometry": {"coordinates":[-0.54657552819035,51.42764959264097],"type":"Point"}
}