{
  "type": "Feature",
  "properties": {
    "iso:country":"GB",
    "wof:name":"CR4 2HY",
    "wof:placetype":"postalcode"
},
  "geometry": {"coordinates":[-0.1526687177023,51.41113239479248],"type":"Point"}
}