{
  "type": "Feature",
  "properties": {
    "iso:country":"GB",
    "wof:name":"LS24 9NY",
    "wof:placetype":"postalcode"
},
  "geometry": {"coordinates":[-1.27431056446612,53.88697601629492],"type":"Point"}
}