{
  "type": "Feature",
  "properties": {
    "iso:country": "GB",
    "wof:name": "LS24 9NY",
    "wof:placetype": "postalcode"
  },
  "geometry": {"coordinates":[-1.274311,53.886976],"type":"Point"}
}
