{
  "type": "Feature",
  "properties": {
    "date:inception_lower":"1981-06-01",
    "date:inception_upper":"1981-06-30",
    "iso:country":"GB",
    "wof:name":"LS24 9NY",
    "wof:placetype":"postalcode"
},
  "geometry": {"coordinates":[-1.274311,53.886976],"type":"Point"}
}