{
  "type": "Feature",
  "properties": {
    "iso:country":"GB",
    "wof:name":"S11 9RS",
    "wof:placetype":"postalcode"
},
  "geometry": {"coordinates":[-1.52599504749562,53.34731604729602],"type":"Point"}
}