{
  "type": "Feature",
  "properties": {
    "iso:country":"GB",
    "wof:name":"HP3 8QD",
    "wof:placetype":"postalcode"
},
  "geometry": {"coordinates":[-0.43427108298701,51.74901942352524],"type":"Point"}
}