{
  "type": "Feature",
  "properties": {
    "date:inception_lower": "1980-01-01",
    "date:inception_upper": "1980-01-01",
    "iso:country": "GB",
    "wof:name": "HP3 8QD",
    "wof:placetype": "postalcode"
  },
  "geometry": {"coordinates":[-0.434271,51.749019],"type":"Point"}
}
