{
  "type": "Feature",
  "properties": {
    "iso:country": "GB",
    "wof:name": "PL18 9EU",
    "wof:placetype": "postalcode"
  },
  "geometry": {"coordinates":[-4.224795,50.517605],"type":"Point"}
}
