{
  "type": "Feature",
  "properties": {
    "iso:country": "GB",
    "wof:name": "EH5 3QJ",
    "wof:placetype": "postalcode"
  },
  "geometry": {"coordinates":[-3.214115,55.971548],"type":"Point"}
}
