{
  "type": "Feature",
  "properties": {
    "iso:country":"GB",
    "wof:name":"DA16 1RS",
    "wof:placetype":"postalcode"
},
  "geometry": {"coordinates":[0.12292417762458,51.46011555670093],"type":"Point"}
}