{
  "type": "Feature",
  "properties": {
    "iso:country":"GB",
    "wof:name":"KT22 9JZ",
    "wof:placetype":"postalcode"
},
  "geometry": {"coordinates":[-0.34983311336061,51.29428517031707],"type":"Point"}
}