{
  "type": "Feature",
  "properties": {
    "date:inception_lower":"1993-01-01",
    "date:inception_upper":"1993-01-31",
    "iso:country":"GB",
    "wof:name":"LN11 0SR",
    "wof:placetype":"postalcode"
},
  "geometry": {"coordinates":[0.007268,53.376903],"type":"Point"}
}