{
  "type": "Feature",
  "properties": {
    "iso:country": "GB",
    "wof:name": "LN11 0SR",
    "wof:placetype": "postalcode"
  },
  "geometry": {"coordinates":[0.007268,53.376903],"type":"Point"}
}
