{
  "type": "Feature",
  "properties": {
    "iso:country":"GB",
    "wof:name":"SL4 1SS",
    "wof:placetype":"postalcode"
},
  "geometry": {"coordinates":[-0.61471448954019,51.48232837265172],"type":"Point"}
}