{
  "type": "Feature",
  "properties": {
    "iso:country": "GB",
    "wof:name": "WN2 5JS",
    "wof:placetype": "postalcode"
  },
  "geometry": {"coordinates":[-2.60742,53.508703],"type":"Point"}
}
