{
  "type": "Feature",
  "properties": {
    "date:inception_lower": "1980-01-01",
    "date:inception_upper": "1980-01-01",
    "iso:country": "GB",
    "wof:name": "HG4 4PA",
    "wof:placetype": "postalcode"
  },
  "geometry": {"coordinates":[-1.674387,54.235345],"type":"Point"}
}
