{
  "type": "Feature",
  "properties": {
    "iso:country":"GB",
    "wof:name":"HG4 4PA",
    "wof:placetype":"postalcode"
},
  "geometry": {"coordinates":[-1.67438024047579,54.23533374870372],"type":"Point"}
}