{
  "type": "Feature",
  "properties": {
    "iso:country":"GB",
    "wof:name":"NE15 7QU",
    "wof:placetype":"postalcode"
},
  "geometry": {"coordinates":[-1.70397224951357,54.97886829425302],"type":"Point"}
}