{
  "type": "Feature",
  "properties": {
    "date:inception_lower":"1990-07-01",
    "date:inception_upper":"1990-07-31",
    "iso:country":"GB",
    "wof:name":"DN9 1EH",
    "wof:placetype":"postalcode"
},
  "geometry": {"coordinates":[-0.832878,53.526512],"type":"Point"}
}