{
  "type": "Feature",
  "properties": {
    "iso:country": "GB",
    "wof:name": "DN9 1EH",
    "wof:placetype": "postalcode"
  },
  "geometry": {"coordinates":[-0.832878,53.526512],"type":"Point"}
}
