{
  "type": "Feature",
  "properties": {
    "iso:country":"GB",
    "wof:name":"M14 6BW",
    "wof:placetype":"postalcode"
},
  "geometry": {"coordinates":[-2.22789891075055,53.43848136868022],"type":"Point"}
}