{
  "type": "Feature",
  "properties": {
    "iso:country": "GB",
    "wof:name": "M14 6BW",
    "wof:placetype": "postalcode"
  },
  "geometry": {"coordinates":[-2.227899,53.438481],"type":"Point"}
}
