{
  "type": "Feature",
  "properties": {
    "date:inception_lower": "2015-05-01",
    "date:inception_upper": "2015-05-01",
    "iso:country": "GB",
    "wof:name": "NN8 2BF",
    "wof:placetype": "postalcode"
  },
  "geometry": {"coordinates":[-0.698312,52.288836],"type":"Point"}
}
