{
  "type": "Feature",
  "properties": {
    "date:inception_lower": "1991-09-01",
    "date:inception_upper": "1991-09-01",
    "iso:country": "GB",
    "wof:name": "NG6 0NX",
    "wof:placetype": "postalcode"
  },
  "geometry": {"coordinates":[-1.174797,52.98831],"type":"Point"}
}
