{
  "type": "Feature",
  "properties": {
    "iso:country":"GB",
    "wof:name":"NG6 0NX",
    "wof:placetype":"postalcode"
},
  "geometry": {"coordinates":[-1.17479673899086,52.98831031175182],"type":"Point"}
}