{
  "type": "Feature",
  "properties": {
    "iso:country": "GB",
    "wof:name": "EX17 5DA",
    "wof:placetype": "postalcode"
  },
  "geometry": {"coordinates":[-3.744065,50.796142],"type":"Point"}
}
