{
  "type": "Feature",
  "properties": {
    "date:inception_lower": "1980-01-01",
    "date:inception_upper": "1980-01-01",
    "iso:country": "GB",
    "wof:name": "EX17 5DA",
    "wof:placetype": "postalcode"
  },
  "geometry": {"coordinates":[-3.744011,50.796214],"type":"Point"}
}
