{
  "type": "Feature",
  "properties": {
    "iso:country":"GB",
    "wof:name":"L35 5DT",
    "wof:placetype":"postalcode"
},
  "geometry": {"coordinates":[-2.8030549176974,53.41962968000065],"type":"Point"}
}