{
  "type": "Feature",
  "properties": {
    "iso:country": "GB",
    "wof:name": "L35 5DT",
    "wof:placetype": "postalcode"
  },
  "geometry": {"coordinates":[-2.803055,53.41963],"type":"Point"}
}
