{
  "type": "Feature",
  "properties": {
    "iso:country":"GB",
    "wof:name":"NP10 8GX",
    "wof:placetype":"postalcode"
},
  "geometry": {"coordinates":[-3.106495298702,51.58287262286499],"type":"Point"}
}