{
  "type": "Feature",
  "properties": {
    "iso:country":"GB",
    "wof:name":"SN15 4RN",
    "wof:placetype":"postalcode"
},
  "geometry": {"coordinates":[-2.07901106485443,51.50751891094708],"type":"Point"}
}