{
  "type": "Feature",
  "properties": {
    "iso:country":"GB",
    "wof:name":"KY7 6RU",
    "wof:placetype":"postalcode"
},
  "geometry": {"coordinates":[-3.16979498183905,56.20794696184545],"type":"Point"}
}