{
  "type": "Feature",
  "properties": {
    "date:inception_lower": "1980-01-01",
    "date:inception_upper": "1980-01-01",
    "iso:country": "GB",
    "wof:name": "RH10 4LU",
    "wof:placetype": "postalcode"
  },
  "geometry": {"coordinates":[-0.075236,51.122517],"type":"Point"}
}
