{
  "type": "Feature",
  "properties": {
    "iso:country":"GB",
    "wof:name":"LS28 7ED",
    "wof:placetype":"postalcode"
},
  "geometry": {"coordinates":[-1.66083217568501,53.79795619179294],"type":"Point"}
}