{
  "type": "Feature",
  "properties": {
    "date:inception_lower":"2007-07-01",
    "date:inception_upper":"2007-07-31",
    "iso:country":"GB",
    "wof:name":"M9 6UY",
    "wof:placetype":"postalcode"
},
  "geometry": {"coordinates":[-2.220402,53.531274],"type":"Point"}
}