{
  "type": "Feature",
  "properties": {
    "iso:country":"GB",
    "wof:name":"M9 6UY",
    "wof:placetype":"postalcode"
},
  "geometry": {"coordinates":[-2.22040165036003,53.53127420951595],"type":"Point"}
}