{
  "type": "Feature",
  "properties": {
    "date:inception_lower":"1980-01-01",
    "date:inception_upper":"1980-01-31",
    "iso:country":"GB",
    "wof:name":"SK1 3JT",
    "wof:placetype":"postalcode"
},
  "geometry": {"coordinates":[-2.149082,53.400943],"type":"Point"}
}