{
  "type": "Feature",
  "properties": {
    "iso:country":"GB",
    "wof:name":"SK1 3JT",
    "wof:placetype":"postalcode"
},
  "geometry": {"coordinates":[-2.14941401133101,53.40086262267246],"type":"Point"}
}