{
  "type": "Feature",
  "properties": {
    "date:inception_lower": "1980-09-01",
    "date:inception_upper": "1980-09-01",
    "iso:country": "GB",
    "wof:name": "PH3 1SH",
    "wof:placetype": "postalcode"
  },
  "geometry": {"coordinates":[-3.755382,56.281633],"type":"Point"}
}
