{
  "type": "Feature",
  "properties": {
    "iso:country": "GB",
    "wof:name": "PH3 1SH",
    "wof:placetype": "postalcode"
  },
  "geometry": {"coordinates":[-3.755382,56.281633],"type":"Point"}
}
