{
  "type": "Feature",
  "properties": {
    "date:inception_lower": "1980-01-01",
    "date:inception_upper": "1980-01-01",
    "iso:country": "GB",
    "wof:name": "DH7 9QX",
    "wof:placetype": "postalcode"
  },
  "geometry": {"coordinates":[-1.697466,54.7903],"type":"Point"}
}
