{
  "type": "Feature",
  "properties": {
    "iso:country": "GB",
    "wof:name": "NR30 5ER",
    "wof:placetype": "postalcode"
  },
  "geometry": {"coordinates":[1.728658,52.647587],"type":"Point"}
}
