{
  "type": "Feature",
  "properties": {
    "date:inception_lower": "2021-05-01",
    "date:inception_upper": "2021-05-01",
    "iso:country": "GB",
    "wof:name": "NN6 9XN",
    "wof:placetype": "postalcode"
  },
  "geometry": {"coordinates":[-0.904445,52.384175],"type":"Point"}
}
