{
  "type": "Feature",
  "properties": {
    "iso:country":"GB",
    "wof:name":"EH47 7AP",
    "wof:placetype":"postalcode"
},
  "geometry": {"coordinates":[-3.59213217132665,55.87806555196141],"type":"Point"}
}