{
  "type": "Feature",
  "properties": {
    "iso:country": "GB",
    "wof:name": "NE67 5LA",
    "wof:placetype": "postalcode"
  },
  "geometry": {"coordinates":[-1.725231,55.55028],"type":"Point"}
}
