{
  "type": "Feature",
  "properties": {
    "iso:country":"GB",
    "wof:name":"NE67 5LA",
    "wof:placetype":"postalcode"
},
  "geometry": {"coordinates":[-1.72523078828523,55.55028007894024],"type":"Point"}
}