{
  "type": "Feature",
  "properties": {
    "date:inception_lower": "1984-02-01",
    "date:inception_upper": "1984-02-01",
    "iso:country": "GB",
    "wof:name": "BN23 6JY",
    "wof:placetype": "postalcode"
  },
  "geometry": {"coordinates":[0.30796,50.790544],"type":"Point"}
}
