{
  "type": "Feature",
  "properties": {
    "iso:country":"GB",
    "wof:name":"AB43 8AB",
    "wof:placetype":"postalcode"
},
  "geometry": {"coordinates":[-1.9102047810466,57.60065015258826],"type":"Point"}
}