{
  "type": "Feature",
  "properties": {
    "date:inception_lower":"2006-07-01",
    "date:inception_upper":"2006-07-31",
    "iso:country":"GB",
    "wof:name":"AB43 8AB",
    "wof:placetype":"postalcode"
},
  "geometry": {"coordinates":[-1.91021,57.600636],"type":"Point"}
}