{
  "type": "Feature",
  "properties": {
    "iso:country":"GB",
    "wof:name":"HA8 9EJ",
    "wof:placetype":"postalcode"
},
  "geometry": {"coordinates":[-0.26378811516796,51.60996206337984],"type":"Point"}
}