{
  "type": "Feature",
  "properties": {
    "iso:country":"GB",
    "wof:name":"DT6 6LQ",
    "wof:placetype":"postalcode"
},
  "geometry": {"coordinates":[-2.82068068772626,50.73437013259826],"type":"Point"}
}