{
  "type": "Feature",
  "properties": {
    "iso:country": "GB",
    "wof:name": "CR2 0HH",
    "wof:placetype": "postalcode"
  },
  "geometry": {"coordinates":[-0.083444,51.339922],"type":"Point"}
}
