{
  "type": "Feature",
  "properties": {
    "iso:country":"GB",
    "wof:name":"CR2 0HH",
    "wof:placetype":"postalcode"
},
  "geometry": {"coordinates":[-0.08344355523746,51.33992212362716],"type":"Point"}
}