{
  "type": "Feature",
  "properties": {
    "iso:country":"GB",
    "wof:name":"EX23 8SY",
    "wof:placetype":"postalcode"
},
  "geometry": {"coordinates":[-4.54425813124457,50.82848279546072],"type":"Point"}
}