{
  "type": "Feature",
  "properties": {
    "date:inception_lower": "2004-06-01",
    "date:inception_upper": "2004-06-01",
    "iso:country": "GB",
    "wof:name": "EX23 8SY",
    "wof:placetype": "postalcode"
  },
  "geometry": {"coordinates":[-4.544258,50.828483],"type":"Point"}
}
