{
  "type": "Feature",
  "properties": {
    "iso:country":"GB",
    "wof:name":"CM8 2QD",
    "wof:placetype":"postalcode"
},
  "geometry": {"coordinates":[0.63594650335354,51.8172889081055],"type":"Point"}
}