{
  "type": "Feature",
  "properties": {
    "iso:country":"GB",
    "wof:name":"GU28 0DS",
    "wof:placetype":"postalcode"
},
  "geometry": {"coordinates":[-0.61090781877519,50.98632318702849],"type":"Point"}
}