{
  "type": "Feature",
  "properties": {
    "date:inception_lower":"1980-01-01",
    "date:inception_upper":"1980-01-31",
    "iso:country":"GB",
    "wof:name":"GU28 0DS",
    "wof:placetype":"postalcode"
},
  "geometry": {"coordinates":[-0.610908,50.986323],"type":"Point"}
}