{
  "type": "Feature",
  "properties": {
    "iso:country":"GB",
    "wof:name":"AB52 6AG",
    "wof:placetype":"postalcode"
},
  "geometry": {"coordinates":[-2.55876555688999,57.32184311502937],"type":"Point"}
}