{
  "type": "Feature",
  "properties": {
    "date:inception_lower": "2021-04-01",
    "date:inception_upper": "2021-04-01",
    "iso:country": "GB",
    "wof:name": "LE13 1FG",
    "wof:placetype": "postalcode"
  },
  "geometry": {"coordinates":[-0.886219,52.773207],"type":"Point"}
}
