{
  "type": "Feature",
  "properties": {
    "date:inception_lower": "2020-04-01",
    "date:inception_upper": "2020-04-01",
    "iso:country": "GB",
    "wof:name": "YO51 9PW",
    "wof:placetype": "postalcode"
  },
  "geometry": {"coordinates":[-1.356854,54.066276],"type":"Point"}
}
