{
  "type": "Feature",
  "properties": {
    "iso:country":"GB",
    "wof:name":"DD8 4TN",
    "wof:placetype":"postalcode"
},
  "geometry": {"coordinates":[-3.00224380542807,56.68283289123691],"type":"Point"}
}