{
  "type": "Feature",
  "properties": {
    "date:inception_lower": "1980-01-01",
    "date:inception_upper": "1980-01-01",
    "iso:country": "GB",
    "wof:name": "SW20 8AW",
    "wof:placetype": "postalcode"
  },
  "geometry": {"coordinates":[-0.226343,51.418142],"type":"Point"}
}
