{
  "type": "Feature",
  "properties": {
    "iso:country":"GB",
    "wof:name":"SW20 8AW",
    "wof:placetype":"postalcode"
},
  "geometry": {"coordinates":[-0.22638179523835,51.41813429084448],"type":"Point"}
}