{
  "type": "Feature",
  "properties": {
    "iso:country":"GB",
    "wof:name":"RG22 4BU",
    "wof:placetype":"postalcode"
},
  "geometry": {"coordinates":[-1.08924288234758,51.24944228961602],"type":"Point"}
}