{
  "type": "Feature",
  "properties": {
    "date:inception_lower": "1983-07-01",
    "date:inception_upper": "1983-07-01",
    "iso:country": "GB",
    "wof:name": "SK13 8RR",
    "wof:placetype": "postalcode"
  },
  "geometry": {"coordinates":[-1.929356,53.441492],"type":"Point"}
}
