{
  "type": "Feature",
  "properties": {
    "date:inception_lower":"1980-01-01",
    "date:inception_upper":"1980-01-31",
    "iso:country":"GB",
    "wof:name":"PL6 5UP",
    "wof:placetype":"postalcode"
},
  "geometry": {"coordinates":[-4.102431,50.398144],"type":"Point"}
}