{
  "type": "Feature",
  "properties": {
    "iso:country":"GB",
    "wof:name":"PL6 5UP",
    "wof:placetype":"postalcode"
},
  "geometry": {"coordinates":[-4.10243103692094,50.39814388162743],"type":"Point"}
}