{
  "type": "Feature",
  "properties": {
    "date:inception_lower": "2014-12-01",
    "date:inception_upper": "2014-12-01",
    "iso:country": "GB",
    "wof:name": "LN3 4FQ",
    "wof:placetype": "postalcode"
  },
  "geometry": {"coordinates":[-0.465814,53.236167],"type":"Point"}
}
