{
  "type": "Feature",
  "properties": {
    "iso:country":"GB",
    "wof:name":"S66 8JB",
    "wof:placetype":"postalcode"
},
  "geometry": {"coordinates":[-1.20689357212031,53.42178507035677],"type":"Point"}
}