{
  "type": "Feature",
  "properties": {
    "iso:country":"GB",
    "wof:name":"OX29 7RA",
    "wof:placetype":"postalcode"
},
  "geometry": {"coordinates":[-1.42606188231255,51.72714223079738],"type":"Point"}
}