{
  "type": "Feature",
  "properties": {
    "iso:country":"GB",
    "wof:name":"ME7 5DU",
    "wof:placetype":"postalcode"
},
  "geometry": {"coordinates":[0.54156041775867,51.38508010472715],"type":"Point"}
}