{
  "type": "Feature",
  "properties": {
    "iso:country":"GB",
    "wof:name":"CH3 8LB",
    "wof:placetype":"postalcode"
},
  "geometry": {"coordinates":[-2.76759103694321,53.19474424588228],"type":"Point"}
}