{
  "type": "Feature",
  "properties": {
    "date:inception_lower": "1995-12-01",
    "date:inception_upper": "1995-12-01",
    "iso:country": "GB",
    "wof:name": "NR1 1AR",
    "wof:placetype": "postalcode"
  },
  "geometry": {"coordinates":[1.299391,52.629185],"type":"Point"}
}
