{
  "type": "Feature",
  "properties": {
    "iso:country":"GB",
    "wof:name":"M26 3AU",
    "wof:placetype":"postalcode"
},
  "geometry": {"coordinates":[-2.33037426368305,53.56144637366408],"type":"Point"}
}