{
  "type": "Feature",
  "properties": {
    "date:inception_lower":"1994-05-01",
    "date:inception_upper":"1994-05-31",
    "iso:country":"GB",
    "wof:name":"M26 3AU",
    "wof:placetype":"postalcode"
},
  "geometry": {"coordinates":[-2.330374,53.561446],"type":"Point"}
}