{
  "type": "Feature",
  "properties": {
    "iso:country":"GB",
    "wof:name":"PA20 9DN",
    "wof:placetype":"postalcode"
},
  "geometry": {"coordinates":[-5.05019666635972,55.83841566539621],"type":"Point"}
}