{
  "type": "Feature",
  "properties": {
    "iso:country": "GB",
    "wof:name": "PA20 9DN",
    "wof:placetype": "postalcode"
  },
  "geometry": {"coordinates":[-5.050197,55.838416],"type":"Point"}
}
