{
  "type": "Feature",
  "properties": {
    "date:inception_lower": "2016-07-01",
    "date:inception_upper": "2016-07-01",
    "iso:country": "GB",
    "wof:name": "WV14 6HQ",
    "wof:placetype": "postalcode"
  },
  "geometry": {"coordinates":[-2.081867,52.578559],"type":"Point"}
}
