{
  "type": "Feature",
  "properties": {
    "iso:country":"GB",
    "wof:name":"TA24 6TN",
    "wof:placetype":"postalcode"
},
  "geometry": {"coordinates":[-3.46047290052611,51.19579449379225],"type":"Point"}
}