{
  "type": "Feature",
  "properties": {
    "date:inception_lower":"2002-06-01",
    "date:inception_upper":"2002-06-30",
    "iso:country":"GB",
    "wof:name":"TA24 6TN",
    "wof:placetype":"postalcode"
},
  "geometry": {"coordinates":[-3.460473,51.195794],"type":"Point"}
}