{
  "type": "Feature",
  "properties": {
    "date:inception_lower": "1980-01-01",
    "date:inception_upper": "1980-01-01",
    "iso:country": "GB",
    "wof:name": "BA20 1BQ",
    "wof:placetype": "postalcode"
  },
  "geometry": {"coordinates":[-2.641119,50.941797],"type":"Point"}
}
