{
  "type": "Feature",
  "properties": {
    "iso:country":"GB",
    "wof:name":"SA18 3DY",
    "wof:placetype":"postalcode"
},
  "geometry": {"coordinates":[-3.99502170487155,51.78903311249234],"type":"Point"}
}