{
  "type": "Feature",
  "properties": {
    "date:inception_lower": "1980-01-01",
    "date:inception_upper": "1980-01-01",
    "iso:country": "GB",
    "wof:name": "LS27 9HG",
    "wof:placetype": "postalcode"
  },
  "geometry": {"coordinates":[-1.594743,53.739886],"type":"Point"}
}
