{
  "type": "Feature",
  "properties": {
    "date:inception_lower": "2018-02-01",
    "date:inception_upper": "2018-02-01",
    "iso:country": "GB",
    "wof:name": "LA9 7TE",
    "wof:placetype": "postalcode"
  },
  "geometry": {"coordinates":[-2.726299,54.296298],"type":"Point"}
}
