{
  "type": "Feature",
  "properties": {
    "iso:country":"GB",
    "wof:name":"WA8 3AA",
    "wof:placetype":"postalcode"
},
  "geometry": {"coordinates":[-2.71570750103135,53.38473359400717],"type":"Point"}
}