{
  "type": "Feature",
  "properties": {
    "iso:country": "GB",
    "wof:name": "WA8 3AA",
    "wof:placetype": "postalcode"
  },
  "geometry": {"coordinates":[-2.715707,53.384734],"type":"Point"}
}
