{
  "type": "Feature",
  "properties": {
    "iso:country": "GB",
    "wof:name": "S6 1GG",
    "wof:placetype": "postalcode"
  },
  "geometry": {"coordinates":[-1.49898,53.422225],"type":"Point"}
}
