{
  "type": "Feature",
  "properties": {
    "iso:country":"GB",
    "wof:name":"BA4 5PT",
    "wof:placetype":"postalcode"
},
  "geometry": {"coordinates":[-2.53573317573514,51.18619552830545],"type":"Point"}
}