{
  "type": "Feature",
  "properties": {
    "date:inception_lower":"1980-01-01",
    "date:inception_upper":"1980-01-31",
    "iso:country":"GB",
    "wof:name":"BA4 5PT",
    "wof:placetype":"postalcode"
},
  "geometry": {"coordinates":[-2.535733,51.186196],"type":"Point"}
}