{
  "type": "Feature",
  "properties": {
    "date:inception_lower":"1987-10-01",
    "date:inception_upper":"1987-10-31",
    "iso:country":"GB",
    "wof:name":"RH11 6BY",
    "wof:placetype":"postalcode"
},
  "geometry": {"coordinates":[-0.228861,51.108128],"type":"Point"}
}