{
  "type": "Feature",
  "properties": {
    "date:inception_lower":"2014-10-01",
    "date:inception_upper":"2014-10-31",
    "iso:country":"GB",
    "wof:name":"CV5 9PR",
    "wof:placetype":"postalcode"
},
  "geometry": {"coordinates":[-1.555868,52.43745],"type":"Point"}
}