{
  "type": "Feature",
  "properties": {
    "iso:country":"GB",
    "wof:name":"CV5 9PR",
    "wof:placetype":"postalcode"
},
  "geometry": {"coordinates":[-1.55536348095908,52.43735094342863],"type":"Point"}
}