{
  "type": "Feature",
  "properties": {
    "iso:country": "GB",
    "wof:name": "CV5 9PR",
    "wof:placetype": "postalcode"
  },
  "geometry": {"coordinates":[-1.555868,52.43745],"type":"Point"}
}
