{
  "type": "Feature",
  "properties": {
    "iso:country":"GB",
    "wof:name":"B6 4TA",
    "wof:placetype":"postalcode"
},
  "geometry": {"coordinates":[-1.88828923177889,52.49724238453955],"type":"Point"}
}