{
  "type": "Feature",
  "properties": {
    "date:inception_lower": "1980-01-01",
    "date:inception_upper": "1980-01-01",
    "iso:country": "GB",
    "wof:name": "SK15 3PH",
    "wof:placetype": "postalcode"
  },
  "geometry": {"coordinates":[-2.019758,53.505392],"type":"Point"}
}
