{
  "type": "Feature",
  "properties": {
    "iso:country":"GB",
    "wof:name":"PA15 4RG",
    "wof:placetype":"postalcode"
},
  "geometry": {"coordinates":[-4.76090626645157,55.94633972368766],"type":"Point"}
}