{
  "type": "Feature",
  "properties": {
    "iso:country":"GB",
    "wof:name":"PL20 6AE",
    "wof:placetype":"postalcode"
},
  "geometry": {"coordinates":[-4.08620810887867,50.49103159770011],"type":"Point"}
}