{
  "type": "Feature",
  "properties": {
    "date:inception_lower": "1980-01-01",
    "date:inception_upper": "1980-01-01",
    "iso:country": "GB",
    "wof:name": "TQ3 1EF",
    "wof:placetype": "postalcode"
  },
  "geometry": {"coordinates":[-3.559766,50.450133],"type":"Point"}
}
