{
  "type": "Feature",
  "properties": {
    "iso:country":"GB",
    "wof:name":"MK10 7DD",
    "wof:placetype":"postalcode"
},
  "geometry": {"coordinates":[-0.68137689783386,52.04251001337335],"type":"Point"}
}