{
  "type": "Feature",
  "properties": {
    "iso:country": "GB",
    "wof:name": "DL1 3TT",
    "wof:placetype": "postalcode"
  },
  "geometry": {"coordinates":[-1.534799,54.548636],"type":"Point"}
}
