{
  "type": "Feature",
  "properties": {
    "iso:country":"GB",
    "wof:name":"DL1 3TT",
    "wof:placetype":"postalcode"
},
  "geometry": {"coordinates":[-1.53479912039254,54.54863579949802],"type":"Point"}
}