{
  "type": "Feature",
  "properties": {
    "iso:country": "GB",
    "wof:name": "S41 7TZ",
    "wof:placetype": "postalcode"
  },
  "geometry": {"coordinates":[-1.423607,53.237112],"type":"Point"}
}
