{
  "type": "Feature",
  "properties": {
    "iso:country":"GB",
    "wof:name":"S41 7TZ",
    "wof:placetype":"postalcode"
},
  "geometry": {"coordinates":[-1.42360681595171,53.23711183571361],"type":"Point"}
}