{
  "type": "Feature",
  "properties": {
    "iso:country":"GB",
    "wof:name":"RM7 0QP",
    "wof:placetype":"postalcode"
},
  "geometry": {"coordinates":[0.17376055713613,51.56616337875713],"type":"Point"}
}