{
  "type": "Feature",
  "properties": {
    "iso:country": "GB",
    "wof:name": "LE6 0JT",
    "wof:placetype": "postalcode"
  },
  "geometry": {"coordinates":[-1.247068,52.650365],"type":"Point"}
}
