{
  "type": "Feature",
  "properties": {
    "iso:country":"GB",
    "wof:name":"LE6 0JT",
    "wof:placetype":"postalcode"
},
  "geometry": {"coordinates":[-1.24706798350389,52.6503655044027],"type":"Point"}
}