{
  "type": "Feature",
  "properties": {
    "iso:country":"GB",
    "wof:name":"DE21 7HS",
    "wof:placetype":"postalcode"
},
  "geometry": {"coordinates":[-1.39921302756392,52.9143246049579],"type":"Point"}
}