{
  "type": "Feature",
  "properties": {
    "iso:country":"GB",
    "wof:name":"CH7 1LP",
    "wof:placetype":"postalcode"
},
  "geometry": {"coordinates":[-3.13740083435651,53.1715698620959],"type":"Point"}
}