{
  "type": "Feature",
  "properties": {
    "iso:country":"GB",
    "wof:name":"GU12 6BB",
    "wof:placetype":"postalcode"
},
  "geometry": {"coordinates":[-0.71185981723626,51.25061933217005],"type":"Point"}
}