{
  "type": "Feature",
  "properties": {
    "iso:country":"GB",
    "wof:name":"DE7 4GU",
    "wof:placetype":"postalcode"
},
  "geometry": {"coordinates":[-1.32693478221749,52.954884165202],"type":"Point"}
}