{
  "type": "Feature",
  "properties": {
    "date:inception_lower": "1980-01-01",
    "date:inception_upper": "1980-01-01",
    "iso:country": "GB",
    "wof:name": "WF4 3JZ",
    "wof:placetype": "postalcode"
  },
  "geometry": {"coordinates":[-1.521988,53.635301],"type":"Point"}
}
