{
  "type": "Feature",
  "properties": {
    "iso:country":"GB",
    "wof:name":"WF4 3JZ",
    "wof:placetype":"postalcode"
},
  "geometry": {"coordinates":[-1.52198837340952,53.6353009107947],"type":"Point"}
}