{
  "type": "Feature",
  "properties": {
    "iso:country":"GB",
    "wof:name":"WA16 6BA",
    "wof:placetype":"postalcode"
},
  "geometry": {"coordinates":[-2.37069649084493,53.30193616010639],"type":"Point"}
}