{
  "type": "Feature",
  "properties": {
    "date:inception_lower":"1992-08-01",
    "date:inception_upper":"1992-08-31",
    "iso:country":"GB",
    "wof:name":"WA16 6BA",
    "wof:placetype":"postalcode"
},
  "geometry": {"coordinates":[-2.370696,53.301936],"type":"Point"}
}