{
  "type": "Feature",
  "properties": {
    "date:inception_lower": "1992-08-01",
    "date:inception_upper": "1992-08-01",
    "iso:country": "GB",
    "wof:name": "WA16 6BA",
    "wof:placetype": "postalcode"
  },
  "geometry": {"coordinates":[-2.37065,53.30197],"type":"Point"}
}
