{
  "type": "Feature",
  "properties": {
    "iso:country": "GB",
    "wof:name": "WA16 6BA",
    "wof:placetype": "postalcode"
  },
  "geometry": {"coordinates":[-2.370696,53.301936],"type":"Point"}
}
