{
  "type": "Feature",
  "properties": {
    "date:inception_lower": "1980-01-01",
    "date:inception_upper": "1980-01-01",
    "iso:country": "GB",
    "wof:name": "IP33 1NZ",
    "wof:placetype": "postalcode"
  },
  "geometry": {"coordinates":[0.71271,52.243991],"type":"Point"}
}
