{
  "type": "Feature",
  "properties": {
    "iso:country":"GB",
    "wof:name":"IP12 4JP",
    "wof:placetype":"postalcode"
},
  "geometry": {"coordinates":[1.30435761785501,52.09880886843962],"type":"Point"}
}