{
  "type": "Feature",
  "properties": {
    "iso:country": "GB",
    "wof:name": "GL52 8PW",
    "wof:placetype": "postalcode"
  },
  "geometry": {"coordinates":[-2.066072,51.947381],"type":"Point"}
}
