{
  "type": "Feature",
  "properties": {
    "date:inception_lower": "2012-12-01",
    "date:inception_upper": "2012-12-01",
    "iso:country": "GB",
    "wof:name": "BN27 9TU",
    "wof:placetype": "postalcode"
  },
  "geometry": {"coordinates":[0.259789,50.864959],"type":"Point"}
}
