{
  "type": "Feature",
  "properties": {
    "iso:country":"GB",
    "wof:name":"BH15 2AS",
    "wof:placetype":"postalcode"
},
  "geometry": {"coordinates":[-1.9868430514873,50.72552379189593],"type":"Point"}
}