{
  "type": "Feature",
  "properties": {
    "iso:country": "GB",
    "wof:name": "CO7 8RU",
    "wof:placetype": "postalcode"
  },
  "geometry": {"coordinates":[1.06397,51.870029],"type":"Point"}
}
