{
  "type": "Feature",
  "properties": {
    "iso:country":"GB",
    "wof:name":"CO7 8RU",
    "wof:placetype":"postalcode"
},
  "geometry": {"coordinates":[1.06397003380539,51.87002874759986],"type":"Point"}
}