{
  "type": "Feature",
  "properties": {
    "date:inception_lower": "2020-04-01",
    "date:inception_upper": "2020-04-01",
    "iso:country": "GB",
    "wof:name": "EH15 1BP",
    "wof:placetype": "postalcode"
  },
  "geometry": {"coordinates":[-3.120264,55.954631],"type":"Point"}
}
