{
  "type": "Feature",
  "properties": {
    "iso:country": "GB",
    "wof:name": "EH15 1BP",
    "wof:placetype": "postalcode"
  },
  "geometry": {"coordinates":[-3.120399,55.954334],"type":"Point"}
}
