{
  "type": "Feature",
  "properties": {
    "date:inception_lower": "1992-08-01",
    "date:inception_upper": "1992-08-01",
    "iso:country": "GB",
    "wof:name": "SN15 3YS",
    "wof:placetype": "postalcode"
  },
  "geometry": {"coordinates":[-2.112131,51.446664],"type":"Point"}
}
