{
  "type": "Feature",
  "properties": {
    "date:inception_lower": "1994-05-01",
    "date:inception_upper": "1994-05-01",
    "iso:country": "GB",
    "wof:name": "M43 7TN",
    "wof:placetype": "postalcode"
  },
  "geometry": {"coordinates":[-2.128841,53.490772],"type":"Point"}
}
