{
  "type": "Feature",
  "properties": {
    "iso:country":"GB",
    "wof:name":"M43 7TN",
    "wof:placetype":"postalcode"
},
  "geometry": {"coordinates":[-2.12884078163836,53.49077157771114],"type":"Point"}
}