{
  "type": "Feature",
  "properties": {
    "iso:country":"GB",
    "wof:name":"DT3 5NL",
    "wof:placetype":"postalcode"
},
  "geometry": {"coordinates":[-2.46875375022517,50.65385302188952],"type":"Point"}
}