{
  "type": "Feature",
  "properties": {
    "iso:country":"GB",
    "wof:name":"ML2 9QB",
    "wof:placetype":"postalcode"
},
  "geometry": {"coordinates":[-3.86264184349277,55.79887024636257],"type":"Point"}
}