{
  "type": "Feature",
  "properties": {
    "iso:country":"GB",
    "wof:name":"NE48 3HL",
    "wof:placetype":"postalcode"
},
  "geometry": {"coordinates":[-2.19135334628514,55.097972221236],"type":"Point"}
}