{
  "type": "Feature",
  "properties": {
    "iso:country": "GB",
    "wof:name": "IP14 3BS",
    "wof:placetype": "postalcode"
  },
  "geometry": {"coordinates":[0.971306,52.188306],"type":"Point"}
}
