{
  "type": "Feature",
  "properties": {
    "date:inception_lower": "1980-01-01",
    "date:inception_upper": "1980-01-01",
    "iso:country": "GB",
    "wof:name": "TS16 0EN",
    "wof:placetype": "postalcode"
  },
  "geometry": {"coordinates":[-1.358056,54.520759],"type":"Point"}
}
