{
  "type": "Feature",
  "properties": {
    "iso:country": "GB",
    "wof:name": "WS12 1DU",
    "wof:placetype": "postalcode"
  },
  "geometry": {"coordinates":[-1.99679,52.708896],"type":"Point"}
}
