{
  "type": "Feature",
  "properties": {
    "iso:country":"GB",
    "wof:name":"WS12 1DU",
    "wof:placetype":"postalcode"
},
  "geometry": {"coordinates":[-1.99678994397346,52.7088960252702],"type":"Point"}
}