{
  "type": "Feature",
  "properties": {
    "iso:country":"GB",
    "wof:name":"WV4 5JG",
    "wof:placetype":"postalcode"
},
  "geometry": {"coordinates":[-2.15507270131326,52.55466531625276],"type":"Point"}
}