{
  "type": "Feature",
  "properties": {
    "iso:country": "GB",
    "wof:name": "W4 5AG",
    "wof:placetype": "postalcode"
  },
  "geometry": {"coordinates":[-0.27012,51.49322],"type":"Point"}
}
