{
  "type": "Feature",
  "properties": {
    "iso:country": "GB",
    "wof:name": "DE6 1QW",
    "wof:placetype": "postalcode"
  },
  "geometry": {"coordinates":[-1.710987,53.083859],"type":"Point"}
}
