{
  "type": "Feature",
  "properties": {
    "date:inception_lower":"2008-05-01",
    "date:inception_upper":"2008-05-31",
    "iso:country":"GB",
    "wof:name":"SE1 0JN",
    "wof:placetype":"postalcode"
},
  "geometry": {"coordinates":[-0.099114,51.500699],"type":"Point"}
}