{
  "type": "Feature",
  "properties": {
    "iso:country": "GB",
    "wof:name": "SE1 0JN",
    "wof:placetype": "postalcode"
  },
  "geometry": {"coordinates":[-0.099114,51.500699],"type":"Point"}
}
