{
  "type": "Feature",
  "properties": {
    "iso:country": "GB",
    "wof:name": "S20 5AZ",
    "wof:placetype": "postalcode"
  },
  "geometry": {"coordinates":[-1.381581,53.332624],"type":"Point"}
}
