{
  "type": "Feature",
  "properties": {
    "iso:country": "GB",
    "wof:name": "S42 6FY",
    "wof:placetype": "postalcode"
  },
  "geometry": {"coordinates":[-1.41709,53.207157],"type":"Point"}
}
