{
  "type": "Feature",
  "properties": {
    "date:inception_lower": "1995-07-01",
    "date:inception_upper": "1995-07-01",
    "iso:country": "GB",
    "wof:name": "RG20 9ED",
    "wof:placetype": "postalcode"
  },
  "geometry": {"coordinates":[-1.335984,51.354976],"type":"Point"}
}
