{
  "type": "Feature",
  "properties": {
    "iso:country": "GB",
    "wof:name": "RG20 9ED",
    "wof:placetype": "postalcode"
  },
  "geometry": {"coordinates":[-1.335984,51.354976],"type":"Point"}
}
