{
  "type": "Feature",
  "properties": {
    "iso:country":"GB",
    "wof:name":"RG20 9ED",
    "wof:placetype":"postalcode"
},
  "geometry": {"coordinates":[-1.33598408770217,51.35497583841407],"type":"Point"}
}