{
  "type": "Feature",
  "properties": {
    "iso:country": "GB",
    "wof:name": "OX16 1HZ",
    "wof:placetype": "postalcode"
  },
  "geometry": {"coordinates":[-1.369417,52.066102],"type":"Point"}
}
