{
  "type": "Feature",
  "properties": {
    "iso:country": "GB",
    "wof:name": "LA23 3GY",
    "wof:placetype": "postalcode"
  },
  "geometry": {"coordinates":[-2.923666,54.352746],"type":"Point"}
}
