{
  "type": "Feature",
  "properties": {
    "date:inception_lower": "2013-08-01",
    "date:inception_upper": "2013-08-01",
    "iso:country": "GB",
    "wof:name": "LA23 3GY",
    "wof:placetype": "postalcode"
  },
  "geometry": {"coordinates":[-2.923666,54.352746],"type":"Point"}
}
