{
  "type": "Feature",
  "properties": {
    "iso:country":"GB",
    "wof:name":"NG7 2GU",
    "wof:placetype":"postalcode"
},
  "geometry": {"coordinates":[-1.18288789001586,52.9479135920568],"type":"Point"}
}