{
  "type": "Feature",
  "properties": {
    "iso:country":"GB",
    "wof:name":"OX3 7LR",
    "wof:placetype":"postalcode"
},
  "geometry": {"coordinates":[-1.21699305548543,51.75477970476486],"type":"Point"}
}