{
  "type": "Feature",
  "properties": {
    "date:inception_lower": "1980-01-01",
    "date:inception_upper": "1980-01-01",
    "iso:country": "GB",
    "wof:name": "WA6 9HY",
    "wof:placetype": "postalcode"
  },
  "geometry": {"coordinates":[-2.751368,53.241069],"type":"Point"}
}
