{
  "type": "Feature",
  "properties": {
    "iso:country":"GB",
    "wof:name":"WA6 9HY",
    "wof:placetype":"postalcode"
},
  "geometry": {"coordinates":[-2.75136775856183,53.24106939238606],"type":"Point"}
}