{
  "type": "Feature",
  "properties": {
    "iso:country": "GB",
    "wof:name": "WA6 9HY",
    "wof:placetype": "postalcode"
  },
  "geometry": {"coordinates":[-2.751368,53.241069],"type":"Point"}
}
