{
  "type": "Feature",
  "properties": {
    "iso:country":"GB",
    "wof:name":"BN2 4AN",
    "wof:placetype":"postalcode"
},
  "geometry": {"coordinates":[-0.12605749930817,50.83822964922401],"type":"Point"}
}