{
  "type": "Feature",
  "properties": {
    "iso:country": "GB",
    "wof:name": "BN2 4AN",
    "wof:placetype": "postalcode"
  },
  "geometry": {"coordinates":[-0.126057,50.83823],"type":"Point"}
}
