{
  "type": "Feature",
  "properties": {
    "iso:country":"GB",
    "wof:name":"BA11 4AQ",
    "wof:placetype":"postalcode"
},
  "geometry": {"coordinates":[-2.33035489433692,51.22241137959912],"type":"Point"}
}