{
  "type": "Feature",
  "properties": {
    "date:inception_lower": "1980-01-01",
    "date:inception_upper": "1980-01-01",
    "iso:country": "GB",
    "wof:name": "TA4 2BY",
    "wof:placetype": "postalcode"
  },
  "geometry": {"coordinates":[-3.386563,51.057394],"type":"Point"}
}
