{
  "type": "Feature",
  "properties": {
    "iso:country":"GB",
    "wof:name":"CM6 2ND",
    "wof:placetype":"postalcode"
},
  "geometry": {"coordinates":[0.34410511086411,51.95226348769186],"type":"Point"}
}