{
  "type": "Feature",
  "properties": {
    "iso:country":"GB",
    "wof:name":"NE23 7SP",
    "wof:placetype":"postalcode"
},
  "geometry": {"coordinates":[-1.5511592810109,55.06372487953593],"type":"Point"}
}