{
  "type": "Feature",
  "properties": {
    "date:inception_lower": "1980-01-01",
    "date:inception_upper": "1980-01-01",
    "iso:country": "GB",
    "wof:name": "NE23 7SP",
    "wof:placetype": "postalcode"
  },
  "geometry": {"coordinates":[-1.551159,55.063725],"type":"Point"}
}
