{
  "type": "Feature",
  "properties": {
    "iso:country": "GB",
    "wof:name": "NE23 7SP",
    "wof:placetype": "postalcode"
  },
  "geometry": {"coordinates":[-1.551159,55.063725],"type":"Point"}
}
