{
  "type": "Feature",
  "properties": {
    "iso:country":"GB",
    "wof:name":"GL50 1UL",
    "wof:placetype":"postalcode"
},
  "geometry": {"coordinates":[-2.07967791315363,51.89575652948607],"type":"Point"}
}