{
  "type": "Feature",
  "properties": {
    "iso:country": "GB",
    "wof:name": "MK45 1NB",
    "wof:placetype": "postalcode"
  },
  "geometry": {"coordinates":[-0.500381,51.998122],"type":"Point"}
}
