{
  "type": "Feature",
  "properties": {
    "iso:country": "GB",
    "wof:name": "CO7 6JZ",
    "wof:placetype": "postalcode"
  },
  "geometry": {"coordinates":[0.957608,51.981099],"type":"Point"}
}
