{
  "type": "Feature",
  "properties": {
    "iso:country":"GB",
    "wof:name":"CO7 6JZ",
    "wof:placetype":"postalcode"
},
  "geometry": {"coordinates":[0.95760802210927,51.98109929029368],"type":"Point"}
}