{
  "type": "Feature",
  "properties": {
    "iso:country":"GB",
    "wof:name":"SA7 9FD",
    "wof:placetype":"postalcode"
},
  "geometry": {"coordinates":[-3.90484098899825,51.65873867144632],"type":"Point"}
}