{
  "type": "Feature",
  "properties": {
    "date:inception_lower":"2000-12-01",
    "date:inception_upper":"2000-12-31",
    "iso:country":"GB",
    "wof:name":"SA7 9FD",
    "wof:placetype":"postalcode"
},
  "geometry": {"coordinates":[-3.905028,51.658642],"type":"Point"}
}