{
  "type": "Feature",
  "properties": {
    "iso:country":"GB",
    "wof:name":"EN5 1FD",
    "wof:placetype":"postalcode"
},
  "geometry": {"coordinates":[-0.18291917736472,51.64083163597927],"type":"Point"}
}