{
  "type": "Feature",
  "properties": {
    "iso:country": "GB",
    "wof:name": "S42 6BL",
    "wof:placetype": "postalcode"
  },
  "geometry": {"coordinates":[-1.408554,53.190935],"type":"Point"}
}
