{
  "type": "Feature",
  "properties": {
    "iso:country":"GB",
    "wof:name":"SW1X 8QD",
    "wof:placetype":"postalcode"
},
  "geometry": {"coordinates":[-0.15283295684543,51.49798526087817],"type":"Point"}
}