{
  "type": "Feature",
  "properties": {
    "date:inception_lower": "1997-12-01",
    "date:inception_upper": "1997-12-01",
    "iso:country": "GB",
    "wof:name": "NR1 3UT",
    "wof:placetype": "postalcode"
  },
  "geometry": {"coordinates":[1.322937,52.64771],"type":"Point"}
}
