{
  "type": "Feature",
  "properties": {
    "iso:country":"GB",
    "wof:name":"M32 9AD",
    "wof:placetype":"postalcode"
},
  "geometry": {"coordinates":[-2.31218141915162,53.44444781152735],"type":"Point"}
}