{
  "type": "Feature",
  "properties": {
    "iso:country": "GB",
    "wof:name": "NW3 6QT",
    "wof:placetype": "postalcode"
  },
  "geometry": {"coordinates":[-0.180287,51.557174],"type":"Point"}
}
