{
  "type": "Feature",
  "properties": {
    "iso:country":"GB",
    "wof:name":"NW3 6QT",
    "wof:placetype":"postalcode"
},
  "geometry": {"coordinates":[-0.18022511759318,51.55717911125875],"type":"Point"}
}