{
  "type": "Feature",
  "properties": {
    "date:inception_lower": "2011-11-01",
    "date:inception_upper": "2011-11-01",
    "iso:country": "GB",
    "wof:name": "LN5 8BF",
    "wof:placetype": "postalcode"
  },
  "geometry": {"coordinates":[-0.553309,53.201779],"type":"Point"}
}
