{
  "type": "Feature",
  "properties": {
    "iso:country":"GB",
    "wof:name":"N14 6PB",
    "wof:placetype":"postalcode"
},
  "geometry": {"coordinates":[-0.12203010771708,51.62965820397719],"type":"Point"}
}