{
  "type": "Feature",
  "properties": {
    "iso:country": "GB",
    "wof:name": "L23 6TP",
    "wof:placetype": "postalcode"
  },
  "geometry": {"coordinates":[-3.054777,53.493716],"type":"Point"}
}
