{
  "type": "Feature",
  "properties": {
    "date:inception_lower": "1980-01-01",
    "date:inception_upper": "1980-01-01",
    "iso:country": "GB",
    "wof:name": "L23 6TP",
    "wof:placetype": "postalcode"
  },
  "geometry": {"coordinates":[-3.054777,53.493716],"type":"Point"}
}
