{
  "type": "Feature",
  "properties": {
    "iso:country":"GB",
    "wof:name":"L23 6TP",
    "wof:placetype":"postalcode"
},
  "geometry": {"coordinates":[-3.05488820822312,53.49384229942847],"type":"Point"}
}