{
  "type": "Feature",
  "properties": {
    "iso:country":"GB",
    "wof:name":"ST4 3LN",
    "wof:placetype":"postalcode"
},
  "geometry": {"coordinates":[-2.15646115300016,53.00096578926041],"type":"Point"}
}