{
  "type": "Feature",
  "properties": {
    "date:inception_lower":"1980-01-01",
    "date:inception_upper":"1980-01-31",
    "iso:country":"GB",
    "wof:name":"ST4 3LN",
    "wof:placetype":"postalcode"
},
  "geometry": {"coordinates":[-2.156461,53.000966],"type":"Point"}
}