{
  "type": "Feature",
  "properties": {
    "iso:country":"GB",
    "wof:name":"L37 2HZ",
    "wof:placetype":"postalcode"
},
  "geometry": {"coordinates":[-3.07943610818693,53.54991117559178],"type":"Point"}
}