{
  "type": "Feature",
  "properties": {
    "date:inception_lower":"1980-01-01",
    "date:inception_upper":"1980-01-31",
    "iso:country":"GB",
    "wof:name":"SN10 4NW",
    "wof:placetype":"postalcode"
},
  "geometry": {"coordinates":[-1.993439,51.294705],"type":"Point"}
}