{
  "type": "Feature",
  "properties": {
    "iso:country":"GB",
    "wof:name":"SN10 4NW",
    "wof:placetype":"postalcode"
},
  "geometry": {"coordinates":[-1.99343929383103,51.29470497627689],"type":"Point"}
}