{
  "type": "Feature",
  "properties": {
    "iso:country": "GB",
    "wof:name": "PE30 4NQ",
    "wof:placetype": "postalcode"
  },
  "geometry": {"coordinates":[0.431376,52.746357],"type":"Point"}
}
