{
  "type": "Feature",
  "properties": {
    "iso:country":"GB",
    "wof:name":"PE30 4NQ",
    "wof:placetype":"postalcode"
},
  "geometry": {"coordinates":[0.43137549858412,52.74635740064659],"type":"Point"}
}