{
  "type": "Feature",
  "properties": {
    "iso:country":"GB",
    "wof:name":"CM1 3PU",
    "wof:placetype":"postalcode"
},
  "geometry": {"coordinates":[0.40008420402444,51.71984926692588],"type":"Point"}
}