{
  "type": "Feature",
  "properties": {
    "iso:country": "GB",
    "wof:name": "CM1 3PU",
    "wof:placetype": "postalcode"
  },
  "geometry": {"coordinates":[0.400084,51.719849],"type":"Point"}
}
