{
  "type": "Feature",
  "properties": {
    "iso:country":"GB",
    "wof:name":"KY8 4EZ",
    "wof:placetype":"postalcode"
},
  "geometry": {"coordinates":[-2.99606458884531,56.19581137069225],"type":"Point"}
}