{
  "type": "Feature",
  "properties": {
    "iso:country": "GB",
    "wof:name": "BN10 7ES",
    "wof:placetype": "postalcode"
  },
  "geometry": {"coordinates":[-0.014878,50.79431],"type":"Point"}
}
