{
  "type": "Feature",
  "properties": {
    "date:inception_lower":"1990-07-01",
    "date:inception_upper":"1990-07-31",
    "iso:country":"GB",
    "wof:name":"BN10 7ES",
    "wof:placetype":"postalcode"
},
  "geometry": {"coordinates":[-0.014878,50.79431],"type":"Point"}
}