{
  "type": "Feature",
  "properties": {
    "iso:country":"GB",
    "wof:name":"LS6 1AA",
    "wof:placetype":"postalcode"
},
  "geometry": {"coordinates":[-1.57450407572693,53.81785927014127],"type":"Point"}
}