{
  "type": "Feature",
  "properties": {
    "date:inception_lower": "1997-12-01",
    "date:inception_upper": "1997-12-01",
    "iso:country": "GB",
    "wof:name": "WS12 4XX",
    "wof:placetype": "postalcode"
  },
  "geometry": {"coordinates":[-2.007254,52.709921],"type":"Point"}
}
