{
  "type": "Feature",
  "properties": {
    "date:inception_lower": "2021-04-01",
    "date:inception_upper": "2021-04-01",
    "iso:country": "GB",
    "wof:name": "CW8 2FB",
    "wof:placetype": "postalcode"
  },
  "geometry": {"coordinates":[-2.55701,53.242628],"type":"Point"}
}
