{
  "type": "Feature",
  "properties": {
    "iso:country": "GB",
    "wof:name": "S36 9FN",
    "wof:placetype": "postalcode"
  },
  "geometry": {"coordinates":[-1.660876,53.515186],"type":"Point"}
}
