{
  "type": "Feature",
  "properties": {
    "iso:country":"GB",
    "wof:name":"S36 9FN",
    "wof:placetype":"postalcode"
},
  "geometry": {"coordinates":[-1.66146431011904,53.51513479957116],"type":"Point"}
}