{
  "type": "Feature",
  "properties": {
    "iso:country": "GB",
    "wof:name": "OX11 0JG",
    "wof:placetype": "postalcode"
  },
  "geometry": {"coordinates":[-1.298552,51.595869],"type":"Point"}
}
