{
  "type": "Feature",
  "properties": {
    "iso:country":"GB",
    "wof:name":"OX11 0JG",
    "wof:placetype":"postalcode"
},
  "geometry": {"coordinates":[-1.29855237095926,51.59586894024306],"type":"Point"}
}