{
  "type": "Feature",
  "properties": {
    "date:inception_lower":"2005-01-01",
    "date:inception_upper":"2005-01-31",
    "iso:country":"GB",
    "wof:name":"LN6 9PH",
    "wof:placetype":"postalcode"
},
  "geometry": {"coordinates":[-0.599973,53.177507],"type":"Point"}
}