{
  "type": "Feature",
  "properties": {
    "date:inception_lower": "2023-12-01",
    "date:inception_upper": "2023-12-01",
    "iso:country": "GB",
    "wof:name": "DE11 7GH",
    "wof:placetype": "postalcode"
  },
  "geometry": {"coordinates":[-1.532045,52.778155],"type":"Point"}
}
