{
  "type": "Feature",
  "properties": {
    "iso:country":"GB",
    "wof:name":"WA14 3DG",
    "wof:placetype":"postalcode"
},
  "geometry": {"coordinates":[-2.36479145649348,53.37135616927795],"type":"Point"}
}