{
  "type": "Feature",
  "properties": {
    "date:inception_lower": "1980-01-01",
    "date:inception_upper": "1980-01-01",
    "iso:country": "GB",
    "wof:name": "PE22 8NT",
    "wof:placetype": "postalcode"
  },
  "geometry": {"coordinates":[0.191409,53.090206],"type":"Point"}
}
