{
  "type": "Feature",
  "properties": {
    "iso:country":"GB",
    "wof:name":"PE22 8NT",
    "wof:placetype":"postalcode"
},
  "geometry": {"coordinates":[0.19135871250488,53.09017055086946],"type":"Point"}
}