{
  "type": "Feature",
  "properties": {
    "iso:country": "GB",
    "wof:name": "DE73 6WF",
    "wof:placetype": "postalcode"
  },
  "geometry": {"coordinates":[-1.433209,52.877482],"type":"Point"}
}
