{
  "type": "Feature",
  "properties": {
    "iso:country": "GB",
    "wof:name": "NN1 2SP",
    "wof:placetype": "postalcode"
  },
  "geometry": {"coordinates":[-0.903129,52.239675],"type":"Point"}
}
