{
  "type": "Feature",
  "properties": {
    "date:inception_lower":"2019-03-01",
    "date:inception_upper":"2019-03-31",
    "iso:country":"GB",
    "wof:name":"NN1 2SP",
    "wof:placetype":"postalcode"
},
  "geometry": {"coordinates":[-0.903129,52.239675],"type":"Point"}
}