{
  "type": "Feature",
  "properties": {
    "iso:country":"GB",
    "wof:name":"HR8 1RR",
    "wof:placetype":"postalcode"
},
  "geometry": {"coordinates":[-2.39154222702176,52.01584214356739],"type":"Point"}
}