{
  "type": "Feature",
  "properties": {
    "date:inception_lower": "1980-01-01",
    "date:inception_upper": "1980-01-01",
    "iso:country": "GB",
    "wof:name": "NG24 3LZ",
    "wof:placetype": "postalcode"
  },
  "geometry": {"coordinates":[-0.776607,53.0633],"type":"Point"}
}
