{
  "type": "Feature",
  "properties": {
    "date:inception_lower":"1983-01-01",
    "date:inception_upper":"1983-01-31",
    "iso:country":"GB",
    "wof:name":"EX5 1JH",
    "wof:placetype":"postalcode"
},
  "geometry": {"coordinates":[-3.400839,50.675026],"type":"Point"}
}