{
  "type": "Feature",
  "properties": {
    "iso:country": "GB",
    "wof:name": "IP3 8AR",
    "wof:placetype": "postalcode"
  },
  "geometry": {"coordinates":[1.171654,52.053575],"type":"Point"}
}
