{
  "type": "Feature",
  "properties": {
    "date:inception_lower": "2022-08-01",
    "date:inception_upper": "2022-08-01",
    "iso:country": "GB",
    "wof:name": "PR9 8ST",
    "wof:placetype": "postalcode"
  },
  "geometry": {"coordinates":[-2.953294,53.667141],"type":"Point"}
}
