{
  "type": "Feature",
  "properties": {
    "iso:country":"GB",
    "wof:name":"L31 4DZ",
    "wof:placetype":"postalcode"
},
  "geometry": {"coordinates":[-2.9563170530184,53.53179538289648],"type":"Point"}
}