{
  "type": "Feature",
  "properties": {
    "date:inception_lower": "1980-01-01",
    "date:inception_upper": "1980-01-01",
    "iso:country": "GB",
    "wof:name": "L31 4DZ",
    "wof:placetype": "postalcode"
  },
  "geometry": {"coordinates":[-2.956317,53.531795],"type":"Point"}
}
