{
  "type": "Feature",
  "properties": {
    "iso:country":"GB",
    "wof:name":"N12 7DL",
    "wof:placetype":"postalcode"
},
  "geometry": {"coordinates":[-0.18716133908463,51.61635724094595],"type":"Point"}
}