{
  "type": "Feature",
  "properties": {
    "iso:country":"GB",
    "wof:name":"BA1 7HR",
    "wof:placetype":"postalcode"
},
  "geometry": {"coordinates":[-2.31760248948001,51.41224511717098],"type":"Point"}
}