{
  "type": "Feature",
  "properties": {
    "iso:country": "GB",
    "wof:name": "BA1 7HR",
    "wof:placetype": "postalcode"
  },
  "geometry": {"coordinates":[-2.317602,51.412245],"type":"Point"}
}
