{
  "type": "Feature",
  "properties": {
    "iso:country":"GB",
    "wof:name":"S73 9HA",
    "wof:placetype":"postalcode"
},
  "geometry": {"coordinates":[-1.37381885958427,53.53642826140359],"type":"Point"}
}