{
  "type": "Feature",
  "properties": {
    "iso:country":"GB",
    "wof:name":"SY20 9PR",
    "wof:placetype":"postalcode"
},
  "geometry": {"coordinates":[-3.71665790012759,52.64047811702883],"type":"Point"}
}