{
  "type": "Feature",
  "properties": {
    "iso:country":"GB",
    "wof:name":"WF10 3FG",
    "wof:placetype":"postalcode"
},
  "geometry": {"coordinates":[-1.32035023785289,53.7169021768936],"type":"Point"}
}