{
  "type": "Feature",
  "properties": {
    "iso:country": "GB",
    "wof:name": "WF10 3FG",
    "wof:placetype": "postalcode"
  },
  "geometry": {"coordinates":[-1.32035,53.716902],"type":"Point"}
}
