{
  "type": "Feature",
  "properties": {
    "date:inception_lower": "2009-08-01",
    "date:inception_upper": "2009-08-01",
    "iso:country": "GB",
    "wof:name": "WF10 3FG",
    "wof:placetype": "postalcode"
  },
  "geometry": {"coordinates":[-1.32035,53.716902],"type":"Point"}
}
