{
  "type": "Feature",
  "properties": {
    "iso:country":"GB",
    "wof:name":"DH2 2SF",
    "wof:placetype":"postalcode"
},
  "geometry": {"coordinates":[-1.62032248725558,54.8626135184241],"type":"Point"}
}