{
  "type": "Feature",
  "properties": {
    "iso:country":"GB",
    "wof:name":"B37 7HP",
    "wof:placetype":"postalcode"
},
  "geometry": {"coordinates":[-1.72961551850916,52.46895581186552],"type":"Point"}
}