{
  "type": "Feature",
  "properties": {
    "iso:country": "GB",
    "wof:name": "B37 7HP",
    "wof:placetype": "postalcode"
  },
  "geometry": {"coordinates":[-1.729615,52.468956],"type":"Point"}
}
