{
  "type": "Feature",
  "properties": {
    "date:inception_lower": "2006-10-01",
    "date:inception_upper": "2006-10-01",
    "iso:country": "GB",
    "wof:name": "NN18 9JT",
    "wof:placetype": "postalcode"
  },
  "geometry": {"coordinates":[-0.713865,52.478027],"type":"Point"}
}
