{
  "type": "Feature",
  "properties": {
    "iso:country": "GB",
    "wof:name": "GU15 2RR",
    "wof:placetype": "postalcode"
  },
  "geometry": {"coordinates":[-0.753516,51.31889],"type":"Point"}
}
