{
  "type": "Feature",
  "properties": {
    "date:inception_lower": "1992-08-01",
    "date:inception_upper": "1992-08-01",
    "iso:country": "GB",
    "wof:name": "CO6 2PZ",
    "wof:placetype": "postalcode"
  },
  "geometry": {"coordinates":[0.700558,51.927258],"type":"Point"}
}
