{
  "type": "Feature",
  "properties": {
    "iso:country":"GB",
    "wof:name":"PO21 5EN",
    "wof:placetype":"postalcode"
},
  "geometry": {"coordinates":[-0.69502354244354,50.80317293570204],"type":"Point"}
}