{
  "type": "Feature",
  "properties": {
    "iso:country": "GB",
    "wof:name": "PO21 5EN",
    "wof:placetype": "postalcode"
  },
  "geometry": {"coordinates":[-0.695024,50.803173],"type":"Point"}
}
