{
  "type": "Feature",
  "properties": {
    "date:inception_lower": "2012-05-01",
    "date:inception_upper": "2012-05-01",
    "iso:country": "GB",
    "wof:name": "PO21 5EN",
    "wof:placetype": "postalcode"
  },
  "geometry": {"coordinates":[-0.695024,50.803173],"type":"Point"}
}
