{
  "type": "Feature",
  "properties": {
    "date:inception_lower": "1980-01-01",
    "date:inception_upper": "1980-01-01",
    "iso:country": "GB",
    "wof:name": "NN12 8PX",
    "wof:placetype": "postalcode"
  },
  "geometry": {"coordinates":[-1.140735,52.117143],"type":"Point"}
}
