{
  "type": "Feature",
  "properties": {
    "iso:country":"GB",
    "wof:name":"W1D 3AF",
    "wof:placetype":"postalcode"
},
  "geometry": {"coordinates":[-0.13239856811776,51.51396507057875],"type":"Point"}
}