{
  "type": "Feature",
  "properties": {
    "iso:country":"GB",
    "wof:name":"IV2 5BU",
    "wof:placetype":"postalcode"
},
  "geometry": {"coordinates":[-4.12329155243266,57.46121519139823],"type":"Point"}
}