{
  "type": "Feature",
  "properties": {
    "date:inception_lower": "1998-12-01",
    "date:inception_upper": "1998-12-01",
    "iso:country": "GB",
    "wof:name": "IV2 5BU",
    "wof:placetype": "postalcode"
  },
  "geometry": {"coordinates":[-4.123291,57.461215],"type":"Point"}
}
