{
  "type": "Feature",
  "properties": {
    "iso:country": "GB",
    "wof:name": "ST17 4AA",
    "wof:placetype": "postalcode"
  },
  "geometry": {"coordinates":[-2.116214,52.802687],"type":"Point"}
}
