{
  "type": "Feature",
  "properties": {
    "iso:country": "GB",
    "wof:name": "SO16 5JS",
    "wof:placetype": "postalcode"
  },
  "geometry": {"coordinates":[-1.429982,50.938732],"type":"Point"}
}
