{
  "type": "Feature",
  "properties": {
    "date:inception_lower":"1994-12-01",
    "date:inception_upper":"1994-12-31",
    "iso:country":"GB",
    "wof:name":"SO16 5JS",
    "wof:placetype":"postalcode"
},
  "geometry": {"coordinates":[-1.429982,50.938732],"type":"Point"}
}