{
  "type": "Feature",
  "properties": {
    "date:inception_lower": "1980-01-01",
    "date:inception_upper": "1980-01-01",
    "iso:country": "GB",
    "wof:name": "CA14 1ES",
    "wof:placetype": "postalcode"
  },
  "geometry": {"coordinates":[-3.530463,54.657808],"type":"Point"}
}
