{
  "type": "Feature",
  "properties": {
    "iso:country": "GB",
    "wof:name": "CA14 1ES",
    "wof:placetype": "postalcode"
  },
  "geometry": {"coordinates":[-3.530463,54.657808],"type":"Point"}
}
