{
  "type": "Feature",
  "properties": {
    "iso:country":"GB",
    "wof:name":"CF3 2ET",
    "wof:placetype":"postalcode"
},
  "geometry": {"coordinates":[-3.12413076273017,51.50031322216995],"type":"Point"}
}