{
  "type": "Feature",
  "properties": {
    "date:inception_lower": "2008-05-01",
    "date:inception_upper": "2008-05-01",
    "iso:country": "GB",
    "wof:name": "CF3 2ET",
    "wof:placetype": "postalcode"
  },
  "geometry": {"coordinates":[-3.124131,51.500313],"type":"Point"}
}
