{
  "type": "Feature",
  "properties": {
    "iso:country":"GB",
    "wof:name":"PE13 1HB",
    "wof:placetype":"postalcode"
},
  "geometry": {"coordinates":[0.16004842136742,52.66453883583685],"type":"Point"}
}