{
  "type": "Feature",
  "properties": {
    "iso:country":"GB",
    "wof:name":"NW6 1BH",
    "wof:placetype":"postalcode"
},
  "geometry": {"coordinates":[-0.1944443329392,51.55110410961136],"type":"Point"}
}