{
  "type": "Feature",
  "properties": {
    "iso:country": "GB",
    "wof:name": "DE7 5HG",
    "wof:placetype": "postalcode"
  },
  "geometry": {"coordinates":[-1.312178,52.97214],"type":"Point"}
}
