{
  "type": "Feature",
  "properties": {
    "iso:country":"GB",
    "wof:name":"DE7 5HG",
    "wof:placetype":"postalcode"
},
  "geometry": {"coordinates":[-1.31217779718246,52.97214026463794],"type":"Point"}
}