{
  "type": "Feature",
  "properties": {
    "iso:country": "GB",
    "wof:name": "CO5 7EE",
    "wof:placetype": "postalcode"
  },
  "geometry": {"coordinates":[0.947153,51.855954],"type":"Point"}
}
