{
  "type": "Feature",
  "properties": {
    "date:inception_lower":"1996-12-01",
    "date:inception_upper":"1996-12-31",
    "iso:country":"GB",
    "wof:name":"CO5 7EE",
    "wof:placetype":"postalcode"
},
  "geometry": {"coordinates":[0.947153,51.855954],"type":"Point"}
}