{
  "type": "Feature",
  "properties": {
    "iso:country":"GB",
    "wof:name":"CO5 7EE",
    "wof:placetype":"postalcode"
},
  "geometry": {"coordinates":[0.94715307487205,51.85595398288064],"type":"Point"}
}