{
  "type": "Feature",
  "properties": {
    "iso:country":"GB",
    "wof:name":"BA14 9DW",
    "wof:placetype":"postalcode"
},
  "geometry": {"coordinates":[-2.22677218286682,51.31914051732944],"type":"Point"}
}