{
  "type": "Feature",
  "properties": {
    "iso:country":"GB",
    "wof:name":"NE47 9PY",
    "wof:placetype":"postalcode"
},
  "geometry": {"coordinates":[-2.25671652510146,54.90500839538135],"type":"Point"}
}