{
  "type": "Feature",
  "properties": {
    "date:inception_lower": "1980-01-01",
    "date:inception_upper": "1980-01-01",
    "iso:country": "GB",
    "wof:name": "DN7 6NA",
    "wof:placetype": "postalcode"
  },
  "geometry": {"coordinates":[-0.98577,53.571871],"type":"Point"}
}
