{
  "type": "Feature",
  "properties": {
    "iso:country":"GB",
    "wof:name":"DN7 6NA",
    "wof:placetype":"postalcode"
},
  "geometry": {"coordinates":[-0.98577037306736,53.57187072263383],"type":"Point"}
}