{
  "type": "Feature",
  "properties": {
    "iso:country":"GB",
    "wof:name":"SN12 7PH",
    "wof:placetype":"postalcode"
},
  "geometry": {"coordinates":[-2.13373795985273,51.37097723350225],"type":"Point"}
}