{
  "type": "Feature",
  "properties": {
    "date:inception_lower": "2017-10-01",
    "date:inception_upper": "2017-10-01",
    "iso:country": "GB",
    "wof:name": "E17 6GZ",
    "wof:placetype": "postalcode"
  },
  "geometry": {"coordinates":[-0.0393,51.59241],"type":"Point"}
}
