{
  "type": "Feature",
  "properties": {
    "iso:country":"GB",
    "wof:name":"TD5 7RG",
    "wof:placetype":"postalcode"
},
  "geometry": {"coordinates":[-2.41644224170745,55.62932772058058],"type":"Point"}
}