{
  "type": "Feature",
  "properties": {
    "iso:country":"GB",
    "wof:name":"NW6 1JE",
    "wof:placetype":"postalcode"
},
  "geometry": {"coordinates":[-0.19060644944132,51.55222298960174],"type":"Point"}
}