{
  "type": "Feature",
  "properties": {
    "iso:country": "GB",
    "wof:name": "BA21 3RS",
    "wof:placetype": "postalcode"
  },
  "geometry": {"coordinates":[-2.659913,50.946313],"type":"Point"}
}
