{
  "type": "Feature",
  "properties": {
    "iso:country":"GB",
    "wof:name":"BA21 3RS",
    "wof:placetype":"postalcode"
},
  "geometry": {"coordinates":[-2.65991318292404,50.94631268900167],"type":"Point"}
}