{
  "type": "Feature",
  "properties": {
    "iso:country": "GB",
    "wof:name": "SW11 6RA",
    "wof:placetype": "postalcode"
  },
  "geometry": {"coordinates":[-0.166515,51.45536],"type":"Point"}
}
