{
  "type": "Feature",
  "properties": {
    "date:inception_lower": "1980-01-01",
    "date:inception_upper": "1980-01-01",
    "iso:country": "GB",
    "wof:name": "SW11 6RA",
    "wof:placetype": "postalcode"
  },
  "geometry": {"coordinates":[-0.166476,51.45536],"type":"Point"}
}
