{
  "type": "Feature",
  "properties": {
    "iso:country":"GB",
    "wof:name":"HU17 0LN",
    "wof:placetype":"postalcode"
},
  "geometry": {"coordinates":[-0.41127614924898,53.84950642200875],"type":"Point"}
}