{
  "type": "Feature",
  "properties": {
    "iso:country":"GB",
    "wof:name":"LA5 9BN",
    "wof:placetype":"postalcode"
},
  "geometry": {"coordinates":[-2.76839247896576,54.13002710541893],"type":"Point"}
}