{
  "type": "Feature",
  "properties": {
    "iso:country": "GB",
    "wof:name": "LA5 9BN",
    "wof:placetype": "postalcode"
  },
  "geometry": {"coordinates":[-2.768392,54.130027],"type":"Point"}
}
