{
  "type": "Feature",
  "properties": {
    "iso:country":"GB",
    "wof:name":"E4 6UH",
    "wof:placetype":"postalcode"
},
  "geometry": {"coordinates":[-0.00247481126804,51.63105700893021],"type":"Point"}
}