{
  "type": "Feature",
  "properties": {
    "date:inception_lower":"1982-03-01",
    "date:inception_upper":"1982-03-31",
    "iso:country":"GB",
    "wof:name":"E4 6UH",
    "wof:placetype":"postalcode"
},
  "geometry": {"coordinates":[-0.002475,51.631057],"type":"Point"}
}