{
  "type": "Feature",
  "properties": {
    "iso:country": "GB",
    "wof:name": "NR3 4RX",
    "wof:placetype": "postalcode"
  },
  "geometry": {"coordinates":[1.310809,52.641017],"type":"Point"}
}
