{
  "type": "Feature",
  "properties": {
    "iso:country": "GB",
    "wof:name": "MK14 7DS",
    "wof:placetype": "postalcode"
  },
  "geometry": {"coordinates":[-0.758469,52.052365],"type":"Point"}
}
