{
  "type": "Feature",
  "properties": {
    "iso:country":"GB",
    "wof:name":"TQ5 0JD",
    "wof:placetype":"postalcode"
},
  "geometry": {"coordinates":[-3.54447356301837,50.39495840157173],"type":"Point"}
}