{
  "type": "Feature",
  "properties": {
    "iso:country":"GB",
    "wof:name":"SS16 5XA",
    "wof:placetype":"postalcode"
},
  "geometry": {"coordinates":[0.42395314321254,51.56555032838706],"type":"Point"}
}