{
  "type": "Feature",
  "properties": {
    "date:inception_lower": "1983-03-01",
    "date:inception_upper": "1983-03-01",
    "iso:country": "GB",
    "wof:name": "SS16 5XA",
    "wof:placetype": "postalcode"
  },
  "geometry": {"coordinates":[0.423953,51.56555],"type":"Point"}
}
