{
  "type": "Feature",
  "properties": {
    "iso:country":"GB",
    "wof:name":"NE16 6JS",
    "wof:placetype":"postalcode"
},
  "geometry": {"coordinates":[-1.74261369841305,54.90254583121196],"type":"Point"}
}