{
  "type": "Feature",
  "properties": {
    "date:inception_lower": "1980-01-01",
    "date:inception_upper": "1980-01-01",
    "iso:country": "GB",
    "wof:name": "NE16 6JS",
    "wof:placetype": "postalcode"
  },
  "geometry": {"coordinates":[-1.742614,54.902546],"type":"Point"}
}
