{
  "type": "Feature",
  "properties": {
    "iso:country": "GB",
    "wof:name": "NE65 0FG",
    "wof:placetype": "postalcode"
  },
  "geometry": {"coordinates":[-1.585463,55.331603],"type":"Point"}
}
