{
  "type": "Feature",
  "properties": {
    "date:inception_lower":"1980-01-01",
    "date:inception_upper":"1980-01-31",
    "iso:country":"GB",
    "wof:name":"BB3 3AR",
    "wof:placetype":"postalcode"
},
  "geometry": {"coordinates":[-2.457421,53.703007],"type":"Point"}
}