{
  "type": "Feature",
  "properties": {
    "iso:country": "GB",
    "wof:name": "BB3 3AR",
    "wof:placetype": "postalcode"
  },
  "geometry": {"coordinates":[-2.457421,53.703007],"type":"Point"}
}
