{
  "type": "Feature",
  "properties": {
    "date:inception_lower": "1980-01-01",
    "date:inception_upper": "1980-01-01",
    "iso:country": "GB",
    "wof:name": "SW16 6JG",
    "wof:placetype": "postalcode"
  },
  "geometry": {"coordinates":[-0.132374,51.42394],"type":"Point"}
}
