{
  "type": "Feature",
  "properties": {
    "iso:country":"GB",
    "wof:name":"NE2 3LB",
    "wof:placetype":"postalcode"
},
  "geometry": {"coordinates":[-1.61114815323768,54.99679533548761],"type":"Point"}
}