{
  "type": "Feature",
  "properties": {
    "iso:country":"GB",
    "wof:name":"HX3 7SD",
    "wof:placetype":"postalcode"
},
  "geometry": {"coordinates":[-1.81638400568868,53.73900094830697],"type":"Point"}
}