{
  "type": "Feature",
  "properties": {
    "date:inception_lower": "2016-06-01",
    "date:inception_upper": "2016-06-01",
    "iso:country": "GB",
    "wof:name": "LE7 7LW",
    "wof:placetype": "postalcode"
  },
  "geometry": {"coordinates":[-1.1985,52.669187],"type":"Point"}
}
