{
  "type": "Feature",
  "properties": {
    "iso:country":"GB",
    "wof:name":"LU6 3BW",
    "wof:placetype":"postalcode"
},
  "geometry": {"coordinates":[-0.51739016836349,51.87866938766525],"type":"Point"}
}