{
  "type": "Feature",
  "properties": {
    "iso:country": "GB",
    "wof:name": "LU6 3BW",
    "wof:placetype": "postalcode"
  },
  "geometry": {"coordinates":[-0.51739,51.878669],"type":"Point"}
}
