{
  "type": "Feature",
  "properties": {
    "iso:country":"GB",
    "wof:name":"IP32 6BH",
    "wof:placetype":"postalcode"
},
  "geometry": {"coordinates":[0.71420554996099,52.25192443914629],"type":"Point"}
}