{
  "type": "Feature",
  "properties": {
    "iso:country":"GB",
    "wof:name":"PE14 7NW",
    "wof:placetype":"postalcode"
},
  "geometry": {"coordinates":[0.21771316752342,52.72648532816189],"type":"Point"}
}