{
  "type": "Feature",
  "properties": {
    "date:inception_lower":"1980-01-01",
    "date:inception_upper":"1980-01-31",
    "iso:country":"GB",
    "wof:name":"PE22 0RJ",
    "wof:placetype":"postalcode"
},
  "geometry": {"coordinates":[0.003263,53.007536],"type":"Point"}
}