{
  "type": "Feature",
  "properties": {
    "iso:country": "GB",
    "wof:name": "PE22 0RJ",
    "wof:placetype": "postalcode"
  },
  "geometry": {"coordinates":[0.003263,53.007536],"type":"Point"}
}
