{
  "type": "Feature",
  "properties": {
    "iso:country":"GB",
    "wof:name":"PE22 0RJ",
    "wof:placetype":"postalcode"
},
  "geometry": {"coordinates":[0.00326300506175,53.00753563325871],"type":"Point"}
}