{
  "type": "Feature",
  "properties": {
    "iso:country":"GB",
    "wof:name":"IP2 9SG",
    "wof:placetype":"postalcode"
},
  "geometry": {"coordinates":[1.14319857217835,52.0445435058915],"type":"Point"}
}