{
  "type": "Feature",
  "properties": {
    "iso:country":"GB",
    "wof:name":"IP29 4EH",
    "wof:placetype":"postalcode"
},
  "geometry": {"coordinates":[0.6760303397431,52.14321887330696],"type":"Point"}
}