{
  "type": "Feature",
  "properties": {
    "iso:country": "GB",
    "wof:name": "IP29 4EH",
    "wof:placetype": "postalcode"
  },
  "geometry": {"coordinates":[0.67606,52.143234],"type":"Point"}
}
