{
  "type": "Feature",
  "properties": {
    "iso:country": "GB",
    "wof:name": "IP29 4EH",
    "wof:placetype": "postalcode"
  },
  "geometry": {"coordinates":[0.675414,52.142952],"type":"Point"}
}
