{
  "type": "Feature",
  "properties": {
    "iso:country":"GB",
    "wof:name":"CR0 3BG",
    "wof:placetype":"postalcode"
},
  "geometry": {"coordinates":[-0.12233122465949,51.38681063550145],"type":"Point"}
}