{
  "type": "Feature",
  "properties": {
    "iso:country":"GB",
    "wof:name":"RM16 6RD",
    "wof:placetype":"postalcode"
},
  "geometry": {"coordinates":[0.31822834082252,51.49378216152742],"type":"Point"}
}