{
  "type": "Feature",
  "properties": {
    "date:inception_lower":"2011-07-01",
    "date:inception_upper":"2011-07-31",
    "iso:country":"GB",
    "wof:name":"KA21 5PD",
    "wof:placetype":"postalcode"
},
  "geometry": {"coordinates":[-4.778044,55.634984],"type":"Point"}
}