{
  "type": "Feature",
  "properties": {
    "iso:country":"GB",
    "wof:name":"KA21 5PD",
    "wof:placetype":"postalcode"
},
  "geometry": {"coordinates":[-4.77804403317645,55.63498426493104],"type":"Point"}
}