{
  "type": "Feature",
  "properties": {
    "iso:country": "GB",
    "wof:name": "KA21 5PD",
    "wof:placetype": "postalcode"
  },
  "geometry": {"coordinates":[-4.778044,55.634984],"type":"Point"}
}
