{
  "type": "Feature",
  "properties": {
    "iso:country":"GB",
    "wof:name":"SN5 5AU",
    "wof:placetype":"postalcode"
},
  "geometry": {"coordinates":[-1.83978562903689,51.57762356803305],"type":"Point"}
}