{
  "type": "Feature",
  "properties": {
    "iso:country": "GB",
    "wof:name": "NP19 7JH",
    "wof:placetype": "postalcode"
  },
  "geometry": {"coordinates":[-2.982989,51.603421],"type":"Point"}
}
