{
  "type": "Feature",
  "properties": {
    "iso:country":"GB",
    "wof:name":"NP19 7JH",
    "wof:placetype":"postalcode"
},
  "geometry": {"coordinates":[-2.98298923475928,51.60342115816462],"type":"Point"}
}