{
  "type": "Feature",
  "properties": {
    "date:inception_lower":"1980-01-01",
    "date:inception_upper":"1980-01-31",
    "iso:country":"GB",
    "wof:name":"RG14 7UN",
    "wof:placetype":"postalcode"
},
  "geometry": {"coordinates":[-1.31695,51.388208],"type":"Point"}
}