{
  "type": "Feature",
  "properties": {
    "iso:country":"GB",
    "wof:name":"IP26 4EU",
    "wof:placetype":"postalcode"
},
  "geometry": {"coordinates":[0.51799190711098,52.48424819053204],"type":"Point"}
}