{
  "type": "Feature",
  "properties": {
    "iso:country": "GB",
    "wof:name": "IP26 4EU",
    "wof:placetype": "postalcode"
  },
  "geometry": {"coordinates":[0.517992,52.484248],"type":"Point"}
}
