{
  "type": "Feature",
  "properties": {
    "iso:country":"GB",
    "wof:name":"BH25 5WH",
    "wof:placetype":"postalcode"
},
  "geometry": {"coordinates":[-1.66201674122241,50.7901152082131],"type":"Point"}
}