{
  "type": "Feature",
  "properties": {
    "date:inception_lower": "1999-06-01",
    "date:inception_upper": "1999-06-01",
    "iso:country": "GB",
    "wof:name": "BH25 5WH",
    "wof:placetype": "postalcode"
  },
  "geometry": {"coordinates":[-1.662151,50.790205],"type":"Point"}
}
