{
  "type": "Feature",
  "properties": {
    "iso:country":"GB",
    "wof:name":"PO30 5ZB",
    "wof:placetype":"postalcode"
},
  "geometry": {"coordinates":[-1.300305311341,50.70165515028854],"type":"Point"}
}