{
  "type": "Feature",
  "properties": {
    "date:inception_lower": "1980-01-01",
    "date:inception_upper": "1980-01-01",
    "iso:country": "GB",
    "wof:name": "OL1 1QU",
    "wof:placetype": "postalcode"
  },
  "geometry": {"coordinates":[-2.110418,53.54177],"type":"Point"}
}
