{
  "type": "Feature",
  "properties": {
    "iso:country": "GB",
    "wof:name": "OL1 1QU",
    "wof:placetype": "postalcode"
  },
  "geometry": {"coordinates":[-2.110463,53.541671],"type":"Point"}
}
