{
  "type": "Feature",
  "properties": {
    "iso:country": "GB",
    "wof:name": "PA16 0HN",
    "wof:placetype": "postalcode"
  },
  "geometry": {"coordinates":[-4.827116,55.941368],"type":"Point"}
}
