{
  "type": "Feature",
  "properties": {
    "date:inception_lower": "2018-04-01",
    "date:inception_upper": "2018-04-01",
    "iso:country": "GB",
    "wof:name": "FK2 8SU",
    "wof:placetype": "postalcode"
  },
  "geometry": {"coordinates":[-3.811874,56.041405],"type":"Point"}
}
