{
  "type": "Feature",
  "properties": {
    "date:inception_lower":"2004-11-01",
    "date:inception_upper":"2004-11-30",
    "iso:country":"GB",
    "wof:name":"CT11 9HN",
    "wof:placetype":"postalcode"
},
  "geometry": {"coordinates":[1.416748,51.334413],"type":"Point"}
}