{
  "type": "Feature",
  "properties": {
    "date:inception_lower": "1980-01-01",
    "date:inception_upper": "1980-01-01",
    "iso:country": "GB",
    "wof:name": "GL52 6RQ",
    "wof:placetype": "postalcode"
  },
  "geometry": {"coordinates":[-2.059226,51.892406],"type":"Point"}
}
