{
  "type": "Feature",
  "properties": {
    "iso:country":"GB",
    "wof:name":"OL2 6LW",
    "wof:placetype":"postalcode"
},
  "geometry": {"coordinates":[-2.10354668290044,53.56335932207207],"type":"Point"}
}