{
  "type": "Feature",
  "properties": {
    "iso:country": "GB",
    "wof:name": "OL2 6LW",
    "wof:placetype": "postalcode"
  },
  "geometry": {"coordinates":[-2.103544,53.563376],"type":"Point"}
}
