{
  "type": "Feature",
  "properties": {
    "iso:country":"GB",
    "wof:name":"SA19 8LY",
    "wof:placetype":"postalcode"
},
  "geometry": {"coordinates":[-3.92960472386793,51.96898703514693],"type":"Point"}
}