{
  "type": "Feature",
  "properties": {
    "date:inception_lower": "2017-04-01",
    "date:inception_upper": "2017-04-01",
    "iso:country": "GB",
    "wof:name": "EH6 5FN",
    "wof:placetype": "postalcode"
  },
  "geometry": {"coordinates":[-3.178177,55.970489],"type":"Point"}
}
