{
  "type": "Feature",
  "properties": {
    "iso:country":"GB",
    "wof:name":"ME19 4HY",
    "wof:placetype":"postalcode"
},
  "geometry": {"coordinates":[0.39918463744493,51.27130293471627],"type":"Point"}
}