{
  "type": "Feature",
  "properties": {
    "date:inception_lower": "2002-07-01",
    "date:inception_upper": "2002-07-01",
    "iso:country": "GB",
    "wof:name": "ME19 4HY",
    "wof:placetype": "postalcode"
  },
  "geometry": {"coordinates":[0.399185,51.271303],"type":"Point"}
}
