{
  "type": "Feature",
  "properties": {
    "iso:country":"GB",
    "wof:name":"RG29 1SY",
    "wof:placetype":"postalcode"
},
  "geometry": {"coordinates":[-0.94484889186993,51.21726091602321],"type":"Point"}
}