{
  "type": "Feature",
  "properties": {
    "iso:country": "GB",
    "wof:name": "RG29 1SY",
    "wof:placetype": "postalcode"
  },
  "geometry": {"coordinates":[-0.944849,51.217261],"type":"Point"}
}
