{
  "type": "Feature",
  "properties": {
    "date:inception_lower": "1980-01-01",
    "date:inception_upper": "1980-01-01",
    "iso:country": "GB",
    "wof:name": "PR2 6SD",
    "wof:placetype": "postalcode"
  },
  "geometry": {"coordinates":[-2.663392,53.783287],"type":"Point"}
}
