{
  "type": "Feature",
  "properties": {
    "iso:country":"GB",
    "wof:name":"PR2 6SD",
    "wof:placetype":"postalcode"
},
  "geometry": {"coordinates":[-2.66339162319669,53.78328737096854],"type":"Point"}
}