{
  "type": "Feature",
  "properties": {
    "date:inception_lower": "1992-01-01",
    "date:inception_upper": "1992-01-01",
    "iso:country": "GB",
    "wof:name": "WR9 7SY",
    "wof:placetype": "postalcode"
  },
  "geometry": {"coordinates":[-2.140331,52.256474],"type":"Point"}
}
