{
  "type": "Feature",
  "properties": {
    "iso:country":"GB",
    "wof:name":"WR9 7SY",
    "wof:placetype":"postalcode"
},
  "geometry": {"coordinates":[-2.14033112754252,52.25647383939746],"type":"Point"}
}