{
  "type": "Feature",
  "properties": {
    "iso:country": "GB",
    "wof:name": "L25 2RR",
    "wof:placetype": "postalcode"
  },
  "geometry": {"coordinates":[-2.866603,53.390996],"type":"Point"}
}
