{
  "type": "Feature",
  "properties": {
    "iso:country":"GB",
    "wof:name":"UB8 2NS",
    "wof:placetype":"postalcode"
},
  "geometry": {"coordinates":[-0.48112956403583,51.5315970184496],"type":"Point"}
}