{
  "type": "Feature",
  "properties": {
    "iso:country": "GB",
    "wof:name": "UB8 2NS",
    "wof:placetype": "postalcode"
  },
  "geometry": {"coordinates":[-0.48113,51.531597],"type":"Point"}
}
