{
  "type": "Feature",
  "properties": {
    "date:inception_lower": "1980-01-01",
    "date:inception_upper": "1980-01-01",
    "iso:country": "GB",
    "wof:name": "SO22 5NR",
    "wof:placetype": "postalcode"
  },
  "geometry": {"coordinates":[-1.348929,51.070208],"type":"Point"}
}
