{
  "type": "Feature",
  "properties": {
    "iso:country":"GB",
    "wof:name":"SO22 5NR",
    "wof:placetype":"postalcode"
},
  "geometry": {"coordinates":[-1.34892895106947,51.07020786516509],"type":"Point"}
}