{
  "type": "Feature",
  "properties": {
    "iso:country":"GB",
    "wof:name":"IG3 9SA",
    "wof:placetype":"postalcode"
},
  "geometry": {"coordinates":[0.11351546323167,51.56175156542789],"type":"Point"}
}