{
  "type": "Feature",
  "properties": {
    "iso:country": "GB",
    "wof:name": "CR0 4SW",
    "wof:placetype": "postalcode"
  },
  "geometry": {"coordinates":[-0.127448,51.370957],"type":"Point"}
}
