{
  "type": "Feature",
  "properties": {
    "iso:country":"GB",
    "wof:name":"CR0 4SW",
    "wof:placetype":"postalcode"
},
  "geometry": {"coordinates":[-0.12744809541616,51.37095744742995],"type":"Point"}
}