{
  "type": "Feature",
  "properties": {
    "date:inception_lower": "2002-07-01",
    "date:inception_upper": "2002-07-01",
    "iso:country": "GB",
    "wof:name": "G77 6FD",
    "wof:placetype": "postalcode"
  },
  "geometry": {"coordinates":[-4.347545,55.771969],"type":"Point"}
}
