{
  "type": "Feature",
  "properties": {
    "iso:country":"GB",
    "wof:name":"BS1 4QA",
    "wof:placetype":"postalcode"
},
  "geometry": {"coordinates":[-2.5970950207447,51.44975522907021],"type":"Point"}
}