{
  "type": "Feature",
  "properties": {
    "iso:country": "GB",
    "wof:name": "BS1 4QA",
    "wof:placetype": "postalcode"
  },
  "geometry": {"coordinates":[-2.597271,51.449896],"type":"Point"}
}
