{
  "type": "Feature",
  "properties": {
    "iso:country":"GB",
    "wof:name":"BS3 4RP",
    "wof:placetype":"postalcode"
},
  "geometry": {"coordinates":[-2.58244080607229,51.44486558416571],"type":"Point"}
}