{
  "type": "Feature",
  "properties": {
    "iso:country": "GB",
    "wof:name": "YO32 9YL",
    "wof:placetype": "postalcode"
  },
  "geometry": {"coordinates":[-1.06604,53.988603],"type":"Point"}
}
