{
  "type": "Feature",
  "properties": {
    "date:inception_lower": "1980-01-01",
    "date:inception_upper": "1980-01-01",
    "iso:country": "GB",
    "wof:name": "LA12 8QW",
    "wof:placetype": "postalcode"
  },
  "geometry": {"coordinates":[-2.986735,54.25323],"type":"Point"}
}
