{
  "type": "Feature",
  "properties": {
    "iso:country":"GB",
    "wof:name":"LA12 8QW",
    "wof:placetype":"postalcode"
},
  "geometry": {"coordinates":[-2.98671978749182,54.25323040555945],"type":"Point"}
}