{
  "type": "Feature",
  "properties": {
    "date:inception_lower": "1981-06-01",
    "date:inception_upper": "1981-06-01",
    "iso:country": "GB",
    "wof:name": "BD7 3JZ",
    "wof:placetype": "postalcode"
  },
  "geometry": {"coordinates":[-1.779708,53.78064],"type":"Point"}
}
