{
  "type": "Feature",
  "properties": {
    "iso:country":"GB",
    "wof:name":"BD7 3JZ",
    "wof:placetype":"postalcode"
},
  "geometry": {"coordinates":[-1.77962980032931,53.78058064182918],"type":"Point"}
}