{
  "type": "Feature",
  "properties": {
    "iso:country":"GB",
    "wof:name":"TQ12 4HQ",
    "wof:placetype":"postalcode"
},
  "geometry": {"coordinates":[-3.58653982190053,50.53088081082731],"type":"Point"}
}