{
  "type": "Feature",
  "properties": {
    "date:inception_lower": "1980-01-01",
    "date:inception_upper": "1980-01-01",
    "iso:country": "GB",
    "wof:name": "TQ12 4HQ",
    "wof:placetype": "postalcode"
  },
  "geometry": {"coordinates":[-3.58654,50.530881],"type":"Point"}
}
