{
  "type": "Feature",
  "properties": {
    "date:inception_lower": "1980-01-01",
    "date:inception_upper": "1980-01-01",
    "iso:country": "GB",
    "wof:name": "SA72 6XT",
    "wof:placetype": "postalcode"
  },
  "geometry": {"coordinates":[-4.951096,51.69183],"type":"Point"}
}
