{
  "type": "Feature",
  "properties": {
    "date:inception_lower": "1980-01-01",
    "date:inception_upper": "1980-01-01",
    "iso:country": "GB",
    "wof:name": "DA1 2SU",
    "wof:placetype": "postalcode"
  },
  "geometry": {"coordinates":[0.209078,51.433191],"type":"Point"}
}
