{
  "type": "Feature",
  "properties": {
    "iso:country":"GB",
    "wof:name":"DA1 2SU",
    "wof:placetype":"postalcode"
},
  "geometry": {"coordinates":[0.20905037547116,51.43319074130029],"type":"Point"}
}