{
  "type": "Feature",
  "properties": {
    "iso:country": "GB",
    "wof:name": "DA1 2SU",
    "wof:placetype": "postalcode"
  },
  "geometry": {"coordinates":[0.209154,51.433271],"type":"Point"}
}
