{
  "type": "Feature",
  "properties": {
    "iso:country":"GB",
    "wof:name":"TS26 8RD",
    "wof:placetype":"postalcode"
},
  "geometry": {"coordinates":[-1.22025124051003,54.69010008186739],"type":"Point"}
}