{
  "type": "Feature",
  "properties": {
    "iso:country": "GB",
    "wof:name": "SY3 9FG",
    "wof:placetype": "postalcode"
  },
  "geometry": {"coordinates":[-2.787808,52.698345],"type":"Point"}
}
