{
  "type": "Feature",
  "properties": {
    "date:inception_lower": "2016-05-01",
    "date:inception_upper": "2016-05-01",
    "iso:country": "GB",
    "wof:name": "SY3 9FG",
    "wof:placetype": "postalcode"
  },
  "geometry": {"coordinates":[-2.787808,52.698345],"type":"Point"}
}
