{
  "type": "Feature",
  "properties": {
    "date:inception_lower": "1992-01-01",
    "date:inception_upper": "1992-01-01",
    "iso:country": "GB",
    "wof:name": "EC1A 9PN",
    "wof:placetype": "postalcode"
  },
  "geometry": {"coordinates":[-0.098967,51.519788],"type":"Point"}
}
