{
  "type": "Feature",
  "properties": {
    "date:inception_lower": "2016-08-01",
    "date:inception_upper": "2016-08-01",
    "iso:country": "GB",
    "wof:name": "NN17 3LZ",
    "wof:placetype": "postalcode"
  },
  "geometry": {"coordinates":[-0.623955,52.493683],"type":"Point"}
}
