{
  "type": "Feature",
  "properties": {
    "iso:country":"GB",
    "wof:name":"AL8 6ED",
    "wof:placetype":"postalcode"
},
  "geometry": {"coordinates":[-0.20817510415726,51.79958038668496],"type":"Point"}
}