{
  "type": "Feature",
  "properties": {
    "iso:country":"GB",
    "wof:name":"BN27 2AU",
    "wof:placetype":"postalcode"
},
  "geometry": {"coordinates":[0.25703722731637,50.86183728909136],"type":"Point"}
}