{
  "type": "Feature",
  "properties": {
    "iso:country": "GB",
    "wof:name": "LE15 9EA",
    "wof:placetype": "postalcode"
  },
  "geometry": {"coordinates":[-0.735324,52.592895],"type":"Point"}
}
