{
  "type": "Feature",
  "properties": {
    "iso:country":"GB",
    "wof:name":"B1 3BN",
    "wof:placetype":"postalcode"
},
  "geometry": {"coordinates":[-1.913121588237,52.48336471125544],"type":"Point"}
}