{
  "type": "Feature",
  "properties": {
    "date:inception_lower":"2015-12-01",
    "date:inception_upper":"2015-12-31",
    "iso:country":"GB",
    "wof:name":"LS16 8FX",
    "wof:placetype":"postalcode"
},
  "geometry": {"coordinates":[-1.587548,53.844491],"type":"Point"}
}