{
  "type": "Feature",
  "properties": {
    "date:inception_lower": "2018-01-01",
    "date:inception_upper": "2018-01-01",
    "iso:country": "GB",
    "wof:name": "DT4 0TW",
    "wof:placetype": "postalcode"
  },
  "geometry": {"coordinates":[-2.481057,50.608117],"type":"Point"}
}
