{
  "type": "Feature",
  "properties": {
    "iso:country":"GB",
    "wof:name":"RM12 5EU",
    "wof:placetype":"postalcode"
},
  "geometry": {"coordinates":[0.20057255204452,51.54498890718898],"type":"Point"}
}