{
  "type": "Feature",
  "properties": {
    "iso:country":"GB",
    "wof:name":"SY8 3DX",
    "wof:placetype":"postalcode"
},
  "geometry": {"coordinates":[-2.69519491130439,52.40941305009901],"type":"Point"}
}