{
  "type": "Feature",
  "properties": {
    "date:inception_lower":"1980-01-01",
    "date:inception_upper":"1980-01-31",
    "iso:country":"GB",
    "wof:name":"SY8 3DX",
    "wof:placetype":"postalcode"
},
  "geometry": {"coordinates":[-2.695194,52.409436],"type":"Point"}
}