{
  "type": "Feature",
  "properties": {
    "iso:country": "GB",
    "wof:name": "SY8 3DX",
    "wof:placetype": "postalcode"
  },
  "geometry": {"coordinates":[-2.695194,52.409436],"type":"Point"}
}
