{
  "type": "Feature",
  "properties": {
    "iso:country":"GB",
    "wof:name":"LE15 8AQ",
    "wof:placetype":"postalcode"
},
  "geometry": {"coordinates":[-0.60045237530184,52.59040725133666],"type":"Point"}
}