{
  "type": "Feature",
  "properties": {
    "iso:country":"GB",
    "wof:name":"ST5 5BX",
    "wof:placetype":"postalcode"
},
  "geometry": {"coordinates":[-2.26854562508569,53.00353392270431],"type":"Point"}
}