{
  "type": "Feature",
  "properties": {
    "iso:country": "GB",
    "wof:name": "ST5 5BX",
    "wof:placetype": "postalcode"
  },
  "geometry": {"coordinates":[-2.268546,53.003534],"type":"Point"}
}
