{
  "type": "Feature",
  "properties": {
    "iso:country":"GB",
    "wof:name":"EH5 1ER",
    "wof:placetype":"postalcode"
},
  "geometry": {"coordinates":[-3.21569637002563,55.9800682214379],"type":"Point"}
}