{
  "type": "Feature",
  "properties": {
    "iso:country":"GB",
    "wof:name":"SE9 5ET",
    "wof:placetype":"postalcode"
},
  "geometry": {"coordinates":[0.04318352654596,51.44651452440613],"type":"Point"}
}