{
  "type": "Feature",
  "properties": {
    "iso:country": "GB",
    "wof:name": "PO22 6EH",
    "wof:placetype": "postalcode"
  },
  "geometry": {"coordinates":[-0.615724,50.794912],"type":"Point"}
}
