{
  "type": "Feature",
  "properties": {
    "iso:country":"GB",
    "wof:name":"PO22 6EH",
    "wof:placetype":"postalcode"
},
  "geometry": {"coordinates":[-0.61572372664227,50.79491167416661],"type":"Point"}
}