{
  "type": "Feature",
  "properties": {
    "iso:country":"GB",
    "wof:name":"CH2 1QL",
    "wof:placetype":"postalcode"
},
  "geometry": {"coordinates":[-2.88055241906275,53.21426022596292],"type":"Point"}
}