{
  "type": "Feature",
  "properties": {
    "iso:country": "GB",
    "wof:name": "GL3 3ST",
    "wof:placetype": "postalcode"
  },
  "geometry": {"coordinates":[-2.176371,51.853529],"type":"Point"}
}
