{
  "type": "Feature",
  "properties": {
    "iso:country":"GB",
    "wof:name":"GL3 3ST",
    "wof:placetype":"postalcode"
},
  "geometry": {"coordinates":[-2.17637067195487,51.8535287791962],"type":"Point"}
}