{
  "type": "Feature",
  "properties": {
    "iso:country": "GB",
    "wof:name": "NW6 5LA",
    "wof:placetype": "postalcode"
  },
  "geometry": {"coordinates":[-0.19334,51.531286],"type":"Point"}
}
