{
  "type": "Feature",
  "properties": {
    "iso:country":"GB",
    "wof:name":"NW6 5LA",
    "wof:placetype":"postalcode"
},
  "geometry": {"coordinates":[-0.19333984994038,51.53128582496363],"type":"Point"}
}