{
  "type": "Feature",
  "properties": {
    "iso:country":"GB",
    "wof:name":"NR24 2NP",
    "wof:placetype":"postalcode"
},
  "geometry": {"coordinates":[0.99743068774088,52.86065166481863],"type":"Point"}
}