{
  "type": "Feature",
  "properties": {
    "date:inception_lower": "1980-01-01",
    "date:inception_upper": "1980-01-01",
    "iso:country": "GB",
    "wof:name": "DN6 7NQ",
    "wof:placetype": "postalcode"
  },
  "geometry": {"coordinates":[-1.200464,53.563889],"type":"Point"}
}
