{
  "type": "Feature",
  "properties": {
    "iso:country":"GB",
    "wof:name":"DN6 7NQ",
    "wof:placetype":"postalcode"
},
  "geometry": {"coordinates":[-1.20046399469487,53.56388905877625],"type":"Point"}
}