{
  "type": "Feature",
  "properties": {
    "iso:country": "GB",
    "wof:name": "DN6 7NQ",
    "wof:placetype": "postalcode"
  },
  "geometry": {"coordinates":[-1.200464,53.563889],"type":"Point"}
}
