{
  "type": "Feature",
  "properties": {
    "date:inception_lower":"2005-02-01",
    "date:inception_upper":"2005-02-28",
    "iso:country":"GB",
    "wof:name":"TA20 2BZ",
    "wof:placetype":"postalcode"
},
  "geometry": {"coordinates":[-2.961677,50.869911],"type":"Point"}
}