{
  "type": "Feature",
  "properties": {
    "date:inception_lower": "1998-12-01",
    "date:inception_upper": "1998-12-01",
    "iso:country": "GB",
    "wof:name": "DN4 0NL",
    "wof:placetype": "postalcode"
  },
  "geometry": {"coordinates":[-1.157355,53.509329],"type":"Point"}
}
