{
  "type": "Feature",
  "properties": {
    "iso:country": "GB",
    "wof:name": "DN4 0NL",
    "wof:placetype": "postalcode"
  },
  "geometry": {"coordinates":[-1.157355,53.509329],"type":"Point"}
}
