{
  "type": "Feature",
  "properties": {
    "iso:country":"GB",
    "wof:name":"DN4 0NL",
    "wof:placetype":"postalcode"
},
  "geometry": {"coordinates":[-1.15735503284133,53.50932885313436],"type":"Point"}
}