{
  "type": "Feature",
  "properties": {
    "iso:country": "GB",
    "wof:name": "SK4 3LW",
    "wof:placetype": "postalcode"
  },
  "geometry": {"coordinates":[-2.184995,53.413882],"type":"Point"}
}
