{
  "type": "Feature",
  "properties": {
    "date:inception_lower":"1990-02-01",
    "date:inception_upper":"1990-02-28",
    "iso:country":"GB",
    "wof:name":"SK4 3LW",
    "wof:placetype":"postalcode"
},
  "geometry": {"coordinates":[-2.184995,53.413882],"type":"Point"}
}