{
  "type": "Feature",
  "properties": {
    "iso:country":"GB",
    "wof:name":"NR10 4DR",
    "wof:placetype":"postalcode"
},
  "geometry": {"coordinates":[1.19957662782813,52.71130051100803],"type":"Point"}
}