{
  "type": "Feature",
  "properties": {
    "iso:country": "GB",
    "wof:name": "S35 2UU",
    "wof:placetype": "postalcode"
  },
  "geometry": {"coordinates":[-1.466013,53.461623],"type":"Point"}
}
