{
  "type": "Feature",
  "properties": {
    "iso:country":"GB",
    "wof:name":"S35 2UU",
    "wof:placetype":"postalcode"
},
  "geometry": {"coordinates":[-1.46601306406168,53.46162338015595],"type":"Point"}
}