{
  "type": "Feature",
  "properties": {
    "iso:country":"GB",
    "wof:name":"B67 6JU",
    "wof:placetype":"postalcode"
},
  "geometry": {"coordinates":[-1.9881476101375,52.47953016507348],"type":"Point"}
}