{
  "type": "Feature",
  "properties": {
    "iso:country":"GB",
    "wof:name":"LS17 7PG",
    "wof:placetype":"postalcode"
},
  "geometry": {"coordinates":[-1.5469379443924,53.86274320687406],"type":"Point"}
}