{
  "type": "Feature",
  "properties": {
    "iso:country":"GB",
    "wof:name":"ME17 1RP",
    "wof:placetype":"postalcode"
},
  "geometry": {"coordinates":[0.61372177352633,51.24840527320804],"type":"Point"}
}