{
  "type": "Feature",
  "properties": {
    "iso:country":"GB",
    "wof:name":"OX26 6UB",
    "wof:placetype":"postalcode"
},
  "geometry": {"coordinates":[-1.14048604580488,51.89656702544229],"type":"Point"}
}