{
  "type": "Feature",
  "properties": {
    "iso:country": "GB",
    "wof:name": "OX26 6UB",
    "wof:placetype": "postalcode"
  },
  "geometry": {"coordinates":[-1.140486,51.896567],"type":"Point"}
}
