{
  "type": "Feature",
  "properties": {
    "date:inception_lower": "1980-01-01",
    "date:inception_upper": "1980-01-01",
    "iso:country": "GB",
    "wof:name": "CB4 1NR",
    "wof:placetype": "postalcode"
  },
  "geometry": {"coordinates":[0.143853,52.217517],"type":"Point"}
}
