{
  "type": "Feature",
  "properties": {
    "iso:country":"GB",
    "wof:name":"CB4 1NR",
    "wof:placetype":"postalcode"
},
  "geometry": {"coordinates":[0.1438527065694,52.21751740400661],"type":"Point"}
}