{
  "type": "Feature",
  "properties": {
    "iso:country":"GB",
    "wof:name":"IV30 6HA",
    "wof:placetype":"postalcode"
},
  "geometry": {"coordinates":[-3.29544733363506,57.6377168363722],"type":"Point"}
}