{
  "type": "Feature",
  "properties": {
    "iso:country": "GB",
    "wof:name": "IV30 6HA",
    "wof:placetype": "postalcode"
  },
  "geometry": {"coordinates":[-3.295447,57.637717],"type":"Point"}
}
