{
  "type": "Feature",
  "properties": {
    "iso:country": "GB",
    "wof:name": "OX16 1AA",
    "wof:placetype": "postalcode"
  },
  "geometry": {"coordinates":[-1.36475,52.07734],"type":"Point"}
}
