{
  "type": "Feature",
  "properties": {
    "iso:country":"GB",
    "wof:name":"OX16 1AA",
    "wof:placetype":"postalcode"
},
  "geometry": {"coordinates":[-1.36474988348011,52.07734011675441],"type":"Point"}
}