{
  "type": "Feature",
  "properties": {
    "iso:country": "GB",
    "wof:name": "PO33 1EH",
    "wof:placetype": "postalcode"
  },
  "geometry": {"coordinates":[-1.15708,50.721146],"type":"Point"}
}
