{
  "type": "Feature",
  "properties": {
    "iso:country": "GB",
    "wof:name": "PO33 1EH",
    "wof:placetype": "postalcode"
  },
  "geometry": {"coordinates":[-1.157106,50.721131],"type":"Point"}
}
