{
  "type": "Feature",
  "properties": {
    "iso:country":"GB",
    "wof:name":"PO33 1EH",
    "wof:placetype":"postalcode"
},
  "geometry": {"coordinates":[-1.15710604895135,50.72113087293874],"type":"Point"}
}