{
  "type": "Feature",
  "properties": {
    "iso:country":"GB",
    "wof:name":"NG34 7SJ",
    "wof:placetype":"postalcode"
},
  "geometry": {"coordinates":[-0.41074188221064,52.99607907062769],"type":"Point"}
}