{
  "type": "Feature",
  "properties": {
    "date:inception_lower": "1999-12-01",
    "date:inception_upper": "1999-12-01",
    "iso:country": "GB",
    "wof:name": "NG34 7SJ",
    "wof:placetype": "postalcode"
  },
  "geometry": {"coordinates":[-0.410742,52.996079],"type":"Point"}
}
