{
  "type": "Feature",
  "properties": {
    "iso:country": "GB",
    "wof:name": "ML11 0AF",
    "wof:placetype": "postalcode"
  },
  "geometry": {"coordinates":[-3.879462,55.628619],"type":"Point"}
}
