{
  "type": "Feature",
  "properties": {
    "iso:country":"GB",
    "wof:name":"ML11 0AF",
    "wof:placetype":"postalcode"
},
  "geometry": {"coordinates":[-3.87946190429831,55.62861872025781],"type":"Point"}
}