{
  "type": "Feature",
  "properties": {
    "date:inception_lower":"1980-01-01",
    "date:inception_upper":"1980-01-31",
    "iso:country":"GB",
    "wof:name":"N11 1HN",
    "wof:placetype":"postalcode"
},
  "geometry": {"coordinates":[-0.148748,51.622604],"type":"Point"}
}