{
  "type": "Feature",
  "properties": {
    "iso:country":"GB",
    "wof:name":"N11 1HN",
    "wof:placetype":"postalcode"
},
  "geometry": {"coordinates":[-0.14836055224316,51.62245093200363],"type":"Point"}
}