{
  "type": "Feature",
  "properties": {
    "iso:country": "GB",
    "wof:name": "N11 1HN",
    "wof:placetype": "postalcode"
  },
  "geometry": {"coordinates":[-0.148748,51.622604],"type":"Point"}
}
