{
  "type": "Feature",
  "properties": {
    "iso:country": "GB",
    "wof:name": "E17 9BP",
    "wof:placetype": "postalcode"
  },
  "geometry": {"coordinates":[-0.014866,51.578229],"type":"Point"}
}
