{
  "type": "Feature",
  "properties": {
    "iso:country":"GB",
    "wof:name":"E17 9BP",
    "wof:placetype":"postalcode"
},
  "geometry": {"coordinates":[-0.01486628715203,51.57822925186348],"type":"Point"}
}