{
  "type": "Feature",
  "properties": {
    "iso:country":"GB",
    "wof:name":"MK17 9QD",
    "wof:placetype":"postalcode"
},
  "geometry": {"coordinates":[-0.61974740980831,51.99313440413344],"type":"Point"}
}