{
  "type": "Feature",
  "properties": {
    "iso:country":"GB",
    "wof:name":"BD18 4SN",
    "wof:placetype":"postalcode"
},
  "geometry": {"coordinates":[-1.79415752332743,53.8323770762493],"type":"Point"}
}