{
  "type": "Feature",
  "properties": {
    "date:inception_lower": "1980-01-01",
    "date:inception_upper": "1980-01-01",
    "iso:country": "GB",
    "wof:name": "BD18 4SN",
    "wof:placetype": "postalcode"
  },
  "geometry": {"coordinates":[-1.794157,53.832377],"type":"Point"}
}
