{
  "type": "Feature",
  "properties": {
    "iso:country":"GB",
    "wof:name":"PR7 6LR",
    "wof:placetype":"postalcode"
},
  "geometry": {"coordinates":[-2.67979083311343,53.65604752335877],"type":"Point"}
}