{
  "type": "Feature",
  "properties": {
    "iso:country": "GB",
    "wof:name": "SW4 9DT",
    "wof:placetype": "postalcode"
  },
  "geometry": {"coordinates":[-0.143545,51.456383],"type":"Point"}
}
