{
  "type": "Feature",
  "properties": {
    "iso:country":"GB",
    "wof:name":"SW4 9DT",
    "wof:placetype":"postalcode"
},
  "geometry": {"coordinates":[-0.14354460238091,51.45638292402827],"type":"Point"}
}