{
  "type": "Feature",
  "properties": {
    "iso:country": "GB",
    "wof:name": "SG6 2TX",
    "wof:placetype": "postalcode"
  },
  "geometry": {"coordinates":[-0.206981,51.974662],"type":"Point"}
}
