{
  "type": "Feature",
  "properties": {
    "date:inception_lower":"1993-08-01",
    "date:inception_upper":"1993-08-31",
    "iso:country":"GB",
    "wof:name":"SG6 2TX",
    "wof:placetype":"postalcode"
},
  "geometry": {"coordinates":[-0.206981,51.974662],"type":"Point"}
}