{
  "type": "Feature",
  "properties": {
    "iso:country":"GB",
    "wof:name":"SG6 2TX",
    "wof:placetype":"postalcode"
},
  "geometry": {"coordinates":[-0.20703789399836,51.97463557182799],"type":"Point"}
}