{
  "type": "Feature",
  "properties": {
    "iso:country":"GB",
    "wof:name":"RM7 0BP",
    "wof:placetype":"postalcode"
},
  "geometry": {"coordinates":[0.17523798597964,51.56718815632711],"type":"Point"}
}