{
  "type": "Feature",
  "properties": {
    "iso:country": "GB",
    "wof:name": "RM7 0BP",
    "wof:placetype": "postalcode"
  },
  "geometry": {"coordinates":[0.175238,51.567188],"type":"Point"}
}
