{
  "type": "Feature",
  "properties": {
    "iso:country": "GB",
    "wof:name": "SW17 9PA",
    "wof:placetype": "postalcode"
  },
  "geometry": {"coordinates":[-0.167396,51.427964],"type":"Point"}
}
