{
  "type": "Feature",
  "properties": {
    "iso:country":"GB",
    "wof:name":"IP31 2AN",
    "wof:placetype":"postalcode"
},
  "geometry": {"coordinates":[0.8882290077822,52.3218779741979],"type":"Point"}
}