{
  "type": "Feature",
  "properties": {
    "date:inception_lower":"1980-01-01",
    "date:inception_upper":"1980-01-31",
    "iso:country":"GB",
    "wof:name":"IP31 2AN",
    "wof:placetype":"postalcode"
},
  "geometry": {"coordinates":[0.88826,52.321896],"type":"Point"}
}