{
  "type": "Feature",
  "properties": {
    "iso:country":"GB",
    "wof:name":"TS6 9RN",
    "wof:placetype":"postalcode"
},
  "geometry": {"coordinates":[-1.14528524295483,54.56545677420024],"type":"Point"}
}