{
  "type": "Feature",
  "properties": {
    "iso:country":"GB",
    "wof:name":"PA13 4PT",
    "wof:placetype":"postalcode"
},
  "geometry": {"coordinates":[-4.61199762264313,55.89937997516621],"type":"Point"}
}