{
  "type": "Feature",
  "properties": {
    "iso:country": "GB",
    "wof:name": "PA13 4PT",
    "wof:placetype": "postalcode"
  },
  "geometry": {"coordinates":[-4.61198,55.899374],"type":"Point"}
}
