{
  "type": "Feature",
  "properties": {
    "iso:country":"GB",
    "wof:name":"PR5 4TA",
    "wof:placetype":"postalcode"
},
  "geometry": {"coordinates":[-2.66927609385423,53.73534756462473],"type":"Point"}
}