{
  "type": "Feature",
  "properties": {
    "date:inception_lower": "1980-01-01",
    "date:inception_upper": "1980-01-01",
    "iso:country": "GB",
    "wof:name": "WN8 0NU",
    "wof:placetype": "postalcode"
  },
  "geometry": {"coordinates":[-2.725931,53.539214],"type":"Point"}
}
