{
  "type": "Feature",
  "properties": {
    "iso:country":"GB",
    "wof:name":"WN8 0NU",
    "wof:placetype":"postalcode"
},
  "geometry": {"coordinates":[-2.72593145170326,53.53921409248828],"type":"Point"}
}