{
  "type": "Feature",
  "properties": {
    "iso:country":"GB",
    "wof:name":"LA17 7XQ",
    "wof:placetype":"postalcode"
},
  "geometry": {"coordinates":[-3.1704533932889,54.26196705154712],"type":"Point"}
}