{
  "type": "Feature",
  "properties": {
    "date:inception_lower": "1997-06-01",
    "date:inception_upper": "1997-06-01",
    "iso:country": "GB",
    "wof:name": "S20 2QL",
    "wof:placetype": "postalcode"
  },
  "geometry": {"coordinates":[-1.33452,53.33842],"type":"Point"}
}
