{
  "type": "Feature",
  "properties": {
    "date:inception_lower": "1992-08-01",
    "date:inception_upper": "1992-08-01",
    "iso:country": "GB",
    "wof:name": "LE7 2JT",
    "wof:placetype": "postalcode"
  },
  "geometry": {"coordinates":[-1.074101,52.697967],"type":"Point"}
}
