{
  "type": "Feature",
  "properties": {
    "iso:country":"GB",
    "wof:name":"LE7 2JT",
    "wof:placetype":"postalcode"
},
  "geometry": {"coordinates":[-1.07410758686806,52.69794725425206],"type":"Point"}
}