{
  "type": "Feature",
  "properties": {
    "iso:country": "GB",
    "wof:name": "LE7 2JT",
    "wof:placetype": "postalcode"
  },
  "geometry": {"coordinates":[-1.074108,52.697947],"type":"Point"}
}
