{
  "type": "Feature",
  "properties": {
    "date:inception_lower": "1999-06-01",
    "date:inception_upper": "1999-06-01",
    "iso:country": "GB",
    "wof:name": "NP15 2YD",
    "wof:placetype": "postalcode"
  },
  "geometry": {"coordinates":[-2.899212,51.789505],"type":"Point"}
}
