{
  "type": "Feature",
  "properties": {
    "iso:country":"GB",
    "wof:name":"BB9 9SL",
    "wof:placetype":"postalcode"
},
  "geometry": {"coordinates":[-2.2137204487292,53.83632605576398],"type":"Point"}
}