{
  "type": "Feature",
  "properties": {
    "iso:country":"GB",
    "wof:name":"L25 1RQ",
    "wof:placetype":"postalcode"
},
  "geometry": {"coordinates":[-2.87738347894372,53.39822550675272],"type":"Point"}
}