{
  "type": "Feature",
  "properties": {
    "date:inception_lower": "1985-04-01",
    "date:inception_upper": "1985-04-01",
    "iso:country": "GB",
    "wof:name": "L25 1RQ",
    "wof:placetype": "postalcode"
  },
  "geometry": {"coordinates":[-2.877383,53.398226],"type":"Point"}
}
