{
  "type": "Feature",
  "properties": {
    "iso:country":"GB",
    "wof:name":"TR8 5BA",
    "wof:placetype":"postalcode"
},
  "geometry": {"coordinates":[-5.00006889228886,50.34380959167234],"type":"Point"}
}