{
  "type": "Feature",
  "properties": {
    "iso:country": "GB",
    "wof:name": "BS5 7UF",
    "wof:placetype": "postalcode"
  },
  "geometry": {"coordinates":[-2.541363,51.468216],"type":"Point"}
}
