{
  "type": "Feature",
  "properties": {
    "date:inception_lower":"1980-01-01",
    "date:inception_upper":"1980-01-31",
    "iso:country":"GB",
    "wof:name":"KA3 3BN",
    "wof:placetype":"postalcode"
},
  "geometry": {"coordinates":[-4.530071,55.67875],"type":"Point"}
}