{
  "type": "Feature",
  "properties": {
    "date:inception_lower":"2015-02-01",
    "date:inception_upper":"2015-02-28",
    "iso:country":"GB",
    "wof:name":"BL7 0LE",
    "wof:placetype":"postalcode"
},
  "geometry": {"coordinates":[-2.409969,53.636862],"type":"Point"}
}