{
  "type": "Feature",
  "properties": {
    "iso:country": "GB",
    "wof:name": "BL7 0LE",
    "wof:placetype": "postalcode"
  },
  "geometry": {"coordinates":[-2.409969,53.636862],"type":"Point"}
}
