{
  "type": "Feature",
  "properties": {
    "date:inception_lower": "2015-02-01",
    "date:inception_upper": "2015-02-01",
    "iso:country": "GB",
    "wof:name": "BL7 0LE",
    "wof:placetype": "postalcode"
  },
  "geometry": {"coordinates":[-2.410047,53.637086],"type":"Point"}
}
