{
  "type": "Feature",
  "properties": {
    "iso:country":"GB",
    "wof:name":"BL7 0LE",
    "wof:placetype":"postalcode"
},
  "geometry": {"coordinates":[-2.41004887973672,53.63707005264284],"type":"Point"}
}