{
  "type": "Feature",
  "properties": {
    "iso:country":"GB",
    "wof:name":"ME8 8NH",
    "wof:placetype":"postalcode"
},
  "geometry": {"coordinates":[0.62492529580861,51.36674691181688],"type":"Point"}
}