{
  "type": "Feature",
  "properties": {
    "iso:country": "GB",
    "wof:name": "NE25 0RD",
    "wof:placetype": "postalcode"
  },
  "geometry": {"coordinates":[-1.520272,55.085596],"type":"Point"}
}
