{
  "type": "Feature",
  "properties": {
    "date:inception_lower":"1980-01-01",
    "date:inception_upper":"1980-01-31",
    "iso:country":"GB",
    "wof:name":"NE25 0RD",
    "wof:placetype":"postalcode"
},
  "geometry": {"coordinates":[-1.520272,55.085596],"type":"Point"}
}