{
  "type": "Feature",
  "properties": {
    "iso:country":"GB",
    "wof:name":"NE25 0RD",
    "wof:placetype":"postalcode"
},
  "geometry": {"coordinates":[-1.52027228288655,55.08559629575529],"type":"Point"}
}