{
  "type": "Feature",
  "properties": {
    "iso:country":"GB",
    "wof:name":"CV47 2AH",
    "wof:placetype":"postalcode"
},
  "geometry": {"coordinates":[-1.40092431908248,52.14911290889498],"type":"Point"}
}