{
  "type": "Feature",
  "properties": {
    "iso:country":"GB",
    "wof:name":"W3 9HR",
    "wof:placetype":"postalcode"
},
  "geometry": {"coordinates":[-0.27142081543902,51.51579951345946],"type":"Point"}
}