{
  "type": "Feature",
  "properties": {
    "iso:country":"GB",
    "wof:name":"WR4 0JE",
    "wof:placetype":"postalcode"
},
  "geometry": {"coordinates":[-2.18527789947728,52.20042882304601],"type":"Point"}
}