{
  "type": "Feature",
  "properties": {
    "iso:country":"GB",
    "wof:name":"SK5 6LX",
    "wof:placetype":"postalcode"
},
  "geometry": {"coordinates":[-2.16167680524357,53.44973523153731],"type":"Point"}
}