{
  "type": "Feature",
  "properties": {
    "iso:country": "GB",
    "wof:name": "SK5 6LX",
    "wof:placetype": "postalcode"
  },
  "geometry": {"coordinates":[-2.161677,53.449735],"type":"Point"}
}
