{
  "type": "Feature",
  "properties": {
    "date:inception_lower": "2016-05-01",
    "date:inception_upper": "2016-05-01",
    "iso:country": "GB",
    "wof:name": "BS21 7FU",
    "wof:placetype": "postalcode"
  },
  "geometry": {"coordinates":[-2.861611,51.442984],"type":"Point"}
}
