{
  "type": "Feature",
  "properties": {
    "iso:country":"GB",
    "wof:name":"NN4 9YD",
    "wof:placetype":"postalcode"
},
  "geometry": {"coordinates":[-0.92195587027098,52.21091900679026],"type":"Point"}
}