{
  "type": "Feature",
  "properties": {
    "date:inception_lower": "1987-04-01",
    "date:inception_upper": "1987-04-01",
    "iso:country": "GB",
    "wof:name": "NN4 9YD",
    "wof:placetype": "postalcode"
  },
  "geometry": {"coordinates":[-0.921956,52.210919],"type":"Point"}
}
