{
  "type": "Feature",
  "properties": {
    "iso:country": "GB",
    "wof:name": "IP24 3AT",
    "wof:placetype": "postalcode"
  },
  "geometry": {"coordinates":[0.742569,52.410774],"type":"Point"}
}
