{
  "type": "Feature",
  "properties": {
    "date:inception_lower":"2000-10-01",
    "date:inception_upper":"2000-10-31",
    "iso:country":"GB",
    "wof:name":"WD25 7AH",
    "wof:placetype":"postalcode"
},
  "geometry": {"coordinates":[-0.410309,51.688362],"type":"Point"}
}