{
  "type": "Feature",
  "properties": {
    "iso:country": "GB",
    "wof:name": "WD25 7AH",
    "wof:placetype": "postalcode"
  },
  "geometry": {"coordinates":[-0.410309,51.688362],"type":"Point"}
}
