{
  "type": "Feature",
  "properties": {
    "date:inception_lower": "1999-12-01",
    "date:inception_upper": "1999-12-01",
    "iso:country": "GB",
    "wof:name": "LE15 6FX",
    "wof:placetype": "postalcode"
  },
  "geometry": {"coordinates":[-0.727393,52.677472],"type":"Point"}
}
