{
  "type": "Feature",
  "properties": {
    "date:inception_lower": "1980-01-01",
    "date:inception_upper": "1980-01-01",
    "iso:country": "GB",
    "wof:name": "NE15 9RA",
    "wof:placetype": "postalcode"
  },
  "geometry": {"coordinates":[-1.774291,54.996578],"type":"Point"}
}
