{
  "type": "Feature",
  "properties": {
    "iso:country":"GB",
    "wof:name":"NG13 8EJ",
    "wof:placetype":"postalcode"
},
  "geometry": {"coordinates":[-0.93591514195248,52.95291748050543],"type":"Point"}
}