{
  "type": "Feature",
  "properties": {
    "date:inception_lower": "1980-01-01",
    "date:inception_upper": "1980-01-01",
    "iso:country": "GB",
    "wof:name": "NG13 8EJ",
    "wof:placetype": "postalcode"
  },
  "geometry": {"coordinates":[-0.935915,52.952917],"type":"Point"}
}
