{
  "type": "Feature",
  "properties": {
    "iso:country":"GB",
    "wof:name":"DN7 5TQ",
    "wof:placetype":"postalcode"
},
  "geometry": {"coordinates":[-1.01235435895653,53.60144110014082],"type":"Point"}
}