{
  "type": "Feature",
  "properties": {
    "iso:country":"GB",
    "wof:name":"CM6 3NZ",
    "wof:placetype":"postalcode"
},
  "geometry": {"coordinates":[0.39983298463478,51.85195065254518],"type":"Point"}
}