{
  "type": "Feature",
  "properties": {
    "iso:country":"GB",
    "wof:name":"NR16 2AG",
    "wof:placetype":"postalcode"
},
  "geometry": {"coordinates":[1.07020604583854,52.47091910164786],"type":"Point"}
}