{
  "type": "Feature",
  "properties": {
    "date:inception_lower": "1980-01-01",
    "date:inception_upper": "1980-01-01",
    "iso:country": "GB",
    "wof:name": "NR16 2AG",
    "wof:placetype": "postalcode"
  },
  "geometry": {"coordinates":[1.069961,52.470857],"type":"Point"}
}
