{
  "type": "Feature",
  "properties": {
    "date:inception_lower": "2017-02-01",
    "date:inception_upper": "2017-02-01",
    "iso:country": "GB",
    "wof:name": "CF36 3BY",
    "wof:placetype": "postalcode"
  },
  "geometry": {"coordinates":[-3.701985,51.474934],"type":"Point"}
}
