{
  "type": "Feature",
  "properties": {
    "iso:country": "GB",
    "wof:name": "LL18 6BF",
    "wof:placetype": "postalcode"
  },
  "geometry": {"coordinates":[-3.422385,53.304267],"type":"Point"}
}
