{
  "type": "Feature",
  "properties": {
    "date:inception_lower": "2020-04-01",
    "date:inception_upper": "2020-04-01",
    "iso:country": "GB",
    "wof:name": "LL18 6BF",
    "wof:placetype": "postalcode"
  },
  "geometry": {"coordinates":[-3.421674,53.304095],"type":"Point"}
}
