{
  "type": "Feature",
  "properties": {
    "date:inception_lower": "1980-01-01",
    "date:inception_upper": "1980-01-01",
    "iso:country": "GB",
    "wof:name": "SS15 5AN",
    "wof:placetype": "postalcode"
  },
  "geometry": {"coordinates":[0.446518,51.571134],"type":"Point"}
}
