{
  "type": "Feature",
  "properties": {
    "iso:country": "GB",
    "wof:name": "TF1 1JB",
    "wof:placetype": "postalcode"
  },
  "geometry": {"coordinates":[-2.512574,52.695903],"type":"Point"}
}
