{
  "type": "Feature",
  "properties": {
    "iso:country":"GB",
    "wof:name":"TF1 1JB",
    "wof:placetype":"postalcode"
},
  "geometry": {"coordinates":[-2.51257371084067,52.69590264142268],"type":"Point"}
}