{
  "type": "Feature",
  "properties": {
    "date:inception_lower": "2004-03-01",
    "date:inception_upper": "2004-03-01",
    "iso:country": "GB",
    "wof:name": "YO25 5PH",
    "wof:placetype": "postalcode"
  },
  "geometry": {"coordinates":[-0.426579,54.002733],"type":"Point"}
}
