{
  "type": "Feature",
  "properties": {
    "iso:country": "GB",
    "wof:name": "TA19 9AW",
    "wof:placetype": "postalcode"
  },
  "geometry": {"coordinates":[-2.912299,50.928427],"type":"Point"}
}
