{
  "type": "Feature",
  "properties": {
    "iso:country":"GB",
    "wof:name":"NP20 7DE",
    "wof:placetype":"postalcode"
},
  "geometry": {"coordinates":[-3.02117681596724,51.61029737511643],"type":"Point"}
}