{
  "type": "Feature",
  "properties": {
    "iso:country": "GB",
    "wof:name": "NP20 7DE",
    "wof:placetype": "postalcode"
  },
  "geometry": {"coordinates":[-3.021177,51.610297],"type":"Point"}
}
