{
  "type": "Feature",
  "properties": {
    "iso:country":"GB",
    "wof:name":"NR12 0UR",
    "wof:placetype":"postalcode"
},
  "geometry": {"coordinates":[1.60269503398545,52.78463092548483],"type":"Point"}
}