{
  "type": "Feature",
  "properties": {
    "date:inception_lower": "1993-08-01",
    "date:inception_upper": "1993-08-01",
    "iso:country": "GB",
    "wof:name": "NR12 0UR",
    "wof:placetype": "postalcode"
  },
  "geometry": {"coordinates":[1.602733,52.784676],"type":"Point"}
}
