{
  "type": "Feature",
  "properties": {
    "iso:country": "GB",
    "wof:name": "NR12 0UR",
    "wof:placetype": "postalcode"
  },
  "geometry": {"coordinates":[1.602695,52.784631],"type":"Point"}
}
