{
  "type": "Feature",
  "properties": {
    "iso:country": "GB",
    "wof:name": "CB9 7QW",
    "wof:placetype": "postalcode"
  },
  "geometry": {"coordinates":[0.497493,52.087363],"type":"Point"}
}
