{
  "type": "Feature",
  "properties": {
    "iso:country":"GB",
    "wof:name":"CB9 7QW",
    "wof:placetype":"postalcode"
},
  "geometry": {"coordinates":[0.49749337576255,52.08736270097779],"type":"Point"}
}