{
  "type": "Feature",
  "properties": {
    "iso:country":"GB",
    "wof:name":"SE11 5RD",
    "wof:placetype":"postalcode"
},
  "geometry": {"coordinates":[-0.11577577727855,51.48719815191188],"type":"Point"}
}