{
  "type": "Feature",
  "properties": {
    "iso:country":"GB",
    "wof:name":"SK17 7JE",
    "wof:placetype":"postalcode"
},
  "geometry": {"coordinates":[-1.88016805348679,53.26619245827441],"type":"Point"}
}