{
  "type": "Feature",
  "properties": {
    "iso:country": "GB",
    "wof:name": "SK17 7JE",
    "wof:placetype": "postalcode"
  },
  "geometry": {"coordinates":[-1.880167,53.266208],"type":"Point"}
}
