{
  "type": "Feature",
  "properties": {
    "iso:country": "GB",
    "wof:name": "YO14 9QP",
    "wof:placetype": "postalcode"
  },
  "geometry": {"coordinates":[-0.268545,54.176552],"type":"Point"}
}
