{
  "type": "Feature",
  "properties": {
    "iso:country":"GB",
    "wof:name":"B48 7HE",
    "wof:placetype":"postalcode"
},
  "geometry": {"coordinates":[-1.89433598920313,52.35227443916559],"type":"Point"}
}