{
  "type": "Feature",
  "properties": {
    "date:inception_lower": "1990-07-01",
    "date:inception_upper": "1990-07-01",
    "iso:country": "GB",
    "wof:name": "S45 9TA",
    "wof:placetype": "postalcode"
  },
  "geometry": {"coordinates":[-1.405479,53.157983],"type":"Point"}
}
