{
  "type": "Feature",
  "properties": {
    "iso:country":"GB",
    "wof:name":"L19 2JX",
    "wof:placetype":"postalcode"
},
  "geometry": {"coordinates":[-2.89640187008298,53.35353516372646],"type":"Point"}
}