{
  "type": "Feature",
  "properties": {
    "iso:country":"GB",
    "wof:name":"CM6 2NH",
    "wof:placetype":"postalcode"
},
  "geometry": {"coordinates":[0.33255832651267,51.93672892775265],"type":"Point"}
}