{
  "type": "Feature",
  "properties": {
    "date:inception_lower":"1980-01-01",
    "date:inception_upper":"1980-01-31",
    "iso:country":"GB",
    "wof:name":"OL4 5BU",
    "wof:placetype":"postalcode"
},
  "geometry": {"coordinates":[-2.073062,53.535581],"type":"Point"}
}