{
  "type": "Feature",
  "properties": {
    "date:inception_lower":"1980-01-01",
    "date:inception_upper":"1980-01-31",
    "iso:country":"GB",
    "wof:name":"WV16 4RZ",
    "wof:placetype":"postalcode"
},
  "geometry": {"coordinates":[-2.435501,52.581798],"type":"Point"}
}