{
  "type": "Feature",
  "properties": {
    "iso:country":"GB",
    "wof:name":"ST5 1LX",
    "wof:placetype":"postalcode"
},
  "geometry": {"coordinates":[-2.22400743481959,53.00695224964096],"type":"Point"}
}