{
  "type": "Feature",
  "properties": {
    "date:inception_lower": "1987-04-01",
    "date:inception_upper": "1987-04-01",
    "iso:country": "GB",
    "wof:name": "WA4 2NF",
    "wof:placetype": "postalcode"
  },
  "geometry": {"coordinates":[-2.537961,53.379393],"type":"Point"}
}
