{
  "type": "Feature",
  "properties": {
    "iso:country":"GB",
    "wof:name":"WA4 2NF",
    "wof:placetype":"postalcode"
},
  "geometry": {"coordinates":[-2.53796087236711,53.37939309013478],"type":"Point"}
}