{
  "type": "Feature",
  "properties": {
    "iso:country": "GB",
    "wof:name": "B34 6ER",
    "wof:placetype": "postalcode"
  },
  "geometry": {"coordinates":[-1.793513,52.491739],"type":"Point"}
}
