{
  "type": "Feature",
  "properties": {
    "iso:country":"GB",
    "wof:name":"HX1 4DY",
    "wof:placetype":"postalcode"
},
  "geometry": {"coordinates":[-1.87924807597326,53.72011581524692],"type":"Point"}
}