{
  "type": "Feature",
  "properties": {
    "iso:country":"GB",
    "wof:name":"BA2 6PF",
    "wof:placetype":"postalcode"
},
  "geometry": {"coordinates":[-2.34778004278415,51.38720755295287],"type":"Point"}
}