{
  "type": "Feature",
  "properties": {
    "date:inception_lower": "1987-04-01",
    "date:inception_upper": "1987-04-01",
    "iso:country": "GB",
    "wof:name": "BA2 6PF",
    "wof:placetype": "postalcode"
  },
  "geometry": {"coordinates":[-2.34775,51.387294],"type":"Point"}
}
