{
  "type": "Feature",
  "properties": {
    "date:inception_lower":"1985-10-01",
    "date:inception_upper":"1985-10-31",
    "iso:country":"GB",
    "wof:name":"LN6 3NJ",
    "wof:placetype":"postalcode"
},
  "geometry": {"coordinates":[-0.604569,53.209231],"type":"Point"}
}