{
  "type": "Feature",
  "properties": {
    "iso:country":"GB",
    "wof:name":"PO7 7QJ",
    "wof:placetype":"postalcode"
},
  "geometry": {"coordinates":[-1.01752546773822,50.88624359355878],"type":"Point"}
}