{
  "type": "Feature",
  "properties": {
    "date:inception_lower": "2009-12-01",
    "date:inception_upper": "2009-12-01",
    "iso:country": "GB",
    "wof:name": "YO8 9RP",
    "wof:placetype": "postalcode"
  },
  "geometry": {"coordinates":[-1.081168,53.767961],"type":"Point"}
}
