{
  "type": "Feature",
  "properties": {
    "iso:country": "GB",
    "wof:name": "KY2 6JX",
    "wof:placetype": "postalcode"
  },
  "geometry": {"coordinates":[-3.180895,56.14057],"type":"Point"}
}
