{
  "type": "Feature",
  "properties": {
    "date:inception_lower":"2005-01-01",
    "date:inception_upper":"2005-01-31",
    "iso:country":"GB",
    "wof:name":"M33 4JE",
    "wof:placetype":"postalcode"
},
  "geometry": {"coordinates":[-2.362859,53.414534],"type":"Point"}
}