{
  "type": "Feature",
  "properties": {
    "iso:country": "GB",
    "wof:name": "M33 4JE",
    "wof:placetype": "postalcode"
  },
  "geometry": {"coordinates":[-2.362859,53.414534],"type":"Point"}
}
