{
  "type": "Feature",
  "properties": {
    "iso:country":"GB",
    "wof:name":"M33 4JE",
    "wof:placetype":"postalcode"
},
  "geometry": {"coordinates":[-2.3628592169793,53.41453440214143],"type":"Point"}
}