{
  "type": "Feature",
  "properties": {
    "iso:country":"GB",
    "wof:name":"S33 6SB",
    "wof:placetype":"postalcode"
},
  "geometry": {"coordinates":[-1.74844277655974,53.34775803098501],"type":"Point"}
}