{
  "type": "Feature",
  "properties": {
    "date:inception_lower": "2013-12-01",
    "date:inception_upper": "2013-12-01",
    "iso:country": "GB",
    "wof:name": "S64 0BF",
    "wof:placetype": "postalcode"
  },
  "geometry": {"coordinates":[-1.268759,53.494332],"type":"Point"}
}
