{
  "type": "Feature",
  "properties": {
    "iso:country":"GB",
    "wof:name":"S64 0BF",
    "wof:placetype":"postalcode"
},
  "geometry": {"coordinates":[-1.26875921569278,53.49433186727804],"type":"Point"}
}