{
  "type": "Feature",
  "properties": {
    "iso:country": "GB",
    "wof:name": "S64 0BF",
    "wof:placetype": "postalcode"
  },
  "geometry": {"coordinates":[-1.268759,53.494332],"type":"Point"}
}
