{
  "type": "Feature",
  "properties": {
    "date:inception_lower":"1999-06-01",
    "date:inception_upper":"1999-06-30",
    "iso:country":"GB",
    "wof:name":"NP16 6NT",
    "wof:placetype":"postalcode"
},
  "geometry": {"coordinates":[-2.762258,51.713768],"type":"Point"}
}