{
  "type": "Feature",
  "properties": {
    "iso:country": "GB",
    "wof:name": "NP16 6NT",
    "wof:placetype": "postalcode"
  },
  "geometry": {"coordinates":[-2.762258,51.713768],"type":"Point"}
}
