{
  "type": "Feature",
  "properties": {
    "iso:country": "GB",
    "wof:name": "CM18 7QQ",
    "wof:placetype": "postalcode"
  },
  "geometry": {"coordinates":[0.090205,51.747543],"type":"Point"}
}
