{
  "type": "Feature",
  "properties": {
    "date:inception_lower":"1980-01-01",
    "date:inception_upper":"1980-01-31",
    "iso:country":"GB",
    "wof:name":"SL4 5BQ",
    "wof:placetype":"postalcode"
},
  "geometry": {"coordinates":[-0.628918,51.479312],"type":"Point"}
}