{
  "type": "Feature",
  "properties": {
    "iso:country":"GB",
    "wof:name":"SL4 5BQ",
    "wof:placetype":"postalcode"
},
  "geometry": {"coordinates":[-0.62891842064181,51.4793120893245],"type":"Point"}
}