{
  "type": "Feature",
  "properties": {
    "iso:country": "GB",
    "wof:name": "SL4 5BQ",
    "wof:placetype": "postalcode"
  },
  "geometry": {"coordinates":[-0.628918,51.479312],"type":"Point"}
}
