{
  "type": "Feature",
  "properties": {
    "date:inception_lower": "2013-04-01",
    "date:inception_upper": "2013-04-01",
    "iso:country": "GB",
    "wof:name": "RG30 1ER",
    "wof:placetype": "postalcode"
  },
  "geometry": {"coordinates":[-0.997496,51.458898],"type":"Point"}
}
