{
  "type": "Feature",
  "properties": {
    "iso:country":"GB",
    "wof:name":"B28 8JR",
    "wof:placetype":"postalcode"
},
  "geometry": {"coordinates":[-1.8436045085015,52.43739047877388],"type":"Point"}
}