{
  "type": "Feature",
  "properties": {
    "iso:country": "GB",
    "wof:name": "B28 8JR",
    "wof:placetype": "postalcode"
  },
  "geometry": {"coordinates":[-1.843604,52.43739],"type":"Point"}
}
