{
  "type": "Feature",
  "properties": {
    "date:inception_lower": "1980-01-01",
    "date:inception_upper": "1980-01-01",
    "iso:country": "GB",
    "wof:name": "HX3 0PJ",
    "wof:placetype": "postalcode"
  },
  "geometry": {"coordinates":[-1.855022,53.705858],"type":"Point"}
}
