{
  "type": "Feature",
  "properties": {
    "iso:country": "GB",
    "wof:name": "NG11 8SZ",
    "wof:placetype": "postalcode"
  },
  "geometry": {"coordinates":[-1.196218,52.903174],"type":"Point"}
}
