{
  "type": "Feature",
  "properties": {
    "iso:country":"GB",
    "wof:name":"NG11 8SZ",
    "wof:placetype":"postalcode"
},
  "geometry": {"coordinates":[-1.19621834974964,52.90317373673027],"type":"Point"}
}