{
  "type": "Feature",
  "properties": {
    "iso:country": "GB",
    "wof:name": "SG18 9HG",
    "wof:placetype": "postalcode"
  },
  "geometry": {"coordinates":[-0.361626,52.09438],"type":"Point"}
}
