{
  "type": "Feature",
  "properties": {
    "iso:country":"GB",
    "wof:name":"SG18 9HG",
    "wof:placetype":"postalcode"
},
  "geometry": {"coordinates":[-0.36162627698247,52.09438016831491],"type":"Point"}
}