{
  "type": "Feature",
  "properties": {
    "iso:country":"GB",
    "wof:name":"ST20 0JQ",
    "wof:placetype":"postalcode"
},
  "geometry": {"coordinates":[-2.24321699961193,52.82130305091761],"type":"Point"}
}