{
  "type": "Feature",
  "properties": {
    "iso:country":"GB",
    "wof:name":"DE7 5SS",
    "wof:placetype":"postalcode"
},
  "geometry": {"coordinates":[-1.29361093589706,52.96468709195589],"type":"Point"}
}