{
  "type": "Feature",
  "properties": {
    "date:inception_lower": "1984-02-01",
    "date:inception_upper": "1984-02-01",
    "iso:country": "GB",
    "wof:name": "SA62 6BH",
    "wof:placetype": "postalcode"
  },
  "geometry": {"coordinates":[-5.131582,51.872325],"type":"Point"}
}
