{
  "type": "Feature",
  "properties": {
    "iso:country":"GB",
    "wof:name":"SA62 6BH",
    "wof:placetype":"postalcode"
},
  "geometry": {"coordinates":[-5.13158223135869,51.87232532792817],"type":"Point"}
}