{
  "type": "Feature",
  "properties": {
    "date:inception_lower": "1980-01-01",
    "date:inception_upper": "1980-01-01",
    "iso:country": "GB",
    "wof:name": "G73 1PP",
    "wof:placetype": "postalcode"
  },
  "geometry": {"coordinates":[-4.19758,55.831283],"type":"Point"}
}
