{
  "type": "Feature",
  "properties": {
    "iso:country":"GB",
    "wof:name":"SK5 6DL",
    "wof:placetype":"postalcode"
},
  "geometry": {"coordinates":[-2.1621077033265,53.43637773261695],"type":"Point"}
}