{
  "type": "Feature",
  "properties": {
    "date:inception_lower":"1980-01-01",
    "date:inception_upper":"1980-01-31",
    "iso:country":"GB",
    "wof:name":"SL4 3PY",
    "wof:placetype":"postalcode"
},
  "geometry": {"coordinates":[-0.624767,51.476584],"type":"Point"}
}