{
  "type": "Feature",
  "properties": {
    "iso:country":"GB",
    "wof:name":"SL4 3PY",
    "wof:placetype":"postalcode"
},
  "geometry": {"coordinates":[-0.62476670371535,51.47658384116304],"type":"Point"}
}