{
  "type": "Feature",
  "properties": {
    "iso:country":"GB",
    "wof:name":"NE2 4RU",
    "wof:placetype":"postalcode"
},
  "geometry": {"coordinates":[-1.6094690564199,54.98458664841099],"type":"Point"}
}