{
  "type": "Feature",
  "properties": {
    "iso:country": "GB",
    "wof:name": "NE2 4RU",
    "wof:placetype": "postalcode"
  },
  "geometry": {"coordinates":[-1.609469,54.984587],"type":"Point"}
}
