{
  "type": "Feature",
  "properties": {
    "date:inception_lower": "1980-01-01",
    "date:inception_upper": "1980-01-01",
    "iso:country": "GB",
    "wof:name": "NE2 4RU",
    "wof:placetype": "postalcode"
  },
  "geometry": {"coordinates":[-1.609469,54.984587],"type":"Point"}
}
