{
  "type": "Feature",
  "properties": {
    "iso:country":"GB",
    "wof:name":"GU1 2HE",
    "wof:placetype":"postalcode"
},
  "geometry": {"coordinates":[-0.54989721037607,51.23610867417198],"type":"Point"}
}