{
  "type": "Feature",
  "properties": {
    "date:inception_lower": "2019-04-01",
    "date:inception_upper": "2019-04-01",
    "iso:country": "GB",
    "wof:name": "FY6 7XP",
    "wof:placetype": "postalcode"
  },
  "geometry": {"coordinates":[-2.971211,53.847941],"type":"Point"}
}
