{
  "type": "Feature",
  "properties": {
    "iso:country": "GB",
    "wof:name": "FY6 7XP",
    "wof:placetype": "postalcode"
  },
  "geometry": {"coordinates":[-2.97382,53.846365],"type":"Point"}
}
