{
  "type": "Feature",
  "properties": {
    "iso:country": "GB",
    "wof:name": "DE24 0EQ",
    "wof:placetype": "postalcode"
  },
  "geometry": {"coordinates":[-1.432562,52.89321],"type":"Point"}
}
