{
  "type": "Feature",
  "properties": {
    "date:inception_lower":"1996-12-01",
    "date:inception_upper":"1996-12-31",
    "iso:country":"GB",
    "wof:name":"B80 7DD",
    "wof:placetype":"postalcode"
},
  "geometry": {"coordinates":[-1.912541,52.270209],"type":"Point"}
}