{
  "type": "Feature",
  "properties": {
    "iso:country":"GB",
    "wof:name":"B80 7DD",
    "wof:placetype":"postalcode"
},
  "geometry": {"coordinates":[-1.91254110378946,52.27020857628352],"type":"Point"}
}