{
  "type": "Feature",
  "properties": {
    "iso:country":"GB",
    "wof:name":"EN5 5TW",
    "wof:placetype":"postalcode"
},
  "geometry": {"coordinates":[-0.19835141078167,51.65512433919534],"type":"Point"}
}