{
  "type": "Feature",
  "properties": {
    "iso:country": "GB",
    "wof:name": "CO4 6DT",
    "wof:placetype": "postalcode"
  },
  "geometry": {"coordinates":[0.893718,51.901155],"type":"Point"}
}
