{
  "type": "Feature",
  "properties": {
    "iso:country":"GB",
    "wof:name":"L36 4JJ",
    "wof:placetype":"postalcode"
},
  "geometry": {"coordinates":[-2.86147877636814,53.41346957088727],"type":"Point"}
}