{
  "type": "Feature",
  "properties": {
    "iso:country":"GB",
    "wof:name":"NG34 8FN",
    "wof:placetype":"postalcode"
},
  "geometry": {"coordinates":[-0.46975160274143,53.03727226623486],"type":"Point"}
}