{
  "type": "Feature",
  "properties": {
    "date:inception_lower": "1999-12-01",
    "date:inception_upper": "1999-12-01",
    "iso:country": "GB",
    "wof:name": "NG34 8FN",
    "wof:placetype": "postalcode"
  },
  "geometry": {"coordinates":[-0.469752,53.037272],"type":"Point"}
}
