{
  "type": "Feature",
  "properties": {
    "iso:country":"GB",
    "wof:name":"NE46 3EG",
    "wof:placetype":"postalcode"
},
  "geometry": {"coordinates":[-2.1105729308992,54.97353403810118],"type":"Point"}
}