{
  "type": "Feature",
  "properties": {
    "iso:country":"GB",
    "wof:name":"TR27 6NJ",
    "wof:placetype":"postalcode"
},
  "geometry": {"coordinates":[-5.47357266073688,50.17227813070649],"type":"Point"}
}