{
  "type": "Feature",
  "properties": {
    "iso:country":"GB",
    "wof:name":"NW5 1UG",
    "wof:placetype":"postalcode"
},
  "geometry": {"coordinates":[-0.14202120481292,51.55444915156977],"type":"Point"}
}