{
  "type": "Feature",
  "properties": {
    "iso:country":"GB",
    "wof:name":"CO4 5NW",
    "wof:placetype":"postalcode"
},
  "geometry": {"coordinates":[0.92939813357113,51.94207123709076],"type":"Point"}
}