{
  "type": "Feature",
  "properties": {
    "date:inception_lower": "1980-01-01",
    "date:inception_upper": "1980-01-01",
    "iso:country": "GB",
    "wof:name": "CO4 5NW",
    "wof:placetype": "postalcode"
  },
  "geometry": {"coordinates":[0.929398,51.942071],"type":"Point"}
}
