{
  "type": "Feature",
  "properties": {
    "iso:country":"GB",
    "wof:name":"BR1 3JP",
    "wof:placetype":"postalcode"
},
  "geometry": {"coordinates":[0.02317266973751,51.41249108543665],"type":"Point"}
}