{
  "type": "Feature",
  "properties": {
    "iso:country":"GB",
    "wof:name":"NW10 7HU",
    "wof:placetype":"postalcode"
},
  "geometry": {"coordinates":[-0.29113006558456,51.53370426883702],"type":"Point"}
}