{
  "type": "Feature",
  "properties": {
    "iso:country":"GB",
    "wof:name":"RH11 8US",
    "wof:placetype":"postalcode"
},
  "geometry": {"coordinates":[-0.21919212854506,51.10099405731597],"type":"Point"}
}