{
  "type": "Feature",
  "properties": {
    "date:inception_lower":"2017-02-01",
    "date:inception_upper":"2017-02-28",
    "iso:country":"GB",
    "wof:name":"CV34 6WG",
    "wof:placetype":"postalcode"
},
  "geometry": {"coordinates":[-1.550932,52.268495],"type":"Point"}
}