{
  "type": "Feature",
  "properties": {
    "iso:country":"GB",
    "wof:name":"BN1 6RA",
    "wof:placetype":"postalcode"
},
  "geometry": {"coordinates":[-0.15108231671691,50.84507717733753],"type":"Point"}
}