{
  "type": "Feature",
  "properties": {
    "iso:country":"GB",
    "wof:name":"TQ2 7LR",
    "wof:placetype":"postalcode"
},
  "geometry": {"coordinates":[-3.56912360556387,50.47714602003548],"type":"Point"}
}