{
  "type": "Feature",
  "properties": {
    "date:inception_lower": "1980-01-01",
    "date:inception_upper": "1980-01-01",
    "iso:country": "GB",
    "wof:name": "TQ2 7LR",
    "wof:placetype": "postalcode"
  },
  "geometry": {"coordinates":[-3.569124,50.477146],"type":"Point"}
}
