{
  "type": "Feature",
  "properties": {
    "iso:country":"GB",
    "wof:name":"RG1 4RD",
    "wof:placetype":"postalcode"
},
  "geometry": {"coordinates":[-0.96148091081462,51.4520030266947],"type":"Point"}
}