{
  "type": "Feature",
  "properties": {
    "iso:country":"GB",
    "wof:name":"ME9 9LS",
    "wof:placetype":"postalcode"
},
  "geometry": {"coordinates":[0.81407655893671,51.33344695914825],"type":"Point"}
}