{
  "type": "Feature",
  "properties": {
    "date:inception_lower": "1980-01-01",
    "date:inception_upper": "1980-01-01",
    "iso:country": "GB",
    "wof:name": "ME9 9LS",
    "wof:placetype": "postalcode"
  },
  "geometry": {"coordinates":[0.814077,51.333447],"type":"Point"}
}
