{
  "type": "Feature",
  "properties": {
    "date:inception_lower":"1980-01-01",
    "date:inception_upper":"1980-01-31",
    "iso:country":"GB",
    "wof:name":"SA73 1BN",
    "wof:placetype":"postalcode"
},
  "geometry": {"coordinates":[-5.022959,51.717294],"type":"Point"}
}