{
  "type": "Feature",
  "properties": {
    "iso:country":"GB",
    "wof:name":"BS8 3SG",
    "wof:placetype":"postalcode"
},
  "geometry": {"coordinates":[-2.67690842868795,51.45777359886664],"type":"Point"}
}