{
  "type": "Feature",
  "properties": {
    "iso:country": "GB",
    "wof:name": "WF3 4ND",
    "wof:placetype": "postalcode"
  },
  "geometry": {"coordinates":[-1.479255,53.701177],"type":"Point"}
}
