{
  "type": "Feature",
  "properties": {
    "iso:country":"GB",
    "wof:name":"SW1P 2AA",
    "wof:placetype":"postalcode"
},
  "geometry": {"coordinates":[-0.12932783702364,51.49463614656778],"type":"Point"}
}