{
  "type": "Feature",
  "properties": {
    "iso:country": "GB",
    "wof:name": "DE13 8FD",
    "wof:placetype": "postalcode"
  },
  "geometry": {"coordinates":[-1.714395,52.75653],"type":"Point"}
}
