{
  "type": "Feature",
  "properties": {
    "iso:country": "GB",
    "wof:name": "CM77 8QG",
    "wof:placetype": "postalcode"
  },
  "geometry": {"coordinates":[0.535066,51.860381],"type":"Point"}
}
