{
  "type": "Feature",
  "properties": {
    "iso:country": "GB",
    "wof:name": "OX26 1DW",
    "wof:placetype": "postalcode"
  },
  "geometry": {"coordinates":[-1.168395,51.89442],"type":"Point"}
}
