{
  "type": "Feature",
  "properties": {
    "iso:country":"GB",
    "wof:name":"LN6 0DF",
    "wof:placetype":"postalcode"
},
  "geometry": {"coordinates":[-0.58115320500897,53.21275745311258],"type":"Point"}
}