{
  "type": "Feature",
  "properties": {
    "iso:country": "GB",
    "wof:name": "LN6 0DF",
    "wof:placetype": "postalcode"
  },
  "geometry": {"coordinates":[-0.581153,53.212757],"type":"Point"}
}
