{
  "type": "Feature",
  "properties": {
    "iso:country":"GB",
    "wof:name":"GL18 1RZ",
    "wof:placetype":"postalcode"
},
  "geometry": {"coordinates":[-2.40198058877051,51.92864126107145],"type":"Point"}
}