{
  "type": "Feature",
  "properties": {
    "date:inception_lower":"1980-01-01",
    "date:inception_upper":"1980-01-31",
    "iso:country":"GB",
    "wof:name":"TR14 8PB",
    "wof:placetype":"postalcode"
},
  "geometry": {"coordinates":[-5.283594,50.223259],"type":"Point"}
}