{
  "type": "Feature",
  "properties": {
    "iso:country":"GB",
    "wof:name":"TR14 8PB",
    "wof:placetype":"postalcode"
},
  "geometry": {"coordinates":[-5.28320696478054,50.2234496987343],"type":"Point"}
}