{
  "type": "Feature",
  "properties": {
    "date:inception_lower": "2020-12-01",
    "date:inception_upper": "2020-12-01",
    "iso:country": "GB",
    "wof:name": "PE28 5WE",
    "wof:placetype": "postalcode"
  },
  "geometry": {"coordinates":[-0.291116,52.436189],"type":"Point"}
}
