{
  "type": "Feature",
  "properties": {
    "iso:country":"GB",
    "wof:name":"BD20 8UP",
    "wof:placetype":"postalcode"
},
  "geometry": {"coordinates":[-1.97050359406167,53.89502422707979],"type":"Point"}
}