{
  "type": "Feature",
  "properties": {
    "iso:country": "GB",
    "wof:name": "BD20 8UP",
    "wof:placetype": "postalcode"
  },
  "geometry": {"coordinates":[-1.970504,53.895024],"type":"Point"}
}
