{
  "type": "Feature",
  "properties": {
    "date:inception_lower": "1980-01-01",
    "date:inception_upper": "1980-01-01",
    "iso:country": "GB",
    "wof:name": "BD20 8UP",
    "wof:placetype": "postalcode"
  },
  "geometry": {"coordinates":[-1.970504,53.895024],"type":"Point"}
}
