{
  "type": "Feature",
  "properties": {
    "iso:country":"GB",
    "wof:name":"ML11 8NH",
    "wof:placetype":"postalcode"
},
  "geometry": {"coordinates":[-3.56801257309506,55.69634124967203],"type":"Point"}
}