{
  "type": "Feature",
  "properties": {
    "iso:country": "GB",
    "wof:name": "NE21 6BF",
    "wof:placetype": "postalcode"
  },
  "geometry": {"coordinates":[-1.728744,54.956297],"type":"Point"}
}
