{
  "type": "Feature",
  "properties": {
    "iso:country": "GB",
    "wof:name": "SY11 4FF",
    "wof:placetype": "postalcode"
  },
  "geometry": {"coordinates":[-3.027418,52.880874],"type":"Point"}
}
