{
  "type": "Feature",
  "properties": {
    "iso:country":"GB",
    "wof:name":"RH14 9DB",
    "wof:placetype":"postalcode"
},
  "geometry": {"coordinates":[-0.44316411142142,51.01890287965823],"type":"Point"}
}