{
  "type": "Feature",
  "properties": {
    "iso:country":"GB",
    "wof:name":"DT4 8TX",
    "wof:placetype":"postalcode"
},
  "geometry": {"coordinates":[-2.4508356987984,50.60707093086565],"type":"Point"}
}