{
  "type": "Feature",
  "properties": {
    "iso:country":"GB",
    "wof:name":"TR20 9EN",
    "wof:placetype":"postalcode"
},
  "geometry": {"coordinates":[-5.40767707864365,50.13700527312113],"type":"Point"}
}