{
  "type": "Feature",
  "properties": {
    "date:inception_lower":"2004-06-01",
    "date:inception_upper":"2004-06-30",
    "iso:country":"GB",
    "wof:name":"DT1 3TT",
    "wof:placetype":"postalcode"
},
  "geometry": {"coordinates":[-2.464639,50.714418],"type":"Point"}
}