{
  "type": "Feature",
  "properties": {
    "iso:country":"GB",
    "wof:name":"DT1 3TT",
    "wof:placetype":"postalcode"
},
  "geometry": {"coordinates":[-2.46465541840468,50.71441786486027],"type":"Point"}
}