{
  "type": "Feature",
  "properties": {
    "date:inception_lower": "1980-01-01",
    "date:inception_upper": "1980-01-01",
    "iso:country": "GB",
    "wof:name": "SY23 3NY",
    "wof:placetype": "postalcode"
  },
  "geometry": {"coordinates":[-3.929366,52.412739],"type":"Point"}
}
