{
  "type": "Feature",
  "properties": {
    "iso:country":"GB",
    "wof:name":"SY23 3NY",
    "wof:placetype":"postalcode"
},
  "geometry": {"coordinates":[-3.92936630896596,52.41273855175663],"type":"Point"}
}