{
  "type": "Feature",
  "properties": {
    "date:inception_lower": "1980-01-01",
    "date:inception_upper": "1980-01-01",
    "iso:country": "GB",
    "wof:name": "L9 1EQ",
    "wof:placetype": "postalcode"
  },
  "geometry": {"coordinates":[-2.970767,53.448515],"type":"Point"}
}
