{
  "type": "Feature",
  "properties": {
    "iso:country":"GB",
    "wof:name":"W1H 1EF",
    "wof:placetype":"postalcode"
},
  "geometry": {"coordinates":[-0.16224386247525,51.52083014946739],"type":"Point"}
}