{
  "type": "Feature",
  "properties": {
    "iso:country": "GB",
    "wof:name": "W1H 1EF",
    "wof:placetype": "postalcode"
  },
  "geometry": {"coordinates":[-0.162244,51.52083],"type":"Point"}
}
