{
  "type": "Feature",
  "properties": {
    "iso:country":"GB",
    "wof:name":"CV2 2NE",
    "wof:placetype":"postalcode"
},
  "geometry": {"coordinates":[-1.44230662900591,52.41718368178972],"type":"Point"}
}