{
  "type": "Feature",
  "properties": {
    "date:inception_lower": "1991-01-01",
    "date:inception_upper": "1991-01-01",
    "iso:country": "GB",
    "wof:name": "LU4 8EF",
    "wof:placetype": "postalcode"
  },
  "geometry": {"coordinates":[-0.448338,51.888497],"type":"Point"}
}
