{
  "type": "Feature",
  "properties": {
    "iso:country":"GB",
    "wof:name":"LU4 8EF",
    "wof:placetype":"postalcode"
},
  "geometry": {"coordinates":[-0.44826423831565,51.88841522218145],"type":"Point"}
}