{
  "type": "Feature",
  "properties": {
    "iso:country": "GB",
    "wof:name": "LU4 8EF",
    "wof:placetype": "postalcode"
  },
  "geometry": {"coordinates":[-0.448338,51.888497],"type":"Point"}
}
