{
  "type": "Feature",
  "properties": {
    "iso:country":"GB",
    "wof:name":"E14 9NB",
    "wof:placetype":"postalcode"
},
  "geometry": {"coordinates":[-0.01821967325544,51.4977840211433],"type":"Point"}
}