{
  "type": "Feature",
  "properties": {
    "iso:country":"GB",
    "wof:name":"DN7 5EA",
    "wof:placetype":"postalcode"
},
  "geometry": {"coordinates":[-1.02269923499636,53.59780471549424],"type":"Point"}
}