{
  "type": "Feature",
  "properties": {
    "iso:country":"GB",
    "wof:name":"DA15 9LB",
    "wof:placetype":"postalcode"
},
  "geometry": {"coordinates":[0.11166768676424,51.44329531760958],"type":"Point"}
}