{
  "type": "Feature",
  "properties": {
    "date:inception_lower":"1992-08-01",
    "date:inception_upper":"1992-08-31",
    "iso:country":"GB",
    "wof:name":"SG6 4YJ",
    "wof:placetype":"postalcode"
},
  "geometry": {"coordinates":[-0.239997,51.985491],"type":"Point"}
}