{
  "type": "Feature",
  "properties": {
    "iso:country": "GB",
    "wof:name": "SG6 4YJ",
    "wof:placetype": "postalcode"
  },
  "geometry": {"coordinates":[-0.239997,51.985491],"type":"Point"}
}
