{
  "type": "Feature",
  "properties": {
    "iso:country": "GB",
    "wof:name": "HP11 2TE",
    "wof:placetype": "postalcode"
  },
  "geometry": {"coordinates":[-0.761777,51.631808],"type":"Point"}
}
