{
  "type": "Feature",
  "properties": {
    "iso:country":"GB",
    "wof:name":"HP11 2TE",
    "wof:placetype":"postalcode"
},
  "geometry": {"coordinates":[-0.76177663884518,51.63180811590568],"type":"Point"}
}