{
  "type": "Feature",
  "properties": {
    "date:inception_lower": "1981-09-01",
    "date:inception_upper": "1981-09-01",
    "iso:country": "GB",
    "wof:name": "HP11 2TE",
    "wof:placetype": "postalcode"
  },
  "geometry": {"coordinates":[-0.761777,51.631808],"type":"Point"}
}
