{
  "type": "Feature",
  "properties": {
    "iso:country":"GB",
    "wof:name":"LS9 8RR",
    "wof:placetype":"postalcode"
},
  "geometry": {"coordinates":[-1.52308820996087,53.79115127556806],"type":"Point"}
}