{
  "type": "Feature",
  "properties": {
    "date:inception_lower":"1983-07-01",
    "date:inception_upper":"1983-07-31",
    "iso:country":"GB",
    "wof:name":"LS9 8RR",
    "wof:placetype":"postalcode"
},
  "geometry": {"coordinates":[-1.523088,53.791151],"type":"Point"}
}