{
  "type": "Feature",
  "properties": {
    "iso:country":"GB",
    "wof:name":"TA1 1DP",
    "wof:placetype":"postalcode"
},
  "geometry": {"coordinates":[-3.11299990325336,51.02297862544321],"type":"Point"}
}