{
  "type": "Feature",
  "properties": {
    "iso:country":"GB",
    "wof:name":"SN1 3LQ",
    "wof:placetype":"postalcode"
},
  "geometry": {"coordinates":[-1.77966316036722,51.55458024588793],"type":"Point"}
}