{
  "type": "Feature",
  "properties": {
    "iso:country":"GB",
    "wof:name":"BA2 7UW",
    "wof:placetype":"postalcode"
},
  "geometry": {"coordinates":[-2.31523478142752,51.33769244719904],"type":"Point"}
}