{
  "type": "Feature",
  "properties": {
    "iso:country":"GB",
    "wof:name":"E13 9PJ",
    "wof:placetype":"postalcode"
},
  "geometry": {"coordinates":[0.03678330597288,51.52998873325306],"type":"Point"}
}