{
  "type": "Feature",
  "properties": {
    "date:inception_lower": "1983-07-01",
    "date:inception_upper": "1983-07-01",
    "iso:country": "GB",
    "wof:name": "NR3 2BT",
    "wof:placetype": "postalcode"
  },
  "geometry": {"coordinates":[1.26261,52.646094],"type":"Point"}
}
