{
  "type": "Feature",
  "properties": {
    "iso:country":"GB",
    "wof:name":"SK15 1HJ",
    "wof:placetype":"postalcode"
},
  "geometry": {"coordinates":[-2.05666834699525,53.49574440548538],"type":"Point"}
}