{
  "type": "Feature",
  "properties": {
    "iso:country":"GB",
    "wof:name":"RG7 4AJ",
    "wof:placetype":"postalcode"
},
  "geometry": {"coordinates":[-1.07154237816567,51.42952931514341],"type":"Point"}
}