{
  "type": "Feature",
  "properties": {
    "iso:country":"GB",
    "wof:name":"AL3 5RX",
    "wof:placetype":"postalcode"
},
  "geometry": {"coordinates":[-0.34428952255631,51.76382789149004],"type":"Point"}
}