{
  "type": "Feature",
  "properties": {
    "iso:country":"GB",
    "wof:name":"W1J 8NY",
    "wof:placetype":"postalcode"
},
  "geometry": {"coordinates":[-0.14333194174025,51.50913882066614],"type":"Point"}
}