{
  "type": "Feature",
  "properties": {
    "iso:country":"GB",
    "wof:name":"NW2 1HX",
    "wof:placetype":"postalcode"
},
  "geometry": {"coordinates":[-0.20672186619095,51.56496979946025],"type":"Point"}
}