{
  "type": "Feature",
  "properties": {
    "date:inception_lower":"1984-10-01",
    "date:inception_upper":"1984-10-31",
    "iso:country":"GB",
    "wof:name":"SR4 7DA",
    "wof:placetype":"postalcode"
},
  "geometry": {"coordinates":[-1.404429,54.903615],"type":"Point"}
}