{
  "type": "Feature",
  "properties": {
    "iso:country":"GB",
    "wof:name":"SR4 7DA",
    "wof:placetype":"postalcode"
},
  "geometry": {"coordinates":[-1.40442899551631,54.90361530653879],"type":"Point"}
}