{
  "type": "Feature",
  "properties": {
    "iso:country":"GB",
    "wof:name":"ML9 1PG",
    "wof:placetype":"postalcode"
},
  "geometry": {"coordinates":[-3.96695177694838,55.72296801745306],"type":"Point"}
}