{
  "type": "Feature",
  "properties": {
    "date:inception_lower": "1980-01-01",
    "date:inception_upper": "1980-01-01",
    "iso:country": "GB",
    "wof:name": "ML9 1PG",
    "wof:placetype": "postalcode"
  },
  "geometry": {"coordinates":[-3.966952,55.722968],"type":"Point"}
}
