{
  "type": "Feature",
  "properties": {
    "iso:country": "GB",
    "wof:name": "PO10 8NA",
    "wof:placetype": "postalcode"
  },
  "geometry": {"coordinates":[-0.908987,50.851944],"type":"Point"}
}
