{
  "type": "Feature",
  "properties": {
    "date:inception_lower": "1980-01-01",
    "date:inception_upper": "1980-01-01",
    "iso:country": "GB",
    "wof:name": "PO10 8NA",
    "wof:placetype": "postalcode"
  },
  "geometry": {"coordinates":[-0.908987,50.851944],"type":"Point"}
}
