{
  "type": "Feature",
  "properties": {
    "date:inception_lower": "2017-02-01",
    "date:inception_upper": "2017-02-01",
    "iso:country": "GB",
    "wof:name": "HP22 7AE",
    "wof:placetype": "postalcode"
  },
  "geometry": {"coordinates":[-0.78337,51.822708],"type":"Point"}
}
