{
  "type": "Feature",
  "properties": {
    "iso:country": "GB",
    "wof:name": "PL19 9NF",
    "wof:placetype": "postalcode"
  },
  "geometry": {"coordinates":[-4.104125,50.600968],"type":"Point"}
}
