{
  "type": "Feature",
  "properties": {
    "iso:country":"GB",
    "wof:name":"PL19 9NF",
    "wof:placetype":"postalcode"
},
  "geometry": {"coordinates":[-4.10412489190558,50.6009676744813],"type":"Point"}
}