{
  "type": "Feature",
  "properties": {
    "iso:country":"GB",
    "wof:name":"HG3 2PS",
    "wof:placetype":"postalcode"
},
  "geometry": {"coordinates":[-1.67978681774352,54.02996598919664],"type":"Point"}
}