{
  "type": "Feature",
  "properties": {
    "iso:country":"GB",
    "wof:name":"CM2 9EQ",
    "wof:placetype":"postalcode"
},
  "geometry": {"coordinates":[0.47433546937877,51.71831754492887],"type":"Point"}
}