{
  "type": "Feature",
  "properties": {
    "date:inception_lower": "1980-01-01",
    "date:inception_upper": "1980-01-01",
    "iso:country": "GB",
    "wof:name": "CM2 9EQ",
    "wof:placetype": "postalcode"
  },
  "geometry": {"coordinates":[0.474336,51.718318],"type":"Point"}
}
