{
  "type": "Feature",
  "properties": {
    "iso:country": "GB",
    "wof:name": "SA5 4HJ",
    "wof:placetype": "postalcode"
  },
  "geometry": {"coordinates":[-3.996524,51.648183],"type":"Point"}
}
