{
  "type": "Feature",
  "properties": {
    "date:inception_lower": "1998-06-01",
    "date:inception_upper": "1998-06-01",
    "iso:country": "GB",
    "wof:name": "SA5 4HJ",
    "wof:placetype": "postalcode"
  },
  "geometry": {"coordinates":[-3.996524,51.648183],"type":"Point"}
}
