{
  "type": "Feature",
  "properties": {
    "iso:country":"GB",
    "wof:name":"B75 7HY",
    "wof:placetype":"postalcode"
},
  "geometry": {"coordinates":[-1.7694694499359,52.56371295392247],"type":"Point"}
}