{
  "type": "Feature",
  "properties": {
    "date:inception_lower": "2003-01-01",
    "date:inception_upper": "2003-01-01",
    "iso:country": "GB",
    "wof:name": "BN1 3AY",
    "wof:placetype": "postalcode"
  },
  "geometry": {"coordinates":[-0.152766,50.828349],"type":"Point"}
}
