{
  "type": "Feature",
  "properties": {
    "date:inception_lower":"1980-01-01",
    "date:inception_upper":"1980-01-31",
    "iso:country":"GB",
    "wof:name":"SS9 4QY",
    "wof:placetype":"postalcode"
},
  "geometry": {"coordinates":[0.639279,51.561088],"type":"Point"}
}