{
  "type": "Feature",
  "properties": {
    "iso:country":"GB",
    "wof:name":"SS9 4QY",
    "wof:placetype":"postalcode"
},
  "geometry": {"coordinates":[0.63970956302427,51.56103715851692],"type":"Point"}
}