{
  "type": "Feature",
  "properties": {
    "iso:country": "GB",
    "wof:name": "SS9 4QY",
    "wof:placetype": "postalcode"
  },
  "geometry": {"coordinates":[0.639279,51.561088],"type":"Point"}
}
