{
  "type": "Feature",
  "properties": {
    "date:inception_lower": "1980-01-01",
    "date:inception_upper": "1980-01-01",
    "iso:country": "GB",
    "wof:name": "SL5 0AW",
    "wof:placetype": "postalcode"
  },
  "geometry": {"coordinates":[-0.645292,51.40003],"type":"Point"}
}
