{
  "type": "Feature",
  "properties": {
    "iso:country": "GB",
    "wof:name": "SL5 0AW",
    "wof:placetype": "postalcode"
  },
  "geometry": {"coordinates":[-0.645292,51.40003],"type":"Point"}
}
