{
  "type": "Feature",
  "properties": {
    "iso:country":"GB",
    "wof:name":"TR15 3ET",
    "wof:placetype":"postalcode"
},
  "geometry": {"coordinates":[-5.2770023363826,50.22519036692982],"type":"Point"}
}