{
  "type": "Feature",
  "properties": {
    "iso:country":"GB",
    "wof:name":"NW2 5AZ",
    "wof:placetype":"postalcode"
},
  "geometry": {"coordinates":[-0.2400022401323,51.55166146043213],"type":"Point"}
}