{
  "type": "Feature",
  "properties": {
    "iso:country":"GB",
    "wof:name":"B65 0JY",
    "wof:placetype":"postalcode"
},
  "geometry": {"coordinates":[-2.03302497434067,52.47792583660294],"type":"Point"}
}