{
  "type": "Feature",
  "properties": {
    "iso:country":"GB",
    "wof:name":"KA30 8DG",
    "wof:placetype":"postalcode"
},
  "geometry": {"coordinates":[-4.86902641804227,55.79287882329081],"type":"Point"}
}