{
  "type": "Feature",
  "properties": {
    "date:inception_lower":"1980-01-01",
    "date:inception_upper":"1980-01-31",
    "iso:country":"GB",
    "wof:name":"KA30 8DG",
    "wof:placetype":"postalcode"
},
  "geometry": {"coordinates":[-4.869026,55.792879],"type":"Point"}
}