{
  "type": "Feature",
  "properties": {
    "iso:country":"GB",
    "wof:name":"WA10 4QL",
    "wof:placetype":"postalcode"
},
  "geometry": {"coordinates":[-2.76824163318753,53.45415078822499],"type":"Point"}
}