{
  "type": "Feature",
  "properties": {
    "iso:country":"GB",
    "wof:name":"TN22 3QN",
    "wof:placetype":"postalcode"
},
  "geometry": {"coordinates":[0.00839200001196,51.00219238944306],"type":"Point"}
}