{
  "type": "Feature",
  "properties": {
    "iso:country": "GB",
    "wof:name": "TN22 3QN",
    "wof:placetype": "postalcode"
  },
  "geometry": {"coordinates":[0.008433,51.002147],"type":"Point"}
}
