{
  "type": "Feature",
  "properties": {
    "date:inception_lower":"1980-01-01",
    "date:inception_upper":"1980-01-31",
    "iso:country":"GB",
    "wof:name":"MK11 1DA",
    "wof:placetype":"postalcode"
},
  "geometry": {"coordinates":[-0.844443,52.059093],"type":"Point"}
}