{
  "type": "Feature",
  "properties": {
    "iso:country": "GB",
    "wof:name": "MK11 1DA",
    "wof:placetype": "postalcode"
  },
  "geometry": {"coordinates":[-0.844443,52.059093],"type":"Point"}
}
