{
  "type": "Feature",
  "properties": {
    "iso:country":"GB",
    "wof:name":"NE5 3ES",
    "wof:placetype":"postalcode"
},
  "geometry": {"coordinates":[-1.66055553292588,54.99523572124698],"type":"Point"}
}