{
  "type": "Feature",
  "properties": {
    "iso:country": "GB",
    "wof:name": "PO4 8YP",
    "wof:placetype": "postalcode"
  },
  "geometry": {"coordinates":[-1.043667,50.798781],"type":"Point"}
}
