{
  "type": "Feature",
  "properties": {
    "iso:country": "GB",
    "wof:name": "BL9 0DF",
    "wof:placetype": "postalcode"
  },
  "geometry": {"coordinates":[-2.298839,53.591757],"type":"Point"}
}
