{
  "type": "Feature",
  "properties": {
    "iso:country":"GB",
    "wof:name":"YO11 2AW",
    "wof:placetype":"postalcode"
},
  "geometry": {"coordinates":[-0.39903339227322,54.27314044147652],"type":"Point"}
}