{
  "type": "Feature",
  "properties": {
    "iso:country":"GB",
    "wof:name":"IG8 7NB",
    "wof:placetype":"postalcode"
},
  "geometry": {"coordinates":[0.03840980819602,51.60863713659072],"type":"Point"}
}