{
  "type": "Feature",
  "properties": {
    "iso:country": "GB",
    "wof:name": "IG8 7NB",
    "wof:placetype": "postalcode"
  },
  "geometry": {"coordinates":[0.03841,51.608637],"type":"Point"}
}
