{
  "type": "Feature",
  "properties": {
    "iso:country": "GB",
    "wof:name": "PO15 6NQ",
    "wof:placetype": "postalcode"
  },
  "geometry": {"coordinates":[-1.212221,50.85995],"type":"Point"}
}
