{
  "type": "Feature",
  "properties": {
    "iso:country":"GB",
    "wof:name":"PO15 6NQ",
    "wof:placetype":"postalcode"
},
  "geometry": {"coordinates":[-1.21222132728629,50.85995026833242],"type":"Point"}
}