{
  "type": "Feature",
  "properties": {
    "iso:country":"GB",
    "wof:name":"BS20 8JY",
    "wof:placetype":"postalcode"
},
  "geometry": {"coordinates":[-2.7918028557581,51.46907567532172],"type":"Point"}
}