{
  "type": "Feature",
  "properties": {
    "date:inception_lower": "1980-01-01",
    "date:inception_upper": "1980-01-01",
    "iso:country": "GB",
    "wof:name": "BS20 8JY",
    "wof:placetype": "postalcode"
  },
  "geometry": {"coordinates":[-2.794781,51.469584],"type":"Point"}
}
