{
  "type": "Feature",
  "properties": {
    "iso:country":"GB",
    "wof:name":"B48 7HR",
    "wof:placetype":"postalcode"
},
  "geometry": {"coordinates":[-1.88291711317733,52.3454042084435],"type":"Point"}
}