{
  "type": "Feature",
  "properties": {
    "iso:country": "GB",
    "wof:name": "B48 7HR",
    "wof:placetype": "postalcode"
  },
  "geometry": {"coordinates":[-1.882917,52.345404],"type":"Point"}
}
