{
  "type": "Feature",
  "properties": {
    "iso:country": "GB",
    "wof:name": "CA28 6ES",
    "wof:placetype": "postalcode"
  },
  "geometry": {"coordinates":[-3.580853,54.561334],"type":"Point"}
}
