{
  "type": "Feature",
  "properties": {
    "iso:country":"GB",
    "wof:name":"NG3 4QF",
    "wof:placetype":"postalcode"
},
  "geometry": {"coordinates":[-1.14277916730888,52.96444153276647],"type":"Point"}
}