{
  "type": "Feature",
  "properties": {
    "iso:country":"GB",
    "wof:name":"OL6 6TF",
    "wof:placetype":"postalcode"
},
  "geometry": {"coordinates":[-2.08230612735093,53.48673203597992],"type":"Point"}
}