{
  "type": "Feature",
  "properties": {
    "iso:country":"GB",
    "wof:name":"PA2 6NG",
    "wof:placetype":"postalcode"
},
  "geometry": {"coordinates":[-4.42068015195453,55.83514603330305],"type":"Point"}
}