{
  "type": "Feature",
  "properties": {
    "iso:country": "GB",
    "wof:name": "GU15 1AN",
    "wof:placetype": "postalcode"
  },
  "geometry": {"coordinates":[-0.712491,51.332645],"type":"Point"}
}
