{
  "type": "Feature",
  "properties": {
    "iso:country":"GB",
    "wof:name":"YO31 9AD",
    "wof:placetype":"postalcode"
},
  "geometry": {"coordinates":[-1.06852148118759,53.97444855350064],"type":"Point"}
}