{
  "type": "Feature",
  "properties": {
    "iso:country": "GB",
    "wof:name": "SO23 3SR",
    "wof:placetype": "postalcode"
  },
  "geometry": {"coordinates":[-1.311328,51.061072],"type":"Point"}
}
