{
  "type": "Feature",
  "properties": {
    "iso:country":"GB",
    "wof:name":"PL21 0DX",
    "wof:placetype":"postalcode"
},
  "geometry": {"coordinates":[-3.87956849367377,50.39661743013062],"type":"Point"}
}