{
  "type": "Feature",
  "properties": {
    "date:inception_lower":"1980-01-01",
    "date:inception_upper":"1980-01-31",
    "iso:country":"GB",
    "wof:name":"PL21 0DX",
    "wof:placetype":"postalcode"
},
  "geometry": {"coordinates":[-3.879568,50.396617],"type":"Point"}
}