{
  "type": "Feature",
  "properties": {
    "iso:country":"GB",
    "wof:name":"HA2 8PT",
    "wof:placetype":"postalcode"
},
  "geometry": {"coordinates":[-0.36586081902433,51.56023495606335],"type":"Point"}
}