{
  "type": "Feature",
  "properties": {
    "iso:country":"GB",
    "wof:name":"NR35 2BU",
    "wof:placetype":"postalcode"
},
  "geometry": {"coordinates":[1.34905638019996,52.4898334549386],"type":"Point"}
}