{
  "type": "Feature",
  "properties": {
    "iso:country":"GB",
    "wof:name":"AB16 7AX",
    "wof:placetype":"postalcode"
},
  "geometry": {"coordinates":[-2.15362896102351,57.16735343734651],"type":"Point"}
}