{
  "type": "Feature",
  "properties": {
    "date:inception_lower": "1980-01-01",
    "date:inception_upper": "1980-01-01",
    "iso:country": "GB",
    "wof:name": "IV51 9UG",
    "wof:placetype": "postalcode"
  },
  "geometry": {"coordinates":[-6.318246,57.688755],"type":"Point"}
}
