{
  "type": "Feature",
  "properties": {
    "iso:country":"GB",
    "wof:name":"IV51 9UG",
    "wof:placetype":"postalcode"
},
  "geometry": {"coordinates":[-6.31824634151224,57.68875527401012],"type":"Point"}
}