{
  "type": "Feature",
  "properties": {
    "date:inception_lower":"1980-01-01",
    "date:inception_upper":"1980-01-31",
    "iso:country":"GB",
    "wof:name":"DG11 1DS",
    "wof:placetype":"postalcode"
},
  "geometry": {"coordinates":[-3.386557,55.052825],"type":"Point"}
}