{
  "type": "Feature",
  "properties": {
    "iso:country":"GB",
    "wof:name":"N15 4JZ",
    "wof:placetype":"postalcode"
},
  "geometry": {"coordinates":[-0.07761760348536,51.58786184943371],"type":"Point"}
}