{
  "type": "Feature",
  "properties": {
    "iso:country":"GB",
    "wof:name":"NE64 6HU",
    "wof:placetype":"postalcode"
},
  "geometry": {"coordinates":[-1.52127834533428,55.18628906045438],"type":"Point"}
}