{
  "type": "Feature",
  "properties": {
    "iso:country":"GB",
    "wof:name":"RH7 6BS",
    "wof:placetype":"postalcode"
},
  "geometry": {"coordinates":[-0.02236556246694,51.17595364414923],"type":"Point"}
}