{
  "type": "Feature",
  "properties": {
    "iso:country":"GB",
    "wof:name":"EH42 1GB",
    "wof:placetype":"postalcode"
},
  "geometry": {"coordinates":[-2.5194223996964,55.98991086684755],"type":"Point"}
}