{
  "type": "Feature",
  "properties": {
    "iso:country": "GB",
    "wof:name": "PH3 1PA",
    "wof:placetype": "postalcode"
  },
  "geometry": {"coordinates":[-3.700834,56.299261],"type":"Point"}
}
