{
  "type": "Feature",
  "properties": {
    "date:inception_lower": "1999-12-01",
    "date:inception_upper": "1999-12-01",
    "iso:country": "GB",
    "wof:name": "HU13 9PE",
    "wof:placetype": "postalcode"
  },
  "geometry": {"coordinates":[-0.433704,53.724693],"type":"Point"}
}
