{
  "type": "Feature",
  "properties": {
    "iso:country":"GB",
    "wof:name":"HU13 9PE",
    "wof:placetype":"postalcode"
},
  "geometry": {"coordinates":[-0.43370358331595,53.72469260556462],"type":"Point"}
}