{
  "type": "Feature",
  "properties": {
    "iso:country": "GB",
    "wof:name": "EH16 4ER",
    "wof:placetype": "postalcode"
  },
  "geometry": {"coordinates":[-3.125863,55.930226],"type":"Point"}
}
