{
  "type": "Feature",
  "properties": {
    "iso:country":"GB",
    "wof:name":"ST6 5XN",
    "wof:placetype":"postalcode"
},
  "geometry": {"coordinates":[-2.22096007613415,53.06382318737437],"type":"Point"}
}