{
  "type": "Feature",
  "properties": {
    "iso:country": "GB",
    "wof:name": "ST6 5XN",
    "wof:placetype": "postalcode"
  },
  "geometry": {"coordinates":[-2.22096,53.063823],"type":"Point"}
}
