{
  "type": "Feature",
  "properties": {
    "iso:country":"GB",
    "wof:name":"BL4 9EA",
    "wof:placetype":"postalcode"
},
  "geometry": {"coordinates":[-2.39875278100396,53.54743166600765],"type":"Point"}
}