{
  "type": "Feature",
  "properties": {
    "iso:country": "GB",
    "wof:name": "CO6 3JT",
    "wof:placetype": "postalcode"
  },
  "geometry": {"coordinates":[0.851017,51.914921],"type":"Point"}
}
