{
  "type": "Feature",
  "properties": {
    "date:inception_lower":"1999-06-01",
    "date:inception_upper":"1999-06-30",
    "iso:country":"GB",
    "wof:name":"CO6 3JT",
    "wof:placetype":"postalcode"
},
  "geometry": {"coordinates":[0.851017,51.914921],"type":"Point"}
}