{
  "type": "Feature",
  "properties": {
    "iso:country": "GB",
    "wof:name": "DN14 0DA",
    "wof:placetype": "postalcode"
  },
  "geometry": {"coordinates":[-1.080325,53.678044],"type":"Point"}
}
