{
  "type": "Feature",
  "properties": {
    "date:inception_lower":"2008-10-01",
    "date:inception_upper":"2008-10-31",
    "iso:country":"GB",
    "wof:name":"DN14 0DA",
    "wof:placetype":"postalcode"
},
  "geometry": {"coordinates":[-1.080325,53.678044],"type":"Point"}
}