{
  "type": "Feature",
  "properties": {
    "iso:country":"GB",
    "wof:name":"SA2 7LY",
    "wof:placetype":"postalcode"
},
  "geometry": {"coordinates":[-4.0035809193582,51.62145764944837],"type":"Point"}
}