{
  "type": "Feature",
  "properties": {
    "date:inception_lower":"2014-08-01",
    "date:inception_upper":"2014-08-31",
    "iso:country":"GB",
    "wof:name":"CT17 9FA",
    "wof:placetype":"postalcode"
},
  "geometry": {"coordinates":[1.31092,51.125818],"type":"Point"}
}