{
  "type": "Feature",
  "properties": {
    "iso:country":"GB",
    "wof:name":"CT17 9FA",
    "wof:placetype":"postalcode"
},
  "geometry": {"coordinates":[1.31091985154922,51.12581829477799],"type":"Point"}
}