{
  "type": "Feature",
  "properties": {
    "iso:country": "GB",
    "wof:name": "FK1 1EN",
    "wof:placetype": "postalcode"
  },
  "geometry": {"coordinates":[-3.786799,55.999742],"type":"Point"}
}
