{
  "type": "Feature",
  "properties": {
    "date:inception_lower":"1980-01-01",
    "date:inception_upper":"1980-01-31",
    "iso:country":"GB",
    "wof:name":"EX32 0NJ",
    "wof:placetype":"postalcode"
},
  "geometry": {"coordinates":[-3.995269,51.0601],"type":"Point"}
}