{
  "type": "Feature",
  "properties": {
    "iso:country": "GB",
    "wof:name": "EX32 0NJ",
    "wof:placetype": "postalcode"
  },
  "geometry": {"coordinates":[-3.995269,51.0601],"type":"Point"}
}
