{
  "type": "Feature",
  "properties": {
    "iso:country":"GB",
    "wof:name":"DH8 6GF",
    "wof:placetype":"postalcode"
},
  "geometry": {"coordinates":[-1.83018069981168,54.85333754320808],"type":"Point"}
}