{
  "type": "Feature",
  "properties": {
    "iso:country": "GB",
    "wof:name": "DH8 6GF",
    "wof:placetype": "postalcode"
  },
  "geometry": {"coordinates":[-1.830181,54.853338],"type":"Point"}
}
