{
  "type": "Feature",
  "properties": {
    "iso:country":"GB",
    "wof:name":"DL17 8SX",
    "wof:placetype":"postalcode"
},
  "geometry": {"coordinates":[-1.53812923729902,54.68762072441813],"type":"Point"}
}