{
  "type": "Feature",
  "properties": {
    "date:inception_lower": "1980-01-01",
    "date:inception_upper": "1980-01-01",
    "iso:country": "GB",
    "wof:name": "FY6 8LY",
    "wof:placetype": "postalcode"
  },
  "geometry": {"coordinates":[-2.947311,53.84904],"type":"Point"}
}
