{
  "type": "Feature",
  "properties": {
    "iso:country":"GB",
    "wof:name":"FY6 8LY",
    "wof:placetype":"postalcode"
},
  "geometry": {"coordinates":[-2.94731604321435,53.84902570071483],"type":"Point"}
}