{
  "type": "Feature",
  "properties": {
    "iso:country": "GB",
    "wof:name": "FY6 8LY",
    "wof:placetype": "postalcode"
  },
  "geometry": {"coordinates":[-2.947311,53.84904],"type":"Point"}
}
