{
  "type": "Feature",
  "properties": {
    "iso:country":"GB",
    "wof:name":"KA23 9QD",
    "wof:placetype":"postalcode"
},
  "geometry": {"coordinates":[-4.87917649676147,55.70685739716249],"type":"Point"}
}