{
  "type": "Feature",
  "properties": {
    "date:inception_lower": "2023-12-01",
    "date:inception_upper": "2023-12-01",
    "iso:country": "GB",
    "wof:name": "E14 8QQ",
    "wof:placetype": "postalcode"
  },
  "geometry": {"coordinates":[-0.021751,51.496802],"type":"Point"}
}
