{
  "type": "Feature",
  "properties": {
    "iso:country":"GB",
    "wof:name":"NP10 8LF",
    "wof:placetype":"postalcode"
},
  "geometry": {"coordinates":[-3.04899824385585,51.57739428949255],"type":"Point"}
}