{
  "type": "Feature",
  "properties": {
    "iso:country": "GB",
    "wof:name": "SY7 8JL",
    "wof:placetype": "postalcode"
  },
  "geometry": {"coordinates":[-3.033858,52.418048],"type":"Point"}
}
