{
  "type": "Feature",
  "properties": {
    "iso:country":"GB",
    "wof:name":"SY7 8JL",
    "wof:placetype":"postalcode"
},
  "geometry": {"coordinates":[-3.03385836823958,52.41804802906141],"type":"Point"}
}