{
  "type": "Feature",
  "properties": {
    "iso:country":"GB",
    "wof:name":"KT3 5AQ",
    "wof:placetype":"postalcode"
},
  "geometry": {"coordinates":[-0.26815194986371,51.40087284241437],"type":"Point"}
}