{
  "type": "Feature",
  "properties": {
    "iso:country": "GB",
    "wof:name": "NR5 9AZ",
    "wof:placetype": "postalcode"
  },
  "geometry": {"coordinates":[1.228254,52.639232],"type":"Point"}
}
