{
  "type": "Feature",
  "properties": {
    "date:inception_lower":"1980-01-01",
    "date:inception_upper":"1980-01-31",
    "iso:country":"GB",
    "wof:name":"NR5 9AZ",
    "wof:placetype":"postalcode"
},
  "geometry": {"coordinates":[1.228254,52.639232],"type":"Point"}
}