{
  "type": "Feature",
  "properties": {
    "iso:country":"GB",
    "wof:name":"SG5 4ED",
    "wof:placetype":"postalcode"
},
  "geometry": {"coordinates":[-0.23070413636975,52.0169489723635],"type":"Point"}
}