{
  "type": "Feature",
  "properties": {
    "iso:country":"GB",
    "wof:name":"PL21 9QN",
    "wof:placetype":"postalcode"
},
  "geometry": {"coordinates":[-3.9650547937965,50.4185709513431],"type":"Point"}
}