{
  "type": "Feature",
  "properties": {
    "iso:country":"GB",
    "wof:name":"CV2 4LS",
    "wof:placetype":"postalcode"
},
  "geometry": {"coordinates":[-1.48337998872828,52.41407079338632],"type":"Point"}
}