{
  "type": "Feature",
  "properties": {
    "iso:country":"GB",
    "wof:name":"BD16 4ND",
    "wof:placetype":"postalcode"
},
  "geometry": {"coordinates":[-1.83092936047603,53.85082369318294],"type":"Point"}
}