{
  "type": "Feature",
  "properties": {
    "iso:country": "GB",
    "wof:name": "BD16 4ND",
    "wof:placetype": "postalcode"
  },
  "geometry": {"coordinates":[-1.830929,53.850824],"type":"Point"}
}
