{
  "type": "Feature",
  "properties": {
    "iso:country": "GB",
    "wof:name": "IG1 1JQ",
    "wof:placetype": "postalcode"
  },
  "geometry": {"coordinates":[0.079839,51.558864],"type":"Point"}
}
