{
  "type": "Feature",
  "properties": {
    "iso:country":"GB",
    "wof:name":"IG1 1JQ",
    "wof:placetype":"postalcode"
},
  "geometry": {"coordinates":[0.07983897598938,51.5588642286775],"type":"Point"}
}