{
  "type": "Feature",
  "properties": {
    "date:inception_lower": "2005-10-01",
    "date:inception_upper": "2005-10-01",
    "iso:country": "GB",
    "wof:name": "IG1 1JQ",
    "wof:placetype": "postalcode"
  },
  "geometry": {"coordinates":[0.079357,51.558784],"type":"Point"}
}
