{
  "type": "Feature",
  "properties": {
    "iso:country":"GB",
    "wof:name":"AB42 3GG",
    "wof:placetype":"postalcode"
},
  "geometry": {"coordinates":[-1.82261051751221,57.50525402155364],"type":"Point"}
}