{
  "type": "Feature",
  "properties": {
    "iso:country": "GB",
    "wof:name": "LE7 2JN",
    "wof:placetype": "postalcode"
  },
  "geometry": {"coordinates":[-1.080003,52.693426],"type":"Point"}
}
