{
  "type": "Feature",
  "properties": {
    "iso:country":"GB",
    "wof:name":"LE67 3DF",
    "wof:placetype":"postalcode"
},
  "geometry": {"coordinates":[-1.37729639920028,52.71778034154315],"type":"Point"}
}