{
  "type": "Feature",
  "properties": {
    "iso:country": "GB",
    "wof:name": "G69 8FH",
    "wof:placetype": "postalcode"
  },
  "geometry": {"coordinates":[-4.104165,55.878823],"type":"Point"}
}
