{
  "type": "Feature",
  "properties": {
    "iso:country":"GB",
    "wof:name":"G69 8FH",
    "wof:placetype":"postalcode"
},
  "geometry": {"coordinates":[-4.10416472470094,55.87882304154775],"type":"Point"}
}