{
  "type": "Feature",
  "properties": {
    "date:inception_lower":"2007-10-01",
    "date:inception_upper":"2007-10-31",
    "iso:country":"GB",
    "wof:name":"G69 8FH",
    "wof:placetype":"postalcode"
},
  "geometry": {"coordinates":[-4.104165,55.878823],"type":"Point"}
}