{
  "type": "Feature",
  "properties": {
    "iso:country": "GB",
    "wof:name": "SN14 6QE",
    "wof:placetype": "postalcode"
  },
  "geometry": {"coordinates":[-2.170189,51.480564],"type":"Point"}
}
