{
  "type": "Feature",
  "properties": {
    "date:inception_lower": "1995-12-01",
    "date:inception_upper": "1995-12-01",
    "iso:country": "GB",
    "wof:name": "SN14 6QE",
    "wof:placetype": "postalcode"
  },
  "geometry": {"coordinates":[-2.170189,51.480564],"type":"Point"}
}
