{
  "type": "Feature",
  "properties": {
    "iso:country":"GB",
    "wof:name":"CF5 4BL",
    "wof:placetype":"postalcode"
},
  "geometry": {"coordinates":[-3.24073126131342,51.48087475903913],"type":"Point"}
}