{
  "type": "Feature",
  "properties": {
    "iso:country":"GB",
    "wof:name":"HG3 5DP",
    "wof:placetype":"postalcode"
},
  "geometry": {"coordinates":[-1.73089841572606,54.08196752994098],"type":"Point"}
}