{
  "type": "Feature",
  "properties": {
    "iso:country":"GB",
    "wof:name":"NE32 5RA",
    "wof:placetype":"postalcode"
},
  "geometry": {"coordinates":[-1.49009509303332,54.96515702879638],"type":"Point"}
}