{
  "type": "Feature",
  "properties": {
    "iso:country":"GB",
    "wof:name":"WD3 5GJ",
    "wof:placetype":"postalcode"
},
  "geometry": {"coordinates":[-0.51103363658213,51.66132133677892],"type":"Point"}
}