{
  "type": "Feature",
  "properties": {
    "date:inception_lower": "1980-01-01",
    "date:inception_upper": "1980-01-01",
    "iso:country": "GB",
    "wof:name": "GU34 5LW",
    "wof:placetype": "postalcode"
  },
  "geometry": {"coordinates":[-1.06427,51.129187],"type":"Point"}
}
