{
  "type": "Feature",
  "properties": {
    "iso:country": "GB",
    "wof:name": "B90 1UN",
    "wof:placetype": "postalcode"
  },
  "geometry": {"coordinates":[-1.850119,52.379355],"type":"Point"}
}
