{
  "type": "Feature",
  "properties": {
    "iso:country":"GB",
    "wof:name":"S61 1HA",
    "wof:placetype":"postalcode"
},
  "geometry": {"coordinates":[-1.39309411850936,53.43344662136695],"type":"Point"}
}