{
  "type": "Feature",
  "properties": {
    "iso:country":"GB",
    "wof:name":"DN9 3RA",
    "wof:placetype":"postalcode"
},
  "geometry": {"coordinates":[-0.98641567701996,53.48482890709964],"type":"Point"}
}