{
  "type": "Feature",
  "properties": {
    "iso:country": "GB",
    "wof:name": "DN9 3RA",
    "wof:placetype": "postalcode"
  },
  "geometry": {"coordinates":[-0.986416,53.484829],"type":"Point"}
}
