{
  "type": "Feature",
  "properties": {
    "iso:country": "GB",
    "wof:name": "SK22 3BR",
    "wof:placetype": "postalcode"
  },
  "geometry": {"coordinates":[-2.003387,53.367771],"type":"Point"}
}
