{
  "type": "Feature",
  "properties": {
    "date:inception_lower": "1996-12-01",
    "date:inception_upper": "1996-12-01",
    "iso:country": "GB",
    "wof:name": "SK22 3BR",
    "wof:placetype": "postalcode"
  },
  "geometry": {"coordinates":[-2.003296,53.367804],"type":"Point"}
}
