{
  "type": "Feature",
  "properties": {
    "iso:country":"GB",
    "wof:name":"EH6 8HN",
    "wof:placetype":"postalcode"
},
  "geometry": {"coordinates":[-3.16834108021304,55.96953705554991],"type":"Point"}
}