{
  "type": "Feature",
  "properties": {
    "iso:country":"GB",
    "wof:name":"LS27 8TE",
    "wof:placetype":"postalcode"
},
  "geometry": {"coordinates":[-1.58201637751475,53.74667333990388],"type":"Point"}
}