{
  "type": "Feature",
  "properties": {
    "date:inception_lower": "1991-01-01",
    "date:inception_upper": "1991-01-01",
    "iso:country": "GB",
    "wof:name": "LS27 8TE",
    "wof:placetype": "postalcode"
  },
  "geometry": {"coordinates":[-1.582016,53.746673],"type":"Point"}
}
