{
  "type": "Feature",
  "properties": {
    "iso:country": "GB",
    "wof:name": "UB2 5HG",
    "wof:placetype": "postalcode"
  },
  "geometry": {"coordinates":[-0.388033,51.491697],"type":"Point"}
}
