{
  "type": "Feature",
  "properties": {
    "iso:country":"GB",
    "wof:name":"UB2 5HG",
    "wof:placetype":"postalcode"
},
  "geometry": {"coordinates":[-0.38803281250485,51.49169715924728],"type":"Point"}
}