{
  "type": "Feature",
  "properties": {
    "iso:country":"GB",
    "wof:name":"CH6 5JN",
    "wof:placetype":"postalcode"
},
  "geometry": {"coordinates":[-3.12653640909539,53.24450475010704],"type":"Point"}
}