{
  "type": "Feature",
  "properties": {
    "iso:country":"GB",
    "wof:name":"LS13 1BA",
    "wof:placetype":"postalcode"
},
  "geometry": {"coordinates":[-1.64728519245682,53.81663014583038],"type":"Point"}
}