{
  "type": "Feature",
  "properties": {
    "date:inception_lower": "1980-01-01",
    "date:inception_upper": "1980-01-01",
    "iso:country": "GB",
    "wof:name": "LS13 1BA",
    "wof:placetype": "postalcode"
  },
  "geometry": {"coordinates":[-1.647285,53.81663],"type":"Point"}
}
