{
  "type": "Feature",
  "properties": {
    "iso:country": "GB",
    "wof:name": "RM13 8BP",
    "wof:placetype": "postalcode"
  },
  "geometry": {"coordinates":[0.176649,51.525733],"type":"Point"}
}
