{
  "type": "Feature",
  "properties": {
    "iso:country":"GB",
    "wof:name":"W1J 7QF",
    "wof:placetype":"postalcode"
},
  "geometry": {"coordinates":[-0.14621867121436,51.50654068609943],"type":"Point"}
}