{
  "type": "Feature",
  "properties": {
    "iso:country":"GB",
    "wof:name":"CO3 3EA",
    "wof:placetype":"postalcode"
},
  "geometry": {"coordinates":[0.88795926152945,51.8827939699269],"type":"Point"}
}