{
  "type": "Feature",
  "properties": {
    "date:inception_lower": "1980-01-01",
    "date:inception_upper": "1980-01-01",
    "iso:country": "GB",
    "wof:name": "CO3 3EA",
    "wof:placetype": "postalcode"
  },
  "geometry": {"coordinates":[0.887959,51.882794],"type":"Point"}
}
