{
  "type": "Feature",
  "properties": {
    "iso:country": "GB",
    "wof:name": "W1T 4PB",
    "wof:placetype": "postalcode"
  },
  "geometry": {"coordinates":[-0.136305,51.519603],"type":"Point"}
}
