{
  "type": "Feature",
  "properties": {
    "iso:country": "GB",
    "wof:name": "B62 0EZ",
    "wof:placetype": "postalcode"
  },
  "geometry": {"coordinates":[-2.0128,52.445674],"type":"Point"}
}
