{
  "type": "Feature",
  "properties": {
    "date:inception_lower": "1981-06-01",
    "date:inception_upper": "1981-06-01",
    "iso:country": "GB",
    "wof:name": "B62 0EZ",
    "wof:placetype": "postalcode"
  },
  "geometry": {"coordinates":[-2.0128,52.445674],"type":"Point"}
}
