{
  "type": "Feature",
  "properties": {
    "iso:country":"GB",
    "wof:name":"B62 0EZ",
    "wof:placetype":"postalcode"
},
  "geometry": {"coordinates":[-2.0128001869126,52.44567372966151],"type":"Point"}
}