{
  "type": "Feature",
  "properties": {
    "date:inception_lower": "1980-01-01",
    "date:inception_upper": "1980-01-01",
    "iso:country": "GB",
    "wof:name": "PO18 9LA",
    "wof:placetype": "postalcode"
  },
  "geometry": {"coordinates":[-0.869452,50.915193],"type":"Point"}
}
