{
  "type": "Feature",
  "properties": {
    "date:inception_lower": "1995-07-01",
    "date:inception_upper": "1995-07-01",
    "iso:country": "GB",
    "wof:name": "CF72 9LT",
    "wof:placetype": "postalcode"
  },
  "geometry": {"coordinates":[-3.429103,51.514231],"type":"Point"}
}
