{
  "type": "Feature",
  "properties": {
    "iso:country": "GB",
    "wof:name": "CF72 9LT",
    "wof:placetype": "postalcode"
  },
  "geometry": {"coordinates":[-3.429103,51.514231],"type":"Point"}
}
