{
  "type": "Feature",
  "properties": {
    "date:inception_lower":"1990-02-01",
    "date:inception_upper":"1990-02-28",
    "iso:country":"GB",
    "wof:name":"DN40 2LA",
    "wof:placetype":"postalcode"
},
  "geometry": {"coordinates":[-0.209023,53.618786],"type":"Point"}
}