{
  "type": "Feature",
  "properties": {
    "date:inception_lower": "1984-02-01",
    "date:inception_upper": "1984-02-01",
    "iso:country": "GB",
    "wof:name": "L7 3QD",
    "wof:placetype": "postalcode"
  },
  "geometry": {"coordinates":[-2.961146,53.401194],"type":"Point"}
}
