{
  "type": "Feature",
  "properties": {
    "iso:country":"GB",
    "wof:name":"W1D 5NB",
    "wof:placetype":"postalcode"
},
  "geometry": {"coordinates":[-0.12994372305524,51.51337741248142],"type":"Point"}
}