{
  "type": "Feature",
  "properties": {
    "iso:country":"GB",
    "wof:name":"YO25 9NF",
    "wof:placetype":"postalcode"
},
  "geometry": {"coordinates":[-0.53000161465035,53.95450647053426],"type":"Point"}
}