{
  "type": "Feature",
  "properties": {
    "iso:country": "GB",
    "wof:name": "YO25 9NF",
    "wof:placetype": "postalcode"
  },
  "geometry": {"coordinates":[-0.530002,53.954506],"type":"Point"}
}
