{
  "type": "Feature",
  "properties": {
    "iso:country":"GB",
    "wof:name":"HX4 8QA",
    "wof:placetype":"postalcode"
},
  "geometry": {"coordinates":[-1.87934375223873,53.69722323148189],"type":"Point"}
}