{
  "type": "Feature",
  "properties": {
    "iso:country": "GB",
    "wof:name": "NG13 8ZJ",
    "wof:placetype": "postalcode"
  },
  "geometry": {"coordinates":[-0.974905,52.963967],"type":"Point"}
}
