{
  "type": "Feature",
  "properties": {
    "iso:country":"GB",
    "wof:name":"NG13 8ZJ",
    "wof:placetype":"postalcode"
},
  "geometry": {"coordinates":[-0.97490532835901,52.96396672122726],"type":"Point"}
}