{
  "type": "Feature",
  "properties": {
    "iso:country":"GB",
    "wof:name":"M27 9PX",
    "wof:placetype":"postalcode"
},
  "geometry": {"coordinates":[-2.34957987414724,53.5141217652703],"type":"Point"}
}