{
  "type": "Feature",
  "properties": {
    "iso:country":"GB",
    "wof:name":"SG1 4QZ",
    "wof:placetype":"postalcode"
},
  "geometry": {"coordinates":[-0.18022314385432,51.92672923721184],"type":"Point"}
}