{
  "type": "Feature",
  "properties": {
    "iso:country":"GB",
    "wof:name":"SR8 4PA",
    "wof:placetype":"postalcode"
},
  "geometry": {"coordinates":[-1.32001038145086,54.76659389939316],"type":"Point"}
}