{
  "type": "Feature",
  "properties": {
    "iso:country": "GB",
    "wof:name": "SR8 4PA",
    "wof:placetype": "postalcode"
  },
  "geometry": {"coordinates":[-1.32001,54.766594],"type":"Point"}
}
