{
  "type": "Feature",
  "properties": {
    "iso:country":"GB",
    "wof:name":"DD11 1HA",
    "wof:placetype":"postalcode"
},
  "geometry": {"coordinates":[-2.57917518668379,56.56100170248284],"type":"Point"}
}