{
  "type": "Feature",
  "properties": {
    "date:inception_lower":"1996-06-01",
    "date:inception_upper":"1996-06-30",
    "iso:country":"GB",
    "wof:name":"SS16 6UP",
    "wof:placetype":"postalcode"
},
  "geometry": {"coordinates":[0.401168,51.563069],"type":"Point"}
}