{
  "type": "Feature",
  "properties": {
    "iso:country":"GB",
    "wof:name":"SS16 6UP",
    "wof:placetype":"postalcode"
},
  "geometry": {"coordinates":[0.4011676766309,51.56306918478528],"type":"Point"}
}