{
  "type": "Feature",
  "properties": {
    "iso:country": "GB",
    "wof:name": "W12 0LQ",
    "wof:placetype": "postalcode"
  },
  "geometry": {"coordinates":[-0.238643,51.509916],"type":"Point"}
}
