{
  "type": "Feature",
  "properties": {
    "iso:country":"GB",
    "wof:name":"AB16 5ES",
    "wof:placetype":"postalcode"
},
  "geometry": {"coordinates":[-2.14153434407279,57.16112450120222],"type":"Point"}
}