{
  "type": "Feature",
  "properties": {
    "iso:country": "GB",
    "wof:name": "AB16 5ES",
    "wof:placetype": "postalcode"
  },
  "geometry": {"coordinates":[-2.141534,57.161124],"type":"Point"}
}
