{
  "type": "Feature",
  "properties": {
    "date:inception_lower": "1980-01-01",
    "date:inception_upper": "1980-01-01",
    "iso:country": "GB",
    "wof:name": "CA14 2UZ",
    "wof:placetype": "postalcode"
  },
  "geometry": {"coordinates":[-3.556467,54.645012],"type":"Point"}
}
