{
  "type": "Feature",
  "properties": {
    "iso:country":"GB",
    "wof:name":"NW8 7EL",
    "wof:placetype":"postalcode"
},
  "geometry": {"coordinates":[-0.16686516228755,51.53281746930718],"type":"Point"}
}