{
  "type": "Feature",
  "properties": {
    "iso:country": "GB",
    "wof:name": "SY6 6LQ",
    "wof:placetype": "postalcode"
  },
  "geometry": {"coordinates":[-2.792273,52.572873],"type":"Point"}
}
