{
  "type": "Feature",
  "properties": {
    "date:inception_lower": "2023-04-01",
    "date:inception_upper": "2023-04-01",
    "iso:country": "GB",
    "wof:name": "CV33 8AZ",
    "wof:placetype": "postalcode"
  },
  "geometry": {"coordinates":[-1.481698,52.201305],"type":"Point"}
}
