{
  "type": "Feature",
  "properties": {
    "iso:country":"GB",
    "wof:name":"WA1 3DA",
    "wof:placetype":"postalcode"
},
  "geometry": {"coordinates":[-2.56575809080232,53.39992955437651],"type":"Point"}
}