{
  "type": "Feature",
  "properties": {
    "date:inception_lower": "1980-01-01",
    "date:inception_upper": "1980-01-01",
    "iso:country": "GB",
    "wof:name": "WA1 3DA",
    "wof:placetype": "postalcode"
  },
  "geometry": {"coordinates":[-2.565758,53.39993],"type":"Point"}
}
