{
  "type": "Feature",
  "properties": {
    "iso:country":"GB",
    "wof:name":"NG31 7BN",
    "wof:placetype":"postalcode"
},
  "geometry": {"coordinates":[-0.64067884858446,52.901308212616],"type":"Point"}
}