{
  "type": "Feature",
  "properties": {
    "iso:country": "GB",
    "wof:name": "L39 5HJ",
    "wof:placetype": "postalcode"
  },
  "geometry": {"coordinates":[-2.902118,53.552082],"type":"Point"}
}
