{
  "type": "Feature",
  "properties": {
    "date:inception_lower":"2015-10-01",
    "date:inception_upper":"2015-10-31",
    "iso:country":"GB",
    "wof:name":"NN15 6FE",
    "wof:placetype":"postalcode"
},
  "geometry": {"coordinates":[-0.716831,52.388177],"type":"Point"}
}