{
  "type": "Feature",
  "properties": {
    "iso:country": "GB",
    "wof:name": "NN15 6FE",
    "wof:placetype": "postalcode"
  },
  "geometry": {"coordinates":[-0.716831,52.388177],"type":"Point"}
}
