{
  "type": "Feature",
  "properties": {
    "iso:country":"GB",
    "wof:name":"N17 7LS",
    "wof:placetype":"postalcode"
},
  "geometry": {"coordinates":[-0.08725801178982,51.60613916248031],"type":"Point"}
}