{
  "type": "Feature",
  "properties": {
    "date:inception_lower":"1980-01-01",
    "date:inception_upper":"1980-01-31",
    "iso:country":"GB",
    "wof:name":"WA15 7XS",
    "wof:placetype":"postalcode"
},
  "geometry": {"coordinates":[-2.315603,53.398256],"type":"Point"}
}