{
  "type": "Feature",
  "properties": {
    "iso:country": "GB",
    "wof:name": "TS21 3DT",
    "wof:placetype": "postalcode"
  },
  "geometry": {"coordinates":[-1.450012,54.675374],"type":"Point"}
}
