{
  "type": "Feature",
  "properties": {
    "iso:country":"GB",
    "wof:name":"TS21 3DT",
    "wof:placetype":"postalcode"
},
  "geometry": {"coordinates":[-1.44999976445047,54.67536352142967],"type":"Point"}
}