{
  "type": "Feature",
  "properties": {
    "iso:country":"GB",
    "wof:name":"HG2 8BB",
    "wof:placetype":"postalcode"
},
  "geometry": {"coordinates":[-1.53339486648365,53.98116930703027],"type":"Point"}
}