{
  "type": "Feature",
  "properties": {
    "iso:country": "GB",
    "wof:name": "PO18 8FE",
    "wof:placetype": "postalcode"
  },
  "geometry": {"coordinates":[-0.886536,50.846813],"type":"Point"}
}
