{
  "type": "Feature",
  "properties": {
    "date:inception_lower":"2013-08-01",
    "date:inception_upper":"2013-08-31",
    "iso:country":"GB",
    "wof:name":"PO18 8FE",
    "wof:placetype":"postalcode"
},
  "geometry": {"coordinates":[-0.886536,50.846813],"type":"Point"}
}