{
  "type": "Feature",
  "properties": {
    "iso:country":"GB",
    "wof:name":"CM6 1PE",
    "wof:placetype":"postalcode"
},
  "geometry": {"coordinates":[0.33045657460028,51.81889497242354],"type":"Point"}
}