{
  "type": "Feature",
  "properties": {
    "iso:country":"GB",
    "wof:name":"BD20 8RU",
    "wof:placetype":"postalcode"
},
  "geometry": {"coordinates":[-2.00357067549303,53.90269432072652],"type":"Point"}
}