{
  "type": "Feature",
  "properties": {
    "iso:country":"GB",
    "wof:name":"TD6 9SZ",
    "wof:placetype":"postalcode"
},
  "geometry": {"coordinates":[-2.73294181246648,55.59709609929196],"type":"Point"}
}