{
  "type": "Feature",
  "properties": {
    "date:inception_lower": "1980-01-01",
    "date:inception_upper": "1980-01-01",
    "iso:country": "GB",
    "wof:name": "TD6 9SZ",
    "wof:placetype": "postalcode"
  },
  "geometry": {"coordinates":[-2.732942,55.597096],"type":"Point"}
}
