{
  "type": "Feature",
  "properties": {
    "iso:country":"GB",
    "wof:name":"TN24 0HH",
    "wof:placetype":"postalcode"
},
  "geometry": {"coordinates":[0.89481122973091,51.14274089898806],"type":"Point"}
}