{
  "type": "Feature",
  "properties": {
    "date:inception_lower": "1980-01-01",
    "date:inception_upper": "1980-01-01",
    "iso:country": "GB",
    "wof:name": "TN24 0HH",
    "wof:placetype": "postalcode"
  },
  "geometry": {"coordinates":[0.894843,51.142741],"type":"Point"}
}
