{
  "type": "Feature",
  "properties": {
    "iso:country":"GB",
    "wof:name":"BN25 2LL",
    "wof:placetype":"postalcode"
},
  "geometry": {"coordinates":[0.09695812777481,50.77953654955275],"type":"Point"}
}