{
  "type": "Feature",
  "properties": {
    "date:inception_lower": "1998-12-01",
    "date:inception_upper": "1998-12-01",
    "iso:country": "GB",
    "wof:name": "M15 6PQ",
    "wof:placetype": "postalcode"
  },
  "geometry": {"coordinates":[-2.239363,53.467086],"type":"Point"}
}
