{
  "type": "Feature",
  "properties": {
    "iso:country": "GB",
    "wof:name": "M15 6PQ",
    "wof:placetype": "postalcode"
  },
  "geometry": {"coordinates":[-2.239363,53.467086],"type":"Point"}
}
