{
  "type": "Feature",
  "properties": {
    "iso:country": "GB",
    "wof:name": "CV37 0HS",
    "wof:placetype": "postalcode"
  },
  "geometry": {"coordinates":[-1.719859,52.201151],"type":"Point"}
}
