{
  "type": "Feature",
  "properties": {
    "iso:country":"GB",
    "wof:name":"HD3 4PJ",
    "wof:placetype":"postalcode"
},
  "geometry": {"coordinates":[-1.83405106741162,53.64128975820777],"type":"Point"}
}