{
  "type": "Feature",
  "properties": {
    "iso:country": "GB",
    "wof:name": "HD3 4PJ",
    "wof:placetype": "postalcode"
  },
  "geometry": {"coordinates":[-1.834051,53.64129],"type":"Point"}
}
