{
  "type": "Feature",
  "properties": {
    "date:inception_lower": "1996-06-01",
    "date:inception_upper": "1996-06-01",
    "iso:country": "GB",
    "wof:name": "M34 5XX",
    "wof:placetype": "postalcode"
  },
  "geometry": {"coordinates":[-2.11176,53.472307],"type":"Point"}
}
