{
  "type": "Feature",
  "properties": {
    "iso:country":"GB",
    "wof:name":"M34 5XX",
    "wof:placetype":"postalcode"
},
  "geometry": {"coordinates":[-2.11189747531114,53.47266798596574],"type":"Point"}
}