{
  "type": "Feature",
  "properties": {
    "iso:country":"GB",
    "wof:name":"CW4 7BP",
    "wof:placetype":"postalcode"
},
  "geometry": {"coordinates":[-2.35195908986385,53.20026635905777],"type":"Point"}
}