{
  "type": "Feature",
  "properties": {
    "date:inception_lower": "1980-01-01",
    "date:inception_upper": "1980-01-01",
    "iso:country": "GB",
    "wof:name": "DG13 0PS",
    "wof:placetype": "postalcode"
  },
  "geometry": {"coordinates":[-3.009797,55.15467],"type":"Point"}
}
