{
  "type": "Feature",
  "properties": {
    "date:inception_lower":"2005-03-01",
    "date:inception_upper":"2005-03-31",
    "iso:country":"GB",
    "wof:name":"NE12 8EG",
    "wof:placetype":"postalcode"
},
  "geometry": {"coordinates":[-1.593959,55.017864],"type":"Point"}
}