{
  "type": "Feature",
  "properties": {
    "iso:country":"GB",
    "wof:name":"NE12 8EG",
    "wof:placetype":"postalcode"
},
  "geometry": {"coordinates":[-1.59344704369414,55.01756757324753],"type":"Point"}
}