{
  "type": "Feature",
  "properties": {
    "iso:country": "GB",
    "wof:name": "NE12 8EG",
    "wof:placetype": "postalcode"
  },
  "geometry": {"coordinates":[-1.593959,55.017864],"type":"Point"}
}
