{
  "type": "Feature",
  "properties": {
    "iso:country":"GB",
    "wof:name":"SA39 9AX",
    "wof:placetype":"postalcode"
},
  "geometry": {"coordinates":[-4.23842070836456,51.99885000695907],"type":"Point"}
}