{
  "type": "Feature",
  "properties": {
    "date:inception_lower": "1980-01-01",
    "date:inception_upper": "1980-01-01",
    "iso:country": "GB",
    "wof:name": "SA39 9AX",
    "wof:placetype": "postalcode"
  },
  "geometry": {"coordinates":[-4.23844,51.998861],"type":"Point"}
}
