{
  "type": "Feature",
  "properties": {
    "iso:country": "GB",
    "wof:name": "SK13 8SS",
    "wof:placetype": "postalcode"
  },
  "geometry": {"coordinates":[-1.931936,53.438078],"type":"Point"}
}
