{
  "type": "Feature",
  "properties": {
    "date:inception_lower": "1988-03-01",
    "date:inception_upper": "1988-03-01",
    "iso:country": "GB",
    "wof:name": "SK13 8SS",
    "wof:placetype": "postalcode"
  },
  "geometry": {"coordinates":[-1.931936,53.438078],"type":"Point"}
}
