{
  "type": "Feature",
  "properties": {
    "iso:country":"GB",
    "wof:name":"PR26 9BF",
    "wof:placetype":"postalcode"
},
  "geometry": {"coordinates":[-2.79030491157455,53.67122442258755],"type":"Point"}
}