{
  "type": "Feature",
  "properties": {
    "date:inception_lower": "2008-09-01",
    "date:inception_upper": "2008-09-01",
    "iso:country": "GB",
    "wof:name": "PR26 9BF",
    "wof:placetype": "postalcode"
  },
  "geometry": {"coordinates":[-2.790997,53.671146],"type":"Point"}
}
