{
  "type": "Feature",
  "properties": {
    "iso:country":"GB",
    "wof:name":"S71 2QB",
    "wof:placetype":"postalcode"
},
  "geometry": {"coordinates":[-1.44275802355263,53.56970289944861],"type":"Point"}
}