{
  "type": "Feature",
  "properties": {
    "date:inception_lower": "1996-12-01",
    "date:inception_upper": "1996-12-01",
    "iso:country": "GB",
    "wof:name": "TF12 5DB",
    "wof:placetype": "postalcode"
  },
  "geometry": {"coordinates":[-2.475033,52.609955],"type":"Point"}
}
