{
  "type": "Feature",
  "properties": {
    "iso:country":"GB",
    "wof:name":"IP6 0NN",
    "wof:placetype":"postalcode"
},
  "geometry": {"coordinates":[1.09158292191519,52.11257195574012],"type":"Point"}
}