{
  "type": "Feature",
  "properties": {
    "iso:country": "GB",
    "wof:name": "NN18 8TD",
    "wof:placetype": "postalcode"
  },
  "geometry": {"coordinates":[-0.667691,52.476014],"type":"Point"}
}
