{
  "type": "Feature",
  "properties": {
    "iso:country":"GB",
    "wof:name":"NN18 8TD",
    "wof:placetype":"postalcode"
},
  "geometry": {"coordinates":[-0.66769149906451,52.47601431231733],"type":"Point"}
}