{
  "type": "Feature",
  "properties": {
    "date:inception_lower":"2012-09-01",
    "date:inception_upper":"2012-09-30",
    "iso:country":"GB",
    "wof:name":"NN18 8TD",
    "wof:placetype":"postalcode"
},
  "geometry": {"coordinates":[-0.667691,52.476014],"type":"Point"}
}