{
  "type": "Feature",
  "properties": {
    "iso:country": "GB",
    "wof:name": "RM14 3AJ",
    "wof:placetype": "postalcode"
  },
  "geometry": {"coordinates":[0.250787,51.551331],"type":"Point"}
}
