{
  "type": "Feature",
  "properties": {
    "date:inception_lower": "1990-07-01",
    "date:inception_upper": "1990-07-01",
    "iso:country": "GB",
    "wof:name": "ST3 7XL",
    "wof:placetype": "postalcode"
  },
  "geometry": {"coordinates":[-2.109967,52.96445],"type":"Point"}
}
