{
  "type": "Feature",
  "properties": {
    "iso:country":"GB",
    "wof:name":"GL7 4JQ",
    "wof:placetype":"postalcode"
},
  "geometry": {"coordinates":[-1.77949621964006,51.71440877481284],"type":"Point"}
}