{
  "type": "Feature",
  "properties": {
    "date:inception_lower": "1980-01-01",
    "date:inception_upper": "1980-01-01",
    "iso:country": "GB",
    "wof:name": "GL7 4JQ",
    "wof:placetype": "postalcode"
  },
  "geometry": {"coordinates":[-1.779496,51.714409],"type":"Point"}
}
