{
  "type": "Feature",
  "properties": {
    "iso:country":"GB",
    "wof:name":"PA67 6DA",
    "wof:placetype":"postalcode"
},
  "geometry": {"coordinates":[-6.23994639713355,56.31519654502328],"type":"Point"}
}