{
  "type": "Feature",
  "properties": {
    "iso:country": "GB",
    "wof:name": "PA67 6DA",
    "wof:placetype": "postalcode"
  },
  "geometry": {"coordinates":[-6.239946,56.315197],"type":"Point"}
}
