{
  "type": "Feature",
  "properties": {
    "date:inception_lower": "1992-08-01",
    "date:inception_upper": "1992-08-01",
    "iso:country": "GB",
    "wof:name": "SS5 5LZ",
    "wof:placetype": "postalcode"
  },
  "geometry": {"coordinates":[0.648019,51.619083],"type":"Point"}
}
