{
  "type": "Feature",
  "properties": {
    "iso:country":"GB",
    "wof:name":"SS5 5LZ",
    "wof:placetype":"postalcode"
},
  "geometry": {"coordinates":[0.64801885261547,51.61908282671502],"type":"Point"}
}