{
  "type": "Feature",
  "properties": {
    "iso:country":"GB",
    "wof:name":"CV33 9TQ",
    "wof:placetype":"postalcode"
},
  "geometry": {"coordinates":[-1.48728735067322,52.19841914523652],"type":"Point"}
}