{
  "type": "Feature",
  "properties": {
    "iso:country":"GB",
    "wof:name":"DN16 3AH",
    "wof:placetype":"postalcode"
},
  "geometry": {"coordinates":[-0.61797702762795,53.56192215711698],"type":"Point"}
}