{
  "type": "Feature",
  "properties": {
    "date:inception_lower": "2009-05-01",
    "date:inception_upper": "2009-05-01",
    "iso:country": "GB",
    "wof:name": "DN16 3AH",
    "wof:placetype": "postalcode"
  },
  "geometry": {"coordinates":[-0.617977,53.561922],"type":"Point"}
}
