{
  "type": "Feature",
  "properties": {
    "iso:country":"GB",
    "wof:name":"BS20 6XY",
    "wof:placetype":"postalcode"
},
  "geometry": {"coordinates":[-2.76250157491421,51.48005994949756],"type":"Point"}
}