{
  "type": "Feature",
  "properties": {
    "date:inception_lower": "1980-01-01",
    "date:inception_upper": "1980-01-01",
    "iso:country": "GB",
    "wof:name": "S70 5ES",
    "wof:placetype": "postalcode"
  },
  "geometry": {"coordinates":[-1.465212,53.531371],"type":"Point"}
}
