{
  "type": "Feature",
  "properties": {
    "iso:country":"GB",
    "wof:name":"M33 7JN",
    "wof:placetype":"postalcode"
},
  "geometry": {"coordinates":[-2.32141576456222,53.42920570276964],"type":"Point"}
}