{
  "type": "Feature",
  "properties": {
    "iso:country": "GB",
    "wof:name": "M33 7JN",
    "wof:placetype": "postalcode"
  },
  "geometry": {"coordinates":[-2.321416,53.429206],"type":"Point"}
}
