{
  "type": "Feature",
  "properties": {
    "date:inception_lower":"1994-05-01",
    "date:inception_upper":"1994-05-31",
    "iso:country":"GB",
    "wof:name":"M33 7JN",
    "wof:placetype":"postalcode"
},
  "geometry": {"coordinates":[-2.321416,53.429206],"type":"Point"}
}