{
  "type": "Feature",
  "properties": {
    "iso:country":"GB",
    "wof:name":"SS7 5EG",
    "wof:placetype":"postalcode"
},
  "geometry": {"coordinates":[0.55265969422754,51.55148838921247],"type":"Point"}
}