{
  "type": "Feature",
  "properties": {
    "iso:country": "GB",
    "wof:name": "G67 4BA",
    "wof:placetype": "postalcode"
  },
  "geometry": {"coordinates":[-3.996952,55.93604],"type":"Point"}
}
