{
  "type": "Feature",
  "properties": {
    "iso:country":"GB",
    "wof:name":"N13 4JY",
    "wof:placetype":"postalcode"
},
  "geometry": {"coordinates":[-0.12245707628526,51.61581677335663],"type":"Point"}
}