{
  "type": "Feature",
  "properties": {
    "iso:country":"GB",
    "wof:name":"WS6 6LP",
    "wof:placetype":"postalcode"
},
  "geometry": {"coordinates":[-2.02172074740245,52.66166243280218],"type":"Point"}
}