{
  "type": "Feature",
  "properties": {
    "date:inception_lower": "1980-01-01",
    "date:inception_upper": "1980-01-01",
    "iso:country": "GB",
    "wof:name": "SK9 2NS",
    "wof:placetype": "postalcode"
  },
  "geometry": {"coordinates":[-2.210904,53.332294],"type":"Point"}
}
