{
  "type": "Feature",
  "properties": {
    "iso:country":"GB",
    "wof:name":"SK9 2NS",
    "wof:placetype":"postalcode"
},
  "geometry": {"coordinates":[-2.21090444594458,53.33229437179783],"type":"Point"}
}