{
  "type": "Feature",
  "properties": {
    "date:inception_lower":"1997-12-01",
    "date:inception_upper":"1997-12-31",
    "iso:country":"GB",
    "wof:name":"SY23 3TS",
    "wof:placetype":"postalcode"
},
  "geometry": {"coordinates":[-4.050739,52.418257],"type":"Point"}
}