{
  "type": "Feature",
  "properties": {
    "iso:country": "GB",
    "wof:name": "SS9 2AH",
    "wof:placetype": "postalcode"
  },
  "geometry": {"coordinates":[0.650812,51.54825],"type":"Point"}
}
