{
  "type": "Feature",
  "properties": {
    "iso:country": "GB",
    "wof:name": "WA2 0GY",
    "wof:placetype": "postalcode"
  },
  "geometry": {"coordinates":[-2.563218,53.413712],"type":"Point"}
}
