{
  "type": "Feature",
  "properties": {
    "iso:country":"GB",
    "wof:name":"WA2 0GY",
    "wof:placetype":"postalcode"
},
  "geometry": {"coordinates":[-2.56321796119233,53.41371221324247],"type":"Point"}
}