{
  "type": "Feature",
  "properties": {
    "iso:country": "GB",
    "wof:name": "AB14 0RJ",
    "wof:placetype": "postalcode"
  },
  "geometry": {"coordinates":[-2.255686,57.100434],"type":"Point"}
}
