{
  "type": "Feature",
  "properties": {
    "date:inception_lower": "1994-12-01",
    "date:inception_upper": "1994-12-01",
    "iso:country": "GB",
    "wof:name": "SO40 2NL",
    "wof:placetype": "postalcode"
  },
  "geometry": {"coordinates":[-1.576653,50.922595],"type":"Point"}
}
