{
  "type": "Feature",
  "properties": {
    "iso:country": "GB",
    "wof:name": "SO40 2NL",
    "wof:placetype": "postalcode"
  },
  "geometry": {"coordinates":[-1.576625,50.922603],"type":"Point"}
}
