{
  "type": "Feature",
  "properties": {
    "iso:country":"GB",
    "wof:name":"SO40 2NL",
    "wof:placetype":"postalcode"
},
  "geometry": {"coordinates":[-1.57715946522621,50.92275696523617],"type":"Point"}
}