{
  "type": "Feature",
  "properties": {
    "iso:country": "GB",
    "wof:name": "NR9 3GN",
    "wof:placetype": "postalcode"
  },
  "geometry": {"coordinates":[1.188413,52.605442],"type":"Point"}
}
