{
  "type": "Feature",
  "properties": {
    "date:inception_lower": "2024-03-01",
    "date:inception_upper": "2024-03-01",
    "iso:country": "GB",
    "wof:name": "SK10 4ZL",
    "wof:placetype": "postalcode"
  },
  "geometry": {"coordinates":[-2.144743,53.292518],"type":"Point"}
}
