{
  "type": "Feature",
  "properties": {
    "date:inception_lower": "2018-04-01",
    "date:inception_upper": "2018-04-01",
    "iso:country": "GB",
    "wof:name": "DE12 6AQ",
    "wof:placetype": "postalcode"
  },
  "geometry": {"coordinates":[-1.530166,52.736355],"type":"Point"}
}
