{
  "type": "Feature",
  "properties": {
    "date:inception_lower": "2018-12-01",
    "date:inception_upper": "2018-12-01",
    "iso:country": "GB",
    "wof:name": "OX7 6RE",
    "wof:placetype": "postalcode"
  },
  "geometry": {"coordinates":[-1.622277,51.912558],"type":"Point"}
}
