{
  "type": "Feature",
  "properties": {
    "iso:country":"GB",
    "wof:name":"MK42 8TJ",
    "wof:placetype":"postalcode"
},
  "geometry": {"coordinates":[-0.48922522876482,52.12516225880603],"type":"Point"}
}