{
  "type": "Feature",
  "properties": {
    "iso:country": "GB",
    "wof:name": "TN27 0BP",
    "wof:placetype": "postalcode"
  },
  "geometry": {"coordinates":[0.750869,51.203519],"type":"Point"}
}
