{
  "type": "Feature",
  "properties": {
    "date:inception_lower": "2008-04-01",
    "date:inception_upper": "2008-04-01",
    "iso:country": "GB",
    "wof:name": "FK10 2UU",
    "wof:placetype": "postalcode"
  },
  "geometry": {"coordinates":[-3.844513,56.134087],"type":"Point"}
}
