{
  "type": "Feature",
  "properties": {
    "iso:country": "GB",
    "wof:name": "NE5 4JT",
    "wof:placetype": "postalcode"
  },
  "geometry": {"coordinates":[-1.691337,55.008842],"type":"Point"}
}
