{
  "type": "Feature",
  "properties": {
    "date:inception_lower": "1980-01-01",
    "date:inception_upper": "1980-01-01",
    "iso:country": "GB",
    "wof:name": "BL8 2RA",
    "wof:placetype": "postalcode"
  },
  "geometry": {"coordinates":[-2.315289,53.595686],"type":"Point"}
}
