{
  "type": "Feature",
  "properties": {
    "date:inception_lower":"1980-01-01",
    "date:inception_upper":"1980-01-31",
    "iso:country":"GB",
    "wof:name":"BL8 2RA",
    "wof:placetype":"postalcode"
},
  "geometry": {"coordinates":[-2.31529,53.595661],"type":"Point"}
}