{
  "type": "Feature",
  "properties": {
    "iso:country": "GB",
    "wof:name": "BL8 2RA",
    "wof:placetype": "postalcode"
  },
  "geometry": {"coordinates":[-2.31529,53.595661],"type":"Point"}
}
