{
  "type": "Feature",
  "properties": {
    "iso:country":"GB",
    "wof:name":"BL8 2RA",
    "wof:placetype":"postalcode"
},
  "geometry": {"coordinates":[-2.31529036478227,53.59566073286159],"type":"Point"}
}