{
  "type": "Feature",
  "properties": {
    "iso:country":"GB",
    "wof:name":"G46 7EB",
    "wof:placetype":"postalcode"
},
  "geometry": {"coordinates":[-4.296575763707,55.80729225782362],"type":"Point"}
}