{
  "type": "Feature",
  "properties": {
    "date:inception_lower":"1996-12-01",
    "date:inception_upper":"1996-12-31",
    "iso:country":"GB",
    "wof:name":"SK12 2PY",
    "wof:placetype":"postalcode"
},
  "geometry": {"coordinates":[-2.013077,53.35788],"type":"Point"}
}