{
  "type": "Feature",
  "properties": {
    "iso:country":"GB",
    "wof:name":"TS19 0LG",
    "wof:placetype":"postalcode"
},
  "geometry": {"coordinates":[-1.32339387956326,54.58213082745876],"type":"Point"}
}