{
  "type": "Feature",
  "properties": {
    "date:inception_lower": "1980-01-01",
    "date:inception_upper": "1980-01-01",
    "iso:country": "GB",
    "wof:name": "TS19 0LG",
    "wof:placetype": "postalcode"
  },
  "geometry": {"coordinates":[-1.323394,54.582131],"type":"Point"}
}
