{
  "type": "Feature",
  "properties": {
    "date:inception_lower":"1985-01-01",
    "date:inception_upper":"1985-01-31",
    "iso:country":"GB",
    "wof:name":"G71 6LY",
    "wof:placetype":"postalcode"
},
  "geometry": {"coordinates":[-4.072975,55.826661],"type":"Point"}
}