{
  "type": "Feature",
  "properties": {
    "date:inception_lower": "2024-10-01",
    "date:inception_upper": "2024-10-01",
    "iso:country": "GB",
    "wof:name": "DE14 2GH",
    "wof:placetype": "postalcode"
  },
  "geometry": {"coordinates":[-1.666957,52.808177],"type":"Point"}
}
