{
  "type": "Feature",
  "properties": {
    "iso:country":"GB",
    "wof:name":"NR15 2BS",
    "wof:placetype":"postalcode"
},
  "geometry": {"coordinates":[1.18728737167174,52.43267297859936],"type":"Point"}
}