{
  "type": "Feature",
  "properties": {
    "iso:country": "GB",
    "wof:name": "PE11 4QN",
    "wof:placetype": "postalcode"
  },
  "geometry": {"coordinates":[-0.190648,52.881424],"type":"Point"}
}
