{
  "type": "Feature",
  "properties": {
    "date:inception_lower": "1980-01-01",
    "date:inception_upper": "1980-01-01",
    "iso:country": "GB",
    "wof:name": "CW8 2HL",
    "wof:placetype": "postalcode"
  },
  "geometry": {"coordinates":[-2.644458,53.203358],"type":"Point"}
}
