{
  "type": "Feature",
  "properties": {
    "iso:country": "GB",
    "wof:name": "NN13 7AW",
    "wof:placetype": "postalcode"
  },
  "geometry": {"coordinates":[-1.140829,52.025554],"type":"Point"}
}
