{
  "type": "Feature",
  "properties": {
    "date:inception_lower": "2012-02-01",
    "date:inception_upper": "2012-02-01",
    "iso:country": "GB",
    "wof:name": "NN13 7AW",
    "wof:placetype": "postalcode"
  },
  "geometry": {"coordinates":[-1.140829,52.025554],"type":"Point"}
}
