{
  "type": "Feature",
  "properties": {
    "iso:country":"GB",
    "wof:name":"SW17 8QL",
    "wof:placetype":"postalcode"
},
  "geometry": {"coordinates":[-0.14831211499834,51.43709727715829],"type":"Point"}
}