{
  "type": "Feature",
  "properties": {
    "date:inception_lower":"1980-01-01",
    "date:inception_upper":"1980-01-31",
    "iso:country":"GB",
    "wof:name":"SW17 8QL",
    "wof:placetype":"postalcode"
},
  "geometry": {"coordinates":[-0.148312,51.437097],"type":"Point"}
}