{
  "type": "Feature",
  "properties": {
    "iso:country":"GB",
    "wof:name":"G76 8HY",
    "wof:placetype":"postalcode"
},
  "geometry": {"coordinates":[-4.26153742984972,55.77990074097011],"type":"Point"}
}