{
  "type": "Feature",
  "properties": {
    "date:inception_lower": "2019-06-01",
    "date:inception_upper": "2019-06-01",
    "iso:country": "GB",
    "wof:name": "DE23 3BD",
    "wof:placetype": "postalcode"
  },
  "geometry": {"coordinates":[-1.52722,52.889786],"type":"Point"}
}
