{
  "type": "Feature",
  "properties": {
    "iso:country": "GB",
    "wof:name": "DE23 3BD",
    "wof:placetype": "postalcode"
  },
  "geometry": {"coordinates":[-1.527028,52.889642],"type":"Point"}
}
