{
  "type": "Feature",
  "properties": {
    "iso:country": "GB",
    "wof:name": "AB39 2AD",
    "wof:placetype": "postalcode"
  },
  "geometry": {"coordinates":[-2.20893,56.964976],"type":"Point"}
}
