{
  "type": "Feature",
  "properties": {
    "iso:country":"GB",
    "wof:name":"SO15 2TR",
    "wof:placetype":"postalcode"
},
  "geometry": {"coordinates":[-1.41116306806279,50.91540182293034],"type":"Point"}
}