{
  "type": "Feature",
  "properties": {
    "iso:country":"GB",
    "wof:name":"M45 8LR",
    "wof:placetype":"postalcode"
},
  "geometry": {"coordinates":[-2.27235614370792,53.55435704794259],"type":"Point"}
}