{
  "type": "Feature",
  "properties": {
    "iso:country":"GB",
    "wof:name":"B68 8JQ",
    "wof:placetype":"postalcode"
},
  "geometry": {"coordinates":[-2.00318187862438,52.49391459846012],"type":"Point"}
}