{
  "type": "Feature",
  "properties": {
    "iso:country":"GB",
    "wof:name":"B37 6NR",
    "wof:placetype":"postalcode"
},
  "geometry": {"coordinates":[-1.7484666265047,52.48806510475269],"type":"Point"}
}