{
  "type": "Feature",
  "properties": {
    "date:inception_lower": "1980-01-01",
    "date:inception_upper": "1980-01-01",
    "iso:country": "GB",
    "wof:name": "M24 4FY",
    "wof:placetype": "postalcode"
  },
  "geometry": {"coordinates":[-2.20693,53.552996],"type":"Point"}
}
