{
  "type": "Feature",
  "properties": {
    "iso:country":"GB",
    "wof:name":"M24 4FY",
    "wof:placetype":"postalcode"
},
  "geometry": {"coordinates":[-2.20693006268552,53.55299620787855],"type":"Point"}
}