{
  "type": "Feature",
  "properties": {
    "date:inception_lower": "2010-12-01",
    "date:inception_upper": "2010-12-01",
    "iso:country": "GB",
    "wof:name": "CF63 4DE",
    "wof:placetype": "postalcode"
  },
  "geometry": {"coordinates":[-3.270004,51.400352],"type":"Point"}
}
