{
  "type": "Feature",
  "properties": {
    "iso:country": "GB",
    "wof:name": "EN8 9JN",
    "wof:placetype": "postalcode"
  },
  "geometry": {"coordinates":[-0.025021,51.708414],"type":"Point"}
}
