{
  "type": "Feature",
  "properties": {
    "iso:country": "GB",
    "wof:name": "LS16 9BE",
    "wof:placetype": "postalcode"
  },
  "geometry": {"coordinates":[-1.615419,53.88476],"type":"Point"}
}
