{
  "type": "Feature",
  "properties": {
    "iso:country":"GB",
    "wof:name":"LS16 9BE",
    "wof:placetype":"postalcode"
},
  "geometry": {"coordinates":[-1.61541863356087,53.88475971391358],"type":"Point"}
}