{
  "type": "Feature",
  "properties": {
    "iso:country":"GB",
    "wof:name":"DH1 3BJ",
    "wof:placetype":"postalcode"
},
  "geometry": {"coordinates":[-1.56793714028919,54.77146811911758],"type":"Point"}
}