{
  "type": "Feature",
  "properties": {
    "iso:country": "GB",
    "wof:name": "TS19 0HZ",
    "wof:placetype": "postalcode"
  },
  "geometry": {"coordinates":[-1.324314,54.574209],"type":"Point"}
}
