{
  "type": "Feature",
  "properties": {
    "date:inception_lower": "1980-01-01",
    "date:inception_upper": "1980-01-01",
    "iso:country": "GB",
    "wof:name": "LA18 4DL",
    "wof:placetype": "postalcode"
  },
  "geometry": {"coordinates":[-3.263507,54.209265],"type":"Point"}
}
