{
  "type": "Feature",
  "properties": {
    "iso:country":"GB",
    "wof:name":"B14 5LT",
    "wof:placetype":"postalcode"
},
  "geometry": {"coordinates":[-1.89180262083872,52.40983584800044],"type":"Point"}
}