{
  "type": "Feature",
  "properties": {
    "date:inception_lower": "1980-01-01",
    "date:inception_upper": "1980-01-01",
    "iso:country": "GB",
    "wof:name": "WV15 5AL",
    "wof:placetype": "postalcode"
  },
  "geometry": {"coordinates":[-2.413232,52.53478],"type":"Point"}
}
