{
  "type": "Feature",
  "properties": {
    "iso:country":"GB",
    "wof:name":"DL13 2PD",
    "wof:placetype":"postalcode"
},
  "geometry": {"coordinates":[-2.01444750165043,54.74963455881561],"type":"Point"}
}