{
  "type": "Feature",
  "properties": {
    "iso:country": "GB",
    "wof:name": "DL13 2PD",
    "wof:placetype": "postalcode"
  },
  "geometry": {"coordinates":[-2.014447,54.749635],"type":"Point"}
}
