{
  "type": "Feature",
  "properties": {
    "date:inception_lower": "1980-01-01",
    "date:inception_upper": "1980-01-01",
    "iso:country": "GB",
    "wof:name": "DN1 3BJ",
    "wof:placetype": "postalcode"
  },
  "geometry": {"coordinates":[-1.135385,53.518961],"type":"Point"}
}
