{
  "type": "Feature",
  "properties": {
    "iso:country":"GB",
    "wof:name":"DN1 3BJ",
    "wof:placetype":"postalcode"
},
  "geometry": {"coordinates":[-1.13538508547143,53.51896069831204],"type":"Point"}
}