{
  "type": "Feature",
  "properties": {
    "date:inception_lower": "1999-06-01",
    "date:inception_upper": "1999-06-01",
    "iso:country": "GB",
    "wof:name": "HP6 6YJ",
    "wof:placetype": "postalcode"
  },
  "geometry": {"coordinates":[-0.58851,51.673351],"type":"Point"}
}
