{
  "type": "Feature",
  "properties": {
    "iso:country":"GB",
    "wof:name":"HP6 6YJ",
    "wof:placetype":"postalcode"
},
  "geometry": {"coordinates":[-0.58853245404582,51.67334716915878],"type":"Point"}
}