{
  "type": "Feature",
  "properties": {
    "iso:country": "GB",
    "wof:name": "CH66 3PT",
    "wof:placetype": "postalcode"
  },
  "geometry": {"coordinates":[-2.936773,53.279596],"type":"Point"}
}
