{
  "type": "Feature",
  "properties": {
    "iso:country": "GB",
    "wof:name": "DE6 1TH",
    "wof:placetype": "postalcode"
  },
  "geometry": {"coordinates":[-1.719742,53.006331],"type":"Point"}
}
