{
  "type": "Feature",
  "properties": {
    "iso:country":"GB",
    "wof:name":"SY5 0DP",
    "wof:placetype":"postalcode"
},
  "geometry": {"coordinates":[-2.96967574525017,52.62750682288212],"type":"Point"}
}