{
  "type": "Feature",
  "properties": {
    "date:inception_lower": "1980-01-01",
    "date:inception_upper": "1980-01-01",
    "iso:country": "GB",
    "wof:name": "SY5 0DP",
    "wof:placetype": "postalcode"
  },
  "geometry": {"coordinates":[-2.969676,52.627507],"type":"Point"}
}
