{
  "type": "Feature",
  "properties": {
    "iso:country": "GB",
    "wof:name": "TA7 9JX",
    "wof:placetype": "postalcode"
  },
  "geometry": {"coordinates":[-2.879023,51.155177],"type":"Point"}
}
