{
  "type": "Feature",
  "properties": {
    "iso:country":"GB",
    "wof:name":"E3 2PZ",
    "wof:placetype":"postalcode"
},
  "geometry": {"coordinates":[-0.02267914228812,51.53321837123493],"type":"Point"}
}