{
  "type": "Feature",
  "properties": {
    "iso:country":"GB",
    "wof:name":"WN5 9SE",
    "wof:placetype":"postalcode"
},
  "geometry": {"coordinates":[-2.6611629790681,53.54277179357595],"type":"Point"}
}