{
  "type": "Feature",
  "properties": {
    "date:inception_lower": "1980-01-01",
    "date:inception_upper": "1980-01-01",
    "iso:country": "GB",
    "wof:name": "LL59 5BA",
    "wof:placetype": "postalcode"
  },
  "geometry": {"coordinates":[-4.166981,53.227069],"type":"Point"}
}
