{
  "type": "Feature",
  "properties": {
    "iso:country": "GB",
    "wof:name": "SA4 3TW",
    "wof:placetype": "postalcode"
  },
  "geometry": {"coordinates":[-4.122244,51.631008],"type":"Point"}
}
