{
  "type": "Feature",
  "properties": {
    "iso:country":"GB",
    "wof:name":"SA4 3TW",
    "wof:placetype":"postalcode"
},
  "geometry": {"coordinates":[-4.1222442331689,51.63100819450108],"type":"Point"}
}