{
  "type": "Feature",
  "properties": {
    "iso:country":"GB",
    "wof:name":"ME3 8TS",
    "wof:placetype":"postalcode"
},
  "geometry": {"coordinates":[0.50018705865807,51.43475128285093],"type":"Point"}
}