{
  "type": "Feature",
  "properties": {
    "date:inception_lower": "1980-01-01",
    "date:inception_upper": "1980-01-01",
    "iso:country": "GB",
    "wof:name": "OL16 3UY",
    "wof:placetype": "postalcode"
  },
  "geometry": {"coordinates":[-2.110901,53.615988],"type":"Point"}
}
