{
  "type": "Feature",
  "properties": {
    "iso:country":"GB",
    "wof:name":"OL16 3UY",
    "wof:placetype":"postalcode"
},
  "geometry": {"coordinates":[-2.11090138792493,53.61598805027917],"type":"Point"}
}