{
  "type": "Feature",
  "properties": {
    "iso:country": "GB",
    "wof:name": "CW12 4ZD",
    "wof:placetype": "postalcode"
  },
  "geometry": {"coordinates":[-2.253374,53.173523],"type":"Point"}
}
