{
  "type": "Feature",
  "properties": {
    "date:inception_lower": "2019-12-01",
    "date:inception_upper": "2019-12-01",
    "iso:country": "GB",
    "wof:name": "CW12 4ZD",
    "wof:placetype": "postalcode"
  },
  "geometry": {"coordinates":[-2.253656,53.173162],"type":"Point"}
}
