{
  "type": "Feature",
  "properties": {
    "iso:country":"GB",
    "wof:name":"EX31 3RD",
    "wof:placetype":"postalcode"
},
  "geometry": {"coordinates":[-4.08631611266274,51.07051611181623],"type":"Point"}
}