{
  "type": "Feature",
  "properties": {
    "date:inception_lower": "1992-08-01",
    "date:inception_upper": "1992-08-01",
    "iso:country": "GB",
    "wof:name": "EX31 3RD",
    "wof:placetype": "postalcode"
  },
  "geometry": {"coordinates":[-4.086316,51.070516],"type":"Point"}
}
