{
  "type": "Feature",
  "properties": {
    "iso:country":"GB",
    "wof:name":"PO11 9JN",
    "wof:placetype":"postalcode"
},
  "geometry": {"coordinates":[-0.96929673993959,50.7840025042645],"type":"Point"}
}