{
  "type": "Feature",
  "properties": {
    "iso:country":"GB",
    "wof:name":"CT14 0JN",
    "wof:placetype":"postalcode"
},
  "geometry": {"coordinates":[1.28345948111391,51.22282307225904],"type":"Point"}
}