{
  "type": "Feature",
  "properties": {
    "iso:country":"GB",
    "wof:name":"BD9 6PQ",
    "wof:placetype":"postalcode"
},
  "geometry": {"coordinates":[-1.81700046997662,53.82052301591332],"type":"Point"}
}