{
  "type": "Feature",
  "properties": {
    "iso:country": "GB",
    "wof:name": "BD11 2EU",
    "wof:placetype": "postalcode"
  },
  "geometry": {"coordinates":[-1.684193,53.747939],"type":"Point"}
}
