{
  "type": "Feature",
  "properties": {
    "date:inception_lower":"1980-01-01",
    "date:inception_upper":"1980-01-31",
    "iso:country":"GB",
    "wof:name":"BD11 2EU",
    "wof:placetype":"postalcode"
},
  "geometry": {"coordinates":[-1.684193,53.747939],"type":"Point"}
}