{
  "type": "Feature",
  "properties": {
    "iso:country": "GB",
    "wof:name": "PE9 2NL",
    "wof:placetype": "postalcode"
  },
  "geometry": {"coordinates":[-0.471883,52.649909],"type":"Point"}
}
