{
  "type": "Feature",
  "properties": {
    "date:inception_lower": "2013-07-01",
    "date:inception_upper": "2013-07-01",
    "iso:country": "GB",
    "wof:name": "PE9 2NL",
    "wof:placetype": "postalcode"
  },
  "geometry": {"coordinates":[-0.471883,52.649909],"type":"Point"}
}
