{
  "type": "Feature",
  "properties": {
    "iso:country":"GB",
    "wof:name":"PE9 2NL",
    "wof:placetype":"postalcode"
},
  "geometry": {"coordinates":[-0.47188321247566,52.6499091772131],"type":"Point"}
}