{
  "type": "Feature",
  "properties": {
    "iso:country":"GB",
    "wof:name":"S10 3GP",
    "wof:placetype":"postalcode"
},
  "geometry": {"coordinates":[-1.52297291591669,53.36911062169797],"type":"Point"}
}