{
  "type": "Feature",
  "properties": {
    "iso:country":"GB",
    "wof:name":"BH7 7DS",
    "wof:placetype":"postalcode"
},
  "geometry": {"coordinates":[-1.81626558059361,50.74794273814906],"type":"Point"}
}