{
  "type": "Feature",
  "properties": {
    "iso:country": "GB",
    "wof:name": "BH7 7DS",
    "wof:placetype": "postalcode"
  },
  "geometry": {"coordinates":[-1.816266,50.747943],"type":"Point"}
}
