{
  "type": "Feature",
  "properties": {
    "iso:country": "GB",
    "wof:name": "PE12 0TR",
    "wof:placetype": "postalcode"
  },
  "geometry": {"coordinates":[-0.044991,52.707363],"type":"Point"}
}
