{
  "type": "Feature",
  "properties": {
    "iso:country":"GB",
    "wof:name":"PE12 0TR",
    "wof:placetype":"postalcode"
},
  "geometry": {"coordinates":[-0.0449754492816,52.70737174731572],"type":"Point"}
}