{
  "type": "Feature",
  "properties": {
    "iso:country":"GB",
    "wof:name":"TS3 7JY",
    "wof:placetype":"postalcode"
},
  "geometry": {"coordinates":[-1.20316440568504,54.55805082847984],"type":"Point"}
}