{
  "type": "Feature",
  "properties": {
    "iso:country": "GB",
    "wof:name": "TS3 7JY",
    "wof:placetype": "postalcode"
  },
  "geometry": {"coordinates":[-1.20321,54.558055],"type":"Point"}
}
