{
  "type": "Feature",
  "properties": {
    "iso:country":"GB",
    "wof:name":"E5 0RL",
    "wof:placetype":"postalcode"
},
  "geometry": {"coordinates":[-0.05038164650945,51.55403225803403],"type":"Point"}
}