{
  "type": "Feature",
  "properties": {
    "iso:country": "GB",
    "wof:name": "FK1 2BD",
    "wof:placetype": "postalcode"
  },
  "geometry": {"coordinates":[-3.751459,55.969188],"type":"Point"}
}
