{
  "type": "Feature",
  "properties": {
    "iso:country":"GB",
    "wof:name":"FK1 2BD",
    "wof:placetype":"postalcode"
},
  "geometry": {"coordinates":[-3.75145918434878,55.96918842742359],"type":"Point"}
}