{
  "type": "Feature",
  "properties": {
    "iso:country": "GB",
    "wof:name": "PO19 8HB",
    "wof:placetype": "postalcode"
  },
  "geometry": {"coordinates":[-0.782052,50.829141],"type":"Point"}
}
