{
  "type": "Feature",
  "properties": {
    "iso:country":"GB",
    "wof:name":"WA3 5RY",
    "wof:placetype":"postalcode"
},
  "geometry": {"coordinates":[-2.51805985074269,53.45134532563803],"type":"Point"}
}