{
  "type": "Feature",
  "properties": {
    "date:inception_lower": "1980-01-01",
    "date:inception_upper": "1980-01-01",
    "iso:country": "GB",
    "wof:name": "SW14 8AR",
    "wof:placetype": "postalcode"
  },
  "geometry": {"coordinates":[-0.26161,51.463804],"type":"Point"}
}
