{
  "type": "Feature",
  "properties": {
    "iso:country":"GB",
    "wof:name":"SW14 8AR",
    "wof:placetype":"postalcode"
},
  "geometry": {"coordinates":[-0.26161009241897,51.46380431592078],"type":"Point"}
}