{
  "type": "Feature",
  "properties": {
    "date:inception_lower": "1990-09-01",
    "date:inception_upper": "1990-09-01",
    "iso:country": "GB",
    "wof:name": "EH26 8HT",
    "wof:placetype": "postalcode"
  },
  "geometry": {"coordinates":[-3.210115,55.830496],"type":"Point"}
}
