{
  "type": "Feature",
  "properties": {
    "iso:country":"GB",
    "wof:name":"EH26 8HT",
    "wof:placetype":"postalcode"
},
  "geometry": {"coordinates":[-3.2101152158408,55.83049559921515],"type":"Point"}
}