{
  "type": "Feature",
  "properties": {
    "iso:country": "GB",
    "wof:name": "BN27 3EQ",
    "wof:placetype": "postalcode"
  },
  "geometry": {"coordinates":[0.251002,50.861927],"type":"Point"}
}
