{
  "type": "Feature",
  "properties": {
    "iso:country":"GB",
    "wof:name":"M29 7BX",
    "wof:placetype":"postalcode"
},
  "geometry": {"coordinates":[-2.45786332471356,53.50641229654406],"type":"Point"}
}