{
  "type": "Feature",
  "properties": {
    "date:inception_lower": "1984-10-01",
    "date:inception_upper": "1984-10-01",
    "iso:country": "GB",
    "wof:name": "M29 7BX",
    "wof:placetype": "postalcode"
  },
  "geometry": {"coordinates":[-2.457863,53.506412],"type":"Point"}
}
