{
  "type": "Feature",
  "properties": {
    "iso:country": "GB",
    "wof:name": "M29 7BX",
    "wof:placetype": "postalcode"
  },
  "geometry": {"coordinates":[-2.457863,53.506412],"type":"Point"}
}
