{
  "type": "Feature",
  "properties": {
    "iso:country":"GB",
    "wof:name":"DL7 8WB",
    "wof:placetype":"postalcode"
},
  "geometry": {"coordinates":[-1.44755748223631,54.34494460280126],"type":"Point"}
}