{
  "type": "Feature",
  "properties": {
    "date:inception_lower":"2014-12-01",
    "date:inception_upper":"2014-12-31",
    "iso:country":"GB",
    "wof:name":"DL7 8WB",
    "wof:placetype":"postalcode"
},
  "geometry": {"coordinates":[-1.447557,54.344945],"type":"Point"}
}