{
  "type": "Feature",
  "properties": {
    "iso:country":"GB",
    "wof:name":"WF12 8HN",
    "wof:placetype":"postalcode"
},
  "geometry": {"coordinates":[-1.60777801973684,53.68973061266065],"type":"Point"}
}