{
  "type": "Feature",
  "properties": {
    "iso:country": "GB",
    "wof:name": "WF12 8HN",
    "wof:placetype": "postalcode"
  },
  "geometry": {"coordinates":[-1.607781,53.689746],"type":"Point"}
}
