{
  "type": "Feature",
  "properties": {
    "iso:country": "GB",
    "wof:name": "BB7 1AS",
    "wof:placetype": "postalcode"
  },
  "geometry": {"coordinates":[-2.390779,53.87202],"type":"Point"}
}
