{
  "type": "Feature",
  "properties": {
    "date:inception_lower": "1991-09-01",
    "date:inception_upper": "1991-09-01",
    "iso:country": "GB",
    "wof:name": "BB7 1AS",
    "wof:placetype": "postalcode"
  },
  "geometry": {"coordinates":[-2.390779,53.87202],"type":"Point"}
}
