{
  "type": "Feature",
  "properties": {
    "date:inception_lower": "2019-07-01",
    "date:inception_upper": "2019-07-01",
    "iso:country": "GB",
    "wof:name": "PE21 9EL",
    "wof:placetype": "postalcode"
  },
  "geometry": {"coordinates":[-0.005346,52.990722],"type":"Point"}
}
