{
  "type": "Feature",
  "properties": {
    "iso:country": "GB",
    "wof:name": "MK42 7PE",
    "wof:placetype": "postalcode"
  },
  "geometry": {"coordinates":[-0.487036,52.116035],"type":"Point"}
}
