{
  "type": "Feature",
  "properties": {
    "iso:country": "GB",
    "wof:name": "NN18 8DQ",
    "wof:placetype": "postalcode"
  },
  "geometry": {"coordinates":[-0.675577,52.475734],"type":"Point"}
}
