{
  "type": "Feature",
  "properties": {
    "iso:country":"GB",
    "wof:name":"PA18 6DF",
    "wof:placetype":"postalcode"
},
  "geometry": {"coordinates":[-4.89132297696333,55.89039166707614],"type":"Point"}
}