{
  "type": "Feature",
  "properties": {
    "iso:country":"GB",
    "wof:name":"W12 7FH",
    "wof:placetype":"postalcode"
},
  "geometry": {"coordinates":[-0.23522037138691,51.51084517882259],"type":"Point"}
}