{
  "type": "Feature",
  "properties": {
    "iso:country":"GB",
    "wof:name":"LE3 1HX",
    "wof:placetype":"postalcode"
},
  "geometry": {"coordinates":[-1.17841377958604,52.62477362925716],"type":"Point"}
}