{
  "type": "Feature",
  "properties": {
    "date:inception_lower":"1997-06-01",
    "date:inception_upper":"1997-06-30",
    "iso:country":"GB",
    "wof:name":"HR7 4LJ",
    "wof:placetype":"postalcode"
},
  "geometry": {"coordinates":[-2.513243,52.185001],"type":"Point"}
}