{
  "type": "Feature",
  "properties": {
    "iso:country": "GB",
    "wof:name": "HR7 4LJ",
    "wof:placetype": "postalcode"
  },
  "geometry": {"coordinates":[-2.513243,52.185001],"type":"Point"}
}
