{
  "type": "Feature",
  "properties": {
    "iso:country": "GB",
    "wof:name": "EX10 0HB",
    "wof:placetype": "postalcode"
  },
  "geometry": {"coordinates":[-3.293827,50.698135],"type":"Point"}
}
