{
  "type": "Feature",
  "properties": {
    "iso:country":"GB",
    "wof:name":"IG9 6BY",
    "wof:placetype":"postalcode"
},
  "geometry": {"coordinates":[0.05567191888914,51.63140208876852],"type":"Point"}
}