{
  "type": "Feature",
  "properties": {
    "date:inception_lower":"1980-01-01",
    "date:inception_upper":"1980-01-31",
    "iso:country":"GB",
    "wof:name":"IG9 6BY",
    "wof:placetype":"postalcode"
},
  "geometry": {"coordinates":[0.055672,51.631402],"type":"Point"}
}