{
  "type": "Feature",
  "properties": {
    "iso:country": "GB",
    "wof:name": "SA15 5DR",
    "wof:placetype": "postalcode"
  },
  "geometry": {"coordinates":[-4.195988,51.788264],"type":"Point"}
}
