{
  "type": "Feature",
  "properties": {
    "date:inception_lower":"1980-01-01",
    "date:inception_upper":"1980-01-31",
    "iso:country":"GB",
    "wof:name":"SA15 5DR",
    "wof:placetype":"postalcode"
},
  "geometry": {"coordinates":[-4.195988,51.788264],"type":"Point"}
}