{
  "type": "Feature",
  "properties": {
    "iso:country":"GB",
    "wof:name":"SA15 5DR",
    "wof:placetype":"postalcode"
},
  "geometry": {"coordinates":[-4.19598775121246,51.78826418746968],"type":"Point"}
}