{
  "type": "Feature",
  "properties": {
    "date:inception_lower": "1980-01-01",
    "date:inception_upper": "1980-01-01",
    "iso:country": "GB",
    "wof:name": "PA5 8JF",
    "wof:placetype": "postalcode"
  },
  "geometry": {"coordinates":[-4.501359,55.833801],"type":"Point"}
}
