{
  "type": "Feature",
  "properties": {
    "date:inception_lower": "1980-01-01",
    "date:inception_upper": "1980-01-01",
    "iso:country": "GB",
    "wof:name": "CA14 4LA",
    "wof:placetype": "postalcode"
  },
  "geometry": {"coordinates":[-3.536659,54.609215],"type":"Point"}
}
