{
  "type": "Feature",
  "properties": {
    "iso:country":"GB",
    "wof:name":"PO30 1QL",
    "wof:placetype":"postalcode"
},
  "geometry": {"coordinates":[-1.30142359223339,50.6959603965397],"type":"Point"}
}