{
  "type": "Feature",
  "properties": {
    "iso:country": "GB",
    "wof:name": "CT1 2AE",
    "wof:placetype": "postalcode"
  },
  "geometry": {"coordinates":[1.08265,51.282815],"type":"Point"}
}
