{
  "type": "Feature",
  "properties": {
    "iso:country":"GB",
    "wof:name":"CT1 2AE",
    "wof:placetype":"postalcode"
},
  "geometry": {"coordinates":[1.0826498646685,51.28281499979261],"type":"Point"}
}