{
  "type": "Feature",
  "properties": {
    "date:inception_lower":"1980-01-01",
    "date:inception_upper":"1980-01-31",
    "iso:country":"GB",
    "wof:name":"CT1 2AE",
    "wof:placetype":"postalcode"
},
  "geometry": {"coordinates":[1.08265,51.282815],"type":"Point"}
}