{
  "type": "Feature",
  "properties": {
    "date:inception_lower":"1991-09-01",
    "date:inception_upper":"1991-09-30",
    "iso:country":"GB",
    "wof:name":"L8 9ZB",
    "wof:placetype":"postalcode"
},
  "geometry": {"coordinates":[-2.963743,53.379006],"type":"Point"}
}