{
  "type": "Feature",
  "properties": {
    "iso:country": "GB",
    "wof:name": "TR15 1BX",
    "wof:placetype": "postalcode"
  },
  "geometry": {"coordinates":[-5.233311,50.240882],"type":"Point"}
}
