{
  "type": "Feature",
  "properties": {
    "iso:country": "GB",
    "wof:name": "TA4 4BQ",
    "wof:placetype": "postalcode"
  },
  "geometry": {"coordinates":[-3.260052,51.132009],"type":"Point"}
}
