{
  "type": "Feature",
  "properties": {
    "date:inception_lower": "1980-01-01",
    "date:inception_upper": "1980-01-01",
    "iso:country": "GB",
    "wof:name": "TA4 4BQ",
    "wof:placetype": "postalcode"
  },
  "geometry": {"coordinates":[-3.260052,51.132009],"type":"Point"}
}
