{
  "type": "Feature",
  "properties": {
    "iso:country":"GB",
    "wof:name":"TA4 4BQ",
    "wof:placetype":"postalcode"
},
  "geometry": {"coordinates":[-3.26006888584468,51.13200355578068],"type":"Point"}
}