{
  "type": "Feature",
  "properties": {
    "iso:country":"GB",
    "wof:name":"TQ3 3EA",
    "wof:placetype":"postalcode"
},
  "geometry": {"coordinates":[-3.58327564405402,50.42952135993741],"type":"Point"}
}