{
  "type": "Feature",
  "properties": {
    "date:inception_lower": "1980-01-01",
    "date:inception_upper": "1980-01-01",
    "iso:country": "GB",
    "wof:name": "SN8 4BY",
    "wof:placetype": "postalcode"
  },
  "geometry": {"coordinates":[-1.729169,51.418002],"type":"Point"}
}
