{
  "type": "Feature",
  "properties": {
    "iso:country":"GB",
    "wof:name":"LL16 4PN",
    "wof:placetype":"postalcode"
},
  "geometry": {"coordinates":[-3.36131422987749,53.13173385745905],"type":"Point"}
}