{
  "type": "Feature",
  "properties": {
    "iso:country": "GB",
    "wof:name": "NR19 1RL",
    "wof:placetype": "postalcode"
  },
  "geometry": {"coordinates":[0.969505,52.654736],"type":"Point"}
}
