{
  "type": "Feature",
  "properties": {
    "iso:country":"GB",
    "wof:name":"NR19 1RL",
    "wof:placetype":"postalcode"
},
  "geometry": {"coordinates":[0.96950485112785,52.6547361660877],"type":"Point"}
}