{
  "type": "Feature",
  "properties": {
    "iso:country":"GB",
    "wof:name":"RG45 7QG",
    "wof:placetype":"postalcode"
},
  "geometry": {"coordinates":[-0.80161863568276,51.36232932250883],"type":"Point"}
}