{
  "type": "Feature",
  "properties": {
    "iso:country": "GB",
    "wof:name": "RG45 7QG",
    "wof:placetype": "postalcode"
  },
  "geometry": {"coordinates":[-0.801619,51.362329],"type":"Point"}
}
