{
  "type": "Feature",
  "properties": {
    "iso:country":"GB",
    "wof:name":"ME20 7EP",
    "wof:placetype":"postalcode"
},
  "geometry": {"coordinates":[0.50397737787197,51.32403180317045],"type":"Point"}
}