{
  "type": "Feature",
  "properties": {
    "iso:country":"GB",
    "wof:name":"N4 2JR",
    "wof:placetype":"postalcode"
},
  "geometry": {"coordinates":[-0.09890198960002,51.56800249811263],"type":"Point"}
}