{
  "type": "Feature",
  "properties": {
    "iso:country":"GB",
    "wof:name":"FY6 0HF",
    "wof:placetype":"postalcode"
},
  "geometry": {"coordinates":[-2.96951637935163,53.93082978236531],"type":"Point"}
}