{
  "type": "Feature",
  "properties": {
    "iso:country": "GB",
    "wof:name": "FY6 0HF",
    "wof:placetype": "postalcode"
  },
  "geometry": {"coordinates":[-2.969516,53.93083],"type":"Point"}
}
