{
  "type": "Feature",
  "properties": {
    "iso:country": "GB",
    "wof:name": "EH53 0NT",
    "wof:placetype": "postalcode"
  },
  "geometry": {"coordinates":[-3.496657,55.906954],"type":"Point"}
}
