{
  "type": "Feature",
  "properties": {
    "iso:country":"GB",
    "wof:name":"SY16 4PJ",
    "wof:placetype":"postalcode"
},
  "geometry": {"coordinates":[-3.24468010309145,52.47989394939981],"type":"Point"}
}