{
  "type": "Feature",
  "properties": {
    "iso:country":"GB",
    "wof:name":"EH41 3TE",
    "wof:placetype":"postalcode"
},
  "geometry": {"coordinates":[-2.74809311601395,55.96293916153233],"type":"Point"}
}