{
  "type": "Feature",
  "properties": {
    "date:inception_lower": "1980-01-01",
    "date:inception_upper": "1980-01-01",
    "iso:country": "GB",
    "wof:name": "EH41 3TE",
    "wof:placetype": "postalcode"
  },
  "geometry": {"coordinates":[-2.748093,55.962939],"type":"Point"}
}
