{
  "type": "Feature",
  "properties": {
    "iso:country": "GB",
    "wof:name": "S18 1UZ",
    "wof:placetype": "postalcode"
  },
  "geometry": {"coordinates":[-1.46932,53.295132],"type":"Point"}
}
