{
  "type": "Feature",
  "properties": {
    "iso:country":"GB",
    "wof:name":"TD9 9QP",
    "wof:placetype":"postalcode"
},
  "geometry": {"coordinates":[-2.78497462851115,55.4267555731597],"type":"Point"}
}