{
  "type": "Feature",
  "properties": {
    "iso:country": "GB",
    "wof:name": "ST18 9ET",
    "wof:placetype": "postalcode"
  },
  "geometry": {"coordinates":[-2.196854,52.780784],"type":"Point"}
}
