{
  "type": "Feature",
  "properties": {
    "iso:country":"GB",
    "wof:name":"CA12 5XE",
    "wof:placetype":"postalcode"
},
  "geometry": {"coordinates":[-3.15184317890774,54.51913014359801],"type":"Point"}
}