{
  "type": "Feature",
  "properties": {
    "iso:country": "GB",
    "wof:name": "CA12 5XE",
    "wof:placetype": "postalcode"
  },
  "geometry": {"coordinates":[-3.150428,54.518702],"type":"Point"}
}
