{
  "type": "Feature",
  "properties": {
    "date:inception_lower": "1980-01-01",
    "date:inception_upper": "1980-01-01",
    "iso:country": "GB",
    "wof:name": "CA12 5XE",
    "wof:placetype": "postalcode"
  },
  "geometry": {"coordinates":[-3.15049,54.51871],"type":"Point"}
}
