{
  "type": "Feature",
  "properties": {
    "iso:country": "GB",
    "wof:name": "ST3 7XA",
    "wof:placetype": "postalcode"
  },
  "geometry": {"coordinates":[-2.099794,52.962328],"type":"Point"}
}
