{
  "type": "Feature",
  "properties": {
    "iso:country":"GB",
    "wof:name":"ST3 7XA",
    "wof:placetype":"postalcode"
},
  "geometry": {"coordinates":[-2.09979378310395,52.96232848045764],"type":"Point"}
}