{
  "type": "Feature",
  "properties": {
    "iso:country":"GB",
    "wof:name":"PO19 6GL",
    "wof:placetype":"postalcode"
},
  "geometry": {"coordinates":[-0.76284824458523,50.84387639996402],"type":"Point"}
}