{
  "type": "Feature",
  "properties": {
    "date:inception_lower":"2003-11-01",
    "date:inception_upper":"2003-11-30",
    "iso:country":"GB",
    "wof:name":"PO19 6GL",
    "wof:placetype":"postalcode"
},
  "geometry": {"coordinates":[-0.762848,50.843876],"type":"Point"}
}