{
  "type": "Feature",
  "properties": {
    "iso:country":"GB",
    "wof:name":"CA6 5PL",
    "wof:placetype":"postalcode"
},
  "geometry": {"coordinates":[-2.92259676308384,55.05785485116341],"type":"Point"}
}