{
  "type": "Feature",
  "properties": {
    "date:inception_lower": "1980-01-01",
    "date:inception_upper": "1980-01-01",
    "iso:country": "GB",
    "wof:name": "CA6 5PL",
    "wof:placetype": "postalcode"
  },
  "geometry": {"coordinates":[-2.922785,55.057724],"type":"Point"}
}
