{
  "type": "Feature",
  "properties": {
    "iso:country":"GB",
    "wof:name":"W6 8QL",
    "wof:placetype":"postalcode"
},
  "geometry": {"coordinates":[-0.21167071449652,51.48328632121355],"type":"Point"}
}