{
  "type": "Feature",
  "properties": {
    "date:inception_lower":"1980-01-01",
    "date:inception_upper":"1980-01-31",
    "iso:country":"GB",
    "wof:name":"W6 8QL",
    "wof:placetype":"postalcode"
},
  "geometry": {"coordinates":[-0.211671,51.483286],"type":"Point"}
}