{
  "type": "Feature",
  "properties": {
    "iso:country":"GB",
    "wof:name":"LL18 1UB",
    "wof:placetype":"postalcode"
},
  "geometry": {"coordinates":[-3.48938476107857,53.31998142373792],"type":"Point"}
}