{
  "type": "Feature",
  "properties": {
    "iso:country":"GB",
    "wof:name":"SA72 6JU",
    "wof:placetype":"postalcode"
},
  "geometry": {"coordinates":[-4.94740716200393,51.69452217026419],"type":"Point"}
}