{
  "type": "Feature",
  "properties": {
    "date:inception_lower":"1980-01-01",
    "date:inception_upper":"1980-01-31",
    "iso:country":"GB",
    "wof:name":"SA72 6JU",
    "wof:placetype":"postalcode"
},
  "geometry": {"coordinates":[-4.947407,51.694522],"type":"Point"}
}