{
  "type": "Feature",
  "properties": {
    "iso:country": "GB",
    "wof:name": "GU22 8TG",
    "wof:placetype": "postalcode"
  },
  "geometry": {"coordinates":[-0.506287,51.324721],"type":"Point"}
}
