{
  "type": "Feature",
  "properties": {
    "date:inception_lower": "1980-01-01",
    "date:inception_upper": "1980-01-01",
    "iso:country": "GB",
    "wof:name": "G44 4LF",
    "wof:placetype": "postalcode"
  },
  "geometry": {"coordinates":[-4.234571,55.821674],"type":"Point"}
}
