{
  "type": "Feature",
  "properties": {
    "iso:country":"GB",
    "wof:name":"S70 9ZW",
    "wof:placetype":"postalcode"
},
  "geometry": {"coordinates":[-1.48285715388121,53.55415314175051],"type":"Point"}
}