{
  "type": "Feature",
  "properties": {
    "date:inception_lower":"2015-05-01",
    "date:inception_upper":"2015-05-31",
    "iso:country":"GB",
    "wof:name":"CO13 0FG",
    "wof:placetype":"postalcode"
},
  "geometry": {"coordinates":[1.233569,51.841057],"type":"Point"}
}