{
  "type": "Feature",
  "properties": {
    "iso:country":"GB",
    "wof:name":"CO13 0FG",
    "wof:placetype":"postalcode"
},
  "geometry": {"coordinates":[1.23356876930846,51.84105739873137],"type":"Point"}
}