{
  "type": "Feature",
  "properties": {
    "iso:country":"GB",
    "wof:name":"SY10 0JU",
    "wof:placetype":"postalcode"
},
  "geometry": {"coordinates":[-3.30468830657381,52.82555387288872],"type":"Point"}
}