{
  "type": "Feature",
  "properties": {
    "iso:country":"GB",
    "wof:name":"HP2 6PR",
    "wof:placetype":"postalcode"
},
  "geometry": {"coordinates":[-0.45658562814666,51.77393416899641],"type":"Point"}
}