{
  "type": "Feature",
  "properties": {
    "iso:country":"GB",
    "wof:name":"SP10 1LB",
    "wof:placetype":"postalcode"
},
  "geometry": {"coordinates":[-1.46385504298935,51.21430510092354],"type":"Point"}
}