{
  "type": "Feature",
  "properties": {
    "iso:country":"GB",
    "wof:name":"PE22 8NA",
    "wof:placetype":"postalcode"
},
  "geometry": {"coordinates":[0.17650934561707,53.07587794425574],"type":"Point"}
}