{
  "type": "Feature",
  "properties": {
    "iso:country": "GB",
    "wof:name": "YO25 6TE",
    "wof:placetype": "postalcode"
  },
  "geometry": {"coordinates":[-0.442678,54.007168],"type":"Point"}
}
