{
  "type": "Feature",
  "properties": {
    "iso:country":"GB",
    "wof:name":"YO25 6TE",
    "wof:placetype":"postalcode"
},
  "geometry": {"coordinates":[-0.44267820278724,54.0071676833535],"type":"Point"}
}