{
  "type": "Feature",
  "properties": {
    "iso:country":"GB",
    "wof:name":"EN5 1PR",
    "wof:placetype":"postalcode"
},
  "geometry": {"coordinates":[-0.17936342933751,51.64841999234929],"type":"Point"}
}