{
  "type": "Feature",
  "properties": {
    "iso:country":"GB",
    "wof:name":"FK7 7SP",
    "wof:placetype":"postalcode"
},
  "geometry": {"coordinates":[-3.91828229230981,56.11505346022732],"type":"Point"}
}