{
  "type": "Feature",
  "properties": {
    "date:inception_lower": "1980-01-01",
    "date:inception_upper": "1980-01-01",
    "iso:country": "GB",
    "wof:name": "TA6 5JS",
    "wof:placetype": "postalcode"
  },
  "geometry": {"coordinates":[-2.995957,51.127502],"type":"Point"}
}
