{
  "type": "Feature",
  "properties": {
    "iso:country":"GB",
    "wof:name":"TA6 5JS",
    "wof:placetype":"postalcode"
},
  "geometry": {"coordinates":[-2.99595687484042,51.12750173346863],"type":"Point"}
}