{
  "type": "Feature",
  "properties": {
    "iso:country":"GB",
    "wof:name":"N1 5TG",
    "wof:placetype":"postalcode"
},
  "geometry": {"coordinates":[-0.08084437297869,51.53868068348465],"type":"Point"}
}