{
  "type": "Feature",
  "properties": {
    "iso:country":"GB",
    "wof:name":"RH19 4LD",
    "wof:placetype":"postalcode"
},
  "geometry": {"coordinates":[-0.04884888993477,51.10471422202313],"type":"Point"}
}