{
  "type": "Feature",
  "properties": {
    "iso:country":"GB",
    "wof:name":"LE3 1PE",
    "wof:placetype":"postalcode"
},
  "geometry": {"coordinates":[-1.16649548538646,52.62536465340705],"type":"Point"}
}