{
  "type": "Feature",
  "properties": {
    "iso:country": "GB",
    "wof:name": "LD3 0NA",
    "wof:placetype": "postalcode"
  },
  "geometry": {"coordinates":[-3.287095,52.012067],"type":"Point"}
}
