{
  "type": "Feature",
  "properties": {
    "iso:country":"GB",
    "wof:name":"LD3 0NA",
    "wof:placetype":"postalcode"
},
  "geometry": {"coordinates":[-3.2870952718503,52.01206691603459],"type":"Point"}
}