{
  "type": "Feature",
  "properties": {
    "iso:country": "GB",
    "wof:name": "TA5 1NU",
    "wof:placetype": "postalcode"
  },
  "geometry": {"coordinates":[-3.155392,51.149667],"type":"Point"}
}
