{
  "type": "Feature",
  "properties": {
    "date:inception_lower": "2002-07-01",
    "date:inception_upper": "2002-07-01",
    "iso:country": "GB",
    "wof:name": "N7 8HH",
    "wof:placetype": "postalcode"
  },
  "geometry": {"coordinates":[-0.111535,51.55151],"type":"Point"}
}
