{
  "type": "Feature",
  "properties": {
    "iso:country":"GB",
    "wof:name":"N7 8HH",
    "wof:placetype":"postalcode"
},
  "geometry": {"coordinates":[-0.11156183246645,51.55150789839888],"type":"Point"}
}