{
  "type": "Feature",
  "properties": {
    "date:inception_lower":"2002-07-01",
    "date:inception_upper":"2002-07-31",
    "iso:country":"GB",
    "wof:name":"N7 8HH",
    "wof:placetype":"postalcode"
},
  "geometry": {"coordinates":[-0.111594,51.551484],"type":"Point"}
}