{
  "type": "Feature",
  "properties": {
    "iso:country": "GB",
    "wof:name": "N7 8HH",
    "wof:placetype": "postalcode"
  },
  "geometry": {"coordinates":[-0.111594,51.551484],"type":"Point"}
}
