{
  "type": "Feature",
  "properties": {
    "date:inception_lower": "2020-08-01",
    "date:inception_upper": "2020-08-01",
    "iso:country": "GB",
    "wof:name": "BS23 9QH",
    "wof:placetype": "postalcode"
  },
  "geometry": {"coordinates":[-2.957028,51.343878],"type":"Point"}
}
