{
  "type": "Feature",
  "properties": {
    "date:inception_lower":"2000-06-01",
    "date:inception_upper":"2000-06-30",
    "iso:country":"GB",
    "wof:name":"PE28 2JB",
    "wof:placetype":"postalcode"
},
  "geometry": {"coordinates":[-0.113007,52.343532],"type":"Point"}
}