{
  "type": "Feature",
  "properties": {
    "iso:country":"GB",
    "wof:name":"PE28 2JB",
    "wof:placetype":"postalcode"
},
  "geometry": {"coordinates":[-0.11300745939483,52.34353239171482],"type":"Point"}
}