{
  "type": "Feature",
  "properties": {
    "iso:country": "GB",
    "wof:name": "IV2 8AD",
    "wof:placetype": "postalcode"
  },
  "geometry": {"coordinates":[-4.036136,57.525774],"type":"Point"}
}
