{
  "type": "Feature",
  "properties": {
    "iso:country": "GB",
    "wof:name": "DL13 2RA",
    "wof:placetype": "postalcode"
  },
  "geometry": {"coordinates":[-1.961943,54.72701],"type":"Point"}
}
