{
  "type": "Feature",
  "properties": {
    "iso:country":"GB",
    "wof:name":"DL13 2RA",
    "wof:placetype":"postalcode"
},
  "geometry": {"coordinates":[-1.96194258368925,54.72701042904325],"type":"Point"}
}