{
  "type": "Feature",
  "properties": {
    "date:inception_lower": "1994-05-01",
    "date:inception_upper": "1994-05-01",
    "iso:country": "GB",
    "wof:name": "EN8 0UH",
    "wof:placetype": "postalcode"
  },
  "geometry": {"coordinates":[-0.038732,51.714012],"type":"Point"}
}
