{
  "type": "Feature",
  "properties": {
    "iso:country":"GB",
    "wof:name":"TS10 1PE",
    "wof:placetype":"postalcode"
},
  "geometry": {"coordinates":[-1.08218145530934,54.61167396427211],"type":"Point"}
}