{
  "type": "Feature",
  "properties": {
    "iso:country": "GB",
    "wof:name": "TS10 1PE",
    "wof:placetype": "postalcode"
  },
  "geometry": {"coordinates":[-1.082181,54.611674],"type":"Point"}
}
