{
  "type": "Feature",
  "properties": {
    "date:inception_lower": "1997-12-01",
    "date:inception_upper": "1997-12-01",
    "iso:country": "GB",
    "wof:name": "BB18 5QT",
    "wof:placetype": "postalcode"
  },
  "geometry": {"coordinates":[-2.187584,53.911032],"type":"Point"}
}
