{
  "type": "Feature",
  "properties": {
    "iso:country": "GB",
    "wof:name": "BB18 5QT",
    "wof:placetype": "postalcode"
  },
  "geometry": {"coordinates":[-2.187584,53.911032],"type":"Point"}
}
