{
  "type": "Feature",
  "properties": {
    "iso:country":"GB",
    "wof:name":"BB18 5QT",
    "wof:placetype":"postalcode"
},
  "geometry": {"coordinates":[-2.18758406838435,53.91103193676058],"type":"Point"}
}