{
  "type": "Feature",
  "properties": {
    "date:inception_lower": "1999-06-01",
    "date:inception_upper": "1999-06-01",
    "iso:country": "GB",
    "wof:name": "TF8 7LQ",
    "wof:placetype": "postalcode"
  },
  "geometry": {"coordinates":[-2.457369,52.621055],"type":"Point"}
}
