{
  "type": "Feature",
  "properties": {
    "iso:country": "GB",
    "wof:name": "TF8 7LQ",
    "wof:placetype": "postalcode"
  },
  "geometry": {"coordinates":[-2.457369,52.621055],"type":"Point"}
}
