{
  "type": "Feature",
  "properties": {
    "iso:country":"GB",
    "wof:name":"TF8 7LQ",
    "wof:placetype":"postalcode"
},
  "geometry": {"coordinates":[-2.45736885431428,52.62105509371271],"type":"Point"}
}