{
  "type": "Feature",
  "properties": {
    "date:inception_lower":"1996-12-01",
    "date:inception_upper":"1996-12-31",
    "iso:country":"GB",
    "wof:name":"BB2 3RA",
    "wof:placetype":"postalcode"
},
  "geometry": {"coordinates":[-2.486106,53.740884],"type":"Point"}
}