{
  "type": "Feature",
  "properties": {
    "iso:country":"GB",
    "wof:name":"BB2 3RA",
    "wof:placetype":"postalcode"
},
  "geometry": {"coordinates":[-2.48602464495795,53.74023093956334],"type":"Point"}
}