{
  "type": "Feature",
  "properties": {
    "iso:country": "GB",
    "wof:name": "NR3 3TQ",
    "wof:placetype": "postalcode"
  },
  "geometry": {"coordinates":[1.290697,52.652172],"type":"Point"}
}
