{
  "type": "Feature",
  "properties": {
    "iso:country":"GB",
    "wof:name":"NR3 3TQ",
    "wof:placetype":"postalcode"
},
  "geometry": {"coordinates":[1.29069708384462,52.65217176985225],"type":"Point"}
}