{
  "type": "Feature",
  "properties": {
    "iso:country":"GB",
    "wof:name":"NR3 1RN",
    "wof:placetype":"postalcode"
},
  "geometry": {"coordinates":[1.30038934487993,52.63360890791655],"type":"Point"}
}