{
  "type": "Feature",
  "properties": {
    "date:inception_lower": "1980-01-01",
    "date:inception_upper": "1980-01-01",
    "iso:country": "GB",
    "wof:name": "NR3 1RN",
    "wof:placetype": "postalcode"
  },
  "geometry": {"coordinates":[1.300389,52.633609],"type":"Point"}
}
