{
  "type": "Feature",
  "properties": {
    "iso:country":"GB",
    "wof:name":"IP22 2JW",
    "wof:placetype":"postalcode"
},
  "geometry": {"coordinates":[0.99384206027022,52.37945665901882],"type":"Point"}
}