{
  "type": "Feature",
  "properties": {
    "date:inception_lower": "1980-01-01",
    "date:inception_upper": "1980-01-01",
    "iso:country": "GB",
    "wof:name": "IP22 2JW",
    "wof:placetype": "postalcode"
  },
  "geometry": {"coordinates":[0.993842,52.379457],"type":"Point"}
}
