{
  "type": "Feature",
  "properties": {
    "iso:country":"GB",
    "wof:name":"IG10 4QU",
    "wof:placetype":"postalcode"
},
  "geometry": {"coordinates":[0.05034432181385,51.64399493071218],"type":"Point"}
}