{
  "type": "Feature",
  "properties": {
    "date:inception_lower": "1980-01-01",
    "date:inception_upper": "1980-01-01",
    "iso:country": "GB",
    "wof:name": "IG10 4QU",
    "wof:placetype": "postalcode"
  },
  "geometry": {"coordinates":[0.050483,51.643608],"type":"Point"}
}
