{
  "type": "Feature",
  "properties": {
    "iso:country":"GB",
    "wof:name":"TR19 7LT",
    "wof:placetype":"postalcode"
},
  "geometry": {"coordinates":[-5.68134680970491,50.12538449829884],"type":"Point"}
}