{
  "type": "Feature",
  "properties": {
    "iso:country":"GB",
    "wof:name":"BN1 2FZ",
    "wof:placetype":"postalcode"
},
  "geometry": {"coordinates":[-0.14978667222458,50.82180859987441],"type":"Point"}
}