{
  "type": "Feature",
  "properties": {
    "date:inception_lower": "2012-02-01",
    "date:inception_upper": "2012-02-01",
    "iso:country": "GB",
    "wof:name": "SE27 9BF",
    "wof:placetype": "postalcode"
  },
  "geometry": {"coordinates":[-0.102757,51.435074],"type":"Point"}
}
