{
  "type": "Feature",
  "properties": {
    "iso:country":"GB",
    "wof:name":"SE27 9BF",
    "wof:placetype":"postalcode"
},
  "geometry": {"coordinates":[-0.1027570058295,51.4350738293647],"type":"Point"}
}