{
  "type": "Feature",
  "properties": {
    "iso:country":"GB",
    "wof:name":"B67 7DD",
    "wof:placetype":"postalcode"
},
  "geometry": {"coordinates":[-1.976170624055,52.49154794834249],"type":"Point"}
}