{
  "type": "Feature",
  "properties": {
    "date:inception_lower": "2020-10-01",
    "date:inception_upper": "2020-10-01",
    "iso:country": "GB",
    "wof:name": "HU9 4DG",
    "wof:placetype": "postalcode"
  },
  "geometry": {"coordinates":[-0.26084,53.762961],"type":"Point"}
}
