{
  "type": "Feature",
  "properties": {
    "date:inception_lower": "1980-01-01",
    "date:inception_upper": "1980-01-01",
    "iso:country": "GB",
    "wof:name": "ST3 7SA",
    "wof:placetype": "postalcode"
  },
  "geometry": {"coordinates":[-2.117047,52.978528],"type":"Point"}
}
