{
  "type": "Feature",
  "properties": {
    "iso:country":"GB",
    "wof:name":"ST3 7SA",
    "wof:placetype":"postalcode"
},
  "geometry": {"coordinates":[-2.11710704128515,52.97851121165689],"type":"Point"}
}