{
  "type": "Feature",
  "properties": {
    "date:inception_lower": "2022-10-01",
    "date:inception_upper": "2022-10-01",
    "iso:country": "GB",
    "wof:name": "TN21 8FS",
    "wof:placetype": "postalcode"
  },
  "geometry": {"coordinates":[0.264096,50.974587],"type":"Point"}
}
