{
  "type": "Feature",
  "properties": {
    "date:inception_lower": "1984-10-01",
    "date:inception_upper": "1984-10-01",
    "iso:country": "GB",
    "wof:name": "OX14 5EZ",
    "wof:placetype": "postalcode"
  },
  "geometry": {"coordinates":[-1.293324,51.665782],"type":"Point"}
}
