{
  "type": "Feature",
  "properties": {
    "iso:country":"GB",
    "wof:name":"OX14 5EZ",
    "wof:placetype":"postalcode"
},
  "geometry": {"coordinates":[-1.29332390370747,51.66578183360643],"type":"Point"}
}