{
  "type": "Feature",
  "properties": {
    "iso:country":"GB",
    "wof:name":"SG4 7NT",
    "wof:placetype":"postalcode"
},
  "geometry": {"coordinates":[-0.24706307569324,51.9130330338484],"type":"Point"}
}