{
  "type": "Feature",
  "properties": {
    "date:inception_lower": "1980-01-01",
    "date:inception_upper": "1980-01-01",
    "iso:country": "GB",
    "wof:name": "SG4 7NT",
    "wof:placetype": "postalcode"
  },
  "geometry": {"coordinates":[-0.24704,51.913039],"type":"Point"}
}
