{
  "type": "Feature",
  "properties": {
    "iso:country":"GB",
    "wof:name":"TR12 6ES",
    "wof:placetype":"postalcode"
},
  "geometry": {"coordinates":[-5.08637069413197,50.08076012184201],"type":"Point"}
}