{
  "type": "Feature",
  "properties": {
    "date:inception_lower": "1980-01-01",
    "date:inception_upper": "1980-01-01",
    "iso:country": "GB",
    "wof:name": "TR12 6ES",
    "wof:placetype": "postalcode"
  },
  "geometry": {"coordinates":[-5.087688,50.080687],"type":"Point"}
}
