{
  "type": "Feature",
  "properties": {
    "iso:country": "GB",
    "wof:name": "TR12 6ES",
    "wof:placetype": "postalcode"
  },
  "geometry": {"coordinates":[-5.086371,50.08076],"type":"Point"}
}
