{
  "type": "Feature",
  "properties": {
    "date:inception_lower": "1980-01-01",
    "date:inception_upper": "1980-01-01",
    "iso:country": "GB",
    "wof:name": "LA21 8AE",
    "wof:placetype": "postalcode"
  },
  "geometry": {"coordinates":[-3.046479,54.370203],"type":"Point"}
}
