{
  "type": "Feature",
  "properties": {
    "iso:country": "GB",
    "wof:name": "WR11 2SH",
    "wof:placetype": "postalcode"
  },
  "geometry": {"coordinates":[-1.954451,52.075969],"type":"Point"}
}
