{
  "type": "Feature",
  "properties": {
    "date:inception_lower": "1989-07-01",
    "date:inception_upper": "1989-07-01",
    "iso:country": "GB",
    "wof:name": "EH12 9EU",
    "wof:placetype": "postalcode"
  },
  "geometry": {"coordinates":[-3.295005,55.933326],"type":"Point"}
}
