{
  "type": "Feature",
  "properties": {
    "iso:country":"GB",
    "wof:name":"CH46 1RW",
    "wof:placetype":"postalcode"
},
  "geometry": {"coordinates":[-3.09926845588753,53.41584960903971],"type":"Point"}
}