{
  "type": "Feature",
  "properties": {
    "iso:country":"GB",
    "wof:name":"TR15 2SH",
    "wof:placetype":"postalcode"
},
  "geometry": {"coordinates":[-5.23106322906757,50.23181291112181],"type":"Point"}
}