{
  "type": "Feature",
  "properties": {
    "iso:country": "GB",
    "wof:name": "ML7 4BL",
    "wof:placetype": "postalcode"
  },
  "geometry": {"coordinates":[-3.804585,55.818159],"type":"Point"}
}
