{
  "type": "Feature",
  "properties": {
    "date:inception_lower": "1989-04-01",
    "date:inception_upper": "1989-04-01",
    "iso:country": "GB",
    "wof:name": "ML7 4BL",
    "wof:placetype": "postalcode"
  },
  "geometry": {"coordinates":[-3.804585,55.818159],"type":"Point"}
}
