{
  "type": "Feature",
  "properties": {
    "date:inception_lower": "2007-04-01",
    "date:inception_upper": "2007-04-01",
    "iso:country": "GB",
    "wof:name": "NE21 5EH",
    "wof:placetype": "postalcode"
  },
  "geometry": {"coordinates":[-1.714397,54.956356],"type":"Point"}
}
