{
  "type": "Feature",
  "properties": {
    "date:inception_lower": "2004-11-01",
    "date:inception_upper": "2004-11-01",
    "iso:country": "GB",
    "wof:name": "YO22 5AJ",
    "wof:placetype": "postalcode"
  },
  "geometry": {"coordinates":[-0.656564,54.456573],"type":"Point"}
}
