{
  "type": "Feature",
  "properties": {
    "iso:country":"GB",
    "wof:name":"LN8 6EF",
    "wof:placetype":"postalcode"
},
  "geometry": {"coordinates":[-0.19430730735039,53.43942819951774],"type":"Point"}
}