{
  "type": "Feature",
  "properties": {
    "iso:country": "GB",
    "wof:name": "DN15 8RY",
    "wof:placetype": "postalcode"
  },
  "geometry": {"coordinates":[-0.70353,53.631331],"type":"Point"}
}
