{
  "type": "Feature",
  "properties": {
    "date:inception_lower": "1980-01-01",
    "date:inception_upper": "1980-01-01",
    "iso:country": "GB",
    "wof:name": "HX1 1TT",
    "wof:placetype": "postalcode"
  },
  "geometry": {"coordinates":[-1.860947,53.723224],"type":"Point"}
}
