{
  "type": "Feature",
  "properties": {
    "iso:country":"GB",
    "wof:name":"B95 6AE",
    "wof:placetype":"postalcode"
},
  "geometry": {"coordinates":[-1.78010489750714,52.28572456508567],"type":"Point"}
}