{
  "type": "Feature",
  "properties": {
    "date:inception_lower":"1980-01-01",
    "date:inception_upper":"1980-01-31",
    "iso:country":"GB",
    "wof:name":"B95 6AE",
    "wof:placetype":"postalcode"
},
  "geometry": {"coordinates":[-1.780105,52.285725],"type":"Point"}
}