{
  "type": "Feature",
  "properties": {
    "iso:country":"GB",
    "wof:name":"SW11 4PZ",
    "wof:placetype":"postalcode"
},
  "geometry": {"coordinates":[-0.16332913997639,51.47521020202413],"type":"Point"}
}