{
  "type": "Feature",
  "properties": {
    "iso:country": "GB",
    "wof:name": "WA12 0LW",
    "wof:placetype": "postalcode"
  },
  "geometry": {"coordinates":[-2.634481,53.462909],"type":"Point"}
}
