{
  "type": "Feature",
  "properties": {
    "iso:country":"GB",
    "wof:name":"WA12 0LW",
    "wof:placetype":"postalcode"
},
  "geometry": {"coordinates":[-2.63448085410609,53.46290919680209],"type":"Point"}
}