{
  "type": "Feature",
  "properties": {
    "iso:country":"GB",
    "wof:name":"TF11 9HS",
    "wof:placetype":"postalcode"
},
  "geometry": {"coordinates":[-2.34857717835327,52.63595285100648],"type":"Point"}
}