{
  "type": "Feature",
  "properties": {
    "date:inception_lower": "1980-01-01",
    "date:inception_upper": "1980-01-01",
    "iso:country": "GB",
    "wof:name": "TF11 9HS",
    "wof:placetype": "postalcode"
  },
  "geometry": {"coordinates":[-2.348577,52.635953],"type":"Point"}
}
