{
  "type": "Feature",
  "properties": {
    "iso:country":"GB",
    "wof:name":"KA26 0TZ",
    "wof:placetype":"postalcode"
},
  "geometry": {"coordinates":[-4.82973369015042,55.1603722960856],"type":"Point"}
}