{
  "type": "Feature",
  "properties": {
    "date:inception_lower":"2011-05-01",
    "date:inception_upper":"2011-05-31",
    "iso:country":"GB",
    "wof:name":"KA26 0TZ",
    "wof:placetype":"postalcode"
},
  "geometry": {"coordinates":[-4.829734,55.160372],"type":"Point"}
}