{
  "type": "Feature",
  "properties": {
    "iso:country":"GB",
    "wof:name":"L26 7XW",
    "wof:placetype":"postalcode"
},
  "geometry": {"coordinates":[-2.84322442354853,53.37519954679726],"type":"Point"}
}