{
  "type": "Feature",
  "properties": {
    "date:inception_lower":"1993-08-01",
    "date:inception_upper":"1993-08-31",
    "iso:country":"GB",
    "wof:name":"L26 7XW",
    "wof:placetype":"postalcode"
},
  "geometry": {"coordinates":[-2.843224,53.3752],"type":"Point"}
}