{
  "type": "Feature",
  "properties": {
    "iso:country":"GB",
    "wof:name":"EX5 1HA",
    "wof:placetype":"postalcode"
},
  "geometry": {"coordinates":[-3.37645672023854,50.68240360003873],"type":"Point"}
}