{
  "type": "Feature",
  "properties": {
    "iso:country":"GB",
    "wof:name":"B97 5DA",
    "wof:placetype":"postalcode"
},
  "geometry": {"coordinates":[-1.94726171046772,52.29155401489719],"type":"Point"}
}