{
  "type": "Feature",
  "properties": {
    "iso:country":"GB",
    "wof:name":"HA4 0SH",
    "wof:placetype":"postalcode"
},
  "geometry": {"coordinates":[-0.39078575518347,51.56361876169614],"type":"Point"}
}