{
  "type": "Feature",
  "properties": {
    "iso:country": "GB",
    "wof:name": "LU7 9HN",
    "wof:placetype": "postalcode"
  },
  "geometry": {"coordinates":[-0.584975,51.930609],"type":"Point"}
}
