{
  "type": "Feature",
  "properties": {
    "iso:country":"GB",
    "wof:name":"LU7 9HN",
    "wof:placetype":"postalcode"
},
  "geometry": {"coordinates":[-0.58498053767312,51.93074409502166],"type":"Point"}
}