{
  "type": "Feature",
  "properties": {
    "iso:country":"GB",
    "wof:name":"MK43 0LG",
    "wof:placetype":"postalcode"
},
  "geometry": {"coordinates":[-0.54756554419614,52.06550998907865],"type":"Point"}
}