{
  "type": "Feature",
  "properties": {
    "date:inception_lower":"1980-01-01",
    "date:inception_upper":"1980-01-31",
    "iso:country":"GB",
    "wof:name":"GL12 8HJ",
    "wof:placetype":"postalcode"
},
  "geometry": {"coordinates":[-2.426157,51.630951],"type":"Point"}
}