{
  "type": "Feature",
  "properties": {
    "iso:country":"GB",
    "wof:name":"GL12 8HJ",
    "wof:placetype":"postalcode"
},
  "geometry": {"coordinates":[-2.42615705725928,51.63095106708071],"type":"Point"}
}