{
  "type": "Feature",
  "properties": {
    "date:inception_lower":"1980-01-01",
    "date:inception_upper":"1980-01-31",
    "iso:country":"GB",
    "wof:name":"TA6 3QW",
    "wof:placetype":"postalcode"
},
  "geometry": {"coordinates":[-3.008296,51.134685],"type":"Point"}
}