{
  "type": "Feature",
  "properties": {
    "iso:country":"GB",
    "wof:name":"TA6 3QW",
    "wof:placetype":"postalcode"
},
  "geometry": {"coordinates":[-3.00815732338521,51.13455505583688],"type":"Point"}
}