{
  "type": "Feature",
  "properties": {
    "iso:country": "GB",
    "wof:name": "RH19 1RG",
    "wof:placetype": "postalcode"
  },
  "geometry": {"coordinates":[-0.034717,51.135117],"type":"Point"}
}
