{
  "type": "Feature",
  "properties": {
    "date:inception_lower":"2013-07-01",
    "date:inception_upper":"2013-07-31",
    "iso:country":"GB",
    "wof:name":"EX7 0FG",
    "wof:placetype":"postalcode"
},
  "geometry": {"coordinates":[-3.466597,50.589266],"type":"Point"}
}