{
  "type": "Feature",
  "properties": {
    "iso:country":"GB",
    "wof:name":"KT6 5HS",
    "wof:placetype":"postalcode"
},
  "geometry": {"coordinates":[-0.3197804241118,51.38353156920143],"type":"Point"}
}