{
  "type": "Feature",
  "properties": {
    "date:inception_lower": "2018-06-01",
    "date:inception_upper": "2018-06-01",
    "iso:country": "GB",
    "wof:name": "SK9 6GJ",
    "wof:placetype": "postalcode"
  },
  "geometry": {"coordinates":[-2.264594,53.319224],"type":"Point"}
}
