{
  "type": "Feature",
  "properties": {
    "iso:country":"GB",
    "wof:name":"YO18 8TH",
    "wof:placetype":"postalcode"
},
  "geometry": {"coordinates":[-0.78346992127391,54.24147304917215],"type":"Point"}
}