{
  "type": "Feature",
  "properties": {
    "date:inception_lower": "1995-01-01",
    "date:inception_upper": "1995-01-01",
    "iso:country": "GB",
    "wof:name": "YO18 8TH",
    "wof:placetype": "postalcode"
  },
  "geometry": {"coordinates":[-0.78347,54.241473],"type":"Point"}
}
