{
  "type": "Feature",
  "properties": {
    "iso:country":"GB",
    "wof:name":"ME2 2PX",
    "wof:placetype":"postalcode"
},
  "geometry": {"coordinates":[0.46778824517128,51.38650474552813],"type":"Point"}
}