{
  "type": "Feature",
  "properties": {
    "iso:country":"GB",
    "wof:name":"SG1 5BG",
    "wof:placetype":"postalcode"
},
  "geometry": {"coordinates":[-0.1899858802356,51.91579278003464],"type":"Point"}
}