{
  "type": "Feature",
  "properties": {
    "date:inception_lower": "1998-12-01",
    "date:inception_upper": "1998-12-01",
    "iso:country": "GB",
    "wof:name": "WR5 1SG",
    "wof:placetype": "postalcode"
  },
  "geometry": {"coordinates":[-2.20477,52.189288],"type":"Point"}
}
