{
  "type": "Feature",
  "properties": {
    "iso:country":"GB",
    "wof:name":"WR5 1SG",
    "wof:placetype":"postalcode"
},
  "geometry": {"coordinates":[-2.20486776714774,52.19050694804177],"type":"Point"}
}