{
  "type": "Feature",
  "properties": {
    "iso:country":"GB",
    "wof:name":"KY16 8ED",
    "wof:placetype":"postalcode"
},
  "geometry": {"coordinates":[-2.79932889420821,56.33232368801932],"type":"Point"}
}