{
  "type": "Feature",
  "properties": {
    "iso:country":"GB",
    "wof:name":"SS9 5BW",
    "wof:placetype":"postalcode"
},
  "geometry": {"coordinates":[0.63847332527788,51.57531970480486],"type":"Point"}
}