{
  "type": "Feature",
  "properties": {
    "iso:country": "GB",
    "wof:name": "SS9 5BW",
    "wof:placetype": "postalcode"
  },
  "geometry": {"coordinates":[0.638473,51.57532],"type":"Point"}
}
