{
  "type": "Feature",
  "properties": {
    "iso:country": "GB",
    "wof:name": "LD7 1EU",
    "wof:placetype": "postalcode"
  },
  "geometry": {"coordinates":[-3.051996,52.34484],"type":"Point"}
}
