{
  "type": "Feature",
  "properties": {
    "iso:country":"GB",
    "wof:name":"LD7 1EU",
    "wof:placetype":"postalcode"
},
  "geometry": {"coordinates":[-3.05199633644311,52.34484023398592],"type":"Point"}
}