{
  "type": "Feature",
  "properties": {
    "date:inception_lower":"2016-02-01",
    "date:inception_upper":"2016-02-29",
    "iso:country":"GB",
    "wof:name":"LS17 1HQ",
    "wof:placetype":"postalcode"
},
  "geometry": {"coordinates":[-1.533689,53.85133],"type":"Point"}
}