{
  "type": "Feature",
  "properties": {
    "iso:country":"GB",
    "wof:name":"TA24 8RP",
    "wof:placetype":"postalcode"
},
  "geometry": {"coordinates":[-3.52638834772589,51.18218336718],"type":"Point"}
}