{
  "type": "Feature",
  "properties": {
    "iso:country":"GB",
    "wof:name":"BS48 1JW",
    "wof:placetype":"postalcode"
},
  "geometry": {"coordinates":[-2.75253612723699,51.43628080828822],"type":"Point"}
}