{
  "type": "Feature",
  "properties": {
    "iso:country":"GB",
    "wof:name":"TW7 4AR",
    "wof:placetype":"postalcode"
},
  "geometry": {"coordinates":[-0.34679528083253,51.47248201656967],"type":"Point"}
}