{
  "type": "Feature",
  "properties": {
    "iso:country": "GB",
    "wof:name": "TW7 4AR",
    "wof:placetype": "postalcode"
  },
  "geometry": {"coordinates":[-0.346795,51.472482],"type":"Point"}
}
