{
  "type": "Feature",
  "properties": {
    "date:inception_lower": "1980-01-01",
    "date:inception_upper": "1980-01-01",
    "iso:country": "GB",
    "wof:name": "CV8 1GT",
    "wof:placetype": "postalcode"
  },
  "geometry": {"coordinates":[-1.579039,52.342286],"type":"Point"}
}
