{
  "type": "Feature",
  "properties": {
    "iso:country":"GB",
    "wof:name":"LN7 6AD",
    "wof:placetype":"postalcode"
},
  "geometry": {"coordinates":[-0.33765784680973,53.48517149913303],"type":"Point"}
}