{
  "type": "Feature",
  "properties": {
    "iso:country": "GB",
    "wof:name": "LN7 6AD",
    "wof:placetype": "postalcode"
  },
  "geometry": {"coordinates":[-0.337658,53.485171],"type":"Point"}
}
