{
  "type": "Feature",
  "properties": {
    "iso:country":"GB",
    "wof:name":"HG1 5QR",
    "wof:placetype":"postalcode"
},
  "geometry": {"coordinates":[-1.5311250718452,53.99048078966261],"type":"Point"}
}