{
  "type": "Feature",
  "properties": {
    "date:inception_lower": "1980-01-01",
    "date:inception_upper": "1980-01-01",
    "iso:country": "GB",
    "wof:name": "HG1 5QR",
    "wof:placetype": "postalcode"
  },
  "geometry": {"coordinates":[-1.531125,53.990481],"type":"Point"}
}
