{
  "type": "Feature",
  "properties": {
    "iso:country":"GB",
    "wof:name":"AL2 3SG",
    "wof:placetype":"postalcode"
},
  "geometry": {"coordinates":[-0.37239689606239,51.71078134558096],"type":"Point"}
}