{
  "type": "Feature",
  "properties": {
    "date:inception_lower": "1980-01-01",
    "date:inception_upper": "1980-01-01",
    "iso:country": "GB",
    "wof:name": "NG9 8LE",
    "wof:placetype": "postalcode"
  },
  "geometry": {"coordinates":[-1.26785,52.940233],"type":"Point"}
}
