{
  "type": "Feature",
  "properties": {
    "iso:country":"GB",
    "wof:name":"NG9 8LE",
    "wof:placetype":"postalcode"
},
  "geometry": {"coordinates":[-1.26784979071655,52.94023282408981],"type":"Point"}
}