{
  "type": "Feature",
  "properties": {
    "date:inception_lower": "2019-10-01",
    "date:inception_upper": "2019-10-01",
    "iso:country": "GB",
    "wof:name": "SW4 9BH",
    "wof:placetype": "postalcode"
  },
  "geometry": {"coordinates":[-0.135093,51.458273],"type":"Point"}
}
