{
  "type": "Feature",
  "properties": {
    "iso:country": "GB",
    "wof:name": "SW4 9BH",
    "wof:placetype": "postalcode"
  },
  "geometry": {"coordinates":[-0.135093,51.458273],"type":"Point"}
}
