{
  "type": "Feature",
  "properties": {
    "iso:country": "GB",
    "wof:name": "BB8 7PJ",
    "wof:placetype": "postalcode"
  },
  "geometry": {"coordinates":[-2.169769,53.87633],"type":"Point"}
}
