{
  "type": "Feature",
  "properties": {
    "iso:country":"GB",
    "wof:name":"HP3 0RU",
    "wof:placetype":"postalcode"
},
  "geometry": {"coordinates":[-0.53999080056929,51.72301820361991],"type":"Point"}
}