{
  "type": "Feature",
  "properties": {
    "date:inception_lower": "1990-02-01",
    "date:inception_upper": "1990-02-01",
    "iso:country": "GB",
    "wof:name": "HP3 0RU",
    "wof:placetype": "postalcode"
  },
  "geometry": {"coordinates":[-0.539991,51.723018],"type":"Point"}
}
