{
  "type": "Feature",
  "properties": {
    "iso:country": "GB",
    "wof:name": "HP3 0RU",
    "wof:placetype": "postalcode"
  },
  "geometry": {"coordinates":[-0.539991,51.723018],"type":"Point"}
}
