{
  "type": "Feature",
  "properties": {
    "date:inception_lower": "2021-06-01",
    "date:inception_upper": "2021-06-01",
    "iso:country": "GB",
    "wof:name": "LS16 9FP",
    "wof:placetype": "postalcode"
  },
  "geometry": {"coordinates":[-1.60457,53.882295],"type":"Point"}
}
