{
  "type": "Feature",
  "properties": {
    "iso:country":"GB",
    "wof:name":"SW6 1QA",
    "wof:placetype":"postalcode"
},
  "geometry": {"coordinates":[-0.19498672536148,51.48270696413705],"type":"Point"}
}