{
  "type": "Feature",
  "properties": {
    "iso:country":"GB",
    "wof:name":"M25 1JD",
    "wof:placetype":"postalcode"
},
  "geometry": {"coordinates":[-2.26724298497027,53.53103478533698],"type":"Point"}
}