{
  "type": "Feature",
  "properties": {
    "date:inception_lower": "2018-01-01",
    "date:inception_upper": "2018-01-01",
    "iso:country": "GB",
    "wof:name": "NW6 4BY",
    "wof:placetype": "postalcode"
  },
  "geometry": {"coordinates":[-0.188287,51.539178],"type":"Point"}
}
