{
  "type": "Feature",
  "properties": {
    "iso:country": "GB",
    "wof:name": "BD22 7HJ",
    "wof:placetype": "postalcode"
  },
  "geometry": {"coordinates":[-1.946172,53.846778],"type":"Point"}
}
