{
  "type": "Feature",
  "properties": {
    "iso:country":"GB",
    "wof:name":"BD22 7HJ",
    "wof:placetype":"postalcode"
},
  "geometry": {"coordinates":[-1.94617253918387,53.84677806676796],"type":"Point"}
}