{
  "type": "Feature",
  "properties": {
    "iso:country": "GB",
    "wof:name": "TQ4 5BH",
    "wof:placetype": "postalcode"
  },
  "geometry": {"coordinates":[-3.56784,50.434497],"type":"Point"}
}
