{
  "type": "Feature",
  "properties": {
    "iso:country": "GB",
    "wof:name": "SR2 8AF",
    "wof:placetype": "postalcode"
  },
  "geometry": {"coordinates":[-1.376149,54.89898],"type":"Point"}
}
