{
  "type": "Feature",
  "properties": {
    "date:inception_lower": "1981-06-01",
    "date:inception_upper": "1981-06-01",
    "iso:country": "GB",
    "wof:name": "SR2 8AF",
    "wof:placetype": "postalcode"
  },
  "geometry": {"coordinates":[-1.376149,54.89898],"type":"Point"}
}
