{
  "type": "Feature",
  "properties": {
    "iso:country":"GB",
    "wof:name":"SR2 8AF",
    "wof:placetype":"postalcode"
},
  "geometry": {"coordinates":[-1.37614862505533,54.898980236154],"type":"Point"}
}