{
  "type": "Feature",
  "properties": {
    "iso:country":"GB",
    "wof:name":"KY2 6SE",
    "wof:placetype":"postalcode"
},
  "geometry": {"coordinates":[-3.17667391613826,56.13144503937653],"type":"Point"}
}