{
  "type": "Feature",
  "properties": {
    "iso:country": "GB",
    "wof:name": "LS29 7LP",
    "wof:placetype": "postalcode"
  },
  "geometry": {"coordinates":[-1.75965,53.912278],"type":"Point"}
}
