{
  "type": "Feature",
  "properties": {
    "iso:country":"GB",
    "wof:name":"LS29 7LP",
    "wof:placetype":"postalcode"
},
  "geometry": {"coordinates":[-1.75965005466051,53.91227803915715],"type":"Point"}
}