{
  "type": "Feature",
  "properties": {
    "iso:country":"GB",
    "wof:name":"DL1 3TE",
    "wof:placetype":"postalcode"
},
  "geometry": {"coordinates":[-1.53827502921782,54.55022181810228],"type":"Point"}
}