{
  "type": "Feature",
  "properties": {
    "iso:country":"GB",
    "wof:name":"TW19 7LX",
    "wof:placetype":"postalcode"
},
  "geometry": {"coordinates":[-0.46943940656978,51.45754727593589],"type":"Point"}
}