{
  "type": "Feature",
  "properties": {
    "date:inception_lower": "1992-08-01",
    "date:inception_upper": "1992-08-01",
    "iso:country": "GB",
    "wof:name": "TW19 7LX",
    "wof:placetype": "postalcode"
  },
  "geometry": {"coordinates":[-0.469439,51.457547],"type":"Point"}
}
