{
  "type": "Feature",
  "properties": {
    "iso:country": "GB",
    "wof:name": "GU24 9JG",
    "wof:placetype": "postalcode"
  },
  "geometry": {"coordinates":[-0.635102,51.340986],"type":"Point"}
}
