{
  "type": "Feature",
  "properties": {
    "iso:country":"GB",
    "wof:name":"NN5 7NU",
    "wof:placetype":"postalcode"
},
  "geometry": {"coordinates":[-0.91931373120238,52.25827600153209],"type":"Point"}
}