{
  "type": "Feature",
  "properties": {
    "date:inception_lower":"1980-01-01",
    "date:inception_upper":"1980-01-31",
    "iso:country":"GB",
    "wof:name":"PE13 5PG",
    "wof:placetype":"postalcode"
},
  "geometry": {"coordinates":[0.129296,52.729158],"type":"Point"}
}