{
  "type": "Feature",
  "properties": {
    "iso:country":"GB",
    "wof:name":"PE13 5PG",
    "wof:placetype":"postalcode"
},
  "geometry": {"coordinates":[0.12929552113545,52.72915828592686],"type":"Point"}
}