{
  "type": "Feature",
  "properties": {
    "iso:country": "GB",
    "wof:name": "PE13 5PG",
    "wof:placetype": "postalcode"
  },
  "geometry": {"coordinates":[0.129296,52.729158],"type":"Point"}
}
