{
  "type": "Feature",
  "properties": {
    "date:inception_lower":"1980-01-01",
    "date:inception_upper":"1980-01-31",
    "iso:country":"GB",
    "wof:name":"B72 1BX",
    "wof:placetype":"postalcode"
},
  "geometry": {"coordinates":[-1.824907,52.549181],"type":"Point"}
}