{
  "type": "Feature",
  "properties": {
    "iso:country":"GB",
    "wof:name":"FY7 7BX",
    "wof:placetype":"postalcode"
},
  "geometry": {"coordinates":[-3.02741273583052,53.92109947301962],"type":"Point"}
}