{
  "type": "Feature",
  "properties": {
    "iso:country":"GB",
    "wof:name":"TR2 5SY",
    "wof:placetype":"postalcode"
},
  "geometry": {"coordinates":[-4.9019193727606,50.25356852135281],"type":"Point"}
}