{
  "type": "Feature",
  "properties": {
    "iso:country":"GB",
    "wof:name":"LA3 2UZ",
    "wof:placetype":"postalcode"
},
  "geometry": {"coordinates":[-2.90240983869225,54.03729464810115],"type":"Point"}
}