{
  "type": "Feature",
  "properties": {
    "iso:country":"GB",
    "wof:name":"S26 2AN",
    "wof:placetype":"postalcode"
},
  "geometry": {"coordinates":[-1.30664918435138,53.36694499652653],"type":"Point"}
}