{
  "type": "Feature",
  "properties": {
    "date:inception_lower": "1997-06-01",
    "date:inception_upper": "1997-06-01",
    "iso:country": "GB",
    "wof:name": "S26 2AN",
    "wof:placetype": "postalcode"
  },
  "geometry": {"coordinates":[-1.306649,53.366945],"type":"Point"}
}
