{
  "type": "Feature",
  "properties": {
    "iso:country":"GB",
    "wof:name":"EX7 0LZ",
    "wof:placetype":"postalcode"
},
  "geometry": {"coordinates":[-3.45635742680327,50.59622923711161],"type":"Point"}
}