{
  "type": "Feature",
  "properties": {
    "date:inception_lower": "1980-01-01",
    "date:inception_upper": "1980-01-01",
    "iso:country": "GB",
    "wof:name": "EX7 0LZ",
    "wof:placetype": "postalcode"
  },
  "geometry": {"coordinates":[-3.456357,50.596229],"type":"Point"}
}
