{
  "type": "Feature",
  "properties": {
    "iso:country": "GB",
    "wof:name": "NG8 6GG",
    "wof:placetype": "postalcode"
  },
  "geometry": {"coordinates":[-1.22098,52.974032],"type":"Point"}
}
