{
  "type": "Feature",
  "properties": {
    "iso:country":"GB",
    "wof:name":"PR7 1LL",
    "wof:placetype":"postalcode"
},
  "geometry": {"coordinates":[-2.64646893182426,53.65582765925144],"type":"Point"}
}