{
  "type": "Feature",
  "properties": {
    "iso:country":"GB",
    "wof:name":"N3 3PT",
    "wof:placetype":"postalcode"
},
  "geometry": {"coordinates":[-0.20924912407832,51.59355007368527],"type":"Point"}
}