{
  "type": "Feature",
  "properties": {
    "date:inception_lower": "2012-04-01",
    "date:inception_upper": "2012-04-01",
    "iso:country": "GB",
    "wof:name": "RH19 4QW",
    "wof:placetype": "postalcode"
  },
  "geometry": {"coordinates":[-0.01236,51.115203],"type":"Point"}
}
