{
  "type": "Feature",
  "properties": {
    "iso:country": "GB",
    "wof:name": "RH19 4QW",
    "wof:placetype": "postalcode"
  },
  "geometry": {"coordinates":[-0.012167,51.115005],"type":"Point"}
}
