{
  "type": "Feature",
  "properties": {
    "date:inception_lower": "2018-07-01",
    "date:inception_upper": "2018-07-01",
    "iso:country": "GB",
    "wof:name": "ML11 7FA",
    "wof:placetype": "postalcode"
  },
  "geometry": {"coordinates":[-3.780297,55.675795],"type":"Point"}
}
