{
  "type": "Feature",
  "properties": {
    "date:inception_lower": "1980-01-01",
    "date:inception_upper": "1980-01-01",
    "iso:country": "GB",
    "wof:name": "OL3 5RS",
    "wof:placetype": "postalcode"
  },
  "geometry": {"coordinates":[-2.002604,53.564905],"type":"Point"}
}
