{
  "type": "Feature",
  "properties": {
    "iso:country":"GB",
    "wof:name":"G82 1BU",
    "wof:placetype":"postalcode"
},
  "geometry": {"coordinates":[-4.55160601846537,55.94248662367833],"type":"Point"}
}