{
  "type": "Feature",
  "properties": {
    "date:inception_lower": "2021-11-01",
    "date:inception_upper": "2021-11-01",
    "iso:country": "GB",
    "wof:name": "MK18 1ZP",
    "wof:placetype": "postalcode"
  },
  "geometry": {"coordinates":[-0.999598,51.994034],"type":"Point"}
}
