{
  "type": "Feature",
  "properties": {
    "iso:country": "GB",
    "wof:name": "TW10 6JY",
    "wof:placetype": "postalcode"
  },
  "geometry": {"coordinates":[-0.290652,51.455365],"type":"Point"}
}
