{
  "type": "Feature",
  "properties": {
    "iso:country":"GB",
    "wof:name":"WA10 6NQ",
    "wof:placetype":"postalcode"
},
  "geometry": {"coordinates":[-2.74688878195815,53.46708611667709],"type":"Point"}
}