{
  "type": "Feature",
  "properties": {
    "iso:country":"GB",
    "wof:name":"CW9 7EZ",
    "wof:placetype":"postalcode"
},
  "geometry": {"coordinates":[-2.48732837558972,53.25668913565455],"type":"Point"}
}