{
  "type": "Feature",
  "properties": {
    "iso:country": "GB",
    "wof:name": "CW9 7EZ",
    "wof:placetype": "postalcode"
  },
  "geometry": {"coordinates":[-2.487328,53.256689],"type":"Point"}
}
