{
  "type": "Feature",
  "properties": {
    "iso:country":"GB",
    "wof:name":"AL9 7QT",
    "wof:placetype":"postalcode"
},
  "geometry": {"coordinates":[-0.20270422931033,51.72157140876781],"type":"Point"}
}