{
  "type": "Feature",
  "properties": {
    "iso:country":"GB",
    "wof:name":"YO16 7BP",
    "wof:placetype":"postalcode"
},
  "geometry": {"coordinates":[-0.19745283529659,54.09362096696547],"type":"Point"}
}