{
  "type": "Feature",
  "properties": {
    "iso:country":"GB",
    "wof:name":"BR1 2TB",
    "wof:placetype":"postalcode"
},
  "geometry": {"coordinates":[0.03756304480667,51.4039773106689],"type":"Point"}
}