{
  "type": "Feature",
  "properties": {
    "iso:country":"GB",
    "wof:name":"KY10 2RJ",
    "wof:placetype":"postalcode"
},
  "geometry": {"coordinates":[-2.78682617960644,56.23635851003932],"type":"Point"}
}