{
  "type": "Feature",
  "properties": {
    "iso:country": "GB",
    "wof:name": "KY10 2RJ",
    "wof:placetype": "postalcode"
  },
  "geometry": {"coordinates":[-2.786826,56.236359],"type":"Point"}
}
