{
  "type": "Feature",
  "properties": {
    "iso:country": "GB",
    "wof:name": "PL17 8LT",
    "wof:placetype": "postalcode"
  },
  "geometry": {"coordinates":[-4.294508,50.559586],"type":"Point"}
}
