{
  "type": "Feature",
  "properties": {
    "iso:country":"GB",
    "wof:name":"PL17 8LT",
    "wof:placetype":"postalcode"
},
  "geometry": {"coordinates":[-4.29437210416093,50.55948114428075],"type":"Point"}
}