{
  "type": "Feature",
  "properties": {
    "iso:country":"GB",
    "wof:name":"BS4 5BJ",
    "wof:placetype":"postalcode"
},
  "geometry": {"coordinates":[-2.55755488920713,51.43126536310954],"type":"Point"}
}