{
  "type": "Feature",
  "properties": {
    "date:inception_lower":"2008-07-01",
    "date:inception_upper":"2008-07-31",
    "iso:country":"GB",
    "wof:name":"LS21 2FN",
    "wof:placetype":"postalcode"
},
  "geometry": {"coordinates":[-1.702442,53.914334],"type":"Point"}
}