{
  "type": "Feature",
  "properties": {
    "iso:country": "GB",
    "wof:name": "LS21 2FN",
    "wof:placetype": "postalcode"
  },
  "geometry": {"coordinates":[-1.702442,53.914334],"type":"Point"}
}
