{
  "type": "Feature",
  "properties": {
    "iso:country":"GB",
    "wof:name":"LS21 2FN",
    "wof:placetype":"postalcode"
},
  "geometry": {"coordinates":[-1.70244170862096,53.91433407799021],"type":"Point"}
}