{
  "type": "Feature",
  "properties": {
    "iso:country":"GB",
    "wof:name":"DL2 3JQ",
    "wof:placetype":"postalcode"
},
  "geometry": {"coordinates":[-1.73128880367652,54.57888787655255],"type":"Point"}
}