{
  "type": "Feature",
  "properties": {
    "date:inception_lower": "1983-03-01",
    "date:inception_upper": "1983-03-01",
    "iso:country": "GB",
    "wof:name": "DL2 3JQ",
    "wof:placetype": "postalcode"
  },
  "geometry": {"coordinates":[-1.731289,54.578888],"type":"Point"}
}
