{
  "type": "Feature",
  "properties": {
    "date:inception_lower":"1980-01-01",
    "date:inception_upper":"1980-01-31",
    "iso:country":"GB",
    "wof:name":"BD23 5JT",
    "wof:placetype":"postalcode"
},
  "geometry": {"coordinates":[-2.271317,54.234841],"type":"Point"}
}