{
  "type": "Feature",
  "properties": {
    "iso:country": "GB",
    "wof:name": "BD23 5JT",
    "wof:placetype": "postalcode"
  },
  "geometry": {"coordinates":[-2.271317,54.234841],"type":"Point"}
}
