{
  "type": "Feature",
  "properties": {
    "iso:country":"GB",
    "wof:name":"BD23 5JT",
    "wof:placetype":"postalcode"
},
  "geometry": {"coordinates":[-2.27172696166875,54.23469307736561],"type":"Point"}
}