{
  "type": "Feature",
  "properties": {
    "iso:country":"GB",
    "wof:name":"OL15 9JL",
    "wof:placetype":"postalcode"
},
  "geometry": {"coordinates":[-2.10073416583127,53.65021516970859],"type":"Point"}
}