{
  "type": "Feature",
  "properties": {
    "date:inception_lower": "1980-01-01",
    "date:inception_upper": "1980-01-01",
    "iso:country": "GB",
    "wof:name": "OL15 9JL",
    "wof:placetype": "postalcode"
  },
  "geometry": {"coordinates":[-2.10093,53.650231],"type":"Point"}
}
