{
  "type": "Feature",
  "properties": {
    "iso:country":"GB",
    "wof:name":"EX32 0JB",
    "wof:placetype":"postalcode"
},
  "geometry": {"coordinates":[-4.0117631779185,51.06200289502197],"type":"Point"}
}