{
  "type": "Feature",
  "properties": {
    "date:inception_lower": "1983-07-01",
    "date:inception_upper": "1983-07-01",
    "iso:country": "GB",
    "wof:name": "BN17 5NY",
    "wof:placetype": "postalcode"
  },
  "geometry": {"coordinates":[-0.537732,50.80834],"type":"Point"}
}
