{
  "type": "Feature",
  "properties": {
    "date:inception_lower": "1980-01-01",
    "date:inception_upper": "1980-01-01",
    "iso:country": "GB",
    "wof:name": "ME3 7PT",
    "wof:placetype": "postalcode"
  },
  "geometry": {"coordinates":[0.497037,51.456915],"type":"Point"}
}
