{
  "type": "Feature",
  "properties": {
    "date:inception_lower": "2023-10-01",
    "date:inception_upper": "2023-10-01",
    "iso:country": "GB",
    "wof:name": "IP8 3RU",
    "wof:placetype": "postalcode"
  },
  "geometry": {"coordinates":[1.033602,52.045427],"type":"Point"}
}
