{
  "type": "Feature",
  "properties": {
    "iso:country":"GB",
    "wof:name":"EH21 8AT",
    "wof:placetype":"postalcode"
},
  "geometry": {"coordinates":[-3.01195461764146,55.93407187981585],"type":"Point"}
}