{
  "type": "Feature",
  "properties": {
    "date:inception_lower": "2016-10-01",
    "date:inception_upper": "2016-10-01",
    "iso:country": "GB",
    "wof:name": "CM6 3UA",
    "wof:placetype": "postalcode"
  },
  "geometry": {"coordinates":[0.370649,51.877452],"type":"Point"}
}
