{
  "type": "Feature",
  "properties": {
    "date:inception_lower": "1980-01-01",
    "date:inception_upper": "1980-01-01",
    "iso:country": "GB",
    "wof:name": "N7 0PG",
    "wof:placetype": "postalcode"
  },
  "geometry": {"coordinates":[-0.121922,51.558077],"type":"Point"}
}
