{
  "type": "Feature",
  "properties": {
    "iso:country":"GB",
    "wof:name":"RG2 8QJ",
    "wof:placetype":"postalcode"
},
  "geometry": {"coordinates":[-0.95793204085369,51.4138009434408],"type":"Point"}
}