{
  "type": "Feature",
  "properties": {
    "iso:country":"GB",
    "wof:name":"BL4 7RY",
    "wof:placetype":"postalcode"
},
  "geometry": {"coordinates":[-2.38912410119312,53.55237106283346],"type":"Point"}
}