{
  "type": "Feature",
  "properties": {
    "date:inception_lower": "1980-01-01",
    "date:inception_upper": "1980-01-01",
    "iso:country": "GB",
    "wof:name": "BL4 7RY",
    "wof:placetype": "postalcode"
  },
  "geometry": {"coordinates":[-2.389124,53.552371],"type":"Point"}
}
