{
  "type": "Feature",
  "properties": {
    "iso:country":"GB",
    "wof:name":"DD8 2PY",
    "wof:placetype":"postalcode"
},
  "geometry": {"coordinates":[-2.76147468142482,56.62770490446957],"type":"Point"}
}