{
  "type": "Feature",
  "properties": {
    "iso:country": "GB",
    "wof:name": "DD8 2PY",
    "wof:placetype": "postalcode"
  },
  "geometry": {"coordinates":[-2.761475,56.627705],"type":"Point"}
}
