{
  "type": "Feature",
  "properties": {
    "date:inception_lower": "1996-06-01",
    "date:inception_upper": "1996-06-01",
    "iso:country": "GB",
    "wof:name": "AB30 1FG",
    "wof:placetype": "postalcode"
  },
  "geometry": {"coordinates":[-2.466331,56.832059],"type":"Point"}
}
