{
  "type": "Feature",
  "properties": {
    "iso:country":"GB",
    "wof:name":"AB30 1FG",
    "wof:placetype":"postalcode"
},
  "geometry": {"coordinates":[-2.4663311449038,56.83205877643415],"type":"Point"}
}