{
  "type": "Feature",
  "properties": {
    "iso:country": "GB",
    "wof:name": "IP21 4FF",
    "wof:placetype": "postalcode"
  },
  "geometry": {"coordinates":[1.21997,52.397452],"type":"Point"}
}
