{
  "type": "Feature",
  "properties": {
    "iso:country":"GB",
    "wof:name":"BA3 3SZ",
    "wof:placetype":"postalcode"
},
  "geometry": {"coordinates":[-2.46500810984404,51.2856522154503],"type":"Point"}
}