{
  "type": "Feature",
  "properties": {
    "date:inception_lower":"1981-06-01",
    "date:inception_upper":"1981-06-30",
    "iso:country":"GB",
    "wof:name":"BH20 7HB",
    "wof:placetype":"postalcode"
},
  "geometry": {"coordinates":[-2.219824,50.752538],"type":"Point"}
}