{
  "type": "Feature",
  "properties": {
    "iso:country":"GB",
    "wof:name":"BH20 7HB",
    "wof:placetype":"postalcode"
},
  "geometry": {"coordinates":[-2.21982423786575,50.75253756190713],"type":"Point"}
}