{
  "type": "Feature",
  "properties": {
    "iso:country": "GB",
    "wof:name": "AL4 0EW",
    "wof:placetype": "postalcode"
  },
  "geometry": {"coordinates":[-0.306294,51.758764],"type":"Point"}
}
