{
  "type": "Feature",
  "properties": {
    "iso:country":"GB",
    "wof:name":"S20 5AH",
    "wof:placetype":"postalcode"
},
  "geometry": {"coordinates":[-1.36268860906479,53.32572898288064],"type":"Point"}
}