{
  "type": "Feature",
  "properties": {
    "date:inception_lower":"1980-01-01",
    "date:inception_upper":"1980-01-31",
    "iso:country":"GB",
    "wof:name":"DN20 8BA",
    "wof:placetype":"postalcode"
},
  "geometry": {"coordinates":[-0.490935,53.559039],"type":"Point"}
}