{
  "type": "Feature",
  "properties": {
    "iso:country":"GB",
    "wof:name":"IP33 2AD",
    "wof:placetype":"postalcode"
},
  "geometry": {"coordinates":[0.71801767590763,52.23998411600127],"type":"Point"}
}