{
  "type": "Feature",
  "properties": {
    "iso:country":"GB",
    "wof:name":"PO20 1NT",
    "wof:placetype":"postalcode"
},
  "geometry": {"coordinates":[-0.77540048957805,50.81200298971587],"type":"Point"}
}