{
  "type": "Feature",
  "properties": {
    "date:inception_lower": "2002-06-01",
    "date:inception_upper": "2002-06-01",
    "iso:country": "GB",
    "wof:name": "PO20 1NT",
    "wof:placetype": "postalcode"
  },
  "geometry": {"coordinates":[-0.775381,50.811993],"type":"Point"}
}
