{
  "type": "Feature",
  "properties": {
    "iso:country":"GB",
    "wof:name":"EC1R 1YB",
    "wof:placetype":"postalcode"
},
  "geometry": {"coordinates":[-0.10766599678333,51.53068142950885],"type":"Point"}
}