{
  "type": "Feature",
  "properties": {
    "iso:country": "GB",
    "wof:name": "EC1R 1YB",
    "wof:placetype": "postalcode"
  },
  "geometry": {"coordinates":[-0.107666,51.530681],"type":"Point"}
}
