{
  "type": "Feature",
  "properties": {
    "iso:country": "GB",
    "wof:name": "SE25 5FB",
    "wof:placetype": "postalcode"
  },
  "geometry": {"coordinates":[-0.076091,51.396582],"type":"Point"}
}
