{
  "type": "Feature",
  "properties": {
    "date:inception_lower": "1980-01-01",
    "date:inception_upper": "1980-01-01",
    "iso:country": "GB",
    "wof:name": "NE48 2JA",
    "wof:placetype": "postalcode"
  },
  "geometry": {"coordinates":[-2.247997,55.181749],"type":"Point"}
}
