{
  "type": "Feature",
  "properties": {
    "iso:country":"GB",
    "wof:name":"NE48 2JA",
    "wof:placetype":"postalcode"
},
  "geometry": {"coordinates":[-2.24798868303691,55.18174507774263],"type":"Point"}
}