{
  "type": "Feature",
  "properties": {
    "iso:country": "GB",
    "wof:name": "SK14 2HW",
    "wof:placetype": "postalcode"
  },
  "geometry": {"coordinates":[-2.076622,53.452049],"type":"Point"}
}
