{
  "type": "Feature",
  "properties": {
    "iso:country":"GB",
    "wof:name":"SK14 2HW",
    "wof:placetype":"postalcode"
},
  "geometry": {"coordinates":[-2.07662216022278,53.45204938300325],"type":"Point"}
}