{
  "type": "Feature",
  "properties": {
    "date:inception_lower": "1994-05-01",
    "date:inception_upper": "1994-05-01",
    "iso:country": "GB",
    "wof:name": "SK14 2HW",
    "wof:placetype": "postalcode"
  },
  "geometry": {"coordinates":[-2.076877,53.451966],"type":"Point"}
}
