{
  "type": "Feature",
  "properties": {
    "iso:country":"GB",
    "wof:name":"DY5 1SE",
    "wof:placetype":"postalcode"
},
  "geometry": {"coordinates":[-2.10857324428694,52.47295395694677],"type":"Point"}
}