{
  "type": "Feature",
  "properties": {
    "date:inception_lower": "2017-04-01",
    "date:inception_upper": "2017-04-01",
    "iso:country": "GB",
    "wof:name": "KT15 2GB",
    "wof:placetype": "postalcode"
  },
  "geometry": {"coordinates":[-0.489808,51.370091],"type":"Point"}
}
