{
  "type": "Feature",
  "properties": {
    "iso:country": "GB",
    "wof:name": "S71 4BJ",
    "wof:placetype": "postalcode"
  },
  "geometry": {"coordinates":[-1.440213,53.598885],"type":"Point"}
}
