{
  "type": "Feature",
  "properties": {
    "iso:country":"GB",
    "wof:name":"S71 4BJ",
    "wof:placetype":"postalcode"
},
  "geometry": {"coordinates":[-1.44021342707843,53.59888536110235],"type":"Point"}
}