{
  "type": "Feature",
  "properties": {
    "iso:country":"GB",
    "wof:name":"PA2 7RX",
    "wof:placetype":"postalcode"
},
  "geometry": {"coordinates":[-4.42130616191146,55.83031620136389],"type":"Point"}
}