{
  "type": "Feature",
  "properties": {
    "date:inception_lower": "2014-02-01",
    "date:inception_upper": "2014-02-01",
    "iso:country": "GB",
    "wof:name": "PA2 7RX",
    "wof:placetype": "postalcode"
  },
  "geometry": {"coordinates":[-4.421306,55.830316],"type":"Point"}
}
