{
  "type": "Feature",
  "properties": {
    "iso:country": "GB",
    "wof:name": "PA2 7RX",
    "wof:placetype": "postalcode"
  },
  "geometry": {"coordinates":[-4.421306,55.830316],"type":"Point"}
}
