{
  "type": "Feature",
  "properties": {
    "date:inception_lower": "2000-12-01",
    "date:inception_upper": "2000-12-01",
    "iso:country": "GB",
    "wof:name": "WD23 1QS",
    "wof:placetype": "postalcode"
  },
  "geometry": {"coordinates":[-0.363927,51.644222],"type":"Point"}
}
