{
  "type": "Feature",
  "properties": {
    "iso:country":"GB",
    "wof:name":"WD23 1QS",
    "wof:placetype":"postalcode"
},
  "geometry": {"coordinates":[-0.36392707626671,51.64422157501092],"type":"Point"}
}