{
  "type": "Feature",
  "properties": {
    "iso:country": "GB",
    "wof:name": "NR19 2AP",
    "wof:placetype": "postalcode"
  },
  "geometry": {"coordinates":[0.940864,52.681968],"type":"Point"}
}
