{
  "type": "Feature",
  "properties": {
    "iso:country": "GB",
    "wof:name": "NR20 5TJ",
    "wof:placetype": "postalcode"
  },
  "geometry": {"coordinates":[1.009087,52.780878],"type":"Point"}
}
