{
  "type": "Feature",
  "properties": {
    "iso:country":"GB",
    "wof:name":"NR20 5TJ",
    "wof:placetype":"postalcode"
},
  "geometry": {"coordinates":[1.00908691843672,52.78087846702402],"type":"Point"}
}