{
  "type": "Feature",
  "properties": {
    "date:inception_lower":"2012-02-01",
    "date:inception_upper":"2012-02-29",
    "iso:country":"GB",
    "wof:name":"E3 4GF",
    "wof:placetype":"postalcode"
},
  "geometry": {"coordinates":[-0.033669,51.524446],"type":"Point"}
}