{
  "type": "Feature",
  "properties": {
    "date:inception_lower": "1991-01-01",
    "date:inception_upper": "1991-01-01",
    "iso:country": "GB",
    "wof:name": "SO43 7JP",
    "wof:placetype": "postalcode"
  },
  "geometry": {"coordinates":[-1.57743,50.870845],"type":"Point"}
}
