{
  "type": "Feature",
  "properties": {
    "iso:country":"GB",
    "wof:name":"GU30 7LJ",
    "wof:placetype":"postalcode"
},
  "geometry": {"coordinates":[-0.78677536444137,51.07324396710617],"type":"Point"}
}