{
  "type": "Feature",
  "properties": {
    "iso:country": "GB",
    "wof:name": "GU30 7LJ",
    "wof:placetype": "postalcode"
  },
  "geometry": {"coordinates":[-0.786757,51.07323],"type":"Point"}
}
