{
  "type": "Feature",
  "properties": {
    "iso:country":"GB",
    "wof:name":"BR6 9EB",
    "wof:placetype":"postalcode"
},
  "geometry": {"coordinates":[0.10770952636358,51.36604513525475],"type":"Point"}
}