{
  "type": "Feature",
  "properties": {
    "iso:country":"GB",
    "wof:name":"L1 1HU",
    "wof:placetype":"postalcode"
},
  "geometry": {"coordinates":[-2.97963292477845,53.40584379584575],"type":"Point"}
}