{
  "type": "Feature",
  "properties": {
    "iso:country":"GB",
    "wof:name":"OX12 0NH",
    "wof:placetype":"postalcode"
},
  "geometry": {"coordinates":[-1.42858168356141,51.60751615690927],"type":"Point"}
}