{
  "type": "Feature",
  "properties": {
    "date:inception_lower": "1980-01-01",
    "date:inception_upper": "1980-01-01",
    "iso:country": "GB",
    "wof:name": "N9 9QH",
    "wof:placetype": "postalcode"
  },
  "geometry": {"coordinates":[-0.066614,51.624658],"type":"Point"}
}
