{
  "type": "Feature",
  "properties": {
    "iso:country":"GB",
    "wof:name":"N9 9QH",
    "wof:placetype":"postalcode"
},
  "geometry": {"coordinates":[-0.06661400416322,51.62465810651483],"type":"Point"}
}