{
  "type": "Feature",
  "properties": {
    "date:inception_lower": "1980-01-01",
    "date:inception_upper": "1980-01-01",
    "iso:country": "GB",
    "wof:name": "OX1 5NA",
    "wof:placetype": "postalcode"
  },
  "geometry": {"coordinates":[-1.254728,51.709039],"type":"Point"}
}
