{
  "type": "Feature",
  "properties": {
    "iso:country":"GB",
    "wof:name":"OX1 5NA",
    "wof:placetype":"postalcode"
},
  "geometry": {"coordinates":[-1.25488893830782,51.70916142292268],"type":"Point"}
}