{
  "type": "Feature",
  "properties": {
    "iso:country":"GB",
    "wof:name":"DD1 5EQ",
    "wof:placetype":"postalcode"
},
  "geometry": {"coordinates":[-2.97841671474798,56.45931187799745],"type":"Point"}
}