{
  "type": "Feature",
  "properties": {
    "date:inception_lower":"1980-01-01",
    "date:inception_upper":"1980-01-31",
    "iso:country":"GB",
    "wof:name":"DN9 2BP",
    "wof:placetype":"postalcode"
},
  "geometry": {"coordinates":[-0.919559,53.51939],"type":"Point"}
}