{
  "type": "Feature",
  "properties": {
    "iso:country": "GB",
    "wof:name": "DN9 2BP",
    "wof:placetype": "postalcode"
  },
  "geometry": {"coordinates":[-0.919559,53.51939],"type":"Point"}
}
