{
  "type": "Feature",
  "properties": {
    "iso:country":"GB",
    "wof:name":"HP3 0EF",
    "wof:placetype":"postalcode"
},
  "geometry": {"coordinates":[-0.53943971526716,51.72214814305623],"type":"Point"}
}