{
  "type": "Feature",
  "properties": {
    "date:inception_lower": "1980-01-01",
    "date:inception_upper": "1980-01-01",
    "iso:country": "GB",
    "wof:name": "HP3 0EF",
    "wof:placetype": "postalcode"
  },
  "geometry": {"coordinates":[-0.53944,51.722148],"type":"Point"}
}
