{
  "type": "Feature",
  "properties": {
    "iso:country": "GB",
    "wof:name": "HP3 0EF",
    "wof:placetype": "postalcode"
  },
  "geometry": {"coordinates":[-0.53944,51.722148],"type":"Point"}
}
