{
  "type": "Feature",
  "properties": {
    "date:inception_lower": "1980-01-01",
    "date:inception_upper": "1980-01-01",
    "iso:country": "GB",
    "wof:name": "CA12 4SB",
    "wof:placetype": "postalcode"
  },
  "geometry": {"coordinates":[-3.058729,54.621035],"type":"Point"}
}
