{
  "type": "Feature",
  "properties": {
    "iso:country":"GB",
    "wof:name":"CA12 4SB",
    "wof:placetype":"postalcode"
},
  "geometry": {"coordinates":[-3.05872895803743,54.62103454072219],"type":"Point"}
}