{
  "type": "Feature",
  "properties": {
    "date:inception_lower": "2016-10-01",
    "date:inception_upper": "2016-10-01",
    "iso:country": "GB",
    "wof:name": "HU7 3FJ",
    "wof:placetype": "postalcode"
  },
  "geometry": {"coordinates":[-0.355103,53.804741],"type":"Point"}
}
