{
  "type": "Feature",
  "properties": {
    "date:inception_lower":"1982-02-01",
    "date:inception_upper":"1982-02-28",
    "iso:country":"GB",
    "wof:name":"G12 0LR",
    "wof:placetype":"postalcode"
},
  "geometry": {"coordinates":[-4.30007,55.888654],"type":"Point"}
}