{
  "type": "Feature",
  "properties": {
    "iso:country": "GB",
    "wof:name": "G12 0LR",
    "wof:placetype": "postalcode"
  },
  "geometry": {"coordinates":[-4.30007,55.888654],"type":"Point"}
}
