{
  "type": "Feature",
  "properties": {
    "iso:country":"GB",
    "wof:name":"G12 0LR",
    "wof:placetype":"postalcode"
},
  "geometry": {"coordinates":[-4.30006974974384,55.88865436681823],"type":"Point"}
}