{
  "type": "Feature",
  "properties": {
    "date:inception_lower": "2023-04-01",
    "date:inception_upper": "2023-04-01",
    "iso:country": "GB",
    "wof:name": "CV13 0BN",
    "wof:placetype": "postalcode"
  },
  "geometry": {"coordinates":[-1.410958,52.634868],"type":"Point"}
}
