{
  "type": "Feature",
  "properties": {
    "iso:country":"GB",
    "wof:name":"BL2 3LX",
    "wof:placetype":"postalcode"
},
  "geometry": {"coordinates":[-2.38711466239267,53.60006977537772],"type":"Point"}
}