{
  "type": "Feature",
  "properties": {
    "iso:country":"GB",
    "wof:name":"CO5 0DE",
    "wof:placetype":"postalcode"
},
  "geometry": {"coordinates":[0.74845399776599,51.81545833761631],"type":"Point"}
}