{
  "type": "Feature",
  "properties": {
    "date:inception_lower": "1995-12-01",
    "date:inception_upper": "1995-12-01",
    "iso:country": "GB",
    "wof:name": "WD3 5GD",
    "wof:placetype": "postalcode"
  },
  "geometry": {"coordinates":[-0.501899,51.6551],"type":"Point"}
}
