{
  "type": "Feature",
  "properties": {
    "iso:country":"GB",
    "wof:name":"PE11 2NP",
    "wof:placetype":"postalcode"
},
  "geometry": {"coordinates":[-0.14692110108726,52.78838890850248],"type":"Point"}
}