{
  "type": "Feature",
  "properties": {
    "date:inception_lower": "1998-06-01",
    "date:inception_upper": "1998-06-01",
    "iso:country": "GB",
    "wof:name": "PE11 2NP",
    "wof:placetype": "postalcode"
  },
  "geometry": {"coordinates":[-0.146921,52.788389],"type":"Point"}
}
