{
  "type": "Feature",
  "properties": {
    "iso:country":"GB",
    "wof:name":"NE22 5UU",
    "wof:placetype":"postalcode"
},
  "geometry": {"coordinates":[-1.56834012745248,55.13893763897287],"type":"Point"}
}