{
  "type": "Feature",
  "properties": {
    "iso:country": "GB",
    "wof:name": "NE22 5UU",
    "wof:placetype": "postalcode"
  },
  "geometry": {"coordinates":[-1.56834,55.138938],"type":"Point"}
}
