{
  "type": "Feature",
  "properties": {
    "iso:country": "GB",
    "wof:name": "SN11 8AA",
    "wof:placetype": "postalcode"
  },
  "geometry": {"coordinates":[-2.004498,51.440541],"type":"Point"}
}
