{
  "type": "Feature",
  "properties": {
    "date:inception_lower":"1997-06-01",
    "date:inception_upper":"1997-06-30",
    "iso:country":"GB",
    "wof:name":"UB2 4XE",
    "wof:placetype":"postalcode"
},
  "geometry": {"coordinates":[-0.35381,51.507192],"type":"Point"}
}