{
  "type": "Feature",
  "properties": {
    "iso:country":"GB",
    "wof:name":"UB2 4XE",
    "wof:placetype":"postalcode"
},
  "geometry": {"coordinates":[-0.35381052358353,51.50719211068062],"type":"Point"}
}