{
  "type": "Feature",
  "properties": {
    "iso:country": "GB",
    "wof:name": "NR3 4ST",
    "wof:placetype": "postalcode"
  },
  "geometry": {"coordinates":[1.303167,52.64418],"type":"Point"}
}
