{
  "type": "Feature",
  "properties": {
    "iso:country":"GB",
    "wof:name":"NR3 4ST",
    "wof:placetype":"postalcode"
},
  "geometry": {"coordinates":[1.30316711105858,52.64417990703203],"type":"Point"}
}