{
  "type": "Feature",
  "properties": {
    "date:inception_lower": "1992-08-01",
    "date:inception_upper": "1992-08-01",
    "iso:country": "GB",
    "wof:name": "WS12 4TF",
    "wof:placetype": "postalcode"
  },
  "geometry": {"coordinates":[-2.040164,52.716476],"type":"Point"}
}
