{
  "type": "Feature",
  "properties": {
    "iso:country":"GB",
    "wof:name":"KT1 3JE",
    "wof:placetype":"postalcode"
},
  "geometry": {"coordinates":[-0.28846796276811,51.40851818625197],"type":"Point"}
}