{
  "type": "Feature",
  "properties": {
    "date:inception_lower": "2020-11-01",
    "date:inception_upper": "2020-11-01",
    "iso:country": "GB",
    "wof:name": "YO62 5FF",
    "wof:placetype": "postalcode"
  },
  "geometry": {"coordinates":[-1.050264,54.244361],"type":"Point"}
}
