{
  "type": "Feature",
  "properties": {
    "iso:country":"GB",
    "wof:name":"DY8 3TZ",
    "wof:placetype":"postalcode"
},
  "geometry": {"coordinates":[-2.15727482246295,52.45702280862866],"type":"Point"}
}