{
  "type": "Feature",
  "properties": {
    "iso:country":"GB",
    "wof:name":"M23 9EW",
    "wof:placetype":"postalcode"
},
  "geometry": {"coordinates":[-2.30384094324532,53.40652864281892],"type":"Point"}
}