{
  "type": "Feature",
  "properties": {
    "iso:country": "GB",
    "wof:name": "BD15 7WJ",
    "wof:placetype": "postalcode"
  },
  "geometry": {"coordinates":[-1.824464,53.797525],"type":"Point"}
}
