{
  "type": "Feature",
  "properties": {
    "iso:country":"GB",
    "wof:name":"OX7 5AA",
    "wof:placetype":"postalcode"
},
  "geometry": {"coordinates":[-1.54559867627864,51.94033843845464],"type":"Point"}
}