{
  "type": "Feature",
  "properties": {
    "iso:country": "GB",
    "wof:name": "SK9 4EP",
    "wof:placetype": "postalcode"
  },
  "geometry": {"coordinates":[-2.224378,53.341753],"type":"Point"}
}
