{
  "type": "Feature",
  "properties": {
    "date:inception_lower": "1980-01-01",
    "date:inception_upper": "1980-01-01",
    "iso:country": "GB",
    "wof:name": "SK9 4EP",
    "wof:placetype": "postalcode"
  },
  "geometry": {"coordinates":[-2.224378,53.341753],"type":"Point"}
}
