{
  "type": "Feature",
  "properties": {
    "iso:country":"GB",
    "wof:name":"BR2 7NS",
    "wof:placetype":"postalcode"
},
  "geometry": {"coordinates":[0.01034055457042,51.38189345346417],"type":"Point"}
}