{
  "type": "Feature",
  "properties": {
    "date:inception_lower": "1980-01-01",
    "date:inception_upper": "1980-01-01",
    "iso:country": "GB",
    "wof:name": "BR2 7NS",
    "wof:placetype": "postalcode"
  },
  "geometry": {"coordinates":[0.010341,51.381893],"type":"Point"}
}
