{
  "type": "Feature",
  "properties": {
    "iso:country":"GB",
    "wof:name":"BS5 0RL",
    "wof:placetype":"postalcode"
},
  "geometry": {"coordinates":[-2.56500865007983,51.46526301980042],"type":"Point"}
}