{
  "type": "Feature",
  "properties": {
    "date:inception_lower": "2011-07-01",
    "date:inception_upper": "2011-07-01",
    "iso:country": "GB",
    "wof:name": "BS5 0RL",
    "wof:placetype": "postalcode"
  },
  "geometry": {"coordinates":[-2.565009,51.465263],"type":"Point"}
}
