{
  "type": "Feature",
  "properties": {
    "iso:country":"GB",
    "wof:name":"LU2 7BJ",
    "wof:placetype":"postalcode"
},
  "geometry": {"coordinates":[-0.42217826206382,51.91213002013716],"type":"Point"}
}