{
  "type": "Feature",
  "properties": {
    "iso:country": "GB",
    "wof:name": "LN6 4RZ",
    "wof:placetype": "postalcode"
  },
  "geometry": {"coordinates":[-0.653533,53.2088],"type":"Point"}
}
