{
  "type": "Feature",
  "properties": {
    "iso:country": "GB",
    "wof:name": "PE24 5US",
    "wof:placetype": "postalcode"
  },
  "geometry": {"coordinates":[0.336495,53.233918],"type":"Point"}
}
