{
  "type": "Feature",
  "properties": {
    "date:inception_lower":"2010-02-01",
    "date:inception_upper":"2010-02-28",
    "iso:country":"GB",
    "wof:name":"SA10 6FN",
    "wof:placetype":"postalcode"
},
  "geometry": {"coordinates":[-3.854777,51.644685],"type":"Point"}
}