{
  "type": "Feature",
  "properties": {
    "date:inception_lower": "1996-12-01",
    "date:inception_upper": "1996-12-01",
    "iso:country": "GB",
    "wof:name": "PO41 0YP",
    "wof:placetype": "postalcode"
  },
  "geometry": {"coordinates":[-1.479097,50.707726],"type":"Point"}
}
