{
  "type": "Feature",
  "properties": {
    "date:inception_lower": "1980-01-01",
    "date:inception_upper": "1980-01-01",
    "iso:country": "GB",
    "wof:name": "NR25 7JY",
    "wof:placetype": "postalcode"
  },
  "geometry": {"coordinates":[1.01306,52.914842],"type":"Point"}
}
