{
  "type": "Feature",
  "properties": {
    "iso:country":"GB",
    "wof:name":"WN2 1PY",
    "wof:placetype":"postalcode"
},
  "geometry": {"coordinates":[-2.56957756645887,53.5629369537193],"type":"Point"}
}