{
  "type": "Feature",
  "properties": {
    "iso:country": "GB",
    "wof:name": "HU17 0WX",
    "wof:placetype": "postalcode"
  },
  "geometry": {"coordinates":[-0.401341,53.840773],"type":"Point"}
}
