{
  "type": "Feature",
  "properties": {
    "date:inception_lower":"2016-11-01",
    "date:inception_upper":"2016-11-30",
    "iso:country":"GB",
    "wof:name":"HU17 0WX",
    "wof:placetype":"postalcode"
},
  "geometry": {"coordinates":[-0.401341,53.840773],"type":"Point"}
}