{
  "type": "Feature",
  "properties": {
    "iso:country":"GB",
    "wof:name":"GL52 7SU",
    "wof:placetype":"postalcode"
},
  "geometry": {"coordinates":[-2.11033400159302,51.95198724196593],"type":"Point"}
}