{
  "type": "Feature",
  "properties": {
    "iso:country":"GB",
    "wof:name":"OL2 5BD",
    "wof:placetype":"postalcode"
},
  "geometry": {"coordinates":[-2.12285120589258,53.5563121450988],"type":"Point"}
}