{
  "type": "Feature",
  "properties": {
    "date:inception_lower":"1992-01-01",
    "date:inception_upper":"1992-01-31",
    "iso:country":"GB",
    "wof:name":"B25 8NF",
    "wof:placetype":"postalcode"
},
  "geometry": {"coordinates":[-1.812323,52.460207],"type":"Point"}
}