{
  "type": "Feature",
  "properties": {
    "iso:country":"GB",
    "wof:name":"B25 8NF",
    "wof:placetype":"postalcode"
},
  "geometry": {"coordinates":[-1.81232268746337,52.46020666095642],"type":"Point"}
}