{
  "type": "Feature",
  "properties": {
    "iso:country":"GB",
    "wof:name":"HP1 2RB",
    "wof:placetype":"postalcode"
},
  "geometry": {"coordinates":[-0.50223246109406,51.74272065611876],"type":"Point"}
}