{
  "type": "Feature",
  "properties": {
    "iso:country":"GB",
    "wof:name":"L21 7NA",
    "wof:placetype":"postalcode"
},
  "geometry": {"coordinates":[-2.98525353672255,53.47587484962614],"type":"Point"}
}