{
  "type": "Feature",
  "properties": {
    "iso:country": "GB",
    "wof:name": "L21 7NA",
    "wof:placetype": "postalcode"
  },
  "geometry": {"coordinates":[-2.985253,53.475875],"type":"Point"}
}
