{
  "type": "Feature",
  "properties": {
    "iso:country": "GB",
    "wof:name": "EX10 0DG",
    "wof:placetype": "postalcode"
  },
  "geometry": {"coordinates":[-3.302001,50.698303],"type":"Point"}
}
