{
  "type": "Feature",
  "properties": {
    "iso:country":"GB",
    "wof:name":"EX10 0DG",
    "wof:placetype":"postalcode"
},
  "geometry": {"coordinates":[-3.30200346107256,50.69834984116192],"type":"Point"}
}