{
  "type": "Feature",
  "properties": {
    "iso:country":"GB",
    "wof:name":"GL56 0UB",
    "wof:placetype":"postalcode"
},
  "geometry": {"coordinates":[-1.7069313334424,51.94131772242277],"type":"Point"}
}