{
  "type": "Feature",
  "properties": {
    "iso:country":"GB",
    "wof:name":"WA6 9LE",
    "wof:placetype":"postalcode"
},
  "geometry": {"coordinates":[-2.75462820815027,53.27732836024311],"type":"Point"}
}