{
  "type": "Feature",
  "properties": {
    "iso:country":"GB",
    "wof:name":"M20 4PX",
    "wof:placetype":"postalcode"
},
  "geometry": {"coordinates":[-2.22526109030389,53.43498085417537],"type":"Point"}
}