{
  "type": "Feature",
  "properties": {
    "iso:country": "GB",
    "wof:name": "LS17 8FZ",
    "wof:placetype": "postalcode"
  },
  "geometry": {"coordinates":[-1.469836,53.852],"type":"Point"}
}
