{
  "type": "Feature",
  "properties": {
    "iso:country":"GB",
    "wof:name":"TS19 7JW",
    "wof:placetype":"postalcode"
},
  "geometry": {"coordinates":[-1.36434143329833,54.57265577930495],"type":"Point"}
}