{
  "type": "Feature",
  "properties": {
    "iso:country": "GB",
    "wof:name": "TN11 0BD",
    "wof:placetype": "postalcode"
  },
  "geometry": {"coordinates":[0.342836,51.210343],"type":"Point"}
}
