{
  "type": "Feature",
  "properties": {
    "iso:country":"GB",
    "wof:name":"LS16 7QS",
    "wof:placetype":"postalcode"
},
  "geometry": {"coordinates":[-1.60450101524466,53.85836272940161],"type":"Point"}
}