{
  "type": "Feature",
  "properties": {
    "iso:country":"GB",
    "wof:name":"LU7 9LX",
    "wof:placetype":"postalcode"
},
  "geometry": {"coordinates":[-0.58102364309937,51.92938371515208],"type":"Point"}
}