{
  "type": "Feature",
  "properties": {
    "iso:country": "GB",
    "wof:name": "LU7 9LX",
    "wof:placetype": "postalcode"
  },
  "geometry": {"coordinates":[-0.581024,51.929384],"type":"Point"}
}
