{
  "type": "Feature",
  "properties": {
    "date:inception_lower": "1980-01-01",
    "date:inception_upper": "1980-01-01",
    "iso:country": "GB",
    "wof:name": "RH12 2NN",
    "wof:placetype": "postalcode"
  },
  "geometry": {"coordinates":[-0.319765,51.067365],"type":"Point"}
}
