{
  "type": "Feature",
  "properties": {
    "iso:country":"GB",
    "wof:name":"NG1 4BY",
    "wof:placetype":"postalcode"
},
  "geometry": {"coordinates":[-1.15061223212009,52.95523856540591],"type":"Point"}
}