{
  "type": "Feature",
  "properties": {
    "date:inception_lower": "2008-03-01",
    "date:inception_upper": "2008-03-01",
    "iso:country": "GB",
    "wof:name": "NG1 4BY",
    "wof:placetype": "postalcode"
  },
  "geometry": {"coordinates":[-1.150612,52.955239],"type":"Point"}
}
