{
  "type": "Feature",
  "properties": {
    "iso:country":"GB",
    "wof:name":"KT12 5EX",
    "wof:placetype":"postalcode"
},
  "geometry": {"coordinates":[-0.40837166717332,51.3637890832022],"type":"Point"}
}