{
  "type": "Feature",
  "properties": {
    "date:inception_lower":"1996-06-01",
    "date:inception_upper":"1996-06-30",
    "iso:country":"GB",
    "wof:name":"NE66 4SJ",
    "wof:placetype":"postalcode"
},
  "geometry": {"coordinates":[-1.891347,55.402666],"type":"Point"}
}