{
  "type": "Feature",
  "properties": {
    "iso:country": "GB",
    "wof:name": "NE66 4SJ",
    "wof:placetype": "postalcode"
  },
  "geometry": {"coordinates":[-1.891347,55.402666],"type":"Point"}
}
