{
  "type": "Feature",
  "properties": {
    "iso:country":"GB",
    "wof:name":"NE66 4SJ",
    "wof:placetype":"postalcode"
},
  "geometry": {"coordinates":[-1.89134744874999,55.40266595441576],"type":"Point"}
}