{
  "type": "Feature",
  "properties": {
    "date:inception_lower":"1980-01-01",
    "date:inception_upper":"1980-01-31",
    "iso:country":"GB",
    "wof:name":"BS13 9PP",
    "wof:placetype":"postalcode"
},
  "geometry": {"coordinates":[-2.606861,51.41033],"type":"Point"}
}