{
  "type": "Feature",
  "properties": {
    "iso:country": "GB",
    "wof:name": "BS13 9PP",
    "wof:placetype": "postalcode"
  },
  "geometry": {"coordinates":[-2.606861,51.41033],"type":"Point"}
}
