{
  "type": "Feature",
  "properties": {
    "date:inception_lower": "1999-06-01",
    "date:inception_upper": "1999-06-01",
    "iso:country": "GB",
    "wof:name": "CH44 9EQ",
    "wof:placetype": "postalcode"
  },
  "geometry": {"coordinates":[-3.031825,53.41184],"type":"Point"}
}
