{
  "type": "Feature",
  "properties": {
    "iso:country": "GB",
    "wof:name": "CH44 9EQ",
    "wof:placetype": "postalcode"
  },
  "geometry": {"coordinates":[-3.031825,53.41184],"type":"Point"}
}
