{
  "type": "Feature",
  "properties": {
    "iso:country":"GB",
    "wof:name":"CH44 9EQ",
    "wof:placetype":"postalcode"
},
  "geometry": {"coordinates":[-3.03182505614244,53.41184019094616],"type":"Point"}
}