{
  "type": "Feature",
  "properties": {
    "date:inception_lower": "1980-01-01",
    "date:inception_upper": "1980-01-01",
    "iso:country": "GB",
    "wof:name": "NG9 2QX",
    "wof:placetype": "postalcode"
  },
  "geometry": {"coordinates":[-1.219191,52.937757],"type":"Point"}
}
