{
  "type": "Feature",
  "properties": {
    "iso:country": "GB",
    "wof:name": "BD16 3EN",
    "wof:placetype": "postalcode"
  },
  "geometry": {"coordinates":[-1.813951,53.85745],"type":"Point"}
}
