{
  "type": "Feature",
  "properties": {
    "iso:country":"GB",
    "wof:name":"BD16 3EN",
    "wof:placetype":"postalcode"
},
  "geometry": {"coordinates":[-1.81395100131945,53.85744964383736],"type":"Point"}
}