{
  "type": "Feature",
  "properties": {
    "iso:country":"GB",
    "wof:name":"SW4 7BU",
    "wof:placetype":"postalcode"
},
  "geometry": {"coordinates":[-0.13512096743396,51.45999014615087],"type":"Point"}
}