{
  "type": "Feature",
  "properties": {
    "iso:country":"GB",
    "wof:name":"ME9 8SG",
    "wof:placetype":"postalcode"
},
  "geometry": {"coordinates":[0.72107071329012,51.375893525475],"type":"Point"}
}