{
  "type": "Feature",
  "properties": {
    "date:inception_lower": "1980-01-01",
    "date:inception_upper": "1980-01-01",
    "iso:country": "GB",
    "wof:name": "DL6 2LU",
    "wof:placetype": "postalcode"
  },
  "geometry": {"coordinates":[-1.359577,54.43212],"type":"Point"}
}
