{
  "type": "Feature",
  "properties": {
    "date:inception_lower": "2008-08-01",
    "date:inception_upper": "2008-08-01",
    "iso:country": "GB",
    "wof:name": "NE33 1BS",
    "wof:placetype": "postalcode"
  },
  "geometry": {"coordinates":[-1.435252,54.997778],"type":"Point"}
}
