{
  "type": "Feature",
  "properties": {
    "iso:country": "GB",
    "wof:name": "DG5 4AW",
    "wof:placetype": "postalcode"
  },
  "geometry": {"coordinates":[-3.826579,54.934013],"type":"Point"}
}
