{
  "type": "Feature",
  "properties": {
    "date:inception_lower": "1980-01-01",
    "date:inception_upper": "1980-01-01",
    "iso:country": "GB",
    "wof:name": "SE17 3TF",
    "wof:placetype": "postalcode"
  },
  "geometry": {"coordinates":[-0.104458,51.484687],"type":"Point"}
}
