{
  "type": "Feature",
  "properties": {
    "iso:country":"GB",
    "wof:name":"SE17 3TF",
    "wof:placetype":"postalcode"
},
  "geometry": {"coordinates":[-0.10445766447085,51.48468666053303],"type":"Point"}
}