{
  "type": "Feature",
  "properties": {
    "iso:country":"GB",
    "wof:name":"BH5 1AD",
    "wof:placetype":"postalcode"
},
  "geometry": {"coordinates":[-1.84271404057309,50.72264904020665],"type":"Point"}
}