{
  "type": "Feature",
  "properties": {
    "date:inception_lower":"2006-04-01",
    "date:inception_upper":"2006-04-30",
    "iso:country":"GB",
    "wof:name":"BH5 1AD",
    "wof:placetype":"postalcode"
},
  "geometry": {"coordinates":[-1.842714,50.722649],"type":"Point"}
}