{
  "type": "Feature",
  "properties": {
    "iso:country": "GB",
    "wof:name": "BH5 1AD",
    "wof:placetype": "postalcode"
  },
  "geometry": {"coordinates":[-1.842714,50.722649],"type":"Point"}
}
