{
  "type": "Feature",
  "properties": {
    "iso:country":"GB",
    "wof:name":"NE63 8LP",
    "wof:placetype":"postalcode"
},
  "geometry": {"coordinates":[-1.58307495698872,55.17157215469442],"type":"Point"}
}