{
  "type": "Feature",
  "properties": {
    "iso:country":"GB",
    "wof:name":"LL12 7AP",
    "wof:placetype":"postalcode"
},
  "geometry": {"coordinates":[-2.98761307010942,53.05279039617333],"type":"Point"}
}