{
  "type": "Feature",
  "properties": {
    "iso:country": "GB",
    "wof:name": "IP31 3SR",
    "wof:placetype": "postalcode"
  },
  "geometry": {"coordinates":[0.81887,52.250307],"type":"Point"}
}
