{
  "type": "Feature",
  "properties": {
    "iso:country": "GB",
    "wof:name": "BR3 1DJ",
    "wof:placetype": "postalcode"
  },
  "geometry": {"coordinates":[-0.029323,51.417684],"type":"Point"}
}
