{
  "type": "Feature",
  "properties": {
    "date:inception_lower": "1980-01-01",
    "date:inception_upper": "1980-01-01",
    "iso:country": "GB",
    "wof:name": "DN36 4AW",
    "wof:placetype": "postalcode"
  },
  "geometry": {"coordinates":[-0.04615,53.535112],"type":"Point"}
}
