{
  "type": "Feature",
  "properties": {
    "iso:country":"GB",
    "wof:name":"MK41 0TY",
    "wof:placetype":"postalcode"
},
  "geometry": {"coordinates":[-0.41668257201781,52.14737221383913],"type":"Point"}
}