{
  "type": "Feature",
  "properties": {
    "iso:country": "GB",
    "wof:name": "MK41 0TY",
    "wof:placetype": "postalcode"
  },
  "geometry": {"coordinates":[-0.417534,52.147063],"type":"Point"}
}
