{
  "type": "Feature",
  "properties": {
    "iso:country": "GB",
    "wof:name": "S10 5NW",
    "wof:placetype": "postalcode"
  },
  "geometry": {"coordinates":[-1.531684,53.377819],"type":"Point"}
}
