{
  "type": "Feature",
  "properties": {
    "iso:country":"GB",
    "wof:name":"S10 5NW",
    "wof:placetype":"postalcode"
},
  "geometry": {"coordinates":[-1.53168445817605,53.37781917613484],"type":"Point"}
}