{
  "type": "Feature",
  "properties": {
    "iso:country":"GB",
    "wof:name":"LL33 0PY",
    "wof:placetype":"postalcode"
},
  "geometry": {"coordinates":[-3.96265545850265,53.26333469102502],"type":"Point"}
}