{
  "type": "Feature",
  "properties": {
    "date:inception_lower": "1992-08-01",
    "date:inception_upper": "1992-08-01",
    "iso:country": "GB",
    "wof:name": "OL12 0NS",
    "wof:placetype": "postalcode"
  },
  "geometry": {"coordinates":[-2.159452,53.619697],"type":"Point"}
}
