{
  "type": "Feature",
  "properties": {
    "iso:country": "GB",
    "wof:name": "OL12 0NS",
    "wof:placetype": "postalcode"
  },
  "geometry": {"coordinates":[-2.157957,53.62014],"type":"Point"}
}
