{
  "type": "Feature",
  "properties": {
    "iso:country":"GB",
    "wof:name":"AB16 5UJ",
    "wof:placetype":"postalcode"
},
  "geometry": {"coordinates":[-2.14631585623937,57.15785817781288],"type":"Point"}
}