{
  "type": "Feature",
  "properties": {
    "iso:country": "GB",
    "wof:name": "SL6 7LA",
    "wof:placetype": "postalcode"
  },
  "geometry": {"coordinates":[-0.722111,51.533147],"type":"Point"}
}
