{
  "type": "Feature",
  "properties": {
    "iso:country":"GB",
    "wof:name":"KT24 5SQ",
    "wof:placetype":"postalcode"
},
  "geometry": {"coordinates":[-0.41360597398264,51.26752343529907],"type":"Point"}
}