{
  "type": "Feature",
  "properties": {
    "iso:country":"GB",
    "wof:name":"GL5 1SQ",
    "wof:placetype":"postalcode"
},
  "geometry": {"coordinates":[-2.21339471473811,51.749459318797],"type":"Point"}
}