{
  "type": "Feature",
  "properties": {
    "iso:country":"GB",
    "wof:name":"IG9 5SS",
    "wof:placetype":"postalcode"
},
  "geometry": {"coordinates":[0.0352208936447,51.63194726950948],"type":"Point"}
}