{
  "type": "Feature",
  "properties": {
    "iso:country": "GB",
    "wof:name": "M24 4TQ",
    "wof:placetype": "postalcode"
  },
  "geometry": {"coordinates":[-2.223669,53.547196],"type":"Point"}
}
