{
  "type": "Feature",
  "properties": {
    "iso:country":"GB",
    "wof:name":"M24 4TQ",
    "wof:placetype":"postalcode"
},
  "geometry": {"coordinates":[-2.22366884871073,53.54719552074451],"type":"Point"}
}