{
  "type": "Feature",
  "properties": {
    "iso:country":"GB",
    "wof:name":"SM6 0QG",
    "wof:placetype":"postalcode"
},
  "geometry": {"coordinates":[-0.14663243972971,51.34594802603036],"type":"Point"}
}