{
  "type": "Feature",
  "properties": {
    "iso:country":"GB",
    "wof:name":"AB11 7SB",
    "wof:placetype":"postalcode"
},
  "geometry": {"coordinates":[-2.10638802466963,57.13303346689082],"type":"Point"}
}