{
  "type": "Feature",
  "properties": {
    "date:inception_lower": "1980-01-01",
    "date:inception_upper": "1980-01-01",
    "iso:country": "GB",
    "wof:name": "E2 9ED",
    "wof:placetype": "postalcode"
  },
  "geometry": {"coordinates":[-0.058656,51.532517],"type":"Point"}
}
