{
  "type": "Feature",
  "properties": {
    "iso:country":"GB",
    "wof:name":"WR11 7PG",
    "wof:placetype":"postalcode"
},
  "geometry": {"coordinates":[-1.83568041494985,52.09074983191516],"type":"Point"}
}