{
  "type": "Feature",
  "properties": {
    "iso:country":"GB",
    "wof:name":"G53 6QE",
    "wof:placetype":"postalcode"
},
  "geometry": {"coordinates":[-4.34047624969419,55.81309710733073],"type":"Point"}
}