{
  "type": "Feature",
  "properties": {
    "date:inception_lower":"2000-06-01",
    "date:inception_upper":"2000-06-30",
    "iso:country":"GB",
    "wof:name":"SN25 4GA",
    "wof:placetype":"postalcode"
},
  "geometry": {"coordinates":[-1.797884,51.605801],"type":"Point"}
}