{
  "type": "Feature",
  "properties": {
    "iso:country":"GB",
    "wof:name":"SN25 4GA",
    "wof:placetype":"postalcode"
},
  "geometry": {"coordinates":[-1.79788391478644,51.60580077155331],"type":"Point"}
}