{
  "type": "Feature",
  "properties": {
    "date:inception_lower":"1992-01-01",
    "date:inception_upper":"1992-01-31",
    "iso:country":"GB",
    "wof:name":"B97 4DL",
    "wof:placetype":"postalcode"
},
  "geometry": {"coordinates":[-1.939723,52.309141],"type":"Point"}
}