{
  "type": "Feature",
  "properties": {
    "iso:country":"GB",
    "wof:name":"B97 4DL",
    "wof:placetype":"postalcode"
},
  "geometry": {"coordinates":[-1.93964320341251,52.30916225303221],"type":"Point"}
}