{
  "type": "Feature",
  "properties": {
    "iso:country":"GB",
    "wof:name":"PR7 1RU",
    "wof:placetype":"postalcode"
},
  "geometry": {"coordinates":[-2.64047974452452,53.65999449100249],"type":"Point"}
}