{
  "type": "Feature",
  "properties": {
    "iso:country": "GB",
    "wof:name": "PR7 1RU",
    "wof:placetype": "postalcode"
  },
  "geometry": {"coordinates":[-2.64048,53.659994],"type":"Point"}
}
