{
  "type": "Feature",
  "properties": {
    "iso:country":"GB",
    "wof:name":"BD9 4JB",
    "wof:placetype":"postalcode"
},
  "geometry": {"coordinates":[-1.76984000329183,53.81973186088783],"type":"Point"}
}