{
  "type": "Feature",
  "properties": {
    "iso:country":"GB",
    "wof:name":"RH4 3LY",
    "wof:placetype":"postalcode"
},
  "geometry": {"coordinates":[-0.35395797625286,51.23105308786486],"type":"Point"}
}