{
  "type": "Feature",
  "properties": {
    "iso:country":"GB",
    "wof:name":"BN10 8JR",
    "wof:placetype":"postalcode"
},
  "geometry": {"coordinates":[-0.00101059631827,50.79141987573729],"type":"Point"}
}