{
  "type": "Feature",
  "properties": {
    "iso:country":"GB",
    "wof:name":"L3 4EF",
    "wof:placetype":"postalcode"
},
  "geometry": {"coordinates":[-2.96913423747968,53.37610418139051],"type":"Point"}
}