{
  "type": "Feature",
  "properties": {
    "iso:country":"GB",
    "wof:name":"ST3 5WY",
    "wof:placetype":"postalcode"
},
  "geometry": {"coordinates":[-2.11623737924575,52.99293971885521],"type":"Point"}
}