{
  "type": "Feature",
  "properties": {
    "date:inception_lower":"2006-09-01",
    "date:inception_upper":"2006-09-30",
    "iso:country":"GB",
    "wof:name":"ST3 5WY",
    "wof:placetype":"postalcode"
},
  "geometry": {"coordinates":[-2.116237,52.99294],"type":"Point"}
}