{
  "type": "Feature",
  "properties": {
    "iso:country":"GB",
    "wof:name":"LS13 1NR",
    "wof:placetype":"postalcode"
},
  "geometry": {"coordinates":[-1.66472382914556,53.82778923967259],"type":"Point"}
}