{
  "type": "Feature",
  "properties": {
    "date:inception_lower": "1980-01-01",
    "date:inception_upper": "1980-01-01",
    "iso:country": "GB",
    "wof:name": "LS13 1NR",
    "wof:placetype": "postalcode"
  },
  "geometry": {"coordinates":[-1.664653,53.827822],"type":"Point"}
}
