{
  "type": "Feature",
  "properties": {
    "iso:country":"GB",
    "wof:name":"LS12 1AF",
    "wof:placetype":"postalcode"
},
  "geometry": {"coordinates":[-1.55928390067182,53.79039986092262],"type":"Point"}
}