{
  "type": "Feature",
  "properties": {
    "date:inception_lower": "2014-05-01",
    "date:inception_upper": "2014-05-01",
    "iso:country": "GB",
    "wof:name": "LS12 1AF",
    "wof:placetype": "postalcode"
  },
  "geometry": {"coordinates":[-1.559288,53.790416],"type":"Point"}
}
