{
  "type": "Feature",
  "properties": {
    "iso:country":"GB",
    "wof:name":"ST7 3PL",
    "wof:placetype":"postalcode"
},
  "geometry": {"coordinates":[-2.20561532483304,53.11919625218867],"type":"Point"}
}