{
  "type": "Feature",
  "properties": {
    "date:inception_lower": "1980-01-01",
    "date:inception_upper": "1980-01-01",
    "iso:country": "GB",
    "wof:name": "LS15 9AF",
    "wof:placetype": "postalcode"
  },
  "geometry": {"coordinates":[-1.43625,53.790838],"type":"Point"}
}
