{
  "type": "Feature",
  "properties": {
    "iso:country":"GB",
    "wof:name":"FK10 4LP",
    "wof:placetype":"postalcode"
},
  "geometry": {"coordinates":[-3.71999134467478,56.06702378208173],"type":"Point"}
}