{
  "type": "Feature",
  "properties": {
    "iso:country":"GB",
    "wof:name":"CA14 1DD",
    "wof:placetype":"postalcode"
},
  "geometry": {"coordinates":[-3.53693894477916,54.64909022307691],"type":"Point"}
}