{
  "type": "Feature",
  "properties": {
    "date:inception_lower": "2014-05-01",
    "date:inception_upper": "2014-05-01",
    "iso:country": "GB",
    "wof:name": "SL5 7SQ",
    "wof:placetype": "postalcode"
  },
  "geometry": {"coordinates":[-0.682156,51.423246],"type":"Point"}
}
