{
  "type": "Feature",
  "properties": {
    "iso:country": "GB",
    "wof:name": "SL5 7SQ",
    "wof:placetype": "postalcode"
  },
  "geometry": {"coordinates":[-0.68238,51.423059],"type":"Point"}
}
