{
  "type": "Feature",
  "properties": {
    "iso:country":"GB",
    "wof:name":"NE61 3XD",
    "wof:placetype":"postalcode"
},
  "geometry": {"coordinates":[-1.79922857456751,55.12682095765238],"type":"Point"}
}