{
  "type": "Feature",
  "properties": {
    "date:inception_lower": "1980-01-01",
    "date:inception_upper": "1980-01-01",
    "iso:country": "GB",
    "wof:name": "NE61 3XD",
    "wof:placetype": "postalcode"
  },
  "geometry": {"coordinates":[-1.799229,55.126821],"type":"Point"}
}
