{
  "type": "Feature",
  "properties": {
    "date:inception_lower":"1980-01-01",
    "date:inception_upper":"1980-01-31",
    "iso:country":"GB",
    "wof:name":"B9 4EP",
    "wof:placetype":"postalcode"
},
  "geometry": {"coordinates":[-1.87874,52.477419],"type":"Point"}
}