{
  "type": "Feature",
  "properties": {
    "iso:country":"GB",
    "wof:name":"CB24 4SY",
    "wof:placetype":"postalcode"
},
  "geometry": {"coordinates":[-0.03798216389707,52.29856639773844],"type":"Point"}
}