{
  "type": "Feature",
  "properties": {
    "date:inception_lower":"2006-09-01",
    "date:inception_upper":"2006-09-30",
    "iso:country":"GB",
    "wof:name":"CB24 4SY",
    "wof:placetype":"postalcode"
},
  "geometry": {"coordinates":[-0.037982,52.298566],"type":"Point"}
}