{
  "type": "Feature",
  "properties": {
    "iso:country": "GB",
    "wof:name": "CB24 4SY",
    "wof:placetype": "postalcode"
  },
  "geometry": {"coordinates":[-0.037982,52.298566],"type":"Point"}
}
