{
  "type": "Feature",
  "properties": {
    "date:inception_lower": "2017-05-01",
    "date:inception_upper": "2017-05-01",
    "iso:country": "GB",
    "wof:name": "FY5 3FW",
    "wof:placetype": "postalcode"
  },
  "geometry": {"coordinates":[-3.018656,53.863151],"type":"Point"}
}
