{
  "type": "Feature",
  "properties": {
    "date:inception_lower": "1980-01-01",
    "date:inception_upper": "1980-01-01",
    "iso:country": "GB",
    "wof:name": "WF10 1EL",
    "wof:placetype": "postalcode"
  },
  "geometry": {"coordinates":[-1.354496,53.724659],"type":"Point"}
}
