{
  "type": "Feature",
  "properties": {
    "date:inception_lower":"2014-02-01",
    "date:inception_upper":"2014-02-28",
    "iso:country":"GB",
    "wof:name":"EH22 2FR",
    "wof:placetype":"postalcode"
},
  "geometry": {"coordinates":[-3.040238,55.897423],"type":"Point"}
}