{
  "type": "Feature",
  "properties": {
    "date:inception_lower": "2023-10-01",
    "date:inception_upper": "2023-10-01",
    "iso:country": "GB",
    "wof:name": "CH3 9GE",
    "wof:placetype": "postalcode"
  },
  "geometry": {"coordinates":[-2.764922,53.122145],"type":"Point"}
}
