{
  "type": "Feature",
  "properties": {
    "iso:country":"GB",
    "wof:name":"BS23 3HW",
    "wof:placetype":"postalcode"
},
  "geometry": {"coordinates":[-2.95328625297596,51.34785906823412],"type":"Point"}
}