{
  "type": "Feature",
  "properties": {
    "iso:country":"GB",
    "wof:name":"G72 7BW",
    "wof:placetype":"postalcode"
},
  "geometry": {"coordinates":[-4.17531925293786,55.81953676434323],"type":"Point"}
}