{
  "type": "Feature",
  "properties": {
    "iso:country":"GB",
    "wof:name":"BR6 0QN",
    "wof:placetype":"postalcode"
},
  "geometry": {"coordinates":[0.10456305410083,51.37199212420748],"type":"Point"}
}