{
  "type": "Feature",
  "properties": {
    "date:inception_lower": "1990-02-01",
    "date:inception_upper": "1990-02-01",
    "iso:country": "GB",
    "wof:name": "BL1 5NL",
    "wof:placetype": "postalcode"
  },
  "geometry": {"coordinates":[-2.46907,53.587247],"type":"Point"}
}
