{
  "type": "Feature",
  "properties": {
    "iso:country": "GB",
    "wof:name": "G12 0YF",
    "wof:placetype": "postalcode"
  },
  "geometry": {"coordinates":[-4.318234,55.88509],"type":"Point"}
}
