{
  "type": "Feature",
  "properties": {
    "date:inception_lower":"1980-01-01",
    "date:inception_upper":"1980-01-31",
    "iso:country":"GB",
    "wof:name":"G12 0YF",
    "wof:placetype":"postalcode"
},
  "geometry": {"coordinates":[-4.318234,55.88509],"type":"Point"}
}