{
  "type": "Feature",
  "properties": {
    "iso:country": "GB",
    "wof:name": "NR7 8TL",
    "wof:placetype": "postalcode"
  },
  "geometry": {"coordinates":[1.308946,52.654523],"type":"Point"}
}
