{
  "type": "Feature",
  "properties": {
    "iso:country":"GB",
    "wof:name":"NR7 8TL",
    "wof:placetype":"postalcode"
},
  "geometry": {"coordinates":[1.30894612374651,52.65452310121989],"type":"Point"}
}