{
  "type": "Feature",
  "properties": {
    "date:inception_lower": "1980-01-01",
    "date:inception_upper": "1980-01-01",
    "iso:country": "GB",
    "wof:name": "SK15 2LW",
    "wof:placetype": "postalcode"
  },
  "geometry": {"coordinates":[-2.047549,53.482302],"type":"Point"}
}
