{
  "type": "Feature",
  "properties": {
    "iso:country":"GB",
    "wof:name":"DT2 8HJ",
    "wof:placetype":"postalcode"
},
  "geometry": {"coordinates":[-2.34573989065223,50.66326696494184],"type":"Point"}
}