{
  "type": "Feature",
  "properties": {
    "iso:country": "GB",
    "wof:name": "BN21 2NX",
    "wof:placetype": "postalcode"
  },
  "geometry": {"coordinates":[0.27659,50.78008],"type":"Point"}
}
