{
  "type": "Feature",
  "properties": {
    "iso:country":"GB",
    "wof:name":"CO12 3AJ",
    "wof:placetype":"postalcode"
},
  "geometry": {"coordinates":[1.28111333524341,51.93744545447711],"type":"Point"}
}