{
  "type": "Feature",
  "properties": {
    "iso:country":"GB",
    "wof:name":"BL9 5JZ",
    "wof:placetype":"postalcode"
},
  "geometry": {"coordinates":[-2.29954794360457,53.62146161258593],"type":"Point"}
}