{
  "type": "Feature",
  "properties": {
    "date:inception_lower": "1980-01-01",
    "date:inception_upper": "1980-01-01",
    "iso:country": "GB",
    "wof:name": "BL9 5JZ",
    "wof:placetype": "postalcode"
  },
  "geometry": {"coordinates":[-2.299548,53.621462],"type":"Point"}
}
