{
  "type": "Feature",
  "properties": {
    "iso:country":"GB",
    "wof:name":"RH1 2DE",
    "wof:placetype":"postalcode"
},
  "geometry": {"coordinates":[-0.1784901668644,51.24933493251579],"type":"Point"}
}