{
  "type": "Feature",
  "properties": {
    "iso:country":"GB",
    "wof:name":"NE49 0JQ",
    "wof:placetype":"postalcode"
},
  "geometry": {"coordinates":[-2.49936011735106,54.95480142863893],"type":"Point"}
}