{
  "type": "Feature",
  "properties": {
    "iso:country": "GB",
    "wof:name": "NE49 0JQ",
    "wof:placetype": "postalcode"
  },
  "geometry": {"coordinates":[-2.49936,54.954801],"type":"Point"}
}
