{
  "type": "Feature",
  "properties": {
    "date:inception_lower": "1980-01-01",
    "date:inception_upper": "1980-01-01",
    "iso:country": "GB",
    "wof:name": "PE13 2QY",
    "wof:placetype": "postalcode"
  },
  "geometry": {"coordinates":[0.163273,52.660957],"type":"Point"}
}
