{
  "type": "Feature",
  "properties": {
    "iso:country":"GB",
    "wof:name":"PE13 2QY",
    "wof:placetype":"postalcode"
},
  "geometry": {"coordinates":[0.16328718527485,52.66094613875344],"type":"Point"}
}