{
  "type": "Feature",
  "properties": {
    "iso:country": "GB",
    "wof:name": "NE42 6RL",
    "wof:placetype": "postalcode"
  },
  "geometry": {"coordinates":[-1.865214,54.95507],"type":"Point"}
}
