{
  "type": "Feature",
  "properties": {
    "iso:country":"GB",
    "wof:name":"NW4 4EJ",
    "wof:placetype":"postalcode"
},
  "geometry": {"coordinates":[-0.22406315124041,51.58870350103687],"type":"Point"}
}