{
  "type": "Feature",
  "properties": {
    "iso:country": "GB",
    "wof:name": "PE27 6RX",
    "wof:placetype": "postalcode"
  },
  "geometry": {"coordinates":[-0.083389,52.332158],"type":"Point"}
}
