{
  "type": "Feature",
  "properties": {
    "iso:country":"GB",
    "wof:name":"CO16 9JR",
    "wof:placetype":"postalcode"
},
  "geometry": {"coordinates":[1.1131601191282,51.85880699379624],"type":"Point"}
}