{
  "type": "Feature",
  "properties": {
    "iso:country": "GB",
    "wof:name": "WA4 5FD",
    "wof:placetype": "postalcode"
  },
  "geometry": {"coordinates":[-2.572449,53.343772],"type":"Point"}
}
