{
  "type": "Feature",
  "properties": {
    "date:inception_lower":"1996-12-01",
    "date:inception_upper":"1996-12-31",
    "iso:country":"GB",
    "wof:name":"WA4 5FD",
    "wof:placetype":"postalcode"
},
  "geometry": {"coordinates":[-2.572449,53.343772],"type":"Point"}
}