{
  "type": "Feature",
  "properties": {
    "iso:country":"GB",
    "wof:name":"WA4 5FD",
    "wof:placetype":"postalcode"
},
  "geometry": {"coordinates":[-2.57244908850116,53.34377202958276],"type":"Point"}
}