{
  "type": "Feature",
  "properties": {
    "iso:country":"GB",
    "wof:name":"PL19 8BP",
    "wof:placetype":"postalcode"
},
  "geometry": {"coordinates":[-4.15711653658297,50.54001611255129],"type":"Point"}
}