{
  "type": "Feature",
  "properties": {
    "iso:country": "GB",
    "wof:name": "HA3 7HX",
    "wof:placetype": "postalcode"
  },
  "geometry": {"coordinates":[-0.329555,51.601412],"type":"Point"}
}
