{
  "type": "Feature",
  "properties": {
    "iso:country":"GB",
    "wof:name":"B15 3RZ",
    "wof:placetype":"postalcode"
},
  "geometry": {"coordinates":[-1.93463852315703,52.4611193372702],"type":"Point"}
}