{
  "type": "Feature",
  "properties": {
    "iso:country":"GB",
    "wof:name":"B63 2SA",
    "wof:placetype":"postalcode"
},
  "geometry": {"coordinates":[-2.0769051210522,52.46360230459081],"type":"Point"}
}