{
  "type": "Feature",
  "properties": {
    "iso:country": "GB",
    "wof:name": "B63 2SA",
    "wof:placetype": "postalcode"
  },
  "geometry": {"coordinates":[-2.077032,52.463608],"type":"Point"}
}
