{
  "type": "Feature",
  "properties": {
    "iso:country":"GB",
    "wof:name":"PR4 2AQ",
    "wof:placetype":"postalcode"
},
  "geometry": {"coordinates":[-2.87700165355143,53.78306532380351],"type":"Point"}
}