{
  "type": "Feature",
  "properties": {
    "iso:country":"GB",
    "wof:name":"NR31 9RW",
    "wof:placetype":"postalcode"
},
  "geometry": {"coordinates":[1.72665272970529,52.54229401745713],"type":"Point"}
}