{
  "type": "Feature",
  "properties": {
    "iso:country":"GB",
    "wof:name":"NE20 9TT",
    "wof:placetype":"postalcode"
},
  "geometry": {"coordinates":[-1.74922031499888,55.02892405833083],"type":"Point"}
}