{
  "type": "Feature",
  "properties": {
    "iso:country": "GB",
    "wof:name": "NE20 9TT",
    "wof:placetype": "postalcode"
  },
  "geometry": {"coordinates":[-1.749108,55.029038],"type":"Point"}
}
