{
  "type": "Feature",
  "properties": {
    "iso:country": "GB",
    "wof:name": "KA13 7QE",
    "wof:placetype": "postalcode"
  },
  "geometry": {"coordinates":[-4.670744,55.642582],"type":"Point"}
}
