{
  "type": "Feature",
  "properties": {
    "iso:country":"GB",
    "wof:name":"KA13 7QE",
    "wof:placetype":"postalcode"
},
  "geometry": {"coordinates":[-4.67074378966726,55.64258210473979],"type":"Point"}
}