{
  "type": "Feature",
  "properties": {
    "date:inception_lower": "2013-11-01",
    "date:inception_upper": "2013-11-01",
    "iso:country": "GB",
    "wof:name": "KA13 7QE",
    "wof:placetype": "postalcode"
  },
  "geometry": {"coordinates":[-4.671869,55.6426],"type":"Point"}
}
