{
  "type": "Feature",
  "properties": {
    "date:inception_lower": "2021-07-01",
    "date:inception_upper": "2021-07-01",
    "iso:country": "GB",
    "wof:name": "CO11 2FZ",
    "wof:placetype": "postalcode"
  },
  "geometry": {"coordinates":[1.151476,51.913356],"type":"Point"}
}
