{
  "type": "Feature",
  "properties": {
    "date:inception_lower": "2016-06-01",
    "date:inception_upper": "2016-06-01",
    "iso:country": "GB",
    "wof:name": "RG6 9RU",
    "wof:placetype": "postalcode"
  },
  "geometry": {"coordinates":[-0.945636,51.457625],"type":"Point"}
}
