{
  "type": "Feature",
  "properties": {
    "iso:country": "GB",
    "wof:name": "EX17 6HE",
    "wof:placetype": "postalcode"
  },
  "geometry": {"coordinates":[-3.813929,50.800804],"type":"Point"}
}
