{
  "type": "Feature",
  "properties": {
    "date:inception_lower":"1980-01-01",
    "date:inception_upper":"1980-01-31",
    "iso:country":"GB",
    "wof:name":"BA14 0TW",
    "wof:placetype":"postalcode"
},
  "geometry": {"coordinates":[-2.203679,51.295364],"type":"Point"}
}