{
  "type": "Feature",
  "properties": {
    "iso:country":"GB",
    "wof:name":"BA14 0TW",
    "wof:placetype":"postalcode"
},
  "geometry": {"coordinates":[-2.20367894208225,51.29536379479997],"type":"Point"}
}