{
  "type": "Feature",
  "properties": {
    "iso:country":"GB",
    "wof:name":"N7 0BJ",
    "wof:placetype":"postalcode"
},
  "geometry": {"coordinates":[-0.12863262968231,51.54887685838427],"type":"Point"}
}