{
  "type": "Feature",
  "properties": {
    "iso:country": "GB",
    "wof:name": "CW1 4TU",
    "wof:placetype": "postalcode"
  },
  "geometry": {"coordinates":[-2.455348,53.12039],"type":"Point"}
}
