{
  "type": "Feature",
  "properties": {
    "date:inception_lower": "1980-01-01",
    "date:inception_upper": "1980-01-01",
    "iso:country": "GB",
    "wof:name": "B77 4EY",
    "wof:placetype": "postalcode"
  },
  "geometry": {"coordinates":[-1.662382,52.626294],"type":"Point"}
}
