{
  "type": "Feature",
  "properties": {
    "iso:country": "GB",
    "wof:name": "B77 4EY",
    "wof:placetype": "postalcode"
  },
  "geometry": {"coordinates":[-1.662382,52.626294],"type":"Point"}
}
