{
  "type": "Feature",
  "properties": {
    "iso:country":"GB",
    "wof:name":"WF3 1SL",
    "wof:placetype":"postalcode"
},
  "geometry": {"coordinates":[-1.55761523595348,53.73686966133908],"type":"Point"}
}