{
  "type": "Feature",
  "properties": {
    "date:inception_lower": "1980-01-01",
    "date:inception_upper": "1980-01-01",
    "iso:country": "GB",
    "wof:name": "DN38 6BL",
    "wof:placetype": "postalcode"
  },
  "geometry": {"coordinates":[-0.360672,53.549638],"type":"Point"}
}
