{
  "type": "Feature",
  "properties": {
    "date:inception_lower": "1981-12-01",
    "date:inception_upper": "1981-12-01",
    "iso:country": "GB",
    "wof:name": "EX2 4DF",
    "wof:placetype": "postalcode"
  },
  "geometry": {"coordinates":[-3.527266,50.718126],"type":"Point"}
}
