{
  "type": "Feature",
  "properties": {
    "date:inception_lower": "1990-02-01",
    "date:inception_upper": "1990-02-01",
    "iso:country": "GB",
    "wof:name": "GL50 4JQ",
    "wof:placetype": "postalcode"
  },
  "geometry": {"coordinates":[-2.081947,51.904656],"type":"Point"}
}
