{
  "type": "Feature",
  "properties": {
    "iso:country": "GB",
    "wof:name": "NE70 7JB",
    "wof:placetype": "postalcode"
  },
  "geometry": {"coordinates":[-1.770772,55.568641],"type":"Point"}
}
