{
  "type": "Feature",
  "properties": {
    "iso:country":"GB",
    "wof:name":"NE70 7JB",
    "wof:placetype":"postalcode"
},
  "geometry": {"coordinates":[-1.77077184977328,55.56864083728506],"type":"Point"}
}