{
  "type": "Feature",
  "properties": {
    "date:inception_lower": "2018-10-01",
    "date:inception_upper": "2018-10-01",
    "iso:country": "GB",
    "wof:name": "G53 6EN",
    "wof:placetype": "postalcode"
  },
  "geometry": {"coordinates":[-4.349901,55.822188],"type":"Point"}
}
