{
  "type": "Feature",
  "properties": {
    "iso:country": "GB",
    "wof:name": "WD24 5BQ",
    "wof:placetype": "postalcode"
  },
  "geometry": {"coordinates":[-0.396989,51.671042],"type":"Point"}
}
