{
  "type": "Feature",
  "properties": {
    "iso:country":"GB",
    "wof:name":"WD24 5BQ",
    "wof:placetype":"postalcode"
},
  "geometry": {"coordinates":[-0.39698924565307,51.67104218477289],"type":"Point"}
}