{
  "type": "Feature",
  "properties": {
    "iso:country":"GB",
    "wof:name":"GU2 7AB",
    "wof:placetype":"postalcode"
},
  "geometry": {"coordinates":[-0.61379379817836,51.23961652463952],"type":"Point"}
}