{
  "type": "Feature",
  "properties": {
    "iso:country":"GB",
    "wof:name":"BB10 2ET",
    "wof:placetype":"postalcode"
},
  "geometry": {"coordinates":[-2.20955648246779,53.81193116923931],"type":"Point"}
}