{
  "type": "Feature",
  "properties": {
    "iso:country":"GB",
    "wof:name":"WA7 6JU",
    "wof:placetype":"postalcode"
},
  "geometry": {"coordinates":[-2.66353983258823,53.32785731088689],"type":"Point"}
}