{
  "type": "Feature",
  "properties": {
    "date:inception_lower":"1997-06-01",
    "date:inception_upper":"1997-06-30",
    "iso:country":"GB",
    "wof:name":"CM17 9QY",
    "wof:placetype":"postalcode"
},
  "geometry": {"coordinates":[0.135872,51.763591],"type":"Point"}
}