{
  "type": "Feature",
  "properties": {
    "iso:country":"GB",
    "wof:name":"CM17 9QY",
    "wof:placetype":"postalcode"
},
  "geometry": {"coordinates":[0.13587157984287,51.76359135552419],"type":"Point"}
}