{
  "type": "Feature",
  "properties": {
    "iso:country": "GB",
    "wof:name": "CM17 9QY",
    "wof:placetype": "postalcode"
  },
  "geometry": {"coordinates":[0.135872,51.763591],"type":"Point"}
}
