{
  "type": "Feature",
  "properties": {
    "iso:country":"GB",
    "wof:name":"LN5 9GL",
    "wof:placetype":"postalcode"
},
  "geometry": {"coordinates":[-0.64854490347452,53.10980949111382],"type":"Point"}
}