{
  "type": "Feature",
  "properties": {
    "iso:country": "GB",
    "wof:name": "LN5 9GL",
    "wof:placetype": "postalcode"
  },
  "geometry": {"coordinates":[-0.648545,53.109809],"type":"Point"}
}
