{
  "type": "Feature",
  "properties": {
    "date:inception_lower": "1999-12-01",
    "date:inception_upper": "1999-12-01",
    "iso:country": "GB",
    "wof:name": "LN5 9GL",
    "wof:placetype": "postalcode"
  },
  "geometry": {"coordinates":[-0.648545,53.109809],"type":"Point"}
}
