{
  "type": "Feature",
  "properties": {
    "date:inception_lower": "1980-01-01",
    "date:inception_upper": "1980-01-01",
    "iso:country": "GB",
    "wof:name": "CW1 2AS",
    "wof:placetype": "postalcode"
  },
  "geometry": {"coordinates":[-2.435982,53.098197],"type":"Point"}
}
