{
  "type": "Feature",
  "properties": {
    "iso:country":"GB",
    "wof:name":"KA7 3HL",
    "wof:placetype":"postalcode"
},
  "geometry": {"coordinates":[-4.60955263623024,55.45338421481672],"type":"Point"}
}