{
  "type": "Feature",
  "properties": {
    "date:inception_lower":"1980-01-01",
    "date:inception_upper":"1980-01-31",
    "iso:country":"GB",
    "wof:name":"KA7 3HL",
    "wof:placetype":"postalcode"
},
  "geometry": {"coordinates":[-4.609553,55.453384],"type":"Point"}
}