{
  "type": "Feature",
  "properties": {
    "iso:country": "GB",
    "wof:name": "BD23 4QY",
    "wof:placetype": "postalcode"
  },
  "geometry": {"coordinates":[-2.253133,54.018607],"type":"Point"}
}
