{
  "type": "Feature",
  "properties": {
    "date:inception_lower": "2004-01-01",
    "date:inception_upper": "2004-01-01",
    "iso:country": "GB",
    "wof:name": "BD23 4QY",
    "wof:placetype": "postalcode"
  },
  "geometry": {"coordinates":[-2.253026,54.018553],"type":"Point"}
}
