{
  "type": "Feature",
  "properties": {
    "date:inception_lower":"2004-01-01",
    "date:inception_upper":"2004-01-31",
    "iso:country":"GB",
    "wof:name":"BD23 4QY",
    "wof:placetype":"postalcode"
},
  "geometry": {"coordinates":[-2.253133,54.018607],"type":"Point"}
}