{
  "type": "Feature",
  "properties": {
    "iso:country":"GB",
    "wof:name":"TS23 3PH",
    "wof:placetype":"postalcode"
},
  "geometry": {"coordinates":[-1.27203216461439,54.61998267911837],"type":"Point"}
}