{
  "type": "Feature",
  "properties": {
    "iso:country":"GB",
    "wof:name":"N1 6AQ",
    "wof:placetype":"postalcode"
},
  "geometry": {"coordinates":[-0.08688416606277,51.53013750648955],"type":"Point"}
}