{
  "type": "Feature",
  "properties": {
    "date:inception_lower":"1980-01-01",
    "date:inception_upper":"1980-01-31",
    "iso:country":"GB",
    "wof:name":"BD21 3SL",
    "wof:placetype":"postalcode"
},
  "geometry": {"coordinates":[-1.909911,53.866161],"type":"Point"}
}