{
  "type": "Feature",
  "properties": {
    "iso:country": "GB",
    "wof:name": "BD21 3SL",
    "wof:placetype": "postalcode"
  },
  "geometry": {"coordinates":[-1.909911,53.866161],"type":"Point"}
}
