{
  "type": "Feature",
  "properties": {
    "iso:country":"GB",
    "wof:name":"BD21 3SL",
    "wof:placetype":"postalcode"
},
  "geometry": {"coordinates":[-1.90991080441443,53.86616121343171],"type":"Point"}
}