{
  "type": "Feature",
  "properties": {
    "iso:country":"GB",
    "wof:name":"W11 4EU",
    "wof:placetype":"postalcode"
},
  "geometry": {"coordinates":[-0.21261166715834,51.51336241573701],"type":"Point"}
}