{
  "type": "Feature",
  "properties": {
    "iso:country":"GB",
    "wof:name":"W5 3AP",
    "wof:placetype":"postalcode"
},
  "geometry": {"coordinates":[-0.28765510108007,51.51949068622663],"type":"Point"}
}