{
  "type": "Feature",
  "properties": {
    "iso:country":"GB",
    "wof:name":"TR2 5NJ",
    "wof:placetype":"postalcode"
},
  "geometry": {"coordinates":[-4.94349044700176,50.22192819000716],"type":"Point"}
}