{
  "type": "Feature",
  "properties": {
    "iso:country":"GB",
    "wof:name":"GU35 9DU",
    "wof:placetype":"postalcode"
},
  "geometry": {"coordinates":[-0.87389548559207,51.10178535724824],"type":"Point"}
}