{
  "type": "Feature",
  "properties": {
    "iso:country":"GB",
    "wof:name":"BH8 9SQ",
    "wof:placetype":"postalcode"
},
  "geometry": {"coordinates":[-1.86087309019604,50.74741986106119],"type":"Point"}
}