{
  "type": "Feature",
  "properties": {
    "date:inception_lower":"1980-01-01",
    "date:inception_upper":"1980-01-31",
    "iso:country":"GB",
    "wof:name":"BH8 9SQ",
    "wof:placetype":"postalcode"
},
  "geometry": {"coordinates":[-1.860879,50.747319],"type":"Point"}
}