{
  "type": "Feature",
  "properties": {
    "iso:country":"GB",
    "wof:name":"PE14 8DQ",
    "wof:placetype":"postalcode"
},
  "geometry": {"coordinates":[0.20844734599723,52.65446632247627],"type":"Point"}
}