{
  "type": "Feature",
  "properties": {
    "date:inception_lower":"1999-12-01",
    "date:inception_upper":"1999-12-31",
    "iso:country":"GB",
    "wof:name":"EX14 1HE",
    "wof:placetype":"postalcode"
},
  "geometry": {"coordinates":[-3.186381,50.798408],"type":"Point"}
}