{
  "type": "Feature",
  "properties": {
    "iso:country":"GB",
    "wof:name":"EX14 1HE",
    "wof:placetype":"postalcode"
},
  "geometry": {"coordinates":[-3.18638102098393,50.79840841719219],"type":"Point"}
}