{
  "type": "Feature",
  "properties": {
    "iso:country": "GB",
    "wof:name": "EX14 1HE",
    "wof:placetype": "postalcode"
  },
  "geometry": {"coordinates":[-3.186381,50.798408],"type":"Point"}
}
