{
  "type": "Feature",
  "properties": {
    "iso:country": "GB",
    "wof:name": "W1F 9QS",
    "wof:placetype": "postalcode"
  },
  "geometry": {"coordinates":[-0.137195,51.513054],"type":"Point"}
}
