{
  "type": "Feature",
  "properties": {
    "date:inception_lower": "2000-10-01",
    "date:inception_upper": "2000-10-01",
    "iso:country": "GB",
    "wof:name": "W1F 9QS",
    "wof:placetype": "postalcode"
  },
  "geometry": {"coordinates":[-0.137195,51.513054],"type":"Point"}
}
