{
  "type": "Feature",
  "properties": {
    "iso:country": "GB",
    "wof:name": "TF1 2LY",
    "wof:placetype": "postalcode"
  },
  "geometry": {"coordinates":[-2.495876,52.690076],"type":"Point"}
}
