{
  "type": "Feature",
  "properties": {
    "iso:country":"GB",
    "wof:name":"TF1 2LY",
    "wof:placetype":"postalcode"
},
  "geometry": {"coordinates":[-2.49587607180562,52.69007643570517],"type":"Point"}
}