{
  "type": "Feature",
  "properties": {
    "iso:country":"GB",
    "wof:name":"SW19 8BF",
    "wof:placetype":"postalcode"
},
  "geometry": {"coordinates":[-0.18936763617464,51.42819753252651],"type":"Point"}
}