{
  "type": "Feature",
  "properties": {
    "iso:country": "GB",
    "wof:name": "M43 7GN",
    "wof:placetype": "postalcode"
  },
  "geometry": {"coordinates":[-2.13347,53.486632],"type":"Point"}
}
