{
  "type": "Feature",
  "properties": {
    "iso:country":"GB",
    "wof:name":"DD3 8DN",
    "wof:placetype":"postalcode"
},
  "geometry": {"coordinates":[-2.98967871048829,56.47553846589994],"type":"Point"}
}