{
  "type": "Feature",
  "properties": {
    "date:inception_lower": "1980-01-01",
    "date:inception_upper": "1980-01-01",
    "iso:country": "GB",
    "wof:name": "CF47 9HR",
    "wof:placetype": "postalcode"
  },
  "geometry": {"coordinates":[-3.36535,51.757329],"type":"Point"}
}
