{
  "type": "Feature",
  "properties": {
    "iso:country":"GB",
    "wof:name":"BR1 4DZ",
    "wof:placetype":"postalcode"
},
  "geometry": {"coordinates":[0.02112362895957,51.41559300055801],"type":"Point"}
}