{
  "type": "Feature",
  "properties": {
    "iso:country": "GB",
    "wof:name": "BR1 4DZ",
    "wof:placetype": "postalcode"
  },
  "geometry": {"coordinates":[0.021124,51.415593],"type":"Point"}
}
