{
  "type": "Feature",
  "properties": {
    "iso:country":"GB",
    "wof:name":"PE15 8UF",
    "wof:placetype":"postalcode"
},
  "geometry": {"coordinates":[0.0819585635315,52.56293228721919],"type":"Point"}
}