{
  "type": "Feature",
  "properties": {
    "iso:country": "GB",
    "wof:name": "PE15 8UF",
    "wof:placetype": "postalcode"
  },
  "geometry": {"coordinates":[0.081959,52.562932],"type":"Point"}
}
