{
  "type": "Feature",
  "properties": {
    "iso:country":"GB",
    "wof:name":"NP4 8JT",
    "wof:placetype":"postalcode"
},
  "geometry": {"coordinates":[-3.03494846571226,51.70775309961927],"type":"Point"}
}