{
  "type": "Feature",
  "properties": {
    "iso:country":"GB",
    "wof:name":"PR2 8EE",
    "wof:placetype":"postalcode"
},
  "geometry": {"coordinates":[-2.69772313801192,53.78155546496281],"type":"Point"}
}