{
  "type": "Feature",
  "properties": {
    "iso:country":"GB",
    "wof:name":"LN6 5SH",
    "wof:placetype":"postalcode"
},
  "geometry": {"coordinates":[-0.61893206263789,53.23197143782601],"type":"Point"}
}