{
  "type": "Feature",
  "properties": {
    "iso:country":"GB",
    "wof:name":"MK16 0NR",
    "wof:placetype":"postalcode"
},
  "geometry": {"coordinates":[-0.73226789370587,52.07843957887842],"type":"Point"}
}