{
  "type": "Feature",
  "properties": {
    "iso:country": "GB",
    "wof:name": "MK16 0NR",
    "wof:placetype": "postalcode"
  },
  "geometry": {"coordinates":[-0.732268,52.07844],"type":"Point"}
}
