{
  "type": "Feature",
  "properties": {
    "iso:country":"GB",
    "wof:name":"AB56 1AS",
    "wof:placetype":"postalcode"
},
  "geometry": {"coordinates":[-2.96365363960188,57.6745731771269],"type":"Point"}
}