{
  "type": "Feature",
  "properties": {
    "date:inception_lower": "1990-08-01",
    "date:inception_upper": "1990-08-01",
    "iso:country": "GB",
    "wof:name": "AB56 1AS",
    "wof:placetype": "postalcode"
  },
  "geometry": {"coordinates":[-2.963654,57.674573],"type":"Point"}
}
