{
  "type": "Feature",
  "properties": {
    "iso:country": "GB",
    "wof:name": "S42 6HF",
    "wof:placetype": "postalcode"
  },
  "geometry": {"coordinates":[-1.430338,53.179104],"type":"Point"}
}
