{
  "type": "Feature",
  "properties": {
    "iso:country":"GB",
    "wof:name":"S42 6HF",
    "wof:placetype":"postalcode"
},
  "geometry": {"coordinates":[-1.43036953539154,53.17909354118075],"type":"Point"}
}