{
  "type": "Feature",
  "properties": {
    "iso:country":"GB",
    "wof:name":"SR6 9RH",
    "wof:placetype":"postalcode"
},
  "geometry": {"coordinates":[-1.38114816249217,54.92479693728332],"type":"Point"}
}