{
  "type": "Feature",
  "properties": {
    "iso:country": "GB",
    "wof:name": "LS24 8JS",
    "wof:placetype": "postalcode"
  },
  "geometry": {"coordinates":[-1.245015,53.890768],"type":"Point"}
}
