{
  "type": "Feature",
  "properties": {
    "iso:country":"GB",
    "wof:name":"LS24 8JS",
    "wof:placetype":"postalcode"
},
  "geometry": {"coordinates":[-1.24501541075359,53.89076813732001],"type":"Point"}
}