{
  "type": "Feature",
  "properties": {
    "date:inception_lower": "1980-01-01",
    "date:inception_upper": "1980-01-01",
    "iso:country": "GB",
    "wof:name": "LA7 7PB",
    "wof:placetype": "postalcode"
  },
  "geometry": {"coordinates":[-2.695895,54.256456],"type":"Point"}
}
