{
  "type": "Feature",
  "properties": {
    "iso:country": "GB",
    "wof:name": "LA7 7PB",
    "wof:placetype": "postalcode"
  },
  "geometry": {"coordinates":[-2.695895,54.256456],"type":"Point"}
}
