{
  "type": "Feature",
  "properties": {
    "iso:country":"GB",
    "wof:name":"BS15 4QW",
    "wof:placetype":"postalcode"
},
  "geometry": {"coordinates":[-2.49766959889663,51.47077442457481],"type":"Point"}
}