{
  "type": "Feature",
  "properties": {
    "iso:country": "GB",
    "wof:name": "BS15 4QW",
    "wof:placetype": "postalcode"
  },
  "geometry": {"coordinates":[-2.49767,51.470774],"type":"Point"}
}
