{
  "type": "Feature",
  "properties": {
    "date:inception_lower": "2016-11-01",
    "date:inception_upper": "2016-11-01",
    "iso:country": "GB",
    "wof:name": "HU13 0FH",
    "wof:placetype": "postalcode"
  },
  "geometry": {"coordinates":[-0.460704,53.730482],"type":"Point"}
}
