{
  "type": "Feature",
  "properties": {
    "date:inception_lower": "2004-10-01",
    "date:inception_upper": "2004-10-01",
    "iso:country": "GB",
    "wof:name": "WF17 6GH",
    "wof:placetype": "postalcode"
  },
  "geometry": {"coordinates":[-1.611611,53.707585],"type":"Point"}
}
