{
  "type": "Feature",
  "properties": {
    "date:inception_lower": "1980-01-01",
    "date:inception_upper": "1980-01-01",
    "iso:country": "GB",
    "wof:name": "SO22 6JS",
    "wof:placetype": "postalcode"
  },
  "geometry": {"coordinates":[-1.332915,51.084146],"type":"Point"}
}
