{
  "type": "Feature",
  "properties": {
    "iso:country":"GB",
    "wof:name":"PR2 6XT",
    "wof:placetype":"postalcode"
},
  "geometry": {"coordinates":[-2.6764509725127,53.77902589435617],"type":"Point"}
}