{
  "type": "Feature",
  "properties": {
    "iso:country":"GB",
    "wof:name":"CV12 8BU",
    "wof:placetype":"postalcode"
},
  "geometry": {"coordinates":[-1.47377188200721,52.48264091227986],"type":"Point"}
}