{
  "type": "Feature",
  "properties": {
    "iso:country": "GB",
    "wof:name": "CV12 8BU",
    "wof:placetype": "postalcode"
  },
  "geometry": {"coordinates":[-1.473772,52.482641],"type":"Point"}
}
