{
  "type": "Feature",
  "properties": {
    "iso:country": "GB",
    "wof:name": "WV16 6NG",
    "wof:placetype": "postalcode"
  },
  "geometry": {"coordinates":[-2.380562,52.446086],"type":"Point"}
}
