{
  "type": "Feature",
  "properties": {
    "iso:country":"GB",
    "wof:name":"WV16 6NG",
    "wof:placetype":"postalcode"
},
  "geometry": {"coordinates":[-2.38056188868029,52.44608623113405],"type":"Point"}
}