{
  "type": "Feature",
  "properties": {
    "iso:country": "GB",
    "wof:name": "GU15 4LT",
    "wof:placetype": "postalcode"
  },
  "geometry": {"coordinates":[-0.749424,51.349582],"type":"Point"}
}
