{
  "type": "Feature",
  "properties": {
    "iso:country":"GB",
    "wof:name":"GU15 4LT",
    "wof:placetype":"postalcode"
},
  "geometry": {"coordinates":[-0.74942354621388,51.34958153850677],"type":"Point"}
}