{
  "type": "Feature",
  "properties": {
    "iso:country": "GB",
    "wof:name": "G81 1QG",
    "wof:placetype": "postalcode"
  },
  "geometry": {"coordinates":[-4.401014,55.896927],"type":"Point"}
}
