{
  "type": "Feature",
  "properties": {
    "date:inception_lower": "1980-01-01",
    "date:inception_upper": "1980-01-01",
    "iso:country": "GB",
    "wof:name": "G81 1QG",
    "wof:placetype": "postalcode"
  },
  "geometry": {"coordinates":[-4.401014,55.896927],"type":"Point"}
}
