{
  "type": "Feature",
  "properties": {
    "date:inception_lower":"2016-10-01",
    "date:inception_upper":"2016-10-31",
    "iso:country":"GB",
    "wof:name":"CF10 4LZ",
    "wof:placetype":"postalcode"
},
  "geometry": {"coordinates":[-3.138312,51.468364],"type":"Point"}
}