{
  "type": "Feature",
  "properties": {
    "iso:country": "GB",
    "wof:name": "PO6 4JH",
    "wof:placetype": "postalcode"
  },
  "geometry": {"coordinates":[-1.109839,50.85158],"type":"Point"}
}
