{
  "type": "Feature",
  "properties": {
    "iso:country":"GB",
    "wof:name":"CV32 5PW",
    "wof:placetype":"postalcode"
},
  "geometry": {"coordinates":[-1.53712666555286,52.29218804066471],"type":"Point"}
}