{
  "type": "Feature",
  "properties": {
    "iso:country":"GB",
    "wof:name":"HX7 6JJ",
    "wof:placetype":"postalcode"
},
  "geometry": {"coordinates":[-2.02434700946589,53.72363427074903],"type":"Point"}
}