{
  "type": "Feature",
  "properties": {
    "iso:country":"GB",
    "wof:name":"RG31 7QG",
    "wof:placetype":"postalcode"
},
  "geometry": {"coordinates":[-1.03165930356234,51.4401857749554],"type":"Point"}
}