{
  "type": "Feature",
  "properties": {
    "date:inception_lower":"2007-07-01",
    "date:inception_upper":"2007-07-31",
    "iso:country":"GB",
    "wof:name":"BB1 2EJ",
    "wof:placetype":"postalcode"
},
  "geometry": {"coordinates":[-2.442856,53.735455],"type":"Point"}
}