{
  "type": "Feature",
  "properties": {
    "iso:country":"GB",
    "wof:name":"BB1 2EJ",
    "wof:placetype":"postalcode"
},
  "geometry": {"coordinates":[-2.44285622865866,53.73545484319226],"type":"Point"}
}