{
  "type": "Feature",
  "properties": {
    "iso:country":"GB",
    "wof:name":"KY8 6DH",
    "wof:placetype":"postalcode"
},
  "geometry": {"coordinates":[-2.94642259104028,56.2165430318632],"type":"Point"}
}