{
  "type": "Feature",
  "properties": {
    "iso:country":"GB",
    "wof:name":"CA7 8PG",
    "wof:placetype":"postalcode"
},
  "geometry": {"coordinates":[-3.18887675716021,54.78779778415303],"type":"Point"}
}