{
  "type": "Feature",
  "properties": {
    "iso:country": "GB",
    "wof:name": "CA7 8PG",
    "wof:placetype": "postalcode"
  },
  "geometry": {"coordinates":[-3.188877,54.787798],"type":"Point"}
}
