{
  "type": "Feature",
  "properties": {
    "iso:country":"GB",
    "wof:name":"TQ13 8BD",
    "wof:placetype":"postalcode"
},
  "geometry": {"coordinates":[-3.83942625303762,50.67012368254176],"type":"Point"}
}