{
  "type": "Feature",
  "properties": {
    "iso:country": "GB",
    "wof:name": "LE17 5LR",
    "wof:placetype": "postalcode"
  },
  "geometry": {"coordinates":[-1.160644,52.486265],"type":"Point"}
}
