{
  "type": "Feature",
  "properties": {
    "date:inception_lower": "1980-01-01",
    "date:inception_upper": "1980-01-01",
    "iso:country": "GB",
    "wof:name": "CA26 3SB",
    "wof:placetype": "postalcode"
  },
  "geometry": {"coordinates":[-3.493884,54.541336],"type":"Point"}
}
