{
  "type": "Feature",
  "properties": {
    "iso:country":"GB",
    "wof:name":"CA26 3SB",
    "wof:placetype":"postalcode"
},
  "geometry": {"coordinates":[-3.49388427407083,54.54133551266962],"type":"Point"}
}