{
  "type": "Feature",
  "properties": {
    "iso:country":"GB",
    "wof:name":"BN16 1HX",
    "wof:placetype":"postalcode"
},
  "geometry": {"coordinates":[-0.48453889607019,50.81350691985511],"type":"Point"}
}