{
  "type": "Feature",
  "properties": {
    "iso:country": "GB",
    "wof:name": "BN16 1HX",
    "wof:placetype": "postalcode"
  },
  "geometry": {"coordinates":[-0.484539,50.813507],"type":"Point"}
}
