{
  "type": "Feature",
  "properties": {
    "iso:country":"GB",
    "wof:name":"SW9 8JN",
    "wof:placetype":"postalcode"
},
  "geometry": {"coordinates":[-0.11246618796639,51.46200163732698],"type":"Point"}
}