{
  "type": "Feature",
  "properties": {
    "date:inception_lower": "2024-09-01",
    "date:inception_upper": "2024-09-01",
    "iso:country": "GB",
    "wof:name": "LN6 6AQ",
    "wof:placetype": "postalcode"
  },
  "geometry": {"coordinates":[-0.669741,53.154847],"type":"Point"}
}
