{
  "type": "Feature",
  "properties": {
    "iso:country":"GB",
    "wof:name":"CH4 9BU",
    "wof:placetype":"postalcode"
},
  "geometry": {"coordinates":[-3.00000965622871,53.14544837999088],"type":"Point"}
}