{
  "type": "Feature",
  "properties": {
    "date:inception_lower": "1980-01-01",
    "date:inception_upper": "1980-01-01",
    "iso:country": "GB",
    "wof:name": "CH4 9BU",
    "wof:placetype": "postalcode"
  },
  "geometry": {"coordinates":[-3.00001,53.145448],"type":"Point"}
}
