{
  "type": "Feature",
  "properties": {
    "iso:country":"GB",
    "wof:name":"SN12 8FH",
    "wof:placetype":"postalcode"
},
  "geometry": {"coordinates":[-2.14486572483189,51.37829218544304],"type":"Point"}
}