{
  "type": "Feature",
  "properties": {
    "date:inception_lower": "2013-04-01",
    "date:inception_upper": "2013-04-01",
    "iso:country": "GB",
    "wof:name": "SN12 8FH",
    "wof:placetype": "postalcode"
  },
  "geometry": {"coordinates":[-2.144866,51.378292],"type":"Point"}
}
