{
  "type": "Feature",
  "properties": {
    "iso:country": "GB",
    "wof:name": "EH52 6DH",
    "wof:placetype": "postalcode"
  },
  "geometry": {"coordinates":[-3.498878,55.932065],"type":"Point"}
}
