{
  "type": "Feature",
  "properties": {
    "date:inception_lower":"1980-01-01",
    "date:inception_upper":"1980-01-31",
    "iso:country":"GB",
    "wof:name":"EH52 6DH",
    "wof:placetype":"postalcode"
},
  "geometry": {"coordinates":[-3.498878,55.932065],"type":"Point"}
}