{
  "type": "Feature",
  "properties": {
    "date:inception_lower": "1998-06-01",
    "date:inception_upper": "1998-06-01",
    "iso:country": "GB",
    "wof:name": "OX10 8HH",
    "wof:placetype": "postalcode"
  },
  "geometry": {"coordinates":[-1.127707,51.604956],"type":"Point"}
}
