{
  "type": "Feature",
  "properties": {
    "iso:country":"GB",
    "wof:name":"OX10 8HH",
    "wof:placetype":"postalcode"
},
  "geometry": {"coordinates":[-1.12770678992663,51.60495647069315],"type":"Point"}
}