{
  "type": "Feature",
  "properties": {
    "date:inception_lower": "2019-09-01",
    "date:inception_upper": "2019-09-01",
    "iso:country": "GB",
    "wof:name": "BN18 0GD",
    "wof:placetype": "postalcode"
  },
  "geometry": {"coordinates":[-0.613675,50.838459],"type":"Point"}
}
