{
  "type": "Feature",
  "properties": {
    "iso:country": "GB",
    "wof:name": "SM6 8QH",
    "wof:placetype": "postalcode"
  },
  "geometry": {"coordinates":[-0.130556,51.362374],"type":"Point"}
}
