{
  "type": "Feature",
  "properties": {
    "date:inception_lower": "1999-12-01",
    "date:inception_upper": "1999-12-01",
    "iso:country": "GB",
    "wof:name": "SM6 8QH",
    "wof:placetype": "postalcode"
  },
  "geometry": {"coordinates":[-0.130556,51.362374],"type":"Point"}
}
