{
  "type": "Feature",
  "properties": {
    "iso:country":"GB",
    "wof:name":"BR6 6JN",
    "wof:placetype":"postalcode"
},
  "geometry": {"coordinates":[0.10214604639543,51.36000288979751],"type":"Point"}
}