{
  "type": "Feature",
  "properties": {
    "iso:country":"GB",
    "wof:name":"SS5 4JQ",
    "wof:placetype":"postalcode"
},
  "geometry": {"coordinates":[0.65577689537935,51.5908747457881],"type":"Point"}
}