{
  "type": "Feature",
  "properties": {
    "date:inception_lower": "1980-01-01",
    "date:inception_upper": "1980-01-01",
    "iso:country": "GB",
    "wof:name": "HU12 8LE",
    "wof:placetype": "postalcode"
  },
  "geometry": {"coordinates":[-0.19256,53.740715],"type":"Point"}
}
