{
  "type": "Feature",
  "properties": {
    "iso:country":"GB",
    "wof:name":"EC1R 4PX",
    "wof:placetype":"postalcode"
},
  "geometry": {"coordinates":[-0.11024670606684,51.52511169966031],"type":"Point"}
}