{
  "type": "Feature",
  "properties": {
    "iso:country": "GB",
    "wof:name": "SK11 9AD",
    "wof:placetype": "postalcode"
  },
  "geometry": {"coordinates":[-2.271773,53.253457],"type":"Point"}
}
