{
  "type": "Feature",
  "properties": {
    "iso:country":"GB",
    "wof:name":"SK11 9AD",
    "wof:placetype":"postalcode"
},
  "geometry": {"coordinates":[-2.27177338488504,53.25345666303095],"type":"Point"}
}