{
  "type": "Feature",
  "properties": {
    "iso:country":"GB",
    "wof:name":"SY13 1WB",
    "wof:placetype":"postalcode"
},
  "geometry": {"coordinates":[-2.68838152083669,52.96474469733228],"type":"Point"}
}