{
  "type": "Feature",
  "properties": {
    "iso:country": "GB",
    "wof:name": "SY13 1WB",
    "wof:placetype": "postalcode"
  },
  "geometry": {"coordinates":[-2.688381,52.964745],"type":"Point"}
}
