{
  "type": "Feature",
  "properties": {
    "iso:country":"GB",
    "wof:name":"S74 0HA",
    "wof:placetype":"postalcode"
},
  "geometry": {"coordinates":[-1.4475870420005,53.50499031715388],"type":"Point"}
}