{
  "type": "Feature",
  "properties": {
    "iso:country":"GB",
    "wof:name":"PH14 9TA",
    "wof:placetype":"postalcode"
},
  "geometry": {"coordinates":[-3.21366961321594,56.4903971033285],"type":"Point"}
}