{
  "type": "Feature",
  "properties": {
    "iso:country":"GB",
    "wof:name":"RG42 6HS",
    "wof:placetype":"postalcode"
},
  "geometry": {"coordinates":[-0.72560380977394,51.45035121264004],"type":"Point"}
}