{
  "type": "Feature",
  "properties": {
    "iso:country":"GB",
    "wof:name":"HP19 7RE",
    "wof:placetype":"postalcode"
},
  "geometry": {"coordinates":[-0.82963952174059,51.816947733055],"type":"Point"}
}