{
  "type": "Feature",
  "properties": {
    "iso:country":"GB",
    "wof:name":"PE10 0WT",
    "wof:placetype":"postalcode"
},
  "geometry": {"coordinates":[-0.37522389023144,52.76058285483783],"type":"Point"}
}