{
  "type": "Feature",
  "properties": {
    "iso:country": "GB",
    "wof:name": "PE10 0WT",
    "wof:placetype": "postalcode"
  },
  "geometry": {"coordinates":[-0.375414,52.760804],"type":"Point"}
}
