{
  "type": "Feature",
  "properties": {
    "iso:country":"GB",
    "wof:name":"RG31 6UA",
    "wof:placetype":"postalcode"
},
  "geometry": {"coordinates":[-1.05296335140082,51.46961010821901],"type":"Point"}
}