{
  "type": "Feature",
  "properties": {
    "date:inception_lower": "2005-01-01",
    "date:inception_upper": "2005-01-01",
    "iso:country": "GB",
    "wof:name": "RG31 6UA",
    "wof:placetype": "postalcode"
  },
  "geometry": {"coordinates":[-1.052963,51.46961],"type":"Point"}
}
