{
  "type": "Feature",
  "properties": {
    "iso:country":"GB",
    "wof:name":"PE4 7AX",
    "wof:placetype":"postalcode"
},
  "geometry": {"coordinates":[-0.24050766136034,52.61151824115554],"type":"Point"}
}