{
  "type": "Feature",
  "properties": {
    "iso:country": "GB",
    "wof:name": "PE4 7AX",
    "wof:placetype": "postalcode"
  },
  "geometry": {"coordinates":[-0.240508,52.611518],"type":"Point"}
}
