{
  "type": "Feature",
  "properties": {
    "iso:country": "GB",
    "wof:name": "SE18 3TE",
    "wof:placetype": "postalcode"
  },
  "geometry": {"coordinates":[0.068584,51.481519],"type":"Point"}
}
