{
  "type": "Feature",
  "properties": {
    "iso:country":"GB",
    "wof:name":"CW8 3ES",
    "wof:placetype":"postalcode"
},
  "geometry": {"coordinates":[-2.56703516154987,53.25608484491324],"type":"Point"}
}