{
  "type": "Feature",
  "properties": {
    "date:inception_lower": "1999-06-01",
    "date:inception_upper": "1999-06-01",
    "iso:country": "GB",
    "wof:name": "NE12 6FB",
    "wof:placetype": "postalcode"
  },
  "geometry": {"coordinates":[-1.550178,55.033959],"type":"Point"}
}
