{
  "type": "Feature",
  "properties": {
    "iso:country": "GB",
    "wof:name": "NE12 6FB",
    "wof:placetype": "postalcode"
  },
  "geometry": {"coordinates":[-1.550178,55.033959],"type":"Point"}
}
