{
  "type": "Feature",
  "properties": {
    "date:inception_lower":"1980-01-01",
    "date:inception_upper":"1980-01-31",
    "iso:country":"GB",
    "wof:name":"TN32 5JR",
    "wof:placetype":"postalcode"
},
  "geometry": {"coordinates":[0.46968,50.955643],"type":"Point"}
}