{
  "type": "Feature",
  "properties": {
    "date:inception_lower": "2021-11-01",
    "date:inception_upper": "2021-11-01",
    "iso:country": "GB",
    "wof:name": "IV2 6HQ",
    "wof:placetype": "postalcode"
  },
  "geometry": {"coordinates":[-4.245514,57.456241],"type":"Point"}
}
