{
  "type": "Feature",
  "properties": {
    "date:inception_lower": "2000-12-01",
    "date:inception_upper": "2000-12-01",
    "iso:country": "GB",
    "wof:name": "PR1 8JW",
    "wof:placetype": "postalcode"
  },
  "geometry": {"coordinates":[-2.714713,53.754329],"type":"Point"}
}
