{
  "type": "Feature",
  "properties": {
    "date:inception_lower": "2012-02-01",
    "date:inception_upper": "2012-02-01",
    "iso:country": "GB",
    "wof:name": "YO18 7AR",
    "wof:placetype": "postalcode"
  },
  "geometry": {"coordinates":[-0.72969,54.230816],"type":"Point"}
}
