{
  "type": "Feature",
  "properties": {
    "iso:country": "GB",
    "wof:name": "CF82 7SA",
    "wof:placetype": "postalcode"
  },
  "geometry": {"coordinates":[-3.220721,51.644871],"type":"Point"}
}
