{
  "type": "Feature",
  "properties": {
    "iso:country": "GB",
    "wof:name": "HR1 4TH",
    "wof:placetype": "postalcode"
  },
  "geometry": {"coordinates":[-2.592742,51.982571],"type":"Point"}
}
