{
  "type": "Feature",
  "properties": {
    "iso:country":"GB",
    "wof:name":"HR1 4TH",
    "wof:placetype":"postalcode"
},
  "geometry": {"coordinates":[-2.59280054201234,51.98266096891874],"type":"Point"}
}