{
  "type": "Feature",
  "properties": {
    "date:inception_lower":"2011-09-01",
    "date:inception_upper":"2011-09-30",
    "iso:country":"GB",
    "wof:name":"HR1 4TH",
    "wof:placetype":"postalcode"
},
  "geometry": {"coordinates":[-2.592742,51.982571],"type":"Point"}
}