{
  "type": "Feature",
  "properties": {
    "iso:country":"GB",
    "wof:name":"OX20 1JH",
    "wof:placetype":"postalcode"
},
  "geometry": {"coordinates":[-1.34899438249762,51.84896651647193],"type":"Point"}
}