{
  "type": "Feature",
  "properties": {
    "iso:country":"GB",
    "wof:name":"HG5 8NG",
    "wof:placetype":"postalcode"
},
  "geometry": {"coordinates":[-1.45360993810381,53.99902451791117],"type":"Point"}
}