{
  "type": "Feature",
  "properties": {
    "iso:country": "GB",
    "wof:name": "HG5 8NG",
    "wof:placetype": "postalcode"
  },
  "geometry": {"coordinates":[-1.45361,53.999025],"type":"Point"}
}
