{
  "type": "Feature",
  "properties": {
    "date:inception_lower": "1987-04-01",
    "date:inception_upper": "1987-04-01",
    "iso:country": "GB",
    "wof:name": "HG5 8NG",
    "wof:placetype": "postalcode"
  },
  "geometry": {"coordinates":[-1.45361,53.999025],"type":"Point"}
}
