{
  "type": "Feature",
  "properties": {
    "iso:country":"GB",
    "wof:name":"GL14 2QR",
    "wof:placetype":"postalcode"
},
  "geometry": {"coordinates":[-2.4966860027634,51.82593544055702],"type":"Point"}
}