{
  "type": "Feature",
  "properties": {
    "iso:country":"GB",
    "wof:name":"PL24 2LW",
    "wof:placetype":"postalcode"
},
  "geometry": {"coordinates":[-4.71529591986934,50.35394377877171],"type":"Point"}
}