{
  "type": "Feature",
  "properties": {
    "iso:country":"GB",
    "wof:name":"SG6 3JT",
    "wof:placetype":"postalcode"
},
  "geometry": {"coordinates":[-0.22671202700213,51.9697362532647],"type":"Point"}
}