{
  "type": "Feature",
  "properties": {
    "iso:country":"GB",
    "wof:name":"M20 3JG",
    "wof:placetype":"postalcode"
},
  "geometry": {"coordinates":[-2.23524614767061,53.42508318810938],"type":"Point"}
}