{
  "type": "Feature",
  "properties": {
    "date:inception_lower": "1994-05-01",
    "date:inception_upper": "1994-05-01",
    "iso:country": "GB",
    "wof:name": "M20 3JG",
    "wof:placetype": "postalcode"
  },
  "geometry": {"coordinates":[-2.235246,53.425083],"type":"Point"}
}
