{
  "type": "Feature",
  "properties": {
    "iso:country":"GB",
    "wof:name":"CO2 0NE",
    "wof:placetype":"postalcode"
},
  "geometry": {"coordinates":[0.82213947682699,51.84030593282282],"type":"Point"}
}