{
  "type": "Feature",
  "properties": {
    "date:inception_lower":"1980-01-01",
    "date:inception_upper":"1980-01-31",
    "iso:country":"GB",
    "wof:name":"CO2 0NE",
    "wof:placetype":"postalcode"
},
  "geometry": {"coordinates":[0.822168,51.840316],"type":"Point"}
}