{
  "type": "Feature",
  "properties": {
    "date:inception_lower":"1980-01-01",
    "date:inception_upper":"1980-01-31",
    "iso:country":"GB",
    "wof:name":"WV12 4LB",
    "wof:placetype":"postalcode"
},
  "geometry": {"coordinates":[-2.050077,52.596047],"type":"Point"}
}