{
  "type": "Feature",
  "properties": {
    "iso:country": "GB",
    "wof:name": "DT1 1AA",
    "wof:placetype": "postalcode"
  },
  "geometry": {"coordinates":[-2.444281,50.71528],"type":"Point"}
}
