{
  "type": "Feature",
  "properties": {
    "iso:country":"GB",
    "wof:name":"S36 9PT",
    "wof:placetype":"postalcode"
},
  "geometry": {"coordinates":[-1.64796997752166,53.52754482394467],"type":"Point"}
}