{
  "type": "Feature",
  "properties": {
    "iso:country": "GB",
    "wof:name": "SK16 4DL",
    "wof:placetype": "postalcode"
  },
  "geometry": {"coordinates":[-2.082183,53.47758],"type":"Point"}
}
