{
  "type": "Feature",
  "properties": {
    "iso:country":"GB",
    "wof:name":"SK16 4DL",
    "wof:placetype":"postalcode"
},
  "geometry": {"coordinates":[-2.08239383300447,53.47758174839219],"type":"Point"}
}