{
  "type": "Feature",
  "properties": {
    "iso:country":"GB",
    "wof:name":"BA1 5BU",
    "wof:placetype":"postalcode"
},
  "geometry": {"coordinates":[-2.3588299754518,51.38889162506097],"type":"Point"}
}