{
  "type": "Feature",
  "properties": {
    "iso:country":"GB",
    "wof:name":"NR34 8AX",
    "wof:placetype":"postalcode"
},
  "geometry": {"coordinates":[1.62353232842672,52.35652219286366],"type":"Point"}
}