{
  "type": "Feature",
  "properties": {
    "iso:country": "GB",
    "wof:name": "NR34 8AX",
    "wof:placetype": "postalcode"
  },
  "geometry": {"coordinates":[1.623532,52.356522],"type":"Point"}
}
