{
  "type": "Feature",
  "properties": {
    "iso:country":"GB",
    "wof:name":"KT6 5BQ",
    "wof:placetype":"postalcode"
},
  "geometry": {"coordinates":[-0.30176753749141,51.38097879716837],"type":"Point"}
}