{
  "type": "Feature",
  "properties": {
    "date:inception_lower": "1981-09-01",
    "date:inception_upper": "1981-09-01",
    "iso:country": "GB",
    "wof:name": "KT6 5BQ",
    "wof:placetype": "postalcode"
  },
  "geometry": {"coordinates":[-0.301697,51.381085],"type":"Point"}
}
