{
  "type": "Feature",
  "properties": {
    "date:inception_lower": "1991-01-01",
    "date:inception_upper": "1991-01-01",
    "iso:country": "GB",
    "wof:name": "NW10 0UR",
    "wof:placetype": "postalcode"
  },
  "geometry": {"coordinates":[-0.253105,51.553892],"type":"Point"}
}
