{
  "type": "Feature",
  "properties": {
    "iso:country":"GB",
    "wof:name":"NW10 0UR",
    "wof:placetype":"postalcode"
},
  "geometry": {"coordinates":[-0.2526748118437,51.5537032872335],"type":"Point"}
}