{
  "type": "Feature",
  "properties": {
    "date:inception_lower": "1980-01-01",
    "date:inception_upper": "1980-01-01",
    "iso:country": "GB",
    "wof:name": "TA2 6AF",
    "wof:placetype": "postalcode"
  },
  "geometry": {"coordinates":[-3.118411,51.025661],"type":"Point"}
}
