{
  "type": "Feature",
  "properties": {
    "iso:country": "GB",
    "wof:name": "TA2 6AF",
    "wof:placetype": "postalcode"
  },
  "geometry": {"coordinates":[-3.118411,51.025661],"type":"Point"}
}
