{
  "type": "Feature",
  "properties": {
    "iso:country":"GB",
    "wof:name":"TA2 6AF",
    "wof:placetype":"postalcode"
},
  "geometry": {"coordinates":[-3.11841135015378,51.0256606788008],"type":"Point"}
}