{
  "type": "Feature",
  "properties": {
    "date:inception_lower": "2021-05-01",
    "date:inception_upper": "2021-05-01",
    "iso:country": "GB",
    "wof:name": "DN18 5FT",
    "wof:placetype": "postalcode"
  },
  "geometry": {"coordinates":[-0.438004,53.684865],"type":"Point"}
}
