{
  "type": "Feature",
  "properties": {
    "date:inception_lower": "1980-01-01",
    "date:inception_upper": "1980-01-01",
    "iso:country": "GB",
    "wof:name": "CO7 8SP",
    "wof:placetype": "postalcode"
  },
  "geometry": {"coordinates":[1.073773,51.891461],"type":"Point"}
}
