{
  "type": "Feature",
  "properties": {
    "iso:country":"GB",
    "wof:name":"CO7 8SP",
    "wof:placetype":"postalcode"
},
  "geometry": {"coordinates":[1.07345764819553,51.89153746265882],"type":"Point"}
}