{
  "type": "Feature",
  "properties": {
    "iso:country": "GB",
    "wof:name": "M8 0QZ",
    "wof:placetype": "postalcode"
  },
  "geometry": {"coordinates":[-2.230877,53.502382],"type":"Point"}
}
