{
  "type": "Feature",
  "properties": {
    "iso:country":"GB",
    "wof:name":"M8 0QZ",
    "wof:placetype":"postalcode"
},
  "geometry": {"coordinates":[-2.2308803227901,53.5024106344731],"type":"Point"}
}