{
  "type": "Feature",
  "properties": {
    "iso:country":"GB",
    "wof:name":"SP2 0LR",
    "wof:placetype":"postalcode"
},
  "geometry": {"coordinates":[-1.87230372059551,51.07324484169549],"type":"Point"}
}