{
  "type": "Feature",
  "properties": {
    "date:inception_lower":"1980-01-01",
    "date:inception_upper":"1980-01-31",
    "iso:country":"GB",
    "wof:name":"SP2 0LR",
    "wof:placetype":"postalcode"
},
  "geometry": {"coordinates":[-1.872304,51.073245],"type":"Point"}
}