{
  "type": "Feature",
  "properties": {
    "date:inception_lower":"2016-03-01",
    "date:inception_upper":"2016-03-31",
    "iso:country":"GB",
    "wof:name":"AB41 9JZ",
    "wof:placetype":"postalcode"
},
  "geometry": {"coordinates":[-2.070881,57.36879],"type":"Point"}
}