{
  "type": "Feature",
  "properties": {
    "iso:country":"GB",
    "wof:name":"AB41 9JZ",
    "wof:placetype":"postalcode"
},
  "geometry": {"coordinates":[-2.07140860102235,57.36870575898546],"type":"Point"}
}