{
  "type": "Feature",
  "properties": {
    "iso:country":"GB",
    "wof:name":"BS21 7LU",
    "wof:placetype":"postalcode"
},
  "geometry": {"coordinates":[-2.84731684507273,51.43799869835224],"type":"Point"}
}