{
  "type": "Feature",
  "properties": {
    "iso:country":"GB",
    "wof:name":"KT11 1BP",
    "wof:placetype":"postalcode"
},
  "geometry": {"coordinates":[-0.40613460556739,51.34298610701224],"type":"Point"}
}