{
  "type": "Feature",
  "properties": {
    "iso:country": "GB",
    "wof:name": "DL9 4JE",
    "wof:placetype": "postalcode"
  },
  "geometry": {"coordinates":[-1.703087,54.370604],"type":"Point"}
}
