{
  "type": "Feature",
  "properties": {
    "iso:country":"GB",
    "wof:name":"DL9 4JE",
    "wof:placetype":"postalcode"
},
  "geometry": {"coordinates":[-1.70356681215008,54.37147570098867],"type":"Point"}
}