{
  "type": "Feature",
  "properties": {
    "iso:country":"GB",
    "wof:name":"RG20 7JU",
    "wof:placetype":"postalcode"
},
  "geometry": {"coordinates":[-1.33014162042005,51.50045545669965],"type":"Point"}
}