{
  "type": "Feature",
  "properties": {
    "iso:country":"GB",
    "wof:name":"WF11 9HF",
    "wof:placetype":"postalcode"
},
  "geometry": {"coordinates":[-1.27198694829525,53.72628060301879],"type":"Point"}
}