{
  "type": "Feature",
  "properties": {
    "date:inception_lower":"1984-10-01",
    "date:inception_upper":"1984-10-31",
    "iso:country":"GB",
    "wof:name":"WF11 9HF",
    "wof:placetype":"postalcode"
},
  "geometry": {"coordinates":[-1.271987,53.726281],"type":"Point"}
}