{
  "type": "Feature",
  "properties": {
    "iso:country":"GB",
    "wof:name":"TW20 0NH",
    "wof:placetype":"postalcode"
},
  "geometry": {"coordinates":[-0.56900048255152,51.43318591030427],"type":"Point"}
}