{
  "type": "Feature",
  "properties": {
    "iso:country": "GB",
    "wof:name": "TW20 0NH",
    "wof:placetype": "postalcode"
  },
  "geometry": {"coordinates":[-0.569,51.433186],"type":"Point"}
}
