{
  "type": "Feature",
  "properties": {
    "iso:country": "GB",
    "wof:name": "NE71 6QX",
    "wof:placetype": "postalcode"
  },
  "geometry": {"coordinates":[-1.994968,55.523047],"type":"Point"}
}
