{
  "type": "Feature",
  "properties": {
    "date:inception_lower": "1980-01-01",
    "date:inception_upper": "1980-01-01",
    "iso:country": "GB",
    "wof:name": "NE71 6QX",
    "wof:placetype": "postalcode"
  },
  "geometry": {"coordinates":[-1.994968,55.523047],"type":"Point"}
}
