{
  "type": "Feature",
  "properties": {
    "iso:country":"GB",
    "wof:name":"TA7 8FB",
    "wof:placetype":"postalcode"
},
  "geometry": {"coordinates":[-2.92101010552609,51.14936490623798],"type":"Point"}
}