{
  "type": "Feature",
  "properties": {
    "date:inception_lower": "2012-02-01",
    "date:inception_upper": "2012-02-01",
    "iso:country": "GB",
    "wof:name": "TA7 8FB",
    "wof:placetype": "postalcode"
  },
  "geometry": {"coordinates":[-2.92101,51.149365],"type":"Point"}
}
