{
  "type": "Feature",
  "properties": {
    "iso:country":"GB",
    "wof:name":"EX23 9HZ",
    "wof:placetype":"postalcode"
},
  "geometry": {"coordinates":[-4.53391253035911,50.89778377571448],"type":"Point"}
}