{
  "type": "Feature",
  "properties": {
    "iso:country":"GB",
    "wof:name":"NE44 6EP",
    "wof:placetype":"postalcode"
},
  "geometry": {"coordinates":[-1.97196089250934,54.94877043046228],"type":"Point"}
}