{
  "type": "Feature",
  "properties": {
    "iso:country":"GB",
    "wof:name":"SN9 5JD",
    "wof:placetype":"postalcode"
},
  "geometry": {"coordinates":[-1.76625342184643,51.33370347375723],"type":"Point"}
}