{
  "type": "Feature",
  "properties": {
    "iso:country":"GB",
    "wof:name":"NN10 8EW",
    "wof:placetype":"postalcode"
},
  "geometry": {"coordinates":[-0.60053562412549,52.31061796113195],"type":"Point"}
}