{
  "type": "Feature",
  "properties": {
    "iso:country": "GB",
    "wof:name": "DE56 1UR",
    "wof:placetype": "postalcode"
  },
  "geometry": {"coordinates":[-1.481062,53.021458],"type":"Point"}
}
