{
  "type": "Feature",
  "properties": {
    "iso:country":"GB",
    "wof:name":"DE56 1UR",
    "wof:placetype":"postalcode"
},
  "geometry": {"coordinates":[-1.48106197578892,53.02145820398979],"type":"Point"}
}