{
  "type": "Feature",
  "properties": {
    "iso:country":"GB",
    "wof:name":"SL4 5EU",
    "wof:placetype":"postalcode"
},
  "geometry": {"coordinates":[-0.63061883580808,51.47975458306937],"type":"Point"}
}