{
  "type": "Feature",
  "properties": {
    "date:inception_lower": "1980-01-01",
    "date:inception_upper": "1980-01-01",
    "iso:country": "GB",
    "wof:name": "W12 9TD",
    "wof:placetype": "postalcode"
  },
  "geometry": {"coordinates":[-0.249493,51.499423],"type":"Point"}
}
