{
  "type": "Feature",
  "properties": {
    "iso:country":"GB",
    "wof:name":"W12 9TD",
    "wof:placetype":"postalcode"
},
  "geometry": {"coordinates":[-0.2494928053646,51.49942289344319],"type":"Point"}
}