{
  "type": "Feature",
  "properties": {
    "iso:country":"GB",
    "wof:name":"LD3 7TA",
    "wof:placetype":"postalcode"
},
  "geometry": {"coordinates":[-3.29772191017694,51.93716077089275],"type":"Point"}
}