{
  "type": "Feature",
  "properties": {
    "iso:country":"GB",
    "wof:name":"CV7 8GJ",
    "wof:placetype":"postalcode"
},
  "geometry": {"coordinates":[-1.5695401783149,52.50567369293816],"type":"Point"}
}