{
  "type": "Feature",
  "properties": {
    "iso:country": "GB",
    "wof:name": "CV7 8GJ",
    "wof:placetype": "postalcode"
  },
  "geometry": {"coordinates":[-1.56954,52.505674],"type":"Point"}
}
