{
  "type": "Feature",
  "properties": {
    "iso:country": "GB",
    "wof:name": "LS29 1HX",
    "wof:placetype": "postalcode"
  },
  "geometry": {"coordinates":[-1.820087,53.923453],"type":"Point"}
}
