{
  "type": "Feature",
  "properties": {
    "date:inception_lower":"1980-01-01",
    "date:inception_upper":"1980-01-31",
    "iso:country":"GB",
    "wof:name":"AL7 2BW",
    "wof:placetype":"postalcode"
},
  "geometry": {"coordinates":[-0.173992,51.801725],"type":"Point"}
}