{
  "type": "Feature",
  "properties": {
    "iso:country": "GB",
    "wof:name": "AL7 2BW",
    "wof:placetype": "postalcode"
  },
  "geometry": {"coordinates":[-0.173992,51.801725],"type":"Point"}
}
