{
  "type": "Feature",
  "properties": {
    "date:inception_lower": "2024-03-01",
    "date:inception_upper": "2024-03-01",
    "iso:country": "GB",
    "wof:name": "BD9 4JL",
    "wof:placetype": "postalcode"
  },
  "geometry": {"coordinates":[-1.776206,53.817206],"type":"Point"}
}
