{
  "type": "Feature",
  "properties": {
    "iso:country":"GB",
    "wof:name":"BD9 4JL",
    "wof:placetype":"postalcode"
},
  "geometry": {"coordinates":[-1.77654115789582,53.81640100014542],"type":"Point"}
}