{
  "type": "Feature",
  "properties": {
    "date:inception_lower": "1980-01-01",
    "date:inception_upper": "1980-01-01",
    "iso:country": "GB",
    "wof:name": "HD3 4TL",
    "wof:placetype": "postalcode"
  },
  "geometry": {"coordinates":[-1.841474,53.646333],"type":"Point"}
}
