{
  "type": "Feature",
  "properties": {
    "iso:country":"GB",
    "wof:name":"HD3 4TL",
    "wof:placetype":"postalcode"
},
  "geometry": {"coordinates":[-1.84147391782111,53.64633319125768],"type":"Point"}
}