{
  "type": "Feature",
  "properties": {
    "iso:country":"GB",
    "wof:name":"SG4 9PL",
    "wof:placetype":"postalcode"
},
  "geometry": {"coordinates":[-0.26615613980726,51.94843776716218],"type":"Point"}
}