{
  "type": "Feature",
  "properties": {
    "iso:country": "GB",
    "wof:name": "SG4 9PL",
    "wof:placetype": "postalcode"
  },
  "geometry": {"coordinates":[-0.266147,51.948445],"type":"Point"}
}
