{
  "type": "Feature",
  "properties": {
    "iso:country": "GB",
    "wof:name": "MK5 6BZ",
    "wof:placetype": "postalcode"
  },
  "geometry": {"coordinates":[-0.78645,52.020298],"type":"Point"}
}
