{
  "type": "Feature",
  "properties": {
    "iso:country":"GB",
    "wof:name":"DY11 5LZ",
    "wof:placetype":"postalcode"
},
  "geometry": {"coordinates":[-2.27819206030456,52.39508315528971],"type":"Point"}
}