{
  "type": "Feature",
  "properties": {
    "iso:country":"GB",
    "wof:name":"M22 0DF",
    "wof:placetype":"postalcode"
},
  "geometry": {"coordinates":[-2.26115302821524,53.37488198892413],"type":"Point"}
}