{
  "type": "Feature",
  "properties": {
    "iso:country":"GB",
    "wof:name":"WD3 5AH",
    "wof:placetype":"postalcode"
},
  "geometry": {"coordinates":[-0.52370912774491,51.65078097358716],"type":"Point"}
}