{
  "type": "Feature",
  "properties": {
    "iso:country":"GB",
    "wof:name":"IG9 6EF",
    "wof:placetype":"postalcode"
},
  "geometry": {"coordinates":[0.0483050608887,51.62664788959356],"type":"Point"}
}