{
  "type": "Feature",
  "properties": {
    "iso:country": "GB",
    "wof:name": "IG9 6EF",
    "wof:placetype": "postalcode"
  },
  "geometry": {"coordinates":[0.048305,51.626648],"type":"Point"}
}
