{
  "type": "Feature",
  "properties": {
    "date:inception_lower": "1990-07-01",
    "date:inception_upper": "1990-07-01",
    "iso:country": "GB",
    "wof:name": "IG9 6EF",
    "wof:placetype": "postalcode"
  },
  "geometry": {"coordinates":[0.048374,51.62664],"type":"Point"}
}
