{
  "type": "Feature",
  "properties": {
    "date:inception_lower":"1990-07-01",
    "date:inception_upper":"1990-07-31",
    "iso:country":"GB",
    "wof:name":"IG9 6EF",
    "wof:placetype":"postalcode"
},
  "geometry": {"coordinates":[0.048305,51.626648],"type":"Point"}
}