{
  "type": "Feature",
  "properties": {
    "iso:country": "GB",
    "wof:name": "WA7 1UB",
    "wof:placetype": "postalcode"
  },
  "geometry": {"coordinates":[-2.660031,53.347589],"type":"Point"}
}
