{
  "type": "Feature",
  "properties": {
    "iso:country":"GB",
    "wof:name":"WA7 1UB",
    "wof:placetype":"postalcode"
},
  "geometry": {"coordinates":[-2.66003081591667,53.34758926780442],"type":"Point"}
}