{
  "type": "Feature",
  "properties": {
    "date:inception_lower":"1991-01-01",
    "date:inception_upper":"1991-01-31",
    "iso:country":"GB",
    "wof:name":"WA7 1UB",
    "wof:placetype":"postalcode"
},
  "geometry": {"coordinates":[-2.660031,53.347589],"type":"Point"}
}