{
  "type": "Feature",
  "properties": {
    "iso:country":"GB",
    "wof:name":"TA18 7NQ",
    "wof:placetype":"postalcode"
},
  "geometry": {"coordinates":[-2.78771395675883,50.90436152837643],"type":"Point"}
}