{
  "type": "Feature",
  "properties": {
    "date:inception_lower":"1980-01-01",
    "date:inception_upper":"1980-01-31",
    "iso:country":"GB",
    "wof:name":"TA18 7NQ",
    "wof:placetype":"postalcode"
},
  "geometry": {"coordinates":[-2.787714,50.904362],"type":"Point"}
}