{
  "type": "Feature",
  "properties": {
    "date:inception_lower": "1995-01-01",
    "date:inception_upper": "1995-01-01",
    "iso:country": "GB",
    "wof:name": "HR2 7ZN",
    "wof:placetype": "postalcode"
  },
  "geometry": {"coordinates":[-2.747149,52.041554],"type":"Point"}
}
