{
  "type": "Feature",
  "properties": {
    "iso:country":"GB",
    "wof:name":"HR2 7ZN",
    "wof:placetype":"postalcode"
},
  "geometry": {"coordinates":[-2.74714917885564,52.04155383976131],"type":"Point"}
}