{
  "type": "Feature",
  "properties": {
    "iso:country":"GB",
    "wof:name":"SR7 8JQ",
    "wof:placetype":"postalcode"
},
  "geometry": {"coordinates":[-1.37229700492216,54.83376310072938],"type":"Point"}
}