{
  "type": "Feature",
  "properties": {
    "date:inception_lower":"1995-12-01",
    "date:inception_upper":"1995-12-31",
    "iso:country":"GB",
    "wof:name":"EN8 8TR",
    "wof:placetype":"postalcode"
},
  "geometry": {"coordinates":[-0.026842,51.697159],"type":"Point"}
}