{
  "type": "Feature",
  "properties": {
    "iso:country": "GB",
    "wof:name": "EN8 8TR",
    "wof:placetype": "postalcode"
  },
  "geometry": {"coordinates":[-0.026842,51.697159],"type":"Point"}
}
