{
  "type": "Feature",
  "properties": {
    "date:inception_lower": "2009-07-01",
    "date:inception_upper": "2009-07-01",
    "iso:country": "GB",
    "wof:name": "SO19 2PW",
    "wof:placetype": "postalcode"
  },
  "geometry": {"coordinates":[-1.364206,50.901856],"type":"Point"}
}
