{
  "type": "Feature",
  "properties": {
    "iso:country": "GB",
    "wof:name": "IP32 6PQ",
    "wof:placetype": "postalcode"
  },
  "geometry": {"coordinates":[0.696456,52.2569],"type":"Point"}
}
