{
  "type": "Feature",
  "properties": {
    "date:inception_lower": "1980-01-01",
    "date:inception_upper": "1980-01-01",
    "iso:country": "GB",
    "wof:name": "IP32 6PQ",
    "wof:placetype": "postalcode"
  },
  "geometry": {"coordinates":[0.696456,52.2569],"type":"Point"}
}
