{
  "type": "Feature",
  "properties": {
    "iso:country": "GB",
    "wof:name": "WA16 8SH",
    "wof:placetype": "postalcode"
  },
  "geometry": {"coordinates":[-2.321282,53.277675],"type":"Point"}
}
