{
  "type": "Feature",
  "properties": {
    "iso:country":"GB",
    "wof:name":"CT16 3LA",
    "wof:placetype":"postalcode"
},
  "geometry": {"coordinates":[1.28993219541543,51.16656558727703],"type":"Point"}
}