{
  "type": "Feature",
  "properties": {
    "date:inception_lower": "1980-01-01",
    "date:inception_upper": "1980-01-01",
    "iso:country": "GB",
    "wof:name": "CT16 3LA",
    "wof:placetype": "postalcode"
  },
  "geometry": {"coordinates":[1.289932,51.166566],"type":"Point"}
}
