{
  "type": "Feature",
  "properties": {
    "iso:country":"GB",
    "wof:name":"DN14 9TP",
    "wof:placetype":"postalcode"
},
  "geometry": {"coordinates":[-1.04464706168168,53.64636748970108],"type":"Point"}
}