{
  "type": "Feature",
  "properties": {
    "iso:country": "GB",
    "wof:name": "DN14 9TP",
    "wof:placetype": "postalcode"
  },
  "geometry": {"coordinates":[-1.04494,53.646291],"type":"Point"}
}
