{
  "type": "Feature",
  "properties": {
    "iso:country": "GB",
    "wof:name": "B30 2SU",
    "wof:placetype": "postalcode"
  },
  "geometry": {"coordinates":[-1.912774,52.428328],"type":"Point"}
}
