{
  "type": "Feature",
  "properties": {
    "iso:country":"GB",
    "wof:name":"NW2 1LS",
    "wof:placetype":"postalcode"
},
  "geometry": {"coordinates":[-0.22465938858633,51.57155517686413],"type":"Point"}
}