{
  "type": "Feature",
  "properties": {
    "date:inception_lower": "2005-08-01",
    "date:inception_upper": "2005-08-01",
    "iso:country": "GB",
    "wof:name": "NW2 1LS",
    "wof:placetype": "postalcode"
  },
  "geometry": {"coordinates":[-0.225478,51.57211],"type":"Point"}
}
