{
  "type": "Feature",
  "properties": {
    "date:inception_lower":"2005-08-01",
    "date:inception_upper":"2005-08-31",
    "iso:country":"GB",
    "wof:name":"NW2 1LS",
    "wof:placetype":"postalcode"
},
  "geometry": {"coordinates":[-0.224659,51.571555],"type":"Point"}
}