{
  "type": "Feature",
  "properties": {
    "iso:country":"GB",
    "wof:name":"DE65 6JL",
    "wof:placetype":"postalcode"
},
  "geometry": {"coordinates":[-1.59875999114957,52.88143745483297],"type":"Point"}
}