{
  "type": "Feature",
  "properties": {
    "iso:country":"GB",
    "wof:name":"M34 6FP",
    "wof:placetype":"postalcode"
},
  "geometry": {"coordinates":[-2.11441527003342,53.44541254736366],"type":"Point"}
}