{
  "type": "Feature",
  "properties": {
    "date:inception_lower": "1997-12-01",
    "date:inception_upper": "1997-12-01",
    "iso:country": "GB",
    "wof:name": "NR20 4UD",
    "wof:placetype": "postalcode"
  },
  "geometry": {"coordinates":[0.982409,52.708477],"type":"Point"}
}
