{
  "type": "Feature",
  "properties": {
    "iso:country":"GB",
    "wof:name":"NR20 4UD",
    "wof:placetype":"postalcode"
},
  "geometry": {"coordinates":[0.98240861940661,52.70847703831367],"type":"Point"}
}