{
  "type": "Feature",
  "properties": {
    "iso:country":"GB",
    "wof:name":"NG21 9LS",
    "wof:placetype":"postalcode"
},
  "geometry": {"coordinates":[-1.07622320885437,53.19550017885295],"type":"Point"}
}