{
  "type": "Feature",
  "properties": {
    "iso:country": "GB",
    "wof:name": "PL12 6PW",
    "wof:placetype": "postalcode"
  },
  "geometry": {"coordinates":[-4.257394,50.437015],"type":"Point"}
}
