{
  "type": "Feature",
  "properties": {
    "iso:country":"GB",
    "wof:name":"PO20 3TP",
    "wof:placetype":"postalcode"
},
  "geometry": {"coordinates":[-0.68864754997782,50.83677119695936],"type":"Point"}
}