{
  "type": "Feature",
  "properties": {
    "iso:country":"GB",
    "wof:name":"RG7 4DG",
    "wof:placetype":"postalcode"
},
  "geometry": {"coordinates":[-1.0930871623597,51.41369246639041],"type":"Point"}
}