{
  "type": "Feature",
  "properties": {
    "date:inception_lower":"1980-01-01",
    "date:inception_upper":"1980-01-31",
    "iso:country":"GB",
    "wof:name":"RG7 4DG",
    "wof:placetype":"postalcode"
},
  "geometry": {"coordinates":[-1.093067,51.413693],"type":"Point"}
}