{
  "type": "Feature",
  "properties": {
    "iso:country": "GB",
    "wof:name": "RG7 4DG",
    "wof:placetype": "postalcode"
  },
  "geometry": {"coordinates":[-1.093067,51.413693],"type":"Point"}
}
