{
  "type": "Feature",
  "properties": {
    "iso:country":"GB",
    "wof:name":"SG5 3EA",
    "wof:placetype":"postalcode"
},
  "geometry": {"coordinates":[-0.33464950565564,51.92598520780732],"type":"Point"}
}