{
  "type": "Feature",
  "properties": {
    "date:inception_lower":"1980-01-01",
    "date:inception_upper":"1980-01-31",
    "iso:country":"GB",
    "wof:name":"EX4 7DW",
    "wof:placetype":"postalcode"
},
  "geometry": {"coordinates":[-3.512848,50.738],"type":"Point"}
}