{
  "type": "Feature",
  "properties": {
    "iso:country": "GB",
    "wof:name": "EX4 7DW",
    "wof:placetype": "postalcode"
  },
  "geometry": {"coordinates":[-3.512848,50.738],"type":"Point"}
}
