{
  "type": "Feature",
  "properties": {
    "date:inception_lower": "1980-01-01",
    "date:inception_upper": "1980-01-01",
    "iso:country": "GB",
    "wof:name": "NE47 9EW",
    "wof:placetype": "postalcode"
  },
  "geometry": {"coordinates":[-2.299626,54.909032],"type":"Point"}
}
