{
  "type": "Feature",
  "properties": {
    "iso:country": "GB",
    "wof:name": "SK4 2BQ",
    "wof:placetype": "postalcode"
  },
  "geometry": {"coordinates":[-2.180522,53.40908],"type":"Point"}
}
