{
  "type": "Feature",
  "properties": {
    "iso:country": "GB",
    "wof:name": "OX3 7TE",
    "wof:placetype": "postalcode"
  },
  "geometry": {"coordinates":[-1.228089,51.765076],"type":"Point"}
}
