{
  "type": "Feature",
  "properties": {
    "iso:country":"GB",
    "wof:name":"OX3 7TE",
    "wof:placetype":"postalcode"
},
  "geometry": {"coordinates":[-1.22808873979282,51.76507612412387],"type":"Point"}
}