{
  "type": "Feature",
  "properties": {
    "iso:country":"GB",
    "wof:name":"TQ2 6EB",
    "wof:placetype":"postalcode"
},
  "geometry": {"coordinates":[-3.55343819808532,50.46772426248137],"type":"Point"}
}