{
  "type": "Feature",
  "properties": {
    "date:inception_lower":"1980-01-01",
    "date:inception_upper":"1980-01-31",
    "iso:country":"GB",
    "wof:name":"LA10 5BL",
    "wof:placetype":"postalcode"
},
  "geometry": {"coordinates":[-2.527492,54.323602],"type":"Point"}
}