{
  "type": "Feature",
  "properties": {
    "iso:country": "GB",
    "wof:name": "GU8 6BF",
    "wof:placetype": "postalcode"
  },
  "geometry": {"coordinates":[-0.707849,51.182548],"type":"Point"}
}
