{
  "type": "Feature",
  "properties": {
    "date:inception_lower": "2012-04-01",
    "date:inception_upper": "2012-04-01",
    "iso:country": "GB",
    "wof:name": "GU8 6BF",
    "wof:placetype": "postalcode"
  },
  "geometry": {"coordinates":[-0.707849,51.182548],"type":"Point"}
}
