{
  "type": "Feature",
  "properties": {
    "iso:country":"GB",
    "wof:name":"DH8 0NA",
    "wof:placetype":"postalcode"
},
  "geometry": {"coordinates":[-1.841064402537,54.8740838029998],"type":"Point"}
}