{
  "type": "Feature",
  "properties": {
    "date:inception_lower": "2018-01-01",
    "date:inception_upper": "2018-01-01",
    "iso:country": "GB",
    "wof:name": "BB8 8FF",
    "wof:placetype": "postalcode"
  },
  "geometry": {"coordinates":[-2.183659,53.848721],"type":"Point"}
}
