{
  "type": "Feature",
  "properties": {
    "iso:country":"GB",
    "wof:name":"BS4 5AN",
    "wof:placetype":"postalcode"
},
  "geometry": {"coordinates":[-2.55200803268751,51.43173221689116],"type":"Point"}
}