{
  "type": "Feature",
  "properties": {
    "iso:country":"GB",
    "wof:name":"GL12 8SU",
    "wof:placetype":"postalcode"
},
  "geometry": {"coordinates":[-2.39739319910546,51.62781512534864],"type":"Point"}
}