{
  "type": "Feature",
  "properties": {
    "iso:country":"GB",
    "wof:name":"SN12 7UB",
    "wof:placetype":"postalcode"
},
  "geometry": {"coordinates":[-2.13533243392465,51.37093943255552],"type":"Point"}
}