{
  "type": "Feature",
  "properties": {
    "iso:country":"GB",
    "wof:name":"L34 2UH",
    "wof:placetype":"postalcode"
},
  "geometry": {"coordinates":[-2.79652295685675,53.42840153361819],"type":"Point"}
}