{
  "type": "Feature",
  "properties": {
    "iso:country":"GB",
    "wof:name":"NG3 3NQ",
    "wof:placetype":"postalcode"
},
  "geometry": {"coordinates":[-1.1309576212067,52.96147008912872],"type":"Point"}
}