{
  "type": "Feature",
  "properties": {
    "iso:country": "GB",
    "wof:name": "PE24 4SH",
    "wof:placetype": "postalcode"
  },
  "geometry": {"coordinates":[0.241202,53.143997],"type":"Point"}
}
