{
  "type": "Feature",
  "properties": {
    "iso:country":"GB",
    "wof:name":"KA3 2AH",
    "wof:placetype":"postalcode"
},
  "geometry": {"coordinates":[-4.49988598854844,55.62400116930647],"type":"Point"}
}