{
  "type": "Feature",
  "properties": {
    "iso:country": "GB",
    "wof:name": "KA3 2AH",
    "wof:placetype": "postalcode"
  },
  "geometry": {"coordinates":[-4.499886,55.624001],"type":"Point"}
}
