{
  "type": "Feature",
  "properties": {
    "date:inception_lower":"1999-06-01",
    "date:inception_upper":"1999-06-30",
    "iso:country":"GB",
    "wof:name":"IV30 4PN",
    "wof:placetype":"postalcode"
},
  "geometry": {"coordinates":[-3.324707,57.661983],"type":"Point"}
}