{
  "type": "Feature",
  "properties": {
    "iso:country": "GB",
    "wof:name": "SK4 3HF",
    "wof:placetype": "postalcode"
  },
  "geometry": {"coordinates":[-2.196156,53.426457],"type":"Point"}
}
