{
  "type": "Feature",
  "properties": {
    "iso:country":"GB",
    "wof:name":"SK4 3HF",
    "wof:placetype":"postalcode"
},
  "geometry": {"coordinates":[-2.19615613138141,53.42645720189839],"type":"Point"}
}