{
  "type": "Feature",
  "properties": {
    "iso:country":"GB",
    "wof:name":"DE23 1RF",
    "wof:placetype":"postalcode"
},
  "geometry": {"coordinates":[-1.49148196850823,52.89328843174192],"type":"Point"}
}