{
  "type": "Feature",
  "properties": {
    "iso:country": "GB",
    "wof:name": "DE23 1RF",
    "wof:placetype": "postalcode"
  },
  "geometry": {"coordinates":[-1.491482,52.893288],"type":"Point"}
}
