{
  "type": "Feature",
  "properties": {
    "iso:country": "GB",
    "wof:name": "DH7 0TE",
    "wof:placetype": "postalcode"
  },
  "geometry": {"coordinates":[-1.802432,54.804104],"type":"Point"}
}
