{
  "type": "Feature",
  "properties": {
    "date:inception_lower":"1980-01-01",
    "date:inception_upper":"1980-01-31",
    "iso:country":"GB",
    "wof:name":"DH7 0TE",
    "wof:placetype":"postalcode"
},
  "geometry": {"coordinates":[-1.802432,54.804104],"type":"Point"}
}