{
  "type": "Feature",
  "properties": {
    "date:inception_lower": "1980-01-01",
    "date:inception_upper": "1980-01-01",
    "iso:country": "GB",
    "wof:name": "DH7 0TE",
    "wof:placetype": "postalcode"
  },
  "geometry": {"coordinates":[-1.801541,54.803867],"type":"Point"}
}
