{
  "type": "Feature",
  "properties": {
    "iso:country":"GB",
    "wof:name":"DH7 0TE",
    "wof:placetype":"postalcode"
},
  "geometry": {"coordinates":[-1.80243175755814,54.80410393021695],"type":"Point"}
}