{
  "type": "Feature",
  "properties": {
    "iso:country":"GB",
    "wof:name":"BS48 4YF",
    "wof:placetype":"postalcode"
},
  "geometry": {"coordinates":[-2.7572206219332,51.42464229037565],"type":"Point"}
}