{
  "type": "Feature",
  "properties": {
    "iso:country": "GB",
    "wof:name": "BS48 4YF",
    "wof:placetype": "postalcode"
  },
  "geometry": {"coordinates":[-2.757221,51.424642],"type":"Point"}
}
