{
  "type": "Feature",
  "properties": {
    "date:inception_lower":"1997-12-01",
    "date:inception_upper":"1997-12-31",
    "iso:country":"GB",
    "wof:name":"BS48 4YF",
    "wof:placetype":"postalcode"
},
  "geometry": {"coordinates":[-2.757221,51.424642],"type":"Point"}
}