{
  "type": "Feature",
  "properties": {
    "date:inception_lower": "1980-01-01",
    "date:inception_upper": "1980-01-01",
    "iso:country": "GB",
    "wof:name": "WV2 1HA",
    "wof:placetype": "postalcode"
  },
  "geometry": {"coordinates":[-2.122731,52.576728],"type":"Point"}
}
