{
  "type": "Feature",
  "properties": {
    "iso:country":"GB",
    "wof:name":"SO30 0ND",
    "wof:placetype":"postalcode"
},
  "geometry": {"coordinates":[-1.30124930079521,50.90851027222652],"type":"Point"}
}