{
  "type": "Feature",
  "properties": {
    "date:inception_lower":"2000-12-01",
    "date:inception_upper":"2000-12-31",
    "iso:country":"GB",
    "wof:name":"EH46 7AN",
    "wof:placetype":"postalcode"
},
  "geometry": {"coordinates":[-3.379895,55.695796],"type":"Point"}
}