{
  "type": "Feature",
  "properties": {
    "iso:country": "GB",
    "wof:name": "EH46 7AN",
    "wof:placetype": "postalcode"
  },
  "geometry": {"coordinates":[-3.379895,55.695796],"type":"Point"}
}
