{
  "type": "Feature",
  "properties": {
    "iso:country":"GB",
    "wof:name":"IV2 7WR",
    "wof:placetype":"postalcode"
},
  "geometry": {"coordinates":[-4.13642310316766,57.49395088608728],"type":"Point"}
}