{
  "type": "Feature",
  "properties": {
    "iso:country":"GB",
    "wof:name":"HX2 6TQ",
    "wof:placetype":"postalcode"
},
  "geometry": {"coordinates":[-1.9382078835916,53.74316103119106],"type":"Point"}
}