{
  "type": "Feature",
  "properties": {
    "iso:country": "GB",
    "wof:name": "CT5 4AZ",
    "wof:placetype": "postalcode"
  },
  "geometry": {"coordinates":[0.998566,51.344507],"type":"Point"}
}
