{
  "type": "Feature",
  "properties": {
    "iso:country":"GB",
    "wof:name":"CT5 4AZ",
    "wof:placetype":"postalcode"
},
  "geometry": {"coordinates":[0.99856595611688,51.3445074413447],"type":"Point"}
}