{
  "type": "Feature",
  "properties": {
    "date:inception_lower":"2001-12-01",
    "date:inception_upper":"2001-12-31",
    "iso:country":"GB",
    "wof:name":"S7 1BA",
    "wof:placetype":"postalcode"
},
  "geometry": {"coordinates":[-1.475813,53.366549],"type":"Point"}
}