{
  "type": "Feature",
  "properties": {
    "iso:country":"GB",
    "wof:name":"CW1 5EW",
    "wof:placetype":"postalcode"
},
  "geometry": {"coordinates":[-2.42995967008809,53.09631305568917],"type":"Point"}
}