{
  "type": "Feature",
  "properties": {
    "iso:country":"GB",
    "wof:name":"LA3 3LN",
    "wof:placetype":"postalcode"
},
  "geometry": {"coordinates":[-2.83947098247837,54.06539732426573],"type":"Point"}
}