{
  "type": "Feature",
  "properties": {
    "iso:country":"GB",
    "wof:name":"LA14 2HJ",
    "wof:placetype":"postalcode"
},
  "geometry": {"coordinates":[-3.22383208133256,54.1104022608017],"type":"Point"}
}