{
  "type": "Feature",
  "properties": {
    "date:inception_lower":"1994-05-01",
    "date:inception_upper":"1994-05-31",
    "iso:country":"GB",
    "wof:name":"M40 1PY",
    "wof:placetype":"postalcode"
},
  "geometry": {"coordinates":[-2.169304,53.500995],"type":"Point"}
}