{
  "type": "Feature",
  "properties": {
    "iso:country":"GB",
    "wof:name":"S10 1SB",
    "wof:placetype":"postalcode"
},
  "geometry": {"coordinates":[-1.50873076435388,53.386940373469],"type":"Point"}
}