{
  "type": "Feature",
  "properties": {
    "date:inception_lower": "1997-06-01",
    "date:inception_upper": "1997-06-01",
    "iso:country": "GB",
    "wof:name": "TQ3 3QA",
    "wof:placetype": "postalcode"
  },
  "geometry": {"coordinates":[-3.574148,50.438324],"type":"Point"}
}
