{
  "type": "Feature",
  "properties": {
    "iso:country": "GB",
    "wof:name": "TQ3 3QA",
    "wof:placetype": "postalcode"
  },
  "geometry": {"coordinates":[-3.574148,50.438324],"type":"Point"}
}
