{
  "type": "Feature",
  "properties": {
    "iso:country":"GB",
    "wof:name":"SK6 7LR",
    "wof:placetype":"postalcode"
},
  "geometry": {"coordinates":[-2.06290064575197,53.3887332482503],"type":"Point"}
}