{
  "type": "Feature",
  "properties": {
    "iso:country": "GB",
    "wof:name": "SK14 4LP",
    "wof:placetype": "postalcode"
  },
  "geometry": {"coordinates":[-2.072456,53.463881],"type":"Point"}
}
