{
  "type": "Feature",
  "properties": {
    "date:inception_lower":"1980-01-01",
    "date:inception_upper":"1980-01-31",
    "iso:country":"GB",
    "wof:name":"SK14 4LP",
    "wof:placetype":"postalcode"
},
  "geometry": {"coordinates":[-2.072456,53.463881],"type":"Point"}
}