{
  "type": "Feature",
  "properties": {
    "iso:country":"GB",
    "wof:name":"BD3 0PF",
    "wof:placetype":"postalcode"
},
  "geometry": {"coordinates":[-1.73754409119827,53.80799026230802],"type":"Point"}
}