{
  "type": "Feature",
  "properties": {
    "iso:country":"GB",
    "wof:name":"BN21 4JS",
    "wof:placetype":"postalcode"
},
  "geometry": {"coordinates":[0.28219233303674,50.76199166616365],"type":"Point"}
}