{
  "type": "Feature",
  "properties": {
    "iso:country":"GB",
    "wof:name":"S75 3RN",
    "wof:placetype":"postalcode"
},
  "geometry": {"coordinates":[-1.52616412285579,53.54326770047992],"type":"Point"}
}