{
  "type": "Feature",
  "properties": {
    "iso:country": "GB",
    "wof:name": "S75 3RN",
    "wof:placetype": "postalcode"
  },
  "geometry": {"coordinates":[-1.526164,53.543268],"type":"Point"}
}
