{
  "type": "Feature",
  "properties": {
    "iso:country":"GB",
    "wof:name":"BH19 2TE",
    "wof:placetype":"postalcode"
},
  "geometry": {"coordinates":[-1.97785892346781,50.60807708503531],"type":"Point"}
}