{
  "type": "Feature",
  "properties": {
    "date:inception_lower": "1997-12-01",
    "date:inception_upper": "1997-12-01",
    "iso:country": "GB",
    "wof:name": "BH19 2TE",
    "wof:placetype": "postalcode"
  },
  "geometry": {"coordinates":[-1.977859,50.608077],"type":"Point"}
}
