{
  "type": "Feature",
  "properties": {
    "iso:country": "GB",
    "wof:name": "B71 4BA",
    "wof:placetype": "postalcode"
  },
  "geometry": {"coordinates":[-1.984834,52.523706],"type":"Point"}
}
