{
  "type": "Feature",
  "properties": {
    "iso:country":"GB",
    "wof:name":"B71 4BA",
    "wof:placetype":"postalcode"
},
  "geometry": {"coordinates":[-1.98483451805201,52.52370628482868],"type":"Point"}
}