{
  "type": "Feature",
  "properties": {
    "date:inception_lower": "1998-06-01",
    "date:inception_upper": "1998-06-01",
    "iso:country": "GB",
    "wof:name": "YO25 4SH",
    "wof:placetype": "postalcode"
  },
  "geometry": {"coordinates":[-0.376156,54.064077],"type":"Point"}
}
