{
  "type": "Feature",
  "properties": {
    "iso:country": "GB",
    "wof:name": "YO25 4SH",
    "wof:placetype": "postalcode"
  },
  "geometry": {"coordinates":[-0.376401,54.064054],"type":"Point"}
}
