{
  "type": "Feature",
  "properties": {
    "iso:country": "GB",
    "wof:name": "SN6 7QJ",
    "wof:placetype": "postalcode"
  },
  "geometry": {"coordinates":[-1.707768,51.623632],"type":"Point"}
}
