{
  "type": "Feature",
  "properties": {
    "date:inception_lower":"1995-07-01",
    "date:inception_upper":"1995-07-31",
    "iso:country":"GB",
    "wof:name":"OX11 7NB",
    "wof:placetype":"postalcode"
},
  "geometry": {"coordinates":[-1.23994,51.607067],"type":"Point"}
}