{
  "type": "Feature",
  "properties": {
    "iso:country":"GB",
    "wof:name":"OX11 7NB",
    "wof:placetype":"postalcode"
},
  "geometry": {"coordinates":[-1.23994005557274,51.60706725175832],"type":"Point"}
}