{
  "type": "Feature",
  "properties": {
    "iso:country":"GB",
    "wof:name":"SW4 8RB",
    "wof:placetype":"postalcode"
},
  "geometry": {"coordinates":[-0.13360462046569,51.45587438712562],"type":"Point"}
}