{
  "type": "Feature",
  "properties": {
    "iso:country":"GB",
    "wof:name":"BD6 3NE",
    "wof:placetype":"postalcode"
},
  "geometry": {"coordinates":[-1.80773088530329,53.77147914387114],"type":"Point"}
}