{
  "type": "Feature",
  "properties": {
    "date:inception_lower": "1980-01-01",
    "date:inception_upper": "1980-01-01",
    "iso:country": "GB",
    "wof:name": "BD6 3NE",
    "wof:placetype": "postalcode"
  },
  "geometry": {"coordinates":[-1.807731,53.771479],"type":"Point"}
}
