{
  "type": "Feature",
  "properties": {
    "date:inception_lower": "2012-11-01",
    "date:inception_upper": "2012-11-01",
    "iso:country": "GB",
    "wof:name": "HU17 8JN",
    "wof:placetype": "postalcode"
  },
  "geometry": {"coordinates":[-0.493933,53.845619],"type":"Point"}
}
