{
  "type": "Feature",
  "properties": {
    "iso:country": "GB",
    "wof:name": "HU17 8JN",
    "wof:placetype": "postalcode"
  },
  "geometry": {"coordinates":[-0.493933,53.845619],"type":"Point"}
}
