{
  "type": "Feature",
  "properties": {
    "date:inception_lower":"2001-06-01",
    "date:inception_upper":"2001-06-30",
    "iso:country":"GB",
    "wof:name":"LS25 7SF",
    "wof:placetype":"postalcode"
},
  "geometry": {"coordinates":[-1.382858,53.764347],"type":"Point"}
}