{
  "type": "Feature",
  "properties": {
    "date:inception_lower":"1980-01-01",
    "date:inception_upper":"1980-01-31",
    "iso:country":"GB",
    "wof:name":"WS7 9JF",
    "wof:placetype":"postalcode"
},
  "geometry": {"coordinates":[-1.898567,52.678099],"type":"Point"}
}