{
  "type": "Feature",
  "properties": {
    "iso:country":"GB",
    "wof:name":"HA8 8DE",
    "wof:placetype":"postalcode"
},
  "geometry": {"coordinates":[-0.28935698409608,51.62248590657066],"type":"Point"}
}