{
  "type": "Feature",
  "properties": {
    "date:inception_lower": "2005-01-01",
    "date:inception_upper": "2005-01-01",
    "iso:country": "GB",
    "wof:name": "HA8 8DE",
    "wof:placetype": "postalcode"
  },
  "geometry": {"coordinates":[-0.289357,51.622486],"type":"Point"}
}
