{
  "type": "Feature",
  "properties": {
    "date:inception_lower": "2018-08-01",
    "date:inception_upper": "2018-08-01",
    "iso:country": "GB",
    "wof:name": "ST4 4FJ",
    "wof:placetype": "postalcode"
  },
  "geometry": {"coordinates":[-2.182276,52.999292],"type":"Point"}
}
