{
  "type": "Feature",
  "properties": {
    "date:inception_lower": "2021-06-01",
    "date:inception_upper": "2021-06-01",
    "iso:country": "GB",
    "wof:name": "PE14 7BW",
    "wof:placetype": "postalcode"
  },
  "geometry": {"coordinates":[0.185482,52.660316],"type":"Point"}
}
