{
  "type": "Feature",
  "properties": {
    "iso:country": "GB",
    "wof:name": "BA2 7BP",
    "wof:placetype": "postalcode"
  },
  "geometry": {"coordinates":[-2.311476,51.380323],"type":"Point"}
}
