{
  "type": "Feature",
  "properties": {
    "iso:country":"GB",
    "wof:name":"BA2 7BP",
    "wof:placetype":"postalcode"
},
  "geometry": {"coordinates":[-2.31147583431901,51.38032321913341],"type":"Point"}
}