{
  "type": "Feature",
  "properties": {
    "iso:country": "GB",
    "wof:name": "ST3 7XE",
    "wof:placetype": "postalcode"
  },
  "geometry": {"coordinates":[-2.104491,52.953667],"type":"Point"}
}
