{
  "type": "Feature",
  "properties": {
    "iso:country":"GB",
    "wof:name":"TA3 6JR",
    "wof:placetype":"postalcode"
},
  "geometry": {"coordinates":[-2.97256674187439,51.02282937721402],"type":"Point"}
}