{
  "type": "Feature",
  "properties": {
    "iso:country": "GB",
    "wof:name": "CM13 3DX",
    "wof:placetype": "postalcode"
  },
  "geometry": {"coordinates":[0.307198,51.588555],"type":"Point"}
}
