{
  "type": "Feature",
  "properties": {
    "iso:country": "GB",
    "wof:name": "CM13 3DX",
    "wof:placetype": "postalcode"
  },
  "geometry": {"coordinates":[0.312299,51.59064],"type":"Point"}
}
