{
  "type": "Feature",
  "properties": {
    "date:inception_lower": "1980-01-01",
    "date:inception_upper": "1980-01-01",
    "iso:country": "GB",
    "wof:name": "TW18 3JL",
    "wof:placetype": "postalcode"
  },
  "geometry": {"coordinates":[-0.516575,51.431473],"type":"Point"}
}
