{
  "type": "Feature",
  "properties": {
    "iso:country":"GB",
    "wof:name":"PL27 7QB",
    "wof:placetype":"postalcode"
},
  "geometry": {"coordinates":[-4.92365353937907,50.50920273942371],"type":"Point"}
}