{
  "type": "Feature",
  "properties": {
    "iso:country":"GB",
    "wof:name":"KT4 8TH",
    "wof:placetype":"postalcode"
},
  "geometry": {"coordinates":[-0.22979759454857,51.37065119207212],"type":"Point"}
}