{
  "type": "Feature",
  "properties": {
    "iso:country": "GB",
    "wof:name": "KT4 8TH",
    "wof:placetype": "postalcode"
  },
  "geometry": {"coordinates":[-0.229798,51.370651],"type":"Point"}
}
