{
  "type": "Feature",
  "properties": {
    "date:inception_lower": "2023-07-01",
    "date:inception_upper": "2023-07-01",
    "iso:country": "GB",
    "wof:name": "PO33 4NY",
    "wof:placetype": "postalcode"
  },
  "geometry": {"coordinates":[-1.235664,50.732318],"type":"Point"}
}
