{
  "type": "Feature",
  "properties": {
    "iso:country":"GB",
    "wof:name":"SK4 4RD",
    "wof:placetype":"postalcode"
},
  "geometry": {"coordinates":[-2.18551906997094,53.42706746272093],"type":"Point"}
}