{
  "type": "Feature",
  "properties": {
    "iso:country": "GB",
    "wof:name": "BB2 7BA",
    "wof:placetype": "postalcode"
  },
  "geometry": {"coordinates":[-2.508086,53.754383],"type":"Point"}
}
