{
  "type": "Feature",
  "properties": {
    "iso:country":"GB",
    "wof:name":"BB2 7BA",
    "wof:placetype":"postalcode"
},
  "geometry": {"coordinates":[-2.50816244931785,53.75425943949815],"type":"Point"}
}