{
  "type": "Feature",
  "properties": {
    "date:inception_lower": "1997-12-01",
    "date:inception_upper": "1997-12-01",
    "iso:country": "GB",
    "wof:name": "KT7 0XF",
    "wof:placetype": "postalcode"
  },
  "geometry": {"coordinates":[-0.324123,51.39031],"type":"Point"}
}
