{
  "type": "Feature",
  "properties": {
    "date:inception_lower":"1997-12-01",
    "date:inception_upper":"1997-12-31",
    "iso:country":"GB",
    "wof:name":"KT7 0XF",
    "wof:placetype":"postalcode"
},
  "geometry": {"coordinates":[-0.323778,51.390332],"type":"Point"}
}