{
  "type": "Feature",
  "properties": {
    "iso:country":"GB",
    "wof:name":"KT7 0XF",
    "wof:placetype":"postalcode"
},
  "geometry": {"coordinates":[-0.32414582820391,51.39031147169518],"type":"Point"}
}