{
  "type": "Feature",
  "properties": {
    "iso:country":"GB",
    "wof:name":"IP1 6EW",
    "wof:placetype":"postalcode"
},
  "geometry": {"coordinates":[1.13151486306308,52.08122605746736],"type":"Point"}
}