{
  "type": "Feature",
  "properties": {
    "date:inception_lower":"2009-06-01",
    "date:inception_upper":"2009-06-30",
    "iso:country":"GB",
    "wof:name":"PL4 8EB",
    "wof:placetype":"postalcode"
},
  "geometry": {"coordinates":[-4.135421,50.374814],"type":"Point"}
}