{
  "type": "Feature",
  "properties": {
    "date:inception_lower":"1991-01-01",
    "date:inception_upper":"1991-01-31",
    "iso:country":"GB",
    "wof:name":"EX16 6SS",
    "wof:placetype":"postalcode"
},
  "geometry": {"coordinates":[-3.463455,50.912701],"type":"Point"}
}