{
  "type": "Feature",
  "properties": {
    "date:inception_lower": "1991-01-01",
    "date:inception_upper": "1991-01-01",
    "iso:country": "GB",
    "wof:name": "EX16 6SS",
    "wof:placetype": "postalcode"
  },
  "geometry": {"coordinates":[-3.463548,50.912909],"type":"Point"}
}
