{
  "type": "Feature",
  "properties": {
    "iso:country":"GB",
    "wof:name":"HR8 2TB",
    "wof:placetype":"postalcode"
},
  "geometry": {"coordinates":[-2.53105752883914,52.0830046075334],"type":"Point"}
}