{
  "type": "Feature",
  "properties": {
    "iso:country": "GB",
    "wof:name": "ST8 6QN",
    "wof:placetype": "postalcode"
  },
  "geometry": {"coordinates":[-2.167835,53.124946],"type":"Point"}
}
