{
  "type": "Feature",
  "properties": {
    "iso:country":"GB",
    "wof:name":"N7 9LG",
    "wof:placetype":"postalcode"
},
  "geometry": {"coordinates":[-0.12746058440639,51.54756324144933],"type":"Point"}
}