{
  "type": "Feature",
  "properties": {
    "date:inception_lower":"1980-01-01",
    "date:inception_upper":"1980-01-31",
    "iso:country":"GB",
    "wof:name":"SA20 0EH",
    "wof:placetype":"postalcode"
},
  "geometry": {"coordinates":[-3.803636,51.996548],"type":"Point"}
}