{
  "type": "Feature",
  "properties": {
    "iso:country": "GB",
    "wof:name": "SA20 0EH",
    "wof:placetype": "postalcode"
  },
  "geometry": {"coordinates":[-3.803636,51.996548],"type":"Point"}
}
