{
  "type": "Feature",
  "properties": {
    "iso:country":"GB",
    "wof:name":"KY9 1WX",
    "wof:placetype":"postalcode"
},
  "geometry": {"coordinates":[-3.01440071965589,56.20116105663331],"type":"Point"}
}