{
  "type": "Feature",
  "properties": {
    "iso:country":"GB",
    "wof:name":"S40 2EJ",
    "wof:placetype":"postalcode"
},
  "geometry": {"coordinates":[-1.4276504549334,53.22712662223412],"type":"Point"}
}