{
  "type": "Feature",
  "properties": {
    "iso:country":"GB",
    "wof:name":"SK9 3DX",
    "wof:placetype":"postalcode"
},
  "geometry": {"coordinates":[-2.22342968186706,53.34701296488252],"type":"Point"}
}