{
  "type": "Feature",
  "properties": {
    "iso:country": "GB",
    "wof:name": "CF35 5EU",
    "wof:placetype": "postalcode"
  },
  "geometry": {"coordinates":[-3.53217,51.506356],"type":"Point"}
}
