{
  "type": "Feature",
  "properties": {
    "iso:country": "GB",
    "wof:name": "B78 3AE",
    "wof:placetype": "postalcode"
  },
  "geometry": {"coordinates":[-1.73639,52.643267],"type":"Point"}
}
