{
  "type": "Feature",
  "properties": {
    "iso:country":"GB",
    "wof:name":"B78 3AE",
    "wof:placetype":"postalcode"
},
  "geometry": {"coordinates":[-1.73639050920845,52.64326661067351],"type":"Point"}
}