{
  "type": "Feature",
  "properties": {
    "iso:country":"GB",
    "wof:name":"SA33 4HP",
    "wof:placetype":"postalcode"
},
  "geometry": {"coordinates":[-4.571737008316,51.78811408108814],"type":"Point"}
}