{
  "type": "Feature",
  "properties": {
    "date:inception_lower": "2004-01-01",
    "date:inception_upper": "2004-01-01",
    "iso:country": "GB",
    "wof:name": "CF3 0RP",
    "wof:placetype": "postalcode"
  },
  "geometry": {"coordinates":[-3.101004,51.516286],"type":"Point"}
}
