{
  "type": "Feature",
  "properties": {
    "iso:country":"GB",
    "wof:name":"CF3 0RP",
    "wof:placetype":"postalcode"
},
  "geometry": {"coordinates":[-3.10100382238425,51.51628632976199],"type":"Point"}
}