{
  "type": "Feature",
  "properties": {
    "date:inception_lower": "1980-01-01",
    "date:inception_upper": "1980-01-01",
    "iso:country": "GB",
    "wof:name": "NP4 9PE",
    "wof:placetype": "postalcode"
  },
  "geometry": {"coordinates":[-3.078679,51.777421],"type":"Point"}
}
