{
  "type": "Feature",
  "properties": {
    "iso:country": "GB",
    "wof:name": "BA5 2HY",
    "wof:placetype": "postalcode"
  },
  "geometry": {"coordinates":[-2.657614,51.211507],"type":"Point"}
}
