{
  "type": "Feature",
  "properties": {
    "iso:country": "GB",
    "wof:name": "BD22 0LX",
    "wof:placetype": "postalcode"
  },
  "geometry": {"coordinates":[-2.060104,53.886861],"type":"Point"}
}
