{
  "type": "Feature",
  "properties": {
    "date:inception_lower": "1980-01-01",
    "date:inception_upper": "1980-01-01",
    "iso:country": "GB",
    "wof:name": "BD22 0LX",
    "wof:placetype": "postalcode"
  },
  "geometry": {"coordinates":[-2.060104,53.886861],"type":"Point"}
}
