{
  "type": "Feature",
  "properties": {
    "iso:country":"GB",
    "wof:name":"BD22 0LX",
    "wof:placetype":"postalcode"
},
  "geometry": {"coordinates":[-2.06010430728146,53.88686066087392],"type":"Point"}
}