{
  "type": "Feature",
  "properties": {
    "iso:country": "GB",
    "wof:name": "WF15 7PF",
    "wof:placetype": "postalcode"
  },
  "geometry": {"coordinates":[-1.706918,53.700764],"type":"Point"}
}
