{
  "type": "Feature",
  "properties": {
    "iso:country":"GB",
    "wof:name":"LS12 4LE",
    "wof:placetype":"postalcode"
},
  "geometry": {"coordinates":[-1.60967633219126,53.79065524763543],"type":"Point"}
}