{
  "type": "Feature",
  "properties": {
    "date:inception_lower": "2000-12-01",
    "date:inception_upper": "2000-12-01",
    "iso:country": "GB",
    "wof:name": "LS12 4LE",
    "wof:placetype": "postalcode"
  },
  "geometry": {"coordinates":[-1.609676,53.790655],"type":"Point"}
}
