{
  "type": "Feature",
  "properties": {
    "iso:country":"GB",
    "wof:name":"IV15 9PQ",
    "wof:placetype":"postalcode"
},
  "geometry": {"coordinates":[-4.43330187919694,57.59610526282222],"type":"Point"}
}