{
  "type": "Feature",
  "properties": {
    "iso:country": "GB",
    "wof:name": "PR6 7PR",
    "wof:placetype": "postalcode"
  },
  "geometry": {"coordinates":[-2.639524,53.684078],"type":"Point"}
}
