{
  "type": "Feature",
  "properties": {
    "iso:country":"GB",
    "wof:name":"AB11 6ED",
    "wof:placetype":"postalcode"
},
  "geometry": {"coordinates":[-2.10471214636335,57.14210773962809],"type":"Point"}
}