{
  "type": "Feature",
  "properties": {
    "iso:country": "GB",
    "wof:name": "BN14 8NT",
    "wof:placetype": "postalcode"
  },
  "geometry": {"coordinates":[-0.360658,50.828175],"type":"Point"}
}
