{
  "type": "Feature",
  "properties": {
    "iso:country": "GB",
    "wof:name": "BN14 8NT",
    "wof:placetype": "postalcode"
  },
  "geometry": {"coordinates":[-0.359877,50.827721],"type":"Point"}
}
