{
  "type": "Feature",
  "properties": {
    "iso:country":"GB",
    "wof:name":"S40 4DG",
    "wof:placetype":"postalcode"
},
  "geometry": {"coordinates":[-1.46437274353773,53.23729289991972],"type":"Point"}
}