{
  "type": "Feature",
  "properties": {
    "iso:country": "GB",
    "wof:name": "SO22 5FP",
    "wof:placetype": "postalcode"
  },
  "geometry": {"coordinates":[-1.344108,51.077033],"type":"Point"}
}
