{
  "type": "Feature",
  "properties": {
    "iso:country": "GB",
    "wof:name": "DY2 0PZ",
    "wof:placetype": "postalcode"
  },
  "geometry": {"coordinates":[-2.087374,52.490661],"type":"Point"}
}
