{
  "type": "Feature",
  "properties": {
    "iso:country":"GB",
    "wof:name":"DY2 0PZ",
    "wof:placetype":"postalcode"
},
  "geometry": {"coordinates":[-2.08739433745609,52.49063681172417],"type":"Point"}
}