{
  "type": "Feature",
  "properties": {
    "date:inception_lower":"2010-06-01",
    "date:inception_upper":"2010-06-30",
    "iso:country":"GB",
    "wof:name":"CV4 9WE",
    "wof:placetype":"postalcode"
},
  "geometry": {"coordinates":[-1.597312,52.409432],"type":"Point"}
}