{
  "type": "Feature",
  "properties": {
    "iso:country":"GB",
    "wof:name":"CV4 9WE",
    "wof:placetype":"postalcode"
},
  "geometry": {"coordinates":[-1.59732071055132,52.40941607416414],"type":"Point"}
}