{
  "type": "Feature",
  "properties": {
    "iso:country":"GB",
    "wof:name":"DT11 0PF",
    "wof:placetype":"postalcode"
},
  "geometry": {"coordinates":[-2.26177834420934,50.83783532784553],"type":"Point"}
}