{
  "type": "Feature",
  "properties": {
    "iso:country":"GB",
    "wof:name":"M21 7WG",
    "wof:placetype":"postalcode"
},
  "geometry": {"coordinates":[-2.26602617948464,53.42838024953643],"type":"Point"}
}