{
  "type": "Feature",
  "properties": {
    "date:inception_lower": "1993-08-01",
    "date:inception_upper": "1993-08-01",
    "iso:country": "GB",
    "wof:name": "LS15 7UF",
    "wof:placetype": "postalcode"
  },
  "geometry": {"coordinates":[-1.466102,53.798873],"type":"Point"}
}
