{
  "type": "Feature",
  "properties": {
    "iso:country":"GB",
    "wof:name":"LS15 7UF",
    "wof:placetype":"postalcode"
},
  "geometry": {"coordinates":[-1.46605169489284,53.79889242421158],"type":"Point"}
}