{
  "type": "Feature",
  "properties": {
    "date:inception_lower":"1980-01-01",
    "date:inception_upper":"1980-01-31",
    "iso:country":"GB",
    "wof:name":"S17 4LH",
    "wof:placetype":"postalcode"
},
  "geometry": {"coordinates":[-1.517121,53.317761],"type":"Point"}
}