{
  "type": "Feature",
  "properties": {
    "iso:country": "GB",
    "wof:name": "S17 4LH",
    "wof:placetype": "postalcode"
  },
  "geometry": {"coordinates":[-1.517135,53.317779],"type":"Point"}
}
