{
  "type": "Feature",
  "properties": {
    "iso:country":"GB",
    "wof:name":"S17 4LH",
    "wof:placetype":"postalcode"
},
  "geometry": {"coordinates":[-1.51712065982714,53.31776143446761],"type":"Point"}
}