{
  "type": "Feature",
  "properties": {
    "iso:country": "GB",
    "wof:name": "SW2 2BW",
    "wof:placetype": "postalcode"
  },
  "geometry": {"coordinates":[-0.118204,51.451653],"type":"Point"}
}
