{
  "type": "Feature",
  "properties": {
    "iso:country":"GB",
    "wof:name":"SW2 2BW",
    "wof:placetype":"postalcode"
},
  "geometry": {"coordinates":[-0.1182039246734,51.45165345428079],"type":"Point"}
}