{
  "type": "Feature",
  "properties": {
    "iso:country": "GB",
    "wof:name": "EH33 2EW",
    "wof:placetype": "postalcode"
  },
  "geometry": {"coordinates":[-2.956099,55.941406],"type":"Point"}
}
