{
  "type": "Feature",
  "properties": {
    "iso:country":"GB",
    "wof:name":"DE7 6JE",
    "wof:placetype":"postalcode"
},
  "geometry": {"coordinates":[-1.35808970972875,52.97195645548115],"type":"Point"}
}