{
  "type": "Feature",
  "properties": {
    "iso:country": "GB",
    "wof:name": "DH1 2TU",
    "wof:placetype": "postalcode"
  },
  "geometry": {"coordinates":[-1.517758,54.787338],"type":"Point"}
}
