{
  "type": "Feature",
  "properties": {
    "date:inception_lower": "2021-05-01",
    "date:inception_upper": "2021-05-01",
    "iso:country": "GB",
    "wof:name": "TF2 9WT",
    "wof:placetype": "postalcode"
  },
  "geometry": {"coordinates":[-2.437024,52.685918],"type":"Point"}
}
