{
  "type": "Feature",
  "properties": {
    "date:inception_lower":"2006-04-01",
    "date:inception_upper":"2006-04-30",
    "iso:country":"GB",
    "wof:name":"EX1 2TT",
    "wof:placetype":"postalcode"
},
  "geometry": {"coordinates":[-3.503267,50.722035],"type":"Point"}
}