{
  "type": "Feature",
  "properties": {
    "iso:country": "GB",
    "wof:name": "TD11 3TL",
    "wof:placetype": "postalcode"
  },
  "geometry": {"coordinates":[-2.348661,55.811794],"type":"Point"}
}
