{
  "type": "Feature",
  "properties": {
    "iso:country": "GB",
    "wof:name": "L15 8AF",
    "wof:placetype": "postalcode"
  },
  "geometry": {"coordinates":[-2.913945,53.40454],"type":"Point"}
}
