{
  "type": "Feature",
  "properties": {
    "iso:country":"GB",
    "wof:name":"L15 8AF",
    "wof:placetype":"postalcode"
},
  "geometry": {"coordinates":[-2.91394487374098,53.4045400241801],"type":"Point"}
}