{
  "type": "Feature",
  "properties": {
    "iso:country":"GB",
    "wof:name":"HA8 8QR",
    "wof:placetype":"postalcode"
},
  "geometry": {"coordinates":[-0.28038540835056,51.6320484237811],"type":"Point"}
}