{
  "type": "Feature",
  "properties": {
    "iso:country":"GB",
    "wof:name":"RG1 2QH",
    "wof:placetype":"postalcode"
},
  "geometry": {"coordinates":[-0.96653996722468,51.44847794830486],"type":"Point"}
}