{
  "type": "Feature",
  "properties": {
    "iso:country": "GB",
    "wof:name": "RG1 2QH",
    "wof:placetype": "postalcode"
  },
  "geometry": {"coordinates":[-0.96654,51.448478],"type":"Point"}
}
