{
  "type": "Feature",
  "properties": {
    "iso:country": "GB",
    "wof:name": "B80 7BG",
    "wof:placetype": "postalcode"
  },
  "geometry": {"coordinates":[-1.894904,52.276277],"type":"Point"}
}
