{
  "type": "Feature",
  "properties": {
    "iso:country": "GB",
    "wof:name": "M45 7JW",
    "wof:placetype": "postalcode"
  },
  "geometry": {"coordinates":[-2.314578,53.544591],"type":"Point"}
}
