{
  "type": "Feature",
  "properties": {
    "iso:country":"GB",
    "wof:name":"AL1 3EU",
    "wof:placetype":"postalcode"
},
  "geometry": {"coordinates":[-0.33537813174166,51.75631964123659],"type":"Point"}
}