{
  "type": "Feature",
  "properties": {
    "date:inception_lower": "2021-03-01",
    "date:inception_upper": "2021-03-01",
    "iso:country": "GB",
    "wof:name": "NR13 4SN",
    "wof:placetype": "postalcode"
  },
  "geometry": {"coordinates":[1.434254,52.650063],"type":"Point"}
}
