{
  "type": "Feature",
  "properties": {
    "iso:country":"GB",
    "wof:name":"S65 3QJ",
    "wof:placetype":"postalcode"
},
  "geometry": {"coordinates":[-1.31039254277034,53.43851704499628],"type":"Point"}
}