{
  "type": "Feature",
  "properties": {
    "date:inception_lower": "2019-06-01",
    "date:inception_upper": "2019-06-01",
    "iso:country": "GB",
    "wof:name": "SR8 2FA",
    "wof:placetype": "postalcode"
  },
  "geometry": {"coordinates":[-1.344771,54.771278],"type":"Point"}
}
