{
  "type": "Feature",
  "properties": {
    "iso:country": "GB",
    "wof:name": "SR8 2FA",
    "wof:placetype": "postalcode"
  },
  "geometry": {"coordinates":[-1.344771,54.771278],"type":"Point"}
}
