{
  "type": "Feature",
  "properties": {
    "date:inception_lower":"1986-04-01",
    "date:inception_upper":"1986-04-30",
    "iso:country":"GB",
    "wof:name":"SK14 2AQ",
    "wof:placetype":"postalcode"
},
  "geometry": {"coordinates":[-2.079951,53.45264],"type":"Point"}
}