{
  "type": "Feature",
  "properties": {
    "date:inception_lower": "1980-01-01",
    "date:inception_upper": "1980-01-01",
    "iso:country": "GB",
    "wof:name": "SA11 2HS",
    "wof:placetype": "postalcode"
  },
  "geometry": {"coordinates":[-3.803775,51.641897],"type":"Point"}
}
