{
  "type": "Feature",
  "properties": {
    "iso:country":"GB",
    "wof:name":"SA11 2HS",
    "wof:placetype":"postalcode"
},
  "geometry": {"coordinates":[-3.80299227259676,51.64184998475031],"type":"Point"}
}