{
  "type": "Feature",
  "properties": {
    "iso:country": "GB",
    "wof:name": "BS39 5AJ",
    "wof:placetype": "postalcode"
  },
  "geometry": {"coordinates":[-2.573512,51.314394],"type":"Point"}
}
