{
  "type": "Feature",
  "properties": {
    "date:inception_lower": "1980-01-01",
    "date:inception_upper": "1980-01-01",
    "iso:country": "GB",
    "wof:name": "NW10 6RT",
    "wof:placetype": "postalcode"
  },
  "geometry": {"coordinates":[-0.244499,51.528529],"type":"Point"}
}
