{
  "type": "Feature",
  "properties": {
    "iso:country":"GB",
    "wof:name":"NW10 6RT",
    "wof:placetype":"postalcode"
},
  "geometry": {"coordinates":[-0.24449861792084,51.52852855001404],"type":"Point"}
}