{
  "type": "Feature",
  "properties": {
    "iso:country": "GB",
    "wof:name": "IP30 9HL",
    "wof:placetype": "postalcode"
  },
  "geometry": {"coordinates":[0.926213,52.250733],"type":"Point"}
}
