{
  "type": "Feature",
  "properties": {
    "date:inception_lower": "1980-01-01",
    "date:inception_upper": "1980-01-01",
    "iso:country": "GB",
    "wof:name": "IP30 9HL",
    "wof:placetype": "postalcode"
  },
  "geometry": {"coordinates":[0.926213,52.250733],"type":"Point"}
}
