{
  "type": "Feature",
  "properties": {
    "iso:country":"GB",
    "wof:name":"IP30 9HL",
    "wof:placetype":"postalcode"
},
  "geometry": {"coordinates":[0.92621327134518,52.25073261572062],"type":"Point"}
}