{
  "type": "Feature",
  "properties": {
    "iso:country": "GB",
    "wof:name": "S70 3JD",
    "wof:placetype": "postalcode"
  },
  "geometry": {"coordinates":[-1.447543,53.542041],"type":"Point"}
}
