{
  "type": "Feature",
  "properties": {
    "date:inception_lower": "1980-01-01",
    "date:inception_upper": "1980-01-01",
    "iso:country": "GB",
    "wof:name": "S70 3JD",
    "wof:placetype": "postalcode"
  },
  "geometry": {"coordinates":[-1.447543,53.542041],"type":"Point"}
}
