{
  "type": "Feature",
  "properties": {
    "iso:country":"GB",
    "wof:name":"S70 3JD",
    "wof:placetype":"postalcode"
},
  "geometry": {"coordinates":[-1.44754264628402,53.54204067516531],"type":"Point"}
}