{
  "type": "Feature",
  "properties": {
    "date:inception_lower":"2013-08-01",
    "date:inception_upper":"2013-08-31",
    "iso:country":"GB",
    "wof:name":"SG8 9FD",
    "wof:placetype":"postalcode"
},
  "geometry": {"coordinates":[-0.039975,52.049421],"type":"Point"}
}