{
  "type": "Feature",
  "properties": {
    "iso:country":"GB",
    "wof:name":"SG8 9FD",
    "wof:placetype":"postalcode"
},
  "geometry": {"coordinates":[-0.03997509309236,52.04942077635371],"type":"Point"}
}