{
  "type": "Feature",
  "properties": {
    "iso:country":"GB",
    "wof:name":"TW14 9QD",
    "wof:placetype":"postalcode"
},
  "geometry": {"coordinates":[-0.41775292305953,51.45040471063969],"type":"Point"}
}