{
  "type": "Feature",
  "properties": {
    "iso:country": "GB",
    "wof:name": "SN9 5LB",
    "wof:placetype": "postalcode"
  },
  "geometry": {"coordinates":[-1.760986,51.359397],"type":"Point"}
}
