{
  "type": "Feature",
  "properties": {
    "iso:country": "GB",
    "wof:name": "DL3 7SJ",
    "wof:placetype": "postalcode"
  },
  "geometry": {"coordinates":[-1.563097,54.523371],"type":"Point"}
}
