{
  "type": "Feature",
  "properties": {
    "iso:country":"GB",
    "wof:name":"SP4 8JE",
    "wof:placetype":"postalcode"
},
  "geometry": {"coordinates":[-1.76833818639857,51.19601552134213],"type":"Point"}
}