{
  "type": "Feature",
  "properties": {
    "date:inception_lower":"1983-01-01",
    "date:inception_upper":"1983-01-31",
    "iso:country":"GB",
    "wof:name":"SP4 8JE",
    "wof:placetype":"postalcode"
},
  "geometry": {"coordinates":[-1.768338,51.196016],"type":"Point"}
}