{
  "type": "Feature",
  "properties": {
    "iso:country":"GB",
    "wof:name":"SN5 5DN",
    "wof:placetype":"postalcode"
},
  "geometry": {"coordinates":[-1.83700446812257,51.57651380870882],"type":"Point"}
}