{
  "type": "Feature",
  "properties": {
    "iso:country": "GB",
    "wof:name": "NN3 8PZ",
    "wof:placetype": "postalcode"
  },
  "geometry": {"coordinates":[-0.816722,52.269979],"type":"Point"}
}
