{
  "type": "Feature",
  "properties": {
    "date:inception_lower": "1993-08-01",
    "date:inception_upper": "1993-08-01",
    "iso:country": "GB",
    "wof:name": "NN3 8PZ",
    "wof:placetype": "postalcode"
  },
  "geometry": {"coordinates":[-0.816722,52.269979],"type":"Point"}
}
