{
  "type": "Feature",
  "properties": {
    "iso:country":"GB",
    "wof:name":"MK6 3JF",
    "wof:placetype":"postalcode"
},
  "geometry": {"coordinates":[-0.74150521049052,52.04157602435948],"type":"Point"}
}