{
  "type": "Feature",
  "properties": {
    "iso:country":"GB",
    "wof:name":"OX9 3TA",
    "wof:placetype":"postalcode"
},
  "geometry": {"coordinates":[-0.97322649839496,51.75158184286474],"type":"Point"}
}