{
  "type": "Feature",
  "properties": {
    "date:inception_lower":"1980-01-01",
    "date:inception_upper":"1980-01-31",
    "iso:country":"GB",
    "wof:name":"OX9 3TA",
    "wof:placetype":"postalcode"
},
  "geometry": {"coordinates":[-0.973226,51.751582],"type":"Point"}
}