{
  "type": "Feature",
  "properties": {
    "iso:country":"GB",
    "wof:name":"BD22 0RB",
    "wof:placetype":"postalcode"
},
  "geometry": {"coordinates":[-1.95724813754565,53.85150113575784],"type":"Point"}
}