{
  "type": "Feature",
  "properties": {
    "iso:country": "GB",
    "wof:name": "CH61 7UB",
    "wof:placetype": "postalcode"
  },
  "geometry": {"coordinates":[-3.095142,53.352443],"type":"Point"}
}
