{
  "type": "Feature",
  "properties": {
    "iso:country":"GB",
    "wof:name":"HU6 7HW",
    "wof:placetype":"postalcode"
},
  "geometry": {"coordinates":[-0.33217599020565,53.76846609412433],"type":"Point"}
}