{
  "type": "Feature",
  "properties": {
    "iso:country": "GB",
    "wof:name": "HU6 7HW",
    "wof:placetype": "postalcode"
  },
  "geometry": {"coordinates":[-0.332176,53.768466],"type":"Point"}
}
