{
  "type": "Feature",
  "properties": {
    "date:inception_lower":"1999-12-01",
    "date:inception_upper":"1999-12-31",
    "iso:country":"GB",
    "wof:name":"HU6 7HW",
    "wof:placetype":"postalcode"
},
  "geometry": {"coordinates":[-0.332176,53.768466],"type":"Point"}
}