{
  "type": "Feature",
  "properties": {
    "iso:country":"GB",
    "wof:name":"GL54 5QB",
    "wof:placetype":"postalcode"
},
  "geometry": {"coordinates":[-1.97269863881306,51.95501202231503],"type":"Point"}
}