{
  "type": "Feature",
  "properties": {
    "iso:country":"GB",
    "wof:name":"BN20 0DS",
    "wof:placetype":"postalcode"
},
  "geometry": {"coordinates":[0.21575479960438,50.76165431040156],"type":"Point"}
}