{
  "type": "Feature",
  "properties": {
    "date:inception_lower": "1980-01-01",
    "date:inception_upper": "1980-01-01",
    "iso:country": "GB",
    "wof:name": "HP8 4PE",
    "wof:placetype": "postalcode"
  },
  "geometry": {"coordinates":[-0.582493,51.630323],"type":"Point"}
}
