{
  "type": "Feature",
  "properties": {
    "iso:country":"GB",
    "wof:name":"DN16 3QS",
    "wof:placetype":"postalcode"
},
  "geometry": {"coordinates":[-0.63881248995815,53.55534734934712],"type":"Point"}
}