{
  "type": "Feature",
  "properties": {
    "iso:country":"GB",
    "wof:name":"EH21 7DZ",
    "wof:placetype":"postalcode"
},
  "geometry": {"coordinates":[-3.05180675626842,55.94213031406213],"type":"Point"}
}