{
  "type": "Feature",
  "properties": {
    "iso:country":"GB",
    "wof:name":"BD19 4DJ",
    "wof:placetype":"postalcode"
},
  "geometry": {"coordinates":[-1.71342808265331,53.730170666442],"type":"Point"}
}