{
  "type": "Feature",
  "properties": {
    "date:inception_lower": "2000-06-01",
    "date:inception_upper": "2000-06-01",
    "iso:country": "GB",
    "wof:name": "PO40 9XH",
    "wof:placetype": "postalcode"
  },
  "geometry": {"coordinates":[-1.523698,50.681225],"type":"Point"}
}
