{
  "type": "Feature",
  "properties": {
    "iso:country": "GB",
    "wof:name": "PO40 9XH",
    "wof:placetype": "postalcode"
  },
  "geometry": {"coordinates":[-1.523698,50.681225],"type":"Point"}
}
