{
  "type": "Feature",
  "properties": {
    "iso:country": "GB",
    "wof:name": "WV7 3NW",
    "wof:placetype": "postalcode"
  },
  "geometry": {"coordinates":[-2.29263,52.646434],"type":"Point"}
}
