{
  "type": "Feature",
  "properties": {
    "iso:country":"GB",
    "wof:name":"WV7 3NW",
    "wof:placetype":"postalcode"
},
  "geometry": {"coordinates":[-2.29262961136718,52.64643356693666],"type":"Point"}
}