{
  "type": "Feature",
  "properties": {
    "date:inception_lower": "1980-01-01",
    "date:inception_upper": "1980-01-01",
    "iso:country": "GB",
    "wof:name": "HU5 2RD",
    "wof:placetype": "postalcode"
  },
  "geometry": {"coordinates":[-0.356739,53.760751],"type":"Point"}
}
