{
  "type": "Feature",
  "properties": {
    "iso:country":"GB",
    "wof:name":"HU5 2RD",
    "wof:placetype":"postalcode"
},
  "geometry": {"coordinates":[-0.35673894878995,53.76075105795562],"type":"Point"}
}