{
  "type": "Feature",
  "properties": {
    "iso:country":"GB",
    "wof:name":"TA21 0NG",
    "wof:placetype":"postalcode"
},
  "geometry": {"coordinates":[-3.33512551618649,50.9730794507537],"type":"Point"}
}