{
  "type": "Feature",
  "properties": {
    "date:inception_lower": "2023-12-01",
    "date:inception_upper": "2023-12-01",
    "iso:country": "GB",
    "wof:name": "NR14 8YN",
    "wof:placetype": "postalcode"
  },
  "geometry": {"coordinates":[1.328902,52.580915],"type":"Point"}
}
