{
  "type": "Feature",
  "properties": {
    "date:inception_lower": "1980-01-01",
    "date:inception_upper": "1980-01-01",
    "iso:country": "GB",
    "wof:name": "CH8 8RU",
    "wof:placetype": "postalcode"
  },
  "geometry": {"coordinates":[-3.304057,53.280781],"type":"Point"}
}
