{
  "type": "Feature",
  "properties": {
    "iso:country":"GB",
    "wof:name":"CH8 8RU",
    "wof:placetype":"postalcode"
},
  "geometry": {"coordinates":[-3.30405615053162,53.28076469161733],"type":"Point"}
}