{
  "type": "Feature",
  "properties": {
    "iso:country": "GB",
    "wof:name": "CH8 8RU",
    "wof:placetype": "postalcode"
  },
  "geometry": {"coordinates":[-3.304056,53.280765],"type":"Point"}
}
