{
  "type": "Feature",
  "properties": {
    "iso:country":"GB",
    "wof:name":"BL3 4SF",
    "wof:placetype":"postalcode"
},
  "geometry": {"coordinates":[-2.48398919676122,53.55635702407957],"type":"Point"}
}