{
  "type": "Feature",
  "properties": {
    "date:inception_lower": "2007-01-01",
    "date:inception_upper": "2007-01-01",
    "iso:country": "GB",
    "wof:name": "BL3 4SF",
    "wof:placetype": "postalcode"
  },
  "geometry": {"coordinates":[-2.483989,53.556357],"type":"Point"}
}
