{
  "type": "Feature",
  "properties": {
    "iso:country": "GB",
    "wof:name": "BS16 2FJ",
    "wof:placetype": "postalcode"
  },
  "geometry": {"coordinates":[-2.5285,51.484962],"type":"Point"}
}
