{
  "type": "Feature",
  "properties": {
    "date:inception_lower": "1997-12-01",
    "date:inception_upper": "1997-12-01",
    "iso:country": "GB",
    "wof:name": "BS30 6HX",
    "wof:placetype": "postalcode"
  },
  "geometry": {"coordinates":[-2.46882,51.430213],"type":"Point"}
}
