{
  "type": "Feature",
  "properties": {
    "iso:country": "GB",
    "wof:name": "PE33 9GP",
    "wof:placetype": "postalcode"
  },
  "geometry": {"coordinates":[0.55028,52.548651],"type":"Point"}
}
