{
  "type": "Feature",
  "properties": {
    "date:inception_lower": "2012-05-01",
    "date:inception_upper": "2012-05-01",
    "iso:country": "GB",
    "wof:name": "PE33 9GP",
    "wof:placetype": "postalcode"
  },
  "geometry": {"coordinates":[0.55028,52.548651],"type":"Point"}
}
