{
  "type": "Feature",
  "properties": {
    "iso:country": "GB",
    "wof:name": "SM7 1DD",
    "wof:placetype": "postalcode"
  },
  "geometry": {"coordinates":[-0.224001,51.322156],"type":"Point"}
}
