{
  "type": "Feature",
  "properties": {
    "iso:country":"GB",
    "wof:name":"WF10 4TN",
    "wof:placetype":"postalcode"
},
  "geometry": {"coordinates":[-1.3470163711315,53.71219674901143],"type":"Point"}
}