{
  "type": "Feature",
  "properties": {
    "iso:country": "GB",
    "wof:name": "RH4 3BN",
    "wof:placetype": "postalcode"
  },
  "geometry": {"coordinates":[-0.336846,51.224175],"type":"Point"}
}
