{
  "type": "Feature",
  "properties": {
    "iso:country":"GB",
    "wof:name":"LU2 8TL",
    "wof:placetype":"postalcode"
},
  "geometry": {"coordinates":[-0.37368149437039,51.8914543544783],"type":"Point"}
}