{
  "type": "Feature",
  "properties": {
    "iso:country": "GB",
    "wof:name": "NN14 2GE",
    "wof:placetype": "postalcode"
  },
  "geometry": {"coordinates":[-0.812169,52.445592],"type":"Point"}
}
