{
  "type": "Feature",
  "properties": {
    "iso:country":"GB",
    "wof:name":"SG2 9JF",
    "wof:placetype":"postalcode"
},
  "geometry": {"coordinates":[-0.16900780636539,51.89710675637335],"type":"Point"}
}