{
  "type": "Feature",
  "properties": {
    "date:inception_lower": "2019-04-01",
    "date:inception_upper": "2019-04-01",
    "iso:country": "GB",
    "wof:name": "ME1 3WS",
    "wof:placetype": "postalcode"
  },
  "geometry": {"coordinates":[0.463509,51.3408],"type":"Point"}
}
