{
  "type": "Feature",
  "properties": {
    "date:inception_lower": "2002-11-01",
    "date:inception_upper": "2002-11-01",
    "iso:country": "GB",
    "wof:name": "NR11 6BF",
    "wof:placetype": "postalcode"
  },
  "geometry": {"coordinates":[1.251838,52.793678],"type":"Point"}
}
