{
  "type": "Feature",
  "properties": {
    "date:inception_lower":"1980-01-01",
    "date:inception_upper":"1980-01-31",
    "iso:country":"GB",
    "wof:name":"LS26 0PD",
    "wof:placetype":"postalcode"
},
  "geometry": {"coordinates":[-1.482078,53.752557],"type":"Point"}
}