{
  "type": "Feature",
  "properties": {
    "iso:country":"GB",
    "wof:name":"WN3 5BA",
    "wof:placetype":"postalcode"
},
  "geometry": {"coordinates":[-2.63565993743558,53.53975515705793],"type":"Point"}
}