{
  "type": "Feature",
  "properties": {
    "iso:country": "GB",
    "wof:name": "WN3 5BA",
    "wof:placetype": "postalcode"
  },
  "geometry": {"coordinates":[-2.63566,53.53977],"type":"Point"}
}
