{
  "type": "Feature",
  "properties": {
    "iso:country":"GB",
    "wof:name":"RG7 3JQ",
    "wof:placetype":"postalcode"
},
  "geometry": {"coordinates":[-1.0672287363184,51.39340173944844],"type":"Point"}
}