{
  "type": "Feature",
  "properties": {
    "iso:country": "GB",
    "wof:name": "RG7 3JQ",
    "wof:placetype": "postalcode"
  },
  "geometry": {"coordinates":[-1.067229,51.393402],"type":"Point"}
}
