{
  "type": "Feature",
  "properties": {
    "iso:country":"GB",
    "wof:name":"DH6 5FA",
    "wof:placetype":"postalcode"
},
  "geometry": {"coordinates":[-1.51673801239591,54.73855478753705],"type":"Point"}
}