{
  "type": "Feature",
  "properties": {
    "date:inception_lower": "2015-12-01",
    "date:inception_upper": "2015-12-01",
    "iso:country": "GB",
    "wof:name": "DH6 5FA",
    "wof:placetype": "postalcode"
  },
  "geometry": {"coordinates":[-1.516883,54.739023],"type":"Point"}
}
