{
  "type": "Feature",
  "properties": {
    "iso:country":"GB",
    "wof:name":"CW8 1PP",
    "wof:placetype":"postalcode"
},
  "geometry": {"coordinates":[-2.53446090161468,53.23907557628996],"type":"Point"}
}