{
  "type": "Feature",
  "properties": {
    "date:inception_lower":"1999-12-01",
    "date:inception_upper":"1999-12-31",
    "iso:country":"GB",
    "wof:name":"MK44 3AR",
    "wof:placetype":"postalcode"
},
  "geometry": {"coordinates":[-0.29182,52.205054],"type":"Point"}
}