{
  "type": "Feature",
  "properties": {
    "iso:country": "GB",
    "wof:name": "MK44 3AR",
    "wof:placetype": "postalcode"
  },
  "geometry": {"coordinates":[-0.29182,52.205054],"type":"Point"}
}
