{
  "type": "Feature",
  "properties": {
    "iso:country":"GB",
    "wof:name":"WD19 7DE",
    "wof:placetype":"postalcode"
},
  "geometry": {"coordinates":[-0.39616533563968,51.62925392284443],"type":"Point"}
}