{
  "type": "Feature",
  "properties": {
    "iso:country":"GB",
    "wof:name":"SL3 9LH",
    "wof:placetype":"postalcode"
},
  "geometry": {"coordinates":[-0.56635807069656,51.48587461751947],"type":"Point"}
}