{
  "type": "Feature",
  "properties": {
    "iso:country": "GB",
    "wof:name": "SL3 9LH",
    "wof:placetype": "postalcode"
  },
  "geometry": {"coordinates":[-0.566358,51.485875],"type":"Point"}
}
