{
  "type": "Feature",
  "properties": {
    "iso:country":"GB",
    "wof:name":"PE6 0AE",
    "wof:placetype":"postalcode"
},
  "geometry": {"coordinates":[-0.16842836652883,52.66921718539611],"type":"Point"}
}