{
  "type": "Feature",
  "properties": {
    "date:inception_lower": "1981-06-01",
    "date:inception_upper": "1981-06-01",
    "iso:country": "GB",
    "wof:name": "PE6 0AE",
    "wof:placetype": "postalcode"
  },
  "geometry": {"coordinates":[-0.168428,52.669217],"type":"Point"}
}
