{
  "type": "Feature",
  "properties": {
    "iso:country": "GB",
    "wof:name": "PE6 0AE",
    "wof:placetype": "postalcode"
  },
  "geometry": {"coordinates":[-0.168428,52.669217],"type":"Point"}
}
