{
  "type": "Feature",
  "properties": {
    "iso:country": "GB",
    "wof:name": "DY11 7ND",
    "wof:placetype": "postalcode"
  },
  "geometry": {"coordinates":[-2.270579,52.375736],"type":"Point"}
}
