{
  "type": "Feature",
  "properties": {
    "date:inception_lower": "1984-02-01",
    "date:inception_upper": "1984-02-01",
    "iso:country": "GB",
    "wof:name": "DY11 7ND",
    "wof:placetype": "postalcode"
  },
  "geometry": {"coordinates":[-2.270579,52.375736],"type":"Point"}
}
