{
  "type": "Feature",
  "properties": {
    "iso:country": "GB",
    "wof:name": "LE67 9NA",
    "wof:placetype": "postalcode"
  },
  "geometry": {"coordinates":[-1.268772,52.684654],"type":"Point"}
}
