{
  "type": "Feature",
  "properties": {
    "iso:country": "GB",
    "wof:name": "TS25 4JQ",
    "wof:placetype": "postalcode"
  },
  "geometry": {"coordinates":[-1.237289,54.670024],"type":"Point"}
}
