{
  "type": "Feature",
  "properties": {
    "iso:country": "GB",
    "wof:name": "PE30 3TR",
    "wof:placetype": "postalcode"
  },
  "geometry": {"coordinates":[0.457984,52.773395],"type":"Point"}
}
