{
  "type": "Feature",
  "properties": {
    "iso:country":"GB",
    "wof:name":"B65 9EB",
    "wof:placetype":"postalcode"
},
  "geometry": {"coordinates":[-2.04195985269217,52.49097639509483],"type":"Point"}
}