{
  "type": "Feature",
  "properties": {
    "iso:country":"GB",
    "wof:name":"SS1 3EE",
    "wof:placetype":"postalcode"
},
  "geometry": {"coordinates":[0.74644982389951,51.53747788531514],"type":"Point"}
}