{
  "type": "Feature",
  "properties": {
    "date:inception_lower": "1980-01-01",
    "date:inception_upper": "1980-01-01",
    "iso:country": "GB",
    "wof:name": "TQ9 6DY",
    "wof:placetype": "postalcode"
  },
  "geometry": {"coordinates":[-3.742203,50.44083],"type":"Point"}
}
