{
  "type": "Feature",
  "properties": {
    "date:inception_lower": "1980-01-01",
    "date:inception_upper": "1980-01-01",
    "iso:country": "GB",
    "wof:name": "DN6 8BJ",
    "wof:placetype": "postalcode"
  },
  "geometry": {"coordinates":[-1.190163,53.588583],"type":"Point"}
}
