{
  "type": "Feature",
  "properties": {
    "date:inception_lower": "1997-12-01",
    "date:inception_upper": "1997-12-01",
    "iso:country": "GB",
    "wof:name": "WF5 0DP",
    "wof:placetype": "postalcode"
  },
  "geometry": {"coordinates":[-1.574618,53.66987],"type":"Point"}
}
