{
  "type": "Feature",
  "properties": {
    "iso:country": "GB",
    "wof:name": "WF5 0DP",
    "wof:placetype": "postalcode"
  },
  "geometry": {"coordinates":[-1.574618,53.66987],"type":"Point"}
}
