{
  "type": "Feature",
  "properties": {
    "iso:country":"GB",
    "wof:name":"WF5 0DP",
    "wof:placetype":"postalcode"
},
  "geometry": {"coordinates":[-1.5746181969786,53.6698704298813],"type":"Point"}
}