{
  "type": "Feature",
  "properties": {
    "iso:country":"GB",
    "wof:name":"LN1 3AN",
    "wof:placetype":"postalcode"
},
  "geometry": {"coordinates":[-0.53872122328563,53.23539307369562],"type":"Point"}
}