{
  "type": "Feature",
  "properties": {
    "iso:country":"GB",
    "wof:name":"OX29 8QF",
    "wof:placetype":"postalcode"
},
  "geometry": {"coordinates":[-1.43072341843387,51.85392169746407],"type":"Point"}
}