{
  "type": "Feature",
  "properties": {
    "iso:country": "GB",
    "wof:name": "BL6 7JN",
    "wof:placetype": "postalcode"
  },
  "geometry": {"coordinates":[-2.553232,53.60268],"type":"Point"}
}
