{
  "type": "Feature",
  "properties": {
    "iso:country":"GB",
    "wof:name":"BL6 7JN",
    "wof:placetype":"postalcode"
},
  "geometry": {"coordinates":[-2.55323239246147,53.60267952568719],"type":"Point"}
}