{
  "type": "Feature",
  "properties": {
    "iso:country":"GB",
    "wof:name":"OL8 2AX",
    "wof:placetype":"postalcode"
},
  "geometry": {"coordinates":[-2.10533470828644,53.53565570875401],"type":"Point"}
}