{
  "type": "Feature",
  "properties": {
    "iso:country": "GB",
    "wof:name": "G33 6JU",
    "wof:placetype": "postalcode"
  },
  "geometry": {"coordinates":[-4.159832,55.886864],"type":"Point"}
}
