{
  "type": "Feature",
  "properties": {
    "date:inception_lower":"1980-01-01",
    "date:inception_upper":"1980-01-31",
    "iso:country":"GB",
    "wof:name":"G33 6JU",
    "wof:placetype":"postalcode"
},
  "geometry": {"coordinates":[-4.159832,55.886864],"type":"Point"}
}