{
  "type": "Feature",
  "properties": {
    "iso:country": "GB",
    "wof:name": "LL24 0TW",
    "wof:placetype": "postalcode"
  },
  "geometry": {"coordinates":[-3.642439,53.041415],"type":"Point"}
}
