{
  "type": "Feature",
  "properties": {
    "iso:country":"GB",
    "wof:name":"S73 8AS",
    "wof:placetype":"postalcode"
},
  "geometry": {"coordinates":[-1.38867819384133,53.53137267747938],"type":"Point"}
}