{
  "type": "Feature",
  "properties": {
    "date:inception_lower":"1998-12-01",
    "date:inception_upper":"1998-12-31",
    "iso:country":"GB",
    "wof:name":"NE63 9EP",
    "wof:placetype":"postalcode"
},
  "geometry": {"coordinates":[-1.554642,55.181581],"type":"Point"}
}