{
  "type": "Feature",
  "properties": {
    "iso:country":"GB",
    "wof:name":"NE63 9EP",
    "wof:placetype":"postalcode"
},
  "geometry": {"coordinates":[-1.55464165516767,55.18158092213213],"type":"Point"}
}