{
  "type": "Feature",
  "properties": {
    "iso:country": "GB",
    "wof:name": "SY7 9AB",
    "wof:placetype": "postalcode"
  },
  "geometry": {"coordinates":[-2.855409,52.432452],"type":"Point"}
}
