{
  "type": "Feature",
  "properties": {
    "iso:country": "GB",
    "wof:name": "CF43 4TA",
    "wof:placetype": "postalcode"
  },
  "geometry": {"coordinates":[-3.467451,51.666468],"type":"Point"}
}
