{
  "type": "Feature",
  "properties": {
    "date:inception_lower":"1980-01-01",
    "date:inception_upper":"1980-01-31",
    "iso:country":"GB",
    "wof:name":"CF43 4TA",
    "wof:placetype":"postalcode"
},
  "geometry": {"coordinates":[-3.467451,51.666468],"type":"Point"}
}