{
  "type": "Feature",
  "properties": {
    "iso:country": "GB",
    "wof:name": "ST9 9HL",
    "wof:placetype": "postalcode"
  },
  "geometry": {"coordinates":[-2.113842,53.079004],"type":"Point"}
}
