{
  "type": "Feature",
  "properties": {
    "iso:country":"GB",
    "wof:name":"CO10 8EF",
    "wof:placetype":"postalcode"
},
  "geometry": {"coordinates":[0.53750274316092,52.11353091532409],"type":"Point"}
}