{
  "type": "Feature",
  "properties": {
    "date:inception_lower": "2021-01-01",
    "date:inception_upper": "2021-01-01",
    "iso:country": "GB",
    "wof:name": "EX6 7BT",
    "wof:placetype": "postalcode"
  },
  "geometry": {"coordinates":[-3.54247,50.660824],"type":"Point"}
}
