{
  "type": "Feature",
  "properties": {
    "date:inception_lower":"1980-01-01",
    "date:inception_upper":"1980-01-31",
    "iso:country":"GB",
    "wof:name":"PA14 6HL",
    "wof:placetype":"postalcode"
},
  "geometry": {"coordinates":[-4.663471,55.922815],"type":"Point"}
}