{
  "type": "Feature",
  "properties": {
    "date:inception_lower": "1980-01-01",
    "date:inception_upper": "1980-01-01",
    "iso:country": "GB",
    "wof:name": "SA45 9RF",
    "wof:placetype": "postalcode"
  },
  "geometry": {"coordinates":[-4.367602,52.211089],"type":"Point"}
}
