{
  "type": "Feature",
  "properties": {
    "iso:country": "GB",
    "wof:name": "NG7 2BE",
    "wof:placetype": "postalcode"
  },
  "geometry": {"coordinates":[-1.180808,52.953844],"type":"Point"}
}
