{
  "type": "Feature",
  "properties": {
    "iso:country":"GB",
    "wof:name":"NG7 2BE",
    "wof:placetype":"postalcode"
},
  "geometry": {"coordinates":[-1.18039952473854,52.9543688961194],"type":"Point"}
}