{
  "type": "Feature",
  "properties": {
    "iso:country": "GB",
    "wof:name": "CV37 8BZ",
    "wof:placetype": "postalcode"
  },
  "geometry": {"coordinates":[-1.642508,52.106973],"type":"Point"}
}
