{
  "type": "Feature",
  "properties": {
    "iso:country":"GB",
    "wof:name":"CV37 8BZ",
    "wof:placetype":"postalcode"
},
  "geometry": {"coordinates":[-1.64250852299185,52.10697332649637],"type":"Point"}
}