{
  "type": "Feature",
  "properties": {
    "date:inception_lower": "1981-06-01",
    "date:inception_upper": "1981-06-01",
    "iso:country": "GB",
    "wof:name": "SN7 8RD",
    "wof:placetype": "postalcode"
  },
  "geometry": {"coordinates":[-1.517019,51.6928],"type":"Point"}
}
