{
  "type": "Feature",
  "properties": {
    "iso:country":"GB",
    "wof:name":"SN7 8RD",
    "wof:placetype":"postalcode"
},
  "geometry": {"coordinates":[-1.51701880480634,51.69280000130048],"type":"Point"}
}