{
  "type": "Feature",
  "properties": {
    "iso:country": "GB",
    "wof:name": "CA7 9JG",
    "wof:placetype": "postalcode"
  },
  "geometry": {"coordinates":[-3.151235,54.829133],"type":"Point"}
}
