{
  "type": "Feature",
  "properties": {
    "date:inception_lower": "1980-01-01",
    "date:inception_upper": "1980-01-01",
    "iso:country": "GB",
    "wof:name": "CA7 9JG",
    "wof:placetype": "postalcode"
  },
  "geometry": {"coordinates":[-3.151235,54.829133],"type":"Point"}
}
