{
  "type": "Feature",
  "properties": {
    "iso:country": "GB",
    "wof:name": "OX25 5BH",
    "wof:placetype": "postalcode"
  },
  "geometry": {"coordinates":[-1.260286,51.92795],"type":"Point"}
}
