{
  "type": "Feature",
  "properties": {
    "iso:country":"GB",
    "wof:name":"OX18 1GG",
    "wof:placetype":"postalcode"
},
  "geometry": {"coordinates":[-1.59214406487626,51.77049853063448],"type":"Point"}
}