{
  "type": "Feature",
  "properties": {
    "date:inception_lower": "2004-09-01",
    "date:inception_upper": "2004-09-01",
    "iso:country": "GB",
    "wof:name": "OX18 1GG",
    "wof:placetype": "postalcode"
  },
  "geometry": {"coordinates":[-1.592144,51.770499],"type":"Point"}
}
