{
  "type": "Feature",
  "properties": {
    "iso:country": "GB",
    "wof:name": "OX18 1GG",
    "wof:placetype": "postalcode"
  },
  "geometry": {"coordinates":[-1.592144,51.770499],"type":"Point"}
}
