{
  "type": "Feature",
  "properties": {
    "iso:country": "GB",
    "wof:name": "NR21 9EY",
    "wof:placetype": "postalcode"
  },
  "geometry": {"coordinates":[0.839612,52.836089],"type":"Point"}
}
