{
  "type": "Feature",
  "properties": {
    "iso:country": "GB",
    "wof:name": "LE10 0AX",
    "wof:placetype": "postalcode"
  },
  "geometry": {"coordinates":[-1.376328,52.542482],"type":"Point"}
}
