{
  "type": "Feature",
  "properties": {
    "iso:country":"GB",
    "wof:name":"LE10 0AX",
    "wof:placetype":"postalcode"
},
  "geometry": {"coordinates":[-1.37632850543382,52.54248182384166],"type":"Point"}
}