{
  "type": "Feature",
  "properties": {
    "date:inception_lower": "1980-01-01",
    "date:inception_upper": "1980-01-01",
    "iso:country": "GB",
    "wof:name": "ME9 8ES",
    "wof:placetype": "postalcode"
  },
  "geometry": {"coordinates":[0.691788,51.311778],"type":"Point"}
}
