{
  "type": "Feature",
  "properties": {
    "iso:country":"GB",
    "wof:name":"ME9 8ES",
    "wof:placetype":"postalcode"
},
  "geometry": {"coordinates":[0.69178752233691,51.31177837824078],"type":"Point"}
}