{
  "type": "Feature",
  "properties": {
    "iso:country": "GB",
    "wof:name": "RG24 9AR",
    "wof:placetype": "postalcode"
  },
  "geometry": {"coordinates":[-1.072304,51.283794],"type":"Point"}
}
