{
  "type": "Feature",
  "properties": {
    "iso:country":"GB",
    "wof:name":"RG24 9AR",
    "wof:placetype":"postalcode"
},
  "geometry": {"coordinates":[-1.07230359068333,51.28379392660975],"type":"Point"}
}