{
  "type": "Feature",
  "properties": {
    "iso:country":"GB",
    "wof:name":"SN9 5HN",
    "wof:placetype":"postalcode"
},
  "geometry": {"coordinates":[-1.76682926180291,51.33337192580063],"type":"Point"}
}