{
  "type": "Feature",
  "properties": {
    "date:inception_lower": "2022-04-01",
    "date:inception_upper": "2022-04-01",
    "iso:country": "GB",
    "wof:name": "ME10 4GA",
    "wof:placetype": "postalcode"
  },
  "geometry": {"coordinates":[0.763354,51.336807],"type":"Point"}
}
