{
  "type": "Feature",
  "properties": {
    "iso:country":"GB",
    "wof:name":"CB7 5QR",
    "wof:placetype":"postalcode"
},
  "geometry": {"coordinates":[0.4146291100551,52.34009334892011],"type":"Point"}
}