{
  "type": "Feature",
  "properties": {
    "iso:country": "GB",
    "wof:name": "GL51 7JE",
    "wof:placetype": "postalcode"
  },
  "geometry": {"coordinates":[-2.103065,51.910474],"type":"Point"}
}
