{
  "type": "Feature",
  "properties": {
    "iso:country":"GB",
    "wof:name":"PE12 8DY",
    "wof:placetype":"postalcode"
},
  "geometry": {"coordinates":[0.03773250012764,52.85662337330068],"type":"Point"}
}