{
  "type": "Feature",
  "properties": {
    "date:inception_lower":"1980-01-01",
    "date:inception_upper":"1980-01-31",
    "iso:country":"GB",
    "wof:name":"DY8 3UW",
    "wof:placetype":"postalcode"
},
  "geometry": {"coordinates":[-2.161369,52.453853],"type":"Point"}
}