{
  "type": "Feature",
  "properties": {
    "iso:country": "GB",
    "wof:name": "DY8 3UW",
    "wof:placetype": "postalcode"
  },
  "geometry": {"coordinates":[-2.161369,52.453853],"type":"Point"}
}
