{
  "type": "Feature",
  "properties": {
    "iso:country": "GB",
    "wof:name": "ME15 9QP",
    "wof:placetype": "postalcode"
  },
  "geometry": {"coordinates":[0.530699,51.249601],"type":"Point"}
}
