{
  "type": "Feature",
  "properties": {
    "iso:country":"GB",
    "wof:name":"SA73 1PA",
    "wof:placetype":"postalcode"
},
  "geometry": {"coordinates":[-4.92999104028961,51.70942935543782],"type":"Point"}
}