{
  "type": "Feature",
  "properties": {
    "iso:country": "GB",
    "wof:name": "SA73 1PA",
    "wof:placetype": "postalcode"
  },
  "geometry": {"coordinates":[-4.929991,51.709429],"type":"Point"}
}
