{
  "type": "Feature",
  "properties": {
    "date:inception_lower": "1990-07-01",
    "date:inception_upper": "1990-07-01",
    "iso:country": "GB",
    "wof:name": "MK15 9JW",
    "wof:placetype": "postalcode"
  },
  "geometry": {"coordinates":[-0.730781,52.063471],"type":"Point"}
}
