{
  "type": "Feature",
  "properties": {
    "iso:country":"GB",
    "wof:name":"PO9 4ES",
    "wof:placetype":"postalcode"
},
  "geometry": {"coordinates":[-0.99555596406782,50.87788230219216],"type":"Point"}
}