{
  "type": "Feature",
  "properties": {
    "iso:country": "GB",
    "wof:name": "PO9 4ES",
    "wof:placetype": "postalcode"
  },
  "geometry": {"coordinates":[-0.99554,50.877873],"type":"Point"}
}
