{
  "type": "Feature",
  "properties": {
    "date:inception_lower": "1990-07-01",
    "date:inception_upper": "1990-07-01",
    "iso:country": "GB",
    "wof:name": "MK46 4AU",
    "wof:placetype": "postalcode"
  },
  "geometry": {"coordinates":[-0.700282,52.151737],"type":"Point"}
}
