{
  "type": "Feature",
  "properties": {
    "iso:country":"GB",
    "wof:name":"NE65 9UR",
    "wof:placetype":"postalcode"
},
  "geometry": {"coordinates":[-1.6146007085275,55.30486438280388],"type":"Point"}
}