{
  "type": "Feature",
  "properties": {
    "date:inception_lower": "1980-01-01",
    "date:inception_upper": "1980-01-01",
    "iso:country": "GB",
    "wof:name": "EX10 0QN",
    "wof:placetype": "postalcode"
  },
  "geometry": {"coordinates":[-3.200797,50.735805],"type":"Point"}
}
