{
  "type": "Feature",
  "properties": {
    "iso:country": "GB",
    "wof:name": "EX10 0QN",
    "wof:placetype": "postalcode"
  },
  "geometry": {"coordinates":[-3.200797,50.735805],"type":"Point"}
}
