{
  "type": "Feature",
  "properties": {
    "date:inception_lower": "2020-11-01",
    "date:inception_upper": "2020-11-01",
    "iso:country": "GB",
    "wof:name": "TR8 5FU",
    "wof:placetype": "postalcode"
  },
  "geometry": {"coordinates":[-5.108085,50.400333],"type":"Point"}
}
