{
  "type": "Feature",
  "properties": {
    "iso:country":"GB",
    "wof:name":"BB7 4AW",
    "wof:placetype":"postalcode"
},
  "geometry": {"coordinates":[-2.35379708212503,53.89247448368367],"type":"Point"}
}