{
  "type": "Feature",
  "properties": {
    "iso:country":"GB",
    "wof:name":"B43 7AY",
    "wof:placetype":"postalcode"
},
  "geometry": {"coordinates":[-1.93567363741071,52.55910096653349],"type":"Point"}
}