{
  "type": "Feature",
  "properties": {
    "iso:country":"GB",
    "wof:name":"NE28 7RB",
    "wof:placetype":"postalcode"
},
  "geometry": {"coordinates":[-1.53450527890025,54.99979740853436],"type":"Point"}
}