{
  "type": "Feature",
  "properties": {
    "iso:country":"GB",
    "wof:name":"CB7 4TF",
    "wof:placetype":"postalcode"
},
  "geometry": {"coordinates":[0.35099682451161,52.45914546661392],"type":"Point"}
}