{
  "type": "Feature",
  "properties": {
    "date:inception_lower": "1980-01-01",
    "date:inception_upper": "1980-01-01",
    "iso:country": "GB",
    "wof:name": "CB7 4TF",
    "wof:placetype": "postalcode"
  },
  "geometry": {"coordinates":[0.351669,52.458925],"type":"Point"}
}
