{
  "type": "Feature",
  "properties": {
    "date:inception_lower": "2020-10-01",
    "date:inception_upper": "2020-10-01",
    "iso:country": "GB",
    "wof:name": "CH7 6FZ",
    "wof:placetype": "postalcode"
  },
  "geometry": {"coordinates":[-3.107302,53.175744],"type":"Point"}
}
