{
  "type": "Feature",
  "properties": {
    "date:inception_lower": "2014-06-01",
    "date:inception_upper": "2014-06-01",
    "iso:country": "GB",
    "wof:name": "EH5 2QQ",
    "wof:placetype": "postalcode"
  },
  "geometry": {"coordinates":[-3.228323,55.972404],"type":"Point"}
}
