{
  "type": "Feature",
  "properties": {
    "iso:country":"GB",
    "wof:name":"EX6 7BQ",
    "wof:placetype":"postalcode"
},
  "geometry": {"coordinates":[-3.65355765573948,50.70000725317131],"type":"Point"}
}