{
  "type": "Feature",
  "properties": {
    "iso:country": "GB",
    "wof:name": "EX6 7BQ",
    "wof:placetype": "postalcode"
  },
  "geometry": {"coordinates":[-3.653558,50.700007],"type":"Point"}
}
