{
  "type": "Feature",
  "properties": {
    "iso:country":"GB",
    "wof:name":"ST7 3UD",
    "wof:placetype":"postalcode"
},
  "geometry": {"coordinates":[-2.29598695337855,53.11554491673182],"type":"Point"}
}