{
  "type": "Feature",
  "properties": {
    "iso:country":"GB",
    "wof:name":"ME4 4PB",
    "wof:placetype":"postalcode"
},
  "geometry": {"coordinates":[0.53514774327327,51.37931928760742],"type":"Point"}
}