{
  "type": "Feature",
  "properties": {
    "date:inception_lower": "1980-01-01",
    "date:inception_upper": "1980-01-01",
    "iso:country": "GB",
    "wof:name": "DH1 4PR",
    "wof:placetype": "postalcode"
  },
  "geometry": {"coordinates":[-1.580215,54.776166],"type":"Point"}
}
