{
  "type": "Feature",
  "properties": {
    "iso:country":"GB",
    "wof:name":"DH1 4PR",
    "wof:placetype":"postalcode"
},
  "geometry": {"coordinates":[-1.58021503830689,54.77616624031243],"type":"Point"}
}