{
  "type": "Feature",
  "properties": {
    "iso:country": "GB",
    "wof:name": "EX2 5QN",
    "wof:placetype": "postalcode"
  },
  "geometry": {"coordinates":[-3.481512,50.720002],"type":"Point"}
}
