{
  "type": "Feature",
  "properties": {
    "iso:country":"GB",
    "wof:name":"EX2 5QN",
    "wof:placetype":"postalcode"
},
  "geometry": {"coordinates":[-3.48151237667023,50.72000224014044],"type":"Point"}
}