{
  "type": "Feature",
  "properties": {
    "date:inception_lower":"1997-06-01",
    "date:inception_upper":"1997-06-30",
    "iso:country":"GB",
    "wof:name":"SG1 4XB",
    "wof:placetype":"postalcode"
},
  "geometry": {"coordinates":[-0.200588,51.922286],"type":"Point"}
}