{
  "type": "Feature",
  "properties": {
    "iso:country":"GB",
    "wof:name":"SG1 4XB",
    "wof:placetype":"postalcode"
},
  "geometry": {"coordinates":[-0.20058807419011,51.92228563758889],"type":"Point"}
}