{
  "type": "Feature",
  "properties": {
    "iso:country": "GB",
    "wof:name": "SG1 4XB",
    "wof:placetype": "postalcode"
  },
  "geometry": {"coordinates":[-0.200588,51.922286],"type":"Point"}
}
