{
  "type": "Feature",
  "properties": {
    "iso:country": "GB",
    "wof:name": "SR5 5LQ",
    "wof:placetype": "postalcode"
  },
  "geometry": {"coordinates":[-1.422097,54.927685],"type":"Point"}
}
