{
  "type": "Feature",
  "properties": {
    "iso:country":"GB",
    "wof:name":"SR5 5LQ",
    "wof:placetype":"postalcode"
},
  "geometry": {"coordinates":[-1.42209675536474,54.92768536517031],"type":"Point"}
}