{
  "type": "Feature",
  "properties": {
    "iso:country":"GB",
    "wof:name":"PL15 8PU",
    "wof:placetype":"postalcode"
},
  "geometry": {"coordinates":[-4.58606645188086,50.62475559408366],"type":"Point"}
}