{
  "type": "Feature",
  "properties": {
    "date:inception_lower": "1980-01-01",
    "date:inception_upper": "1980-01-01",
    "iso:country": "GB",
    "wof:name": "PL15 8PU",
    "wof:placetype": "postalcode"
  },
  "geometry": {"coordinates":[-4.586066,50.624756],"type":"Point"}
}
