{
  "type": "Feature",
  "properties": {
    "iso:country":"GB",
    "wof:name":"NN3 6PH",
    "wof:placetype":"postalcode"
},
  "geometry": {"coordinates":[-0.85731779010492,52.26537045087098],"type":"Point"}
}