{
  "type": "Feature",
  "properties": {
    "date:inception_lower":"1980-01-01",
    "date:inception_upper":"1980-01-31",
    "iso:country":"GB",
    "wof:name":"HR1 4RW",
    "wof:placetype":"postalcode"
},
  "geometry": {"coordinates":[-2.567779,51.993636],"type":"Point"}
}