{
  "type": "Feature",
  "properties": {
    "iso:country":"GB",
    "wof:name":"HR1 4RW",
    "wof:placetype":"postalcode"
},
  "geometry": {"coordinates":[-2.5677785778557,51.99363622587752],"type":"Point"}
}