{
  "type": "Feature",
  "properties": {
    "iso:country":"GB",
    "wof:name":"SK17 7SX",
    "wof:placetype":"postalcode"
},
  "geometry": {"coordinates":[-1.8960908000872,53.25361408936826],"type":"Point"}
}