{
  "type": "Feature",
  "properties": {
    "date:inception_lower":"2007-10-01",
    "date:inception_upper":"2007-10-31",
    "iso:country":"GB",
    "wof:name":"TN23 7US",
    "wof:placetype":"postalcode"
},
  "geometry": {"coordinates":[0.866845,51.139077],"type":"Point"}
}