{
  "type": "Feature",
  "properties": {
    "iso:country": "GB",
    "wof:name": "TN23 7US",
    "wof:placetype": "postalcode"
  },
  "geometry": {"coordinates":[0.866845,51.139077],"type":"Point"}
}
