{
  "type": "Feature",
  "properties": {
    "iso:country":"GB",
    "wof:name":"AL2 1BX",
    "wof:placetype":"postalcode"
},
  "geometry": {"coordinates":[-0.27847741500205,51.71674429569362],"type":"Point"}
}