{
  "type": "Feature",
  "properties": {
    "iso:country":"GB",
    "wof:name":"CH7 4NN",
    "wof:placetype":"postalcode"
},
  "geometry": {"coordinates":[-3.12812337906487,53.11217501272479],"type":"Point"}
}