{
  "type": "Feature",
  "properties": {
    "date:inception_lower": "1987-04-01",
    "date:inception_upper": "1987-04-01",
    "iso:country": "GB",
    "wof:name": "DH4 6NF",
    "wof:placetype": "postalcode"
  },
  "geometry": {"coordinates":[-1.499262,54.836986],"type":"Point"}
}
