{
  "type": "Feature",
  "properties": {
    "iso:country":"GB",
    "wof:name":"DH4 6NF",
    "wof:placetype":"postalcode"
},
  "geometry": {"coordinates":[-1.49926233246137,54.83698588337239],"type":"Point"}
}