{
  "type": "Feature",
  "properties": {
    "iso:country":"GB",
    "wof:name":"BH15 2EJ",
    "wof:placetype":"postalcode"
},
  "geometry": {"coordinates":[-1.97628736049969,50.72756348127464],"type":"Point"}
}