{
  "type": "Feature",
  "properties": {
    "iso:country": "GB",
    "wof:name": "HG2 0FF",
    "wof:placetype": "postalcode"
  },
  "geometry": {"coordinates":[-1.5602,53.984746],"type":"Point"}
}
