{
  "type": "Feature",
  "properties": {
    "iso:country":"GB",
    "wof:name":"TS6 0BN",
    "wof:placetype":"postalcode"
},
  "geometry": {"coordinates":[-1.16104340504659,54.56252937272841],"type":"Point"}
}