{
  "type": "Feature",
  "properties": {
    "iso:country": "GB",
    "wof:name": "IV27 4LG",
    "wof:placetype": "postalcode"
  },
  "geometry": {"coordinates":[-5.242938,58.147076],"type":"Point"}
}
