{
  "type": "Feature",
  "properties": {
    "iso:country":"GB",
    "wof:name":"IV27 4LG",
    "wof:placetype":"postalcode"
},
  "geometry": {"coordinates":[-5.24293772147886,58.14707643149135],"type":"Point"}
}