{
  "type": "Feature",
  "properties": {
    "iso:country":"GB",
    "wof:name":"SE15 3BL",
    "wof:placetype":"postalcode"
},
  "geometry": {"coordinates":[-0.05077084488491,51.45949930342467],"type":"Point"}
}