{
  "type": "Feature",
  "properties": {
    "iso:country": "GB",
    "wof:name": "GU21 4QZ",
    "wof:placetype": "postalcode"
  },
  "geometry": {"coordinates":[-0.565961,51.324801],"type":"Point"}
}
