{
  "type": "Feature",
  "properties": {
    "iso:country":"GB",
    "wof:name":"GU21 4QZ",
    "wof:placetype":"postalcode"
},
  "geometry": {"coordinates":[-0.56596068617945,51.3248009085054],"type":"Point"}
}