{
  "type": "Feature",
  "properties": {
    "date:inception_lower": "1980-01-01",
    "date:inception_upper": "1980-01-01",
    "iso:country": "GB",
    "wof:name": "HP13 7HR",
    "wof:placetype": "postalcode"
  },
  "geometry": {"coordinates":[-0.709171,51.630711],"type":"Point"}
}
