{
  "type": "Feature",
  "properties": {
    "iso:country": "GB",
    "wof:name": "TF9 3AP",
    "wof:placetype": "postalcode"
  },
  "geometry": {"coordinates":[-2.489269,52.907274],"type":"Point"}
}
