{
  "type": "Feature",
  "properties": {
    "iso:country":"GB",
    "wof:name":"TF9 3AP",
    "wof:placetype":"postalcode"
},
  "geometry": {"coordinates":[-2.48947637432129,52.90719191015626],"type":"Point"}
}