{
  "type": "Feature",
  "properties": {
    "iso:country":"GB",
    "wof:name":"AB42 4ES",
    "wof:placetype":"postalcode"
},
  "geometry": {"coordinates":[-2.0086314443488,57.5817646778038],"type":"Point"}
}