{
  "type": "Feature",
  "properties": {
    "date:inception_lower": "1980-01-01",
    "date:inception_upper": "1980-01-01",
    "iso:country": "GB",
    "wof:name": "LL12 7NF",
    "wof:placetype": "postalcode"
  },
  "geometry": {"coordinates":[-2.979743,53.056397],"type":"Point"}
}
