{
  "type": "Feature",
  "properties": {
    "iso:country":"GB",
    "wof:name":"SN3 6HG",
    "wof:placetype":"postalcode"
},
  "geometry": {"coordinates":[-1.72828351116842,51.54546325319021],"type":"Point"}
}