{
  "type": "Feature",
  "properties": {
    "iso:country": "GB",
    "wof:name": "WF8 2NR",
    "wof:placetype": "postalcode"
  },
  "geometry": {"coordinates":[-1.301574,53.696903],"type":"Point"}
}
