{
  "type": "Feature",
  "properties": {
    "iso:country":"GB",
    "wof:name":"OX44 7TE",
    "wof:placetype":"postalcode"
},
  "geometry": {"coordinates":[-1.07923864038445,51.66532414964833],"type":"Point"}
}