{
  "type": "Feature",
  "properties": {
    "iso:country": "GB",
    "wof:name": "OX44 7TE",
    "wof:placetype": "postalcode"
  },
  "geometry": {"coordinates":[-1.079239,51.665324],"type":"Point"}
}
