{
  "type": "Feature",
  "properties": {
    "iso:country":"GB",
    "wof:name":"TN6 1UQ",
    "wof:placetype":"postalcode"
},
  "geometry": {"coordinates":[0.14916227974493,51.04975399685119],"type":"Point"}
}