{
  "type": "Feature",
  "properties": {
    "date:inception_lower":"1980-01-01",
    "date:inception_upper":"1980-01-31",
    "iso:country":"GB",
    "wof:name":"TN6 1UQ",
    "wof:placetype":"postalcode"
},
  "geometry": {"coordinates":[0.149162,51.049754],"type":"Point"}
}