{
  "type": "Feature",
  "properties": {
    "date:inception_lower": "2018-05-01",
    "date:inception_upper": "2018-05-01",
    "iso:country": "GB",
    "wof:name": "CV23 0SW",
    "wof:placetype": "postalcode"
  },
  "geometry": {"coordinates":[-1.23775,52.409802],"type":"Point"}
}
