{
  "type": "Feature",
  "properties": {
    "iso:country":"GB",
    "wof:name":"TD1 1DD",
    "wof:placetype":"postalcode"
},
  "geometry": {"coordinates":[-2.81337592241178,55.6205174197105],"type":"Point"}
}