{
  "type": "Feature",
  "properties": {
    "iso:country": "GB",
    "wof:name": "TD1 1DD",
    "wof:placetype": "postalcode"
  },
  "geometry": {"coordinates":[-2.813613,55.620281],"type":"Point"}
}
