{
  "type": "Feature",
  "properties": {
    "iso:country": "GB",
    "wof:name": "TD1 1DD",
    "wof:placetype": "postalcode"
  },
  "geometry": {"coordinates":[-2.81338,55.620517],"type":"Point"}
}
