{
  "type": "Feature",
  "properties": {
    "date:inception_lower": "1980-01-01",
    "date:inception_upper": "1980-01-01",
    "iso:country": "GB",
    "wof:name": "WS13 8NT",
    "wof:placetype": "postalcode"
  },
  "geometry": {"coordinates":[-1.762986,52.721119],"type":"Point"}
}
