{
  "type": "Feature",
  "properties": {
    "iso:country":"GB",
    "wof:name":"TN2 3SA",
    "wof:placetype":"postalcode"
},
  "geometry": {"coordinates":[0.27785067462939,51.13989599461434],"type":"Point"}
}