{
  "type": "Feature",
  "properties": {
    "iso:country":"GB",
    "wof:name":"RG17 0RW",
    "wof:placetype":"postalcode"
},
  "geometry": {"coordinates":[-1.53229095425364,51.37098469072222],"type":"Point"}
}