{
  "type": "Feature",
  "properties": {
    "date:inception_lower": "1980-01-01",
    "date:inception_upper": "1980-01-01",
    "iso:country": "GB",
    "wof:name": "RG17 0RW",
    "wof:placetype": "postalcode"
  },
  "geometry": {"coordinates":[-1.532291,51.370985],"type":"Point"}
}
