{
  "type": "Feature",
  "properties": {
    "iso:country":"GB",
    "wof:name":"NR5 8QG",
    "wof:placetype":"postalcode"
},
  "geometry": {"coordinates":[1.25336465533841,52.63734794688332],"type":"Point"}
}