{
  "type": "Feature",
  "properties": {
    "iso:country": "GB",
    "wof:name": "HD4 6BL",
    "wof:placetype": "postalcode"
  },
  "geometry": {"coordinates":[-1.793347,53.63222],"type":"Point"}
}
