{
  "type": "Feature",
  "properties": {
    "iso:country":"GB",
    "wof:name":"SA6 5PE",
    "wof:placetype":"postalcode"
},
  "geometry": {"coordinates":[-3.88226020191404,51.69926252805397],"type":"Point"}
}