{
  "type": "Feature",
  "properties": {
    "iso:country": "GB",
    "wof:name": "SA6 5PE",
    "wof:placetype": "postalcode"
  },
  "geometry": {"coordinates":[-3.88226,51.699263],"type":"Point"}
}
