{
  "type": "Feature",
  "properties": {
    "iso:country":"GB",
    "wof:name":"PL11 2BS",
    "wof:placetype":"postalcode"
},
  "geometry": {"coordinates":[-4.19574579200981,50.37485944926685],"type":"Point"}
}