{
  "type": "Feature",
  "properties": {
    "iso:country": "GB",
    "wof:name": "PL11 2BS",
    "wof:placetype": "postalcode"
  },
  "geometry": {"coordinates":[-4.195746,50.374859],"type":"Point"}
}
