{
  "type": "Feature",
  "properties": {
    "date:inception_lower":"1980-01-01",
    "date:inception_upper":"1980-01-31",
    "iso:country":"GB",
    "wof:name":"PL11 2BS",
    "wof:placetype":"postalcode"
},
  "geometry": {"coordinates":[-4.195746,50.374859],"type":"Point"}
}