{
  "type": "Feature",
  "properties": {
    "iso:country":"GB",
    "wof:name":"N1 9JA",
    "wof:placetype":"postalcode"
},
  "geometry": {"coordinates":[-0.11586947734156,51.53208142439376],"type":"Point"}
}