{
  "type": "Feature",
  "properties": {
    "date:inception_lower": "1980-01-01",
    "date:inception_upper": "1980-01-01",
    "iso:country": "GB",
    "wof:name": "N1 9JA",
    "wof:placetype": "postalcode"
  },
  "geometry": {"coordinates":[-0.115869,51.532081],"type":"Point"}
}
