{
  "type": "Feature",
  "properties": {
    "iso:country": "GB",
    "wof:name": "WS13 6GB",
    "wof:placetype": "postalcode"
  },
  "geometry": {"coordinates":[-1.806948,52.689681],"type":"Point"}
}
