{
  "type": "Feature",
  "properties": {
    "iso:country":"GB",
    "wof:name":"WS13 6GB",
    "wof:placetype":"postalcode"
},
  "geometry": {"coordinates":[-1.80694771691609,52.68968130950989],"type":"Point"}
}