{
  "type": "Feature",
  "properties": {
    "date:inception_lower":"2010-09-01",
    "date:inception_upper":"2010-09-30",
    "iso:country":"GB",
    "wof:name":"WS13 6GB",
    "wof:placetype":"postalcode"
},
  "geometry": {"coordinates":[-1.806948,52.689681],"type":"Point"}
}