{
  "type": "Feature",
  "properties": {
    "date:inception_lower": "1980-01-01",
    "date:inception_upper": "1980-01-01",
    "iso:country": "GB",
    "wof:name": "PR1 5NE",
    "wof:placetype": "postalcode"
  },
  "geometry": {"coordinates":[-2.680483,53.763937],"type":"Point"}
}
