{
  "type": "Feature",
  "properties": {
    "iso:country":"GB",
    "wof:name":"PR1 5NE",
    "wof:placetype":"postalcode"
},
  "geometry": {"coordinates":[-2.6797849379528,53.76278335555266],"type":"Point"}
}