{
  "type": "Feature",
  "properties": {
    "iso:country":"GB",
    "wof:name":"SN12 7QT",
    "wof:placetype":"postalcode"
},
  "geometry": {"coordinates":[-2.10935079553267,51.37937382022341],"type":"Point"}
}