{
  "type": "Feature",
  "properties": {
    "date:inception_lower": "1980-01-01",
    "date:inception_upper": "1980-01-01",
    "iso:country": "GB",
    "wof:name": "SN12 7QT",
    "wof:placetype": "postalcode"
  },
  "geometry": {"coordinates":[-2.109351,51.379374],"type":"Point"}
}
