{
  "type": "Feature",
  "properties": {
    "date:inception_lower": "1980-01-01",
    "date:inception_upper": "1980-01-01",
    "iso:country": "GB",
    "wof:name": "ME5 9PR",
    "wof:placetype": "postalcode"
  },
  "geometry": {"coordinates":[0.526756,51.335495],"type":"Point"}
}
