{
  "type": "Feature",
  "properties": {
    "iso:country":"GB",
    "wof:name":"M25 3JA",
    "wof:placetype":"postalcode"
},
  "geometry": {"coordinates":[-2.29278144300843,53.53067831155182],"type":"Point"}
}