{
  "type": "Feature",
  "properties": {
    "iso:country":"GB",
    "wof:name":"NE3 3TE",
    "wof:placetype":"postalcode"
},
  "geometry": {"coordinates":[-1.64830918371372,55.00863534720319],"type":"Point"}
}