{
  "type": "Feature",
  "properties": {
    "date:inception_lower":"1980-01-01",
    "date:inception_upper":"1980-01-31",
    "iso:country":"GB",
    "wof:name":"NE3 3TE",
    "wof:placetype":"postalcode"
},
  "geometry": {"coordinates":[-1.648309,55.008635],"type":"Point"}
}