{
  "type": "Feature",
  "properties": {
    "date:inception_lower": "2014-10-01",
    "date:inception_upper": "2014-10-01",
    "iso:country": "GB",
    "wof:name": "ME17 1FN",
    "wof:placetype": "postalcode"
  },
  "geometry": {"coordinates":[0.664875,51.242574],"type":"Point"}
}
