{
  "type": "Feature",
  "properties": {
    "iso:country":"GB",
    "wof:name":"YO7 2JS",
    "wof:placetype":"postalcode"
},
  "geometry": {"coordinates":[-1.26743708016846,54.31127199083689],"type":"Point"}
}