{
  "type": "Feature",
  "properties": {
    "date:inception_lower": "1995-01-01",
    "date:inception_upper": "1995-01-01",
    "iso:country": "GB",
    "wof:name": "YO7 2JS",
    "wof:placetype": "postalcode"
  },
  "geometry": {"coordinates":[-1.267437,54.311272],"type":"Point"}
}
