{
  "type": "Feature",
  "properties": {
    "iso:country":"GB",
    "wof:name":"W1U 4NJ",
    "wof:placetype":"postalcode"
},
  "geometry": {"coordinates":[-0.15143137882883,51.5187358535439],"type":"Point"}
}