{
  "type": "Feature",
  "properties": {
    "iso:country":"GB",
    "wof:name":"B9 4PX",
    "wof:placetype":"postalcode"
},
  "geometry": {"coordinates":[-1.86822638380702,52.47774955191006],"type":"Point"}
}