{
  "type": "Feature",
  "properties": {
    "iso:country":"GB",
    "wof:name":"SG2 9UF",
    "wof:placetype":"postalcode"
},
  "geometry": {"coordinates":[-0.17458083020025,51.89731023764902],"type":"Point"}
}