{
  "type": "Feature",
  "properties": {
    "iso:country":"GB",
    "wof:name":"CO11 2NU",
    "wof:placetype":"postalcode"
},
  "geometry": {"coordinates":[1.08094762480723,51.91134397870885],"type":"Point"}
}