{
  "type": "Feature",
  "properties": {
    "iso:country": "GB",
    "wof:name": "CO11 2NU",
    "wof:placetype": "postalcode"
  },
  "geometry": {"coordinates":[1.073786,51.913154],"type":"Point"}
}
