{
  "type": "Feature",
  "properties": {
    "iso:country":"GB",
    "wof:name":"DL2 2DY",
    "wof:placetype":"postalcode"
},
  "geometry": {"coordinates":[-1.53352727211345,54.48661182185772],"type":"Point"}
}