{
  "type": "Feature",
  "properties": {
    "iso:country": "GB",
    "wof:name": "DN39 6UB",
    "wof:placetype": "postalcode"
  },
  "geometry": {"coordinates":[-0.320957,53.61942],"type":"Point"}
}
