{
  "type": "Feature",
  "properties": {
    "date:inception_lower": "1980-01-01",
    "date:inception_upper": "1980-01-01",
    "iso:country": "GB",
    "wof:name": "DN39 6UB",
    "wof:placetype": "postalcode"
  },
  "geometry": {"coordinates":[-0.320957,53.61942],"type":"Point"}
}
