{
  "type": "Feature",
  "properties": {
    "iso:country": "GB",
    "wof:name": "LA2 8JH",
    "wof:placetype": "postalcode"
  },
  "geometry": {"coordinates":[-2.391018,54.116848],"type":"Point"}
}
