{
  "type": "Feature",
  "properties": {
    "date:inception_lower": "1984-02-01",
    "date:inception_upper": "1984-02-01",
    "iso:country": "GB",
    "wof:name": "LA2 8JH",
    "wof:placetype": "postalcode"
  },
  "geometry": {"coordinates":[-2.390834,54.116795],"type":"Point"}
}
