{
  "type": "Feature",
  "properties": {
    "iso:country":"GB",
    "wof:name":"B19 1DR",
    "wof:placetype":"postalcode"
},
  "geometry": {"coordinates":[-1.91553929813225,52.4973368301202],"type":"Point"}
}