{
  "type": "Feature",
  "properties": {
    "date:inception_lower": "1981-06-01",
    "date:inception_upper": "1981-06-01",
    "iso:country": "GB",
    "wof:name": "HX7 5QH",
    "wof:placetype": "postalcode"
  },
  "geometry": {"coordinates":[-1.967827,53.734352],"type":"Point"}
}
