{
  "type": "Feature",
  "properties": {
    "iso:country":"GB",
    "wof:name":"OX3 0JY",
    "wof:placetype":"postalcode"
},
  "geometry": {"coordinates":[-1.23646979450999,51.7647532085179],"type":"Point"}
}