{
  "type": "Feature",
  "properties": {
    "date:inception_lower": "1981-06-01",
    "date:inception_upper": "1981-06-01",
    "iso:country": "GB",
    "wof:name": "WS13 6BW",
    "wof:placetype": "postalcode"
  },
  "geometry": {"coordinates":[-1.818248,52.690274],"type":"Point"}
}
