{
  "type": "Feature",
  "properties": {
    "iso:country": "GB",
    "wof:name": "SS12 9RS",
    "wof:placetype": "postalcode"
  },
  "geometry": {"coordinates":[0.531051,51.605022],"type":"Point"}
}
