{
  "type": "Feature",
  "properties": {
    "date:inception_lower":"2016-12-01",
    "date:inception_upper":"2016-12-31",
    "iso:country":"GB",
    "wof:name":"SS12 9RS",
    "wof:placetype":"postalcode"
},
  "geometry": {"coordinates":[0.531051,51.605022],"type":"Point"}
}