{
  "type": "Feature",
  "properties": {
    "iso:country": "GB",
    "wof:name": "DH5 9NY",
    "wof:placetype": "postalcode"
  },
  "geometry": {"coordinates":[-1.47881,54.824247],"type":"Point"}
}
