{
  "type": "Feature",
  "properties": {
    "date:inception_lower":"1980-01-01",
    "date:inception_upper":"1980-01-31",
    "iso:country":"GB",
    "wof:name":"TS17 8DR",
    "wof:placetype":"postalcode"
},
  "geometry": {"coordinates":[-1.303748,54.549226],"type":"Point"}
}