{
  "type": "Feature",
  "properties": {
    "iso:country":"GB",
    "wof:name":"TS17 8DR",
    "wof:placetype":"postalcode"
},
  "geometry": {"coordinates":[-1.3037478876285,54.54922581998485],"type":"Point"}
}