{
  "type": "Feature",
  "properties": {
    "iso:country": "GB",
    "wof:name": "TS17 8DR",
    "wof:placetype": "postalcode"
  },
  "geometry": {"coordinates":[-1.303748,54.549226],"type":"Point"}
}
