{
  "type": "Feature",
  "properties": {
    "iso:country":"GB",
    "wof:name":"SN2 1RB",
    "wof:placetype":"postalcode"
},
  "geometry": {"coordinates":[-1.77922481982097,51.58258754994785],"type":"Point"}
}