{
  "type": "Feature",
  "properties": {
    "date:inception_lower": "1980-01-01",
    "date:inception_upper": "1980-01-01",
    "iso:country": "GB",
    "wof:name": "SN2 1RB",
    "wof:placetype": "postalcode"
  },
  "geometry": {"coordinates":[-1.779213,51.582535],"type":"Point"}
}
