{
  "type": "Feature",
  "properties": {
    "date:inception_lower": "1980-01-01",
    "date:inception_upper": "1980-01-01",
    "iso:country": "GB",
    "wof:name": "W3 8LQ",
    "wof:placetype": "postalcode"
  },
  "geometry": {"coordinates":[-0.286985,51.499474],"type":"Point"}
}
