{
  "type": "Feature",
  "properties": {
    "iso:country": "GB",
    "wof:name": "W3 8LQ",
    "wof:placetype": "postalcode"
  },
  "geometry": {"coordinates":[-0.289646,51.49998],"type":"Point"}
}
