{
  "type": "Feature",
  "properties": {
    "iso:country":"GB",
    "wof:name":"W3 8LQ",
    "wof:placetype":"postalcode"
},
  "geometry": {"coordinates":[-0.2874585871775,51.49974960905414],"type":"Point"}
}