{
  "type": "Feature",
  "properties": {
    "iso:country": "GB",
    "wof:name": "CW9 8GW",
    "wof:placetype": "postalcode"
  },
  "geometry": {"coordinates":[-2.517307,53.225746],"type":"Point"}
}
