{
  "type": "Feature",
  "properties": {
    "date:inception_lower": "1985-04-01",
    "date:inception_upper": "1985-04-01",
    "iso:country": "GB",
    "wof:name": "N12 8EQ",
    "wof:placetype": "postalcode"
  },
  "geometry": {"coordinates":[-0.178781,51.612442],"type":"Point"}
}
