{
  "type": "Feature",
  "properties": {
    "iso:country":"GB",
    "wof:name":"N12 8EQ",
    "wof:placetype":"postalcode"
},
  "geometry": {"coordinates":[-0.17878130659193,51.6124417627109],"type":"Point"}
}