{
  "type": "Feature",
  "properties": {
    "date:inception_lower":"2017-09-01",
    "date:inception_upper":"2017-09-30",
    "iso:country":"GB",
    "wof:name":"M1 3LF",
    "wof:placetype":"postalcode"
},
  "geometry": {"coordinates":[-2.238325,53.47817],"type":"Point"}
}