{
  "type": "Feature",
  "properties": {
    "iso:country": "GB",
    "wof:name": "DN36 5XF",
    "wof:placetype": "postalcode"
  },
  "geometry": {"coordinates":[0.057728,53.496952],"type":"Point"}
}
