{
  "type": "Feature",
  "properties": {
    "iso:country":"GB",
    "wof:name":"DN36 5XF",
    "wof:placetype":"postalcode"
},
  "geometry": {"coordinates":[0.05772823659077,53.49695223058334],"type":"Point"}
}