{
  "type": "Feature",
  "properties": {
    "date:inception_lower":"1980-01-01",
    "date:inception_upper":"1980-01-31",
    "iso:country":"GB",
    "wof:name":"DE6 2EU",
    "wof:placetype":"postalcode"
},
  "geometry": {"coordinates":[-1.763272,52.958027],"type":"Point"}
}