{
  "type": "Feature",
  "properties": {
    "iso:country": "GB",
    "wof:name": "DE6 2EU",
    "wof:placetype": "postalcode"
  },
  "geometry": {"coordinates":[-1.763272,52.958027],"type":"Point"}
}
