{
  "type": "Feature",
  "properties": {
    "iso:country":"GB",
    "wof:name":"G32 9EB",
    "wof:placetype":"postalcode"
},
  "geometry": {"coordinates":[-4.14867915578714,55.84824318033782],"type":"Point"}
}