{
  "type": "Feature",
  "properties": {
    "iso:country":"GB",
    "wof:name":"DT5 1NH",
    "wof:placetype":"postalcode"
},
  "geometry": {"coordinates":[-2.44483759583277,50.55996202565758],"type":"Point"}
}