{
  "type": "Feature",
  "properties": {
    "date:inception_lower": "1997-06-01",
    "date:inception_upper": "1997-06-01",
    "iso:country": "GB",
    "wof:name": "CF82 8LE",
    "wof:placetype": "postalcode"
  },
  "geometry": {"coordinates":[-3.241022,51.66373],"type":"Point"}
}
