{
  "type": "Feature",
  "properties": {
    "iso:country": "GB",
    "wof:name": "AL3 6JR",
    "wof:placetype": "postalcode"
  },
  "geometry": {"coordinates":[-0.355309,51.787182],"type":"Point"}
}
