{
  "type": "Feature",
  "properties": {
    "iso:country":"GB",
    "wof:name":"LU1 4DW",
    "wof:placetype":"postalcode"
},
  "geometry": {"coordinates":[-0.44983576760242,51.85751358881829],"type":"Point"}
}