{
  "type": "Feature",
  "properties": {
    "date:inception_lower": "1991-09-01",
    "date:inception_upper": "1991-09-01",
    "iso:country": "GB",
    "wof:name": "GU34 1JU",
    "wof:placetype": "postalcode"
  },
  "geometry": {"coordinates":[-0.97044,51.15154],"type":"Point"}
}
