{
  "type": "Feature",
  "properties": {
    "iso:country": "GB",
    "wof:name": "GU34 1JU",
    "wof:placetype": "postalcode"
  },
  "geometry": {"coordinates":[-0.97044,51.15154],"type":"Point"}
}
