{
  "type": "Feature",
  "properties": {
    "iso:country":"GB",
    "wof:name":"GU34 1JU",
    "wof:placetype":"postalcode"
},
  "geometry": {"coordinates":[-0.97044007102561,51.15153956716021],"type":"Point"}
}