{
  "type": "Feature",
  "properties": {
    "iso:country":"GB",
    "wof:name":"DH8 0PY",
    "wof:placetype":"postalcode"
},
  "geometry": {"coordinates":[-1.83832085104442,54.89379621621169],"type":"Point"}
}