{
  "type": "Feature",
  "properties": {
    "iso:country": "GB",
    "wof:name": "DH8 0PY",
    "wof:placetype": "postalcode"
  },
  "geometry": {"coordinates":[-1.838321,54.893796],"type":"Point"}
}
