{
  "type": "Feature",
  "properties": {
    "iso:country": "GB",
    "wof:name": "ML11 9HY",
    "wof:placetype": "postalcode"
  },
  "geometry": {"coordinates":[-3.785148,55.673847],"type":"Point"}
}
