{
  "type": "Feature",
  "properties": {
    "iso:country":"GB",
    "wof:name":"ML11 9HY",
    "wof:placetype":"postalcode"
},
  "geometry": {"coordinates":[-3.78514851314127,55.67384736278198],"type":"Point"}
}