{
  "type": "Feature",
  "properties": {
    "iso:country":"GB",
    "wof:name":"TS6 9PW",
    "wof:placetype":"postalcode"
},
  "geometry": {"coordinates":[-1.14549004058841,54.56305865629491],"type":"Point"}
}