{
  "type": "Feature",
  "properties": {
    "iso:country":"GB",
    "wof:name":"CH1 4HZ",
    "wof:placetype":"postalcode"
},
  "geometry": {"coordinates":[-2.90205239343163,53.1919590524036],"type":"Point"}
}