{
  "type": "Feature",
  "properties": {
    "date:inception_lower": "1996-06-01",
    "date:inception_upper": "1996-06-01",
    "iso:country": "GB",
    "wof:name": "SO41 6HA",
    "wof:placetype": "postalcode"
  },
  "geometry": {"coordinates":[-1.60636,50.781811],"type":"Point"}
}
