{
  "type": "Feature",
  "properties": {
    "iso:country":"GB",
    "wof:name":"DN19 7JP",
    "wof:placetype":"postalcode"
},
  "geometry": {"coordinates":[-0.33317921681678,53.68219269321434],"type":"Point"}
}