{
  "type": "Feature",
  "properties": {
    "iso:country":"GB",
    "wof:name":"HD4 6PW",
    "wof:placetype":"postalcode"
},
  "geometry": {"coordinates":[-1.76851803476102,53.62919084480927],"type":"Point"}
}