{
  "type": "Feature",
  "properties": {
    "iso:country":"GB",
    "wof:name":"SL4 3RN",
    "wof:placetype":"postalcode"
},
  "geometry": {"coordinates":[-0.632682358585,51.47479705182969],"type":"Point"}
}