{
  "type": "Feature",
  "properties": {
    "iso:country":"GB",
    "wof:name":"SW7 3JZ",
    "wof:placetype":"postalcode"
},
  "geometry": {"coordinates":[-0.17661396924659,51.49270114078038],"type":"Point"}
}