{
  "type": "Feature",
  "properties": {
    "iso:country":"GB",
    "wof:name":"EH1 2JL",
    "wof:placetype":"postalcode"
},
  "geometry": {"coordinates":[-3.19437342041612,55.94862092919008],"type":"Point"}
}