{
  "type": "Feature",
  "properties": {
    "date:inception_lower": "1980-01-01",
    "date:inception_upper": "1980-01-01",
    "iso:country": "GB",
    "wof:name": "W2 2NT",
    "wof:placetype": "postalcode"
  },
  "geometry": {"coordinates":[-0.168527,51.512601],"type":"Point"}
}
