{
  "type": "Feature",
  "properties": {
    "date:inception_lower": "1997-12-01",
    "date:inception_upper": "1997-12-01",
    "iso:country": "GB",
    "wof:name": "TW20 0NN",
    "wof:placetype": "postalcode"
  },
  "geometry": {"coordinates":[-0.561062,51.431254],"type":"Point"}
}
