{
  "type": "Feature",
  "properties": {
    "iso:country":"GB",
    "wof:name":"TW20 0NN",
    "wof:placetype":"postalcode"
},
  "geometry": {"coordinates":[-0.56106247488144,51.43125433901798],"type":"Point"}
}