{
  "type": "Feature",
  "properties": {
    "iso:country":"GB",
    "wof:name":"W5 1PR",
    "wof:placetype":"postalcode"
},
  "geometry": {"coordinates":[-0.30326399419252,51.52456435927699],"type":"Point"}
}