{
  "type": "Feature",
  "properties": {
    "iso:country":"GB",
    "wof:name":"WS12 4HZ",
    "wof:placetype":"postalcode"
},
  "geometry": {"coordinates":[-2.00365845751531,52.71821821317451],"type":"Point"}
}