{
  "type": "Feature",
  "properties": {
    "date:inception_lower": "2018-12-01",
    "date:inception_upper": "2018-12-01",
    "iso:country": "GB",
    "wof:name": "MK43 9SG",
    "wof:placetype": "postalcode"
  },
  "geometry": {"coordinates":[-0.508359,52.072063],"type":"Point"}
}
