{
  "type": "Feature",
  "properties": {
    "iso:country": "GB",
    "wof:name": "PL20 6BE",
    "wof:placetype": "postalcode"
  },
  "geometry": {"coordinates":[-4.080293,50.493098],"type":"Point"}
}
