{
  "type": "Feature",
  "properties": {
    "date:inception_lower":"1980-01-01",
    "date:inception_upper":"1980-01-31",
    "iso:country":"GB",
    "wof:name":"PL20 6BE",
    "wof:placetype":"postalcode"
},
  "geometry": {"coordinates":[-4.080293,50.493098],"type":"Point"}
}