{
  "type": "Feature",
  "properties": {
    "iso:country":"GB",
    "wof:name":"PL20 6BE",
    "wof:placetype":"postalcode"
},
  "geometry": {"coordinates":[-4.08029279060725,50.49309823968844],"type":"Point"}
}