{
  "type": "Feature",
  "properties": {
    "iso:country":"GB",
    "wof:name":"DL4 1EQ",
    "wof:placetype":"postalcode"
},
  "geometry": {"coordinates":[-1.64871618906182,54.63351400209],"type":"Point"}
}