{
  "type": "Feature",
  "properties": {
    "iso:country": "GB",
    "wof:name": "RG2 9YX",
    "wof:placetype": "postalcode"
  },
  "geometry": {"coordinates":[-0.897915,51.382932],"type":"Point"}
}
