{
  "type": "Feature",
  "properties": {
    "date:inception_lower": "2019-11-01",
    "date:inception_upper": "2019-11-01",
    "iso:country": "GB",
    "wof:name": "RG2 9YX",
    "wof:placetype": "postalcode"
  },
  "geometry": {"coordinates":[-0.897915,51.382932],"type":"Point"}
}
