{
  "type": "Feature",
  "properties": {
    "iso:country":"GB",
    "wof:name":"CF32 9RD",
    "wof:placetype":"postalcode"
},
  "geometry": {"coordinates":[-3.59392097307847,51.5424458934272],"type":"Point"}
}