{
  "type": "Feature",
  "properties": {
    "iso:country": "GB",
    "wof:name": "CF32 9RD",
    "wof:placetype": "postalcode"
  },
  "geometry": {"coordinates":[-3.594381,51.54237],"type":"Point"}
}
