{
  "type": "Feature",
  "properties": {
    "date:inception_lower": "1981-09-01",
    "date:inception_upper": "1981-09-01",
    "iso:country": "GB",
    "wof:name": "SY5 8RQ",
    "wof:placetype": "postalcode"
  },
  "geometry": {"coordinates":[-2.829279,52.679193],"type":"Point"}
}
