{
  "type": "Feature",
  "properties": {
    "iso:country": "GB",
    "wof:name": "SY5 8RQ",
    "wof:placetype": "postalcode"
  },
  "geometry": {"coordinates":[-2.829279,52.679193],"type":"Point"}
}
