{
  "type": "Feature",
  "properties": {
    "iso:country":"GB",
    "wof:name":"SY5 8RQ",
    "wof:placetype":"postalcode"
},
  "geometry": {"coordinates":[-2.82930968156146,52.67915923270073],"type":"Point"}
}