{
  "type": "Feature",
  "properties": {
    "iso:country":"GB",
    "wof:name":"B90 4HF",
    "wof:placetype":"postalcode"
},
  "geometry": {"coordinates":[-1.81268545558273,52.38150824518944],"type":"Point"}
}