{
  "type": "Feature",
  "properties": {
    "iso:country":"GB",
    "wof:name":"NW7 4SJ",
    "wof:placetype":"postalcode"
},
  "geometry": {"coordinates":[-0.237373449429,51.61553926824816],"type":"Point"}
}