{
  "type": "Feature",
  "properties": {
    "iso:country":"GB",
    "wof:name":"TR11 3NP",
    "wof:placetype":"postalcode"
},
  "geometry": {"coordinates":[-5.07029299119778,50.15265029962145],"type":"Point"}
}