{
  "type": "Feature",
  "properties": {
    "iso:country":"GB",
    "wof:name":"WR6 6ET",
    "wof:placetype":"postalcode"
},
  "geometry": {"coordinates":[-2.4389768269061,52.27329867922777],"type":"Point"}
}