{
  "type": "Feature",
  "properties": {
    "iso:country": "GB",
    "wof:name": "WR6 6ET",
    "wof:placetype": "postalcode"
  },
  "geometry": {"coordinates":[-2.438977,52.273299],"type":"Point"}
}
