{
  "type": "Feature",
  "properties": {
    "date:inception_lower":"1980-01-01",
    "date:inception_upper":"1980-01-31",
    "iso:country":"GB",
    "wof:name":"WR6 6ET",
    "wof:placetype":"postalcode"
},
  "geometry": {"coordinates":[-2.438977,52.273299],"type":"Point"}
}