{
  "type": "Feature",
  "properties": {
    "iso:country": "GB",
    "wof:name": "YO22 4DD",
    "wof:placetype": "postalcode"
  },
  "geometry": {"coordinates":[-0.612402,54.487989],"type":"Point"}
}
