{
  "type": "Feature",
  "properties": {
    "iso:country":"GB",
    "wof:name":"YO22 4DD",
    "wof:placetype":"postalcode"
},
  "geometry": {"coordinates":[-0.61240182398642,54.48798929301314],"type":"Point"}
}