{
  "type": "Feature",
  "properties": {
    "iso:country":"GB",
    "wof:name":"M9 8JS",
    "wof:placetype":"postalcode"
},
  "geometry": {"coordinates":[-2.23671980392017,53.52494212626351],"type":"Point"}
}