{
  "type": "Feature",
  "properties": {
    "iso:country":"GB",
    "wof:name":"EX6 7DJ",
    "wof:placetype":"postalcode"
},
  "geometry": {"coordinates":[-3.7135244519218,50.69833149085186],"type":"Point"}
}