{
  "type": "Feature",
  "properties": {
    "date:inception_lower":"1986-04-01",
    "date:inception_upper":"1986-04-30",
    "iso:country":"GB",
    "wof:name":"RG6 4HA",
    "wof:placetype":"postalcode"
},
  "geometry": {"coordinates":[-0.914936,51.422951],"type":"Point"}
}