{
  "type": "Feature",
  "properties": {
    "date:inception_lower": "2024-02-01",
    "date:inception_upper": "2024-02-01",
    "iso:country": "GB",
    "wof:name": "LS12 1FH",
    "wof:placetype": "postalcode"
  },
  "geometry": {"coordinates":[-1.56234,53.791739],"type":"Point"}
}
