{
  "type": "Feature",
  "properties": {
    "iso:country": "GB",
    "wof:name": "ME15 9FU",
    "wof:placetype": "postalcode"
  },
  "geometry": {"coordinates":[0.55583,51.240457],"type":"Point"}
}
