{
  "type": "Feature",
  "properties": {
    "date:inception_lower": "2015-03-01",
    "date:inception_upper": "2015-03-01",
    "iso:country": "GB",
    "wof:name": "ME15 9FU",
    "wof:placetype": "postalcode"
  },
  "geometry": {"coordinates":[0.55583,51.240457],"type":"Point"}
}
