{
  "type": "Feature",
  "properties": {
    "iso:country":"GB",
    "wof:name":"SP4 0LW",
    "wof:placetype":"postalcode"
},
  "geometry": {"coordinates":[-1.73245905590641,51.12937125096551],"type":"Point"}
}