{
  "type": "Feature",
  "properties": {
    "iso:country":"GB",
    "wof:name":"TR26 3LE",
    "wof:placetype":"postalcode"
},
  "geometry": {"coordinates":[-5.43829743787473,50.18586994524531],"type":"Point"}
}