{
  "type": "Feature",
  "properties": {
    "iso:country": "GB",
    "wof:name": "TR26 3LE",
    "wof:placetype": "postalcode"
  },
  "geometry": {"coordinates":[-5.438297,50.18587],"type":"Point"}
}
