{
  "type": "Feature",
  "properties": {
    "iso:country":"GB",
    "wof:name":"DL7 8QH",
    "wof:placetype":"postalcode"
},
  "geometry": {"coordinates":[-1.43960230914451,54.33832027217169],"type":"Point"}
}