{
  "type": "Feature",
  "properties": {
    "iso:country": "GB",
    "wof:name": "DA12 1PW",
    "wof:placetype": "postalcode"
  },
  "geometry": {"coordinates":[0.390222,51.432387],"type":"Point"}
}
