{
  "type": "Feature",
  "properties": {
    "iso:country": "GB",
    "wof:name": "M1 1PW",
    "wof:placetype": "postalcode"
  },
  "geometry": {"coordinates":[-2.24239,53.482496],"type":"Point"}
}
