{
  "type": "Feature",
  "properties": {
    "iso:country":"GB",
    "wof:name":"M1 1PW",
    "wof:placetype":"postalcode"
},
  "geometry": {"coordinates":[-2.24239022526213,53.48249640729486],"type":"Point"}
}