{
  "type": "Feature",
  "properties": {
    "date:inception_lower": "1990-02-01",
    "date:inception_upper": "1990-02-01",
    "iso:country": "GB",
    "wof:name": "MK44 3AG",
    "wof:placetype": "postalcode"
  },
  "geometry": {"coordinates":[-0.306196,52.198005],"type":"Point"}
}
