{
  "type": "Feature",
  "properties": {
    "iso:country":"GB",
    "wof:name":"MK44 3AG",
    "wof:placetype":"postalcode"
},
  "geometry": {"coordinates":[-0.30619575760941,52.19800530528784],"type":"Point"}
}