{
  "type": "Feature",
  "properties": {
    "iso:country":"GB",
    "wof:name":"S63 0JU",
    "wof:placetype":"postalcode"
},
  "geometry": {"coordinates":[-1.31119243882241,53.54633099683841],"type":"Point"}
}