{
  "type": "Feature",
  "properties": {
    "iso:country":"GB",
    "wof:name":"WV14 9TD",
    "wof:placetype":"postalcode"
},
  "geometry": {"coordinates":[-2.09452093454094,52.53783732800195],"type":"Point"}
}