{
  "type": "Feature",
  "properties": {
    "iso:country":"GB",
    "wof:name":"MK16 8HA",
    "wof:placetype":"postalcode"
},
  "geometry": {"coordinates":[-0.72827123448266,52.08659642111696],"type":"Point"}
}