{
  "type": "Feature",
  "properties": {
    "iso:country":"GB",
    "wof:name":"GU29 0AH",
    "wof:placetype":"postalcode"
},
  "geometry": {"coordinates":[-0.72533791135815,50.99534343338177],"type":"Point"}
}