{
  "type": "Feature",
  "properties": {
    "iso:country": "GB",
    "wof:name": "GU29 0AH",
    "wof:placetype": "postalcode"
  },
  "geometry": {"coordinates":[-0.72542,50.995267],"type":"Point"}
}
