{
  "type": "Feature",
  "properties": {
    "iso:country":"GB",
    "wof:name":"CV21 1BD",
    "wof:placetype":"postalcode"
},
  "geometry": {"coordinates":[-1.25516845158907,52.38447163588437],"type":"Point"}
}