{
  "type": "Feature",
  "properties": {
    "iso:country":"GB",
    "wof:name":"TF1 5LQ",
    "wof:placetype":"postalcode"
},
  "geometry": {"coordinates":[-2.49397857666487,52.70022476289273],"type":"Point"}
}