{
  "type": "Feature",
  "properties": {
    "iso:country": "GB",
    "wof:name": "CF37 2NP",
    "wof:placetype": "postalcode"
  },
  "geometry": {"coordinates":[-3.386343,51.610032],"type":"Point"}
}
