{
  "type": "Feature",
  "properties": {
    "date:inception_lower": "1980-01-01",
    "date:inception_upper": "1980-01-01",
    "iso:country": "GB",
    "wof:name": "CF37 2NP",
    "wof:placetype": "postalcode"
  },
  "geometry": {"coordinates":[-3.386343,51.610032],"type":"Point"}
}
