{
  "type": "Feature",
  "properties": {
    "iso:country":"GB",
    "wof:name":"CF37 2NP",
    "wof:placetype":"postalcode"
},
  "geometry": {"coordinates":[-3.38634334761344,51.61003178201573],"type":"Point"}
}