{
  "type": "Feature",
  "properties": {
    "iso:country":"GB",
    "wof:name":"TW2 7EU",
    "wof:placetype":"postalcode"
},
  "geometry": {"coordinates":[-0.35823442445819,51.4558540327642],"type":"Point"}
}