{
  "type": "Feature",
  "properties": {
    "iso:country":"GB",
    "wof:name":"CO13 0LT",
    "wof:placetype":"postalcode"
},
  "geometry": {"coordinates":[1.21705138075099,51.84216729107197],"type":"Point"}
}