{
  "type": "Feature",
  "properties": {
    "iso:country":"GB",
    "wof:name":"TQ3 2DL",
    "wof:placetype":"postalcode"
},
  "geometry": {"coordinates":[-3.55541670547291,50.44814551783794],"type":"Point"}
}