{
  "type": "Feature",
  "properties": {
    "iso:country": "GB",
    "wof:name": "HP16 9JJ",
    "wof:placetype": "postalcode"
  },
  "geometry": {"coordinates":[-0.688036,51.729913],"type":"Point"}
}
