{
  "type": "Feature",
  "properties": {
    "iso:country":"GB",
    "wof:name":"HP16 9JJ",
    "wof:placetype":"postalcode"
},
  "geometry": {"coordinates":[-0.68805960086864,51.7299077103184],"type":"Point"}
}