{
  "type": "Feature",
  "properties": {
    "date:inception_lower": "2021-04-01",
    "date:inception_upper": "2021-04-01",
    "iso:country": "GB",
    "wof:name": "TS10 5FE",
    "wof:placetype": "postalcode"
  },
  "geometry": {"coordinates":[-1.088316,54.597632],"type":"Point"}
}
