{
  "type": "Feature",
  "properties": {
    "date:inception_lower": "2016-12-01",
    "date:inception_upper": "2016-12-01",
    "iso:country": "GB",
    "wof:name": "PO7 3BH",
    "wof:placetype": "postalcode"
  },
  "geometry": {"coordinates":[-1.039933,50.88187],"type":"Point"}
}
