{
  "type": "Feature",
  "properties": {
    "date:inception_lower":"2004-11-01",
    "date:inception_upper":"2004-11-30",
    "iso:country":"GB",
    "wof:name":"PH7 3FB",
    "wof:placetype":"postalcode"
},
  "geometry": {"coordinates":[-3.831566,56.366399],"type":"Point"}
}