{
  "type": "Feature",
  "properties": {
    "iso:country":"GB",
    "wof:name":"PH7 3FB",
    "wof:placetype":"postalcode"
},
  "geometry": {"coordinates":[-3.83156627092949,56.36639886510214],"type":"Point"}
}