{
  "type": "Feature",
  "properties": {
    "iso:country":"GB",
    "wof:name":"W3 8QG",
    "wof:placetype":"postalcode"
},
  "geometry": {"coordinates":[-0.27542349254537,51.50522046760653],"type":"Point"}
}