{
  "type": "Feature",
  "properties": {
    "iso:country":"GB",
    "wof:name":"BD22 6DP",
    "wof:placetype":"postalcode"
},
  "geometry": {"coordinates":[-1.92497124898067,53.86276514182327],"type":"Point"}
}