{
  "type": "Feature",
  "properties": {
    "iso:country": "GB",
    "wof:name": "ME1 2QU",
    "wof:placetype": "postalcode"
  },
  "geometry": {"coordinates":[0.514178,51.370625],"type":"Point"}
}
