{
  "type": "Feature",
  "properties": {
    "iso:country":"GB",
    "wof:name":"ME1 2QU",
    "wof:placetype":"postalcode"
},
  "geometry": {"coordinates":[0.51417771389488,51.37062486069702],"type":"Point"}
}