{
  "type": "Feature",
  "properties": {
    "iso:country":"GB",
    "wof:name":"NR10 3QZ",
    "wof:placetype":"postalcode"
},
  "geometry": {"coordinates":[1.32511789708813,52.68440566267292],"type":"Point"}
}