{
  "type": "Feature",
  "properties": {
    "iso:country": "GB",
    "wof:name": "NR10 3QZ",
    "wof:placetype": "postalcode"
  },
  "geometry": {"coordinates":[1.325118,52.684406],"type":"Point"}
}
