{
  "type": "Feature",
  "properties": {
    "iso:country":"GB",
    "wof:name":"DT11 0PR",
    "wof:placetype":"postalcode"
},
  "geometry": {"coordinates":[-2.18536837062521,50.86119147855617],"type":"Point"}
}