{
  "type": "Feature",
  "properties": {
    "iso:country": "GB",
    "wof:name": "DT11 0PR",
    "wof:placetype": "postalcode"
  },
  "geometry": {"coordinates":[-2.185368,50.861191],"type":"Point"}
}
