{
  "type": "Feature",
  "properties": {
    "iso:country": "GB",
    "wof:name": "IP11 2EJ",
    "wof:placetype": "postalcode"
  },
  "geometry": {"coordinates":[1.33347,51.948421],"type":"Point"}
}
