{
  "type": "Feature",
  "properties": {
    "iso:country":"GB",
    "wof:name":"IP11 2EJ",
    "wof:placetype":"postalcode"
},
  "geometry": {"coordinates":[1.33346958564915,51.94842147695991],"type":"Point"}
}