{
  "type": "Feature",
  "properties": {
    "iso:country":"GB",
    "wof:name":"IP17 2EX",
    "wof:placetype":"postalcode"
},
  "geometry": {"coordinates":[1.41874246009487,52.26543902858143],"type":"Point"}
}