{
  "type": "Feature",
  "properties": {
    "date:inception_lower": "1980-01-01",
    "date:inception_upper": "1980-01-01",
    "iso:country": "GB",
    "wof:name": "IP17 2EX",
    "wof:placetype": "postalcode"
  },
  "geometry": {"coordinates":[1.419712,52.266223],"type":"Point"}
}
