{
  "type": "Feature",
  "properties": {
    "iso:country": "GB",
    "wof:name": "PL11 2LU",
    "wof:placetype": "postalcode"
  },
  "geometry": {"coordinates":[-4.199836,50.378412],"type":"Point"}
}
