{
  "type": "Feature",
  "properties": {
    "iso:country":"GB",
    "wof:name":"PL11 2LU",
    "wof:placetype":"postalcode"
},
  "geometry": {"coordinates":[-4.19966057098168,50.37769963782516],"type":"Point"}
}