{
  "type": "Feature",
  "properties": {
    "date:inception_lower": "1999-06-01",
    "date:inception_upper": "1999-06-01",
    "iso:country": "GB",
    "wof:name": "CH66 4SN",
    "wof:placetype": "postalcode"
  },
  "geometry": {"coordinates":[-2.929243,53.267789],"type":"Point"}
}
