{
  "type": "Feature",
  "properties": {
    "iso:country":"GB",
    "wof:name":"CH66 4SN",
    "wof:placetype":"postalcode"
},
  "geometry": {"coordinates":[-2.92924266234734,53.26778924275212],"type":"Point"}
}