{
  "type": "Feature",
  "properties": {
    "iso:country": "GB",
    "wof:name": "DN6 7UN",
    "wof:placetype": "postalcode"
  },
  "geometry": {"coordinates":[-1.187018,53.574549],"type":"Point"}
}
