{
  "type": "Feature",
  "properties": {
    "iso:country":"GB",
    "wof:name":"DN6 7UN",
    "wof:placetype":"postalcode"
},
  "geometry": {"coordinates":[-1.18701845895351,53.57454878674515],"type":"Point"}
}