{
  "type": "Feature",
  "properties": {
    "date:inception_lower": "1997-06-01",
    "date:inception_upper": "1997-06-01",
    "iso:country": "GB",
    "wof:name": "DN6 7UN",
    "wof:placetype": "postalcode"
  },
  "geometry": {"coordinates":[-1.187018,53.574549],"type":"Point"}
}
