{
  "type": "Feature",
  "properties": {
    "date:inception_lower": "1980-01-01",
    "date:inception_upper": "1980-01-01",
    "iso:country": "GB",
    "wof:name": "BD23 2DJ",
    "wof:placetype": "postalcode"
  },
  "geometry": {"coordinates":[-2.015112,53.958516],"type":"Point"}
}
