{
  "type": "Feature",
  "properties": {
    "iso:country":"GB",
    "wof:name":"BA3 4AZ",
    "wof:placetype":"postalcode"
},
  "geometry": {"coordinates":[-2.47210768353078,51.28022867132798],"type":"Point"}
}