{
  "type": "Feature",
  "properties": {
    "iso:country":"GB",
    "wof:name":"HR8 2UG",
    "wof:placetype":"postalcode"
},
  "geometry": {"coordinates":[-2.55852851997229,52.10104770668408],"type":"Point"}
}