{
  "type": "Feature",
  "properties": {
    "iso:country": "GB",
    "wof:name": "HR8 2UG",
    "wof:placetype": "postalcode"
  },
  "geometry": {"coordinates":[-2.558528,52.101048],"type":"Point"}
}
