{
  "type": "Feature",
  "properties": {
    "iso:country":"GB",
    "wof:name":"NR14 8HQ",
    "wof:placetype":"postalcode"
},
  "geometry": {"coordinates":[1.20906888385821,52.55467489842123],"type":"Point"}
}