{
  "type": "Feature",
  "properties": {
    "date:inception_lower": "1980-01-01",
    "date:inception_upper": "1980-01-01",
    "iso:country": "GB",
    "wof:name": "NR14 8HQ",
    "wof:placetype": "postalcode"
  },
  "geometry": {"coordinates":[1.209069,52.554675],"type":"Point"}
}
