{
  "type": "Feature",
  "properties": {
    "iso:country": "GB",
    "wof:name": "IP28 6JS",
    "wof:placetype": "postalcode"
  },
  "geometry": {"coordinates":[0.689587,52.276571],"type":"Point"}
}
