{
  "type": "Feature",
  "properties": {
    "date:inception_lower": "1980-01-01",
    "date:inception_upper": "1980-01-01",
    "iso:country": "GB",
    "wof:name": "IP28 6JS",
    "wof:placetype": "postalcode"
  },
  "geometry": {"coordinates":[0.689587,52.276571],"type":"Point"}
}
