{
  "type": "Feature",
  "properties": {
    "iso:country":"GB",
    "wof:name":"IP28 6JS",
    "wof:placetype":"postalcode"
},
  "geometry": {"coordinates":[0.68958648538968,52.27657083268361],"type":"Point"}
}