{
  "type": "Feature",
  "properties": {
    "iso:country":"GB",
    "wof:name":"S42 7DQ",
    "wof:placetype":"postalcode"
},
  "geometry": {"coordinates":[-1.54079228849898,53.25202976104006],"type":"Point"}
}