{
  "type": "Feature",
  "properties": {
    "iso:country":"GB",
    "wof:name":"NN8 3TB",
    "wof:placetype":"postalcode"
},
  "geometry": {"coordinates":[-0.72717797867219,52.30272691689338],"type":"Point"}
}