{
  "type": "Feature",
  "properties": {
    "iso:country": "GB",
    "wof:name": "B67 6EQ",
    "wof:placetype": "postalcode"
  },
  "geometry": {"coordinates":[-1.972426,52.487139],"type":"Point"}
}
