{
  "type": "Feature",
  "properties": {
    "iso:country":"GB",
    "wof:name":"NN18 8BT",
    "wof:placetype":"postalcode"
},
  "geometry": {"coordinates":[-0.69956247371196,52.47971339488684],"type":"Point"}
}