{
  "type": "Feature",
  "properties": {
    "iso:country":"GB",
    "wof:name":"BS36 2FB",
    "wof:placetype":"postalcode"
},
  "geometry": {"coordinates":[-2.46464587862499,51.530550807277],"type":"Point"}
}