{
  "type": "Feature",
  "properties": {
    "iso:country": "GB",
    "wof:name": "BS36 2FB",
    "wof:placetype": "postalcode"
  },
  "geometry": {"coordinates":[-2.464646,51.530551],"type":"Point"}
}
