{
  "type": "Feature",
  "properties": {
    "iso:country": "GB",
    "wof:name": "SG2 0NY",
    "wof:placetype": "postalcode"
  },
  "geometry": {"coordinates":[-0.161803,51.905186],"type":"Point"}
}
