{
  "type": "Feature",
  "properties": {
    "date:inception_lower": "1980-01-01",
    "date:inception_upper": "1980-01-01",
    "iso:country": "GB",
    "wof:name": "B71 2PS",
    "wof:placetype": "postalcode"
  },
  "geometry": {"coordinates":[-2.012254,52.543125],"type":"Point"}
}
