{
  "type": "Feature",
  "properties": {
    "iso:country":"GB",
    "wof:name":"B71 2PS",
    "wof:placetype":"postalcode"
},
  "geometry": {"coordinates":[-2.01225403544531,52.54312469344287],"type":"Point"}
}