{
  "type": "Feature",
  "properties": {
    "iso:country": "GB",
    "wof:name": "NR31 0JW",
    "wof:placetype": "postalcode"
  },
  "geometry": {"coordinates":[1.723928,52.597445],"type":"Point"}
}
