{
  "type": "Feature",
  "properties": {
    "iso:country":"GB",
    "wof:name":"KA4 8HY",
    "wof:placetype":"postalcode"
},
  "geometry": {"coordinates":[-4.37798109777224,55.59664885310853],"type":"Point"}
}