{
  "type": "Feature",
  "properties": {
    "iso:country": "GB",
    "wof:name": "KA4 8HY",
    "wof:placetype": "postalcode"
  },
  "geometry": {"coordinates":[-4.377981,55.596649],"type":"Point"}
}
