{
  "type": "Feature",
  "properties": {
    "iso:country":"GB",
    "wof:name":"ME5 7SL",
    "wof:placetype":"postalcode"
},
  "geometry": {"coordinates":[0.54519461685551,51.36224735212644],"type":"Point"}
}