{
  "type": "Feature",
  "properties": {
    "date:inception_lower": "2021-06-01",
    "date:inception_upper": "2021-06-01",
    "iso:country": "GB",
    "wof:name": "ME19 4XW",
    "wof:placetype": "postalcode"
  },
  "geometry": {"coordinates":[0.398439,51.281768],"type":"Point"}
}
