{
  "type": "Feature",
  "properties": {
    "date:inception_lower": "2019-02-01",
    "date:inception_upper": "2019-02-01",
    "iso:country": "GB",
    "wof:name": "OL11 2BJ",
    "wof:placetype": "postalcode"
  },
  "geometry": {"coordinates":[-2.176584,53.587909],"type":"Point"}
}
