{
  "type": "Feature",
  "properties": {
    "iso:country": "GB",
    "wof:name": "OL11 2BJ",
    "wof:placetype": "postalcode"
  },
  "geometry": {"coordinates":[-2.176584,53.587909],"type":"Point"}
}
