{
  "type": "Feature",
  "properties": {
    "iso:country":"GB",
    "wof:name":"L10 8JN",
    "wof:placetype":"postalcode"
},
  "geometry": {"coordinates":[-2.92613459649164,53.47885564579893],"type":"Point"}
}