{
  "type": "Feature",
  "properties": {
    "date:inception_lower": "1980-01-01",
    "date:inception_upper": "1980-01-01",
    "iso:country": "GB",
    "wof:name": "L10 8JN",
    "wof:placetype": "postalcode"
  },
  "geometry": {"coordinates":[-2.926135,53.478856],"type":"Point"}
}
