{
  "type": "Feature",
  "properties": {
    "iso:country":"GB",
    "wof:name":"OX10 0RQ",
    "wof:placetype":"postalcode"
},
  "geometry": {"coordinates":[-1.15130631452085,51.61088397615499],"type":"Point"}
}