{
  "type": "Feature",
  "properties": {
    "iso:country": "GB",
    "wof:name": "TS18 3TN",
    "wof:placetype": "postalcode"
  },
  "geometry": {"coordinates":[-1.330871,54.547684],"type":"Point"}
}
