{
  "type": "Feature",
  "properties": {
    "iso:country":"GB",
    "wof:name":"TS18 3TN",
    "wof:placetype":"postalcode"
},
  "geometry": {"coordinates":[-1.33085865442562,54.54768019220388],"type":"Point"}
}