{
  "type": "Feature",
  "properties": {
    "iso:country":"GB",
    "wof:name":"LS29 8JP",
    "wof:placetype":"postalcode"
},
  "geometry": {"coordinates":[-1.81552861185587,53.92745825781854],"type":"Point"}
}