{
  "type": "Feature",
  "properties": {
    "iso:country":"GB",
    "wof:name":"WC1E 6AF",
    "wof:placetype":"postalcode"
},
  "geometry": {"coordinates":[-0.13297309512167,51.5224721378215],"type":"Point"}
}