{
  "type": "Feature",
  "properties": {
    "iso:country": "GB",
    "wof:name": "SY6 6BZ",
    "wof:placetype": "postalcode"
  },
  "geometry": {"coordinates":[-2.807229,52.537998],"type":"Point"}
}
