{
  "type": "Feature",
  "properties": {
    "iso:country":"GB",
    "wof:name":"S66 1GL",
    "wof:placetype":"postalcode"
},
  "geometry": {"coordinates":[-1.27939893976873,53.41970954814859],"type":"Point"}
}