{
  "type": "Feature",
  "properties": {
    "date:inception_lower": "2010-11-01",
    "date:inception_upper": "2010-11-01",
    "iso:country": "GB",
    "wof:name": "S66 1GL",
    "wof:placetype": "postalcode"
  },
  "geometry": {"coordinates":[-1.279399,53.41971],"type":"Point"}
}
