{
  "type": "Feature",
  "properties": {
    "iso:country": "GB",
    "wof:name": "WA6 6BE",
    "wof:placetype": "postalcode"
  },
  "geometry": {"coordinates":[-2.719735,53.286533],"type":"Point"}
}
