{
  "type": "Feature",
  "properties": {
    "iso:country":"GB",
    "wof:name":"WA6 6BE",
    "wof:placetype":"postalcode"
},
  "geometry": {"coordinates":[-2.71973489709214,53.28653307217074],"type":"Point"}
}