{
  "type": "Feature",
  "properties": {
    "iso:country":"GB",
    "wof:name":"YO8 5AS",
    "wof:placetype":"postalcode"
},
  "geometry": {"coordinates":[-1.06346032633999,53.7865020053079],"type":"Point"}
}