{
  "type": "Feature",
  "properties": {
    "iso:country":"GB",
    "wof:name":"CO9 1XA",
    "wof:placetype":"postalcode"
},
  "geometry": {"coordinates":[0.63048848949739,51.94142641786237],"type":"Point"}
}