{
  "type": "Feature",
  "properties": {
    "iso:country": "GB",
    "wof:name": "DY2 0DH",
    "wof:placetype": "postalcode"
  },
  "geometry": {"coordinates":[-2.084738,52.475452],"type":"Point"}
}
