{
  "type": "Feature",
  "properties": {
    "iso:country": "GB",
    "wof:name": "WA11 7JL",
    "wof:placetype": "postalcode"
  },
  "geometry": {"coordinates":[-2.801809,53.490952],"type":"Point"}
}
