{
  "type": "Feature",
  "properties": {
    "iso:country":"GB",
    "wof:name":"AL3 8HQ",
    "wof:placetype":"postalcode"
},
  "geometry": {"coordinates":[-0.44118986475504,51.82699833955758],"type":"Point"}
}