{
  "type": "Feature",
  "properties": {
    "iso:country":"GB",
    "wof:name":"SN15 1HA",
    "wof:placetype":"postalcode"
},
  "geometry": {"coordinates":[-2.1178338705681,51.45975041225488],"type":"Point"}
}