{
  "type": "Feature",
  "properties": {
    "iso:country":"GB",
    "wof:name":"LS18 4ED",
    "wof:placetype":"postalcode"
},
  "geometry": {"coordinates":[-1.65825641460284,53.83282223620235],"type":"Point"}
}