{
  "type": "Feature",
  "properties": {
    "iso:country":"GB",
    "wof:name":"ML3 8DX",
    "wof:placetype":"postalcode"
},
  "geometry": {"coordinates":[-4.0589435157973,55.76051819063412],"type":"Point"}
}