{
  "type": "Feature",
  "properties": {
    "date:inception_lower": "2018-11-01",
    "date:inception_upper": "2018-11-01",
    "iso:country": "GB",
    "wof:name": "NG19 9EN",
    "wof:placetype": "postalcode"
  },
  "geometry": {"coordinates":[-1.186187,53.154808],"type":"Point"}
}
