{
  "type": "Feature",
  "properties": {
    "date:inception_lower": "1980-01-01",
    "date:inception_upper": "1980-01-01",
    "iso:country": "GB",
    "wof:name": "NE65 7YQ",
    "wof:placetype": "postalcode"
  },
  "geometry": {"coordinates":[-1.919736,55.310387],"type":"Point"}
}
