{
  "type": "Feature",
  "properties": {
    "iso:country":"GB",
    "wof:name":"NE65 7YQ",
    "wof:placetype":"postalcode"
},
  "geometry": {"coordinates":[-1.9197360337865,55.31038744119584],"type":"Point"}
}