{
  "type": "Feature",
  "properties": {
    "iso:country":"GB",
    "wof:name":"DY13 8UT",
    "wof:placetype":"postalcode"
},
  "geometry": {"coordinates":[-2.28162561582462,52.33887753788356],"type":"Point"}
}