{
  "type": "Feature",
  "properties": {
    "date:inception_lower": "2021-02-01",
    "date:inception_upper": "2021-02-01",
    "iso:country": "GB",
    "wof:name": "S81 8GG",
    "wof:placetype": "postalcode"
  },
  "geometry": {"coordinates":[-1.15042,53.326548],"type":"Point"}
}
