{
  "type": "Feature",
  "properties": {
    "iso:country": "GB",
    "wof:name": "RG45 6BD",
    "wof:placetype": "postalcode"
  },
  "geometry": {"coordinates":[-0.817942,51.370903],"type":"Point"}
}
