{
  "type": "Feature",
  "properties": {
    "iso:country": "GB",
    "wof:name": "TS12 2SP",
    "wof:placetype": "postalcode"
  },
  "geometry": {"coordinates":[-0.939538,54.566691],"type":"Point"}
}
