{
  "type": "Feature",
  "properties": {
    "iso:country":"GB",
    "wof:name":"TS12 2SP",
    "wof:placetype":"postalcode"
},
  "geometry": {"coordinates":[-0.93953733216661,54.56666897741912],"type":"Point"}
}