{
  "type": "Feature",
  "properties": {
    "iso:country":"GB",
    "wof:name":"E2 9JG",
    "wof:placetype":"postalcode"
},
  "geometry": {"coordinates":[-0.046086028933,51.53241458309559],"type":"Point"}
}