{
  "type": "Feature",
  "properties": {
    "date:inception_lower": "1980-01-01",
    "date:inception_upper": "1980-01-01",
    "iso:country": "GB",
    "wof:name": "OL14 6RJ",
    "wof:placetype": "postalcode"
  },
  "geometry": {"coordinates":[-2.106384,53.700703],"type":"Point"}
}
