{
  "type": "Feature",
  "properties": {
    "iso:country":"GB",
    "wof:name":"OL14 6RJ",
    "wof:placetype":"postalcode"
},
  "geometry": {"coordinates":[-2.10632293618408,53.70068774576843],"type":"Point"}
}