{
  "type": "Feature",
  "properties": {
    "iso:country":"GB",
    "wof:name":"BH9 2AF",
    "wof:placetype":"postalcode"
},
  "geometry": {"coordinates":[-1.87887812944115,50.74031774001254],"type":"Point"}
}