{
  "type": "Feature",
  "properties": {
    "iso:country":"GB",
    "wof:name":"BH20 6DD",
    "wof:placetype":"postalcode"
},
  "geometry": {"coordinates":[-2.21692725065473,50.6778586902082],"type":"Point"}
}