{
  "type": "Feature",
  "properties": {
    "iso:country":"GB",
    "wof:name":"HR5 3QN",
    "wof:placetype":"postalcode"
},
  "geometry": {"coordinates":[-3.19308542878178,52.13905743061154],"type":"Point"}
}