{
  "type": "Feature",
  "properties": {
    "iso:country":"GB",
    "wof:name":"LS23 7FU",
    "wof:placetype":"postalcode"
},
  "geometry": {"coordinates":[-1.33311502791581,53.91846031361565],"type":"Point"}
}