{
  "type": "Feature",
  "properties": {
    "date:inception_lower": "2012-02-01",
    "date:inception_upper": "2012-02-01",
    "iso:country": "GB",
    "wof:name": "LS23 7FU",
    "wof:placetype": "postalcode"
  },
  "geometry": {"coordinates":[-1.333115,53.91846],"type":"Point"}
}
