{
  "type": "Feature",
  "properties": {
    "iso:country":"GB",
    "wof:name":"EX20 4HN",
    "wof:placetype":"postalcode"
},
  "geometry": {"coordinates":[-4.0761756513184,50.69375617279878],"type":"Point"}
}