{
  "type": "Feature",
  "properties": {
    "iso:country": "GB",
    "wof:name": "LN7 6AY",
    "wof:placetype": "postalcode"
  },
  "geometry": {"coordinates":[-0.310243,53.493233],"type":"Point"}
}
