{
  "type": "Feature",
  "properties": {
    "iso:country":"GB",
    "wof:name":"NN8 3HP",
    "wof:placetype":"postalcode"
},
  "geometry": {"coordinates":[-0.7055229652783,52.30148462557918],"type":"Point"}
}