{
  "type": "Feature",
  "properties": {
    "iso:country":"GB",
    "wof:name":"M21 9GX",
    "wof:placetype":"postalcode"
},
  "geometry": {"coordinates":[-2.28117082059871,53.43817898803118],"type":"Point"}
}