{
  "type": "Feature",
  "properties": {
    "iso:country":"GB",
    "wof:name":"ST1 6DX",
    "wof:placetype":"postalcode"
},
  "geometry": {"coordinates":[-2.16909756611904,53.04299068046043],"type":"Point"}
}