{
  "type": "Feature",
  "properties": {
    "iso:country":"GB",
    "wof:name":"YO12 7SY",
    "wof:placetype":"postalcode"
},
  "geometry": {"coordinates":[-0.40935182900277,54.28355965106635],"type":"Point"}
}