{
  "type": "Feature",
  "properties": {
    "iso:country":"GB",
    "wof:name":"RH19 3PU",
    "wof:placetype":"postalcode"
},
  "geometry": {"coordinates":[0.03983333350721,51.14531580910999],"type":"Point"}
}