{
  "type": "Feature",
  "properties": {
    "iso:country":"GB",
    "wof:name":"G33 2BG",
    "wof:placetype":"postalcode"
},
  "geometry": {"coordinates":[-4.18777839469489,55.87226000955782],"type":"Point"}
}