{
  "type": "Feature",
  "properties": {
    "iso:country":"GB",
    "wof:name":"CT14 9LN",
    "wof:placetype":"postalcode"
},
  "geometry": {"coordinates":[1.36376034733087,51.21139220298829],"type":"Point"}
}