{
  "type": "Feature",
  "properties": {
    "iso:country": "GB",
    "wof:name": "CT14 9LN",
    "wof:placetype": "postalcode"
  },
  "geometry": {"coordinates":[1.36376,51.211392],"type":"Point"}
}
