{
  "type": "Feature",
  "properties": {
    "date:inception_lower": "1980-01-01",
    "date:inception_upper": "1980-01-01",
    "iso:country": "GB",
    "wof:name": "WN4 8RR",
    "wof:placetype": "postalcode"
  },
  "geometry": {"coordinates":[-2.627949,53.491815],"type":"Point"}
}
