{
  "type": "Feature",
  "properties": {
    "iso:country":"GB",
    "wof:name":"WN4 8RR",
    "wof:placetype":"postalcode"
},
  "geometry": {"coordinates":[-2.6279489092324,53.4918150894334],"type":"Point"}
}