{
  "type": "Feature",
  "properties": {
    "iso:country":"GB",
    "wof:name":"PO20 7RR",
    "wof:placetype":"postalcode"
},
  "geometry": {"coordinates":[-0.78744270240031,50.77504178557671],"type":"Point"}
}