{
  "type": "Feature",
  "properties": {
    "iso:country":"GB",
    "wof:name":"DE13 8LJ",
    "wof:placetype":"postalcode"
},
  "geometry": {"coordinates":[-1.72420012222359,52.76040994310957],"type":"Point"}
}