{
  "type": "Feature",
  "properties": {
    "date:inception_lower":"1980-01-01",
    "date:inception_upper":"1980-01-31",
    "iso:country":"GB",
    "wof:name":"DE13 8LJ",
    "wof:placetype":"postalcode"
},
  "geometry": {"coordinates":[-1.724253,52.760427],"type":"Point"}
}