{
  "type": "Feature",
  "properties": {
    "iso:country": "GB",
    "wof:name": "DE13 8LJ",
    "wof:placetype": "postalcode"
  },
  "geometry": {"coordinates":[-1.724253,52.760427],"type":"Point"}
}
