{
  "type": "Feature",
  "properties": {
    "iso:country": "GB",
    "wof:name": "WR1 1SD",
    "wof:placetype": "postalcode"
  },
  "geometry": {"coordinates":[-2.226972,52.205898],"type":"Point"}
}
