{
  "type": "Feature",
  "properties": {
    "iso:country":"GB",
    "wof:name":"WN2 5RD",
    "wof:placetype":"postalcode"
},
  "geometry": {"coordinates":[-2.59305258722941,53.51099518401804],"type":"Point"}
}