{
  "type": "Feature",
  "properties": {
    "date:inception_lower": "1980-01-01",
    "date:inception_upper": "1980-01-01",
    "iso:country": "GB",
    "wof:name": "PA14 5LA",
    "wof:placetype": "postalcode"
  },
  "geometry": {"coordinates":[-4.695793,55.932792],"type":"Point"}
}
