{
  "type": "Feature",
  "properties": {
    "iso:country":"GB",
    "wof:name":"TF9 3SL",
    "wof:placetype":"postalcode"
},
  "geometry": {"coordinates":[-2.49603851820568,52.90893558957215],"type":"Point"}
}