{
  "type": "Feature",
  "properties": {
    "date:inception_lower":"1980-01-01",
    "date:inception_upper":"1980-01-31",
    "iso:country":"GB",
    "wof:name":"TF9 3SL",
    "wof:placetype":"postalcode"
},
  "geometry": {"coordinates":[-2.496038,52.908936],"type":"Point"}
}