{
  "type": "Feature",
  "properties": {
    "date:inception_lower": "1980-01-01",
    "date:inception_upper": "1980-01-01",
    "iso:country": "GB",
    "wof:name": "SL7 3HP",
    "wof:placetype": "postalcode"
  },
  "geometry": {"coordinates":[-0.773887,51.575413],"type":"Point"}
}
