{
  "type": "Feature",
  "properties": {
    "iso:country":"GB",
    "wof:name":"SL7 3HP",
    "wof:placetype":"postalcode"
},
  "geometry": {"coordinates":[-0.7738872234671,51.57541290523777],"type":"Point"}
}