{
  "type": "Feature",
  "properties": {
    "date:inception_lower":"1980-01-01",
    "date:inception_upper":"1980-01-31",
    "iso:country":"GB",
    "wof:name":"YO13 9NS",
    "wof:placetype":"postalcode"
},
  "geometry": {"coordinates":[-0.623091,54.232387],"type":"Point"}
}