{
  "type": "Feature",
  "properties": {
    "iso:country":"GB",
    "wof:name":"YO13 9NS",
    "wof:placetype":"postalcode"
},
  "geometry": {"coordinates":[-0.62309110419143,54.2323866258316],"type":"Point"}
}