{
  "type": "Feature",
  "properties": {
    "iso:country":"GB",
    "wof:name":"HU9 1JT",
    "wof:placetype":"postalcode"
},
  "geometry": {"coordinates":[-0.31652216363577,53.75052062874387],"type":"Point"}
}