{
  "type": "Feature",
  "properties": {
    "date:inception_lower": "1980-01-01",
    "date:inception_upper": "1980-01-01",
    "iso:country": "GB",
    "wof:name": "HU9 1JT",
    "wof:placetype": "postalcode"
  },
  "geometry": {"coordinates":[-0.316522,53.750521],"type":"Point"}
}
