{
  "type": "Feature",
  "properties": {
    "iso:country": "GB",
    "wof:name": "LE9 7BJ",
    "wof:placetype": "postalcode"
  },
  "geometry": {"coordinates":[-1.310649,52.572855],"type":"Point"}
}
