{
  "type": "Feature",
  "properties": {
    "iso:country":"GB",
    "wof:name":"LE9 7BJ",
    "wof:placetype":"postalcode"
},
  "geometry": {"coordinates":[-1.31064931077248,52.57285456929738],"type":"Point"}
}