{
  "type": "Feature",
  "properties": {
    "date:inception_lower":"1980-01-01",
    "date:inception_upper":"1980-01-31",
    "iso:country":"GB",
    "wof:name":"NG10 2DF",
    "wof:placetype":"postalcode"
},
  "geometry": {"coordinates":[-1.264661,52.896569],"type":"Point"}
}