{
  "type": "Feature",
  "properties": {
    "iso:country":"GB",
    "wof:name":"NE48 2EX",
    "wof:placetype":"postalcode"
},
  "geometry": {"coordinates":[-2.19534125422356,55.12841046576869],"type":"Point"}
}