{
  "type": "Feature",
  "properties": {
    "date:inception_lower":"1980-01-01",
    "date:inception_upper":"1980-01-31",
    "iso:country":"GB",
    "wof:name":"NE48 2EX",
    "wof:placetype":"postalcode"
},
  "geometry": {"coordinates":[-2.195341,55.12841],"type":"Point"}
}