{
  "type": "Feature",
  "properties": {
    "iso:country":"GB",
    "wof:name":"SO19 1BQ",
    "wof:placetype":"postalcode"
},
  "geometry": {"coordinates":[-1.34636623040091,50.90027354893035],"type":"Point"}
}