{
  "type": "Feature",
  "properties": {
    "iso:country":"GB",
    "wof:name":"SK14 4QD",
    "wof:placetype":"postalcode"
},
  "geometry": {"coordinates":[-2.08880905313597,53.46156870170614],"type":"Point"}
}