{
  "type": "Feature",
  "properties": {
    "iso:country":"GB",
    "wof:name":"ST1 3GF",
    "wof:placetype":"postalcode"
},
  "geometry": {"coordinates":[-2.16728011877629,53.02047549145714],"type":"Point"}
}