{
  "type": "Feature",
  "properties": {
    "iso:country": "GB",
    "wof:name": "M30 8LY",
    "wof:placetype": "postalcode"
  },
  "geometry": {"coordinates":[-2.366875,53.486044],"type":"Point"}
}
