{
  "type": "Feature",
  "properties": {
    "iso:country":"GB",
    "wof:name":"IP9 2NA",
    "wof:placetype":"postalcode"
},
  "geometry": {"coordinates":[1.10911628896525,51.99188093745718],"type":"Point"}
}