{
  "type": "Feature",
  "properties": {
    "iso:country":"GB",
    "wof:name":"GU14 6JN",
    "wof:placetype":"postalcode"
},
  "geometry": {"coordinates":[-0.74142365235352,51.27726134248811],"type":"Point"}
}