{
  "type": "Feature",
  "properties": {
    "iso:country": "GB",
    "wof:name": "RG6 5XS",
    "wof:placetype": "postalcode"
  },
  "geometry": {"coordinates":[-0.937821,51.425948],"type":"Point"}
}
