{
  "type": "Feature",
  "properties": {
    "iso:country":"GB",
    "wof:name":"RG6 5XS",
    "wof:placetype":"postalcode"
},
  "geometry": {"coordinates":[-0.93782111529774,51.42594839254097],"type":"Point"}
}