{
  "type": "Feature",
  "properties": {
    "date:inception_lower": "1995-07-01",
    "date:inception_upper": "1995-07-01",
    "iso:country": "GB",
    "wof:name": "RG6 5XS",
    "wof:placetype": "postalcode"
  },
  "geometry": {"coordinates":[-0.937821,51.425948],"type":"Point"}
}
