{
  "type": "Feature",
  "properties": {
    "iso:country":"GB",
    "wof:name":"SW3 2SR",
    "wof:placetype":"postalcode"
},
  "geometry": {"coordinates":[-0.16092276975396,51.49135902834864],"type":"Point"}
}