{
  "type": "Feature",
  "properties": {
    "iso:country":"GB",
    "wof:name":"DN20 9RL",
    "wof:placetype":"postalcode"
},
  "geometry": {"coordinates":[-0.54556283223883,53.53952553480977],"type":"Point"}
}