{
  "type": "Feature",
  "properties": {
    "iso:country": "GB",
    "wof:name": "LE9 2AT",
    "wof:placetype": "postalcode"
  },
  "geometry": {"coordinates":[-1.230076,52.637788],"type":"Point"}
}
