{
  "type": "Feature",
  "properties": {
    "iso:country":"GB",
    "wof:name":"LE9 2AT",
    "wof:placetype":"postalcode"
},
  "geometry": {"coordinates":[-1.23008335620481,52.63776941011873],"type":"Point"}
}