{
  "type": "Feature",
  "properties": {
    "date:inception_lower": "1980-01-01",
    "date:inception_upper": "1980-01-01",
    "iso:country": "GB",
    "wof:name": "PO22 8LH",
    "wof:placetype": "postalcode"
  },
  "geometry": {"coordinates":[-0.639214,50.797095],"type":"Point"}
}
