{
  "type": "Feature",
  "properties": {
    "iso:country":"GB",
    "wof:name":"PO22 8LH",
    "wof:placetype":"postalcode"
},
  "geometry": {"coordinates":[-0.63921429013511,50.79709456546794],"type":"Point"}
}