{
  "type": "Feature",
  "properties": {
    "date:inception_lower": "1980-01-01",
    "date:inception_upper": "1980-01-01",
    "iso:country": "GB",
    "wof:name": "MK41 6AD",
    "wof:placetype": "postalcode"
  },
  "geometry": {"coordinates":[-0.481804,52.178721],"type":"Point"}
}
