{
  "type": "Feature",
  "properties": {
    "iso:country":"GB",
    "wof:name":"MK41 6AD",
    "wof:placetype":"postalcode"
},
  "geometry": {"coordinates":[-0.48419422177797,52.18042075791431],"type":"Point"}
}