{
  "type": "Feature",
  "properties": {
    "date:inception_lower": "2003-09-01",
    "date:inception_upper": "2003-09-01",
    "iso:country": "GB",
    "wof:name": "SN11 9QT",
    "wof:placetype": "postalcode"
  },
  "geometry": {"coordinates":[-2.006355,51.44768],"type":"Point"}
}
