{
  "type": "Feature",
  "properties": {
    "iso:country": "GB",
    "wof:name": "SN11 9QT",
    "wof:placetype": "postalcode"
  },
  "geometry": {"coordinates":[-2.006355,51.44768],"type":"Point"}
}
