{
  "type": "Feature",
  "properties": {
    "date:inception_lower":"1980-01-01",
    "date:inception_upper":"1980-01-31",
    "iso:country":"GB",
    "wof:name":"NG8 5PR",
    "wof:placetype":"postalcode"
},
  "geometry": {"coordinates":[-1.208135,52.976105],"type":"Point"}
}