{
  "type": "Feature",
  "properties": {
    "iso:country":"GB",
    "wof:name":"NG8 5PR",
    "wof:placetype":"postalcode"
},
  "geometry": {"coordinates":[-1.20813539931011,52.9761045716835],"type":"Point"}
}