{
  "type": "Feature",
  "properties": {
    "iso:country":"GB",
    "wof:name":"L34 6JJ",
    "wof:placetype":"postalcode"
},
  "geometry": {"coordinates":[-2.80177097040003,53.43215966885034],"type":"Point"}
}