{
  "type": "Feature",
  "properties": {
    "iso:country": "GB",
    "wof:name": "L34 6JJ",
    "wof:placetype": "postalcode"
  },
  "geometry": {"coordinates":[-2.801771,53.43216],"type":"Point"}
}
