{
  "type": "Feature",
  "properties": {
    "date:inception_lower": "1980-01-01",
    "date:inception_upper": "1980-01-01",
    "iso:country": "GB",
    "wof:name": "TQ4 7DW",
    "wof:placetype": "postalcode"
  },
  "geometry": {"coordinates":[-3.586994,50.424083],"type":"Point"}
}
