{
  "type": "Feature",
  "properties": {
    "iso:country":"GB",
    "wof:name":"WF17 7DL",
    "wof:placetype":"postalcode"
},
  "geometry": {"coordinates":[-1.64817443091645,53.70848842607538],"type":"Point"}
}