{
  "type": "Feature",
  "properties": {
    "date:inception_lower":"2013-10-01",
    "date:inception_upper":"2013-10-31",
    "iso:country":"GB",
    "wof:name":"OX1 1GH",
    "wof:placetype":"postalcode"
},
  "geometry": {"coordinates":[-1.273093,51.759887],"type":"Point"}
}