{
  "type": "Feature",
  "properties": {
    "iso:country":"GB",
    "wof:name":"OX1 1GH",
    "wof:placetype":"postalcode"
},
  "geometry": {"coordinates":[-1.27309308765164,51.75988727038019],"type":"Point"}
}