{
  "type": "Feature",
  "properties": {
    "iso:country": "GB",
    "wof:name": "CH43 7ST",
    "wof:placetype": "postalcode"
  },
  "geometry": {"coordinates":[-3.067054,53.401391],"type":"Point"}
}
