{
  "type": "Feature",
  "properties": {
    "date:inception_lower": "1999-06-01",
    "date:inception_upper": "1999-06-01",
    "iso:country": "GB",
    "wof:name": "CH43 7ST",
    "wof:placetype": "postalcode"
  },
  "geometry": {"coordinates":[-3.067054,53.401391],"type":"Point"}
}
