{
  "type": "Feature",
  "properties": {
    "date:inception_lower":"1980-01-01",
    "date:inception_upper":"1980-01-31",
    "iso:country":"GB",
    "wof:name":"IP4 3JL",
    "wof:placetype":"postalcode"
},
  "geometry": {"coordinates":[1.196271,52.06917],"type":"Point"}
}