{
  "type": "Feature",
  "properties": {
    "iso:country":"GB",
    "wof:name":"IG6 2LR",
    "wof:placetype":"postalcode"
},
  "geometry": {"coordinates":[0.07967004614403,51.59594407493799],"type":"Point"}
}