{
  "type": "Feature",
  "properties": {
    "iso:country": "GB",
    "wof:name": "IG6 2LR",
    "wof:placetype": "postalcode"
  },
  "geometry": {"coordinates":[0.07967,51.595944],"type":"Point"}
}
