{
  "type": "Feature",
  "properties": {
    "date:inception_lower": "1990-07-01",
    "date:inception_upper": "1990-07-01",
    "iso:country": "GB",
    "wof:name": "IG6 2LR",
    "wof:placetype": "postalcode"
  },
  "geometry": {"coordinates":[0.079695,51.59591],"type":"Point"}
}
