{
  "type": "Feature",
  "properties": {
    "date:inception_lower": "2012-08-01",
    "date:inception_upper": "2012-08-01",
    "iso:country": "GB",
    "wof:name": "SA61 2AU",
    "wof:placetype": "postalcode"
  },
  "geometry": {"coordinates":[-4.988281,51.803386],"type":"Point"}
}
