{
  "type": "Feature",
  "properties": {
    "iso:country":"GB",
    "wof:name":"SA61 2AU",
    "wof:placetype":"postalcode"
},
  "geometry": {"coordinates":[-4.98828060217829,51.80338552601768],"type":"Point"}
}