{
  "type": "Feature",
  "properties": {
    "iso:country":"GB",
    "wof:name":"CO12 3DL",
    "wof:placetype":"postalcode"
},
  "geometry": {"coordinates":[1.28906871532628,51.94494039423122],"type":"Point"}
}