{
  "type": "Feature",
  "properties": {
    "date:inception_lower": "2003-02-01",
    "date:inception_upper": "2003-02-01",
    "iso:country": "GB",
    "wof:name": "KY11 2GB",
    "wof:placetype": "postalcode"
  },
  "geometry": {"coordinates":[-3.429623,56.033942],"type":"Point"}
}
