{
  "type": "Feature",
  "properties": {
    "date:inception_lower":"1987-04-01",
    "date:inception_upper":"1987-04-30",
    "iso:country":"GB",
    "wof:name":"GU24 8NQ",
    "wof:placetype":"postalcode"
},
  "geometry": {"coordinates":[-0.603721,51.35031],"type":"Point"}
}