{
  "type": "Feature",
  "properties": {
    "iso:country": "GB",
    "wof:name": "GU24 8NQ",
    "wof:placetype": "postalcode"
  },
  "geometry": {"coordinates":[-0.603721,51.35031],"type":"Point"}
}
