{
  "type": "Feature",
  "properties": {
    "date:inception_lower":"2001-12-01",
    "date:inception_upper":"2001-12-31",
    "iso:country":"GB",
    "wof:name":"HD4 6JB",
    "wof:placetype":"postalcode"
},
  "geometry": {"coordinates":[-1.786318,53.628721],"type":"Point"}
}