{
  "type": "Feature",
  "properties": {
    "iso:country": "GB",
    "wof:name": "HD4 6JB",
    "wof:placetype": "postalcode"
  },
  "geometry": {"coordinates":[-1.786318,53.628721],"type":"Point"}
}
