{
  "type": "Feature",
  "properties": {
    "iso:country":"GB",
    "wof:name":"HD4 6JB",
    "wof:placetype":"postalcode"
},
  "geometry": {"coordinates":[-1.78631800973698,53.62872056110002],"type":"Point"}
}