{
  "type": "Feature",
  "properties": {
    "iso:country":"GB",
    "wof:name":"CF10 3NQ",
    "wof:placetype":"postalcode"
},
  "geometry": {"coordinates":[-3.18257301872617,51.4883726166005],"type":"Point"}
}