{
  "type": "Feature",
  "properties": {
    "iso:country":"GB",
    "wof:name":"L6 2BB",
    "wof:placetype":"postalcode"
},
  "geometry": {"coordinates":[-2.95940901093198,53.41756777153473],"type":"Point"}
}