{
  "type": "Feature",
  "properties": {
    "iso:country":"GB",
    "wof:name":"TR13 9DX",
    "wof:placetype":"postalcode"
},
  "geometry": {"coordinates":[-5.3147088184866,50.08397618940819],"type":"Point"}
}