{
  "type": "Feature",
  "properties": {
    "date:inception_lower": "2004-10-01",
    "date:inception_upper": "2004-10-01",
    "iso:country": "GB",
    "wof:name": "AL3 5JF",
    "wof:placetype": "postalcode"
  },
  "geometry": {"coordinates":[-0.34391,51.755586],"type":"Point"}
}
