{
  "type": "Feature",
  "properties": {
    "iso:country":"GB",
    "wof:name":"AL3 5JF",
    "wof:placetype":"postalcode"
},
  "geometry": {"coordinates":[-0.34391000591683,51.75558592988802],"type":"Point"}
}