{
  "type": "Feature",
  "properties": {
    "iso:country":"GB",
    "wof:name":"M4 4EW",
    "wof:placetype":"postalcode"
},
  "geometry": {"coordinates":[-2.24110442711789,53.48959089770732],"type":"Point"}
}