{
  "type": "Feature",
  "properties": {
    "iso:country": "GB",
    "wof:name": "M4 4EW",
    "wof:placetype": "postalcode"
  },
  "geometry": {"coordinates":[-2.241059,53.489546],"type":"Point"}
}
