{
  "type": "Feature",
  "properties": {
    "date:inception_lower": "2004-08-01",
    "date:inception_upper": "2004-08-01",
    "iso:country": "GB",
    "wof:name": "NE65 7BA",
    "wof:placetype": "postalcode"
  },
  "geometry": {"coordinates":[-1.90853,55.310445],"type":"Point"}
}
