{
  "type": "Feature",
  "properties": {
    "date:inception_lower": "2024-01-01",
    "date:inception_upper": "2024-01-01",
    "iso:country": "GB",
    "wof:name": "OX26 9PZ",
    "wof:placetype": "postalcode"
  },
  "geometry": {"coordinates":[-1.141501,51.901779],"type":"Point"}
}
