{
  "type": "Feature",
  "properties": {
    "date:inception_lower":"2014-10-01",
    "date:inception_upper":"2014-10-31",
    "iso:country":"GB",
    "wof:name":"LL11 6FB",
    "wof:placetype":"postalcode"
},
  "geometry": {"coordinates":[-3.027308,53.058826],"type":"Point"}
}