{
  "type": "Feature",
  "properties": {
    "iso:country":"GB",
    "wof:name":"PE1 3QQ",
    "wof:placetype":"postalcode"
},
  "geometry": {"coordinates":[-0.24842262874151,52.59009342499966],"type":"Point"}
}