{
  "type": "Feature",
  "properties": {
    "iso:country": "GB",
    "wof:name": "PE13 1EF",
    "wof:placetype": "postalcode"
  },
  "geometry": {"coordinates":[0.158858,52.664399],"type":"Point"}
}
