{
  "type": "Feature",
  "properties": {
    "date:inception_lower": "1980-01-01",
    "date:inception_upper": "1980-01-01",
    "iso:country": "GB",
    "wof:name": "NN8 4NT",
    "wof:placetype": "postalcode"
  },
  "geometry": {"coordinates":[-0.684389,52.30794],"type":"Point"}
}
