{
  "type": "Feature",
  "properties": {
    "iso:country":"GB",
    "wof:name":"NN8 4NT",
    "wof:placetype":"postalcode"
},
  "geometry": {"coordinates":[-0.68438892026848,52.30794030479565],"type":"Point"}
}