{
  "type": "Feature",
  "properties": {
    "iso:country":"GB",
    "wof:name":"N6 5AW",
    "wof:placetype":"postalcode"
},
  "geometry": {"coordinates":[-0.13693379268628,51.57763191491225],"type":"Point"}
}