{
  "type": "Feature",
  "properties": {
    "iso:country":"GB",
    "wof:name":"GL51 9SQ",
    "wof:placetype":"postalcode"
},
  "geometry": {"coordinates":[-2.10307185350811,51.9197078911306],"type":"Point"}
}