{
  "type": "Feature",
  "properties": {
    "iso:country":"GB",
    "wof:name":"LU4 0FH",
    "wof:placetype":"postalcode"
},
  "geometry": {"coordinates":[-0.47546912582504,51.89650360107027],"type":"Point"}
}