{
  "type": "Feature",
  "properties": {
    "iso:country":"GB",
    "wof:name":"NR12 8EG",
    "wof:placetype":"postalcode"
},
  "geometry": {"coordinates":[1.42763073697411,52.71758428245084],"type":"Point"}
}