{
  "type": "Feature",
  "properties": {
    "iso:country":"GB",
    "wof:name":"CB7 4HL",
    "wof:placetype":"postalcode"
},
  "geometry": {"coordinates":[0.25495345066111,52.39702128938022],"type":"Point"}
}