{
  "type": "Feature",
  "properties": {
    "iso:country": "GB",
    "wof:name": "CB7 4HL",
    "wof:placetype": "postalcode"
  },
  "geometry": {"coordinates":[0.254953,52.397021],"type":"Point"}
}
