{
  "type": "Feature",
  "properties": {
    "date:inception_lower": "1980-01-01",
    "date:inception_upper": "1980-01-01",
    "iso:country": "GB",
    "wof:name": "CB7 4HL",
    "wof:placetype": "postalcode"
  },
  "geometry": {"coordinates":[0.254953,52.397021],"type":"Point"}
}
