{
  "type": "Feature",
  "properties": {
    "iso:country":"GB",
    "wof:name":"S63 7SN",
    "wof:placetype":"postalcode"
},
  "geometry": {"coordinates":[-1.34838340266294,53.49686864510348],"type":"Point"}
}