{
  "type": "Feature",
  "properties": {
    "iso:country": "GB",
    "wof:name": "S63 7SN",
    "wof:placetype": "postalcode"
  },
  "geometry": {"coordinates":[-1.348383,53.496869],"type":"Point"}
}
