{
  "type": "Feature",
  "properties": {
    "iso:country":"GB",
    "wof:name":"NE16 3DY",
    "wof:placetype":"postalcode"
},
  "geometry": {"coordinates":[-1.68184007683477,54.95422608471688],"type":"Point"}
}