{
  "type": "Feature",
  "properties": {
    "date:inception_lower": "1990-07-01",
    "date:inception_upper": "1990-07-01",
    "iso:country": "GB",
    "wof:name": "DT2 8XB",
    "wof:placetype": "postalcode"
  },
  "geometry": {"coordinates":[-2.384293,50.678677],"type":"Point"}
}
