{
  "type": "Feature",
  "properties": {
    "iso:country": "GB",
    "wof:name": "DT2 8XB",
    "wof:placetype": "postalcode"
  },
  "geometry": {"coordinates":[-2.384293,50.678677],"type":"Point"}
}
