{
  "type": "Feature",
  "properties": {
    "iso:country":"GB",
    "wof:name":"DT2 8XB",
    "wof:placetype":"postalcode"
},
  "geometry": {"coordinates":[-2.3843077544052,50.67868562365229],"type":"Point"}
}