{
  "type": "Feature",
  "properties": {
    "iso:country":"GB",
    "wof:name":"OX29 6QB",
    "wof:placetype":"postalcode"
},
  "geometry": {"coordinates":[-1.42753279171256,51.83188716297367],"type":"Point"}
}