{
  "type": "Feature",
  "properties": {
    "iso:country": "GB",
    "wof:name": "OX29 6QB",
    "wof:placetype": "postalcode"
  },
  "geometry": {"coordinates":[-1.427533,51.831887],"type":"Point"}
}
