{
  "type": "Feature",
  "properties": {
    "iso:country":"GB",
    "wof:name":"WD6 1EB",
    "wof:placetype":"postalcode"
},
  "geometry": {"coordinates":[-0.27430740828508,51.65627408899937],"type":"Point"}
}