{
  "type": "Feature",
  "properties": {
    "date:inception_lower": "2021-11-01",
    "date:inception_upper": "2021-11-01",
    "iso:country": "GB",
    "wof:name": "SG14 2GP",
    "wof:placetype": "postalcode"
  },
  "geometry": {"coordinates":[-0.106347,51.797559],"type":"Point"}
}
