{
  "type": "Feature",
  "properties": {
    "date:inception_lower": "1990-07-01",
    "date:inception_upper": "1990-07-01",
    "iso:country": "GB",
    "wof:name": "CW2 6UN",
    "wof:placetype": "postalcode"
  },
  "geometry": {"coordinates":[-2.442876,53.078719],"type":"Point"}
}
