{
  "type": "Feature",
  "properties": {
    "iso:country":"GB",
    "wof:name":"CW2 6UN",
    "wof:placetype":"postalcode"
},
  "geometry": {"coordinates":[-2.44287582155894,53.07871893752176],"type":"Point"}
}