{
  "type": "Feature",
  "properties": {
    "iso:country":"GB",
    "wof:name":"TR27 4PQ",
    "wof:placetype":"postalcode"
},
  "geometry": {"coordinates":[-5.40499691482133,50.19499367322216],"type":"Point"}
}