{
  "type": "Feature",
  "properties": {
    "iso:country":"GB",
    "wof:name":"PH10 7NH",
    "wof:placetype":"postalcode"
},
  "geometry": {"coordinates":[-3.46293275713096,56.67514610097974],"type":"Point"}
}