{
  "type": "Feature",
  "properties": {
    "iso:country": "GB",
    "wof:name": "SS9 3FP",
    "wof:placetype": "postalcode"
  },
  "geometry": {"coordinates":[0.672259,51.549683],"type":"Point"}
}
