{
  "type": "Feature",
  "properties": {
    "date:inception_lower": "2016-10-01",
    "date:inception_upper": "2016-10-01",
    "iso:country": "GB",
    "wof:name": "SS9 3FP",
    "wof:placetype": "postalcode"
  },
  "geometry": {"coordinates":[0.672259,51.549683],"type":"Point"}
}
