{
  "type": "Feature",
  "properties": {
    "iso:country":"GB",
    "wof:name":"NW3 7BT",
    "wof:placetype":"postalcode"
},
  "geometry": {"coordinates":[-0.19232945662757,51.55460555518126],"type":"Point"}
}