{
  "type": "Feature",
  "properties": {
    "iso:country":"GB",
    "wof:name":"RM8 1JB",
    "wof:placetype":"postalcode"
},
  "geometry": {"coordinates":[0.14755067735799,51.56695182296359],"type":"Point"}
}