{
  "type": "Feature",
  "properties": {
    "iso:country":"GB",
    "wof:name":"SK17 9HZ",
    "wof:placetype":"postalcode"
},
  "geometry": {"coordinates":[-1.90395369942374,53.23616442405278],"type":"Point"}
}