{
  "type": "Feature",
  "properties": {
    "iso:country": "GB",
    "wof:name": "DH8 9BD",
    "wof:placetype": "postalcode"
  },
  "geometry": {"coordinates":[-1.894733,54.850229],"type":"Point"}
}
