{
  "type": "Feature",
  "properties": {
    "iso:country":"GB",
    "wof:name":"DN16 2LN",
    "wof:placetype":"postalcode"
},
  "geometry": {"coordinates":[-0.63750579538235,53.56970597433882],"type":"Point"}
}