{
  "type": "Feature",
  "properties": {
    "date:inception_lower": "1981-06-01",
    "date:inception_upper": "1981-06-01",
    "iso:country": "GB",
    "wof:name": "OL7 0SY",
    "wof:placetype": "postalcode"
  },
  "geometry": {"coordinates":[-2.106479,53.48061],"type":"Point"}
}
