{
  "type": "Feature",
  "properties": {
    "date:inception_lower": "2003-03-01",
    "date:inception_upper": "2003-03-01",
    "iso:country": "GB",
    "wof:name": "RG26 5JU",
    "wof:placetype": "postalcode"
  },
  "geometry": {"coordinates":[-1.057885,51.324835],"type":"Point"}
}
