{
  "type": "Feature",
  "properties": {
    "iso:country":"GB",
    "wof:name":"SS12 9QT",
    "wof:placetype":"postalcode"
},
  "geometry": {"coordinates":[0.52722561153,51.59983875057394],"type":"Point"}
}