{
  "type": "Feature",
  "properties": {
    "iso:country": "GB",
    "wof:name": "SS12 9QT",
    "wof:placetype": "postalcode"
  },
  "geometry": {"coordinates":[0.527226,51.599839],"type":"Point"}
}
