{
  "type": "Feature",
  "properties": {
    "date:inception_lower": "1998-06-01",
    "date:inception_upper": "1998-06-01",
    "iso:country": "GB",
    "wof:name": "DN36 4GP",
    "wof:placetype": "postalcode"
  },
  "geometry": {"coordinates":[-0.065952,53.527615],"type":"Point"}
}
