{
  "type": "Feature",
  "properties": {
    "iso:country":"GB",
    "wof:name":"UB8 3QR",
    "wof:placetype":"postalcode"
},
  "geometry": {"coordinates":[-0.4613540406495,51.53358737258041],"type":"Point"}
}