{
  "type": "Feature",
  "properties": {
    "iso:country":"GB",
    "wof:name":"NW10 0PW",
    "wof:placetype":"postalcode"
},
  "geometry": {"coordinates":[-0.26612763122883,51.54891211998498],"type":"Point"}
}