{
  "type": "Feature",
  "properties": {
    "date:inception_lower":"1985-04-01",
    "date:inception_upper":"1985-04-30",
    "iso:country":"GB",
    "wof:name":"NW10 0PW",
    "wof:placetype":"postalcode"
},
  "geometry": {"coordinates":[-0.266144,51.548867],"type":"Point"}
}