{
  "type": "Feature",
  "properties": {
    "iso:country":"GB",
    "wof:name":"EX34 9HA",
    "wof:placetype":"postalcode"
},
  "geometry": {"coordinates":[-4.12185675734351,51.20853520519466],"type":"Point"}
}