{
  "type": "Feature",
  "properties": {
    "iso:country":"GB",
    "wof:name":"CW9 6AB",
    "wof:placetype":"postalcode"
},
  "geometry": {"coordinates":[-2.53903146156361,53.27487570033291],"type":"Point"}
}