{
  "type": "Feature",
  "properties": {
    "iso:country":"GB",
    "wof:name":"DL11 7DP",
    "wof:placetype":"postalcode"
},
  "geometry": {"coordinates":[-1.86931172441835,54.48873448491492],"type":"Point"}
}