{
  "type": "Feature",
  "properties": {
    "iso:country": "GB",
    "wof:name": "CB11 3LS",
    "wof:placetype": "postalcode"
  },
  "geometry": {"coordinates":[0.2792,51.969869],"type":"Point"}
}
