{
  "type": "Feature",
  "properties": {
    "iso:country":"GB",
    "wof:name":"CB11 3LS",
    "wof:placetype":"postalcode"
},
  "geometry": {"coordinates":[0.28282402450347,51.9698073136715],"type":"Point"}
}