{
  "type": "Feature",
  "properties": {
    "date:inception_lower": "1980-01-01",
    "date:inception_upper": "1980-01-01",
    "iso:country": "GB",
    "wof:name": "CB11 3LS",
    "wof:placetype": "postalcode"
  },
  "geometry": {"coordinates":[0.282851,51.969816],"type":"Point"}
}
