{
  "type": "Feature",
  "properties": {
    "iso:country":"GB",
    "wof:name":"EX23 8PJ",
    "wof:placetype":"postalcode"
},
  "geometry": {"coordinates":[-4.54278801883184,50.8262572972398],"type":"Point"}
}