{
  "type": "Feature",
  "properties": {
    "iso:country": "GB",
    "wof:name": "BD23 3JA",
    "wof:placetype": "postalcode"
  },
  "geometry": {"coordinates":[-2.107633,53.951845],"type":"Point"}
}
