{
  "type": "Feature",
  "properties": {
    "iso:country":"GB",
    "wof:name":"SL4 1EB",
    "wof:placetype":"postalcode"
},
  "geometry": {"coordinates":[-0.6093896668537,51.48125824431618],"type":"Point"}
}