{
  "type": "Feature",
  "properties": {
    "date:inception_lower": "1980-01-01",
    "date:inception_upper": "1980-01-01",
    "iso:country": "GB",
    "wof:name": "SL4 1EB",
    "wof:placetype": "postalcode"
  },
  "geometry": {"coordinates":[-0.60939,51.481258],"type":"Point"}
}
