{
  "type": "Feature",
  "properties": {
    "date:inception_lower": "1999-06-01",
    "date:inception_upper": "1999-06-01",
    "iso:country": "GB",
    "wof:name": "CF24 4PY",
    "wof:placetype": "postalcode"
  },
  "geometry": {"coordinates":[-3.179136,51.499728],"type":"Point"}
}
