{
  "type": "Feature",
  "properties": {
    "iso:country": "GB",
    "wof:name": "EH54 9AU",
    "wof:placetype": "postalcode"
  },
  "geometry": {"coordinates":[-3.501442,55.867991],"type":"Point"}
}
