{
  "type": "Feature",
  "properties": {
    "iso:country":"GB",
    "wof:name":"CM2 8DY",
    "wof:placetype":"postalcode"
},
  "geometry": {"coordinates":[0.49843649040524,51.71296005222382],"type":"Point"}
}