{
  "type": "Feature",
  "properties": {
    "iso:country":"GB",
    "wof:name":"W1H 6BW",
    "wof:placetype":"postalcode"
},
  "geometry": {"coordinates":[-0.15657494942836,51.51628991623665],"type":"Point"}
}