{
  "type": "Feature",
  "properties": {
    "iso:country":"GB",
    "wof:name":"OL2 8BX",
    "wof:placetype":"postalcode"
},
  "geometry": {"coordinates":[-2.08863382103418,53.5938775887368],"type":"Point"}
}