{
  "type": "Feature",
  "properties": {
    "iso:country":"GB",
    "wof:name":"CM9 6EA",
    "wof:placetype":"postalcode"
},
  "geometry": {"coordinates":[0.66723794294136,51.72670374269217],"type":"Point"}
}