{
  "type": "Feature",
  "properties": {
    "date:inception_lower": "1981-06-01",
    "date:inception_upper": "1981-06-01",
    "iso:country": "GB",
    "wof:name": "SA9 1DG",
    "wof:placetype": "postalcode"
  },
  "geometry": {"coordinates":[-3.777869,51.773132],"type":"Point"}
}
