{
  "type": "Feature",
  "properties": {
    "iso:country":"GB",
    "wof:name":"SA9 1DG",
    "wof:placetype":"postalcode"
},
  "geometry": {"coordinates":[-3.77786950355748,51.77313183538352],"type":"Point"}
}