{
  "type": "Feature",
  "properties": {
    "iso:country":"GB",
    "wof:name":"SA1 6HQ",
    "wof:placetype":"postalcode"
},
  "geometry": {"coordinates":[-3.95010181858614,51.62588354189366],"type":"Point"}
}