{
  "type": "Feature",
  "properties": {
    "iso:country": "GB",
    "wof:name": "SA1 6HQ",
    "wof:placetype": "postalcode"
  },
  "geometry": {"coordinates":[-3.950102,51.625884],"type":"Point"}
}
