{
  "type": "Feature",
  "properties": {
    "iso:country": "GB",
    "wof:name": "ME6 5JU",
    "wof:placetype": "postalcode"
  },
  "geometry": {"coordinates":[0.438135,51.319144],"type":"Point"}
}
