{
  "type": "Feature",
  "properties": {
    "iso:country":"GB",
    "wof:name":"ME6 5JU",
    "wof:placetype":"postalcode"
},
  "geometry": {"coordinates":[0.43813526116211,51.31914403964679],"type":"Point"}
}