{
  "type": "Feature",
  "properties": {
    "date:inception_lower":"1996-06-01",
    "date:inception_upper":"1996-06-30",
    "iso:country":"GB",
    "wof:name":"WA14 4AJ",
    "wof:placetype":"postalcode"
},
  "geometry": {"coordinates":[-2.355929,53.388228],"type":"Point"}
}