{
  "type": "Feature",
  "properties": {
    "iso:country":"GB",
    "wof:name":"ML4 1LT",
    "wof:placetype":"postalcode"
},
  "geometry": {"coordinates":[-4.01806789139009,55.82695455120336],"type":"Point"}
}