{
  "type": "Feature",
  "properties": {
    "iso:country": "GB",
    "wof:name": "PR5 5JJ",
    "wof:placetype": "postalcode"
  },
  "geometry": {"coordinates":[-2.695323,53.725429],"type":"Point"}
}
