{
  "type": "Feature",
  "properties": {
    "date:inception_lower": "2024-04-01",
    "date:inception_upper": "2024-04-01",
    "iso:country": "GB",
    "wof:name": "M11 1BL",
    "wof:placetype": "postalcode"
  },
  "geometry": {"coordinates":[-2.173945,53.47501],"type":"Point"}
}
