{
  "type": "Feature",
  "properties": {
    "iso:country":"GB",
    "wof:name":"KT17 2NB",
    "wof:placetype":"postalcode"
},
  "geometry": {"coordinates":[-0.24335802802621,51.35906600042711],"type":"Point"}
}