{
  "type": "Feature",
  "properties": {
    "iso:country":"GB",
    "wof:name":"TN15 8SJ",
    "wof:placetype":"postalcode"
},
  "geometry": {"coordinates":[0.30480314998908,51.28820065629419],"type":"Point"}
}