{
  "type": "Feature",
  "properties": {
    "iso:country":"GB",
    "wof:name":"G1 3SJ",
    "wof:placetype":"postalcode"
},
  "geometry": {"coordinates":[-4.25869470012861,55.85969925647772],"type":"Point"}
}