{
  "type": "Feature",
  "properties": {
    "iso:country": "GB",
    "wof:name": "G1 3SJ",
    "wof:placetype": "postalcode"
  },
  "geometry": {"coordinates":[-4.258749,55.857065],"type":"Point"}
}
