{
  "type": "Feature",
  "properties": {
    "iso:country": "GB",
    "wof:name": "W6 7BG",
    "wof:placetype": "postalcode"
  },
  "geometry": {"coordinates":[-0.223364,51.496296],"type":"Point"}
}
