{
  "type": "Feature",
  "properties": {
    "iso:country":"GB",
    "wof:name":"W6 7BG",
    "wof:placetype":"postalcode"
},
  "geometry": {"coordinates":[-0.22336391845279,51.49629628603548],"type":"Point"}
}