{
  "type": "Feature",
  "properties": {
    "iso:country":"GB",
    "wof:name":"PO16 8NJ",
    "wof:placetype":"postalcode"
},
  "geometry": {"coordinates":[-1.13455295633497,50.84873504586556],"type":"Point"}
}