{
  "type": "Feature",
  "properties": {
    "iso:country": "GB",
    "wof:name": "SN14 6XW",
    "wof:placetype": "postalcode"
  },
  "geometry": {"coordinates":[-2.134959,51.473318],"type":"Point"}
}
