{
  "type": "Feature",
  "properties": {
    "date:inception_lower": "1995-07-01",
    "date:inception_upper": "1995-07-01",
    "iso:country": "GB",
    "wof:name": "SN14 6XW",
    "wof:placetype": "postalcode"
  },
  "geometry": {"coordinates":[-2.134959,51.473318],"type":"Point"}
}
