{
  "type": "Feature",
  "properties": {
    "iso:country":"GB",
    "wof:name":"LL30 1RP",
    "wof:placetype":"postalcode"
},
  "geometry": {"coordinates":[-3.81116271029398,53.30287083880554],"type":"Point"}
}