{
  "type": "Feature",
  "properties": {
    "iso:country": "GB",
    "wof:name": "LL30 1RP",
    "wof:placetype": "postalcode"
  },
  "geometry": {"coordinates":[-3.811163,53.302871],"type":"Point"}
}
