{
  "type": "Feature",
  "properties": {
    "iso:country":"GB",
    "wof:name":"NR11 6FJ",
    "wof:placetype":"postalcode"
},
  "geometry": {"coordinates":[1.23179897974428,52.78934262498233],"type":"Point"}
}