{
  "type": "Feature",
  "properties": {
    "date:inception_lower": "2014-06-01",
    "date:inception_upper": "2014-06-01",
    "iso:country": "GB",
    "wof:name": "G40 4RX",
    "wof:placetype": "postalcode"
  },
  "geometry": {"coordinates":[-4.209321,55.840316],"type":"Point"}
}
