{
  "type": "Feature",
  "properties": {
    "iso:country":"GB",
    "wof:name":"DH9 0RS",
    "wof:placetype":"postalcode"
},
  "geometry": {"coordinates":[-1.6567178771963,54.87883437180915],"type":"Point"}
}