{
  "type": "Feature",
  "properties": {
    "iso:country": "GB",
    "wof:name": "DH9 0RS",
    "wof:placetype": "postalcode"
  },
  "geometry": {"coordinates":[-1.656729,54.878842],"type":"Point"}
}
