{
  "type": "Feature",
  "properties": {
    "iso:country":"GB",
    "wof:name":"LU7 3EQ",
    "wof:placetype":"postalcode"
},
  "geometry": {"coordinates":[-0.6523223949684,51.92540211028057],"type":"Point"}
}