{
  "type": "Feature",
  "properties": {
    "iso:country":"GB",
    "wof:name":"PR26 9HS",
    "wof:placetype":"postalcode"
},
  "geometry": {"coordinates":[-2.77237418643549,53.66659557560193],"type":"Point"}
}