{
  "type": "Feature",
  "properties": {
    "iso:country":"GB",
    "wof:name":"OX29 8AZ",
    "wof:placetype":"postalcode"
},
  "geometry": {"coordinates":[-1.4024308108702,51.81185611385025],"type":"Point"}
}