{
  "type": "Feature",
  "properties": {
    "iso:country": "GB",
    "wof:name": "BH23 5LS",
    "wof:placetype": "postalcode"
  },
  "geometry": {"coordinates":[-1.694335,50.746455],"type":"Point"}
}
