{
  "type": "Feature",
  "properties": {
    "date:inception_lower": "1980-01-01",
    "date:inception_upper": "1980-01-01",
    "iso:country": "GB",
    "wof:name": "TN13 3SG",
    "wof:placetype": "postalcode"
  },
  "geometry": {"coordinates":[0.204245,51.283312],"type":"Point"}
}
