{
  "type": "Feature",
  "properties": {
    "date:inception_lower": "1997-12-01",
    "date:inception_upper": "1997-12-01",
    "iso:country": "GB",
    "wof:name": "AB12 3TW",
    "wof:placetype": "postalcode"
  },
  "geometry": {"coordinates":[-2.093754,57.111675],"type":"Point"}
}
