{
  "type": "Feature",
  "properties": {
    "iso:country":"GB",
    "wof:name":"S66 7JG",
    "wof:placetype":"postalcode"
},
  "geometry": {"coordinates":[-1.19570591881871,53.4165776841131],"type":"Point"}
}