{
  "type": "Feature",
  "properties": {
    "date:inception_lower": "1992-01-01",
    "date:inception_upper": "1992-01-01",
    "iso:country": "GB",
    "wof:name": "NE37 3HP",
    "wof:placetype": "postalcode"
  },
  "geometry": {"coordinates":[-1.507367,54.919163],"type":"Point"}
}
