{
  "type": "Feature",
  "properties": {
    "iso:country": "GB",
    "wof:name": "NE37 3HP",
    "wof:placetype": "postalcode"
  },
  "geometry": {"coordinates":[-1.507367,54.919163],"type":"Point"}
}
