{
  "type": "Feature",
  "properties": {
    "iso:country":"GB",
    "wof:name":"NE37 3HP",
    "wof:placetype":"postalcode"
},
  "geometry": {"coordinates":[-1.50735414978176,54.91915509726103],"type":"Point"}
}