{
  "type": "Feature",
  "properties": {
    "iso:country":"GB",
    "wof:name":"PE24 4JQ",
    "wof:placetype":"postalcode"
},
  "geometry": {"coordinates":[0.22783542424955,53.10156794887646],"type":"Point"}
}