{
  "type": "Feature",
  "properties": {
    "date:inception_lower":"2008-03-01",
    "date:inception_upper":"2008-03-31",
    "iso:country":"GB",
    "wof:name":"RG6 6UA",
    "wof:placetype":"postalcode"
},
  "geometry": {"coordinates":[-0.943567,51.44126],"type":"Point"}
}