{
  "type": "Feature",
  "properties": {
    "date:inception_lower": "1980-04-01",
    "date:inception_upper": "1980-04-01",
    "iso:country": "GB",
    "wof:name": "EH6 6RB",
    "wof:placetype": "postalcode"
  },
  "geometry": {"coordinates":[-3.170248,55.975309],"type":"Point"}
}
