{
  "type": "Feature",
  "properties": {
    "date:inception_lower":"1980-04-01",
    "date:inception_upper":"1980-04-30",
    "iso:country":"GB",
    "wof:name":"EH6 6RB",
    "wof:placetype":"postalcode"
},
  "geometry": {"coordinates":[-3.170246,55.975315],"type":"Point"}
}