{
  "type": "Feature",
  "properties": {
    "iso:country": "GB",
    "wof:name": "IP11 2HE",
    "wof:placetype": "postalcode"
  },
  "geometry": {"coordinates":[1.334549,51.954138],"type":"Point"}
}
