{
  "type": "Feature",
  "properties": {
    "date:inception_lower": "2019-10-01",
    "date:inception_upper": "2019-10-01",
    "iso:country": "GB",
    "wof:name": "CV10 9GX",
    "wof:placetype": "postalcode"
  },
  "geometry": {"coordinates":[-1.527383,52.527528],"type":"Point"}
}
