{
  "type": "Feature",
  "properties": {
    "iso:country":"GB",
    "wof:name":"SE24 0ED",
    "wof:placetype":"postalcode"
},
  "geometry": {"coordinates":[-0.10102516827483,51.45670906590795],"type":"Point"}
}