{
  "type": "Feature",
  "properties": {
    "iso:country":"GB",
    "wof:name":"NP23 6TN",
    "wof:placetype":"postalcode"
},
  "geometry": {"coordinates":[-3.19387711521582,51.75461084838602],"type":"Point"}
}