{
  "type": "Feature",
  "properties": {
    "iso:country": "GB",
    "wof:name": "GU9 0BB",
    "wof:placetype": "postalcode"
  },
  "geometry": {"coordinates":[-0.808588,51.230314],"type":"Point"}
}
