{
  "type": "Feature",
  "properties": {
    "iso:country":"GB",
    "wof:name":"NG31 8EA",
    "wof:placetype":"postalcode"
},
  "geometry": {"coordinates":[-0.63962076087616,52.92749291328867],"type":"Point"}
}