{
  "type": "Feature",
  "properties": {
    "iso:country": "GB",
    "wof:name": "NG31 8EA",
    "wof:placetype": "postalcode"
  },
  "geometry": {"coordinates":[-0.639523,52.927622],"type":"Point"}
}
