{
  "type": "Feature",
  "properties": {
    "date:inception_lower":"1980-01-01",
    "date:inception_upper":"1980-01-31",
    "iso:country":"GB",
    "wof:name":"E2 0JW",
    "wof:placetype":"postalcode"
},
  "geometry": {"coordinates":[-0.050722,51.52885],"type":"Point"}
}