{
  "type": "Feature",
  "properties": {
    "date:inception_lower": "2022-02-01",
    "date:inception_upper": "2022-02-01",
    "iso:country": "GB",
    "wof:name": "M33 7GT",
    "wof:placetype": "postalcode"
  },
  "geometry": {"coordinates":[-2.317082,53.43131],"type":"Point"}
}
