{
  "type": "Feature",
  "properties": {
    "iso:country": "GB",
    "wof:name": "N7 0LY",
    "wof:placetype": "postalcode"
  },
  "geometry": {"coordinates":[-0.125668,51.555376],"type":"Point"}
}
