{
  "type": "Feature",
  "properties": {
    "iso:country": "GB",
    "wof:name": "SO24 0DT",
    "wof:placetype": "postalcode"
  },
  "geometry": {"coordinates":[-1.079763,51.083043],"type":"Point"}
}
