{
  "type": "Feature",
  "properties": {
    "iso:country":"GB",
    "wof:name":"SO24 0DT",
    "wof:placetype":"postalcode"
},
  "geometry": {"coordinates":[-1.07970733764615,51.08303852737036],"type":"Point"}
}