{
  "type": "Feature",
  "properties": {
    "iso:country":"GB",
    "wof:name":"EC2M 2AR",
    "wof:placetype":"postalcode"
},
  "geometry": {"coordinates":[-0.08299893501601,51.51931897741461],"type":"Point"}
}