{
  "type": "Feature",
  "properties": {
    "iso:country": "GB",
    "wof:name": "EC2M 2AR",
    "wof:placetype": "postalcode"
  },
  "geometry": {"coordinates":[-0.082999,51.519319],"type":"Point"}
}
