{
  "type": "Feature",
  "properties": {
    "iso:country":"GB",
    "wof:name":"AB41 9BL",
    "wof:placetype":"postalcode"
},
  "geometry": {"coordinates":[-2.07070199623375,57.36439446502547],"type":"Point"}
}