{
  "type": "Feature",
  "properties": {
    "iso:country": "GB",
    "wof:name": "SL1 2YS",
    "wof:placetype": "postalcode"
  },
  "geometry": {"coordinates":[-0.618624,51.511644],"type":"Point"}
}
