{
  "type": "Feature",
  "properties": {
    "date:inception_lower": "1987-04-01",
    "date:inception_upper": "1987-04-01",
    "iso:country": "GB",
    "wof:name": "SL1 2YS",
    "wof:placetype": "postalcode"
  },
  "geometry": {"coordinates":[-0.618624,51.511644],"type":"Point"}
}
