{
  "type": "Feature",
  "properties": {
    "iso:country":"GB",
    "wof:name":"S74 0AS",
    "wof:placetype":"postalcode"
},
  "geometry": {"coordinates":[-1.45755151960482,53.50037987251591],"type":"Point"}
}