{
  "type": "Feature",
  "properties": {
    "iso:country":"GB",
    "wof:name":"BS1 6TE",
    "wof:placetype":"postalcode"
},
  "geometry": {"coordinates":[-2.5915281639849,51.44659142326913],"type":"Point"}
}