{
  "type": "Feature",
  "properties": {
    "iso:country": "GB",
    "wof:name": "TA6 9HP",
    "wof:placetype": "postalcode"
  },
  "geometry": {"coordinates":[-3.004586,51.126389],"type":"Point"}
}
