{
  "type": "Feature",
  "properties": {
    "iso:country": "GB",
    "wof:name": "G69 7NP",
    "wof:placetype": "postalcode"
  },
  "geometry": {"coordinates":[-4.118932,55.849676],"type":"Point"}
}
