{
  "type": "Feature",
  "properties": {
    "iso:country":"GB",
    "wof:name":"G69 7NP",
    "wof:placetype":"postalcode"
},
  "geometry": {"coordinates":[-4.11893181823371,55.8496759463445],"type":"Point"}
}