{
  "type": "Feature",
  "properties": {
    "iso:country": "GB",
    "wof:name": "SW1X 9AH",
    "wof:placetype": "postalcode"
  },
  "geometry": {"coordinates":[-0.156574,51.494637],"type":"Point"}
}
