{
  "type": "Feature",
  "properties": {
    "date:inception_lower":"1980-01-01",
    "date:inception_upper":"1980-01-31",
    "iso:country":"GB",
    "wof:name":"BR5 4PN",
    "wof:placetype":"postalcode"
},
  "geometry": {"coordinates":[0.121422,51.371472],"type":"Point"}
}