{
  "type": "Feature",
  "properties": {
    "date:inception_lower":"2004-05-01",
    "date:inception_upper":"2004-05-31",
    "iso:country":"GB",
    "wof:name":"E2 9AW",
    "wof:placetype":"postalcode"
},
  "geometry": {"coordinates":[-0.063105,51.534657],"type":"Point"}
}