{
  "type": "Feature",
  "properties": {
    "iso:country":"GB",
    "wof:name":"E2 9AW",
    "wof:placetype":"postalcode"
},
  "geometry": {"coordinates":[-0.06310530106414,51.53465721969397],"type":"Point"}
}