{
  "type": "Feature",
  "properties": {
    "date:inception_lower":"1991-09-01",
    "date:inception_upper":"1991-09-30",
    "iso:country":"GB",
    "wof:name":"CR0 7LY",
    "wof:placetype":"postalcode"
},
  "geometry": {"coordinates":[-0.045786,51.384057],"type":"Point"}
}