{
  "type": "Feature",
  "properties": {
    "iso:country":"GB",
    "wof:name":"CR0 7LY",
    "wof:placetype":"postalcode"
},
  "geometry": {"coordinates":[-0.04578638936841,51.38405713570924],"type":"Point"}
}