{
  "type": "Feature",
  "properties": {
    "iso:country":"GB",
    "wof:name":"SO32 2NJ",
    "wof:placetype":"postalcode"
},
  "geometry": {"coordinates":[-1.20325037779741,50.93779202944695],"type":"Point"}
}