{
  "type": "Feature",
  "properties": {
    "date:inception_lower":"2000-10-01",
    "date:inception_upper":"2000-10-31",
    "iso:country":"GB",
    "wof:name":"WD24 4GS",
    "wof:placetype":"postalcode"
},
  "geometry": {"coordinates":[-0.388394,51.661393],"type":"Point"}
}