{
  "type": "Feature",
  "properties": {
    "iso:country": "GB",
    "wof:name": "WD24 4GS",
    "wof:placetype": "postalcode"
  },
  "geometry": {"coordinates":[-0.388394,51.661393],"type":"Point"}
}
