{
  "type": "Feature",
  "properties": {
    "date:inception_lower": "1980-01-01",
    "date:inception_upper": "1980-01-01",
    "iso:country": "GB",
    "wof:name": "DE55 1BL",
    "wof:placetype": "postalcode"
  },
  "geometry": {"coordinates":[-1.399708,53.075254],"type":"Point"}
}
