{
  "type": "Feature",
  "properties": {
    "iso:country":"GB",
    "wof:name":"DE55 1BL",
    "wof:placetype":"postalcode"
},
  "geometry": {"coordinates":[-1.39951310621919,53.07530664254306],"type":"Point"}
}