{
  "type": "Feature",
  "properties": {
    "iso:country": "GB",
    "wof:name": "SP6 3NU",
    "wof:placetype": "postalcode"
  },
  "geometry": {"coordinates":[-1.849531,50.971536],"type":"Point"}
}
