{
  "type": "Feature",
  "properties": {
    "date:inception_lower": "1980-01-01",
    "date:inception_upper": "1980-01-01",
    "iso:country": "GB",
    "wof:name": "SP6 3NU",
    "wof:placetype": "postalcode"
  },
  "geometry": {"coordinates":[-1.849417,50.971563],"type":"Point"}
}
