{
  "type": "Feature",
  "properties": {
    "iso:country":"GB",
    "wof:name":"SP6 3NU",
    "wof:placetype":"postalcode"
},
  "geometry": {"coordinates":[-1.8494959154818,50.97151587495657],"type":"Point"}
}