{
  "type": "Feature",
  "properties": {
    "date:inception_lower": "2019-08-01",
    "date:inception_upper": "2019-08-01",
    "iso:country": "GB",
    "wof:name": "KT1 4FU",
    "wof:placetype": "postalcode"
  },
  "geometry": {"coordinates":[-0.310327,51.412118],"type":"Point"}
}
