{
  "type": "Feature",
  "properties": {
    "iso:country": "GB",
    "wof:name": "KT1 4FU",
    "wof:placetype": "postalcode"
  },
  "geometry": {"coordinates":[-0.310311,51.412171],"type":"Point"}
}
