{
  "type": "Feature",
  "properties": {
    "iso:country":"GB",
    "wof:name":"PO18 0RP",
    "wof:placetype":"postalcode"
},
  "geometry": {"coordinates":[-0.78508336343951,50.90705984819213],"type":"Point"}
}