{
  "type": "Feature",
  "properties": {
    "date:inception_lower": "1980-01-01",
    "date:inception_upper": "1980-01-01",
    "iso:country": "GB",
    "wof:name": "PO18 0RP",
    "wof:placetype": "postalcode"
  },
  "geometry": {"coordinates":[-0.785121,50.907053],"type":"Point"}
}
