{
  "type": "Feature",
  "properties": {
    "iso:country":"GB",
    "wof:name":"NW4 4XB",
    "wof:placetype":"postalcode"
},
  "geometry": {"coordinates":[-0.23177429319449,51.59942184153473],"type":"Point"}
}