{
  "type": "Feature",
  "properties": {
    "date:inception_lower": "2016-12-01",
    "date:inception_upper": "2016-12-01",
    "iso:country": "GB",
    "wof:name": "SS17 0FW",
    "wof:placetype": "postalcode"
  },
  "geometry": {"coordinates":[0.419356,51.508531],"type":"Point"}
}
