{
  "type": "Feature",
  "properties": {
    "iso:country": "GB",
    "wof:name": "WA10 4BY",
    "wof:placetype": "postalcode"
  },
  "geometry": {"coordinates":[-2.760835,53.45178],"type":"Point"}
}
