{
  "type": "Feature",
  "properties": {
    "iso:country":"GB",
    "wof:name":"DN6 0BJ",
    "wof:placetype":"postalcode"
},
  "geometry": {"coordinates":[-1.15261774056526,53.61599903669267],"type":"Point"}
}