{
  "type": "Feature",
  "properties": {
    "date:inception_lower":"1981-09-01",
    "date:inception_upper":"1981-09-30",
    "iso:country":"GB",
    "wof:name":"HP4 1JZ",
    "wof:placetype":"postalcode"
},
  "geometry": {"coordinates":[-0.581992,51.77064],"type":"Point"}
}