{
  "type": "Feature",
  "properties": {
    "iso:country": "GB",
    "wof:name": "HP4 1JZ",
    "wof:placetype": "postalcode"
  },
  "geometry": {"coordinates":[-0.581992,51.77064],"type":"Point"}
}
