{
  "type": "Feature",
  "properties": {
    "iso:country":"GB",
    "wof:name":"HP4 1JZ",
    "wof:placetype":"postalcode"
},
  "geometry": {"coordinates":[-0.58199239967128,51.7706401606507],"type":"Point"}
}