{
  "type": "Feature",
  "properties": {
    "iso:country": "GB",
    "wof:name": "NG7 2DE",
    "wof:placetype": "postalcode"
  },
  "geometry": {"coordinates":[-1.180148,52.951913],"type":"Point"}
}
