{
  "type": "Feature",
  "properties": {
    "date:inception_lower": "1980-01-01",
    "date:inception_upper": "1980-01-01",
    "iso:country": "GB",
    "wof:name": "NG33 4LY",
    "wof:placetype": "postalcode"
  },
  "geometry": {"coordinates":[-0.516795,52.811731],"type":"Point"}
}
