{
  "type": "Feature",
  "properties": {
    "iso:country": "GB",
    "wof:name": "NG33 4LY",
    "wof:placetype": "postalcode"
  },
  "geometry": {"coordinates":[-0.516795,52.811731],"type":"Point"}
}
