{
  "type": "Feature",
  "properties": {
    "iso:country":"GB",
    "wof:name":"CF23 9NU",
    "wof:placetype":"postalcode"
},
  "geometry": {"coordinates":[-3.14897486716772,51.51546647388685],"type":"Point"}
}