{
  "type": "Feature",
  "properties": {
    "date:inception_lower":"1980-01-01",
    "date:inception_upper":"1980-01-31",
    "iso:country":"GB",
    "wof:name":"LL53 8PQ",
    "wof:placetype":"postalcode"
},
  "geometry": {"coordinates":[-4.462637,52.92094],"type":"Point"}
}