{
  "type": "Feature",
  "properties": {
    "iso:country": "GB",
    "wof:name": "LL53 8PQ",
    "wof:placetype": "postalcode"
  },
  "geometry": {"coordinates":[-4.462637,52.92094],"type":"Point"}
}
