{
  "type": "Feature",
  "properties": {
    "date:inception_lower": "1980-01-01",
    "date:inception_upper": "1980-01-01",
    "iso:country": "GB",
    "wof:name": "G31 3EA",
    "wof:placetype": "postalcode"
  },
  "geometry": {"coordinates":[-4.21277,55.864794],"type":"Point"}
}
