{
  "type": "Feature",
  "properties": {
    "iso:country":"GB",
    "wof:name":"GU6 7BJ",
    "wof:placetype":"postalcode"
},
  "geometry": {"coordinates":[-0.4785082736241,51.13991663057059],"type":"Point"}
}