{
  "type": "Feature",
  "properties": {
    "iso:country":"GB",
    "wof:name":"AB43 8WL",
    "wof:placetype":"postalcode"
},
  "geometry": {"coordinates":[-1.93640665432478,57.67739284706455],"type":"Point"}
}