{
  "type": "Feature",
  "properties": {
    "iso:country":"GB",
    "wof:name":"WS11 9PT",
    "wof:placetype":"postalcode"
},
  "geometry": {"coordinates":[-1.96803248118808,52.66674838853236],"type":"Point"}
}