{
  "type": "Feature",
  "properties": {
    "date:inception_lower": "1984-02-01",
    "date:inception_upper": "1984-02-01",
    "iso:country": "GB",
    "wof:name": "TQ12 3RG",
    "wof:placetype": "postalcode"
  },
  "geometry": {"coordinates":[-3.586314,50.551902],"type":"Point"}
}
