{
  "type": "Feature",
  "properties": {
    "iso:country":"GB",
    "wof:name":"DN21 4ET",
    "wof:placetype":"postalcode"
},
  "geometry": {"coordinates":[-0.59229944838361,53.45437277657715],"type":"Point"}
}