{
  "type": "Feature",
  "properties": {
    "date:inception_lower":"1980-01-01",
    "date:inception_upper":"1980-01-31",
    "iso:country":"GB",
    "wof:name":"DN21 4ET",
    "wof:placetype":"postalcode"
},
  "geometry": {"coordinates":[-0.592299,53.454373],"type":"Point"}
}