{
  "type": "Feature",
  "properties": {
    "iso:country":"GB",
    "wof:name":"HX3 8PP",
    "wof:placetype":"postalcode"
},
  "geometry": {"coordinates":[-1.81853261615452,53.72234932214484],"type":"Point"}
}