{
  "type": "Feature",
  "properties": {
    "iso:country":"GB",
    "wof:name":"NG33 5PN",
    "wof:placetype":"postalcode"
},
  "geometry": {"coordinates":[-0.62755788484401,52.76591011482874],"type":"Point"}
}