{
  "type": "Feature",
  "properties": {
    "iso:country":"GB",
    "wof:name":"RG45 7PT",
    "wof:placetype":"postalcode"
},
  "geometry": {"coordinates":[-0.81182509192614,51.36367416838324],"type":"Point"}
}