{
  "type": "Feature",
  "properties": {
    "iso:country": "GB",
    "wof:name": "RG45 7PT",
    "wof:placetype": "postalcode"
  },
  "geometry": {"coordinates":[-0.810421,51.363445],"type":"Point"}
}
