{
  "type": "Feature",
  "properties": {
    "iso:country": "GB",
    "wof:name": "L25 2RL",
    "wof:placetype": "postalcode"
  },
  "geometry": {"coordinates":[-2.867379,53.39215],"type":"Point"}
}
