{
  "type": "Feature",
  "properties": {
    "iso:country":"GB",
    "wof:name":"L25 2RL",
    "wof:placetype":"postalcode"
},
  "geometry": {"coordinates":[-2.86737886636913,53.39215024323168],"type":"Point"}
}