{
  "type": "Feature",
  "properties": {
    "iso:country": "GB",
    "wof:name": "EH15 2HP",
    "wof:placetype": "postalcode"
  },
  "geometry": {"coordinates":[-3.101016,55.948655],"type":"Point"}
}
