{
  "type": "Feature",
  "properties": {
    "date:inception_lower":"1980-01-01",
    "date:inception_upper":"1980-01-31",
    "iso:country":"GB",
    "wof:name":"EH15 2HP",
    "wof:placetype":"postalcode"
},
  "geometry": {"coordinates":[-3.101016,55.948655],"type":"Point"}
}