{
  "type": "Feature",
  "properties": {
    "iso:country":"GB",
    "wof:name":"EH15 2HP",
    "wof:placetype":"postalcode"
},
  "geometry": {"coordinates":[-3.10101629113174,55.94865499444204],"type":"Point"}
}