{
  "type": "Feature",
  "properties": {
    "iso:country":"GB",
    "wof:name":"HA4 7TW",
    "wof:placetype":"postalcode"
},
  "geometry": {"coordinates":[-0.43662404637963,51.58837318780067],"type":"Point"}
}