{
  "type": "Feature",
  "properties": {
    "iso:country":"GB",
    "wof:name":"OL16 3ER",
    "wof:placetype":"postalcode"
},
  "geometry": {"coordinates":[-2.10525594115878,53.61317085402785],"type":"Point"}
}