{
  "type": "Feature",
  "properties": {
    "iso:country":"GB",
    "wof:name":"BA2 3AR",
    "wof:placetype":"postalcode"
},
  "geometry": {"coordinates":[-2.36797400608741,51.37684136629619],"type":"Point"}
}