{
  "type": "Feature",
  "properties": {
    "iso:country":"GB",
    "wof:name":"GL12 8LY",
    "wof:placetype":"postalcode"
},
  "geometry": {"coordinates":[-2.40325137338629,51.62374904580584],"type":"Point"}
}