{
  "type": "Feature",
  "properties": {
    "iso:country":"GB",
    "wof:name":"LE2 5FH",
    "wof:placetype":"postalcode"
},
  "geometry": {"coordinates":[-1.09272651892638,52.60063961587196],"type":"Point"}
}