{
  "type": "Feature",
  "properties": {
    "iso:country": "GB",
    "wof:name": "BN21 3EH",
    "wof:placetype": "postalcode"
  },
  "geometry": {"coordinates":[0.292511,50.767689],"type":"Point"}
}
