{
  "type": "Feature",
  "properties": {
    "date:inception_lower":"1986-07-01",
    "date:inception_upper":"1986-07-31",
    "iso:country":"GB",
    "wof:name":"WR5 3HQ",
    "wof:placetype":"postalcode"
},
  "geometry": {"coordinates":[-2.210652,52.167059],"type":"Point"}
}