{
  "type": "Feature",
  "properties": {
    "iso:country":"GB",
    "wof:name":"SA18 1EN",
    "wof:placetype":"postalcode"
},
  "geometry": {"coordinates":[-3.88469006956144,51.79665419178794],"type":"Point"}
}