{
  "type": "Feature",
  "properties": {
    "iso:country": "GB",
    "wof:name": "SA18 1EN",
    "wof:placetype": "postalcode"
  },
  "geometry": {"coordinates":[-3.88469,51.796654],"type":"Point"}
}
