{
  "type": "Feature",
  "properties": {
    "date:inception_lower":"1980-01-01",
    "date:inception_upper":"1980-01-31",
    "iso:country":"GB",
    "wof:name":"BR1 4NR",
    "wof:placetype":"postalcode"
},
  "geometry": {"coordinates":[0.002626,51.419481],"type":"Point"}
}