{
  "type": "Feature",
  "properties": {
    "iso:country": "GB",
    "wof:name": "BR1 4NR",
    "wof:placetype": "postalcode"
  },
  "geometry": {"coordinates":[0.002626,51.419481],"type":"Point"}
}
