{
  "type": "Feature",
  "properties": {
    "iso:country":"GB",
    "wof:name":"BR1 4NR",
    "wof:placetype":"postalcode"
},
  "geometry": {"coordinates":[0.00262627178234,51.41948070795255],"type":"Point"}
}