{
  "type": "Feature",
  "properties": {
    "date:inception_lower": "1983-07-01",
    "date:inception_upper": "1983-07-01",
    "iso:country": "GB",
    "wof:name": "TN16 3BW",
    "wof:placetype": "postalcode"
  },
  "geometry": {"coordinates":[0.031604,51.320079],"type":"Point"}
}
