{
  "type": "Feature",
  "properties": {
    "iso:country":"GB",
    "wof:name":"TN16 3BW",
    "wof:placetype":"postalcode"
},
  "geometry": {"coordinates":[0.03215557392467,51.31989750444822],"type":"Point"}
}