{
  "type": "Feature",
  "properties": {
    "iso:country": "GB",
    "wof:name": "EX20 4EX",
    "wof:placetype": "postalcode"
  },
  "geometry": {"coordinates":[-4.117483,50.66523],"type":"Point"}
}
