{
  "type": "Feature",
  "properties": {
    "iso:country":"GB",
    "wof:name":"BD2 4AN",
    "wof:placetype":"postalcode"
},
  "geometry": {"coordinates":[-1.74641890889311,53.81194606145824],"type":"Point"}
}