{
  "type": "Feature",
  "properties": {
    "iso:country": "GB",
    "wof:name": "B77 3BB",
    "wof:placetype": "postalcode"
  },
  "geometry": {"coordinates":[-1.667349,52.63476],"type":"Point"}
}
