{
  "type": "Feature",
  "properties": {
    "iso:country":"GB",
    "wof:name":"B77 3BB",
    "wof:placetype":"postalcode"
},
  "geometry": {"coordinates":[-1.66734877655438,52.63475956210479],"type":"Point"}
}