{
  "type": "Feature",
  "properties": {
    "iso:country":"GB",
    "wof:name":"KT16 0JQ",
    "wof:placetype":"postalcode"
},
  "geometry": {"coordinates":[-0.52544728502621,51.36318983381282],"type":"Point"}
}