{
  "type": "Feature",
  "properties": {
    "date:inception_lower": "1980-01-01",
    "date:inception_upper": "1980-01-01",
    "iso:country": "GB",
    "wof:name": "KT16 0JQ",
    "wof:placetype": "postalcode"
  },
  "geometry": {"coordinates":[-0.525447,51.36319],"type":"Point"}
}
