{
  "type": "Feature",
  "properties": {
    "iso:country": "GB",
    "wof:name": "HR2 8RR",
    "wof:placetype": "postalcode"
  },
  "geometry": {"coordinates":[-2.802891,51.923458],"type":"Point"}
}
