{
  "type": "Feature",
  "properties": {
    "iso:country":"GB",
    "wof:name":"GL6 0QB",
    "wof:placetype":"postalcode"
},
  "geometry": {"coordinates":[-2.23418122983389,51.67946854588086],"type":"Point"}
}