{
  "type": "Feature",
  "properties": {
    "iso:country": "GB",
    "wof:name": "CH8 8JQ",
    "wof:placetype": "postalcode"
  },
  "geometry": {"coordinates":[-3.217048,53.229023],"type":"Point"}
}
