{
  "type": "Feature",
  "properties": {
    "iso:country":"GB",
    "wof:name":"LS11 7AN",
    "wof:placetype":"postalcode"
},
  "geometry": {"coordinates":[-1.55630971727338,53.77735621728911],"type":"Point"}
}