{
  "type": "Feature",
  "properties": {
    "iso:country": "GB",
    "wof:name": "DT7 3BS",
    "wof:placetype": "postalcode"
  },
  "geometry": {"coordinates":[-2.932209,50.72521],"type":"Point"}
}
