{
  "type": "Feature",
  "properties": {
    "date:inception_lower": "1980-01-01",
    "date:inception_upper": "1980-01-01",
    "iso:country": "GB",
    "wof:name": "DT7 3BS",
    "wof:placetype": "postalcode"
  },
  "geometry": {"coordinates":[-2.93194,50.72524],"type":"Point"}
}
