{
  "type": "Feature",
  "properties": {
    "iso:country": "GB",
    "wof:name": "PE20 3FA",
    "wof:placetype": "postalcode"
  },
  "geometry": {"coordinates":[-0.150945,52.947069],"type":"Point"}
}
