{
  "type": "Feature",
  "properties": {
    "date:inception_lower":"2005-03-01",
    "date:inception_upper":"2005-03-31",
    "iso:country":"GB",
    "wof:name":"YO24 3JN",
    "wof:placetype":"postalcode"
},
  "geometry": {"coordinates":[-1.134879,53.944772],"type":"Point"}
}