{
  "type": "Feature",
  "properties": {
    "iso:country":"GB",
    "wof:name":"YO24 3JN",
    "wof:placetype":"postalcode"
},
  "geometry": {"coordinates":[-1.1348785510369,53.94477166579222],"type":"Point"}
}