{
  "type": "Feature",
  "properties": {
    "iso:country":"GB",
    "wof:name":"SY3 0EQ",
    "wof:placetype":"postalcode"
},
  "geometry": {"coordinates":[-2.76162320770294,52.67228687238869],"type":"Point"}
}