{
  "type": "Feature",
  "properties": {
    "iso:country":"GB",
    "wof:name":"B31 2QB",
    "wof:placetype":"postalcode"
},
  "geometry": {"coordinates":[-1.96989238504554,52.41057357972043],"type":"Point"}
}