{
  "type": "Feature",
  "properties": {
    "iso:country":"GB",
    "wof:name":"LE16 9AW",
    "wof:placetype":"postalcode"
},
  "geometry": {"coordinates":[-0.93087059267571,52.47805569624492],"type":"Point"}
}