{
  "type": "Feature",
  "properties": {
    "iso:country":"GB",
    "wof:name":"NE61 6NQ",
    "wof:placetype":"postalcode"
},
  "geometry": {"coordinates":[-1.65262198821905,55.13196406397586],"type":"Point"}
}