{
  "type": "Feature",
  "properties": {
    "iso:country":"GB",
    "wof:name":"S73 8HE",
    "wof:placetype":"postalcode"
},
  "geometry": {"coordinates":[-1.40119246566437,53.52227668187984],"type":"Point"}
}