{
  "type": "Feature",
  "properties": {
    "iso:country":"GB",
    "wof:name":"KW16 3DE",
    "wof:placetype":"postalcode"
},
  "geometry": {"coordinates":[-3.30160772991804,58.95979153750593],"type":"Point"}
}