{
  "type": "Feature",
  "properties": {
    "date:inception_lower": "1980-01-01",
    "date:inception_upper": "1980-01-01",
    "iso:country": "GB",
    "wof:name": "KW16 3DE",
    "wof:placetype": "postalcode"
  },
  "geometry": {"coordinates":[-3.301617,58.959782],"type":"Point"}
}
