{
  "type": "Feature",
  "properties": {
    "iso:country":"GB",
    "wof:name":"ST17 9QZ",
    "wof:placetype":"postalcode"
},
  "geometry": {"coordinates":[-2.14359570759925,52.79262737594288],"type":"Point"}
}