{
  "type": "Feature",
  "properties": {
    "iso:country":"GB",
    "wof:name":"NE38 7LX",
    "wof:placetype":"postalcode"
},
  "geometry": {"coordinates":[-1.51205109366153,54.89584533420427],"type":"Point"}
}