{
  "type": "Feature",
  "properties": {
    "iso:country": "GB",
    "wof:name": "NE38 7LX",
    "wof:placetype": "postalcode"
  },
  "geometry": {"coordinates":[-1.512051,54.895845],"type":"Point"}
}
