{
  "type": "Feature",
  "properties": {
    "iso:country":"GB",
    "wof:name":"B4 6DH",
    "wof:placetype":"postalcode"
},
  "geometry": {"coordinates":[-1.8953161192323,52.48449206171246],"type":"Point"}
}