{
  "type": "Feature",
  "properties": {
    "iso:country":"GB",
    "wof:name":"WV5 9HH",
    "wof:placetype":"postalcode"
},
  "geometry": {"coordinates":[-2.18724386657523,52.53469718301835],"type":"Point"}
}