{
  "type": "Feature",
  "properties": {
    "iso:country":"GB",
    "wof:name":"SW2 2DS",
    "wof:placetype":"postalcode"
},
  "geometry": {"coordinates":[-0.1143997434544,51.44722191072267],"type":"Point"}
}