{
  "type": "Feature",
  "properties": {
    "date:inception_lower":"1980-01-01",
    "date:inception_upper":"1980-01-31",
    "iso:country":"GB",
    "wof:name":"S6 1LU",
    "wof:placetype":"postalcode"
},
  "geometry": {"coordinates":[-1.50295,53.415977],"type":"Point"}
}