{
  "type": "Feature",
  "properties": {
    "iso:country":"GB",
    "wof:name":"S6 1LU",
    "wof:placetype":"postalcode"
},
  "geometry": {"coordinates":[-1.50302489945884,53.41599506119422],"type":"Point"}
}