{
  "type": "Feature",
  "properties": {
    "date:inception_lower": "1980-01-01",
    "date:inception_upper": "1980-01-01",
    "iso:country": "GB",
    "wof:name": "IP19 0RW",
    "wof:placetype": "postalcode"
  },
  "geometry": {"coordinates":[1.49807,52.391356],"type":"Point"}
}
