{
  "type": "Feature",
  "properties": {
    "iso:country":"GB",
    "wof:name":"CB5 8UJ",
    "wof:placetype":"postalcode"
},
  "geometry": {"coordinates":[0.17317775948705,52.21455308614795],"type":"Point"}
}