{
  "type": "Feature",
  "properties": {
    "iso:country": "GB",
    "wof:name": "CB5 8UJ",
    "wof:placetype": "postalcode"
  },
  "geometry": {"coordinates":[0.173178,52.214553],"type":"Point"}
}
