{
  "type": "Feature",
  "properties": {
    "date:inception_lower": "1980-01-01",
    "date:inception_upper": "1980-01-01",
    "iso:country": "GB",
    "wof:name": "SW1V 3RS",
    "wof:placetype": "postalcode"
  },
  "geometry": {"coordinates":[-0.13311,51.487035],"type":"Point"}
}
