{
  "type": "Feature",
  "properties": {
    "iso:country":"GB",
    "wof:name":"SW1V 3RS",
    "wof:placetype":"postalcode"
},
  "geometry": {"coordinates":[-0.1331102768561,51.48703477319758],"type":"Point"}
}