{
  "type": "Feature",
  "properties": {
    "iso:country": "GB",
    "wof:name": "DY13 0DL",
    "wof:placetype": "postalcode"
  },
  "geometry": {"coordinates":[-2.287711,52.326663],"type":"Point"}
}
