{
  "type": "Feature",
  "properties": {
    "iso:country":"GB",
    "wof:name":"KT3 6AZ",
    "wof:placetype":"postalcode"
},
  "geometry": {"coordinates":[-0.24947762517905,51.38805076741866],"type":"Point"}
}