{
  "type": "Feature",
  "properties": {
    "iso:country":"GB",
    "wof:name":"L37 2LG",
    "wof:placetype":"postalcode"
},
  "geometry": {"coordinates":[-3.08401023590308,53.55348328977218],"type":"Point"}
}