{
  "type": "Feature",
  "properties": {
    "date:inception_lower": "1999-06-01",
    "date:inception_upper": "1999-06-01",
    "iso:country": "GB",
    "wof:name": "NP19 4TG",
    "wof:placetype": "postalcode"
  },
  "geometry": {"coordinates":[-2.95689,51.572841],"type":"Point"}
}
