{
  "type": "Feature",
  "properties": {
    "iso:country": "GB",
    "wof:name": "EX31 4LR",
    "wof:placetype": "postalcode"
  },
  "geometry": {"coordinates":[-3.999072,51.15145],"type":"Point"}
}
