{
  "type": "Feature",
  "properties": {
    "iso:country":"GB",
    "wof:name":"EX31 4LR",
    "wof:placetype":"postalcode"
},
  "geometry": {"coordinates":[-3.99905057387871,51.15145189015126],"type":"Point"}
}