{
  "type": "Feature",
  "properties": {
    "iso:country": "GB",
    "wof:name": "SA9 2QB",
    "wof:placetype": "postalcode"
  },
  "geometry": {"coordinates":[-3.777796,51.776062],"type":"Point"}
}
