{
  "type": "Feature",
  "properties": {
    "iso:country":"GB",
    "wof:name":"SA9 2QB",
    "wof:placetype":"postalcode"
},
  "geometry": {"coordinates":[-3.77778151008653,51.77605558338946],"type":"Point"}
}