{
  "type": "Feature",
  "properties": {
    "iso:country":"GB",
    "wof:name":"TS3 0JZ",
    "wof:placetype":"postalcode"
},
  "geometry": {"coordinates":[-1.18531527017843,54.55440006865427],"type":"Point"}
}