{
  "type": "Feature",
  "properties": {
    "iso:country": "GB",
    "wof:name": "TS3 0JZ",
    "wof:placetype": "postalcode"
  },
  "geometry": {"coordinates":[-1.185315,54.5544],"type":"Point"}
}
