{
  "type": "Feature",
  "properties": {
    "date:inception_lower": "1980-01-01",
    "date:inception_upper": "1980-01-01",
    "iso:country": "GB",
    "wof:name": "KA18 1QU",
    "wof:placetype": "postalcode"
  },
  "geometry": {"coordinates":[-4.253472,55.453721],"type":"Point"}
}
