{
  "type": "Feature",
  "properties": {
    "date:inception_lower": "2019-12-01",
    "date:inception_upper": "2019-12-01",
    "iso:country": "GB",
    "wof:name": "NG1 1PJ",
    "wof:placetype": "postalcode"
  },
  "geometry": {"coordinates":[-1.144004,52.952074],"type":"Point"}
}
