{
  "type": "Feature",
  "properties": {
    "date:inception_lower":"1990-02-01",
    "date:inception_upper":"1990-02-28",
    "iso:country":"GB",
    "wof:name":"NG9 6LG",
    "wof:placetype":"postalcode"
},
  "geometry": {"coordinates":[-1.269479,52.91242],"type":"Point"}
}