{
  "type": "Feature",
  "properties": {
    "date:inception_lower": "2012-02-01",
    "date:inception_upper": "2012-02-01",
    "iso:country": "GB",
    "wof:name": "PE23 5GL",
    "wof:placetype": "postalcode"
  },
  "geometry": {"coordinates":[0.095515,53.175672],"type":"Point"}
}
