{
  "type": "Feature",
  "properties": {
    "iso:country":"GB",
    "wof:name":"PE23 5GL",
    "wof:placetype":"postalcode"
},
  "geometry": {"coordinates":[0.0955148661245,53.17567185131619],"type":"Point"}
}