{
  "type": "Feature",
  "properties": {
    "iso:country": "GB",
    "wof:name": "PE23 5GL",
    "wof:placetype": "postalcode"
  },
  "geometry": {"coordinates":[0.095515,53.175672],"type":"Point"}
}
