{
  "type": "Feature",
  "properties": {
    "iso:country":"GB",
    "wof:name":"WD24 6DF",
    "wof:placetype":"postalcode"
},
  "geometry": {"coordinates":[-0.39727025894122,51.67455290198028],"type":"Point"}
}