{
  "type": "Feature",
  "properties": {
    "iso:country": "GB",
    "wof:name": "WD24 6DF",
    "wof:placetype": "postalcode"
  },
  "geometry": {"coordinates":[-0.39727,51.674553],"type":"Point"}
}
