{
  "type": "Feature",
  "properties": {
    "date:inception_lower": "1986-09-01",
    "date:inception_upper": "1986-09-01",
    "iso:country": "GB",
    "wof:name": "G77 5JW",
    "wof:placetype": "postalcode"
  },
  "geometry": {"coordinates":[-4.317324,55.771339],"type":"Point"}
}
