{
  "type": "Feature",
  "properties": {
    "iso:country":"GB",
    "wof:name":"CM2 9XH",
    "wof:placetype":"postalcode"
},
  "geometry": {"coordinates":[0.45914400180601,51.7249227307334],"type":"Point"}
}