{
  "type": "Feature",
  "properties": {
    "iso:country":"GB",
    "wof:name":"DA13 0JP",
    "wof:placetype":"postalcode"
},
  "geometry": {"coordinates":[0.33502115737972,51.37010681649699],"type":"Point"}
}