{
  "type": "Feature",
  "properties": {
    "date:inception_lower": "1980-01-01",
    "date:inception_upper": "1980-01-01",
    "iso:country": "GB",
    "wof:name": "DA13 0JP",
    "wof:placetype": "postalcode"
  },
  "geometry": {"coordinates":[0.335021,51.370107],"type":"Point"}
}
