{
  "type": "Feature",
  "properties": {
    "iso:country":"GB",
    "wof:name":"S45 0JT",
    "wof:placetype":"postalcode"
},
  "geometry": {"coordinates":[-1.49115328186972,53.14443721040361],"type":"Point"}
}