{
  "type": "Feature",
  "properties": {
    "iso:country":"GB",
    "wof:name":"PO22 8PD",
    "wof:placetype":"postalcode"
},
  "geometry": {"coordinates":[-0.67200473743052,50.79266114468227],"type":"Point"}
}