{
  "type": "Feature",
  "properties": {
    "iso:country": "GB",
    "wof:name": "TN30 7AQ",
    "wof:placetype": "postalcode"
  },
  "geometry": {"coordinates":[0.687764,51.064253],"type":"Point"}
}
