{
  "type": "Feature",
  "properties": {
    "iso:country":"GB",
    "wof:name":"WA4 2AP",
    "wof:placetype":"postalcode"
},
  "geometry": {"coordinates":[-2.57574966196183,53.37134262281791],"type":"Point"}
}