{
  "type": "Feature",
  "properties": {
    "iso:country":"GB",
    "wof:name":"NN6 6JE",
    "wof:placetype":"postalcode"
},
  "geometry": {"coordinates":[-1.03942594455654,52.39979974861832],"type":"Point"}
}