{
  "type": "Feature",
  "properties": {
    "date:inception_lower": "1993-08-01",
    "date:inception_upper": "1993-08-01",
    "iso:country": "GB",
    "wof:name": "NN6 6JE",
    "wof:placetype": "postalcode"
  },
  "geometry": {"coordinates":[-1.039426,52.3998],"type":"Point"}
}
