{
  "type": "Feature",
  "properties": {
    "date:inception_lower": "2024-06-01",
    "date:inception_upper": "2024-06-01",
    "iso:country": "GB",
    "wof:name": "BS37 6GE",
    "wof:placetype": "postalcode"
  },
  "geometry": {"coordinates":[-2.362146,51.532377],"type":"Point"}
}
