{
  "type": "Feature",
  "properties": {
    "iso:country":"GB",
    "wof:name":"CH41 2SS",
    "wof:placetype":"postalcode"
},
  "geometry": {"coordinates":[-3.02587094691204,53.38698305730119],"type":"Point"}
}