{
  "type": "Feature",
  "properties": {
    "iso:country":"GB",
    "wof:name":"ME9 7RZ",
    "wof:placetype":"postalcode"
},
  "geometry": {"coordinates":[0.65160572652568,51.29709119044175],"type":"Point"}
}