{
  "type": "Feature",
  "properties": {
    "date:inception_lower":"1985-04-01",
    "date:inception_upper":"1985-04-30",
    "iso:country":"GB",
    "wof:name":"ME9 7RZ",
    "wof:placetype":"postalcode"
},
  "geometry": {"coordinates":[0.651637,51.297091],"type":"Point"}
}