{
  "type": "Feature",
  "properties": {
    "iso:country":"GB",
    "wof:name":"OX14 1JS",
    "wof:placetype":"postalcode"
},
  "geometry": {"coordinates":[-1.29157905484008,51.68124544680899],"type":"Point"}
}