{
  "type": "Feature",
  "properties": {
    "iso:country":"GB",
    "wof:name":"BH25 7BR",
    "wof:placetype":"postalcode"
},
  "geometry": {"coordinates":[-1.65810581301578,50.74079721702832],"type":"Point"}
}