{
  "type": "Feature",
  "properties": {
    "date:inception_lower": "1980-01-01",
    "date:inception_upper": "1980-01-01",
    "iso:country": "GB",
    "wof:name": "BH25 7BR",
    "wof:placetype": "postalcode"
  },
  "geometry": {"coordinates":[-1.658106,50.740797],"type":"Point"}
}
