{
  "type": "Feature",
  "properties": {
    "iso:country":"GB",
    "wof:name":"NW2 5UB",
    "wof:placetype":"postalcode"
},
  "geometry": {"coordinates":[-0.22886625114697,51.54982130997066],"type":"Point"}
}