{
  "type": "Feature",
  "properties": {
    "iso:country":"GB",
    "wof:name":"WR2 4JY",
    "wof:placetype":"postalcode"
},
  "geometry": {"coordinates":[-2.24241836440484,52.18508639160811],"type":"Point"}
}