{
  "type": "Feature",
  "properties": {
    "date:inception_lower": "1980-01-01",
    "date:inception_upper": "1980-01-01",
    "iso:country": "GB",
    "wof:name": "CO6 4AH",
    "wof:placetype": "postalcode"
  },
  "geometry": {"coordinates":[0.872702,51.951567],"type":"Point"}
}
