{
  "type": "Feature",
  "properties": {
    "iso:country":"GB",
    "wof:name":"CO6 4AH",
    "wof:placetype":"postalcode"
},
  "geometry": {"coordinates":[0.87272617591091,51.95151784427003],"type":"Point"}
}