{
  "type": "Feature",
  "properties": {
    "iso:country":"GB",
    "wof:name":"LL62 5DA",
    "wof:placetype":"postalcode"
},
  "geometry": {"coordinates":[-4.41978166949735,53.22070891933303],"type":"Point"}
}