{
  "type": "Feature",
  "properties": {
    "iso:country": "GB",
    "wof:name": "LL62 5DA",
    "wof:placetype": "postalcode"
  },
  "geometry": {"coordinates":[-4.419782,53.220709],"type":"Point"}
}
