{
  "type": "Feature",
  "properties": {
    "iso:country":"GB",
    "wof:name":"E13 0JX",
    "wof:placetype":"postalcode"
},
  "geometry": {"coordinates":[0.01570361528425,51.53355426773076],"type":"Point"}
}