{
  "type": "Feature",
  "properties": {
    "iso:country":"GB",
    "wof:name":"NP15 1LQ",
    "wof:placetype":"postalcode"
},
  "geometry": {"coordinates":[-2.88192293447958,51.66791994661212],"type":"Point"}
}