{
  "type": "Feature",
  "properties": {
    "date:inception_lower":"1999-06-01",
    "date:inception_upper":"1999-06-30",
    "iso:country":"GB",
    "wof:name":"NP15 1LQ",
    "wof:placetype":"postalcode"
},
  "geometry": {"coordinates":[-2.881923,51.66792],"type":"Point"}
}