{
  "type": "Feature",
  "properties": {
    "date:inception_lower": "1995-07-01",
    "date:inception_upper": "1995-07-01",
    "iso:country": "GB",
    "wof:name": "RG41 1HJ",
    "wof:placetype": "postalcode"
  },
  "geometry": {"coordinates":[-0.854959,51.424773],"type":"Point"}
}
