{
  "type": "Feature",
  "properties": {
    "iso:country":"GB",
    "wof:name":"RG41 1HJ",
    "wof:placetype":"postalcode"
},
  "geometry": {"coordinates":[-0.8549586791803,51.42477276053499],"type":"Point"}
}