{
  "type": "Feature",
  "properties": {
    "iso:country":"GB",
    "wof:name":"CT1 1HN",
    "wof:placetype":"postalcode"
},
  "geometry": {"coordinates":[1.09099073340067,51.28485258217454],"type":"Point"}
}