{
  "type": "Feature",
  "properties": {
    "iso:country":"GB",
    "wof:name":"DL3 6HG",
    "wof:placetype":"postalcode"
},
  "geometry": {"coordinates":[-1.56709382114831,54.53400805353142],"type":"Point"}
}