{
  "type": "Feature",
  "properties": {
    "iso:country": "GB",
    "wof:name": "DL3 6HG",
    "wof:placetype": "postalcode"
  },
  "geometry": {"coordinates":[-1.567118,54.534001],"type":"Point"}
}
