{
  "type": "Feature",
  "properties": {
    "iso:country":"GB",
    "wof:name":"CH3 5JL",
    "wof:placetype":"postalcode"
},
  "geometry": {"coordinates":[-2.86433548945056,53.19646362673877],"type":"Point"}
}