{
  "type": "Feature",
  "properties": {
    "iso:country":"GB",
    "wof:name":"OL12 9LA",
    "wof:placetype":"postalcode"
},
  "geometry": {"coordinates":[-2.12971408459269,53.6480749948544],"type":"Point"}
}