{
  "type": "Feature",
  "properties": {
    "date:inception_lower":"1995-12-01",
    "date:inception_upper":"1995-12-31",
    "iso:country":"GB",
    "wof:name":"OL12 9LA",
    "wof:placetype":"postalcode"
},
  "geometry": {"coordinates":[-2.129714,53.648075],"type":"Point"}
}