{
  "type": "Feature",
  "properties": {
    "date:inception_lower":"1980-01-01",
    "date:inception_upper":"1980-01-31",
    "iso:country":"GB",
    "wof:name":"WA14 4AU",
    "wof:placetype":"postalcode"
},
  "geometry": {"coordinates":[-2.359479,53.388406],"type":"Point"}
}