{
  "type": "Feature",
  "properties": {
    "iso:country": "GB",
    "wof:name": "CB1 9JH",
    "wof:placetype": "postalcode"
  },
  "geometry": {"coordinates":[0.178185,52.18824],"type":"Point"}
}
