{
  "type": "Feature",
  "properties": {
    "iso:country":"GB",
    "wof:name":"IV17 0QW",
    "wof:placetype":"postalcode"
},
  "geometry": {"coordinates":[-4.25641075780174,57.69545958755391],"type":"Point"}
}