{
  "type": "Feature",
  "properties": {
    "iso:country":"GB",
    "wof:name":"GU9 9LX",
    "wof:placetype":"postalcode"
},
  "geometry": {"coordinates":[-0.76103574788657,51.2303778347911],"type":"Point"}
}