{
  "type": "Feature",
  "properties": {
    "iso:country":"GB",
    "wof:name":"GL6 6BL",
    "wof:placetype":"postalcode"
},
  "geometry": {"coordinates":[-2.23280236539791,51.76580419423589],"type":"Point"}
}