{
  "type": "Feature",
  "properties": {
    "iso:country":"GB",
    "wof:name":"NP8 1LU",
    "wof:placetype":"postalcode"
},
  "geometry": {"coordinates":[-3.23260404304348,51.87212512949466],"type":"Point"}
}