{
  "type": "Feature",
  "properties": {
    "date:inception_lower": "1980-01-01",
    "date:inception_upper": "1980-01-01",
    "iso:country": "GB",
    "wof:name": "NP8 1LU",
    "wof:placetype": "postalcode"
  },
  "geometry": {"coordinates":[-3.232604,51.872125],"type":"Point"}
}
