{
  "type": "Feature",
  "properties": {
    "iso:country": "GB",
    "wof:name": "CV11 6QR",
    "wof:placetype": "postalcode"
  },
  "geometry": {"coordinates":[-1.402828,52.494477],"type":"Point"}
}
