{
  "type": "Feature",
  "properties": {
    "iso:country":"GB",
    "wof:name":"CV11 6QR",
    "wof:placetype":"postalcode"
},
  "geometry": {"coordinates":[-1.40282781401118,52.49447682117307],"type":"Point"}
}