{
  "type": "Feature",
  "properties": {
    "date:inception_lower": "2022-06-01",
    "date:inception_upper": "2022-06-01",
    "iso:country": "GB",
    "wof:name": "BB3 3GT",
    "wof:placetype": "postalcode"
  },
  "geometry": {"coordinates":[-2.447234,53.688249],"type":"Point"}
}
