{
  "type": "Feature",
  "properties": {
    "iso:country":"GB",
    "wof:name":"B97 4PN",
    "wof:placetype":"postalcode"
},
  "geometry": {"coordinates":[-1.94559441282159,52.30020187396948],"type":"Point"}
}