{
  "type": "Feature",
  "properties": {
    "iso:country":"GB",
    "wof:name":"SO45 2QL",
    "wof:placetype":"postalcode"
},
  "geometry": {"coordinates":[-1.39433484691665,50.83970660367257],"type":"Point"}
}