{
  "type": "Feature",
  "properties": {
    "date:inception_lower":"1994-12-01",
    "date:inception_upper":"1994-12-31",
    "iso:country":"GB",
    "wof:name":"SO45 2QL",
    "wof:placetype":"postalcode"
},
  "geometry": {"coordinates":[-1.394325,50.839698],"type":"Point"}
}