{
  "type": "Feature",
  "properties": {
    "iso:country":"GB",
    "wof:name":"IV12 5SP",
    "wof:placetype":"postalcode"
},
  "geometry": {"coordinates":[-3.85664982221628,57.58098292461643],"type":"Point"}
}