{
  "type": "Feature",
  "properties": {
    "iso:country":"GB",
    "wof:name":"CR0 2PG",
    "wof:placetype":"postalcode"
},
  "geometry": {"coordinates":[-0.10330297334678,51.38505632211388],"type":"Point"}
}