{
  "type": "Feature",
  "properties": {
    "iso:country":"GB",
    "wof:name":"NW2 7UD",
    "wof:placetype":"postalcode"
},
  "geometry": {"coordinates":[-0.23784918065858,51.56594494037382],"type":"Point"}
}