{
  "type": "Feature",
  "properties": {
    "iso:country":"GB",
    "wof:name":"BA15 1SY",
    "wof:placetype":"postalcode"
},
  "geometry": {"coordinates":[-2.24717281584644,51.35300703074277],"type":"Point"}
}