{
  "type": "Feature",
  "properties": {
    "date:inception_lower":"2002-06-01",
    "date:inception_upper":"2002-06-30",
    "iso:country":"GB",
    "wof:name":"CF31 5EL",
    "wof:placetype":"postalcode"
},
  "geometry": {"coordinates":[-3.6057,51.499338],"type":"Point"}
}