{
  "type": "Feature",
  "properties": {
    "date:inception_lower":"1985-04-01",
    "date:inception_upper":"1985-04-30",
    "iso:country":"GB",
    "wof:name":"BA20 2SY",
    "wof:placetype":"postalcode"
},
  "geometry": {"coordinates":[-2.663783,50.930203],"type":"Point"}
}