{
  "type": "Feature",
  "properties": {
    "iso:country": "GB",
    "wof:name": "RG41 1AH",
    "wof:placetype": "postalcode"
  },
  "geometry": {"coordinates":[-0.849274,51.423603],"type":"Point"}
}
