{
  "type": "Feature",
  "properties": {
    "date:inception_lower": "2017-11-01",
    "date:inception_upper": "2017-11-01",
    "iso:country": "GB",
    "wof:name": "RG41 1AH",
    "wof:placetype": "postalcode"
  },
  "geometry": {"coordinates":[-0.849274,51.423603],"type":"Point"}
}
