{
  "type": "Feature",
  "properties": {
    "date:inception_lower": "2018-03-01",
    "date:inception_upper": "2018-03-01",
    "iso:country": "GB",
    "wof:name": "WV8 1FL",
    "wof:placetype": "postalcode"
  },
  "geometry": {"coordinates":[-2.186115,52.624352],"type":"Point"}
}
