{
  "type": "Feature",
  "properties": {
    "iso:country": "GB",
    "wof:name": "GL55 6UY",
    "wof:placetype": "postalcode"
  },
  "geometry": {"coordinates":[-1.766484,52.037969],"type":"Point"}
}
