{
  "type": "Feature",
  "properties": {
    "iso:country":"GB",
    "wof:name":"GL55 6UY",
    "wof:placetype":"postalcode"
},
  "geometry": {"coordinates":[-1.76465251891737,52.03066216829988],"type":"Point"}
}