{
  "type": "Feature",
  "properties": {
    "date:inception_lower":"1980-01-01",
    "date:inception_upper":"1980-01-31",
    "iso:country":"GB",
    "wof:name":"GL55 6UY",
    "wof:placetype":"postalcode"
},
  "geometry": {"coordinates":[-1.766484,52.037969],"type":"Point"}
}