{
  "type": "Feature",
  "properties": {
    "iso:country": "GB",
    "wof:name": "TN25 6DY",
    "wof:placetype": "postalcode"
  },
  "geometry": {"coordinates":[1.014868,51.116879],"type":"Point"}
}
