{
  "type": "Feature",
  "properties": {
    "iso:country":"GB",
    "wof:name":"HX2 9XQ",
    "wof:placetype":"postalcode"
},
  "geometry": {"coordinates":[-1.87355739788998,53.76834878325126],"type":"Point"}
}