{
  "type": "Feature",
  "properties": {
    "iso:country":"GB",
    "wof:name":"ST3 7QZ",
    "wof:placetype":"postalcode"
},
  "geometry": {"coordinates":[-2.08940830241947,52.96520433029676],"type":"Point"}
}