{
  "type": "Feature",
  "properties": {
    "date:inception_lower": "1980-01-01",
    "date:inception_upper": "1980-01-01",
    "iso:country": "GB",
    "wof:name": "DY5 3QG",
    "wof:placetype": "postalcode"
  },
  "geometry": {"coordinates":[-2.127498,52.477525],"type":"Point"}
}
