{
  "type": "Feature",
  "properties": {
    "iso:country": "GB",
    "wof:name": "DY5 3QG",
    "wof:placetype": "postalcode"
  },
  "geometry": {"coordinates":[-2.127498,52.477525],"type":"Point"}
}
