{
  "type": "Feature",
  "properties": {
    "date:inception_lower":"1994-05-01",
    "date:inception_upper":"1994-05-31",
    "iso:country":"GB",
    "wof:name":"SE20 7WB",
    "wof:placetype":"postalcode"
},
  "geometry": {"coordinates":[-0.053384,51.411252],"type":"Point"}
}