{
  "type": "Feature",
  "properties": {
    "iso:country": "GB",
    "wof:name": "LN5 0LE",
    "wof:placetype": "postalcode"
  },
  "geometry": {"coordinates":[-0.52905,53.119693],"type":"Point"}
}
