{
  "type": "Feature",
  "properties": {
    "iso:country":"GB",
    "wof:name":"LN5 0LE",
    "wof:placetype":"postalcode"
},
  "geometry": {"coordinates":[-0.52904955353016,53.11969321071315],"type":"Point"}
}