{
  "type": "Feature",
  "properties": {
    "iso:country":"GB",
    "wof:name":"BR2 7QL",
    "wof:placetype":"postalcode"
},
  "geometry": {"coordinates":[0.00726720948024,51.38423932953012],"type":"Point"}
}