{
  "type": "Feature",
  "properties": {
    "iso:country": "GB",
    "wof:name": "NE3 5DY",
    "wof:placetype": "postalcode"
  },
  "geometry": {"coordinates":[-1.619903,55.013178],"type":"Point"}
}
