{
  "type": "Feature",
  "properties": {
    "date:inception_lower":"2002-05-01",
    "date:inception_upper":"2002-05-31",
    "iso:country":"GB",
    "wof:name":"CB6 3QJ",
    "wof:placetype":"postalcode"
},
  "geometry": {"coordinates":[0.175645,52.351463],"type":"Point"}
}