{
  "type": "Feature",
  "properties": {
    "iso:country": "GB",
    "wof:name": "CB6 3QJ",
    "wof:placetype": "postalcode"
  },
  "geometry": {"coordinates":[0.175645,52.351463],"type":"Point"}
}
