{
  "type": "Feature",
  "properties": {
    "iso:country":"GB",
    "wof:name":"CB6 3QJ",
    "wof:placetype":"postalcode"
},
  "geometry": {"coordinates":[0.17564457877213,52.35146302749302],"type":"Point"}
}