{
  "type": "Feature",
  "properties": {
    "iso:country": "GB",
    "wof:name": "NN7 3PY",
    "wof:placetype": "postalcode"
  },
  "geometry": {"coordinates":[-1.00341,52.211239],"type":"Point"}
}
