{
  "type": "Feature",
  "properties": {
    "iso:country":"GB",
    "wof:name":"MK40 3BB",
    "wof:placetype":"postalcode"
},
  "geometry": {"coordinates":[-0.44851327370823,52.1415372883416],"type":"Point"}
}