{
  "type": "Feature",
  "properties": {
    "iso:country": "GB",
    "wof:name": "SL6 3NW",
    "wof:placetype": "postalcode"
  },
  "geometry": {"coordinates":[-0.761292,51.502527],"type":"Point"}
}
