{
  "type": "Feature",
  "properties": {
    "iso:country": "GB",
    "wof:name": "BH21 1TX",
    "wof:placetype": "postalcode"
  },
  "geometry": {"coordinates":[-1.970078,50.779072],"type":"Point"}
}
