{
  "type": "Feature",
  "properties": {
    "iso:country":"GB",
    "wof:name":"BH21 1TX",
    "wof:placetype":"postalcode"
},
  "geometry": {"coordinates":[-1.9700776001602,50.77907179342795],"type":"Point"}
}