{
  "type": "Feature",
  "properties": {
    "date:inception_lower":"1980-01-01",
    "date:inception_upper":"1980-01-31",
    "iso:country":"GB",
    "wof:name":"BH21 1TX",
    "wof:placetype":"postalcode"
},
  "geometry": {"coordinates":[-1.970078,50.779072],"type":"Point"}
}