{
  "type": "Feature",
  "properties": {
    "date:inception_lower": "1996-06-01",
    "date:inception_upper": "1996-06-01",
    "iso:country": "GB",
    "wof:name": "CH7 1AE",
    "wof:placetype": "postalcode"
  },
  "geometry": {"coordinates":[-3.13717,53.176993],"type":"Point"}
}
