{
  "type": "Feature",
  "properties": {
    "iso:country":"GB",
    "wof:name":"NE26 1JH",
    "wof:placetype":"postalcode"
},
  "geometry": {"coordinates":[-1.45664145995854,55.05526142030285],"type":"Point"}
}