{
  "type": "Feature",
  "properties": {
    "iso:country": "GB",
    "wof:name": "SN6 7EG",
    "wof:placetype": "postalcode"
  },
  "geometry": {"coordinates":[-1.718358,51.63485],"type":"Point"}
}
