{
  "type": "Feature",
  "properties": {
    "iso:country":"GB",
    "wof:name":"SN6 7EG",
    "wof:placetype":"postalcode"
},
  "geometry": {"coordinates":[-1.71835848463036,51.63484985112621],"type":"Point"}
}