{
  "type": "Feature",
  "properties": {
    "date:inception_lower": "2020-01-01",
    "date:inception_upper": "2020-01-01",
    "iso:country": "GB",
    "wof:name": "SO31 8NJ",
    "wof:placetype": "postalcode"
  },
  "geometry": {"coordinates":[-1.322447,50.895623],"type":"Point"}
}
