{
  "type": "Feature",
  "properties": {
    "iso:country": "GB",
    "wof:name": "DA13 9LJ",
    "wof:placetype": "postalcode"
  },
  "geometry": {"coordinates":[0.310167,51.424065],"type":"Point"}
}
