{
  "type": "Feature",
  "properties": {
    "iso:country":"GB",
    "wof:name":"SP7 8HF",
    "wof:placetype":"postalcode"
},
  "geometry": {"coordinates":[-2.20038488048847,51.00298503758499],"type":"Point"}
}