{
  "type": "Feature",
  "properties": {
    "iso:country":"GB",
    "wof:name":"PO21 4UP",
    "wof:placetype":"postalcode"
},
  "geometry": {"coordinates":[-0.74313602370275,50.76971659346702],"type":"Point"}
}