{
  "type": "Feature",
  "properties": {
    "iso:country": "GB",
    "wof:name": "PO21 4UP",
    "wof:placetype": "postalcode"
  },
  "geometry": {"coordinates":[-0.743136,50.769717],"type":"Point"}
}
