{
  "type": "Feature",
  "properties": {
    "iso:country":"GB",
    "wof:name":"RM12 6RR",
    "wof:placetype":"postalcode"
},
  "geometry": {"coordinates":[0.21724845423222,51.54861377189756],"type":"Point"}
}