{
  "type": "Feature",
  "properties": {
    "iso:country": "GB",
    "wof:name": "B92 0JW",
    "wof:placetype": "postalcode"
  },
  "geometry": {"coordinates":[-1.705337,52.40114],"type":"Point"}
}
