{
  "type": "Feature",
  "properties": {
    "iso:country":"GB",
    "wof:name":"B92 0JW",
    "wof:placetype":"postalcode"
},
  "geometry": {"coordinates":[-1.7053374132794,52.40113982748517],"type":"Point"}
}