{
  "type": "Feature",
  "properties": {
    "iso:country": "GB",
    "wof:name": "RH6 9UU",
    "wof:placetype": "postalcode"
  },
  "geometry": {"coordinates":[-0.149238,51.160566],"type":"Point"}
}
