{
  "type": "Feature",
  "properties": {
    "date:inception_lower": "1997-06-01",
    "date:inception_upper": "1997-06-01",
    "iso:country": "GB",
    "wof:name": "WR15 8LD",
    "wof:placetype": "postalcode"
  },
  "geometry": {"coordinates":[-2.597617,52.316304],"type":"Point"}
}
