{
  "type": "Feature",
  "properties": {
    "iso:country": "GB",
    "wof:name": "WR15 8LD",
    "wof:placetype": "postalcode"
  },
  "geometry": {"coordinates":[-2.597617,52.316304],"type":"Point"}
}
