{
  "type": "Feature",
  "properties": {
    "iso:country":"GB",
    "wof:name":"WR15 8LD",
    "wof:placetype":"postalcode"
},
  "geometry": {"coordinates":[-2.59761697043715,52.31630419037516],"type":"Point"}
}