{
  "type": "Feature",
  "properties": {
    "iso:country": "GB",
    "wof:name": "PO17 5LF",
    "wof:placetype": "postalcode"
  },
  "geometry": {"coordinates":[-1.202616,50.883284],"type":"Point"}
}
