{
  "type": "Feature",
  "properties": {
    "iso:country":"GB",
    "wof:name":"WR10 3DB",
    "wof:placetype":"postalcode"
},
  "geometry": {"coordinates":[-2.11290644266502,52.08361720711376],"type":"Point"}
}