{
  "type": "Feature",
  "properties": {
    "iso:country": "GB",
    "wof:name": "WR10 3DB",
    "wof:placetype": "postalcode"
  },
  "geometry": {"coordinates":[-2.112753,52.083727],"type":"Point"}
}
