{
  "type": "Feature",
  "properties": {
    "date:inception_lower": "1980-01-01",
    "date:inception_upper": "1980-01-01",
    "iso:country": "GB",
    "wof:name": "SR6 8AD",
    "wof:placetype": "postalcode"
  },
  "geometry": {"coordinates":[-1.36721,54.939984],"type":"Point"}
}
