{
  "type": "Feature",
  "properties": {
    "iso:country":"GB",
    "wof:name":"SR6 8AD",
    "wof:placetype":"postalcode"
},
  "geometry": {"coordinates":[-1.36721012512003,54.93998418359592],"type":"Point"}
}