{
  "type": "Feature",
  "properties": {
    "iso:country":"GB",
    "wof:name":"TW4 7EY",
    "wof:placetype":"postalcode"
},
  "geometry": {"coordinates":[-0.38621196046379,51.46982984585019],"type":"Point"}
}