{
  "type": "Feature",
  "properties": {
    "iso:country": "GB",
    "wof:name": "WA16 8QN",
    "wof:placetype": "postalcode"
  },
  "geometry": {"coordinates":[-2.358463,53.292445],"type":"Point"}
}
