{
  "type": "Feature",
  "properties": {
    "date:inception_lower": "2010-08-01",
    "date:inception_upper": "2010-08-01",
    "iso:country": "GB",
    "wof:name": "EH35 5HJ",
    "wof:placetype": "postalcode"
  },
  "geometry": {"coordinates":[-2.949461,55.910453],"type":"Point"}
}
