{
  "type": "Feature",
  "properties": {
    "iso:country":"GB",
    "wof:name":"EH35 5HJ",
    "wof:placetype":"postalcode"
},
  "geometry": {"coordinates":[-2.94946153468542,55.91045304788855],"type":"Point"}
}