{
  "type": "Feature",
  "properties": {
    "date:inception_lower":"1983-03-01",
    "date:inception_upper":"1983-03-31",
    "iso:country":"GB",
    "wof:name":"BA15 1NJ",
    "wof:placetype":"postalcode"
},
  "geometry": {"coordinates":[-2.253838,51.348173],"type":"Point"}
}