{
  "type": "Feature",
  "properties": {
    "iso:country": "GB",
    "wof:name": "BA15 1NJ",
    "wof:placetype": "postalcode"
  },
  "geometry": {"coordinates":[-2.253838,51.348173],"type":"Point"}
}
