{
  "type": "Feature",
  "properties": {
    "iso:country": "GB",
    "wof:name": "NG12 5QF",
    "wof:placetype": "postalcode"
  },
  "geometry": {"coordinates":[-1.03954,52.84347],"type":"Point"}
}
