{
  "type": "Feature",
  "properties": {
    "date:inception_lower": "2007-04-01",
    "date:inception_upper": "2007-04-01",
    "iso:country": "GB",
    "wof:name": "MK3 6GX",
    "wof:placetype": "postalcode"
  },
  "geometry": {"coordinates":[-0.743205,51.999156],"type":"Point"}
}
