{
  "type": "Feature",
  "properties": {
    "iso:country":"GB",
    "wof:name":"MK3 6GX",
    "wof:placetype":"postalcode"
},
  "geometry": {"coordinates":[-0.74320484350915,51.99915576914901],"type":"Point"}
}