{
  "type": "Feature",
  "properties": {
    "date:inception_lower": "2019-04-01",
    "date:inception_upper": "2019-04-01",
    "iso:country": "GB",
    "wof:name": "DN3 1EQ",
    "wof:placetype": "postalcode"
  },
  "geometry": {"coordinates":[-1.08031,53.566255],"type":"Point"}
}
