{
  "type": "Feature",
  "properties": {
    "iso:country": "GB",
    "wof:name": "WS11 1NZ",
    "wof:placetype": "postalcode"
  },
  "geometry": {"coordinates":[-2.032906,52.691101],"type":"Point"}
}
