{
  "type": "Feature",
  "properties": {
    "iso:country":"GB",
    "wof:name":"PO13 0AH",
    "wof:placetype":"postalcode"
},
  "geometry": {"coordinates":[-1.16192763303292,50.82087760068844],"type":"Point"}
}