{
  "type": "Feature",
  "properties": {
    "iso:country":"GB",
    "wof:name":"HA3 5LP",
    "wof:placetype":"postalcode"
},
  "geometry": {"coordinates":[-0.34499704120912,51.59766480084861],"type":"Point"}
}