{
  "type": "Feature",
  "properties": {
    "date:inception_lower":"1996-06-01",
    "date:inception_upper":"1996-06-30",
    "iso:country":"GB",
    "wof:name":"B93 8TF",
    "wof:placetype":"postalcode"
},
  "geometry": {"coordinates":[-1.765747,52.373172],"type":"Point"}
}