{
  "type": "Feature",
  "properties": {
    "iso:country": "GB",
    "wof:name": "B93 8TF",
    "wof:placetype": "postalcode"
  },
  "geometry": {"coordinates":[-1.765747,52.373172],"type":"Point"}
}
