{
  "type": "Feature",
  "properties": {
    "iso:country":"GB",
    "wof:name":"NN11 9YX",
    "wof:placetype":"postalcode"
},
  "geometry": {"coordinates":[-1.17721059360446,52.26572173939834],"type":"Point"}
}