{
  "type": "Feature",
  "properties": {
    "iso:country": "GB",
    "wof:name": "NN11 9YX",
    "wof:placetype": "postalcode"
  },
  "geometry": {"coordinates":[-1.177211,52.265722],"type":"Point"}
}
