{
  "type": "Feature",
  "properties": {
    "iso:country": "GB",
    "wof:name": "TF10 8HF",
    "wof:placetype": "postalcode"
  },
  "geometry": {"coordinates":[-2.401406,52.773301],"type":"Point"}
}
