{
  "type": "Feature",
  "properties": {
    "date:inception_lower": "1980-01-01",
    "date:inception_upper": "1980-01-01",
    "iso:country": "GB",
    "wof:name": "TF10 8HF",
    "wof:placetype": "postalcode"
  },
  "geometry": {"coordinates":[-2.401406,52.773301],"type":"Point"}
}
