{
  "type": "Feature",
  "properties": {
    "iso:country":"GB",
    "wof:name":"N16 5NR",
    "wof:placetype":"postalcode"
},
  "geometry": {"coordinates":[-0.08270335071597,51.56683968245502],"type":"Point"}
}