{
  "type": "Feature",
  "properties": {
    "iso:country":"GB",
    "wof:name":"CA22 2JE",
    "wof:placetype":"postalcode"
},
  "geometry": {"coordinates":[-3.5422797086219,54.48219850742769],"type":"Point"}
}