{
  "type": "Feature",
  "properties": {
    "iso:country":"GB",
    "wof:name":"EX4 2EL",
    "wof:placetype":"postalcode"
},
  "geometry": {"coordinates":[-3.55898356495231,50.72706774953947],"type":"Point"}
}