{
  "type": "Feature",
  "properties": {
    "iso:country": "GB",
    "wof:name": "WN3 4LU",
    "wof:placetype": "postalcode"
  },
  "geometry": {"coordinates":[-2.619453,53.536595],"type":"Point"}
}
