{
  "type": "Feature",
  "properties": {
    "iso:country":"GB",
    "wof:name":"WN3 4LU",
    "wof:placetype":"postalcode"
},
  "geometry": {"coordinates":[-2.61945293625051,53.53659539128684],"type":"Point"}
}