{
  "type": "Feature",
  "properties": {
    "date:inception_lower": "1980-01-01",
    "date:inception_upper": "1980-01-01",
    "iso:country": "GB",
    "wof:name": "WN3 4LU",
    "wof:placetype": "postalcode"
  },
  "geometry": {"coordinates":[-2.619453,53.536595],"type":"Point"}
}
