{
  "type": "Feature",
  "properties": {
    "iso:country":"GB",
    "wof:name":"B36 8RX",
    "wof:placetype":"postalcode"
},
  "geometry": {"coordinates":[-1.80348664842457,52.50777621827328],"type":"Point"}
}