{
  "type": "Feature",
  "properties": {
    "iso:country": "GB",
    "wof:name": "B36 8RX",
    "wof:placetype": "postalcode"
  },
  "geometry": {"coordinates":[-1.803487,52.507776],"type":"Point"}
}
