{
  "type": "Feature",
  "properties": {
    "date:inception_lower": "2018-07-01",
    "date:inception_upper": "2018-07-01",
    "iso:country": "GB",
    "wof:name": "BA21 3FU",
    "wof:placetype": "postalcode"
  },
  "geometry": {"coordinates":[-2.666811,50.955717],"type":"Point"}
}
