{
  "type": "Feature",
  "properties": {
    "iso:country":"GB",
    "wof:name":"CV47 8JZ",
    "wof:placetype":"postalcode"
},
  "geometry": {"coordinates":[-1.3613511348622,52.27135610729584],"type":"Point"}
}