{
  "type": "Feature",
  "properties": {
    "iso:country": "GB",
    "wof:name": "CV47 8JZ",
    "wof:placetype": "postalcode"
  },
  "geometry": {"coordinates":[-1.361351,52.271356],"type":"Point"}
}
