{
  "type": "Feature",
  "properties": {
    "date:inception_lower": "1995-07-01",
    "date:inception_upper": "1995-07-01",
    "iso:country": "GB",
    "wof:name": "CF81 9AU",
    "wof:placetype": "postalcode"
  },
  "geometry": {"coordinates":[-3.227253,51.695669],"type":"Point"}
}
