{
  "type": "Feature",
  "properties": {
    "date:inception_lower": "2010-05-01",
    "date:inception_upper": "2010-05-01",
    "iso:country": "GB",
    "wof:name": "IP3 9GW",
    "wof:placetype": "postalcode"
  },
  "geometry": {"coordinates":[1.193463,52.026363],"type":"Point"}
}
