{
  "type": "Feature",
  "properties": {
    "iso:country":"GB",
    "wof:name":"IP3 9GW",
    "wof:placetype":"postalcode"
},
  "geometry": {"coordinates":[1.1934632465688,52.02636300790046],"type":"Point"}
}