{
  "type": "Feature",
  "properties": {
    "iso:country": "GB",
    "wof:name": "IP3 9GW",
    "wof:placetype": "postalcode"
  },
  "geometry": {"coordinates":[1.193463,52.026363],"type":"Point"}
}
