{
  "type": "Feature",
  "properties": {
    "iso:country":"GB",
    "wof:name":"TA22 9BQ",
    "wof:placetype":"postalcode"
},
  "geometry": {"coordinates":[-3.51902162474167,51.01188462051112],"type":"Point"}
}