{
  "type": "Feature",
  "properties": {
    "date:inception_lower": "1980-01-01",
    "date:inception_upper": "1980-01-01",
    "iso:country": "GB",
    "wof:name": "TA22 9BQ",
    "wof:placetype": "postalcode"
  },
  "geometry": {"coordinates":[-3.519009,51.01188],"type":"Point"}
}
