{
  "type": "Feature",
  "properties": {
    "iso:country":"GB",
    "wof:name":"SO23 0QJ",
    "wof:placetype":"postalcode"
},
  "geometry": {"coordinates":[-1.29563893456809,51.0577414731302],"type":"Point"}
}