{
  "type": "Feature",
  "properties": {
    "iso:country":"GB",
    "wof:name":"CM1 1ER",
    "wof:placetype":"postalcode"
},
  "geometry": {"coordinates":[0.47280669816749,51.73407859978047],"type":"Point"}
}