{
  "type": "Feature",
  "properties": {
    "date:inception_lower": "1980-01-01",
    "date:inception_upper": "1980-01-01",
    "iso:country": "GB",
    "wof:name": "DE7 4PJ",
    "wof:placetype": "postalcode"
  },
  "geometry": {"coordinates":[-1.34283,52.943233],"type":"Point"}
}
