{
  "type": "Feature",
  "properties": {
    "date:inception_lower":"1980-01-01",
    "date:inception_upper":"1980-01-31",
    "iso:country":"GB",
    "wof:name":"SA41 3SE",
    "wof:placetype":"postalcode"
},
  "geometry": {"coordinates":[-4.69996,51.97986],"type":"Point"}
}