{
  "type": "Feature",
  "properties": {
    "iso:country":"GB",
    "wof:name":"SA41 3SE",
    "wof:placetype":"postalcode"
},
  "geometry": {"coordinates":[-4.69995987601648,51.9798602068751],"type":"Point"}
}