{
  "type": "Feature",
  "properties": {
    "iso:country": "GB",
    "wof:name": "BS3 1HT",
    "wof:placetype": "postalcode"
  },
  "geometry": {"coordinates":[-2.601968,51.441519],"type":"Point"}
}
