{
  "type": "Feature",
  "properties": {
    "date:inception_lower": "1992-08-01",
    "date:inception_upper": "1992-08-01",
    "iso:country": "GB",
    "wof:name": "DE21 6TG",
    "wof:placetype": "postalcode"
  },
  "geometry": {"coordinates":[-1.426232,52.916705],"type":"Point"}
}
