{
  "type": "Feature",
  "properties": {
    "iso:country":"GB",
    "wof:name":"DE21 6TG",
    "wof:placetype":"postalcode"
},
  "geometry": {"coordinates":[-1.42623224854247,52.91670545105168],"type":"Point"}
}