{
  "type": "Feature",
  "properties": {
    "iso:country":"GB",
    "wof:name":"NE66 3DJ",
    "wof:placetype":"postalcode"
},
  "geometry": {"coordinates":[-1.66738725716416,55.49474167173749],"type":"Point"}
}