{
  "type": "Feature",
  "properties": {
    "iso:country": "GB",
    "wof:name": "NE66 3DJ",
    "wof:placetype": "postalcode"
  },
  "geometry": {"coordinates":[-1.667387,55.494742],"type":"Point"}
}
