{
  "type": "Feature",
  "properties": {
    "date:inception_lower":"1994-12-01",
    "date:inception_upper":"1994-12-31",
    "iso:country":"GB",
    "wof:name":"NE66 3DJ",
    "wof:placetype":"postalcode"
},
  "geometry": {"coordinates":[-1.667387,55.494742],"type":"Point"}
}