{
  "type": "Feature",
  "properties": {
    "iso:country": "GB",
    "wof:name": "DE11 9FE",
    "wof:placetype": "postalcode"
  },
  "geometry": {"coordinates":[-1.558587,52.761968],"type":"Point"}
}
