{
  "type": "Feature",
  "properties": {
    "iso:country":"GB",
    "wof:name":"DE11 9FE",
    "wof:placetype":"postalcode"
},
  "geometry": {"coordinates":[-1.55858690777492,52.76196831631439],"type":"Point"}
}