{
  "type": "Feature",
  "properties": {
    "date:inception_lower": "1995-07-01",
    "date:inception_upper": "1995-07-01",
    "iso:country": "GB",
    "wof:name": "DE11 9FE",
    "wof:placetype": "postalcode"
  },
  "geometry": {"coordinates":[-1.558587,52.761968],"type":"Point"}
}
