{
  "type": "Feature",
  "properties": {
    "date:inception_lower":"1995-01-01",
    "date:inception_upper":"1995-01-31",
    "iso:country":"GB",
    "wof:name":"WD7 9JR",
    "wof:placetype":"postalcode"
},
  "geometry": {"coordinates":[-0.293994,51.695246],"type":"Point"}
}