{
  "type": "Feature",
  "properties": {
    "iso:country":"GB",
    "wof:name":"NR13 4HN",
    "wof:placetype":"postalcode"
},
  "geometry": {"coordinates":[1.47882371210756,52.60041019439623],"type":"Point"}
}