{
  "type": "Feature",
  "properties": {
    "iso:country": "GB",
    "wof:name": "PO40 9FQ",
    "wof:placetype": "postalcode"
  },
  "geometry": {"coordinates":[-1.525822,50.682492],"type":"Point"}
}
