{
  "type": "Feature",
  "properties": {
    "iso:country":"GB",
    "wof:name":"PO40 9FQ",
    "wof:placetype":"postalcode"
},
  "geometry": {"coordinates":[-1.52583164564881,50.68245739127577],"type":"Point"}
}