{
  "type": "Feature",
  "properties": {
    "iso:country": "GB",
    "wof:name": "M22 9PJ",
    "wof:placetype": "postalcode"
  },
  "geometry": {"coordinates":[-2.266772,53.386474],"type":"Point"}
}
