{
  "type": "Feature",
  "properties": {
    "iso:country":"GB",
    "wof:name":"M22 9PJ",
    "wof:placetype":"postalcode"
},
  "geometry": {"coordinates":[-2.26677195844366,53.38647385366797],"type":"Point"}
}