{
  "type": "Feature",
  "properties": {
    "iso:country":"GB",
    "wof:name":"NG31 6SU",
    "wof:placetype":"postalcode"
},
  "geometry": {"coordinates":[-0.64034278884048,52.91631765159872],"type":"Point"}
}