{
  "type": "Feature",
  "properties": {
    "iso:country":"GB",
    "wof:name":"TD15 2PX",
    "wof:placetype":"postalcode"
},
  "geometry": {"coordinates":[-2.08656241057098,55.63005852924549],"type":"Point"}
}