{
  "type": "Feature",
  "properties": {
    "date:inception_lower": "1980-01-01",
    "date:inception_upper": "1980-01-01",
    "iso:country": "GB",
    "wof:name": "TD15 2PX",
    "wof:placetype": "postalcode"
  },
  "geometry": {"coordinates":[-2.089291,55.631474],"type":"Point"}
}
