{
  "type": "Feature",
  "properties": {
    "iso:country":"GB",
    "wof:name":"WV2 4BA",
    "wof:placetype":"postalcode"
},
  "geometry": {"coordinates":[-2.13093362612322,52.58112462395977],"type":"Point"}
}