{
  "type": "Feature",
  "properties": {
    "iso:country":"GB",
    "wof:name":"M46 9SL",
    "wof:placetype":"postalcode"
},
  "geometry": {"coordinates":[-2.48749008271151,53.53393463719613],"type":"Point"}
}