{
  "type": "Feature",
  "properties": {
    "date:inception_lower": "1980-01-01",
    "date:inception_upper": "1980-01-01",
    "iso:country": "GB",
    "wof:name": "B77 2DA",
    "wof:placetype": "postalcode"
  },
  "geometry": {"coordinates":[-1.664144,52.62567],"type":"Point"}
}
