{
  "type": "Feature",
  "properties": {
    "date:inception_lower":"1980-01-01",
    "date:inception_upper":"1980-01-31",
    "iso:country":"GB",
    "wof:name":"BR1 5NE",
    "wof:placetype":"postalcode"
},
  "geometry": {"coordinates":[0.012471,51.430445],"type":"Point"}
}