{
  "type": "Feature",
  "properties": {
    "iso:country":"GB",
    "wof:name":"G13 1AZ",
    "wof:placetype":"postalcode"
},
  "geometry": {"coordinates":[-4.32875711919295,55.89794724046732],"type":"Point"}
}