{
  "type": "Feature",
  "properties": {
    "iso:country":"GB",
    "wof:name":"B63 2DG",
    "wof:placetype":"postalcode"
},
  "geometry": {"coordinates":[-2.09078787830906,52.45796470005307],"type":"Point"}
}