{
  "type": "Feature",
  "properties": {
    "iso:country":"GB",
    "wof:name":"SG19 1ES",
    "wof:placetype":"postalcode"
},
  "geometry": {"coordinates":[-0.29798146730218,52.12802375486819],"type":"Point"}
}