{
  "type": "Feature",
  "properties": {
    "iso:country": "GB",
    "wof:name": "SG19 1ES",
    "wof:placetype": "postalcode"
  },
  "geometry": {"coordinates":[-0.297981,52.128024],"type":"Point"}
}
