{
  "type": "Feature",
  "properties": {
    "iso:country":"GB",
    "wof:name":"GU21 7JB",
    "wof:placetype":"postalcode"
},
  "geometry": {"coordinates":[-0.58680175551269,51.31447022734314],"type":"Point"}
}