{
  "type": "Feature",
  "properties": {
    "iso:country":"GB",
    "wof:name":"DG8 6DB",
    "wof:placetype":"postalcode"
},
  "geometry": {"coordinates":[-4.48363017481277,54.9597259082728],"type":"Point"}
}