{
  "type": "Feature",
  "properties": {
    "iso:country":"GB",
    "wof:name":"TN31 7BN",
    "wof:placetype":"postalcode"
},
  "geometry": {"coordinates":[0.72279998041643,50.95445068929144],"type":"Point"}
}