{
  "type": "Feature",
  "properties": {
    "iso:country": "GB",
    "wof:name": "RG4 7JR",
    "wof:placetype": "postalcode"
  },
  "geometry": {"coordinates":[-0.997873,51.479817],"type":"Point"}
}
