{
  "type": "Feature",
  "properties": {
    "iso:country":"GB",
    "wof:name":"SG1 4FH",
    "wof:placetype":"postalcode"
},
  "geometry": {"coordinates":[-0.21057459782432,51.92348993889222],"type":"Point"}
}