{
  "type": "Feature",
  "properties": {
    "date:inception_lower": "2008-09-01",
    "date:inception_upper": "2008-09-01",
    "iso:country": "GB",
    "wof:name": "SG1 4FH",
    "wof:placetype": "postalcode"
  },
  "geometry": {"coordinates":[-0.210575,51.92349],"type":"Point"}
}
