{
  "type": "Feature",
  "properties": {
    "date:inception_lower": "2021-08-01",
    "date:inception_upper": "2021-08-01",
    "iso:country": "GB",
    "wof:name": "HP22 3AG",
    "wof:placetype": "postalcode"
  },
  "geometry": {"coordinates":[-0.792906,51.788926],"type":"Point"}
}
