{
  "type": "Feature",
  "properties": {
    "date:inception_lower": "2020-11-01",
    "date:inception_upper": "2020-11-01",
    "iso:country": "GB",
    "wof:name": "SO14 1BX",
    "wof:placetype": "postalcode"
  },
  "geometry": {"coordinates":[-1.398294,50.902234],"type":"Point"}
}
