{
  "type": "Feature",
  "properties": {
    "iso:country":"GB",
    "wof:name":"CT16 3LU",
    "wof:placetype":"postalcode"
},
  "geometry": {"coordinates":[1.2893596612109,51.16133753405341],"type":"Point"}
}