{
  "type": "Feature",
  "properties": {
    "iso:country":"GB",
    "wof:name":"CB24 8TR",
    "wof:placetype":"postalcode"
},
  "geometry": {"coordinates":[0.12199159907802,52.28588196455161],"type":"Point"}
}