{
  "type": "Feature",
  "properties": {
    "iso:country": "GB",
    "wof:name": "CB24 8TR",
    "wof:placetype": "postalcode"
  },
  "geometry": {"coordinates":[0.121992,52.285882],"type":"Point"}
}
