{
  "type": "Feature",
  "properties": {
    "iso:country":"GB",
    "wof:name":"HU16 5AH",
    "wof:placetype":"postalcode"
},
  "geometry": {"coordinates":[-0.4255759942651,53.77832259159235],"type":"Point"}
}