{
  "type": "Feature",
  "properties": {
    "iso:country": "GB",
    "wof:name": "HU16 5AH",
    "wof:placetype": "postalcode"
  },
  "geometry": {"coordinates":[-0.425576,53.778323],"type":"Point"}
}
