{
  "type": "Feature",
  "properties": {
    "date:inception_lower": "1980-01-01",
    "date:inception_upper": "1980-01-01",
    "iso:country": "GB",
    "wof:name": "TW9 1LZ",
    "wof:placetype": "postalcode"
  },
  "geometry": {"coordinates":[-0.30683,51.460276],"type":"Point"}
}
