{
  "type": "Feature",
  "properties": {
    "iso:country":"GB",
    "wof:name":"TW9 1LZ",
    "wof:placetype":"postalcode"
},
  "geometry": {"coordinates":[-0.30682956752305,51.46027558478394],"type":"Point"}
}