{
  "type": "Feature",
  "properties": {
    "iso:country": "GB",
    "wof:name": "SA19 9UG",
    "wof:placetype": "postalcode"
  },
  "geometry": {"coordinates":[-3.787154,51.911126],"type":"Point"}
}
