{
  "type": "Feature",
  "properties": {
    "iso:country":"GB",
    "wof:name":"DT8 3NW",
    "wof:placetype":"postalcode"
},
  "geometry": {"coordinates":[-2.71809743725367,50.80258268139482],"type":"Point"}
}