{
  "type": "Feature",
  "properties": {
    "iso:country": "GB",
    "wof:name": "SA2 0TQ",
    "wof:placetype": "postalcode"
  },
  "geometry": {"coordinates":[-3.981592,51.622425],"type":"Point"}
}
