{
  "type": "Feature",
  "properties": {
    "iso:country": "GB",
    "wof:name": "SS13 1PP",
    "wof:placetype": "postalcode"
  },
  "geometry": {"coordinates":[0.505352,51.578931],"type":"Point"}
}
