{
  "type": "Feature",
  "properties": {
    "iso:country":"GB",
    "wof:name":"SS13 1PP",
    "wof:placetype":"postalcode"
},
  "geometry": {"coordinates":[0.50535201273847,51.57893081509793],"type":"Point"}
}