{
  "type": "Feature",
  "properties": {
    "iso:country": "GB",
    "wof:name": "LA1 1RN",
    "wof:placetype": "postalcode"
  },
  "geometry": {"coordinates":[-2.801717,54.046448],"type":"Point"}
}
