{
  "type": "Feature",
  "properties": {
    "iso:country":"GB",
    "wof:name":"DD1 1UQ",
    "wof:placetype":"postalcode"
},
  "geometry": {"coordinates":[-2.97136435126864,56.46020283285026],"type":"Point"}
}