{
  "type": "Feature",
  "properties": {
    "date:inception_lower": "2005-10-01",
    "date:inception_upper": "2005-10-01",
    "iso:country": "GB",
    "wof:name": "PA3 2ND",
    "wof:placetype": "postalcode"
  },
  "geometry": {"coordinates":[-4.429573,55.855068],"type":"Point"}
}
