{
  "type": "Feature",
  "properties": {
    "iso:country":"GB",
    "wof:name":"PA3 2ND",
    "wof:placetype":"postalcode"
},
  "geometry": {"coordinates":[-4.42957321974202,55.85506755509666],"type":"Point"}
}