{
  "type": "Feature",
  "properties": {
    "iso:country":"GB",
    "wof:name":"GL4 6QS",
    "wof:placetype":"postalcode"
},
  "geometry": {"coordinates":[-2.2255273247874,51.84983934052934],"type":"Point"}
}