{
  "type": "Feature",
  "properties": {
    "date:inception_lower": "1995-12-01",
    "date:inception_upper": "1995-12-01",
    "iso:country": "GB",
    "wof:name": "GL4 6QS",
    "wof:placetype": "postalcode"
  },
  "geometry": {"coordinates":[-2.225754,51.849459],"type":"Point"}
}
