{
  "type": "Feature",
  "properties": {
    "date:inception_lower": "1980-01-01",
    "date:inception_upper": "1980-01-01",
    "iso:country": "GB",
    "wof:name": "DG10 9PF",
    "wof:placetype": "postalcode"
  },
  "geometry": {"coordinates":[-3.449519,55.30424],"type":"Point"}
}
