{
  "type": "Feature",
  "properties": {
    "iso:country": "GB",
    "wof:name": "WS8 6AH",
    "wof:placetype": "postalcode"
  },
  "geometry": {"coordinates":[-1.926289,52.649083],"type":"Point"}
}
