{
  "type": "Feature",
  "properties": {
    "iso:country":"GB",
    "wof:name":"WS8 6AH",
    "wof:placetype":"postalcode"
},
  "geometry": {"coordinates":[-1.92628942032168,52.64908311546289],"type":"Point"}
}