{
  "type": "Feature",
  "properties": {
    "date:inception_lower": "1980-01-01",
    "date:inception_upper": "1980-01-01",
    "iso:country": "GB",
    "wof:name": "TR11 5EA",
    "wof:placetype": "postalcode"
  },
  "geometry": {"coordinates":[-5.104164,50.140277],"type":"Point"}
}
