{
  "type": "Feature",
  "properties": {
    "date:inception_lower":"1990-02-01",
    "date:inception_upper":"1990-02-28",
    "iso:country":"GB",
    "wof:name":"CO2 7JZ",
    "wof:placetype":"postalcode"
},
  "geometry": {"coordinates":[0.881813,51.873268],"type":"Point"}
}