{
  "type": "Feature",
  "properties": {
    "iso:country":"GB",
    "wof:name":"HA4 6DX",
    "wof:placetype":"postalcode"
},
  "geometry": {"coordinates":[-0.41512600976066,51.56400396463547],"type":"Point"}
}