{
  "type": "Feature",
  "properties": {
    "date:inception_lower": "1980-01-01",
    "date:inception_upper": "1980-01-01",
    "iso:country": "GB",
    "wof:name": "HA4 6DX",
    "wof:placetype": "postalcode"
  },
  "geometry": {"coordinates":[-0.415126,51.564004],"type":"Point"}
}
