{
  "type": "Feature",
  "properties": {
    "iso:country": "GB",
    "wof:name": "AL7 4RY",
    "wof:placetype": "postalcode"
  },
  "geometry": {"coordinates":[-0.180017,51.784275],"type":"Point"}
}
