{
  "type": "Feature",
  "properties": {
    "iso:country":"GB",
    "wof:name":"SO16 5FR",
    "wof:placetype":"postalcode"
},
  "geometry": {"coordinates":[-1.44189461305414,50.93517419154307],"type":"Point"}
}