{
  "type": "Feature",
  "properties": {
    "date:inception_lower":"1990-07-01",
    "date:inception_upper":"1990-07-31",
    "iso:country":"GB",
    "wof:name":"BN24 5AF",
    "wof:placetype":"postalcode"
},
  "geometry": {"coordinates":[0.310723,50.820089],"type":"Point"}
}