{
  "type": "Feature",
  "properties": {
    "iso:country": "GB",
    "wof:name": "SY3 7PN",
    "wof:placetype": "postalcode"
  },
  "geometry": {"coordinates":[-2.741621,52.700633],"type":"Point"}
}
