{
  "type": "Feature",
  "properties": {
    "date:inception_lower":"1980-01-01",
    "date:inception_upper":"1980-01-31",
    "iso:country":"GB",
    "wof:name":"TR16 5BU",
    "wof:placetype":"postalcode"
},
  "geometry": {"coordinates":[-5.199611,50.256164],"type":"Point"}
}