{
  "type": "Feature",
  "properties": {
    "iso:country":"GB",
    "wof:name":"TR16 5BU",
    "wof:placetype":"postalcode"
},
  "geometry": {"coordinates":[-5.1996109343839,50.25616358667117],"type":"Point"}
}