{
  "type": "Feature",
  "properties": {
    "iso:country":"GB",
    "wof:name":"SO53 3AS",
    "wof:placetype":"postalcode"
},
  "geometry": {"coordinates":[-1.38552253523312,50.9742600903539],"type":"Point"}
}