{
  "type": "Feature",
  "properties": {
    "iso:country": "GB",
    "wof:name": "SK2 7DU",
    "wof:placetype": "postalcode"
  },
  "geometry": {"coordinates":[-2.148092,53.384092],"type":"Point"}
}
