{
  "type": "Feature",
  "properties": {
    "iso:country":"GB",
    "wof:name":"SK2 7DU",
    "wof:placetype":"postalcode"
},
  "geometry": {"coordinates":[-2.14809231796041,53.38409158739795],"type":"Point"}
}