{
  "type": "Feature",
  "properties": {
    "date:inception_lower":"1980-01-01",
    "date:inception_upper":"1980-01-31",
    "iso:country":"GB",
    "wof:name":"SS14 2AR",
    "wof:placetype":"postalcode"
},
  "geometry": {"coordinates":[0.458184,51.573894],"type":"Point"}
}