{
  "type": "Feature",
  "properties": {
    "iso:country":"GB",
    "wof:name":"SS14 2AR",
    "wof:placetype":"postalcode"
},
  "geometry": {"coordinates":[0.45818354589805,51.57389419134865],"type":"Point"}
}