{
  "type": "Feature",
  "properties": {
    "iso:country":"GB",
    "wof:name":"TW12 2BG",
    "wof:placetype":"postalcode"
},
  "geometry": {"coordinates":[-0.36705669431085,51.41351524581331],"type":"Point"}
}