{
  "type": "Feature",
  "properties": {
    "iso:country": "GB",
    "wof:name": "HU7 4QR",
    "wof:placetype": "postalcode"
  },
  "geometry": {"coordinates":[-0.30283,53.779408],"type":"Point"}
}
