{
  "type": "Feature",
  "properties": {
    "iso:country": "GB",
    "wof:name": "HP13 5UW",
    "wof:placetype": "postalcode"
  },
  "geometry": {"coordinates":[-0.777305,51.645395],"type":"Point"}
}
