{
  "type": "Feature",
  "properties": {
    "date:inception_lower": "2003-10-01",
    "date:inception_upper": "2003-10-01",
    "iso:country": "GB",
    "wof:name": "WF5 9JJ",
    "wof:placetype": "postalcode"
  },
  "geometry": {"coordinates":[-1.584212,53.683953],"type":"Point"}
}
