{
  "type": "Feature",
  "properties": {
    "iso:country":"GB",
    "wof:name":"NP7 7RW",
    "wof:placetype":"postalcode"
},
  "geometry": {"coordinates":[-3.02605307071936,51.83193921636065],"type":"Point"}
}