{
  "type": "Feature",
  "properties": {
    "iso:country":"GB",
    "wof:name":"PL5 3PT",
    "wof:placetype":"postalcode"
},
  "geometry": {"coordinates":[-4.16133537699254,50.40776712342064],"type":"Point"}
}