{
  "type": "Feature",
  "properties": {
    "date:inception_lower": "1980-01-01",
    "date:inception_upper": "1980-01-01",
    "iso:country": "GB",
    "wof:name": "PL5 3PT",
    "wof:placetype": "postalcode"
  },
  "geometry": {"coordinates":[-4.161335,50.407767],"type":"Point"}
}
