{
  "type": "Feature",
  "properties": {
    "iso:country":"GB",
    "wof:name":"CM2 7LJ",
    "wof:placetype":"postalcode"
},
  "geometry": {"coordinates":[0.48997444790205,51.72362570959029],"type":"Point"}
}