{
  "type": "Feature",
  "properties": {
    "date:inception_lower": "2024-06-01",
    "date:inception_upper": "2024-06-01",
    "iso:country": "GB",
    "wof:name": "S75 1FZ",
    "wof:placetype": "postalcode"
  },
  "geometry": {"coordinates":[-1.504204,53.565641],"type":"Point"}
}
