{
  "type": "Feature",
  "properties": {
    "iso:country":"GB",
    "wof:name":"EX20 2EB",
    "wof:placetype":"postalcode"
},
  "geometry": {"coordinates":[-3.90353411776898,50.79974433487931],"type":"Point"}
}