{
  "type": "Feature",
  "properties": {
    "iso:country":"GB",
    "wof:name":"WA7 5SX",
    "wof:placetype":"postalcode"
},
  "geometry": {"coordinates":[-2.72472560478154,53.33853955123649],"type":"Point"}
}