{
  "type": "Feature",
  "properties": {
    "date:inception_lower": "1980-01-01",
    "date:inception_upper": "1980-01-01",
    "iso:country": "GB",
    "wof:name": "WA7 5SX",
    "wof:placetype": "postalcode"
  },
  "geometry": {"coordinates":[-2.724726,53.33854],"type":"Point"}
}
