{
  "type": "Feature",
  "properties": {
    "iso:country": "GB",
    "wof:name": "TW18 3EG",
    "wof:placetype": "postalcode"
  },
  "geometry": {"coordinates":[-0.521471,51.431319],"type":"Point"}
}
