{
  "type": "Feature",
  "properties": {
    "iso:country":"GB",
    "wof:name":"TW18 3EG",
    "wof:placetype":"postalcode"
},
  "geometry": {"coordinates":[-0.52147132807837,51.43131921337416],"type":"Point"}
}