{
  "type": "Feature",
  "properties": {
    "date:inception_lower": "1991-11-01",
    "date:inception_upper": "1991-11-01",
    "iso:country": "GB",
    "wof:name": "ML9 1NT",
    "wof:placetype": "postalcode"
  },
  "geometry": {"coordinates":[-3.98657,55.736465],"type":"Point"}
}
