{
  "type": "Feature",
  "properties": {
    "date:inception_lower":"1980-01-01",
    "date:inception_upper":"1980-01-31",
    "iso:country":"GB",
    "wof:name":"TR7 1AY",
    "wof:placetype":"postalcode"
},
  "geometry": {"coordinates":[-5.085174,50.413186],"type":"Point"}
}