{
  "type": "Feature",
  "properties": {
    "iso:country":"GB",
    "wof:name":"HP4 3LG",
    "wof:placetype":"postalcode"
},
  "geometry": {"coordinates":[-0.5804166125233,51.76081120196893],"type":"Point"}
}