{
  "type": "Feature",
  "properties": {
    "iso:country":"GB",
    "wof:name":"UB3 1EF",
    "wof:placetype":"postalcode"
},
  "geometry": {"coordinates":[-0.43652743763518,51.51377310266921],"type":"Point"}
}