{
  "type": "Feature",
  "properties": {
    "iso:country": "GB",
    "wof:name": "UB3 1EF",
    "wof:placetype": "postalcode"
  },
  "geometry": {"coordinates":[-0.436527,51.513773],"type":"Point"}
}
