{
  "type": "Feature",
  "properties": {
    "iso:country":"GB",
    "wof:name":"SW8 4HP",
    "wof:placetype":"postalcode"
},
  "geometry": {"coordinates":[-0.13473369591302,51.47372464329817],"type":"Point"}
}