{
  "type": "Feature",
  "properties": {
    "date:inception_lower": "1985-10-01",
    "date:inception_upper": "1985-10-01",
    "iso:country": "GB",
    "wof:name": "SW8 4HP",
    "wof:placetype": "postalcode"
  },
  "geometry": {"coordinates":[-0.134734,51.473725],"type":"Point"}
}
