{
  "type": "Feature",
  "properties": {
    "iso:country":"GB",
    "wof:name":"ME19 5BA",
    "wof:placetype":"postalcode"
},
  "geometry": {"coordinates":[0.37564836161636,51.30641691706043],"type":"Point"}
}