{
  "type": "Feature",
  "properties": {
    "date:inception_lower": "1980-01-01",
    "date:inception_upper": "1980-01-01",
    "iso:country": "GB",
    "wof:name": "ME19 5BA",
    "wof:placetype": "postalcode"
  },
  "geometry": {"coordinates":[0.375648,51.306417],"type":"Point"}
}
