{
  "type": "Feature",
  "properties": {
    "iso:country":"GB",
    "wof:name":"W12 9BP",
    "wof:placetype":"postalcode"
},
  "geometry": {"coordinates":[-0.242339695051,51.5018517693506],"type":"Point"}
}