{
  "type": "Feature",
  "properties": {
    "iso:country":"GB",
    "wof:name":"IV6 7UR",
    "wof:placetype":"postalcode"
},
  "geometry": {"coordinates":[-4.57982809264456,57.54768170488801],"type":"Point"}
}