{
  "type": "Feature",
  "properties": {
    "iso:country": "GB",
    "wof:name": "PL6 8PN",
    "wof:placetype": "postalcode"
  },
  "geometry": {"coordinates":[-4.093138,50.400236],"type":"Point"}
}
