{
  "type": "Feature",
  "properties": {
    "iso:country": "GB",
    "wof:name": "DN36 4JR",
    "wof:placetype": "postalcode"
  },
  "geometry": {"coordinates":[-0.028161,53.52528],"type":"Point"}
}
