{
  "type": "Feature",
  "properties": {
    "iso:country":"GB",
    "wof:name":"WD7 7JF",
    "wof:placetype":"postalcode"
},
  "geometry": {"coordinates":[-0.3163224088327,51.68077597128419],"type":"Point"}
}