{
  "type": "Feature",
  "properties": {
    "iso:country":"GB",
    "wof:name":"NG22 9LB",
    "wof:placetype":"postalcode"
},
  "geometry": {"coordinates":[-0.97212309570069,53.20271118694545],"type":"Point"}
}