{
  "type": "Feature",
  "properties": {
    "iso:country":"GB",
    "wof:name":"RG24 9ER",
    "wof:placetype":"postalcode"
},
  "geometry": {"coordinates":[-1.09186165228989,51.28016155940669],"type":"Point"}
}