{
  "type": "Feature",
  "properties": {
    "date:inception_lower": "1980-01-01",
    "date:inception_upper": "1980-01-01",
    "iso:country": "GB",
    "wof:name": "TD9 8TQ",
    "wof:placetype": "postalcode"
  },
  "geometry": {"coordinates":[-2.59068,55.388113],"type":"Point"}
}
