{
  "type": "Feature",
  "properties": {
    "iso:country":"GB",
    "wof:name":"TD9 8TQ",
    "wof:placetype":"postalcode"
},
  "geometry": {"coordinates":[-2.59068022220102,55.38811339077304],"type":"Point"}
}