{
  "type": "Feature",
  "properties": {
    "iso:country":"GB",
    "wof:name":"WA15 8JB",
    "wof:placetype":"postalcode"
},
  "geometry": {"coordinates":[-2.34353986739963,53.39380994173717],"type":"Point"}
}