{
  "type": "Feature",
  "properties": {
    "iso:country": "GB",
    "wof:name": "WA15 8JB",
    "wof:placetype": "postalcode"
  },
  "geometry": {"coordinates":[-2.34354,53.39381],"type":"Point"}
}
