{
  "type": "Feature",
  "properties": {
    "iso:country": "GB",
    "wof:name": "CB4 2PD",
    "wof:placetype": "postalcode"
  },
  "geometry": {"coordinates":[0.139969,52.232047],"type":"Point"}
}
