{
  "type": "Feature",
  "properties": {
    "iso:country":"GB",
    "wof:name":"CB4 2PD",
    "wof:placetype":"postalcode"
},
  "geometry": {"coordinates":[0.1399690688102,52.23204689557224],"type":"Point"}
}