{
  "type": "Feature",
  "properties": {
    "iso:country":"GB",
    "wof:name":"BH22 8LW",
    "wof:placetype":"postalcode"
},
  "geometry": {"coordinates":[-1.87885920403195,50.79169246601763],"type":"Point"}
}