{
  "type": "Feature",
  "properties": {
    "iso:country": "GB",
    "wof:name": "LS14 6FJ",
    "wof:placetype": "postalcode"
  },
  "geometry": {"coordinates":[-1.465752,53.815625],"type":"Point"}
}
