{
  "type": "Feature",
  "properties": {
    "iso:country":"GB",
    "wof:name":"WF6 2RN",
    "wof:placetype":"postalcode"
},
  "geometry": {"coordinates":[-1.42415667690718,53.71176523729451],"type":"Point"}
}