{
  "type": "Feature",
  "properties": {
    "iso:country":"GB",
    "wof:name":"TW13 4PS",
    "wof:placetype":"postalcode"
},
  "geometry": {"coordinates":[-0.42293554502082,51.43197735509133],"type":"Point"}
}