{
  "type": "Feature",
  "properties": {
    "date:inception_lower":"1990-07-01",
    "date:inception_upper":"1990-07-31",
    "iso:country":"GB",
    "wof:name":"BB12 0LD",
    "wof:placetype":"postalcode"
},
  "geometry": {"coordinates":[-2.264188,53.800579],"type":"Point"}
}