{
  "type": "Feature",
  "properties": {
    "iso:country":"GB",
    "wof:name":"G31 4UR",
    "wof:placetype":"postalcode"
},
  "geometry": {"coordinates":[-4.19071092799426,55.84883183089002],"type":"Point"}
}