{
  "type": "Feature",
  "properties": {
    "iso:country": "GB",
    "wof:name": "GL52 8YQ",
    "wof:placetype": "postalcode"
  },
  "geometry": {"coordinates":[-2.070581,51.942227],"type":"Point"}
}
