{
  "type": "Feature",
  "properties": {
    "date:inception_lower": "1996-12-01",
    "date:inception_upper": "1996-12-01",
    "iso:country": "GB",
    "wof:name": "M1 7DP",
    "wof:placetype": "postalcode"
  },
  "geometry": {"coordinates":[-2.232,53.47607],"type":"Point"}
}
