{
  "type": "Feature",
  "properties": {
    "iso:country":"GB",
    "wof:name":"B31 3SA",
    "wof:placetype":"postalcode"
},
  "geometry": {"coordinates":[-1.9634465695258,52.40093442003257],"type":"Point"}
}