{
  "type": "Feature",
  "properties": {
    "iso:country":"GB",
    "wof:name":"W1U 1PU",
    "wof:placetype":"postalcode"
},
  "geometry": {"coordinates":[-0.14988265190016,51.51604965815567],"type":"Point"}
}