{
  "type": "Feature",
  "properties": {
    "iso:country": "GB",
    "wof:name": "TN17 1JA",
    "wof:placetype": "postalcode"
  },
  "geometry": {"coordinates":[0.461884,51.116423],"type":"Point"}
}
