{
  "type": "Feature",
  "properties": {
    "iso:country": "GB",
    "wof:name": "S42 5SX",
    "wof:placetype": "postalcode"
  },
  "geometry": {"coordinates":[-1.359391,53.185879],"type":"Point"}
}
