{
  "type": "Feature",
  "properties": {
    "date:inception_lower": "1980-01-01",
    "date:inception_upper": "1980-01-01",
    "iso:country": "GB",
    "wof:name": "S42 5SX",
    "wof:placetype": "postalcode"
  },
  "geometry": {"coordinates":[-1.359391,53.185879],"type":"Point"}
}
