{
  "type": "Feature",
  "properties": {
    "iso:country":"GB",
    "wof:name":"S42 5SX",
    "wof:placetype":"postalcode"
},
  "geometry": {"coordinates":[-1.35939060127923,53.18587946213326],"type":"Point"}
}