{
  "type": "Feature",
  "properties": {
    "iso:country": "GB",
    "wof:name": "BR8 8FB",
    "wof:placetype": "postalcode"
  },
  "geometry": {"coordinates":[0.177158,51.393094],"type":"Point"}
}
