{
  "type": "Feature",
  "properties": {
    "date:inception_lower": "2020-01-01",
    "date:inception_upper": "2020-01-01",
    "iso:country": "GB",
    "wof:name": "DT4 4HL",
    "wof:placetype": "postalcode"
  },
  "geometry": {"coordinates":[-2.456096,50.609198],"type":"Point"}
}
