{
  "type": "Feature",
  "properties": {
    "iso:country":"GB",
    "wof:name":"SO41 8BS",
    "wof:placetype":"postalcode"
},
  "geometry": {"coordinates":[-1.56883532878424,50.75325314917575],"type":"Point"}
}