{
  "type": "Feature",
  "properties": {
    "iso:country": "GB",
    "wof:name": "SO41 8BS",
    "wof:placetype": "postalcode"
  },
  "geometry": {"coordinates":[-1.568835,50.753253],"type":"Point"}
}
