{
  "type": "Feature",
  "properties": {
    "iso:country":"GB",
    "wof:name":"W1W 7AR",
    "wof:placetype":"postalcode"
},
  "geometry": {"coordinates":[-0.14172654626007,51.51884328505965],"type":"Point"}
}