{
  "type": "Feature",
  "properties": {
    "date:inception_lower": "1980-01-01",
    "date:inception_upper": "1980-01-01",
    "iso:country": "GB",
    "wof:name": "GL53 9JL",
    "wof:placetype": "postalcode"
  },
  "geometry": {"coordinates":[-2.059061,51.877382],"type":"Point"}
}
