{
  "type": "Feature",
  "properties": {
    "date:inception_lower": "1980-01-01",
    "date:inception_upper": "1980-01-01",
    "iso:country": "GB",
    "wof:name": "BB9 8NL",
    "wof:placetype": "postalcode"
  },
  "geometry": {"coordinates":[-2.21779,53.84719],"type":"Point"}
}
