{
  "type": "Feature",
  "properties": {
    "iso:country":"GB",
    "wof:name":"BB9 8NL",
    "wof:placetype":"postalcode"
},
  "geometry": {"coordinates":[-2.21780371773412,53.84718508582706],"type":"Point"}
}