{
  "type": "Feature",
  "properties": {
    "iso:country":"GB",
    "wof:name":"W1U 1NF",
    "wof:placetype":"postalcode"
},
  "geometry": {"coordinates":[-0.15028502232691,51.5157232821195],"type":"Point"}
}