{
  "type": "Feature",
  "properties": {
    "iso:country": "GB",
    "wof:name": "EX8 3NX",
    "wof:placetype": "postalcode"
  },
  "geometry": {"coordinates":[-3.41294,50.642055],"type":"Point"}
}
