{
  "type": "Feature",
  "properties": {
    "iso:country":"GB",
    "wof:name":"EX8 3NX",
    "wof:placetype":"postalcode"
},
  "geometry": {"coordinates":[-3.41294022018173,50.64205467286305],"type":"Point"}
}