{
  "type": "Feature",
  "properties": {
    "iso:country":"GB",
    "wof:name":"W1B 2LQ",
    "wof:placetype":"postalcode"
},
  "geometry": {"coordinates":[-0.14302226053664,51.51462833877925],"type":"Point"}
}