{
  "type": "Feature",
  "properties": {
    "iso:country":"GB",
    "wof:name":"CA6 4DQ",
    "wof:placetype":"postalcode"
},
  "geometry": {"coordinates":[-2.96397833403592,54.9420025744673],"type":"Point"}
}