{
  "type": "Feature",
  "properties": {
    "date:inception_lower": "1980-01-01",
    "date:inception_upper": "1980-01-01",
    "iso:country": "GB",
    "wof:name": "DE14 2HR",
    "wof:placetype": "postalcode"
  },
  "geometry": {"coordinates":[-1.647927,52.81215],"type":"Point"}
}
