{
  "type": "Feature",
  "properties": {
    "iso:country":"GB",
    "wof:name":"TN13 1YF",
    "wof:placetype":"postalcode"
},
  "geometry": {"coordinates":[0.18955962606365,51.27243559709839],"type":"Point"}
}