{
  "type": "Feature",
  "properties": {
    "iso:country":"GB",
    "wof:name":"AB24 3LY",
    "wof:placetype":"postalcode"
},
  "geometry": {"coordinates":[-2.10759699183822,57.16246977213302],"type":"Point"}
}