{
  "type": "Feature",
  "properties": {
    "iso:country": "GB",
    "wof:name": "ME5 7TD",
    "wof:placetype": "postalcode"
  },
  "geometry": {"coordinates":[0.53462,51.35494],"type":"Point"}
}
