{
  "type": "Feature",
  "properties": {
    "iso:country":"GB",
    "wof:name":"ME5 7TD",
    "wof:placetype":"postalcode"
},
  "geometry": {"coordinates":[0.53461996303489,51.35494005881467],"type":"Point"}
}