{
  "type": "Feature",
  "properties": {
    "iso:country":"GB",
    "wof:name":"NG19 0QW",
    "wof:placetype":"postalcode"
},
  "geometry": {"coordinates":[-1.16705148788623,53.15614980582232],"type":"Point"}
}