{
  "type": "Feature",
  "properties": {
    "date:inception_lower": "1990-07-01",
    "date:inception_upper": "1990-07-01",
    "iso:country": "GB",
    "wof:name": "NG19 0QW",
    "wof:placetype": "postalcode"
  },
  "geometry": {"coordinates":[-1.167051,53.15615],"type":"Point"}
}
