{
  "type": "Feature",
  "properties": {
    "date:inception_lower": "1980-01-01",
    "date:inception_upper": "1980-01-01",
    "iso:country": "GB",
    "wof:name": "NN17 2TA",
    "wof:placetype": "postalcode"
  },
  "geometry": {"coordinates":[-0.721645,52.491561],"type":"Point"}
}
