{
  "type": "Feature",
  "properties": {
    "iso:country":"GB",
    "wof:name":"NW8 0ND",
    "wof:placetype":"postalcode"
},
  "geometry": {"coordinates":[-0.1783289398956,51.53856236399103],"type":"Point"}
}