{
  "type": "Feature",
  "properties": {
    "iso:country": "GB",
    "wof:name": "BD16 1RF",
    "wof:placetype": "postalcode"
  },
  "geometry": {"coordinates":[-1.835388,53.830068],"type":"Point"}
}
