{
  "type": "Feature",
  "properties": {
    "iso:country":"GB",
    "wof:name":"HR4 7BB",
    "wof:placetype":"postalcode"
},
  "geometry": {"coordinates":[-2.88552892828362,52.11828464689764],"type":"Point"}
}