{
  "type": "Feature",
  "properties": {
    "iso:country": "GB",
    "wof:name": "HR4 7BB",
    "wof:placetype": "postalcode"
  },
  "geometry": {"coordinates":[-2.885545,52.118231],"type":"Point"}
}
