{
  "type": "Feature",
  "properties": {
    "date:inception_lower":"1997-12-01",
    "date:inception_upper":"1997-12-31",
    "iso:country":"GB",
    "wof:name":"BS34 7RJ",
    "wof:placetype":"postalcode"
},
  "geometry": {"coordinates":[-2.581886,51.505346],"type":"Point"}
}