{
  "type": "Feature",
  "properties": {
    "iso:country": "GB",
    "wof:name": "BS34 7RJ",
    "wof:placetype": "postalcode"
  },
  "geometry": {"coordinates":[-2.581886,51.505346],"type":"Point"}
}
