{
  "type": "Feature",
  "properties": {
    "date:inception_lower": "1980-01-01",
    "date:inception_upper": "1980-01-01",
    "iso:country": "GB",
    "wof:name": "NE3 3PJ",
    "wof:placetype": "postalcode"
  },
  "geometry": {"coordinates":[-1.63642,55.011018],"type":"Point"}
}
