{
  "type": "Feature",
  "properties": {
    "iso:country":"GB",
    "wof:name":"B29 4BP",
    "wof:placetype":"postalcode"
},
  "geometry": {"coordinates":[-1.9572706706611,52.43450122383226],"type":"Point"}
}