{
  "type": "Feature",
  "properties": {
    "date:inception_lower": "1994-12-01",
    "date:inception_upper": "1994-12-01",
    "iso:country": "GB",
    "wof:name": "YO13 0SE",
    "wof:placetype": "postalcode"
  },
  "geometry": {"coordinates":[-0.443769,54.304151],"type":"Point"}
}
