{
  "type": "Feature",
  "properties": {
    "iso:country": "GB",
    "wof:name": "YO13 0SE",
    "wof:placetype": "postalcode"
  },
  "geometry": {"coordinates":[-0.443769,54.304151],"type":"Point"}
}
