{
  "type": "Feature",
  "properties": {
    "iso:country":"GB",
    "wof:name":"B75 7HR",
    "wof:placetype":"postalcode"
},
  "geometry": {"coordinates":[-1.77150081164197,52.57309329113851],"type":"Point"}
}