{
  "type": "Feature",
  "properties": {
    "iso:country":"GB",
    "wof:name":"BH18 9HF",
    "wof:placetype":"postalcode"
},
  "geometry": {"coordinates":[-2.00658337503231,50.76125204202861],"type":"Point"}
}