{
  "type": "Feature",
  "properties": {
    "iso:country": "GB",
    "wof:name": "SO17 1EG",
    "wof:placetype": "postalcode"
  },
  "geometry": {"coordinates":[-1.4028,50.924217],"type":"Point"}
}
