{
  "type": "Feature",
  "properties": {
    "iso:country": "GB",
    "wof:name": "BS16 1JG",
    "wof:placetype": "postalcode"
  },
  "geometry": {"coordinates":[-2.532678,51.49006],"type":"Point"}
}
