{
  "type": "Feature",
  "properties": {
    "iso:country": "GB",
    "wof:name": "NR1 2FF",
    "wof:placetype": "postalcode"
  },
  "geometry": {"coordinates":[1.304762,52.622011],"type":"Point"}
}
