{
  "type": "Feature",
  "properties": {
    "date:inception_lower": "2008-11-01",
    "date:inception_upper": "2008-11-01",
    "iso:country": "GB",
    "wof:name": "NR1 2FF",
    "wof:placetype": "postalcode"
  },
  "geometry": {"coordinates":[1.304762,52.622011],"type":"Point"}
}
