{
  "type": "Feature",
  "properties": {
    "iso:country":"GB",
    "wof:name":"NR1 2FF",
    "wof:placetype":"postalcode"
},
  "geometry": {"coordinates":[1.30476229715701,52.62201098064698],"type":"Point"}
}