{
  "type": "Feature",
  "properties": {
    "iso:country":"GB",
    "wof:name":"LE7 3ZP",
    "wof:placetype":"postalcode"
},
  "geometry": {"coordinates":[-1.05569046825303,52.71411876169911],"type":"Point"}
}