{
  "type": "Feature",
  "properties": {
    "date:inception_lower": "1992-08-01",
    "date:inception_upper": "1992-08-01",
    "iso:country": "GB",
    "wof:name": "LE7 3ZP",
    "wof:placetype": "postalcode"
  },
  "geometry": {"coordinates":[-1.05569,52.714119],"type":"Point"}
}
