{
  "type": "Feature",
  "properties": {
    "iso:country": "GB",
    "wof:name": "SK8 7NU",
    "wof:placetype": "postalcode"
  },
  "geometry": {"coordinates":[-2.217761,53.393134],"type":"Point"}
}
