{
  "type": "Feature",
  "properties": {
    "iso:country":"GB",
    "wof:name":"LS24 9QE",
    "wof:placetype":"postalcode"
},
  "geometry": {"coordinates":[-1.27532272584533,53.82753494360014],"type":"Point"}
}