{
  "type": "Feature",
  "properties": {
    "iso:country":"GB",
    "wof:name":"DL8 4RR",
    "wof:placetype":"postalcode"
},
  "geometry": {"coordinates":[-1.86529785844386,54.25795040520674],"type":"Point"}
}