{
  "type": "Feature",
  "properties": {
    "date:inception_lower": "1980-01-01",
    "date:inception_upper": "1980-01-01",
    "iso:country": "GB",
    "wof:name": "LE10 3DX",
    "wof:placetype": "postalcode"
  },
  "geometry": {"coordinates":[-1.384046,52.563478],"type":"Point"}
}
