{
  "type": "Feature",
  "properties": {
    "iso:country":"GB",
    "wof:name":"LE10 3DX",
    "wof:placetype":"postalcode"
},
  "geometry": {"coordinates":[-1.38281421503957,52.56682470333531],"type":"Point"}
}