{
  "type": "Feature",
  "properties": {
    "iso:country":"GB",
    "wof:name":"E2 6QA",
    "wof:placetype":"postalcode"
},
  "geometry": {"coordinates":[-0.06098950568209,51.52947851309298],"type":"Point"}
}