{
  "type": "Feature",
  "properties": {
    "iso:country": "GB",
    "wof:name": "PL7 4FF",
    "wof:placetype": "postalcode"
  },
  "geometry": {"coordinates":[-4.043086,50.396364],"type":"Point"}
}
