{
  "type": "Feature",
  "properties": {
    "iso:country":"GB",
    "wof:name":"AB45 3SS",
    "wof:placetype":"postalcode"
},
  "geometry": {"coordinates":[-2.40182448292572,57.63224435113947],"type":"Point"}
}