{
  "type": "Feature",
  "properties": {
    "iso:country":"GB",
    "wof:name":"YO43 4EQ",
    "wof:placetype":"postalcode"
},
  "geometry": {"coordinates":[-0.77988700447042,53.83495341231561],"type":"Point"}
}