{
  "type": "Feature",
  "properties": {
    "iso:country": "GB",
    "wof:name": "YO43 4EQ",
    "wof:placetype": "postalcode"
  },
  "geometry": {"coordinates":[-0.779887,53.834953],"type":"Point"}
}
