{
  "type": "Feature",
  "properties": {
    "date:inception_lower": "2001-12-01",
    "date:inception_upper": "2001-12-01",
    "iso:country": "GB",
    "wof:name": "YO43 4EQ",
    "wof:placetype": "postalcode"
  },
  "geometry": {"coordinates":[-0.779887,53.834953],"type":"Point"}
}
