{
  "type": "Feature",
  "properties": {
    "iso:country":"GB",
    "wof:name":"HU7 6DQ",
    "wof:placetype":"postalcode"
},
  "geometry": {"coordinates":[-0.34082032860925,53.78742723952736],"type":"Point"}
}