{
  "type": "Feature",
  "properties": {
    "date:inception_lower":"1980-01-01",
    "date:inception_upper":"1980-01-31",
    "iso:country":"GB",
    "wof:name":"HU7 6DQ",
    "wof:placetype":"postalcode"
},
  "geometry": {"coordinates":[-0.34082,53.787427],"type":"Point"}
}