{
  "type": "Feature",
  "properties": {
    "iso:country": "GB",
    "wof:name": "ME17 4UT",
    "wof:placetype": "postalcode"
  },
  "geometry": {"coordinates":[0.546024,51.242424],"type":"Point"}
}
