{
  "type": "Feature",
  "properties": {
    "iso:country":"GB",
    "wof:name":"ME17 4UT",
    "wof:placetype":"postalcode"
},
  "geometry": {"coordinates":[0.54602346900103,51.24242424176455],"type":"Point"}
}