{
  "type": "Feature",
  "properties": {
    "iso:country":"GB",
    "wof:name":"NW8 9PX",
    "wof:placetype":"postalcode"
},
  "geometry": {"coordinates":[-0.17931797034356,51.53112299091327],"type":"Point"}
}