{
  "type": "Feature",
  "properties": {
    "iso:country": "GB",
    "wof:name": "HP6 5AJ",
    "wof:placetype": "postalcode"
  },
  "geometry": {"coordinates":[-0.602853,51.674669],"type":"Point"}
}
