{
  "type": "Feature",
  "properties": {
    "date:inception_lower":"2014-08-01",
    "date:inception_upper":"2014-08-31",
    "iso:country":"GB",
    "wof:name":"HP6 5AJ",
    "wof:placetype":"postalcode"
},
  "geometry": {"coordinates":[-0.602853,51.674669],"type":"Point"}
}