{
  "type": "Feature",
  "properties": {
    "iso:country":"GB",
    "wof:name":"HP6 5AJ",
    "wof:placetype":"postalcode"
},
  "geometry": {"coordinates":[-0.60285261924347,51.67466931631577],"type":"Point"}
}