{
  "type": "Feature",
  "properties": {
    "iso:country":"GB",
    "wof:name":"SL2 4QF",
    "wof:placetype":"postalcode"
},
  "geometry": {"coordinates":[-0.57619048474577,51.54473055023179],"type":"Point"}
}