{
  "type": "Feature",
  "properties": {
    "iso:country":"GB",
    "wof:name":"S43 1LU",
    "wof:placetype":"postalcode"
},
  "geometry": {"coordinates":[-1.40796168430234,53.25905805640181],"type":"Point"}
}