{
  "type": "Feature",
  "properties": {
    "iso:country": "GB",
    "wof:name": "DN4 0BG",
    "wof:placetype": "postalcode"
  },
  "geometry": {"coordinates":[-1.144819,53.518716],"type":"Point"}
}
