{
  "type": "Feature",
  "properties": {
    "iso:country": "GB",
    "wof:name": "SY17 5DD",
    "wof:placetype": "postalcode"
  },
  "geometry": {"coordinates":[-3.442957,52.488556],"type":"Point"}
}
