{
  "type": "Feature",
  "properties": {
    "date:inception_lower": "1980-01-01",
    "date:inception_upper": "1980-01-01",
    "iso:country": "GB",
    "wof:name": "SY17 5DD",
    "wof:placetype": "postalcode"
  },
  "geometry": {"coordinates":[-3.442957,52.488556],"type":"Point"}
}
