{
  "type": "Feature",
  "properties": {
    "iso:country":"GB",
    "wof:name":"SY17 5DD",
    "wof:placetype":"postalcode"
},
  "geometry": {"coordinates":[-3.4429574002036,52.48855576192993],"type":"Point"}
}