{
  "type": "Feature",
  "properties": {
    "iso:country":"GB",
    "wof:name":"NR1 4EX",
    "wof:placetype":"postalcode"
},
  "geometry": {"coordinates":[1.31218554273597,52.63419676709302],"type":"Point"}
}