{
  "type": "Feature",
  "properties": {
    "iso:country": "GB",
    "wof:name": "NR1 4EX",
    "wof:placetype": "postalcode"
  },
  "geometry": {"coordinates":[1.312186,52.634197],"type":"Point"}
}
