{
  "type": "Feature",
  "properties": {
    "iso:country":"GB",
    "wof:name":"CV13 0BX",
    "wof:placetype":"postalcode"
},
  "geometry": {"coordinates":[-1.40903665119208,52.64213189902227],"type":"Point"}
}