{
  "type": "Feature",
  "properties": {
    "iso:country": "GB",
    "wof:name": "BS20 7TT",
    "wof:placetype": "postalcode"
  },
  "geometry": {"coordinates":[-2.715765,51.482124],"type":"Point"}
}
