{
  "type": "Feature",
  "properties": {
    "date:inception_lower":"1999-12-01",
    "date:inception_upper":"1999-12-31",
    "iso:country":"GB",
    "wof:name":"BS20 7TT",
    "wof:placetype":"postalcode"
},
  "geometry": {"coordinates":[-2.715765,51.482124],"type":"Point"}
}