{
  "type": "Feature",
  "properties": {
    "iso:country":"GB",
    "wof:name":"CB4 2AN",
    "wof:placetype":"postalcode"
},
  "geometry": {"coordinates":[0.12922845277346,52.2230424803434],"type":"Point"}
}