{
  "type": "Feature",
  "properties": {
    "date:inception_lower": "1980-01-01",
    "date:inception_upper": "1980-01-01",
    "iso:country": "GB",
    "wof:name": "RH19 1QY",
    "wof:placetype": "postalcode"
  },
  "geometry": {"coordinates":[-0.034659,51.136516],"type":"Point"}
}
