{
  "type": "Feature",
  "properties": {
    "iso:country":"GB",
    "wof:name":"BD21 3PJ",
    "wof:placetype":"postalcode"
},
  "geometry": {"coordinates":[-1.90907495603377,53.86592690073042],"type":"Point"}
}