{
  "type": "Feature",
  "properties": {
    "iso:country":"GB",
    "wof:name":"LL22 9AG",
    "wof:placetype":"postalcode"
},
  "geometry": {"coordinates":[-3.56300263300982,53.29679895761964],"type":"Point"}
}