{
  "type": "Feature",
  "properties": {
    "iso:country": "GB",
    "wof:name": "LL22 9AG",
    "wof:placetype": "postalcode"
  },
  "geometry": {"coordinates":[-3.563003,53.296799],"type":"Point"}
}
