{
  "type": "Feature",
  "properties": {
    "iso:country":"GB",
    "wof:name":"WF9 2DW",
    "wof:placetype":"postalcode"
},
  "geometry": {"coordinates":[-1.28008299597815,53.59909912293681],"type":"Point"}
}