{
  "type": "Feature",
  "properties": {
    "iso:country": "GB",
    "wof:name": "DD11 2BA",
    "wof:placetype": "postalcode"
  },
  "geometry": {"coordinates":[-2.593768,56.55777],"type":"Point"}
}
