{
  "type": "Feature",
  "properties": {
    "date:inception_lower": "1980-01-01",
    "date:inception_upper": "1980-01-01",
    "iso:country": "GB",
    "wof:name": "OX4 4RR",
    "wof:placetype": "postalcode"
  },
  "geometry": {"coordinates":[-1.22597,51.72542],"type":"Point"}
}
