{
  "type": "Feature",
  "properties": {
    "iso:country":"GB",
    "wof:name":"OX4 4RR",
    "wof:placetype":"postalcode"
},
  "geometry": {"coordinates":[-1.22596984891558,51.72541965988847],"type":"Point"}
}