{
  "type": "Feature",
  "properties": {
    "iso:country":"GB",
    "wof:name":"BS9 4HP",
    "wof:placetype":"postalcode"
},
  "geometry": {"coordinates":[-2.61234336059059,51.48158784924806],"type":"Point"}
}