{
  "type": "Feature",
  "properties": {
    "iso:country": "GB",
    "wof:name": "SW19 6TT",
    "wof:placetype": "postalcode"
  },
  "geometry": {"coordinates":[-0.213936,51.439303],"type":"Point"}
}
