{
  "type": "Feature",
  "properties": {
    "iso:country":"GB",
    "wof:name":"PL1 3AY",
    "wof:placetype":"postalcode"
},
  "geometry": {"coordinates":[-4.14875662860805,50.3673996868154],"type":"Point"}
}