{
  "type": "Feature",
  "properties": {
    "iso:country": "GB",
    "wof:name": "PL1 3AY",
    "wof:placetype": "postalcode"
  },
  "geometry": {"coordinates":[-4.148815,50.367421],"type":"Point"}
}
