{
  "type": "Feature",
  "properties": {
    "date:inception_lower": "2019-06-01",
    "date:inception_upper": "2019-06-01",
    "iso:country": "GB",
    "wof:name": "TW15 2AZ",
    "wof:placetype": "postalcode"
  },
  "geometry": {"coordinates":[-0.470069,51.435956],"type":"Point"}
}
