{
  "type": "Feature",
  "properties": {
    "iso:country":"GB",
    "wof:name":"BH25 6BU",
    "wof:placetype":"postalcode"
},
  "geometry": {"coordinates":[-1.65180084862198,50.7539708107326],"type":"Point"}
}