{
  "type": "Feature",
  "properties": {
    "iso:country": "GB",
    "wof:name": "NG15 7UT",
    "wof:placetype": "postalcode"
  },
  "geometry": {"coordinates":[-1.195237,53.034674],"type":"Point"}
}
