{
  "type": "Feature",
  "properties": {
    "iso:country":"GB",
    "wof:name":"GL9 1HJ",
    "wof:placetype":"postalcode"
},
  "geometry": {"coordinates":[-2.27065384557029,51.52606996634163],"type":"Point"}
}