{
  "type": "Feature",
  "properties": {
    "iso:country":"GB",
    "wof:name":"B11 4HA",
    "wof:placetype":"postalcode"
},
  "geometry": {"coordinates":[-1.8630201254578,52.44736647062771],"type":"Point"}
}