{
  "type": "Feature",
  "properties": {
    "iso:country": "GB",
    "wof:name": "B11 4HA",
    "wof:placetype": "postalcode"
  },
  "geometry": {"coordinates":[-1.86302,52.447366],"type":"Point"}
}
