{
  "type": "Feature",
  "properties": {
    "iso:country":"GB",
    "wof:name":"IG1 1JW",
    "wof:placetype":"postalcode"
},
  "geometry": {"coordinates":[0.07760027056353,51.55501005025815],"type":"Point"}
}