{
  "type": "Feature",
  "properties": {
    "iso:country":"GB",
    "wof:name":"RG12 7YX",
    "wof:placetype":"postalcode"
},
  "geometry": {"coordinates":[-0.76242354472687,51.38885330665995],"type":"Point"}
}