{
  "type": "Feature",
  "properties": {
    "iso:country":"GB",
    "wof:name":"LN9 6DG",
    "wof:placetype":"postalcode"
},
  "geometry": {"coordinates":[-0.10543101589346,53.20152243286723],"type":"Point"}
}