{
  "type": "Feature",
  "properties": {
    "iso:country":"GB",
    "wof:name":"OL7 9RR",
    "wof:placetype":"postalcode"
},
  "geometry": {"coordinates":[-2.10498049739457,53.50841225188769],"type":"Point"}
}