{
  "type": "Feature",
  "properties": {
    "iso:country":"GB",
    "wof:name":"ME15 6QW",
    "wof:placetype":"postalcode"
},
  "geometry": {"coordinates":[0.51029656794615,51.26415160792063],"type":"Point"}
}