{
  "type": "Feature",
  "properties": {
    "iso:country":"GB",
    "wof:name":"NG7 2NB",
    "wof:placetype":"postalcode"
},
  "geometry": {"coordinates":[-1.17992160588411,52.94500753930069],"type":"Point"}
}