{
  "type": "Feature",
  "properties": {
    "iso:country":"GB",
    "wof:name":"SY10 8PE",
    "wof:placetype":"postalcode"
},
  "geometry": {"coordinates":[-2.99957315643218,52.76003148937278],"type":"Point"}
}