{
  "type": "Feature",
  "properties": {
    "date:inception_lower": "1986-07-01",
    "date:inception_upper": "1986-07-01",
    "iso:country": "GB",
    "wof:name": "SY10 8PE",
    "wof:placetype": "postalcode"
  },
  "geometry": {"coordinates":[-2.999573,52.760031],"type":"Point"}
}
