{
  "type": "Feature",
  "properties": {
    "date:inception_lower": "1986-07-01",
    "date:inception_upper": "1986-07-01",
    "iso:country": "GB",
    "wof:name": "NR17 2PP",
    "wof:placetype": "postalcode"
  },
  "geometry": {"coordinates":[1.004004,52.514249],"type":"Point"}
}
