{
  "type": "Feature",
  "properties": {
    "iso:country": "GB",
    "wof:name": "HP9 1XT",
    "wof:placetype": "postalcode"
  },
  "geometry": {"coordinates":[-0.665707,51.617547],"type":"Point"}
}
