{
  "type": "Feature",
  "properties": {
    "iso:country":"GB",
    "wof:name":"HP9 1XT",
    "wof:placetype":"postalcode"
},
  "geometry": {"coordinates":[-0.66570657915896,51.61754684282798],"type":"Point"}
}