{
  "type": "Feature",
  "properties": {
    "date:inception_lower": "1980-01-01",
    "date:inception_upper": "1980-01-01",
    "iso:country": "GB",
    "wof:name": "HP9 1XT",
    "wof:placetype": "postalcode"
  },
  "geometry": {"coordinates":[-0.665707,51.617547],"type":"Point"}
}
