{
  "type": "Feature",
  "properties": {
    "date:inception_lower":"2005-05-01",
    "date:inception_upper":"2005-05-31",
    "iso:country":"GB",
    "wof:name":"G42 8TN",
    "wof:placetype":"postalcode"
},
  "geometry": {"coordinates":[-4.264683,55.833822],"type":"Point"}
}