{
  "type": "Feature",
  "properties": {
    "iso:country":"GB",
    "wof:name":"G42 8TN",
    "wof:placetype":"postalcode"
},
  "geometry": {"coordinates":[-4.26468346447779,55.83382199388778],"type":"Point"}
}