{
  "type": "Feature",
  "properties": {
    "iso:country": "GB",
    "wof:name": "TN23 7RP",
    "wof:placetype": "postalcode"
  },
  "geometry": {"coordinates":[0.871629,51.141523],"type":"Point"}
}
