{
  "type": "Feature",
  "properties": {
    "iso:country": "GB",
    "wof:name": "CM14 4NX",
    "wof:placetype": "postalcode"
  },
  "geometry": {"coordinates":[0.282687,51.61337],"type":"Point"}
}
