{
  "type": "Feature",
  "properties": {
    "iso:country":"GB",
    "wof:name":"UB7 9LD",
    "wof:placetype":"postalcode"
},
  "geometry": {"coordinates":[-0.46323876308325,51.50115935744586],"type":"Point"}
}