{
  "type": "Feature",
  "properties": {
    "iso:country": "GB",
    "wof:name": "UB7 9LD",
    "wof:placetype": "postalcode"
  },
  "geometry": {"coordinates":[-0.463239,51.501159],"type":"Point"}
}
