{
  "type": "Feature",
  "properties": {
    "iso:country": "GB",
    "wof:name": "SA12 9PR",
    "wof:placetype": "postalcode"
  },
  "geometry": {"coordinates":[-3.76016,51.619984],"type":"Point"}
}
