{
  "type": "Feature",
  "properties": {
    "iso:country":"GB",
    "wof:name":"DE13 9SD",
    "wof:placetype":"postalcode"
},
  "geometry": {"coordinates":[-1.69810180526561,52.79513596322173],"type":"Point"}
}