{
  "type": "Feature",
  "properties": {
    "iso:country": "GB",
    "wof:name": "DE13 9SD",
    "wof:placetype": "postalcode"
  },
  "geometry": {"coordinates":[-1.698102,52.795136],"type":"Point"}
}
