{
  "type": "Feature",
  "properties": {
    "iso:country": "GB",
    "wof:name": "DT1 2FG",
    "wof:placetype": "postalcode"
  },
  "geometry": {"coordinates":[-2.456775,50.714062],"type":"Point"}
}
