{
  "type": "Feature",
  "properties": {
    "iso:country":"GB",
    "wof:name":"DT1 2FG",
    "wof:placetype":"postalcode"
},
  "geometry": {"coordinates":[-2.45697886522669,50.71445721553745],"type":"Point"}
}