{
  "type": "Feature",
  "properties": {
    "date:inception_lower": "2010-11-01",
    "date:inception_upper": "2010-11-01",
    "iso:country": "GB",
    "wof:name": "DT1 2FG",
    "wof:placetype": "postalcode"
  },
  "geometry": {"coordinates":[-2.456775,50.714053],"type":"Point"}
}
