{
  "type": "Feature",
  "properties": {
    "iso:country":"GB",
    "wof:name":"SW1X 7AF",
    "wof:placetype":"postalcode"
},
  "geometry": {"coordinates":[-0.14936016420182,51.49871285912798],"type":"Point"}
}