{
  "type": "Feature",
  "properties": {
    "iso:country":"GB",
    "wof:name":"DY9 0EJ",
    "wof:placetype":"postalcode"
},
  "geometry": {"coordinates":[-2.14867839675265,52.39533524590863],"type":"Point"}
}