{
  "type": "Feature",
  "properties": {
    "date:inception_lower":"1980-01-01",
    "date:inception_upper":"1980-01-31",
    "iso:country":"GB",
    "wof:name":"DY9 0EJ",
    "wof:placetype":"postalcode"
},
  "geometry": {"coordinates":[-2.148678,52.395335],"type":"Point"}
}