{
  "type": "Feature",
  "properties": {
    "iso:country": "GB",
    "wof:name": "TQ4 6JY",
    "wof:placetype": "postalcode"
  },
  "geometry": {"coordinates":[-3.562657,50.402405],"type":"Point"}
}
