{
  "type": "Feature",
  "properties": {
    "date:inception_lower": "1980-01-01",
    "date:inception_upper": "1980-01-01",
    "iso:country": "GB",
    "wof:name": "TQ4 6JY",
    "wof:placetype": "postalcode"
  },
  "geometry": {"coordinates":[-3.562657,50.402405],"type":"Point"}
}
