{
  "type": "Feature",
  "properties": {
    "iso:country": "GB",
    "wof:name": "SY8 3ET",
    "wof:placetype": "postalcode"
  },
  "geometry": {"coordinates":[-2.674244,52.383265],"type":"Point"}
}
