{
  "type": "Feature",
  "properties": {
    "iso:country":"GB",
    "wof:name":"EX15 3DQ",
    "wof:placetype":"postalcode"
},
  "geometry": {"coordinates":[-3.34756690967596,50.88815191352538],"type":"Point"}
}