{
  "type": "Feature",
  "properties": {
    "iso:country": "GB",
    "wof:name": "DE73 7HT",
    "wof:placetype": "postalcode"
  },
  "geometry": {"coordinates":[-1.448551,52.841551],"type":"Point"}
}
