{
  "type": "Feature",
  "properties": {
    "iso:country":"GB",
    "wof:name":"DE73 7HT",
    "wof:placetype":"postalcode"
},
  "geometry": {"coordinates":[-1.4485572363496,52.84153336652795],"type":"Point"}
}