{
  "type": "Feature",
  "properties": {
    "iso:country":"GB",
    "wof:name":"BS41 9FE",
    "wof:placetype":"postalcode"
},
  "geometry": {"coordinates":[-2.66828899872206,51.42637912470806],"type":"Point"}
}