{
  "type": "Feature",
  "properties": {
    "date:inception_lower": "2007-01-01",
    "date:inception_upper": "2007-01-01",
    "iso:country": "GB",
    "wof:name": "BS41 9FE",
    "wof:placetype": "postalcode"
  },
  "geometry": {"coordinates":[-2.668289,51.426379],"type":"Point"}
}
