{
  "type": "Feature",
  "properties": {
    "iso:country":"GB",
    "wof:name":"S40 3PS",
    "wof:placetype":"postalcode"
},
  "geometry": {"coordinates":[-1.47776273536613,53.23274995985139],"type":"Point"}
}