{
  "type": "Feature",
  "properties": {
    "iso:country":"GB",
    "wof:name":"ME3 9LF",
    "wof:placetype":"postalcode"
},
  "geometry": {"coordinates":[0.555452320991,51.42930507732979],"type":"Point"}
}