{
  "type": "Feature",
  "properties": {
    "iso:country": "GB",
    "wof:name": "B49 5BT",
    "wof:placetype": "postalcode"
  },
  "geometry": {"coordinates":[-1.874222,52.212061],"type":"Point"}
}
