{
  "type": "Feature",
  "properties": {
    "date:inception_lower": "1980-01-01",
    "date:inception_upper": "1980-01-01",
    "iso:country": "GB",
    "wof:name": "BB12 6SY",
    "wof:placetype": "postalcode"
  },
  "geometry": {"coordinates":[-2.272272,53.79462],"type":"Point"}
}
