{
  "type": "Feature",
  "properties": {
    "iso:country":"GB",
    "wof:name":"G15 6AT",
    "wof:placetype":"postalcode"
},
  "geometry": {"coordinates":[-4.35889605150308,55.90693611403582],"type":"Point"}
}