{
  "type": "Feature",
  "properties": {
    "iso:country": "GB",
    "wof:name": "EX22 6JY",
    "wof:placetype": "postalcode"
  },
  "geometry": {"coordinates":[-4.376858,50.804214],"type":"Point"}
}
