{
  "type": "Feature",
  "properties": {
    "iso:country":"GB",
    "wof:name":"TQ3 3ST",
    "wof:placetype":"postalcode"
},
  "geometry": {"coordinates":[-3.58397773881958,50.44127563744254],"type":"Point"}
}