{
  "type": "Feature",
  "properties": {
    "iso:country":"GB",
    "wof:name":"EH44 6LX",
    "wof:placetype":"postalcode"
},
  "geometry": {"coordinates":[-3.05358875596595,55.62036028217547],"type":"Point"}
}