{
  "type": "Feature",
  "properties": {
    "date:inception_lower": "1980-01-01",
    "date:inception_upper": "1980-01-01",
    "iso:country": "GB",
    "wof:name": "BB9 5JG",
    "wof:placetype": "postalcode"
  },
  "geometry": {"coordinates":[-2.233295,53.820206],"type":"Point"}
}
