{
  "type": "Feature",
  "properties": {
    "iso:country":"GB",
    "wof:name":"PL19 9AE",
    "wof:placetype":"postalcode"
},
  "geometry": {"coordinates":[-4.13985597689512,50.54594709846864],"type":"Point"}
}