{
  "type": "Feature",
  "properties": {
    "iso:country": "GB",
    "wof:name": "BB5 4AQ",
    "wof:placetype": "postalcode"
  },
  "geometry": {"coordinates":[-2.381716,53.758576],"type":"Point"}
}
