{
  "type": "Feature",
  "properties": {
    "iso:country":"GB",
    "wof:name":"CV35 7AW",
    "wof:placetype":"postalcode"
},
  "geometry": {"coordinates":[-1.68753372945571,52.3038473039833],"type":"Point"}
}