{
  "type": "Feature",
  "properties": {
    "date:inception_lower":"1980-01-01",
    "date:inception_upper":"1980-01-31",
    "iso:country":"GB",
    "wof:name":"CV35 7AW",
    "wof:placetype":"postalcode"
},
  "geometry": {"coordinates":[-1.687523,52.303862],"type":"Point"}
}