{
  "type": "Feature",
  "properties": {
    "iso:country": "GB",
    "wof:name": "LS11 5HE",
    "wof:placetype": "postalcode"
  },
  "geometry": {"coordinates":[-1.53965,53.777159],"type":"Point"}
}
