{
  "type": "Feature",
  "properties": {
    "iso:country":"GB",
    "wof:name":"LS11 5HE",
    "wof:placetype":"postalcode"
},
  "geometry": {"coordinates":[-1.53965030842003,53.77715862951892],"type":"Point"}
}