{
  "type": "Feature",
  "properties": {
    "iso:country":"GB",
    "wof:name":"LA8 8EW",
    "wof:placetype":"postalcode"
},
  "geometry": {"coordinates":[-2.81773429657076,54.26371668600713],"type":"Point"}
}