{
  "type": "Feature",
  "properties": {
    "iso:country":"GB",
    "wof:name":"SL1 7NZ",
    "wof:placetype":"postalcode"
},
  "geometry": {"coordinates":[-0.66779848367416,51.52679733972618],"type":"Point"}
}