{
  "type": "Feature",
  "properties": {
    "iso:country": "GB",
    "wof:name": "SL1 7NZ",
    "wof:placetype": "postalcode"
  },
  "geometry": {"coordinates":[-0.667798,51.526797],"type":"Point"}
}
