{
  "type": "Feature",
  "properties": {
    "iso:country":"GB",
    "wof:name":"S4 7SD",
    "wof:placetype":"postalcode"
},
  "geometry": {"coordinates":[-1.45133610261033,53.39901403394165],"type":"Point"}
}