{
  "type": "Feature",
  "properties": {
    "iso:country":"GB",
    "wof:name":"TW8 0QP",
    "wof:placetype":"postalcode"
},
  "geometry": {"coordinates":[-0.30733574663114,51.48977789325752],"type":"Point"}
}