{
  "type": "Feature",
  "properties": {
    "iso:country":"GB",
    "wof:name":"PA8 6BQ",
    "wof:placetype":"postalcode"
},
  "geometry": {"coordinates":[-4.46544657301498,55.9105372503688],"type":"Point"}
}