{
  "type": "Feature",
  "properties": {
    "iso:country":"GB",
    "wof:name":"N17 0ES",
    "wof:placetype":"postalcode"
},
  "geometry": {"coordinates":[-0.0632467460185,51.60669861972113],"type":"Point"}
}