{
  "type": "Feature",
  "properties": {
    "date:inception_lower": "1980-01-01",
    "date:inception_upper": "1980-01-01",
    "iso:country": "GB",
    "wof:name": "LD1 5UN",
    "wof:placetype": "postalcode"
  },
  "geometry": {"coordinates":[-3.231729,52.311824],"type":"Point"}
}
