{
  "type": "Feature",
  "properties": {
    "iso:country":"GB",
    "wof:name":"NE28 8JN",
    "wof:placetype":"postalcode"
},
  "geometry": {"coordinates":[-1.53631062027732,54.99099776200413],"type":"Point"}
}