{
  "type": "Feature",
  "properties": {
    "iso:country":"GB",
    "wof:name":"TF13 6AD",
    "wof:placetype":"postalcode"
},
  "geometry": {"coordinates":[-2.56003667611877,52.59488500267291],"type":"Point"}
}