{
  "type": "Feature",
  "properties": {
    "iso:country":"GB",
    "wof:name":"W1F 8WR",
    "wof:placetype":"postalcode"
},
  "geometry": {"coordinates":[-0.13509355879487,51.51467339805479],"type":"Point"}
}