{
  "type": "Feature",
  "properties": {
    "iso:country": "GB",
    "wof:name": "CT2 8AP",
    "wof:placetype": "postalcode"
  },
  "geometry": {"coordinates":[1.071312,51.282264],"type":"Point"}
}
