{
  "type": "Feature",
  "properties": {
    "iso:country":"GB",
    "wof:name":"OX1 1NS",
    "wof:placetype":"postalcode"
},
  "geometry": {"coordinates":[-1.26354306319266,51.75197849344566],"type":"Point"}
}