{
  "type": "Feature",
  "properties": {
    "iso:country":"GB",
    "wof:name":"PE11 3DL",
    "wof:placetype":"postalcode"
},
  "geometry": {"coordinates":[-0.26495976656898,52.70354885458713],"type":"Point"}
}