{
  "type": "Feature",
  "properties": {
    "date:inception_lower": "1980-01-01",
    "date:inception_upper": "1980-01-01",
    "iso:country": "GB",
    "wof:name": "N19 3HT",
    "wof:placetype": "postalcode"
  },
  "geometry": {"coordinates":[-0.124101,51.567935],"type":"Point"}
}
