{
  "type": "Feature",
  "properties": {
    "iso:country":"GB",
    "wof:name":"N19 3HT",
    "wof:placetype":"postalcode"
},
  "geometry": {"coordinates":[-0.12389012831391,51.56808995028378],"type":"Point"}
}