{
  "type": "Feature",
  "properties": {
    "iso:country":"GB",
    "wof:name":"CA3 9QH",
    "wof:placetype":"postalcode"
},
  "geometry": {"coordinates":[-2.95547269778914,54.91181156301536],"type":"Point"}
}