{
  "type": "Feature",
  "properties": {
    "iso:country": "GB",
    "wof:name": "EX23 8PL",
    "wof:placetype": "postalcode"
  },
  "geometry": {"coordinates":[-4.543407,50.826154],"type":"Point"}
}
