{
  "type": "Feature",
  "properties": {
    "iso:country":"GB",
    "wof:name":"EX23 8PL",
    "wof:placetype":"postalcode"
},
  "geometry": {"coordinates":[-4.54340722156626,50.82615384936406],"type":"Point"}
}