{
  "type": "Feature",
  "properties": {
    "date:inception_lower": "1993-01-01",
    "date:inception_upper": "1993-01-01",
    "iso:country": "GB",
    "wof:name": "L16 5HF",
    "wof:placetype": "postalcode"
  },
  "geometry": {"coordinates":[-2.88453,53.39544],"type":"Point"}
}
