{
  "type": "Feature",
  "properties": {
    "iso:country": "GB",
    "wof:name": "AB41 8PR",
    "wof:placetype": "postalcode"
  },
  "geometry": {"coordinates":[-2.126341,57.37372],"type":"Point"}
}
