{
  "type": "Feature",
  "properties": {
    "iso:country":"GB",
    "wof:name":"RH6 7NG",
    "wof:placetype":"postalcode"
},
  "geometry": {"coordinates":[-0.16216646235096,51.16776590530551],"type":"Point"}
}