{
  "type": "Feature",
  "properties": {
    "date:inception_lower":"2010-08-01",
    "date:inception_upper":"2010-08-31",
    "iso:country":"GB",
    "wof:name":"TS17 5BZ",
    "wof:placetype":"postalcode"
},
  "geometry": {"coordinates":[-1.317458,54.519736],"type":"Point"}
}