{
  "type": "Feature",
  "properties": {
    "iso:country":"GB",
    "wof:name":"TS17 5BZ",
    "wof:placetype":"postalcode"
},
  "geometry": {"coordinates":[-1.31745799823903,54.51973649776834],"type":"Point"}
}