{
  "type": "Feature",
  "properties": {
    "date:inception_lower": "1998-06-01",
    "date:inception_upper": "1998-06-01",
    "iso:country": "GB",
    "wof:name": "E6 5UE",
    "wof:placetype": "postalcode"
  },
  "geometry": {"coordinates":[0.049007,51.518058],"type":"Point"}
}
