{
  "type": "Feature",
  "properties": {
    "iso:country":"GB",
    "wof:name":"E6 5UE",
    "wof:placetype":"postalcode"
},
  "geometry": {"coordinates":[0.04900728463224,51.51805831576538],"type":"Point"}
}