{
  "type": "Feature",
  "properties": {
    "date:inception_lower":"1980-01-01",
    "date:inception_upper":"1980-01-31",
    "iso:country":"GB",
    "wof:name":"SW10 0TP",
    "wof:placetype":"postalcode"
},
  "geometry": {"coordinates":[-0.182236,51.481737],"type":"Point"}
}