{
  "type": "Feature",
  "properties": {
    "iso:country":"GB",
    "wof:name":"SW10 0TP",
    "wof:placetype":"postalcode"
},
  "geometry": {"coordinates":[-0.18223605427996,51.48173664412908],"type":"Point"}
}