{
  "type": "Feature",
  "properties": {
    "iso:country": "GB",
    "wof:name": "PE14 0NE",
    "wof:placetype": "postalcode"
  },
  "geometry": {"coordinates":[0.115343,52.604519],"type":"Point"}
}
