{
  "type": "Feature",
  "properties": {
    "iso:country":"GB",
    "wof:name":"PE14 0NE",
    "wof:placetype":"postalcode"
},
  "geometry": {"coordinates":[0.11534294662474,52.60451905336956],"type":"Point"}
}