{
  "type": "Feature",
  "properties": {
    "iso:country":"GB",
    "wof:name":"NE6 4TD",
    "wof:placetype":"postalcode"
},
  "geometry": {"coordinates":[-1.54562676033695,54.98811235608335],"type":"Point"}
}