{
  "type": "Feature",
  "properties": {
    "iso:country":"GB",
    "wof:name":"CF63 1QF",
    "wof:placetype":"postalcode"
},
  "geometry": {"coordinates":[-3.25858253837246,51.42310857151414],"type":"Point"}
}