{
  "type": "Feature",
  "properties": {
    "iso:country":"GB",
    "wof:name":"TS22 5PL",
    "wof:placetype":"postalcode"
},
  "geometry": {"coordinates":[-1.27061797043936,54.64796848807977],"type":"Point"}
}