{
  "type": "Feature",
  "properties": {
    "iso:country": "GB",
    "wof:name": "TS22 5PL",
    "wof:placetype": "postalcode"
  },
  "geometry": {"coordinates":[-1.270618,54.647968],"type":"Point"}
}
