{
  "type": "Feature",
  "properties": {
    "date:inception_lower": "1980-01-01",
    "date:inception_upper": "1980-01-01",
    "iso:country": "GB",
    "wof:name": "TS22 5PL",
    "wof:placetype": "postalcode"
  },
  "geometry": {"coordinates":[-1.270618,54.647968],"type":"Point"}
}
