{
  "type": "Feature",
  "properties": {
    "iso:country":"GB",
    "wof:name":"TN34 1UF",
    "wof:placetype":"postalcode"
},
  "geometry": {"coordinates":[0.57711518017903,50.86002659357368],"type":"Point"}
}