{
  "type": "Feature",
  "properties": {
    "iso:country":"GB",
    "wof:name":"N22 8YF",
    "wof:placetype":"postalcode"
},
  "geometry": {"coordinates":[-0.11995630926202,51.60607395325187],"type":"Point"}
}