{
  "type": "Feature",
  "properties": {
    "date:inception_lower": "1980-01-01",
    "date:inception_upper": "1980-01-01",
    "iso:country": "GB",
    "wof:name": "GL53 0PB",
    "wof:placetype": "postalcode"
  },
  "geometry": {"coordinates":[-2.079742,51.874331],"type":"Point"}
}
