{
  "type": "Feature",
  "properties": {
    "iso:country": "GB",
    "wof:name": "PA19 1QR",
    "wof:placetype": "postalcode"
  },
  "geometry": {"coordinates":[-4.816565,55.962149],"type":"Point"}
}
