{
  "type": "Feature",
  "properties": {
    "date:inception_lower":"1980-01-01",
    "date:inception_upper":"1980-01-31",
    "iso:country":"GB",
    "wof:name":"PA19 1QR",
    "wof:placetype":"postalcode"
},
  "geometry": {"coordinates":[-4.816565,55.962149],"type":"Point"}
}