{
  "type": "Feature",
  "properties": {
    "iso:country":"GB",
    "wof:name":"M46 9DB",
    "wof:placetype":"postalcode"
},
  "geometry": {"coordinates":[-2.48285708821271,53.52455152076434],"type":"Point"}
}