{
  "type": "Feature",
  "properties": {
    "date:inception_lower": "1980-01-01",
    "date:inception_upper": "1980-01-01",
    "iso:country": "GB",
    "wof:name": "HU14 3PJ",
    "wof:placetype": "postalcode"
  },
  "geometry": {"coordinates":[-0.501369,53.736652],"type":"Point"}
}
