{
  "type": "Feature",
  "properties": {
    "iso:country":"GB",
    "wof:name":"HU14 3PJ",
    "wof:placetype":"postalcode"
},
  "geometry": {"coordinates":[-0.50067775410183,53.73674957771271],"type":"Point"}
}