{
  "type": "Feature",
  "properties": {
    "date:inception_lower": "1980-01-01",
    "date:inception_upper": "1980-01-01",
    "iso:country": "GB",
    "wof:name": "CF33 6LD",
    "wof:placetype": "postalcode"
  },
  "geometry": {"coordinates":[-3.688347,51.532602],"type":"Point"}
}
