{
  "type": "Feature",
  "properties": {
    "iso:country":"GB",
    "wof:name":"M8 8QA",
    "wof:placetype":"postalcode"
},
  "geometry": {"coordinates":[-2.23852559362843,53.49198700298471],"type":"Point"}
}