{
  "type": "Feature",
  "properties": {
    "iso:country": "GB",
    "wof:name": "CV1 2RU",
    "wof:placetype": "postalcode"
  },
  "geometry": {"coordinates":[-1.502991,52.403726],"type":"Point"}
}
