{
  "type": "Feature",
  "properties": {
    "iso:country":"GB",
    "wof:name":"RG29 1SW",
    "wof:placetype":"postalcode"
},
  "geometry": {"coordinates":[-0.93949752702217,51.21585472735897],"type":"Point"}
}