{
  "type": "Feature",
  "properties": {
    "iso:country": "GB",
    "wof:name": "RG29 1SW",
    "wof:placetype": "postalcode"
  },
  "geometry": {"coordinates":[-0.939497,51.215855],"type":"Point"}
}
