{
  "type": "Feature",
  "properties": {
    "iso:country": "GB",
    "wof:name": "TA7 8BJ",
    "wof:placetype": "postalcode"
  },
  "geometry": {"coordinates":[-2.966891,51.166821],"type":"Point"}
}
