{
  "type": "Feature",
  "properties": {
    "iso:country":"GB",
    "wof:name":"SG8 5JX",
    "wof:placetype":"postalcode"
},
  "geometry": {"coordinates":[-0.04599165106061,52.08132494069321],"type":"Point"}
}