{
  "type": "Feature",
  "properties": {
    "iso:country":"GB",
    "wof:name":"TW1 4QB",
    "wof:placetype":"postalcode"
},
  "geometry": {"coordinates":[-0.33780329094407,51.4378061925468],"type":"Point"}
}