{
  "type": "Feature",
  "properties": {
    "date:inception_lower": "1980-01-01",
    "date:inception_upper": "1980-01-01",
    "iso:country": "GB",
    "wof:name": "TW1 4QB",
    "wof:placetype": "postalcode"
  },
  "geometry": {"coordinates":[-0.337803,51.437806],"type":"Point"}
}
