{
  "type": "Feature",
  "properties": {
    "iso:country":"GB",
    "wof:name":"BN21 4EX",
    "wof:placetype":"postalcode"
},
  "geometry": {"coordinates":[0.27956562841586,50.76542480575674],"type":"Point"}
}