{
  "type": "Feature",
  "properties": {
    "iso:country":"GB",
    "wof:name":"PE29 1PH",
    "wof:placetype":"postalcode"
},
  "geometry": {"coordinates":[-0.16903982351,52.34149188888085],"type":"Point"}
}