{
  "type": "Feature",
  "properties": {
    "iso:country":"GB",
    "wof:name":"TS29 6QG",
    "wof:placetype":"postalcode"
},
  "geometry": {"coordinates":[-1.43240869554498,54.70022969961429],"type":"Point"}
}