{
  "type": "Feature",
  "properties": {
    "date:inception_lower":"1980-01-01",
    "date:inception_upper":"1980-01-31",
    "iso:country":"GB",
    "wof:name":"TS27 3AD",
    "wof:placetype":"postalcode"
},
  "geometry": {"coordinates":[-1.272743,54.707771],"type":"Point"}
}