{
  "type": "Feature",
  "properties": {
    "iso:country":"GB",
    "wof:name":"TS27 3AD",
    "wof:placetype":"postalcode"
},
  "geometry": {"coordinates":[-1.27274272460819,54.70777092746582],"type":"Point"}
}