{
  "type": "Feature",
  "properties": {
    "iso:country":"GB",
    "wof:name":"S3 9SR",
    "wof:placetype":"postalcode"
},
  "geometry": {"coordinates":[-1.47869426572082,53.39645792160564],"type":"Point"}
}