{
  "type": "Feature",
  "properties": {
    "iso:country":"GB",
    "wof:name":"EX34 8JA",
    "wof:placetype":"postalcode"
},
  "geometry": {"coordinates":[-4.11992353012295,51.20042238681351],"type":"Point"}
}