{
  "type": "Feature",
  "properties": {
    "date:inception_lower": "1980-01-01",
    "date:inception_upper": "1980-01-01",
    "iso:country": "GB",
    "wof:name": "CF5 4RH",
    "wof:placetype": "postalcode"
  },
  "geometry": {"coordinates":[-3.263989,51.473073],"type":"Point"}
}
