{
  "type": "Feature",
  "properties": {
    "iso:country":"GB",
    "wof:name":"NW7 1RT",
    "wof:placetype":"postalcode"
},
  "geometry": {"coordinates":[-0.21475741229505,51.61249982744429],"type":"Point"}
}