{
  "type": "Feature",
  "properties": {
    "iso:country":"GB",
    "wof:name":"TF9 3QH",
    "wof:placetype":"postalcode"
},
  "geometry": {"coordinates":[-2.53621759745031,52.8814330828429],"type":"Point"}
}