{
  "type": "Feature",
  "properties": {
    "iso:country":"GB",
    "wof:name":"DY4 9ND",
    "wof:placetype":"postalcode"
},
  "geometry": {"coordinates":[-2.06133683446402,52.54025954163347],"type":"Point"}
}