{
  "type": "Feature",
  "properties": {
    "date:inception_lower": "1980-01-01",
    "date:inception_upper": "1980-01-01",
    "iso:country": "GB",
    "wof:name": "DY4 9ND",
    "wof:placetype": "postalcode"
  },
  "geometry": {"coordinates":[-2.061337,52.54026],"type":"Point"}
}
