{
  "type": "Feature",
  "properties": {
    "date:inception_lower":"1995-07-01",
    "date:inception_upper":"1995-07-31",
    "iso:country":"GB",
    "wof:name":"TW13 5DU",
    "wof:placetype":"postalcode"
},
  "geometry": {"coordinates":[-0.397041,51.445133],"type":"Point"}
}