{
  "type": "Feature",
  "properties": {
    "iso:country":"GB",
    "wof:name":"TW13 5DU",
    "wof:placetype":"postalcode"
},
  "geometry": {"coordinates":[-0.39704068947376,51.44513261682579],"type":"Point"}
}