{
  "type": "Feature",
  "properties": {
    "iso:country":"GB",
    "wof:name":"SA15 3LQ",
    "wof:placetype":"postalcode"
},
  "geometry": {"coordinates":[-4.1577013541881,51.69149389324068],"type":"Point"}
}