{
  "type": "Feature",
  "properties": {
    "iso:country": "GB",
    "wof:name": "S12 4NF",
    "wof:placetype": "postalcode"
  },
  "geometry": {"coordinates":[-1.377506,53.343363],"type":"Point"}
}
