{
  "type": "Feature",
  "properties": {
    "iso:country":"GB",
    "wof:name":"S12 4NF",
    "wof:placetype":"postalcode"
},
  "geometry": {"coordinates":[-1.37734115273132,53.34333449046078],"type":"Point"}
}