{
  "type": "Feature",
  "properties": {
    "date:inception_lower": "2001-06-01",
    "date:inception_upper": "2001-06-01",
    "iso:country": "GB",
    "wof:name": "HD9 2DA",
    "wof:placetype": "postalcode"
  },
  "geometry": {"coordinates":[-1.786741,53.553784],"type":"Point"}
}
