{
  "type": "Feature",
  "properties": {
    "iso:country":"GB",
    "wof:name":"HD9 2DA",
    "wof:placetype":"postalcode"
},
  "geometry": {"coordinates":[-1.78655813814776,53.55403732525837],"type":"Point"}
}