{
  "type": "Feature",
  "properties": {
    "date:inception_lower": "1980-01-01",
    "date:inception_upper": "1980-01-01",
    "iso:country": "GB",
    "wof:name": "LU5 5HN",
    "wof:placetype": "postalcode"
  },
  "geometry": {"coordinates":[-0.522699,51.908624],"type":"Point"}
}
