{
  "type": "Feature",
  "properties": {
    "iso:country":"GB",
    "wof:name":"NR5 8RG",
    "wof:placetype":"postalcode"
},
  "geometry": {"coordinates":[1.23676527639936,52.63617516142642],"type":"Point"}
}