{
  "type": "Feature",
  "properties": {
    "date:inception_lower":"1984-02-01",
    "date:inception_upper":"1984-02-29",
    "iso:country":"GB",
    "wof:name":"S81 0XW",
    "wof:placetype":"postalcode"
},
  "geometry": {"coordinates":[-1.110093,53.32716],"type":"Point"}
}