{
  "type": "Feature",
  "properties": {
    "iso:country":"GB",
    "wof:name":"S81 0XW",
    "wof:placetype":"postalcode"
},
  "geometry": {"coordinates":[-1.11009323468115,53.32716017561147],"type":"Point"}
}