{
  "type": "Feature",
  "properties": {
    "date:inception_lower": "2018-10-01",
    "date:inception_upper": "2018-10-01",
    "iso:country": "GB",
    "wof:name": "SL2 3FW",
    "wof:placetype": "postalcode"
  },
  "geometry": {"coordinates":[-0.615285,51.537081],"type":"Point"}
}
