{
  "type": "Feature",
  "properties": {
    "iso:country": "GB",
    "wof:name": "CH8 7HN",
    "wof:placetype": "postalcode"
  },
  "geometry": {"coordinates":[-3.219225,53.273491],"type":"Point"}
}
