{
  "type": "Feature",
  "properties": {
    "date:inception_lower":"1990-07-01",
    "date:inception_upper":"1990-07-31",
    "iso:country":"GB",
    "wof:name":"CH8 7HN",
    "wof:placetype":"postalcode"
},
  "geometry": {"coordinates":[-3.219225,53.273491],"type":"Point"}
}