{
  "type": "Feature",
  "properties": {
    "iso:country":"GB",
    "wof:name":"NG15 6NF",
    "wof:placetype":"postalcode"
},
  "geometry": {"coordinates":[-1.21314848728794,53.03953998103981],"type":"Point"}
}