{
  "type": "Feature",
  "properties": {
    "iso:country":"GB",
    "wof:name":"PE34 4NY",
    "wof:placetype":"postalcode"
},
  "geometry": {"coordinates":[0.27644784911454,52.75913490739913],"type":"Point"}
}