{
  "type": "Feature",
  "properties": {
    "date:inception_lower":"1980-01-01",
    "date:inception_upper":"1980-01-31",
    "iso:country":"GB",
    "wof:name":"PE34 4NY",
    "wof:placetype":"postalcode"
},
  "geometry": {"coordinates":[0.276448,52.759135],"type":"Point"}
}