{
  "type": "Feature",
  "properties": {
    "iso:country":"GB",
    "wof:name":"NN8 3SX",
    "wof:placetype":"postalcode"
},
  "geometry": {"coordinates":[-0.72842469084731,52.30425978627314],"type":"Point"}
}