{
  "type": "Feature",
  "properties": {
    "date:inception_lower":"2006-01-01",
    "date:inception_upper":"2006-01-31",
    "iso:country":"GB",
    "wof:name":"M46 0GS",
    "wof:placetype":"postalcode"
},
  "geometry": {"coordinates":[-2.508729,53.521029],"type":"Point"}
}