{
  "type": "Feature",
  "properties": {
    "iso:country":"GB",
    "wof:name":"B38 8BG",
    "wof:placetype":"postalcode"
},
  "geometry": {"coordinates":[-1.93407209505107,52.40654954230145],"type":"Point"}
}