{
  "type": "Feature",
  "properties": {
    "iso:country": "GB",
    "wof:name": "SK17 6LY",
    "wof:placetype": "postalcode"
  },
  "geometry": {"coordinates":[-1.91328,53.254787],"type":"Point"}
}
