{
  "type": "Feature",
  "properties": {
    "iso:country":"GB",
    "wof:name":"IP13 9RN",
    "wof:placetype":"postalcode"
},
  "geometry": {"coordinates":[1.33917249903477,52.22079600525599],"type":"Point"}
}