{
  "type": "Feature",
  "properties": {
    "iso:country": "GB",
    "wof:name": "NR34 9RP",
    "wof:placetype": "postalcode"
  },
  "geometry": {"coordinates":[1.574319,52.4552],"type":"Point"}
}
