{
  "type": "Feature",
  "properties": {
    "iso:country":"GB",
    "wof:name":"SW1Y 6RP",
    "wof:placetype":"postalcode"
},
  "geometry": {"coordinates":[-0.13554031656928,51.50867350101552],"type":"Point"}
}