{
  "type": "Feature",
  "properties": {
    "iso:country":"GB",
    "wof:name":"PL19 0BN",
    "wof:placetype":"postalcode"
},
  "geometry": {"coordinates":[-4.14346276227129,50.55108833972245],"type":"Point"}
}