{
  "type": "Feature",
  "properties": {
    "iso:country":"GB",
    "wof:name":"TR1 2LB",
    "wof:placetype":"postalcode"
},
  "geometry": {"coordinates":[-5.06296284247307,50.26104537203518],"type":"Point"}
}