{
  "type": "Feature",
  "properties": {
    "iso:country":"GB",
    "wof:name":"DH4 7QF",
    "wof:placetype":"postalcode"
},
  "geometry": {"coordinates":[-1.51169458894091,54.87632536873188],"type":"Point"}
}