{
  "type": "Feature",
  "properties": {
    "date:inception_lower": "1982-03-01",
    "date:inception_upper": "1982-03-01",
    "iso:country": "GB",
    "wof:name": "WF13 2TU",
    "wof:placetype": "postalcode"
  },
  "geometry": {"coordinates":[-1.637547,53.691748],"type":"Point"}
}
