{
  "type": "Feature",
  "properties": {
    "date:inception_lower": "1980-01-01",
    "date:inception_upper": "1980-01-01",
    "iso:country": "GB",
    "wof:name": "DT6 5HE",
    "wof:placetype": "postalcode"
  },
  "geometry": {"coordinates":[-2.760846,50.740845],"type":"Point"}
}
