{
  "type": "Feature",
  "properties": {
    "iso:country":"GB",
    "wof:name":"DT6 5HE",
    "wof:placetype":"postalcode"
},
  "geometry": {"coordinates":[-2.76084535594869,50.74084618550246],"type":"Point"}
}