{
  "type": "Feature",
  "properties": {
    "iso:country":"GB",
    "wof:name":"BD10 8QY",
    "wof:placetype":"postalcode"
},
  "geometry": {"coordinates":[-1.73555448195171,53.83219044748978],"type":"Point"}
}