{
  "type": "Feature",
  "properties": {
    "iso:country": "GB",
    "wof:name": "LA8 9JE",
    "wof:placetype": "postalcode"
  },
  "geometry": {"coordinates":[-2.821317,54.385904],"type":"Point"}
}
