{
  "type": "Feature",
  "properties": {
    "iso:country":"GB",
    "wof:name":"GL16 8EP",
    "wof:placetype":"postalcode"
},
  "geometry": {"coordinates":[-2.62037288046813,51.79976811295975],"type":"Point"}
}