{
  "type": "Feature",
  "properties": {
    "iso:country": "GB",
    "wof:name": "GL16 8EP",
    "wof:placetype": "postalcode"
  },
  "geometry": {"coordinates":[-2.620375,51.799782],"type":"Point"}
}
