{
  "type": "Feature",
  "properties": {
    "date:inception_lower": "1988-03-01",
    "date:inception_upper": "1988-03-01",
    "iso:country": "GB",
    "wof:name": "GL16 8EP",
    "wof:placetype": "postalcode"
  },
  "geometry": {"coordinates":[-2.620375,51.799782],"type":"Point"}
}
