{
  "type": "Feature",
  "properties": {
    "iso:country":"GB",
    "wof:name":"WN4 9AZ",
    "wof:placetype":"postalcode"
},
  "geometry": {"coordinates":[-2.63929445037692,53.48753927513248],"type":"Point"}
}