{
  "type": "Feature",
  "properties": {
    "iso:country":"GB",
    "wof:name":"TS10 4NP",
    "wof:placetype":"postalcode"
},
  "geometry": {"coordinates":[-1.06971293003112,54.59895191048155],"type":"Point"}
}