{
  "type": "Feature",
  "properties": {
    "iso:country":"GB",
    "wof:name":"KA7 3NY",
    "wof:placetype":"postalcode"
},
  "geometry": {"coordinates":[-4.60147778657013,55.45061690160914],"type":"Point"}
}