{
  "type": "Feature",
  "properties": {
    "iso:country": "GB",
    "wof:name": "TA9 4BP",
    "wof:placetype": "postalcode"
  },
  "geometry": {"coordinates":[-2.961871,51.261321],"type":"Point"}
}
