{
  "type": "Feature",
  "properties": {
    "date:inception_lower":"1993-08-01",
    "date:inception_upper":"1993-08-31",
    "iso:country":"GB",
    "wof:name":"TF3 4LN",
    "wof:placetype":"postalcode"
},
  "geometry": {"coordinates":[-2.448991,52.674217],"type":"Point"}
}