{
  "type": "Feature",
  "properties": {
    "iso:country":"GB",
    "wof:name":"TF3 4LN",
    "wof:placetype":"postalcode"
},
  "geometry": {"coordinates":[-2.44899133595478,52.6742167234834],"type":"Point"}
}