{
  "type": "Feature",
  "properties": {
    "iso:country": "GB",
    "wof:name": "SA65 9LN",
    "wof:placetype": "postalcode"
  },
  "geometry": {"coordinates":[-4.973459,51.991137],"type":"Point"}
}
