{
  "type": "Feature",
  "properties": {
    "date:inception_lower": "1980-01-01",
    "date:inception_upper": "1980-01-01",
    "iso:country": "GB",
    "wof:name": "GU31 5NW",
    "wof:placetype": "postalcode"
  },
  "geometry": {"coordinates":[-0.881043,50.971822],"type":"Point"}
}
