{
  "type": "Feature",
  "properties": {
    "iso:country":"GB",
    "wof:name":"GU31 5NW",
    "wof:placetype":"postalcode"
},
  "geometry": {"coordinates":[-0.88104301170698,50.97182188633336],"type":"Point"}
}