{
  "type": "Feature",
  "properties": {
    "iso:country":"GB",
    "wof:name":"NW3 7UJ",
    "wof:placetype":"postalcode"
},
  "geometry": {"coordinates":[-0.19316129327667,51.56455495085636],"type":"Point"}
}