{
  "type": "Feature",
  "properties": {
    "iso:country":"GB",
    "wof:name":"TS22 5HZ",
    "wof:placetype":"postalcode"
},
  "geometry": {"coordinates":[-1.30454650487933,54.61224722693879],"type":"Point"}
}