{
  "type": "Feature",
  "properties": {
    "date:inception_lower": "1999-06-01",
    "date:inception_upper": "1999-06-01",
    "iso:country": "GB",
    "wof:name": "NP11 7PA",
    "wof:placetype": "postalcode"
  },
  "geometry": {"coordinates":[-3.127649,51.619987],"type":"Point"}
}
