{
  "type": "Feature",
  "properties": {
    "iso:country":"GB",
    "wof:name":"NP11 7PA",
    "wof:placetype":"postalcode"
},
  "geometry": {"coordinates":[-3.12764952883765,51.61998680182801],"type":"Point"}
}