{
  "type": "Feature",
  "properties": {
    "iso:country": "GB",
    "wof:name": "SP11 9RD",
    "wof:placetype": "postalcode"
  },
  "geometry": {"coordinates":[-1.61586,51.255339],"type":"Point"}
}
