{
  "type": "Feature",
  "properties": {
    "iso:country":"GB",
    "wof:name":"TN22 3LP",
    "wof:placetype":"postalcode"
},
  "geometry": {"coordinates":[0.05801884427225,51.02723860788064],"type":"Point"}
}