{
  "type": "Feature",
  "properties": {
    "date:inception_lower": "1980-01-01",
    "date:inception_upper": "1980-01-01",
    "iso:country": "GB",
    "wof:name": "PE20 1HE",
    "wof:placetype": "postalcode"
  },
  "geometry": {"coordinates":[-0.057607,52.931568],"type":"Point"}
}
