{
  "type": "Feature",
  "properties": {
    "date:inception_lower": "2019-01-01",
    "date:inception_upper": "2019-01-01",
    "iso:country": "GB",
    "wof:name": "IV2 7AL",
    "wof:placetype": "postalcode"
  },
  "geometry": {"coordinates":[-4.158326,57.484208],"type":"Point"}
}
