{
  "type": "Feature",
  "properties": {
    "iso:country":"GB",
    "wof:name":"CT15 4HU",
    "wof:placetype":"postalcode"
},
  "geometry": {"coordinates":[1.22832289645905,51.22075142926779],"type":"Point"}
}