{
  "type": "Feature",
  "properties": {
    "iso:country":"GB",
    "wof:name":"PO12 1PG",
    "wof:placetype":"postalcode"
},
  "geometry": {"coordinates":[-1.13490427463203,50.79437666228631],"type":"Point"}
}