{
  "type": "Feature",
  "properties": {
    "iso:country":"GB",
    "wof:name":"SS0 8JH",
    "wof:placetype":"postalcode"
},
  "geometry": {"coordinates":[0.67648253394905,51.53734201066701],"type":"Point"}
}