{
  "type": "Feature",
  "properties": {
    "iso:country":"GB",
    "wof:name":"BL3 6RH",
    "wof:placetype":"postalcode"
},
  "geometry": {"coordinates":[-2.43206875019947,53.56744089067225],"type":"Point"}
}