{
  "type": "Feature",
  "properties": {
    "iso:country":"GB",
    "wof:name":"CW5 8AX",
    "wof:placetype":"postalcode"
},
  "geometry": {"coordinates":[-2.51025150679419,53.01618985725018],"type":"Point"}
}