{
  "type": "Feature",
  "properties": {
    "date:inception_lower": "1980-01-01",
    "date:inception_upper": "1980-01-01",
    "iso:country": "GB",
    "wof:name": "NR25 7QD",
    "wof:placetype": "postalcode"
  },
  "geometry": {"coordinates":[1.047845,52.887344],"type":"Point"}
}
