{
  "type": "Feature",
  "properties": {
    "date:inception_lower": "1983-03-01",
    "date:inception_upper": "1983-03-01",
    "iso:country": "GB",
    "wof:name": "EX9 7JQ",
    "wof:placetype": "postalcode"
  },
  "geometry": {"coordinates":[-3.296679,50.658803],"type":"Point"}
}
