{
  "type": "Feature",
  "properties": {
    "iso:country": "GB",
    "wof:name": "EX9 7JQ",
    "wof:placetype": "postalcode"
  },
  "geometry": {"coordinates":[-3.296679,50.658803],"type":"Point"}
}
