{
  "type": "Feature",
  "properties": {
    "iso:country":"GB",
    "wof:name":"TA1 1UX",
    "wof:placetype":"postalcode"
},
  "geometry": {"coordinates":[-3.10784105386022,51.01830657208118],"type":"Point"}
}