{
  "type": "Feature",
  "properties": {
    "iso:country": "GB",
    "wof:name": "KT11 9FF",
    "wof:placetype": "postalcode"
  },
  "geometry": {"coordinates":[-0.410656,51.329081],"type":"Point"}
}
