{
  "type": "Feature",
  "properties": {
    "iso:country": "GB",
    "wof:name": "CT4 6HF",
    "wof:placetype": "postalcode"
  },
  "geometry": {"coordinates":[1.18737,51.210568],"type":"Point"}
}
