{
  "type": "Feature",
  "properties": {
    "iso:country":"GB",
    "wof:name":"CT4 6HF",
    "wof:placetype":"postalcode"
},
  "geometry": {"coordinates":[1.18736959519347,51.21056839160541],"type":"Point"}
}