{
  "type": "Feature",
  "properties": {
    "iso:country": "GB",
    "wof:name": "MK40 4WJ",
    "wof:placetype": "postalcode"
  },
  "geometry": {"coordinates":[-0.508958,52.125075],"type":"Point"}
}
