{
  "type": "Feature",
  "properties": {
    "iso:country": "GB",
    "wof:name": "CH7 6GT",
    "wof:placetype": "postalcode"
  },
  "geometry": {"coordinates":[-3.136672,53.176242],"type":"Point"}
}
