{
  "type": "Feature",
  "properties": {
    "date:inception_lower": "1996-06-01",
    "date:inception_upper": "1996-06-01",
    "iso:country": "GB",
    "wof:name": "CH7 6GT",
    "wof:placetype": "postalcode"
  },
  "geometry": {"coordinates":[-3.136672,53.176242],"type":"Point"}
}
