{
  "type": "Feature",
  "properties": {
    "iso:country":"GB",
    "wof:name":"CH7 6GT",
    "wof:placetype":"postalcode"
},
  "geometry": {"coordinates":[-3.13667161058255,53.17624232166002],"type":"Point"}
}