{
  "type": "Feature",
  "properties": {
    "date:inception_lower":"2013-08-01",
    "date:inception_upper":"2013-08-31",
    "iso:country":"GB",
    "wof:name":"DE55 1SG",
    "wof:placetype":"postalcode"
},
  "geometry": {"coordinates":[-1.382452,53.081548],"type":"Point"}
}