{
  "type": "Feature",
  "properties": {
    "iso:country":"GB",
    "wof:name":"DE55 1SG",
    "wof:placetype":"postalcode"
},
  "geometry": {"coordinates":[-1.38245229401279,53.08154776092351],"type":"Point"}
}