{
  "type": "Feature",
  "properties": {
    "date:inception_lower":"2005-03-01",
    "date:inception_upper":"2005-03-31",
    "iso:country":"GB",
    "wof:name":"SE5 7TX",
    "wof:placetype":"postalcode"
},
  "geometry": {"coordinates":[-0.088292,51.479649],"type":"Point"}
}