{
  "type": "Feature",
  "properties": {
    "iso:country":"GB",
    "wof:name":"SE5 7TX",
    "wof:placetype":"postalcode"
},
  "geometry": {"coordinates":[-0.08829201190199,51.4796491446322],"type":"Point"}
}