{
  "type": "Feature",
  "properties": {
    "date:inception_lower": "2019-10-01",
    "date:inception_upper": "2019-10-01",
    "iso:country": "GB",
    "wof:name": "GU6 8UU",
    "wof:placetype": "postalcode"
  },
  "geometry": {"coordinates":[-0.503734,51.142001],"type":"Point"}
}
