{
  "type": "Feature",
  "properties": {
    "iso:country":"GB",
    "wof:name":"GL5 5BY",
    "wof:placetype":"postalcode"
},
  "geometry": {"coordinates":[-2.2081336016978,51.72049039957422],"type":"Point"}
}