{
  "type": "Feature",
  "properties": {
    "date:inception_lower": "1980-01-01",
    "date:inception_upper": "1980-01-01",
    "iso:country": "GB",
    "wof:name": "GL5 5BY",
    "wof:placetype": "postalcode"
  },
  "geometry": {"coordinates":[-2.208134,51.72049],"type":"Point"}
}
