{
  "type": "Feature",
  "properties": {
    "iso:country": "GB",
    "wof:name": "TR18 5PN",
    "wof:placetype": "postalcode"
  },
  "geometry": {"coordinates":[-5.554287,50.108332],"type":"Point"}
}
