{
  "type": "Feature",
  "properties": {
    "iso:country":"GB",
    "wof:name":"IP2 8EE",
    "wof:placetype":"postalcode"
},
  "geometry": {"coordinates":[1.1526620479317,52.04657494017294],"type":"Point"}
}