{
  "type": "Feature",
  "properties": {
    "iso:country":"GB",
    "wof:name":"HA4 6UB",
    "wof:placetype":"postalcode"
},
  "geometry": {"coordinates":[-0.39781215029024,51.55499250198385],"type":"Point"}
}