{
  "type": "Feature",
  "properties": {
    "date:inception_lower":"1980-01-01",
    "date:inception_upper":"1980-01-31",
    "iso:country":"GB",
    "wof:name":"SS2 5LY",
    "wof:placetype":"postalcode"
},
  "geometry": {"coordinates":[0.721632,51.551772],"type":"Point"}
}