{
  "type": "Feature",
  "properties": {
    "iso:country":"GB",
    "wof:name":"SS2 5LY",
    "wof:placetype":"postalcode"
},
  "geometry": {"coordinates":[0.7216323872168,51.5517719093051],"type":"Point"}
}