{
  "type": "Feature",
  "properties": {
    "iso:country": "GB",
    "wof:name": "SS2 5LY",
    "wof:placetype": "postalcode"
  },
  "geometry": {"coordinates":[0.721632,51.551772],"type":"Point"}
}
