{
  "type": "Feature",
  "properties": {
    "iso:country":"GB",
    "wof:name":"GU14 9DY",
    "wof:placetype":"postalcode"
},
  "geometry": {"coordinates":[-0.77613905394829,51.30457903740268],"type":"Point"}
}