{
  "type": "Feature",
  "properties": {
    "iso:country": "GB",
    "wof:name": "GL51 4UW",
    "wof:placetype": "postalcode"
  },
  "geometry": {"coordinates":[-2.142814,51.875126],"type":"Point"}
}
