{
  "type": "Feature",
  "properties": {
    "iso:country":"GB",
    "wof:name":"GL51 4UW",
    "wof:placetype":"postalcode"
},
  "geometry": {"coordinates":[-2.14281368986744,51.87512558403852],"type":"Point"}
}