{
  "type": "Feature",
  "properties": {
    "date:inception_lower":"2000-10-01",
    "date:inception_upper":"2000-10-31",
    "iso:country":"GB",
    "wof:name":"GL51 4UW",
    "wof:placetype":"postalcode"
},
  "geometry": {"coordinates":[-2.142814,51.875126],"type":"Point"}
}