{
  "type": "Feature",
  "properties": {
    "date:inception_lower":"1980-01-01",
    "date:inception_upper":"1980-01-31",
    "iso:country":"GB",
    "wof:name":"SG12 0PL",
    "wof:placetype":"postalcode"
},
  "geometry": {"coordinates":[-0.088267,51.87452],"type":"Point"}
}