{
  "type": "Feature",
  "properties": {
    "iso:country":"GB",
    "wof:name":"SG12 0PL",
    "wof:placetype":"postalcode"
},
  "geometry": {"coordinates":[-0.08826718964298,51.87452048806779],"type":"Point"}
}