{
  "type": "Feature",
  "properties": {
    "iso:country": "GB",
    "wof:name": "WR6 6LW",
    "wof:placetype": "postalcode"
  },
  "geometry": {"coordinates":[-2.311784,52.269577],"type":"Point"}
}
