{
  "type": "Feature",
  "properties": {
    "iso:country":"GB",
    "wof:name":"WR6 6LW",
    "wof:placetype":"postalcode"
},
  "geometry": {"coordinates":[-2.31178410993989,52.26957673483997],"type":"Point"}
}