{
  "type": "Feature",
  "properties": {
    "iso:country":"GB",
    "wof:name":"PO8 0UU",
    "wof:placetype":"postalcode"
},
  "geometry": {"coordinates":[-0.99698909109601,50.90911721410016],"type":"Point"}
}