{
  "type": "Feature",
  "properties": {
    "iso:country":"GB",
    "wof:name":"CW1 3NY",
    "wof:placetype":"postalcode"
},
  "geometry": {"coordinates":[-2.46753737589487,53.11185726889033],"type":"Point"}
}