{
  "type": "Feature",
  "properties": {
    "iso:country": "GB",
    "wof:name": "DA13 0AF",
    "wof:placetype": "postalcode"
  },
  "geometry": {"coordinates":[0.366625,51.369985],"type":"Point"}
}
