{
  "type": "Feature",
  "properties": {
    "date:inception_lower": "1980-01-01",
    "date:inception_upper": "1980-01-01",
    "iso:country": "GB",
    "wof:name": "NN7 3AT",
    "wof:placetype": "postalcode"
  },
  "geometry": {"coordinates":[-0.926755,52.193341],"type":"Point"}
}
