{
  "type": "Feature",
  "properties": {
    "iso:country":"GB",
    "wof:name":"NN7 3AT",
    "wof:placetype":"postalcode"
},
  "geometry": {"coordinates":[-0.92675539716839,52.19334082648195],"type":"Point"}
}