{
  "type": "Feature",
  "properties": {
    "date:inception_lower": "2020-12-01",
    "date:inception_upper": "2020-12-01",
    "iso:country": "GB",
    "wof:name": "EH25 9AY",
    "wof:placetype": "postalcode"
  },
  "geometry": {"coordinates":[-3.166524,55.861131],"type":"Point"}
}
