{
  "type": "Feature",
  "properties": {
    "iso:country":"GB",
    "wof:name":"BR2 8DT",
    "wof:placetype":"postalcode"
},
  "geometry": {"coordinates":[0.05760699510959,51.38317717735309],"type":"Point"}
}