{
  "type": "Feature",
  "properties": {
    "iso:country":"GB",
    "wof:name":"CF5 4TG",
    "wof:placetype":"postalcode"
},
  "geometry": {"coordinates":[-3.27055884369357,51.47529498457246],"type":"Point"}
}