{
  "type": "Feature",
  "properties": {
    "iso:country":"GB",
    "wof:name":"WA2 8QP",
    "wof:placetype":"postalcode"
},
  "geometry": {"coordinates":[-2.60698981511666,53.42156051141629],"type":"Point"}
}