{
  "type": "Feature",
  "properties": {
    "date:inception_lower":"1987-04-01",
    "date:inception_upper":"1987-04-30",
    "iso:country":"GB",
    "wof:name":"WA2 8QP",
    "wof:placetype":"postalcode"
},
  "geometry": {"coordinates":[-2.606732,53.421427],"type":"Point"}
}