{
  "type": "Feature",
  "properties": {
    "iso:country": "GB",
    "wof:name": "CO16 8RR",
    "wof:placetype": "postalcode"
  },
  "geometry": {"coordinates":[1.078743,51.798278],"type":"Point"}
}
