{
  "type": "Feature",
  "properties": {
    "iso:country":"GB",
    "wof:name":"S20 7LW",
    "wof:placetype":"postalcode"
},
  "geometry": {"coordinates":[-1.34748094339802,53.33744914725654],"type":"Point"}
}