{
  "type": "Feature",
  "properties": {
    "iso:country":"GB",
    "wof:name":"BB1 9DQ",
    "wof:placetype":"postalcode"
},
  "geometry": {"coordinates":[-2.49074847871375,53.77868978913234],"type":"Point"}
}