{
  "type": "Feature",
  "properties": {
    "date:inception_lower": "1980-01-01",
    "date:inception_upper": "1980-01-01",
    "iso:country": "GB",
    "wof:name": "BB1 9DQ",
    "wof:placetype": "postalcode"
  },
  "geometry": {"coordinates":[-2.490748,53.77869],"type":"Point"}
}
