{
  "type": "Feature",
  "properties": {
    "date:inception_lower": "1980-01-01",
    "date:inception_upper": "1980-01-01",
    "iso:country": "GB",
    "wof:name": "BB1 9DQ",
    "wof:placetype": "postalcode"
  },
  "geometry": {"coordinates":[-2.489913,53.777476],"type":"Point"}
}
