{
  "type": "Feature",
  "properties": {
    "iso:country": "GB",
    "wof:name": "LN12 1FR",
    "wof:placetype": "postalcode"
  },
  "geometry": {"coordinates":[0.254886,53.336447],"type":"Point"}
}
