{
  "type": "Feature",
  "properties": {
    "iso:country": "GB",
    "wof:name": "EX4 2HW",
    "wof:placetype": "postalcode"
  },
  "geometry": {"coordinates":[-3.622708,50.734643],"type":"Point"}
}
