{
  "type": "Feature",
  "properties": {
    "iso:country":"GB",
    "wof:name":"EX4 2HW",
    "wof:placetype":"postalcode"
},
  "geometry": {"coordinates":[-3.62270781510411,50.73464276813652],"type":"Point"}
}