{
  "type": "Feature",
  "properties": {
    "iso:country": "GB",
    "wof:name": "EH6 6HB",
    "wof:placetype": "postalcode"
  },
  "geometry": {"coordinates":[-3.175228,55.976327],"type":"Point"}
}
