{
  "type": "Feature",
  "properties": {
    "iso:country": "GB",
    "wof:name": "EN9 2SF",
    "wof:placetype": "postalcode"
  },
  "geometry": {"coordinates":[0.044049,51.720645],"type":"Point"}
}
