{
  "type": "Feature",
  "properties": {
    "iso:country":"GB",
    "wof:name":"EN9 2SF",
    "wof:placetype":"postalcode"
},
  "geometry": {"coordinates":[0.04386179107637,51.7212456267809],"type":"Point"}
}