{
  "type": "Feature",
  "properties": {
    "date:inception_lower":"2006-01-01",
    "date:inception_upper":"2006-01-31",
    "iso:country":"GB",
    "wof:name":"KT6 4SQ",
    "wof:placetype":"postalcode"
},
  "geometry": {"coordinates":[-0.300224,51.396423],"type":"Point"}
}