{
  "type": "Feature",
  "properties": {
    "iso:country":"GB",
    "wof:name":"KT6 4SQ",
    "wof:placetype":"postalcode"
},
  "geometry": {"coordinates":[-0.30024822166659,51.3963879090503],"type":"Point"}
}