{
  "type": "Feature",
  "properties": {
    "iso:country": "GB",
    "wof:name": "KT6 4SQ",
    "wof:placetype": "postalcode"
  },
  "geometry": {"coordinates":[-0.300224,51.396423],"type":"Point"}
}
