{
  "type": "Feature",
  "properties": {
    "iso:country":"GB",
    "wof:name":"SO23 9QU",
    "wof:placetype":"postalcode"
},
  "geometry": {"coordinates":[-1.32241041092046,51.05164104331644],"type":"Point"}
}