{
  "type": "Feature",
  "properties": {
    "iso:country": "GB",
    "wof:name": "SO23 9QU",
    "wof:placetype": "postalcode"
  },
  "geometry": {"coordinates":[-1.32241,51.051641],"type":"Point"}
}
