{
  "type": "Feature",
  "properties": {
    "iso:country": "GB",
    "wof:name": "CV1 5BA",
    "wof:placetype": "postalcode"
  },
  "geometry": {"coordinates":[-1.490925,52.41636],"type":"Point"}
}
