{
  "type": "Feature",
  "properties": {
    "iso:country":"GB",
    "wof:name":"PR2 3SF",
    "wof:placetype":"postalcode"
},
  "geometry": {"coordinates":[-2.72354381062122,53.77749251395579],"type":"Point"}
}