{
  "type": "Feature",
  "properties": {
    "date:inception_lower": "1980-01-01",
    "date:inception_upper": "1980-01-01",
    "iso:country": "GB",
    "wof:name": "BA14 7BH",
    "wof:placetype": "postalcode"
  },
  "geometry": {"coordinates":[-2.199189,51.318256],"type":"Point"}
}
