{
  "type": "Feature",
  "properties": {
    "iso:country":"GB",
    "wof:name":"BA14 7BH",
    "wof:placetype":"postalcode"
},
  "geometry": {"coordinates":[-2.19918869643865,51.3182555934039],"type":"Point"}
}