{
  "type": "Feature",
  "properties": {
    "iso:country": "GB",
    "wof:name": "BA14 7BH",
    "wof:placetype": "postalcode"
  },
  "geometry": {"coordinates":[-2.199189,51.318256],"type":"Point"}
}
