{
  "type": "Feature",
  "properties": {
    "iso:country":"GB",
    "wof:name":"TD9 8TD",
    "wof:placetype":"postalcode"
},
  "geometry": {"coordinates":[-2.64037940981213,55.44809450618987],"type":"Point"}
}