{
  "type": "Feature",
  "properties": {
    "iso:country":"GB",
    "wof:name":"CF81 8QZ",
    "wof:placetype":"postalcode"
},
  "geometry": {"coordinates":[-3.22967644045933,51.69166013368912],"type":"Point"}
}