{
  "type": "Feature",
  "properties": {
    "iso:country":"GB",
    "wof:name":"NW10 9EH",
    "wof:placetype":"postalcode"
},
  "geometry": {"coordinates":[-0.25468535046591,51.54338303862298],"type":"Point"}
}