{
  "type": "Feature",
  "properties": {
    "iso:country": "GB",
    "wof:name": "NW10 9EH",
    "wof:placetype": "postalcode"
  },
  "geometry": {"coordinates":[-0.254685,51.543383],"type":"Point"}
}
