{
  "type": "Feature",
  "properties": {
    "date:inception_lower": "2008-04-01",
    "date:inception_upper": "2008-04-01",
    "iso:country": "GB",
    "wof:name": "SN15 4AT",
    "wof:placetype": "postalcode"
  },
  "geometry": {"coordinates":[-2.010371,51.543359],"type":"Point"}
}
