{
  "type": "Feature",
  "properties": {
    "iso:country":"GB",
    "wof:name":"SN15 4AT",
    "wof:placetype":"postalcode"
},
  "geometry": {"coordinates":[-2.00756516323497,51.54240519268446],"type":"Point"}
}