{
  "type": "Feature",
  "properties": {
    "date:inception_lower":"1980-01-01",
    "date:inception_upper":"1980-01-31",
    "iso:country":"GB",
    "wof:name":"ST17 9PN",
    "wof:placetype":"postalcode"
},
  "geometry": {"coordinates":[-2.122301,52.782125],"type":"Point"}
}