{
  "type": "Feature",
  "properties": {
    "iso:country":"GB",
    "wof:name":"ST17 9PN",
    "wof:placetype":"postalcode"
},
  "geometry": {"coordinates":[-2.12230077019039,52.78212458241118],"type":"Point"}
}