{
  "type": "Feature",
  "properties": {
    "iso:country": "GB",
    "wof:name": "ST17 9PN",
    "wof:placetype": "postalcode"
  },
  "geometry": {"coordinates":[-2.122301,52.782125],"type":"Point"}
}
