{
  "type": "Feature",
  "properties": {
    "iso:country":"GB",
    "wof:name":"W1J 6PD",
    "wof:placetype":"postalcode"
},
  "geometry": {"coordinates":[-0.14586218358432,51.51070757403976],"type":"Point"}
}