{
  "type": "Feature",
  "properties": {
    "iso:country": "GB",
    "wof:name": "SK4 2PA",
    "wof:placetype": "postalcode"
  },
  "geometry": {"coordinates":[-2.17391,53.421961],"type":"Point"}
}
