{
  "type": "Feature",
  "properties": {
    "iso:country":"GB",
    "wof:name":"OX7 5DJ",
    "wof:placetype":"postalcode"
},
  "geometry": {"coordinates":[-1.54584481621544,51.9375702043001],"type":"Point"}
}