{
  "type": "Feature",
  "properties": {
    "iso:country":"GB",
    "wof:name":"S75 4BE",
    "wof:placetype":"postalcode"
},
  "geometry": {"coordinates":[-1.58855063458906,53.58666063999188],"type":"Point"}
}