{
  "type": "Feature",
  "properties": {
    "iso:country": "GB",
    "wof:name": "BN14 9LJ",
    "wof:placetype": "postalcode"
  },
  "geometry": {"coordinates":[-0.373528,50.829216],"type":"Point"}
}
