{
  "type": "Feature",
  "properties": {
    "date:inception_lower": "2016-07-01",
    "date:inception_upper": "2016-07-01",
    "iso:country": "GB",
    "wof:name": "MK42 9EN",
    "wof:placetype": "postalcode"
  },
  "geometry": {"coordinates":[-0.466622,52.129352],"type":"Point"}
}
