{
  "type": "Feature",
  "properties": {
    "iso:country": "GB",
    "wof:name": "MK42 9EN",
    "wof:placetype": "postalcode"
  },
  "geometry": {"coordinates":[-0.466622,52.129352],"type":"Point"}
}
