{
  "type": "Feature",
  "properties": {
    "iso:country":"GB",
    "wof:name":"M34 2BH",
    "wof:placetype":"postalcode"
},
  "geometry": {"coordinates":[-2.11785185035468,53.45223146198759],"type":"Point"}
}