{
  "type": "Feature",
  "properties": {
    "iso:country": "GB",
    "wof:name": "NN18 8GJ",
    "wof:placetype": "postalcode"
  },
  "geometry": {"coordinates":[-0.673788,52.473547],"type":"Point"}
}
