{
  "type": "Feature",
  "properties": {
    "iso:country":"GB",
    "wof:name":"HU13 9BA",
    "wof:placetype":"postalcode"
},
  "geometry": {"coordinates":[-0.42829121605766,53.7328557259189],"type":"Point"}
}