{
  "type": "Feature",
  "properties": {
    "iso:country": "GB",
    "wof:name": "HU13 9BA",
    "wof:placetype": "postalcode"
  },
  "geometry": {"coordinates":[-0.428291,53.732856],"type":"Point"}
}
