{
  "type": "Feature",
  "properties": {
    "iso:country":"GB",
    "wof:name":"BN3 3LN",
    "wof:placetype":"postalcode"
},
  "geometry": {"coordinates":[-0.17397500859217,50.83467257456595],"type":"Point"}
}