{
  "type": "Feature",
  "properties": {
    "iso:country":"GB",
    "wof:name":"NE6 5AR",
    "wof:placetype":"postalcode"
},
  "geometry": {"coordinates":[-1.59257793242377,54.97985843269026],"type":"Point"}
}