{
  "type": "Feature",
  "properties": {
    "iso:country":"GB",
    "wof:name":"IG1 2UG",
    "wof:placetype":"postalcode"
},
  "geometry": {"coordinates":[0.08366247957391,51.55098170733889],"type":"Point"}
}