{
  "type": "Feature",
  "properties": {
    "date:inception_lower":"1980-01-01",
    "date:inception_upper":"1980-01-31",
    "iso:country":"GB",
    "wof:name":"ME3 0EB",
    "wof:placetype":"postalcode"
},
  "geometry": {"coordinates":[0.714731,51.453271],"type":"Point"}
}