{
  "type": "Feature",
  "properties": {
    "iso:country":"GB",
    "wof:name":"ME3 0EB",
    "wof:placetype":"postalcode"
},
  "geometry": {"coordinates":[0.71473101058517,51.45327069516846],"type":"Point"}
}