{
  "type": "Feature",
  "properties": {
    "iso:country":"GB",
    "wof:name":"GL51 7BD",
    "wof:placetype":"postalcode"
},
  "geometry": {"coordinates":[-2.10691368687419,51.89664295467819],"type":"Point"}
}