{
  "type": "Feature",
  "properties": {
    "iso:country":"GB",
    "wof:name":"FK2 9JE",
    "wof:placetype":"postalcode"
},
  "geometry": {"coordinates":[-3.74932481903847,55.99289756845409],"type":"Point"}
}