{
  "type": "Feature",
  "properties": {
    "iso:country":"GB",
    "wof:name":"NW11 8SP",
    "wof:placetype":"postalcode"
},
  "geometry": {"coordinates":[-0.21066072274793,51.56350122826731],"type":"Point"}
}