{
  "type": "Feature",
  "properties": {
    "date:inception_lower": "2015-12-01",
    "date:inception_upper": "2015-12-01",
    "iso:country": "GB",
    "wof:name": "CH7 1XQ",
    "wof:placetype": "postalcode"
  },
  "geometry": {"coordinates":[-3.148801,53.167116],"type":"Point"}
}
