{
  "type": "Feature",
  "properties": {
    "iso:country": "GB",
    "wof:name": "CH7 1XQ",
    "wof:placetype": "postalcode"
  },
  "geometry": {"coordinates":[-3.148801,53.167116],"type":"Point"}
}
