{
  "type": "Feature",
  "properties": {
    "iso:country":"GB",
    "wof:name":"CH7 1XQ",
    "wof:placetype":"postalcode"
},
  "geometry": {"coordinates":[-3.14912282176475,53.16738512232085],"type":"Point"}
}