{
  "type": "Feature",
  "properties": {
    "iso:country":"GB",
    "wof:name":"M24 5TP",
    "wof:placetype":"postalcode"
},
  "geometry": {"coordinates":[-2.20126171144013,53.55128911895144],"type":"Point"}
}