{
  "type": "Feature",
  "properties": {
    "iso:country":"GB",
    "wof:name":"RH19 1EP",
    "wof:placetype":"postalcode"
},
  "geometry": {"coordinates":[-0.01068047654485,51.12632912246873],"type":"Point"}
}