{
  "type": "Feature",
  "properties": {
    "iso:country":"GB",
    "wof:name":"CR4 2JE",
    "wof:placetype":"postalcode"
},
  "geometry": {"coordinates":[-0.15913371540055,51.40770002275274],"type":"Point"}
}