{
  "type": "Feature",
  "properties": {
    "iso:country": "GB",
    "wof:name": "SA42 0QY",
    "wof:placetype": "postalcode"
  },
  "geometry": {"coordinates":[-4.858167,52.00457],"type":"Point"}
}
