{
  "type": "Feature",
  "properties": {
    "date:inception_lower": "2024-04-01",
    "date:inception_upper": "2024-04-01",
    "iso:country": "GB",
    "wof:name": "WD19 7FT",
    "wof:placetype": "postalcode"
  },
  "geometry": {"coordinates":[-0.387237,51.627373],"type":"Point"}
}
