{
  "type": "Feature",
  "properties": {
    "iso:country":"GB",
    "wof:name":"BS30 5LL",
    "wof:placetype":"postalcode"
},
  "geometry": {"coordinates":[-2.46801799522003,51.45029684251924],"type":"Point"}
}