{
  "type": "Feature",
  "properties": {
    "iso:country":"GB",
    "wof:name":"CT19 6AX",
    "wof:placetype":"postalcode"
},
  "geometry": {"coordinates":[1.19239592354387,51.08381795464616],"type":"Point"}
}