{
  "type": "Feature",
  "properties": {
    "iso:country": "GB",
    "wof:name": "CT19 6AX",
    "wof:placetype": "postalcode"
  },
  "geometry": {"coordinates":[1.192396,51.083818],"type":"Point"}
}
