{
  "type": "Feature",
  "properties": {
    "date:inception_lower": "1980-01-01",
    "date:inception_upper": "1980-01-01",
    "iso:country": "GB",
    "wof:name": "S72 0AF",
    "wof:placetype": "postalcode"
  },
  "geometry": {"coordinates":[-1.356495,53.558484],"type":"Point"}
}
