{
  "type": "Feature",
  "properties": {
    "iso:country":"GB",
    "wof:name":"S72 0AF",
    "wof:placetype":"postalcode"
},
  "geometry": {"coordinates":[-1.35649506613217,53.5584839954094],"type":"Point"}
}