{
  "type": "Feature",
  "properties": {
    "iso:country":"GB",
    "wof:name":"DD9 6ER",
    "wof:placetype":"postalcode"
},
  "geometry": {"coordinates":[-2.66041424011888,56.73177714480506],"type":"Point"}
}