{
  "type": "Feature",
  "properties": {
    "iso:country": "GB",
    "wof:name": "PE20 3EY",
    "wof:placetype": "postalcode"
  },
  "geometry": {"coordinates":[-0.143718,52.950908],"type":"Point"}
}
