{
  "type": "Feature",
  "properties": {
    "iso:country": "GB",
    "wof:name": "WV4 6BP",
    "wof:placetype": "postalcode"
  },
  "geometry": {"coordinates":[-2.110604,52.560397],"type":"Point"}
}
