{
  "type": "Feature",
  "properties": {
    "iso:country":"GB",
    "wof:name":"CV32 5JX",
    "wof:placetype":"postalcode"
},
  "geometry": {"coordinates":[-1.53770023225426,52.29201946979229],"type":"Point"}
}