{
  "type": "Feature",
  "properties": {
    "iso:country": "GB",
    "wof:name": "CV32 5JX",
    "wof:placetype": "postalcode"
  },
  "geometry": {"coordinates":[-1.537689,52.292034],"type":"Point"}
}
