{
  "type": "Feature",
  "properties": {
    "date:inception_lower": "1994-05-01",
    "date:inception_upper": "1994-05-01",
    "iso:country": "GB",
    "wof:name": "L39 8TF",
    "wof:placetype": "postalcode"
  },
  "geometry": {"coordinates":[-2.942493,53.594824],"type":"Point"}
}
