{
  "type": "Feature",
  "properties": {
    "date:inception_lower":"1994-05-01",
    "date:inception_upper":"1994-05-31",
    "iso:country":"GB",
    "wof:name":"L39 8TF",
    "wof:placetype":"postalcode"
},
  "geometry": {"coordinates":[-2.942143,53.594692],"type":"Point"}
}