{
  "type": "Feature",
  "properties": {
    "iso:country": "GB",
    "wof:name": "SO32 3LP",
    "wof:placetype": "postalcode"
  },
  "geometry": {"coordinates":[-1.176979,50.987719],"type":"Point"}
}
