{
  "type": "Feature",
  "properties": {
    "date:inception_lower": "1994-12-01",
    "date:inception_upper": "1994-12-01",
    "iso:country": "GB",
    "wof:name": "SO32 3LP",
    "wof:placetype": "postalcode"
  },
  "geometry": {"coordinates":[-1.176979,50.987719],"type":"Point"}
}
