{
  "type": "Feature",
  "properties": {
    "iso:country":"GB",
    "wof:name":"SW7 2AP",
    "wof:placetype":"postalcode"
},
  "geometry": {"coordinates":[-0.17754000248893,51.50126739084927],"type":"Point"}
}