{
  "type": "Feature",
  "properties": {
    "iso:country":"GB",
    "wof:name":"TD15 2BT",
    "wof:placetype":"postalcode"
},
  "geometry": {"coordinates":[-2.01498213768064,55.75319357646514],"type":"Point"}
}