{
  "type": "Feature",
  "properties": {
    "iso:country":"GB",
    "wof:name":"SM1 4HZ",
    "wof:placetype":"postalcode"
},
  "geometry": {"coordinates":[-0.18099477749728,51.3669720206687],"type":"Point"}
}