{
  "type": "Feature",
  "properties": {
    "iso:country":"GB",
    "wof:name":"WN7 4TZ",
    "wof:placetype":"postalcode"
},
  "geometry": {"coordinates":[-2.54464654973157,53.49793159580002],"type":"Point"}
}