{
  "type": "Feature",
  "properties": {
    "date:inception_lower": "2014-09-01",
    "date:inception_upper": "2014-09-01",
    "iso:country": "GB",
    "wof:name": "E2 0FG",
    "wof:placetype": "postalcode"
  },
  "geometry": {"coordinates":[-0.041102,51.528267],"type":"Point"}
}
