{
  "type": "Feature",
  "properties": {
    "iso:country":"GB",
    "wof:name":"E2 0FG",
    "wof:placetype":"postalcode"
},
  "geometry": {"coordinates":[-0.04110234641656,51.52826680782943],"type":"Point"}
}