{
  "type": "Feature",
  "properties": {
    "iso:country":"GB",
    "wof:name":"CH46 9QD",
    "wof:placetype":"postalcode"
},
  "geometry": {"coordinates":[-3.10736271657494,53.40077211942936],"type":"Point"}
}