{
  "type": "Feature",
  "properties": {
    "iso:country": "GB",
    "wof:name": "CH46 9QD",
    "wof:placetype": "postalcode"
  },
  "geometry": {"coordinates":[-3.107363,53.400772],"type":"Point"}
}
