{
  "type": "Feature",
  "properties": {
    "iso:country":"GB",
    "wof:name":"ST15 8UF",
    "wof:placetype":"postalcode"
},
  "geometry": {"coordinates":[-2.13517533594979,52.91755387378484],"type":"Point"}
}