{
  "type": "Feature",
  "properties": {
    "iso:country":"GB",
    "wof:name":"NE40 3HS",
    "wof:placetype":"postalcode"
},
  "geometry": {"coordinates":[-1.75280303435654,54.97032349210938],"type":"Point"}
}