{
  "type": "Feature",
  "properties": {
    "iso:country": "GB",
    "wof:name": "NE40 3HS",
    "wof:placetype": "postalcode"
  },
  "geometry": {"coordinates":[-1.753084,54.970315],"type":"Point"}
}
