{
  "type": "Feature",
  "properties": {
    "iso:country":"GB",
    "wof:name":"EH22 4RN",
    "wof:placetype":"postalcode"
},
  "geometry": {"coordinates":[-3.06841447560657,55.87076016893789],"type":"Point"}
}