{
  "type": "Feature",
  "properties": {
    "iso:country": "GB",
    "wof:name": "EH22 4RN",
    "wof:placetype": "postalcode"
  },
  "geometry": {"coordinates":[-3.068498,55.870773],"type":"Point"}
}
