{
  "type": "Feature",
  "properties": {
    "date:inception_lower": "2020-04-01",
    "date:inception_upper": "2020-04-01",
    "iso:country": "GB",
    "wof:name": "HG3 1FL",
    "wof:placetype": "postalcode"
  },
  "geometry": {"coordinates":[-1.566418,53.982153],"type":"Point"}
}
