{
  "type": "Feature",
  "properties": {
    "iso:country": "GB",
    "wof:name": "HG3 1FL",
    "wof:placetype": "postalcode"
  },
  "geometry": {"coordinates":[-1.567119,53.982173],"type":"Point"}
}
