{
  "type": "Feature",
  "properties": {
    "iso:country": "GB",
    "wof:name": "GU22 9AZ",
    "wof:placetype": "postalcode"
  },
  "geometry": {"coordinates":[-0.555309,51.298835],"type":"Point"}
}
