{
  "type": "Feature",
  "properties": {
    "iso:country":"GB",
    "wof:name":"CM3 4XA",
    "wof:placetype":"postalcode"
},
  "geometry": {"coordinates":[0.58337177208474,51.69134625132609],"type":"Point"}
}