{
  "type": "Feature",
  "properties": {
    "date:inception_lower": "2005-03-01",
    "date:inception_upper": "2005-03-01",
    "iso:country": "GB",
    "wof:name": "L24 9LP",
    "wof:placetype": "postalcode"
  },
  "geometry": {"coordinates":[-2.857502,53.355646],"type":"Point"}
}
