{
  "type": "Feature",
  "properties": {
    "date:inception_lower":"1980-01-01",
    "date:inception_upper":"1980-01-31",
    "iso:country":"GB",
    "wof:name":"BN2 3AD",
    "wof:placetype":"postalcode"
},
  "geometry": {"coordinates":[-0.125693,50.834225],"type":"Point"}
}