{
  "type": "Feature",
  "properties": {
    "iso:country": "GB",
    "wof:name": "DG11 1TU",
    "wof:placetype": "postalcode"
  },
  "geometry": {"coordinates":[-3.512112,55.193235],"type":"Point"}
}
