{
  "type": "Feature",
  "properties": {
    "iso:country":"GB",
    "wof:name":"TA2 6RX",
    "wof:placetype":"postalcode"
},
  "geometry": {"coordinates":[-3.13874140651138,51.02667827133856],"type":"Point"}
}