{
  "type": "Feature",
  "properties": {
    "date:inception_lower": "2009-06-01",
    "date:inception_upper": "2009-06-01",
    "iso:country": "GB",
    "wof:name": "TW20 0AW",
    "wof:placetype": "postalcode"
  },
  "geometry": {"coordinates":[-0.569075,51.429302],"type":"Point"}
}
