{
  "type": "Feature",
  "properties": {
    "iso:country":"GB",
    "wof:name":"BB1 1TS",
    "wof:placetype":"postalcode"
},
  "geometry": {"coordinates":[-2.45976380143113,53.74284229819364],"type":"Point"}
}