{
  "type": "Feature",
  "properties": {
    "iso:country":"GB",
    "wof:name":"ST5 6SH",
    "wof:placetype":"postalcode"
},
  "geometry": {"coordinates":[-2.2544510472201,53.01406430311505],"type":"Point"}
}