{
  "type": "Feature",
  "properties": {
    "date:inception_lower": "1980-01-01",
    "date:inception_upper": "1980-01-01",
    "iso:country": "GB",
    "wof:name": "BD21 4EL",
    "wof:placetype": "postalcode"
  },
  "geometry": {"coordinates":[-1.888917,53.875248],"type":"Point"}
}
