{
  "type": "Feature",
  "properties": {
    "iso:country":"GB",
    "wof:name":"WA5 3NU",
    "wof:placetype":"postalcode"
},
  "geometry": {"coordinates":[-2.66320294202801,53.39514925277273],"type":"Point"}
}