{
  "type": "Feature",
  "properties": {
    "iso:country": "GB",
    "wof:name": "WA5 3NU",
    "wof:placetype": "postalcode"
  },
  "geometry": {"coordinates":[-2.663203,53.395149],"type":"Point"}
}
