{
  "type": "Feature",
  "properties": {
    "date:inception_lower": "1994-02-01",
    "date:inception_upper": "1994-02-01",
    "iso:country": "GB",
    "wof:name": "EH17 8UL",
    "wof:placetype": "postalcode"
  },
  "geometry": {"coordinates":[-3.149193,55.898651],"type":"Point"}
}
