{
  "type": "Feature",
  "properties": {
    "iso:country":"GB",
    "wof:name":"EH17 8UL",
    "wof:placetype":"postalcode"
},
  "geometry": {"coordinates":[-3.14919272774639,55.89865121314799],"type":"Point"}
}