{
  "type": "Feature",
  "properties": {
    "date:inception_lower": "2005-10-01",
    "date:inception_upper": "2005-10-01",
    "iso:country": "GB",
    "wof:name": "IP5 2HB",
    "wof:placetype": "postalcode"
  },
  "geometry": {"coordinates":[1.235644,52.057437],"type":"Point"}
}
