{
  "type": "Feature",
  "properties": {
    "iso:country": "GB",
    "wof:name": "S80 2LR",
    "wof:placetype": "postalcode"
  },
  "geometry": {"coordinates":[-1.114138,53.302237],"type":"Point"}
}
