{
  "type": "Feature",
  "properties": {
    "iso:country":"GB",
    "wof:name":"BR6 7BP",
    "wof:placetype":"postalcode"
},
  "geometry": {"coordinates":[0.06587412048761,51.35995578611006],"type":"Point"}
}