{
  "type": "Feature",
  "properties": {
    "iso:country":"GB",
    "wof:name":"TS22 5AH",
    "wof:placetype":"postalcode"
},
  "geometry": {"coordinates":[-1.30053084747662,54.60623879101472],"type":"Point"}
}