{
  "type": "Feature",
  "properties": {
    "iso:country": "GB",
    "wof:name": "SE24 0EN",
    "wof:placetype": "postalcode"
  },
  "geometry": {"coordinates":[-0.104764,51.454701],"type":"Point"}
}
