{
  "type": "Feature",
  "properties": {
    "iso:country":"GB",
    "wof:name":"SE24 0EN",
    "wof:placetype":"postalcode"
},
  "geometry": {"coordinates":[-0.10484309864189,51.45454067649094],"type":"Point"}
}