{
  "type": "Feature",
  "properties": {
    "iso:country":"GB",
    "wof:name":"SG13 7TZ",
    "wof:placetype":"postalcode"
},
  "geometry": {"coordinates":[-0.05898416530568,51.79611490088823],"type":"Point"}
}