{
  "type": "Feature",
  "properties": {
    "iso:country":"GB",
    "wof:name":"SE9 5JX",
    "wof:placetype":"postalcode"
},
  "geometry": {"coordinates":[0.03878773653783,51.45250833301559],"type":"Point"}
}