{
  "type": "Feature",
  "properties": {
    "date:inception_lower":"1985-04-01",
    "date:inception_upper":"1985-04-30",
    "iso:country":"GB",
    "wof:name":"PR1 7JD",
    "wof:placetype":"postalcode"
},
  "geometry": {"coordinates":[-2.709364,53.768317],"type":"Point"}
}