{
  "type": "Feature",
  "properties": {
    "iso:country": "GB",
    "wof:name": "PR1 7JD",
    "wof:placetype": "postalcode"
  },
  "geometry": {"coordinates":[-2.709364,53.768317],"type":"Point"}
}
