{
  "type": "Feature",
  "properties": {
    "iso:country": "GB",
    "wof:name": "NE2 3QY",
    "wof:placetype": "postalcode"
  },
  "geometry": {"coordinates":[-1.606731,54.999205],"type":"Point"}
}
