{
  "type": "Feature",
  "properties": {
    "iso:country":"GB",
    "wof:name":"NE2 3QY",
    "wof:placetype":"postalcode"
},
  "geometry": {"coordinates":[-1.6067329421718,54.99913554606678],"type":"Point"}
}