{
  "type": "Feature",
  "properties": {
    "date:inception_lower": "1991-09-01",
    "date:inception_upper": "1991-09-01",
    "iso:country": "GB",
    "wof:name": "LS11 8JH",
    "wof:placetype": "postalcode"
  },
  "geometry": {"coordinates":[-1.572233,53.763366],"type":"Point"}
}
