{
  "type": "Feature",
  "properties": {
    "iso:country":"GB",
    "wof:name":"LS11 8JH",
    "wof:placetype":"postalcode"
},
  "geometry": {"coordinates":[-1.57223332225667,53.76336569177525],"type":"Point"}
}