{
  "type": "Feature",
  "properties": {
    "iso:country": "GB",
    "wof:name": "PO22 8NW",
    "wof:placetype": "postalcode"
  },
  "geometry": {"coordinates":[-0.6405,50.803162],"type":"Point"}
}
