{
  "type": "Feature",
  "properties": {
    "iso:country":"GB",
    "wof:name":"PO22 8NW",
    "wof:placetype":"postalcode"
},
  "geometry": {"coordinates":[-0.64049980716537,50.80316187730479],"type":"Point"}
}