{
  "type": "Feature",
  "properties": {
    "iso:country":"GB",
    "wof:name":"BB9 7JR",
    "wof:placetype":"postalcode"
},
  "geometry": {"coordinates":[-2.21516471613141,53.83645829010273],"type":"Point"}
}