{
  "type": "Feature",
  "properties": {
    "date:inception_lower": "1998-12-01",
    "date:inception_upper": "1998-12-01",
    "iso:country": "GB",
    "wof:name": "EC1A 9BW",
    "wof:placetype": "postalcode"
  },
  "geometry": {"coordinates":[-0.103014,51.517387],"type":"Point"}
}
