{
  "type": "Feature",
  "properties": {
    "iso:country":"GB",
    "wof:name":"EC1A 9BW",
    "wof:placetype":"postalcode"
},
  "geometry": {"coordinates":[-0.1030138232831,51.51738726180874],"type":"Point"}
}