{
  "type": "Feature",
  "properties": {
    "iso:country":"GB",
    "wof:name":"CO4 9QH",
    "wof:placetype":"postalcode"
},
  "geometry": {"coordinates":[0.92640542095037,51.92315122595001],"type":"Point"}
}