{
  "type": "Feature",
  "properties": {
    "iso:country":"GB",
    "wof:name":"SN9 6JS",
    "wof:placetype":"postalcode"
},
  "geometry": {"coordinates":[-1.81058811113553,51.31044986016789],"type":"Point"}
}