{
  "type": "Feature",
  "properties": {
    "date:inception_lower":"1980-01-01",
    "date:inception_upper":"1980-01-31",
    "iso:country":"GB",
    "wof:name":"WN2 5NY",
    "wof:placetype":"postalcode"
},
  "geometry": {"coordinates":[-2.591996,53.520672],"type":"Point"}
}