{
  "type": "Feature",
  "properties": {
    "iso:country":"GB",
    "wof:name":"WN2 5NY",
    "wof:placetype":"postalcode"
},
  "geometry": {"coordinates":[-2.59199625274798,53.52067207107766],"type":"Point"}
}