{
  "type": "Feature",
  "properties": {
    "iso:country":"GB",
    "wof:name":"PO21 1JJ",
    "wof:placetype":"postalcode"
},
  "geometry": {"coordinates":[-0.66038689623585,50.78711450083546],"type":"Point"}
}