{
  "type": "Feature",
  "properties": {
    "iso:country": "GB",
    "wof:name": "WA7 5NB",
    "wof:placetype": "postalcode"
  },
  "geometry": {"coordinates":[-2.707327,53.329026],"type":"Point"}
}
