{
  "type": "Feature",
  "properties": {
    "iso:country":"GB",
    "wof:name":"WA7 5NB",
    "wof:placetype":"postalcode"
},
  "geometry": {"coordinates":[-2.7073269498038,53.32902591456841],"type":"Point"}
}