{
  "type": "Feature",
  "properties": {
    "date:inception_lower": "2023-03-01",
    "date:inception_upper": "2023-03-01",
    "iso:country": "GB",
    "wof:name": "NE40 3DD",
    "wof:placetype": "postalcode"
  },
  "geometry": {"coordinates":[-1.75787,54.96636],"type":"Point"}
}
