{
  "type": "Feature",
  "properties": {
    "date:inception_lower": "2000-06-01",
    "date:inception_upper": "2000-06-01",
    "iso:country": "GB",
    "wof:name": "FK14 7JF",
    "wof:placetype": "postalcode"
  },
  "geometry": {"coordinates":[-3.613919,56.187546],"type":"Point"}
}
