{
  "type": "Feature",
  "properties": {
    "iso:country":"GB",
    "wof:name":"FK14 7JF",
    "wof:placetype":"postalcode"
},
  "geometry": {"coordinates":[-3.61391911915074,56.18754602925237],"type":"Point"}
}