{
  "type": "Feature",
  "properties": {
    "iso:country":"GB",
    "wof:name":"NG31 7TP",
    "wof:placetype":"postalcode"
},
  "geometry": {"coordinates":[-0.62367748334529,52.90999460049006],"type":"Point"}
}