{
  "type": "Feature",
  "properties": {
    "iso:country": "GB",
    "wof:name": "NG31 7TP",
    "wof:placetype": "postalcode"
  },
  "geometry": {"coordinates":[-0.623677,52.909995],"type":"Point"}
}
