{
  "type": "Feature",
  "properties": {
    "iso:country":"GB",
    "wof:name":"B80 7JS",
    "wof:placetype":"postalcode"
},
  "geometry": {"coordinates":[-1.90552193415484,52.27005034992106],"type":"Point"}
}