{
  "type": "Feature",
  "properties": {
    "iso:country": "GB",
    "wof:name": "B80 7JS",
    "wof:placetype": "postalcode"
  },
  "geometry": {"coordinates":[-1.905522,52.27005],"type":"Point"}
}
