{
  "type": "Feature",
  "properties": {
    "date:inception_lower": "1980-01-01",
    "date:inception_upper": "1980-01-01",
    "iso:country": "GB",
    "wof:name": "B80 7JS",
    "wof:placetype": "postalcode"
  },
  "geometry": {"coordinates":[-1.905514,52.270065],"type":"Point"}
}
