{
  "type": "Feature",
  "properties": {
    "iso:country": "GB",
    "wof:name": "NN14 1LH",
    "wof:placetype": "postalcode"
  },
  "geometry": {"coordinates":[-0.834648,52.392759],"type":"Point"}
}
