{
  "type": "Feature",
  "properties": {
    "date:inception_lower":"1983-03-01",
    "date:inception_upper":"1983-03-31",
    "iso:country":"GB",
    "wof:name":"NN14 1LH",
    "wof:placetype":"postalcode"
},
  "geometry": {"coordinates":[-0.834648,52.392759],"type":"Point"}
}