{
  "type": "Feature",
  "properties": {
    "iso:country":"GB",
    "wof:name":"PL6 8TN",
    "wof:placetype":"postalcode"
},
  "geometry": {"coordinates":[-4.10158891338016,50.40900622340342],"type":"Point"}
}