{
  "type": "Feature",
  "properties": {
    "date:inception_lower":"1994-05-01",
    "date:inception_upper":"1994-05-31",
    "iso:country":"GB",
    "wof:name":"M8 0GH",
    "wof:placetype":"postalcode"
},
  "geometry": {"coordinates":[-2.231166,53.507812],"type":"Point"}
}