{
  "type": "Feature",
  "properties": {
    "date:inception_lower":"1980-01-01",
    "date:inception_upper":"1980-01-31",
    "iso:country":"GB",
    "wof:name":"NG17 9BG",
    "wof:placetype":"postalcode"
},
  "geometry": {"coordinates":[-1.246227,53.077275],"type":"Point"}
}