{
  "type": "Feature",
  "properties": {
    "iso:country":"GB",
    "wof:name":"YO8 8ES",
    "wof:placetype":"postalcode"
},
  "geometry": {"coordinates":[-1.02638929502783,53.75133186459907],"type":"Point"}
}