{
  "type": "Feature",
  "properties": {
    "iso:country":"GB",
    "wof:name":"NE61 5PR",
    "wof:placetype":"postalcode"
},
  "geometry": {"coordinates":[-1.61976247608308,55.241081238179],"type":"Point"}
}