{
  "type": "Feature",
  "properties": {
    "date:inception_lower":"2002-11-01",
    "date:inception_upper":"2002-11-30",
    "iso:country":"GB",
    "wof:name":"NE61 5PR",
    "wof:placetype":"postalcode"
},
  "geometry": {"coordinates":[-1.619762,55.241081],"type":"Point"}
}