{
  "type": "Feature",
  "properties": {
    "iso:country":"GB",
    "wof:name":"ST16 2TU",
    "wof:placetype":"postalcode"
},
  "geometry": {"coordinates":[-2.12891765884473,52.80869047274247],"type":"Point"}
}