{
  "type": "Feature",
  "properties": {
    "date:inception_lower": "1980-01-01",
    "date:inception_upper": "1980-01-01",
    "iso:country": "GB",
    "wof:name": "ST17 4QG",
    "wof:placetype": "postalcode"
  },
  "geometry": {"coordinates":[-2.085696,52.789798],"type":"Point"}
}
