{
  "type": "Feature",
  "properties": {
    "iso:country":"GB",
    "wof:name":"ST17 4QG",
    "wof:placetype":"postalcode"
},
  "geometry": {"coordinates":[-2.08569599577132,52.78979781444183],"type":"Point"}
}