{
  "type": "Feature",
  "properties": {
    "iso:country": "GB",
    "wof:name": "ST17 4QG",
    "wof:placetype": "postalcode"
  },
  "geometry": {"coordinates":[-2.085696,52.789798],"type":"Point"}
}
