{
  "type": "Feature",
  "properties": {
    "iso:country": "GB",
    "wof:name": "TQ13 7JJ",
    "wof:placetype": "postalcode"
  },
  "geometry": {"coordinates":[-3.764462,50.495519],"type":"Point"}
}
