{
  "type": "Feature",
  "properties": {
    "date:inception_lower": "1980-01-01",
    "date:inception_upper": "1980-01-01",
    "iso:country": "GB",
    "wof:name": "L21 8NE",
    "wof:placetype": "postalcode"
  },
  "geometry": {"coordinates":[-2.990683,53.469646],"type":"Point"}
}
