{
  "type": "Feature",
  "properties": {
    "iso:country":"GB",
    "wof:name":"BB9 8QD",
    "wof:placetype":"postalcode"
},
  "geometry": {"coordinates":[-2.2161475379135,53.85024396933691],"type":"Point"}
}