{
  "type": "Feature",
  "properties": {
    "iso:country":"GB",
    "wof:name":"KA26 0EF",
    "wof:placetype":"postalcode"
},
  "geometry": {"coordinates":[-4.84735734756034,55.23661704532929],"type":"Point"}
}