{
  "type": "Feature",
  "properties": {
    "iso:country": "GB",
    "wof:name": "DA13 9HE",
    "wof:placetype": "postalcode"
  },
  "geometry": {"coordinates":[0.344966,51.404451],"type":"Point"}
}
