{
  "type": "Feature",
  "properties": {
    "iso:country":"GB",
    "wof:name":"SO19 2AB",
    "wof:placetype":"postalcode"
},
  "geometry": {"coordinates":[-1.36359536058701,50.89654688247316],"type":"Point"}
}