{
  "type": "Feature",
  "properties": {
    "iso:country": "GB",
    "wof:name": "IP30 9LU",
    "wof:placetype": "postalcode"
  },
  "geometry": {"coordinates":[0.802701,52.246474],"type":"Point"}
}
