{
  "type": "Feature",
  "properties": {
    "iso:country":"GB",
    "wof:name":"HR2 6GB",
    "wof:placetype":"postalcode"
},
  "geometry": {"coordinates":[-2.7095182071821,52.03877459913796],"type":"Point"}
}