{
  "type": "Feature",
  "properties": {
    "iso:country": "GB",
    "wof:name": "BB6 7FE",
    "wof:placetype": "postalcode"
  },
  "geometry": {"coordinates":[-2.401009,53.782376],"type":"Point"}
}
