{
  "type": "Feature",
  "properties": {
    "iso:country":"GB",
    "wof:name":"BB6 7FE",
    "wof:placetype":"postalcode"
},
  "geometry": {"coordinates":[-2.40100864262819,53.78237622931815],"type":"Point"}
}