{
  "type": "Feature",
  "properties": {
    "date:inception_lower": "1995-07-01",
    "date:inception_upper": "1995-07-01",
    "iso:country": "GB",
    "wof:name": "EN8 0NN",
    "wof:placetype": "postalcode"
  },
  "geometry": {"coordinates":[-0.037163,51.71716],"type":"Point"}
}
