{
  "type": "Feature",
  "properties": {
    "iso:country": "GB",
    "wof:name": "B71 1AN",
    "wof:placetype": "postalcode"
  },
  "geometry": {"coordinates":[-1.993072,52.531915],"type":"Point"}
}
