{
  "type": "Feature",
  "properties": {
    "iso:country":"GB",
    "wof:name":"B71 1AN",
    "wof:placetype":"postalcode"
},
  "geometry": {"coordinates":[-1.99307221359267,52.53191479999057],"type":"Point"}
}