{
  "type": "Feature",
  "properties": {
    "iso:country": "GB",
    "wof:name": "CW7 2LA",
    "wof:placetype": "postalcode"
  },
  "geometry": {"coordinates":[-2.551418,53.196822],"type":"Point"}
}
