{
  "type": "Feature",
  "properties": {
    "iso:country":"GB",
    "wof:name":"AB51 8XU",
    "wof:placetype":"postalcode"
},
  "geometry": {"coordinates":[-2.55908184347538,57.46280036369521],"type":"Point"}
}