{
  "type": "Feature",
  "properties": {
    "date:inception_lower":"2002-12-01",
    "date:inception_upper":"2002-12-31",
    "iso:country":"GB",
    "wof:name":"AB51 8XU",
    "wof:placetype":"postalcode"
},
  "geometry": {"coordinates":[-2.559082,57.4628],"type":"Point"}
}