{
  "type": "Feature",
  "properties": {
    "iso:country": "GB",
    "wof:name": "AB51 8XU",
    "wof:placetype": "postalcode"
  },
  "geometry": {"coordinates":[-2.559082,57.4628],"type":"Point"}
}
