{
  "type": "Feature",
  "properties": {
    "iso:country":"GB",
    "wof:name":"L4 8SY",
    "wof:placetype":"postalcode"
},
  "geometry": {"coordinates":[-2.94303521442316,53.43849846106229],"type":"Point"}
}