{
  "type": "Feature",
  "properties": {
    "iso:country": "GB",
    "wof:name": "L4 8SY",
    "wof:placetype": "postalcode"
  },
  "geometry": {"coordinates":[-2.943035,53.438498],"type":"Point"}
}
