{
  "type": "Feature",
  "properties": {
    "iso:country":"GB",
    "wof:name":"CV35 7BB",
    "wof:placetype":"postalcode"
},
  "geometry": {"coordinates":[-1.69926634814872,52.3016661273108],"type":"Point"}
}