{
  "type": "Feature",
  "properties": {
    "iso:country": "GB",
    "wof:name": "BS36 2HH",
    "wof:placetype": "postalcode"
  },
  "geometry": {"coordinates":[-2.47524,51.533188],"type":"Point"}
}
