{
  "type": "Feature",
  "properties": {
    "date:inception_lower": "1994-05-01",
    "date:inception_upper": "1994-05-01",
    "iso:country": "GB",
    "wof:name": "M34 2BS",
    "wof:placetype": "postalcode"
  },
  "geometry": {"coordinates":[-2.120841,53.449568],"type":"Point"}
}
