{
  "type": "Feature",
  "properties": {
    "iso:country":"GB",
    "wof:name":"M34 2BS",
    "wof:placetype":"postalcode"
},
  "geometry": {"coordinates":[-2.12084085659433,53.44956787804698],"type":"Point"}
}