{
  "type": "Feature",
  "properties": {
    "iso:country": "GB",
    "wof:name": "PO19 6FJ",
    "wof:placetype": "postalcode"
  },
  "geometry": {"coordinates":[-0.772258,50.841431],"type":"Point"}
}
