{
  "type": "Feature",
  "properties": {
    "date:inception_lower":"1991-01-01",
    "date:inception_upper":"1991-01-31",
    "iso:country":"GB",
    "wof:name":"EX22 7XB",
    "wof:placetype":"postalcode"
},
  "geometry": {"coordinates":[-4.33461,50.917807],"type":"Point"}
}