{
  "type": "Feature",
  "properties": {
    "iso:country":"GB",
    "wof:name":"EX22 7XB",
    "wof:placetype":"postalcode"
},
  "geometry": {"coordinates":[-4.33460954635179,50.91780737321462],"type":"Point"}
}