{
  "type": "Feature",
  "properties": {
    "iso:country":"GB",
    "wof:name":"N9 7LT",
    "wof:placetype":"postalcode"
},
  "geometry": {"coordinates":[-0.05849759671649,51.63913686892768],"type":"Point"}
}