{
  "type": "Feature",
  "properties": {
    "iso:country": "GB",
    "wof:name": "HP12 4TX",
    "wof:placetype": "postalcode"
  },
  "geometry": {"coordinates":[-0.76917,51.616298],"type":"Point"}
}
