{
  "type": "Feature",
  "properties": {
    "date:inception_lower": "1980-01-01",
    "date:inception_upper": "1980-01-01",
    "iso:country": "GB",
    "wof:name": "LE7 9EE",
    "wof:placetype": "postalcode"
  },
  "geometry": {"coordinates":[-0.893903,52.581752],"type":"Point"}
}
