{
  "type": "Feature",
  "properties": {
    "iso:country":"GB",
    "wof:name":"LE7 9EE",
    "wof:placetype":"postalcode"
},
  "geometry": {"coordinates":[-0.89390265500785,52.58175183551242],"type":"Point"}
}