{
  "type": "Feature",
  "properties": {
    "iso:country":"GB",
    "wof:name":"LE67 2XA",
    "wof:placetype":"postalcode"
},
  "geometry": {"coordinates":[-1.38239999350831,52.71386052654145],"type":"Point"}
}