{
  "type": "Feature",
  "properties": {
    "iso:country": "GB",
    "wof:name": "LE67 2XA",
    "wof:placetype": "postalcode"
  },
  "geometry": {"coordinates":[-1.3824,52.713861],"type":"Point"}
}
