{
  "type": "Feature",
  "properties": {
    "iso:country": "GB",
    "wof:name": "KY6 3JQ",
    "wof:placetype": "postalcode"
  },
  "geometry": {"coordinates":[-3.281767,56.200943],"type":"Point"}
}
