{
  "type": "Feature",
  "properties": {
    "iso:country":"GB",
    "wof:name":"WA3 2EY",
    "wof:placetype":"postalcode"
},
  "geometry": {"coordinates":[-2.57675750469539,53.47809596564277],"type":"Point"}
}