{
  "type": "Feature",
  "properties": {
    "iso:country":"GB",
    "wof:name":"DY3 1JH",
    "wof:placetype":"postalcode"
},
  "geometry": {"coordinates":[-2.11915491775615,52.54241785508287],"type":"Point"}
}