{
  "type": "Feature",
  "properties": {
    "iso:country":"GB",
    "wof:name":"SS9 5AW",
    "wof:placetype":"postalcode"
},
  "geometry": {"coordinates":[0.65101881505584,51.57239274676826],"type":"Point"}
}