{
  "type": "Feature",
  "properties": {
    "date:inception_lower": "1980-01-01",
    "date:inception_upper": "1980-01-01",
    "iso:country": "GB",
    "wof:name": "NE32 3TB",
    "wof:placetype": "postalcode"
  },
  "geometry": {"coordinates":[-1.470721,54.972776],"type":"Point"}
}
