{
  "type": "Feature",
  "properties": {
    "iso:country":"GB",
    "wof:name":"KA24 5DH",
    "wof:placetype":"postalcode"
},
  "geometry": {"coordinates":[-4.7210540269755,55.70840687591012],"type":"Point"}
}