{
  "type": "Feature",
  "properties": {
    "date:inception_lower":"1980-01-01",
    "date:inception_upper":"1980-01-31",
    "iso:country":"GB",
    "wof:name":"KA24 5DH",
    "wof:placetype":"postalcode"
},
  "geometry": {"coordinates":[-4.721245,55.708412],"type":"Point"}
}