{
  "type": "Feature",
  "properties": {
    "iso:country":"GB",
    "wof:name":"KT11 1LJ",
    "wof:placetype":"postalcode"
},
  "geometry": {"coordinates":[-0.42287234769983,51.31297096615101],"type":"Point"}
}