{
  "type": "Feature",
  "properties": {
    "iso:country":"GB",
    "wof:name":"DD11 1UB",
    "wof:placetype":"postalcode"
},
  "geometry": {"coordinates":[-2.57948555527901,56.56321032874747],"type":"Point"}
}