{
  "type": "Feature",
  "properties": {
    "iso:country": "GB",
    "wof:name": "DD11 1UB",
    "wof:placetype": "postalcode"
  },
  "geometry": {"coordinates":[-2.579404,56.563229],"type":"Point"}
}
