{
  "type": "Feature",
  "properties": {
    "iso:country":"GB",
    "wof:name":"GU33 6AH",
    "wof:placetype":"postalcode"
},
  "geometry": {"coordinates":[-0.88562158210661,51.07266320250585],"type":"Point"}
}