{
  "type": "Feature",
  "properties": {
    "date:inception_lower": "1980-01-01",
    "date:inception_upper": "1980-01-01",
    "iso:country": "GB",
    "wof:name": "HP1 2BG",
    "wof:placetype": "postalcode"
  },
  "geometry": {"coordinates":[-0.496316,51.750997],"type":"Point"}
}
