{
  "type": "Feature",
  "properties": {
    "iso:country":"GB",
    "wof:name":"BD16 2HE",
    "wof:placetype":"postalcode"
},
  "geometry": {"coordinates":[-1.84677641362325,53.86121694867769],"type":"Point"}
}