{
  "type": "Feature",
  "properties": {
    "date:inception_lower": "1980-01-01",
    "date:inception_upper": "1980-01-01",
    "iso:country": "GB",
    "wof:name": "HA3 5DQ",
    "wof:placetype": "postalcode"
  },
  "geometry": {"coordinates":[-0.335506,51.5956],"type":"Point"}
}
