{
  "type": "Feature",
  "properties": {
    "iso:country":"GB",
    "wof:name":"HA3 5DQ",
    "wof:placetype":"postalcode"
},
  "geometry": {"coordinates":[-0.33552751125748,51.59563355407664],"type":"Point"}
}