{
  "type": "Feature",
  "properties": {
    "iso:country": "GB",
    "wof:name": "SK14 3LR",
    "wof:placetype": "postalcode"
  },
  "geometry": {"coordinates":[-2.034302,53.44458],"type":"Point"}
}
