{
  "type": "Feature",
  "properties": {
    "iso:country": "GB",
    "wof:name": "SL6 5JS",
    "wof:placetype": "postalcode"
  },
  "geometry": {"coordinates":[-0.760014,51.528375],"type":"Point"}
}
