{
  "type": "Feature",
  "properties": {
    "iso:country": "GB",
    "wof:name": "HD5 0PX",
    "wof:placetype": "postalcode"
  },
  "geometry": {"coordinates":[-1.715371,53.678125],"type":"Point"}
}
