{
  "type": "Feature",
  "properties": {
    "date:inception_lower": "1980-01-01",
    "date:inception_upper": "1980-01-01",
    "iso:country": "GB",
    "wof:name": "HD5 0PX",
    "wof:placetype": "postalcode"
  },
  "geometry": {"coordinates":[-1.715371,53.678125],"type":"Point"}
}
