{
  "type": "Feature",
  "properties": {
    "iso:country":"GB",
    "wof:name":"SY11 1LF",
    "wof:placetype":"postalcode"
},
  "geometry": {"coordinates":[-3.0563781778151,52.86114253487834],"type":"Point"}
}