{
  "type": "Feature",
  "properties": {
    "iso:country":"GB",
    "wof:name":"TS17 0SZ",
    "wof:placetype":"postalcode"
},
  "geometry": {"coordinates":[-1.31143854851904,54.52216485012195],"type":"Point"}
}