{
  "type": "Feature",
  "properties": {
    "iso:country": "GB",
    "wof:name": "TS17 0SZ",
    "wof:placetype": "postalcode"
  },
  "geometry": {"coordinates":[-1.311438,54.522165],"type":"Point"}
}
