{
  "type": "Feature",
  "properties": {
    "iso:country":"GB",
    "wof:name":"CH5 3DT",
    "wof:placetype":"postalcode"
},
  "geometry": {"coordinates":[-3.05205481103223,53.18945210360989],"type":"Point"}
}