{
  "type": "Feature",
  "properties": {
    "iso:country": "GB",
    "wof:name": "CH5 3DT",
    "wof:placetype": "postalcode"
  },
  "geometry": {"coordinates":[-3.051038,53.190142],"type":"Point"}
}
