{
  "type": "Feature",
  "properties": {
    "date:inception_lower":"1980-01-01",
    "date:inception_upper":"1980-01-31",
    "iso:country":"GB",
    "wof:name":"NR31 0AW",
    "wof:placetype":"postalcode"
},
  "geometry": {"coordinates":[1.717017,52.608178],"type":"Point"}
}