{
  "type": "Feature",
  "properties": {
    "iso:country":"GB",
    "wof:name":"PH7 4HH",
    "wof:placetype":"postalcode"
},
  "geometry": {"coordinates":[-3.84741444886259,56.35397867135521],"type":"Point"}
}