{
  "type": "Feature",
  "properties": {
    "iso:country":"GB",
    "wof:name":"IP30 9RG",
    "wof:placetype":"postalcode"
},
  "geometry": {"coordinates":[0.8895393408024,52.2160505245612],"type":"Point"}
}