{
  "type": "Feature",
  "properties": {
    "iso:country": "GB",
    "wof:name": "GU21 7QS",
    "wof:placetype": "postalcode"
  },
  "geometry": {"coordinates":[-0.581512,51.311043],"type":"Point"}
}
