{
  "type": "Feature",
  "properties": {
    "iso:country":"GB",
    "wof:name":"LA2 9PL",
    "wof:placetype":"postalcode"
},
  "geometry": {"coordinates":[-2.70099323857203,54.07452606574264],"type":"Point"}
}