{
  "type": "Feature",
  "properties": {
    "iso:country": "GB",
    "wof:name": "SG18 8EW",
    "wof:placetype": "postalcode"
  },
  "geometry": {"coordinates":[-0.239953,52.08983],"type":"Point"}
}
