{
  "type": "Feature",
  "properties": {
    "iso:country":"GB",
    "wof:name":"DN17 1RX",
    "wof:placetype":"postalcode"
},
  "geometry": {"coordinates":[-0.67963107973157,53.56847040224364],"type":"Point"}
}