{
  "type": "Feature",
  "properties": {
    "date:inception_lower": "2020-06-01",
    "date:inception_upper": "2020-06-01",
    "iso:country": "GB",
    "wof:name": "MK43 9TA",
    "wof:placetype": "postalcode"
  },
  "geometry": {"coordinates":[-0.502616,52.071019],"type":"Point"}
}
