{
  "type": "Feature",
  "properties": {
    "iso:country":"GB",
    "wof:name":"PE10 0SA",
    "wof:placetype":"postalcode"
},
  "geometry": {"coordinates":[-0.42129109499156,52.83086241525974],"type":"Point"}
}