{
  "type": "Feature",
  "properties": {
    "iso:country": "GB",
    "wof:name": "PE10 0SA",
    "wof:placetype": "postalcode"
  },
  "geometry": {"coordinates":[-0.421291,52.830862],"type":"Point"}
}
