{
  "type": "Feature",
  "properties": {
    "iso:country": "GB",
    "wof:name": "HP2 5SW",
    "wof:placetype": "postalcode"
  },
  "geometry": {"coordinates":[-0.46269,51.76023],"type":"Point"}
}
