{
  "type": "Feature",
  "properties": {
    "iso:country":"GB",
    "wof:name":"HP2 5SW",
    "wof:placetype":"postalcode"
},
  "geometry": {"coordinates":[-0.46268957764864,51.76022970815408],"type":"Point"}
}