{
  "type": "Feature",
  "properties": {
    "iso:country": "GB",
    "wof:name": "CT21 5HZ",
    "wof:placetype": "postalcode"
  },
  "geometry": {"coordinates":[1.08826,51.07505],"type":"Point"}
}
