{
  "type": "Feature",
  "properties": {
    "iso:country":"GB",
    "wof:name":"CT21 5HZ",
    "wof:placetype":"postalcode"
},
  "geometry": {"coordinates":[1.0882599745764,51.075050194475],"type":"Point"}
}