{
  "type": "Feature",
  "properties": {
    "iso:country": "GB",
    "wof:name": "OX17 2GA",
    "wof:placetype": "postalcode"
  },
  "geometry": {"coordinates":[-1.275978,52.077082],"type":"Point"}
}
