{
  "type": "Feature",
  "properties": {
    "date:inception_lower": "2020-04-01",
    "date:inception_upper": "2020-04-01",
    "iso:country": "GB",
    "wof:name": "YO25 5DZ",
    "wof:placetype": "postalcode"
  },
  "geometry": {"coordinates":[-0.41994,54.01276],"type":"Point"}
}
