{
  "type": "Feature",
  "properties": {
    "date:inception_lower": "1980-01-01",
    "date:inception_upper": "1980-01-01",
    "iso:country": "GB",
    "wof:name": "NR7 9AD",
    "wof:placetype": "postalcode"
  },
  "geometry": {"coordinates":[1.341711,52.649762],"type":"Point"}
}
