{
  "type": "Feature",
  "properties": {
    "iso:country":"GB",
    "wof:name":"NW3 5AS",
    "wof:placetype":"postalcode"
},
  "geometry": {"coordinates":[-0.17098397429837,51.54948179161856],"type":"Point"}
}