{
  "type": "Feature",
  "properties": {
    "date:inception_lower":"1980-01-01",
    "date:inception_upper":"1980-01-31",
    "iso:country":"GB",
    "wof:name":"NW3 5AS",
    "wof:placetype":"postalcode"
},
  "geometry": {"coordinates":[-0.170883,51.549573],"type":"Point"}
}