{
  "type": "Feature",
  "properties": {
    "date:inception_lower": "2000-06-01",
    "date:inception_upper": "2000-06-01",
    "iso:country": "GB",
    "wof:name": "CA7 1BY",
    "wof:placetype": "postalcode"
  },
  "geometry": {"coordinates":[-3.244755,54.77211],"type":"Point"}
}
