{
  "type": "Feature",
  "properties": {
    "iso:country": "GB",
    "wof:name": "CA7 1BY",
    "wof:placetype": "postalcode"
  },
  "geometry": {"coordinates":[-3.244617,54.772147],"type":"Point"}
}
