{
  "type": "Feature",
  "properties": {
    "iso:country":"GB",
    "wof:name":"CA7 1BY",
    "wof:placetype":"postalcode"
},
  "geometry": {"coordinates":[-3.24475296956752,54.77210285653771],"type":"Point"}
}