{
  "type": "Feature",
  "properties": {
    "iso:country":"GB",
    "wof:name":"BA1 4EN",
    "wof:placetype":"postalcode"
},
  "geometry": {"coordinates":[-2.38961084049807,51.40043748178761],"type":"Point"}
}