{
  "type": "Feature",
  "properties": {
    "iso:country": "GB",
    "wof:name": "YO17 9FA",
    "wof:placetype": "postalcode"
  },
  "geometry": {"coordinates":[-0.77376,54.124809],"type":"Point"}
}
