{
  "type": "Feature",
  "properties": {
    "iso:country":"GB",
    "wof:name":"YO17 9FA",
    "wof:placetype":"postalcode"
},
  "geometry": {"coordinates":[-0.77376019751051,54.12480901881487],"type":"Point"}
}