{
  "type": "Feature",
  "properties": {
    "iso:country":"GB",
    "wof:name":"OL1 1NR",
    "wof:placetype":"postalcode"
},
  "geometry": {"coordinates":[-2.11575392774318,53.54433778933782],"type":"Point"}
}