{
  "type": "Feature",
  "properties": {
    "date:inception_lower": "1992-01-01",
    "date:inception_upper": "1992-01-01",
    "iso:country": "GB",
    "wof:name": "OL1 1NR",
    "wof:placetype": "postalcode"
  },
  "geometry": {"coordinates":[-2.115754,53.544338],"type":"Point"}
}
