{
  "type": "Feature",
  "properties": {
    "iso:country":"GB",
    "wof:name":"PE9 3AB",
    "wof:placetype":"postalcode"
},
  "geometry": {"coordinates":[-0.52703808259254,52.61157978702661],"type":"Point"}
}