{
  "type": "Feature",
  "properties": {
    "date:inception_lower": "2006-04-01",
    "date:inception_upper": "2006-04-01",
    "iso:country": "GB",
    "wof:name": "PE9 3AB",
    "wof:placetype": "postalcode"
  },
  "geometry": {"coordinates":[-0.527038,52.61158],"type":"Point"}
}
