{
  "type": "Feature",
  "properties": {
    "date:inception_lower": "2020-02-01",
    "date:inception_upper": "2020-02-01",
    "iso:country": "GB",
    "wof:name": "PL31 9BJ",
    "wof:placetype": "postalcode"
  },
  "geometry": {"coordinates":[-4.719111,50.47007],"type":"Point"}
}
