{
  "type": "Feature",
  "properties": {
    "iso:country":"GB",
    "wof:name":"G76 0DQ",
    "wof:placetype":"postalcode"
},
  "geometry": {"coordinates":[-4.27658854889839,55.7574233702431],"type":"Point"}
}