{
  "type": "Feature",
  "properties": {
    "iso:country": "GB",
    "wof:name": "HP14 4TT",
    "wof:placetype": "postalcode"
  },
  "geometry": {"coordinates":[-0.79041,51.673756],"type":"Point"}
}
