{
  "type": "Feature",
  "properties": {
    "iso:country": "GB",
    "wof:name": "NG32 2BJ",
    "wof:placetype": "postalcode"
  },
  "geometry": {"coordinates":[-0.62252,52.991448],"type":"Point"}
}
