{
  "type": "Feature",
  "properties": {
    "iso:country":"GB",
    "wof:name":"M14 7JT",
    "wof:placetype":"postalcode"
},
  "geometry": {"coordinates":[-2.23971161891162,53.45109607133768],"type":"Point"}
}