{
  "type": "Feature",
  "properties": {
    "iso:country":"GB",
    "wof:name":"B26 2TD",
    "wof:placetype":"postalcode"
},
  "geometry": {"coordinates":[-1.78398325402668,52.4679077470044],"type":"Point"}
}