{
  "type": "Feature",
  "properties": {
    "iso:country": "GB",
    "wof:name": "SM1 4RA",
    "wof:placetype": "postalcode"
  },
  "geometry": {"coordinates":[-0.191558,51.36111],"type":"Point"}
}
