{
  "type": "Feature",
  "properties": {
    "iso:country":"GB",
    "wof:name":"SM1 4RA",
    "wof:placetype":"postalcode"
},
  "geometry": {"coordinates":[-0.19171271964954,51.36111286665645],"type":"Point"}
}