{
  "type": "Feature",
  "properties": {
    "iso:country":"GB",
    "wof:name":"LN11 0TW",
    "wof:placetype":"postalcode"
},
  "geometry": {"coordinates":[-0.06176689327264,53.42988918429482],"type":"Point"}
}