{
  "type": "Feature",
  "properties": {
    "iso:country": "GB",
    "wof:name": "LN11 0TW",
    "wof:placetype": "postalcode"
  },
  "geometry": {"coordinates":[-0.061769,53.429914],"type":"Point"}
}
