{
  "type": "Feature",
  "properties": {
    "iso:country":"GB",
    "wof:name":"SS2 4DL",
    "wof:placetype":"postalcode"
},
  "geometry": {"coordinates":[0.72906964569344,51.54804656264842],"type":"Point"}
}