{
  "type": "Feature",
  "properties": {
    "iso:country":"GB",
    "wof:name":"DT4 8QG",
    "wof:placetype":"postalcode"
},
  "geometry": {"coordinates":[-2.46132965107241,50.59634624712631],"type":"Point"}
}