{
  "type": "Feature",
  "properties": {
    "iso:country":"GB",
    "wof:name":"DY6 8EJ",
    "wof:placetype":"postalcode"
},
  "geometry": {"coordinates":[-2.15918087421696,52.49579400525663],"type":"Point"}
}