{
  "type": "Feature",
  "properties": {
    "iso:country":"GB",
    "wof:name":"SK10 1BW",
    "wof:placetype":"postalcode"
},
  "geometry": {"coordinates":[-2.13359143924459,53.2616199713494],"type":"Point"}
}