{
  "type": "Feature",
  "properties": {
    "date:inception_lower":"2001-12-01",
    "date:inception_upper":"2001-12-31",
    "iso:country":"GB",
    "wof:name":"BS3 4HT",
    "wof:placetype":"postalcode"
},
  "geometry": {"coordinates":[-2.592564,51.444374],"type":"Point"}
}