{
  "type": "Feature",
  "properties": {
    "iso:country":"GB",
    "wof:name":"PA4 9QG",
    "wof:placetype":"postalcode"
},
  "geometry": {"coordinates":[-4.43663119833637,55.89198493001513],"type":"Point"}
}