{
  "type": "Feature",
  "properties": {
    "date:inception_lower": "1980-01-01",
    "date:inception_upper": "1980-01-01",
    "iso:country": "GB",
    "wof:name": "TD1 3BW",
    "wof:placetype": "postalcode"
  },
  "geometry": {"coordinates":[-2.800087,55.612042],"type":"Point"}
}
