{
  "type": "Feature",
  "properties": {
    "iso:country":"GB",
    "wof:name":"BN6 9AS",
    "wof:placetype":"postalcode"
},
  "geometry": {"coordinates":[-0.16576037388252,50.93003516146242],"type":"Point"}
}