{
  "type": "Feature",
  "properties": {
    "iso:country": "GB",
    "wof:name": "BN6 9AS",
    "wof:placetype": "postalcode"
  },
  "geometry": {"coordinates":[-0.16576,50.930035],"type":"Point"}
}
