{
  "type": "Feature",
  "properties": {
    "iso:country":"GB",
    "wof:name":"WD7 8ET",
    "wof:placetype":"postalcode"
},
  "geometry": {"coordinates":[-0.32607674904193,51.69436750376043],"type":"Point"}
}