{
  "type": "Feature",
  "properties": {
    "iso:country":"GB",
    "wof:name":"ML3 6RF",
    "wof:placetype":"postalcode"
},
  "geometry": {"coordinates":[-4.04417082909216,55.76848482838709],"type":"Point"}
}