{
  "type": "Feature",
  "properties": {
    "iso:country": "GB",
    "wof:name": "OX14 1AJ",
    "wof:placetype": "postalcode"
  },
  "geometry": {"coordinates":[-1.296472,51.670719],"type":"Point"}
}
