{
  "type": "Feature",
  "properties": {
    "iso:country":"GB",
    "wof:name":"CM15 9RS",
    "wof:placetype":"postalcode"
},
  "geometry": {"coordinates":[0.27868972304313,51.63908331727414],"type":"Point"}
}