{
  "type": "Feature",
  "properties": {
    "iso:country": "GB",
    "wof:name": "CM15 9RS",
    "wof:placetype": "postalcode"
  },
  "geometry": {"coordinates":[0.27869,51.639083],"type":"Point"}
}
