{
  "type": "Feature",
  "properties": {
    "date:inception_lower": "1995-12-01",
    "date:inception_upper": "1995-12-01",
    "iso:country": "GB",
    "wof:name": "CM15 9RS",
    "wof:placetype": "postalcode"
  },
  "geometry": {"coordinates":[0.27869,51.639083],"type":"Point"}
}
