{
  "type": "Feature",
  "properties": {
    "iso:country": "GB",
    "wof:name": "BL9 6HE",
    "wof:placetype": "postalcode"
  },
  "geometry": {"coordinates":[-2.286777,53.602033],"type":"Point"}
}
