{
  "type": "Feature",
  "properties": {
    "iso:country":"GB",
    "wof:name":"BL9 6HE",
    "wof:placetype":"postalcode"
},
  "geometry": {"coordinates":[-2.28677715214162,53.60203331448046],"type":"Point"}
}