{
  "type": "Feature",
  "properties": {
    "iso:country": "GB",
    "wof:name": "KT2 7HA",
    "wof:placetype": "postalcode"
  },
  "geometry": {"coordinates":[-0.270974,51.414871],"type":"Point"}
}
