{
  "type": "Feature",
  "properties": {
    "iso:country": "GB",
    "wof:name": "BA5 3FL",
    "wof:placetype": "postalcode"
  },
  "geometry": {"coordinates":[-2.667567,51.25111],"type":"Point"}
}
