{
  "type": "Feature",
  "properties": {
    "date:inception_lower": "1999-06-01",
    "date:inception_upper": "1999-06-01",
    "iso:country": "GB",
    "wof:name": "NP18 2DR",
    "wof:placetype": "postalcode"
  },
  "geometry": {"coordinates":[-2.913073,51.591137],"type":"Point"}
}
