{
  "type": "Feature",
  "properties": {
    "iso:country":"GB",
    "wof:name":"RG2 7PT",
    "wof:placetype":"postalcode"
},
  "geometry": {"coordinates":[-0.96234769426244,51.43852288617624],"type":"Point"}
}