{
  "type": "Feature",
  "properties": {
    "iso:country":"GB",
    "wof:name":"GU10 4HP",
    "wof:placetype":"postalcode"
},
  "geometry": {"coordinates":[-0.81190241197062,51.1532831923946],"type":"Point"}
}