{
  "type": "Feature",
  "properties": {
    "date:inception_lower": "1980-01-01",
    "date:inception_upper": "1980-01-01",
    "iso:country": "GB",
    "wof:name": "HP10 0EP",
    "wof:placetype": "postalcode"
  },
  "geometry": {"coordinates":[-0.683577,51.585495],"type":"Point"}
}
