{
  "type": "Feature",
  "properties": {
    "iso:country":"GB",
    "wof:name":"DE22 2FB",
    "wof:placetype":"postalcode"
},
  "geometry": {"coordinates":[-1.47367693368916,52.95939072942787],"type":"Point"}
}