{
  "type": "Feature",
  "properties": {
    "iso:country":"GB",
    "wof:name":"YO11 3AF",
    "wof:placetype":"postalcode"
},
  "geometry": {"coordinates":[-0.3807427994695,54.25471268823147],"type":"Point"}
}