{
  "type": "Feature",
  "properties": {
    "iso:country":"GB",
    "wof:name":"W2 1NG",
    "wof:placetype":"postalcode"
},
  "geometry": {"coordinates":[-0.17552802135603,51.52314176113214],"type":"Point"}
}