{
  "type": "Feature",
  "properties": {
    "date:inception_lower": "1983-07-01",
    "date:inception_upper": "1983-07-01",
    "iso:country": "GB",
    "wof:name": "PE14 0EA",
    "wof:placetype": "postalcode"
  },
  "geometry": {"coordinates":[0.190515,52.635873],"type":"Point"}
}
