{
  "type": "Feature",
  "properties": {
    "iso:country": "GB",
    "wof:name": "PE14 0EA",
    "wof:placetype": "postalcode"
  },
  "geometry": {"coordinates":[0.190427,52.635901],"type":"Point"}
}
