{
  "type": "Feature",
  "properties": {
    "date:inception_lower": "1993-08-01",
    "date:inception_upper": "1993-08-01",
    "iso:country": "GB",
    "wof:name": "AL9 7HB",
    "wof:placetype": "postalcode"
  },
  "geometry": {"coordinates":[-0.217195,51.740195],"type":"Point"}
}
