{
  "type": "Feature",
  "properties": {
    "iso:country":"GB",
    "wof:name":"AL9 7HB",
    "wof:placetype":"postalcode"
},
  "geometry": {"coordinates":[-0.2172172029352,51.74019038441882],"type":"Point"}
}