{
  "type": "Feature",
  "properties": {
    "iso:country":"GB",
    "wof:name":"DH7 9LJ",
    "wof:placetype":"postalcode"
},
  "geometry": {"coordinates":[-1.71131204557534,54.77638695053661],"type":"Point"}
}