{
  "type": "Feature",
  "properties": {
    "date:inception_lower":"1980-01-01",
    "date:inception_upper":"1980-01-31",
    "iso:country":"GB",
    "wof:name":"DH7 9LJ",
    "wof:placetype":"postalcode"
},
  "geometry": {"coordinates":[-1.711312,54.776387],"type":"Point"}
}