{
  "type": "Feature",
  "properties": {
    "date:inception_lower":"1994-05-01",
    "date:inception_upper":"1994-05-31",
    "iso:country":"GB",
    "wof:name":"M26 1HF",
    "wof:placetype":"postalcode"
},
  "geometry": {"coordinates":[-2.369145,53.546089],"type":"Point"}
}