{
  "type": "Feature",
  "properties": {
    "iso:country": "GB",
    "wof:name": "HR2 8EY",
    "wof:placetype": "postalcode"
  },
  "geometry": {"coordinates":[-2.811106,51.934076],"type":"Point"}
}
