{
  "type": "Feature",
  "properties": {
    "date:inception_lower": "2008-06-01",
    "date:inception_upper": "2008-06-01",
    "iso:country": "GB",
    "wof:name": "CR0 6AW",
    "wof:placetype": "postalcode"
  },
  "geometry": {"coordinates":[-0.083396,51.375821],"type":"Point"}
}
