{
  "type": "Feature",
  "properties": {
    "iso:country":"GB",
    "wof:name":"CR0 6AW",
    "wof:placetype":"postalcode"
},
  "geometry": {"coordinates":[-0.08339586202391,51.37582054598085],"type":"Point"}
}