{
  "type": "Feature",
  "properties": {
    "iso:country": "GB",
    "wof:name": "OL15 9EW",
    "wof:placetype": "postalcode"
  },
  "geometry": {"coordinates":[-2.082404,53.660862],"type":"Point"}
}
