{
  "type": "Feature",
  "properties": {
    "iso:country":"GB",
    "wof:name":"PL2 3PZ",
    "wof:placetype":"postalcode"
},
  "geometry": {"coordinates":[-4.14856671766015,50.39524977937455],"type":"Point"}
}