{
  "type": "Feature",
  "properties": {
    "date:inception_lower":"1980-01-01",
    "date:inception_upper":"1980-01-31",
    "iso:country":"GB",
    "wof:name":"PL2 3PZ",
    "wof:placetype":"postalcode"
},
  "geometry": {"coordinates":[-4.148567,50.39525],"type":"Point"}
}