{
  "type": "Feature",
  "properties": {
    "date:inception_lower": "1980-01-01",
    "date:inception_upper": "1980-01-01",
    "iso:country": "GB",
    "wof:name": "TN18 5JA",
    "wof:placetype": "postalcode"
  },
  "geometry": {"coordinates":[0.563565,51.027264],"type":"Point"}
}
