{
  "type": "Feature",
  "properties": {
    "iso:country":"GB",
    "wof:name":"TN18 5JA",
    "wof:placetype":"postalcode"
},
  "geometry": {"coordinates":[0.56333956940933,51.0273428984076],"type":"Point"}
}