{
  "type": "Feature",
  "properties": {
    "date:inception_lower": "2021-07-01",
    "date:inception_upper": "2021-07-01",
    "iso:country": "GB",
    "wof:name": "B33 9FH",
    "wof:placetype": "postalcode"
  },
  "geometry": {"coordinates":[-1.812094,52.488368],"type":"Point"}
}
