{
  "type": "Feature",
  "properties": {
    "iso:country":"GB",
    "wof:name":"HX4 8LS",
    "wof:placetype":"postalcode"
},
  "geometry": {"coordinates":[-1.85204829429181,53.68949885901105],"type":"Point"}
}