{
  "type": "Feature",
  "properties": {
    "date:inception_lower":"1980-01-01",
    "date:inception_upper":"1980-01-31",
    "iso:country":"GB",
    "wof:name":"HX4 8LS",
    "wof:placetype":"postalcode"
},
  "geometry": {"coordinates":[-1.852048,53.689499],"type":"Point"}
}