{
  "type": "Feature",
  "properties": {
    "iso:country":"GB",
    "wof:name":"HU10 7RP",
    "wof:placetype":"postalcode"
},
  "geometry": {"coordinates":[-0.46433579416839,53.75048305088423],"type":"Point"}
}