{
  "type": "Feature",
  "properties": {
    "iso:country":"GB",
    "wof:name":"CO9 3LS",
    "wof:placetype":"postalcode"
},
  "geometry": {"coordinates":[0.53681990137542,51.98127107323175],"type":"Point"}
}