{
  "type": "Feature",
  "properties": {
    "iso:country": "GB",
    "wof:name": "PL9 0JX",
    "wof:placetype": "postalcode"
  },
  "geometry": {"coordinates":[-4.074853,50.322763],"type":"Point"}
}
