{
  "type": "Feature",
  "properties": {
    "iso:country":"GB",
    "wof:name":"PL9 0JX",
    "wof:placetype":"postalcode"
},
  "geometry": {"coordinates":[-4.07485348945582,50.3227631606422],"type":"Point"}
}