{
  "type": "Feature",
  "properties": {
    "date:inception_lower": "1982-03-01",
    "date:inception_upper": "1982-03-01",
    "iso:country": "GB",
    "wof:name": "SS2 4DX",
    "wof:placetype": "postalcode"
  },
  "geometry": {"coordinates":[0.722472,51.555197],"type":"Point"}
}
