{
  "type": "Feature",
  "properties": {
    "iso:country":"GB",
    "wof:name":"SS2 4DX",
    "wof:placetype":"postalcode"
},
  "geometry": {"coordinates":[0.72247172560257,51.55519700596631],"type":"Point"}
}