{
  "type": "Feature",
  "properties": {
    "iso:country":"GB",
    "wof:name":"SO45 1RJ",
    "wof:placetype":"postalcode"
},
  "geometry": {"coordinates":[-1.36455707772788,50.82058290619087],"type":"Point"}
}