{
  "type": "Feature",
  "properties": {
    "iso:country":"GB",
    "wof:name":"B79 9LE",
    "wof:placetype":"postalcode"
},
  "geometry": {"coordinates":[-1.6818883762929,52.69387085713173],"type":"Point"}
}