{
  "type": "Feature",
  "properties": {
    "iso:country": "GB",
    "wof:name": "B79 9LE",
    "wof:placetype": "postalcode"
  },
  "geometry": {"coordinates":[-1.681888,52.693871],"type":"Point"}
}
