{
  "type": "Feature",
  "properties": {
    "date:inception_lower": "1998-06-01",
    "date:inception_upper": "1998-06-01",
    "iso:country": "GB",
    "wof:name": "B79 9LE",
    "wof:placetype": "postalcode"
  },
  "geometry": {"coordinates":[-1.681888,52.693871],"type":"Point"}
}
