{
  "type": "Feature",
  "properties": {
    "iso:country":"GB",
    "wof:name":"HA4 7TN",
    "wof:placetype":"postalcode"
},
  "geometry": {"coordinates":[-0.43439163985618,51.58528612121578],"type":"Point"}
}