{
  "type": "Feature",
  "properties": {
    "iso:country": "GB",
    "wof:name": "E11 1SZ",
    "wof:placetype": "postalcode"
  },
  "geometry": {"coordinates":[0.025585,51.586567],"type":"Point"}
}
