{
  "type": "Feature",
  "properties": {
    "iso:country":"GB",
    "wof:name":"E11 1SZ",
    "wof:placetype":"postalcode"
},
  "geometry": {"coordinates":[0.02558456669979,51.5865665403464],"type":"Point"}
}