{
  "type": "Feature",
  "properties": {
    "date:inception_lower":"1990-02-01",
    "date:inception_upper":"1990-02-28",
    "iso:country":"GB",
    "wof:name":"E11 1SZ",
    "wof:placetype":"postalcode"
},
  "geometry": {"coordinates":[0.025585,51.586567],"type":"Point"}
}