{
  "type": "Feature",
  "properties": {
    "iso:country": "GB",
    "wof:name": "SK10 1EW",
    "wof:placetype": "postalcode"
  },
  "geometry": {"coordinates":[-2.125634,53.262761],"type":"Point"}
}
