{
  "type": "Feature",
  "properties": {
    "iso:country":"GB",
    "wof:name":"NW4 3DX",
    "wof:placetype":"postalcode"
},
  "geometry": {"coordinates":[-0.22940094750412,51.58136549594246],"type":"Point"}
}