{
  "type": "Feature",
  "properties": {
    "iso:country": "GB",
    "wof:name": "CH70 8AQ",
    "wof:placetype": "postalcode"
  },
  "geometry": {"coordinates":[-2.92259,53.192746],"type":"Point"}
}
