{
  "type": "Feature",
  "properties": {
    "date:inception_lower": "1980-01-01",
    "date:inception_upper": "1980-01-01",
    "iso:country": "GB",
    "wof:name": "KW9 6QU",
    "wof:placetype": "postalcode"
  },
  "geometry": {"coordinates":[-3.851681,58.01276],"type":"Point"}
}
