{
  "type": "Feature",
  "properties": {
    "iso:country":"GB",
    "wof:name":"KW9 6QU",
    "wof:placetype":"postalcode"
},
  "geometry": {"coordinates":[-3.85168059082727,58.01276001224601],"type":"Point"}
}