{
  "type": "Feature",
  "properties": {
    "iso:country":"GB",
    "wof:name":"CF43 4BA",
    "wof:placetype":"postalcode"
},
  "geometry": {"coordinates":[-3.48392545902602,51.67324774287741],"type":"Point"}
}