{
  "type": "Feature",
  "properties": {
    "date:inception_lower": "1998-12-01",
    "date:inception_upper": "1998-12-01",
    "iso:country": "GB",
    "wof:name": "IV30 8TY",
    "wof:placetype": "postalcode"
  },
  "geometry": {"coordinates":[-3.38212,57.625159],"type":"Point"}
}
