{
  "type": "Feature",
  "properties": {
    "iso:country":"GB",
    "wof:name":"IV30 8TY",
    "wof:placetype":"postalcode"
},
  "geometry": {"coordinates":[-3.38179269209556,57.62528587342405],"type":"Point"}
}