{
  "type": "Feature",
  "properties": {
    "date:inception_lower": "1980-01-01",
    "date:inception_upper": "1980-01-01",
    "iso:country": "GB",
    "wof:name": "CW12 2JU",
    "wof:placetype": "postalcode"
  },
  "geometry": {"coordinates":[-2.260336,53.194084],"type":"Point"}
}
