{
  "type": "Feature",
  "properties": {
    "iso:country": "GB",
    "wof:name": "E4 8SU",
    "wof:placetype": "postalcode"
  },
  "geometry": {"coordinates":[-0.022624,51.606706],"type":"Point"}
}
