{
  "type": "Feature",
  "properties": {
    "iso:country":"GB",
    "wof:name":"E4 8SU",
    "wof:placetype":"postalcode"
},
  "geometry": {"coordinates":[-0.02265051705916,51.60670516028541],"type":"Point"}
}