{
  "type": "Feature",
  "properties": {
    "iso:country": "GB",
    "wof:name": "NG3 4GG",
    "wof:placetype": "postalcode"
  },
  "geometry": {"coordinates":[-1.150654,52.964525],"type":"Point"}
}
