{
  "type": "Feature",
  "properties": {
    "iso:country":"GB",
    "wof:name":"NG3 4GG",
    "wof:placetype":"postalcode"
},
  "geometry": {"coordinates":[-1.15065360554633,52.96452500955471],"type":"Point"}
}