{
  "type": "Feature",
  "properties": {
    "date:inception_lower": "1980-01-01",
    "date:inception_upper": "1980-01-01",
    "iso:country": "GB",
    "wof:name": "SG12 8PP",
    "wof:placetype": "postalcode"
  },
  "geometry": {"coordinates":[0.054392,51.797956],"type":"Point"}
}
