{
  "type": "Feature",
  "properties": {
    "iso:country": "GB",
    "wof:name": "MK40 4TQ",
    "wof:placetype": "postalcode"
  },
  "geometry": {"coordinates":[-0.4906,52.141799],"type":"Point"}
}
