{
  "type": "Feature",
  "properties": {
    "date:inception_lower": "1980-01-01",
    "date:inception_upper": "1980-01-01",
    "iso:country": "GB",
    "wof:name": "DY5 2YT",
    "wof:placetype": "postalcode"
  },
  "geometry": {"coordinates":[-2.113489,52.47478],"type":"Point"}
}
