{
  "type": "Feature",
  "properties": {
    "iso:country":"GB",
    "wof:name":"DY5 2YT",
    "wof:placetype":"postalcode"
},
  "geometry": {"coordinates":[-2.11349440125298,52.47454055244343],"type":"Point"}
}