{
  "type": "Feature",
  "properties": {
    "iso:country":"GB",
    "wof:name":"SP6 3ER",
    "wof:placetype":"postalcode"
},
  "geometry": {"coordinates":[-1.83250494426927,50.91205345230365],"type":"Point"}
}