{
  "type": "Feature",
  "properties": {
    "date:inception_lower": "1980-01-01",
    "date:inception_upper": "1980-01-01",
    "iso:country": "GB",
    "wof:name": "SP6 3ER",
    "wof:placetype": "postalcode"
  },
  "geometry": {"coordinates":[-1.832505,50.912053],"type":"Point"}
}
