{
  "type": "Feature",
  "properties": {
    "date:inception_lower": "1980-01-01",
    "date:inception_upper": "1980-01-01",
    "iso:country": "GB",
    "wof:name": "L30 5RQ",
    "wof:placetype": "postalcode"
  },
  "geometry": {"coordinates":[-2.971653,53.491932],"type":"Point"}
}
