{
  "type": "Feature",
  "properties": {
    "iso:country":"GB",
    "wof:name":"CF46 5AT",
    "wof:placetype":"postalcode"
},
  "geometry": {"coordinates":[-3.30921602256128,51.65993176362475],"type":"Point"}
}