{
  "type": "Feature",
  "properties": {
    "iso:country": "GB",
    "wof:name": "SO14 3EB",
    "wof:placetype": "postalcode"
  },
  "geometry": {"coordinates":[-1.400675,50.898011],"type":"Point"}
}
