{
  "type": "Feature",
  "properties": {
    "iso:country": "GB",
    "wof:name": "RG5 4SY",
    "wof:placetype": "postalcode"
  },
  "geometry": {"coordinates":[-0.878356,51.453117],"type":"Point"}
}
