{
  "type": "Feature",
  "properties": {
    "iso:country": "GB",
    "wof:name": "SN8 1EX",
    "wof:placetype": "postalcode"
  },
  "geometry": {"coordinates":[-1.727534,51.420271],"type":"Point"}
}
