{
  "type": "Feature",
  "properties": {
    "iso:country":"GB",
    "wof:name":"RM14 2TF",
    "wof:placetype":"postalcode"
},
  "geometry": {"coordinates":[0.2515576816058,51.52659293308383],"type":"Point"}
}