{
  "type": "Feature",
  "properties": {
    "date:inception_lower": "1980-01-01",
    "date:inception_upper": "1980-01-01",
    "iso:country": "GB",
    "wof:name": "L25 1PJ",
    "wof:placetype": "postalcode"
  },
  "geometry": {"coordinates":[-2.878386,53.394344],"type":"Point"}
}
