{
  "type": "Feature",
  "properties": {
    "iso:country": "GB",
    "wof:name": "NE34 8EX",
    "wof:placetype": "postalcode"
  },
  "geometry": {"coordinates":[-1.409328,54.968287],"type":"Point"}
}
