{
  "type": "Feature",
  "properties": {
    "iso:country":"GB",
    "wof:name":"CF39 0BY",
    "wof:placetype":"postalcode"
},
  "geometry": {"coordinates":[-3.41427544009319,51.61565115352423],"type":"Point"}
}