{
  "type": "Feature",
  "properties": {
    "date:inception_lower": "1980-01-01",
    "date:inception_upper": "1980-01-01",
    "iso:country": "GB",
    "wof:name": "DE6 5BS",
    "wof:placetype": "postalcode"
  },
  "geometry": {"coordinates":[-1.605963,52.922921],"type":"Point"}
}
