{
  "type": "Feature",
  "properties": {
    "iso:country":"GB",
    "wof:name":"DE6 5BS",
    "wof:placetype":"postalcode"
},
  "geometry": {"coordinates":[-1.60596259342717,52.92292053015313],"type":"Point"}
}