{
  "type": "Feature",
  "properties": {
    "iso:country":"GB",
    "wof:name":"G66 1ND",
    "wof:placetype":"postalcode"
},
  "geometry": {"coordinates":[-4.15223097310956,55.93815179649601],"type":"Point"}
}