{
  "type": "Feature",
  "properties": {
    "iso:country": "GB",
    "wof:name": "HP1 2NJ",
    "wof:placetype": "postalcode"
  },
  "geometry": {"coordinates":[-0.501953,51.758165],"type":"Point"}
}
