{
  "type": "Feature",
  "properties": {
    "iso:country": "GB",
    "wof:name": "WD23 2BB",
    "wof:placetype": "postalcode"
  },
  "geometry": {"coordinates":[-0.377702,51.66201],"type":"Point"}
}
