{
  "type": "Feature",
  "properties": {
    "iso:country": "GB",
    "wof:name": "YO23 2RS",
    "wof:placetype": "postalcode"
  },
  "geometry": {"coordinates":[-1.10732,53.920374],"type":"Point"}
}
