{
  "type": "Feature",
  "properties": {
    "iso:country": "GB",
    "wof:name": "SW16 6RE",
    "wof:placetype": "postalcode"
  },
  "geometry": {"coordinates":[-0.143799,51.423852],"type":"Point"}
}
