{
  "type": "Feature",
  "properties": {
    "iso:country": "GB",
    "wof:name": "LL54 7EU",
    "wof:placetype": "postalcode"
  },
  "geometry": {"coordinates":[-4.230338,53.091172],"type":"Point"}
}
