{
  "type": "Feature",
  "properties": {
    "iso:country":"GB",
    "wof:name":"LL54 7EU",
    "wof:placetype":"postalcode"
},
  "geometry": {"coordinates":[-4.23033845379403,53.09117163451171],"type":"Point"}
}