{
  "type": "Feature",
  "properties": {
    "iso:country": "GB",
    "wof:name": "CB4 2GU",
    "wof:placetype": "postalcode"
  },
  "geometry": {"coordinates":[0.121537,52.234619],"type":"Point"}
}
