{
  "type": "Feature",
  "properties": {
    "iso:country":"GB",
    "wof:name":"CB4 2GU",
    "wof:placetype":"postalcode"
},
  "geometry": {"coordinates":[0.12153719553156,52.23461868565673],"type":"Point"}
}