{
  "type": "Feature",
  "properties": {
    "iso:country": "GB",
    "wof:name": "AL5 2HY",
    "wof:placetype": "postalcode"
  },
  "geometry": {"coordinates":[-0.356863,51.813828],"type":"Point"}
}
