{
  "type": "Feature",
  "properties": {
    "date:inception_lower": "1980-01-01",
    "date:inception_upper": "1980-01-01",
    "iso:country": "GB",
    "wof:name": "AL5 2HY",
    "wof:placetype": "postalcode"
  },
  "geometry": {"coordinates":[-0.356863,51.813828],"type":"Point"}
}
