{
  "type": "Feature",
  "properties": {
    "iso:country":"GB",
    "wof:name":"AL5 2HY",
    "wof:placetype":"postalcode"
},
  "geometry": {"coordinates":[-0.35686348961794,51.81382835652163],"type":"Point"}
}