{
  "type": "Feature",
  "properties": {
    "iso:country":"GB",
    "wof:name":"CM5 5AH",
    "wof:placetype":"postalcode"
},
  "geometry": {"coordinates":[0.24516431659174,51.70381191352903],"type":"Point"}
}