{
  "type": "Feature",
  "properties": {
    "iso:country":"GB",
    "wof:name":"G33 3RH",
    "wof:placetype":"postalcode"
},
  "geometry": {"coordinates":[-4.1710756431561,55.87085728931513],"type":"Point"}
}