{
  "type": "Feature",
  "properties": {
    "date:inception_lower": "2001-12-01",
    "date:inception_upper": "2001-12-01",
    "iso:country": "GB",
    "wof:name": "G33 3RH",
    "wof:placetype": "postalcode"
  },
  "geometry": {"coordinates":[-4.171076,55.870857],"type":"Point"}
}
