{
  "type": "Feature",
  "properties": {
    "iso:country":"GB",
    "wof:name":"GU47 0YB",
    "wof:placetype":"postalcode"
},
  "geometry": {"coordinates":[-0.78273270232046,51.34761236067077],"type":"Point"}
}