{
  "type": "Feature",
  "properties": {
    "iso:country": "GB",
    "wof:name": "NW2 6PR",
    "wof:placetype": "postalcode"
  },
  "geometry": {"coordinates":[-0.224445,51.559286],"type":"Point"}
}
