{
  "type": "Feature",
  "properties": {
    "date:inception_lower": "1980-01-01",
    "date:inception_upper": "1980-01-01",
    "iso:country": "GB",
    "wof:name": "NW2 6PR",
    "wof:placetype": "postalcode"
  },
  "geometry": {"coordinates":[-0.224445,51.559286],"type":"Point"}
}
