{
  "type": "Feature",
  "properties": {
    "date:inception_lower": "1980-01-01",
    "date:inception_upper": "1980-01-01",
    "iso:country": "GB",
    "wof:name": "SA18 3YR",
    "wof:placetype": "postalcode"
  },
  "geometry": {"coordinates":[-4.007941,51.81873],"type":"Point"}
}
