{
  "type": "Feature",
  "properties": {
    "iso:country":"GB",
    "wof:name":"TD15 1EJ",
    "wof:placetype":"postalcode"
},
  "geometry": {"coordinates":[-2.00222153228651,55.76844209022988],"type":"Point"}
}