{
  "type": "Feature",
  "properties": {
    "date:inception_lower": "1980-01-01",
    "date:inception_upper": "1980-01-01",
    "iso:country": "GB",
    "wof:name": "PE7 1QR",
    "wof:placetype": "postalcode"
  },
  "geometry": {"coordinates":[-0.141929,52.56272],"type":"Point"}
}
