{
  "type": "Feature",
  "properties": {
    "date:inception_lower": "1980-01-01",
    "date:inception_upper": "1980-01-01",
    "iso:country": "GB",
    "wof:name": "BD22 7AX",
    "wof:placetype": "postalcode"
  },
  "geometry": {"coordinates":[-1.924906,53.848304],"type":"Point"}
}
