{
  "type": "Feature",
  "properties": {
    "iso:country":"GB",
    "wof:name":"BD22 7AX",
    "wof:placetype":"postalcode"
},
  "geometry": {"coordinates":[-1.92490582068851,53.84830361734785],"type":"Point"}
}