{
  "type": "Feature",
  "properties": {
    "iso:country": "GB",
    "wof:name": "LL13 9UA",
    "wof:placetype": "postalcode"
  },
  "geometry": {"coordinates":[-2.921449,53.046624],"type":"Point"}
}
