{
  "type": "Feature",
  "properties": {
    "iso:country":"GB",
    "wof:name":"SE28 0AN",
    "wof:placetype":"postalcode"
},
  "geometry": {"coordinates":[0.07925707554583,51.49262490600879],"type":"Point"}
}