{
  "type": "Feature",
  "properties": {
    "iso:country": "GB",
    "wof:name": "SE28 0AN",
    "wof:placetype": "postalcode"
  },
  "geometry": {"coordinates":[0.079257,51.492625],"type":"Point"}
}
