{
  "type": "Feature",
  "properties": {
    "iso:country":"GB",
    "wof:name":"SO18 2FF",
    "wof:placetype":"postalcode"
},
  "geometry": {"coordinates":[-1.3568490040928,50.92901776948296],"type":"Point"}
}