{
  "type": "Feature",
  "properties": {
    "iso:country":"GB",
    "wof:name":"EC2R 6AB",
    "wof:placetype":"postalcode"
},
  "geometry": {"coordinates":[-0.08985044695824,51.5150693662618],"type":"Point"}
}