{
  "type": "Feature",
  "properties": {
    "iso:country": "GB",
    "wof:name": "EC2R 6AB",
    "wof:placetype": "postalcode"
  },
  "geometry": {"coordinates":[-0.08985,51.515069],"type":"Point"}
}
