{
  "type": "Feature",
  "properties": {
    "iso:country":"GB",
    "wof:name":"EX7 0DT",
    "wof:placetype":"postalcode"
},
  "geometry": {"coordinates":[-3.46958533673187,50.584524467229],"type":"Point"}
}