{
  "type": "Feature",
  "properties": {
    "iso:country":"GB",
    "wof:name":"GU34 4FE",
    "wof:placetype":"postalcode"
},
  "geometry": {"coordinates":[-0.9216635389932,51.17880549003839],"type":"Point"}
}