{
  "type": "Feature",
  "properties": {
    "date:inception_lower": "2019-06-01",
    "date:inception_upper": "2019-06-01",
    "iso:country": "GB",
    "wof:name": "PR25 5BB",
    "wof:placetype": "postalcode"
  },
  "geometry": {"coordinates":[-2.664242,53.702827],"type":"Point"}
}
