{
  "type": "Feature",
  "properties": {
    "date:inception_lower": "1980-01-01",
    "date:inception_upper": "1980-01-01",
    "iso:country": "GB",
    "wof:name": "BL3 5BB",
    "wof:placetype": "postalcode"
  },
  "geometry": {"coordinates":[-2.441185,53.571479],"type":"Point"}
}
