{
  "type": "Feature",
  "properties": {
    "iso:country":"GB",
    "wof:name":"BL3 5BB",
    "wof:placetype":"postalcode"
},
  "geometry": {"coordinates":[-2.44118543545156,53.57147933141149],"type":"Point"}
}