{
  "type": "Feature",
  "properties": {
    "iso:country":"GB",
    "wof:name":"WF6 1WG",
    "wof:placetype":"postalcode"
},
  "geometry": {"coordinates":[-1.39730143874188,53.69533752821127],"type":"Point"}
}