{
  "type": "Feature",
  "properties": {
    "iso:country": "GB",
    "wof:name": "WF6 1WG",
    "wof:placetype": "postalcode"
  },
  "geometry": {"coordinates":[-1.397301,53.695338],"type":"Point"}
}
