{
  "type": "Feature",
  "properties": {
    "iso:country":"GB",
    "wof:name":"WA11 8PX",
    "wof:placetype":"postalcode"
},
  "geometry": {"coordinates":[-2.78096937025891,53.49449036882888],"type":"Point"}
}