{
  "type": "Feature",
  "properties": {
    "date:inception_lower":"1999-06-01",
    "date:inception_upper":"1999-06-30",
    "iso:country":"GB",
    "wof:name":"CH62 9AQ",
    "wof:placetype":"postalcode"
},
  "geometry": {"coordinates":[-2.961423,53.306016],"type":"Point"}
}