{
  "type": "Feature",
  "properties": {
    "iso:country":"GB",
    "wof:name":"EH39 5LF",
    "wof:placetype":"postalcode"
},
  "geometry": {"coordinates":[-2.71042135631245,56.00597544822177],"type":"Point"}
}