{
  "type": "Feature",
  "properties": {
    "date:inception_lower": "1980-01-01",
    "date:inception_upper": "1980-01-01",
    "iso:country": "GB",
    "wof:name": "EH39 5LF",
    "wof:placetype": "postalcode"
  },
  "geometry": {"coordinates":[-2.72376,55.995157],"type":"Point"}
}
