{
  "type": "Feature",
  "properties": {
    "iso:country":"GB",
    "wof:name":"EN9 3EN",
    "wof:placetype":"postalcode"
},
  "geometry": {"coordinates":[0.01776172546402,51.68654535631286],"type":"Point"}
}