{
  "type": "Feature",
  "properties": {
    "iso:country": "GB",
    "wof:name": "EN9 3EN",
    "wof:placetype": "postalcode"
  },
  "geometry": {"coordinates":[0.017762,51.686545],"type":"Point"}
}
