{
  "type": "Feature",
  "properties": {
    "iso:country":"GB",
    "wof:name":"EX2 6LR",
    "wof:placetype":"postalcode"
},
  "geometry": {"coordinates":[-3.50020088367642,50.69835015364907],"type":"Point"}
}