{
  "type": "Feature",
  "properties": {
    "iso:country": "GB",
    "wof:name": "LL55 4BH",
    "wof:placetype": "postalcode"
  },
  "geometry": {"coordinates":[-4.184591,53.148887],"type":"Point"}
}
