{
  "type": "Feature",
  "properties": {
    "iso:country":"GB",
    "wof:name":"LL53 9AR",
    "wof:placetype":"postalcode"
},
  "geometry": {"coordinates":[-4.42340115035214,52.88062875975165],"type":"Point"}
}