{
  "type": "Feature",
  "properties": {
    "date:inception_lower": "2011-07-01",
    "date:inception_upper": "2011-07-01",
    "iso:country": "GB",
    "wof:name": "LL53 9AR",
    "wof:placetype": "postalcode"
  },
  "geometry": {"coordinates":[-4.423401,52.880629],"type":"Point"}
}
