{
  "type": "Feature",
  "properties": {
    "date:inception_lower": "1980-01-01",
    "date:inception_upper": "1980-01-01",
    "iso:country": "GB",
    "wof:name": "SK12 2HE",
    "wof:placetype": "postalcode"
  },
  "geometry": {"coordinates":[-2.028644,53.358868],"type":"Point"}
}
