{
  "type": "Feature",
  "properties": {
    "iso:country":"GB",
    "wof:name":"SK12 2HE",
    "wof:placetype":"postalcode"
},
  "geometry": {"coordinates":[-2.02864394375084,53.35886836000021],"type":"Point"}
}