{
  "type": "Feature",
  "properties": {
    "iso:country":"GB",
    "wof:name":"OX3 8ED",
    "wof:placetype":"postalcode"
},
  "geometry": {"coordinates":[-1.18359664186673,51.76458682895846],"type":"Point"}
}