{
  "type": "Feature",
  "properties": {
    "iso:country":"GB",
    "wof:name":"G12 0QG",
    "wof:placetype":"postalcode"
},
  "geometry": {"coordinates":[-4.29814734989614,55.88643441533267],"type":"Point"}
}