{
  "type": "Feature",
  "properties": {
    "iso:country": "GB",
    "wof:name": "L30 6TU",
    "wof:placetype": "postalcode"
  },
  "geometry": {"coordinates":[-2.959388,53.480751],"type":"Point"}
}
