{
  "type": "Feature",
  "properties": {
    "date:inception_lower": "2022-03-01",
    "date:inception_upper": "2022-03-01",
    "iso:country": "GB",
    "wof:name": "BS35 2FZ",
    "wof:placetype": "postalcode"
  },
  "geometry": {"coordinates":[-2.522185,51.60653],"type":"Point"}
}
