{
  "type": "Feature",
  "properties": {
    "iso:country": "GB",
    "wof:name": "AB52 6TQ",
    "wof:placetype": "postalcode"
  },
  "geometry": {"coordinates":[-2.610143,57.37101],"type":"Point"}
}
