{
  "type": "Feature",
  "properties": {
    "date:inception_lower": "2004-06-01",
    "date:inception_upper": "2004-06-01",
    "iso:country": "GB",
    "wof:name": "L13 3DG",
    "wof:placetype": "postalcode"
  },
  "geometry": {"coordinates":[-2.916856,53.416796],"type":"Point"}
}
