{
  "type": "Feature",
  "properties": {
    "date:inception_lower":"1980-01-01",
    "date:inception_upper":"1980-01-31",
    "iso:country":"GB",
    "wof:name":"ME17 3DD",
    "wof:placetype":"postalcode"
},
  "geometry": {"coordinates":[0.612906,51.213284],"type":"Point"}
}