{
  "type": "Feature",
  "properties": {
    "date:inception_lower": "1980-01-01",
    "date:inception_upper": "1980-01-01",
    "iso:country": "GB",
    "wof:name": "RH2 9BS",
    "wof:placetype": "postalcode"
  },
  "geometry": {"coordinates":[-0.210581,51.238507],"type":"Point"}
}
