{
  "type": "Feature",
  "properties": {
    "date:inception_lower": "1980-01-01",
    "date:inception_upper": "1980-01-01",
    "iso:country": "GB",
    "wof:name": "LE3 3PA",
    "wof:placetype": "postalcode"
  },
  "geometry": {"coordinates":[-1.214489,52.621521],"type":"Point"}
}
