{
  "type": "Feature",
  "properties": {
    "iso:country": "GB",
    "wof:name": "LE3 3PA",
    "wof:placetype": "postalcode"
  },
  "geometry": {"coordinates":[-1.214489,52.621521],"type":"Point"}
}
