{
  "type": "Feature",
  "properties": {
    "iso:country":"GB",
    "wof:name":"BN27 3SH",
    "wof:placetype":"postalcode"
},
  "geometry": {"coordinates":[0.17304316117409,50.88151828769001],"type":"Point"}
}