{
  "type": "Feature",
  "properties": {
    "date:inception_lower":"1980-01-01",
    "date:inception_upper":"1980-01-31",
    "iso:country":"GB",
    "wof:name":"BN27 3SH",
    "wof:placetype":"postalcode"
},
  "geometry": {"coordinates":[0.173117,50.881287],"type":"Point"}
}