{
  "type": "Feature",
  "properties": {
    "iso:country": "GB",
    "wof:name": "BN27 3SH",
    "wof:placetype": "postalcode"
  },
  "geometry": {"coordinates":[0.173117,50.881287],"type":"Point"}
}
