{
  "type": "Feature",
  "properties": {
    "date:inception_lower": "2017-05-01",
    "date:inception_upper": "2017-05-01",
    "iso:country": "GB",
    "wof:name": "PR4 6FD",
    "wof:placetype": "postalcode"
  },
  "geometry": {"coordinates":[-2.830611,53.678877],"type":"Point"}
}
