{
  "type": "Feature",
  "properties": {
    "iso:country": "GB",
    "wof:name": "SS15 6EZ",
    "wof:placetype": "postalcode"
  },
  "geometry": {"coordinates":[0.420906,51.574732],"type":"Point"}
}
