{
  "type": "Feature",
  "properties": {
    "iso:country":"GB",
    "wof:name":"SY22 6HX",
    "wof:placetype":"postalcode"
},
  "geometry": {"coordinates":[-3.30595555472181,52.70094546261898],"type":"Point"}
}