{
  "type": "Feature",
  "properties": {
    "date:inception_lower":"1980-01-01",
    "date:inception_upper":"1980-01-31",
    "iso:country":"GB",
    "wof:name":"SY22 6HX",
    "wof:placetype":"postalcode"
},
  "geometry": {"coordinates":[-3.305956,52.700945],"type":"Point"}
}