{
  "type": "Feature",
  "properties": {
    "iso:country":"GB",
    "wof:name":"HX1 2BB",
    "wof:placetype":"postalcode"
},
  "geometry": {"coordinates":[-1.86452244895449,53.71893165337697],"type":"Point"}
}