{
  "type": "Feature",
  "properties": {
    "iso:country": "GB",
    "wof:name": "HX1 2BB",
    "wof:placetype": "postalcode"
  },
  "geometry": {"coordinates":[-1.864522,53.718932],"type":"Point"}
}
