{
  "type": "Feature",
  "properties": {
    "iso:country": "GB",
    "wof:name": "S8 9HT",
    "wof:placetype": "postalcode"
  },
  "geometry": {"coordinates":[-1.466249,53.352628],"type":"Point"}
}
