{
  "type": "Feature",
  "properties": {
    "iso:country":"GB",
    "wof:name":"S8 9HT",
    "wof:placetype":"postalcode"
},
  "geometry": {"coordinates":[-1.4662488276961,53.35262796126638],"type":"Point"}
}