{
  "type": "Feature",
  "properties": {
    "iso:country":"GB",
    "wof:name":"CT18 7DT",
    "wof:placetype":"postalcode"
},
  "geometry": {"coordinates":[1.1573962616446,51.12682070933605],"type":"Point"}
}