{
  "type": "Feature",
  "properties": {
    "iso:country": "GB",
    "wof:name": "DN22 0EY",
    "wof:placetype": "postalcode"
  },
  "geometry": {"coordinates":[-0.775602,53.308466],"type":"Point"}
}
