{
  "type": "Feature",
  "properties": {
    "iso:country":"GB",
    "wof:name":"DN22 0EY",
    "wof:placetype":"postalcode"
},
  "geometry": {"coordinates":[-0.77560176086667,53.3084658362405],"type":"Point"}
}