{
  "type": "Feature",
  "properties": {
    "iso:country": "GB",
    "wof:name": "OX17 3SG",
    "wof:placetype": "postalcode"
  },
  "geometry": {"coordinates":[-1.278771,52.024231],"type":"Point"}
}
