{
  "type": "Feature",
  "properties": {
    "date:inception_lower": "2014-06-01",
    "date:inception_upper": "2014-06-01",
    "iso:country": "GB",
    "wof:name": "OX17 3SG",
    "wof:placetype": "postalcode"
  },
  "geometry": {"coordinates":[-1.278771,52.024231],"type":"Point"}
}
