{
  "type": "Feature",
  "properties": {
    "date:inception_lower": "2008-06-01",
    "date:inception_upper": "2008-06-01",
    "iso:country": "GB",
    "wof:name": "IP28 6WF",
    "wof:placetype": "postalcode"
  },
  "geometry": {"coordinates":[0.517637,52.309958],"type":"Point"}
}
