{
  "type": "Feature",
  "properties": {
    "iso:country":"GB",
    "wof:name":"IP28 6WF",
    "wof:placetype":"postalcode"
},
  "geometry": {"coordinates":[0.51763685133681,52.30995806555102],"type":"Point"}
}