{
  "type": "Feature",
  "properties": {
    "iso:country":"GB",
    "wof:name":"OX9 3QU",
    "wof:placetype":"postalcode"
},
  "geometry": {"coordinates":[-0.9227491138435,51.74087089624135],"type":"Point"}
}