{
  "type": "Feature",
  "properties": {
    "iso:country":"GB",
    "wof:name":"KA6 7ST",
    "wof:placetype":"postalcode"
},
  "geometry": {"coordinates":[-4.39469164215322,55.3127072676831],"type":"Point"}
}