{
  "type": "Feature",
  "properties": {
    "iso:country": "GB",
    "wof:name": "KA6 7ST",
    "wof:placetype": "postalcode"
  },
  "geometry": {"coordinates":[-4.394692,55.312707],"type":"Point"}
}
