{
  "type": "Feature",
  "properties": {
    "iso:country":"GB",
    "wof:name":"NN8 4BA",
    "wof:placetype":"postalcode"
},
  "geometry": {"coordinates":[-0.682231345611,52.3158911074642],"type":"Point"}
}