{
  "type": "Feature",
  "properties": {
    "iso:country":"GB",
    "wof:name":"BB8 7JG",
    "wof:placetype":"postalcode"
},
  "geometry": {"coordinates":[-2.13089554029174,53.86276170455092],"type":"Point"}
}