{
  "type": "Feature",
  "properties": {
    "date:inception_lower": "2003-06-01",
    "date:inception_upper": "2003-06-01",
    "iso:country": "GB",
    "wof:name": "BB8 7JG",
    "wof:placetype": "postalcode"
  },
  "geometry": {"coordinates":[-2.130895,53.862762],"type":"Point"}
}
