{
  "type": "Feature",
  "properties": {
    "date:inception_lower": "1990-02-01",
    "date:inception_upper": "1990-02-01",
    "iso:country": "GB",
    "wof:name": "NG9 7AU",
    "wof:placetype": "postalcode"
  },
  "geometry": {"coordinates":[-1.276986,52.926832],"type":"Point"}
}
