{
  "type": "Feature",
  "properties": {
    "iso:country":"GB",
    "wof:name":"M20 4UA",
    "wof:placetype":"postalcode"
},
  "geometry": {"coordinates":[-2.22172476870262,53.42649331732026],"type":"Point"}
}