{
  "type": "Feature",
  "properties": {
    "iso:country": "GB",
    "wof:name": "GL12 7HT",
    "wof:placetype": "postalcode"
  },
  "geometry": {"coordinates":[-2.341543,51.637576],"type":"Point"}
}
