{
  "type": "Feature",
  "properties": {
    "iso:country": "GB",
    "wof:name": "LL60 6DZ",
    "wof:placetype": "postalcode"
  },
  "geometry": {"coordinates":[-4.256062,53.210751],"type":"Point"}
}
