{
  "type": "Feature",
  "properties": {
    "date:inception_lower": "2009-09-01",
    "date:inception_upper": "2009-09-01",
    "iso:country": "GB",
    "wof:name": "LL60 6DZ",
    "wof:placetype": "postalcode"
  },
  "geometry": {"coordinates":[-4.256062,53.210751],"type":"Point"}
}
