{
  "type": "Feature",
  "properties": {
    "iso:country":"GB",
    "wof:name":"LL60 6DZ",
    "wof:placetype":"postalcode"
},
  "geometry": {"coordinates":[-4.25606164214586,53.21075088427084],"type":"Point"}
}