{
  "type": "Feature",
  "properties": {
    "iso:country":"GB",
    "wof:name":"BB4 8QH",
    "wof:placetype":"postalcode"
},
  "geometry": {"coordinates":[-2.28593098054381,53.73382909401202],"type":"Point"}
}