{
  "type": "Feature",
  "properties": {
    "iso:country": "GB",
    "wof:name": "DE21 5AU",
    "wof:placetype": "postalcode"
  },
  "geometry": {"coordinates":[-1.451761,52.977297],"type":"Point"}
}
