{
  "type": "Feature",
  "properties": {
    "date:inception_lower":"1980-11-01",
    "date:inception_upper":"1980-11-30",
    "iso:country":"GB",
    "wof:name":"ZE2 9ET",
    "wof:placetype":"postalcode"
},
  "geometry": {"coordinates":[-1.11173,60.143929],"type":"Point"}
}