{
  "type": "Feature",
  "properties": {
    "iso:country":"GB",
    "wof:name":"ZE2 9ET",
    "wof:placetype":"postalcode"
},
  "geometry": {"coordinates":[-1.11172961594764,60.14392884125948],"type":"Point"}
}