{
  "type": "Feature",
  "properties": {
    "iso:country": "GB",
    "wof:name": "ZE2 9ET",
    "wof:placetype": "postalcode"
  },
  "geometry": {"coordinates":[-1.11173,60.143929],"type":"Point"}
}
