{
  "type": "Feature",
  "properties": {
    "iso:country":"GB",
    "wof:name":"HX3 9LT",
    "wof:placetype":"postalcode"
},
  "geometry": {"coordinates":[-1.84899588199734,53.70465800956042],"type":"Point"}
}