{
  "type": "Feature",
  "properties": {
    "iso:country": "GB",
    "wof:name": "NP22 4RB",
    "wof:placetype": "postalcode"
  },
  "geometry": {"coordinates":[-3.238652,51.775017],"type":"Point"}
}
