{
  "type": "Feature",
  "properties": {
    "date:inception_lower": "1999-12-01",
    "date:inception_upper": "1999-12-01",
    "iso:country": "GB",
    "wof:name": "IP22 4XU",
    "wof:placetype": "postalcode"
  },
  "geometry": {"coordinates":[1.099169,52.390835],"type":"Point"}
}
