{
  "type": "Feature",
  "properties": {
    "iso:country":"GB",
    "wof:name":"IP22 4XU",
    "wof:placetype":"postalcode"
},
  "geometry": {"coordinates":[1.10157261902719,52.38860192619971],"type":"Point"}
}