{
  "type": "Feature",
  "properties": {
    "date:inception_lower": "2023-02-01",
    "date:inception_upper": "2023-02-01",
    "iso:country": "GB",
    "wof:name": "EX23 8TE",
    "wof:placetype": "postalcode"
  },
  "geometry": {"coordinates":[-4.52298,50.828581],"type":"Point"}
}
