{
  "type": "Feature",
  "properties": {
    "iso:country": "GB",
    "wof:name": "DE4 3SW",
    "wof:placetype": "postalcode"
  },
  "geometry": {"coordinates":[-1.564224,53.139208],"type":"Point"}
}
