{
  "type": "Feature",
  "properties": {
    "iso:country":"GB",
    "wof:name":"DE4 3SW",
    "wof:placetype":"postalcode"
},
  "geometry": {"coordinates":[-1.56422426782197,53.13920758252511],"type":"Point"}
}