{
  "type": "Feature",
  "properties": {
    "iso:country":"GB",
    "wof:name":"DN20 8LW",
    "wof:placetype":"postalcode"
},
  "geometry": {"coordinates":[-0.49380129028355,53.55059779602037],"type":"Point"}
}