{
  "type": "Feature",
  "properties": {
    "iso:country":"GB",
    "wof:name":"PE9 4HL",
    "wof:placetype":"postalcode"
},
  "geometry": {"coordinates":[-0.47105439482307,52.6855278957274],"type":"Point"}
}