{
  "type": "Feature",
  "properties": {
    "iso:country":"GB",
    "wof:name":"BN22 8TL",
    "wof:placetype":"postalcode"
},
  "geometry": {"coordinates":[0.29047018693524,50.7839816091671],"type":"Point"}
}