{
  "type": "Feature",
  "properties": {
    "date:inception_lower":"2004-07-01",
    "date:inception_upper":"2004-07-31",
    "iso:country":"GB",
    "wof:name":"BH8 8PT",
    "wof:placetype":"postalcode"
},
  "geometry": {"coordinates":[-1.860223,50.737149],"type":"Point"}
}