{
  "type": "Feature",
  "properties": {
    "iso:country":"GB",
    "wof:name":"PR9 8QJ",
    "wof:placetype":"postalcode"
},
  "geometry": {"coordinates":[-2.9538409567676,53.66783998189393],"type":"Point"}
}