{
  "type": "Feature",
  "properties": {
    "iso:country":"GB",
    "wof:name":"G78 1TA",
    "wof:placetype":"postalcode"
},
  "geometry": {"coordinates":[-4.37534410688352,55.80589414120641],"type":"Point"}
}