{
  "type": "Feature",
  "properties": {
    "iso:country": "GB",
    "wof:name": "G78 1TA",
    "wof:placetype": "postalcode"
  },
  "geometry": {"coordinates":[-4.375344,55.805894],"type":"Point"}
}
