{
  "type": "Feature",
  "properties": {
    "iso:country":"GB",
    "wof:name":"CA10 3DR",
    "wof:placetype":"postalcode"
},
  "geometry": {"coordinates":[-2.68204273465329,54.60027802001897],"type":"Point"}
}