{
  "type": "Feature",
  "properties": {
    "iso:country":"GB",
    "wof:name":"BN3 8EW",
    "wof:placetype":"postalcode"
},
  "geometry": {"coordinates":[-0.20155184688382,50.85285382176218],"type":"Point"}
}