{
  "type": "Feature",
  "properties": {
    "iso:country": "GB",
    "wof:name": "BN3 8EW",
    "wof:placetype": "postalcode"
  },
  "geometry": {"coordinates":[-0.201552,50.852854],"type":"Point"}
}
