{
  "type": "Feature",
  "properties": {
    "iso:country": "GB",
    "wof:name": "NG31 7SH",
    "wof:placetype": "postalcode"
  },
  "geometry": {"coordinates":[-0.650329,52.902695],"type":"Point"}
}
