{
  "type": "Feature",
  "properties": {
    "iso:country":"GB",
    "wof:name":"MK6 2JY",
    "wof:placetype":"postalcode"
},
  "geometry": {"coordinates":[-0.75768860884487,52.03371863876202],"type":"Point"}
}