{
  "type": "Feature",
  "properties": {
    "iso:country":"GB",
    "wof:name":"WA4 5DY",
    "wof:placetype":"postalcode"
},
  "geometry": {"coordinates":[-2.57214294740934,53.34895102796862],"type":"Point"}
}