{
  "type": "Feature",
  "properties": {
    "iso:country":"GB",
    "wof:name":"NE61 2JT",
    "wof:placetype":"postalcode"
},
  "geometry": {"coordinates":[-1.69951507234603,55.16142781406997],"type":"Point"}
}