{
  "type": "Feature",
  "properties": {
    "iso:country":"GB",
    "wof:name":"DY2 7LP",
    "wof:placetype":"postalcode"
},
  "geometry": {"coordinates":[-2.06678744117478,52.50809074687314],"type":"Point"}
}