{
  "type": "Feature",
  "properties": {
    "iso:country":"GB",
    "wof:name":"BA11 5JQ",
    "wof:placetype":"postalcode"
},
  "geometry": {"coordinates":[-2.30066207976832,51.22985586851004],"type":"Point"}
}