{
  "type": "Feature",
  "properties": {
    "iso:country": "GB",
    "wof:name": "BA11 5JQ",
    "wof:placetype": "postalcode"
  },
  "geometry": {"coordinates":[-2.300662,51.229856],"type":"Point"}
}
