{
  "type": "Feature",
  "properties": {
    "iso:country": "GB",
    "wof:name": "NE46 2JA",
    "wof:placetype": "postalcode"
  },
  "geometry": {"coordinates":[-2.115331,54.960437],"type":"Point"}
}
