{
  "type": "Feature",
  "properties": {
    "iso:country":"GB",
    "wof:name":"NE46 2JA",
    "wof:placetype":"postalcode"
},
  "geometry": {"coordinates":[-2.11533125687095,54.96043670185518],"type":"Point"}
}