{
  "type": "Feature",
  "properties": {
    "iso:country": "GB",
    "wof:name": "B45 0HR",
    "wof:placetype": "postalcode"
  },
  "geometry": {"coordinates":[-2.020856,52.401765],"type":"Point"}
}
