{
  "type": "Feature",
  "properties": {
    "iso:country": "GB",
    "wof:name": "CA22 2NF",
    "wof:placetype": "postalcode"
  },
  "geometry": {"coordinates":[-3.544596,54.476903],"type":"Point"}
}
