{
  "type": "Feature",
  "properties": {
    "iso:country":"GB",
    "wof:name":"NE38 7AD",
    "wof:placetype":"postalcode"
},
  "geometry": {"coordinates":[-1.51438399979637,54.90281914495363],"type":"Point"}
}