{
  "type": "Feature",
  "properties": {
    "iso:country": "GB",
    "wof:name": "FY4 4SN",
    "wof:placetype": "postalcode"
  },
  "geometry": {"coordinates":[-2.99264,53.799322],"type":"Point"}
}
