{
  "type": "Feature",
  "properties": {
    "iso:country":"GB",
    "wof:name":"BR1 4QB",
    "wof:placetype":"postalcode"
},
  "geometry": {"coordinates":[0.00390733794207,51.42476456262913],"type":"Point"}
}