{
  "type": "Feature",
  "properties": {
    "date:inception_lower": "1980-01-01",
    "date:inception_upper": "1980-01-01",
    "iso:country": "GB",
    "wof:name": "SK11 7RL",
    "wof:placetype": "postalcode"
  },
  "geometry": {"coordinates":[-2.12337,53.247024],"type":"Point"}
}
