{
  "type": "Feature",
  "properties": {
    "iso:country":"GB",
    "wof:name":"IP13 6DA",
    "wof:placetype":"postalcode"
},
  "geometry": {"coordinates":[1.34548280439212,52.1208351744964],"type":"Point"}
}