{
  "type": "Feature",
  "properties": {
    "iso:country": "GB",
    "wof:name": "IP13 6DA",
    "wof:placetype": "postalcode"
  },
  "geometry": {"coordinates":[1.345467,52.120825],"type":"Point"}
}
