{
  "type": "Feature",
  "properties": {
    "date:inception_lower":"2009-06-01",
    "date:inception_upper":"2009-06-30",
    "iso:country":"GB",
    "wof:name":"IP13 6DA",
    "wof:placetype":"postalcode"
},
  "geometry": {"coordinates":[1.345467,52.120825],"type":"Point"}
}