{
  "type": "Feature",
  "properties": {
    "iso:country":"GB",
    "wof:name":"SL1 3WE",
    "wof:placetype":"postalcode"
},
  "geometry": {"coordinates":[-0.62030149986172,51.51527815423157],"type":"Point"}
}