{
  "type": "Feature",
  "properties": {
    "date:inception_lower": "2001-06-01",
    "date:inception_upper": "2001-06-01",
    "iso:country": "GB",
    "wof:name": "SL1 3WE",
    "wof:placetype": "postalcode"
  },
  "geometry": {"coordinates":[-0.620301,51.515278],"type":"Point"}
}
