{
  "type": "Feature",
  "properties": {
    "iso:country":"GB",
    "wof:name":"BN1 9QG",
    "wof:placetype":"postalcode"
},
  "geometry": {"coordinates":[-0.08529872897177,50.86450336591729],"type":"Point"}
}