{
  "type": "Feature",
  "properties": {
    "iso:country": "GB",
    "wof:name": "CA3 9AU",
    "wof:placetype": "postalcode"
  },
  "geometry": {"coordinates":[-2.923772,54.908929],"type":"Point"}
}
