{
  "type": "Feature",
  "properties": {
    "iso:country":"GB",
    "wof:name":"CA3 9AU",
    "wof:placetype":"postalcode"
},
  "geometry": {"coordinates":[-2.92377242908759,54.90892936228416],"type":"Point"}
}