{
  "type": "Feature",
  "properties": {
    "iso:country": "GB",
    "wof:name": "SO15 3EH",
    "wof:placetype": "postalcode"
  },
  "geometry": {"coordinates":[-1.426696,50.91592],"type":"Point"}
}
