{
  "type": "Feature",
  "properties": {
    "date:inception_lower": "1994-12-01",
    "date:inception_upper": "1994-12-01",
    "iso:country": "GB",
    "wof:name": "SO15 3EH",
    "wof:placetype": "postalcode"
  },
  "geometry": {"coordinates":[-1.426696,50.91592],"type":"Point"}
}
