{
  "type": "Feature",
  "properties": {
    "iso:country": "GB",
    "wof:name": "BN12 6FJ",
    "wof:placetype": "postalcode"
  },
  "geometry": {"coordinates":[-0.455637,50.819235],"type":"Point"}
}
