{
  "type": "Feature",
  "properties": {
    "date:inception_lower": "2020-09-01",
    "date:inception_upper": "2020-09-01",
    "iso:country": "GB",
    "wof:name": "LU2 8EG",
    "wof:placetype": "postalcode"
  },
  "geometry": {"coordinates":[-0.371192,51.921433],"type":"Point"}
}
