{
  "type": "Feature",
  "properties": {
    "date:inception_lower":"1991-09-01",
    "date:inception_upper":"1991-09-30",
    "iso:country":"GB",
    "wof:name":"RG27 9SR",
    "wof:placetype":"postalcode"
},
  "geometry": {"coordinates":[-0.971386,51.283832],"type":"Point"}
}