{
  "type": "Feature",
  "properties": {
    "iso:country":"GB",
    "wof:name":"RG27 9SR",
    "wof:placetype":"postalcode"
},
  "geometry": {"coordinates":[-0.97138578691742,51.28383229134351],"type":"Point"}
}