{
  "type": "Feature",
  "properties": {
    "iso:country": "GB",
    "wof:name": "SY8 3HL",
    "wof:placetype": "postalcode"
  },
  "geometry": {"coordinates":[-2.631945,52.391586],"type":"Point"}
}
