{
  "type": "Feature",
  "properties": {
    "iso:country":"GB",
    "wof:name":"SY8 3HL",
    "wof:placetype":"postalcode"
},
  "geometry": {"coordinates":[-2.63200619442944,52.39161659580134],"type":"Point"}
}