{
  "type": "Feature",
  "properties": {
    "iso:country":"GB",
    "wof:name":"SA73 1GA",
    "wof:placetype":"postalcode"
},
  "geometry": {"coordinates":[-4.95073587522082,51.71141904286414],"type":"Point"}
}