{
  "type": "Feature",
  "properties": {
    "date:inception_lower":"2009-06-01",
    "date:inception_upper":"2009-06-30",
    "iso:country":"GB",
    "wof:name":"SA73 1GA",
    "wof:placetype":"postalcode"
},
  "geometry": {"coordinates":[-4.950736,51.711419],"type":"Point"}
}