{
  "type": "Feature",
  "properties": {
    "iso:country":"GB",
    "wof:name":"CV5 9PQ",
    "wof:placetype":"postalcode"
},
  "geometry": {"coordinates":[-1.56009054425413,52.43535482962631],"type":"Point"}
}