{
  "type": "Feature",
  "properties": {
    "iso:country": "GB",
    "wof:name": "TN39 3GD",
    "wof:placetype": "postalcode"
  },
  "geometry": {"coordinates":[0.469491,50.84541],"type":"Point"}
}
