{
  "type": "Feature",
  "properties": {
    "iso:country":"GB",
    "wof:name":"PL26 6UD",
    "wof:placetype":"postalcode"
},
  "geometry": {"coordinates":[-4.78778040223233,50.27030756169811],"type":"Point"}
}