{
  "type": "Feature",
  "properties": {
    "date:inception_lower": "2016-10-01",
    "date:inception_upper": "2016-10-01",
    "iso:country": "GB",
    "wof:name": "CW5 5WB",
    "wof:placetype": "postalcode"
  },
  "geometry": {"coordinates":[-2.535811,53.059116],"type":"Point"}
}
