{
  "type": "Feature",
  "properties": {
    "iso:country": "GB",
    "wof:name": "L7 7ET",
    "wof:placetype": "postalcode"
  },
  "geometry": {"coordinates":[-2.96143,53.397776],"type":"Point"}
}
