{
  "type": "Feature",
  "properties": {
    "date:inception_lower":"1980-01-01",
    "date:inception_upper":"1980-01-31",
    "iso:country":"GB",
    "wof:name":"L7 7ET",
    "wof:placetype":"postalcode"
},
  "geometry": {"coordinates":[-2.96143,53.397776],"type":"Point"}
}