{
  "type": "Feature",
  "properties": {
    "iso:country":"GB",
    "wof:name":"IP1 6EJ",
    "wof:placetype":"postalcode"
},
  "geometry": {"coordinates":[1.13213584835492,52.08092174139023],"type":"Point"}
}