{
  "type": "Feature",
  "properties": {
    "iso:country": "GB",
    "wof:name": "BS37 8QD",
    "wof:placetype": "postalcode"
  },
  "geometry": {"coordinates":[-2.437287,51.51438],"type":"Point"}
}
