{
  "type": "Feature",
  "properties": {
    "iso:country": "GB",
    "wof:name": "CH3 7HW",
    "wof:placetype": "postalcode"
  },
  "geometry": {"coordinates":[-2.801037,53.205515],"type":"Point"}
}
