{
  "type": "Feature",
  "properties": {
    "iso:country":"GB",
    "wof:name":"CH3 7HW",
    "wof:placetype":"postalcode"
},
  "geometry": {"coordinates":[-2.79671468293399,53.20983447413605],"type":"Point"}
}