{
  "type": "Feature",
  "properties": {
    "iso:country": "GB",
    "wof:name": "NE63 8BJ",
    "wof:placetype": "postalcode"
  },
  "geometry": {"coordinates":[-1.572093,55.17822],"type":"Point"}
}
