{
  "type": "Feature",
  "properties": {
    "date:inception_lower": "1980-01-01",
    "date:inception_upper": "1980-01-01",
    "iso:country": "GB",
    "wof:name": "GU26 6HA",
    "wof:placetype": "postalcode"
  },
  "geometry": {"coordinates":[-0.746567,51.106807],"type":"Point"}
}
