{
  "type": "Feature",
  "properties": {
    "iso:country":"GB",
    "wof:name":"GU26 6HA",
    "wof:placetype":"postalcode"
},
  "geometry": {"coordinates":[-0.74658651486619,51.10681184862499],"type":"Point"}
}