{
  "type": "Feature",
  "properties": {
    "iso:country": "GB",
    "wof:name": "NE34 0LJ",
    "wof:placetype": "postalcode"
  },
  "geometry": {"coordinates":[-1.437205,54.967683],"type":"Point"}
}
