{
  "type": "Feature",
  "properties": {
    "iso:country":"GB",
    "wof:name":"NE34 0LJ",
    "wof:placetype":"postalcode"
},
  "geometry": {"coordinates":[-1.43720536673577,54.96768270301724],"type":"Point"}
}