{
  "type": "Feature",
  "properties": {
    "iso:country":"GB",
    "wof:name":"HU8 9DF",
    "wof:placetype":"postalcode"
},
  "geometry": {"coordinates":[-0.28420559404398,53.77089936857694],"type":"Point"}
}