{
  "type": "Feature",
  "properties": {
    "iso:country": "GB",
    "wof:name": "NR2 3HX",
    "wof:placetype": "postalcode"
  },
  "geometry": {"coordinates":[1.272349,52.628874],"type":"Point"}
}
