{
  "type": "Feature",
  "properties": {
    "date:inception_lower": "1980-01-01",
    "date:inception_upper": "1980-01-01",
    "iso:country": "GB",
    "wof:name": "NR2 3HX",
    "wof:placetype": "postalcode"
  },
  "geometry": {"coordinates":[1.272349,52.628874],"type":"Point"}
}
