{
  "type": "Feature",
  "properties": {
    "iso:country": "GB",
    "wof:name": "GL20 8SY",
    "wof:placetype": "postalcode"
  },
  "geometry": {"coordinates":[-2.119765,52.007379],"type":"Point"}
}
