{
  "type": "Feature",
  "properties": {
    "iso:country":"GB",
    "wof:name":"MK43 0UA",
    "wof:placetype":"postalcode"
},
  "geometry": {"coordinates":[-0.57829290772362,52.0148320176397],"type":"Point"}
}