{
  "type": "Feature",
  "properties": {
    "iso:country": "GB",
    "wof:name": "MK43 0UA",
    "wof:placetype": "postalcode"
  },
  "geometry": {"coordinates":[-0.578293,52.014832],"type":"Point"}
}
