{
  "type": "Feature",
  "properties": {
    "date:inception_lower": "2008-09-01",
    "date:inception_upper": "2008-09-01",
    "iso:country": "GB",
    "wof:name": "IP31 3GA",
    "wof:placetype": "postalcode"
  },
  "geometry": {"coordinates":[0.940819,52.302926],"type":"Point"}
}
