{
  "type": "Feature",
  "properties": {
    "iso:country": "GB",
    "wof:name": "TQ5 9LQ",
    "wof:placetype": "postalcode"
  },
  "geometry": {"coordinates":[-3.52166,50.387239],"type":"Point"}
}
