{
  "type": "Feature",
  "properties": {
    "iso:country":"GB",
    "wof:name":"TQ5 9LQ",
    "wof:placetype":"postalcode"
},
  "geometry": {"coordinates":[-3.52164529521793,50.38725489420352],"type":"Point"}
}