{
  "type": "Feature",
  "properties": {
    "date:inception_lower": "2001-06-01",
    "date:inception_upper": "2001-06-01",
    "iso:country": "GB",
    "wof:name": "BS41 9JA",
    "wof:placetype": "postalcode"
  },
  "geometry": {"coordinates":[-2.646227,51.43669],"type":"Point"}
}
