{
  "type": "Feature",
  "properties": {
    "iso:country":"GB",
    "wof:name":"CV34 5DS",
    "wof:placetype":"postalcode"
},
  "geometry": {"coordinates":[-1.59704661526659,52.29090615746151],"type":"Point"}
}