{
  "type": "Feature",
  "properties": {
    "iso:country":"GB",
    "wof:name":"DN36 5RH",
    "wof:placetype":"postalcode"
},
  "geometry": {"coordinates":[-0.05413166512398,53.46455627592489],"type":"Point"}
}