{
  "type": "Feature",
  "properties": {
    "date:inception_lower": "1980-01-01",
    "date:inception_upper": "1980-01-01",
    "iso:country": "GB",
    "wof:name": "DN36 5RH",
    "wof:placetype": "postalcode"
  },
  "geometry": {"coordinates":[-0.05412,53.464572],"type":"Point"}
}
