{
  "type": "Feature",
  "properties": {
    "iso:country":"GB",
    "wof:name":"LS10 3UY",
    "wof:placetype":"postalcode"
},
  "geometry": {"coordinates":[-1.5343046273825,53.76520182199523],"type":"Point"}
}