{
  "type": "Feature",
  "properties": {
    "date:inception_lower": "1980-01-01",
    "date:inception_upper": "1980-01-01",
    "iso:country": "GB",
    "wof:name": "NP7 9SY",
    "wof:placetype": "postalcode"
  },
  "geometry": {"coordinates":[-2.978334,51.803416],"type":"Point"}
}
