{
  "type": "Feature",
  "properties": {
    "iso:country":"GB",
    "wof:name":"NP7 9SY",
    "wof:placetype":"postalcode"
},
  "geometry": {"coordinates":[-2.97470601300689,51.80158092772638],"type":"Point"}
}