{
  "type": "Feature",
  "properties": {
    "date:inception_lower": "1980-01-01",
    "date:inception_upper": "1980-01-01",
    "iso:country": "GB",
    "wof:name": "BH24 3BA",
    "wof:placetype": "postalcode"
  },
  "geometry": {"coordinates":[-1.786562,50.841864],"type":"Point"}
}
