{
  "type": "Feature",
  "properties": {
    "iso:country": "GB",
    "wof:name": "BH24 3BA",
    "wof:placetype": "postalcode"
  },
  "geometry": {"coordinates":[-1.786562,50.841864],"type":"Point"}
}
