{
  "type": "Feature",
  "properties": {
    "iso:country": "GB",
    "wof:name": "NN10 9QQ",
    "wof:placetype": "postalcode"
  },
  "geometry": {"coordinates":[-0.615088,52.288492],"type":"Point"}
}
