{
  "type": "Feature",
  "properties": {
    "iso:country": "GB",
    "wof:name": "TN10 3PU",
    "wof:placetype": "postalcode"
  },
  "geometry": {"coordinates":[0.286574,51.216863],"type":"Point"}
}
