{
  "type": "Feature",
  "properties": {
    "iso:country":"GB",
    "wof:name":"SE12 8JP",
    "wof:placetype":"postalcode"
},
  "geometry": {"coordinates":[0.02454093279364,51.45484158312339],"type":"Point"}
}