{
  "type": "Feature",
  "properties": {
    "date:inception_lower": "1980-01-01",
    "date:inception_upper": "1980-01-01",
    "iso:country": "GB",
    "wof:name": "SE12 8JP",
    "wof:placetype": "postalcode"
  },
  "geometry": {"coordinates":[0.024541,51.454842],"type":"Point"}
}
