{
  "type": "Feature",
  "properties": {
    "iso:country":"GB",
    "wof:name":"WF6 1AU",
    "wof:placetype":"postalcode"
},
  "geometry": {"coordinates":[-1.42311784818278,53.69577017586236],"type":"Point"}
}