{
  "type": "Feature",
  "properties": {
    "date:inception_lower": "1980-01-01",
    "date:inception_upper": "1980-01-01",
    "iso:country": "GB",
    "wof:name": "WF6 1AU",
    "wof:placetype": "postalcode"
  },
  "geometry": {"coordinates":[-1.423118,53.69577],"type":"Point"}
}
