{
  "type": "Feature",
  "properties": {
    "iso:country":"GB",
    "wof:name":"OX3 9PQ",
    "wof:placetype":"postalcode"
},
  "geometry": {"coordinates":[-1.19346595985523,51.76695669833776],"type":"Point"}
}