{
  "type": "Feature",
  "properties": {
    "date:inception_lower":"2013-10-01",
    "date:inception_upper":"2013-10-31",
    "iso:country":"GB",
    "wof:name":"SL4 1AG",
    "wof:placetype":"postalcode"
},
  "geometry": {"coordinates":[-0.611699,51.480602],"type":"Point"}
}