{
  "type": "Feature",
  "properties": {
    "iso:country": "GB",
    "wof:name": "SL4 1AG",
    "wof:placetype": "postalcode"
  },
  "geometry": {"coordinates":[-0.611699,51.480602],"type":"Point"}
}
