{
  "type": "Feature",
  "properties": {
    "iso:country":"GB",
    "wof:name":"SL4 1AG",
    "wof:placetype":"postalcode"
},
  "geometry": {"coordinates":[-0.61169937512802,51.48060220952707],"type":"Point"}
}