{
  "type": "Feature",
  "properties": {
    "iso:country":"GB",
    "wof:name":"SO22 4NL",
    "wof:placetype":"postalcode"
},
  "geometry": {"coordinates":[-1.32623128478429,51.05772392074084],"type":"Point"}
}