{
  "type": "Feature",
  "properties": {
    "date:inception_lower": "1980-01-01",
    "date:inception_upper": "1980-01-01",
    "iso:country": "GB",
    "wof:name": "SO22 4NL",
    "wof:placetype": "postalcode"
  },
  "geometry": {"coordinates":[-1.326231,51.057724],"type":"Point"}
}
