{
  "type": "Feature",
  "properties": {
    "iso:country":"GB",
    "wof:name":"TS24 7PH",
    "wof:placetype":"postalcode"
},
  "geometry": {"coordinates":[-1.21562269651991,54.68234148982888],"type":"Point"}
}