{
  "type": "Feature",
  "properties": {
    "iso:country":"GB",
    "wof:name":"TA20 2NP",
    "wof:placetype":"postalcode"
},
  "geometry": {"coordinates":[-2.96080930108373,50.84842535309671],"type":"Point"}
}