{
  "type": "Feature",
  "properties": {
    "date:inception_lower": "2013-11-01",
    "date:inception_upper": "2013-11-01",
    "iso:country": "GB",
    "wof:name": "TA20 2NP",
    "wof:placetype": "postalcode"
  },
  "geometry": {"coordinates":[-2.960809,50.848425],"type":"Point"}
}
