{
  "type": "Feature",
  "properties": {
    "iso:country":"GB",
    "wof:name":"SE25 6TB",
    "wof:placetype":"postalcode"
},
  "geometry": {"coordinates":[-0.08923921142218,51.40698588866729],"type":"Point"}
}