{
  "type": "Feature",
  "properties": {
    "iso:country":"GB",
    "wof:name":"NG15 9AD",
    "wof:placetype":"postalcode"
},
  "geometry": {"coordinates":[-1.16596535151059,53.08095612622233],"type":"Point"}
}