{
  "type": "Feature",
  "properties": {
    "iso:country":"GB",
    "wof:name":"CV8 1FR",
    "wof:placetype":"postalcode"
},
  "geometry": {"coordinates":[-1.57767406675145,52.3345941867188],"type":"Point"}
}