{
  "type": "Feature",
  "properties": {
    "date:inception_lower":"1983-08-01",
    "date:inception_upper":"1983-08-31",
    "iso:country":"GB",
    "wof:name":"EH31 2BL",
    "wof:placetype":"postalcode"
},
  "geometry": {"coordinates":[-2.830217,56.034527],"type":"Point"}
}