{
  "type": "Feature",
  "properties": {
    "iso:country":"GB",
    "wof:name":"EH31 2BL",
    "wof:placetype":"postalcode"
},
  "geometry": {"coordinates":[-2.83021681075091,56.0345270642712],"type":"Point"}
}