{
  "type": "Feature",
  "properties": {
    "iso:country":"GB",
    "wof:name":"BA4 4JL",
    "wof:placetype":"postalcode"
},
  "geometry": {"coordinates":[-2.53903961066298,51.20346299793132],"type":"Point"}
}