{
  "type": "Feature",
  "properties": {
    "iso:country":"GB",
    "wof:name":"LU1 1QD",
    "wof:placetype":"postalcode"
},
  "geometry": {"coordinates":[-0.42588066489485,51.87858675191593],"type":"Point"}
}