{
  "type": "Feature",
  "properties": {
    "date:inception_lower":"2005-08-01",
    "date:inception_upper":"2005-08-31",
    "iso:country":"GB",
    "wof:name":"LU1 1QD",
    "wof:placetype":"postalcode"
},
  "geometry": {"coordinates":[-0.425881,51.878587],"type":"Point"}
}