{
  "type": "Feature",
  "properties": {
    "iso:country":"GB",
    "wof:name":"LE12 9HD",
    "wof:placetype":"postalcode"
},
  "geometry": {"coordinates":[-1.28021279072357,52.76706116307858],"type":"Point"}
}