{
  "type": "Feature",
  "properties": {
    "date:inception_lower": "1983-01-01",
    "date:inception_upper": "1983-01-01",
    "iso:country": "GB",
    "wof:name": "LE12 9HD",
    "wof:placetype": "postalcode"
  },
  "geometry": {"coordinates":[-1.280213,52.767061],"type":"Point"}
}
