{
  "type": "Feature",
  "properties": {
    "iso:country": "GB",
    "wof:name": "LE12 9HD",
    "wof:placetype": "postalcode"
  },
  "geometry": {"coordinates":[-1.280213,52.767061],"type":"Point"}
}
