{
  "type": "Feature",
  "properties": {
    "iso:country": "GB",
    "wof:name": "RG8 7NT",
    "wof:placetype": "postalcode"
  },
  "geometry": {"coordinates":[-1.087956,51.495633],"type":"Point"}
}
