{
  "type": "Feature",
  "properties": {
    "iso:country":"GB",
    "wof:name":"RG8 7NT",
    "wof:placetype":"postalcode"
},
  "geometry": {"coordinates":[-1.08797638101179,51.49563094250152],"type":"Point"}
}