{
  "type": "Feature",
  "properties": {
    "iso:country":"GB",
    "wof:name":"SG4 9AQ",
    "wof:placetype":"postalcode"
},
  "geometry": {"coordinates":[-0.27291067385211,51.94646894787804],"type":"Point"}
}