{
  "type": "Feature",
  "properties": {
    "iso:country": "GB",
    "wof:name": "WD3 3PQ",
    "wof:placetype": "postalcode"
  },
  "geometry": {"coordinates":[-0.446691,51.652521],"type":"Point"}
}
