{
  "type": "Feature",
  "properties": {
    "iso:country":"GB",
    "wof:name":"WD3 3PQ",
    "wof:placetype":"postalcode"
},
  "geometry": {"coordinates":[-0.44669092566275,51.65252111224959],"type":"Point"}
}