{
  "type": "Feature",
  "properties": {
    "iso:country":"GB",
    "wof:name":"KW15 1TF",
    "wof:placetype":"postalcode"
},
  "geometry": {"coordinates":[-2.95144052526572,58.96980901121743],"type":"Point"}
}