{
  "type": "Feature",
  "properties": {
    "date:inception_lower":"1980-03-01",
    "date:inception_upper":"1980-03-31",
    "iso:country":"GB",
    "wof:name":"KW15 1TF",
    "wof:placetype":"postalcode"
},
  "geometry": {"coordinates":[-2.95144,58.969809],"type":"Point"}
}