{
  "type": "Feature",
  "properties": {
    "iso:country":"GB",
    "wof:name":"SE1 7BD",
    "wof:placetype":"postalcode"
},
  "geometry": {"coordinates":[-0.11038213479667,51.49989879259158],"type":"Point"}
}