{
  "type": "Feature",
  "properties": {
    "iso:country":"GB",
    "wof:name":"CF32 9GA",
    "wof:placetype":"postalcode"
},
  "geometry": {"coordinates":[-3.60179519263659,51.54410109212163],"type":"Point"}
}