{
  "type": "Feature",
  "properties": {
    "iso:country": "GB",
    "wof:name": "CF32 9GA",
    "wof:placetype": "postalcode"
  },
  "geometry": {"coordinates":[-3.601795,51.544101],"type":"Point"}
}
