{
  "type": "Feature",
  "properties": {
    "date:inception_lower": "2013-09-01",
    "date:inception_upper": "2013-09-01",
    "iso:country": "GB",
    "wof:name": "CF32 9GA",
    "wof:placetype": "postalcode"
  },
  "geometry": {"coordinates":[-3.601795,51.544101],"type":"Point"}
}
