{
  "type": "Feature",
  "properties": {
    "iso:country": "GB",
    "wof:name": "G51 1AW",
    "wof:placetype": "postalcode"
  },
  "geometry": {"coordinates":[-4.295367,55.852621],"type":"Point"}
}
