{
  "type": "Feature",
  "properties": {
    "date:inception_lower": "1980-01-01",
    "date:inception_upper": "1980-01-01",
    "iso:country": "GB",
    "wof:name": "DN7 6LH",
    "wof:placetype": "postalcode"
  },
  "geometry": {"coordinates":[-1.00655,53.577672],"type":"Point"}
}
