{
  "type": "Feature",
  "properties": {
    "iso:country":"GB",
    "wof:name":"DN7 6LH",
    "wof:placetype":"postalcode"
},
  "geometry": {"coordinates":[-1.00654978714306,53.57767196970775],"type":"Point"}
}