{
  "type": "Feature",
  "properties": {
    "iso:country": "GB",
    "wof:name": "DE11 7QJ",
    "wof:placetype": "postalcode"
  },
  "geometry": {"coordinates":[-1.528404,52.771273],"type":"Point"}
}
