{
  "type": "Feature",
  "properties": {
    "date:inception_lower": "1980-01-01",
    "date:inception_upper": "1980-01-01",
    "iso:country": "GB",
    "wof:name": "CT13 0PS",
    "wof:placetype": "postalcode"
  },
  "geometry": {"coordinates":[1.29203,51.262997],"type":"Point"}
}
