{
  "type": "Feature",
  "properties": {
    "iso:country":"GB",
    "wof:name":"S26 3XB",
    "wof:placetype":"postalcode"
},
  "geometry": {"coordinates":[-1.32227833441809,53.36981225618283],"type":"Point"}
}