{
  "type": "Feature",
  "properties": {
    "iso:country":"GB",
    "wof:name":"G42 8RL",
    "wof:placetype":"postalcode"
},
  "geometry": {"coordinates":[-4.26501023645884,55.83504726428863],"type":"Point"}
}