{
  "type": "Feature",
  "properties": {
    "iso:country":"GB",
    "wof:name":"M13 9YS",
    "wof:placetype":"postalcode"
},
  "geometry": {"coordinates":[-2.23057856120618,53.47183252377798],"type":"Point"}
}