{
  "type": "Feature",
  "properties": {
    "iso:country":"GB",
    "wof:name":"B47 5DH",
    "wof:placetype":"postalcode"
},
  "geometry": {"coordinates":[-1.88792599293627,52.39066538614243],"type":"Point"}
}