{
  "type": "Feature",
  "properties": {
    "iso:country":"GB",
    "wof:name":"ME15 0HX",
    "wof:placetype":"postalcode"
},
  "geometry": {"coordinates":[0.51094271914447,51.24918121265834],"type":"Point"}
}