{
  "type": "Feature",
  "properties": {
    "iso:country":"GB",
    "wof:name":"LL65 2EJ",
    "wof:placetype":"postalcode"
},
  "geometry": {"coordinates":[-4.5954087464321,53.27080672270059],"type":"Point"}
}