{
  "type": "Feature",
  "properties": {
    "iso:country": "GB",
    "wof:name": "BL1 7HD",
    "wof:placetype": "postalcode"
  },
  "geometry": {"coordinates":[-2.433387,53.610679],"type":"Point"}
}
