{
  "type": "Feature",
  "properties": {
    "date:inception_lower":"1980-01-01",
    "date:inception_upper":"1980-01-31",
    "iso:country":"GB",
    "wof:name":"BH12 2ER",
    "wof:placetype":"postalcode"
},
  "geometry": {"coordinates":[-1.924944,50.735698],"type":"Point"}
}