{
  "type": "Feature",
  "properties": {
    "iso:country":"GB",
    "wof:name":"BH12 2ER",
    "wof:placetype":"postalcode"
},
  "geometry": {"coordinates":[-1.92494388091457,50.73569819167288],"type":"Point"}
}