{
  "type": "Feature",
  "properties": {
    "iso:country":"GB",
    "wof:name":"PL13 1NA",
    "wof:placetype":"postalcode"
},
  "geometry": {"coordinates":[-4.45085163024712,50.36364425088832],"type":"Point"}
}