{
  "type": "Feature",
  "properties": {
    "iso:country":"GB",
    "wof:name":"CV3 2RT",
    "wof:placetype":"postalcode"
},
  "geometry": {"coordinates":[-1.44424389614117,52.39289234193873],"type":"Point"}
}