{
  "type": "Feature",
  "properties": {
    "iso:country":"GB",
    "wof:name":"SK14 2DL",
    "wof:placetype":"postalcode"
},
  "geometry": {"coordinates":[-2.09068663149151,53.45212938965324],"type":"Point"}
}