{
  "type": "Feature",
  "properties": {
    "iso:country":"GB",
    "wof:name":"GL15 5RL",
    "wof:placetype":"postalcode"
},
  "geometry": {"coordinates":[-2.52955436701745,51.72595448689436],"type":"Point"}
}