{
  "type": "Feature",
  "properties": {
    "date:inception_lower": "2024-06-01",
    "date:inception_upper": "2024-06-01",
    "iso:country": "GB",
    "wof:name": "CM77 8QH",
    "wof:placetype": "postalcode"
  },
  "geometry": {"coordinates":[0.587618,51.865011],"type":"Point"}
}
