{
  "type": "Feature",
  "properties": {
    "iso:country":"GB",
    "wof:name":"BB9 9DN",
    "wof:placetype":"postalcode"
},
  "geometry": {"coordinates":[-2.20854234214438,53.83399832026635],"type":"Point"}
}