{
  "type": "Feature",
  "properties": {
    "iso:country": "GB",
    "wof:name": "BB9 9DN",
    "wof:placetype": "postalcode"
  },
  "geometry": {"coordinates":[-2.208573,53.834025],"type":"Point"}
}
