{
  "type": "Feature",
  "properties": {
    "date:inception_lower": "1980-01-01",
    "date:inception_upper": "1980-01-01",
    "iso:country": "GB",
    "wof:name": "BB9 9DN",
    "wof:placetype": "postalcode"
  },
  "geometry": {"coordinates":[-2.208573,53.834025],"type":"Point"}
}
