{
  "type": "Feature",
  "properties": {
    "iso:country":"GB",
    "wof:name":"OL12 0LQ",
    "wof:placetype":"postalcode"
},
  "geometry": {"coordinates":[-2.14932076920874,53.62268737806612],"type":"Point"}
}