{
  "type": "Feature",
  "properties": {
    "iso:country": "GB",
    "wof:name": "WD4 8JN",
    "wof:placetype": "postalcode"
  },
  "geometry": {"coordinates":[-0.44012,51.718417],"type":"Point"}
}
