{
  "type": "Feature",
  "properties": {
    "iso:country": "GB",
    "wof:name": "WD25 8AR",
    "wof:placetype": "postalcode"
  },
  "geometry": {"coordinates":[-0.354845,51.673508],"type":"Point"}
}
