{
  "type": "Feature",
  "properties": {
    "iso:country": "GB",
    "wof:name": "NN7 3RE",
    "wof:placetype": "postalcode"
  },
  "geometry": {"coordinates":[-1.007652,52.210061],"type":"Point"}
}
