{
  "type": "Feature",
  "properties": {
    "date:inception_lower":"1980-01-01",
    "date:inception_upper":"1980-01-31",
    "iso:country":"GB",
    "wof:name":"NN7 3RE",
    "wof:placetype":"postalcode"
},
  "geometry": {"coordinates":[-1.007652,52.210061],"type":"Point"}
}