{
  "type": "Feature",
  "properties": {
    "iso:country": "GB",
    "wof:name": "EH21 7JH",
    "wof:placetype": "postalcode"
  },
  "geometry": {"coordinates":[-3.038334,55.937662],"type":"Point"}
}
