{
  "type": "Feature",
  "properties": {
    "iso:country":"GB",
    "wof:name":"TS23 1LT",
    "wof:placetype":"postalcode"
},
  "geometry": {"coordinates":[-1.29204486948422,54.5992245825034],"type":"Point"}
}