{
  "type": "Feature",
  "properties": {
    "date:inception_lower":"2008-03-01",
    "date:inception_upper":"2008-03-31",
    "iso:country":"GB",
    "wof:name":"DH7 6GA",
    "wof:placetype":"postalcode"
},
  "geometry": {"coordinates":[-1.632458,54.835296],"type":"Point"}
}