{
  "type": "Feature",
  "properties": {
    "date:inception_lower":"2012-03-01",
    "date:inception_upper":"2012-03-31",
    "iso:country":"GB",
    "wof:name":"PR1 5TG",
    "wof:placetype":"postalcode"
},
  "geometry": {"coordinates":[-2.652109,53.767216],"type":"Point"}
}