{
  "type": "Feature",
  "properties": {
    "iso:country":"GB",
    "wof:name":"S5 9GE",
    "wof:placetype":"postalcode"
},
  "geometry": {"coordinates":[-1.46100451562006,53.43370028996731],"type":"Point"}
}