{
  "type": "Feature",
  "properties": {
    "iso:country":"GB",
    "wof:name":"DE11 7EE",
    "wof:placetype":"postalcode"
},
  "geometry": {"coordinates":[-1.5319196336626,52.76821281545274],"type":"Point"}
}