{
  "type": "Feature",
  "properties": {
    "iso:country": "GB",
    "wof:name": "DE11 7EE",
    "wof:placetype": "postalcode"
  },
  "geometry": {"coordinates":[-1.53192,52.768213],"type":"Point"}
}
