{
  "type": "Feature",
  "properties": {
    "iso:country":"GB",
    "wof:name":"MK43 9EG",
    "wof:placetype":"postalcode"
},
  "geometry": {"coordinates":[-0.52262573185957,52.09536582337325],"type":"Point"}
}