{
  "type": "Feature",
  "properties": {
    "iso:country": "GB",
    "wof:name": "MK43 9EG",
    "wof:placetype": "postalcode"
  },
  "geometry": {"coordinates":[-0.522626,52.095366],"type":"Point"}
}
