{
  "type": "Feature",
  "properties": {
    "date:inception_lower": "1980-01-01",
    "date:inception_upper": "1980-01-01",
    "iso:country": "GB",
    "wof:name": "DY10 3NN",
    "wof:placetype": "postalcode"
  },
  "geometry": {"coordinates":[-2.206232,52.389981],"type":"Point"}
}
