{
  "type": "Feature",
  "properties": {
    "iso:country": "GB",
    "wof:name": "RG30 2UH",
    "wof:placetype": "postalcode"
  },
  "geometry": {"coordinates":[-0.996237,51.454617],"type":"Point"}
}
