{
  "type": "Feature",
  "properties": {
    "date:inception_lower": "1980-01-01",
    "date:inception_upper": "1980-01-01",
    "iso:country": "GB",
    "wof:name": "SS9 2NP",
    "wof:placetype": "postalcode"
  },
  "geometry": {"coordinates":[0.63713,51.544133],"type":"Point"}
}
