{
  "type": "Feature",
  "properties": {
    "iso:country":"GB",
    "wof:name":"B29 7BA",
    "wof:placetype":"postalcode"
},
  "geometry": {"coordinates":[-1.92828249373908,52.44166130150481],"type":"Point"}
}