{
  "type": "Feature",
  "properties": {
    "date:inception_lower": "1980-01-01",
    "date:inception_upper": "1980-01-01",
    "iso:country": "GB",
    "wof:name": "B29 7BA",
    "wof:placetype": "postalcode"
  },
  "geometry": {"coordinates":[-1.928282,52.441661],"type":"Point"}
}
