{
  "type": "Feature",
  "properties": {
    "iso:country":"GB",
    "wof:name":"TW3 4BF",
    "wof:placetype":"postalcode"
},
  "geometry": {"coordinates":[-0.36235028484209,51.47718745641878],"type":"Point"}
}