{
  "type": "Feature",
  "properties": {
    "date:inception_lower": "2014-10-01",
    "date:inception_upper": "2014-10-01",
    "iso:country": "GB",
    "wof:name": "NE38 8FP",
    "wof:placetype": "postalcode"
  },
  "geometry": {"coordinates":[-1.495377,54.893629],"type":"Point"}
}
