{
  "type": "Feature",
  "properties": {
    "iso:country":"GB",
    "wof:name":"RG31 5AR",
    "wof:placetype":"postalcode"
},
  "geometry": {"coordinates":[-1.03656860409883,51.46055672300195],"type":"Point"}
}