{
  "type": "Feature",
  "properties": {
    "iso:country":"GB",
    "wof:name":"BS6 5AP",
    "wof:placetype":"postalcode"
},
  "geometry": {"coordinates":[-2.58999087170296,51.47244112439255],"type":"Point"}
}