{
  "type": "Feature",
  "properties": {
    "iso:country": "GB",
    "wof:name": "NP15 1NF",
    "wof:placetype": "postalcode"
  },
  "geometry": {"coordinates":[-2.853598,51.688],"type":"Point"}
}
