{
  "type": "Feature",
  "properties": {
    "iso:country":"GB",
    "wof:name":"SP4 9DD",
    "wof:placetype":"postalcode"
},
  "geometry": {"coordinates":[-1.76391425149625,51.19356087862084],"type":"Point"}
}