{
  "type": "Feature",
  "properties": {
    "date:inception_lower": "1980-01-01",
    "date:inception_upper": "1980-01-01",
    "iso:country": "GB",
    "wof:name": "EH4 7SW",
    "wof:placetype": "postalcode"
  },
  "geometry": {"coordinates":[-3.295867,55.953867],"type":"Point"}
}
