{
  "type": "Feature",
  "properties": {
    "iso:country":"GB",
    "wof:name":"CF11 0AQ",
    "wof:placetype":"postalcode"
},
  "geometry": {"coordinates":[-3.18971537385724,51.45234158298109],"type":"Point"}
}