{
  "type": "Feature",
  "properties": {
    "iso:country":"GB",
    "wof:name":"LA23 2JT",
    "wof:placetype":"postalcode"
},
  "geometry": {"coordinates":[-2.91172199818567,54.36715405840459],"type":"Point"}
}