{
  "type": "Feature",
  "properties": {
    "iso:country":"GB",
    "wof:name":"B19 1LY",
    "wof:placetype":"postalcode"
},
  "geometry": {"coordinates":[-1.90379391196539,52.50670438459657],"type":"Point"}
}