{
  "type": "Feature",
  "properties": {
    "date:inception_lower":"1981-06-01",
    "date:inception_upper":"1981-06-30",
    "iso:country":"GB",
    "wof:name":"ST3 7TA",
    "wof:placetype":"postalcode"
},
  "geometry": {"coordinates":[-2.088493,52.961816],"type":"Point"}
}