{
  "type": "Feature",
  "properties": {
    "date:inception_lower": "1994-12-01",
    "date:inception_upper": "1994-12-01",
    "iso:country": "GB",
    "wof:name": "SO30 2NS",
    "wof:placetype": "postalcode"
  },
  "geometry": {"coordinates":[-1.291414,50.9073],"type":"Point"}
}
