{
  "type": "Feature",
  "properties": {
    "iso:country": "GB",
    "wof:name": "LE4 0HR",
    "wof:placetype": "postalcode"
  },
  "geometry": {"coordinates":[-1.147587,52.656461],"type":"Point"}
}
