{
  "type": "Feature",
  "properties": {
    "date:inception_lower": "1980-01-01",
    "date:inception_upper": "1980-01-01",
    "iso:country": "GB",
    "wof:name": "LE4 0HR",
    "wof:placetype": "postalcode"
  },
  "geometry": {"coordinates":[-1.147587,52.656461],"type":"Point"}
}
