{
  "type": "Feature",
  "properties": {
    "iso:country": "GB",
    "wof:name": "SG8 6HT",
    "wof:placetype": "postalcode"
  },
  "geometry": {"coordinates":[0.022625,52.083413],"type":"Point"}
}
