{
  "type": "Feature",
  "properties": {
    "iso:country":"GB",
    "wof:name":"CR2 8SL",
    "wof:placetype":"postalcode"
},
  "geometry": {"coordinates":[-0.05261879721489,51.34632914665235],"type":"Point"}
}