{
  "type": "Feature",
  "properties": {
    "iso:country":"GB",
    "wof:name":"BA6 8LE",
    "wof:placetype":"postalcode"
},
  "geometry": {"coordinates":[-2.68163887660118,51.13991803358528],"type":"Point"}
}