{
  "type": "Feature",
  "properties": {
    "iso:country":"GB",
    "wof:name":"TS12 2JS",
    "wof:placetype":"postalcode"
},
  "geometry": {"coordinates":[-0.97585738346855,54.56404291186338],"type":"Point"}
}