{
  "type": "Feature",
  "properties": {
    "iso:country":"GB",
    "wof:name":"EX14 2YG",
    "wof:placetype":"postalcode"
},
  "geometry": {"coordinates":[-3.18963502798949,50.78852799497992],"type":"Point"}
}