{
  "type": "Feature",
  "properties": {
    "date:inception_lower": "1999-12-01",
    "date:inception_upper": "1999-12-01",
    "iso:country": "GB",
    "wof:name": "EX14 2YG",
    "wof:placetype": "postalcode"
  },
  "geometry": {"coordinates":[-3.189635,50.788528],"type":"Point"}
}
