{
  "type": "Feature",
  "properties": {
    "iso:country": "GB",
    "wof:name": "TR11 5LR",
    "wof:placetype": "postalcode"
  },
  "geometry": {"coordinates":[-5.128091,50.105281],"type":"Point"}
}
