{
  "type": "Feature",
  "properties": {
    "iso:country":"GB",
    "wof:name":"TR11 5LR",
    "wof:placetype":"postalcode"
},
  "geometry": {"coordinates":[-5.12809100896381,50.10528095137264],"type":"Point"}
}