{
  "type": "Feature",
  "properties": {
    "iso:country":"GB",
    "wof:name":"UB6 8DB",
    "wof:placetype":"postalcode"
},
  "geometry": {"coordinates":[-0.32059118610739,51.53396784690896],"type":"Point"}
}