{
  "type": "Feature",
  "properties": {
    "date:inception_lower": "1980-01-01",
    "date:inception_upper": "1980-01-01",
    "iso:country": "GB",
    "wof:name": "CO7 0AW",
    "wof:placetype": "postalcode"
  },
  "geometry": {"coordinates":[1.024515,51.806672],"type":"Point"}
}
