{
  "type": "Feature",
  "properties": {
    "iso:country":"GB",
    "wof:name":"LL48 6SE",
    "wof:placetype":"postalcode"
},
  "geometry": {"coordinates":[-4.06522389311518,52.95614485403293],"type":"Point"}
}