{
  "type": "Feature",
  "properties": {
    "iso:country":"GB",
    "wof:name":"TS6 0LF",
    "wof:placetype":"postalcode"
},
  "geometry": {"coordinates":[-1.15645131810834,54.55648506763175],"type":"Point"}
}