{
  "type": "Feature",
  "properties": {
    "date:inception_lower": "1980-01-01",
    "date:inception_upper": "1980-01-01",
    "iso:country": "GB",
    "wof:name": "TS6 0LF",
    "wof:placetype": "postalcode"
  },
  "geometry": {"coordinates":[-1.156451,54.556485],"type":"Point"}
}
