{
  "type": "Feature",
  "properties": {
    "iso:country": "GB",
    "wof:name": "TS6 0LF",
    "wof:placetype": "postalcode"
  },
  "geometry": {"coordinates":[-1.156451,54.556485],"type":"Point"}
}
