{
  "type": "Feature",
  "properties": {
    "iso:country":"GB",
    "wof:name":"ME6 5DF",
    "wof:placetype":"postalcode"
},
  "geometry": {"coordinates":[0.44183468805034,51.3301559438418],"type":"Point"}
}