{
  "type": "Feature",
  "properties": {
    "date:inception_lower": "1980-01-01",
    "date:inception_upper": "1980-01-01",
    "iso:country": "GB",
    "wof:name": "NG24 4EP",
    "wof:placetype": "postalcode"
  },
  "geometry": {"coordinates":[-0.810361,53.061206],"type":"Point"}
}
