{
  "type": "Feature",
  "properties": {
    "iso:country":"GB",
    "wof:name":"NG24 4EP",
    "wof:placetype":"postalcode"
},
  "geometry": {"coordinates":[-0.81036459032971,53.06118577168852],"type":"Point"}
}