{
  "type": "Feature",
  "properties": {
    "iso:country":"GB",
    "wof:name":"BS5 9LT",
    "wof:placetype":"postalcode"
},
  "geometry": {"coordinates":[-2.56229010252086,51.45841548774458],"type":"Point"}
}