{
  "type": "Feature",
  "properties": {
    "date:inception_lower":"2007-11-01",
    "date:inception_upper":"2007-11-30",
    "iso:country":"GB",
    "wof:name":"SA44 5HG",
    "wof:placetype":"postalcode"
},
  "geometry": {"coordinates":[-4.402602,52.004303],"type":"Point"}
}