{
  "type": "Feature",
  "properties": {
    "iso:country":"GB",
    "wof:name":"SA44 5HG",
    "wof:placetype":"postalcode"
},
  "geometry": {"coordinates":[-4.40409610742805,52.00294804259824],"type":"Point"}
}