{
  "type": "Feature",
  "properties": {
    "iso:country": "GB",
    "wof:name": "SA44 5HG",
    "wof:placetype": "postalcode"
  },
  "geometry": {"coordinates":[-4.402602,52.004303],"type":"Point"}
}
