{
  "type": "Feature",
  "properties": {
    "date:inception_lower":"1980-01-01",
    "date:inception_upper":"1980-01-31",
    "iso:country":"GB",
    "wof:name":"EC1V 7JD",
    "wof:placetype":"postalcode"
},
  "geometry": {"coordinates":[-0.102338,51.529489],"type":"Point"}
}