{
  "type": "Feature",
  "properties": {
    "iso:country":"GB",
    "wof:name":"HA3 0YG",
    "wof:placetype":"postalcode"
},
  "geometry": {"coordinates":[-0.30054514639698,51.58633787878296],"type":"Point"}
}