{
  "type": "Feature",
  "properties": {
    "date:inception_lower":"2017-12-01",
    "date:inception_upper":"2017-12-31",
    "iso:country":"GB",
    "wof:name":"CV22 7ZR",
    "wof:placetype":"postalcode"
},
  "geometry": {"coordinates":[-1.312925,52.358137],"type":"Point"}
}