{
  "type": "Feature",
  "properties": {
    "iso:country":"GB",
    "wof:name":"RG5 3JB",
    "wof:placetype":"postalcode"
},
  "geometry": {"coordinates":[-0.91400209491911,51.44779635506995],"type":"Point"}
}