{
  "type": "Feature",
  "properties": {
    "iso:country":"GB",
    "wof:name":"WF17 8HH",
    "wof:placetype":"postalcode"
},
  "geometry": {"coordinates":[-1.64581679259874,53.72044468908216],"type":"Point"}
}