{
  "type": "Feature",
  "properties": {
    "iso:country": "GB",
    "wof:name": "WF17 8HH",
    "wof:placetype": "postalcode"
  },
  "geometry": {"coordinates":[-1.645817,53.720445],"type":"Point"}
}
