{
  "type": "Feature",
  "properties": {
    "iso:country": "GB",
    "wof:name": "LL66 0BG",
    "wof:placetype": "postalcode"
  },
  "geometry": {"coordinates":[-4.411159,53.365162],"type":"Point"}
}
