{
  "type": "Feature",
  "properties": {
    "iso:country":"GB",
    "wof:name":"LL66 0BG",
    "wof:placetype":"postalcode"
},
  "geometry": {"coordinates":[-4.411159170884,53.36516218071083],"type":"Point"}
}