{
  "type": "Feature",
  "properties": {
    "iso:country":"GB",
    "wof:name":"BR2 9PW",
    "wof:placetype":"postalcode"
},
  "geometry": {"coordinates":[0.036839641674,51.38931351268869],"type":"Point"}
}