{
  "type": "Feature",
  "properties": {
    "iso:country":"GB",
    "wof:name":"TW15 2LE",
    "wof:placetype":"postalcode"
},
  "geometry": {"coordinates":[-0.46630867699938,51.43284957939381],"type":"Point"}
}