{
  "type": "Feature",
  "properties": {
    "date:inception_lower": "1980-01-01",
    "date:inception_upper": "1980-01-01",
    "iso:country": "GB",
    "wof:name": "TA24 5JN",
    "wof:placetype": "postalcode"
  },
  "geometry": {"coordinates":[-3.477567,51.210714],"type":"Point"}
}
