{
  "type": "Feature",
  "properties": {
    "iso:country":"GB",
    "wof:name":"TA24 5JN",
    "wof:placetype":"postalcode"
},
  "geometry": {"coordinates":[-3.47756668244627,51.21071429488459],"type":"Point"}
}