{
  "type": "Feature",
  "properties": {
    "iso:country":"GB",
    "wof:name":"SG18 8UU",
    "wof:placetype":"postalcode"
},
  "geometry": {"coordinates":[-0.26499551929672,52.08658656201492],"type":"Point"}
}