{
  "type": "Feature",
  "properties": {
    "iso:country":"GB",
    "wof:name":"NR2 1SH",
    "wof:placetype":"postalcode"
},
  "geometry": {"coordinates":[1.28976617620151,52.62580137020022],"type":"Point"}
}