{
  "type": "Feature",
  "properties": {
    "iso:country":"GB",
    "wof:name":"HR1 2RH",
    "wof:placetype":"postalcode"
},
  "geometry": {"coordinates":[-2.6979585727505,52.0547753315086],"type":"Point"}
}