{
  "type": "Feature",
  "properties": {
    "date:inception_lower": "1980-01-01",
    "date:inception_upper": "1980-01-01",
    "iso:country": "GB",
    "wof:name": "HR1 2RH",
    "wof:placetype": "postalcode"
  },
  "geometry": {"coordinates":[-2.697959,52.054775],"type":"Point"}
}
