{
  "type": "Feature",
  "properties": {
    "iso:country":"GB",
    "wof:name":"DN14 8SB",
    "wof:placetype":"postalcode"
},
  "geometry": {"coordinates":[-0.94565411862561,53.70743226718839],"type":"Point"}
}