{
  "type": "Feature",
  "properties": {
    "iso:country":"GB",
    "wof:name":"B98 9DJ",
    "wof:placetype":"postalcode"
},
  "geometry": {"coordinates":[-1.87880189109314,52.33109669238086],"type":"Point"}
}