{
  "type": "Feature",
  "properties": {
    "iso:country":"GB",
    "wof:name":"BD12 0TY",
    "wof:placetype":"postalcode"
},
  "geometry": {"coordinates":[-1.77131580819755,53.75222585238773],"type":"Point"}
}