{
  "type": "Feature",
  "properties": {
    "date:inception_lower": "1996-06-01",
    "date:inception_upper": "1996-06-01",
    "iso:country": "GB",
    "wof:name": "AB10 1TZ",
    "wof:placetype": "postalcode"
  },
  "geometry": {"coordinates":[-2.113678,57.145379],"type":"Point"}
}
