{
  "type": "Feature",
  "properties": {
    "iso:country":"GB",
    "wof:name":"AB10 1TZ",
    "wof:placetype":"postalcode"
},
  "geometry": {"coordinates":[-2.11367822642469,57.14537872048517],"type":"Point"}
}