{
  "type": "Feature",
  "properties": {
    "iso:country": "GB",
    "wof:name": "GL2 5EX",
    "wof:placetype": "postalcode"
  },
  "geometry": {"coordinates":[-2.259839,51.853563],"type":"Point"}
}
