{
  "type": "Feature",
  "properties": {
    "iso:country": "GB",
    "wof:name": "SK14 1HB",
    "wof:placetype": "postalcode"
  },
  "geometry": {"coordinates":[-2.075981,53.447385],"type":"Point"}
}
