{
  "type": "Feature",
  "properties": {
    "date:inception_lower": "1980-01-01",
    "date:inception_upper": "1980-01-01",
    "iso:country": "GB",
    "wof:name": "SK14 1HB",
    "wof:placetype": "postalcode"
  },
  "geometry": {"coordinates":[-2.075815,53.447266],"type":"Point"}
}
