{
  "type": "Feature",
  "properties": {
    "iso:country":"GB",
    "wof:name":"BS14 9PY",
    "wof:placetype":"postalcode"
},
  "geometry": {"coordinates":[-2.56574914332735,51.40873788337028],"type":"Point"}
}