{
  "type": "Feature",
  "properties": {
    "iso:country":"GB",
    "wof:name":"WA8 7DS",
    "wof:placetype":"postalcode"
},
  "geometry": {"coordinates":[-2.74073168359511,53.3721134287297],"type":"Point"}
}