{
  "type": "Feature",
  "properties": {
    "iso:country": "GB",
    "wof:name": "WA8 7DS",
    "wof:placetype": "postalcode"
  },
  "geometry": {"coordinates":[-2.740732,53.372113],"type":"Point"}
}
