{
  "type": "Feature",
  "properties": {
    "iso:country": "GB",
    "wof:name": "CM3 1DZ",
    "wof:placetype": "postalcode"
  },
  "geometry": {"coordinates":[0.442771,51.782224],"type":"Point"}
}
