{
  "type": "Feature",
  "properties": {
    "date:inception_lower":"1980-01-01",
    "date:inception_upper":"1980-01-31",
    "iso:country":"GB",
    "wof:name":"CM3 1DZ",
    "wof:placetype":"postalcode"
},
  "geometry": {"coordinates":[0.442771,51.782224],"type":"Point"}
}