{
  "type": "Feature",
  "properties": {
    "iso:country":"GB",
    "wof:name":"DN5 8RL",
    "wof:placetype":"postalcode"
},
  "geometry": {"coordinates":[-1.18062422991538,53.54203840127037],"type":"Point"}
}