{
  "type": "Feature",
  "properties": {
    "iso:country": "GB",
    "wof:name": "M40 8QX",
    "wof:placetype": "postalcode"
  },
  "geometry": {"coordinates":[-2.211562,53.498222],"type":"Point"}
}
