{
  "type": "Feature",
  "properties": {
    "iso:country": "GB",
    "wof:name": "EN2 0TS",
    "wof:placetype": "postalcode"
  },
  "geometry": {"coordinates":[-0.093489,51.664565],"type":"Point"}
}
