{
  "type": "Feature",
  "properties": {
    "iso:country":"GB",
    "wof:name":"EN2 0TS",
    "wof:placetype":"postalcode"
},
  "geometry": {"coordinates":[-0.09348878492305,51.6645651968084],"type":"Point"}
}