{
  "type": "Feature",
  "properties": {
    "iso:country":"GB",
    "wof:name":"LU2 9PA",
    "wof:placetype":"postalcode"
},
  "geometry": {"coordinates":[-0.38177591050377,51.8801284765521],"type":"Point"}
}