{
  "type": "Feature",
  "properties": {
    "date:inception_lower": "1981-06-01",
    "date:inception_upper": "1981-06-01",
    "iso:country": "GB",
    "wof:name": "LU2 9PA",
    "wof:placetype": "postalcode"
  },
  "geometry": {"coordinates":[-0.381776,51.880128],"type":"Point"}
}
