{
  "type": "Feature",
  "properties": {
    "date:inception_lower": "1980-01-01",
    "date:inception_upper": "1980-01-01",
    "iso:country": "GB",
    "wof:name": "B68 8QH",
    "wof:placetype": "postalcode"
  },
  "geometry": {"coordinates":[-2.004095,52.489312],"type":"Point"}
}
