{
  "type": "Feature",
  "properties": {
    "iso:country":"GB",
    "wof:name":"LN8 5PG",
    "wof:placetype":"postalcode"
},
  "geometry": {"coordinates":[-0.30190426171637,53.28953811777583],"type":"Point"}
}