{
  "type": "Feature",
  "properties": {
    "date:inception_lower": "1998-06-01",
    "date:inception_upper": "1998-06-01",
    "iso:country": "GB",
    "wof:name": "YO62 5QT",
    "wof:placetype": "postalcode"
  },
  "geometry": {"coordinates":[-1.152274,54.29887],"type":"Point"}
}
