{
  "type": "Feature",
  "properties": {
    "iso:country": "GB",
    "wof:name": "YO62 5QT",
    "wof:placetype": "postalcode"
  },
  "geometry": {"coordinates":[-1.152274,54.29887],"type":"Point"}
}
