{
  "type": "Feature",
  "properties": {
    "iso:country":"GB",
    "wof:name":"SN1 3PE",
    "wof:placetype":"postalcode"
},
  "geometry": {"coordinates":[-1.79091564650021,51.55724427721661],"type":"Point"}
}