{
  "type": "Feature",
  "properties": {
    "iso:country": "GB",
    "wof:name": "HP16 0BN",
    "wof:placetype": "postalcode"
  },
  "geometry": {"coordinates":[-0.704693,51.698648],"type":"Point"}
}
