{
  "type": "Feature",
  "properties": {
    "iso:country":"GB",
    "wof:name":"CT20 2JQ",
    "wof:placetype":"postalcode"
},
  "geometry": {"coordinates":[1.15300536483559,51.07453467269725],"type":"Point"}
}