{
  "type": "Feature",
  "properties": {
    "iso:country": "GB",
    "wof:name": "CT20 2JQ",
    "wof:placetype": "postalcode"
  },
  "geometry": {"coordinates":[1.153037,51.074529],"type":"Point"}
}
