{
  "type": "Feature",
  "properties": {
    "iso:country": "GB",
    "wof:name": "DY14 8AT",
    "wof:placetype": "postalcode"
  },
  "geometry": {"coordinates":[-2.479715,52.382669],"type":"Point"}
}
