{
  "type": "Feature",
  "properties": {
    "iso:country":"GB",
    "wof:name":"DY14 8AT",
    "wof:placetype":"postalcode"
},
  "geometry": {"coordinates":[-2.47971460021857,52.38266858421316],"type":"Point"}
}