{
  "type": "Feature",
  "properties": {
    "date:inception_lower": "1980-01-01",
    "date:inception_upper": "1980-01-01",
    "iso:country": "GB",
    "wof:name": "TR19 6UL",
    "wof:placetype": "postalcode"
  },
  "geometry": {"coordinates":[-5.55504,50.086025],"type":"Point"}
}
