{
  "type": "Feature",
  "properties": {
    "iso:country":"GB",
    "wof:name":"TA7 0AP",
    "wof:placetype":"postalcode"
},
  "geometry": {"coordinates":[-2.96235682065949,51.0888373316381],"type":"Point"}
}