{
  "type": "Feature",
  "properties": {
    "date:inception_lower": "1980-01-01",
    "date:inception_upper": "1980-01-01",
    "iso:country": "GB",
    "wof:name": "TA7 0AP",
    "wof:placetype": "postalcode"
  },
  "geometry": {"coordinates":[-2.962357,51.088837],"type":"Point"}
}
