{
  "type": "Feature",
  "properties": {
    "iso:country":"GB",
    "wof:name":"CA10 3LU",
    "wof:placetype":"postalcode"
},
  "geometry": {"coordinates":[-2.67888684222136,54.53060151305481],"type":"Point"}
}