{
  "type": "Feature",
  "properties": {
    "date:inception_lower": "2009-10-01",
    "date:inception_upper": "2009-10-01",
    "iso:country": "GB",
    "wof:name": "DG5 4RH",
    "wof:placetype": "postalcode"
  },
  "geometry": {"coordinates":[-3.801919,54.885182],"type":"Point"}
}
