{
  "type": "Feature",
  "properties": {
    "date:inception_lower": "2009-10-01",
    "date:inception_upper": "2009-10-01",
    "iso:country": "GB",
    "wof:name": "DG5 4RH",
    "wof:placetype": "postalcode"
  },
  "geometry": {"coordinates":[-3.802463,54.884858],"type":"Point"}
}
