{
  "type": "Feature",
  "properties": {
    "iso:country":"GB",
    "wof:name":"UB4 9JJ",
    "wof:placetype":"postalcode"
},
  "geometry": {"coordinates":[-0.40826800604293,51.53149436076951],"type":"Point"}
}