{
  "type": "Feature",
  "properties": {
    "date:inception_lower": "1980-01-01",
    "date:inception_upper": "1980-01-01",
    "iso:country": "GB",
    "wof:name": "UB4 9JJ",
    "wof:placetype": "postalcode"
  },
  "geometry": {"coordinates":[-0.408268,51.531494],"type":"Point"}
}
