{
  "type": "Feature",
  "properties": {
    "date:inception_lower": "1980-01-01",
    "date:inception_upper": "1980-01-01",
    "iso:country": "GB",
    "wof:name": "SG18 9NR",
    "wof:placetype": "postalcode"
  },
  "geometry": {"coordinates":[-0.291072,52.07223],"type":"Point"}
}
