{
  "type": "Feature",
  "properties": {
    "iso:country": "GB",
    "wof:name": "LE7 2PS",
    "wof:placetype": "postalcode"
  },
  "geometry": {"coordinates":[-1.073478,52.690625],"type":"Point"}
}
