{
  "type": "Feature",
  "properties": {
    "iso:country":"GB",
    "wof:name":"LE7 2PS",
    "wof:placetype":"postalcode"
},
  "geometry": {"coordinates":[-1.07347830867061,52.69062452743687],"type":"Point"}
}