{
  "type": "Feature",
  "properties": {
    "iso:country":"GB",
    "wof:name":"TS7 8PU",
    "wof:placetype":"postalcode"
},
  "geometry": {"coordinates":[-1.19003057689121,54.52866561306794],"type":"Point"}
}