{
  "type": "Feature",
  "properties": {
    "iso:country":"GB",
    "wof:name":"BA14 0QJ",
    "wof:placetype":"postalcode"
},
  "geometry": {"coordinates":[-2.21461646033554,51.31262643777939],"type":"Point"}
}