{
  "type": "Feature",
  "properties": {
    "iso:country": "GB",
    "wof:name": "BA14 0QJ",
    "wof:placetype": "postalcode"
  },
  "geometry": {"coordinates":[-2.214616,51.312626],"type":"Point"}
}
