{
  "type": "Feature",
  "properties": {
    "date:inception_lower": "1980-01-01",
    "date:inception_upper": "1980-01-01",
    "iso:country": "GB",
    "wof:name": "BA14 0QJ",
    "wof:placetype": "postalcode"
  },
  "geometry": {"coordinates":[-2.214616,51.312626],"type":"Point"}
}
