{
  "type": "Feature",
  "properties": {
    "iso:country": "GB",
    "wof:name": "BL1 6HG",
    "wof:placetype": "postalcode"
  },
  "geometry": {"coordinates":[-2.453736,53.592762],"type":"Point"}
}
