{
  "type": "Feature",
  "properties": {
    "iso:country": "GB",
    "wof:name": "B79 7JF",
    "wof:placetype": "postalcode"
  },
  "geometry": {"coordinates":[-1.6893,52.633561],"type":"Point"}
}
