{
  "type": "Feature",
  "properties": {
    "date:inception_lower":"1980-01-01",
    "date:inception_upper":"1980-01-31",
    "iso:country":"GB",
    "wof:name":"G61 1DE",
    "wof:placetype":"postalcode"
},
  "geometry": {"coordinates":[-4.323251,55.908315],"type":"Point"}
}