{
  "type": "Feature",
  "properties": {
    "iso:country":"GB",
    "wof:name":"WA14 4QU",
    "wof:placetype":"postalcode"
},
  "geometry": {"coordinates":[-2.37301522579683,53.38883162353049],"type":"Point"}
}