{
  "type": "Feature",
  "properties": {
    "iso:country":"GB",
    "wof:name":"DA11 0EJ",
    "wof:placetype":"postalcode"
},
  "geometry": {"coordinates":[0.35830696254833,51.44266580659389],"type":"Point"}
}