{
  "type": "Feature",
  "properties": {
    "iso:country":"GB",
    "wof:name":"PL25 5ST",
    "wof:placetype":"postalcode"
},
  "geometry": {"coordinates":[-4.81810445891749,50.34145724026507],"type":"Point"}
}