{
  "type": "Feature",
  "properties": {
    "iso:country": "GB",
    "wof:name": "IP9 1LF",
    "wof:placetype": "postalcode"
  },
  "geometry": {"coordinates":[1.243407,51.969036],"type":"Point"}
}
