{
  "type": "Feature",
  "properties": {
    "date:inception_lower":"1980-01-01",
    "date:inception_upper":"1980-01-31",
    "iso:country":"GB",
    "wof:name":"IP9 1LF",
    "wof:placetype":"postalcode"
},
  "geometry": {"coordinates":[1.243407,51.969036],"type":"Point"}
}