{
  "type": "Feature",
  "properties": {
    "iso:country":"GB",
    "wof:name":"IP9 1LF",
    "wof:placetype":"postalcode"
},
  "geometry": {"coordinates":[1.2434065026643,51.96903568792331],"type":"Point"}
}