{
  "type": "Feature",
  "properties": {
    "iso:country":"GB",
    "wof:name":"OL2 6EG",
    "wof:placetype":"postalcode"
},
  "geometry": {"coordinates":[-2.11807479337571,53.56485586922307],"type":"Point"}
}