{
  "type": "Feature",
  "properties": {
    "iso:country":"GB",
    "wof:name":"BB7 9HJ",
    "wof:placetype":"postalcode"
},
  "geometry": {"coordinates":[-2.33940131996628,53.83599115144092],"type":"Point"}
}