{
  "type": "Feature",
  "properties": {
    "date:inception_lower": "2009-07-01",
    "date:inception_upper": "2009-07-01",
    "iso:country": "GB",
    "wof:name": "HD6 3NN",
    "wof:placetype": "postalcode"
  },
  "geometry": {"coordinates":[-1.797735,53.685591],"type":"Point"}
}
