{
  "type": "Feature",
  "properties": {
    "iso:country":"GB",
    "wof:name":"HD6 3NN",
    "wof:placetype":"postalcode"
},
  "geometry": {"coordinates":[-1.79773483488924,53.68559063593216],"type":"Point"}
}