{
  "type": "Feature",
  "properties": {
    "iso:country":"GB",
    "wof:name":"BD16 2BP",
    "wof:placetype":"postalcode"
},
  "geometry": {"coordinates":[-1.84492586492232,53.86001918917103],"type":"Point"}
}