{
  "type": "Feature",
  "properties": {
    "date:inception_lower": "2006-09-01",
    "date:inception_upper": "2006-09-01",
    "iso:country": "GB",
    "wof:name": "NG9 2UU",
    "wof:placetype": "postalcode"
  },
  "geometry": {"coordinates":[-1.205608,52.933621],"type":"Point"}
}
