{
  "type": "Feature",
  "properties": {
    "iso:country":"GB",
    "wof:name":"NG9 2UU",
    "wof:placetype":"postalcode"
},
  "geometry": {"coordinates":[-1.20560789050039,52.93362146379477],"type":"Point"}
}