{
  "type": "Feature",
  "properties": {
    "iso:country": "GB",
    "wof:name": "GU17 9EF",
    "wof:placetype": "postalcode"
  },
  "geometry": {"coordinates":[-0.775144,51.320827],"type":"Point"}
}
