{
  "type": "Feature",
  "properties": {
    "date:inception_lower": "2011-07-01",
    "date:inception_upper": "2011-07-01",
    "iso:country": "GB",
    "wof:name": "WA1 2GN",
    "wof:placetype": "postalcode"
  },
  "geometry": {"coordinates":[-2.576532,53.392507],"type":"Point"}
}
