{
  "type": "Feature",
  "properties": {
    "iso:country": "GB",
    "wof:name": "ME1 3BF",
    "wof:placetype": "postalcode"
  },
  "geometry": {"coordinates":[0.501508,51.37068],"type":"Point"}
}
