{
  "type": "Feature",
  "properties": {
    "iso:country":"GB",
    "wof:name":"ME1 3BF",
    "wof:placetype":"postalcode"
},
  "geometry": {"coordinates":[0.50150768124163,51.37068032509357],"type":"Point"}
}