{
  "type": "Feature",
  "properties": {
    "iso:country":"GB",
    "wof:name":"LS26 8HF",
    "wof:placetype":"postalcode"
},
  "geometry": {"coordinates":[-1.41575695221031,53.76142028002057],"type":"Point"}
}