{
  "type": "Feature",
  "properties": {
    "date:inception_lower": "2003-01-01",
    "date:inception_upper": "2003-01-01",
    "iso:country": "GB",
    "wof:name": "LS26 8HF",
    "wof:placetype": "postalcode"
  },
  "geometry": {"coordinates":[-1.415757,53.76142],"type":"Point"}
}
