{
  "type": "Feature",
  "properties": {
    "iso:country":"GB",
    "wof:name":"BH14 0BD",
    "wof:placetype":"postalcode"
},
  "geometry": {"coordinates":[-1.94834581794741,50.72968577534041],"type":"Point"}
}