{
  "type": "Feature",
  "properties": {
    "iso:country":"GB",
    "wof:name":"TN39 4SP",
    "wof:placetype":"postalcode"
},
  "geometry": {"coordinates":[0.43348731234698,50.8420289032903],"type":"Point"}
}