{
  "type": "Feature",
  "properties": {
    "iso:country":"GB",
    "wof:name":"WA12 0NZ",
    "wof:placetype":"postalcode"
},
  "geometry": {"coordinates":[-2.63782392314381,53.47993379719144],"type":"Point"}
}