{
  "type": "Feature",
  "properties": {
    "iso:country": "GB",
    "wof:name": "GL52 5DW",
    "wof:placetype": "postalcode"
  },
  "geometry": {"coordinates":[-2.05884,51.907646],"type":"Point"}
}
