{
  "type": "Feature",
  "properties": {
    "iso:country": "GB",
    "wof:name": "CM16 4EL",
    "wof:placetype": "postalcode"
  },
  "geometry": {"coordinates":[0.102387,51.689211],"type":"Point"}
}
