{
  "type": "Feature",
  "properties": {
    "iso:country":"GB",
    "wof:name":"CM16 4EL",
    "wof:placetype":"postalcode"
},
  "geometry": {"coordinates":[0.10267598264468,51.68914741722174],"type":"Point"}
}