{
  "type": "Feature",
  "properties": {
    "iso:country":"GB",
    "wof:name":"SL6 6PT",
    "wof:placetype":"postalcode"
},
  "geometry": {"coordinates":[-0.74921230254229,51.54800616115735],"type":"Point"}
}