{
  "type": "Feature",
  "properties": {
    "iso:country": "GB",
    "wof:name": "WN6 0HW",
    "wof:placetype": "postalcode"
  },
  "geometry": {"coordinates":[-2.66295,53.586599],"type":"Point"}
}
