{
  "type": "Feature",
  "properties": {
    "iso:country":"GB",
    "wof:name":"WN6 0HW",
    "wof:placetype":"postalcode"
},
  "geometry": {"coordinates":[-2.6629498453509,53.58659873615122],"type":"Point"}
}