{
  "type": "Feature",
  "properties": {
    "iso:country": "GB",
    "wof:name": "NN11 9BY",
    "wof:placetype": "postalcode"
  },
  "geometry": {"coordinates":[-1.168748,52.259846],"type":"Point"}
}
