{
  "type": "Feature",
  "properties": {
    "iso:country":"GB",
    "wof:name":"LL18 2BU",
    "wof:placetype":"postalcode"
},
  "geometry": {"coordinates":[-3.48494986012246,53.31764550580654],"type":"Point"}
}