{
  "type": "Feature",
  "properties": {
    "iso:country":"GB",
    "wof:name":"UB3 1NG",
    "wof:placetype":"postalcode"
},
  "geometry": {"coordinates":[-0.43123723046297,51.49828083321042],"type":"Point"}
}