{
  "type": "Feature",
  "properties": {
    "date:inception_lower": "2003-06-01",
    "date:inception_upper": "2003-06-01",
    "iso:country": "GB",
    "wof:name": "W5 3BF",
    "wof:placetype": "postalcode"
  },
  "geometry": {"coordinates":[-0.286427,51.526864],"type":"Point"}
}
