{
  "type": "Feature",
  "properties": {
    "iso:country":"GB",
    "wof:name":"TS6 7HJ",
    "wof:placetype":"postalcode"
},
  "geometry": {"coordinates":[-1.14497185090614,54.58043608690565],"type":"Point"}
}