{
  "type": "Feature",
  "properties": {
    "iso:country":"GB",
    "wof:name":"BA3 3HE",
    "wof:placetype":"postalcode"
},
  "geometry": {"coordinates":[-2.44504117557779,51.29531515847157],"type":"Point"}
}