{
  "type": "Feature",
  "properties": {
    "iso:country":"GB",
    "wof:name":"CW7 3BH",
    "wof:placetype":"postalcode"
},
  "geometry": {"coordinates":[-2.51526124905061,53.21115066224814],"type":"Point"}
}