{
  "type": "Feature",
  "properties": {
    "iso:country": "GB",
    "wof:name": "SE12 9RX",
    "wof:placetype": "postalcode"
  },
  "geometry": {"coordinates":[0.032079,51.428488],"type":"Point"}
}
