{
  "type": "Feature",
  "properties": {
    "iso:country":"GB",
    "wof:name":"S61 4BN",
    "wof:placetype":"postalcode"
},
  "geometry": {"coordinates":[-1.38499534912846,53.45123868388348],"type":"Point"}
}