{
  "type": "Feature",
  "properties": {
    "iso:country": "GB",
    "wof:name": "TS20 2NX",
    "wof:placetype": "postalcode"
  },
  "geometry": {"coordinates":[-1.308955,54.584134],"type":"Point"}
}
