{
  "type": "Feature",
  "properties": {
    "iso:country":"GB",
    "wof:name":"SY10 7PB",
    "wof:placetype":"postalcode"
},
  "geometry": {"coordinates":[-3.12275669064618,52.89040646768628],"type":"Point"}
}