{
  "type": "Feature",
  "properties": {
    "iso:country": "GB",
    "wof:name": "SY10 7PB",
    "wof:placetype": "postalcode"
  },
  "geometry": {"coordinates":[-3.122757,52.890406],"type":"Point"}
}
