{
  "type": "Feature",
  "properties": {
    "date:inception_lower": "1980-01-01",
    "date:inception_upper": "1980-01-01",
    "iso:country": "GB",
    "wof:name": "SP3 6SS",
    "wof:placetype": "postalcode"
  },
  "geometry": {"coordinates":[-2.12356,51.053538],"type":"Point"}
}
