{
  "type": "Feature",
  "properties": {
    "iso:country":"GB",
    "wof:name":"NR11 7PG",
    "wof:placetype":"postalcode"
},
  "geometry": {"coordinates":[1.24855444852537,52.86421277969613],"type":"Point"}
}