{
  "type": "Feature",
  "properties": {
    "date:inception_lower": "1980-01-01",
    "date:inception_upper": "1980-01-01",
    "iso:country": "GB",
    "wof:name": "GU12 4RD",
    "wof:placetype": "postalcode"
  },
  "geometry": {"coordinates":[-0.747913,51.245795],"type":"Point"}
}
