{
  "type": "Feature",
  "properties": {
    "iso:country": "GB",
    "wof:name": "MK42 0UW",
    "wof:placetype": "postalcode"
  },
  "geometry": {"coordinates":[-0.433814,52.108138],"type":"Point"}
}
