{
  "type": "Feature",
  "properties": {
    "iso:country":"GB",
    "wof:name":"MK42 0UW",
    "wof:placetype":"postalcode"
},
  "geometry": {"coordinates":[-0.43381431529797,52.10813804082127],"type":"Point"}
}