{
  "type": "Feature",
  "properties": {
    "iso:country": "GB",
    "wof:name": "M29 8SF",
    "wof:placetype": "postalcode"
  },
  "geometry": {"coordinates":[-2.435406,53.510252],"type":"Point"}
}
