{
  "type": "Feature",
  "properties": {
    "date:inception_lower": "2017-12-01",
    "date:inception_upper": "2017-12-01",
    "iso:country": "GB",
    "wof:name": "M29 8SF",
    "wof:placetype": "postalcode"
  },
  "geometry": {"coordinates":[-2.434895,53.510407],"type":"Point"}
}
