{
  "type": "Feature",
  "properties": {
    "iso:country": "GB",
    "wof:name": "NG17 8NA",
    "wof:placetype": "postalcode"
  },
  "geometry": {"coordinates":[-1.264788,53.109294],"type":"Point"}
}
