{
  "type": "Feature",
  "properties": {
    "iso:country":"GB",
    "wof:name":"PE1 4FR",
    "wof:placetype":"postalcode"
},
  "geometry": {"coordinates":[-0.22759327579736,52.58275260575058],"type":"Point"}
}