{
  "type": "Feature",
  "properties": {
    "iso:country": "GB",
    "wof:name": "WV1 1JP",
    "wof:placetype": "postalcode"
  },
  "geometry": {"coordinates":[-2.125789,52.58843],"type":"Point"}
}
