{
  "type": "Feature",
  "properties": {
    "date:inception_lower": "1980-01-01",
    "date:inception_upper": "1980-01-01",
    "iso:country": "GB",
    "wof:name": "CM1 1JP",
    "wof:placetype": "postalcode"
  },
  "geometry": {"coordinates":[0.471512,51.734832],"type":"Point"}
}
