{
  "type": "Feature",
  "properties": {
    "iso:country":"GB",
    "wof:name":"CM1 1JP",
    "wof:placetype":"postalcode"
},
  "geometry": {"coordinates":[0.47048481875765,51.7353235290767],"type":"Point"}
}