{
  "type": "Feature",
  "properties": {
    "iso:country": "GB",
    "wof:name": "EC4M 9DD",
    "wof:placetype": "postalcode"
  },
  "geometry": {"coordinates":[-0.093295,51.512994],"type":"Point"}
}
