{
  "type": "Feature",
  "properties": {
    "date:inception_lower": "1980-01-01",
    "date:inception_upper": "1980-01-01",
    "iso:country": "GB",
    "wof:name": "EC4M 9DD",
    "wof:placetype": "postalcode"
  },
  "geometry": {"coordinates":[-0.093295,51.512994],"type":"Point"}
}
