{
  "type": "Feature",
  "properties": {
    "iso:country": "GB",
    "wof:name": "TQ12 3UD",
    "wof:placetype": "postalcode"
  },
  "geometry": {"coordinates":[-3.592633,50.543811],"type":"Point"}
}
