{
  "type": "Feature",
  "properties": {
    "date:inception_lower": "1991-09-01",
    "date:inception_upper": "1991-09-01",
    "iso:country": "GB",
    "wof:name": "TQ12 3UD",
    "wof:placetype": "postalcode"
  },
  "geometry": {"coordinates":[-3.592633,50.543811],"type":"Point"}
}
