{
  "type": "Feature",
  "properties": {
    "date:inception_lower": "1980-01-01",
    "date:inception_upper": "1980-01-01",
    "iso:country": "GB",
    "wof:name": "NE20 0TA",
    "wof:placetype": "postalcode"
  },
  "geometry": {"coordinates":[-1.957618,55.072179],"type":"Point"}
}
