{
  "type": "Feature",
  "properties": {
    "iso:country":"GB",
    "wof:name":"NE20 0TA",
    "wof:placetype":"postalcode"
},
  "geometry": {"coordinates":[-1.95760890047475,55.0721729588863],"type":"Point"}
}