{
  "type": "Feature",
  "properties": {
    "iso:country":"GB",
    "wof:name":"SY21 9HS",
    "wof:placetype":"postalcode"
},
  "geometry": {"coordinates":[-3.12990638201043,52.67353666768115],"type":"Point"}
}