{
  "type": "Feature",
  "properties": {
    "iso:country":"GB",
    "wof:name":"DY8 1BA",
    "wof:placetype":"postalcode"
},
  "geometry": {"coordinates":[-2.15114584800274,52.45071083826225],"type":"Point"}
}