{
  "type": "Feature",
  "properties": {
    "iso:country": "GB",
    "wof:name": "DY8 1BA",
    "wof:placetype": "postalcode"
  },
  "geometry": {"coordinates":[-2.15114,52.450734],"type":"Point"}
}
