{
  "type": "Feature",
  "properties": {
    "iso:country":"GB",
    "wof:name":"YO12 5SE",
    "wof:placetype":"postalcode"
},
  "geometry": {"coordinates":[-0.44534723507405,54.29367346308531],"type":"Point"}
}