{
  "type": "Feature",
  "properties": {
    "date:inception_lower": "1996-12-01",
    "date:inception_upper": "1996-12-01",
    "iso:country": "GB",
    "wof:name": "S60 1BX",
    "wof:placetype": "postalcode"
  },
  "geometry": {"coordinates":[-1.363571,53.42177],"type":"Point"}
}
