{
  "type": "Feature",
  "properties": {
    "iso:country":"GB",
    "wof:name":"S60 1BX",
    "wof:placetype":"postalcode"
},
  "geometry": {"coordinates":[-1.36446556731999,53.42133387349855],"type":"Point"}
}