{
  "type": "Feature",
  "properties": {
    "iso:country":"GB",
    "wof:name":"SS14 1TL",
    "wof:placetype":"postalcode"
},
  "geometry": {"coordinates":[0.4931619379787,51.56587145983586],"type":"Point"}
}