{
  "type": "Feature",
  "properties": {
    "date:inception_lower": "1980-01-01",
    "date:inception_upper": "1980-01-01",
    "iso:country": "GB",
    "wof:name": "S43 4AL",
    "wof:placetype": "postalcode"
  },
  "geometry": {"coordinates":[-1.252056,53.279927],"type":"Point"}
}
