{
  "type": "Feature",
  "properties": {
    "iso:country":"GB",
    "wof:name":"TA1 5ET",
    "wof:placetype":"postalcode"
},
  "geometry": {"coordinates":[-3.13562325064312,51.01695168590241],"type":"Point"}
}