{
  "type": "Feature",
  "properties": {
    "date:inception_lower": "2003-03-01",
    "date:inception_upper": "2003-03-01",
    "iso:country": "GB",
    "wof:name": "TA1 5ET",
    "wof:placetype": "postalcode"
  },
  "geometry": {"coordinates":[-3.135633,51.016947],"type":"Point"}
}
