{
  "type": "Feature",
  "properties": {
    "iso:country":"GB",
    "wof:name":"SN14 0QS",
    "wof:placetype":"postalcode"
},
  "geometry": {"coordinates":[-2.13828259303633,51.45828938925374],"type":"Point"}
}