{
  "type": "Feature",
  "properties": {
    "iso:country":"GB",
    "wof:name":"OX7 5XA",
    "wof:placetype":"postalcode"
},
  "geometry": {"coordinates":[-1.5396660795126,51.93155830636132],"type":"Point"}
}