{
  "type": "Feature",
  "properties": {
    "iso:country":"GB",
    "wof:name":"BN21 4BP",
    "wof:placetype":"postalcode"
},
  "geometry": {"coordinates":[0.28425279926282,50.7626618426103],"type":"Point"}
}