{
  "type": "Feature",
  "properties": {
    "iso:country":"GB",
    "wof:name":"B17 8AE",
    "wof:placetype":"postalcode"
},
  "geometry": {"coordinates":[-1.97178068464304,52.46990816619559],"type":"Point"}
}