{
  "type": "Feature",
  "properties": {
    "iso:country":"GB",
    "wof:name":"BH23 5EG",
    "wof:placetype":"postalcode"
},
  "geometry": {"coordinates":[-1.69819271945495,50.74168113058593],"type":"Point"}
}