{
  "type": "Feature",
  "properties": {
    "iso:country":"GB",
    "wof:name":"W10 5YA",
    "wof:placetype":"postalcode"
},
  "geometry": {"coordinates":[-0.21178678340784,51.52338538265894],"type":"Point"}
}