{
  "type": "Feature",
  "properties": {
    "iso:country": "GB",
    "wof:name": "W10 5YA",
    "wof:placetype": "postalcode"
  },
  "geometry": {"coordinates":[-0.211787,51.523385],"type":"Point"}
}
