{
  "type": "Feature",
  "properties": {
    "date:inception_lower": "2018-11-01",
    "date:inception_upper": "2018-11-01",
    "iso:country": "GB",
    "wof:name": "PE30 5FP",
    "wof:placetype": "postalcode"
  },
  "geometry": {"coordinates":[0.399839,52.74356],"type":"Point"}
}
