{
  "type": "Feature",
  "properties": {
    "iso:country":"GB",
    "wof:name":"NE1 4XN",
    "wof:placetype":"postalcode"
},
  "geometry": {"coordinates":[-1.6193874543397,54.97182163777445],"type":"Point"}
}