{
  "type": "Feature",
  "properties": {
    "iso:country":"GB",
    "wof:name":"CM3 2NP",
    "wof:placetype":"postalcode"
},
  "geometry": {"coordinates":[0.60200740935333,51.76416692121416],"type":"Point"}
}