{
  "type": "Feature",
  "properties": {
    "date:inception_lower":"2005-02-01",
    "date:inception_upper":"2005-02-28",
    "iso:country":"GB",
    "wof:name":"NG5 5UU",
    "wof:placetype":"postalcode"
},
  "geometry": {"coordinates":[-1.168809,52.992125],"type":"Point"}
}