{
  "type": "Feature",
  "properties": {
    "iso:country":"GB",
    "wof:name":"UB7 7UF",
    "wof:placetype":"postalcode"
},
  "geometry": {"coordinates":[-0.47367867934039,51.49701539718656],"type":"Point"}
}