{
  "type": "Feature",
  "properties": {
    "iso:country": "GB",
    "wof:name": "NP4 5SN",
    "wof:placetype": "postalcode"
  },
  "geometry": {"coordinates":[-3.034265,51.69554],"type":"Point"}
}
