{
  "type": "Feature",
  "properties": {
    "iso:country":"GB",
    "wof:name":"NP4 5SN",
    "wof:placetype":"postalcode"
},
  "geometry": {"coordinates":[-3.03426463896651,51.69553968625477],"type":"Point"}
}