{
  "type": "Feature",
  "properties": {
    "date:inception_lower": "1980-01-01",
    "date:inception_upper": "1980-01-01",
    "iso:country": "GB",
    "wof:name": "NP44 3QT",
    "wof:placetype": "postalcode"
  },
  "geometry": {"coordinates":[-3.018843,51.65051],"type":"Point"}
}
