{
  "type": "Feature",
  "properties": {
    "iso:country":"GB",
    "wof:name":"DA9 9PT",
    "wof:placetype":"postalcode"
},
  "geometry": {"coordinates":[0.26683345177743,51.4486436106266],"type":"Point"}
}