{
  "type": "Feature",
  "properties": {
    "iso:country": "GB",
    "wof:name": "DA9 9PT",
    "wof:placetype": "postalcode"
  },
  "geometry": {"coordinates":[0.266833,51.448644],"type":"Point"}
}
