{
  "type": "Feature",
  "properties": {
    "date:inception_lower": "1980-01-01",
    "date:inception_upper": "1980-01-01",
    "iso:country": "GB",
    "wof:name": "S75 6DJ",
    "wof:placetype": "postalcode"
  },
  "geometry": {"coordinates":[-1.487246,53.583205],"type":"Point"}
}
