{
  "type": "Feature",
  "properties": {
    "iso:country":"GB",
    "wof:name":"TF3 2ED",
    "wof:placetype":"postalcode"
},
  "geometry": {"coordinates":[-2.43344876019616,52.67432855053257],"type":"Point"}
}