{
  "type": "Feature",
  "properties": {
    "iso:country": "GB",
    "wof:name": "TF3 2ED",
    "wof:placetype": "postalcode"
  },
  "geometry": {"coordinates":[-2.433449,52.674329],"type":"Point"}
}
