{
  "type": "Feature",
  "properties": {
    "iso:country":"GB",
    "wof:name":"TN14 6JB",
    "wof:placetype":"postalcode"
},
  "geometry": {"coordinates":[0.14057886255613,51.24733332550423],"type":"Point"}
}