{
  "type": "Feature",
  "properties": {
    "iso:country":"GB",
    "wof:name":"SW19 5EG",
    "wof:placetype":"postalcode"
},
  "geometry": {"coordinates":[-0.21660424738928,51.42509902579211],"type":"Point"}
}