{
  "type": "Feature",
  "properties": {
    "iso:country": "GB",
    "wof:name": "SW19 5EG",
    "wof:placetype": "postalcode"
  },
  "geometry": {"coordinates":[-0.216638,51.42509],"type":"Point"}
}
