{
  "type": "Feature",
  "properties": {
    "date:inception_lower": "1980-01-01",
    "date:inception_upper": "1980-01-01",
    "iso:country": "GB",
    "wof:name": "TW14 9HJ",
    "wof:placetype": "postalcode"
  },
  "geometry": {"coordinates":[-0.41988,51.456728],"type":"Point"}
}
