{
  "type": "Feature",
  "properties": {
    "iso:country":"GB",
    "wof:name":"TW14 9HJ",
    "wof:placetype":"postalcode"
},
  "geometry": {"coordinates":[-0.4198804802692,51.45672801083794],"type":"Point"}
}