{
  "type": "Feature",
  "properties": {
    "iso:country":"GB",
    "wof:name":"M32 0HG",
    "wof:placetype":"postalcode"
},
  "geometry": {"coordinates":[-2.30128212406144,53.45307783142466],"type":"Point"}
}