{
  "type": "Feature",
  "properties": {
    "iso:country":"GB",
    "wof:name":"B31 3TE",
    "wof:placetype":"postalcode"
},
  "geometry": {"coordinates":[-1.96554324852785,52.40753375944243],"type":"Point"}
}