{
  "type": "Feature",
  "properties": {
    "iso:country": "GB",
    "wof:name": "NR12 0TJ",
    "wof:placetype": "postalcode"
  },
  "geometry": {"coordinates":[1.546806,52.788117],"type":"Point"}
}
