{
  "type": "Feature",
  "properties": {
    "iso:country": "GB",
    "wof:name": "AB56 5RW",
    "wof:placetype": "postalcode"
  },
  "geometry": {"coordinates":[-3.010983,57.664853],"type":"Point"}
}
