{
  "type": "Feature",
  "properties": {
    "iso:country":"GB",
    "wof:name":"W1U 3AZ",
    "wof:placetype":"postalcode"
},
  "geometry": {"coordinates":[-0.15206015850699,51.51602103771744],"type":"Point"}
}