{
  "type": "Feature",
  "properties": {
    "date:inception_lower":"2012-10-01",
    "date:inception_upper":"2012-10-31",
    "iso:country":"GB",
    "wof:name":"UB7 9GP",
    "wof:placetype":"postalcode"
},
  "geometry": {"coordinates":[-0.459674,51.507326],"type":"Point"}
}