{
  "type": "Feature",
  "properties": {
    "iso:country":"GB",
    "wof:name":"UB7 9GP",
    "wof:placetype":"postalcode"
},
  "geometry": {"coordinates":[-0.45967386143438,51.50732619658348],"type":"Point"}
}