{
  "type": "Feature",
  "properties": {
    "iso:country":"GB",
    "wof:name":"HU8 8TX",
    "wof:placetype":"postalcode"
},
  "geometry": {"coordinates":[-0.3184171338406,53.75927572589328],"type":"Point"}
}