{
  "type": "Feature",
  "properties": {
    "iso:country":"GB",
    "wof:name":"DL13 3LP",
    "wof:placetype":"postalcode"
},
  "geometry": {"coordinates":[-1.90754853011833,54.74202476507905],"type":"Point"}
}