{
  "type": "Feature",
  "properties": {
    "date:inception_lower":"1987-04-01",
    "date:inception_upper":"1987-04-30",
    "iso:country":"GB",
    "wof:name":"PL21 9DF",
    "wof:placetype":"postalcode"
},
  "geometry": {"coordinates":[-3.924688,50.386493],"type":"Point"}
}