{
  "type": "Feature",
  "properties": {
    "date:inception_lower": "1996-06-01",
    "date:inception_upper": "1996-06-01",
    "iso:country": "GB",
    "wof:name": "NN9 6NW",
    "wof:placetype": "postalcode"
  },
  "geometry": {"coordinates":[-0.53387,52.343768],"type":"Point"}
}
