{
  "type": "Feature",
  "properties": {
    "iso:country":"GB",
    "wof:name":"RH11 7HE",
    "wof:placetype":"postalcode"
},
  "geometry": {"coordinates":[-0.19939672567203,51.11934233743072],"type":"Point"}
}