{
  "type": "Feature",
  "properties": {
    "date:inception_lower": "1980-01-01",
    "date:inception_upper": "1980-01-01",
    "iso:country": "GB",
    "wof:name": "ST18 9HP",
    "wof:placetype": "postalcode"
  },
  "geometry": {"coordinates":[-2.200348,52.78298],"type":"Point"}
}
