{
  "type": "Feature",
  "properties": {
    "iso:country":"GB",
    "wof:name":"B67 5BB",
    "wof:placetype":"postalcode"
},
  "geometry": {"coordinates":[-1.97095221253634,52.47620993561037],"type":"Point"}
}