{
  "type": "Feature",
  "properties": {
    "iso:country":"GB",
    "wof:name":"TN10 3ED",
    "wof:placetype":"postalcode"
},
  "geometry": {"coordinates":[0.27679279382014,51.20523626329111],"type":"Point"}
}