{
  "type": "Feature",
  "properties": {
    "iso:country": "GB",
    "wof:name": "AB51 0ZN",
    "wof:placetype": "postalcode"
  },
  "geometry": {"coordinates":[-2.349161,57.230588],"type":"Point"}
}
