{
  "type": "Feature",
  "properties": {
    "iso:country":"GB",
    "wof:name":"AB51 0ZN",
    "wof:placetype":"postalcode"
},
  "geometry": {"coordinates":[-2.34916094355115,57.23058801503304],"type":"Point"}
}