{
  "type": "Feature",
  "properties": {
    "iso:country": "GB",
    "wof:name": "IP14 6LW",
    "wof:placetype": "postalcode"
  },
  "geometry": {"coordinates":[1.208587,52.19985],"type":"Point"}
}
