{
  "type": "Feature",
  "properties": {
    "iso:country":"GB",
    "wof:name":"IP14 6LW",
    "wof:placetype":"postalcode"
},
  "geometry": {"coordinates":[1.21072822699586,52.19969316840554],"type":"Point"}
}