{
  "type": "Feature",
  "properties": {
    "iso:country":"GB",
    "wof:name":"E4 9LG",
    "wof:placetype":"postalcode"
},
  "geometry": {"coordinates":[-0.00127809609908,51.60765606700483],"type":"Point"}
}