{
  "type": "Feature",
  "properties": {
    "date:inception_lower": "2019-12-01",
    "date:inception_upper": "2019-12-01",
    "iso:country": "GB",
    "wof:name": "SO31 8NG",
    "wof:placetype": "postalcode"
  },
  "geometry": {"coordinates":[-1.323751,50.894002],"type":"Point"}
}
