{
  "type": "Feature",
  "properties": {
    "iso:country": "GB",
    "wof:name": "B18 4EZ",
    "wof:placetype": "postalcode"
  },
  "geometry": {"coordinates":[-1.940991,52.48749],"type":"Point"}
}
