{
  "type": "Feature",
  "properties": {
    "iso:country":"GB",
    "wof:name":"B18 4EZ",
    "wof:placetype":"postalcode"
},
  "geometry": {"coordinates":[-1.94099094368194,52.4874902378011],"type":"Point"}
}