{
  "type": "Feature",
  "properties": {
    "iso:country": "GB",
    "wof:name": "CT19 4LZ",
    "wof:placetype": "postalcode"
  },
  "geometry": {"coordinates":[1.137666,51.092389],"type":"Point"}
}
