{
  "type": "Feature",
  "properties": {
    "iso:country": "GB",
    "wof:name": "BN24 5FB",
    "wof:placetype": "postalcode"
  },
  "geometry": {"coordinates":[0.294899,50.817343],"type":"Point"}
}
