{
  "type": "Feature",
  "properties": {
    "iso:country":"GB",
    "wof:name":"BN24 5FB",
    "wof:placetype":"postalcode"
},
  "geometry": {"coordinates":[0.29489921268347,50.81734317957386],"type":"Point"}
}