{
  "type": "Feature",
  "properties": {
    "date:inception_lower":"2003-11-01",
    "date:inception_upper":"2003-11-30",
    "iso:country":"GB",
    "wof:name":"PO13 9FA",
    "wof:placetype":"postalcode"
},
  "geometry": {"coordinates":[-1.199077,50.799439],"type":"Point"}
}