{
  "type": "Feature",
  "properties": {
    "iso:country":"GB",
    "wof:name":"W1F 8GY",
    "wof:placetype":"postalcode"
},
  "geometry": {"coordinates":[-0.13568014469821,51.51513234880633],"type":"Point"}
}