{
  "type": "Feature",
  "properties": {
    "date:inception_lower":"2000-12-01",
    "date:inception_upper":"2000-12-31",
    "iso:country":"GB",
    "wof:name":"W1F 8GY",
    "wof:placetype":"postalcode"
},
  "geometry": {"coordinates":[-0.13568,51.515132],"type":"Point"}
}