{
  "type": "Feature",
  "properties": {
    "iso:country":"GB",
    "wof:name":"LL55 1NB",
    "wof:placetype":"postalcode"
},
  "geometry": {"coordinates":[-4.26798409661585,53.14072826680511],"type":"Point"}
}