{
  "type": "Feature",
  "properties": {
    "iso:country":"GB",
    "wof:name":"RM10 8UB",
    "wof:placetype":"postalcode"
},
  "geometry": {"coordinates":[0.16670860097011,51.54287648923891],"type":"Point"}
}