{
  "type": "Feature",
  "properties": {
    "iso:country": "GB",
    "wof:name": "SP1 3TJ",
    "wof:placetype": "postalcode"
  },
  "geometry": {"coordinates":[-1.792974,51.07609],"type":"Point"}
}
