{
  "type": "Feature",
  "properties": {
    "date:inception_lower":"1980-01-01",
    "date:inception_upper":"1980-01-31",
    "iso:country":"GB",
    "wof:name":"SP1 3TJ",
    "wof:placetype":"postalcode"
},
  "geometry": {"coordinates":[-1.792974,51.07609],"type":"Point"}
}