{
  "type": "Feature",
  "properties": {
    "iso:country":"GB",
    "wof:name":"SP1 3TJ",
    "wof:placetype":"postalcode"
},
  "geometry": {"coordinates":[-1.7929745038242,51.07608986666884],"type":"Point"}
}