{
  "type": "Feature",
  "properties": {
    "date:inception_lower": "1980-01-01",
    "date:inception_upper": "1980-01-01",
    "iso:country": "GB",
    "wof:name": "B77 1ED",
    "wof:placetype": "postalcode"
  },
  "geometry": {"coordinates":[-1.682737,52.615474],"type":"Point"}
}
