{
  "type": "Feature",
  "properties": {
    "iso:country":"GB",
    "wof:name":"DY12 1EP",
    "wof:placetype":"postalcode"
},
  "geometry": {"coordinates":[-2.30490187951741,52.38337500889229],"type":"Point"}
}