{
  "type": "Feature",
  "properties": {
    "date:inception_lower":"1980-01-01",
    "date:inception_upper":"1980-01-31",
    "iso:country":"GB",
    "wof:name":"DY12 1EP",
    "wof:placetype":"postalcode"
},
  "geometry": {"coordinates":[-2.304902,52.383375],"type":"Point"}
}