{
  "type": "Feature",
  "properties": {
    "iso:country":"GB",
    "wof:name":"ST8 6SB",
    "wof:placetype":"postalcode"
},
  "geometry": {"coordinates":[-2.18429673233798,53.10595444449456],"type":"Point"}
}