{
  "type": "Feature",
  "properties": {
    "iso:country": "GB",
    "wof:name": "ST8 6SB",
    "wof:placetype": "postalcode"
  },
  "geometry": {"coordinates":[-2.184297,53.105954],"type":"Point"}
}
