{
  "type": "Feature",
  "properties": {
    "iso:country":"GB",
    "wof:name":"DD2 5LR",
    "wof:placetype":"postalcode"
},
  "geometry": {"coordinates":[-3.0917621008295,56.48125042121409],"type":"Point"}
}