{
  "type": "Feature",
  "properties": {
    "date:inception_lower": "1980-01-01",
    "date:inception_upper": "1980-01-01",
    "iso:country": "GB",
    "wof:name": "CA15 6PH",
    "wof:placetype": "postalcode"
  },
  "geometry": {"coordinates":[-3.430788,54.772118],"type":"Point"}
}
