{
  "type": "Feature",
  "properties": {
    "date:inception_lower":"2014-05-01",
    "date:inception_upper":"2014-05-31",
    "iso:country":"GB",
    "wof:name":"LE10 0FZ",
    "wof:placetype":"postalcode"
},
  "geometry": {"coordinates":[-1.381759,52.551617],"type":"Point"}
}