{
  "type": "Feature",
  "properties": {
    "iso:country":"GB",
    "wof:name":"LE10 0FZ",
    "wof:placetype":"postalcode"
},
  "geometry": {"coordinates":[-1.38175915506444,52.5516171581731],"type":"Point"}
}