{
  "type": "Feature",
  "properties": {
    "date:inception_lower": "2021-01-01",
    "date:inception_upper": "2021-01-01",
    "iso:country": "GB",
    "wof:name": "NN4 0AJ",
    "wof:placetype": "postalcode"
  },
  "geometry": {"coordinates":[-0.905725,52.19781],"type":"Point"}
}
