{
  "type": "Feature",
  "properties": {
    "iso:country":"GB",
    "wof:name":"W1J 6NJ",
    "wof:placetype":"postalcode"
},
  "geometry": {"coordinates":[-0.14509887886754,51.51069550473928],"type":"Point"}
}