{
  "type": "Feature",
  "properties": {
    "iso:country":"GB",
    "wof:name":"HR1 2NS",
    "wof:placetype":"postalcode"
},
  "geometry": {"coordinates":[-2.71171214677694,52.05390185535965],"type":"Point"}
}