{
  "type": "Feature",
  "properties": {
    "iso:country":"GB",
    "wof:name":"EX33 1JG",
    "wof:placetype":"postalcode"
},
  "geometry": {"coordinates":[-4.20697766501751,51.13046211022735],"type":"Point"}
}