{
  "type": "Feature",
  "properties": {
    "iso:country":"GB",
    "wof:name":"NG2 4JH",
    "wof:placetype":"postalcode"
},
  "geometry": {"coordinates":[-1.1329629898521,52.95052651383968],"type":"Point"}
}