{
  "type": "Feature",
  "properties": {
    "iso:country":"GB",
    "wof:name":"SG5 2JX",
    "wof:placetype":"postalcode"
},
  "geometry": {"coordinates":[-0.28354748880651,51.95026616688506],"type":"Point"}
}