{
  "type": "Feature",
  "properties": {
    "iso:country": "GB",
    "wof:name": "SG5 2JX",
    "wof:placetype": "postalcode"
  },
  "geometry": {"coordinates":[-0.283523,51.950265],"type":"Point"}
}
