{
  "type": "Feature",
  "properties": {
    "date:inception_lower":"2014-06-01",
    "date:inception_upper":"2014-06-30",
    "iso:country":"GB",
    "wof:name":"M22 2DQ",
    "wof:placetype":"postalcode"
},
  "geometry": {"coordinates":[-2.258733,53.397233],"type":"Point"}
}