{
  "type": "Feature",
  "properties": {
    "iso:country":"GB",
    "wof:name":"DE22 3RQ",
    "wof:placetype":"postalcode"
},
  "geometry": {"coordinates":[-1.48755285660845,52.91766880286792],"type":"Point"}
}