{
  "type": "Feature",
  "properties": {
    "iso:country":"GB",
    "wof:name":"SW1Y 4PE",
    "wof:placetype":"postalcode"
},
  "geometry": {"coordinates":[-0.13318512531758,51.50847417150195],"type":"Point"}
}