{
  "type": "Feature",
  "properties": {
    "iso:country":"GB",
    "wof:name":"HG3 1HW",
    "wof:placetype":"postalcode"
},
  "geometry": {"coordinates":[-1.51718384268266,53.9364628550038],"type":"Point"}
}