{
  "type": "Feature",
  "properties": {
    "date:inception_lower": "1980-01-01",
    "date:inception_upper": "1980-01-01",
    "iso:country": "GB",
    "wof:name": "HG3 1HW",
    "wof:placetype": "postalcode"
  },
  "geometry": {"coordinates":[-1.517184,53.936463],"type":"Point"}
}
