{
  "type": "Feature",
  "properties": {
    "iso:country":"GB",
    "wof:name":"EX15 3SU",
    "wof:placetype":"postalcode"
},
  "geometry": {"coordinates":[-3.21637308436685,50.92921533534456],"type":"Point"}
}