{
  "type": "Feature",
  "properties": {
    "iso:country":"GB",
    "wof:name":"M34 2HR",
    "wof:placetype":"postalcode"
},
  "geometry": {"coordinates":[-2.14666468305128,53.44974564727499],"type":"Point"}
}