{
  "type": "Feature",
  "properties": {
    "iso:country":"GB",
    "wof:name":"GL2 0DX",
    "wof:placetype":"postalcode"
},
  "geometry": {"coordinates":[-2.2125578883723,51.87950656920562],"type":"Point"}
}