{
  "type": "Feature",
  "properties": {
    "iso:country":"GB",
    "wof:name":"IG6 2SJ",
    "wof:placetype":"postalcode"
},
  "geometry": {"coordinates":[0.07802641114076,51.60421945508245],"type":"Point"}
}