{
  "type": "Feature",
  "properties": {
    "date:inception_lower":"1981-06-01",
    "date:inception_upper":"1981-06-30",
    "iso:country":"GB",
    "wof:name":"SN12 6UA",
    "wof:placetype":"postalcode"
},
  "geometry": {"coordinates":[-2.127049,51.357317],"type":"Point"}
}