{
  "type": "Feature",
  "properties": {
    "iso:country":"GB",
    "wof:name":"SN12 6UA",
    "wof:placetype":"postalcode"
},
  "geometry": {"coordinates":[-2.12704879043772,51.35731734104714],"type":"Point"}
}