{
  "type": "Feature",
  "properties": {
    "iso:country":"GB",
    "wof:name":"SW12 8NG",
    "wof:placetype":"postalcode"
},
  "geometry": {"coordinates":[-0.16268243974675,51.44829435255023],"type":"Point"}
}