{
  "type": "Feature",
  "properties": {
    "iso:country":"GB",
    "wof:name":"FY2 9GJ",
    "wof:placetype":"postalcode"
},
  "geometry": {"coordinates":[-3.05261325198056,53.84600873010945],"type":"Point"}
}