{
  "type": "Feature",
  "properties": {
    "iso:country":"GB",
    "wof:name":"WA3 2SQ",
    "wof:placetype":"postalcode"
},
  "geometry": {"coordinates":[-2.58519333098299,53.46919219647778],"type":"Point"}
}