{
  "type": "Feature",
  "properties": {
    "date:inception_lower": "1992-08-01",
    "date:inception_upper": "1992-08-01",
    "iso:country": "GB",
    "wof:name": "GL7 2DF",
    "wof:placetype": "postalcode"
  },
  "geometry": {"coordinates":[-1.972751,51.721158],"type":"Point"}
}
