{
  "type": "Feature",
  "properties": {
    "iso:country":"GB",
    "wof:name":"GL7 2DF",
    "wof:placetype":"postalcode"
},
  "geometry": {"coordinates":[-1.97275148028531,51.72115760644728],"type":"Point"}
}