{
  "type": "Feature",
  "properties": {
    "iso:country":"GB",
    "wof:name":"G78 3JJ",
    "wof:placetype":"postalcode"
},
  "geometry": {"coordinates":[-4.43345174666708,55.77933045694202],"type":"Point"}
}