{
  "type": "Feature",
  "properties": {
    "iso:country":"GB",
    "wof:name":"BB7 3JL",
    "wof:placetype":"postalcode"
},
  "geometry": {"coordinates":[-2.4116424149452,53.88873974678658],"type":"Point"}
}