{
  "type": "Feature",
  "properties": {
    "iso:country":"GB",
    "wof:name":"NR20 4UA",
    "wof:placetype":"postalcode"
},
  "geometry": {"coordinates":[0.94782415287838,52.68150988744046],"type":"Point"}
}