{
  "type": "Feature",
  "properties": {
    "date:inception_lower": "1980-01-01",
    "date:inception_upper": "1980-01-01",
    "iso:country": "GB",
    "wof:name": "NG5 6AS",
    "wof:placetype": "postalcode"
  },
  "geometry": {"coordinates":[-1.14503,52.998285],"type":"Point"}
}
