{
  "type": "Feature",
  "properties": {
    "iso:country": "GB",
    "wof:name": "TS24 8HU",
    "wof:placetype": "postalcode"
  },
  "geometry": {"coordinates":[-1.220681,54.696025],"type":"Point"}
}
