{
  "type": "Feature",
  "properties": {
    "date:inception_lower":"2015-11-01",
    "date:inception_upper":"2015-11-30",
    "iso:country":"GB",
    "wof:name":"TS24 8HU",
    "wof:placetype":"postalcode"
},
  "geometry": {"coordinates":[-1.220681,54.696025],"type":"Point"}
}