{
  "type": "Feature",
  "properties": {
    "iso:country": "GB",
    "wof:name": "TD9 8QU",
    "wof:placetype": "postalcode"
  },
  "geometry": {"coordinates":[-2.676149,55.400556],"type":"Point"}
}
