{
  "type": "Feature",
  "properties": {
    "iso:country":"GB",
    "wof:name":"HU1 2ED",
    "wof:placetype":"postalcode"
},
  "geometry": {"coordinates":[-0.33447787636017,53.74327451841064],"type":"Point"}
}