{
  "type": "Feature",
  "properties": {
    "date:inception_lower": "1999-06-01",
    "date:inception_upper": "1999-06-01",
    "iso:country": "GB",
    "wof:name": "HU1 2ED",
    "wof:placetype": "postalcode"
  },
  "geometry": {"coordinates":[-0.334478,53.743275],"type":"Point"}
}
