{
  "type": "Feature",
  "properties": {
    "iso:country":"GB",
    "wof:name":"EX38 8DX",
    "wof:placetype":"postalcode"
},
  "geometry": {"coordinates":[-4.14667673347206,50.95217399959443],"type":"Point"}
}