{
  "type": "Feature",
  "properties": {
    "iso:country": "GB",
    "wof:name": "EX38 8DX",
    "wof:placetype": "postalcode"
  },
  "geometry": {"coordinates":[-4.146677,50.952174],"type":"Point"}
}
