{
  "type": "Feature",
  "properties": {
    "iso:country":"GB",
    "wof:name":"SA9 1EY",
    "wof:placetype":"postalcode"
},
  "geometry": {"coordinates":[-3.75862604769357,51.77736889680109],"type":"Point"}
}