{
  "type": "Feature",
  "properties": {
    "iso:country": "GB",
    "wof:name": "HX2 6PU",
    "wof:placetype": "postalcode"
  },
  "geometry": {"coordinates":[-1.93704,53.733031],"type":"Point"}
}
