{
  "type": "Feature",
  "properties": {
    "iso:country": "GB",
    "wof:name": "ST17 0TA",
    "wof:placetype": "postalcode"
  },
  "geometry": {"coordinates":[-2.063559,52.770646],"type":"Point"}
}
