{
  "type": "Feature",
  "properties": {
    "iso:country": "GB",
    "wof:name": "KY8 5LF",
    "wof:placetype": "postalcode"
  },
  "geometry": {"coordinates":[-3.053685,56.21307],"type":"Point"}
}
