{
  "type": "Feature",
  "properties": {
    "iso:country":"GB",
    "wof:name":"KY8 5LF",
    "wof:placetype":"postalcode"
},
  "geometry": {"coordinates":[-3.05395918842099,56.21306768585143],"type":"Point"}
}