{
  "type": "Feature",
  "properties": {
    "iso:country":"GB",
    "wof:name":"SN7 7NB",
    "wof:placetype":"postalcode"
},
  "geometry": {"coordinates":[-1.61155963297835,51.64075836913893],"type":"Point"}
}