{
  "type": "Feature",
  "properties": {
    "iso:country":"GB",
    "wof:name":"RM12 5NS",
    "wof:placetype":"postalcode"
},
  "geometry": {"coordinates":[0.20123441235941,51.54137033785184],"type":"Point"}
}