{
  "type": "Feature",
  "properties": {
    "iso:country":"GB",
    "wof:name":"N19 3AQ",
    "wof:placetype":"postalcode"
},
  "geometry": {"coordinates":[-0.12253518816427,51.57190805460306],"type":"Point"}
}