{
  "type": "Feature",
  "properties": {
    "iso:country":"GB",
    "wof:name":"KT3 3QQ",
    "wof:placetype":"postalcode"
},
  "geometry": {"coordinates":[-0.26013712705908,51.40068218202725],"type":"Point"}
}