{
  "type": "Feature",
  "properties": {
    "iso:country":"GB",
    "wof:name":"DE23 3YJ",
    "wof:placetype":"postalcode"
},
  "geometry": {"coordinates":[-1.52107741222095,52.88911443212992],"type":"Point"}
}