{
  "type": "Feature",
  "properties": {
    "iso:country":"GB",
    "wof:name":"LL11 3YU",
    "wof:placetype":"postalcode"
},
  "geometry": {"coordinates":[-3.08560186672441,53.05928082830263],"type":"Point"}
}