{
  "type": "Feature",
  "properties": {
    "date:inception_lower": "1984-10-01",
    "date:inception_upper": "1984-10-01",
    "iso:country": "GB",
    "wof:name": "LL11 3YU",
    "wof:placetype": "postalcode"
  },
  "geometry": {"coordinates":[-3.085602,53.059281],"type":"Point"}
}
