{
  "type": "Feature",
  "properties": {
    "date:inception_lower": "1997-06-01",
    "date:inception_upper": "1997-06-01",
    "iso:country": "GB",
    "wof:name": "EN8 9RN",
    "wof:placetype": "postalcode"
  },
  "geometry": {"coordinates":[-0.032273,51.703401],"type":"Point"}
}
