{
  "type": "Feature",
  "properties": {
    "iso:country":"GB",
    "wof:name":"KA3 1LU",
    "wof:placetype":"postalcode"
},
  "geometry": {"coordinates":[-4.50637988920459,55.61648914201006],"type":"Point"}
}