{
  "type": "Feature",
  "properties": {
    "date:inception_lower": "1993-02-01",
    "date:inception_upper": "1993-02-01",
    "iso:country": "GB",
    "wof:name": "KA3 1LU",
    "wof:placetype": "postalcode"
  },
  "geometry": {"coordinates":[-4.506358,55.616642],"type":"Point"}
}
