{
  "type": "Feature",
  "properties": {
    "iso:country":"GB",
    "wof:name":"TA4 3AE",
    "wof:placetype":"postalcode"
},
  "geometry": {"coordinates":[-3.22924136951002,51.04424985944551],"type":"Point"}
}