{
  "type": "Feature",
  "properties": {
    "iso:country": "GB",
    "wof:name": "TA4 3AE",
    "wof:placetype": "postalcode"
  },
  "geometry": {"coordinates":[-3.229241,51.04425],"type":"Point"}
}
