{
  "type": "Feature",
  "properties": {
    "iso:country":"GB",
    "wof:name":"PO21 4TG",
    "wof:placetype":"postalcode"
},
  "geometry": {"coordinates":[-0.74169646801828,50.76681431174967],"type":"Point"}
}