{
  "type": "Feature",
  "properties": {
    "iso:country":"GB",
    "wof:name":"IP2 8QP",
    "wof:placetype":"postalcode"
},
  "geometry": {"coordinates":[1.14360264210158,52.03721166635296],"type":"Point"}
}