{
  "type": "Feature",
  "properties": {
    "iso:country": "GB",
    "wof:name": "ME16 8RP",
    "wof:placetype": "postalcode"
  },
  "geometry": {"coordinates":[0.51458,51.271164],"type":"Point"}
}
