{
  "type": "Feature",
  "properties": {
    "date:inception_lower": "1980-01-01",
    "date:inception_upper": "1980-01-01",
    "iso:country": "GB",
    "wof:name": "CO10 0DN",
    "wof:placetype": "postalcode"
  },
  "geometry": {"coordinates":[0.746967,52.033207],"type":"Point"}
}
