{
  "type": "Feature",
  "properties": {
    "iso:country":"GB",
    "wof:name":"CO10 0DN",
    "wof:placetype":"postalcode"
},
  "geometry": {"coordinates":[0.74696286453896,52.03316652268084],"type":"Point"}
}