{
  "type": "Feature",
  "properties": {
    "date:inception_lower":"1990-07-01",
    "date:inception_upper":"1990-07-31",
    "iso:country":"GB",
    "wof:name":"M4 7EY",
    "wof:placetype":"postalcode"
},
  "geometry": {"coordinates":[-2.214888,53.482243],"type":"Point"}
}