{
  "type": "Feature",
  "properties": {
    "iso:country":"GB",
    "wof:name":"DT6 6QE",
    "wof:placetype":"postalcode"
},
  "geometry": {"coordinates":[-2.89949325130814,50.73940016521883],"type":"Point"}
}