{
  "type": "Feature",
  "properties": {
    "date:inception_lower": "1980-01-01",
    "date:inception_upper": "1980-01-01",
    "iso:country": "GB",
    "wof:name": "DT6 6QE",
    "wof:placetype": "postalcode"
  },
  "geometry": {"coordinates":[-2.899493,50.7394],"type":"Point"}
}
