{
  "type": "Feature",
  "properties": {
    "iso:country": "GB",
    "wof:name": "SY10 7UB",
    "wof:placetype": "postalcode"
  },
  "geometry": {"coordinates":[-3.033383,52.902284],"type":"Point"}
}
