{
  "type": "Feature",
  "properties": {
    "date:inception_lower":"2000-12-01",
    "date:inception_upper":"2000-12-31",
    "iso:country":"GB",
    "wof:name":"WD4 8ND",
    "wof:placetype":"postalcode"
},
  "geometry": {"coordinates":[-0.431702,51.718188],"type":"Point"}
}