{
  "type": "Feature",
  "properties": {
    "iso:country":"GB",
    "wof:name":"CO7 8AA",
    "wof:placetype":"postalcode"
},
  "geometry": {"coordinates":[0.99760720868225,51.85350905720684],"type":"Point"}
}