{
  "type": "Feature",
  "properties": {
    "iso:country": "GB",
    "wof:name": "CO7 8AA",
    "wof:placetype": "postalcode"
  },
  "geometry": {"coordinates":[0.997607,51.853509],"type":"Point"}
}
