{
  "type": "Feature",
  "properties": {
    "iso:country":"GB",
    "wof:name":"HA7 3AG",
    "wof:placetype":"postalcode"
},
  "geometry": {"coordinates":[-0.3177479676414,51.62003664274293],"type":"Point"}
}