{
  "type": "Feature",
  "properties": {
    "iso:country":"GB",
    "wof:name":"B98 9NR",
    "wof:placetype":"postalcode"
},
  "geometry": {"coordinates":[-1.88838104332959,52.31490576395723],"type":"Point"}
}