{
  "type": "Feature",
  "properties": {
    "iso:country":"GB",
    "wof:name":"B67 7HE",
    "wof:placetype":"postalcode"
},
  "geometry": {"coordinates":[-1.99132607018007,52.48955422894232],"type":"Point"}
}