{
  "type": "Feature",
  "properties": {
    "iso:country": "GB",
    "wof:name": "PE19 2NN",
    "wof:placetype": "postalcode"
  },
  "geometry": {"coordinates":[-0.262008,52.214833],"type":"Point"}
}
