{
  "type": "Feature",
  "properties": {
    "iso:country":"GB",
    "wof:name":"PE19 2NN",
    "wof:placetype":"postalcode"
},
  "geometry": {"coordinates":[-0.26200795419966,52.21483299423343],"type":"Point"}
}