{
  "type": "Feature",
  "properties": {
    "iso:country": "GB",
    "wof:name": "M9 0GN",
    "wof:placetype": "postalcode"
  },
  "geometry": {"coordinates":[-2.230402,53.536585],"type":"Point"}
}
