{
  "type": "Feature",
  "properties": {
    "iso:country":"GB",
    "wof:name":"CV2 1NL",
    "wof:placetype":"postalcode"
},
  "geometry": {"coordinates":[-1.46688134995666,52.45209775923389],"type":"Point"}
}