{
  "type": "Feature",
  "properties": {
    "date:inception_lower": "1993-01-01",
    "date:inception_upper": "1993-01-01",
    "iso:country": "GB",
    "wof:name": "HU7 4WY",
    "wof:placetype": "postalcode"
  },
  "geometry": {"coordinates":[-0.306486,53.776061],"type":"Point"}
}
