{
  "type": "Feature",
  "properties": {
    "iso:country":"GB",
    "wof:name":"HX3 7EE",
    "wof:placetype":"postalcode"
},
  "geometry": {"coordinates":[-1.83413423685902,53.73970089207226],"type":"Point"}
}