{
  "type": "Feature",
  "properties": {
    "iso:country":"GB",
    "wof:name":"RG27 0SF",
    "wof:placetype":"postalcode"
},
  "geometry": {"coordinates":[-1.04504582381459,51.30106439424839],"type":"Point"}
}