{
  "type": "Feature",
  "properties": {
    "iso:country": "GB",
    "wof:name": "RG27 0SF",
    "wof:placetype": "postalcode"
  },
  "geometry": {"coordinates":[-1.045046,51.301064],"type":"Point"}
}
