{
  "type": "Feature",
  "properties": {
    "iso:country": "GB",
    "wof:name": "SG9 0LJ",
    "wof:placetype": "postalcode"
  },
  "geometry": {"coordinates":[0.08371,51.931362],"type":"Point"}
}
