{
  "type": "Feature",
  "properties": {
    "iso:country":"GB",
    "wof:name":"SG9 0LJ",
    "wof:placetype":"postalcode"
},
  "geometry": {"coordinates":[0.08371025836382,51.93136249995282],"type":"Point"}
}