{
  "type": "Feature",
  "properties": {
    "iso:country":"GB",
    "wof:name":"TW10 6EG",
    "wof:placetype":"postalcode"
},
  "geometry": {"coordinates":[-0.29355276709026,51.46039783501607],"type":"Point"}
}