{
  "type": "Feature",
  "properties": {
    "iso:country":"GB",
    "wof:name":"DE24 9BX",
    "wof:placetype":"postalcode"
},
  "geometry": {"coordinates":[-1.4503350780367,52.89003985328903],"type":"Point"}
}