{
  "type": "Feature",
  "properties": {
    "iso:country":"GB",
    "wof:name":"SA11 3HY",
    "wof:placetype":"postalcode"
},
  "geometry": {"coordinates":[-3.79191621201795,51.66406855559867],"type":"Point"}
}