{
  "type": "Feature",
  "properties": {
    "iso:country":"GB",
    "wof:name":"B28 8JP",
    "wof:placetype":"postalcode"
},
  "geometry": {"coordinates":[-1.84485884762981,52.43625039392374],"type":"Point"}
}