{
  "type": "Feature",
  "properties": {
    "iso:country": "GB",
    "wof:name": "B28 8JP",
    "wof:placetype": "postalcode"
  },
  "geometry": {"coordinates":[-1.844859,52.43625],"type":"Point"}
}
