{
  "type": "Feature",
  "properties": {
    "iso:country":"GB",
    "wof:name":"KT3 6NY",
    "wof:placetype":"postalcode"
},
  "geometry": {"coordinates":[-0.24701720048877,51.39451560450028],"type":"Point"}
}