{
  "type": "Feature",
  "properties": {
    "iso:country": "GB",
    "wof:name": "KT3 6NY",
    "wof:placetype": "postalcode"
  },
  "geometry": {"coordinates":[-0.247017,51.394516],"type":"Point"}
}
