{
  "type": "Feature",
  "properties": {
    "iso:country":"GB",
    "wof:name":"ME2 2UH",
    "wof:placetype":"postalcode"
},
  "geometry": {"coordinates":[0.47818537790881,51.39218496219674],"type":"Point"}
}