{
  "type": "Feature",
  "properties": {
    "iso:country": "GB",
    "wof:name": "AB55 4EX",
    "wof:placetype": "postalcode"
  },
  "geometry": {"coordinates":[-3.134778,57.444757],"type":"Point"}
}
