{
  "type": "Feature",
  "properties": {
    "iso:country":"GB",
    "wof:name":"AB55 4EX",
    "wof:placetype":"postalcode"
},
  "geometry": {"coordinates":[-3.1347785167235,57.44475697362108],"type":"Point"}
}