{
  "type": "Feature",
  "properties": {
    "iso:country": "GB",
    "wof:name": "DL5 6JZ",
    "wof:placetype": "postalcode"
  },
  "geometry": {"coordinates":[-1.56426,54.596951],"type":"Point"}
}
