{
  "type": "Feature",
  "properties": {
    "iso:country":"GB",
    "wof:name":"DL5 6JZ",
    "wof:placetype":"postalcode"
},
  "geometry": {"coordinates":[-1.56426000013878,54.59695102856703],"type":"Point"}
}