{
  "type": "Feature",
  "properties": {
    "iso:country": "GB",
    "wof:name": "GL7 7EX",
    "wof:placetype": "postalcode"
  },
  "geometry": {"coordinates":[-1.985311,51.805305],"type":"Point"}
}
