{
  "type": "Feature",
  "properties": {
    "iso:country":"GB",
    "wof:name":"GL7 7EX",
    "wof:placetype":"postalcode"
},
  "geometry": {"coordinates":[-1.98508699308588,51.8055049056027],"type":"Point"}
}