{
  "type": "Feature",
  "properties": {
    "iso:country":"GB",
    "wof:name":"AB52 6NS",
    "wof:placetype":"postalcode"
},
  "geometry": {"coordinates":[-2.66662032570506,57.31755380821016],"type":"Point"}
}