{
  "type": "Feature",
  "properties": {
    "iso:country": "GB",
    "wof:name": "AL5 3BH",
    "wof:placetype": "postalcode"
  },
  "geometry": {"coordinates":[-0.367956,51.823631],"type":"Point"}
}
