{
  "type": "Feature",
  "properties": {
    "iso:country": "GB",
    "wof:name": "SA68 0ZB",
    "wof:placetype": "postalcode"
  },
  "geometry": {"coordinates":[-4.71786,51.733708],"type":"Point"}
}
