{
  "type": "Feature",
  "properties": {
    "date:inception_lower": "2013-11-01",
    "date:inception_upper": "2013-11-01",
    "iso:country": "GB",
    "wof:name": "OX9 3EN",
    "wof:placetype": "postalcode"
  },
  "geometry": {"coordinates":[-0.971325,51.739607],"type":"Point"}
}
