{
  "type": "Feature",
  "properties": {
    "iso:country":"GB",
    "wof:name":"B29 7HH",
    "wof:placetype":"postalcode"
},
  "geometry": {"coordinates":[-1.91545805868692,52.4473615178221],"type":"Point"}
}