{
  "type": "Feature",
  "properties": {
    "date:inception_lower":"2013-12-01",
    "date:inception_upper":"2013-12-31",
    "iso:country":"GB",
    "wof:name":"FK5 4XF",
    "wof:placetype":"postalcode"
},
  "geometry": {"coordinates":[-3.818851,56.037704],"type":"Point"}
}