{
  "type": "Feature",
  "properties": {
    "iso:country":"GB",
    "wof:name":"FK5 4XF",
    "wof:placetype":"postalcode"
},
  "geometry": {"coordinates":[-3.81885057884661,56.0377036633625],"type":"Point"}
}