{
  "type": "Feature",
  "properties": {
    "iso:country": "GB",
    "wof:name": "HD7 6EY",
    "wof:placetype": "postalcode"
  },
  "geometry": {"coordinates":[-1.928353,53.599893],"type":"Point"}
}
