{
  "type": "Feature",
  "properties": {
    "iso:country":"GB",
    "wof:name":"HD7 6EY",
    "wof:placetype":"postalcode"
},
  "geometry": {"coordinates":[-1.92835256293517,53.59989347507962],"type":"Point"}
}