{
  "type": "Feature",
  "properties": {
    "iso:country":"GB",
    "wof:name":"WN8 8UZ",
    "wof:placetype":"postalcode"
},
  "geometry": {"coordinates":[-2.81169075303647,53.55450946343422],"type":"Point"}
}