{
  "type": "Feature",
  "properties": {
    "iso:country":"GB",
    "wof:name":"DY12 2BS",
    "wof:placetype":"postalcode"
},
  "geometry": {"coordinates":[-2.32462262815918,52.37792836490215],"type":"Point"}
}