{
  "type": "Feature",
  "properties": {
    "iso:country": "GB",
    "wof:name": "OX1 5EX",
    "wof:placetype": "postalcode"
  },
  "geometry": {"coordinates":[-1.293735,51.716513],"type":"Point"}
}
