{
  "type": "Feature",
  "properties": {
    "iso:country": "GB",
    "wof:name": "LE12 6YS",
    "wof:placetype": "postalcode"
  },
  "geometry": {"coordinates":[-1.184928,52.823927],"type":"Point"}
}
