{
  "type": "Feature",
  "properties": {
    "date:inception_lower": "2020-04-01",
    "date:inception_upper": "2020-04-01",
    "iso:country": "GB",
    "wof:name": "LE12 6YS",
    "wof:placetype": "postalcode"
  },
  "geometry": {"coordinates":[-1.184928,52.823927],"type":"Point"}
}
