{
  "type": "Feature",
  "properties": {
    "iso:country":"GB",
    "wof:name":"NN7 4BD",
    "wof:placetype":"postalcode"
},
  "geometry": {"coordinates":[-0.98323497528213,52.22759208981787],"type":"Point"}
}