{
  "type": "Feature",
  "properties": {
    "iso:country":"GB",
    "wof:name":"SO24 9EY",
    "wof:placetype":"postalcode"
},
  "geometry": {"coordinates":[-1.16482487387248,51.08777789279509],"type":"Point"}
}