{
  "type": "Feature",
  "properties": {
    "iso:country":"GB",
    "wof:name":"S71 5DY",
    "wof:placetype":"postalcode"
},
  "geometry": {"coordinates":[-1.41849438714051,53.54751183095229],"type":"Point"}
}