{
  "type": "Feature",
  "properties": {
    "iso:country": "GB",
    "wof:name": "CB25 0EB",
    "wof:placetype": "postalcode"
  },
  "geometry": {"coordinates":[0.323284,52.279844],"type":"Point"}
}
