{
  "type": "Feature",
  "properties": {
    "iso:country":"GB",
    "wof:name":"CB25 0EB",
    "wof:placetype":"postalcode"
},
  "geometry": {"coordinates":[0.32328415198332,52.27984418702154],"type":"Point"}
}