{
  "type": "Feature",
  "properties": {
    "date:inception_lower":"2000-10-01",
    "date:inception_upper":"2000-10-31",
    "iso:country":"GB",
    "wof:name":"WD23 1DQ",
    "wof:placetype":"postalcode"
},
  "geometry": {"coordinates":[-0.353715,51.636076],"type":"Point"}
}