{
  "type": "Feature",
  "properties": {
    "iso:country":"GB",
    "wof:name":"TQ12 6HG",
    "wof:placetype":"postalcode"
},
  "geometry": {"coordinates":[-3.67003754802056,50.56147837853018],"type":"Point"}
}