{
  "type": "Feature",
  "properties": {
    "date:inception_lower": "1980-01-01",
    "date:inception_upper": "1980-01-01",
    "iso:country": "GB",
    "wof:name": "TQ12 6HG",
    "wof:placetype": "postalcode"
  },
  "geometry": {"coordinates":[-3.670038,50.561478],"type":"Point"}
}
