{
  "type": "Feature",
  "properties": {
    "iso:country":"GB",
    "wof:name":"BL2 5PR",
    "wof:placetype":"postalcode"
},
  "geometry": {"coordinates":[-2.36749134262,53.59375897342993],"type":"Point"}
}