{
  "type": "Feature",
  "properties": {
    "iso:country":"GB",
    "wof:name":"LN11 8DT",
    "wof:placetype":"postalcode"
},
  "geometry": {"coordinates":[0.01262589635514,53.3655386814693],"type":"Point"}
}