{
  "type": "Feature",
  "properties": {
    "iso:country":"GB",
    "wof:name":"NR20 5DA",
    "wof:placetype":"postalcode"
},
  "geometry": {"coordinates":[1.02113161310484,52.82369275419015],"type":"Point"}
}