{
  "type": "Feature",
  "properties": {
    "date:inception_lower": "1980-01-01",
    "date:inception_upper": "1980-01-01",
    "iso:country": "GB",
    "wof:name": "NR20 5DA",
    "wof:placetype": "postalcode"
  },
  "geometry": {"coordinates":[1.021132,52.823693],"type":"Point"}
}
