{
  "type": "Feature",
  "properties": {
    "iso:country": "GB",
    "wof:name": "TA5 1SH",
    "wof:placetype": "postalcode"
  },
  "geometry": {"coordinates":[-3.204254,51.16697],"type":"Point"}
}
