{
  "type": "Feature",
  "properties": {
    "iso:country": "GB",
    "wof:name": "BD2 3PQ",
    "wof:placetype": "postalcode"
  },
  "geometry": {"coordinates":[-1.714695,53.811659],"type":"Point"}
}
