{
  "type": "Feature",
  "properties": {
    "iso:country":"GB",
    "wof:name":"BD2 3PQ",
    "wof:placetype":"postalcode"
},
  "geometry": {"coordinates":[-1.71469548298871,53.81165916109364],"type":"Point"}
}