{
  "type": "Feature",
  "properties": {
    "iso:country":"GB",
    "wof:name":"IP15 5BX",
    "wof:placetype":"postalcode"
},
  "geometry": {"coordinates":[1.60189000864537,52.15226609869278],"type":"Point"}
}