{
  "type": "Feature",
  "properties": {
    "iso:country": "GB",
    "wof:name": "IP15 5BX",
    "wof:placetype": "postalcode"
  },
  "geometry": {"coordinates":[1.60189,52.152266],"type":"Point"}
}
