{
  "type": "Feature",
  "properties": {
    "iso:country":"GB",
    "wof:name":"BS48 2AU",
    "wof:placetype":"postalcode"
},
  "geometry": {"coordinates":[-2.77441327039296,51.43175930304731],"type":"Point"}
}