{
  "type": "Feature",
  "properties": {
    "date:inception_lower": "1984-10-01",
    "date:inception_upper": "1984-10-01",
    "iso:country": "GB",
    "wof:name": "DN7 6RQ",
    "wof:placetype": "postalcode"
  },
  "geometry": {"coordinates":[-1.002105,53.577213],"type":"Point"}
}
