{
  "type": "Feature",
  "properties": {
    "iso:country": "GB",
    "wof:name": "PH33 6SH",
    "wof:placetype": "postalcode"
  },
  "geometry": {"coordinates":[-5.167423,56.774513],"type":"Point"}
}
