{
  "type": "Feature",
  "properties": {
    "iso:country":"GB",
    "wof:name":"PH33 6SH",
    "wof:placetype":"postalcode"
},
  "geometry": {"coordinates":[-5.16742302163439,56.77451342987591],"type":"Point"}
}