{
  "type": "Feature",
  "properties": {
    "iso:country": "GB",
    "wof:name": "NG32 3LX",
    "wof:placetype": "postalcode"
  },
  "geometry": {"coordinates":[-0.550654,52.93295],"type":"Point"}
}
