{
  "type": "Feature",
  "properties": {
    "date:inception_lower": "1991-09-01",
    "date:inception_upper": "1991-09-01",
    "iso:country": "GB",
    "wof:name": "NG32 3LX",
    "wof:placetype": "postalcode"
  },
  "geometry": {"coordinates":[-0.550654,52.93295],"type":"Point"}
}
