{
  "type": "Feature",
  "properties": {
    "iso:country": "GB",
    "wof:name": "G64 4EX",
    "wof:placetype": "postalcode"
  },
  "geometry": {"coordinates":[-4.21153,55.939105],"type":"Point"}
}
