{
  "type": "Feature",
  "properties": {
    "iso:country":"GB",
    "wof:name":"G64 4EX",
    "wof:placetype":"postalcode"
},
  "geometry": {"coordinates":[-4.21153048006599,55.93910531171328],"type":"Point"}
}