{
  "type": "Feature",
  "properties": {
    "date:inception_lower": "1980-01-01",
    "date:inception_upper": "1980-01-01",
    "iso:country": "GB",
    "wof:name": "G64 4EX",
    "wof:placetype": "postalcode"
  },
  "geometry": {"coordinates":[-4.211299,55.939499],"type":"Point"}
}
