{
  "type": "Feature",
  "properties": {
    "iso:country":"GB",
    "wof:name":"B71 4HJ",
    "wof:placetype":"postalcode"
},
  "geometry": {"coordinates":[-1.9878844481995,52.52735652412325],"type":"Point"}
}