{
  "type": "Feature",
  "properties": {
    "iso:country": "GB",
    "wof:name": "B71 4HJ",
    "wof:placetype": "postalcode"
  },
  "geometry": {"coordinates":[-1.988866,52.528091],"type":"Point"}
}
