{
  "type": "Feature",
  "properties": {
    "iso:country": "GB",
    "wof:name": "TN22 2NA",
    "wof:placetype": "postalcode"
  },
  "geometry": {"coordinates":[0.078968,50.997585],"type":"Point"}
}
