{
  "type": "Feature",
  "properties": {
    "date:inception_lower": "1999-06-01",
    "date:inception_upper": "1999-06-01",
    "iso:country": "GB",
    "wof:name": "TN22 2NA",
    "wof:placetype": "postalcode"
  },
  "geometry": {"coordinates":[0.078968,50.997585],"type":"Point"}
}
