{
  "type": "Feature",
  "properties": {
    "date:inception_lower":"2011-10-01",
    "date:inception_upper":"2011-10-31",
    "iso:country":"GB",
    "wof:name":"BN12 6FB",
    "wof:placetype":"postalcode"
},
  "geometry": {"coordinates":[-0.442723,50.825808],"type":"Point"}
}