{
  "type": "Feature",
  "properties": {
    "iso:country":"GB",
    "wof:name":"SS6 8QR",
    "wof:placetype":"postalcode"
},
  "geometry": {"coordinates":[0.6226027905483,51.58570333541395],"type":"Point"}
}