{
  "type": "Feature",
  "properties": {
    "iso:country":"GB",
    "wof:name":"MK45 2NW",
    "wof:placetype":"postalcode"
},
  "geometry": {"coordinates":[-0.50277832187359,52.01620731574631],"type":"Point"}
}