{
  "type": "Feature",
  "properties": {
    "date:inception_lower":"2005-02-01",
    "date:inception_upper":"2005-02-28",
    "iso:country":"GB",
    "wof:name":"MK45 2NW",
    "wof:placetype":"postalcode"
},
  "geometry": {"coordinates":[-0.502778,52.016207],"type":"Point"}
}