{
  "type": "Feature",
  "properties": {
    "iso:country":"GB",
    "wof:name":"YO1 6LJ",
    "wof:placetype":"postalcode"
},
  "geometry": {"coordinates":[-1.08815622651554,53.95710836216087],"type":"Point"}
}