{
  "type": "Feature",
  "properties": {
    "iso:country": "GB",
    "wof:name": "B78 3UA",
    "wof:placetype": "postalcode"
  },
  "geometry": {"coordinates":[-1.718132,52.598204],"type":"Point"}
}
