{
  "type": "Feature",
  "properties": {
    "iso:country":"GB",
    "wof:name":"B78 3UA",
    "wof:placetype":"postalcode"
},
  "geometry": {"coordinates":[-1.7181323099001,52.59820385473469],"type":"Point"}
}