{
  "type": "Feature",
  "properties": {
    "date:inception_lower": "1983-01-01",
    "date:inception_upper": "1983-01-01",
    "iso:country": "GB",
    "wof:name": "EX4 5EY",
    "wof:placetype": "postalcode"
  },
  "geometry": {"coordinates":[-3.516939,50.744449],"type":"Point"}
}
