{
  "type": "Feature",
  "properties": {
    "iso:country":"GB",
    "wof:name":"EX4 5EY",
    "wof:placetype":"postalcode"
},
  "geometry": {"coordinates":[-3.51693946860969,50.74444892172817],"type":"Point"}
}