{
  "type": "Feature",
  "properties": {
    "iso:country":"GB",
    "wof:name":"DH1 4DA",
    "wof:placetype":"postalcode"
},
  "geometry": {"coordinates":[-1.58514376974866,54.77762103272985],"type":"Point"}
}