{
  "type": "Feature",
  "properties": {
    "iso:country": "GB",
    "wof:name": "DH1 4DA",
    "wof:placetype": "postalcode"
  },
  "geometry": {"coordinates":[-1.585144,54.777621],"type":"Point"}
}
