{
  "type": "Feature",
  "properties": {
    "iso:country": "GB",
    "wof:name": "RH1 4LZ",
    "wof:placetype": "postalcode"
  },
  "geometry": {"coordinates":[-0.086288,51.237081],"type":"Point"}
}
