{
  "type": "Feature",
  "properties": {
    "iso:country":"GB",
    "wof:name":"RH1 4LZ",
    "wof:placetype":"postalcode"
},
  "geometry": {"coordinates":[-0.08628802819921,51.23708111546726],"type":"Point"}
}