{
  "type": "Feature",
  "properties": {
    "iso:country":"GB",
    "wof:name":"CO9 2BX",
    "wof:placetype":"postalcode"
},
  "geometry": {"coordinates":[0.64114804833974,51.94602590828807],"type":"Point"}
}