{
  "type": "Feature",
  "properties": {
    "date:inception_lower":"1997-06-01",
    "date:inception_upper":"1997-06-30",
    "iso:country":"GB",
    "wof:name":"S35 4FQ",
    "wof:placetype":"postalcode"
},
  "geometry": {"coordinates":[-1.492884,53.467898],"type":"Point"}
}