{
  "type": "Feature",
  "properties": {
    "iso:country": "GB",
    "wof:name": "RG2 7TW",
    "wof:placetype": "postalcode"
  },
  "geometry": {"coordinates":[-0.957983,51.439401],"type":"Point"}
}
