{
  "type": "Feature",
  "properties": {
    "iso:country":"GB",
    "wof:name":"WA12 9QN",
    "wof:placetype":"postalcode"
},
  "geometry": {"coordinates":[-2.63547849453245,53.45205461625269],"type":"Point"}
}