{
  "type": "Feature",
  "properties": {
    "date:inception_lower": "1980-01-01",
    "date:inception_upper": "1980-01-01",
    "iso:country": "GB",
    "wof:name": "WA12 9QN",
    "wof:placetype": "postalcode"
  },
  "geometry": {"coordinates":[-2.635478,53.452055],"type":"Point"}
}
