{
  "type": "Feature",
  "properties": {
    "date:inception_lower":"1990-02-01",
    "date:inception_upper":"1990-02-28",
    "iso:country":"GB",
    "wof:name":"ME4 4HF",
    "wof:placetype":"postalcode"
},
  "geometry": {"coordinates":[0.520405,51.384323],"type":"Point"}
}