{
  "type": "Feature",
  "properties": {
    "iso:country": "GB",
    "wof:name": "ME4 4HF",
    "wof:placetype": "postalcode"
  },
  "geometry": {"coordinates":[0.520405,51.384323],"type":"Point"}
}
