{
  "type": "Feature",
  "properties": {
    "iso:country":"GB",
    "wof:name":"ME4 4HF",
    "wof:placetype":"postalcode"
},
  "geometry": {"coordinates":[0.52040467984745,51.38432312487722],"type":"Point"}
}