{
  "type": "Feature",
  "properties": {
    "iso:country":"GB",
    "wof:name":"DL13 1HS",
    "wof:placetype":"postalcode"
},
  "geometry": {"coordinates":[-2.2314808988945,54.74425578056864],"type":"Point"}
}