{
  "type": "Feature",
  "properties": {
    "iso:country":"GB",
    "wof:name":"TS10 1NE",
    "wof:placetype":"postalcode"
},
  "geometry": {"coordinates":[-1.07388494413495,54.60814177648793],"type":"Point"}
}