{
  "type": "Feature",
  "properties": {
    "iso:country": "GB",
    "wof:name": "LN5 9UD",
    "wof:placetype": "postalcode"
  },
  "geometry": {"coordinates":[-0.553801,53.192966],"type":"Point"}
}
