{
  "type": "Feature",
  "properties": {
    "iso:country":"GB",
    "wof:name":"TS6 9JU",
    "wof:placetype":"postalcode"
},
  "geometry": {"coordinates":[-1.13621616594725,54.55988327918092],"type":"Point"}
}