{
  "type": "Feature",
  "properties": {
    "iso:country":"GB",
    "wof:name":"HR7 4LL",
    "wof:placetype":"postalcode"
},
  "geometry": {"coordinates":[-2.50966541160927,52.19190296457786],"type":"Point"}
}