{
  "type": "Feature",
  "properties": {
    "iso:country":"GB",
    "wof:name":"BD3 0DN",
    "wof:placetype":"postalcode"
},
  "geometry": {"coordinates":[-1.74155719107706,53.80237249715763],"type":"Point"}
}