{
  "type": "Feature",
  "properties": {
    "iso:country": "GB",
    "wof:name": "BD3 0DN",
    "wof:placetype": "postalcode"
  },
  "geometry": {"coordinates":[-1.741557,53.802372],"type":"Point"}
}
