{
  "type": "Feature",
  "properties": {
    "iso:country":"GB",
    "wof:name":"LE18 3TL",
    "wof:placetype":"postalcode"
},
  "geometry": {"coordinates":[-1.08634369993397,52.55327563175267],"type":"Point"}
}