{
  "type": "Feature",
  "properties": {
    "iso:country": "GB",
    "wof:name": "CA8 2ES",
    "wof:placetype": "postalcode"
  },
  "geometry": {"coordinates":[-2.627372,55.015971],"type":"Point"}
}
