{
  "type": "Feature",
  "properties": {
    "iso:country":"GB",
    "wof:name":"RM3 8RR",
    "wof:placetype":"postalcode"
},
  "geometry": {"coordinates":[0.22467792734426,51.60064982771451],"type":"Point"}
}