{
  "type": "Feature",
  "properties": {
    "date:inception_lower":"2012-08-01",
    "date:inception_upper":"2012-08-31",
    "iso:country":"GB",
    "wof:name":"NR34 9BS",
    "wof:placetype":"postalcode"
},
  "geometry": {"coordinates":[1.563047,52.458014],"type":"Point"}
}