{
  "type": "Feature",
  "properties": {
    "iso:country":"GB",
    "wof:name":"NR34 9BS",
    "wof:placetype":"postalcode"
},
  "geometry": {"coordinates":[1.5630473754347,52.45801375012199],"type":"Point"}
}