{
  "type": "Feature",
  "properties": {
    "iso:country": "GB",
    "wof:name": "NR34 9BS",
    "wof:placetype": "postalcode"
  },
  "geometry": {"coordinates":[1.563047,52.458014],"type":"Point"}
}
