{
  "type": "Feature",
  "properties": {
    "iso:country": "GB",
    "wof:name": "PE14 0RU",
    "wof:placetype": "postalcode"
  },
  "geometry": {"coordinates":[0.138182,52.640426],"type":"Point"}
}
