{
  "type": "Feature",
  "properties": {
    "iso:country": "GB",
    "wof:name": "G46 8DX",
    "wof:placetype": "postalcode"
  },
  "geometry": {"coordinates":[-4.328951,55.807735],"type":"Point"}
}
