{
  "type": "Feature",
  "properties": {
    "iso:country":"GB",
    "wof:name":"CO11 2DZ",
    "wof:placetype":"postalcode"
},
  "geometry": {"coordinates":[1.05259653649324,51.9386511435223],"type":"Point"}
}