{
  "type": "Feature",
  "properties": {
    "date:inception_lower": "2008-07-01",
    "date:inception_upper": "2008-07-01",
    "iso:country": "GB",
    "wof:name": "EN5 2UP",
    "wof:placetype": "postalcode"
  },
  "geometry": {"coordinates":[-0.200903,51.643249],"type":"Point"}
}
