{
  "type": "Feature",
  "properties": {
    "iso:country":"GB",
    "wof:name":"EN5 2UP",
    "wof:placetype":"postalcode"
},
  "geometry": {"coordinates":[-0.20090343907232,51.64324873526763],"type":"Point"}
}