{
  "type": "Feature",
  "properties": {
    "date:inception_lower": "1980-01-01",
    "date:inception_upper": "1980-01-01",
    "iso:country": "GB",
    "wof:name": "GL7 7AB",
    "wof:placetype": "postalcode"
  },
  "geometry": {"coordinates":[-2.013263,51.745157],"type":"Point"}
}
