{
  "type": "Feature",
  "properties": {
    "iso:country":"GB",
    "wof:name":"GL7 7AB",
    "wof:placetype":"postalcode"
},
  "geometry": {"coordinates":[-2.01326340759453,51.74515718321466],"type":"Point"}
}