{
  "type": "Feature",
  "properties": {
    "date:inception_lower": "2000-12-01",
    "date:inception_upper": "2000-12-01",
    "iso:country": "GB",
    "wof:name": "LE3 1PW",
    "wof:placetype": "postalcode"
  },
  "geometry": {"coordinates":[-1.167477,52.627331],"type":"Point"}
}
