{
  "type": "Feature",
  "properties": {
    "iso:country":"GB",
    "wof:name":"W1U 8JA",
    "wof:placetype":"postalcode"
},
  "geometry": {"coordinates":[-0.15811794527151,51.51769899870916],"type":"Point"}
}