{
  "type": "Feature",
  "properties": {
    "iso:country": "GB",
    "wof:name": "HU18 1AQ",
    "wof:placetype": "postalcode"
  },
  "geometry": {"coordinates":[-0.172539,53.909796],"type":"Point"}
}
