{
  "type": "Feature",
  "properties": {
    "date:inception_lower": "1980-01-01",
    "date:inception_upper": "1980-01-01",
    "iso:country": "GB",
    "wof:name": "KT16 8HT",
    "wof:placetype": "postalcode"
  },
  "geometry": {"coordinates":[-0.497654,51.388015],"type":"Point"}
}
