{
  "type": "Feature",
  "properties": {
    "iso:country":"GB",
    "wof:name":"RG4 5JB",
    "wof:placetype":"postalcode"
},
  "geometry": {"coordinates":[-0.96017917095446,51.47446212497952],"type":"Point"}
}