{
  "type": "Feature",
  "properties": {
    "iso:country": "GB",
    "wof:name": "N19 4QG",
    "wof:placetype": "postalcode"
  },
  "geometry": {"coordinates":[-0.130213,51.560287],"type":"Point"}
}
