{
  "type": "Feature",
  "properties": {
    "date:inception_lower": "1987-04-01",
    "date:inception_upper": "1987-04-01",
    "iso:country": "GB",
    "wof:name": "PR6 7PD",
    "wof:placetype": "postalcode"
  },
  "geometry": {"coordinates":[-2.640244,53.681361],"type":"Point"}
}
