{
  "type": "Feature",
  "properties": {
    "iso:country":"GB",
    "wof:name":"PR6 7PD",
    "wof:placetype":"postalcode"
},
  "geometry": {"coordinates":[-2.64024382154639,53.68136097607564],"type":"Point"}
}