{
  "type": "Feature",
  "properties": {
    "iso:country": "GB",
    "wof:name": "PR25 2FR",
    "wof:placetype": "postalcode"
  },
  "geometry": {"coordinates":[-2.69601,53.691782],"type":"Point"}
}
