{
  "type": "Feature",
  "properties": {
    "date:inception_lower": "1980-01-01",
    "date:inception_upper": "1980-01-01",
    "iso:country": "GB",
    "wof:name": "GL2 7AL",
    "wof:placetype": "postalcode"
  },
  "geometry": {"coordinates":[-2.364327,51.732616],"type":"Point"}
}
