{
  "type": "Feature",
  "properties": {
    "iso:country":"GB",
    "wof:name":"GL2 7AL",
    "wof:placetype":"postalcode"
},
  "geometry": {"coordinates":[-2.36432753611009,51.73261630383328],"type":"Point"}
}