{
  "type": "Feature",
  "properties": {
    "iso:country": "GB",
    "wof:name": "GL2 7AL",
    "wof:placetype": "postalcode"
  },
  "geometry": {"coordinates":[-2.364327,51.732616],"type":"Point"}
}
