{
  "type": "Feature",
  "properties": {
    "iso:country":"GB",
    "wof:name":"NP7 8HH",
    "wof:placetype":"postalcode"
},
  "geometry": {"coordinates":[-2.93329732403135,51.91644678648043],"type":"Point"}
}