{
  "type": "Feature",
  "properties": {
    "iso:country": "GB",
    "wof:name": "NP7 8HH",
    "wof:placetype": "postalcode"
  },
  "geometry": {"coordinates":[-2.933297,51.916447],"type":"Point"}
}
