{
  "type": "Feature",
  "properties": {
    "iso:country":"GB",
    "wof:name":"PE21 9QH",
    "wof:placetype":"postalcode"
},
  "geometry": {"coordinates":[-0.00990244842696,52.98476760803034],"type":"Point"}
}