{
  "type": "Feature",
  "properties": {
    "date:inception_lower": "2006-03-01",
    "date:inception_upper": "2006-03-01",
    "iso:country": "GB",
    "wof:name": "PE21 9QH",
    "wof:placetype": "postalcode"
  },
  "geometry": {"coordinates":[-0.009902,52.984768],"type":"Point"}
}
