{
  "type": "Feature",
  "properties": {
    "iso:country":"GB",
    "wof:name":"BS23 3RD",
    "wof:placetype":"postalcode"
},
  "geometry": {"coordinates":[-2.96842364197871,51.33643194358484],"type":"Point"}
}