{
  "type": "Feature",
  "properties": {
    "iso:country": "GB",
    "wof:name": "S7 2ED",
    "wof:placetype": "postalcode"
  },
  "geometry": {"coordinates":[-1.501852,53.3528],"type":"Point"}
}
