{
  "type": "Feature",
  "properties": {
    "iso:country":"GB",
    "wof:name":"RH2 9AE",
    "wof:placetype":"postalcode"
},
  "geometry": {"coordinates":[-0.20880543020544,51.23767149796872],"type":"Point"}
}