{
  "type": "Feature",
  "properties": {
    "iso:country":"GB",
    "wof:name":"RH1 4LW",
    "wof:placetype":"postalcode"
},
  "geometry": {"coordinates":[-0.09881937100669,51.23994727477081],"type":"Point"}
}