{
  "type": "Feature",
  "properties": {
    "iso:country": "GB",
    "wof:name": "RH1 4LW",
    "wof:placetype": "postalcode"
  },
  "geometry": {"coordinates":[-0.098819,51.239947],"type":"Point"}
}
