{
  "type": "Feature",
  "properties": {
    "iso:country":"GB",
    "wof:name":"MK8 0HF",
    "wof:placetype":"postalcode"
},
  "geometry": {"coordinates":[-0.80609047184549,52.02975936288943],"type":"Point"}
}