{
  "type": "Feature",
  "properties": {
    "date:inception_lower": "1990-07-01",
    "date:inception_upper": "1990-07-01",
    "iso:country": "GB",
    "wof:name": "MK8 0HF",
    "wof:placetype": "postalcode"
  },
  "geometry": {"coordinates":[-0.80609,52.029759],"type":"Point"}
}
