{
  "type": "Feature",
  "properties": {
    "iso:country":"GB",
    "wof:name":"UB6 8RZ",
    "wof:placetype":"postalcode"
},
  "geometry": {"coordinates":[-0.34609805903811,51.52956430679593],"type":"Point"}
}