{
  "type": "Feature",
  "properties": {
    "iso:country":"GB",
    "wof:name":"L34 2QW",
    "wof:placetype":"postalcode"
},
  "geometry": {"coordinates":[-2.78873812674396,53.43225545553499],"type":"Point"}
}