{
  "type": "Feature",
  "properties": {
    "iso:country":"GB",
    "wof:name":"HA3 0SQ",
    "wof:placetype":"postalcode"
},
  "geometry": {"coordinates":[-0.29577314284724,51.58232109242802],"type":"Point"}
}