{
  "type": "Feature",
  "properties": {
    "iso:country":"GB",
    "wof:name":"NG8 6LD",
    "wof:placetype":"postalcode"
},
  "geometry": {"coordinates":[-1.223996343126,52.97608327355358],"type":"Point"}
}