{
  "type": "Feature",
  "properties": {
    "date:inception_lower": "1980-01-01",
    "date:inception_upper": "1980-01-01",
    "iso:country": "GB",
    "wof:name": "NG8 6LD",
    "wof:placetype": "postalcode"
  },
  "geometry": {"coordinates":[-1.223996,52.976083],"type":"Point"}
}
