{
  "type": "Feature",
  "properties": {
    "date:inception_lower": "2005-10-01",
    "date:inception_upper": "2005-10-01",
    "iso:country": "GB",
    "wof:name": "NR30 5BE",
    "wof:placetype": "postalcode"
  },
  "geometry": {"coordinates":[1.724556,52.647969],"type":"Point"}
}
