{
  "type": "Feature",
  "properties": {
    "iso:country":"GB",
    "wof:name":"NR30 5BE",
    "wof:placetype":"postalcode"
},
  "geometry": {"coordinates":[1.72453301109613,52.64794134231843],"type":"Point"}
}