{
  "type": "Feature",
  "properties": {
    "iso:country":"GB",
    "wof:name":"CV6 5QE",
    "wof:placetype":"postalcode"
},
  "geometry": {"coordinates":[-1.48765200501936,52.42984908443721],"type":"Point"}
}