{
  "type": "Feature",
  "properties": {
    "date:inception_lower": "2000-06-01",
    "date:inception_upper": "2000-06-01",
    "iso:country": "GB",
    "wof:name": "CV6 5QE",
    "wof:placetype": "postalcode"
  },
  "geometry": {"coordinates":[-1.487652,52.429849],"type":"Point"}
}
