{
  "type": "Feature",
  "properties": {
    "date:inception_lower": "2017-11-01",
    "date:inception_upper": "2017-11-01",
    "iso:country": "GB",
    "wof:name": "TF4 3FT",
    "wof:placetype": "postalcode"
  },
  "geometry": {"coordinates":[-2.487828,52.657186],"type":"Point"}
}
