{
  "type": "Feature",
  "properties": {
    "date:inception_lower":"1980-01-01",
    "date:inception_upper":"1980-01-31",
    "iso:country":"GB",
    "wof:name":"TF8 7EF",
    "wof:placetype":"postalcode"
},
  "geometry": {"coordinates":[-2.484431,52.642487],"type":"Point"}
}