{
  "type": "Feature",
  "properties": {
    "iso:country":"GB",
    "wof:name":"TF8 7EF",
    "wof:placetype":"postalcode"
},
  "geometry": {"coordinates":[-2.484430691306,52.64248705517083],"type":"Point"}
}