{
  "type": "Feature",
  "properties": {
    "iso:country": "GB",
    "wof:name": "TF8 7EF",
    "wof:placetype": "postalcode"
  },
  "geometry": {"coordinates":[-2.484431,52.642487],"type":"Point"}
}
