{
  "type": "Feature",
  "properties": {
    "date:inception_lower":"1980-01-01",
    "date:inception_upper":"1980-01-31",
    "iso:country":"GB",
    "wof:name":"BH21 3DF",
    "wof:placetype":"postalcode"
},
  "geometry": {"coordinates":[-2.003565,50.781665],"type":"Point"}
}