{
  "type": "Feature",
  "properties": {
    "iso:country": "GB",
    "wof:name": "UB10 9PB",
    "wof:placetype": "postalcode"
  },
  "geometry": {"coordinates":[-0.449476,51.544536],"type":"Point"}
}
