{
  "type": "Feature",
  "properties": {
    "iso:country":"GB",
    "wof:name":"UB10 9PB",
    "wof:placetype":"postalcode"
},
  "geometry": {"coordinates":[-0.449523412769,51.54442901739692],"type":"Point"}
}