{
  "type": "Feature",
  "properties": {
    "iso:country":"GB",
    "wof:name":"BR3 4HL",
    "wof:placetype":"postalcode"
},
  "geometry": {"coordinates":[-0.03869325526267,51.40508065431792],"type":"Point"}
}