{
  "type": "Feature",
  "properties": {
    "date:inception_lower": "2001-06-01",
    "date:inception_upper": "2001-06-01",
    "iso:country": "GB",
    "wof:name": "HD9 1QG",
    "wof:placetype": "postalcode"
  },
  "geometry": {"coordinates":[-1.770123,53.576008],"type":"Point"}
}
