{
  "type": "Feature",
  "properties": {
    "iso:country":"GB",
    "wof:name":"BS29 6NP",
    "wof:placetype":"postalcode"
},
  "geometry": {"coordinates":[-2.86183193368761,51.32396584478984],"type":"Point"}
}