{
  "type": "Feature",
  "properties": {
    "iso:country": "GB",
    "wof:name": "BS29 6NP",
    "wof:placetype": "postalcode"
  },
  "geometry": {"coordinates":[-2.861832,51.323966],"type":"Point"}
}
