{
  "type": "Feature",
  "properties": {
    "iso:country":"GB",
    "wof:name":"UB10 8QW",
    "wof:placetype":"postalcode"
},
  "geometry": {"coordinates":[-0.45140069142269,51.55667410961805],"type":"Point"}
}