{
  "type": "Feature",
  "properties": {
    "date:inception_lower": "2017-01-01",
    "date:inception_upper": "2017-01-01",
    "iso:country": "GB",
    "wof:name": "TD4 6FE",
    "wof:placetype": "postalcode"
  },
  "geometry": {"coordinates":[-2.668811,55.638561],"type":"Point"}
}
