{
  "type": "Feature",
  "properties": {
    "iso:country":"GB",
    "wof:name":"DA8 2DJ",
    "wof:placetype":"postalcode"
},
  "geometry": {"coordinates":[0.18615699235532,51.46657037866244],"type":"Point"}
}