{
  "type": "Feature",
  "properties": {
    "date:inception_lower": "1980-01-01",
    "date:inception_upper": "1980-01-01",
    "iso:country": "GB",
    "wof:name": "SN8 4LE",
    "wof:placetype": "postalcode"
  },
  "geometry": {"coordinates":[-1.8487,51.356525],"type":"Point"}
}
