{
  "type": "Feature",
  "properties": {
    "iso:country":"GB",
    "wof:name":"SN8 4LE",
    "wof:placetype":"postalcode"
},
  "geometry": {"coordinates":[-1.84869954244072,51.3565248702687],"type":"Point"}
}