{
  "type": "Feature",
  "properties": {
    "iso:country": "GB",
    "wof:name": "BA12 0QY",
    "wof:placetype": "postalcode"
  },
  "geometry": {"coordinates":[-1.988058,51.138111],"type":"Point"}
}
