{
  "type": "Feature",
  "properties": {
    "iso:country":"GB",
    "wof:name":"TQ13 9BJ",
    "wof:placetype":"postalcode"
},
  "geometry": {"coordinates":[-3.67681474630908,50.59368609620567],"type":"Point"}
}