{
  "type": "Feature",
  "properties": {
    "iso:country":"GB",
    "wof:name":"PR6 9RB",
    "wof:placetype":"postalcode"
},
  "geometry": {"coordinates":[-2.60010769187913,53.61534288802074],"type":"Point"}
}