{
  "type": "Feature",
  "properties": {
    "iso:country": "GB",
    "wof:name": "CW10 0DJ",
    "wof:placetype": "postalcode"
  },
  "geometry": {"coordinates":[-2.438294,53.180123],"type":"Point"}
}
