{
  "type": "Feature",
  "properties": {
    "iso:country":"GB",
    "wof:name":"CA14 3XQ",
    "wof:placetype":"postalcode"
},
  "geometry": {"coordinates":[-3.55866228077301,54.63312886458063],"type":"Point"}
}