{
  "type": "Feature",
  "properties": {
    "iso:country":"GB",
    "wof:name":"PE24 5QF",
    "wof:placetype":"postalcode"
},
  "geometry": {"coordinates":[0.30268756257062,53.23528593140095],"type":"Point"}
}