{
  "type": "Feature",
  "properties": {
    "iso:country": "GB",
    "wof:name": "PE24 5QF",
    "wof:placetype": "postalcode"
  },
  "geometry": {"coordinates":[0.302688,53.235286],"type":"Point"}
}
