{
  "type": "Feature",
  "properties": {
    "iso:country":"GB",
    "wof:name":"FY5 2UZ",
    "wof:placetype":"postalcode"
},
  "geometry": {"coordinates":[-3.01693826045327,53.87480935487712],"type":"Point"}
}