{
  "type": "Feature",
  "properties": {
    "iso:country": "GB",
    "wof:name": "FY5 2UZ",
    "wof:placetype": "postalcode"
  },
  "geometry": {"coordinates":[-3.016938,53.874809],"type":"Point"}
}
