{
  "type": "Feature",
  "properties": {
    "iso:country":"GB",
    "wof:name":"N16 7UH",
    "wof:placetype":"postalcode"
},
  "geometry": {"coordinates":[-0.06919978286862,51.55623189009508],"type":"Point"}
}