{
  "type": "Feature",
  "properties": {
    "date:inception_lower": "1990-02-01",
    "date:inception_upper": "1990-02-01",
    "iso:country": "GB",
    "wof:name": "AL6 0SX",
    "wof:placetype": "postalcode"
  },
  "geometry": {"coordinates":[-0.185167,51.846443],"type":"Point"}
}
