{
  "type": "Feature",
  "properties": {
    "iso:country": "GB",
    "wof:name": "EC1A 9LJ",
    "wof:placetype": "postalcode"
  },
  "geometry": {"coordinates":[-0.102744,51.517644],"type":"Point"}
}
