{
  "type": "Feature",
  "properties": {
    "iso:country":"GB",
    "wof:name":"LU7 1DG",
    "wof:placetype":"postalcode"
},
  "geometry": {"coordinates":[-0.66113043566981,51.9157919005707],"type":"Point"}
}