{
  "type": "Feature",
  "properties": {
    "iso:country":"GB",
    "wof:name":"NR25 7NN",
    "wof:placetype":"postalcode"
},
  "geometry": {"coordinates":[1.02632258859997,52.95480946890967],"type":"Point"}
}