{
  "type": "Feature",
  "properties": {
    "iso:country":"GB",
    "wof:name":"CF14 5HL",
    "wof:placetype":"postalcode"
},
  "geometry": {"coordinates":[-3.20524011526903,51.53355086253369],"type":"Point"}
}