{
  "type": "Feature",
  "properties": {
    "iso:country": "GB",
    "wof:name": "CF14 5HL",
    "wof:placetype": "postalcode"
  },
  "geometry": {"coordinates":[-3.20524,51.533551],"type":"Point"}
}
