{
  "type": "Feature",
  "properties": {
    "iso:country": "GB",
    "wof:name": "BH23 4BN",
    "wof:placetype": "postalcode"
  },
  "geometry": {"coordinates":[-1.742764,50.731383],"type":"Point"}
}
