{
  "type": "Feature",
  "properties": {
    "iso:country":"GB",
    "wof:name":"BH23 4BN",
    "wof:placetype":"postalcode"
},
  "geometry": {"coordinates":[-1.74276412455892,50.73138335081155],"type":"Point"}
}