{
  "type": "Feature",
  "properties": {
    "iso:country": "GB",
    "wof:name": "OX15 6DP",
    "wof:placetype": "postalcode"
  },
  "geometry": {"coordinates":[-1.44659,52.124819],"type":"Point"}
}
