{
  "type": "Feature",
  "properties": {
    "iso:country":"GB",
    "wof:name":"OX15 6DP",
    "wof:placetype":"postalcode"
},
  "geometry": {"coordinates":[-1.44658994121707,52.12481857254969],"type":"Point"}
}