{
  "type": "Feature",
  "properties": {
    "iso:country":"GB",
    "wof:name":"RG7 3LB",
    "wof:placetype":"postalcode"
},
  "geometry": {"coordinates":[-1.06956199798147,51.3988333975971],"type":"Point"}
}