{
  "type": "Feature",
  "properties": {
    "iso:country": "GB",
    "wof:name": "NE42 6BR",
    "wof:placetype": "postalcode"
  },
  "geometry": {"coordinates":[-1.862447,54.972894],"type":"Point"}
}
