{
  "type": "Feature",
  "properties": {
    "iso:country":"GB",
    "wof:name":"CB5 8RX",
    "wof:placetype":"postalcode"
},
  "geometry": {"coordinates":[0.17520345940937,52.21017263164081],"type":"Point"}
}