{
  "type": "Feature",
  "properties": {
    "date:inception_lower": "2021-01-01",
    "date:inception_upper": "2021-01-01",
    "iso:country": "GB",
    "wof:name": "EH54 9FW",
    "wof:placetype": "postalcode"
  },
  "geometry": {"coordinates":[-3.502034,55.865625],"type":"Point"}
}
