{
  "type": "Feature",
  "properties": {
    "iso:country":"GB",
    "wof:name":"AB42 1JY",
    "wof:placetype":"postalcode"
},
  "geometry": {"coordinates":[-1.7774755421771,57.50981758167749],"type":"Point"}
}