{
  "type": "Feature",
  "properties": {
    "date:inception_lower": "2018-05-01",
    "date:inception_upper": "2018-05-01",
    "iso:country": "GB",
    "wof:name": "KA22 7DE",
    "wof:placetype": "postalcode"
  },
  "geometry": {"coordinates":[-4.809164,55.653338],"type":"Point"}
}
