{
  "type": "Feature",
  "properties": {
    "date:inception_lower":"2002-12-01",
    "date:inception_upper":"2002-12-31",
    "iso:country":"GB",
    "wof:name":"BA2 3EB",
    "wof:placetype":"postalcode"
},
  "geometry": {"coordinates":[-2.373453,51.381005],"type":"Point"}
}