{
  "type": "Feature",
  "properties": {
    "date:inception_lower":"1980-01-01",
    "date:inception_upper":"1980-01-31",
    "iso:country":"GB",
    "wof:name":"EX7 0AD",
    "wof:placetype":"postalcode"
},
  "geometry": {"coordinates":[-3.459485,50.584526],"type":"Point"}
}