{
  "type": "Feature",
  "properties": {
    "iso:country":"GB",
    "wof:name":"EX7 0AD",
    "wof:placetype":"postalcode"
},
  "geometry": {"coordinates":[-3.45948536237186,50.58452559038648],"type":"Point"}
}