{
  "type": "Feature",
  "properties": {
    "iso:country":"GB",
    "wof:name":"BL0 0AD",
    "wof:placetype":"postalcode"
},
  "geometry": {"coordinates":[-2.31326854415369,53.64908327678484],"type":"Point"}
}