{
  "type": "Feature",
  "properties": {
    "iso:country": "GB",
    "wof:name": "BL0 0AD",
    "wof:placetype": "postalcode"
  },
  "geometry": {"coordinates":[-2.313284,53.649155],"type":"Point"}
}
