{
  "type": "Feature",
  "properties": {
    "date:inception_lower": "1993-08-01",
    "date:inception_upper": "1993-08-01",
    "iso:country": "GB",
    "wof:name": "NN11 3NX",
    "wof:placetype": "postalcode"
  },
  "geometry": {"coordinates":[-1.20999,52.169189],"type":"Point"}
}
