{
  "type": "Feature",
  "properties": {
    "iso:country":"GB",
    "wof:name":"ML11 0BA",
    "wof:placetype":"postalcode"
},
  "geometry": {"coordinates":[-3.87738858076188,55.62910881384408],"type":"Point"}
}