{
  "type": "Feature",
  "properties": {
    "iso:country":"GB",
    "wof:name":"SM7 3PY",
    "wof:placetype":"postalcode"
},
  "geometry": {"coordinates":[-0.16827151733323,51.31498473520155],"type":"Point"}
}