{
  "type": "Feature",
  "properties": {
    "iso:country": "GB",
    "wof:name": "SM7 3PY",
    "wof:placetype": "postalcode"
  },
  "geometry": {"coordinates":[-0.168271,51.314985],"type":"Point"}
}
