{
  "type": "Feature",
  "properties": {
    "date:inception_lower":"1980-01-01",
    "date:inception_upper":"1980-01-31",
    "iso:country":"GB",
    "wof:name":"B61 8LR",
    "wof:placetype":"postalcode"
},
  "geometry": {"coordinates":[-2.065348,52.3429],"type":"Point"}
}