{
  "type": "Feature",
  "properties": {
    "iso:country":"GB",
    "wof:name":"B61 8LR",
    "wof:placetype":"postalcode"
},
  "geometry": {"coordinates":[-2.06534831770621,52.3428995178966],"type":"Point"}
}