{
  "type": "Feature",
  "properties": {
    "iso:country":"GB",
    "wof:name":"WN8 6RJ",
    "wof:placetype":"postalcode"
},
  "geometry": {"coordinates":[-2.78095814411948,53.56437684849487],"type":"Point"}
}