{
  "type": "Feature",
  "properties": {
    "date:inception_lower":"1993-08-01",
    "date:inception_upper":"1993-08-31",
    "iso:country":"GB",
    "wof:name":"WN8 6RJ",
    "wof:placetype":"postalcode"
},
  "geometry": {"coordinates":[-2.780958,53.564377],"type":"Point"}
}