{
  "type": "Feature",
  "properties": {
    "iso:country":"GB",
    "wof:name":"BB3 0EE",
    "wof:placetype":"postalcode"
},
  "geometry": {"coordinates":[-2.46429028287689,53.70370838403944],"type":"Point"}
}