{
  "type": "Feature",
  "properties": {
    "iso:country":"GB",
    "wof:name":"ME5 0ES",
    "wof:placetype":"postalcode"
},
  "geometry": {"coordinates":[0.53078388715827,51.36195710022241],"type":"Point"}
}