{
  "type": "Feature",
  "properties": {
    "iso:country": "GB",
    "wof:name": "DH8 9DP",
    "wof:placetype": "postalcode"
  },
  "geometry": {"coordinates":[-1.916304,54.834834],"type":"Point"}
}
