{
  "type": "Feature",
  "properties": {
    "iso:country":"GB",
    "wof:name":"NG16 3AD",
    "wof:placetype":"postalcode"
},
  "geometry": {"coordinates":[-1.30706346091229,53.01818100464956],"type":"Point"}
}