{
  "type": "Feature",
  "properties": {
    "date:inception_lower":"1980-01-01",
    "date:inception_upper":"1980-01-31",
    "iso:country":"GB",
    "wof:name":"NG16 3AD",
    "wof:placetype":"postalcode"
},
  "geometry": {"coordinates":[-1.307063,53.018181],"type":"Point"}
}