{
  "type": "Feature",
  "properties": {
    "iso:country": "GB",
    "wof:name": "LL32 8EE",
    "wof:placetype": "postalcode"
  },
  "geometry": {"coordinates":[-3.838382,53.285643],"type":"Point"}
}
