{
  "type": "Feature",
  "properties": {
    "iso:country":"GB",
    "wof:name":"SY23 3JT",
    "wof:placetype":"postalcode"
},
  "geometry": {"coordinates":[-3.83596417340906,52.41122337610994],"type":"Point"}
}