{
  "type": "Feature",
  "properties": {
    "iso:country":"GB",
    "wof:name":"NW4 1JT",
    "wof:placetype":"postalcode"
},
  "geometry": {"coordinates":[-0.21304454237432,51.59800515989065],"type":"Point"}
}