{
  "type": "Feature",
  "properties": {
    "iso:country":"GB",
    "wof:name":"EH6 5PA",
    "wof:placetype":"postalcode"
},
  "geometry": {"coordinates":[-3.18523204038088,55.969133152163],"type":"Point"}
}