{
  "type": "Feature",
  "properties": {
    "date:inception_lower": "1980-01-01",
    "date:inception_upper": "1980-01-01",
    "iso:country": "GB",
    "wof:name": "L31 9DL",
    "wof:placetype": "postalcode"
  },
  "geometry": {"coordinates":[-2.926971,53.519263],"type":"Point"}
}
