{
  "type": "Feature",
  "properties": {
    "iso:country": "GB",
    "wof:name": "PR2 1QN",
    "wof:placetype": "postalcode"
  },
  "geometry": {"coordinates":[-2.768647,53.765266],"type":"Point"}
}
