{
  "type": "Feature",
  "properties": {
    "iso:country":"GB",
    "wof:name":"M33 2RH",
    "wof:placetype":"postalcode"
},
  "geometry": {"coordinates":[-2.288935804251,53.41563513830688],"type":"Point"}
}