{
  "type": "Feature",
  "properties": {
    "iso:country":"GB",
    "wof:name":"ME1 3PX",
    "wof:placetype":"postalcode"
},
  "geometry": {"coordinates":[0.49928605891151,51.36286739378548],"type":"Point"}
}