{
  "type": "Feature",
  "properties": {
    "iso:country": "GB",
    "wof:name": "ME1 3PX",
    "wof:placetype": "postalcode"
  },
  "geometry": {"coordinates":[0.499286,51.362867],"type":"Point"}
}
