{
  "type": "Feature",
  "properties": {
    "iso:country": "GB",
    "wof:name": "CM7 1HB",
    "wof:placetype": "postalcode"
  },
  "geometry": {"coordinates":[0.554063,51.868307],"type":"Point"}
}
