{
  "type": "Feature",
  "properties": {
    "iso:country":"GB",
    "wof:name":"CM7 1HB",
    "wof:placetype":"postalcode"
},
  "geometry": {"coordinates":[0.5540625153513,51.86830657221238],"type":"Point"}
}