{
  "type": "Feature",
  "properties": {
    "iso:country":"GB",
    "wof:name":"SN13 9RJ",
    "wof:placetype":"postalcode"
},
  "geometry": {"coordinates":[-2.21055595958474,51.41895149310648],"type":"Point"}
}