{
  "type": "Feature",
  "properties": {
    "iso:country": "GB",
    "wof:name": "SN13 9RJ",
    "wof:placetype": "postalcode"
  },
  "geometry": {"coordinates":[-2.210556,51.418951],"type":"Point"}
}
