{
  "type": "Feature",
  "properties": {
    "date:inception_lower": "2019-10-01",
    "date:inception_upper": "2019-10-01",
    "iso:country": "GB",
    "wof:name": "BL6 6GB",
    "wof:placetype": "postalcode"
  },
  "geometry": {"coordinates":[-2.536298,53.592472],"type":"Point"}
}
