{
  "type": "Feature",
  "properties": {
    "iso:country":"GB",
    "wof:name":"LU2 0TN",
    "wof:placetype":"postalcode"
},
  "geometry": {"coordinates":[-0.40065381125195,51.89144637779383],"type":"Point"}
}