{
  "type": "Feature",
  "properties": {
    "date:inception_lower": "1984-02-01",
    "date:inception_upper": "1984-02-01",
    "iso:country": "GB",
    "wof:name": "LU2 0TN",
    "wof:placetype": "postalcode"
  },
  "geometry": {"coordinates":[-0.400654,51.891446],"type":"Point"}
}
