{
  "type": "Feature",
  "properties": {
    "iso:country":"GB",
    "wof:name":"RG7 2ZQ",
    "wof:placetype":"postalcode"
},
  "geometry": {"coordinates":[-0.97125155524072,51.43156069433687],"type":"Point"}
}