{
  "type": "Feature",
  "properties": {
    "date:inception_lower":"1980-01-01",
    "date:inception_upper":"1980-01-31",
    "iso:country":"GB",
    "wof:name":"L21 0DB",
    "wof:placetype":"postalcode"
},
  "geometry": {"coordinates":[-2.98528,53.48034],"type":"Point"}
}