{
  "type": "Feature",
  "properties": {
    "iso:country":"GB",
    "wof:name":"L21 0DB",
    "wof:placetype":"postalcode"
},
  "geometry": {"coordinates":[-2.98528130246711,53.4803240891921],"type":"Point"}
}