{
  "type": "Feature",
  "properties": {
    "iso:country":"GB",
    "wof:name":"LS11 6JE",
    "wof:placetype":"postalcode"
},
  "geometry": {"coordinates":[-1.54976596773138,53.774851131136],"type":"Point"}
}