{
  "type": "Feature",
  "properties": {
    "iso:country":"GB",
    "wof:name":"MK2 2EZ",
    "wof:placetype":"postalcode"
},
  "geometry": {"coordinates":[-0.72007064680796,51.99566085237328],"type":"Point"}
}