{
  "type": "Feature",
  "properties": {
    "iso:country": "GB",
    "wof:name": "TA19 0HR",
    "wof:placetype": "postalcode"
  },
  "geometry": {"coordinates":[-2.909972,50.922213],"type":"Point"}
}
