{
  "type": "Feature",
  "properties": {
    "iso:country":"GB",
    "wof:name":"TA19 0HR",
    "wof:placetype":"postalcode"
},
  "geometry": {"coordinates":[-2.90997199491254,50.92221293286927],"type":"Point"}
}