{
  "type": "Feature",
  "properties": {
    "date:inception_lower": "2014-03-01",
    "date:inception_upper": "2014-03-01",
    "iso:country": "GB",
    "wof:name": "WA10 4FW",
    "wof:placetype": "postalcode"
  },
  "geometry": {"coordinates":[-2.765042,53.454603],"type":"Point"}
}
