{
  "type": "Feature",
  "properties": {
    "iso:country": "GB",
    "wof:name": "PO20 0PZ",
    "wof:placetype": "postalcode"
  },
  "geometry": {"coordinates":[-0.793031,50.730935],"type":"Point"}
}
