{
  "type": "Feature",
  "properties": {
    "iso:country":"GB",
    "wof:name":"PO20 0PZ",
    "wof:placetype":"postalcode"
},
  "geometry": {"coordinates":[-0.79303084886751,50.73093503697921],"type":"Point"}
}