{
  "type": "Feature",
  "properties": {
    "date:inception_lower": "1980-01-01",
    "date:inception_upper": "1980-01-01",
    "iso:country": "GB",
    "wof:name": "PO20 0PZ",
    "wof:placetype": "postalcode"
  },
  "geometry": {"coordinates":[-0.793031,50.730935],"type":"Point"}
}
