{
  "type": "Feature",
  "properties": {
    "iso:country":"GB",
    "wof:name":"G13 4RG",
    "wof:placetype":"postalcode"
},
  "geometry": {"coordinates":[-4.37223352199674,55.89006155133083],"type":"Point"}
}