{
  "type": "Feature",
  "properties": {
    "date:inception_lower": "1980-01-01",
    "date:inception_upper": "1980-01-01",
    "iso:country": "GB",
    "wof:name": "G13 4RG",
    "wof:placetype": "postalcode"
  },
  "geometry": {"coordinates":[-4.372233,55.890062],"type":"Point"}
}
