{
  "type": "Feature",
  "properties": {
    "date:inception_lower":"2008-06-01",
    "date:inception_upper":"2008-06-30",
    "iso:country":"GB",
    "wof:name":"TS24 0ZD",
    "wof:placetype":"postalcode"
},
  "geometry": {"coordinates":[-1.198689,54.688477],"type":"Point"}
}