{
  "type": "Feature",
  "properties": {
    "iso:country": "GB",
    "wof:name": "TS24 0ZD",
    "wof:placetype": "postalcode"
  },
  "geometry": {"coordinates":[-1.198689,54.688477],"type":"Point"}
}
