{
  "type": "Feature",
  "properties": {
    "date:inception_lower": "2001-12-01",
    "date:inception_upper": "2001-12-01",
    "iso:country": "GB",
    "wof:name": "CV22 7FT",
    "wof:placetype": "postalcode"
  },
  "geometry": {"coordinates":[-1.306538,52.361697],"type":"Point"}
}
