{
  "type": "Feature",
  "properties": {
    "iso:country": "GB",
    "wof:name": "DH3 1NH",
    "wof:placetype": "postalcode"
  },
  "geometry": {"coordinates":[-1.575928,54.905116],"type":"Point"}
}
