{
  "type": "Feature",
  "properties": {
    "iso:country":"GB",
    "wof:name":"DH3 1NH",
    "wof:placetype":"postalcode"
},
  "geometry": {"coordinates":[-1.57592782629748,54.90511622972218],"type":"Point"}
}