{
  "type": "Feature",
  "properties": {
    "iso:country":"GB",
    "wof:name":"LE15 8PZ",
    "wof:placetype":"postalcode"
},
  "geometry": {"coordinates":[-0.59091742590769,52.66718046857195],"type":"Point"}
}