{
  "type": "Feature",
  "properties": {
    "date:inception_lower": "1980-01-01",
    "date:inception_upper": "1980-01-01",
    "iso:country": "GB",
    "wof:name": "LE15 8PZ",
    "wof:placetype": "postalcode"
  },
  "geometry": {"coordinates":[-0.590917,52.66718],"type":"Point"}
}
