{
  "type": "Feature",
  "properties": {
    "iso:country":"GB",
    "wof:name":"NG32 2DA",
    "wof:placetype":"postalcode"
},
  "geometry": {"coordinates":[-0.57922860224656,52.95589584540033],"type":"Point"}
}