{
  "type": "Feature",
  "properties": {
    "date:inception_lower": "1980-01-01",
    "date:inception_upper": "1980-01-01",
    "iso:country": "GB",
    "wof:name": "NG32 2DA",
    "wof:placetype": "postalcode"
  },
  "geometry": {"coordinates":[-0.579229,52.955896],"type":"Point"}
}
