{
  "type": "Feature",
  "properties": {
    "iso:country":"GB",
    "wof:name":"WF4 4QY",
    "wof:placetype":"postalcode"
},
  "geometry": {"coordinates":[-1.60661475210197,53.64715862174421],"type":"Point"}
}