{
  "type": "Feature",
  "properties": {
    "iso:country": "GB",
    "wof:name": "PA31 8LH",
    "wof:placetype": "postalcode"
  },
  "geometry": {"coordinates":[-5.433562,56.036744],"type":"Point"}
}
