{
  "type": "Feature",
  "properties": {
    "iso:country":"GB",
    "wof:name":"SG2 8QE",
    "wof:placetype":"postalcode"
},
  "geometry": {"coordinates":[-0.18087722310272,51.87924402411447],"type":"Point"}
}