{
  "type": "Feature",
  "properties": {
    "date:inception_lower":"1998-06-01",
    "date:inception_upper":"1998-06-30",
    "iso:country":"GB",
    "wof:name":"SG2 8QE",
    "wof:placetype":"postalcode"
},
  "geometry": {"coordinates":[-0.180877,51.879244],"type":"Point"}
}