{
  "type": "Feature",
  "properties": {
    "date:inception_lower":"1981-06-01",
    "date:inception_upper":"1981-06-30",
    "iso:country":"GB",
    "wof:name":"NE20 0TF",
    "wof:placetype":"postalcode"
},
  "geometry": {"coordinates":[-1.952697,55.040621],"type":"Point"}
}