{
  "type": "Feature",
  "properties": {
    "iso:country": "GB",
    "wof:name": "TR10 8RA",
    "wof:placetype": "postalcode"
  },
  "geometry": {"coordinates":[-5.117622,50.169207],"type":"Point"}
}
