{
  "type": "Feature",
  "properties": {
    "iso:country":"GB",
    "wof:name":"TR10 8RA",
    "wof:placetype":"postalcode"
},
  "geometry": {"coordinates":[-5.11776714142583,50.16916026999591],"type":"Point"}
}