{
  "type": "Feature",
  "properties": {
    "date:inception_lower":"1980-01-01",
    "date:inception_upper":"1980-01-31",
    "iso:country":"GB",
    "wof:name":"PE15 9JQ",
    "wof:placetype":"postalcode"
},
  "geometry": {"coordinates":[0.089171,52.54921],"type":"Point"}
}