{
  "type": "Feature",
  "properties": {
    "iso:country":"GB",
    "wof:name":"BL1 5XQ",
    "wof:placetype":"postalcode"
},
  "geometry": {"coordinates":[-2.49331951388226,53.57593158248519],"type":"Point"}
}