{
  "type": "Feature",
  "properties": {
    "iso:country": "GB",
    "wof:name": "MK18 5JP",
    "wof:placetype": "postalcode"
  },
  "geometry": {"coordinates":[-1.001819,52.016835],"type":"Point"}
}
