{
  "type": "Feature",
  "properties": {
    "iso:country":"GB",
    "wof:name":"MK18 5JP",
    "wof:placetype":"postalcode"
},
  "geometry": {"coordinates":[-1.00181871078092,52.01683455703937],"type":"Point"}
}