{
  "type": "Feature",
  "properties": {
    "iso:country": "GB",
    "wof:name": "SL6 7QE",
    "wof:placetype": "postalcode"
  },
  "geometry": {"coordinates":[-0.73658,51.537009],"type":"Point"}
}
