{
  "type": "Feature",
  "properties": {
    "iso:country":"GB",
    "wof:name":"NW8 8QY",
    "wof:placetype":"postalcode"
},
  "geometry": {"coordinates":[-0.17653520821521,51.52751876023522],"type":"Point"}
}