{
  "type": "Feature",
  "properties": {
    "date:inception_lower": "1980-01-01",
    "date:inception_upper": "1980-01-01",
    "iso:country": "GB",
    "wof:name": "CF47 8JD",
    "wof:placetype": "postalcode"
  },
  "geometry": {"coordinates":[-3.378907,51.748143],"type":"Point"}
}
