{
  "type": "Feature",
  "properties": {
    "iso:country": "GB",
    "wof:name": "PE9 1QN",
    "wof:placetype": "postalcode"
  },
  "geometry": {"coordinates":[-0.477572,52.65722],"type":"Point"}
}
