{
  "type": "Feature",
  "properties": {
    "iso:country":"GB",
    "wof:name":"NP11 3AX",
    "wof:placetype":"postalcode"
},
  "geometry": {"coordinates":[-3.15040446318622,51.69151027372611],"type":"Point"}
}