{
  "type": "Feature",
  "properties": {
    "iso:country": "GB",
    "wof:name": "NP11 3AX",
    "wof:placetype": "postalcode"
  },
  "geometry": {"coordinates":[-3.150404,51.69151],"type":"Point"}
}
