{
  "type": "Feature",
  "properties": {
    "iso:country":"GB",
    "wof:name":"DA11 7PX",
    "wof:placetype":"postalcode"
},
  "geometry": {"coordinates":[0.36814485062807,51.42837496862374],"type":"Point"}
}