{
  "type": "Feature",
  "properties": {
    "iso:country": "GB",
    "wof:name": "DA11 7PX",
    "wof:placetype": "postalcode"
  },
  "geometry": {"coordinates":[0.368145,51.428375],"type":"Point"}
}
