{
  "type": "Feature",
  "properties": {
    "date:inception_lower": "1980-01-01",
    "date:inception_upper": "1980-01-01",
    "iso:country": "GB",
    "wof:name": "NE5 3UU",
    "wof:placetype": "postalcode"
  },
  "geometry": {"coordinates":[-1.658283,54.997844],"type":"Point"}
}
