{
  "type": "Feature",
  "properties": {
    "iso:country":"GB",
    "wof:name":"NE5 3UU",
    "wof:placetype":"postalcode"
},
  "geometry": {"coordinates":[-1.65828259629577,54.9978443517643],"type":"Point"}
}