{
  "type": "Feature",
  "properties": {
    "date:inception_lower": "1980-01-01",
    "date:inception_upper": "1980-01-01",
    "iso:country": "GB",
    "wof:name": "DY11 5SW",
    "wof:placetype": "postalcode"
  },
  "geometry": {"coordinates":[-2.267998,52.427399],"type":"Point"}
}
