{
  "type": "Feature",
  "properties": {
    "iso:country":"GB",
    "wof:name":"DY11 5SW",
    "wof:placetype":"postalcode"
},
  "geometry": {"coordinates":[-2.26799807500473,52.42739912313834],"type":"Point"}
}