{
  "type": "Feature",
  "properties": {
    "iso:country": "GB",
    "wof:name": "DY11 5SW",
    "wof:placetype": "postalcode"
  },
  "geometry": {"coordinates":[-2.267998,52.427399],"type":"Point"}
}
