{
  "type": "Feature",
  "properties": {
    "iso:country":"GB",
    "wof:name":"L31 2JA",
    "wof:placetype":"postalcode"
},
  "geometry": {"coordinates":[-2.94960594406201,53.52449610690829],"type":"Point"}
}