{
  "type": "Feature",
  "properties": {
    "iso:country":"GB",
    "wof:name":"B20 2NA",
    "wof:placetype":"postalcode"
},
  "geometry": {"coordinates":[-1.92782278830192,52.52517769938495],"type":"Point"}
}