{
  "type": "Feature",
  "properties": {
    "iso:country":"GB",
    "wof:name":"CT5 1NF",
    "wof:placetype":"postalcode"
},
  "geometry": {"coordinates":[1.03011062970713,51.35939943401767],"type":"Point"}
}