{
  "type": "Feature",
  "properties": {
    "iso:country": "GB",
    "wof:name": "KY10 3EQ",
    "wof:placetype": "postalcode"
  },
  "geometry": {"coordinates":[-2.711532,56.219663],"type":"Point"}
}
