{
  "type": "Feature",
  "properties": {
    "date:inception_lower":"1986-09-01",
    "date:inception_upper":"1986-09-30",
    "iso:country":"GB",
    "wof:name":"KY10 3EQ",
    "wof:placetype":"postalcode"
},
  "geometry": {"coordinates":[-2.711532,56.219663],"type":"Point"}
}