{
  "type": "Feature",
  "properties": {
    "date:inception_lower": "2019-04-01",
    "date:inception_upper": "2019-04-01",
    "iso:country": "GB",
    "wof:name": "EH16 4WS",
    "wof:placetype": "postalcode"
  },
  "geometry": {"coordinates":[-3.121489,55.924466],"type":"Point"}
}
