{
  "type": "Feature",
  "properties": {
    "date:inception_lower":"1993-08-01",
    "date:inception_upper":"1993-08-31",
    "iso:country":"GB",
    "wof:name":"BD20 0NG",
    "wof:placetype":"postalcode"
},
  "geometry": {"coordinates":[-1.936578,53.909517],"type":"Point"}
}