{
  "type": "Feature",
  "properties": {
    "iso:country":"GB",
    "wof:name":"BD20 0NG",
    "wof:placetype":"postalcode"
},
  "geometry": {"coordinates":[-1.93657842465561,53.90951748233664],"type":"Point"}
}