{
  "type": "Feature",
  "properties": {
    "iso:country":"GB",
    "wof:name":"W1U 4PS",
    "wof:placetype":"postalcode"
},
  "geometry": {"coordinates":[-0.15154128571381,51.52029328559144],"type":"Point"}
}