{
  "type": "Feature",
  "properties": {
    "iso:country":"GB",
    "wof:name":"BH4 9LJ",
    "wof:placetype":"postalcode"
},
  "geometry": {"coordinates":[-1.895244169102,50.72866109056492],"type":"Point"}
}