{
  "type": "Feature",
  "properties": {
    "iso:country": "GB",
    "wof:name": "NG8 5SL",
    "wof:placetype": "postalcode"
  },
  "geometry": {"coordinates":[-1.183966,52.966369],"type":"Point"}
}
