{
  "type": "Feature",
  "properties": {
    "iso:country": "GB",
    "wof:name": "NE28 9DR",
    "wof:placetype": "postalcode"
  },
  "geometry": {"coordinates":[-1.52589,55.003952],"type":"Point"}
}
