{
  "type": "Feature",
  "properties": {
    "iso:country":"GB",
    "wof:name":"NE28 9DR",
    "wof:placetype":"postalcode"
},
  "geometry": {"coordinates":[-1.52588980553756,55.00395175657045],"type":"Point"}
}