{
  "type": "Feature",
  "properties": {
    "iso:country":"GB",
    "wof:name":"IG8 7AB",
    "wof:placetype":"postalcode"
},
  "geometry": {"coordinates":[0.03882445403426,51.59887296372838],"type":"Point"}
}