{
  "type": "Feature",
  "properties": {
    "iso:country":"GB",
    "wof:name":"ST1 1DF",
    "wof:placetype":"postalcode"
},
  "geometry": {"coordinates":[-2.17602320854738,53.02592825229333],"type":"Point"}
}