{
  "type": "Feature",
  "properties": {
    "iso:country":"GB",
    "wof:name":"SE3 9RR",
    "wof:placetype":"postalcode"
},
  "geometry": {"coordinates":[0.0114131574983,51.4639973849369],"type":"Point"}
}