{
  "type": "Feature",
  "properties": {
    "iso:country":"GB",
    "wof:name":"SO23 0HQ",
    "wof:placetype":"postalcode"
},
  "geometry": {"coordinates":[-1.30374175539846,51.0635720388762],"type":"Point"}
}