{
  "type": "Feature",
  "properties": {
    "iso:country": "GB",
    "wof:name": "CF48 2ER",
    "wof:placetype": "postalcode"
  },
  "geometry": {"coordinates":[-3.398428,51.771848],"type":"Point"}
}
