{
  "type": "Feature",
  "properties": {
    "iso:country":"GB",
    "wof:name":"CF48 2ER",
    "wof:placetype":"postalcode"
},
  "geometry": {"coordinates":[-3.39842817728752,51.77184847837203],"type":"Point"}
}