{
  "type": "Feature",
  "properties": {
    "iso:country":"GB",
    "wof:name":"BS14 9EY",
    "wof:placetype":"postalcode"
},
  "geometry": {"coordinates":[-2.55802324545324,51.42012245072314],"type":"Point"}
}