{
  "type": "Feature",
  "properties": {
    "iso:country":"GB",
    "wof:name":"WR14 9FX",
    "wof:placetype":"postalcode"
},
  "geometry": {"coordinates":[-2.32926671646894,52.11128853722555],"type":"Point"}
}