{
  "type": "Feature",
  "properties": {
    "iso:country": "GB",
    "wof:name": "PL27 7SX",
    "wof:placetype": "postalcode"
  },
  "geometry": {"coordinates":[-4.969007,50.49036],"type":"Point"}
}
