{
  "type": "Feature",
  "properties": {
    "date:inception_lower": "1980-01-01",
    "date:inception_upper": "1980-01-01",
    "iso:country": "GB",
    "wof:name": "SP7 9PE",
    "wof:placetype": "postalcode"
  },
  "geometry": {"coordinates":[-2.215002,51.0276],"type":"Point"}
}
