{
  "type": "Feature",
  "properties": {
    "iso:country": "GB",
    "wof:name": "SP7 9PE",
    "wof:placetype": "postalcode"
  },
  "geometry": {"coordinates":[-2.215002,51.0276],"type":"Point"}
}
