{
  "type": "Feature",
  "properties": {
    "iso:country": "GB",
    "wof:name": "SP7 9PE",
    "wof:placetype": "postalcode"
  },
  "geometry": {"coordinates":[-2.215179,51.027858],"type":"Point"}
}
