{
  "type": "Feature",
  "properties": {
    "iso:country":"GB",
    "wof:name":"SO16 7HN",
    "wof:placetype":"postalcode"
},
  "geometry": {"coordinates":[-1.40939471800372,50.95397044531768],"type":"Point"}
}