{
  "type": "Feature",
  "properties": {
    "iso:country": "GB",
    "wof:name": "SO16 7HN",
    "wof:placetype": "postalcode"
  },
  "geometry": {"coordinates":[-1.409395,50.95397],"type":"Point"}
}
