{
  "type": "Feature",
  "properties": {
    "date:inception_lower":"1980-01-01",
    "date:inception_upper":"1980-01-31",
    "iso:country":"GB",
    "wof:name":"WR13 6AF",
    "wof:placetype":"postalcode"
},
  "geometry": {"coordinates":[-2.324781,52.020469],"type":"Point"}
}