{
  "type": "Feature",
  "properties": {
    "iso:country":"GB",
    "wof:name":"WR13 6AF",
    "wof:placetype":"postalcode"
},
  "geometry": {"coordinates":[-2.3247808649419,52.02046867586071],"type":"Point"}
}