{
  "type": "Feature",
  "properties": {
    "iso:country":"GB",
    "wof:name":"NR7 8AS",
    "wof:placetype":"postalcode"
},
  "geometry": {"coordinates":[1.32170632654068,52.65838380854767],"type":"Point"}
}