{
  "type": "Feature",
  "properties": {
    "iso:country": "GB",
    "wof:name": "NR7 8AS",
    "wof:placetype": "postalcode"
  },
  "geometry": {"coordinates":[1.321706,52.658384],"type":"Point"}
}
