{
  "type": "Feature",
  "properties": {
    "iso:country": "GB",
    "wof:name": "CV34 6RH",
    "wof:placetype": "postalcode"
  },
  "geometry": {"coordinates":[-1.54699,52.276718],"type":"Point"}
}
