{
  "type": "Feature",
  "properties": {
    "iso:country":"GB",
    "wof:name":"SP8 5JH",
    "wof:placetype":"postalcode"
},
  "geometry": {"coordinates":[-2.27603540082262,51.02498750704947],"type":"Point"}
}