{
  "type": "Feature",
  "properties": {
    "iso:country": "GB",
    "wof:name": "SP8 5JH",
    "wof:placetype": "postalcode"
  },
  "geometry": {"coordinates":[-2.276035,51.024988],"type":"Point"}
}
