{
  "type": "Feature",
  "properties": {
    "iso:country":"GB",
    "wof:name":"B69 1UY",
    "wof:placetype":"postalcode"
},
  "geometry": {"coordinates":[-2.05907923027416,52.5061620307488],"type":"Point"}
}