{
  "type": "Feature",
  "properties": {
    "date:inception_lower":"1980-01-01",
    "date:inception_upper":"1980-01-31",
    "iso:country":"GB",
    "wof:name":"B69 1UY",
    "wof:placetype":"postalcode"
},
  "geometry": {"coordinates":[-2.059079,52.506162],"type":"Point"}
}