{
  "type": "Feature",
  "properties": {
    "iso:country":"GB",
    "wof:name":"SP3 6BZ",
    "wof:placetype":"postalcode"
},
  "geometry": {"coordinates":[-2.15331720178854,51.06079526443297],"type":"Point"}
}