{
  "type": "Feature",
  "properties": {
    "iso:country":"GB",
    "wof:name":"EH18 1BY",
    "wof:placetype":"postalcode"
},
  "geometry": {"coordinates":[-3.12383747553512,55.87242302996433],"type":"Point"}
}