{
  "type": "Feature",
  "properties": {
    "date:inception_lower":"1980-01-01",
    "date:inception_upper":"1980-01-31",
    "iso:country":"GB",
    "wof:name":"HP10 9BD",
    "wof:placetype":"postalcode"
},
  "geometry": {"coordinates":[-0.706286,51.595494],"type":"Point"}
}