{
  "type": "Feature",
  "properties": {
    "iso:country":"GB",
    "wof:name":"BS15 8JN",
    "wof:placetype":"postalcode"
},
  "geometry": {"coordinates":[-2.51014183495291,51.45955323965651],"type":"Point"}
}