{
  "type": "Feature",
  "properties": {
    "iso:country":"GB",
    "wof:name":"NE45 5AZ",
    "wof:placetype":"postalcode"
},
  "geometry": {"coordinates":[-2.01646309663174,54.96573843256691],"type":"Point"}
}