{
  "type": "Feature",
  "properties": {
    "iso:country":"GB",
    "wof:name":"CF24 3SE",
    "wof:placetype":"postalcode"
},
  "geometry": {"coordinates":[-3.1599962965512,51.49150253777016],"type":"Point"}
}