{
  "type": "Feature",
  "properties": {
    "iso:country":"GB",
    "wof:name":"NP24 6PB",
    "wof:placetype":"postalcode"
},
  "geometry": {"coordinates":[-3.22868979755327,51.71558818937802],"type":"Point"}
}