{
  "type": "Feature",
  "properties": {
    "date:inception_lower": "2005-02-01",
    "date:inception_upper": "2005-02-01",
    "iso:country": "GB",
    "wof:name": "SK1 9SP",
    "wof:placetype": "postalcode"
  },
  "geometry": {"coordinates":[-2.158487,53.405974],"type":"Point"}
}
