{
  "type": "Feature",
  "properties": {
    "date:inception_lower": "2023-08-01",
    "date:inception_upper": "2023-08-01",
    "iso:country": "GB",
    "wof:name": "CB10 1FQ",
    "wof:placetype": "postalcode"
  },
  "geometry": {"coordinates":[0.197486,52.05829],"type":"Point"}
}
