{
  "type": "Feature",
  "properties": {
    "date:inception_lower": "2021-08-01",
    "date:inception_upper": "2021-08-01",
    "iso:country": "GB",
    "wof:name": "IV36 2NS",
    "wof:placetype": "postalcode"
  },
  "geometry": {"coordinates":[-3.619386,57.596235],"type":"Point"}
}
