{
  "type": "Feature",
  "properties": {
    "date:inception_lower": "2019-12-01",
    "date:inception_upper": "2019-12-01",
    "iso:country": "GB",
    "wof:name": "LE17 5FU",
    "wof:placetype": "postalcode"
  },
  "geometry": {"coordinates":[-1.157329,52.487311],"type":"Point"}
}
