{
  "type": "Feature",
  "properties": {
    "iso:country": "GB",
    "wof:name": "LE17 5FU",
    "wof:placetype": "postalcode"
  },
  "geometry": {"coordinates":[-1.276857,52.491563],"type":"Point"}
}
