{
  "type": "Feature",
  "properties": {
    "iso:country": "GB",
    "wof:name": "LE17 5FU",
    "wof:placetype": "postalcode"
  },
  "geometry": {"coordinates":[-1.157329,52.487311],"type":"Point"}
}
