{
  "type": "Feature",
  "properties": {
    "date:inception_lower":"1980-01-01",
    "date:inception_upper":"1980-01-31",
    "iso:country":"GB",
    "wof:name":"NG34 9BD",
    "wof:placetype":"postalcode"
},
  "geometry": {"coordinates":[-0.29384,52.96106],"type":"Point"}
}