{
  "type": "Feature",
  "properties": {
    "iso:country": "GB",
    "wof:name": "L24 0SL",
    "wof:placetype": "postalcode"
  },
  "geometry": {"coordinates":[-2.842164,53.345058],"type":"Point"}
}
