{
  "type": "Feature",
  "properties": {
    "iso:country":"GB",
    "wof:name":"S40 3QU",
    "wof:placetype":"postalcode"
},
  "geometry": {"coordinates":[-1.45598760766049,53.2345133262281],"type":"Point"}
}