{
  "type": "Feature",
  "properties": {
    "date:inception_lower":"2002-06-01",
    "date:inception_upper":"2002-06-30",
    "iso:country":"GB",
    "wof:name":"S40 3QU",
    "wof:placetype":"postalcode"
},
  "geometry": {"coordinates":[-1.455988,53.234513],"type":"Point"}
}