{
  "type": "Feature",
  "properties": {
    "iso:country":"GB",
    "wof:name":"TN11 9HS",
    "wof:placetype":"postalcode"
},
  "geometry": {"coordinates":[0.23618163530419,51.21803479731252],"type":"Point"}
}