{
  "type": "Feature",
  "properties": {
    "iso:country":"GB",
    "wof:name":"LL30 3DY",
    "wof:placetype":"postalcode"
},
  "geometry": {"coordinates":[-3.78201658325235,53.31653419335077],"type":"Point"}
}