{
  "type": "Feature",
  "properties": {
    "date:inception_lower": "1980-01-01",
    "date:inception_upper": "1980-01-01",
    "iso:country": "GB",
    "wof:name": "KA9 1SG",
    "wof:placetype": "postalcode"
  },
  "geometry": {"coordinates":[-4.618569,55.488464],"type":"Point"}
}
