{
  "type": "Feature",
  "properties": {
    "iso:country": "GB",
    "wof:name": "TR16 6NS",
    "wof:placetype": "postalcode"
  },
  "geometry": {"coordinates":[-5.224312,50.18228],"type":"Point"}
}
