{
  "type": "Feature",
  "properties": {
    "iso:country":"GB",
    "wof:name":"SE13 7JJ",
    "wof:placetype":"postalcode"
},
  "geometry": {"coordinates":[-0.02032704362441,51.45978051391462],"type":"Point"}
}