{
  "type": "Feature",
  "properties": {
    "iso:country":"GB",
    "wof:name":"TW18 1JF",
    "wof:placetype":"postalcode"
},
  "geometry": {"coordinates":[-0.49151716863603,51.42574006590839],"type":"Point"}
}