{
  "type": "Feature",
  "properties": {
    "iso:country": "GB",
    "wof:name": "NW6 5BZ",
    "wof:placetype": "postalcode"
  },
  "geometry": {"coordinates":[-0.193513,51.531999],"type":"Point"}
}
