{
  "type": "Feature",
  "properties": {
    "iso:country":"GB",
    "wof:name":"CF46 6RS",
    "wof:placetype":"postalcode"
},
  "geometry": {"coordinates":[-3.31161440381628,51.7034159593315],"type":"Point"}
}