{
  "type": "Feature",
  "properties": {
    "iso:country": "GB",
    "wof:name": "CF46 6RS",
    "wof:placetype": "postalcode"
  },
  "geometry": {"coordinates":[-3.311614,51.703416],"type":"Point"}
}
