{
  "type": "Feature",
  "properties": {
    "iso:country":"GB",
    "wof:name":"WS10 8HZ",
    "wof:placetype":"postalcode"
},
  "geometry": {"coordinates":[-2.03565200725629,52.57596877031774],"type":"Point"}
}