{
  "type": "Feature",
  "properties": {
    "iso:country": "GB",
    "wof:name": "WS10 8HZ",
    "wof:placetype": "postalcode"
  },
  "geometry": {"coordinates":[-2.035652,52.575969],"type":"Point"}
}
