{
  "type": "Feature",
  "properties": {
    "iso:country":"GB",
    "wof:name":"WF9 1DF",
    "wof:placetype":"postalcode"
},
  "geometry": {"coordinates":[-1.28822678795357,53.61353832847877],"type":"Point"}
}