{
  "type": "Feature",
  "properties": {
    "iso:country":"GB",
    "wof:name":"DL6 3QW",
    "wof:placetype":"postalcode"
},
  "geometry": {"coordinates":[-1.4044587182699,54.34359833734192],"type":"Point"}
}