{
  "type": "Feature",
  "properties": {
    "date:inception_lower": "2017-12-01",
    "date:inception_upper": "2017-12-01",
    "iso:country": "GB",
    "wof:name": "MK43 9RE",
    "wof:placetype": "postalcode"
  },
  "geometry": {"coordinates":[-0.529516,52.089835],"type":"Point"}
}
