{
  "type": "Feature",
  "properties": {
    "iso:country": "GB",
    "wof:name": "MK43 9RE",
    "wof:placetype": "postalcode"
  },
  "geometry": {"coordinates":[-0.529516,52.089835],"type":"Point"}
}
