{
  "type": "Feature",
  "properties": {
    "iso:country": "GB",
    "wof:name": "DT1 1BY",
    "wof:placetype": "postalcode"
  },
  "geometry": {"coordinates":[-2.437142,50.712393],"type":"Point"}
}
