{
  "type": "Feature",
  "properties": {
    "iso:country":"GB",
    "wof:name":"DT1 1BY",
    "wof:placetype":"postalcode"
},
  "geometry": {"coordinates":[-2.43721406305941,50.71230285417643],"type":"Point"}
}