{
  "type": "Feature",
  "properties": {
    "iso:country": "GB",
    "wof:name": "DY1 1RD",
    "wof:placetype": "postalcode"
  },
  "geometry": {"coordinates":[-2.09544,52.508895],"type":"Point"}
}
