{
  "type": "Feature",
  "properties": {
    "iso:country":"GB",
    "wof:name":"DY1 1RD",
    "wof:placetype":"postalcode"
},
  "geometry": {"coordinates":[-2.09571097712907,52.5088709281831],"type":"Point"}
}