{
  "type": "Feature",
  "properties": {
    "iso:country":"GB",
    "wof:name":"BA4 6LJ",
    "wof:placetype":"postalcode"
},
  "geometry": {"coordinates":[-2.50901613079715,51.14951039847414],"type":"Point"}
}