{
  "type": "Feature",
  "properties": {
    "date:inception_lower": "1980-01-01",
    "date:inception_upper": "1980-01-01",
    "iso:country": "GB",
    "wof:name": "DG12 6QW",
    "wof:placetype": "postalcode"
  },
  "geometry": {"coordinates":[-3.224988,54.997914],"type":"Point"}
}
