{
  "type": "Feature",
  "properties": {
    "iso:country":"GB",
    "wof:name":"LL20 7TU",
    "wof:placetype":"postalcode"
},
  "geometry": {"coordinates":[-3.08738779920159,52.97551755047538],"type":"Point"}
}