{
  "type": "Feature",
  "properties": {
    "date:inception_lower": "2002-11-01",
    "date:inception_upper": "2002-11-01",
    "iso:country": "GB",
    "wof:name": "DN22 7JP",
    "wof:placetype": "postalcode"
  },
  "geometry": {"coordinates":[-0.931428,53.312912],"type":"Point"}
}
