{
  "type": "Feature",
  "properties": {
    "iso:country":"GB",
    "wof:name":"DN22 7JP",
    "wof:placetype":"postalcode"
},
  "geometry": {"coordinates":[-0.93142827394227,53.31291163755859],"type":"Point"}
}