{
  "type": "Feature",
  "properties": {
    "date:inception_lower": "1990-07-01",
    "date:inception_upper": "1990-07-01",
    "iso:country": "GB",
    "wof:name": "SO41 8JF",
    "wof:placetype": "postalcode"
  },
  "geometry": {"coordinates":[-1.558236,50.751334],"type":"Point"}
}
