{
  "type": "Feature",
  "properties": {
    "iso:country":"GB",
    "wof:name":"EH10 7AB",
    "wof:placetype":"postalcode"
},
  "geometry": {"coordinates":[-3.20068359023587,55.90052299357501],"type":"Point"}
}