{
  "type": "Feature",
  "properties": {
    "iso:country":"GB",
    "wof:name":"CF11 6EL",
    "wof:placetype":"postalcode"
},
  "geometry": {"coordinates":[-3.18949638034074,51.47768312013916],"type":"Point"}
}