{
  "type": "Feature",
  "properties": {
    "iso:country":"GB",
    "wof:name":"EC1Y 0RE",
    "wof:placetype":"postalcode"
},
  "geometry": {"coordinates":[-0.09599887218746,51.52212058019441],"type":"Point"}
}