{
  "type": "Feature",
  "properties": {
    "iso:country":"GB",
    "wof:name":"CA2 6HT",
    "wof:placetype":"postalcode"
},
  "geometry": {"coordinates":[-2.96065172103453,54.8777649069967],"type":"Point"}
}