{
  "type": "Feature",
  "properties": {
    "iso:country":"GB",
    "wof:name":"CM3 1AE",
    "wof:placetype":"postalcode"
},
  "geometry": {"coordinates":[0.46558062548607,51.78968134134261],"type":"Point"}
}