{
  "type": "Feature",
  "properties": {
    "iso:country":"GB",
    "wof:name":"SY12 9AX",
    "wof:placetype":"postalcode"
},
  "geometry": {"coordinates":[-2.9089499530503,52.88702155046931],"type":"Point"}
}