{
  "type": "Feature",
  "properties": {
    "date:inception_lower": "1980-01-01",
    "date:inception_upper": "1980-01-01",
    "iso:country": "GB",
    "wof:name": "SY12 9AX",
    "wof:placetype": "postalcode"
  },
  "geometry": {"coordinates":[-2.90895,52.887022],"type":"Point"}
}
