{
  "type": "Feature",
  "properties": {
    "date:inception_lower": "1992-01-01",
    "date:inception_upper": "1992-01-01",
    "iso:country": "GB",
    "wof:name": "LN6 0FH",
    "wof:placetype": "postalcode"
  },
  "geometry": {"coordinates":[-0.613696,53.218273],"type":"Point"}
}
