{
  "type": "Feature",
  "properties": {
    "iso:country":"GB",
    "wof:name":"LN6 0FH",
    "wof:placetype":"postalcode"
},
  "geometry": {"coordinates":[-0.61369630968214,53.21827349220255],"type":"Point"}
}