{
  "type": "Feature",
  "properties": {
    "iso:country": "GB",
    "wof:name": "LN6 0FH",
    "wof:placetype": "postalcode"
  },
  "geometry": {"coordinates":[-0.613696,53.218273],"type":"Point"}
}
