{
  "type": "Feature",
  "properties": {
    "iso:country":"GB",
    "wof:name":"WN5 0HY",
    "wof:placetype":"postalcode"
},
  "geometry": {"coordinates":[-2.68603063410327,53.54733267281509],"type":"Point"}
}