{
  "type": "Feature",
  "properties": {
    "date:inception_lower": "1999-06-01",
    "date:inception_upper": "1999-06-01",
    "iso:country": "GB",
    "wof:name": "NP24 6EU",
    "wof:placetype": "postalcode"
  },
  "geometry": {"coordinates":[-3.25097,51.723701],"type":"Point"}
}
