{
  "type": "Feature",
  "properties": {
    "date:inception_lower": "1984-10-01",
    "date:inception_upper": "1984-10-01",
    "iso:country": "GB",
    "wof:name": "DT1 1RD",
    "wof:placetype": "postalcode"
  },
  "geometry": {"coordinates":[-2.441864,50.70992],"type":"Point"}
}
