{
  "type": "Feature",
  "properties": {
    "iso:country":"GB",
    "wof:name":"DT1 1RD",
    "wof:placetype":"postalcode"
},
  "geometry": {"coordinates":[-2.44190790434096,50.70990207172623],"type":"Point"}
}