{
  "type": "Feature",
  "properties": {
    "date:inception_lower": "1980-01-01",
    "date:inception_upper": "1980-01-01",
    "iso:country": "GB",
    "wof:name": "CH8 7TQ",
    "wof:placetype": "postalcode"
  },
  "geometry": {"coordinates":[-3.223555,53.272771],"type":"Point"}
}
