{
  "type": "Feature",
  "properties": {
    "iso:country":"GB",
    "wof:name":"CH8 7TQ",
    "wof:placetype":"postalcode"
},
  "geometry": {"coordinates":[-3.22334896814444,53.27295445279979],"type":"Point"}
}