{
  "type": "Feature",
  "properties": {
    "iso:country":"GB",
    "wof:name":"SO45 2PS",
    "wof:placetype":"postalcode"
},
  "geometry": {"coordinates":[-1.39143340413933,50.82910723054044],"type":"Point"}
}