{
  "type": "Feature",
  "properties": {
    "iso:country": "GB",
    "wof:name": "TR15 1QZ",
    "wof:placetype": "postalcode"
  },
  "geometry": {"coordinates":[-5.215737,50.240704],"type":"Point"}
}
