{
  "type": "Feature",
  "properties": {
    "iso:country":"GB",
    "wof:name":"TR15 1QZ",
    "wof:placetype":"postalcode"
},
  "geometry": {"coordinates":[-5.215722746026,50.24059618449638],"type":"Point"}
}