{
  "type": "Feature",
  "properties": {
    "iso:country":"GB",
    "wof:name":"LE8 4DE",
    "wof:placetype":"postalcode"
},
  "geometry": {"coordinates":[-1.16773727422413,52.57155010557592],"type":"Point"}
}