{
  "type": "Feature",
  "properties": {
    "date:inception_lower": "1994-05-01",
    "date:inception_upper": "1994-05-01",
    "iso:country": "GB",
    "wof:name": "LE8 4DE",
    "wof:placetype": "postalcode"
  },
  "geometry": {"coordinates":[-1.167737,52.57155],"type":"Point"}
}
