{
  "type": "Feature",
  "properties": {
    "iso:country":"GB",
    "wof:name":"WR12 7DH",
    "wof:placetype":"postalcode"
},
  "geometry": {"coordinates":[-1.87390095867435,52.04078212554212],"type":"Point"}
}