{
  "type": "Feature",
  "properties": {
    "date:inception_lower": "2000-06-01",
    "date:inception_upper": "2000-06-01",
    "iso:country": "GB",
    "wof:name": "OX16 4RX",
    "wof:placetype": "postalcode"
  },
  "geometry": {"coordinates":[-1.324515,52.062246],"type":"Point"}
}
