{
  "type": "Feature",
  "properties": {
    "iso:country": "GB",
    "wof:name": "NE5 5AL",
    "wof:placetype": "postalcode"
  },
  "geometry": {"coordinates":[-1.713817,54.989684],"type":"Point"}
}
