{
  "type": "Feature",
  "properties": {
    "date:inception_lower": "1980-01-01",
    "date:inception_upper": "1980-01-01",
    "iso:country": "GB",
    "wof:name": "NE5 5AL",
    "wof:placetype": "postalcode"
  },
  "geometry": {"coordinates":[-1.713817,54.989684],"type":"Point"}
}
