{
  "type": "Feature",
  "properties": {
    "iso:country": "GB",
    "wof:name": "NP22 4PU",
    "wof:placetype": "postalcode"
  },
  "geometry": {"coordinates":[-3.241558,51.78636],"type":"Point"}
}
