{
  "type": "Feature",
  "properties": {
    "iso:country":"GB",
    "wof:name":"ME12 3TB",
    "wof:placetype":"postalcode"
},
  "geometry": {"coordinates":[0.79245734276125,51.41258132642324],"type":"Point"}
}