{
  "type": "Feature",
  "properties": {
    "iso:country": "GB",
    "wof:name": "ME12 3TB",
    "wof:placetype": "postalcode"
  },
  "geometry": {"coordinates":[0.792531,51.412583],"type":"Point"}
}
