{
  "type": "Feature",
  "properties": {
    "iso:country": "GB",
    "wof:name": "DE1 3EE",
    "wof:placetype": "postalcode"
  },
  "geometry": {"coordinates":[-1.480261,52.927697],"type":"Point"}
}
