{
  "type": "Feature",
  "properties": {
    "date:inception_lower":"1986-07-01",
    "date:inception_upper":"1986-07-31",
    "iso:country":"GB",
    "wof:name":"DE1 3EE",
    "wof:placetype":"postalcode"
},
  "geometry": {"coordinates":[-1.480261,52.927697],"type":"Point"}
}