{
  "type": "Feature",
  "properties": {
    "iso:country":"GB",
    "wof:name":"S80 2BW",
    "wof:placetype":"postalcode"
},
  "geometry": {"coordinates":[-1.11739905881979,53.30344753912809],"type":"Point"}
}