{
  "type": "Feature",
  "properties": {
    "iso:country": "GB",
    "wof:name": "SK10 3NH",
    "wof:placetype": "postalcode"
  },
  "geometry": {"coordinates":[-2.1664,53.263718],"type":"Point"}
}
