{
  "type": "Feature",
  "properties": {
    "date:inception_lower": "1980-01-01",
    "date:inception_upper": "1980-01-01",
    "iso:country": "GB",
    "wof:name": "SK10 3NH",
    "wof:placetype": "postalcode"
  },
  "geometry": {"coordinates":[-2.1664,53.263718],"type":"Point"}
}
