{
  "type": "Feature",
  "properties": {
    "date:inception_lower":"1980-01-01",
    "date:inception_upper":"1980-01-31",
    "iso:country":"GB",
    "wof:name":"YO15 3EX",
    "wof:placetype":"postalcode"
},
  "geometry": {"coordinates":[-0.198845,54.083001],"type":"Point"}
}