{
  "type": "Feature",
  "properties": {
    "iso:country": "GB",
    "wof:name": "YO15 3EX",
    "wof:placetype": "postalcode"
  },
  "geometry": {"coordinates":[-0.198845,54.083001],"type":"Point"}
}
