{
  "type": "Feature",
  "properties": {
    "iso:country":"GB",
    "wof:name":"KY1 4NG",
    "wof:placetype":"postalcode"
},
  "geometry": {"coordinates":[-3.09144712443196,56.1506828965303],"type":"Point"}
}