{
  "type": "Feature",
  "properties": {
    "iso:country": "GB",
    "wof:name": "KY1 4NG",
    "wof:placetype": "postalcode"
  },
  "geometry": {"coordinates":[-3.091447,56.150683],"type":"Point"}
}
