{
  "type": "Feature",
  "properties": {
    "iso:country":"GB",
    "wof:name":"M16 7JX",
    "wof:placetype":"postalcode"
},
  "geometry": {"coordinates":[-2.24812852096979,53.45618433755342],"type":"Point"}
}