{
  "type": "Feature",
  "properties": {
    "iso:country":"GB",
    "wof:name":"BD22 9JJ",
    "wof:placetype":"postalcode"
},
  "geometry": {"coordinates":[-1.95092596126931,53.8110082150841],"type":"Point"}
}