{
  "type": "Feature",
  "properties": {
    "iso:country": "GB",
    "wof:name": "BD22 9JJ",
    "wof:placetype": "postalcode"
  },
  "geometry": {"coordinates":[-1.950926,53.811008],"type":"Point"}
}
