{
  "type": "Feature",
  "properties": {
    "date:inception_lower": "1995-01-01",
    "date:inception_upper": "1995-01-01",
    "iso:country": "GB",
    "wof:name": "NR28 9ND",
    "wof:placetype": "postalcode"
  },
  "geometry": {"coordinates":[1.387071,52.818979],"type":"Point"}
}
