{
  "type": "Feature",
  "properties": {
    "iso:country":"GB",
    "wof:name":"NR28 9ND",
    "wof:placetype":"postalcode"
},
  "geometry": {"coordinates":[1.3870792899494,52.81894981637315],"type":"Point"}
}