{
  "type": "Feature",
  "properties": {
    "date:inception_lower": "2000-06-01",
    "date:inception_upper": "2000-06-01",
    "iso:country": "GB",
    "wof:name": "PE25 1TT",
    "wof:placetype": "postalcode"
  },
  "geometry": {"coordinates":[0.316514,53.160519],"type":"Point"}
}
