{
  "type": "Feature",
  "properties": {
    "iso:country":"GB",
    "wof:name":"PE25 1TT",
    "wof:placetype":"postalcode"
},
  "geometry": {"coordinates":[0.31651421074362,53.16051905431153],"type":"Point"}
}