{
  "type": "Feature",
  "properties": {
    "iso:country": "GB",
    "wof:name": "EX11 1GJ",
    "wof:placetype": "postalcode"
  },
  "geometry": {"coordinates":[-3.29212,50.746833],"type":"Point"}
}
