{
  "type": "Feature",
  "properties": {
    "iso:country":"GB",
    "wof:name":"EN5 3DA",
    "wof:placetype":"postalcode"
},
  "geometry": {"coordinates":[-0.22586685130864,51.64835848336357],"type":"Point"}
}