{
  "type": "Feature",
  "properties": {
    "iso:country":"GB",
    "wof:name":"CT1 1FJ",
    "wof:placetype":"postalcode"
},
  "geometry": {"coordinates":[1.09396515478509,51.28834483310168],"type":"Point"}
}