{
  "type": "Feature",
  "properties": {
    "iso:country": "GB",
    "wof:name": "DD1 2AN",
    "wof:placetype": "postalcode"
  },
  "geometry": {"coordinates":[-2.966473,56.469998],"type":"Point"}
}
