{
  "type": "Feature",
  "properties": {
    "date:inception_lower":"1980-01-01",
    "date:inception_upper":"1980-01-31",
    "iso:country":"GB",
    "wof:name":"TN31 6HP",
    "wof:placetype":"postalcode"
},
  "geometry": {"coordinates":[0.592831,50.981281],"type":"Point"}
}