{
  "type": "Feature",
  "properties": {
    "iso:country":"GB",
    "wof:name":"TN31 6HP",
    "wof:placetype":"postalcode"
},
  "geometry": {"coordinates":[0.59283049362697,50.98128052443061],"type":"Point"}
}