{
  "type": "Feature",
  "properties": {
    "iso:country": "GB",
    "wof:name": "TQ14 8RE",
    "wof:placetype": "postalcode"
  },
  "geometry": {"coordinates":[-3.493507,50.560163],"type":"Point"}
}
