{
  "type": "Feature",
  "properties": {
    "iso:country":"GB",
    "wof:name":"GU27 3PE",
    "wof:placetype":"postalcode"
},
  "geometry": {"coordinates":[-0.72503540802938,51.05160722395453],"type":"Point"}
}