{
  "type": "Feature",
  "properties": {
    "iso:country":"GB",
    "wof:name":"G42 9QG",
    "wof:placetype":"postalcode"
},
  "geometry": {"coordinates":[-4.2684305744369,55.82686848057015],"type":"Point"}
}