{
  "type": "Feature",
  "properties": {
    "iso:country":"GB",
    "wof:name":"SA9 1HJ",
    "wof:placetype":"postalcode"
},
  "geometry": {"coordinates":[-3.75303140280844,51.78000621931203],"type":"Point"}
}