{
  "type": "Feature",
  "properties": {
    "iso:country":"GB",
    "wof:name":"RH1 5BB",
    "wof:placetype":"postalcode"
},
  "geometry": {"coordinates":[-0.16672846712114,51.21178592425571],"type":"Point"}
}