{
  "type": "Feature",
  "properties": {
    "date:inception_lower": "1980-01-01",
    "date:inception_upper": "1980-01-01",
    "iso:country": "GB",
    "wof:name": "DE6 2FS",
    "wof:placetype": "postalcode"
  },
  "geometry": {"coordinates":[-1.809016,53.100129],"type":"Point"}
}
