{
  "type": "Feature",
  "properties": {
    "iso:country":"GB",
    "wof:name":"DE6 2FS",
    "wof:placetype":"postalcode"
},
  "geometry": {"coordinates":[-1.80901579796984,53.10012883739046],"type":"Point"}
}