{
  "type": "Feature",
  "properties": {
    "iso:country":"GB",
    "wof:name":"N1 0RY",
    "wof:placetype":"postalcode"
},
  "geometry": {"coordinates":[-0.10666466603657,51.53883047644126],"type":"Point"}
}