{
  "type": "Feature",
  "properties": {
    "iso:country": "GB",
    "wof:name": "N1 0RY",
    "wof:placetype": "postalcode"
  },
  "geometry": {"coordinates":[-0.106665,51.53883],"type":"Point"}
}
