{
  "type": "Feature",
  "properties": {
    "iso:country":"GB",
    "wof:name":"HG5 8LU",
    "wof:placetype":"postalcode"
},
  "geometry": {"coordinates":[-1.48887760356733,53.99420035432971],"type":"Point"}
}