{
  "type": "Feature",
  "properties": {
    "iso:country": "GB",
    "wof:name": "PO7 3DB",
    "wof:placetype": "postalcode"
  },
  "geometry": {"coordinates":[-1.04496,50.87728],"type":"Point"}
}
