{
  "type": "Feature",
  "properties": {
    "date:inception_lower": "2019-04-01",
    "date:inception_upper": "2019-04-01",
    "iso:country": "GB",
    "wof:name": "PO7 3DB",
    "wof:placetype": "postalcode"
  },
  "geometry": {"coordinates":[-1.043588,50.87762],"type":"Point"}
}
