{
  "type": "Feature",
  "properties": {
    "iso:country":"GB",
    "wof:name":"PR6 9NU",
    "wof:placetype":"postalcode"
},
  "geometry": {"coordinates":[-2.59541562060573,53.61921335501967],"type":"Point"}
}