{
  "type": "Feature",
  "properties": {
    "iso:country": "GB",
    "wof:name": "IP33 3PP",
    "wof:placetype": "postalcode"
  },
  "geometry": {"coordinates":[0.711491,52.242967],"type":"Point"}
}
