{
  "type": "Feature",
  "properties": {
    "date:inception_lower":"2003-03-01",
    "date:inception_upper":"2003-03-31",
    "iso:country":"GB",
    "wof:name":"IP33 3PP",
    "wof:placetype":"postalcode"
},
  "geometry": {"coordinates":[0.711491,52.242967],"type":"Point"}
}