{
  "type": "Feature",
  "properties": {
    "iso:country":"GB",
    "wof:name":"W1F 9EP",
    "wof:placetype":"postalcode"
},
  "geometry": {"coordinates":[-0.13798437502853,51.51305571234651],"type":"Point"}
}