{
  "type": "Feature",
  "properties": {
    "iso:country":"GB",
    "wof:name":"NR10 5BF",
    "wof:placetype":"postalcode"
},
  "geometry": {"coordinates":[1.25059829628515,52.72792533785016],"type":"Point"}
}