{
  "type": "Feature",
  "properties": {
    "iso:country":"GB",
    "wof:name":"SO41 0LU",
    "wof:placetype":"postalcode"
},
  "geometry": {"coordinates":[-1.58934756616232,50.74516178606455],"type":"Point"}
}