{
  "type": "Feature",
  "properties": {
    "iso:country":"GB",
    "wof:name":"CV37 6XJ",
    "wof:placetype":"postalcode"
},
  "geometry": {"coordinates":[-1.70521766750075,52.20031505377103],"type":"Point"}
}