{
  "type": "Feature",
  "properties": {
    "date:inception_lower": "2007-09-01",
    "date:inception_upper": "2007-09-01",
    "iso:country": "GB",
    "wof:name": "GU51 1GR",
    "wof:placetype": "postalcode"
  },
  "geometry": {"coordinates":[-0.843862,51.29382],"type":"Point"}
}
