{
  "type": "Feature",
  "properties": {
    "iso:country":"GB",
    "wof:name":"GU51 1GR",
    "wof:placetype":"postalcode"
},
  "geometry": {"coordinates":[-0.84386215643977,51.29382007292097],"type":"Point"}
}