{
  "type": "Feature",
  "properties": {
    "iso:country":"GB",
    "wof:name":"NG10 4LF",
    "wof:placetype":"postalcode"
},
  "geometry": {"coordinates":[-1.27791552931945,52.89958103142861],"type":"Point"}
}