{
  "type": "Feature",
  "properties": {
    "iso:country":"GB",
    "wof:name":"W1G 8PE",
    "wof:placetype":"postalcode"
},
  "geometry": {"coordinates":[-0.14801697118806,51.51976109120338],"type":"Point"}
}