{
  "type": "Feature",
  "properties": {
    "iso:country":"GB",
    "wof:name":"LE5 2PD",
    "wof:placetype":"postalcode"
},
  "geometry": {"coordinates":[-1.05227812469745,52.64200988884578],"type":"Point"}
}