{
  "type": "Feature",
  "properties": {
    "iso:country": "GB",
    "wof:name": "DN32 0NJ",
    "wof:placetype": "postalcode"
  },
  "geometry": {"coordinates":[-0.080654,53.559496],"type":"Point"}
}
