{
  "type": "Feature",
  "properties": {
    "iso:country":"GB",
    "wof:name":"SM5 3LJ",
    "wof:placetype":"postalcode"
},
  "geometry": {"coordinates":[-0.1714299091201,51.35499773900158],"type":"Point"}
}