{
  "type": "Feature",
  "properties": {
    "iso:country":"GB",
    "wof:name":"LE7 9TS",
    "wof:placetype":"postalcode"
},
  "geometry": {"coordinates":[-1.03796389244568,52.64575129215331],"type":"Point"}
}