{
  "type": "Feature",
  "properties": {
    "iso:country": "GB",
    "wof:name": "LE7 9TS",
    "wof:placetype": "postalcode"
  },
  "geometry": {"coordinates":[-1.037964,52.645751],"type":"Point"}
}
