{
  "type": "Feature",
  "properties": {
    "date:inception_lower":"2014-04-01",
    "date:inception_upper":"2014-04-30",
    "iso:country":"GB",
    "wof:name":"LE7 9TS",
    "wof:placetype":"postalcode"
},
  "geometry": {"coordinates":[-1.037964,52.645751],"type":"Point"}
}