{
  "type": "Feature",
  "properties": {
    "iso:country": "GB",
    "wof:name": "HP21 8FT",
    "wof:placetype": "postalcode"
  },
  "geometry": {"coordinates":[-0.829087,51.808598],"type":"Point"}
}
