{
  "type": "Feature",
  "properties": {
    "iso:country":"GB",
    "wof:name":"HP21 8FT",
    "wof:placetype":"postalcode"
},
  "geometry": {"coordinates":[-0.82908699141994,51.80859819439143],"type":"Point"}
}