{
  "type": "Feature",
  "properties": {
    "date:inception_lower":"1999-12-01",
    "date:inception_upper":"1999-12-31",
    "iso:country":"GB",
    "wof:name":"HP21 8FT",
    "wof:placetype":"postalcode"
},
  "geometry": {"coordinates":[-0.829087,51.808598],"type":"Point"}
}