{
  "type": "Feature",
  "properties": {
    "iso:country": "GB",
    "wof:name": "NE3 4AP",
    "wof:placetype": "postalcode"
  },
  "geometry": {"coordinates":[-1.619348,54.999176],"type":"Point"}
}
