{
  "type": "Feature",
  "properties": {
    "date:inception_lower": "1999-06-01",
    "date:inception_upper": "1999-06-01",
    "iso:country": "GB",
    "wof:name": "NP12 0LD",
    "wof:placetype": "postalcode"
  },
  "geometry": {"coordinates":[-3.174237,51.680711],"type":"Point"}
}
