{
  "type": "Feature",
  "properties": {
    "date:inception_lower": "1981-09-01",
    "date:inception_upper": "1981-09-01",
    "iso:country": "GB",
    "wof:name": "SL9 8BW",
    "wof:placetype": "postalcode"
  },
  "geometry": {"coordinates":[-0.553335,51.587238],"type":"Point"}
}
