{
  "type": "Feature",
  "properties": {
    "iso:country": "GB",
    "wof:name": "SL9 8BW",
    "wof:placetype": "postalcode"
  },
  "geometry": {"coordinates":[-0.553494,51.587231],"type":"Point"}
}
