{
  "type": "Feature",
  "properties": {
    "date:inception_lower": "2013-07-01",
    "date:inception_upper": "2013-07-01",
    "iso:country": "GB",
    "wof:name": "SA10 6ES",
    "wof:placetype": "postalcode"
  },
  "geometry": {"coordinates":[-3.856556,51.658483],"type":"Point"}
}
