{
  "type": "Feature",
  "properties": {
    "iso:country":"GB",
    "wof:name":"SA10 6ES",
    "wof:placetype":"postalcode"
},
  "geometry": {"coordinates":[-3.85561860482821,51.65822313976607],"type":"Point"}
}