{
  "type": "Feature",
  "properties": {
    "iso:country": "GB",
    "wof:name": "SY4 4NF",
    "wof:placetype": "postalcode"
  },
  "geometry": {"coordinates":[-2.640807,52.811219],"type":"Point"}
}
