{
  "type": "Feature",
  "properties": {
    "date:inception_lower":"1980-01-01",
    "date:inception_upper":"1980-01-31",
    "iso:country":"GB",
    "wof:name":"LN11 7BN",
    "wof:placetype":"postalcode"
},
  "geometry": {"coordinates":[0.138647,53.424733],"type":"Point"}
}