{
  "type": "Feature",
  "properties": {
    "iso:country":"GB",
    "wof:name":"LN11 7BN",
    "wof:placetype":"postalcode"
},
  "geometry": {"coordinates":[0.13864654128478,53.42473296522969],"type":"Point"}
}