{
  "type": "Feature",
  "properties": {
    "iso:country":"GB",
    "wof:name":"AB30 1HX",
    "wof:placetype":"postalcode"
},
  "geometry": {"coordinates":[-2.37740854297858,56.82184866039242],"type":"Point"}
}