{
  "type": "Feature",
  "properties": {
    "iso:country": "GB",
    "wof:name": "AB30 1HX",
    "wof:placetype": "postalcode"
  },
  "geometry": {"coordinates":[-2.377408,56.821849],"type":"Point"}
}
