{
  "type": "Feature",
  "properties": {
    "iso:country": "GB",
    "wof:name": "M25 1LB",
    "wof:placetype": "postalcode"
  },
  "geometry": {"coordinates":[-2.274723,53.53526],"type":"Point"}
}
