{
  "type": "Feature",
  "properties": {
    "iso:country":"GB",
    "wof:name":"M25 1LB",
    "wof:placetype":"postalcode"
},
  "geometry": {"coordinates":[-2.27472293473628,53.53526033667458],"type":"Point"}
}