{
  "type": "Feature",
  "properties": {
    "iso:country":"GB",
    "wof:name":"TR9 6BX",
    "wof:placetype":"postalcode"
},
  "geometry": {"coordinates":[-4.94060342033338,50.4285193470801],"type":"Point"}
}