{
  "type": "Feature",
  "properties": {
    "iso:country": "GB",
    "wof:name": "IP30 9DT",
    "wof:placetype": "postalcode"
  },
  "geometry": {"coordinates":[0.910802,52.231545],"type":"Point"}
}
