{
  "type": "Feature",
  "properties": {
    "iso:country":"GB",
    "wof:name":"NR32 1XT",
    "wof:placetype":"postalcode"
},
  "geometry": {"coordinates":[1.75756634086993,52.48660840694002],"type":"Point"}
}