{
  "type": "Feature",
  "properties": {
    "iso:country": "GB",
    "wof:name": "HP20 1XW",
    "wof:placetype": "postalcode"
  },
  "geometry": {"coordinates":[-0.793388,51.824988],"type":"Point"}
}
