{
  "type": "Feature",
  "properties": {
    "iso:country":"GB",
    "wof:name":"HP20 1XW",
    "wof:placetype":"postalcode"
},
  "geometry": {"coordinates":[-0.79338755463345,51.82498842437991],"type":"Point"}
}