{
  "type": "Feature",
  "properties": {
    "date:inception_lower": "1986-04-01",
    "date:inception_upper": "1986-04-01",
    "iso:country": "GB",
    "wof:name": "HP20 1XW",
    "wof:placetype": "postalcode"
  },
  "geometry": {"coordinates":[-0.793388,51.824988],"type":"Point"}
}
