{
  "type": "Feature",
  "properties": {
    "iso:country":"GB",
    "wof:name":"SE19 2EB",
    "wof:placetype":"postalcode"
},
  "geometry": {"coordinates":[-0.08100147059219,51.40936024664942],"type":"Point"}
}