{
  "type": "Feature",
  "properties": {
    "date:inception_lower": "1980-01-01",
    "date:inception_upper": "1980-01-01",
    "iso:country": "GB",
    "wof:name": "SE19 2EB",
    "wof:placetype": "postalcode"
  },
  "geometry": {"coordinates":[-0.081001,51.40936],"type":"Point"}
}
