{
  "type": "Feature",
  "properties": {
    "date:inception_lower": "1980-01-01",
    "date:inception_upper": "1980-01-01",
    "iso:country": "GB",
    "wof:name": "WR9 9EZ",
    "wof:placetype": "postalcode"
  },
  "geometry": {"coordinates":[-2.167504,52.271164],"type":"Point"}
}
