{
  "type": "Feature",
  "properties": {
    "iso:country":"GB",
    "wof:name":"SG4 8LG",
    "wof:placetype":"postalcode"
},
  "geometry": {"coordinates":[-0.31535534951804,51.90486777418175],"type":"Point"}
}