{
  "type": "Feature",
  "properties": {
    "date:inception_lower":"1980-01-01",
    "date:inception_upper":"1980-01-31",
    "iso:country":"GB",
    "wof:name":"SG4 8LG",
    "wof:placetype":"postalcode"
},
  "geometry": {"coordinates":[-0.31546,51.904948],"type":"Point"}
}