{
  "type": "Feature",
  "properties": {
    "iso:country":"GB",
    "wof:name":"LA11 7HT",
    "wof:placetype":"postalcode"
},
  "geometry": {"coordinates":[-2.91421134033581,54.19011554819766],"type":"Point"}
}