{
  "type": "Feature",
  "properties": {
    "iso:country": "GB",
    "wof:name": "SW20 0JF",
    "wof:placetype": "postalcode"
  },
  "geometry": {"coordinates":[-0.232633,51.407069],"type":"Point"}
}
