{
  "type": "Feature",
  "properties": {
    "date:inception_lower":"1980-01-01",
    "date:inception_upper":"1980-01-31",
    "iso:country":"GB",
    "wof:name":"SN3 4DY",
    "wof:placetype":"postalcode"
},
  "geometry": {"coordinates":[-1.74717,51.5723],"type":"Point"}
}