{
  "type": "Feature",
  "properties": {
    "iso:country": "GB",
    "wof:name": "SN3 4DY",
    "wof:placetype": "postalcode"
  },
  "geometry": {"coordinates":[-1.74717,51.5723],"type":"Point"}
}
