{
  "type": "Feature",
  "properties": {
    "iso:country":"GB",
    "wof:name":"SN3 4DY",
    "wof:placetype":"postalcode"
},
  "geometry": {"coordinates":[-1.74717002081707,51.57229977358791],"type":"Point"}
}