{
  "type": "Feature",
  "properties": {
    "iso:country": "GB",
    "wof:name": "BS15 1RB",
    "wof:placetype": "postalcode"
  },
  "geometry": {"coordinates":[-2.507255,51.464044],"type":"Point"}
}
