{
  "type": "Feature",
  "properties": {
    "date:inception_lower": "2022-02-01",
    "date:inception_upper": "2022-02-01",
    "iso:country": "GB",
    "wof:name": "EH3 1HY",
    "wof:placetype": "postalcode"
  },
  "geometry": {"coordinates":[-3.232955,55.943214],"type":"Point"}
}
