{
  "type": "Feature",
  "properties": {
    "date:inception_lower": "2003-06-01",
    "date:inception_upper": "2003-06-01",
    "iso:country": "GB",
    "wof:name": "SN10 3GD",
    "wof:placetype": "postalcode"
  },
  "geometry": {"coordinates":[-1.973309,51.346833],"type":"Point"}
}
