{
  "type": "Feature",
  "properties": {
    "iso:country":"GB",
    "wof:name":"SN10 3GD",
    "wof:placetype":"postalcode"
},
  "geometry": {"coordinates":[-1.97333084259075,51.3468362819475],"type":"Point"}
}