{
  "type": "Feature",
  "properties": {
    "iso:country":"GB",
    "wof:name":"ML2 7DH",
    "wof:placetype":"postalcode"
},
  "geometry": {"coordinates":[-3.9123817305404,55.77990813851211],"type":"Point"}
}