{
  "type": "Feature",
  "properties": {
    "iso:country": "GB",
    "wof:name": "ML2 7DH",
    "wof:placetype": "postalcode"
  },
  "geometry": {"coordinates":[-3.912382,55.779908],"type":"Point"}
}
