{
  "type": "Feature",
  "properties": {
    "iso:country": "GB",
    "wof:name": "CV47 2SE",
    "wof:placetype": "postalcode"
  },
  "geometry": {"coordinates":[-1.40536,52.183641],"type":"Point"}
}
