{
  "type": "Feature",
  "properties": {
    "iso:country":"GB",
    "wof:name":"HA3 5EX",
    "wof:placetype":"postalcode"
},
  "geometry": {"coordinates":[-0.34187374267075,51.60254842928344],"type":"Point"}
}