{
  "type": "Feature",
  "properties": {
    "iso:country":"GB",
    "wof:name":"RH10 6BJ",
    "wof:placetype":"postalcode"
},
  "geometry": {"coordinates":[-0.19041307798551,51.10789943805718],"type":"Point"}
}