{
  "type": "Feature",
  "properties": {
    "iso:country":"GB",
    "wof:name":"SP10 4LQ",
    "wof:placetype":"postalcode"
},
  "geometry": {"coordinates":[-1.49185510684211,51.2211649532826],"type":"Point"}
}