{
  "type": "Feature",
  "properties": {
    "iso:country":"GB",
    "wof:name":"SG1 2JA",
    "wof:placetype":"postalcode"
},
  "geometry": {"coordinates":[-0.22243166411757,51.91895788051426],"type":"Point"}
}