{
  "type": "Feature",
  "properties": {
    "date:inception_lower": "1980-01-01",
    "date:inception_upper": "1980-01-01",
    "iso:country": "GB",
    "wof:name": "SG1 2JA",
    "wof:placetype": "postalcode"
  },
  "geometry": {"coordinates":[-0.221909,51.918714],"type":"Point"}
}
