{
  "type": "Feature",
  "properties": {
    "iso:country": "GB",
    "wof:name": "PO18 8JT",
    "wof:placetype": "postalcode"
  },
  "geometry": {"coordinates":[-0.843745,50.840758],"type":"Point"}
}
