{
  "type": "Feature",
  "properties": {
    "date:inception_lower": "1980-01-01",
    "date:inception_upper": "1980-01-01",
    "iso:country": "GB",
    "wof:name": "BN17 5LZ",
    "wof:placetype": "postalcode"
  },
  "geometry": {"coordinates":[-0.534987,50.805527],"type":"Point"}
}
