{
  "type": "Feature",
  "properties": {
    "iso:country": "GB",
    "wof:name": "BN17 5LZ",
    "wof:placetype": "postalcode"
  },
  "geometry": {"coordinates":[-0.534987,50.805527],"type":"Point"}
}
