{
  "type": "Feature",
  "properties": {
    "date:inception_lower": "1980-01-01",
    "date:inception_upper": "1980-01-01",
    "iso:country": "GB",
    "wof:name": "LS4 2SS",
    "wof:placetype": "postalcode"
  },
  "geometry": {"coordinates":[-1.589758,53.811243],"type":"Point"}
}
