{
  "type": "Feature",
  "properties": {
    "iso:country": "GB",
    "wof:name": "LS4 2SS",
    "wof:placetype": "postalcode"
  },
  "geometry": {"coordinates":[-1.589758,53.811243],"type":"Point"}
}
