{
  "type": "Feature",
  "properties": {
    "date:inception_lower": "1980-01-01",
    "date:inception_upper": "1980-01-01",
    "iso:country": "GB",
    "wof:name": "SS3 0LL",
    "wof:placetype": "postalcode"
  },
  "geometry": {"coordinates":[0.7913,51.5676],"type":"Point"}
}
