{
  "type": "Feature",
  "properties": {
    "iso:country":"GB",
    "wof:name":"SS3 0LL",
    "wof:placetype":"postalcode"
},
  "geometry": {"coordinates":[0.7912997941713,51.5676002937378],"type":"Point"}
}