{
  "type": "Feature",
  "properties": {
    "date:inception_lower": "1980-01-01",
    "date:inception_upper": "1980-01-01",
    "iso:country": "GB",
    "wof:name": "LL22 8YR",
    "wof:placetype": "postalcode"
  },
  "geometry": {"coordinates":[-3.626809,53.220701],"type":"Point"}
}
