{
  "type": "Feature",
  "properties": {
    "iso:country":"GB",
    "wof:name":"LL22 8YR",
    "wof:placetype":"postalcode"
},
  "geometry": {"coordinates":[-3.62680921415781,53.2207008347742],"type":"Point"}
}