{
  "type": "Feature",
  "properties": {
    "iso:country":"GB",
    "wof:name":"B17 0LN",
    "wof:placetype":"postalcode"
},
  "geometry": {"coordinates":[-1.95054451004427,52.45146277632466],"type":"Point"}
}