{
  "type": "Feature",
  "properties": {
    "date:inception_lower":"2009-11-01",
    "date:inception_upper":"2009-11-30",
    "iso:country":"GB",
    "wof:name":"HU6 7TZ",
    "wof:placetype":"postalcode"
},
  "geometry": {"coordinates":[-0.357001,53.769968],"type":"Point"}
}