{
  "type": "Feature",
  "properties": {
    "iso:country": "GB",
    "wof:name": "HU6 7TZ",
    "wof:placetype": "postalcode"
  },
  "geometry": {"coordinates":[-0.357001,53.769968],"type":"Point"}
}
