{
  "type": "Feature",
  "properties": {
    "iso:country":"GB",
    "wof:name":"MK3 5GY",
    "wof:placetype":"postalcode"
},
  "geometry": {"coordinates":[-0.73483843079761,51.97659710725543],"type":"Point"}
}