{
  "type": "Feature",
  "properties": {
    "date:inception_lower": "2014-12-01",
    "date:inception_upper": "2014-12-01",
    "iso:country": "GB",
    "wof:name": "MK3 5GY",
    "wof:placetype": "postalcode"
  },
  "geometry": {"coordinates":[-0.734838,51.976597],"type":"Point"}
}
