{
  "type": "Feature",
  "properties": {
    "iso:country":"GB",
    "wof:name":"DL16 7UD",
    "wof:placetype":"postalcode"
},
  "geometry": {"coordinates":[-1.6041167213398,54.69569048064142],"type":"Point"}
}