{
  "type": "Feature",
  "properties": {
    "iso:country": "GB",
    "wof:name": "CV3 2GD",
    "wof:placetype": "postalcode"
  },
  "geometry": {"coordinates":[-1.454557,52.396707],"type":"Point"}
}
