{
  "type": "Feature",
  "properties": {
    "iso:country":"GB",
    "wof:name":"FK5 3LW",
    "wof:placetype":"postalcode"
},
  "geometry": {"coordinates":[-3.82028348499785,56.01870337942685],"type":"Point"}
}