{
  "type": "Feature",
  "properties": {
    "iso:country":"GB",
    "wof:name":"GU24 9EW",
    "wof:placetype":"postalcode"
},
  "geometry": {"coordinates":[-0.64647007489258,51.32451795669096],"type":"Point"}
}