{
  "type": "Feature",
  "properties": {
    "iso:country": "GB",
    "wof:name": "GU24 9EW",
    "wof:placetype": "postalcode"
  },
  "geometry": {"coordinates":[-0.64647,51.324518],"type":"Point"}
}
