{
  "type": "Feature",
  "properties": {
    "date:inception_lower":"1994-05-01",
    "date:inception_upper":"1994-05-31",
    "iso:country":"GB",
    "wof:name":"CH7 1GT",
    "wof:placetype":"postalcode"
},
  "geometry": {"coordinates":[-3.134527,53.16472],"type":"Point"}
}