{
  "type": "Feature",
  "properties": {
    "date:inception_lower":"1980-01-01",
    "date:inception_upper":"1980-01-31",
    "iso:country":"GB",
    "wof:name":"B13 9BB",
    "wof:placetype":"postalcode"
},
  "geometry": {"coordinates":[-1.877974,52.450862],"type":"Point"}
}