{
  "type": "Feature",
  "properties": {
    "iso:country":"GB",
    "wof:name":"B13 9BB",
    "wof:placetype":"postalcode"
},
  "geometry": {"coordinates":[-1.87797383634728,52.45086194378121],"type":"Point"}
}