{
  "type": "Feature",
  "properties": {
    "iso:country":"GB",
    "wof:name":"DH9 8DH",
    "wof:placetype":"postalcode"
},
  "geometry": {"coordinates":[-1.74951223100184,54.86891532521295],"type":"Point"}
}