{
  "type": "Feature",
  "properties": {
    "iso:country":"GB",
    "wof:name":"NE34 0SN",
    "wof:placetype":"postalcode"
},
  "geometry": {"coordinates":[-1.420119764127,54.98160320846496],"type":"Point"}
}