{
  "type": "Feature",
  "properties": {
    "iso:country":"GB",
    "wof:name":"HA3 8RL",
    "wof:placetype":"postalcode"
},
  "geometry": {"coordinates":[-0.31297783547603,51.59752370382561],"type":"Point"}
}