{
  "type": "Feature",
  "properties": {
    "date:inception_lower": "2006-10-01",
    "date:inception_upper": "2006-10-01",
    "iso:country": "GB",
    "wof:name": "HP9 1UB",
    "wof:placetype": "postalcode"
  },
  "geometry": {"coordinates":[-0.66846,51.599963],"type":"Point"}
}
