{
  "type": "Feature",
  "properties": {
    "iso:country":"GB",
    "wof:name":"HP9 1UB",
    "wof:placetype":"postalcode"
},
  "geometry": {"coordinates":[-0.66845992456973,51.59996306753714],"type":"Point"}
}