{
  "type": "Feature",
  "properties": {
    "iso:country": "GB",
    "wof:name": "RH9 8HL",
    "wof:placetype": "postalcode"
  },
  "geometry": {"coordinates":[-0.041564,51.21856],"type":"Point"}
}
