{
  "type": "Feature",
  "properties": {
    "iso:country":"GB",
    "wof:name":"BS5 7ED",
    "wof:placetype":"postalcode"
},
  "geometry": {"coordinates":[-2.54858000304302,51.46616829199879],"type":"Point"}
}