{
  "type": "Feature",
  "properties": {
    "iso:country":"GB",
    "wof:name":"LS11 8UT",
    "wof:placetype":"postalcode"
},
  "geometry": {"coordinates":[-1.56909737643374,53.77334022067352],"type":"Point"}
}