{
  "type": "Feature",
  "properties": {
    "iso:country": "GB",
    "wof:name": "FY1 3TX",
    "wof:placetype": "postalcode"
  },
  "geometry": {"coordinates":[-3.045438,53.820356],"type":"Point"}
}
