{
  "type": "Feature",
  "properties": {
    "date:inception_lower": "2001-12-01",
    "date:inception_upper": "2001-12-01",
    "iso:country": "GB",
    "wof:name": "FY1 3TX",
    "wof:placetype": "postalcode"
  },
  "geometry": {"coordinates":[-3.045438,53.820356],"type":"Point"}
}
