{
  "type": "Feature",
  "properties": {
    "iso:country":"GB",
    "wof:name":"WD4 8QW",
    "wof:placetype":"postalcode"
},
  "geometry": {"coordinates":[-0.45365279123356,51.70237440063443],"type":"Point"}
}