{
  "type": "Feature",
  "properties": {
    "iso:country": "GB",
    "wof:name": "SO31 1DH",
    "wof:placetype": "postalcode"
  },
  "geometry": {"coordinates":[-1.31026,50.900273],"type":"Point"}
}
