{
  "type": "Feature",
  "properties": {
    "iso:country":"GB",
    "wof:name":"DN19 7ED",
    "wof:placetype":"postalcode"
},
  "geometry": {"coordinates":[-0.36103846011383,53.67015405733656],"type":"Point"}
}