{
  "type": "Feature",
  "properties": {
    "iso:country":"GB",
    "wof:name":"UB6 9NR",
    "wof:placetype":"postalcode"
},
  "geometry": {"coordinates":[-0.35354120862817,51.53504636901646],"type":"Point"}
}