{
  "type": "Feature",
  "properties": {
    "iso:country": "GB",
    "wof:name": "PL19 8FN",
    "wof:placetype": "postalcode"
  },
  "geometry": {"coordinates":[-4.152542,50.545865],"type":"Point"}
}
