{
  "type": "Feature",
  "properties": {
    "iso:country": "GB",
    "wof:name": "RH10 7WP",
    "wof:placetype": "postalcode"
  },
  "geometry": {"coordinates":[-0.150123,51.110542],"type":"Point"}
}
