{
  "type": "Feature",
  "properties": {
    "date:inception_lower":"1992-01-01",
    "date:inception_upper":"1992-01-31",
    "iso:country":"GB",
    "wof:name":"RH10 7WP",
    "wof:placetype":"postalcode"
},
  "geometry": {"coordinates":[-0.150123,51.110542],"type":"Point"}
}