{
  "type": "Feature",
  "properties": {
    "iso:country":"GB",
    "wof:name":"NN9 6TE",
    "wof:placetype":"postalcode"
},
  "geometry": {"coordinates":[-0.55966967597182,52.33586773621028],"type":"Point"}
}