{
  "type": "Feature",
  "properties": {
    "iso:country": "GB",
    "wof:name": "TA3 7AJ",
    "wof:placetype": "postalcode"
  },
  "geometry": {"coordinates":[-3.094787,50.970103],"type":"Point"}
}
