{
  "type": "Feature",
  "properties": {
    "date:inception_lower": "1980-01-01",
    "date:inception_upper": "1980-01-01",
    "iso:country": "GB",
    "wof:name": "TA3 7AJ",
    "wof:placetype": "postalcode"
  },
  "geometry": {"coordinates":[-3.094787,50.970103],"type":"Point"}
}
