{
  "type": "Feature",
  "properties": {
    "iso:country":"GB",
    "wof:name":"SY23 1HL",
    "wof:placetype":"postalcode"
},
  "geometry": {"coordinates":[-4.07093649040565,52.41023456595475],"type":"Point"}
}