{
  "type": "Feature",
  "properties": {
    "iso:country":"GB",
    "wof:name":"BL3 3HW",
    "wof:placetype":"postalcode"
},
  "geometry": {"coordinates":[-2.43965752349253,53.55811923093665],"type":"Point"}
}