{
  "type": "Feature",
  "properties": {
    "iso:country": "GB",
    "wof:name": "HX2 9EL",
    "wof:placetype": "postalcode"
  },
  "geometry": {"coordinates":[-1.890207,53.754943],"type":"Point"}
}
