{
  "type": "Feature",
  "properties": {
    "iso:country": "GB",
    "wof:name": "HX2 9EL",
    "wof:placetype": "postalcode"
  },
  "geometry": {"coordinates":[-1.89007,53.754934],"type":"Point"}
}
