{
  "type": "Feature",
  "properties": {
    "iso:country": "GB",
    "wof:name": "BN2 5NT",
    "wof:placetype": "postalcode"
  },
  "geometry": {"coordinates":[-0.104291,50.824397],"type":"Point"}
}
