{
  "type": "Feature",
  "properties": {
    "iso:country":"GB",
    "wof:name":"BN2 5NT",
    "wof:placetype":"postalcode"
},
  "geometry": {"coordinates":[-0.10429089137328,50.82439677872806],"type":"Point"}
}