{
  "type": "Feature",
  "properties": {
    "iso:country":"GB",
    "wof:name":"GL1 5JY",
    "wof:placetype":"postalcode"
},
  "geometry": {"coordinates":[-2.2424650748484,51.84904138282442],"type":"Point"}
}