{
  "type": "Feature",
  "properties": {
    "iso:country": "GB",
    "wof:name": "M33 3BW",
    "wof:placetype": "postalcode"
  },
  "geometry": {"coordinates":[-2.316797,53.421407],"type":"Point"}
}
