{
  "type": "Feature",
  "properties": {
    "date:inception_lower": "1980-01-01",
    "date:inception_upper": "1980-01-01",
    "iso:country": "GB",
    "wof:name": "FK2 8HR",
    "wof:placetype": "postalcode"
  },
  "geometry": {"coordinates":[-3.775995,56.029036],"type":"Point"}
}
