{
  "type": "Feature",
  "properties": {
    "iso:country":"GB",
    "wof:name":"CV11 6DB",
    "wof:placetype":"postalcode"
},
  "geometry": {"coordinates":[-1.44460592412419,52.53607021322573],"type":"Point"}
}