{
  "type": "Feature",
  "properties": {
    "iso:country": "GB",
    "wof:name": "CV11 6DB",
    "wof:placetype": "postalcode"
  },
  "geometry": {"coordinates":[-1.444606,52.53607],"type":"Point"}
}
