{
  "type": "Feature",
  "properties": {
    "date:inception_lower": "2019-03-01",
    "date:inception_upper": "2019-03-01",
    "iso:country": "GB",
    "wof:name": "WA4 9TN",
    "wof:placetype": "postalcode"
  },
  "geometry": {"coordinates":[-2.607241,53.389647],"type":"Point"}
}
