{
  "type": "Feature",
  "properties": {
    "date:inception_lower":"1980-01-01",
    "date:inception_upper":"1980-01-31",
    "iso:country":"GB",
    "wof:name":"SP7 0EY",
    "wof:placetype":"postalcode"
},
  "geometry": {"coordinates":[-2.077204,51.000794],"type":"Point"}
}