{
  "type": "Feature",
  "properties": {
    "iso:country": "GB",
    "wof:name": "SP7 0EY",
    "wof:placetype": "postalcode"
  },
  "geometry": {"coordinates":[-2.077204,51.000794],"type":"Point"}
}
