{
  "type": "Feature",
  "properties": {
    "iso:country":"GB",
    "wof:name":"SP7 0EY",
    "wof:placetype":"postalcode"
},
  "geometry": {"coordinates":[-2.07720385062273,51.00079365940145],"type":"Point"}
}