{
  "type": "Feature",
  "properties": {
    "date:inception_lower": "2006-02-01",
    "date:inception_upper": "2006-02-01",
    "iso:country": "GB",
    "wof:name": "HP5 2BQ",
    "wof:placetype": "postalcode"
  },
  "geometry": {"coordinates":[-0.615305,51.721583],"type":"Point"}
}
