{
  "type": "Feature",
  "properties": {
    "iso:country":"GB",
    "wof:name":"HP5 2BQ",
    "wof:placetype":"postalcode"
},
  "geometry": {"coordinates":[-0.61530552988387,51.72158293114409],"type":"Point"}
}