{
  "type": "Feature",
  "properties": {
    "iso:country":"GB",
    "wof:name":"W3 0HN",
    "wof:placetype":"postalcode"
},
  "geometry": {"coordinates":[-0.28570554042827,51.5172860646829],"type":"Point"}
}