{
  "type": "Feature",
  "properties": {
    "iso:country":"GB",
    "wof:name":"RG30 4QE",
    "wof:placetype":"postalcode"
},
  "geometry": {"coordinates":[-1.04179277509032,51.4530374085199],"type":"Point"}
}