{
  "type": "Feature",
  "properties": {
    "iso:country": "GB",
    "wof:name": "RH20 3NX",
    "wof:placetype": "postalcode"
  },
  "geometry": {"coordinates":[-0.439299,50.92545],"type":"Point"}
}
