{
  "type": "Feature",
  "properties": {
    "iso:country":"GB",
    "wof:name":"RH20 3NX",
    "wof:placetype":"postalcode"
},
  "geometry": {"coordinates":[-0.43929901591255,50.92545036202606],"type":"Point"}
}