{
  "type": "Feature",
  "properties": {
    "iso:country":"GB",
    "wof:name":"TQ13 0JP",
    "wof:placetype":"postalcode"
},
  "geometry": {"coordinates":[-3.60976329500553,50.60126057739082],"type":"Point"}
}