{
  "type": "Feature",
  "properties": {
    "date:inception_lower": "1981-06-01",
    "date:inception_upper": "1981-06-01",
    "iso:country": "GB",
    "wof:name": "TQ13 0JP",
    "wof:placetype": "postalcode"
  },
  "geometry": {"coordinates":[-3.609763,50.601261],"type":"Point"}
}
