{
  "type": "Feature",
  "properties": {
    "iso:country": "GB",
    "wof:name": "TQ13 0JP",
    "wof:placetype": "postalcode"
  },
  "geometry": {"coordinates":[-3.609763,50.601261],"type":"Point"}
}
