{
  "type": "Feature",
  "properties": {
    "iso:country":"GB",
    "wof:name":"DL7 9NF",
    "wof:placetype":"postalcode"
},
  "geometry": {"coordinates":[-1.5318668469377,54.27889389201871],"type":"Point"}
}