{
  "type": "Feature",
  "properties": {
    "iso:country": "GB",
    "wof:name": "DL7 9NF",
    "wof:placetype": "postalcode"
  },
  "geometry": {"coordinates":[-1.533806,54.280648],"type":"Point"}
}
