{
  "type": "Feature",
  "properties": {
    "date:inception_lower": "1980-01-01",
    "date:inception_upper": "1980-01-01",
    "iso:country": "GB",
    "wof:name": "DL7 9NF",
    "wof:placetype": "postalcode"
  },
  "geometry": {"coordinates":[-1.533806,54.280648],"type":"Point"}
}
