{
  "type": "Feature",
  "properties": {
    "iso:country":"GB",
    "wof:name":"S11 7GZ",
    "wof:placetype":"postalcode"
},
  "geometry": {"coordinates":[-1.51220809989666,53.36024922424057],"type":"Point"}
}