{
  "type": "Feature",
  "properties": {
    "date:inception_lower": "1980-01-01",
    "date:inception_upper": "1980-01-01",
    "iso:country": "GB",
    "wof:name": "LS25 1HH",
    "wof:placetype": "postalcode"
  },
  "geometry": {"coordinates":[-1.381497,53.792211],"type":"Point"}
}
