{
  "type": "Feature",
  "properties": {
    "iso:country":"GB",
    "wof:name":"LS25 1HH",
    "wof:placetype":"postalcode"
},
  "geometry": {"coordinates":[-1.38129961853106,53.79195996569554],"type":"Point"}
}