{
  "type": "Feature",
  "properties": {
    "iso:country": "GB",
    "wof:name": "BH11 9AT",
    "wof:placetype": "postalcode"
  },
  "geometry": {"coordinates":[-1.908892,50.766071],"type":"Point"}
}
