{
  "type": "Feature",
  "properties": {
    "iso:country":"GB",
    "wof:name":"BD20 5LL",
    "wof:placetype":"postalcode"
},
  "geometry": {"coordinates":[-1.8650798133027,53.87162884544883],"type":"Point"}
}