{
  "type": "Feature",
  "properties": {
    "iso:country":"GB",
    "wof:name":"HP11 2TU",
    "wof:placetype":"postalcode"
},
  "geometry": {"coordinates":[-0.76442428646885,51.6199758888941],"type":"Point"}
}