{
  "type": "Feature",
  "properties": {
    "date:inception_lower":"1985-10-01",
    "date:inception_upper":"1985-10-31",
    "iso:country":"GB",
    "wof:name":"HP11 2TU",
    "wof:placetype":"postalcode"
},
  "geometry": {"coordinates":[-0.764424,51.619976],"type":"Point"}
}