{
  "type": "Feature",
  "properties": {
    "date:inception_lower": "1990-02-01",
    "date:inception_upper": "1990-02-01",
    "iso:country": "GB",
    "wof:name": "CA3 0DB",
    "wof:placetype": "postalcode"
  },
  "geometry": {"coordinates":[-2.942771,54.922308],"type":"Point"}
}
