{
  "type": "Feature",
  "properties": {
    "iso:country":"GB",
    "wof:name":"CA3 0DB",
    "wof:placetype":"postalcode"
},
  "geometry": {"coordinates":[-2.9427711543212,54.92230838794641],"type":"Point"}
}