{
  "type": "Feature",
  "properties": {
    "iso:country":"GB",
    "wof:name":"NE71 6EA",
    "wof:placetype":"postalcode"
},
  "geometry": {"coordinates":[-2.01843750676156,55.54915739698066],"type":"Point"}
}