{
  "type": "Feature",
  "properties": {
    "iso:country":"GB",
    "wof:name":"CF62 6NX",
    "wof:placetype":"postalcode"
},
  "geometry": {"coordinates":[-3.2952750566184,51.396730528892],"type":"Point"}
}