{
  "type": "Feature",
  "properties": {
    "iso:country": "GB",
    "wof:name": "CF62 6NX",
    "wof:placetype": "postalcode"
  },
  "geometry": {"coordinates":[-3.295275,51.396731],"type":"Point"}
}
