{
  "type": "Feature",
  "properties": {
    "iso:country":"GB",
    "wof:name":"SO30 2NE",
    "wof:placetype":"postalcode"
},
  "geometry": {"coordinates":[-1.30185816857373,50.93532053812445],"type":"Point"}
}