{
  "type": "Feature",
  "properties": {
    "date:inception_lower":"1997-06-01",
    "date:inception_upper":"1997-06-30",
    "iso:country":"GB",
    "wof:name":"SO30 2NE",
    "wof:placetype":"postalcode"
},
  "geometry": {"coordinates":[-1.301861,50.935321],"type":"Point"}
}