{
  "type": "Feature",
  "properties": {
    "iso:country":"GB",
    "wof:name":"RG10 9SP",
    "wof:placetype":"postalcode"
},
  "geometry": {"coordinates":[-0.84331932829635,51.49495744077751],"type":"Point"}
}