{
  "type": "Feature",
  "properties": {
    "iso:country": "GB",
    "wof:name": "RG10 9SP",
    "wof:placetype": "postalcode"
  },
  "geometry": {"coordinates":[-0.843431,51.494925],"type":"Point"}
}
