{
  "type": "Feature",
  "properties": {
    "iso:country":"GB",
    "wof:name":"RH6 9AN",
    "wof:placetype":"postalcode"
},
  "geometry": {"coordinates":[-0.15465890079745,51.17595720096638],"type":"Point"}
}