{
  "type": "Feature",
  "properties": {
    "iso:country":"GB",
    "wof:name":"LN6 8AE",
    "wof:placetype":"postalcode"
},
  "geometry": {"coordinates":[-0.56424223112797,53.19943003831333],"type":"Point"}
}