{
  "type": "Feature",
  "properties": {
    "iso:country":"GB",
    "wof:name":"LA3 1JJ",
    "wof:placetype":"postalcode"
},
  "geometry": {"coordinates":[-2.88322897472258,54.05661730264918],"type":"Point"}
}