{
  "type": "Feature",
  "properties": {
    "iso:country": "GB",
    "wof:name": "LA3 1JJ",
    "wof:placetype": "postalcode"
  },
  "geometry": {"coordinates":[-2.883229,54.056617],"type":"Point"}
}
