{
  "type": "Feature",
  "properties": {
    "date:inception_lower": "1980-01-01",
    "date:inception_upper": "1980-01-01",
    "iso:country": "GB",
    "wof:name": "LA3 1JJ",
    "wof:placetype": "postalcode"
  },
  "geometry": {"coordinates":[-2.883229,54.056617],"type":"Point"}
}
