{
  "type": "Feature",
  "properties": {
    "date:inception_lower": "1995-12-01",
    "date:inception_upper": "1995-12-01",
    "iso:country": "GB",
    "wof:name": "FY8 3AZ",
    "wof:placetype": "postalcode"
  },
  "geometry": {"coordinates":[-3.013934,53.767559],"type":"Point"}
}
