{
  "type": "Feature",
  "properties": {
    "iso:country":"GB",
    "wof:name":"GL51 8BJ",
    "wof:placetype":"postalcode"
},
  "geometry": {"coordinates":[-2.1007528043171,51.90355337722989],"type":"Point"}
}