{
  "type": "Feature",
  "properties": {
    "iso:country":"GB",
    "wof:name":"AB10 6QL",
    "wof:placetype":"postalcode"
},
  "geometry": {"coordinates":[-2.11699952021632,57.14004872789914],"type":"Point"}
}