{
  "type": "Feature",
  "properties": {
    "iso:country": "GB",
    "wof:name": "LS19 6BT",
    "wof:placetype": "postalcode"
  },
  "geometry": {"coordinates":[-1.692113,53.853092],"type":"Point"}
}
