{
  "type": "Feature",
  "properties": {
    "iso:country":"GB",
    "wof:name":"NE34 9JW",
    "wof:placetype":"postalcode"
},
  "geometry": {"coordinates":[-1.4476171360752,54.96475593379039],"type":"Point"}
}