{
  "type": "Feature",
  "properties": {
    "date:inception_lower": "1980-01-01",
    "date:inception_upper": "1980-01-01",
    "iso:country": "GB",
    "wof:name": "NG7 5FU",
    "wof:placetype": "postalcode"
  },
  "geometry": {"coordinates":[-1.169911,52.964985],"type":"Point"}
}
