{
  "type": "Feature",
  "properties": {
    "date:inception_lower": "1980-01-01",
    "date:inception_upper": "1980-01-01",
    "iso:country": "GB",
    "wof:name": "L1 6BD",
    "wof:placetype": "postalcode"
  },
  "geometry": {"coordinates":[-2.98732,53.407174],"type":"Point"}
}
