{
  "type": "Feature",
  "properties": {
    "iso:country":"GB",
    "wof:name":"NW6 4BE",
    "wof:placetype":"postalcode"
},
  "geometry": {"coordinates":[-0.17991507074919,51.54145556627489],"type":"Point"}
}