{
  "type": "Feature",
  "properties": {
    "date:inception_lower": "1993-08-01",
    "date:inception_upper": "1993-08-01",
    "iso:country": "GB",
    "wof:name": "NW6 4BE",
    "wof:placetype": "postalcode"
  },
  "geometry": {"coordinates":[-0.179915,51.541456],"type":"Point"}
}
