{
  "type": "Feature",
  "properties": {
    "iso:country": "GB",
    "wof:name": "SG12 8TH",
    "wof:placetype": "postalcode"
  },
  "geometry": {"coordinates":[0.067334,51.824383],"type":"Point"}
}
