{
  "type": "Feature",
  "properties": {
    "iso:country":"GB",
    "wof:name":"SG12 8TH",
    "wof:placetype":"postalcode"
},
  "geometry": {"coordinates":[0.06733421678256,51.82438252193044],"type":"Point"}
}