{
  "type": "Feature",
  "properties": {
    "iso:country": "GB",
    "wof:name": "LE10 0UT",
    "wof:placetype": "postalcode"
  },
  "geometry": {"coordinates":[-1.391598,52.54079],"type":"Point"}
}
