{
  "type": "Feature",
  "properties": {
    "date:inception_lower": "2020-01-01",
    "date:inception_upper": "2020-01-01",
    "iso:country": "GB",
    "wof:name": "M28 3ZT",
    "wof:placetype": "postalcode"
  },
  "geometry": {"coordinates":[-2.396448,53.536849],"type":"Point"}
}
