{
  "type": "Feature",
  "properties": {
    "iso:country": "GB",
    "wof:name": "M28 3ZT",
    "wof:placetype": "postalcode"
  },
  "geometry": {"coordinates":[-2.397234,53.537008],"type":"Point"}
}
