{
  "type": "Feature",
  "properties": {
    "date:inception_lower": "2007-02-01",
    "date:inception_upper": "2007-02-01",
    "iso:country": "GB",
    "wof:name": "BA9 9FE",
    "wof:placetype": "postalcode"
  },
  "geometry": {"coordinates":[-2.412985,51.05355],"type":"Point"}
}
