{
  "type": "Feature",
  "properties": {
    "iso:country": "GB",
    "wof:name": "OX15 6PG",
    "wof:placetype": "postalcode"
  },
  "geometry": {"coordinates":[-1.438797,52.057891],"type":"Point"}
}
