{
  "type": "Feature",
  "properties": {
    "iso:country": "GB",
    "wof:name": "HU4 6BS",
    "wof:placetype": "postalcode"
  },
  "geometry": {"coordinates":[-0.395633,53.745451],"type":"Point"}
}
