{
  "type": "Feature",
  "properties": {
    "date:inception_lower":"1996-12-01",
    "date:inception_upper":"1996-12-31",
    "iso:country":"GB",
    "wof:name":"SK22 4HQ",
    "wof:placetype":"postalcode"
},
  "geometry": {"coordinates":[-1.989425,53.37257],"type":"Point"}
}