{
  "type": "Feature",
  "properties": {
    "iso:country": "GB",
    "wof:name": "SK22 4HQ",
    "wof:placetype": "postalcode"
  },
  "geometry": {"coordinates":[-1.989425,53.37257],"type":"Point"}
}
