{
  "type": "Feature",
  "properties": {
    "date:inception_lower": "2009-03-01",
    "date:inception_upper": "2009-03-01",
    "iso:country": "GB",
    "wof:name": "DE56 0AB",
    "wof:placetype": "postalcode"
  },
  "geometry": {"coordinates":[-1.42905,53.007781],"type":"Point"}
}
