{
  "type": "Feature",
  "properties": {
    "iso:country": "GB",
    "wof:name": "DE56 0AB",
    "wof:placetype": "postalcode"
  },
  "geometry": {"coordinates":[-1.42905,53.007781],"type":"Point"}
}
