{
  "type": "Feature",
  "properties": {
    "iso:country":"GB",
    "wof:name":"TW1 1QQ",
    "wof:placetype":"postalcode"
},
  "geometry": {"coordinates":[-0.32192347012652,51.45770494560256],"type":"Point"}
}