{
  "type": "Feature",
  "properties": {
    "date:inception_lower": "1980-01-01",
    "date:inception_upper": "1980-01-01",
    "iso:country": "GB",
    "wof:name": "TW1 1QQ",
    "wof:placetype": "postalcode"
  },
  "geometry": {"coordinates":[-0.321597,51.457754],"type":"Point"}
}
