{
  "type": "Feature",
  "properties": {
    "iso:country": "GB",
    "wof:name": "DT11 0AQ",
    "wof:placetype": "postalcode"
  },
  "geometry": {"coordinates":[-2.232915,50.802466],"type":"Point"}
}
