{
  "type": "Feature",
  "properties": {
    "iso:country":"GB",
    "wof:name":"DT11 0AQ",
    "wof:placetype":"postalcode"
},
  "geometry": {"coordinates":[-2.23291540323514,50.80246599814397],"type":"Point"}
}