{
  "type": "Feature",
  "properties": {
    "date:inception_lower": "2023-02-01",
    "date:inception_upper": "2023-02-01",
    "iso:country": "GB",
    "wof:name": "DE6 2HU",
    "wof:placetype": "postalcode"
  },
  "geometry": {"coordinates":[-1.798742,53.099096],"type":"Point"}
}
