{
  "type": "Feature",
  "properties": {
    "iso:country": "GB",
    "wof:name": "S3 9DB",
    "wof:placetype": "postalcode"
  },
  "geometry": {"coordinates":[-1.461907,53.39437],"type":"Point"}
}
