{
  "type": "Feature",
  "properties": {
    "iso:country":"GB",
    "wof:name":"BD3 7EH",
    "wof:placetype":"postalcode"
},
  "geometry": {"coordinates":[-1.71515038768609,53.80055110263395],"type":"Point"}
}