{
  "type": "Feature",
  "properties": {
    "date:inception_lower": "1993-01-01",
    "date:inception_upper": "1993-01-01",
    "iso:country": "GB",
    "wof:name": "KT22 9BZ",
    "wof:placetype": "postalcode"
  },
  "geometry": {"coordinates":[-0.359284,51.283438],"type":"Point"}
}
