{
  "type": "Feature",
  "properties": {
    "iso:country": "GB",
    "wof:name": "PE29 3BU",
    "wof:placetype": "postalcode"
  },
  "geometry": {"coordinates":[-0.187616,52.332014],"type":"Point"}
}
