{
  "type": "Feature",
  "properties": {
    "iso:country":"GB",
    "wof:name":"PE29 3BU",
    "wof:placetype":"postalcode"
},
  "geometry": {"coordinates":[-0.18761581325968,52.33201375552652],"type":"Point"}
}