{
  "type": "Feature",
  "properties": {
    "iso:country":"GB",
    "wof:name":"TR19 7PD",
    "wof:placetype":"postalcode"
},
  "geometry": {"coordinates":[-5.69145536229104,50.10963341800844],"type":"Point"}
}