{
  "type": "Feature",
  "properties": {
    "iso:country":"GB",
    "wof:name":"TW18 1LY",
    "wof:placetype":"postalcode"
},
  "geometry": {"coordinates":[-0.48533891190552,51.42335837554519],"type":"Point"}
}