{
  "type": "Feature",
  "properties": {
    "iso:country": "GB",
    "wof:name": "TW18 1LY",
    "wof:placetype": "postalcode"
  },
  "geometry": {"coordinates":[-0.485339,51.423358],"type":"Point"}
}
