{
  "type": "Feature",
  "properties": {
    "iso:country": "GB",
    "wof:name": "G83 7AE",
    "wof:placetype": "postalcode"
  },
  "geometry": {"coordinates":[-4.748143,56.194168],"type":"Point"}
}
