{
  "type": "Feature",
  "properties": {
    "iso:country":"GB",
    "wof:name":"G83 7AE",
    "wof:placetype":"postalcode"
},
  "geometry": {"coordinates":[-4.74814330034602,56.19416771355757],"type":"Point"}
}