{
  "type": "Feature",
  "properties": {
    "iso:country": "GB",
    "wof:name": "AL6 0TR",
    "wof:placetype": "postalcode"
  },
  "geometry": {"coordinates":[-0.185573,51.848861],"type":"Point"}
}
