{
  "type": "Feature",
  "properties": {
    "iso:country":"GB",
    "wof:name":"SK6 4HL",
    "wof:placetype":"postalcode"
},
  "geometry": {"coordinates":[-2.06901256162402,53.41180348787427],"type":"Point"}
}