{
  "type": "Feature",
  "properties": {
    "date:inception_lower":"1985-10-01",
    "date:inception_upper":"1985-10-31",
    "iso:country":"GB",
    "wof:name":"SK6 4HL",
    "wof:placetype":"postalcode"
},
  "geometry": {"coordinates":[-2.069013,53.411803],"type":"Point"}
}