{
  "type": "Feature",
  "properties": {
    "date:inception_lower":"1983-01-01",
    "date:inception_upper":"1983-01-31",
    "iso:country":"GB",
    "wof:name":"WD7 8JT",
    "wof:placetype":"postalcode"
},
  "geometry": {"coordinates":[-0.321885,51.682132],"type":"Point"}
}