{
  "type": "Feature",
  "properties": {
    "iso:country":"GB",
    "wof:name":"WD7 8JT",
    "wof:placetype":"postalcode"
},
  "geometry": {"coordinates":[-0.3218846342963,51.68213244233261],"type":"Point"}
}