{
  "type": "Feature",
  "properties": {
    "iso:country": "GB",
    "wof:name": "WD7 8JT",
    "wof:placetype": "postalcode"
  },
  "geometry": {"coordinates":[-0.321885,51.682132],"type":"Point"}
}
