{
  "type": "Feature",
  "properties": {
    "iso:country":"GB",
    "wof:name":"NG12 4AR",
    "wof:placetype":"postalcode"
},
  "geometry": {"coordinates":[-1.11654829403126,52.91022232996229],"type":"Point"}
}