{
  "type": "Feature",
  "properties": {
    "date:inception_lower": "1980-01-01",
    "date:inception_upper": "1980-01-01",
    "iso:country": "GB",
    "wof:name": "NG12 4AR",
    "wof:placetype": "postalcode"
  },
  "geometry": {"coordinates":[-1.116548,52.910222],"type":"Point"}
}
