{
  "type": "Feature",
  "properties": {
    "date:inception_lower": "2020-04-01",
    "date:inception_upper": "2020-04-01",
    "iso:country": "GB",
    "wof:name": "SY11 4FL",
    "wof:placetype": "postalcode"
  },
  "geometry": {"coordinates":[-2.999527,52.871223],"type":"Point"}
}
