{
  "type": "Feature",
  "properties": {
    "iso:country":"GB",
    "wof:name":"NR2 2AE",
    "wof:placetype":"postalcode"
},
  "geometry": {"coordinates":[1.27236145284969,52.62013222464128],"type":"Point"}
}