{
  "type": "Feature",
  "properties": {
    "iso:country":"GB",
    "wof:name":"S61 1ER",
    "wof:placetype":"postalcode"
},
  "geometry": {"coordinates":[-1.39126114165057,53.43321258219506],"type":"Point"}
}