{
  "type": "Feature",
  "properties": {
    "date:inception_lower": "2020-12-01",
    "date:inception_upper": "2020-12-01",
    "iso:country": "GB",
    "wof:name": "WN6 7GB",
    "wof:placetype": "postalcode"
  },
  "geometry": {"coordinates":[-2.641774,53.546991],"type":"Point"}
}
