{
  "type": "Feature",
  "properties": {
    "iso:country":"GB",
    "wof:name":"CF37 5YL",
    "wof:placetype":"postalcode"
},
  "geometry": {"coordinates":[-3.28276729365083,51.56548606327637],"type":"Point"}
}