{
  "type": "Feature",
  "properties": {
    "date:inception_lower": "1980-01-01",
    "date:inception_upper": "1980-01-01",
    "iso:country": "GB",
    "wof:name": "PE3 8JQ",
    "wof:placetype": "postalcode"
  },
  "geometry": {"coordinates":[-0.287293,52.601838],"type":"Point"}
}
