{
  "type": "Feature",
  "properties": {
    "iso:country":"GB",
    "wof:name":"LS20 8PG",
    "wof:placetype":"postalcode"
},
  "geometry": {"coordinates":[-1.76612479150025,53.87047939195479],"type":"Point"}
}