{
  "type": "Feature",
  "properties": {
    "iso:country": "GB",
    "wof:name": "LS20 8PG",
    "wof:placetype": "postalcode"
  },
  "geometry": {"coordinates":[-1.763978,53.871425],"type":"Point"}
}
