{
  "type": "Feature",
  "properties": {
    "iso:country":"GB",
    "wof:name":"CA14 4RB",
    "wof:placetype":"postalcode"
},
  "geometry": {"coordinates":[-3.49837253601187,54.59207906635599],"type":"Point"}
}