{
  "type": "Feature",
  "properties": {
    "date:inception_lower": "1980-01-01",
    "date:inception_upper": "1980-01-01",
    "iso:country": "GB",
    "wof:name": "CA14 4RB",
    "wof:placetype": "postalcode"
  },
  "geometry": {"coordinates":[-3.498372,54.592079],"type":"Point"}
}
