{
  "type": "Feature",
  "properties": {
    "date:inception_lower": "2016-12-01",
    "date:inception_upper": "2016-12-01",
    "iso:country": "GB",
    "wof:name": "TQ13 9GF",
    "wof:placetype": "postalcode"
  },
  "geometry": {"coordinates":[-3.657975,50.590258],"type":"Point"}
}
