{
  "type": "Feature",
  "properties": {
    "iso:country":"GB",
    "wof:name":"BS4 1RX",
    "wof:placetype":"postalcode"
},
  "geometry": {"coordinates":[-2.59182975544022,51.42429055918933],"type":"Point"}
}