{
  "type": "Feature",
  "properties": {
    "iso:country": "GB",
    "wof:name": "HU13 0BX",
    "wof:placetype": "postalcode"
  },
  "geometry": {"coordinates":[-0.437602,53.72051],"type":"Point"}
}
