{
  "type": "Feature",
  "properties": {
    "iso:country": "GB",
    "wof:name": "ML6 7QS",
    "wof:placetype": "postalcode"
  },
  "geometry": {"coordinates":[-3.887384,55.891739],"type":"Point"}
}
