{
  "type": "Feature",
  "properties": {
    "iso:country":"GB",
    "wof:name":"ML6 7QS",
    "wof:placetype":"postalcode"
},
  "geometry": {"coordinates":[-3.88738371090141,55.89173889228451],"type":"Point"}
}