{
  "type": "Feature",
  "properties": {
    "iso:country":"GB",
    "wof:name":"BL0 0BN",
    "wof:placetype":"postalcode"
},
  "geometry": {"coordinates":[-2.30928474112038,53.64839256109858],"type":"Point"}
}