{
  "type": "Feature",
  "properties": {
    "iso:country": "GB",
    "wof:name": "BL0 0BN",
    "wof:placetype": "postalcode"
  },
  "geometry": {"coordinates":[-2.309283,53.648409],"type":"Point"}
}
