{
  "type": "Feature",
  "properties": {
    "date:inception_lower": "2004-02-01",
    "date:inception_upper": "2004-02-01",
    "iso:country": "GB",
    "wof:name": "BL0 0BN",
    "wof:placetype": "postalcode"
  },
  "geometry": {"coordinates":[-2.309661,53.648399],"type":"Point"}
}
