{
  "type": "Feature",
  "properties": {
    "date:inception_lower": "1980-01-01",
    "date:inception_upper": "1980-01-01",
    "iso:country": "GB",
    "wof:name": "CR0 2SN",
    "wof:placetype": "postalcode"
  },
  "geometry": {"coordinates":[-0.106653,51.38503],"type":"Point"}
}
