{
  "type": "Feature",
  "properties": {
    "iso:country":"GB",
    "wof:name":"CR0 2SN",
    "wof:placetype":"postalcode"
},
  "geometry": {"coordinates":[-0.10665269926753,51.38502956605311],"type":"Point"}
}