{
  "type": "Feature",
  "properties": {
    "date:inception_lower": "1980-01-01",
    "date:inception_upper": "1980-01-01",
    "iso:country": "GB",
    "wof:name": "OX13 6SL",
    "wof:placetype": "postalcode"
  },
  "geometry": {"coordinates":[-1.33146,51.62103],"type":"Point"}
}
