{
  "type": "Feature",
  "properties": {
    "iso:country":"GB",
    "wof:name":"OX13 6SL",
    "wof:placetype":"postalcode"
},
  "geometry": {"coordinates":[-1.33145962689082,51.62103010684013],"type":"Point"}
}