{
  "type": "Feature",
  "properties": {
    "iso:country": "GB",
    "wof:name": "SG9 9DP",
    "wof:placetype": "postalcode"
  },
  "geometry": {"coordinates":[-0.022903,51.944469],"type":"Point"}
}
