{
  "type": "Feature",
  "properties": {
    "iso:country": "GB",
    "wof:name": "PO11 0AN",
    "wof:placetype": "postalcode"
  },
  "geometry": {"coordinates":[-0.991924,50.785909],"type":"Point"}
}
