{
  "type": "Feature",
  "properties": {
    "iso:country":"GB",
    "wof:name":"PO11 0AN",
    "wof:placetype":"postalcode"
},
  "geometry": {"coordinates":[-0.99192411699302,50.78590884506556],"type":"Point"}
}