{
  "type": "Feature",
  "properties": {
    "iso:country":"GB",
    "wof:name":"LL22 8UT",
    "wof:placetype":"postalcode"
},
  "geometry": {"coordinates":[-3.68060883166012,53.13871161873607],"type":"Point"}
}