{
  "type": "Feature",
  "properties": {
    "date:inception_lower": "1980-01-01",
    "date:inception_upper": "1980-01-01",
    "iso:country": "GB",
    "wof:name": "LL22 8UT",
    "wof:placetype": "postalcode"
  },
  "geometry": {"coordinates":[-3.680627,53.138736],"type":"Point"}
}
