{
  "type": "Feature",
  "properties": {
    "iso:country":"GB",
    "wof:name":"LL20 7RS",
    "wof:placetype":"postalcode"
},
  "geometry": {"coordinates":[-3.09344540120836,52.9612133597062],"type":"Point"}
}