{
  "type": "Feature",
  "properties": {
    "iso:country":"GB",
    "wof:name":"EN11 8BX",
    "wof:placetype":"postalcode"
},
  "geometry": {"coordinates":[-0.01017739413184,51.75573278704224],"type":"Point"}
}