{
  "type": "Feature",
  "properties": {
    "iso:country":"GB",
    "wof:name":"N18 2SZ",
    "wof:placetype":"postalcode"
},
  "geometry": {"coordinates":[-0.0667772510896,51.60994015376573],"type":"Point"}
}