{
  "type": "Feature",
  "properties": {
    "iso:country":"GB",
    "wof:name":"WD5 0HP",
    "wof:placetype":"postalcode"
},
  "geometry": {"coordinates":[-0.41878891603383,51.7036727788151],"type":"Point"}
}