{
  "type": "Feature",
  "properties": {
    "date:inception_lower":"2013-04-01",
    "date:inception_upper":"2013-04-30",
    "iso:country":"GB",
    "wof:name":"EX4 1GA",
    "wof:placetype":"postalcode"
},
  "geometry": {"coordinates":[-3.540448,50.717925],"type":"Point"}
}