{
  "type": "Feature",
  "properties": {
    "date:inception_lower":"2013-04-01",
    "date:inception_upper":"2013-04-30",
    "iso:country":"GB",
    "wof:name":"EX23 0NF",
    "wof:placetype":"postalcode"
},
  "geometry": {"coordinates":[-4.620327,50.740577],"type":"Point"}
}