{
  "type": "Feature",
  "properties": {
    "iso:country": "GB",
    "wof:name": "EX23 0NF",
    "wof:placetype": "postalcode"
  },
  "geometry": {"coordinates":[-4.620327,50.740577],"type":"Point"}
}
