{
  "type": "Feature",
  "properties": {
    "iso:country":"GB",
    "wof:name":"EX23 0NF",
    "wof:placetype":"postalcode"
},
  "geometry": {"coordinates":[-4.62032687195398,50.74057730005093],"type":"Point"}
}