{
  "type": "Feature",
  "properties": {
    "iso:country":"GB",
    "wof:name":"YO43 3EJ",
    "wof:placetype":"postalcode"
},
  "geometry": {"coordinates":[-0.67253073885872,53.86264918679124],"type":"Point"}
}