{
  "type": "Feature",
  "properties": {
    "date:inception_lower": "1998-06-01",
    "date:inception_upper": "1998-06-01",
    "iso:country": "GB",
    "wof:name": "YO43 3EJ",
    "wof:placetype": "postalcode"
  },
  "geometry": {"coordinates":[-0.672531,53.862649],"type":"Point"}
}
