{
  "type": "Feature",
  "properties": {
    "iso:country": "GB",
    "wof:name": "TN34 3BA",
    "wof:placetype": "postalcode"
  },
  "geometry": {"coordinates":[0.59272,50.856974],"type":"Point"}
}
