{
  "type": "Feature",
  "properties": {
    "iso:country":"GB",
    "wof:name":"TN34 3BA",
    "wof:placetype":"postalcode"
},
  "geometry": {"coordinates":[0.59271998208256,50.85697351127435],"type":"Point"}
}