{
  "type": "Feature",
  "properties": {
    "iso:country":"GB",
    "wof:name":"SG2 7ET",
    "wof:placetype":"postalcode"
},
  "geometry": {"coordinates":[-0.15136596934045,51.88853133091795],"type":"Point"}
}