{
  "type": "Feature",
  "properties": {
    "date:inception_lower":"1980-01-01",
    "date:inception_upper":"1980-01-31",
    "iso:country":"GB",
    "wof:name":"SG2 7ET",
    "wof:placetype":"postalcode"
},
  "geometry": {"coordinates":[-0.151366,51.888531],"type":"Point"}
}