{
  "type": "Feature",
  "properties": {
    "date:inception_lower": "2007-04-01",
    "date:inception_upper": "2007-04-01",
    "iso:country": "GB",
    "wof:name": "AB31 4GL",
    "wof:placetype": "postalcode"
  },
  "geometry": {"coordinates":[-2.62616,57.103631],"type":"Point"}
}
