{
  "type": "Feature",
  "properties": {
    "iso:country":"GB",
    "wof:name":"AB31 4GL",
    "wof:placetype":"postalcode"
},
  "geometry": {"coordinates":[-2.62616049311761,57.10363067454229],"type":"Point"}
}