{
  "type": "Feature",
  "properties": {
    "iso:country":"GB",
    "wof:name":"BN6 9EY",
    "wof:placetype":"postalcode"
},
  "geometry": {"coordinates":[-0.1894352479379,50.93750037101499],"type":"Point"}
}