{
  "type": "Feature",
  "properties": {
    "iso:country":"GB",
    "wof:name":"DL2 2RN",
    "wof:placetype":"postalcode"
},
  "geometry": {"coordinates":[-1.65980712097559,54.51465871863909],"type":"Point"}
}