{
  "type": "Feature",
  "properties": {
    "date:inception_lower": "2019-07-01",
    "date:inception_upper": "2019-07-01",
    "iso:country": "GB",
    "wof:name": "PL31 2TD",
    "wof:placetype": "postalcode"
  },
  "geometry": {"coordinates":[-4.748233,50.470618],"type":"Point"}
}
