{
  "type": "Feature",
  "properties": {
    "iso:country": "GB",
    "wof:name": "PL31 2TD",
    "wof:placetype": "postalcode"
  },
  "geometry": {"coordinates":[-4.748233,50.470618],"type":"Point"}
}
