{
  "type": "Feature",
  "properties": {
    "iso:country":"GB",
    "wof:name":"SY7 0NQ",
    "wof:placetype":"postalcode"
},
  "geometry": {"coordinates":[-2.88706908857513,52.33526153269576],"type":"Point"}
}