{
  "type": "Feature",
  "properties": {
    "date:inception_lower":"1980-01-01",
    "date:inception_upper":"1980-01-31",
    "iso:country":"GB",
    "wof:name":"SY7 0NQ",
    "wof:placetype":"postalcode"
},
  "geometry": {"coordinates":[-2.887069,52.335262],"type":"Point"}
}