{
  "type": "Feature",
  "properties": {
    "date:inception_lower": "1980-01-01",
    "date:inception_upper": "1980-01-01",
    "iso:country": "GB",
    "wof:name": "SY7 0NQ",
    "wof:placetype": "postalcode"
  },
  "geometry": {"coordinates":[-2.887083,52.335265],"type":"Point"}
}
