{
  "type": "Feature",
  "properties": {
    "iso:country":"GB",
    "wof:name":"SO50 5DZ",
    "wof:placetype":"postalcode"
},
  "geometry": {"coordinates":[-1.36472862603622,50.96374469880126],"type":"Point"}
}