{
  "type": "Feature",
  "properties": {
    "iso:country":"GB",
    "wof:name":"LD3 0EN",
    "wof:placetype":"postalcode"
},
  "geometry": {"coordinates":[-3.20968980333992,51.96703236426909],"type":"Point"}
}