{
  "type": "Feature",
  "properties": {
    "date:inception_lower": "1980-01-01",
    "date:inception_upper": "1980-01-01",
    "iso:country": "GB",
    "wof:name": "LD3 0EN",
    "wof:placetype": "postalcode"
  },
  "geometry": {"coordinates":[-3.20969,51.967032],"type":"Point"}
}
