{
  "type": "Feature",
  "properties": {
    "date:inception_lower": "2020-11-01",
    "date:inception_upper": "2020-11-01",
    "iso:country": "GB",
    "wof:name": "CW2 8GP",
    "wof:placetype": "postalcode"
  },
  "geometry": {"coordinates":[-2.474775,53.08548],"type":"Point"}
}
