{
  "type": "Feature",
  "properties": {
    "iso:country":"GB",
    "wof:name":"PO20 1PN",
    "wof:placetype":"postalcode"
},
  "geometry": {"coordinates":[-0.75114421157795,50.81407507592219],"type":"Point"}
}