{
  "type": "Feature",
  "properties": {
    "iso:country": "GB",
    "wof:name": "PO20 1PN",
    "wof:placetype": "postalcode"
  },
  "geometry": {"coordinates":[-0.751144,50.814075],"type":"Point"}
}
