{
  "type": "Feature",
  "properties": {
    "date:inception_lower": "2023-06-01",
    "date:inception_upper": "2023-06-01",
    "iso:country": "GB",
    "wof:name": "ME8 1FS",
    "wof:placetype": "postalcode"
  },
  "geometry": {"coordinates":[0.575541,51.36618],"type":"Point"}
}
