{
  "type": "Feature",
  "properties": {
    "iso:country":"GB",
    "wof:name":"TN24 8BF",
    "wof:placetype":"postalcode"
},
  "geometry": {"coordinates":[0.862864839433,51.15792777757669],"type":"Point"}
}