{
  "type": "Feature",
  "properties": {
    "date:inception_lower": "1980-01-01",
    "date:inception_upper": "1980-01-01",
    "iso:country": "GB",
    "wof:name": "SM2 7JX",
    "wof:placetype": "postalcode"
  },
  "geometry": {"coordinates":[-0.232418,51.346249],"type":"Point"}
}
