{
  "type": "Feature",
  "properties": {
    "iso:country":"GB",
    "wof:name":"SM2 7JX",
    "wof:placetype":"postalcode"
},
  "geometry": {"coordinates":[-0.23241810478628,51.34624881539607],"type":"Point"}
}