{
  "type": "Feature",
  "properties": {
    "iso:country":"GB",
    "wof:name":"DN6 7BD",
    "wof:placetype":"postalcode"
},
  "geometry": {"coordinates":[-1.17323428748705,53.57666553663756],"type":"Point"}
}