{
  "type": "Feature",
  "properties": {
    "iso:country":"GB",
    "wof:name":"EX36 4HT",
    "wof:placetype":"postalcode"
},
  "geometry": {"coordinates":[-3.89515232862305,50.99703409734791],"type":"Point"}
}