{
  "type": "Feature",
  "properties": {
    "iso:country": "GB",
    "wof:name": "EX36 4HT",
    "wof:placetype": "postalcode"
  },
  "geometry": {"coordinates":[-3.895152,50.997034],"type":"Point"}
}
