{
  "type": "Feature",
  "properties": {
    "date:inception_lower": "1980-01-01",
    "date:inception_upper": "1980-01-01",
    "iso:country": "GB",
    "wof:name": "WV15 6HX",
    "wof:placetype": "postalcode"
  },
  "geometry": {"coordinates":[-2.336789,52.44194],"type":"Point"}
}
