{
  "type": "Feature",
  "properties": {
    "iso:country":"GB",
    "wof:name":"WV15 6HX",
    "wof:placetype":"postalcode"
},
  "geometry": {"coordinates":[-2.3367889016689,52.44193980510205],"type":"Point"}
}