{
  "type": "Feature",
  "properties": {
    "iso:country":"GB",
    "wof:name":"IG3 9DJ",
    "wof:placetype":"postalcode"
},
  "geometry": {"coordinates":[0.09996836687901,51.55205785102159],"type":"Point"}
}