{
  "type": "Feature",
  "properties": {
    "date:inception_lower": "2020-09-01",
    "date:inception_upper": "2020-09-01",
    "iso:country": "GB",
    "wof:name": "CH7 6FY",
    "wof:placetype": "postalcode"
  },
  "geometry": {"coordinates":[-3.106986,53.175081],"type":"Point"}
}
