{
  "type": "Feature",
  "properties": {
    "iso:country":"GB",
    "wof:name":"CV32 5RH",
    "wof:placetype":"postalcode"
},
  "geometry": {"coordinates":[-1.53603735293192,52.29541129267564],"type":"Point"}
}