{
  "type": "Feature",
  "properties": {
    "date:inception_lower": "1980-01-01",
    "date:inception_upper": "1980-01-01",
    "iso:country": "GB",
    "wof:name": "WA16 9AX",
    "wof:placetype": "postalcode"
  },
  "geometry": {"coordinates":[-2.369409,53.291909],"type":"Point"}
}
