{
  "type": "Feature",
  "properties": {
    "iso:country":"GB",
    "wof:name":"BR2 0XT",
    "wof:placetype":"postalcode"
},
  "geometry": {"coordinates":[0.01040619456306,51.39781867101808],"type":"Point"}
}