{
  "type": "Feature",
  "properties": {
    "date:inception_lower":"1980-01-01",
    "date:inception_upper":"1980-01-31",
    "iso:country":"GB",
    "wof:name":"FK10 2HT",
    "wof:placetype":"postalcode"
},
  "geometry": {"coordinates":[-3.806076,56.126693],"type":"Point"}
}