{
  "type": "Feature",
  "properties": {
    "iso:country":"GB",
    "wof:name":"BH1 3ER",
    "wof:placetype":"postalcode"
},
  "geometry": {"coordinates":[-1.85668980955284,50.72014907391107],"type":"Point"}
}