{
  "type": "Feature",
  "properties": {
    "iso:country":"GB",
    "wof:name":"SP3 4NR",
    "wof:placetype":"postalcode"
},
  "geometry": {"coordinates":[-1.93288879119463,51.12616863510589],"type":"Point"}
}