{
  "type": "Feature",
  "properties": {
    "date:inception_lower":"1980-01-01",
    "date:inception_upper":"1980-01-31",
    "iso:country":"GB",
    "wof:name":"SP3 4NR",
    "wof:placetype":"postalcode"
},
  "geometry": {"coordinates":[-1.932966,51.126144],"type":"Point"}
}