{
  "type": "Feature",
  "properties": {
    "iso:country": "GB",
    "wof:name": "SP3 4NR",
    "wof:placetype": "postalcode"
  },
  "geometry": {"coordinates":[-1.932966,51.126144],"type":"Point"}
}
