{
  "type": "Feature",
  "properties": {
    "iso:country":"GB",
    "wof:name":"WF8 3QT",
    "wof:placetype":"postalcode"
},
  "geometry": {"coordinates":[-1.3094784420212,53.67938579331319],"type":"Point"}
}