{
  "type": "Feature",
  "properties": {
    "iso:country":"GB",
    "wof:name":"M33 2ZP",
    "wof:placetype":"postalcode"
},
  "geometry": {"coordinates":[-2.29251825386275,53.42244872847512],"type":"Point"}
}