{
  "type": "Feature",
  "properties": {
    "date:inception_lower": "2003-08-01",
    "date:inception_upper": "2003-08-01",
    "iso:country": "GB",
    "wof:name": "M33 2ZP",
    "wof:placetype": "postalcode"
  },
  "geometry": {"coordinates":[-2.292518,53.422449],"type":"Point"}
}
