{
  "type": "Feature",
  "properties": {
    "date:inception_lower":"1980-01-01",
    "date:inception_upper":"1980-01-31",
    "iso:country":"GB",
    "wof:name":"G73 3SD",
    "wof:placetype":"postalcode"
},
  "geometry": {"coordinates":[-4.199395,55.817846],"type":"Point"}
}