{
  "type": "Feature",
  "properties": {
    "iso:country": "GB",
    "wof:name": "IV3 8QT",
    "wof:placetype": "postalcode"
  },
  "geometry": {"coordinates":[-4.259425,57.477412],"type":"Point"}
}
