{
  "type": "Feature",
  "properties": {
    "iso:country":"GB",
    "wof:name":"IV3 8QT",
    "wof:placetype":"postalcode"
},
  "geometry": {"coordinates":[-4.25942499502731,57.47741224254178],"type":"Point"}
}