{
  "type": "Feature",
  "properties": {
    "iso:country": "GB",
    "wof:name": "EN6 5HW",
    "wof:placetype": "postalcode"
  },
  "geometry": {"coordinates":[-0.165827,51.70014],"type":"Point"}
}
