{
  "type": "Feature",
  "properties": {
    "date:inception_lower": "2000-12-01",
    "date:inception_upper": "2000-12-01",
    "iso:country": "GB",
    "wof:name": "OX15 4UA",
    "wof:placetype": "postalcode"
  },
  "geometry": {"coordinates":[-1.382556,52.018806],"type":"Point"}
}
