{
  "type": "Feature",
  "properties": {
    "iso:country":"GB",
    "wof:name":"RH6 9QA",
    "wof:placetype":"postalcode"
},
  "geometry": {"coordinates":[-0.11483696618205,51.16875730483237],"type":"Point"}
}