{
  "type": "Feature",
  "properties": {
    "iso:country":"GB",
    "wof:name":"CH2 4JZ",
    "wof:placetype":"postalcode"
},
  "geometry": {"coordinates":[-2.87601207113659,53.26400341085365],"type":"Point"}
}