{
  "type": "Feature",
  "properties": {
    "iso:country": "GB",
    "wof:name": "CH2 4JZ",
    "wof:placetype": "postalcode"
  },
  "geometry": {"coordinates":[-2.875979,53.263903],"type":"Point"}
}
