{
  "type": "Feature",
  "properties": {
    "date:inception_lower":"1993-08-01",
    "date:inception_upper":"1993-08-31",
    "iso:country":"GB",
    "wof:name":"CH2 4JZ",
    "wof:placetype":"postalcode"
},
  "geometry": {"coordinates":[-2.875979,53.263903],"type":"Point"}
}