{
  "type": "Feature",
  "properties": {
    "iso:country":"GB",
    "wof:name":"LA12 7XA",
    "wof:placetype":"postalcode"
},
  "geometry": {"coordinates":[-3.1039832590002,54.19671337929012],"type":"Point"}
}