{
  "type": "Feature",
  "properties": {
    "iso:country": "GB",
    "wof:name": "LA12 7XA",
    "wof:placetype": "postalcode"
  },
  "geometry": {"coordinates":[-3.103792,54.197012],"type":"Point"}
}
