{
  "type": "Feature",
  "properties": {
    "date:inception_lower": "2020-02-01",
    "date:inception_upper": "2020-02-01",
    "iso:country": "GB",
    "wof:name": "BB2 5FF",
    "wof:placetype": "postalcode"
  },
  "geometry": {"coordinates":[-2.519156,53.723623],"type":"Point"}
}
