{
  "type": "Feature",
  "properties": {
    "iso:country": "GB",
    "wof:name": "BB2 5FF",
    "wof:placetype": "postalcode"
  },
  "geometry": {"coordinates":[-2.519702,53.723621],"type":"Point"}
}
