{
  "type": "Feature",
  "properties": {
    "iso:country":"GB",
    "wof:name":"GU28 9ET",
    "wof:placetype":"postalcode"
},
  "geometry": {"coordinates":[-0.66464944392145,51.03545657046038],"type":"Point"}
}