{
  "type": "Feature",
  "properties": {
    "date:inception_lower": "1980-01-01",
    "date:inception_upper": "1980-01-01",
    "iso:country": "GB",
    "wof:name": "GU28 9ET",
    "wof:placetype": "postalcode"
  },
  "geometry": {"coordinates":[-0.664672,51.035425],"type":"Point"}
}
