{
  "type": "Feature",
  "properties": {
    "iso:country":"GB",
    "wof:name":"LA10 5PT",
    "wof:placetype":"postalcode"
},
  "geometry": {"coordinates":[-2.31750698092468,54.32856097737967],"type":"Point"}
}