{
  "type": "Feature",
  "properties": {
    "iso:country": "GB",
    "wof:name": "DL8 4DH",
    "wof:placetype": "postalcode"
  },
  "geometry": {"coordinates":[-1.992487,54.303341],"type":"Point"}
}
