{
  "type": "Feature",
  "properties": {
    "iso:country":"GB",
    "wof:name":"DL8 4DH",
    "wof:placetype":"postalcode"
},
  "geometry": {"coordinates":[-1.9927586160586,54.30332078881095],"type":"Point"}
}