{
  "type": "Feature",
  "properties": {
    "date:inception_lower": "1980-01-01",
    "date:inception_upper": "1980-01-01",
    "iso:country": "GB",
    "wof:name": "B94 6SQ",
    "wof:placetype": "postalcode"
  },
  "geometry": {"coordinates":[-1.818511,52.35965],"type":"Point"}
}
