{
  "type": "Feature",
  "properties": {
    "iso:country": "GB",
    "wof:name": "B94 6SQ",
    "wof:placetype": "postalcode"
  },
  "geometry": {"coordinates":[-1.818511,52.35965],"type":"Point"}
}
