{
  "type": "Feature",
  "properties": {
    "iso:country":"GB",
    "wof:name":"NR17 1RP",
    "wof:placetype":"postalcode"
},
  "geometry": {"coordinates":[1.04374387681475,52.48138809746664],"type":"Point"}
}