{
  "type": "Feature",
  "properties": {
    "iso:country":"GB",
    "wof:name":"PH33 6HS",
    "wof:placetype":"postalcode"
},
  "geometry": {"coordinates":[-5.10404395452242,56.8158746926237],"type":"Point"}
}