{
  "type": "Feature",
  "properties": {
    "iso:country":"GB",
    "wof:name":"G51 1HD",
    "wof:placetype":"postalcode"
},
  "geometry": {"coordinates":[-4.27919611631355,55.85449480161488],"type":"Point"}
}