{
  "type": "Feature",
  "properties": {
    "date:inception_lower": "1992-01-01",
    "date:inception_upper": "1992-01-01",
    "iso:country": "GB",
    "wof:name": "G51 1HD",
    "wof:placetype": "postalcode"
  },
  "geometry": {"coordinates":[-4.279196,55.854495],"type":"Point"}
}
