{
  "type": "Feature",
  "properties": {
    "iso:country": "GB",
    "wof:name": "G51 1HD",
    "wof:placetype": "postalcode"
  },
  "geometry": {"coordinates":[-4.279196,55.854495],"type":"Point"}
}
