{
  "type": "Feature",
  "properties": {
    "iso:country":"GB",
    "wof:name":"B16 8HH",
    "wof:placetype":"postalcode"
},
  "geometry": {"coordinates":[-1.92000021033847,52.47414584571492],"type":"Point"}
}