{
  "type": "Feature",
  "properties": {
    "date:inception_lower": "2014-07-01",
    "date:inception_upper": "2014-07-01",
    "iso:country": "GB",
    "wof:name": "E3 5GR",
    "wof:placetype": "postalcode"
  },
  "geometry": {"coordinates":[-0.02996,51.532217],"type":"Point"}
}
