{
  "type": "Feature",
  "properties": {
    "iso:country":"GB",
    "wof:name":"E3 5GR",
    "wof:placetype":"postalcode"
},
  "geometry": {"coordinates":[-0.02996050461386,51.53221680893726],"type":"Point"}
}