{
  "type": "Feature",
  "properties": {
    "iso:country":"GB",
    "wof:name":"AL1 1NS",
    "wof:placetype":"postalcode"
},
  "geometry": {"coordinates":[-0.33633867726381,51.74989500109012],"type":"Point"}
}