{
  "type": "Feature",
  "properties": {
    "iso:country":"GB",
    "wof:name":"SA8 4QD",
    "wof:placetype":"postalcode"
},
  "geometry": {"coordinates":[-3.83316298828685,51.73226722033916],"type":"Point"}
}