{
  "type": "Feature",
  "properties": {
    "iso:country": "GB",
    "wof:name": "CH46 9AF",
    "wof:placetype": "postalcode"
  },
  "geometry": {"coordinates":[-3.096696,53.401346],"type":"Point"}
}
