{
  "type": "Feature",
  "properties": {
    "iso:country":"GB",
    "wof:name":"YO31 7LT",
    "wof:placetype":"postalcode"
},
  "geometry": {"coordinates":[-1.07744789029054,53.96652701894199],"type":"Point"}
}