{
  "type": "Feature",
  "properties": {
    "iso:country":"GB",
    "wof:name":"DA5 2AX",
    "wof:placetype":"postalcode"
},
  "geometry": {"coordinates":[0.16502702670365,51.43689004694718],"type":"Point"}
}