{
  "type": "Feature",
  "properties": {
    "date:inception_lower":"1994-05-01",
    "date:inception_upper":"1994-05-31",
    "iso:country":"GB",
    "wof:name":"HP9 2LH",
    "wof:placetype":"postalcode"
},
  "geometry": {"coordinates":[-0.647969,51.612677],"type":"Point"}
}