{
  "type": "Feature",
  "properties": {
    "iso:country": "GB",
    "wof:name": "CM12 9TF",
    "wof:placetype": "postalcode"
  },
  "geometry": {"coordinates":[0.408671,51.604823],"type":"Point"}
}
