{
  "type": "Feature",
  "properties": {
    "iso:country":"GB",
    "wof:name":"NR20 5NR",
    "wof:placetype":"postalcode"
},
  "geometry": {"coordinates":[0.89239255458931,52.75238949117151],"type":"Point"}
}