{
  "type": "Feature",
  "properties": {
    "date:inception_lower": "2014-07-01",
    "date:inception_upper": "2014-07-01",
    "iso:country": "GB",
    "wof:name": "NR20 5NR",
    "wof:placetype": "postalcode"
  },
  "geometry": {"coordinates":[0.892473,52.75244],"type":"Point"}
}
