{
  "type": "Feature",
  "properties": {
    "iso:country": "GB",
    "wof:name": "PA5 0PR",
    "wof:placetype": "postalcode"
  },
  "geometry": {"coordinates":[-4.538518,55.821238],"type":"Point"}
}
