{
  "type": "Feature",
  "properties": {
    "iso:country":"GB",
    "wof:name":"PA5 0PR",
    "wof:placetype":"postalcode"
},
  "geometry": {"coordinates":[-4.53851839895752,55.82123773921629],"type":"Point"}
}