{
  "type": "Feature",
  "properties": {
    "iso:country":"GB",
    "wof:name":"CV2 3GJ",
    "wof:placetype":"postalcode"
},
  "geometry": {"coordinates":[-1.47698917642328,52.4174050286207],"type":"Point"}
}