{
  "type": "Feature",
  "properties": {
    "iso:country":"GB",
    "wof:name":"NR19 1QD",
    "wof:placetype":"postalcode"
},
  "geometry": {"coordinates":[0.93341190095716,52.67047383372425],"type":"Point"}
}