{
  "type": "Feature",
  "properties": {
    "iso:country": "GB",
    "wof:name": "CA10 1EY",
    "wof:placetype": "postalcode"
  },
  "geometry": {"coordinates":[-2.685118,54.771208],"type":"Point"}
}
