{
  "type": "Feature",
  "properties": {
    "iso:country":"GB",
    "wof:name":"BD4 7RD",
    "wof:placetype":"postalcode"
},
  "geometry": {"coordinates":[-1.734153959563,53.77975152632654],"type":"Point"}
}