{
  "type": "Feature",
  "properties": {
    "iso:country":"GB",
    "wof:name":"IG7 5BX",
    "wof:placetype":"postalcode"
},
  "geometry": {"coordinates":[0.06540765020865,51.61064711448971],"type":"Point"}
}