{
  "type": "Feature",
  "properties": {
    "iso:country": "GB",
    "wof:name": "IG7 5BX",
    "wof:placetype": "postalcode"
  },
  "geometry": {"coordinates":[0.065408,51.610647],"type":"Point"}
}
