{
  "type": "Feature",
  "properties": {
    "iso:country":"GB",
    "wof:name":"WS15 2PG",
    "wof:placetype":"postalcode"
},
  "geometry": {"coordinates":[-1.95539352511326,52.76524335856147],"type":"Point"}
}