{
  "type": "Feature",
  "properties": {
    "iso:country":"GB",
    "wof:name":"CV6 7FG",
    "wof:placetype":"postalcode"
},
  "geometry": {"coordinates":[-1.48821120058824,52.43490395324979],"type":"Point"}
}