{
  "type": "Feature",
  "properties": {
    "iso:country": "GB",
    "wof:name": "L31 1AR",
    "wof:placetype": "postalcode"
  },
  "geometry": {"coordinates":[-2.901195,53.505849],"type":"Point"}
}
