{
  "type": "Feature",
  "properties": {
    "iso:country": "GB",
    "wof:name": "SG1 4HZ",
    "wof:placetype": "postalcode"
  },
  "geometry": {"coordinates":[-0.180746,51.922421],"type":"Point"}
}
