{
  "type": "Feature",
  "properties": {
    "iso:country":"GB",
    "wof:name":"EH32 0QU",
    "wof:placetype":"postalcode"
},
  "geometry": {"coordinates":[-2.90647600684607,55.97071716325931],"type":"Point"}
}