{
  "type": "Feature",
  "properties": {
    "date:inception_lower":"1980-01-01",
    "date:inception_upper":"1980-01-31",
    "iso:country":"GB",
    "wof:name":"EH32 0QU",
    "wof:placetype":"postalcode"
},
  "geometry": {"coordinates":[-2.906476,55.970717],"type":"Point"}
}