{
  "type": "Feature",
  "properties": {
    "iso:country":"GB",
    "wof:name":"WS7 2PE",
    "wof:placetype":"postalcode"
},
  "geometry": {"coordinates":[-1.92953471540462,52.69004201826849],"type":"Point"}
}