{
  "type": "Feature",
  "properties": {
    "iso:country":"GB",
    "wof:name":"LE2 2AF",
    "wof:placetype":"postalcode"
},
  "geometry": {"coordinates":[-1.103721241629,52.61753469032891],"type":"Point"}
}