{
  "type": "Feature",
  "properties": {
    "iso:country":"GB",
    "wof:name":"E3 4RR",
    "wof:placetype":"postalcode"
},
  "geometry": {"coordinates":[-0.03590211005538,51.51945701027691],"type":"Point"}
}