{
  "type": "Feature",
  "properties": {
    "iso:country":"GB",
    "wof:name":"EX4 2JF",
    "wof:placetype":"postalcode"
},
  "geometry": {"coordinates":[-3.56705193638396,50.72725633358772],"type":"Point"}
}