{
  "type": "Feature",
  "properties": {
    "iso:country": "GB",
    "wof:name": "CW12 2GX",
    "wof:placetype": "postalcode"
  },
  "geometry": {"coordinates":[-2.21114,53.176446],"type":"Point"}
}
