{
  "type": "Feature",
  "properties": {
    "date:inception_lower": "2019-05-01",
    "date:inception_upper": "2019-05-01",
    "iso:country": "GB",
    "wof:name": "CW12 2GX",
    "wof:placetype": "postalcode"
  },
  "geometry": {"coordinates":[-2.21114,53.176446],"type":"Point"}
}
