{
  "type": "Feature",
  "properties": {
    "date:inception_lower":"2002-06-01",
    "date:inception_upper":"2002-06-30",
    "iso:country":"GB",
    "wof:name":"HU11 5FD",
    "wof:placetype":"postalcode"
},
  "geometry": {"coordinates":[-0.288893,53.866395],"type":"Point"}
}