{
  "type": "Feature",
  "properties": {
    "iso:country":"GB",
    "wof:name":"HU11 5FD",
    "wof:placetype":"postalcode"
},
  "geometry": {"coordinates":[-0.28889260956808,53.8663950203912],"type":"Point"}
}