{
  "type": "Feature",
  "properties": {
    "iso:country":"GB",
    "wof:name":"NW11 7EG",
    "wof:placetype":"postalcode"
},
  "geometry": {"coordinates":[-0.19037324666058,51.57408886325561],"type":"Point"}
}