{
  "type": "Feature",
  "properties": {
    "iso:country": "GB",
    "wof:name": "SA2 0RJ",
    "wof:placetype": "postalcode"
  },
  "geometry": {"coordinates":[-3.965665,51.621946],"type":"Point"}
}
