{
  "type": "Feature",
  "properties": {
    "iso:country": "GB",
    "wof:name": "AB38 7BS",
    "wof:placetype": "postalcode"
  },
  "geometry": {"coordinates":[-3.210786,57.530335],"type":"Point"}
}
