{
  "type": "Feature",
  "properties": {
    "iso:country":"GB",
    "wof:name":"AB38 7BS",
    "wof:placetype":"postalcode"
},
  "geometry": {"coordinates":[-3.21078628622859,57.53033492331938],"type":"Point"}
}