{
  "type": "Feature",
  "properties": {
    "iso:country":"GB",
    "wof:name":"MK18 2JA",
    "wof:placetype":"postalcode"
},
  "geometry": {"coordinates":[-0.9273143272396,51.96489470816265],"type":"Point"}
}