{
  "type": "Feature",
  "properties": {
    "date:inception_lower": "1980-01-01",
    "date:inception_upper": "1980-01-01",
    "iso:country": "GB",
    "wof:name": "MK18 2JA",
    "wof:placetype": "postalcode"
  },
  "geometry": {"coordinates":[-0.927208,51.964858],"type":"Point"}
}
