{
  "type": "Feature",
  "properties": {
    "iso:country":"GB",
    "wof:name":"WD6 2LR",
    "wof:placetype":"postalcode"
},
  "geometry": {"coordinates":[-0.25833526484067,51.6528011079337],"type":"Point"}
}