{
  "type": "Feature",
  "properties": {
    "date:inception_lower": "1995-07-01",
    "date:inception_upper": "1995-07-01",
    "iso:country": "GB",
    "wof:name": "RG41 5DD",
    "wof:placetype": "postalcode"
  },
  "geometry": {"coordinates":[-0.894055,51.424627],"type":"Point"}
}
