{
  "type": "Feature",
  "properties": {
    "date:inception_lower":"1994-12-01",
    "date:inception_upper":"1994-12-31",
    "iso:country":"GB",
    "wof:name":"NW5 1JG",
    "wof:placetype":"postalcode"
},
  "geometry": {"coordinates":[-0.140918,51.56239],"type":"Point"}
}