{
  "type": "Feature",
  "properties": {
    "iso:country":"GB",
    "wof:name":"NW5 1JG",
    "wof:placetype":"postalcode"
},
  "geometry": {"coordinates":[-0.14095206045536,51.562273626956],"type":"Point"}
}