{
  "type": "Feature",
  "properties": {
    "date:inception_lower":"1980-01-01",
    "date:inception_upper":"1980-01-31",
    "iso:country":"GB",
    "wof:name":"BD14 6AX",
    "wof:placetype":"postalcode"
},
  "geometry": {"coordinates":[-1.820424,53.783516],"type":"Point"}
}