{
  "type": "Feature",
  "properties": {
    "iso:country":"GB",
    "wof:name":"BD14 6AX",
    "wof:placetype":"postalcode"
},
  "geometry": {"coordinates":[-1.82042426325793,53.78351575404977],"type":"Point"}
}