{
  "type": "Feature",
  "properties": {
    "iso:country":"GB",
    "wof:name":"PO4 9JS",
    "wof:placetype":"postalcode"
},
  "geometry": {"coordinates":[-1.04940334395022,50.78882835577204],"type":"Point"}
}