{
  "type": "Feature",
  "properties": {
    "date:inception_lower": "1980-01-01",
    "date:inception_upper": "1980-01-01",
    "iso:country": "GB",
    "wof:name": "WV1 2HT",
    "wof:placetype": "postalcode"
  },
  "geometry": {"coordinates":[-2.101726,52.582976],"type":"Point"}
}
