{
  "type": "Feature",
  "properties": {
    "iso:country":"GB",
    "wof:name":"PO9 2UZ",
    "wof:placetype":"postalcode"
},
  "geometry": {"coordinates":[-0.96280454027434,50.86006010167559],"type":"Point"}
}