{
  "type": "Feature",
  "properties": {
    "iso:country":"GB",
    "wof:name":"SL3 7LA",
    "wof:placetype":"postalcode"
},
  "geometry": {"coordinates":[-0.55898232168305,51.49688948631771],"type":"Point"}
}