{
  "type": "Feature",
  "properties": {
    "date:inception_lower":"1980-01-01",
    "date:inception_upper":"1980-01-31",
    "iso:country":"GB",
    "wof:name":"SY4 3PH",
    "wof:placetype":"postalcode"
},
  "geometry": {"coordinates":[-2.782786,52.771495],"type":"Point"}
}