{
  "type": "Feature",
  "properties": {
    "iso:country":"GB",
    "wof:name":"SY4 3PH",
    "wof:placetype":"postalcode"
},
  "geometry": {"coordinates":[-2.78278652900625,52.77149534968157],"type":"Point"}
}