{
  "type": "Feature",
  "properties": {
    "iso:country": "GB",
    "wof:name": "SY4 3PH",
    "wof:placetype": "postalcode"
  },
  "geometry": {"coordinates":[-2.782786,52.771495],"type":"Point"}
}
