{
  "type": "Feature",
  "properties": {
    "iso:country": "GB",
    "wof:name": "EH21 6QE",
    "wof:placetype": "postalcode"
  },
  "geometry": {"coordinates":[-3.062607,55.94246],"type":"Point"}
}
