{
  "type": "Feature",
  "properties": {
    "iso:country":"GB",
    "wof:name":"EH21 6QE",
    "wof:placetype":"postalcode"
},
  "geometry": {"coordinates":[-3.0626068845064,55.94245993573279],"type":"Point"}
}