{
  "type": "Feature",
  "properties": {
    "iso:country":"GB",
    "wof:name":"SR6 9EG",
    "wof:placetype":"postalcode"
},
  "geometry": {"coordinates":[-1.37590544196267,54.92983849785667],"type":"Point"}
}