{
  "type": "Feature",
  "properties": {
    "iso:country":"GB",
    "wof:name":"DY4 7QH",
    "wof:placetype":"postalcode"
},
  "geometry": {"coordinates":[-2.04818281134794,52.52491094347847],"type":"Point"}
}