{
  "type": "Feature",
  "properties": {
    "date:inception_lower": "1980-01-01",
    "date:inception_upper": "1980-01-01",
    "iso:country": "GB",
    "wof:name": "DY4 7QH",
    "wof:placetype": "postalcode"
  },
  "geometry": {"coordinates":[-2.048183,52.524911],"type":"Point"}
}
