{
  "type": "Feature",
  "properties": {
    "date:inception_lower":"1997-12-01",
    "date:inception_upper":"1997-12-31",
    "iso:country":"GB",
    "wof:name":"SK13 7BH",
    "wof:placetype":"postalcode"
},
  "geometry": {"coordinates":[-1.956927,53.450008],"type":"Point"}
}