{
  "type": "Feature",
  "properties": {
    "iso:country":"GB",
    "wof:name":"RG19 3TX",
    "wof:placetype":"postalcode"
},
  "geometry": {"coordinates":[-1.28319021478817,51.40488406595122],"type":"Point"}
}