{
  "type": "Feature",
  "properties": {
    "date:inception_lower": "1983-08-01",
    "date:inception_upper": "1983-08-01",
    "iso:country": "GB",
    "wof:name": "KY6 3QE",
    "wof:placetype": "postalcode"
  },
  "geometry": {"coordinates":[-3.192135,56.208318],"type":"Point"}
}
