{
  "type": "Feature",
  "properties": {
    "iso:country":"GB",
    "wof:name":"KY6 3QE",
    "wof:placetype":"postalcode"
},
  "geometry": {"coordinates":[-3.19213462813966,56.20831763964535],"type":"Point"}
}