{
  "type": "Feature",
  "properties": {
    "iso:country":"GB",
    "wof:name":"BN14 8AW",
    "wof:placetype":"postalcode"
},
  "geometry": {"coordinates":[-0.37277436306676,50.82310829311092],"type":"Point"}
}