{
  "type": "Feature",
  "properties": {
    "iso:country":"GB",
    "wof:name":"TW16 6DE",
    "wof:placetype":"postalcode"
},
  "geometry": {"coordinates":[-0.41695706795141,51.40182635046567],"type":"Point"}
}