{
  "type": "Feature",
  "properties": {
    "iso:country":"GB",
    "wof:name":"M6 8GL",
    "wof:placetype":"postalcode"
},
  "geometry": {"coordinates":[-2.30406210239774,53.49016626156212],"type":"Point"}
}