{
  "type": "Feature",
  "properties": {
    "iso:country":"GB",
    "wof:name":"CM20 2FP",
    "wof:placetype":"postalcode"
},
  "geometry": {"coordinates":[0.09762238024403,51.78569130965212],"type":"Point"}
}