{
  "type": "Feature",
  "properties": {
    "date:inception_lower": "2015-04-01",
    "date:inception_upper": "2015-04-01",
    "iso:country": "GB",
    "wof:name": "CM20 2FP",
    "wof:placetype": "postalcode"
  },
  "geometry": {"coordinates":[0.097502,51.785655],"type":"Point"}
}
