{
  "type": "Feature",
  "properties": {
    "iso:country":"GB",
    "wof:name":"SY8 2ET",
    "wof:placetype":"postalcode"
},
  "geometry": {"coordinates":[-2.59960076135963,52.4433891030982],"type":"Point"}
}