{
  "type": "Feature",
  "properties": {
    "date:inception_lower": "2023-10-01",
    "date:inception_upper": "2023-10-01",
    "iso:country": "GB",
    "wof:name": "HR4 7FJ",
    "wof:placetype": "postalcode"
  },
  "geometry": {"coordinates":[-2.744976,52.078232],"type":"Point"}
}
