{
  "type": "Feature",
  "properties": {
    "date:inception_lower": "1996-06-01",
    "date:inception_upper": "1996-06-01",
    "iso:country": "GB",
    "wof:name": "LL68 9EL",
    "wof:placetype": "postalcode"
  },
  "geometry": {"coordinates":[-4.344188,53.409904],"type":"Point"}
}
