{
  "type": "Feature",
  "properties": {
    "iso:country":"GB",
    "wof:name":"LL68 9EL",
    "wof:placetype":"postalcode"
},
  "geometry": {"coordinates":[-4.34418827543121,53.40990435277907],"type":"Point"}
}