{
  "type": "Feature",
  "properties": {
    "iso:country": "GB",
    "wof:name": "LS16 7SX",
    "wof:placetype": "postalcode"
  },
  "geometry": {"coordinates":[-1.61428,53.858617],"type":"Point"}
}
