{
  "type": "Feature",
  "properties": {
    "iso:country": "GB",
    "wof:name": "HA5 2TJ",
    "wof:placetype": "postalcode"
  },
  "geometry": {"coordinates":[-0.397956,51.584965],"type":"Point"}
}
