{
  "type": "Feature",
  "properties": {
    "iso:country":"GB",
    "wof:name":"HA5 2TJ",
    "wof:placetype":"postalcode"
},
  "geometry": {"coordinates":[-0.39795616340732,51.58496530911702],"type":"Point"}
}