{
  "type": "Feature",
  "properties": {
    "iso:country":"GB",
    "wof:name":"TW1 4SD",
    "wof:placetype":"postalcode"
},
  "geometry": {"coordinates":[-0.33253937617838,51.43774942028375],"type":"Point"}
}