{
  "type": "Feature",
  "properties": {
    "date:inception_lower":"2003-06-01",
    "date:inception_upper":"2003-06-30",
    "iso:country":"GB",
    "wof:name":"BD24 9FD",
    "wof:placetype":"postalcode"
},
  "geometry": {"coordinates":[-2.28521,54.069724],"type":"Point"}
}