{
  "type": "Feature",
  "properties": {
    "iso:country": "GB",
    "wof:name": "LS17 8NL",
    "wof:placetype": "postalcode"
  },
  "geometry": {"coordinates":[-1.474042,53.838547],"type":"Point"}
}
