{
  "type": "Feature",
  "properties": {
    "iso:country":"GB",
    "wof:name":"LS17 8NL",
    "wof:placetype":"postalcode"
},
  "geometry": {"coordinates":[-1.4740425292902,53.83854698771718],"type":"Point"}
}