{
  "type": "Feature",
  "properties": {
    "date:inception_lower":"2008-02-01",
    "date:inception_upper":"2008-02-29",
    "iso:country":"GB",
    "wof:name":"GU35 0RF",
    "wof:placetype":"postalcode"
},
  "geometry": {"coordinates":[-0.852144,51.116744],"type":"Point"}
}