{
  "type": "Feature",
  "properties": {
    "date:inception_lower": "1988-03-01",
    "date:inception_upper": "1988-03-01",
    "iso:country": "GB",
    "wof:name": "NR33 8TB",
    "wof:placetype": "postalcode"
  },
  "geometry": {"coordinates":[1.715113,52.453024],"type":"Point"}
}
