{
  "type": "Feature",
  "properties": {
    "iso:country":"GB",
    "wof:name":"NR30 4JY",
    "wof:placetype":"postalcode"
},
  "geometry": {"coordinates":[1.73095263903319,52.61914483559527],"type":"Point"}
}