{
  "type": "Feature",
  "properties": {
    "date:inception_lower": "1997-12-01",
    "date:inception_upper": "1997-12-01",
    "iso:country": "GB",
    "wof:name": "KA3 1UR",
    "wof:placetype": "postalcode"
  },
  "geometry": {"coordinates":[-4.484811,55.628011],"type":"Point"}
}
