{
  "type": "Feature",
  "properties": {
    "iso:country":"GB",
    "wof:name":"KA3 1UR",
    "wof:placetype":"postalcode"
},
  "geometry": {"coordinates":[-4.48481074803921,55.62801082079795],"type":"Point"}
}