{
  "type": "Feature",
  "properties": {
    "date:inception_lower":"1980-01-01",
    "date:inception_upper":"1980-01-31",
    "iso:country":"GB",
    "wof:name":"WV2 1DB",
    "wof:placetype":"postalcode"
},
  "geometry": {"coordinates":[-2.119737,52.579659],"type":"Point"}
}