{
  "type": "Feature",
  "properties": {
    "iso:country": "GB",
    "wof:name": "WV2 1DB",
    "wof:placetype": "postalcode"
  },
  "geometry": {"coordinates":[-2.119737,52.579659],"type":"Point"}
}
