{
  "type": "Feature",
  "properties": {
    "iso:country": "GB",
    "wof:name": "HP21 7QQ",
    "wof:placetype": "postalcode"
  },
  "geometry": {"coordinates":[-0.807351,51.812174],"type":"Point"}
}
