{
  "type": "Feature",
  "properties": {
    "iso:country": "GB",
    "wof:name": "EN10 6QW",
    "wof:placetype": "postalcode"
  },
  "geometry": {"coordinates":[-0.022905,51.739671],"type":"Point"}
}
