{
  "type": "Feature",
  "properties": {
    "date:inception_lower":"2008-01-01",
    "date:inception_upper":"2008-01-31",
    "iso:country":"GB",
    "wof:name":"NP26 5AE",
    "wof:placetype":"postalcode"
},
  "geometry": {"coordinates":[-2.76018,51.588001],"type":"Point"}
}