{
  "type": "Feature",
  "properties": {
    "iso:country": "GB",
    "wof:name": "NP26 5AE",
    "wof:placetype": "postalcode"
  },
  "geometry": {"coordinates":[-2.76018,51.588001],"type":"Point"}
}
