{
  "type": "Feature",
  "properties": {
    "iso:country": "GB",
    "wof:name": "S13 7AA",
    "wof:placetype": "postalcode"
  },
  "geometry": {"coordinates":[-1.362157,53.355336],"type":"Point"}
}
