{
  "type": "Feature",
  "properties": {
    "iso:country": "GB",
    "wof:name": "DN7 5EL",
    "wof:placetype": "postalcode"
  },
  "geometry": {"coordinates":[-1.021389,53.5989],"type":"Point"}
}
