{
  "type": "Feature",
  "properties": {
    "iso:country":"GB",
    "wof:name":"DN7 5EL",
    "wof:placetype":"postalcode"
},
  "geometry": {"coordinates":[-1.02138953827544,53.59889961740721],"type":"Point"}
}