{
  "type": "Feature",
  "properties": {
    "iso:country": "GB",
    "wof:name": "CF36 5DU",
    "wof:placetype": "postalcode"
  },
  "geometry": {"coordinates":[-3.694891,51.486402],"type":"Point"}
}
