{
  "type": "Feature",
  "properties": {
    "iso:country":"GB",
    "wof:name":"GU14 6AN",
    "wof:placetype":"postalcode"
},
  "geometry": {"coordinates":[-0.75041654438698,51.2744891194103],"type":"Point"}
}