{
  "type": "Feature",
  "properties": {
    "iso:country":"GB",
    "wof:name":"GU51 5SF",
    "wof:placetype":"postalcode"
},
  "geometry": {"coordinates":[-0.85971640610643,51.26519150835804],"type":"Point"}
}