{
  "type": "Feature",
  "properties": {
    "date:inception_lower": "2001-06-01",
    "date:inception_upper": "2001-06-01",
    "iso:country": "GB",
    "wof:name": "GU51 5SF",
    "wof:placetype": "postalcode"
  },
  "geometry": {"coordinates":[-0.859716,51.265192],"type":"Point"}
}
