{
  "type": "Feature",
  "properties": {
    "iso:country":"GB",
    "wof:name":"G52 1DQ",
    "wof:placetype":"postalcode"
},
  "geometry": {"coordinates":[-4.32480000849082,55.8497136912237],"type":"Point"}
}