{
  "type": "Feature",
  "properties": {
    "date:inception_lower": "1980-01-01",
    "date:inception_upper": "1980-01-01",
    "iso:country": "GB",
    "wof:name": "CA11 0HN",
    "wof:placetype": "postalcode"
  },
  "geometry": {"coordinates":[-2.835788,54.642101],"type":"Point"}
}
