{
  "type": "Feature",
  "properties": {
    "iso:country":"GB",
    "wof:name":"CA11 0HN",
    "wof:placetype":"postalcode"
},
  "geometry": {"coordinates":[-2.83578760706836,54.64210114363407],"type":"Point"}
}