{
  "type": "Feature",
  "properties": {
    "date:inception_lower":"2016-11-01",
    "date:inception_upper":"2016-11-30",
    "iso:country":"GB",
    "wof:name":"ST21 6LN",
    "wof:placetype":"postalcode"
},
  "geometry": {"coordinates":[-2.242036,52.857333],"type":"Point"}
}