{
  "type": "Feature",
  "properties": {
    "iso:country": "GB",
    "wof:name": "ST21 6LN",
    "wof:placetype": "postalcode"
  },
  "geometry": {"coordinates":[-2.241871,52.857099],"type":"Point"}
}
