{
  "type": "Feature",
  "properties": {
    "iso:country": "GB",
    "wof:name": "ST21 6LN",
    "wof:placetype": "postalcode"
  },
  "geometry": {"coordinates":[-2.242036,52.857333],"type":"Point"}
}
