{
  "type": "Feature",
  "properties": {
    "date:inception_lower": "2020-07-01",
    "date:inception_upper": "2020-07-01",
    "iso:country": "GB",
    "wof:name": "TA4 3LF",
    "wof:placetype": "postalcode"
  },
  "geometry": {"coordinates":[-3.19584,51.054106],"type":"Point"}
}
