{
  "type": "Feature",
  "properties": {
    "iso:country":"GB",
    "wof:name":"G1 1BL",
    "wof:placetype":"postalcode"
},
  "geometry": {"coordinates":[-4.24314644500436,55.8583210949286],"type":"Point"}
}