{
  "type": "Feature",
  "properties": {
    "iso:country": "GB",
    "wof:name": "MK3 5LH",
    "wof:placetype": "postalcode"
  },
  "geometry": {"coordinates":[-0.774757,51.988456],"type":"Point"}
}
