{
  "type": "Feature",
  "properties": {
    "date:inception_lower":"1997-12-01",
    "date:inception_upper":"1997-12-31",
    "iso:country":"GB",
    "wof:name":"HP11 1PE",
    "wof:placetype":"postalcode"
},
  "geometry": {"coordinates":[-0.750891,51.626226],"type":"Point"}
}