{
  "type": "Feature",
  "properties": {
    "iso:country":"GB",
    "wof:name":"HP11 1PE",
    "wof:placetype":"postalcode"
},
  "geometry": {"coordinates":[-0.75089118155009,51.62622585014275],"type":"Point"}
}