{
  "type": "Feature",
  "properties": {
    "iso:country":"GB",
    "wof:name":"CM7 5TJ",
    "wof:placetype":"postalcode"
},
  "geometry": {"coordinates":[0.54571409482605,51.88664443254013],"type":"Point"}
}