{
  "type": "Feature",
  "properties": {
    "date:inception_lower": "2023-05-01",
    "date:inception_upper": "2023-05-01",
    "iso:country": "GB",
    "wof:name": "SW6 9RS",
    "wof:placetype": "postalcode"
  },
  "geometry": {"coordinates":[-0.198493,51.479381],"type":"Point"}
}
