{
  "type": "Feature",
  "properties": {
    "iso:country": "GB",
    "wof:name": "ST7 1RF",
    "wof:placetype": "postalcode"
  },
  "geometry": {"coordinates":[-2.255264,53.070901],"type":"Point"}
}
