{
  "type": "Feature",
  "properties": {
    "iso:country":"GB",
    "wof:name":"ST7 1RF",
    "wof:placetype":"postalcode"
},
  "geometry": {"coordinates":[-2.25526387436776,53.07090079333204],"type":"Point"}
}