{
  "type": "Feature",
  "properties": {
    "iso:country": "GB",
    "wof:name": "NE11 9QG",
    "wof:placetype": "postalcode"
  },
  "geometry": {"coordinates":[-1.649691,54.953641],"type":"Point"}
}
