{
  "type": "Feature",
  "properties": {
    "date:inception_lower": "2021-12-01",
    "date:inception_upper": "2021-12-01",
    "iso:country": "GB",
    "wof:name": "NE29 8BF",
    "wof:placetype": "postalcode"
  },
  "geometry": {"coordinates":[-1.476823,55.02121],"type":"Point"}
}
