{
  "type": "Feature",
  "properties": {
    "date:inception_lower": "1996-12-01",
    "date:inception_upper": "1996-12-01",
    "iso:country": "GB",
    "wof:name": "KY12 0XP",
    "wof:placetype": "postalcode"
  },
  "geometry": {"coordinates":[-3.441203,56.080218],"type":"Point"}
}
