{
  "type": "Feature",
  "properties": {
    "iso:country":"GB",
    "wof:name":"KY12 0XP",
    "wof:placetype":"postalcode"
},
  "geometry": {"coordinates":[-3.44120299603548,56.08021831811614],"type":"Point"}
}