{
  "type": "Feature",
  "properties": {
    "iso:country": "GB",
    "wof:name": "HX2 0UT",
    "wof:placetype": "postalcode"
  },
  "geometry": {"coordinates":[-1.920278,53.739555],"type":"Point"}
}
