{
  "type": "Feature",
  "properties": {
    "iso:country":"GB",
    "wof:name":"HX2 0UT",
    "wof:placetype":"postalcode"
},
  "geometry": {"coordinates":[-1.92027802602134,53.7395552688369],"type":"Point"}
}