{
  "type": "Feature",
  "properties": {
    "iso:country":"GB",
    "wof:name":"S71 5NQ",
    "wof:placetype":"postalcode"
},
  "geometry": {"coordinates":[-1.43471948120571,53.56103630550876],"type":"Point"}
}