{
  "type": "Feature",
  "properties": {
    "iso:country":"GB",
    "wof:name":"NG17 4JJ",
    "wof:placetype":"postalcode"
},
  "geometry": {"coordinates":[-1.2478448300801,53.13260529393069],"type":"Point"}
}