{
  "type": "Feature",
  "properties": {
    "date:inception_lower": "1980-01-01",
    "date:inception_upper": "1980-01-01",
    "iso:country": "GB",
    "wof:name": "PO9 4QA",
    "wof:placetype": "postalcode"
  },
  "geometry": {"coordinates":[-0.997803,50.871859],"type":"Point"}
}
