{
  "type": "Feature",
  "properties": {
    "iso:country":"GB",
    "wof:name":"PO9 4QA",
    "wof:placetype":"postalcode"
},
  "geometry": {"coordinates":[-0.99780301617142,50.87185851152509],"type":"Point"}
}