{
  "type": "Feature",
  "properties": {
    "iso:country":"GB",
    "wof:name":"SA10 7TD",
    "wof:placetype":"postalcode"
},
  "geometry": {"coordinates":[-3.81711350227633,51.68017303449079],"type":"Point"}
}