{
  "type": "Feature",
  "properties": {
    "iso:country":"GB",
    "wof:name":"TQ1 1PX",
    "wof:placetype":"postalcode"
},
  "geometry": {"coordinates":[-3.51611010616791,50.46373783084719],"type":"Point"}
}