{
  "type": "Feature",
  "properties": {
    "iso:country": "GB",
    "wof:name": "TQ1 1PX",
    "wof:placetype": "postalcode"
  },
  "geometry": {"coordinates":[-3.51611,50.463738],"type":"Point"}
}
