{
  "type": "Feature",
  "properties": {
    "date:inception_lower": "1980-01-01",
    "date:inception_upper": "1980-01-01",
    "iso:country": "GB",
    "wof:name": "SA73 1BW",
    "wof:placetype": "postalcode"
  },
  "geometry": {"coordinates":[-5.022233,51.717484],"type":"Point"}
}
