{
  "type": "Feature",
  "properties": {
    "iso:country":"GB",
    "wof:name":"SA73 1BW",
    "wof:placetype":"postalcode"
},
  "geometry": {"coordinates":[-5.02215198854573,51.71745396074483],"type":"Point"}
}