{
  "type": "Feature",
  "properties": {
    "iso:country":"GB",
    "wof:name":"PO22 6AX",
    "wof:placetype":"postalcode"
},
  "geometry": {"coordinates":[-0.63286214728389,50.79887287226732],"type":"Point"}
}