{
  "type": "Feature",
  "properties": {
    "iso:country": "GB",
    "wof:name": "LL28 4HZ",
    "wof:placetype": "postalcode"
  },
  "geometry": {"coordinates":[-3.758251,53.311403],"type":"Point"}
}
