{
  "type": "Feature",
  "properties": {
    "iso:country": "GB",
    "wof:name": "LL16 3PU",
    "wof:placetype": "postalcode"
  },
  "geometry": {"coordinates":[-3.427292,53.183605],"type":"Point"}
}
