{
  "type": "Feature",
  "properties": {
    "iso:country":"GB",
    "wof:name":"WA4 4DX",
    "wof:placetype":"postalcode"
},
  "geometry": {"coordinates":[-2.58411802229307,53.32386820922623],"type":"Point"}
}