{
  "type": "Feature",
  "properties": {
    "iso:country": "GB",
    "wof:name": "WA4 4DX",
    "wof:placetype": "postalcode"
  },
  "geometry": {"coordinates":[-2.584118,53.323868],"type":"Point"}
}
