{
  "type": "Feature",
  "properties": {
    "iso:country":"GB",
    "wof:name":"M9 4ES",
    "wof:placetype":"postalcode"
},
  "geometry": {"coordinates":[-2.20423418339336,53.51665188130153],"type":"Point"}
}