{
  "type": "Feature",
  "properties": {
    "iso:country":"GB",
    "wof:name":"B78 2JJ",
    "wof:placetype":"postalcode"
},
  "geometry": {"coordinates":[-1.68416510871587,52.57090600355352],"type":"Point"}
}