{
  "type": "Feature",
  "properties": {
    "iso:country": "GB",
    "wof:name": "B78 2JJ",
    "wof:placetype": "postalcode"
  },
  "geometry": {"coordinates":[-1.684261,52.570905],"type":"Point"}
}
