{
  "type": "Feature",
  "properties": {
    "date:inception_lower": "2016-08-01",
    "date:inception_upper": "2016-08-01",
    "iso:country": "GB",
    "wof:name": "E20 1GZ",
    "wof:placetype": "postalcode"
  },
  "geometry": {"coordinates":[-0.013325,51.54906],"type":"Point"}
}
