{
  "type": "Feature",
  "properties": {
    "iso:country": "GB",
    "wof:name": "WF3 3FS",
    "wof:placetype": "postalcode"
  },
  "geometry": {"coordinates":[-1.510162,53.743973],"type":"Point"}
}
