{
  "type": "Feature",
  "properties": {
    "iso:country":"GB",
    "wof:name":"WF3 3FS",
    "wof:placetype":"postalcode"
},
  "geometry": {"coordinates":[-1.51011282701826,53.74394743089071],"type":"Point"}
}