{
  "type": "Feature",
  "properties": {
    "date:inception_lower":"2009-09-01",
    "date:inception_upper":"2009-09-30",
    "iso:country":"GB",
    "wof:name":"WF3 3FS",
    "wof:placetype":"postalcode"
},
  "geometry": {"coordinates":[-1.510162,53.743973],"type":"Point"}
}