{
  "type": "Feature",
  "properties": {
    "date:inception_lower": "1980-01-01",
    "date:inception_upper": "1980-01-01",
    "iso:country": "GB",
    "wof:name": "RH20 3LZ",
    "wof:placetype": "postalcode"
  },
  "geometry": {"coordinates":[-0.435671,50.921616],"type":"Point"}
}
