{
  "type": "Feature",
  "properties": {
    "iso:country":"GB",
    "wof:name":"CR0 3JX",
    "wof:placetype":"postalcode"
},
  "geometry": {"coordinates":[-0.12224965510538,51.38283455278486],"type":"Point"}
}