{
  "type": "Feature",
  "properties": {
    "iso:country":"GB",
    "wof:name":"B47 5DF",
    "wof:placetype":"postalcode"
},
  "geometry": {"coordinates":[-1.89084089006709,52.38846553252549],"type":"Point"}
}