{
  "type": "Feature",
  "properties": {
    "iso:country":"GB",
    "wof:name":"NN11 6EB",
    "wof:placetype":"postalcode"
},
  "geometry": {"coordinates":[-1.29369093326667,52.24536607881523],"type":"Point"}
}