{
  "type": "Feature",
  "properties": {
    "iso:country": "GB",
    "wof:name": "NN11 6EB",
    "wof:placetype": "postalcode"
  },
  "geometry": {"coordinates":[-1.293691,52.245366],"type":"Point"}
}
