{
  "type": "Feature",
  "properties": {
    "date:inception_lower": "1980-01-01",
    "date:inception_upper": "1980-01-01",
    "iso:country": "GB",
    "wof:name": "NN11 6EB",
    "wof:placetype": "postalcode"
  },
  "geometry": {"coordinates":[-1.293691,52.245366],"type":"Point"}
}
