{
  "type": "Feature",
  "properties": {
    "iso:country":"GB",
    "wof:name":"SY11 4LT",
    "wof:placetype":"postalcode"
},
  "geometry": {"coordinates":[-3.01393828392303,52.85397918897082],"type":"Point"}
}