{
  "type": "Feature",
  "properties": {
    "date:inception_lower": "1985-04-01",
    "date:inception_upper": "1985-04-01",
    "iso:country": "GB",
    "wof:name": "AL4 9BL",
    "wof:placetype": "postalcode"
  },
  "geometry": {"coordinates":[-0.297807,51.770987],"type":"Point"}
}
