{
  "type": "Feature",
  "properties": {
    "iso:country":"GB",
    "wof:name":"AL4 9BL",
    "wof:placetype":"postalcode"
},
  "geometry": {"coordinates":[-0.29780710314459,51.77098697068613],"type":"Point"}
}