{
  "type": "Feature",
  "properties": {
    "iso:country":"GB",
    "wof:name":"L39 4UD",
    "wof:placetype":"postalcode"
},
  "geometry": {"coordinates":[-2.88913568843122,53.55271820942396],"type":"Point"}
}