{
  "type": "Feature",
  "properties": {
    "iso:country": "GB",
    "wof:name": "L39 4UD",
    "wof:placetype": "postalcode"
  },
  "geometry": {"coordinates":[-2.889136,53.552718],"type":"Point"}
}
