{
  "type": "Feature",
  "properties": {
    "iso:country": "GB",
    "wof:name": "N15 5QH",
    "wof:placetype": "postalcode"
  },
  "geometry": {"coordinates":[-0.083707,51.58208],"type":"Point"}
}
