{
  "type": "Feature",
  "properties": {
    "iso:country": "GB",
    "wof:name": "TN22 4HQ",
    "wof:placetype": "postalcode"
  },
  "geometry": {"coordinates":[0.1835,50.996523],"type":"Point"}
}
