{
  "type": "Feature",
  "properties": {
    "iso:country":"GB",
    "wof:name":"TN15 6DP",
    "wof:placetype":"postalcode"
},
  "geometry": {"coordinates":[0.25716567982628,51.35353869889256],"type":"Point"}
}