{
  "type": "Feature",
  "properties": {
    "iso:country":"GB",
    "wof:name":"NR19 1HL",
    "wof:placetype":"postalcode"
},
  "geometry": {"coordinates":[0.95590721704387,52.6699595091833],"type":"Point"}
}