{
  "type": "Feature",
  "properties": {
    "iso:country":"GB",
    "wof:name":"DH3 4ST",
    "wof:placetype":"postalcode"
},
  "geometry": {"coordinates":[-1.53602017383594,54.83439094619632],"type":"Point"}
}