{
  "type": "Feature",
  "properties": {
    "date:inception_lower":"1992-08-01",
    "date:inception_upper":"1992-08-31",
    "iso:country":"GB",
    "wof:name":"LE7 3WR",
    "wof:placetype":"postalcode"
},
  "geometry": {"coordinates":[-1.054587,52.719288],"type":"Point"}
}