{
  "type": "Feature",
  "properties": {
    "iso:country": "GB",
    "wof:name": "LL20 7PW",
    "wof:placetype": "postalcode"
  },
  "geometry": {"coordinates":[-3.151696,52.967711],"type":"Point"}
}
