{
  "type": "Feature",
  "properties": {
    "date:inception_lower":"1980-01-01",
    "date:inception_upper":"1980-01-31",
    "iso:country":"GB",
    "wof:name":"LL20 7PW",
    "wof:placetype":"postalcode"
},
  "geometry": {"coordinates":[-3.151696,52.967711],"type":"Point"}
}