{
  "type": "Feature",
  "properties": {
    "iso:country":"GB",
    "wof:name":"LL20 7PW",
    "wof:placetype":"postalcode"
},
  "geometry": {"coordinates":[-3.15166578176164,52.96771130364384],"type":"Point"}
}