{
  "type": "Feature",
  "properties": {
    "iso:country":"GB",
    "wof:name":"NW6 6SP",
    "wof:placetype":"postalcode"
},
  "geometry": {"coordinates":[-0.21310744978901,51.53383669634858],"type":"Point"}
}