{
  "type": "Feature",
  "properties": {
    "iso:country":"GB",
    "wof:name":"CT5 3ES",
    "wof:placetype":"postalcode"
},
  "geometry": {"coordinates":[1.06956169736842,51.33685672442796],"type":"Point"}
}