{
  "type": "Feature",
  "properties": {
    "iso:country": "GB",
    "wof:name": "CT5 3ES",
    "wof:placetype": "postalcode"
  },
  "geometry": {"coordinates":[1.069579,51.33687],"type":"Point"}
}
