{
  "type": "Feature",
  "properties": {
    "date:inception_lower":"1980-01-01",
    "date:inception_upper":"1980-01-31",
    "iso:country":"GB",
    "wof:name":"CT5 3ES",
    "wof:placetype":"postalcode"
},
  "geometry": {"coordinates":[1.069579,51.33687],"type":"Point"}
}