{
  "type": "Feature",
  "properties": {
    "iso:country":"GB",
    "wof:name":"RG31 6FN",
    "wof:placetype":"postalcode"
},
  "geometry": {"coordinates":[-1.05249136669393,51.47015479525686],"type":"Point"}
}