{
  "type": "Feature",
  "properties": {
    "iso:country":"GB",
    "wof:name":"NE1 3PN",
    "wof:placetype":"postalcode"
},
  "geometry": {"coordinates":[-1.61582553757946,54.96529540166907],"type":"Point"}
}