{
  "type": "Feature",
  "properties": {
    "date:inception_lower": "2008-07-01",
    "date:inception_upper": "2008-07-01",
    "iso:country": "GB",
    "wof:name": "NE1 3PN",
    "wof:placetype": "postalcode"
  },
  "geometry": {"coordinates":[-1.615825,54.965295],"type":"Point"}
}
