{
  "type": "Feature",
  "properties": {
    "iso:country":"GB",
    "wof:name":"PH3 1PE",
    "wof:placetype":"postalcode"
},
  "geometry": {"coordinates":[-3.69937524714421,56.29288287252452],"type":"Point"}
}