{
  "type": "Feature",
  "properties": {
    "iso:country": "GB",
    "wof:name": "PH3 1PE",
    "wof:placetype": "postalcode"
  },
  "geometry": {"coordinates":[-3.699375,56.292883],"type":"Point"}
}
