{
  "type": "Feature",
  "properties": {
    "iso:country":"GB",
    "wof:name":"LU6 1QQ",
    "wof:placetype":"postalcode"
},
  "geometry": {"coordinates":[-0.57515859015542,51.88585697042917],"type":"Point"}
}