{
  "type": "Feature",
  "properties": {
    "iso:country": "GB",
    "wof:name": "PO2 0PP",
    "wof:placetype": "postalcode"
  },
  "geometry": {"coordinates":[-1.071034,50.8191],"type":"Point"}
}
