{
  "type": "Feature",
  "properties": {
    "iso:country":"GB",
    "wof:name":"GL51 8DN",
    "wof:placetype":"postalcode"
},
  "geometry": {"coordinates":[-2.10369465721101,51.90606825179966],"type":"Point"}
}