{
  "type": "Feature",
  "properties": {
    "iso:country":"GB",
    "wof:name":"NW9 8LT",
    "wof:placetype":"postalcode"
},
  "geometry": {"coordinates":[-0.26058549418022,51.57434125970113],"type":"Point"}
}