{
  "type": "Feature",
  "properties": {
    "iso:country":"GB",
    "wof:name":"LL41 3YY",
    "wof:placetype":"postalcode"
},
  "geometry": {"coordinates":[-4.01999698259311,52.94055026714463],"type":"Point"}
}