{
  "type": "Feature",
  "properties": {
    "date:inception_lower": "1980-01-01",
    "date:inception_upper": "1980-01-01",
    "iso:country": "GB",
    "wof:name": "LL41 3YY",
    "wof:placetype": "postalcode"
  },
  "geometry": {"coordinates":[-4.019997,52.94055],"type":"Point"}
}
