{
  "type": "Feature",
  "properties": {
    "iso:country": "GB",
    "wof:name": "N3 2DG",
    "wof:placetype": "postalcode"
  },
  "geometry": {"coordinates":[-0.188311,51.603075],"type":"Point"}
}
