{
  "type": "Feature",
  "properties": {
    "iso:country":"GB",
    "wof:name":"PR2 8JX",
    "wof:placetype":"postalcode"
},
  "geometry": {"coordinates":[-2.71246484192592,53.77830490266452],"type":"Point"}
}