{
  "type": "Feature",
  "properties": {
    "date:inception_lower": "1995-01-01",
    "date:inception_upper": "1995-01-01",
    "iso:country": "GB",
    "wof:name": "PR2 8JX",
    "wof:placetype": "postalcode"
  },
  "geometry": {"coordinates":[-2.712465,53.778305],"type":"Point"}
}
