{
  "type": "Feature",
  "properties": {
    "iso:country":"GB",
    "wof:name":"EH22 4NX",
    "wof:placetype":"postalcode"
},
  "geometry": {"coordinates":[-3.06312953569867,55.86040977713365],"type":"Point"}
}