{
  "type": "Feature",
  "properties": {
    "date:inception_lower": "1980-01-01",
    "date:inception_upper": "1980-01-01",
    "iso:country": "GB",
    "wof:name": "KY8 4SW",
    "wof:placetype": "postalcode"
  },
  "geometry": {"coordinates":[-2.993628,56.201312],"type":"Point"}
}
