{
  "type": "Feature",
  "properties": {
    "iso:country":"GB",
    "wof:name":"KY8 4SW",
    "wof:placetype":"postalcode"
},
  "geometry": {"coordinates":[-2.99373146098018,56.20156251235494],"type":"Point"}
}