{
  "type": "Feature",
  "properties": {
    "iso:country":"GB",
    "wof:name":"HD2 1NR",
    "wof:placetype":"postalcode"
},
  "geometry": {"coordinates":[-1.77240973139948,53.67315957317908],"type":"Point"}
}