{
  "type": "Feature",
  "properties": {
    "date:inception_lower": "1995-01-01",
    "date:inception_upper": "1995-01-01",
    "iso:country": "GB",
    "wof:name": "SG10 6HD",
    "wof:placetype": "postalcode"
  },
  "geometry": {"coordinates":[0.071792,51.867431],"type":"Point"}
}
