{
  "type": "Feature",
  "properties": {
    "iso:country":"GB",
    "wof:name":"SG10 6HD",
    "wof:placetype":"postalcode"
},
  "geometry": {"coordinates":[0.07179165340141,51.86743122295091],"type":"Point"}
}