{
  "type": "Feature",
  "properties": {
    "date:inception_lower":"1980-01-01",
    "date:inception_upper":"1980-01-31",
    "iso:country":"GB",
    "wof:name":"BD1 4DR",
    "wof:placetype":"postalcode"
},
  "geometry": {"coordinates":[-1.748756,53.796914],"type":"Point"}
}