{
  "type": "Feature",
  "properties": {
    "date:inception_lower": "1980-01-01",
    "date:inception_upper": "1980-01-01",
    "iso:country": "GB",
    "wof:name": "S5 9AY",
    "wof:placetype": "postalcode"
  },
  "geometry": {"coordinates":[-1.481784,53.436812],"type":"Point"}
}
