{
  "type": "Feature",
  "properties": {
    "date:inception_lower": "1980-01-01",
    "date:inception_upper": "1980-01-01",
    "iso:country": "GB",
    "wof:name": "CV31 1LW",
    "wof:placetype": "postalcode"
  },
  "geometry": {"coordinates":[-1.530605,52.283924],"type":"Point"}
}
