{
  "type": "Feature",
  "properties": {
    "iso:country":"GB",
    "wof:name":"CV31 1LW",
    "wof:placetype":"postalcode"
},
  "geometry": {"coordinates":[-1.53106889062934,52.2840818539192],"type":"Point"}
}