{
  "type": "Feature",
  "properties": {
    "iso:country":"GB",
    "wof:name":"CH4 7RA",
    "wof:placetype":"postalcode"
},
  "geometry": {"coordinates":[-2.9033680128615,53.17337739281451],"type":"Point"}
}