{
  "type": "Feature",
  "properties": {
    "date:inception_lower":"1980-01-01",
    "date:inception_upper":"1980-01-31",
    "iso:country":"GB",
    "wof:name":"CH4 7RA",
    "wof:placetype":"postalcode"
},
  "geometry": {"coordinates":[-2.903368,53.173377],"type":"Point"}
}