{
  "type": "Feature",
  "properties": {
    "iso:country":"GB",
    "wof:name":"DN21 1FZ",
    "wof:placetype":"postalcode"
},
  "geometry": {"coordinates":[-0.76350104541416,53.41035069081278],"type":"Point"}
}