{
  "type": "Feature",
  "properties": {
    "date:inception_lower": "2017-04-01",
    "date:inception_upper": "2017-04-01",
    "iso:country": "GB",
    "wof:name": "NG22 0BZ",
    "wof:placetype": "postalcode"
  },
  "geometry": {"coordinates":[-0.993167,53.149784],"type":"Point"}
}
