{
  "type": "Feature",
  "properties": {
    "iso:country":"GB",
    "wof:name":"NN11 4DT",
    "wof:placetype":"postalcode"
},
  "geometry": {"coordinates":[-1.15853764961002,52.25279664693294],"type":"Point"}
}