{
  "type": "Feature",
  "properties": {
    "iso:country":"GB",
    "wof:name":"DL9 4AP",
    "wof:placetype":"postalcode"
},
  "geometry": {"coordinates":[-1.72043587264685,54.37846294943142],"type":"Point"}
}