{
  "type": "Feature",
  "properties": {
    "iso:country": "GB",
    "wof:name": "DL9 4AP",
    "wof:placetype": "postalcode"
  },
  "geometry": {"coordinates":[-1.720436,54.378463],"type":"Point"}
}
