{
  "type": "Feature",
  "properties": {
    "iso:country":"GB",
    "wof:name":"CH60 2UH",
    "wof:placetype":"postalcode"
},
  "geometry": {"coordinates":[-3.08512683305481,53.32309495400717],"type":"Point"}
}