{
  "type": "Feature",
  "properties": {
    "iso:country": "GB",
    "wof:name": "CH60 2UH",
    "wof:placetype": "postalcode"
  },
  "geometry": {"coordinates":[-3.085127,53.323095],"type":"Point"}
}
