{
  "type": "Feature",
  "properties": {
    "date:inception_lower":"1999-06-01",
    "date:inception_upper":"1999-06-30",
    "iso:country":"GB",
    "wof:name":"CH60 2UH",
    "wof:placetype":"postalcode"
},
  "geometry": {"coordinates":[-3.085127,53.323095],"type":"Point"}
}