{
  "type": "Feature",
  "properties": {
    "iso:country":"GB",
    "wof:name":"HU7 0DS",
    "wof:placetype":"postalcode"
},
  "geometry": {"coordinates":[-0.32219418566123,53.77221911129089],"type":"Point"}
}