{
  "type": "Feature",
  "properties": {
    "iso:country": "GB",
    "wof:name": "TA1 2QD",
    "wof:placetype": "postalcode"
  },
  "geometry": {"coordinates":[-3.080778,51.007724],"type":"Point"}
}
