{
  "type": "Feature",
  "properties": {
    "iso:country": "GB",
    "wof:name": "E16 2ZA",
    "wof:placetype": "postalcode"
  },
  "geometry": {"coordinates":[0.027099,51.50059],"type":"Point"}
}
