{
  "type": "Feature",
  "properties": {
    "iso:country": "GB",
    "wof:name": "SN13 8EH",
    "wof:placetype": "postalcode"
  },
  "geometry": {"coordinates":[-2.250229,51.413128],"type":"Point"}
}
