{
  "type": "Feature",
  "properties": {
    "date:inception_lower": "1987-04-01",
    "date:inception_upper": "1987-04-01",
    "iso:country": "GB",
    "wof:name": "MK16 0NT",
    "wof:placetype": "postalcode"
  },
  "geometry": {"coordinates":[-0.733831,52.076307],"type":"Point"}
}
