{
  "type": "Feature",
  "properties": {
    "iso:country": "GB",
    "wof:name": "YO16 7BX",
    "wof:placetype": "postalcode"
  },
  "geometry": {"coordinates":[-0.199257,54.09327],"type":"Point"}
}
