{
  "type": "Feature",
  "properties": {
    "iso:country":"GB",
    "wof:name":"YO16 7BX",
    "wof:placetype":"postalcode"
},
  "geometry": {"coordinates":[-0.19925716588388,54.09327045188292],"type":"Point"}
}