{
  "type": "Feature",
  "properties": {
    "iso:country":"GB",
    "wof:name":"OX7 6JH",
    "wof:placetype":"postalcode"
},
  "geometry": {"coordinates":[-1.61587053138292,51.86236775301841],"type":"Point"}
}