{
  "type": "Feature",
  "properties": {
    "date:inception_lower":"1992-08-01",
    "date:inception_upper":"1992-08-31",
    "iso:country":"GB",
    "wof:name":"DE72 2HN",
    "wof:placetype":"postalcode"
},
  "geometry": {"coordinates":[-1.33071,52.862602],"type":"Point"}
}