{
  "type": "Feature",
  "properties": {
    "iso:country":"GB",
    "wof:name":"DE72 2HN",
    "wof:placetype":"postalcode"
},
  "geometry": {"coordinates":[-1.33070995976596,52.86260159922862],"type":"Point"}
}