{
  "type": "Feature",
  "properties": {
    "iso:country":"GB",
    "wof:name":"DL10 4QU",
    "wof:placetype":"postalcode"
},
  "geometry": {"coordinates":[-1.73945236922803,54.40225833055496],"type":"Point"}
}