{
  "type": "Feature",
  "properties": {
    "iso:country": "GB",
    "wof:name": "DL10 4QU",
    "wof:placetype": "postalcode"
  },
  "geometry": {"coordinates":[-1.739452,54.402258],"type":"Point"}
}
