{
  "type": "Feature",
  "properties": {
    "iso:country":"GB",
    "wof:name":"TF4 3QJ",
    "wof:placetype":"postalcode"
},
  "geometry": {"coordinates":[-2.47606942865916,52.6509713580961],"type":"Point"}
}