{
  "type": "Feature",
  "properties": {
    "iso:country":"GB",
    "wof:name":"BB5 2LG",
    "wof:placetype":"postalcode"
},
  "geometry": {"coordinates":[-2.36111359063418,53.74389038560192],"type":"Point"}
}