{
  "type": "Feature",
  "properties": {
    "iso:country":"GB",
    "wof:name":"HA7 1HQ",
    "wof:placetype":"postalcode"
},
  "geometry": {"coordinates":[-0.28745602401228,51.59162389394957],"type":"Point"}
}