{
  "type": "Feature",
  "properties": {
    "iso:country": "GB",
    "wof:name": "L33 1TF",
    "wof:placetype": "postalcode"
  },
  "geometry": {"coordinates":[-2.874344,53.494922],"type":"Point"}
}
