{
  "type": "Feature",
  "properties": {
    "iso:country":"GB",
    "wof:name":"IP13 0PB",
    "wof:placetype":"postalcode"
},
  "geometry": {"coordinates":[1.38237727144376,52.15861916940328],"type":"Point"}
}