{
  "type": "Feature",
  "properties": {
    "date:inception_lower": "1992-08-01",
    "date:inception_upper": "1992-08-01",
    "iso:country": "GB",
    "wof:name": "DE75 7BS",
    "wof:placetype": "postalcode"
  },
  "geometry": {"coordinates":[-1.348506,53.006199],"type":"Point"}
}
