{
  "type": "Feature",
  "properties": {
    "iso:country":"GB",
    "wof:name":"DE75 7BS",
    "wof:placetype":"postalcode"
},
  "geometry": {"coordinates":[-1.34850625099311,53.00619867678537],"type":"Point"}
}