{
  "type": "Feature",
  "properties": {
    "iso:country":"GB",
    "wof:name":"MK15 0BD",
    "wof:placetype":"postalcode"
},
  "geometry": {"coordinates":[-0.72990168743569,52.04405897711803],"type":"Point"}
}