{
  "type": "Feature",
  "properties": {
    "date:inception_lower": "1984-10-01",
    "date:inception_upper": "1984-10-01",
    "iso:country": "GB",
    "wof:name": "MK15 0BD",
    "wof:placetype": "postalcode"
  },
  "geometry": {"coordinates":[-0.729902,52.044059],"type":"Point"}
}
