{
  "type": "Feature",
  "properties": {
    "iso:country":"GB",
    "wof:name":"BN25 2PE",
    "wof:placetype":"postalcode"
},
  "geometry": {"coordinates":[0.09387125939944,50.77585060503129],"type":"Point"}
}