{
  "type": "Feature",
  "properties": {
    "iso:country":"GB",
    "wof:name":"BL3 3RR",
    "wof:placetype":"postalcode"
},
  "geometry": {"coordinates":[-2.45790866163629,53.55953380090891],"type":"Point"}
}