{
  "type": "Feature",
  "properties": {
    "iso:country":"GB",
    "wof:name":"LA1 5NX",
    "wof:placetype":"postalcode"
},
  "geometry": {"coordinates":[-2.81161160077532,54.04870940781563],"type":"Point"}
}