{
  "type": "Feature",
  "properties": {
    "date:inception_lower": "1980-01-01",
    "date:inception_upper": "1980-01-01",
    "iso:country": "GB",
    "wof:name": "LA1 5NX",
    "wof:placetype": "postalcode"
  },
  "geometry": {"coordinates":[-2.811612,54.048709],"type":"Point"}
}
