{
  "type": "Feature",
  "properties": {
    "iso:country": "GB",
    "wof:name": "CB8 0FJ",
    "wof:placetype": "postalcode"
  },
  "geometry": {"coordinates":[0.390549,52.240905],"type":"Point"}
}
