{
  "type": "Feature",
  "properties": {
    "iso:country":"GB",
    "wof:name":"WR5 3EF",
    "wof:placetype":"postalcode"
},
  "geometry": {"coordinates":[-2.22041767176724,52.17869244167368],"type":"Point"}
}