{
  "type": "Feature",
  "properties": {
    "date:inception_lower": "2010-07-01",
    "date:inception_upper": "2010-07-01",
    "iso:country": "GB",
    "wof:name": "AB12 4AB",
    "wof:placetype": "postalcode"
  },
  "geometry": {"coordinates":[-2.135467,57.070771],"type":"Point"}
}
