{
  "type": "Feature",
  "properties": {
    "iso:country":"GB",
    "wof:name":"AB12 4AB",
    "wof:placetype":"postalcode"
},
  "geometry": {"coordinates":[-2.13546675820703,57.07077056637642],"type":"Point"}
}