{
  "type": "Feature",
  "properties": {
    "iso:country":"GB",
    "wof:name":"OX16 0HB",
    "wof:placetype":"postalcode"
},
  "geometry": {"coordinates":[-1.35213549785971,52.06473841922247],"type":"Point"}
}