{
  "type": "Feature",
  "properties": {
    "date:inception_lower": "1980-01-01",
    "date:inception_upper": "1980-01-01",
    "iso:country": "GB",
    "wof:name": "CT9 3EY",
    "wof:placetype": "postalcode"
  },
  "geometry": {"coordinates":[1.42364,51.38623],"type":"Point"}
}
