{
  "type": "Feature",
  "properties": {
    "iso:country": "GB",
    "wof:name": "CT9 3EY",
    "wof:placetype": "postalcode"
  },
  "geometry": {"coordinates":[1.42364,51.38623],"type":"Point"}
}
