{
  "type": "Feature",
  "properties": {
    "iso:country":"GB",
    "wof:name":"CT9 3EY",
    "wof:placetype":"postalcode"
},
  "geometry": {"coordinates":[1.42361411583724,51.38622287343312],"type":"Point"}
}