{
  "type": "Feature",
  "properties": {
    "date:inception_lower": "1980-01-01",
    "date:inception_upper": "1980-01-01",
    "iso:country": "GB",
    "wof:name": "CT9 3EY",
    "wof:placetype": "postalcode"
  },
  "geometry": {"coordinates":[1.423457,51.38628],"type":"Point"}
}
