{
  "type": "Feature",
  "properties": {
    "iso:country": "GB",
    "wof:name": "M16 7RZ",
    "wof:placetype": "postalcode"
  },
  "geometry": {"coordinates":[-2.263953,53.455629],"type":"Point"}
}
