{
  "type": "Feature",
  "properties": {
    "iso:country":"GB",
    "wof:name":"M16 7RZ",
    "wof:placetype":"postalcode"
},
  "geometry": {"coordinates":[-2.26395275504877,53.45562906068336],"type":"Point"}
}