{
  "type": "Feature",
  "properties": {
    "iso:country":"GB",
    "wof:name":"SA69 9HF",
    "wof:placetype":"postalcode"
},
  "geometry": {"coordinates":[-4.70268505161457,51.71341627176592],"type":"Point"}
}