{
  "type": "Feature",
  "properties": {
    "iso:country":"GB",
    "wof:name":"N12 8EB",
    "wof:placetype":"postalcode"
},
  "geometry": {"coordinates":[-0.17975792250659,51.61330218899906],"type":"Point"}
}