{
  "type": "Feature",
  "properties": {
    "iso:country": "GB",
    "wof:name": "N12 8EB",
    "wof:placetype": "postalcode"
  },
  "geometry": {"coordinates":[-0.179758,51.613302],"type":"Point"}
}
