{
  "type": "Feature",
  "properties": {
    "iso:country":"GB",
    "wof:name":"L13 3AX",
    "wof:placetype":"postalcode"
},
  "geometry": {"coordinates":[-2.92737722370974,53.41421633464945],"type":"Point"}
}