{
  "type": "Feature",
  "properties": {
    "iso:country":"GB",
    "wof:name":"OX16 4SL",
    "wof:placetype":"postalcode"
},
  "geometry": {"coordinates":[-1.32622337577963,52.06215670223512],"type":"Point"}
}