{
  "type": "Feature",
  "properties": {
    "iso:country": "GB",
    "wof:name": "OX16 4SL",
    "wof:placetype": "postalcode"
  },
  "geometry": {"coordinates":[-1.326223,52.062157],"type":"Point"}
}
