{
  "type": "Feature",
  "properties": {
    "date:inception_lower": "2021-06-01",
    "date:inception_upper": "2021-06-01",
    "iso:country": "GB",
    "wof:name": "LS16 9FR",
    "wof:placetype": "postalcode"
  },
  "geometry": {"coordinates":[-1.604287,53.881584],"type":"Point"}
}
