{
  "type": "Feature",
  "properties": {
    "iso:country":"GB",
    "wof:name":"SO17 2HU",
    "wof:placetype":"postalcode"
},
  "geometry": {"coordinates":[-1.38711007410543,50.9217796546669],"type":"Point"}
}