{
  "type": "Feature",
  "properties": {
    "iso:country": "GB",
    "wof:name": "SO17 2HU",
    "wof:placetype": "postalcode"
  },
  "geometry": {"coordinates":[-1.38711,50.92178],"type":"Point"}
}
