{
  "type": "Feature",
  "properties": {
    "date:inception_lower":"1980-01-01",
    "date:inception_upper":"1980-01-31",
    "iso:country":"GB",
    "wof:name":"TW4 5NY",
    "wof:placetype":"postalcode"
},
  "geometry": {"coordinates":[-0.383441,51.446789],"type":"Point"}
}