{
  "type": "Feature",
  "properties": {
    "iso:country":"GB",
    "wof:name":"TW4 5NY",
    "wof:placetype":"postalcode"
},
  "geometry": {"coordinates":[-0.38344106198464,51.44678931193988],"type":"Point"}
}