{
  "type": "Feature",
  "properties": {
    "iso:country": "GB",
    "wof:name": "TN6 2HJ",
    "wof:placetype": "postalcode"
  },
  "geometry": {"coordinates":[0.178196,51.05124],"type":"Point"}
}
