{
  "type": "Feature",
  "properties": {
    "iso:country":"GB",
    "wof:name":"GU26 6DG",
    "wof:placetype":"postalcode"
},
  "geometry": {"coordinates":[-0.7619664358533,51.09948491486389],"type":"Point"}
}