{
  "type": "Feature",
  "properties": {
    "iso:country": "GB",
    "wof:name": "PL18 9LA",
    "wof:placetype": "postalcode"
  },
  "geometry": {"coordinates":[-4.216867,50.525132],"type":"Point"}
}
