{
  "type": "Feature",
  "properties": {
    "iso:country":"GB",
    "wof:name":"PL18 9LA",
    "wof:placetype":"postalcode"
},
  "geometry": {"coordinates":[-4.21686732583666,50.52513209134597],"type":"Point"}
}