{
  "type": "Feature",
  "properties": {
    "date:inception_lower": "1980-01-01",
    "date:inception_upper": "1980-01-01",
    "iso:country": "GB",
    "wof:name": "LA12 0LT",
    "wof:placetype": "postalcode"
  },
  "geometry": {"coordinates":[-3.153096,54.173046],"type":"Point"}
}
