{
  "type": "Feature",
  "properties": {
    "date:inception_lower":"2014-10-01",
    "date:inception_upper":"2014-10-31",
    "iso:country":"GB",
    "wof:name":"WV14 0AN",
    "wof:placetype":"postalcode"
},
  "geometry": {"coordinates":[-2.066983,52.559072],"type":"Point"}
}