{
  "type": "Feature",
  "properties": {
    "iso:country": "GB",
    "wof:name": "NR34 8HX",
    "wof:placetype": "postalcode"
  },
  "geometry": {"coordinates":[1.497764,52.430013],"type":"Point"}
}
