{
  "type": "Feature",
  "properties": {
    "iso:country":"GB",
    "wof:name":"NR34 8HX",
    "wof:placetype":"postalcode"
},
  "geometry": {"coordinates":[1.4977637357726,52.43001336392721],"type":"Point"}
}