{
  "type": "Feature",
  "properties": {
    "date:inception_lower": "1980-01-01",
    "date:inception_upper": "1980-01-01",
    "iso:country": "GB",
    "wof:name": "L9 3BD",
    "wof:placetype": "postalcode"
  },
  "geometry": {"coordinates":[-2.968053,53.460276],"type":"Point"}
}
