{
  "type": "Feature",
  "properties": {
    "iso:country": "GB",
    "wof:name": "BR5 1DP",
    "wof:placetype": "postalcode"
  },
  "geometry": {"coordinates":[0.073008,51.383373],"type":"Point"}
}
