{
  "type": "Feature",
  "properties": {
    "iso:country":"GB",
    "wof:name":"BR5 1DP",
    "wof:placetype":"postalcode"
},
  "geometry": {"coordinates":[0.07300773816513,51.38337330934205],"type":"Point"}
}