{
  "type": "Feature",
  "properties": {
    "iso:country": "GB",
    "wof:name": "NP22 4AX",
    "wof:placetype": "postalcode"
  },
  "geometry": {"coordinates":[-3.248247,51.784977],"type":"Point"}
}
