{
  "type": "Feature",
  "properties": {
    "iso:country":"GB",
    "wof:name":"DH6 4HR",
    "wof:placetype":"postalcode"
},
  "geometry": {"coordinates":[-1.50919722058946,54.7212162009298],"type":"Point"}
}