{
  "type": "Feature",
  "properties": {
    "iso:country":"GB",
    "wof:name":"PO12 4EG",
    "wof:placetype":"postalcode"
},
  "geometry": {"coordinates":[-1.14318817017542,50.8084664651873],"type":"Point"}
}