{
  "type": "Feature",
  "properties": {
    "iso:country": "GB",
    "wof:name": "PO12 4EG",
    "wof:placetype": "postalcode"
  },
  "geometry": {"coordinates":[-1.143188,50.808466],"type":"Point"}
}
