{
  "type": "Feature",
  "properties": {
    "iso:country": "GB",
    "wof:name": "LS23 6FB",
    "wof:placetype": "postalcode"
  },
  "geometry": {"coordinates":[-1.344781,53.893933],"type":"Point"}
}
