{
  "type": "Feature",
  "properties": {
    "iso:country": "GB",
    "wof:name": "DN16 1EU",
    "wof:placetype": "postalcode"
  },
  "geometry": {"coordinates":[-0.637577,53.58017],"type":"Point"}
}
