{
  "type": "Feature",
  "properties": {
    "iso:country":"GB",
    "wof:name":"DY3 2PX",
    "wof:placetype":"postalcode"
},
  "geometry": {"coordinates":[-2.12728255921693,52.51297647555862],"type":"Point"}
}