{
  "type": "Feature",
  "properties": {
    "date:inception_lower":"1980-01-01",
    "date:inception_upper":"1980-01-31",
    "iso:country":"GB",
    "wof:name":"DY3 2PX",
    "wof:placetype":"postalcode"
},
  "geometry": {"coordinates":[-2.127247,52.513],"type":"Point"}
}