{
  "type": "Feature",
  "properties": {
    "iso:country": "GB",
    "wof:name": "DY3 2PX",
    "wof:placetype": "postalcode"
  },
  "geometry": {"coordinates":[-2.127247,52.513],"type":"Point"}
}
