{
  "type": "Feature",
  "properties": {
    "iso:country":"GB",
    "wof:name":"BN16 4HD",
    "wof:placetype":"postalcode"
},
  "geometry": {"coordinates":[-0.48450775459324,50.82411843135013],"type":"Point"}
}