{
  "type": "Feature",
  "properties": {
    "iso:country": "GB",
    "wof:name": "BN16 4HD",
    "wof:placetype": "postalcode"
  },
  "geometry": {"coordinates":[-0.484508,50.824118],"type":"Point"}
}
