{
  "type": "Feature",
  "properties": {
    "iso:country": "GB",
    "wof:name": "FK7 7RE",
    "wof:placetype": "postalcode"
  },
  "geometry": {"coordinates":[-3.930064,56.108786],"type":"Point"}
}
