{
  "type": "Feature",
  "properties": {
    "date:inception_lower":"1980-01-01",
    "date:inception_upper":"1980-01-31",
    "iso:country":"GB",
    "wof:name":"HU11 4TA",
    "wof:placetype":"postalcode"
},
  "geometry": {"coordinates":[-0.184401,53.847951],"type":"Point"}
}