{
  "type": "Feature",
  "properties": {
    "iso:country": "GB",
    "wof:name": "HU11 4TA",
    "wof:placetype": "postalcode"
  },
  "geometry": {"coordinates":[-0.184401,53.847951],"type":"Point"}
}
