{
  "type": "Feature",
  "properties": {
    "iso:country": "GB",
    "wof:name": "KA18 2BL",
    "wof:placetype": "postalcode"
  },
  "geometry": {"coordinates":[-4.293429,55.467146],"type":"Point"}
}
