{
  "type": "Feature",
  "properties": {
    "date:inception_lower":"2016-09-01",
    "date:inception_upper":"2016-09-30",
    "iso:country":"GB",
    "wof:name":"KA18 2BL",
    "wof:placetype":"postalcode"
},
  "geometry": {"coordinates":[-4.293429,55.467146],"type":"Point"}
}