{
  "type": "Feature",
  "properties": {
    "iso:country":"GB",
    "wof:name":"SW3 3JD",
    "wof:placetype":"postalcode"
},
  "geometry": {"coordinates":[-0.16344104050695,51.49106577143094],"type":"Point"}
}