{
  "type": "Feature",
  "properties": {
    "iso:country":"GB",
    "wof:name":"DT8 3PP",
    "wof:placetype":"postalcode"
},
  "geometry": {"coordinates":[-2.75314182924451,50.81096763638848],"type":"Point"}
}