{
  "type": "Feature",
  "properties": {
    "date:inception_lower": "1980-01-01",
    "date:inception_upper": "1980-01-01",
    "iso:country": "GB",
    "wof:name": "SP11 8DR",
    "wof:placetype": "postalcode"
  },
  "geometry": {"coordinates":[-1.560945,51.21658],"type":"Point"}
}
