{
  "type": "Feature",
  "properties": {
    "iso:country":"GB",
    "wof:name":"SP11 8DR",
    "wof:placetype":"postalcode"
},
  "geometry": {"coordinates":[-1.56094517795395,51.21657972872492],"type":"Point"}
}