{
  "type": "Feature",
  "properties": {
    "iso:country": "GB",
    "wof:name": "NR5 0BG",
    "wof:placetype": "postalcode"
  },
  "geometry": {"coordinates":[1.237827,52.645544],"type":"Point"}
}
