{
  "type": "Feature",
  "properties": {
    "date:inception_lower": "1980-01-01",
    "date:inception_upper": "1980-01-01",
    "iso:country": "GB",
    "wof:name": "BL3 1HB",
    "wof:placetype": "postalcode"
  },
  "geometry": {"coordinates":[-2.380404,53.559563],"type":"Point"}
}
