{
  "type": "Feature",
  "properties": {
    "date:inception_lower":"1980-01-01",
    "date:inception_upper":"1980-01-31",
    "iso:country":"GB",
    "wof:name":"M60 9AH",
    "wof:placetype":"postalcode"
},
  "geometry": {"coordinates":[-2.245686,53.492188],"type":"Point"}
}