{
  "type": "Feature",
  "properties": {
    "iso:country": "GB",
    "wof:name": "M60 9AH",
    "wof:placetype": "postalcode"
  },
  "geometry": {"coordinates":[-2.245686,53.492188],"type":"Point"}
}
