{
  "type": "Feature",
  "properties": {
    "iso:country":"GB",
    "wof:name":"TS4 3PN",
    "wof:placetype":"postalcode"
},
  "geometry": {"coordinates":[-1.2202332673449,54.54602043166493],"type":"Point"}
}