{
  "type": "Feature",
  "properties": {
    "date:inception_lower": "1980-01-01",
    "date:inception_upper": "1980-01-01",
    "iso:country": "GB",
    "wof:name": "IP13 9LP",
    "wof:placetype": "postalcode"
  },
  "geometry": {"coordinates":[1.339037,52.198692],"type":"Point"}
}
