{
  "type": "Feature",
  "properties": {
    "iso:country": "GB",
    "wof:name": "NR6 7HP",
    "wof:placetype": "postalcode"
  },
  "geometry": {"coordinates":[1.304724,52.670488],"type":"Point"}
}
