{
  "type": "Feature",
  "properties": {
    "iso:country":"GB",
    "wof:name":"NR6 7HP",
    "wof:placetype":"postalcode"
},
  "geometry": {"coordinates":[1.30472364172512,52.67048781733019],"type":"Point"}
}