{
  "type": "Feature",
  "properties": {
    "date:inception_lower": "1990-02-01",
    "date:inception_upper": "1990-02-01",
    "iso:country": "GB",
    "wof:name": "CF5 4ND",
    "wof:placetype": "postalcode"
  },
  "geometry": {"coordinates":[-3.26231,51.466509],"type":"Point"}
}
