{
  "type": "Feature",
  "properties": {
    "iso:country":"GB",
    "wof:name":"TN29 0EL",
    "wof:placetype":"postalcode"
},
  "geometry": {"coordinates":[0.83906843291193,51.03095833320173],"type":"Point"}
}