{
  "type": "Feature",
  "properties": {
    "iso:country": "GB",
    "wof:name": "NP12 2XN",
    "wof:placetype": "postalcode"
  },
  "geometry": {"coordinates":[-3.187996,51.648851],"type":"Point"}
}
