{
  "type": "Feature",
  "properties": {
    "iso:country":"GB",
    "wof:name":"B28 8PY",
    "wof:placetype":"postalcode"
},
  "geometry": {"coordinates":[-1.83118783906328,52.43393025161886],"type":"Point"}
}