{
  "type": "Feature",
  "properties": {
    "iso:country": "GB",
    "wof:name": "CV32 6NS",
    "wof:placetype": "postalcode"
  },
  "geometry": {"coordinates":[-1.530113,52.303776],"type":"Point"}
}
