{
  "type": "Feature",
  "properties": {
    "iso:country":"GB",
    "wof:name":"HU9 4ST",
    "wof:placetype":"postalcode"
},
  "geometry": {"coordinates":[-0.27015285883621,53.76650843285831],"type":"Point"}
}