{
  "type": "Feature",
  "properties": {
    "date:inception_lower":"1997-12-01",
    "date:inception_upper":"1997-12-31",
    "iso:country":"GB",
    "wof:name":"BS20 7TX",
    "wof:placetype":"postalcode"
},
  "geometry": {"coordinates":[-2.720698,51.472735],"type":"Point"}
}