{
  "type": "Feature",
  "properties": {
    "iso:country":"GB",
    "wof:name":"BS20 7TX",
    "wof:placetype":"postalcode"
},
  "geometry": {"coordinates":[-2.72069768355263,51.47273543526688],"type":"Point"}
}