{
  "type": "Feature",
  "properties": {
    "iso:country":"GB",
    "wof:name":"HG5 9JX",
    "wof:placetype":"postalcode"
},
  "geometry": {"coordinates":[-1.43906136613708,54.05768343763838],"type":"Point"}
}