{
  "type": "Feature",
  "properties": {
    "iso:country":"GB",
    "wof:name":"TA7 9HA",
    "wof:placetype":"postalcode"
},
  "geometry": {"coordinates":[-2.8757762612086,51.15023399508168],"type":"Point"}
}