{
  "type": "Feature",
  "properties": {
    "iso:country": "GB",
    "wof:name": "NP8 1ES",
    "wof:placetype": "postalcode"
  },
  "geometry": {"coordinates":[-3.100753,51.841969],"type":"Point"}
}
