{
  "type": "Feature",
  "properties": {
    "iso:country":"GB",
    "wof:name":"NP8 1ES",
    "wof:placetype":"postalcode"
},
  "geometry": {"coordinates":[-3.09830454336483,51.84064652301684],"type":"Point"}
}