{
  "type": "Feature",
  "properties": {
    "date:inception_lower": "1980-01-01",
    "date:inception_upper": "1980-01-01",
    "iso:country": "GB",
    "wof:name": "DL2 3AJ",
    "wof:placetype": "postalcode"
  },
  "geometry": {"coordinates":[-1.830294,54.591729],"type":"Point"}
}
