{
  "type": "Feature",
  "properties": {
    "iso:country":"GB",
    "wof:name":"DL2 3AJ",
    "wof:placetype":"postalcode"
},
  "geometry": {"coordinates":[-1.8302941228364,54.59172935196371],"type":"Point"}
}