{
  "type": "Feature",
  "properties": {
    "iso:country":"GB",
    "wof:name":"DN41 7RB",
    "wof:placetype":"postalcode"
},
  "geometry": {"coordinates":[-0.16182080960329,53.58115934971558],"type":"Point"}
}