{
  "type": "Feature",
  "properties": {
    "date:inception_lower": "2015-04-01",
    "date:inception_upper": "2015-04-01",
    "iso:country": "GB",
    "wof:name": "TA11 6AT",
    "wof:placetype": "postalcode"
  },
  "geometry": {"coordinates":[-2.651713,51.086558],"type":"Point"}
}
