{
  "type": "Feature",
  "properties": {
    "iso:country": "GB",
    "wof:name": "TA11 6AT",
    "wof:placetype": "postalcode"
  },
  "geometry": {"coordinates":[-2.651713,51.086558],"type":"Point"}
}
