{
  "type": "Feature",
  "properties": {
    "iso:country":"GB",
    "wof:name":"TA11 6AT",
    "wof:placetype":"postalcode"
},
  "geometry": {"coordinates":[-2.65171348685561,51.08655820461701],"type":"Point"}
}