{
  "type": "Feature",
  "properties": {
    "iso:country": "GB",
    "wof:name": "OX18 2NY",
    "wof:placetype": "postalcode"
  },
  "geometry": {"coordinates":[-1.509651,51.725318],"type":"Point"}
}
