{
  "type": "Feature",
  "properties": {
    "iso:country":"GB",
    "wof:name":"OX18 2NY",
    "wof:placetype":"postalcode"
},
  "geometry": {"coordinates":[-1.50965084099345,51.72531770416473],"type":"Point"}
}