{
  "type": "Feature",
  "properties": {
    "date:inception_lower":"2008-09-01",
    "date:inception_upper":"2008-09-30",
    "iso:country":"GB",
    "wof:name":"OX18 2NY",
    "wof:placetype":"postalcode"
},
  "geometry": {"coordinates":[-1.509651,51.725318],"type":"Point"}
}