{
  "type": "Feature",
  "properties": {
    "date:inception_lower": "2010-05-01",
    "date:inception_upper": "2010-05-01",
    "iso:country": "GB",
    "wof:name": "BS23 2EB",
    "wof:placetype": "postalcode"
  },
  "geometry": {"coordinates":[-2.977324,51.356014],"type":"Point"}
}
