{
  "type": "Feature",
  "properties": {
    "iso:country":"GB",
    "wof:name":"BS23 2EB",
    "wof:placetype":"postalcode"
},
  "geometry": {"coordinates":[-2.977324206607,51.35601448364186],"type":"Point"}
}