{
  "type": "Feature",
  "properties": {
    "iso:country":"GB",
    "wof:name":"B71 1BF",
    "wof:placetype":"postalcode"
},
  "geometry": {"coordinates":[-1.99963214750026,52.53783032453538],"type":"Point"}
}