{
  "type": "Feature",
  "properties": {
    "date:inception_lower": "2007-02-01",
    "date:inception_upper": "2007-02-01",
    "iso:country": "GB",
    "wof:name": "B71 1BF",
    "wof:placetype": "postalcode"
  },
  "geometry": {"coordinates":[-1.999632,52.53783],"type":"Point"}
}
