{
  "type": "Feature",
  "properties": {
    "iso:country": "GB",
    "wof:name": "CF61 2ZB",
    "wof:placetype": "postalcode"
  },
  "geometry": {"coordinates":[-3.465045,51.418551],"type":"Point"}
}
