{
  "type": "Feature",
  "properties": {
    "date:inception_lower": "2016-06-01",
    "date:inception_upper": "2016-06-01",
    "iso:country": "GB",
    "wof:name": "CF61 2ZB",
    "wof:placetype": "postalcode"
  },
  "geometry": {"coordinates":[-3.465046,51.418569],"type":"Point"}
}
