{
  "type": "Feature",
  "properties": {
    "iso:country": "GB",
    "wof:name": "CO4 0ES",
    "wof:placetype": "postalcode"
  },
  "geometry": {"coordinates":[0.923366,51.902793],"type":"Point"}
}
