{
  "type": "Feature",
  "properties": {
    "iso:country":"GB",
    "wof:name":"CO4 0ES",
    "wof:placetype":"postalcode"
},
  "geometry": {"coordinates":[0.92336575806872,51.90279330348325],"type":"Point"}
}