{
  "type": "Feature",
  "properties": {
    "iso:country": "GB",
    "wof:name": "TN18 4LX",
    "wof:placetype": "postalcode"
  },
  "geometry": {"coordinates":[0.503096,51.039496],"type":"Point"}
}
