{
  "type": "Feature",
  "properties": {
    "iso:country":"GB",
    "wof:name":"CF5 1PQ",
    "wof:placetype":"postalcode"
},
  "geometry": {"coordinates":[-3.20553999703725,51.4788590402024],"type":"Point"}
}