{
  "type": "Feature",
  "properties": {
    "date:inception_lower": "1995-07-01",
    "date:inception_upper": "1995-07-01",
    "iso:country": "GB",
    "wof:name": "CW8 1SG",
    "wof:placetype": "postalcode"
  },
  "geometry": {"coordinates":[-2.535333,53.244105],"type":"Point"}
}
