{
  "type": "Feature",
  "properties": {
    "iso:country":"GB",
    "wof:name":"CW8 1SG",
    "wof:placetype":"postalcode"
},
  "geometry": {"coordinates":[-2.53533280171913,53.24410545073284],"type":"Point"}
}