{
  "type": "Feature",
  "properties": {
    "iso:country":"GB",
    "wof:name":"EN2 7AZ",
    "wof:placetype":"postalcode"
},
  "geometry": {"coordinates":[-0.0977787900656,51.65362812266456],"type":"Point"}
}