{
  "type": "Feature",
  "properties": {
    "date:inception_lower": "2017-08-01",
    "date:inception_upper": "2017-08-01",
    "iso:country": "GB",
    "wof:name": "CA10 2FG",
    "wof:placetype": "postalcode"
  },
  "geometry": {"coordinates":[-2.717435,54.629451],"type":"Point"}
}
