{
  "type": "Feature",
  "properties": {
    "iso:country": "GB",
    "wof:name": "NE13 9EB",
    "wof:placetype": "postalcode"
  },
  "geometry": {"coordinates":[-1.657752,55.026992],"type":"Point"}
}
