{
  "type": "Feature",
  "properties": {
    "iso:country":"GB",
    "wof:name":"CF5 3JT",
    "wof:placetype":"postalcode"
},
  "geometry": {"coordinates":[-3.2413651171632,51.49095702563399],"type":"Point"}
}