{
  "type": "Feature",
  "properties": {
    "iso:country":"GB",
    "wof:name":"L5 2RF",
    "wof:placetype":"postalcode"
},
  "geometry": {"coordinates":[-2.98644268349847,53.42514985015266],"type":"Point"}
}