{
  "type": "Feature",
  "properties": {
    "date:inception_lower": "1980-01-01",
    "date:inception_upper": "1980-01-01",
    "iso:country": "GB",
    "wof:name": "L5 2RF",
    "wof:placetype": "postalcode"
  },
  "geometry": {"coordinates":[-2.986425,53.425077],"type":"Point"}
}
