{
  "type": "Feature",
  "properties": {
    "iso:country": "GB",
    "wof:name": "SY5 6AL",
    "wof:placetype": "postalcode"
  },
  "geometry": {"coordinates":[-2.660518,52.649187],"type":"Point"}
}
