{
  "type": "Feature",
  "properties": {
    "iso:country":"GB",
    "wof:name":"EX6 8LP",
    "wof:placetype":"postalcode"
},
  "geometry": {"coordinates":[-3.46679226622349,50.63690134197908],"type":"Point"}
}