{
  "type": "Feature",
  "properties": {
    "date:inception_lower":"1980-01-01",
    "date:inception_upper":"1980-01-31",
    "iso:country":"GB",
    "wof:name":"EX6 8LP",
    "wof:placetype":"postalcode"
},
  "geometry": {"coordinates":[-3.466792,50.636901],"type":"Point"}
}