{
  "type": "Feature",
  "properties": {
    "iso:country": "GB",
    "wof:name": "NN12 8HB",
    "wof:placetype": "postalcode"
  },
  "geometry": {"coordinates":[-1.105844,52.190833],"type":"Point"}
}
