{
  "type": "Feature",
  "properties": {
    "date:inception_lower": "1996-12-01",
    "date:inception_upper": "1996-12-01",
    "iso:country": "GB",
    "wof:name": "KA5 6DD",
    "wof:placetype": "postalcode"
  },
  "geometry": {"coordinates":[-4.378641,55.516005],"type":"Point"}
}
