{
  "type": "Feature",
  "properties": {
    "iso:country":"GB",
    "wof:name":"KA5 6DD",
    "wof:placetype":"postalcode"
},
  "geometry": {"coordinates":[-4.37833651346936,55.51593764691356],"type":"Point"}
}