{
  "type": "Feature",
  "properties": {
    "iso:country":"GB",
    "wof:name":"TR14 0LW",
    "wof:placetype":"postalcode"
},
  "geometry": {"coordinates":[-5.3291842909587,50.1980661434577],"type":"Point"}
}