{
  "type": "Feature",
  "properties": {
    "iso:country":"GB",
    "wof:name":"GU52 8DZ",
    "wof:placetype":"postalcode"
},
  "geometry": {"coordinates":[-0.82681670367434,51.26313099154057],"type":"Point"}
}