{
  "type": "Feature",
  "properties": {
    "iso:country": "GB",
    "wof:name": "GU52 8DZ",
    "wof:placetype": "postalcode"
  },
  "geometry": {"coordinates":[-0.826817,51.263131],"type":"Point"}
}
