{
  "type": "Feature",
  "properties": {
    "iso:country":"GB",
    "wof:name":"S71 2NX",
    "wof:placetype":"postalcode"
},
  "geometry": {"coordinates":[-1.44410334426268,53.5672912689674],"type":"Point"}
}