{
  "type": "Feature",
  "properties": {
    "iso:country":"GB",
    "wof:name":"NW6 3QG",
    "wof:placetype":"postalcode"
},
  "geometry": {"coordinates":[-0.18074924865303,51.54187316383757],"type":"Point"}
}