{
  "type": "Feature",
  "properties": {
    "iso:country": "GB",
    "wof:name": "NW6 3QG",
    "wof:placetype": "postalcode"
  },
  "geometry": {"coordinates":[-0.180749,51.541873],"type":"Point"}
}
