{
  "type": "Feature",
  "properties": {
    "iso:country":"GB",
    "wof:name":"MK8 0PQ",
    "wof:placetype":"postalcode"
},
  "geometry": {"coordinates":[-0.81439615264439,52.02270427204122],"type":"Point"}
}