{
  "type": "Feature",
  "properties": {
    "date:inception_lower": "2005-01-01",
    "date:inception_upper": "2005-01-01",
    "iso:country": "GB",
    "wof:name": "MK8 0PQ",
    "wof:placetype": "postalcode"
  },
  "geometry": {"coordinates":[-0.814396,52.022704],"type":"Point"}
}
