{
  "type": "Feature",
  "properties": {
    "iso:country":"GB",
    "wof:name":"PL15 7RW",
    "wof:placetype":"postalcode"
},
  "geometry": {"coordinates":[-4.49725052860527,50.60306585103149],"type":"Point"}
}