{
  "type": "Feature",
  "properties": {
    "iso:country": "GB",
    "wof:name": "PL15 7RW",
    "wof:placetype": "postalcode"
  },
  "geometry": {"coordinates":[-4.49725,50.603066],"type":"Point"}
}
