{
  "type": "Feature",
  "properties": {
    "iso:country":"GB",
    "wof:name":"LE10 0FJ",
    "wof:placetype":"postalcode"
},
  "geometry": {"coordinates":[-1.40303963540298,52.53322492718583],"type":"Point"}
}