{
  "type": "Feature",
  "properties": {
    "date:inception_lower": "2002-09-01",
    "date:inception_upper": "2002-09-01",
    "iso:country": "GB",
    "wof:name": "LE10 0FJ",
    "wof:placetype": "postalcode"
  },
  "geometry": {"coordinates":[-1.40304,52.533225],"type":"Point"}
}
