{
  "type": "Feature",
  "properties": {
    "iso:country":"GB",
    "wof:name":"CM2 6BZ",
    "wof:placetype":"postalcode"
},
  "geometry": {"coordinates":[0.48948513211985,51.73869948778854],"type":"Point"}
}