{
  "type": "Feature",
  "properties": {
    "iso:country": "GB",
    "wof:name": "PH1 1LX",
    "wof:placetype": "postalcode"
  },
  "geometry": {"coordinates":[-3.463158,56.397667],"type":"Point"}
}
