{
  "type": "Feature",
  "properties": {
    "iso:country":"GB",
    "wof:name":"BS15 4NE",
    "wof:placetype":"postalcode"
},
  "geometry": {"coordinates":[-2.47734359784473,51.45999713187128],"type":"Point"}
}