{
  "type": "Feature",
  "properties": {
    "iso:country": "GB",
    "wof:name": "BS15 4NE",
    "wof:placetype": "postalcode"
  },
  "geometry": {"coordinates":[-2.477318,51.460274],"type":"Point"}
}
