{
  "type": "Feature",
  "properties": {
    "date:inception_lower":"1980-01-01",
    "date:inception_upper":"1980-01-31",
    "iso:country":"GB",
    "wof:name":"BS15 4NE",
    "wof:placetype":"postalcode"
},
  "geometry": {"coordinates":[-2.477318,51.460274],"type":"Point"}
}