{
  "type": "Feature",
  "properties": {
    "iso:country":"GB",
    "wof:name":"PL15 9NP",
    "wof:placetype":"postalcode"
},
  "geometry": {"coordinates":[-4.35964476426532,50.57807169282828],"type":"Point"}
}