{
  "type": "Feature",
  "properties": {
    "date:inception_lower": "1980-01-01",
    "date:inception_upper": "1980-01-01",
    "iso:country": "GB",
    "wof:name": "PL15 9NP",
    "wof:placetype": "postalcode"
  },
  "geometry": {"coordinates":[-4.359645,50.578072],"type":"Point"}
}
