{
  "type": "Feature",
  "properties": {
    "iso:country":"GB",
    "wof:name":"M30 9LU",
    "wof:placetype":"postalcode"
},
  "geometry": {"coordinates":[-2.34752197194483,53.49484755053427],"type":"Point"}
}