{
  "type": "Feature",
  "properties": {
    "iso:country":"GB",
    "wof:name":"SK2 6SL",
    "wof:placetype":"postalcode"
},
  "geometry": {"coordinates":[-2.15629276376426,53.39824711814117],"type":"Point"}
}