{
  "type": "Feature",
  "properties": {
    "iso:country":"GB",
    "wof:name":"TR15 2FB",
    "wof:placetype":"postalcode"
},
  "geometry": {"coordinates":[-5.21675892120822,50.22890866276901],"type":"Point"}
}