{
  "type": "Feature",
  "properties": {
    "date:inception_lower": "2000-06-01",
    "date:inception_upper": "2000-06-01",
    "iso:country": "GB",
    "wof:name": "CA7 1EZ",
    "wof:placetype": "postalcode"
  },
  "geometry": {"coordinates":[-3.165504,54.721195],"type":"Point"}
}
