{
  "type": "Feature",
  "properties": {
    "iso:country":"GB",
    "wof:name":"S81 0JG",
    "wof:placetype":"postalcode"
},
  "geometry": {"coordinates":[-1.11408405501867,53.31498282689707],"type":"Point"}
}