{
  "type": "Feature",
  "properties": {
    "iso:country":"GB",
    "wof:name":"SR5 4QE",
    "wof:placetype":"postalcode"
},
  "geometry": {"coordinates":[-1.4563976079979,54.92867026858612],"type":"Point"}
}