{
  "type": "Feature",
  "properties": {
    "iso:country": "GB",
    "wof:name": "LS6 2HE",
    "wof:placetype": "postalcode"
  },
  "geometry": {"coordinates":[-1.55966,53.816772],"type":"Point"}
}
