{
  "type": "Feature",
  "properties": {
    "date:inception_lower": "1991-09-01",
    "date:inception_upper": "1991-09-01",
    "iso:country": "GB",
    "wof:name": "LS6 2HE",
    "wof:placetype": "postalcode"
  },
  "geometry": {"coordinates":[-1.55966,53.816772],"type":"Point"}
}
