{
  "type": "Feature",
  "properties": {
    "iso:country": "GB",
    "wof:name": "SW19 2TJ",
    "wof:placetype": "postalcode"
  },
  "geometry": {"coordinates":[-0.185142,51.411406],"type":"Point"}
}
