{
  "type": "Feature",
  "properties": {
    "iso:country":"GB",
    "wof:name":"BS4 1JZ",
    "wof:placetype":"postalcode"
},
  "geometry": {"coordinates":[-2.58842375057809,51.42673546797113],"type":"Point"}
}