{
  "type": "Feature",
  "properties": {
    "iso:country":"GB",
    "wof:name":"IV30 1YF",
    "wof:placetype":"postalcode"
},
  "geometry": {"coordinates":[-3.33639106407523,57.64106369173842],"type":"Point"}
}