{
  "type": "Feature",
  "properties": {
    "iso:country":"GB",
    "wof:name":"WV10 9YG",
    "wof:placetype":"postalcode"
},
  "geometry": {"coordinates":[-2.11295644730733,52.60326705003284],"type":"Point"}
}