{
  "type": "Feature",
  "properties": {
    "iso:country":"GB",
    "wof:name":"PA13 4HX",
    "wof:placetype":"postalcode"
},
  "geometry": {"coordinates":[-4.63658251125697,55.89366040848252],"type":"Point"}
}