{
  "type": "Feature",
  "properties": {
    "date:inception_lower":"1980-01-01",
    "date:inception_upper":"1980-01-31",
    "iso:country":"GB",
    "wof:name":"HP2 5TL",
    "wof:placetype":"postalcode"
},
  "geometry": {"coordinates":[-0.460822,51.767839],"type":"Point"}
}