{
  "type": "Feature",
  "properties": {
    "iso:country":"GB",
    "wof:name":"HP2 5TL",
    "wof:placetype":"postalcode"
},
  "geometry": {"coordinates":[-0.46082241816186,51.76783932299559],"type":"Point"}
}