{
  "type": "Feature",
  "properties": {
    "iso:country": "GB",
    "wof:name": "TS19 9EH",
    "wof:placetype": "postalcode"
  },
  "geometry": {"coordinates":[-1.33555,54.587213],"type":"Point"}
}
