{
  "type": "Feature",
  "properties": {
    "iso:country":"GB",
    "wof:name":"NG2 2NE",
    "wof:placetype":"postalcode"
},
  "geometry": {"coordinates":[-1.15210968355911,52.94031767385924],"type":"Point"}
}