{
  "type": "Feature",
  "properties": {
    "iso:country":"GB",
    "wof:name":"GU3 3PE",
    "wof:placetype":"postalcode"
},
  "geometry": {"coordinates":[-0.62204247263915,51.27231137169559],"type":"Point"}
}