{
  "type": "Feature",
  "properties": {
    "date:inception_lower":"1980-01-01",
    "date:inception_upper":"1980-01-31",
    "iso:country":"GB",
    "wof:name":"SA18 2SP",
    "wof:placetype":"postalcode"
},
  "geometry": {"coordinates":[-3.983552,51.780766],"type":"Point"}
}