{
  "type": "Feature",
  "properties": {
    "iso:country": "GB",
    "wof:name": "SA18 2SP",
    "wof:placetype": "postalcode"
  },
  "geometry": {"coordinates":[-3.983552,51.780766],"type":"Point"}
}
