{
  "type": "Feature",
  "properties": {
    "iso:country":"GB",
    "wof:name":"SA18 2SP",
    "wof:placetype":"postalcode"
},
  "geometry": {"coordinates":[-3.98355182175791,51.78076552339768],"type":"Point"}
}