{
  "type": "Feature",
  "properties": {
    "iso:country": "GB",
    "wof:name": "SK8 1HS",
    "wof:placetype": "postalcode"
  },
  "geometry": {"coordinates":[-2.209807,53.383891],"type":"Point"}
}
