{
  "type": "Feature",
  "properties": {
    "iso:country":"GB",
    "wof:name":"SK8 1HS",
    "wof:placetype":"postalcode"
},
  "geometry": {"coordinates":[-2.20980658281042,53.38389109011913],"type":"Point"}
}