{
  "type": "Feature",
  "properties": {
    "iso:country":"GB",
    "wof:name":"KW12 6XA",
    "wof:placetype":"postalcode"
},
  "geometry": {"coordinates":[-3.44517957504806,58.49804409419151],"type":"Point"}
}