{
  "type": "Feature",
  "properties": {
    "iso:country": "GB",
    "wof:name": "IP25 6ZQ",
    "wof:placetype": "postalcode"
  },
  "geometry": {"coordinates":[0.817022,52.573333],"type":"Point"}
}
