{
  "type": "Feature",
  "properties": {
    "iso:country":"GB",
    "wof:name":"E5 8GZ",
    "wof:placetype":"postalcode"
},
  "geometry": {"coordinates":[-0.059998536655,51.55007308571486],"type":"Point"}
}