{
  "type": "Feature",
  "properties": {
    "iso:country":"GB",
    "wof:name":"LE12 8FN",
    "wof:placetype":"postalcode"
},
  "geometry": {"coordinates":[-1.17652594408845,52.74732865957904],"type":"Point"}
}