{
  "type": "Feature",
  "properties": {
    "date:inception_lower":"2004-01-01",
    "date:inception_upper":"2004-01-31",
    "iso:country":"GB",
    "wof:name":"LE12 8FN",
    "wof:placetype":"postalcode"
},
  "geometry": {"coordinates":[-1.176526,52.747329],"type":"Point"}
}