{
  "type": "Feature",
  "properties": {
    "iso:country": "GB",
    "wof:name": "PO15 5LE",
    "wof:placetype": "postalcode"
  },
  "geometry": {"coordinates":[-1.208896,50.854092],"type":"Point"}
}
