{
  "type": "Feature",
  "properties": {
    "iso:country":"GB",
    "wof:name":"G67 4LR",
    "wof:placetype":"postalcode"
},
  "geometry": {"coordinates":[-4.02197337148102,55.93720488233765],"type":"Point"}
}