{
  "type": "Feature",
  "properties": {
    "date:inception_lower":"1980-01-01",
    "date:inception_upper":"1980-01-31",
    "iso:country":"GB",
    "wof:name":"G67 4LR",
    "wof:placetype":"postalcode"
},
  "geometry": {"coordinates":[-4.021973,55.937205],"type":"Point"}
}