{
  "type": "Feature",
  "properties": {
    "date:inception_lower": "1980-01-01",
    "date:inception_upper": "1980-01-01",
    "iso:country": "GB",
    "wof:name": "SY3 0JE",
    "wof:placetype": "postalcode"
  },
  "geometry": {"coordinates":[-2.775548,52.677839],"type":"Point"}
}
