{
  "type": "Feature",
  "properties": {
    "iso:country":"GB",
    "wof:name":"SY3 0JE",
    "wof:placetype":"postalcode"
},
  "geometry": {"coordinates":[-2.77556348957023,52.67780612863483],"type":"Point"}
}