{
  "type": "Feature",
  "properties": {
    "iso:country":"GB",
    "wof:name":"DN15 9RA",
    "wof:placetype":"postalcode"
},
  "geometry": {"coordinates":[-0.55640824244162,53.63807872063329],"type":"Point"}
}