{
  "type": "Feature",
  "properties": {
    "iso:country": "GB",
    "wof:name": "DN15 9RA",
    "wof:placetype": "postalcode"
  },
  "geometry": {"coordinates":[-0.556408,53.638079],"type":"Point"}
}
