{
  "type": "Feature",
  "properties": {
    "iso:country": "GB",
    "wof:name": "CT21 6HH",
    "wof:placetype": "postalcode"
  },
  "geometry": {"coordinates":[1.090642,51.06709],"type":"Point"}
}
