{
  "type": "Feature",
  "properties": {
    "iso:country":"GB",
    "wof:name":"CT21 6HH",
    "wof:placetype":"postalcode"
},
  "geometry": {"coordinates":[1.09064200267091,51.06708969029457],"type":"Point"}
}