{
  "type": "Feature",
  "properties": {
    "iso:country": "GB",
    "wof:name": "PO37 6BZ",
    "wof:placetype": "postalcode"
  },
  "geometry": {"coordinates":[-1.177568,50.613829],"type":"Point"}
}
