{
  "type": "Feature",
  "properties": {
    "date:inception_lower":"1980-01-01",
    "date:inception_upper":"1980-01-31",
    "iso:country":"GB",
    "wof:name":"WV13 3ND",
    "wof:placetype":"postalcode"
},
  "geometry": {"coordinates":[-2.080658,52.583921],"type":"Point"}
}