{
  "type": "Feature",
  "properties": {
    "iso:country":"GB",
    "wof:name":"NW8 8UB",
    "wof:placetype":"postalcode"
},
  "geometry": {"coordinates":[-0.17426415750306,51.52662915261256],"type":"Point"}
}