{
  "type": "Feature",
  "properties": {
    "iso:country": "GB",
    "wof:name": "NW8 8UB",
    "wof:placetype": "postalcode"
  },
  "geometry": {"coordinates":[-0.174264,51.526629],"type":"Point"}
}
