{
  "type": "Feature",
  "properties": {
    "iso:country":"GB",
    "wof:name":"S33 9HB",
    "wof:placetype":"postalcode"
},
  "geometry": {"coordinates":[-1.76370175401536,53.32105685561285],"type":"Point"}
}