{
  "type": "Feature",
  "properties": {
    "date:inception_lower":"1982-03-01",
    "date:inception_upper":"1982-03-31",
    "iso:country":"GB",
    "wof:name":"WV6 7TB",
    "wof:placetype":"postalcode"
},
  "geometry": {"coordinates":[-2.205033,52.59054],"type":"Point"}
}