{
  "type": "Feature",
  "properties": {
    "iso:country":"GB",
    "wof:name":"NR7 0QE",
    "wof:placetype":"postalcode"
},
  "geometry": {"coordinates":[1.34682606073778,52.62671987443682],"type":"Point"}
}