{
  "type": "Feature",
  "properties": {
    "iso:country":"GB",
    "wof:name":"UB3 4EH",
    "wof:placetype":"postalcode"
},
  "geometry": {"coordinates":[-0.42550813381985,51.49563228811373],"type":"Point"}
}