{
  "type": "Feature",
  "properties": {
    "date:inception_lower":"1980-01-01",
    "date:inception_upper":"1980-01-31",
    "iso:country":"GB",
    "wof:name":"YO16 4SX",
    "wof:placetype":"postalcode"
},
  "geometry": {"coordinates":[-0.215356,54.080872],"type":"Point"}
}