{
  "type": "Feature",
  "properties": {
    "iso:country": "GB",
    "wof:name": "BS40 5NS",
    "wof:placetype": "postalcode"
  },
  "geometry": {"coordinates":[-2.777495,51.371773],"type":"Point"}
}
