{
  "type": "Feature",
  "properties": {
    "iso:country":"GB",
    "wof:name":"BS32 0HD",
    "wof:placetype":"postalcode"
},
  "geometry": {"coordinates":[-2.53136073372516,51.5279027131725],"type":"Point"}
}