{
  "type": "Feature",
  "properties": {
    "iso:country":"GB",
    "wof:name":"BH15 1NR",
    "wof:placetype":"postalcode"
},
  "geometry": {"coordinates":[-1.98503274329407,50.71557768416724],"type":"Point"}
}