{
  "type": "Feature",
  "properties": {
    "iso:country": "GB",
    "wof:name": "BH15 1NR",
    "wof:placetype": "postalcode"
  },
  "geometry": {"coordinates":[-1.985026,50.715568],"type":"Point"}
}
