{
  "type": "Feature",
  "properties": {
    "iso:country": "GB",
    "wof:name": "SY17 5HS",
    "wof:placetype": "postalcode"
  },
  "geometry": {"coordinates":[-3.459003,52.516631],"type":"Point"}
}
