{
  "type": "Feature",
  "properties": {
    "date:inception_lower": "2019-09-01",
    "date:inception_upper": "2019-09-01",
    "iso:country": "GB",
    "wof:name": "WS13 6UL",
    "wof:placetype": "postalcode"
  },
  "geometry": {"coordinates":[-1.846568,52.674869],"type":"Point"}
}
