{
  "type": "Feature",
  "properties": {
    "iso:country":"GB",
    "wof:name":"WA2 8TS",
    "wof:placetype":"postalcode"
},
  "geometry": {"coordinates":[-2.60434086683137,53.4172773647575],"type":"Point"}
}