{
  "type": "Feature",
  "properties": {
    "date:inception_lower":"1993-08-01",
    "date:inception_upper":"1993-08-31",
    "iso:country":"GB",
    "wof:name":"WA2 8TS",
    "wof:placetype":"postalcode"
},
  "geometry": {"coordinates":[-2.604341,53.417277],"type":"Point"}
}