{
  "type": "Feature",
  "properties": {
    "iso:country": "GB",
    "wof:name": "NR12 7AD",
    "wof:placetype": "postalcode"
  },
  "geometry": {"coordinates":[1.319513,52.708171],"type":"Point"}
}
