{
  "type": "Feature",
  "properties": {
    "iso:country":"GB",
    "wof:name":"NR12 7AD",
    "wof:placetype":"postalcode"
},
  "geometry": {"coordinates":[1.31949071871667,52.70814483007871],"type":"Point"}
}