{
  "type": "Feature",
  "properties": {
    "iso:country": "GB",
    "wof:name": "EX8 2SY",
    "wof:placetype": "postalcode"
  },
  "geometry": {"coordinates":[-3.410168,50.618912],"type":"Point"}
}
