{
  "type": "Feature",
  "properties": {
    "iso:country":"GB",
    "wof:name":"BS14 0HT",
    "wof:placetype":"postalcode"
},
  "geometry": {"coordinates":[-2.57241377710056,51.40245627230512],"type":"Point"}
}