{
  "type": "Feature",
  "properties": {
    "iso:country":"GB",
    "wof:name":"EN5 5XP",
    "wof:placetype":"postalcode"
},
  "geometry": {"coordinates":[-0.20153435315735,51.65579359454373],"type":"Point"}
}