{
  "type": "Feature",
  "properties": {
    "date:inception_lower":"1980-01-01",
    "date:inception_upper":"1980-01-31",
    "iso:country":"GB",
    "wof:name":"EN5 5XP",
    "wof:placetype":"postalcode"
},
  "geometry": {"coordinates":[-0.201379,51.655804],"type":"Point"}
}