{
  "type": "Feature",
  "properties": {
    "iso:country":"GB",
    "wof:name":"DY6 8RH",
    "wof:placetype":"postalcode"
},
  "geometry": {"coordinates":[-2.14832215423215,52.4904860904884],"type":"Point"}
}