{
  "type": "Feature",
  "properties": {
    "iso:country":"GB",
    "wof:name":"LS25 2EU",
    "wof:placetype":"postalcode"
},
  "geometry": {"coordinates":[-1.37363794145685,53.79575813813671],"type":"Point"}
}