{
  "type": "Feature",
  "properties": {
    "iso:country":"GB",
    "wof:name":"SK14 5NP",
    "wof:placetype":"postalcode"
},
  "geometry": {"coordinates":[-2.06170147084927,53.44302462391649],"type":"Point"}
}