{
  "type": "Feature",
  "properties": {
    "iso:country": "GB",
    "wof:name": "BN2 5HH",
    "wof:placetype": "postalcode"
  },
  "geometry": {"coordinates":[-0.106738,50.827081],"type":"Point"}
}
