{
  "type": "Feature",
  "properties": {
    "iso:country":"GB",
    "wof:name":"BN2 5HH",
    "wof:placetype":"postalcode"
},
  "geometry": {"coordinates":[-0.10673811162603,50.82708060653543],"type":"Point"}
}