{
  "type": "Feature",
  "properties": {
    "iso:country": "GB",
    "wof:name": "SK8 1NJ",
    "wof:placetype": "postalcode"
  },
  "geometry": {"coordinates":[-2.216502,53.387978],"type":"Point"}
}
