{
  "type": "Feature",
  "properties": {
    "iso:country":"GB",
    "wof:name":"SK8 1NJ",
    "wof:placetype":"postalcode"
},
  "geometry": {"coordinates":[-2.2165024826616,53.38797792123221],"type":"Point"}
}