{
  "type": "Feature",
  "properties": {
    "iso:country":"GB",
    "wof:name":"W1T 6EQ",
    "wof:placetype":"postalcode"
},
  "geometry": {"coordinates":[-0.14092490516261,51.52330884466585],"type":"Point"}
}