{
  "type": "Feature",
  "properties": {
    "iso:country": "GB",
    "wof:name": "AL4 8PX",
    "wof:placetype": "postalcode"
  },
  "geometry": {"coordinates":[-0.296914,51.807032],"type":"Point"}
}
