{
  "type": "Feature",
  "properties": {
    "date:inception_lower": "2012-08-01",
    "date:inception_upper": "2012-08-01",
    "iso:country": "GB",
    "wof:name": "M17 1NJ",
    "wof:placetype": "postalcode"
  },
  "geometry": {"coordinates":[-2.316553,53.47363],"type":"Point"}
}
