{
  "type": "Feature",
  "properties": {
    "iso:country": "GB",
    "wof:name": "M17 1NJ",
    "wof:placetype": "postalcode"
  },
  "geometry": {"coordinates":[-2.317265,53.474149],"type":"Point"}
}
