{
  "type": "Feature",
  "properties": {
    "iso:country": "GB",
    "wof:name": "IG7 5NF",
    "wof:placetype": "postalcode"
  },
  "geometry": {"coordinates":[0.086144,51.607394],"type":"Point"}
}
