{
  "type": "Feature",
  "properties": {
    "iso:country":"GB",
    "wof:name":"IG7 5NF",
    "wof:placetype":"postalcode"
},
  "geometry": {"coordinates":[0.08614351159718,51.60739374547161],"type":"Point"}
}