{
  "type": "Feature",
  "properties": {
    "date:inception_lower":"1980-01-01",
    "date:inception_upper":"1980-01-31",
    "iso:country":"GB",
    "wof:name":"IG7 5NF",
    "wof:placetype":"postalcode"
},
  "geometry": {"coordinates":[0.086144,51.607394],"type":"Point"}
}