{
  "type": "Feature",
  "properties": {
    "iso:country":"GB",
    "wof:name":"SL7 1BP",
    "wof:placetype":"postalcode"
},
  "geometry": {"coordinates":[-0.7728582314829,51.57343294458654],"type":"Point"}
}