{
  "type": "Feature",
  "properties": {
    "iso:country": "GB",
    "wof:name": "SM1 2SD",
    "wof:placetype": "postalcode"
  },
  "geometry": {"coordinates":[-0.199399,51.364361],"type":"Point"}
}
