{
  "type": "Feature",
  "properties": {
    "iso:country":"GB",
    "wof:name":"SM1 2SD",
    "wof:placetype":"postalcode"
},
  "geometry": {"coordinates":[-0.19939942137455,51.36436070874044],"type":"Point"}
}