{
  "type": "Feature",
  "properties": {
    "iso:country":"GB",
    "wof:name":"BL0 9DP",
    "wof:placetype":"postalcode"
},
  "geometry": {"coordinates":[-2.32225106961635,53.6525648244706],"type":"Point"}
}