{
  "type": "Feature",
  "properties": {
    "date:inception_lower": "1980-01-01",
    "date:inception_upper": "1980-01-01",
    "iso:country": "GB",
    "wof:name": "BL0 9DP",
    "wof:placetype": "postalcode"
  },
  "geometry": {"coordinates":[-2.322251,53.652565],"type":"Point"}
}
