{
  "type": "Feature",
  "properties": {
    "date:inception_lower":"2002-06-01",
    "date:inception_upper":"2002-06-30",
    "iso:country":"GB",
    "wof:name":"NR29 3LU",
    "wof:placetype":"postalcode"
},
  "geometry": {"coordinates":[1.716379,52.678537],"type":"Point"}
}