{
  "type": "Feature",
  "properties": {
    "date:inception_lower": "1980-01-01",
    "date:inception_upper": "1980-01-01",
    "iso:country": "GB",
    "wof:name": "DT9 6PX",
    "wof:placetype": "postalcode"
  },
  "geometry": {"coordinates":[-2.563123,50.91837],"type":"Point"}
}
