{
  "type": "Feature",
  "properties": {
    "iso:country":"GB",
    "wof:name":"DT9 6PX",
    "wof:placetype":"postalcode"
},
  "geometry": {"coordinates":[-2.56282540030691,50.91851297469044],"type":"Point"}
}