{
  "type": "Feature",
  "properties": {
    "iso:country": "GB",
    "wof:name": "HD1 2LT",
    "wof:placetype": "postalcode"
  },
  "geometry": {"coordinates":[-1.783607,53.644391],"type":"Point"}
}
