{
  "type": "Feature",
  "properties": {
    "iso:country":"GB",
    "wof:name":"CM6 1QE",
    "wof:placetype":"postalcode"
},
  "geometry": {"coordinates":[0.31071300418285,51.79687486946944],"type":"Point"}
}