{
  "type": "Feature",
  "properties": {
    "iso:country":"GB",
    "wof:name":"FK7 0EG",
    "wof:placetype":"postalcode"
},
  "geometry": {"coordinates":[-3.92197904454091,56.09435413327746],"type":"Point"}
}