{
  "type": "Feature",
  "properties": {
    "iso:country":"GB",
    "wof:name":"B72 1SQ",
    "wof:placetype":"postalcode"
},
  "geometry": {"coordinates":[-1.82075784589845,52.56488935500001],"type":"Point"}
}