{
  "type": "Feature",
  "properties": {
    "iso:country":"GB",
    "wof:name":"TN2 5TD",
    "wof:placetype":"postalcode"
},
  "geometry": {"coordinates":[0.25845500689224,51.12621540576706],"type":"Point"}
}