{
  "type": "Feature",
  "properties": {
    "date:inception_lower": "1980-01-01",
    "date:inception_upper": "1980-01-01",
    "iso:country": "GB",
    "wof:name": "HU10 7QZ",
    "wof:placetype": "postalcode"
  },
  "geometry": {"coordinates":[-0.452827,53.748762],"type":"Point"}
}
