{
  "type": "Feature",
  "properties": {
    "iso:country":"GB",
    "wof:name":"HU10 7QZ",
    "wof:placetype":"postalcode"
},
  "geometry": {"coordinates":[-0.45282715399508,53.74876197420856],"type":"Point"}
}