{
  "type": "Feature",
  "properties": {
    "iso:country":"GB",
    "wof:name":"PO31 7UH",
    "wof:placetype":"postalcode"
},
  "geometry": {"coordinates":[-1.31063439675689,50.74856011459433],"type":"Point"}
}