{
  "type": "Feature",
  "properties": {
    "iso:country":"GB",
    "wof:name":"DG3 4BA",
    "wof:placetype":"postalcode"
},
  "geometry": {"coordinates":[-3.81644118201391,55.23344301559658],"type":"Point"}
}