{
  "type": "Feature",
  "properties": {
    "iso:country":"GB",
    "wof:name":"SW7 4AB",
    "wof:placetype":"postalcode"
},
  "geometry": {"coordinates":[-0.18803113584302,51.4972214714434],"type":"Point"}
}