{
  "type": "Feature",
  "properties": {
    "iso:country": "GB",
    "wof:name": "IP17 3QE",
    "wof:placetype": "postalcode"
  },
  "geometry": {"coordinates":[1.53679,52.276206],"type":"Point"}
}
