{
  "type": "Feature",
  "properties": {
    "iso:country":"GB",
    "wof:name":"IP17 3QE",
    "wof:placetype":"postalcode"
},
  "geometry": {"coordinates":[1.53678980677241,52.27620558632],"type":"Point"}
}