{
  "type": "Feature",
  "properties": {
    "iso:country":"GB",
    "wof:name":"SA10 6DA",
    "wof:placetype":"postalcode"
},
  "geometry": {"coordinates":[-3.83846841319551,51.65779157227902],"type":"Point"}
}