{
  "type": "Feature",
  "properties": {
    "iso:country": "GB",
    "wof:name": "EH10 6QG",
    "wof:placetype": "postalcode"
  },
  "geometry": {"coordinates":[-3.204627,55.906999],"type":"Point"}
}
