{
  "type": "Feature",
  "properties": {
    "date:inception_lower": "2000-06-01",
    "date:inception_upper": "2000-06-01",
    "iso:country": "GB",
    "wof:name": "PE28 4BW",
    "wof:placetype": "postalcode"
  },
  "geometry": {"coordinates":[-0.224575,52.36783],"type":"Point"}
}
