{
  "type": "Feature",
  "properties": {
    "iso:country":"GB",
    "wof:name":"TQ7 1HT",
    "wof:placetype":"postalcode"
},
  "geometry": {"coordinates":[-3.7815206869838,50.28606794525738],"type":"Point"}
}