{
  "type": "Feature",
  "properties": {
    "iso:country":"GB",
    "wof:name":"BN10 8HG",
    "wof:placetype":"postalcode"
},
  "geometry": {"coordinates":[0.00475172048998,50.79178863867638],"type":"Point"}
}