{
  "type": "Feature",
  "properties": {
    "iso:country":"GB",
    "wof:name":"BB7 9HL",
    "wof:placetype":"postalcode"
},
  "geometry": {"coordinates":[-2.33899504335061,53.83648663785933],"type":"Point"}
}