{
  "type": "Feature",
  "properties": {
    "date:inception_lower": "1994-05-01",
    "date:inception_upper": "1994-05-01",
    "iso:country": "GB",
    "wof:name": "BB7 9HL",
    "wof:placetype": "postalcode"
  },
  "geometry": {"coordinates":[-2.338995,53.836487],"type":"Point"}
}
