{
  "type": "Feature",
  "properties": {
    "iso:country":"GB",
    "wof:name":"LE17 4QE",
    "wof:placetype":"postalcode"
},
  "geometry": {"coordinates":[-1.21104805234013,52.45525354943307],"type":"Point"}
}