{
  "type": "Feature",
  "properties": {
    "iso:country":"GB",
    "wof:name":"CF46 5DW",
    "wof:placetype":"postalcode"
},
  "geometry": {"coordinates":[-3.31115372975648,51.65643932142438],"type":"Point"}
}