{
  "type": "Feature",
  "properties": {
    "iso:country":"GB",
    "wof:name":"G83 9AN",
    "wof:placetype":"postalcode"
},
  "geometry": {"coordinates":[-4.57145420296657,55.98264606589917],"type":"Point"}
}