{
  "type": "Feature",
  "properties": {
    "iso:country": "GB",
    "wof:name": "S43 9AZ",
    "wof:placetype": "postalcode"
  },
  "geometry": {"coordinates":[-1.348294,53.274084],"type":"Point"}
}
