{
  "type": "Feature",
  "properties": {
    "iso:country": "GB",
    "wof:name": "YO31 8WD",
    "wof:placetype": "postalcode"
  },
  "geometry": {"coordinates":[-1.071071,53.967458],"type":"Point"}
}
