{
  "type": "Feature",
  "properties": {
    "iso:country": "GB",
    "wof:name": "M13 9TN",
    "wof:placetype": "postalcode"
  },
  "geometry": {"coordinates":[-2.228797,53.468607],"type":"Point"}
}
