{
  "type": "Feature",
  "properties": {
    "iso:country":"GB",
    "wof:name":"M13 9TN",
    "wof:placetype":"postalcode"
},
  "geometry": {"coordinates":[-2.22858763782861,53.46860050324508],"type":"Point"}
}