{
  "type": "Feature",
  "properties": {
    "date:inception_lower": "1980-01-01",
    "date:inception_upper": "1980-01-01",
    "iso:country": "GB",
    "wof:name": "M13 9TN",
    "wof:placetype": "postalcode"
  },
  "geometry": {"coordinates":[-2.228797,53.468607],"type":"Point"}
}
