{
  "type": "Feature",
  "properties": {
    "iso:country":"GB",
    "wof:name":"BB4 7RT",
    "wof:placetype":"postalcode"
},
  "geometry": {"coordinates":[-2.28335697184389,53.70273635845125],"type":"Point"}
}