{
  "type": "Feature",
  "properties": {
    "date:inception_lower": "1980-01-01",
    "date:inception_upper": "1980-01-01",
    "iso:country": "GB",
    "wof:name": "BB4 7RT",
    "wof:placetype": "postalcode"
  },
  "geometry": {"coordinates":[-2.283357,53.702736],"type":"Point"}
}
