{
  "type": "Feature",
  "properties": {
    "iso:country": "GB",
    "wof:name": "WN2 4JB",
    "wof:placetype": "postalcode"
  },
  "geometry": {"coordinates":[-2.562731,53.535078],"type":"Point"}
}
