{
  "type": "Feature",
  "properties": {
    "iso:country":"GB",
    "wof:name":"NE66 4BQ",
    "wof:placetype":"postalcode"
},
  "geometry": {"coordinates":[-1.92502876272583,55.42797647597077],"type":"Point"}
}