{
  "type": "Feature",
  "properties": {
    "iso:country":"GB",
    "wof:name":"ST2 7JY",
    "wof:placetype":"postalcode"
},
  "geometry": {"coordinates":[-2.13517541820009,53.05569078147559],"type":"Point"}
}