{
  "type": "Feature",
  "properties": {
    "iso:country":"GB",
    "wof:name":"PO36 0HN",
    "wof:placetype":"postalcode"
},
  "geometry": {"coordinates":[-1.16229138070234,50.6710148458465],"type":"Point"}
}