{
  "type": "Feature",
  "properties": {
    "iso:country": "GB",
    "wof:name": "PO36 0HN",
    "wof:placetype": "postalcode"
  },
  "geometry": {"coordinates":[-1.162291,50.671015],"type":"Point"}
}
