{
  "type": "Feature",
  "properties": {
    "iso:country":"GB",
    "wof:name":"L8 7NL",
    "wof:placetype":"postalcode"
},
  "geometry": {"coordinates":[-2.96847791728755,53.39950773371623],"type":"Point"}
}