{
  "type": "Feature",
  "properties": {
    "iso:country":"GB",
    "wof:name":"SL6 8FT",
    "wof:placetype":"postalcode"
},
  "geometry": {"coordinates":[-0.71032190022884,51.52840544366303],"type":"Point"}
}