{
  "type": "Feature",
  "properties": {
    "iso:country":"GB",
    "wof:name":"GU3 1AG",
    "wof:placetype":"postalcode"
},
  "geometry": {"coordinates":[-0.64673642114299,51.22615368298445],"type":"Point"}
}