{
  "type": "Feature",
  "properties": {
    "iso:country":"GB",
    "wof:name":"UB10 9LE",
    "wof:placetype":"postalcode"
},
  "geometry": {"coordinates":[-0.4536576918729,51.54839515242221],"type":"Point"}
}