{
  "type": "Feature",
  "properties": {
    "date:inception_lower": "1980-01-01",
    "date:inception_upper": "1980-01-01",
    "iso:country": "GB",
    "wof:name": "UB10 9LE",
    "wof:placetype": "postalcode"
  },
  "geometry": {"coordinates":[-0.453658,51.548395],"type":"Point"}
}
