{
  "type": "Feature",
  "properties": {
    "iso:country": "GB",
    "wof:name": "CO5 9FS",
    "wof:placetype": "postalcode"
  },
  "geometry": {"coordinates":[0.740283,51.862309],"type":"Point"}
}
