{
  "type": "Feature",
  "properties": {
    "date:inception_lower":"1980-01-01",
    "date:inception_upper":"1980-01-31",
    "iso:country":"GB",
    "wof:name":"WV7 3LE",
    "wof:placetype":"postalcode"
},
  "geometry": {"coordinates":[-2.285997,52.635635],"type":"Point"}
}