{
  "type": "Feature",
  "properties": {
    "iso:country": "GB",
    "wof:name": "WV7 3LE",
    "wof:placetype": "postalcode"
  },
  "geometry": {"coordinates":[-2.285997,52.635635],"type":"Point"}
}
