{
  "type": "Feature",
  "properties": {
    "date:inception_lower": "2017-10-01",
    "date:inception_upper": "2017-10-01",
    "iso:country": "GB",
    "wof:name": "LN13 9NL",
    "wof:placetype": "postalcode"
  },
  "geometry": {"coordinates":[0.199029,53.21936],"type":"Point"}
}
