{
  "type": "Feature",
  "properties": {
    "date:inception_lower": "1980-01-01",
    "date:inception_upper": "1980-01-01",
    "iso:country": "GB",
    "wof:name": "WN8 8ER",
    "wof:placetype": "postalcode"
  },
  "geometry": {"coordinates":[-2.799506,53.550367],"type":"Point"}
}
