{
  "type": "Feature",
  "properties": {
    "iso:country":"GB",
    "wof:name":"WN8 8ER",
    "wof:placetype":"postalcode"
},
  "geometry": {"coordinates":[-2.79950650713541,53.55036692279849],"type":"Point"}
}