{
  "type": "Feature",
  "properties": {
    "iso:country":"GB",
    "wof:name":"NE46 2BH",
    "wof:placetype":"postalcode"
},
  "geometry": {"coordinates":[-2.11474024326122,54.96675457100007],"type":"Point"}
}