{
  "type": "Feature",
  "properties": {
    "iso:country": "GB",
    "wof:name": "NE46 2BH",
    "wof:placetype": "postalcode"
  },
  "geometry": {"coordinates":[-2.11474,54.966755],"type":"Point"}
}
