{
  "type": "Feature",
  "properties": {
    "iso:country":"GB",
    "wof:name":"CM7 3LL",
    "wof:placetype":"postalcode"
},
  "geometry": {"coordinates":[0.58129330984567,51.87832380165558],"type":"Point"}
}