{
  "type": "Feature",
  "properties": {
    "date:inception_lower":"2002-06-01",
    "date:inception_upper":"2002-06-30",
    "iso:country":"GB",
    "wof:name":"CM7 3LL",
    "wof:placetype":"postalcode"
},
  "geometry": {"coordinates":[0.581293,51.878324],"type":"Point"}
}