{
  "type": "Feature",
  "properties": {
    "date:inception_lower":"1980-01-01",
    "date:inception_upper":"1980-01-31",
    "iso:country":"GB",
    "wof:name":"EH22 2EY",
    "wof:placetype":"postalcode"
},
  "geometry": {"coordinates":[-3.048968,55.892623],"type":"Point"}
}