{
  "type": "Feature",
  "properties": {
    "iso:country": "GB",
    "wof:name": "PH15 2FL",
    "wof:placetype": "postalcode"
  },
  "geometry": {"coordinates":[-3.874712,56.613357],"type":"Point"}
}
