{
  "type": "Feature",
  "properties": {
    "iso:country": "GB",
    "wof:name": "PO35 5TT",
    "wof:placetype": "postalcode"
  },
  "geometry": {"coordinates":[-1.073821,50.687387],"type":"Point"}
}
