{
  "type": "Feature",
  "properties": {
    "date:inception_lower": "1991-09-01",
    "date:inception_upper": "1991-09-01",
    "iso:country": "GB",
    "wof:name": "PO35 5TT",
    "wof:placetype": "postalcode"
  },
  "geometry": {"coordinates":[-1.073821,50.687387],"type":"Point"}
}
