{
  "type": "Feature",
  "properties": {
    "iso:country":"GB",
    "wof:name":"PO35 5TT",
    "wof:placetype":"postalcode"
},
  "geometry": {"coordinates":[-1.07382105718782,50.68738725448211],"type":"Point"}
}