{
  "type": "Feature",
  "properties": {
    "date:inception_lower":"1980-01-01",
    "date:inception_upper":"1980-01-31",
    "iso:country":"GB",
    "wof:name":"SK8 3EL",
    "wof:placetype":"postalcode"
},
  "geometry": {"coordinates":[-2.224434,53.372368],"type":"Point"}
}