{
  "type": "Feature",
  "properties": {
    "iso:country":"GB",
    "wof:name":"SK8 3EL",
    "wof:placetype":"postalcode"
},
  "geometry": {"coordinates":[-2.22443424081561,53.3723680250627],"type":"Point"}
}