{
  "type": "Feature",
  "properties": {
    "iso:country":"GB",
    "wof:name":"TD3 6NW",
    "wof:placetype":"postalcode"
},
  "geometry": {"coordinates":[-2.56871625413315,55.75950590496009],"type":"Point"}
}