{
  "type": "Feature",
  "properties": {
    "iso:country":"GB",
    "wof:name":"SY4 3PA",
    "wof:placetype":"postalcode"
},
  "geometry": {"coordinates":[-2.77724229715355,52.7739590402863],"type":"Point"}
}