{
  "type": "Feature",
  "properties": {
    "iso:country": "GB",
    "wof:name": "SY4 3PA",
    "wof:placetype": "postalcode"
  },
  "geometry": {"coordinates":[-2.777242,52.773959],"type":"Point"}
}
