{
  "type": "Feature",
  "properties": {
    "iso:country": "GB",
    "wof:name": "NE12 8JY",
    "wof:placetype": "postalcode"
  },
  "geometry": {"coordinates":[-1.568112,55.014522],"type":"Point"}
}
