{
  "type": "Feature",
  "properties": {
    "iso:country":"GB",
    "wof:name":"NE12 8JY",
    "wof:placetype":"postalcode"
},
  "geometry": {"coordinates":[-1.56809741748438,55.01451485342035],"type":"Point"}
}