{
  "type": "Feature",
  "properties": {
    "iso:country":"GB",
    "wof:name":"BS31 2LW",
    "wof:placetype":"postalcode"
},
  "geometry": {"coordinates":[-2.51509271542242,51.40836911678471],"type":"Point"}
}