{
  "type": "Feature",
  "properties": {
    "iso:country": "GB",
    "wof:name": "BS31 2LW",
    "wof:placetype": "postalcode"
  },
  "geometry": {"coordinates":[-2.515093,51.408369],"type":"Point"}
}
