{
  "type": "Feature",
  "properties": {
    "iso:country": "GB",
    "wof:name": "TN22 2AJ",
    "wof:placetype": "postalcode"
  },
  "geometry": {"coordinates":[0.100612,50.982323],"type":"Point"}
}
