{
  "type": "Feature",
  "properties": {
    "iso:country": "GB",
    "wof:name": "E10 7RB",
    "wof:placetype": "postalcode"
  },
  "geometry": {"coordinates":[-0.017286,51.57336],"type":"Point"}
}
