{
  "type": "Feature",
  "properties": {
    "iso:country": "GB",
    "wof:name": "BA14 6GU",
    "wof:placetype": "postalcode"
  },
  "geometry": {"coordinates":[-2.178194,51.31879],"type":"Point"}
}
