{
  "type": "Feature",
  "properties": {
    "iso:country":"GB",
    "wof:name":"CR2 8LL",
    "wof:placetype":"postalcode"
},
  "geometry": {"coordinates":[-0.06040304808941,51.34493852378919],"type":"Point"}
}