{
  "type": "Feature",
  "properties": {
    "date:inception_lower":"1980-01-01",
    "date:inception_upper":"1980-01-31",
    "iso:country":"GB",
    "wof:name":"CH8 9TN",
    "wof:placetype":"postalcode"
},
  "geometry": {"coordinates":[-3.293582,53.328747],"type":"Point"}
}