{
  "type": "Feature",
  "properties": {
    "iso:country": "GB",
    "wof:name": "CH8 9TN",
    "wof:placetype": "postalcode"
  },
  "geometry": {"coordinates":[-3.293582,53.328747],"type":"Point"}
}
