{
  "type": "Feature",
  "properties": {
    "iso:country": "GB",
    "wof:name": "G73 2RA",
    "wof:placetype": "postalcode"
  },
  "geometry": {"coordinates":[-4.222152,55.827022],"type":"Point"}
}
