{
  "type": "Feature",
  "properties": {
    "iso:country":"GB",
    "wof:name":"G73 2RA",
    "wof:placetype":"postalcode"
},
  "geometry": {"coordinates":[-4.22215192547624,55.82702155420259],"type":"Point"}
}