{
  "type": "Feature",
  "properties": {
    "iso:country":"GB",
    "wof:name":"OX15 5SW",
    "wof:placetype":"postalcode"
},
  "geometry": {"coordinates":[-1.40299756241897,52.02782120476918],"type":"Point"}
}