{
  "type": "Feature",
  "properties": {
    "date:inception_lower":"1980-01-01",
    "date:inception_upper":"1980-01-31",
    "iso:country":"GB",
    "wof:name":"OX15 5SW",
    "wof:placetype":"postalcode"
},
  "geometry": {"coordinates":[-1.402998,52.027821],"type":"Point"}
}