{
  "type": "Feature",
  "properties": {
    "iso:country":"GB",
    "wof:name":"CV35 9EH",
    "wof:placetype":"postalcode"
},
  "geometry": {"coordinates":[-1.59151386736902,52.21649192389093],"type":"Point"}
}