{
  "type": "Feature",
  "properties": {
    "date:inception_lower": "1980-01-01",
    "date:inception_upper": "1980-01-01",
    "iso:country": "GB",
    "wof:name": "CV35 9EH",
    "wof:placetype": "postalcode"
  },
  "geometry": {"coordinates":[-1.585147,52.215261],"type":"Point"}
}
