{
  "type": "Feature",
  "properties": {
    "date:inception_lower": "2017-08-01",
    "date:inception_upper": "2017-08-01",
    "iso:country": "GB",
    "wof:name": "TN23 3SP",
    "wof:placetype": "postalcode"
  },
  "geometry": {"coordinates":[0.847866,51.155901],"type":"Point"}
}
