{
  "type": "Feature",
  "properties": {
    "iso:country":"GB",
    "wof:name":"SN3 1BQ",
    "wof:placetype":"postalcode"
},
  "geometry": {"coordinates":[-1.76697934810299,51.56133528326283],"type":"Point"}
}