{
  "type": "Feature",
  "properties": {
    "iso:country":"GB",
    "wof:name":"OX29 4BD",
    "wof:placetype":"postalcode"
},
  "geometry": {"coordinates":[-1.38997532822204,51.78569995544991],"type":"Point"}
}