{
  "type": "Feature",
  "properties": {
    "iso:country":"GB",
    "wof:name":"EX17 4NR",
    "wof:placetype":"postalcode"
},
  "geometry": {"coordinates":[-3.66712948908864,50.81107089812755],"type":"Point"}
}