{
  "type": "Feature",
  "properties": {
    "date:inception_lower": "1980-01-01",
    "date:inception_upper": "1980-01-01",
    "iso:country": "GB",
    "wof:name": "NG23 5NQ",
    "wof:placetype": "postalcode"
  },
  "geometry": {"coordinates":[-0.893162,53.025316],"type":"Point"}
}
