{
  "type": "Feature",
  "properties": {
    "iso:country": "GB",
    "wof:name": "NG23 5NQ",
    "wof:placetype": "postalcode"
  },
  "geometry": {"coordinates":[-0.893162,53.025316],"type":"Point"}
}
