{
  "type": "Feature",
  "properties": {
    "iso:country":"GB",
    "wof:name":"LL13 0PW",
    "wof:placetype":"postalcode"
},
  "geometry": {"coordinates":[-2.96152079986908,53.02336595373637],"type":"Point"}
}