{
  "type": "Feature",
  "properties": {
    "iso:country": "GB",
    "wof:name": "LL13 0PW",
    "wof:placetype": "postalcode"
  },
  "geometry": {"coordinates":[-2.961521,53.023366],"type":"Point"}
}
