{
  "type": "Feature",
  "properties": {
    "iso:country": "GB",
    "wof:name": "HU2 0QQ",
    "wof:placetype": "postalcode"
  },
  "geometry": {"coordinates":[-0.332608,53.756205],"type":"Point"}
}
