{
  "type": "Feature",
  "properties": {
    "date:inception_lower": "2002-08-01",
    "date:inception_upper": "2002-08-01",
    "iso:country": "GB",
    "wof:name": "HU2 0QQ",
    "wof:placetype": "postalcode"
  },
  "geometry": {"coordinates":[-0.332608,53.756205],"type":"Point"}
}
