{
  "type": "Feature",
  "properties": {
    "iso:country": "GB",
    "wof:name": "CH44 9DD",
    "wof:placetype": "postalcode"
  },
  "geometry": {"coordinates":[-3.028022,53.411981],"type":"Point"}
}
