{
  "type": "Feature",
  "properties": {
    "date:inception_lower":"1980-01-01",
    "date:inception_upper":"1980-01-31",
    "iso:country":"GB",
    "wof:name":"EH51 9JG",
    "wof:placetype":"postalcode"
},
  "geometry": {"coordinates":[-3.608002,56.00353],"type":"Point"}
}