{
  "type": "Feature",
  "properties": {
    "iso:country":"GB",
    "wof:name":"SL9 9DG",
    "wof:placetype":"postalcode"
},
  "geometry": {"coordinates":[-0.56411447433143,51.6030672968607],"type":"Point"}
}