{
  "type": "Feature",
  "properties": {
    "date:inception_lower":"1980-01-01",
    "date:inception_upper":"1980-01-31",
    "iso:country":"GB",
    "wof:name":"SL9 9DG",
    "wof:placetype":"postalcode"
},
  "geometry": {"coordinates":[-0.564114,51.603067],"type":"Point"}
}