{
  "type": "Feature",
  "properties": {
    "iso:country":"GB",
    "wof:name":"MK8 8HA",
    "wof:placetype":"postalcode"
},
  "geometry": {"coordinates":[-0.80327550061981,52.03856008478981],"type":"Point"}
}