{
  "type": "Feature",
  "properties": {
    "iso:country": "GB",
    "wof:name": "MK8 8HA",
    "wof:placetype": "postalcode"
  },
  "geometry": {"coordinates":[-0.803275,52.03856],"type":"Point"}
}
