{
  "type": "Feature",
  "properties": {
    "iso:country": "GB",
    "wof:name": "BA11 3BE",
    "wof:placetype": "postalcode"
  },
  "geometry": {"coordinates":[-2.329853,51.232295],"type":"Point"}
}
