{
  "type": "Feature",
  "properties": {
    "iso:country":"GB",
    "wof:name":"BA11 3BE",
    "wof:placetype":"postalcode"
},
  "geometry": {"coordinates":[-2.32985281977255,51.23229491366786],"type":"Point"}
}