{
  "type": "Feature",
  "properties": {
    "iso:country":"GB",
    "wof:name":"DE24 8WQ",
    "wof:placetype":"postalcode"
},
  "geometry": {"coordinates":[-1.45089454368136,52.90693358004012],"type":"Point"}
}