{
  "type": "Feature",
  "properties": {
    "iso:country": "GB",
    "wof:name": "KT12 2PF",
    "wof:placetype": "postalcode"
  },
  "geometry": {"coordinates":[-0.4218,51.390012],"type":"Point"}
}
