{
  "type": "Feature",
  "properties": {
    "date:inception_lower": "1980-01-01",
    "date:inception_upper": "1980-01-01",
    "iso:country": "GB",
    "wof:name": "BS2 0UG",
    "wof:placetype": "postalcode"
  },
  "geometry": {"coordinates":[-2.563698,51.449901],"type":"Point"}
}
