{
  "type": "Feature",
  "properties": {
    "iso:country": "GB",
    "wof:name": "AL2 2BL",
    "wof:placetype": "postalcode"
  },
  "geometry": {"coordinates":[-0.351696,51.715241],"type":"Point"}
}
