{
  "type": "Feature",
  "properties": {
    "iso:country":"GB",
    "wof:name":"AL2 2BL",
    "wof:placetype":"postalcode"
},
  "geometry": {"coordinates":[-0.35169564734057,51.71524052536049],"type":"Point"}
}