{
  "type": "Feature",
  "properties": {
    "date:inception_lower": "1980-01-01",
    "date:inception_upper": "1980-01-01",
    "iso:country": "GB",
    "wof:name": "SO23 7AX",
    "wof:placetype": "postalcode"
  },
  "geometry": {"coordinates":[-1.315244,51.073199],"type":"Point"}
}
