{
  "type": "Feature",
  "properties": {
    "iso:country":"GB",
    "wof:name":"SO23 7AX",
    "wof:placetype":"postalcode"
},
  "geometry": {"coordinates":[-1.31524449791417,51.07319874019017],"type":"Point"}
}