{
  "type": "Feature",
  "properties": {
    "iso:country":"GB",
    "wof:name":"N9 9LU",
    "wof:placetype":"postalcode"
},
  "geometry": {"coordinates":[-0.07146476033207,51.62338003758754],"type":"Point"}
}