{
  "type": "Feature",
  "properties": {
    "date:inception_lower": "2009-02-01",
    "date:inception_upper": "2009-02-01",
    "iso:country": "GB",
    "wof:name": "CT12 6FD",
    "wof:placetype": "postalcode"
  },
  "geometry": {"coordinates":[1.389328,51.341542],"type":"Point"}
}
