{
  "type": "Feature",
  "properties": {
    "iso:country": "GB",
    "wof:name": "CM2 8QW",
    "wof:placetype": "postalcode"
  },
  "geometry": {"coordinates":[0.469381,51.69807],"type":"Point"}
}
