{
  "type": "Feature",
  "properties": {
    "iso:country": "GB",
    "wof:name": "G41 5EB",
    "wof:placetype": "postalcode"
  },
  "geometry": {"coordinates":[-4.280177,55.843692],"type":"Point"}
}
