{
  "type": "Feature",
  "properties": {
    "iso:country":"GB",
    "wof:name":"EX31 1SX",
    "wof:placetype":"postalcode"
},
  "geometry": {"coordinates":[-4.05834367885414,51.08028438662351],"type":"Point"}
}