{
  "type": "Feature",
  "properties": {
    "iso:country":"GB",
    "wof:name":"FK7 7HD",
    "wof:placetype":"postalcode"
},
  "geometry": {"coordinates":[-3.87620025427124,56.10504228586653],"type":"Point"}
}