{
  "type": "Feature",
  "properties": {
    "date:inception_lower":"1994-05-01",
    "date:inception_upper":"1994-05-31",
    "iso:country":"GB",
    "wof:name":"M23 9WD",
    "wof:placetype":"postalcode"
},
  "geometry": {"coordinates":[-2.301231,53.396926],"type":"Point"}
}