{
  "type": "Feature",
  "properties": {
    "date:inception_lower": "2000-06-01",
    "date:inception_upper": "2000-06-01",
    "iso:country": "GB",
    "wof:name": "SA14 8EQ",
    "wof:placetype": "postalcode"
  },
  "geometry": {"coordinates":[-4.136913,51.708474],"type":"Point"}
}
