{
  "type": "Feature",
  "properties": {
    "iso:country":"GB",
    "wof:name":"SA14 8EQ",
    "wof:placetype":"postalcode"
},
  "geometry": {"coordinates":[-4.13691344775856,51.70847440005575],"type":"Point"}
}