{
  "type": "Feature",
  "properties": {
    "iso:country":"GB",
    "wof:name":"E16 4ND",
    "wof:placetype":"postalcode"
},
  "geometry": {"coordinates":[0.01028618391035,51.52219057990106],"type":"Point"}
}