{
  "type": "Feature",
  "properties": {
    "date:inception_lower": "1994-05-01",
    "date:inception_upper": "1994-05-01",
    "iso:country": "GB",
    "wof:name": "CT11 7TF",
    "wof:placetype": "postalcode"
  },
  "geometry": {"coordinates":[1.423156,51.346594],"type":"Point"}
}
