{
  "type": "Feature",
  "properties": {
    "iso:country": "GB",
    "wof:name": "KT3 5PS",
    "wof:placetype": "postalcode"
  },
  "geometry": {"coordinates":[-0.265339,51.384536],"type":"Point"}
}
