{
  "type": "Feature",
  "properties": {
    "iso:country":"GB",
    "wof:name":"EX12 2AR",
    "wof:placetype":"postalcode"
},
  "geometry": {"coordinates":[-3.07053198624798,50.70945619026349],"type":"Point"}
}