{
  "type": "Feature",
  "properties": {
    "iso:country":"GB",
    "wof:name":"LN1 3ET",
    "wof:placetype":"postalcode"
},
  "geometry": {"coordinates":[-0.53612483244892,53.23990997114584],"type":"Point"}
}