{
  "type": "Feature",
  "properties": {
    "iso:country": "GB",
    "wof:name": "PE15 9RR",
    "wof:placetype": "postalcode"
  },
  "geometry": {"coordinates":[0.082339,52.544484],"type":"Point"}
}
