{
  "type": "Feature",
  "properties": {
    "iso:country": "GB",
    "wof:name": "L20 8PZ",
    "wof:placetype": "postalcode"
  },
  "geometry": {"coordinates":[-2.993677,53.43983],"type":"Point"}
}
