{
  "type": "Feature",
  "properties": {
    "date:inception_lower": "1998-12-01",
    "date:inception_upper": "1998-12-01",
    "iso:country": "GB",
    "wof:name": "LE67 9PZ",
    "wof:placetype": "postalcode"
  },
  "geometry": {"coordinates":[-1.240044,52.713152],"type":"Point"}
}
