{
  "type": "Feature",
  "properties": {
    "iso:country":"GB",
    "wof:name":"LE67 9PZ",
    "wof:placetype":"postalcode"
},
  "geometry": {"coordinates":[-1.2400815344662,52.71315104206374],"type":"Point"}
}