{
  "type": "Feature",
  "properties": {
    "iso:country": "GB",
    "wof:name": "LE67 9PZ",
    "wof:placetype": "postalcode"
  },
  "geometry": {"coordinates":[-1.240081,52.713151],"type":"Point"}
}
