{
  "type": "Feature",
  "properties": {
    "iso:country":"GB",
    "wof:name":"M7 4DH",
    "wof:placetype":"postalcode"
},
  "geometry": {"coordinates":[-2.25546913890862,53.50739408019166],"type":"Point"}
}