{
  "type": "Feature",
  "properties": {
    "iso:country":"GB",
    "wof:name":"RH16 4BW",
    "wof:placetype":"postalcode"
},
  "geometry": {"coordinates":[-0.12404513852272,51.00050023410999],"type":"Point"}
}