{
  "type": "Feature",
  "properties": {
    "iso:country": "GB",
    "wof:name": "RH16 4BW",
    "wof:placetype": "postalcode"
  },
  "geometry": {"coordinates":[-0.124045,51.0005],"type":"Point"}
}
