{
  "type": "Feature",
  "properties": {
    "date:inception_lower": "1999-06-01",
    "date:inception_upper": "1999-06-01",
    "iso:country": "GB",
    "wof:name": "CF11 7LT",
    "wof:placetype": "postalcode"
  },
  "geometry": {"coordinates":[-3.184329,51.467962],"type":"Point"}
}
