{
  "type": "Feature",
  "properties": {
    "iso:country":"GB",
    "wof:name":"CF11 7LT",
    "wof:placetype":"postalcode"
},
  "geometry": {"coordinates":[-3.18427801656257,51.46801566932959],"type":"Point"}
}