{
  "type": "Feature",
  "properties": {
    "iso:country":"GB",
    "wof:name":"HP9 1RE",
    "wof:placetype":"postalcode"
},
  "geometry": {"coordinates":[-0.63920416650014,51.60972548141938],"type":"Point"}
}