{
  "type": "Feature",
  "properties": {
    "iso:country":"GB",
    "wof:name":"SN12 8DX",
    "wof:placetype":"postalcode"
},
  "geometry": {"coordinates":[-2.15026340358268,51.38563155658954],"type":"Point"}
}