{
  "type": "Feature",
  "properties": {
    "iso:country":"GB",
    "wof:name":"EH32 0RW",
    "wof:placetype":"postalcode"
},
  "geometry": {"coordinates":[-2.86143290318179,56.00795991849047],"type":"Point"}
}