{
  "type": "Feature",
  "properties": {
    "date:inception_lower": "1980-01-01",
    "date:inception_upper": "1980-01-01",
    "iso:country": "GB",
    "wof:name": "EH32 0RW",
    "wof:placetype": "postalcode"
  },
  "geometry": {"coordinates":[-2.861433,56.00796],"type":"Point"}
}
