{
  "type": "Feature",
  "properties": {
    "iso:country": "GB",
    "wof:name": "CO7 0JF",
    "wof:placetype": "postalcode"
  },
  "geometry": {"coordinates":[1.022867,51.816518],"type":"Point"}
}
