{
  "type": "Feature",
  "properties": {
    "iso:country":"GB",
    "wof:name":"CO7 0JF",
    "wof:placetype":"postalcode"
},
  "geometry": {"coordinates":[1.02286719197604,51.81651784310316],"type":"Point"}
}