{
  "type": "Feature",
  "properties": {
    "iso:country":"GB",
    "wof:name":"WA8 7EL",
    "wof:placetype":"postalcode"
},
  "geometry": {"coordinates":[-2.7445977392561,53.36971631969268],"type":"Point"}
}