{
  "type": "Feature",
  "properties": {
    "iso:country":"GB",
    "wof:name":"DG11 1LW",
    "wof:placetype":"postalcode"
},
  "geometry": {"coordinates":[-3.41170692076005,55.11667568738744],"type":"Point"}
}