{
  "type": "Feature",
  "properties": {
    "date:inception_lower":"1980-01-01",
    "date:inception_upper":"1980-01-31",
    "iso:country":"GB",
    "wof:name":"DG11 1LW",
    "wof:placetype":"postalcode"
},
  "geometry": {"coordinates":[-3.411707,55.116676],"type":"Point"}
}