{
  "type": "Feature",
  "properties": {
    "iso:country": "GB",
    "wof:name": "TS22 5SJ",
    "wof:placetype": "postalcode"
  },
  "geometry": {"coordinates":[-1.354469,54.636474],"type":"Point"}
}
