{
  "type": "Feature",
  "properties": {
    "iso:country":"GB",
    "wof:name":"TS22 5SJ",
    "wof:placetype":"postalcode"
},
  "geometry": {"coordinates":[-1.35446946221598,54.63647366344683],"type":"Point"}
}