{
  "type": "Feature",
  "properties": {
    "iso:country":"GB",
    "wof:name":"N19 4DX",
    "wof:placetype":"postalcode"
},
  "geometry": {"coordinates":[-0.12176422721849,51.56645528406374],"type":"Point"}
}