{
  "type": "Feature",
  "properties": {
    "date:inception_lower":"1980-01-01",
    "date:inception_upper":"1980-01-31",
    "iso:country":"GB",
    "wof:name":"SA19 6HD",
    "wof:placetype":"postalcode"
},
  "geometry": {"coordinates":[-3.991505,51.884231],"type":"Point"}
}