{
  "type": "Feature",
  "properties": {
    "iso:country":"GB",
    "wof:name":"SA19 6HD",
    "wof:placetype":"postalcode"
},
  "geometry": {"coordinates":[-3.99146347120063,51.88427616970423],"type":"Point"}
}