{
  "type": "Feature",
  "properties": {
    "iso:country":"GB",
    "wof:name":"EX14 9ER",
    "wof:placetype":"postalcode"
},
  "geometry": {"coordinates":[-3.07555604145415,50.81625481685561],"type":"Point"}
}