{
  "type": "Feature",
  "properties": {
    "iso:country":"GB",
    "wof:name":"BA10 0NS",
    "wof:placetype":"postalcode"
},
  "geometry": {"coordinates":[-2.45577128212441,51.10854629772481],"type":"Point"}
}