{
  "type": "Feature",
  "properties": {
    "iso:country": "GB",
    "wof:name": "BA10 0NS",
    "wof:placetype": "postalcode"
  },
  "geometry": {"coordinates":[-2.455771,51.108546],"type":"Point"}
}
