{
  "type": "Feature",
  "properties": {
    "date:inception_lower": "2022-08-01",
    "date:inception_upper": "2022-08-01",
    "iso:country": "GB",
    "wof:name": "BN18 0GN",
    "wof:placetype": "postalcode"
  },
  "geometry": {"coordinates":[-0.607171,50.816015],"type":"Point"}
}
