{
  "type": "Feature",
  "properties": {
    "iso:country":"GB",
    "wof:name":"NR21 0JN",
    "wof:placetype":"postalcode"
},
  "geometry": {"coordinates":[0.90542312840901,52.85387571102061],"type":"Point"}
}