{
  "type": "Feature",
  "properties": {
    "iso:country": "GB",
    "wof:name": "SO51 0RJ",
    "wof:placetype": "postalcode"
  },
  "geometry": {"coordinates":[-1.466232,51.024456],"type":"Point"}
}
