{
  "type": "Feature",
  "properties": {
    "iso:country":"GB",
    "wof:name":"SO51 0RJ",
    "wof:placetype":"postalcode"
},
  "geometry": {"coordinates":[-1.46623221419582,51.02445603924258],"type":"Point"}
}