{
  "type": "Feature",
  "properties": {
    "date:inception_lower": "2000-06-01",
    "date:inception_upper": "2000-06-01",
    "iso:country": "GB",
    "wof:name": "SO51 0RJ",
    "wof:placetype": "postalcode"
  },
  "geometry": {"coordinates":[-1.466232,51.024456],"type":"Point"}
}
