{
  "type": "Feature",
  "properties": {
    "iso:country":"GB",
    "wof:name":"NE32 4AS",
    "wof:placetype":"postalcode"
},
  "geometry": {"coordinates":[-1.46902508758849,54.96397956275033],"type":"Point"}
}