{
  "type": "Feature",
  "properties": {
    "iso:country": "GB",
    "wof:name": "NE32 4AS",
    "wof:placetype": "postalcode"
  },
  "geometry": {"coordinates":[-1.469025,54.96398],"type":"Point"}
}
