{
  "type": "Feature",
  "properties": {
    "iso:country":"GB",
    "wof:name":"PE4 6LR",
    "wof:placetype":"postalcode"
},
  "geometry": {"coordinates":[-0.2794305672689,52.61480526059619],"type":"Point"}
}