{
  "type": "Feature",
  "properties": {
    "iso:country":"GB",
    "wof:name":"E14 7GG",
    "wof:placetype":"postalcode"
},
  "geometry": {"coordinates":[-0.03397076659312,51.51309384228249],"type":"Point"}
}