{
  "type": "Feature",
  "properties": {
    "date:inception_lower":"2012-03-01",
    "date:inception_upper":"2012-03-31",
    "iso:country":"GB",
    "wof:name":"E14 7GG",
    "wof:placetype":"postalcode"
},
  "geometry": {"coordinates":[-0.033971,51.513094],"type":"Point"}
}