{
  "type": "Feature",
  "properties": {
    "iso:country":"GB",
    "wof:name":"LE2 2EE",
    "wof:placetype":"postalcode"
},
  "geometry": {"coordinates":[-1.10200272809919,52.61489658827409],"type":"Point"}
}