{
  "type": "Feature",
  "properties": {
    "iso:country":"GB",
    "wof:name":"HP7 9LU",
    "wof:placetype":"postalcode"
},
  "geometry": {"coordinates":[-0.57834604029605,51.66519461686049],"type":"Point"}
}