{
  "type": "Feature",
  "properties": {
    "date:inception_lower": "1980-01-01",
    "date:inception_upper": "1980-01-01",
    "iso:country": "GB",
    "wof:name": "HP7 9LU",
    "wof:placetype": "postalcode"
  },
  "geometry": {"coordinates":[-0.578192,51.665269],"type":"Point"}
}
