{
  "type": "Feature",
  "properties": {
    "iso:country": "GB",
    "wof:name": "HP7 9LU",
    "wof:placetype": "postalcode"
  },
  "geometry": {"coordinates":[-0.578346,51.665195],"type":"Point"}
}
