{
  "type": "Feature",
  "properties": {
    "iso:country":"GB",
    "wof:name":"B19 1DS",
    "wof:placetype":"postalcode"
},
  "geometry": {"coordinates":[-1.91461300013546,52.49646414378066],"type":"Point"}
}