{
  "type": "Feature",
  "properties": {
    "iso:country":"GB",
    "wof:name":"SW13 0HX",
    "wof:placetype":"postalcode"
},
  "geometry": {"coordinates":[-0.24048233411779,51.46552145301546],"type":"Point"}
}