{
  "type": "Feature",
  "properties": {
    "date:inception_lower":"1980-01-01",
    "date:inception_upper":"1980-01-31",
    "iso:country":"GB",
    "wof:name":"LE3 8DD",
    "wof:placetype":"postalcode"
},
  "geometry": {"coordinates":[-1.201166,52.648204],"type":"Point"}
}