{
  "type": "Feature",
  "properties": {
    "iso:country":"GB",
    "wof:name":"LE3 8DD",
    "wof:placetype":"postalcode"
},
  "geometry": {"coordinates":[-1.20116610228475,52.64820415197283],"type":"Point"}
}