{
  "type": "Feature",
  "properties": {
    "iso:country": "GB",
    "wof:name": "SA2 0AQ",
    "wof:placetype": "postalcode"
  },
  "geometry": {"coordinates":[-3.965475,51.61453],"type":"Point"}
}
