{
  "type": "Feature",
  "properties": {
    "iso:country":"GB",
    "wof:name":"L16 3NE",
    "wof:placetype":"postalcode"
},
  "geometry": {"coordinates":[-2.8814602090227,53.40554836027765],"type":"Point"}
}