{
  "type": "Feature",
  "properties": {
    "date:inception_lower": "1980-01-01",
    "date:inception_upper": "1980-01-01",
    "iso:country": "GB",
    "wof:name": "NN6 8AW",
    "wof:placetype": "postalcode"
  },
  "geometry": {"coordinates":[-0.934301,52.288891],"type":"Point"}
}
