{
  "type": "Feature",
  "properties": {
    "iso:country":"GB",
    "wof:name":"NN6 8AW",
    "wof:placetype":"postalcode"
},
  "geometry": {"coordinates":[-0.93430062451796,52.28889054977462],"type":"Point"}
}