{
  "type": "Feature",
  "properties": {
    "iso:country":"GB",
    "wof:name":"DE12 8HF",
    "wof:placetype":"postalcode"
},
  "geometry": {"coordinates":[-1.6390825462018,52.73527154711411],"type":"Point"}
}