{
  "type": "Feature",
  "properties": {
    "iso:country":"GB",
    "wof:name":"SA12 8EH",
    "wof:placetype":"postalcode"
},
  "geometry": {"coordinates":[-3.80435721901029,51.61325152513906],"type":"Point"}
}