{
  "type": "Feature",
  "properties": {
    "date:inception_lower": "2015-04-01",
    "date:inception_upper": "2015-04-01",
    "iso:country": "GB",
    "wof:name": "LL14 5AX",
    "wof:placetype": "postalcode"
  },
  "geometry": {"coordinates":[-3.042726,52.953351],"type":"Point"}
}
