{
  "type": "Feature",
  "properties": {
    "iso:country": "GB",
    "wof:name": "LL14 5AX",
    "wof:placetype": "postalcode"
  },
  "geometry": {"coordinates":[-3.042425,52.953821],"type":"Point"}
}
