{
  "type": "Feature",
  "properties": {
    "date:inception_lower":"1980-01-01",
    "date:inception_upper":"1980-01-31",
    "iso:country":"GB",
    "wof:name":"CO7 7QY",
    "wof:placetype":"postalcode"
},
  "geometry": {"coordinates":[0.937448,51.923182],"type":"Point"}
}