{
  "type": "Feature",
  "properties": {
    "iso:country": "GB",
    "wof:name": "CO7 7QY",
    "wof:placetype": "postalcode"
  },
  "geometry": {"coordinates":[0.937448,51.923182],"type":"Point"}
}
