{
  "type": "Feature",
  "properties": {
    "iso:country":"GB",
    "wof:name":"CO7 7QY",
    "wof:placetype":"postalcode"
},
  "geometry": {"coordinates":[0.93744764962465,51.92318177650195],"type":"Point"}
}