{
  "type": "Feature",
  "properties": {
    "iso:country":"GB",
    "wof:name":"BB3 0NB",
    "wof:placetype":"postalcode"
},
  "geometry": {"coordinates":[-2.52214163766417,53.70258026244304],"type":"Point"}
}