{
  "type": "Feature",
  "properties": {
    "date:inception_lower":"1980-01-01",
    "date:inception_upper":"1980-01-31",
    "iso:country":"GB",
    "wof:name":"BB3 0NB",
    "wof:placetype":"postalcode"
},
  "geometry": {"coordinates":[-2.525097,53.702907],"type":"Point"}
}