{
  "type": "Feature",
  "properties": {
    "iso:country": "GB",
    "wof:name": "BB3 0NB",
    "wof:placetype": "postalcode"
  },
  "geometry": {"coordinates":[-2.525097,53.702907],"type":"Point"}
}
