{
  "type": "Feature",
  "properties": {
    "date:inception_lower": "1986-09-01",
    "date:inception_upper": "1986-09-01",
    "iso:country": "GB",
    "wof:name": "EH33 2PY",
    "wof:placetype": "postalcode"
  },
  "geometry": {"coordinates":[-2.94036,55.94021],"type":"Point"}
}
