{
  "type": "Feature",
  "properties": {
    "iso:country":"GB",
    "wof:name":"EH33 2PY",
    "wof:placetype":"postalcode"
},
  "geometry": {"coordinates":[-2.94035969993543,55.94021011831572],"type":"Point"}
}