{
  "type": "Feature",
  "properties": {
    "iso:country": "GB",
    "wof:name": "PE15 0SJ",
    "wof:placetype": "postalcode"
  },
  "geometry": {"coordinates":[0.05457,52.501244],"type":"Point"}
}
