{
  "type": "Feature",
  "properties": {
    "iso:country":"GB",
    "wof:name":"MK7 8DL",
    "wof:placetype":"postalcode"
},
  "geometry": {"coordinates":[-0.68438475636626,52.0135559249262],"type":"Point"}
}