{
  "type": "Feature",
  "properties": {
    "iso:country": "GB",
    "wof:name": "MK7 8DL",
    "wof:placetype": "postalcode"
  },
  "geometry": {"coordinates":[-0.684385,52.013556],"type":"Point"}
}
