{
  "type": "Feature",
  "properties": {
    "iso:country":"GB",
    "wof:name":"DH6 4BB",
    "wof:placetype":"postalcode"
},
  "geometry": {"coordinates":[-1.47562706442974,54.71078595976233],"type":"Point"}
}