{
  "type": "Feature",
  "properties": {
    "date:inception_lower":"1980-01-01",
    "date:inception_upper":"1980-01-31",
    "iso:country":"GB",
    "wof:name":"DH6 4BB",
    "wof:placetype":"postalcode"
},
  "geometry": {"coordinates":[-1.475627,54.710786],"type":"Point"}
}