{
  "type": "Feature",
  "properties": {
    "iso:country": "GB",
    "wof:name": "DH6 4BB",
    "wof:placetype": "postalcode"
  },
  "geometry": {"coordinates":[-1.475627,54.710786],"type":"Point"}
}
