{
  "type": "Feature",
  "properties": {
    "iso:country":"GB",
    "wof:name":"LN3 4RJ",
    "wof:placetype":"postalcode"
},
  "geometry": {"coordinates":[-0.50672360636051,53.23088824596436],"type":"Point"}
}