{
  "type": "Feature",
  "properties": {
    "iso:country": "GB",
    "wof:name": "LN3 4RJ",
    "wof:placetype": "postalcode"
  },
  "geometry": {"coordinates":[-0.506994,53.230896],"type":"Point"}
}
