{
  "type": "Feature",
  "properties": {
    "date:inception_lower":"1986-07-01",
    "date:inception_upper":"1986-07-31",
    "iso:country":"GB",
    "wof:name":"MK18 7HZ",
    "wof:placetype":"postalcode"
},
  "geometry": {"coordinates":[-0.972622,51.997326],"type":"Point"}
}