{
  "type": "Feature",
  "properties": {
    "iso:country": "GB",
    "wof:name": "MK18 7HZ",
    "wof:placetype": "postalcode"
  },
  "geometry": {"coordinates":[-0.972622,51.997326],"type":"Point"}
}
