{
  "type": "Feature",
  "properties": {
    "iso:country":"GB",
    "wof:name":"IG10 2EU",
    "wof:placetype":"postalcode"
},
  "geometry": {"coordinates":[0.0864505931182,51.65816962554925],"type":"Point"}
}