{
  "type": "Feature",
  "properties": {
    "date:inception_lower":"2003-08-01",
    "date:inception_upper":"2003-08-31",
    "iso:country":"GB",
    "wof:name":"SO15 2QZ",
    "wof:placetype":"postalcode"
},
  "geometry": {"coordinates":[-1.406288,50.918435],"type":"Point"}
}