{
  "type": "Feature",
  "properties": {
    "iso:country":"GB",
    "wof:name":"SO15 2QZ",
    "wof:placetype":"postalcode"
},
  "geometry": {"coordinates":[-1.40628797147341,50.91843458482453],"type":"Point"}
}