{
  "type": "Feature",
  "properties": {
    "iso:country":"GB",
    "wof:name":"CR0 5QH",
    "wof:placetype":"postalcode"
},
  "geometry": {"coordinates":[-0.08126580667124,51.37418496759123],"type":"Point"}
}