{
  "type": "Feature",
  "properties": {
    "iso:country":"GB",
    "wof:name":"KA1 5JE",
    "wof:placetype":"postalcode"
},
  "geometry": {"coordinates":[-4.41617470851359,55.59048195212796],"type":"Point"}
}