{
  "type": "Feature",
  "properties": {
    "date:inception_lower": "2019-08-01",
    "date:inception_upper": "2019-08-01",
    "iso:country": "GB",
    "wof:name": "BS16 7NR",
    "wof:placetype": "postalcode"
  },
  "geometry": {"coordinates":[-2.461959,51.494468],"type":"Point"}
}
