{
  "type": "Feature",
  "properties": {
    "iso:country": "GB",
    "wof:name": "BS16 7NR",
    "wof:placetype": "postalcode"
  },
  "geometry": {"coordinates":[-2.462548,51.494322],"type":"Point"}
}
