{
  "type": "Feature",
  "properties": {
    "iso:country":"GB",
    "wof:name":"RG27 9BS",
    "wof:placetype":"postalcode"
},
  "geometry": {"coordinates":[-0.97360798852516,51.30572055924983],"type":"Point"}
}