{
  "type": "Feature",
  "properties": {
    "iso:country":"GB",
    "wof:name":"CV6 1AL",
    "wof:placetype":"postalcode"
},
  "geometry": {"coordinates":[-1.5298825485295,52.41413886341781],"type":"Point"}
}