{
  "type": "Feature",
  "properties": {
    "iso:country":"GB",
    "wof:name":"WN8 6BH",
    "wof:placetype":"postalcode"
},
  "geometry": {"coordinates":[-2.75224811810921,53.54350971883441],"type":"Point"}
}