{
  "type": "Feature",
  "properties": {
    "date:inception_lower": "1997-12-01",
    "date:inception_upper": "1997-12-01",
    "iso:country": "GB",
    "wof:name": "WN8 6BH",
    "wof:placetype": "postalcode"
  },
  "geometry": {"coordinates":[-2.75226,53.543346],"type":"Point"}
}
