{
  "type": "Feature",
  "properties": {
    "iso:country":"GB",
    "wof:name":"HA6 1DS",
    "wof:placetype":"postalcode"
},
  "geometry": {"coordinates":[-0.42086710634586,51.60816965444407],"type":"Point"}
}