{
  "type": "Feature",
  "properties": {
    "iso:country": "GB",
    "wof:name": "SY13 2RD",
    "wof:placetype": "postalcode"
  },
  "geometry": {"coordinates":[-2.713175,52.897142],"type":"Point"}
}
