{
  "type": "Feature",
  "properties": {
    "iso:country":"GB",
    "wof:name":"SY13 2RD",
    "wof:placetype":"postalcode"
},
  "geometry": {"coordinates":[-2.7131751414749,52.8971415733326],"type":"Point"}
}