{
  "type": "Feature",
  "properties": {
    "date:inception_lower": "1980-01-01",
    "date:inception_upper": "1980-01-01",
    "iso:country": "GB",
    "wof:name": "LL11 5EG",
    "wof:placetype": "postalcode"
  },
  "geometry": {"coordinates":[-3.06893,53.091055],"type":"Point"}
}
