{
  "type": "Feature",
  "properties": {
    "iso:country":"GB",
    "wof:name":"LL11 5EG",
    "wof:placetype":"postalcode"
},
  "geometry": {"coordinates":[-3.06893012852083,53.09103884317394],"type":"Point"}
}