{
  "type": "Feature",
  "properties": {
    "iso:country":"GB",
    "wof:name":"HU4 7QL",
    "wof:placetype":"postalcode"
},
  "geometry": {"coordinates":[-0.41541725747106,53.74059657552299],"type":"Point"}
}