{
  "type": "Feature",
  "properties": {
    "iso:country": "GB",
    "wof:name": "GU21 2QX",
    "wof:placetype": "postalcode"
  },
  "geometry": {"coordinates":[-0.62149,51.311844],"type":"Point"}
}
