{
  "type": "Feature",
  "properties": {
    "iso:country":"GB",
    "wof:name":"PO41 0XH",
    "wof:placetype":"postalcode"
},
  "geometry": {"coordinates":[-1.47197308327118,50.7064975145901],"type":"Point"}
}