{
  "type": "Feature",
  "properties": {
    "date:inception_lower": "1980-01-01",
    "date:inception_upper": "1980-01-01",
    "iso:country": "GB",
    "wof:name": "WV14 0PT",
    "wof:placetype": "postalcode"
  },
  "geometry": {"coordinates":[-2.087032,52.553234],"type":"Point"}
}
