{
  "type": "Feature",
  "properties": {
    "iso:country": "GB",
    "wof:name": "NE12 8TY",
    "wof:placetype": "postalcode"
  },
  "geometry": {"coordinates":[-1.592372,55.009494],"type":"Point"}
}
