{
  "type": "Feature",
  "properties": {
    "iso:country":"GB",
    "wof:name":"NE12 8TY",
    "wof:placetype":"postalcode"
},
  "geometry": {"coordinates":[-1.59237158822964,55.00949436005349],"type":"Point"}
}