{
  "type": "Feature",
  "properties": {
    "date:inception_lower": "1980-01-01",
    "date:inception_upper": "1980-01-01",
    "iso:country": "GB",
    "wof:name": "NE12 8TY",
    "wof:placetype": "postalcode"
  },
  "geometry": {"coordinates":[-1.592558,55.009511],"type":"Point"}
}
