{
  "type": "Feature",
  "properties": {
    "iso:country": "GB",
    "wof:name": "WR3 7UR",
    "wof:placetype": "postalcode"
  },
  "geometry": {"coordinates":[-2.206706,52.227247],"type":"Point"}
}
