{
  "type": "Feature",
  "properties": {
    "iso:country":"GB",
    "wof:name":"B91 2EH",
    "wof:placetype":"postalcode"
},
  "geometry": {"coordinates":[-1.78603760080524,52.43276050063621],"type":"Point"}
}