{
  "type": "Feature",
  "properties": {
    "iso:country": "GB",
    "wof:name": "B91 2EH",
    "wof:placetype": "postalcode"
  },
  "geometry": {"coordinates":[-1.786038,52.43276],"type":"Point"}
}
