{
  "type": "Feature",
  "properties": {
    "date:inception_lower": "1992-08-01",
    "date:inception_upper": "1992-08-01",
    "iso:country": "GB",
    "wof:name": "DE56 4DH",
    "wof:placetype": "postalcode"
  },
  "geometry": {"coordinates":[-1.501627,52.985931],"type":"Point"}
}
