{
  "type": "Feature",
  "properties": {
    "date:inception_lower":"1980-01-01",
    "date:inception_upper":"1980-01-31",
    "iso:country":"GB",
    "wof:name":"DL11 7RP",
    "wof:placetype":"postalcode"
},
  "geometry": {"coordinates":[-1.709139,54.489103],"type":"Point"}
}