{
  "type": "Feature",
  "properties": {
    "iso:country": "GB",
    "wof:name": "DL11 7RP",
    "wof:placetype": "postalcode"
  },
  "geometry": {"coordinates":[-1.709139,54.489103],"type":"Point"}
}
