{
  "type": "Feature",
  "properties": {
    "iso:country": "GB",
    "wof:name": "IP31 2DG",
    "wof:placetype": "postalcode"
  },
  "geometry": {"coordinates":[0.882528,52.322683],"type":"Point"}
}
