{
  "type": "Feature",
  "properties": {
    "date:inception_lower": "2002-06-01",
    "date:inception_upper": "2002-06-01",
    "iso:country": "GB",
    "wof:name": "NR30 5WB",
    "wof:placetype": "postalcode"
  },
  "geometry": {"coordinates":[1.713582,52.661283],"type":"Point"}
}
