{
  "type": "Feature",
  "properties": {
    "iso:country": "GB",
    "wof:name": "RG24 8SH",
    "wof:placetype": "postalcode"
  },
  "geometry": {"coordinates":[-1.071363,51.275685],"type":"Point"}
}
