{
  "type": "Feature",
  "properties": {
    "iso:country":"GB",
    "wof:name":"RG24 8SH",
    "wof:placetype":"postalcode"
},
  "geometry": {"coordinates":[-1.07136298816893,51.27568462689405],"type":"Point"}
}