{
  "type": "Feature",
  "properties": {
    "date:inception_lower":"1993-08-01",
    "date:inception_upper":"1993-08-31",
    "iso:country":"GB",
    "wof:name":"RG24 8SH",
    "wof:placetype":"postalcode"
},
  "geometry": {"coordinates":[-1.071363,51.275685],"type":"Point"}
}