{
  "type": "Feature",
  "properties": {
    "iso:country":"GB",
    "wof:name":"S73 0TQ",
    "wof:placetype":"postalcode"
},
  "geometry": {"coordinates":[-1.38126067171501,53.51238673187432],"type":"Point"}
}