{
  "type": "Feature",
  "properties": {
    "date:inception_lower":"1980-01-01",
    "date:inception_upper":"1980-01-31",
    "iso:country":"GB",
    "wof:name":"S73 0TQ",
    "wof:placetype":"postalcode"
},
  "geometry": {"coordinates":[-1.381261,53.512387],"type":"Point"}
}