{
  "type": "Feature",
  "properties": {
    "iso:country": "GB",
    "wof:name": "S73 0TQ",
    "wof:placetype": "postalcode"
  },
  "geometry": {"coordinates":[-1.381261,53.512387],"type":"Point"}
}
