{
  "type": "Feature",
  "properties": {
    "iso:country":"GB",
    "wof:name":"IG11 9SN",
    "wof:placetype":"postalcode"
},
  "geometry": {"coordinates":[0.09942683652105,51.53434281516984],"type":"Point"}
}