{
  "type": "Feature",
  "properties": {
    "iso:country":"GB",
    "wof:name":"CA7 4AG",
    "wof:placetype":"postalcode"
},
  "geometry": {"coordinates":[-3.38978662590186,54.8670602863703],"type":"Point"}
}