{
  "type": "Feature",
  "properties": {
    "iso:country": "GB",
    "wof:name": "CA7 4AG",
    "wof:placetype": "postalcode"
  },
  "geometry": {"coordinates":[-3.389846,54.866976],"type":"Point"}
}
