{
  "type": "Feature",
  "properties": {
    "date:inception_lower": "1991-09-01",
    "date:inception_upper": "1991-09-01",
    "iso:country": "GB",
    "wof:name": "HD7 4DJ",
    "wof:placetype": "postalcode"
  },
  "geometry": {"coordinates":[-1.84839,53.64153],"type":"Point"}
}
