{
  "type": "Feature",
  "properties": {
    "iso:country": "GB",
    "wof:name": "HD7 4DJ",
    "wof:placetype": "postalcode"
  },
  "geometry": {"coordinates":[-1.84848,53.641489],"type":"Point"}
}
