{
  "type": "Feature",
  "properties": {
    "iso:country":"GB",
    "wof:name":"AB24 5PF",
    "wof:placetype":"postalcode"
},
  "geometry": {"coordinates":[-2.09572491230697,57.1619673825325],"type":"Point"}
}