{
  "type": "Feature",
  "properties": {
    "iso:country": "GB",
    "wof:name": "AB24 5PF",
    "wof:placetype": "postalcode"
  },
  "geometry": {"coordinates":[-2.095725,57.161967],"type":"Point"}
}
