{
  "type": "Feature",
  "properties": {
    "iso:country": "GB",
    "wof:name": "DN19 7SL",
    "wof:placetype": "postalcode"
  },
  "geometry": {"coordinates":[-0.38554,53.677445],"type":"Point"}
}
