{
  "type": "Feature",
  "properties": {
    "iso:country":"GB",
    "wof:name":"IP17 1ES",
    "wof:placetype":"postalcode"
},
  "geometry": {"coordinates":[1.49638106256448,52.21312656970954],"type":"Point"}
}