{
  "type": "Feature",
  "properties": {
    "date:inception_lower": "1980-01-01",
    "date:inception_upper": "1980-01-01",
    "iso:country": "GB",
    "wof:name": "IP17 1ES",
    "wof:placetype": "postalcode"
  },
  "geometry": {"coordinates":[1.496381,52.213127],"type":"Point"}
}
