{
  "type": "Feature",
  "properties": {
    "iso:country":"GB",
    "wof:name":"DE23 8LT",
    "wof:placetype":"postalcode"
},
  "geometry": {"coordinates":[-1.46795648780247,52.90752357205667],"type":"Point"}
}