{
  "type": "Feature",
  "properties": {
    "iso:country": "GB",
    "wof:name": "BN17 5BZ",
    "wof:placetype": "postalcode"
  },
  "geometry": {"coordinates":[-0.547788,50.809509],"type":"Point"}
}
