{
  "type": "Feature",
  "properties": {
    "date:inception_lower": "1997-06-01",
    "date:inception_upper": "1997-06-01",
    "iso:country": "GB",
    "wof:name": "S66 1FQ",
    "wof:placetype": "postalcode"
  },
  "geometry": {"coordinates":[-1.280726,53.420419],"type":"Point"}
}
