{
  "type": "Feature",
  "properties": {
    "iso:country":"GB",
    "wof:name":"SN8 1PU",
    "wof:placetype":"postalcode"
},
  "geometry": {"coordinates":[-1.786370263581,51.4187580679731],"type":"Point"}
}