{
  "type": "Feature",
  "properties": {
    "date:inception_lower": "1980-01-01",
    "date:inception_upper": "1980-01-01",
    "iso:country": "GB",
    "wof:name": "WC1X 8AX",
    "wof:placetype": "postalcode"
  },
  "geometry": {"coordinates":[-0.113338,51.521899],"type":"Point"}
}
