{
  "type": "Feature",
  "properties": {
    "iso:country": "GB",
    "wof:name": "PR3 1UU",
    "wof:placetype": "postalcode"
  },
  "geometry": {"coordinates":[-2.646462,53.884415],"type":"Point"}
}
