{
  "type": "Feature",
  "properties": {
    "iso:country": "GB",
    "wof:name": "BN41 2PQ",
    "wof:placetype": "postalcode"
  },
  "geometry": {"coordinates":[-0.22411,50.845447],"type":"Point"}
}
