{
  "type": "Feature",
  "properties": {
    "iso:country": "GB",
    "wof:name": "ST18 0DD",
    "wof:placetype": "postalcode"
  },
  "geometry": {"coordinates":[-2.082413,52.810053],"type":"Point"}
}
