{
  "type": "Feature",
  "properties": {
    "iso:country":"GB",
    "wof:name":"AB56 5JB",
    "wof:placetype":"postalcode"
},
  "geometry": {"coordinates":[-2.91491586254514,57.64538174645035],"type":"Point"}
}