{
  "type": "Feature",
  "properties": {
    "iso:country":"GB",
    "wof:name":"GU1 3QS",
    "wof:placetype":"postalcode"
},
  "geometry": {"coordinates":[-0.57187694177648,51.23499407123701],"type":"Point"}
}