{
  "type": "Feature",
  "properties": {
    "iso:country": "GB",
    "wof:name": "SY24 5HG",
    "wof:placetype": "postalcode"
  },
  "geometry": {"coordinates":[-3.982797,52.489971],"type":"Point"}
}
