{
  "type": "Feature",
  "properties": {
    "iso:country":"GB",
    "wof:name":"SY24 5HG",
    "wof:placetype":"postalcode"
},
  "geometry": {"coordinates":[-3.98279725385942,52.48997131613071],"type":"Point"}
}