{
  "type": "Feature",
  "properties": {
    "date:inception_lower": "1980-01-01",
    "date:inception_upper": "1980-01-01",
    "iso:country": "GB",
    "wof:name": "SY24 5HG",
    "wof:placetype": "postalcode"
  },
  "geometry": {"coordinates":[-3.982797,52.489971],"type":"Point"}
}
