{
  "type": "Feature",
  "properties": {
    "iso:country": "GB",
    "wof:name": "TR18 2NY",
    "wof:placetype": "postalcode"
  },
  "geometry": {"coordinates":[-5.539592,50.118867],"type":"Point"}
}
