{
  "type": "Feature",
  "properties": {
    "iso:country":"GB",
    "wof:name":"DH7 6EY",
    "wof:placetype":"postalcode"
},
  "geometry": {"coordinates":[-1.65804607370133,54.83604478182455],"type":"Point"}
}