{
  "type": "Feature",
  "properties": {
    "date:inception_lower":"1995-07-01",
    "date:inception_upper":"1995-07-31",
    "iso:country":"GB",
    "wof:name":"CM14 4FS",
    "wof:placetype":"postalcode"
},
  "geometry": {"coordinates":[0.305175,51.618998],"type":"Point"}
}