{
  "type": "Feature",
  "properties": {
    "iso:country":"GB",
    "wof:name":"AB54 4XY",
    "wof:placetype":"postalcode"
},
  "geometry": {"coordinates":[-2.96106587351238,57.44091924964544],"type":"Point"}
}