{
  "type": "Feature",
  "properties": {
    "date:inception_lower": "2015-03-01",
    "date:inception_upper": "2015-03-01",
    "iso:country": "GB",
    "wof:name": "EH16 6AH",
    "wof:placetype": "postalcode"
  },
  "geometry": {"coordinates":[-3.167059,55.92105],"type":"Point"}
}
