{
  "type": "Feature",
  "properties": {
    "iso:country":"GB",
    "wof:name":"EH16 6AH",
    "wof:placetype":"postalcode"
},
  "geometry": {"coordinates":[-3.16704216542795,55.92106386597701],"type":"Point"}
}