{
  "type": "Feature",
  "properties": {
    "iso:country":"GB",
    "wof:name":"KT3 3HN",
    "wof:placetype":"postalcode"
},
  "geometry": {"coordinates":[-0.26566396373085,51.40431615422171],"type":"Point"}
}