{
  "type": "Feature",
  "properties": {
    "date:inception_lower":"1980-01-01",
    "date:inception_upper":"1980-01-31",
    "iso:country":"GB",
    "wof:name":"TW9 4AA",
    "wof:placetype":"postalcode"
},
  "geometry": {"coordinates":[-0.281627,51.479342],"type":"Point"}
}