{
  "type": "Feature",
  "properties": {
    "iso:country":"GB",
    "wof:name":"TW9 4AA",
    "wof:placetype":"postalcode"
},
  "geometry": {"coordinates":[-0.28162739698478,51.47934152940691],"type":"Point"}
}