{
  "type": "Feature",
  "properties": {
    "iso:country":"GB",
    "wof:name":"AL1 4LA",
    "wof:placetype":"postalcode"
},
  "geometry": {"coordinates":[-0.31601083316492,51.75347204876908],"type":"Point"}
}