{
  "type": "Feature",
  "properties": {
    "iso:country":"GB",
    "wof:name":"TA19 9HG",
    "wof:placetype":"postalcode"
},
  "geometry": {"coordinates":[-2.92692092421143,50.9546236993949],"type":"Point"}
}