{
  "type": "Feature",
  "properties": {
    "iso:country": "GB",
    "wof:name": "BB9 5BN",
    "wof:placetype": "postalcode"
  },
  "geometry": {"coordinates":[-2.226594,53.822785],"type":"Point"}
}
