{
  "type": "Feature",
  "properties": {
    "date:inception_lower":"2015-12-01",
    "date:inception_upper":"2015-12-31",
    "iso:country":"GB",
    "wof:name":"S2 5QD",
    "wof:placetype":"postalcode"
},
  "geometry": {"coordinates":[-1.458594,53.381681],"type":"Point"}
}