{
  "type": "Feature",
  "properties": {
    "date:inception_lower": "2015-12-01",
    "date:inception_upper": "2015-12-01",
    "iso:country": "GB",
    "wof:name": "S2 5QD",
    "wof:placetype": "postalcode"
  },
  "geometry": {"coordinates":[-1.458533,53.381726],"type":"Point"}
}
