{
  "type": "Feature",
  "properties": {
    "iso:country":"GB",
    "wof:name":"CM3 5DE",
    "wof:placetype":"postalcode"
},
  "geometry": {"coordinates":[0.62002394687582,51.64497371801425],"type":"Point"}
}