{
  "type": "Feature",
  "properties": {
    "iso:country": "GB",
    "wof:name": "CM3 5DE",
    "wof:placetype": "postalcode"
  },
  "geometry": {"coordinates":[0.620024,51.644974],"type":"Point"}
}
