{
  "type": "Feature",
  "properties": {
    "iso:country":"GB",
    "wof:name":"NW11 8DD",
    "wof:placetype":"postalcode"
},
  "geometry": {"coordinates":[-0.19499846658434,51.56698418898718],"type":"Point"}
}