{
  "type": "Feature",
  "properties": {
    "iso:country":"GB",
    "wof:name":"E12 5DQ",
    "wof:placetype":"postalcode"
},
  "geometry": {"coordinates":[0.04418627307754,51.55813295815192],"type":"Point"}
}