{
  "type": "Feature",
  "properties": {
    "iso:country":"GB",
    "wof:name":"TS5 8PF",
    "wof:placetype":"postalcode"
},
  "geometry": {"coordinates":[-1.26118156355474,54.5452528139967],"type":"Point"}
}