{
  "type": "Feature",
  "properties": {
    "date:inception_lower":"2008-01-01",
    "date:inception_upper":"2008-01-31",
    "iso:country":"GB",
    "wof:name":"L28 0QU",
    "wof:placetype":"postalcode"
},
  "geometry": {"coordinates":[-2.877519,53.43551],"type":"Point"}
}