{
  "type": "Feature",
  "properties": {
    "iso:country":"GB",
    "wof:name":"B75 7NR",
    "wof:placetype":"postalcode"
},
  "geometry": {"coordinates":[-1.78613022293978,52.56559608918891],"type":"Point"}
}