{
  "type": "Feature",
  "properties": {
    "date:inception_lower": "2015-03-01",
    "date:inception_upper": "2015-03-01",
    "iso:country": "GB",
    "wof:name": "NN6 9RP",
    "wof:placetype": "postalcode"
  },
  "geometry": {"coordinates":[-0.822492,52.342003],"type":"Point"}
}
