{
  "type": "Feature",
  "properties": {
    "iso:country": "GB",
    "wof:name": "NN6 9RP",
    "wof:placetype": "postalcode"
  },
  "geometry": {"coordinates":[-0.822492,52.342003],"type":"Point"}
}
