{
  "type": "Feature",
  "properties": {
    "iso:country":"GB",
    "wof:name":"B29 7PZ",
    "wof:placetype":"postalcode"
},
  "geometry": {"coordinates":[-1.91503492268502,52.43784078698027],"type":"Point"}
}