{
  "type": "Feature",
  "properties": {
    "iso:country":"GB",
    "wof:name":"TR6 0AR",
    "wof:placetype":"postalcode"
},
  "geometry": {"coordinates":[-5.13961469761572,50.33826900740249],"type":"Point"}
}