{
  "type": "Feature",
  "properties": {
    "iso:country": "GB",
    "wof:name": "SO45 1EL",
    "wof:placetype": "postalcode"
  },
  "geometry": {"coordinates":[-1.36686,50.821405],"type":"Point"}
}
