{
  "type": "Feature",
  "properties": {
    "iso:country":"GB",
    "wof:name":"SO45 1EL",
    "wof:placetype":"postalcode"
},
  "geometry": {"coordinates":[-1.36685995945145,50.82140475592989],"type":"Point"}
}