{
  "type": "Feature",
  "properties": {
    "iso:country":"GB",
    "wof:name":"CA28 7NJ",
    "wof:placetype":"postalcode"
},
  "geometry": {"coordinates":[-3.58569750828637,54.54788711926515],"type":"Point"}
}