{
  "type": "Feature",
  "properties": {
    "date:inception_lower": "2021-08-01",
    "date:inception_upper": "2021-08-01",
    "iso:country": "GB",
    "wof:name": "PE28 4NA",
    "wof:placetype": "postalcode"
  },
  "geometry": {"coordinates":[-0.235726,52.373569],"type":"Point"}
}
