{
  "type": "Feature",
  "properties": {
    "iso:country":"GB",
    "wof:name":"HA4 6PA",
    "wof:placetype":"postalcode"
},
  "geometry": {"coordinates":[-0.41367017366047,51.56064820755113],"type":"Point"}
}