{
  "type": "Feature",
  "properties": {
    "iso:country":"GB",
    "wof:name":"B19 3BU",
    "wof:placetype":"postalcode"
},
  "geometry": {"coordinates":[-1.90576839980466,52.49276258622978],"type":"Point"}
}