{
  "type": "Feature",
  "properties": {
    "iso:country":"GB",
    "wof:name":"OX2 8DA",
    "wof:placetype":"postalcode"
},
  "geometry": {"coordinates":[-1.27413704083248,51.78424192238731],"type":"Point"}
}