{
  "type": "Feature",
  "properties": {
    "iso:country":"GB",
    "wof:name":"SG3 6AU",
    "wof:placetype":"postalcode"
},
  "geometry": {"coordinates":[-0.18712163895568,51.86559170834246],"type":"Point"}
}