{
  "type": "Feature",
  "properties": {
    "date:inception_lower": "1999-12-01",
    "date:inception_upper": "1999-12-01",
    "iso:country": "GB",
    "wof:name": "TA1 2LU",
    "wof:placetype": "postalcode"
  },
  "geometry": {"coordinates":[-3.082356,51.007557],"type":"Point"}
}
