{
  "type": "Feature",
  "properties": {
    "iso:country":"GB",
    "wof:name":"IP5 2QJ",
    "wof:placetype":"postalcode"
},
  "geometry": {"coordinates":[1.25946999174534,52.06404713318565],"type":"Point"}
}