{
  "type": "Feature",
  "properties": {
    "iso:country":"GB",
    "wof:name":"E3 4QE",
    "wof:placetype":"postalcode"
},
  "geometry": {"coordinates":[-0.03202611516404,51.52209881929993],"type":"Point"}
}