{
  "type": "Feature",
  "properties": {
    "date:inception_lower": "2010-09-01",
    "date:inception_upper": "2010-09-01",
    "iso:country": "GB",
    "wof:name": "HG3 4HH",
    "wof:placetype": "postalcode"
  },
  "geometry": {"coordinates":[-1.708118,54.057321],"type":"Point"}
}
