{
  "type": "Feature",
  "properties": {
    "iso:country": "GB",
    "wof:name": "HG3 4HH",
    "wof:placetype": "postalcode"
  },
  "geometry": {"coordinates":[-1.708409,54.057187],"type":"Point"}
}
