{
  "type": "Feature",
  "properties": {
    "date:inception_lower": "2002-07-01",
    "date:inception_upper": "2002-07-01",
    "iso:country": "GB",
    "wof:name": "HP19 7GL",
    "wof:placetype": "postalcode"
  },
  "geometry": {"coordinates":[-0.841609,51.815798],"type":"Point"}
}
