{
  "type": "Feature",
  "properties": {
    "iso:country": "GB",
    "wof:name": "CV34 5NR",
    "wof:placetype": "postalcode"
  },
  "geometry": {"coordinates":[-1.565849,52.291062],"type":"Point"}
}
