{
  "type": "Feature",
  "properties": {
    "iso:country":"GB",
    "wof:name":"CV34 5NR",
    "wof:placetype":"postalcode"
},
  "geometry": {"coordinates":[-1.5658754918205,52.29100254177393],"type":"Point"}
}