{
  "type": "Feature",
  "properties": {
    "date:inception_lower":"1980-01-01",
    "date:inception_upper":"1980-01-31",
    "iso:country":"GB",
    "wof:name":"B47 6EP",
    "wof:placetype":"postalcode"
},
  "geometry": {"coordinates":[-1.879707,52.376228],"type":"Point"}
}