{
  "type": "Feature",
  "properties": {
    "iso:country": "GB",
    "wof:name": "B47 6EP",
    "wof:placetype": "postalcode"
  },
  "geometry": {"coordinates":[-1.879707,52.376228],"type":"Point"}
}
