{
  "type": "Feature",
  "properties": {
    "date:inception_lower": "1980-01-01",
    "date:inception_upper": "1980-01-01",
    "iso:country": "GB",
    "wof:name": "BH9 1DZ",
    "wof:placetype": "postalcode"
  },
  "geometry": {"coordinates":[-1.865747,50.743271],"type":"Point"}
}
