{
  "type": "Feature",
  "properties": {
    "iso:country": "GB",
    "wof:name": "PR6 0PY",
    "wof:placetype": "postalcode"
  },
  "geometry": {"coordinates":[-2.617213,53.650327],"type":"Point"}
}
