{
  "type": "Feature",
  "properties": {
    "iso:country":"GB",
    "wof:name":"PO13 8NQ",
    "wof:placetype":"postalcode"
},
  "geometry": {"coordinates":[-1.16712772441658,50.80148155657513],"type":"Point"}
}