{
  "type": "Feature",
  "properties": {
    "date:inception_lower":"2014-09-01",
    "date:inception_upper":"2014-09-30",
    "iso:country":"GB",
    "wof:name":"PO13 8NQ",
    "wof:placetype":"postalcode"
},
  "geometry": {"coordinates":[-1.167128,50.801482],"type":"Point"}
}