{
  "type": "Feature",
  "properties": {
    "iso:country":"GB",
    "wof:name":"N15 4PF",
    "wof:placetype":"postalcode"
},
  "geometry": {"coordinates":[-0.06687903927078,51.58272159653737],"type":"Point"}
}