{
  "type": "Feature",
  "properties": {
    "iso:country":"GB",
    "wof:name":"CM2 6HB",
    "wof:placetype":"postalcode"
},
  "geometry": {"coordinates":[0.48376778615203,51.73428800782694],"type":"Point"}
}