{
  "type": "Feature",
  "properties": {
    "date:inception_lower": "1980-01-01",
    "date:inception_upper": "1980-01-01",
    "iso:country": "GB",
    "wof:name": "CM2 6HB",
    "wof:placetype": "postalcode"
  },
  "geometry": {"coordinates":[0.483768,51.734288],"type":"Point"}
}
