{
  "type": "Feature",
  "properties": {
    "iso:country": "GB",
    "wof:name": "CM2 6HB",
    "wof:placetype": "postalcode"
  },
  "geometry": {"coordinates":[0.483768,51.734288],"type":"Point"}
}
