{
  "type": "Feature",
  "properties": {
    "iso:country": "GB",
    "wof:name": "NP19 9EB",
    "wof:placetype": "postalcode"
  },
  "geometry": {"coordinates":[-2.948062,51.591012],"type":"Point"}
}
