{
  "type": "Feature",
  "properties": {
    "iso:country":"GB",
    "wof:name":"SN1 2JH",
    "wof:placetype":"postalcode"
},
  "geometry": {"coordinates":[-1.77791980590267,51.5601246515386],"type":"Point"}
}