{
  "type": "Feature",
  "properties": {
    "iso:country":"GB",
    "wof:name":"BL3 4NG",
    "wof:placetype":"postalcode"
},
  "geometry": {"coordinates":[-2.47419733090014,53.56759581454649],"type":"Point"}
}