{
  "type": "Feature",
  "properties": {
    "iso:country":"GB",
    "wof:name":"TA3 6QS",
    "wof:placetype":"postalcode"
},
  "geometry": {"coordinates":[-2.88615540670471,50.98432772376952],"type":"Point"}
}