{
  "type": "Feature",
  "properties": {
    "iso:country": "GB",
    "wof:name": "TA3 6QS",
    "wof:placetype": "postalcode"
  },
  "geometry": {"coordinates":[-2.886155,50.984328],"type":"Point"}
}
