{
  "type": "Feature",
  "properties": {
    "iso:country":"GB",
    "wof:name":"BA4 6EN",
    "wof:placetype":"postalcode"
},
  "geometry": {"coordinates":[-2.46078230279437,51.15132903085579],"type":"Point"}
}