{
  "type": "Feature",
  "properties": {
    "iso:country": "GB",
    "wof:name": "SK13 7QB",
    "wof:placetype": "postalcode"
  },
  "geometry": {"coordinates":[-1.927153,53.443044],"type":"Point"}
}
