{
  "type": "Feature",
  "properties": {
    "date:inception_lower": "1993-08-01",
    "date:inception_upper": "1993-08-01",
    "iso:country": "GB",
    "wof:name": "NN3 9DD",
    "wof:placetype": "postalcode"
  },
  "geometry": {"coordinates":[-0.827547,52.252402],"type":"Point"}
}
