{
  "type": "Feature",
  "properties": {
    "iso:country": "GB",
    "wof:name": "LL16 3UD",
    "wof:placetype": "postalcode"
  },
  "geometry": {"coordinates":[-3.418994,53.186065],"type":"Point"}
}
