{
  "type": "Feature",
  "properties": {
    "date:inception_lower": "1980-01-01",
    "date:inception_upper": "1980-01-01",
    "iso:country": "GB",
    "wof:name": "LL16 3UD",
    "wof:placetype": "postalcode"
  },
  "geometry": {"coordinates":[-3.418994,53.186065],"type":"Point"}
}
