{
  "type": "Feature",
  "properties": {
    "iso:country": "GB",
    "wof:name": "NP44 1LE",
    "wof:placetype": "postalcode"
  },
  "geometry": {"coordinates":[-3.038393,51.661605],"type":"Point"}
}
