{
  "type": "Feature",
  "properties": {
    "date:inception_lower": "1990-08-01",
    "date:inception_upper": "1990-08-01",
    "iso:country": "GB",
    "wof:name": "AB41 8HR",
    "wof:placetype": "postalcode"
  },
  "geometry": {"coordinates":[-1.990681,57.422176],"type":"Point"}
}
