{
  "type": "Feature",
  "properties": {
    "iso:country":"GB",
    "wof:name":"SA6 8NB",
    "wof:placetype":"postalcode"
},
  "geometry": {"coordinates":[-3.92895530349135,51.65698706392259],"type":"Point"}
}