{
  "type": "Feature",
  "properties": {
    "iso:country": "GB",
    "wof:name": "SA6 8NB",
    "wof:placetype": "postalcode"
  },
  "geometry": {"coordinates":[-3.928955,51.656987],"type":"Point"}
}
