{
  "type": "Feature",
  "properties": {
    "iso:country":"GB",
    "wof:name":"CH41 4HJ",
    "wof:placetype":"postalcode"
},
  "geometry": {"coordinates":[-3.03208996077943,53.39544201595925],"type":"Point"}
}