{
  "type": "Feature",
  "properties": {
    "iso:country":"GB",
    "wof:name":"MK9 3JZ",
    "wof:placetype":"postalcode"
},
  "geometry": {"coordinates":[-0.75219562214934,52.04670675874437],"type":"Point"}
}