{
  "type": "Feature",
  "properties": {
    "iso:country":"GB",
    "wof:name":"LA6 3DQ",
    "wof:placetype":"postalcode"
},
  "geometry": {"coordinates":[-2.46710342522953,54.14772439574143],"type":"Point"}
}