{
  "type": "Feature",
  "properties": {
    "iso:country":"GB",
    "wof:name":"HS2 9LP",
    "wof:placetype":"postalcode"
},
  "geometry": {"coordinates":[-6.82982919982307,58.20227764183355],"type":"Point"}
}