{
  "type": "Feature",
  "properties": {
    "iso:country": "GB",
    "wof:name": "HS2 9LP",
    "wof:placetype": "postalcode"
  },
  "geometry": {"coordinates":[-6.829829,58.202278],"type":"Point"}
}
