{
  "type": "Feature",
  "properties": {
    "date:inception_lower": "1995-01-01",
    "date:inception_upper": "1995-01-01",
    "iso:country": "GB",
    "wof:name": "WV14 6LU",
    "wof:placetype": "postalcode"
  },
  "geometry": {"coordinates":[-2.073265,52.575817],"type":"Point"}
}
