{
  "type": "Feature",
  "properties": {
    "iso:country":"GB",
    "wof:name":"M28 3BU",
    "wof:placetype":"postalcode"
},
  "geometry": {"coordinates":[-2.3992766999553,53.52453642414739],"type":"Point"}
}