{
  "type": "Feature",
  "properties": {
    "date:inception_lower": "2018-09-01",
    "date:inception_upper": "2018-09-01",
    "iso:country": "GB",
    "wof:name": "M28 3BU",
    "wof:placetype": "postalcode"
  },
  "geometry": {"coordinates":[-2.399275,53.524553],"type":"Point"}
}
