{
  "type": "Feature",
  "properties": {
    "iso:country":"GB",
    "wof:name":"G62 7HB",
    "wof:placetype":"postalcode"
},
  "geometry": {"coordinates":[-4.36302243935197,55.96842212862984],"type":"Point"}
}