{
  "type": "Feature",
  "properties": {
    "iso:country":"GB",
    "wof:name":"M18 8NS",
    "wof:placetype":"postalcode"
},
  "geometry": {"coordinates":[-2.16818440134806,53.46567179876021],"type":"Point"}
}