{
  "type": "Feature",
  "properties": {
    "iso:country": "GB",
    "wof:name": "M18 8NS",
    "wof:placetype": "postalcode"
  },
  "geometry": {"coordinates":[-2.168184,53.465672],"type":"Point"}
}
