{
  "type": "Feature",
  "properties": {
    "iso:country": "GB",
    "wof:name": "GU14 8SE",
    "wof:placetype": "postalcode"
  },
  "geometry": {"coordinates":[-0.770299,51.307854],"type":"Point"}
}
