{
  "type": "Feature",
  "properties": {
    "date:inception_lower":"2003-07-01",
    "date:inception_upper":"2003-07-31",
    "iso:country":"GB",
    "wof:name":"DN16 3WF",
    "wof:placetype":"postalcode"
},
  "geometry": {"coordinates":[-0.64346,53.551634],"type":"Point"}
}