{
  "type": "Feature",
  "properties": {
    "iso:country":"GB",
    "wof:name":"G66 2PF",
    "wof:placetype":"postalcode"
},
  "geometry": {"coordinates":[-4.12979055339028,55.94297255768915],"type":"Point"}
}