{
  "type": "Feature",
  "properties": {
    "iso:country":"GB",
    "wof:name":"RG5 4HH",
    "wof:placetype":"postalcode"
},
  "geometry": {"coordinates":[-0.90130068693637,51.44937750947271],"type":"Point"}
}