{
  "type": "Feature",
  "properties": {
    "iso:country":"GB",
    "wof:name":"BB11 5RG",
    "wof:placetype":"postalcode"
},
  "geometry": {"coordinates":[-2.31825276166722,53.78038658743334],"type":"Point"}
}