{
  "type": "Feature",
  "properties": {
    "iso:country":"GB",
    "wof:name":"TA1 1DQ",
    "wof:placetype":"postalcode"
},
  "geometry": {"coordinates":[-3.10712415921638,51.01993202884076],"type":"Point"}
}