{
  "type": "Feature",
  "properties": {
    "iso:country":"GB",
    "wof:name":"NN16 9UJ",
    "wof:placetype":"postalcode"
},
  "geometry": {"coordinates":[-0.71556216271296,52.41618986642181],"type":"Point"}
}