{
  "type": "Feature",
  "properties": {
    "iso:country":"GB",
    "wof:name":"OL12 0HE",
    "wof:placetype":"postalcode"
},
  "geometry": {"coordinates":[-2.15199549335621,53.62232447658113],"type":"Point"}
}