{
  "type": "Feature",
  "properties": {
    "date:inception_lower":"2007-07-01",
    "date:inception_upper":"2007-07-31",
    "iso:country":"GB",
    "wof:name":"TD11 3TE",
    "wof:placetype":"postalcode"
},
  "geometry": {"coordinates":[-2.215469,55.79891],"type":"Point"}
}