{
  "type": "Feature",
  "properties": {
    "iso:country":"GB",
    "wof:name":"WA3 2PG",
    "wof:placetype":"postalcode"
},
  "geometry": {"coordinates":[-2.56844112364242,53.47140338867477],"type":"Point"}
}