{
  "type": "Feature",
  "properties": {
    "date:inception_lower": "1980-01-01",
    "date:inception_upper": "1980-01-01",
    "iso:country": "GB",
    "wof:name": "B42 2RT",
    "wof:placetype": "postalcode"
  },
  "geometry": {"coordinates":[-1.898242,52.537481],"type":"Point"}
}
