{
  "type": "Feature",
  "properties": {
    "iso:country":"GB",
    "wof:name":"EH42 1EY",
    "wof:placetype":"postalcode"
},
  "geometry": {"coordinates":[-2.51532009019114,56.00325257299087],"type":"Point"}
}