{
  "type": "Feature",
  "properties": {
    "iso:country": "GB",
    "wof:name": "IG1 4TU",
    "wof:placetype": "postalcode"
  },
  "geometry": {"coordinates":[0.077328,51.570554],"type":"Point"}
}
