{
  "type": "Feature",
  "properties": {
    "date:inception_lower": "2018-12-01",
    "date:inception_upper": "2018-12-01",
    "iso:country": "GB",
    "wof:name": "OX2 0FG",
    "wof:placetype": "postalcode"
  },
  "geometry": {"coordinates":[-1.291963,51.750081],"type":"Point"}
}
