{
  "type": "Feature",
  "properties": {
    "iso:country": "GB",
    "wof:name": "M5 5AA",
    "wof:placetype": "postalcode"
  },
  "geometry": {"coordinates":[-2.328768,53.484967],"type":"Point"}
}
