{
  "type": "Feature",
  "properties": {
    "iso:country": "GB",
    "wof:name": "HP21 8LF",
    "wof:placetype": "postalcode"
  },
  "geometry": {"coordinates":[-0.822575,51.810799],"type":"Point"}
}
