{
  "type": "Feature",
  "properties": {
    "iso:country":"GB",
    "wof:name":"HX4 9JR",
    "wof:placetype":"postalcode"
},
  "geometry": {"coordinates":[-1.88147560542285,53.66069755224368],"type":"Point"}
}