{
  "type": "Feature",
  "properties": {
    "iso:country":"GB",
    "wof:name":"SY16 2HF",
    "wof:placetype":"postalcode"
},
  "geometry": {"coordinates":[-3.31887895737339,52.51875609301689],"type":"Point"}
}