{
  "type": "Feature",
  "properties": {
    "iso:country":"GB",
    "wof:name":"HD7 6BT",
    "wof:placetype":"postalcode"
},
  "geometry": {"coordinates":[-1.92762512411164,53.60114240645255],"type":"Point"}
}