{
  "type": "Feature",
  "properties": {
    "iso:country": "GB",
    "wof:name": "HD7 6BT",
    "wof:placetype": "postalcode"
  },
  "geometry": {"coordinates":[-1.927625,53.601142],"type":"Point"}
}
