{
  "type": "Feature",
  "properties": {
    "date:inception_lower": "1999-06-01",
    "date:inception_upper": "1999-06-01",
    "iso:country": "GB",
    "wof:name": "CH44 6PA",
    "wof:placetype": "postalcode"
  },
  "geometry": {"coordinates":[-3.017796,53.410882],"type":"Point"}
}
