{
  "type": "Feature",
  "properties": {
    "iso:country":"GB",
    "wof:name":"CH44 6PA",
    "wof:placetype":"postalcode"
},
  "geometry": {"coordinates":[-3.01779562877468,53.41088194517814],"type":"Point"}
}