{
  "type": "Feature",
  "properties": {
    "date:inception_lower": "1985-04-01",
    "date:inception_upper": "1985-04-01",
    "iso:country": "GB",
    "wof:name": "SN5 6ED",
    "wof:placetype": "postalcode"
  },
  "geometry": {"coordinates":[-1.84515,51.553318],"type":"Point"}
}
