{
  "type": "Feature",
  "properties": {
    "iso:country": "GB",
    "wof:name": "SN5 6ED",
    "wof:placetype": "postalcode"
  },
  "geometry": {"coordinates":[-1.84515,51.553318],"type":"Point"}
}
