{
  "type": "Feature",
  "properties": {
    "iso:country": "GB",
    "wof:name": "S71 3LS",
    "wof:placetype": "postalcode"
  },
  "geometry": {"coordinates":[-1.481164,53.580293],"type":"Point"}
}
