{
  "type": "Feature",
  "properties": {
    "date:inception_lower": "2015-07-01",
    "date:inception_upper": "2015-07-01",
    "iso:country": "GB",
    "wof:name": "CO3 3FA",
    "wof:placetype": "postalcode"
  },
  "geometry": {"coordinates":[0.876407,51.885991],"type":"Point"}
}
