{
  "type": "Feature",
  "properties": {
    "iso:country": "GB",
    "wof:name": "CO3 3FA",
    "wof:placetype": "postalcode"
  },
  "geometry": {"coordinates":[0.876407,51.885991],"type":"Point"}
}
