{
  "type": "Feature",
  "properties": {
    "iso:country":"GB",
    "wof:name":"BB8 0ED",
    "wof:placetype":"postalcode"
},
  "geometry": {"coordinates":[-2.1688698079988,53.85690803290796],"type":"Point"}
}