{
  "type": "Feature",
  "properties": {
    "date:inception_lower": "1980-01-01",
    "date:inception_upper": "1980-01-01",
    "iso:country": "GB",
    "wof:name": "DH7 6BB",
    "wof:placetype": "postalcode"
  },
  "geometry": {"coordinates":[-1.627556,54.824911],"type":"Point"}
}
