{
  "type": "Feature",
  "properties": {
    "iso:country":"GB",
    "wof:name":"BA22 7HW",
    "wof:placetype":"postalcode"
},
  "geometry": {"coordinates":[-2.54866236930198,51.01448408163953],"type":"Point"}
}