{
  "type": "Feature",
  "properties": {
    "iso:country":"GB",
    "wof:name":"GL5 2SL",
    "wof:placetype":"postalcode"
},
  "geometry": {"coordinates":[-2.20735228596701,51.72373758227531],"type":"Point"}
}