{
  "type": "Feature",
  "properties": {
    "date:inception_lower": "1980-01-01",
    "date:inception_upper": "1980-01-01",
    "iso:country": "GB",
    "wof:name": "LN2 5JG",
    "wof:placetype": "postalcode"
  },
  "geometry": {"coordinates":[-0.528735,53.231674],"type":"Point"}
}
