{
  "type": "Feature",
  "properties": {
    "date:inception_lower": "2003-08-01",
    "date:inception_upper": "2003-08-01",
    "iso:country": "GB",
    "wof:name": "TS26 0GB",
    "wof:placetype": "postalcode"
  },
  "geometry": {"coordinates":[-1.248358,54.685227],"type":"Point"}
}
