{
  "type": "Feature",
  "properties": {
    "iso:country":"GB",
    "wof:name":"TS26 0GB",
    "wof:placetype":"postalcode"
},
  "geometry": {"coordinates":[-1.24835836759661,54.68522697481339],"type":"Point"}
}