{
  "type": "Feature",
  "properties": {
    "date:inception_lower": "2007-01-01",
    "date:inception_upper": "2007-01-01",
    "iso:country": "GB",
    "wof:name": "LU7 4QR",
    "wof:placetype": "postalcode"
  },
  "geometry": {"coordinates":[-0.642521,51.906102],"type":"Point"}
}
