{
  "type": "Feature",
  "properties": {
    "iso:country":"GB",
    "wof:name":"LU7 4QR",
    "wof:placetype":"postalcode"
},
  "geometry": {"coordinates":[-0.64252089599558,51.90610179746307],"type":"Point"}
}