{
  "type": "Feature",
  "properties": {
    "iso:country": "GB",
    "wof:name": "BN42 4WF",
    "wof:placetype": "postalcode"
  },
  "geometry": {"coordinates":[-0.234862,50.846608],"type":"Point"}
}
