{
  "type": "Feature",
  "properties": {
    "iso:country":"GB",
    "wof:name":"LL15 2NG",
    "wof:placetype":"postalcode"
},
  "geometry": {"coordinates":[-3.38883774463252,53.06237461242053],"type":"Point"}
}