{
  "type": "Feature",
  "properties": {
    "iso:country":"GB",
    "wof:name":"CH5 4LJ",
    "wof:placetype":"postalcode"
},
  "geometry": {"coordinates":[-3.07005185080851,53.21076722166379],"type":"Point"}
}