{
  "type": "Feature",
  "properties": {
    "date:inception_lower":"2001-06-01",
    "date:inception_upper":"2001-06-30",
    "iso:country":"GB",
    "wof:name":"BS36 2GZ",
    "wof:placetype":"postalcode"
},
  "geometry": {"coordinates":[-2.467033,51.529948],"type":"Point"}
}