{
  "type": "Feature",
  "properties": {
    "iso:country":"GB",
    "wof:name":"BS36 2GZ",
    "wof:placetype":"postalcode"
},
  "geometry": {"coordinates":[-2.46703274566739,51.5299478870174],"type":"Point"}
}