{
  "type": "Feature",
  "properties": {
    "iso:country":"GB",
    "wof:name":"GL1 4EW",
    "wof:placetype":"postalcode"
},
  "geometry": {"coordinates":[-2.23839683496149,51.85938029219988],"type":"Point"}
}