{
  "type": "Feature",
  "properties": {
    "date:inception_lower": "1980-01-01",
    "date:inception_upper": "1980-01-01",
    "iso:country": "GB",
    "wof:name": "GL1 4EW",
    "wof:placetype": "postalcode"
  },
  "geometry": {"coordinates":[-2.238397,51.85938],"type":"Point"}
}
