{
  "type": "Feature",
  "properties": {
    "iso:country": "GB",
    "wof:name": "SA70 8HS",
    "wof:placetype": "postalcode"
  },
  "geometry": {"coordinates":[-4.707109,51.67842],"type":"Point"}
}
