{
  "type": "Feature",
  "properties": {
    "iso:country":"GB",
    "wof:name":"SA70 8HS",
    "wof:placetype":"postalcode"
},
  "geometry": {"coordinates":[-4.70710940658448,51.67841962963568],"type":"Point"}
}