{
  "type": "Feature",
  "properties": {
    "date:inception_lower": "1993-08-01",
    "date:inception_upper": "1993-08-01",
    "iso:country": "GB",
    "wof:name": "SY16 2JW",
    "wof:placetype": "postalcode"
  },
  "geometry": {"coordinates":[-3.301238,52.521765],"type":"Point"}
}
