{
  "type": "Feature",
  "properties": {
    "iso:country":"GB",
    "wof:name":"IP16 4EF",
    "wof:placetype":"postalcode"
},
  "geometry": {"coordinates":[1.57092749944866,52.20237394712329],"type":"Point"}
}