{
  "type": "Feature",
  "properties": {
    "iso:country":"GB",
    "wof:name":"DT2 7AQ",
    "wof:placetype":"postalcode"
},
  "geometry": {"coordinates":[-2.47328355752498,50.7750568452847],"type":"Point"}
}