{
  "type": "Feature",
  "properties": {
    "iso:country": "GB",
    "wof:name": "DT2 7AQ",
    "wof:placetype": "postalcode"
  },
  "geometry": {"coordinates":[-2.473269,50.775101],"type":"Point"}
}
