{
  "type": "Feature",
  "properties": {
    "date:inception_lower":"1980-01-01",
    "date:inception_upper":"1980-01-31",
    "iso:country":"GB",
    "wof:name":"WS11 1NT",
    "wof:placetype":"postalcode"
},
  "geometry": {"coordinates":[-2.044883,52.684571],"type":"Point"}
}