{
  "type": "Feature",
  "properties": {
    "iso:country":"GB",
    "wof:name":"SL1 7AU",
    "wof:placetype":"postalcode"
},
  "geometry": {"coordinates":[-0.66638771462972,51.53215850840101],"type":"Point"}
}