{
  "type": "Feature",
  "properties": {
    "iso:country": "GB",
    "wof:name": "SL1 7AU",
    "wof:placetype": "postalcode"
  },
  "geometry": {"coordinates":[-0.666388,51.532159],"type":"Point"}
}
