{
  "type": "Feature",
  "properties": {
    "date:inception_lower": "2023-07-01",
    "date:inception_upper": "2023-07-01",
    "iso:country": "GB",
    "wof:name": "CH5 2GP",
    "wof:placetype": "postalcode"
  },
  "geometry": {"coordinates":[-3.010353,53.219853],"type":"Point"}
}
