{
  "type": "Feature",
  "properties": {
    "iso:country":"GB",
    "wof:name":"SS16 5DL",
    "wof:placetype":"postalcode"
},
  "geometry": {"coordinates":[0.4614521365584,51.56306974114428],"type":"Point"}
}