{
  "type": "Feature",
  "properties": {
    "iso:country": "GB",
    "wof:name": "NG17 5AT",
    "wof:placetype": "postalcode"
  },
  "geometry": {"coordinates":[-1.262981,53.118039],"type":"Point"}
}
