{
  "type": "Feature",
  "properties": {
    "iso:country":"GB",
    "wof:name":"N8 7JW",
    "wof:placetype":"postalcode"
},
  "geometry": {"coordinates":[-0.12120096945747,51.58536636559764],"type":"Point"}
}