{
  "type": "Feature",
  "properties": {
    "iso:country":"GB",
    "wof:name":"DD1 1LA",
    "wof:placetype":"postalcode"
},
  "geometry": {"coordinates":[-2.97645338094788,56.46437663457605],"type":"Point"}
}