{
  "type": "Feature",
  "properties": {
    "date:inception_lower": "1980-01-01",
    "date:inception_upper": "1980-01-01",
    "iso:country": "GB",
    "wof:name": "LL16 3DS",
    "wof:placetype": "postalcode"
  },
  "geometry": {"coordinates":[-3.409828,53.188649],"type":"Point"}
}
