{
  "type": "Feature",
  "properties": {
    "iso:country":"GB",
    "wof:name":"CT17 0TT",
    "wof:placetype":"postalcode"
},
  "geometry": {"coordinates":[1.29863448335585,51.13454932865711],"type":"Point"}
}