{
  "type": "Feature",
  "properties": {
    "iso:country":"GB",
    "wof:name":"LE16 7XT",
    "wof:placetype":"postalcode"
},
  "geometry": {"coordinates":[-0.89682318666906,52.47590913184879],"type":"Point"}
}