{
  "type": "Feature",
  "properties": {
    "date:inception_lower":"2001-06-01",
    "date:inception_upper":"2001-06-30",
    "iso:country":"GB",
    "wof:name":"LE16 7XT",
    "wof:placetype":"postalcode"
},
  "geometry": {"coordinates":[-0.896823,52.475909],"type":"Point"}
}