{
  "type": "Feature",
  "properties": {
    "iso:country":"GB",
    "wof:name":"TS10 5BU",
    "wof:placetype":"postalcode"
},
  "geometry": {"coordinates":[-1.08493309187579,54.61118252088509],"type":"Point"}
}