{
  "type": "Feature",
  "properties": {
    "iso:country":"GB",
    "wof:name":"PA20 0EB",
    "wof:placetype":"postalcode"
},
  "geometry": {"coordinates":[-5.06307330369805,55.83131726392541],"type":"Point"}
}