{
  "type": "Feature",
  "properties": {
    "date:inception_lower": "1980-01-01",
    "date:inception_upper": "1980-01-01",
    "iso:country": "GB",
    "wof:name": "SA67 8TP",
    "wof:placetype": "postalcode"
  },
  "geometry": {"coordinates":[-4.671955,51.79401],"type":"Point"}
}
