{
  "type": "Feature",
  "properties": {
    "iso:country": "GB",
    "wof:name": "SA67 8TP",
    "wof:placetype": "postalcode"
  },
  "geometry": {"coordinates":[-4.671955,51.79401],"type":"Point"}
}
