{
  "type": "Feature",
  "properties": {
    "iso:country":"GB",
    "wof:name":"SA67 8TP",
    "wof:placetype":"postalcode"
},
  "geometry": {"coordinates":[-4.66479286362007,51.79280325573063],"type":"Point"}
}