{
  "type": "Feature",
  "properties": {
    "iso:country": "GB",
    "wof:name": "NW11 0HN",
    "wof:placetype": "postalcode"
  },
  "geometry": {"coordinates":[-0.201367,51.582207],"type":"Point"}
}
