{
  "type": "Feature",
  "properties": {
    "iso:country":"GB",
    "wof:name":"NW11 0HN",
    "wof:placetype":"postalcode"
},
  "geometry": {"coordinates":[-0.2013668137623,51.58220711246779],"type":"Point"}
}