{
  "type": "Feature",
  "properties": {
    "iso:country":"GB",
    "wof:name":"EX32 9BR",
    "wof:placetype":"postalcode"
},
  "geometry": {"coordinates":[-4.05100856244596,51.07261615521525],"type":"Point"}
}