{
  "type": "Feature",
  "properties": {
    "date:inception_lower":"1980-01-01",
    "date:inception_upper":"1980-01-31",
    "iso:country":"GB",
    "wof:name":"GU29 0NL",
    "wof:placetype":"postalcode"
},
  "geometry": {"coordinates":[-0.773787,50.993776],"type":"Point"}
}