{
  "type": "Feature",
  "properties": {
    "iso:country":"GB",
    "wof:name":"HR6 8PL",
    "wof:placetype":"postalcode"
},
  "geometry": {"coordinates":[-2.74442247960113,52.22291306135087],"type":"Point"}
}