{
  "type": "Feature",
  "properties": {
    "iso:country":"GB",
    "wof:name":"WN4 9BJ",
    "wof:placetype":"postalcode"
},
  "geometry": {"coordinates":[-2.63871894682334,53.48935804755052],"type":"Point"}
}