{
  "type": "Feature",
  "properties": {
    "date:inception_lower":"1980-01-01",
    "date:inception_upper":"1980-01-31",
    "iso:country":"GB",
    "wof:name":"WN4 9BJ",
    "wof:placetype":"postalcode"
},
  "geometry": {"coordinates":[-2.638749,53.4894],"type":"Point"}
}