{
  "type": "Feature",
  "properties": {
    "iso:country":"GB",
    "wof:name":"BB5 5JJ",
    "wof:placetype":"postalcode"
},
  "geometry": {"coordinates":[-2.38521920510606,53.7701144001649],"type":"Point"}
}