{
  "type": "Feature",
  "properties": {
    "iso:country": "GB",
    "wof:name": "MK45 1RP",
    "wof:placetype": "postalcode"
  },
  "geometry": {"coordinates":[-0.491814,52.00989],"type":"Point"}
}
