{
  "type": "Feature",
  "properties": {
    "iso:country":"GB",
    "wof:name":"MK45 1RP",
    "wof:placetype":"postalcode"
},
  "geometry": {"coordinates":[-0.49181357195381,52.00989034727785],"type":"Point"}
}