{
  "type": "Feature",
  "properties": {
    "iso:country":"GB",
    "wof:name":"N21 1EL",
    "wof:placetype":"postalcode"
},
  "geometry": {"coordinates":[-0.10864661048389,51.64086367111096],"type":"Point"}
}