{
  "type": "Feature",
  "properties": {
    "iso:country": "GB",
    "wof:name": "N21 1EL",
    "wof:placetype": "postalcode"
  },
  "geometry": {"coordinates":[-0.108647,51.640864],"type":"Point"}
}
