{
  "type": "Feature",
  "properties": {
    "iso:country":"GB",
    "wof:name":"DN14 0DN",
    "wof:placetype":"postalcode"
},
  "geometry": {"coordinates":[-1.06447117592862,53.66794364589344],"type":"Point"}
}