{
  "type": "Feature",
  "properties": {
    "date:inception_lower": "1980-01-01",
    "date:inception_upper": "1980-01-01",
    "iso:country": "GB",
    "wof:name": "DN14 0DN",
    "wof:placetype": "postalcode"
  },
  "geometry": {"coordinates":[-1.064471,53.667944],"type":"Point"}
}
