{
  "type": "Feature",
  "properties": {
    "date:inception_lower": "2019-01-01",
    "date:inception_upper": "2019-01-01",
    "iso:country": "GB",
    "wof:name": "CM8 3FX",
    "wof:placetype": "postalcode"
  },
  "geometry": {"coordinates":[0.623422,51.851483],"type":"Point"}
}
