{
  "type": "Feature",
  "properties": {
    "date:inception_lower": "2011-05-01",
    "date:inception_upper": "2011-05-01",
    "iso:country": "GB",
    "wof:name": "SG13 8FF",
    "wof:placetype": "postalcode"
  },
  "geometry": {"coordinates":[-0.064028,51.793132],"type":"Point"}
}
