{
  "type": "Feature",
  "properties": {
    "iso:country":"GB",
    "wof:name":"SG13 8FF",
    "wof:placetype":"postalcode"
},
  "geometry": {"coordinates":[-0.06402820423564,51.79313172839657],"type":"Point"}
}