{
  "type": "Feature",
  "properties": {
    "iso:country":"GB",
    "wof:name":"ML6 6SN",
    "wof:placetype":"postalcode"
},
  "geometry": {"coordinates":[-3.98757180033868,55.87667247371997],"type":"Point"}
}