{
  "type": "Feature",
  "properties": {
    "iso:country":"GB",
    "wof:name":"HA1 4PQ",
    "wof:placetype":"postalcode"
},
  "geometry": {"coordinates":[-0.35727798549048,51.58462782576656],"type":"Point"}
}