{
  "type": "Feature",
  "properties": {
    "iso:country":"GB",
    "wof:name":"NG13 8ZT",
    "wof:placetype":"postalcode"
},
  "geometry": {"coordinates":[-0.95550901586835,52.94527924396743],"type":"Point"}
}