{
  "type": "Feature",
  "properties": {
    "iso:country": "GB",
    "wof:name": "NG13 8ZT",
    "wof:placetype": "postalcode"
  },
  "geometry": {"coordinates":[-0.955509,52.945279],"type":"Point"}
}
