{
  "type": "Feature",
  "properties": {
    "iso:country":"GB",
    "wof:name":"BN43 5HZ",
    "wof:placetype":"postalcode"
},
  "geometry": {"coordinates":[-0.25527571481973,50.82983712777099],"type":"Point"}
}