{
  "type": "Feature",
  "properties": {
    "iso:country":"GB",
    "wof:name":"SG6 3HD",
    "wof:placetype":"postalcode"
},
  "geometry": {"coordinates":[-0.23271297110461,51.97631852692712],"type":"Point"}
}