{
  "type": "Feature",
  "properties": {
    "date:inception_lower":"1984-02-01",
    "date:inception_upper":"1984-02-29",
    "iso:country":"GB",
    "wof:name":"SG6 3HD",
    "wof:placetype":"postalcode"
},
  "geometry": {"coordinates":[-0.232713,51.976319],"type":"Point"}
}