{
  "type": "Feature",
  "properties": {
    "iso:country": "GB",
    "wof:name": "SG6 3HD",
    "wof:placetype": "postalcode"
  },
  "geometry": {"coordinates":[-0.232713,51.976319],"type":"Point"}
}
