{
  "type": "Feature",
  "properties": {
    "iso:country":"GB",
    "wof:name":"OL4 1BN",
    "wof:placetype":"postalcode"
},
  "geometry": {"coordinates":[-2.09618166857693,53.53796445914063],"type":"Point"}
}