{
  "type": "Feature",
  "properties": {
    "date:inception_lower": "1980-01-01",
    "date:inception_upper": "1980-01-01",
    "iso:country": "GB",
    "wof:name": "OL4 1BN",
    "wof:placetype": "postalcode"
  },
  "geometry": {"coordinates":[-2.096166,53.537929],"type":"Point"}
}
