{
  "type": "Feature",
  "properties": {
    "iso:country":"GB",
    "wof:name":"BS9 3EX",
    "wof:placetype":"postalcode"
},
  "geometry": {"coordinates":[-2.61482050490472,51.49338085300818],"type":"Point"}
}