{
  "type": "Feature",
  "properties": {
    "iso:country":"GB",
    "wof:name":"DD3 8LL",
    "wof:placetype":"postalcode"
},
  "geometry": {"coordinates":[-2.98286158626597,56.48437945777166],"type":"Point"}
}