{
  "type": "Feature",
  "properties": {
    "iso:country": "GB",
    "wof:name": "DD3 8LL",
    "wof:placetype": "postalcode"
  },
  "geometry": {"coordinates":[-2.982862,56.484379],"type":"Point"}
}
