{
  "type": "Feature",
  "properties": {
    "iso:country": "GB",
    "wof:name": "TR3 6BG",
    "wof:placetype": "postalcode"
  },
  "geometry": {"coordinates":[-5.115968,50.26389],"type":"Point"}
}
