{
  "type": "Feature",
  "properties": {
    "iso:country":"GB",
    "wof:name":"TR3 6BG",
    "wof:placetype":"postalcode"
},
  "geometry": {"coordinates":[-5.11596818791501,50.26389000410371],"type":"Point"}
}