{
  "type": "Feature",
  "properties": {
    "date:inception_lower": "2006-02-01",
    "date:inception_upper": "2006-02-01",
    "iso:country": "GB",
    "wof:name": "BS39 5ED",
    "wof:placetype": "postalcode"
  },
  "geometry": {"coordinates":[-2.589081,51.306638],"type":"Point"}
}
