{
  "type": "Feature",
  "properties": {
    "iso:country":"GB",
    "wof:name":"BS39 5ED",
    "wof:placetype":"postalcode"
},
  "geometry": {"coordinates":[-2.58908075732241,51.30663803289636],"type":"Point"}
}