{
  "type": "Feature",
  "properties": {
    "date:inception_lower":"1980-01-01",
    "date:inception_upper":"1980-01-31",
    "iso:country":"GB",
    "wof:name":"EX12 2DF",
    "wof:placetype":"postalcode"
},
  "geometry": {"coordinates":[-3.06841,50.710807],"type":"Point"}
}