{
  "type": "Feature",
  "properties": {
    "iso:country":"GB",
    "wof:name":"PA4 9QH",
    "wof:placetype":"postalcode"
},
  "geometry": {"coordinates":[-4.43829084437812,55.89192509243244],"type":"Point"}
}