{
  "type": "Feature",
  "properties": {
    "date:inception_lower": "2013-09-01",
    "date:inception_upper": "2013-09-01",
    "iso:country": "GB",
    "wof:name": "BA6 9GX",
    "wof:placetype": "postalcode"
  },
  "geometry": {"coordinates":[-2.735788,51.138322],"type":"Point"}
}
