{
  "type": "Feature",
  "properties": {
    "iso:country":"GB",
    "wof:name":"WA14 2TF",
    "wof:placetype":"postalcode"
},
  "geometry": {"coordinates":[-2.36250013863301,53.38116976543478],"type":"Point"}
}