{
  "type": "Feature",
  "properties": {
    "date:inception_lower": "2008-03-01",
    "date:inception_upper": "2008-03-01",
    "iso:country": "GB",
    "wof:name": "GU7 1UA",
    "wof:placetype": "postalcode"
  },
  "geometry": {"coordinates":[-0.61005,51.186049],"type":"Point"}
}
