{
  "type": "Feature",
  "properties": {
    "iso:country": "GB",
    "wof:name": "KT18 5FN",
    "wof:placetype": "postalcode"
  },
  "geometry": {"coordinates":[-0.22755,51.313207],"type":"Point"}
}
