{
  "type": "Feature",
  "properties": {
    "date:inception_lower":"1983-03-01",
    "date:inception_upper":"1983-03-31",
    "iso:country":"GB",
    "wof:name":"BD21 4YQ",
    "wof:placetype":"postalcode"
},
  "geometry": {"coordinates":[-1.894675,53.859597],"type":"Point"}
}