{
  "type": "Feature",
  "properties": {
    "date:inception_lower": "1980-01-01",
    "date:inception_upper": "1980-01-01",
    "iso:country": "GB",
    "wof:name": "NE37 1RB",
    "wof:placetype": "postalcode"
  },
  "geometry": {"coordinates":[-1.532843,54.905974],"type":"Point"}
}
