{
  "type": "Feature",
  "properties": {
    "iso:country":"GB",
    "wof:name":"DH8 7AH",
    "wof:placetype":"postalcode"
},
  "geometry": {"coordinates":[-1.82018813205945,54.84126343737589],"type":"Point"}
}