{
  "type": "Feature",
  "properties": {
    "date:inception_lower": "1980-01-01",
    "date:inception_upper": "1980-01-01",
    "iso:country": "GB",
    "wof:name": "LL30 2AH",
    "wof:placetype": "postalcode"
  },
  "geometry": {"coordinates":[-3.841805,53.321262],"type":"Point"}
}
