{
  "type": "Feature",
  "properties": {
    "iso:country":"GB",
    "wof:name":"LL30 2AH",
    "wof:placetype":"postalcode"
},
  "geometry": {"coordinates":[-3.84180500624247,53.3212625013856],"type":"Point"}
}