{
  "type": "Feature",
  "properties": {
    "iso:country":"GB",
    "wof:name":"EX22 6UR",
    "wof:placetype":"postalcode"
},
  "geometry": {"coordinates":[-4.49964027892841,50.74716814415623],"type":"Point"}
}