{
  "type": "Feature",
  "properties": {
    "date:inception_lower":"1980-01-01",
    "date:inception_upper":"1980-01-31",
    "iso:country":"GB",
    "wof:name":"GU9 9DH",
    "wof:placetype":"postalcode"
},
  "geometry": {"coordinates":[-0.784918,51.238811],"type":"Point"}
}