{
  "type": "Feature",
  "properties": {
    "iso:country":"GB",
    "wof:name":"GU9 9DH",
    "wof:placetype":"postalcode"
},
  "geometry": {"coordinates":[-0.78491844522797,51.23881118385995],"type":"Point"}
}