{
  "type": "Feature",
  "properties": {
    "date:inception_lower":"1980-01-01",
    "date:inception_upper":"1980-01-31",
    "iso:country":"GB",
    "wof:name":"TN11 0BH",
    "wof:placetype":"postalcode"
},
  "geometry": {"coordinates":[0.347722,51.209842],"type":"Point"}
}