{
  "type": "Feature",
  "properties": {
    "iso:country":"GB",
    "wof:name":"TN11 0BH",
    "wof:placetype":"postalcode"
},
  "geometry": {"coordinates":[0.34772195553094,51.20984186438253],"type":"Point"}
}