{
  "type": "Feature",
  "properties": {
    "iso:country": "GB",
    "wof:name": "HP7 0LG",
    "wof:placetype": "postalcode"
  },
  "geometry": {"coordinates":[-0.630592,51.649729],"type":"Point"}
}
