{
  "type": "Feature",
  "properties": {
    "iso:country":"GB",
    "wof:name":"TR15 1AQ",
    "wof:placetype":"postalcode"
},
  "geometry": {"coordinates":[-5.23034763364653,50.23947944400165],"type":"Point"}
}