{
  "type": "Feature",
  "properties": {
    "iso:country":"GB",
    "wof:name":"BH21 3RH",
    "wof:placetype":"postalcode"
},
  "geometry": {"coordinates":[-2.03721405174969,50.78639849005409],"type":"Point"}
}