{
  "type": "Feature",
  "properties": {
    "iso:country": "GB",
    "wof:name": "BH21 3RH",
    "wof:placetype": "postalcode"
  },
  "geometry": {"coordinates":[-2.037214,50.786398],"type":"Point"}
}
