{
  "type": "Feature",
  "properties": {
    "iso:country":"GB",
    "wof:name":"W1J 5AZ",
    "wof:placetype":"postalcode"
},
  "geometry": {"coordinates":[-0.14596322681193,51.50892865534778],"type":"Point"}
}