{
  "type": "Feature",
  "properties": {
    "iso:country":"GB",
    "wof:name":"TS26 8BG",
    "wof:placetype":"postalcode"
},
  "geometry": {"coordinates":[-1.21915926870976,54.68718129999301],"type":"Point"}
}