{
  "type": "Feature",
  "properties": {
    "iso:country":"GB",
    "wof:name":"HU9 3BA",
    "wof:placetype":"postalcode"
},
  "geometry": {"coordinates":[-0.30425055685155,53.75809632655444],"type":"Point"}
}