{
  "type": "Feature",
  "properties": {
    "date:inception_lower":"1980-01-01",
    "date:inception_upper":"1980-01-31",
    "iso:country":"GB",
    "wof:name":"M12 4NG",
    "wof:placetype":"postalcode"
},
  "geometry": {"coordinates":[-2.210224,53.465488],"type":"Point"}
}