{
  "type": "Feature",
  "properties": {
    "iso:country":"GB",
    "wof:name":"RG26 4ES",
    "wof:placetype":"postalcode"
},
  "geometry": {"coordinates":[-1.15204166334095,51.35774573885602],"type":"Point"}
}