{
  "type": "Feature",
  "properties": {
    "iso:country":"GB",
    "wof:name":"WF1 1LH",
    "wof:placetype":"postalcode"
},
  "geometry": {"coordinates":[-1.49819866550496,53.68123253144499],"type":"Point"}
}