{
  "type": "Feature",
  "properties": {
    "iso:country":"GB",
    "wof:name":"S60 2UD",
    "wof:placetype":"postalcode"
},
  "geometry": {"coordinates":[-1.34288044881962,53.4139722214253],"type":"Point"}
}