{
  "type": "Feature",
  "properties": {
    "iso:country":"GB",
    "wof:name":"BH24 2DU",
    "wof:placetype":"postalcode"
},
  "geometry": {"coordinates":[-1.84399517307698,50.84036366204462],"type":"Point"}
}