{
  "type": "Feature",
  "properties": {
    "iso:country": "GB",
    "wof:name": "SA12 9UB",
    "wof:placetype": "postalcode"
  },
  "geometry": {"coordinates":[-3.752255,51.645766],"type":"Point"}
}
