{
  "type": "Feature",
  "properties": {
    "iso:country":"GB",
    "wof:name":"SA12 9UB",
    "wof:placetype":"postalcode"
},
  "geometry": {"coordinates":[-3.75225547646129,51.64576560434177],"type":"Point"}
}