{
  "type": "Feature",
  "properties": {
    "iso:country":"GB",
    "wof:name":"PE7 1PH",
    "wof:placetype":"postalcode"
},
  "geometry": {"coordinates":[-0.12286993614099,52.55298766074882],"type":"Point"}
}