{
  "type": "Feature",
  "properties": {
    "date:inception_lower":"1990-07-01",
    "date:inception_upper":"1990-07-31",
    "iso:country":"GB",
    "wof:name":"PE7 1PH",
    "wof:placetype":"postalcode"
},
  "geometry": {"coordinates":[-0.12287,52.552988],"type":"Point"}
}