{
  "type": "Feature",
  "properties": {
    "iso:country": "GB",
    "wof:name": "LS11 9TH",
    "wof:placetype": "postalcode"
  },
  "geometry": {"coordinates":[-1.554421,53.789528],"type":"Point"}
}
