{
  "type": "Feature",
  "properties": {
    "date:inception_lower":"2007-01-01",
    "date:inception_upper":"2007-01-31",
    "iso:country":"GB",
    "wof:name":"SY21 8BF",
    "wof:placetype":"postalcode"
},
  "geometry": {"coordinates":[-3.19431,52.594124],"type":"Point"}
}