{
  "type": "Feature",
  "properties": {
    "iso:country":"GB",
    "wof:name":"SY21 8BF",
    "wof:placetype":"postalcode"
},
  "geometry": {"coordinates":[-3.19431052348058,52.59412358774844],"type":"Point"}
}