{
  "type": "Feature",
  "properties": {
    "iso:country":"GB",
    "wof:name":"PE12 7LQ",
    "wof:placetype":"postalcode"
},
  "geometry": {"coordinates":[0.01215403934559,52.80136992984507],"type":"Point"}
}