{
  "type": "Feature",
  "properties": {
    "iso:country":"GB",
    "wof:name":"TW17 8BQ",
    "wof:placetype":"postalcode"
},
  "geometry": {"coordinates":[-0.44877240168458,51.39842103744982],"type":"Point"}
}