{
  "type": "Feature",
  "properties": {
    "iso:country": "GB",
    "wof:name": "NP16 7LT",
    "wof:placetype": "postalcode"
  },
  "geometry": {"coordinates":[-2.607535,51.685053],"type":"Point"}
}
