{
  "type": "Feature",
  "properties": {
    "iso:country":"GB",
    "wof:name":"SG13 8AE",
    "wof:placetype":"postalcode"
},
  "geometry": {"coordinates":[-0.07342613403241,51.79514750326678],"type":"Point"}
}