{
  "type": "Feature",
  "properties": {
    "iso:country":"GB",
    "wof:name":"GL2 7JD",
    "wof:placetype":"postalcode"
},
  "geometry": {"coordinates":[-2.36699222968158,51.77731182450618],"type":"Point"}
}