{
  "type": "Feature",
  "properties": {
    "iso:country": "GB",
    "wof:name": "GL2 7JD",
    "wof:placetype": "postalcode"
  },
  "geometry": {"coordinates":[-2.366992,51.777312],"type":"Point"}
}
