{
  "type": "Feature",
  "properties": {
    "date:inception_lower": "1980-01-01",
    "date:inception_upper": "1980-01-01",
    "iso:country": "GB",
    "wof:name": "CV32 5EB",
    "wof:placetype": "postalcode"
  },
  "geometry": {"coordinates":[-1.53834,52.291507],"type":"Point"}
}
