{
  "type": "Feature",
  "properties": {
    "iso:country":"GB",
    "wof:name":"DT5 2EX",
    "wof:placetype":"postalcode"
},
  "geometry": {"coordinates":[-2.44279574899107,50.5439533069272],"type":"Point"}
}