{
  "type": "Feature",
  "properties": {
    "iso:country":"GB",
    "wof:name":"TN6 2SW",
    "wof:placetype":"postalcode"
},
  "geometry": {"coordinates":[0.16374844756421,51.06055578444312],"type":"Point"}
}