{
  "type": "Feature",
  "properties": {
    "iso:country":"GB",
    "wof:name":"WF17 9PP",
    "wof:placetype":"postalcode"
},
  "geometry": {"coordinates":[-1.6629974408377,53.73041707534949],"type":"Point"}
}