{
  "type": "Feature",
  "properties": {
    "date:inception_lower": "1980-01-01",
    "date:inception_upper": "1980-01-01",
    "iso:country": "GB",
    "wof:name": "WF17 9PP",
    "wof:placetype": "postalcode"
  },
  "geometry": {"coordinates":[-1.662997,53.730417],"type":"Point"}
}
