{
  "type": "Feature",
  "properties": {
    "iso:country": "GB",
    "wof:name": "SW1E 6DY",
    "wof:placetype": "postalcode"
  },
  "geometry": {"coordinates":[-0.14016,51.49926],"type":"Point"}
}
