{
  "type": "Feature",
  "properties": {
    "date:inception_lower": "1998-06-01",
    "date:inception_upper": "1998-06-01",
    "iso:country": "GB",
    "wof:name": "N17 7NT",
    "wof:placetype": "postalcode"
  },
  "geometry": {"coordinates":[-0.089269,51.608105],"type":"Point"}
}
