{
  "type": "Feature",
  "properties": {
    "iso:country":"GB",
    "wof:name":"N17 7NT",
    "wof:placetype":"postalcode"
},
  "geometry": {"coordinates":[-0.08926948723315,51.60810529808],"type":"Point"}
}