{
  "type": "Feature",
  "properties": {
    "iso:country": "GB",
    "wof:name": "CF81 9EF",
    "wof:placetype": "postalcode"
  },
  "geometry": {"coordinates":[-3.216649,51.681899],"type":"Point"}
}
