{
  "type": "Feature",
  "properties": {
    "iso:country": "GB",
    "wof:name": "CF81 9EF",
    "wof:placetype": "postalcode"
  },
  "geometry": {"coordinates":[-3.216518,51.681882],"type":"Point"}
}
