{
  "type": "Feature",
  "properties": {
    "iso:country":"GB",
    "wof:name":"CO7 0SZ",
    "wof:placetype":"postalcode"
},
  "geometry": {"coordinates":[1.03675339476317,51.80873080919447],"type":"Point"}
}