{
  "type": "Feature",
  "properties": {
    "iso:country":"GB",
    "wof:name":"GU52 6DH",
    "wof:placetype":"postalcode"
},
  "geometry": {"coordinates":[-0.85434227322979,51.25535551215762],"type":"Point"}
}