{
  "type": "Feature",
  "properties": {
    "date:inception_lower": "2001-06-01",
    "date:inception_upper": "2001-06-01",
    "iso:country": "GB",
    "wof:name": "GU52 6DH",
    "wof:placetype": "postalcode"
  },
  "geometry": {"coordinates":[-0.854342,51.255356],"type":"Point"}
}
