{
  "type": "Feature",
  "properties": {
    "date:inception_lower": "1980-01-01",
    "date:inception_upper": "1980-01-01",
    "iso:country": "GB",
    "wof:name": "SY23 4AD",
    "wof:placetype": "postalcode"
  },
  "geometry": {"coordinates":[-3.784438,52.351322],"type":"Point"}
}
