{
  "type": "Feature",
  "properties": {
    "iso:country": "GB",
    "wof:name": "SY23 4AD",
    "wof:placetype": "postalcode"
  },
  "geometry": {"coordinates":[-3.784438,52.351322],"type":"Point"}
}
