{
  "type": "Feature",
  "properties": {
    "iso:country": "GB",
    "wof:name": "YO16 4TP",
    "wof:placetype": "postalcode"
  },
  "geometry": {"coordinates":[-0.212332,54.081888],"type":"Point"}
}
