{
  "type": "Feature",
  "properties": {
    "date:inception_lower": "2015-02-01",
    "date:inception_upper": "2015-02-01",
    "iso:country": "GB",
    "wof:name": "NE15 6AA",
    "wof:placetype": "postalcode"
  },
  "geometry": {"coordinates":[-1.684424,54.971253],"type":"Point"}
}
