{
  "type": "Feature",
  "properties": {
    "iso:country":"GB",
    "wof:name":"NE15 6AA",
    "wof:placetype":"postalcode"
},
  "geometry": {"coordinates":[-1.68442369237908,54.97125278008302],"type":"Point"}
}