{
  "type": "Feature",
  "properties": {
    "iso:country":"GB",
    "wof:name":"PO31 8JH",
    "wof:placetype":"postalcode"
},
  "geometry": {"coordinates":[-1.3251292962054,50.75486784388841],"type":"Point"}
}