{
  "type": "Feature",
  "properties": {
    "iso:country":"GB",
    "wof:name":"SO18 2LX",
    "wof:placetype":"postalcode"
},
  "geometry": {"coordinates":[-1.36909122802821,50.94021717856699],"type":"Point"}
}