{
  "type": "Feature",
  "properties": {
    "iso:country": "GB",
    "wof:name": "CB22 4UG",
    "wof:placetype": "postalcode"
  },
  "geometry": {"coordinates":[0.148347,52.110674],"type":"Point"}
}
