{
  "type": "Feature",
  "properties": {
    "iso:country":"GB",
    "wof:name":"CB22 4UG",
    "wof:placetype":"postalcode"
},
  "geometry": {"coordinates":[0.14834731999315,52.11067361644491],"type":"Point"}
}