{
  "type": "Feature",
  "properties": {
    "date:inception_lower": "2004-03-01",
    "date:inception_upper": "2004-03-01",
    "iso:country": "GB",
    "wof:name": "B28 0TQ",
    "wof:placetype": "postalcode"
  },
  "geometry": {"coordinates":[-1.855315,52.414589],"type":"Point"}
}
