{
  "type": "Feature",
  "properties": {
    "iso:country":"GB",
    "wof:name":"B28 0TQ",
    "wof:placetype":"postalcode"
},
  "geometry": {"coordinates":[-1.85531457846212,52.41458861679694],"type":"Point"}
}