{
  "type": "Feature",
  "properties": {
    "iso:country":"GB",
    "wof:name":"SN15 3TA",
    "wof:placetype":"postalcode"
},
  "geometry": {"coordinates":[-2.09380183299847,51.44821802763099],"type":"Point"}
}