{
  "type": "Feature",
  "properties": {
    "date:inception_lower":"1980-01-01",
    "date:inception_upper":"1980-01-31",
    "iso:country":"GB",
    "wof:name":"BA3 3HA",
    "wof:placetype":"postalcode"
},
  "geometry": {"coordinates":[-2.446844,51.293429],"type":"Point"}
}