{
  "type": "Feature",
  "properties": {
    "iso:country":"GB",
    "wof:name":"BA3 3HA",
    "wof:placetype":"postalcode"
},
  "geometry": {"coordinates":[-2.44684430131497,51.29342899325377],"type":"Point"}
}