{
  "type": "Feature",
  "properties": {
    "iso:country": "GB",
    "wof:name": "L14 0LL",
    "wof:placetype": "postalcode"
  },
  "geometry": {"coordinates":[-2.87614,53.415313],"type":"Point"}
}
