{
  "type": "Feature",
  "properties": {
    "iso:country":"GB",
    "wof:name":"RG26 3LJ",
    "wof:placetype":"postalcode"
},
  "geometry": {"coordinates":[-1.13857829217188,51.35195567126656],"type":"Point"}
}