{
  "type": "Feature",
  "properties": {
    "iso:country":"GB",
    "wof:name":"LU4 0DN",
    "wof:placetype":"postalcode"
},
  "geometry": {"coordinates":[-0.48367163130111,51.88986586864119],"type":"Point"}
}