{
  "type": "Feature",
  "properties": {
    "iso:country":"GB",
    "wof:name":"W4 2RX",
    "wof:placetype":"postalcode"
},
  "geometry": {"coordinates":[-0.2561253634132,51.48079051030307],"type":"Point"}
}