{
  "type": "Feature",
  "properties": {
    "iso:country": "GB",
    "wof:name": "W4 2RX",
    "wof:placetype": "postalcode"
  },
  "geometry": {"coordinates":[-0.256125,51.480791],"type":"Point"}
}
