{
  "type": "Feature",
  "properties": {
    "iso:country":"GB",
    "wof:name":"CH63 7NW",
    "wof:placetype":"postalcode"
},
  "geometry": {"coordinates":[-3.00308538691917,53.35345899636118],"type":"Point"}
}