{
  "type": "Feature",
  "properties": {
    "iso:country": "GB",
    "wof:name": "OX12 7JR",
    "wof:placetype": "postalcode"
  },
  "geometry": {"coordinates":[-1.422537,51.608028],"type":"Point"}
}
