{
  "type": "Feature",
  "properties": {
    "iso:country":"GB",
    "wof:name":"OX12 7JR",
    "wof:placetype":"postalcode"
},
  "geometry": {"coordinates":[-1.42255428630644,51.60797221454258],"type":"Point"}
}