{
  "type": "Feature",
  "properties": {
    "date:inception_lower": "1980-01-01",
    "date:inception_upper": "1980-01-01",
    "iso:country": "GB",
    "wof:name": "OX12 7JR",
    "wof:placetype": "postalcode"
  },
  "geometry": {"coordinates":[-1.422538,51.607974],"type":"Point"}
}
