{
  "type": "Feature",
  "properties": {
    "iso:country":"GB",
    "wof:name":"S40 4LE",
    "wof:placetype":"postalcode"
},
  "geometry": {"coordinates":[-1.45278937996583,53.24682249605554],"type":"Point"}
}