{
  "type": "Feature",
  "properties": {
    "iso:country":"GB",
    "wof:name":"IP14 6PZ",
    "wof:placetype":"postalcode"
},
  "geometry": {"coordinates":[1.17919376365878,52.22685463449023],"type":"Point"}
}