{
  "type": "Feature",
  "properties": {
    "iso:country": "GB",
    "wof:name": "IP14 6PZ",
    "wof:placetype": "postalcode"
  },
  "geometry": {"coordinates":[1.17925,52.226844],"type":"Point"}
}
