{
  "type": "Feature",
  "properties": {
    "iso:country": "GB",
    "wof:name": "LE2 0UF",
    "wof:placetype": "postalcode"
  },
  "geometry": {"coordinates":[-1.11742,52.632642],"type":"Point"}
}
