{
  "type": "Feature",
  "properties": {
    "iso:country":"GB",
    "wof:name":"BL1 2XD",
    "wof:placetype":"postalcode"
},
  "geometry": {"coordinates":[-2.43586820686289,53.58597908649578],"type":"Point"}
}