{
  "type": "Feature",
  "properties": {
    "iso:country": "GB",
    "wof:name": "DY2 7QT",
    "wof:placetype": "postalcode"
  },
  "geometry": {"coordinates":[-2.065727,52.512008],"type":"Point"}
}
