{
  "type": "Feature",
  "properties": {
    "iso:country": "GB",
    "wof:name": "KA22 8LF",
    "wof:placetype": "postalcode"
  },
  "geometry": {"coordinates":[-4.812183,55.648364],"type":"Point"}
}
