{
  "type": "Feature",
  "properties": {
    "iso:country":"GB",
    "wof:name":"KA22 8LF",
    "wof:placetype":"postalcode"
},
  "geometry": {"coordinates":[-4.81218346173818,55.64836378635403],"type":"Point"}
}