{
  "type": "Feature",
  "properties": {
    "iso:country":"GB",
    "wof:name":"BR1 5LR",
    "wof:placetype":"postalcode"
},
  "geometry": {"coordinates":[0.01394290412719,51.43152599057444],"type":"Point"}
}