{
  "type": "Feature",
  "properties": {
    "iso:country": "GB",
    "wof:name": "BR1 5LR",
    "wof:placetype": "postalcode"
  },
  "geometry": {"coordinates":[0.013943,51.431526],"type":"Point"}
}
