{
  "type": "Feature",
  "properties": {
    "iso:country": "GB",
    "wof:name": "DH1 1JU",
    "wof:placetype": "postalcode"
  },
  "geometry": {"coordinates":[-1.567053,54.780038],"type":"Point"}
}
