{
  "type": "Feature",
  "properties": {
    "date:inception_lower": "1980-01-01",
    "date:inception_upper": "1980-01-01",
    "iso:country": "GB",
    "wof:name": "DH1 1JU",
    "wof:placetype": "postalcode"
  },
  "geometry": {"coordinates":[-1.567053,54.780038],"type":"Point"}
}
