{
  "type": "Feature",
  "properties": {
    "date:inception_lower": "1980-01-01",
    "date:inception_upper": "1980-01-01",
    "iso:country": "GB",
    "wof:name": "NW2 7HR",
    "wof:placetype": "postalcode"
  },
  "geometry": {"coordinates":[-0.233958,51.567325],"type":"Point"}
}
