{
  "type": "Feature",
  "properties": {
    "iso:country":"GB",
    "wof:name":"NW2 7HR",
    "wof:placetype":"postalcode"
},
  "geometry": {"coordinates":[-0.23395770912887,51.56732521033374],"type":"Point"}
}