{
  "type": "Feature",
  "properties": {
    "iso:country":"GB",
    "wof:name":"BB1 4NT",
    "wof:placetype":"postalcode"
},
  "geometry": {"coordinates":[-2.4109080533439,53.77041554142944],"type":"Point"}
}