{
  "type": "Feature",
  "properties": {
    "iso:country": "GB",
    "wof:name": "SO31 7EQ",
    "wof:placetype": "postalcode"
  },
  "geometry": {"coordinates":[-1.280265,50.875605],"type":"Point"}
}
