{
  "type": "Feature",
  "properties": {
    "date:inception_lower":"2005-01-01",
    "date:inception_upper":"2005-01-31",
    "iso:country":"GB",
    "wof:name":"YO16 6RR",
    "wof:placetype":"postalcode"
},
  "geometry": {"coordinates":[-0.181536,54.106514],"type":"Point"}
}