{
  "type": "Feature",
  "properties": {
    "date:inception_lower": "1985-04-01",
    "date:inception_upper": "1985-04-01",
    "iso:country": "GB",
    "wof:name": "DT3 4LG",
    "wof:placetype": "postalcode"
  },
  "geometry": {"coordinates":[-2.479651,50.665606],"type":"Point"}
}
