{
  "type": "Feature",
  "properties": {
    "date:inception_lower": "1994-12-01",
    "date:inception_upper": "1994-12-01",
    "iso:country": "GB",
    "wof:name": "SO30 3FE",
    "wof:placetype": "postalcode"
  },
  "geometry": {"coordinates":[-1.335748,50.929161],"type":"Point"}
}
