{
  "type": "Feature",
  "properties": {
    "iso:country":"GB",
    "wof:name":"SO30 3FE",
    "wof:placetype":"postalcode"
},
  "geometry": {"coordinates":[-1.33571678209209,50.92914231270394],"type":"Point"}
}