{
  "type": "Feature",
  "properties": {
    "iso:country":"GB",
    "wof:name":"CT14 8BQ",
    "wof:placetype":"postalcode"
},
  "geometry": {"coordinates":[1.39792069850922,51.18481258752933],"type":"Point"}
}