{
  "type": "Feature",
  "properties": {
    "iso:country": "GB",
    "wof:name": "FK2 9TL",
    "wof:placetype": "postalcode"
  },
  "geometry": {"coordinates":[-3.750434,55.988362],"type":"Point"}
}
