{
  "type": "Feature",
  "properties": {
    "iso:country": "GB",
    "wof:name": "SN16 9RX",
    "wof:placetype": "postalcode"
  },
  "geometry": {"coordinates":[-2.087306,51.602957],"type":"Point"}
}
