{
  "type": "Feature",
  "properties": {
    "iso:country":"GB",
    "wof:name":"SN16 9RX",
    "wof:placetype":"postalcode"
},
  "geometry": {"coordinates":[-2.08730614020952,51.60295652043389],"type":"Point"}
}