{
  "type": "Feature",
  "properties": {
    "iso:country": "GB",
    "wof:name": "NE16 6AH",
    "wof:placetype": "postalcode"
  },
  "geometry": {"coordinates":[-1.738418,54.907551],"type":"Point"}
}
