{
  "type": "Feature",
  "properties": {
    "iso:country":"GB",
    "wof:name":"NE16 6AH",
    "wof:placetype":"postalcode"
},
  "geometry": {"coordinates":[-1.73841755170253,54.90755125096508],"type":"Point"}
}