{
  "type": "Feature",
  "properties": {
    "iso:country": "GB",
    "wof:name": "NN6 9QQ",
    "wof:placetype": "postalcode"
  },
  "geometry": {"coordinates":[-0.825405,52.34066],"type":"Point"}
}
