{
  "type": "Feature",
  "properties": {
    "iso:country":"GB",
    "wof:name":"TQ12 1UT",
    "wof:placetype":"postalcode"
},
  "geometry": {"coordinates":[-3.63118490253472,50.53295280962816],"type":"Point"}
}