{
  "type": "Feature",
  "properties": {
    "iso:country": "GB",
    "wof:name": "TQ12 1UT",
    "wof:placetype": "postalcode"
  },
  "geometry": {"coordinates":[-3.631185,50.532953],"type":"Point"}
}
