{
  "type": "Feature",
  "properties": {
    "iso:country":"GB",
    "wof:name":"MK6 4BB",
    "wof:placetype":"postalcode"
},
  "geometry": {"coordinates":[-0.73420438782995,52.01458722757642],"type":"Point"}
}