{
  "type": "Feature",
  "properties": {
    "date:inception_lower": "2009-09-01",
    "date:inception_upper": "2009-09-01",
    "iso:country": "GB",
    "wof:name": "MK6 4BB",
    "wof:placetype": "postalcode"
  },
  "geometry": {"coordinates":[-0.735984,52.013798],"type":"Point"}
}
