{
  "type": "Feature",
  "properties": {
    "iso:country": "GB",
    "wof:name": "MK6 4BB",
    "wof:placetype": "postalcode"
  },
  "geometry": {"coordinates":[-0.735984,52.013798],"type":"Point"}
}
