{
  "type": "Feature",
  "properties": {
    "date:inception_lower":"1980-01-01",
    "date:inception_upper":"1980-01-31",
    "iso:country":"GB",
    "wof:name":"DL5 6QE",
    "wof:placetype":"postalcode"
},
  "geometry": {"coordinates":[-1.596563,54.607775],"type":"Point"}
}