{
  "type": "Feature",
  "properties": {
    "iso:country":"GB",
    "wof:name":"DL5 6QE",
    "wof:placetype":"postalcode"
},
  "geometry": {"coordinates":[-1.59656315970007,54.60777520852609],"type":"Point"}
}