{
  "type": "Feature",
  "properties": {
    "iso:country":"GB",
    "wof:name":"WF1 3TR",
    "wof:placetype":"postalcode"
},
  "geometry": {"coordinates":[-1.49707282717783,53.71474484357807],"type":"Point"}
}