{
  "type": "Feature",
  "properties": {
    "iso:country":"GB",
    "wof:name":"DT3 4JY",
    "wof:placetype":"postalcode"
},
  "geometry": {"coordinates":[-2.63349372038788,50.67042982843306],"type":"Point"}
}