{
  "type": "Feature",
  "properties": {
    "date:inception_lower": "1980-01-01",
    "date:inception_upper": "1980-01-01",
    "iso:country": "GB",
    "wof:name": "TN5 6UW",
    "wof:placetype": "postalcode"
  },
  "geometry": {"coordinates":[0.332608,51.065921],"type":"Point"}
}
