{
  "type": "Feature",
  "properties": {
    "iso:country": "GB",
    "wof:name": "TN5 6UW",
    "wof:placetype": "postalcode"
  },
  "geometry": {"coordinates":[0.332652,51.065947],"type":"Point"}
}
