{
  "type": "Feature",
  "properties": {
    "iso:country":"GB",
    "wof:name":"HR9 5AZ",
    "wof:placetype":"postalcode"
},
  "geometry": {"coordinates":[-2.5892479243501,51.90832413283615],"type":"Point"}
}