{
  "type": "Feature",
  "properties": {
    "iso:country":"GB",
    "wof:name":"PE24 5HD",
    "wof:placetype":"postalcode"
},
  "geometry": {"coordinates":[0.25033430500217,53.16251649404698],"type":"Point"}
}