{
  "type": "Feature",
  "properties": {
    "iso:country":"GB",
    "wof:name":"G13 3RJ",
    "wof:placetype":"postalcode"
},
  "geometry": {"coordinates":[-4.3504709002157,55.88642572989215],"type":"Point"}
}