{
  "type": "Feature",
  "properties": {
    "iso:country":"GB",
    "wof:name":"SN7 7DJ",
    "wof:placetype":"postalcode"
},
  "geometry": {"coordinates":[-1.59110921798925,51.65068730664071],"type":"Point"}
}