{
  "type": "Feature",
  "properties": {
    "iso:country":"GB",
    "wof:name":"W2 1AP",
    "wof:placetype":"postalcode"
},
  "geometry": {"coordinates":[-0.1712223389767,51.51907306672893],"type":"Point"}
}