{
  "type": "Feature",
  "properties": {
    "iso:country":"GB",
    "wof:name":"SN14 0NN",
    "wof:placetype":"postalcode"
},
  "geometry": {"coordinates":[-2.144963541767,51.45456780013853],"type":"Point"}
}