{
  "type": "Feature",
  "properties": {
    "date:inception_lower": "1980-01-01",
    "date:inception_upper": "1980-01-01",
    "iso:country": "GB",
    "wof:name": "BN25 4NE",
    "wof:placetype": "postalcode"
  },
  "geometry": {"coordinates":[0.123331,50.771433],"type":"Point"}
}
