{
  "type": "Feature",
  "properties": {
    "iso:country":"GB",
    "wof:name":"BN25 4NE",
    "wof:placetype":"postalcode"
},
  "geometry": {"coordinates":[0.12333086720069,50.77143256708041],"type":"Point"}
}