{
  "type": "Feature",
  "properties": {
    "iso:country":"GB",
    "wof:name":"OL1 4QJ",
    "wof:placetype":"postalcode"
},
  "geometry": {"coordinates":[-2.08492330179002,53.56689745108113],"type":"Point"}
}