{
  "type": "Feature",
  "properties": {
    "iso:country":"GB",
    "wof:name":"HG5 9BB",
    "wof:placetype":"postalcode"
},
  "geometry": {"coordinates":[-1.4701011478973,54.01220246632519],"type":"Point"}
}