{
  "type": "Feature",
  "properties": {
    "date:inception_lower":"1986-04-01",
    "date:inception_upper":"1986-04-30",
    "iso:country":"GB",
    "wof:name":"HG5 9BB",
    "wof:placetype":"postalcode"
},
  "geometry": {"coordinates":[-1.470101,54.012202],"type":"Point"}
}