{
  "type": "Feature",
  "properties": {
    "iso:country": "GB",
    "wof:name": "TQ12 6YW",
    "wof:placetype": "postalcode"
  },
  "geometry": {"coordinates":[-3.638274,50.518454],"type":"Point"}
}
