{
  "type": "Feature",
  "properties": {
    "date:inception_lower":"1990-07-01",
    "date:inception_upper":"1990-07-31",
    "iso:country":"GB",
    "wof:name":"TQ12 6YW",
    "wof:placetype":"postalcode"
},
  "geometry": {"coordinates":[-3.638274,50.518454],"type":"Point"}
}