{
  "type": "Feature",
  "properties": {
    "iso:country":"GB",
    "wof:name":"TQ12 6YW",
    "wof:placetype":"postalcode"
},
  "geometry": {"coordinates":[-3.63827417098407,50.51845437041939],"type":"Point"}
}