{
  "type": "Feature",
  "properties": {
    "date:inception_lower":"2016-10-01",
    "date:inception_upper":"2016-10-31",
    "iso:country":"GB",
    "wof:name":"HP11 1BD",
    "wof:placetype":"postalcode"
},
  "geometry": {"coordinates":[-0.745972,51.617914],"type":"Point"}
}