{
  "type": "Feature",
  "properties": {
    "date:inception_lower": "2016-10-01",
    "date:inception_upper": "2016-10-01",
    "iso:country": "GB",
    "wof:name": "HP11 1BD",
    "wof:placetype": "postalcode"
  },
  "geometry": {"coordinates":[-0.74565,51.618081],"type":"Point"}
}
