{
  "type": "Feature",
  "properties": {
    "iso:country": "GB",
    "wof:name": "HP11 1BD",
    "wof:placetype": "postalcode"
  },
  "geometry": {"coordinates":[-0.745972,51.617914],"type":"Point"}
}
