{
  "type": "Feature",
  "properties": {
    "date:inception_lower": "2007-10-01",
    "date:inception_upper": "2007-10-01",
    "iso:country": "GB",
    "wof:name": "HP3 9YD",
    "wof:placetype": "postalcode"
  },
  "geometry": {"coordinates":[-0.453009,51.738639],"type":"Point"}
}
