{
  "type": "Feature",
  "properties": {
    "iso:country":"GB",
    "wof:name":"HP3 9YD",
    "wof:placetype":"postalcode"
},
  "geometry": {"coordinates":[-0.45300900561936,51.73863917935071],"type":"Point"}
}