{
  "type": "Feature",
  "properties": {
    "iso:country":"GB",
    "wof:name":"NG2 7UL",
    "wof:placetype":"postalcode"
},
  "geometry": {"coordinates":[-1.15362006795221,52.92467765816701],"type":"Point"}
}