{
  "type": "Feature",
  "properties": {
    "iso:country":"GB",
    "wof:name":"SY7 9BH",
    "wof:placetype":"postalcode"
},
  "geometry": {"coordinates":[-2.81741145896389,52.38916694631444],"type":"Point"}
}