{
  "type": "Feature",
  "properties": {
    "date:inception_lower": "1980-01-01",
    "date:inception_upper": "1980-01-01",
    "iso:country": "GB",
    "wof:name": "LL53 6BP",
    "wof:placetype": "postalcode"
  },
  "geometry": {"coordinates":[-4.541067,52.932216],"type":"Point"}
}
