{
  "type": "Feature",
  "properties": {
    "date:inception_lower": "1980-01-01",
    "date:inception_upper": "1980-01-01",
    "iso:country": "GB",
    "wof:name": "LL53 6BP",
    "wof:placetype": "postalcode"
  },
  "geometry": {"coordinates":[-4.539656,52.930988],"type":"Point"}
}
