{
  "type": "Feature",
  "properties": {
    "iso:country":"GB",
    "wof:name":"AB41 9AZ",
    "wof:placetype":"postalcode"
},
  "geometry": {"coordinates":[-2.08688124559198,57.36619881269694],"type":"Point"}
}