{
  "type": "Feature",
  "properties": {
    "date:inception_lower": "2022-12-01",
    "date:inception_upper": "2022-12-01",
    "iso:country": "GB",
    "wof:name": "GL52 8GH",
    "wof:placetype": "postalcode"
  },
  "geometry": {"coordinates":[-2.055359,51.95573],"type":"Point"}
}
