{
  "type": "Feature",
  "properties": {
    "date:inception_lower": "1980-01-01",
    "date:inception_upper": "1980-01-01",
    "iso:country": "GB",
    "wof:name": "M1 4QT",
    "wof:placetype": "postalcode"
  },
  "geometry": {"coordinates":[-2.239277,53.478242],"type":"Point"}
}
