{
  "type": "Feature",
  "properties": {
    "iso:country": "GB",
    "wof:name": "YO24 2TG",
    "wof:placetype": "postalcode"
  },
  "geometry": {"coordinates":[-1.119992,53.939765],"type":"Point"}
}
