{
  "type": "Feature",
  "properties": {
    "iso:country":"GB",
    "wof:name":"YO24 2TG",
    "wof:placetype":"postalcode"
},
  "geometry": {"coordinates":[-1.11999210532537,53.93976507141452],"type":"Point"}
}