{
  "type": "Feature",
  "properties": {
    "iso:country":"GB",
    "wof:name":"SW4 0RS",
    "wof:placetype":"postalcode"
},
  "geometry": {"coordinates":[-0.14495582255764,51.46311372409432],"type":"Point"}
}