{
  "type": "Feature",
  "properties": {
    "iso:country": "GB",
    "wof:name": "CF38 1TH",
    "wof:placetype": "postalcode"
  },
  "geometry": {"coordinates":[-3.31204,51.574487],"type":"Point"}
}
