{
  "type": "Feature",
  "properties": {
    "iso:country": "GB",
    "wof:name": "WF11 9DX",
    "wof:placetype": "postalcode"
  },
  "geometry": {"coordinates":[-1.258122,53.723517],"type":"Point"}
}
