{
  "type": "Feature",
  "properties": {
    "iso:country":"GB",
    "wof:name":"WF11 9DX",
    "wof:placetype":"postalcode"
},
  "geometry": {"coordinates":[-1.25812208678598,53.72351708808342],"type":"Point"}
}