{
  "type": "Feature",
  "properties": {
    "date:inception_lower": "1980-01-01",
    "date:inception_upper": "1980-01-01",
    "iso:country": "GB",
    "wof:name": "WF11 9DX",
    "wof:placetype": "postalcode"
  },
  "geometry": {"coordinates":[-1.257673,53.723425],"type":"Point"}
}
