{
  "type": "Feature",
  "properties": {
    "iso:country": "GB",
    "wof:name": "DY3 1NB",
    "wof:placetype": "postalcode"
  },
  "geometry": {"coordinates":[-2.114355,52.544931],"type":"Point"}
}
