{
  "type": "Feature",
  "properties": {
    "iso:country":"GB",
    "wof:name":"DY3 1NB",
    "wof:placetype":"postalcode"
},
  "geometry": {"coordinates":[-2.11435459881476,52.54493077231004],"type":"Point"}
}