{
  "type": "Feature",
  "properties": {
    "iso:country": "GB",
    "wof:name": "TQ12 6NZ",
    "wof:placetype": "postalcode"
  },
  "geometry": {"coordinates":[-3.693938,50.529005],"type":"Point"}
}
