{
  "type": "Feature",
  "properties": {
    "iso:country":"GB",
    "wof:name":"TQ12 6NZ",
    "wof:placetype":"postalcode"
},
  "geometry": {"coordinates":[-3.69328756461306,50.53259654909918],"type":"Point"}
}