{
  "type": "Feature",
  "properties": {
    "iso:country":"GB",
    "wof:name":"CV37 8ET",
    "wof:placetype":"postalcode"
},
  "geometry": {"coordinates":[-1.78638836870995,52.16468982829321],"type":"Point"}
}