{
  "type": "Feature",
  "properties": {
    "iso:country":"GB",
    "wof:name":"CF71 7AF",
    "wof:placetype":"postalcode"
},
  "geometry": {"coordinates":[-3.45041860050171,51.46253398120071],"type":"Point"}
}