{
  "type": "Feature",
  "properties": {
    "iso:country":"GB",
    "wof:name":"G1 5DX",
    "wof:placetype":"postalcode"
},
  "geometry": {"coordinates":[-4.23776808756113,55.85565991767115],"type":"Point"}
}