{
  "type": "Feature",
  "properties": {
    "iso:country":"GB",
    "wof:name":"HG4 2PE",
    "wof:placetype":"postalcode"
},
  "geometry": {"coordinates":[-1.5307293574503,54.12466496937694],"type":"Point"}
}