{
  "type": "Feature",
  "properties": {
    "date:inception_lower": "1980-01-01",
    "date:inception_upper": "1980-01-01",
    "iso:country": "GB",
    "wof:name": "HG4 2PE",
    "wof:placetype": "postalcode"
  },
  "geometry": {"coordinates":[-1.530729,54.124665],"type":"Point"}
}
