{
  "type": "Feature",
  "properties": {
    "date:inception_lower":"1980-01-01",
    "date:inception_upper":"1980-01-31",
    "iso:country":"GB",
    "wof:name":"NG8 4AF",
    "wof:placetype":"postalcode"
},
  "geometry": {"coordinates":[-1.226003,52.967125],"type":"Point"}
}