{
  "type": "Feature",
  "properties": {
    "iso:country": "GB",
    "wof:name": "HR8 2AG",
    "wof:placetype": "postalcode"
  },
  "geometry": {"coordinates":[-2.426128,52.03677],"type":"Point"}
}
