{
  "type": "Feature",
  "properties": {
    "iso:country": "GB",
    "wof:name": "CF64 3HU",
    "wof:placetype": "postalcode"
  },
  "geometry": {"coordinates":[-3.191348,51.428811],"type":"Point"}
}
