{
  "type": "Feature",
  "properties": {
    "date:inception_lower":"2005-01-01",
    "date:inception_upper":"2005-01-31",
    "iso:country":"GB",
    "wof:name":"CF64 3HU",
    "wof:placetype":"postalcode"
},
  "geometry": {"coordinates":[-3.191348,51.428811],"type":"Point"}
}