{
  "type": "Feature",
  "properties": {
    "date:inception_lower": "1980-01-01",
    "date:inception_upper": "1980-01-01",
    "iso:country": "GB",
    "wof:name": "LL53 8UB",
    "wof:placetype": "postalcode"
  },
  "geometry": {"coordinates":[-4.574358,52.897026],"type":"Point"}
}
