{
  "type": "Feature",
  "properties": {
    "iso:country":"GB",
    "wof:name":"LU2 8LF",
    "wof:placetype":"postalcode"
},
  "geometry": {"coordinates":[-0.38008725304475,51.91497507186782],"type":"Point"}
}