{
  "type": "Feature",
  "properties": {
    "date:inception_lower": "1980-01-01",
    "date:inception_upper": "1980-01-01",
    "iso:country": "GB",
    "wof:name": "LU2 8LF",
    "wof:placetype": "postalcode"
  },
  "geometry": {"coordinates":[-0.380036,51.91491],"type":"Point"}
}
