{
  "type": "Feature",
  "properties": {
    "iso:country":"GB",
    "wof:name":"BL2 2EA",
    "wof:placetype":"postalcode"
},
  "geometry": {"coordinates":[-2.41214916153979,53.58723167579605],"type":"Point"}
}