{
  "type": "Feature",
  "properties": {
    "iso:country":"GB",
    "wof:name":"RM9 5YB",
    "wof:placetype":"postalcode"
},
  "geometry": {"coordinates":[0.12736586772071,51.54783220836806],"type":"Point"}
}