{
  "type": "Feature",
  "properties": {
    "iso:country":"GB",
    "wof:name":"BN11 5NY",
    "wof:placetype":"postalcode"
},
  "geometry": {"coordinates":[-0.39805050488543,50.8109664797601],"type":"Point"}
}