{
  "type": "Feature",
  "properties": {
    "iso:country":"GB",
    "wof:name":"B30 1TQ",
    "wof:placetype":"postalcode"
},
  "geometry": {"coordinates":[-1.94301977798589,52.432895022926],"type":"Point"}
}