{
  "type": "Feature",
  "properties": {
    "iso:country":"GB",
    "wof:name":"BS35 3UG",
    "wof:placetype":"postalcode"
},
  "geometry": {"coordinates":[-2.50104656177117,51.61979367810329],"type":"Point"}
}