{
  "type": "Feature",
  "properties": {
    "date:inception_lower": "1997-12-01",
    "date:inception_upper": "1997-12-01",
    "iso:country": "GB",
    "wof:name": "BS35 3UG",
    "wof:placetype": "postalcode"
  },
  "geometry": {"coordinates":[-2.501047,51.619794],"type":"Point"}
}
