{
  "type": "Feature",
  "properties": {
    "iso:country": "GB",
    "wof:name": "PO21 5EP",
    "wof:placetype": "postalcode"
  },
  "geometry": {"coordinates":[-0.700474,50.804151],"type":"Point"}
}
