{
  "type": "Feature",
  "properties": {
    "date:inception_lower": "1985-04-01",
    "date:inception_upper": "1985-04-01",
    "iso:country": "GB",
    "wof:name": "PO21 5EP",
    "wof:placetype": "postalcode"
  },
  "geometry": {"coordinates":[-0.700474,50.804151],"type":"Point"}
}
