{
  "type": "Feature",
  "properties": {
    "iso:country":"GB",
    "wof:name":"SO31 5GW",
    "wof:placetype":"postalcode"
},
  "geometry": {"coordinates":[-1.3443139072505,50.87831128453406],"type":"Point"}
}