{
  "type": "Feature",
  "properties": {
    "date:inception_lower": "1993-01-01",
    "date:inception_upper": "1993-01-01",
    "iso:country": "GB",
    "wof:name": "L26 7ZY",
    "wof:placetype": "postalcode"
  },
  "geometry": {"coordinates":[-2.841582,53.371184],"type":"Point"}
}
