{
  "type": "Feature",
  "properties": {
    "iso:country":"GB",
    "wof:name":"L26 7ZY",
    "wof:placetype":"postalcode"
},
  "geometry": {"coordinates":[-2.84158196649444,53.37118412431737],"type":"Point"}
}