{
  "type": "Feature",
  "properties": {
    "iso:country":"GB",
    "wof:name":"B46 2AA",
    "wof:placetype":"postalcode"
},
  "geometry": {"coordinates":[-1.68719602876586,52.50566532359758],"type":"Point"}
}