{
  "type": "Feature",
  "properties": {
    "iso:country":"GB",
    "wof:name":"PL28 8JB",
    "wof:placetype":"postalcode"
},
  "geometry": {"coordinates":[-5.01008367509427,50.53205914466384],"type":"Point"}
}