{
  "type": "Feature",
  "properties": {
    "date:inception_lower":"1980-01-01",
    "date:inception_upper":"1980-01-31",
    "iso:country":"GB",
    "wof:name":"EH26 8JR",
    "wof:placetype":"postalcode"
},
  "geometry": {"coordinates":[-3.20799,55.837139],"type":"Point"}
}