{
  "type": "Feature",
  "properties": {
    "date:inception_lower": "1980-01-01",
    "date:inception_upper": "1980-01-01",
    "iso:country": "GB",
    "wof:name": "BA14 7JS",
    "wof:placetype": "postalcode"
  },
  "geometry": {"coordinates":[-2.196342,51.320248],"type":"Point"}
}
