{
  "type": "Feature",
  "properties": {
    "iso:country":"GB",
    "wof:name":"BB1 8RW",
    "wof:placetype":"postalcode"
},
  "geometry": {"coordinates":[-2.48084200198616,53.76300977506305],"type":"Point"}
}