{
  "type": "Feature",
  "properties": {
    "iso:country":"GB",
    "wof:name":"MK44 1LA",
    "wof:placetype":"postalcode"
},
  "geometry": {"coordinates":[-0.55563453654812,52.22672195460637],"type":"Point"}
}