{
  "type": "Feature",
  "properties": {
    "date:inception_lower": "1997-12-01",
    "date:inception_upper": "1997-12-01",
    "iso:country": "GB",
    "wof:name": "TN16 1AT",
    "wof:placetype": "postalcode"
  },
  "geometry": {"coordinates":[0.070295,51.266809],"type":"Point"}
}
