{
  "type": "Feature",
  "properties": {
    "iso:country":"GB",
    "wof:name":"E1 8AN",
    "wof:placetype":"postalcode"
},
  "geometry": {"coordinates":[-0.07290905462043,51.51249013129058],"type":"Point"}
}