{
  "type": "Feature",
  "properties": {
    "iso:country":"GB",
    "wof:name":"NE38 8TF",
    "wof:placetype":"postalcode"
},
  "geometry": {"coordinates":[-1.49851628067764,54.89717416781071],"type":"Point"}
}