{
  "type": "Feature",
  "properties": {
    "iso:country":"GB",
    "wof:name":"WC2R 0PZ",
    "wof:placetype":"postalcode"
},
  "geometry": {"coordinates":[-0.12354192542792,51.50993893842379],"type":"Point"}
}