{
  "type": "Feature",
  "properties": {
    "date:inception_lower": "2016-11-01",
    "date:inception_upper": "2016-11-01",
    "iso:country": "GB",
    "wof:name": "CV37 8FD",
    "wof:placetype": "postalcode"
  },
  "geometry": {"coordinates":[-1.788936,52.161965],"type":"Point"}
}
