{
  "type": "Feature",
  "properties": {
    "iso:country":"GB",
    "wof:name":"LL57 2UP",
    "wof:placetype":"postalcode"
},
  "geometry": {"coordinates":[-4.13260535897999,53.22451534231033],"type":"Point"}
}