{
  "type": "Feature",
  "properties": {
    "iso:country":"GB",
    "wof:name":"AB42 3EB",
    "wof:placetype":"postalcode"
},
  "geometry": {"coordinates":[-1.88235680019337,57.51444096844161],"type":"Point"}
}