{
  "type": "Feature",
  "properties": {
    "date:inception_lower": "1996-06-01",
    "date:inception_upper": "1996-06-01",
    "iso:country": "GB",
    "wof:name": "AB42 3EB",
    "wof:placetype": "postalcode"
  },
  "geometry": {"coordinates":[-1.882357,57.514441],"type":"Point"}
}
