{
  "type": "Feature",
  "properties": {
    "iso:country":"GB",
    "wof:name":"LE3 9ST",
    "wof:placetype":"postalcode"
},
  "geometry": {"coordinates":[-1.17014002624159,52.64903383765304],"type":"Point"}
}