{
  "type": "Feature",
  "properties": {
    "iso:country": "GB",
    "wof:name": "LE3 9ST",
    "wof:placetype": "postalcode"
  },
  "geometry": {"coordinates":[-1.17014,52.649034],"type":"Point"}
}
