{
  "type": "Feature",
  "properties": {
    "date:inception_lower":"2011-05-01",
    "date:inception_upper":"2011-05-31",
    "iso:country":"GB",
    "wof:name":"LE3 9ST",
    "wof:placetype":"postalcode"
},
  "geometry": {"coordinates":[-1.17014,52.649034],"type":"Point"}
}