{
  "type": "Feature",
  "properties": {
    "iso:country":"GB",
    "wof:name":"AB39 3YP",
    "wof:placetype":"postalcode"
},
  "geometry": {"coordinates":[-2.40290465587063,56.94418680678342],"type":"Point"}
}