{
  "type": "Feature",
  "properties": {
    "date:inception_lower": "1996-06-01",
    "date:inception_upper": "1996-06-01",
    "iso:country": "GB",
    "wof:name": "AB39 3YP",
    "wof:placetype": "postalcode"
  },
  "geometry": {"coordinates":[-2.402987,56.944213],"type":"Point"}
}
