{
  "type": "Feature",
  "properties": {
    "iso:country": "GB",
    "wof:name": "CT9 4DN",
    "wof:placetype": "postalcode"
  },
  "geometry": {"coordinates":[1.383032,51.377472],"type":"Point"}
}
