{
  "type": "Feature",
  "properties": {
    "iso:country":"GB",
    "wof:name":"CT9 4DN",
    "wof:placetype":"postalcode"
},
  "geometry": {"coordinates":[1.38303168528732,51.37747210454163],"type":"Point"}
}