{
  "type": "Feature",
  "properties": {
    "date:inception_lower": "2021-05-01",
    "date:inception_upper": "2021-05-01",
    "iso:country": "GB",
    "wof:name": "SE1 5YQ",
    "wof:placetype": "postalcode"
  },
  "geometry": {"coordinates":[-0.079044,51.494859],"type":"Point"}
}
