{
  "type": "Feature",
  "properties": {
    "iso:country": "GB",
    "wof:name": "TD11 3HQ",
    "wof:placetype": "postalcode"
  },
  "geometry": {"coordinates":[-2.33239,55.776726],"type":"Point"}
}
