{
  "type": "Feature",
  "properties": {
    "iso:country": "GB",
    "wof:name": "YO14 9LU",
    "wof:placetype": "postalcode"
  },
  "geometry": {"coordinates":[-0.295349,54.211784],"type":"Point"}
}
