{
  "type": "Feature",
  "properties": {
    "iso:country":"GB",
    "wof:name":"BR5 3EZ",
    "wof:placetype":"postalcode"
},
  "geometry": {"coordinates":[0.10581701496585,51.41120591755665],"type":"Point"}
}