{
  "type": "Feature",
  "properties": {
    "iso:country": "GB",
    "wof:name": "PE37 8EP",
    "wof:placetype": "postalcode"
  },
  "geometry": {"coordinates":[0.776138,52.650003],"type":"Point"}
}
