{
  "type": "Feature",
  "properties": {
    "iso:country": "GB",
    "wof:name": "PO19 6XD",
    "wof:placetype": "postalcode"
  },
  "geometry": {"coordinates":[-0.773871,50.841151],"type":"Point"}
}
