{
  "type": "Feature",
  "properties": {
    "date:inception_lower": "2002-06-01",
    "date:inception_upper": "2002-06-01",
    "iso:country": "GB",
    "wof:name": "PO19 6XD",
    "wof:placetype": "postalcode"
  },
  "geometry": {"coordinates":[-0.773871,50.841151],"type":"Point"}
}
