{
  "type": "Feature",
  "properties": {
    "iso:country":"GB",
    "wof:name":"S80 3PB",
    "wof:placetype":"postalcode"
},
  "geometry": {"coordinates":[-1.04392573258478,53.27128479481068],"type":"Point"}
}