{
  "type": "Feature",
  "properties": {
    "iso:country": "GB",
    "wof:name": "M7 2JJ",
    "wof:placetype": "postalcode"
  },
  "geometry": {"coordinates":[-2.268366,53.498719],"type":"Point"}
}
