{
  "type": "Feature",
  "properties": {
    "iso:country": "GB",
    "wof:name": "BH21 3XB",
    "wof:placetype": "postalcode"
  },
  "geometry": {"coordinates":[-2.010997,50.779965],"type":"Point"}
}
