{
  "type": "Feature",
  "properties": {
    "iso:country":"GB",
    "wof:name":"BH21 3XB",
    "wof:placetype":"postalcode"
},
  "geometry": {"coordinates":[-2.01099726661648,50.77996528479876],"type":"Point"}
}