{
  "type": "Feature",
  "properties": {
    "iso:country":"GB",
    "wof:name":"TF9 2BE",
    "wof:placetype":"postalcode"
},
  "geometry": {"coordinates":[-2.49386458303825,52.85638343269352],"type":"Point"}
}