{
  "type": "Feature",
  "properties": {
    "iso:country":"GB",
    "wof:name":"CA3 0HW",
    "wof:placetype":"postalcode"
},
  "geometry": {"coordinates":[-2.951457599568,54.91485361807796],"type":"Point"}
}