{
  "type": "Feature",
  "properties": {
    "iso:country":"GB",
    "wof:name":"DN7 6EX",
    "wof:placetype":"postalcode"
},
  "geometry": {"coordinates":[-0.98051663636955,53.57557436775716],"type":"Point"}
}