{
  "type": "Feature",
  "properties": {
    "date:inception_lower":"1980-01-01",
    "date:inception_upper":"1980-01-31",
    "iso:country":"GB",
    "wof:name":"DN7 6EX",
    "wof:placetype":"postalcode"
},
  "geometry": {"coordinates":[-0.980517,53.575574],"type":"Point"}
}