{
  "type": "Feature",
  "properties": {
    "iso:country": "GB",
    "wof:name": "DT11 0RH",
    "wof:placetype": "postalcode"
  },
  "geometry": {"coordinates":[-2.243928,50.895183],"type":"Point"}
}
