{
  "type": "Feature",
  "properties": {
    "iso:country":"GB",
    "wof:name":"NP19 7EZ",
    "wof:placetype":"postalcode"
},
  "geometry": {"coordinates":[-2.98254506614365,51.59421746689103],"type":"Point"}
}