{
  "type": "Feature",
  "properties": {
    "iso:country":"GB",
    "wof:name":"CV6 1QH",
    "wof:placetype":"postalcode"
},
  "geometry": {"coordinates":[-1.53062994857646,52.41436658437767],"type":"Point"}
}