{
  "type": "Feature",
  "properties": {
    "iso:country":"GB",
    "wof:name":"WV16 4ND",
    "wof:placetype":"postalcode"
},
  "geometry": {"coordinates":[-2.43055606522395,52.54252125178618],"type":"Point"}
}