{
  "type": "Feature",
  "properties": {
    "date:inception_lower": "1980-01-01",
    "date:inception_upper": "1980-01-01",
    "iso:country": "GB",
    "wof:name": "L12 4XT",
    "wof:placetype": "postalcode"
  },
  "geometry": {"coordinates":[-2.891997,53.436778],"type":"Point"}
}
