{
  "type": "Feature",
  "properties": {
    "iso:country":"GB",
    "wof:name":"SE23 3HF",
    "wof:placetype":"postalcode"
},
  "geometry": {"coordinates":[-0.0549539378995,51.43965895719244],"type":"Point"}
}