{
  "type": "Feature",
  "properties": {
    "iso:country":"GB",
    "wof:name":"BH8 9UF",
    "wof:placetype":"postalcode"
},
  "geometry": {"coordinates":[-1.83767543186957,50.75004275989613],"type":"Point"}
}