{
  "type": "Feature",
  "properties": {
    "iso:country":"GB",
    "wof:name":"TQ7 2TB",
    "wof:placetype":"postalcode"
},
  "geometry": {"coordinates":[-3.67700199350046,50.27464495900658],"type":"Point"}
}