{
  "type": "Feature",
  "properties": {
    "iso:country": "GB",
    "wof:name": "SE1 2SG",
    "wof:placetype": "postalcode"
  },
  "geometry": {"coordinates":[-0.078653,51.50345],"type":"Point"}
}
