{
  "type": "Feature",
  "properties": {
    "iso:country": "GB",
    "wof:name": "OX10 7JW",
    "wof:placetype": "postalcode"
  },
  "geometry": {"coordinates":[-1.165494,51.640212],"type":"Point"}
}
