{
  "type": "Feature",
  "properties": {
    "iso:country":"GB",
    "wof:name":"OX10 7JW",
    "wof:placetype":"postalcode"
},
  "geometry": {"coordinates":[-1.16552582818962,51.64032510091257],"type":"Point"}
}