{
  "type": "Feature",
  "properties": {
    "iso:country":"GB",
    "wof:name":"M41 9PP",
    "wof:placetype":"postalcode"
},
  "geometry": {"coordinates":[-2.3306298270244,53.44901824414622],"type":"Point"}
}