{
  "type": "Feature",
  "properties": {
    "iso:country":"GB",
    "wof:name":"GU9 7QF",
    "wof:placetype":"postalcode"
},
  "geometry": {"coordinates":[-0.79918545970733,51.20967043706653],"type":"Point"}
}