{
  "type": "Feature",
  "properties": {
    "iso:country":"GB",
    "wof:name":"SE16 3UX",
    "wof:placetype":"postalcode"
},
  "geometry": {"coordinates":[-0.06284457947743,51.49290028810506],"type":"Point"}
}