{
  "type": "Feature",
  "properties": {
    "date:inception_lower":"1995-01-01",
    "date:inception_upper":"1995-01-31",
    "iso:country":"GB",
    "wof:name":"M21 7GZ",
    "wof:placetype":"postalcode"
},
  "geometry": {"coordinates":[-2.265997,53.430906],"type":"Point"}
}