{
  "type": "Feature",
  "properties": {
    "iso:country":"GB",
    "wof:name":"CF39 8YS",
    "wof:placetype":"postalcode"
},
  "geometry": {"coordinates":[-3.42890514254709,51.59213986676959],"type":"Point"}
}