{
  "type": "Feature",
  "properties": {
    "date:inception_lower": "1980-01-01",
    "date:inception_upper": "1980-01-01",
    "iso:country": "GB",
    "wof:name": "CF39 8YS",
    "wof:placetype": "postalcode"
  },
  "geometry": {"coordinates":[-3.42892,51.592233],"type":"Point"}
}
