{
  "type": "Feature",
  "properties": {
    "iso:country": "GB",
    "wof:name": "N1 8RD",
    "wof:placetype": "postalcode"
  },
  "geometry": {"coordinates":[-0.096772,51.536413],"type":"Point"}
}
