{
  "type": "Feature",
  "properties": {
    "date:inception_lower":"1995-07-01",
    "date:inception_upper":"1995-07-31",
    "iso:country":"GB",
    "wof:name":"N1 8RD",
    "wof:placetype":"postalcode"
},
  "geometry": {"coordinates":[-0.096772,51.536413],"type":"Point"}
}