{
  "type": "Feature",
  "properties": {
    "iso:country":"GB",
    "wof:name":"TA23 0LT",
    "wof:placetype":"postalcode"
},
  "geometry": {"coordinates":[-3.35989512614853,51.12358306121246],"type":"Point"}
}