{
  "type": "Feature",
  "properties": {
    "date:inception_lower": "1998-12-01",
    "date:inception_upper": "1998-12-01",
    "iso:country": "GB",
    "wof:name": "S43 4FB",
    "wof:placetype": "postalcode"
  },
  "geometry": {"coordinates":[-1.289457,53.287322],"type":"Point"}
}
