{
  "type": "Feature",
  "properties": {
    "date:inception_lower": "2021-02-01",
    "date:inception_upper": "2021-02-01",
    "iso:country": "GB",
    "wof:name": "CW12 2PU",
    "wof:placetype": "postalcode"
  },
  "geometry": {"coordinates":[-2.208053,53.175579],"type":"Point"}
}
