{
  "type": "Feature",
  "properties": {
    "date:inception_lower": "2009-05-01",
    "date:inception_upper": "2009-05-01",
    "iso:country": "GB",
    "wof:name": "E14 5GL",
    "wof:placetype": "postalcode"
  },
  "geometry": {"coordinates":[-0.016276,51.505395],"type":"Point"}
}
