{
  "type": "Feature",
  "properties": {
    "iso:country":"GB",
    "wof:name":"E14 5GL",
    "wof:placetype":"postalcode"
},
  "geometry": {"coordinates":[-0.01627555609647,51.50539491905127],"type":"Point"}
}