{
  "type": "Feature",
  "properties": {
    "date:inception_lower":"1981-06-01",
    "date:inception_upper":"1981-06-30",
    "iso:country":"GB",
    "wof:name":"NG31 8AS",
    "wof:placetype":"postalcode"
},
  "geometry": {"coordinates":[-0.659342,52.915122],"type":"Point"}
}