{
  "type": "Feature",
  "properties": {
    "iso:country":"GB",
    "wof:name":"NG31 8AS",
    "wof:placetype":"postalcode"
},
  "geometry": {"coordinates":[-0.65934249065226,52.91512212031086],"type":"Point"}
}