{
  "type": "Feature",
  "properties": {
    "iso:country": "GB",
    "wof:name": "NG31 8AS",
    "wof:placetype": "postalcode"
  },
  "geometry": {"coordinates":[-0.659342,52.915122],"type":"Point"}
}
