{
  "type": "Feature",
  "properties": {
    "iso:country":"GB",
    "wof:name":"TS5 7PF",
    "wof:placetype":"postalcode"
},
  "geometry": {"coordinates":[-1.2386677540745,54.54892380208642],"type":"Point"}
}