{
  "type": "Feature",
  "properties": {
    "iso:country": "GB",
    "wof:name": "LL40 2BL",
    "wof:placetype": "postalcode"
  },
  "geometry": {"coordinates":[-3.766122,52.77855],"type":"Point"}
}
