{
  "type": "Feature",
  "properties": {
    "iso:country":"GB",
    "wof:name":"LL40 2BL",
    "wof:placetype":"postalcode"
},
  "geometry": {"coordinates":[-3.76612238436725,52.77854992816521],"type":"Point"}
}