{
  "type": "Feature",
  "properties": {
    "date:inception_lower":"1980-01-01",
    "date:inception_upper":"1980-01-31",
    "iso:country":"GB",
    "wof:name":"LL40 2BL",
    "wof:placetype":"postalcode"
},
  "geometry": {"coordinates":[-3.766122,52.77855],"type":"Point"}
}