{
  "type": "Feature",
  "properties": {
    "iso:country":"GB",
    "wof:name":"SW20 8NY",
    "wof:placetype":"postalcode"
},
  "geometry": {"coordinates":[-0.22943505558827,51.41467336432071],"type":"Point"}
}