{
  "type": "Feature",
  "properties": {
    "iso:country": "GB",
    "wof:name": "SW20 8NY",
    "wof:placetype": "postalcode"
  },
  "geometry": {"coordinates":[-0.229435,51.414673],"type":"Point"}
}
