{
  "type": "Feature",
  "properties": {
    "date:inception_lower": "1980-01-01",
    "date:inception_upper": "1980-01-01",
    "iso:country": "GB",
    "wof:name": "SW20 8NY",
    "wof:placetype": "postalcode"
  },
  "geometry": {"coordinates":[-0.229499,51.414629],"type":"Point"}
}
