{
  "type": "Feature",
  "properties": {
    "iso:country":"GB",
    "wof:name":"SP5 3ET",
    "wof:placetype":"postalcode"
},
  "geometry": {"coordinates":[-1.74260676162287,51.06990225664109],"type":"Point"}
}