{
  "type": "Feature",
  "properties": {
    "iso:country":"GB",
    "wof:name":"CO4 5JN",
    "wof:placetype":"postalcode"
},
  "geometry": {"coordinates":[0.90353780992794,51.91005666347584],"type":"Point"}
}