{
  "type": "Feature",
  "properties": {
    "date:inception_lower":"1980-01-01",
    "date:inception_upper":"1980-01-31",
    "iso:country":"GB",
    "wof:name":"TN25 4EJ",
    "wof:placetype":"postalcode"
},
  "geometry": {"coordinates":[0.893038,51.174508],"type":"Point"}
}