{
  "type": "Feature",
  "properties": {
    "date:inception_lower": "1980-01-01",
    "date:inception_upper": "1980-01-01",
    "iso:country": "GB",
    "wof:name": "SG14 2PD",
    "wof:placetype": "postalcode"
  },
  "geometry": {"coordinates":[-0.122008,51.78122],"type":"Point"}
}
