{
  "type": "Feature",
  "properties": {
    "iso:country":"GB",
    "wof:name":"SG14 2PD",
    "wof:placetype":"postalcode"
},
  "geometry": {"coordinates":[-0.12224354694052,51.78143302808349],"type":"Point"}
}