{
  "type": "Feature",
  "properties": {
    "iso:country":"GB",
    "wof:name":"NG19 8RQ",
    "wof:placetype":"postalcode"
},
  "geometry": {"coordinates":[-1.22877229374885,53.17938874382106],"type":"Point"}
}