{
  "type": "Feature",
  "properties": {
    "iso:country": "GB",
    "wof:name": "NG19 8RQ",
    "wof:placetype": "postalcode"
  },
  "geometry": {"coordinates":[-1.228772,53.179389],"type":"Point"}
}
