{
  "type": "Feature",
  "properties": {
    "date:inception_lower": "1993-01-01",
    "date:inception_upper": "1993-01-01",
    "iso:country": "GB",
    "wof:name": "CW7 2TU",
    "wof:placetype": "postalcode"
  },
  "geometry": {"coordinates":[-2.55129,53.191474],"type":"Point"}
}
