{
  "type": "Feature",
  "properties": {
    "iso:country": "GB",
    "wof:name": "M5 3JQ",
    "wof:placetype": "postalcode"
  },
  "geometry": {"coordinates":[-2.282033,53.475111],"type":"Point"}
}
