{
  "type": "Feature",
  "properties": {
    "iso:country":"GB",
    "wof:name":"KY1 1JJ",
    "wof:placetype":"postalcode"
},
  "geometry": {"coordinates":[-3.15159930275303,56.11451067682232],"type":"Point"}
}