{
  "type": "Feature",
  "properties": {
    "date:inception_lower": "2004-11-01",
    "date:inception_upper": "2004-11-01",
    "iso:country": "GB",
    "wof:name": "KY1 1JJ",
    "wof:placetype": "postalcode"
  },
  "geometry": {"coordinates":[-3.151599,56.114511],"type":"Point"}
}
