{
  "type": "Feature",
  "properties": {
    "date:inception_lower":"1980-01-01",
    "date:inception_upper":"1980-01-31",
    "iso:country":"GB",
    "wof:name":"SR4 7HH",
    "wof:placetype":"postalcode"
},
  "geometry": {"coordinates":[-1.401055,54.900831],"type":"Point"}
}