{
  "type": "Feature",
  "properties": {
    "iso:country": "GB",
    "wof:name": "SR4 7HH",
    "wof:placetype": "postalcode"
  },
  "geometry": {"coordinates":[-1.401055,54.900831],"type":"Point"}
}
