{
  "type": "Feature",
  "properties": {
    "date:inception_lower":"2005-02-01",
    "date:inception_upper":"2005-02-28",
    "iso:country":"GB",
    "wof:name":"FY6 6SD",
    "wof:placetype":"postalcode"
},
  "geometry": {"coordinates":[-2.989757,53.850957],"type":"Point"}
}