{
  "type": "Feature",
  "properties": {
    "iso:country": "GB",
    "wof:name": "IP33 9HQ",
    "wof:placetype": "postalcode"
  },
  "geometry": {"coordinates":[0.753105,52.242165],"type":"Point"}
}
