{
  "type": "Feature",
  "properties": {
    "date:inception_lower":"1990-02-01",
    "date:inception_upper":"1990-02-28",
    "iso:country":"GB",
    "wof:name":"BH21 3XF",
    "wof:placetype":"postalcode"
},
  "geometry": {"coordinates":[-2.010983,50.777816],"type":"Point"}
}