{
  "type": "Feature",
  "properties": {
    "iso:country":"GB",
    "wof:name":"BH21 3XF",
    "wof:placetype":"postalcode"
},
  "geometry": {"coordinates":[-2.01098256724225,50.77781605962419],"type":"Point"}
}