{
  "type": "Feature",
  "properties": {
    "iso:country":"GB",
    "wof:name":"CO5 8HH",
    "wof:placetype":"postalcode"
},
  "geometry": {"coordinates":[0.93125381227831,51.78250388062754],"type":"Point"}
}