{
  "type": "Feature",
  "properties": {
    "iso:country":"GB",
    "wof:name":"M33 7NS",
    "wof:placetype":"postalcode"
},
  "geometry": {"coordinates":[-2.32794639604619,53.4251520746746],"type":"Point"}
}