{
  "type": "Feature",
  "properties": {
    "date:inception_lower": "1994-05-01",
    "date:inception_upper": "1994-05-01",
    "iso:country": "GB",
    "wof:name": "M33 7NS",
    "wof:placetype": "postalcode"
  },
  "geometry": {"coordinates":[-2.327947,53.425168],"type":"Point"}
}
