{
  "type": "Feature",
  "properties": {
    "iso:country":"GB",
    "wof:name":"ME1 1PS",
    "wof:placetype":"postalcode"
},
  "geometry": {"coordinates":[0.49271581196905,51.38076066444354],"type":"Point"}
}