{
  "type": "Feature",
  "properties": {
    "iso:country": "GB",
    "wof:name": "ME1 1PS",
    "wof:placetype": "postalcode"
  },
  "geometry": {"coordinates":[0.492716,51.380761],"type":"Point"}
}
