{
  "type": "Feature",
  "properties": {
    "iso:country":"GB",
    "wof:name":"AB11 6ER",
    "wof:placetype":"postalcode"
},
  "geometry": {"coordinates":[-2.11265608467447,57.14075338817621],"type":"Point"}
}