{
  "type": "Feature",
  "properties": {
    "iso:country": "GB",
    "wof:name": "DT9 4FA",
    "wof:placetype": "postalcode"
  },
  "geometry": {"coordinates":[-2.526163,50.951123],"type":"Point"}
}
