{
  "type": "Feature",
  "properties": {
    "iso:country": "GB",
    "wof:name": "WS10 9DB",
    "wof:placetype": "postalcode"
  },
  "geometry": {"coordinates":[-2.017655,52.554397],"type":"Point"}
}
