{
  "type": "Feature",
  "properties": {
    "iso:country":"GB",
    "wof:name":"WS10 9DB",
    "wof:placetype":"postalcode"
},
  "geometry": {"coordinates":[-2.01765537323933,52.55439727449185],"type":"Point"}
}