{
  "type": "Feature",
  "properties": {
    "date:inception_lower": "1992-08-01",
    "date:inception_upper": "1992-08-01",
    "iso:country": "GB",
    "wof:name": "LE18 1HU",
    "wof:placetype": "postalcode"
  },
  "geometry": {"coordinates":[-1.119557,52.596814],"type":"Point"}
}
