{
  "type": "Feature",
  "properties": {
    "date:inception_lower": "1980-01-01",
    "date:inception_upper": "1980-01-01",
    "iso:country": "GB",
    "wof:name": "CA5 7QB",
    "wof:placetype": "postalcode"
  },
  "geometry": {"coordinates":[-2.984484,54.838677],"type":"Point"}
}
