{
  "type": "Feature",
  "properties": {
    "iso:country":"GB",
    "wof:name":"CA5 7QB",
    "wof:placetype":"postalcode"
},
  "geometry": {"coordinates":[-2.98462965994743,54.83842631033595],"type":"Point"}
}