{
  "type": "Feature",
  "properties": {
    "iso:country":"GB",
    "wof:name":"ST4 4QR",
    "wof:placetype":"postalcode"
},
  "geometry": {"coordinates":[-2.19669574016453,52.97861275559976],"type":"Point"}
}