{
  "type": "Feature",
  "properties": {
    "date:inception_lower":"1980-01-01",
    "date:inception_upper":"1980-01-31",
    "iso:country":"GB",
    "wof:name":"ST4 4QR",
    "wof:placetype":"postalcode"
},
  "geometry": {"coordinates":[-2.196696,52.978613],"type":"Point"}
}