{
  "type": "Feature",
  "properties": {
    "date:inception_lower": "1980-01-01",
    "date:inception_upper": "1980-01-01",
    "iso:country": "GB",
    "wof:name": "DN11 9AF",
    "wof:placetype": "postalcode"
  },
  "geometry": {"coordinates":[-1.152107,53.460977],"type":"Point"}
}
