{
  "type": "Feature",
  "properties": {
    "iso:country":"GB",
    "wof:name":"DN11 9AF",
    "wof:placetype":"postalcode"
},
  "geometry": {"coordinates":[-1.15210699787783,53.46097741934795],"type":"Point"}
}