{
  "type": "Feature",
  "properties": {
    "iso:country":"GB",
    "wof:name":"SA43 2TN",
    "wof:placetype":"postalcode"
},
  "geometry": {"coordinates":[-4.63313464062154,52.0360337033281],"type":"Point"}
}