{
  "type": "Feature",
  "properties": {
    "date:inception_lower":"1980-01-01",
    "date:inception_upper":"1980-01-31",
    "iso:country":"GB",
    "wof:name":"TR20 9PW",
    "wof:placetype":"postalcode"
},
  "geometry": {"coordinates":[-5.429885,50.118934],"type":"Point"}
}