{
  "type": "Feature",
  "properties": {
    "iso:country":"GB",
    "wof:name":"DE65 6HY",
    "wof:placetype":"postalcode"
},
  "geometry": {"coordinates":[-1.5850602295929,52.88289164686655],"type":"Point"}
}