{
  "type": "Feature",
  "properties": {
    "iso:country": "GB",
    "wof:name": "DE65 6HY",
    "wof:placetype": "postalcode"
  },
  "geometry": {"coordinates":[-1.58506,52.882892],"type":"Point"}
}
