{
  "type": "Feature",
  "properties": {
    "iso:country":"GB",
    "wof:name":"SE10 9JA",
    "wof:placetype":"postalcode"
},
  "geometry": {"coordinates":[-0.00900247381689,51.48117125853769],"type":"Point"}
}