{
  "type": "Feature",
  "properties": {
    "iso:country":"GB",
    "wof:name":"SP2 8JX",
    "wof:placetype":"postalcode"
},
  "geometry": {"coordinates":[-1.80569151423606,51.05932333529037],"type":"Point"}
}