{
  "type": "Feature",
  "properties": {
    "iso:country":"GB",
    "wof:name":"RM6 6SS",
    "wof:placetype":"postalcode"
},
  "geometry": {"coordinates":[0.13882607839021,51.57905359686401],"type":"Point"}
}