{
  "type": "Feature",
  "properties": {
    "iso:country": "GB",
    "wof:name": "DN20 8AJ",
    "wof:placetype": "postalcode"
  },
  "geometry": {"coordinates":[-0.493949,53.555373],"type":"Point"}
}
