{
  "type": "Feature",
  "properties": {
    "iso:country":"GB",
    "wof:name":"BL1 4ET",
    "wof:placetype":"postalcode"
},
  "geometry": {"coordinates":[-2.46057926476306,53.58578759096586],"type":"Point"}
}