{
  "type": "Feature",
  "properties": {
    "iso:country": "GB",
    "wof:name": "G43 1EL",
    "wof:placetype": "postalcode"
  },
  "geometry": {"coordinates":[-4.304655,55.814376],"type":"Point"}
}
