{
  "type": "Feature",
  "properties": {
    "date:inception_lower": "2009-02-01",
    "date:inception_upper": "2009-02-01",
    "iso:country": "GB",
    "wof:name": "TW2 6AU",
    "wof:placetype": "postalcode"
  },
  "geometry": {"coordinates":[-0.37782,51.449868],"type":"Point"}
}
