{
  "type": "Feature",
  "properties": {
    "iso:country":"GB",
    "wof:name":"TW2 6AU",
    "wof:placetype":"postalcode"
},
  "geometry": {"coordinates":[-0.37782033146356,51.44986798719281],"type":"Point"}
}