{
  "type": "Feature",
  "properties": {
    "iso:country": "GB",
    "wof:name": "SW17 7AH",
    "wof:placetype": "postalcode"
  },
  "geometry": {"coordinates":[-0.157645,51.437946],"type":"Point"}
}
