{
  "type": "Feature",
  "properties": {
    "iso:country":"GB",
    "wof:name":"SW17 7AH",
    "wof:placetype":"postalcode"
},
  "geometry": {"coordinates":[-0.1576445750766,51.43794575414034],"type":"Point"}
}