{
  "type": "Feature",
  "properties": {
    "iso:country":"GB",
    "wof:name":"HU17 7DQ",
    "wof:placetype":"postalcode"
},
  "geometry": {"coordinates":[-0.44714270248565,53.8555400476293],"type":"Point"}
}