{
  "type": "Feature",
  "properties": {
    "iso:country": "GB",
    "wof:name": "NE38 7HZ",
    "wof:placetype": "postalcode"
  },
  "geometry": {"coordinates":[-1.524636,54.90232],"type":"Point"}
}
