{
  "type": "Feature",
  "properties": {
    "iso:country": "GB",
    "wof:name": "RM3 0GT",
    "wof:placetype": "postalcode"
  },
  "geometry": {"coordinates":[0.224135,51.59102],"type":"Point"}
}
