{
  "type": "Feature",
  "properties": {
    "iso:country":"GB",
    "wof:name":"RM3 0GT",
    "wof:placetype":"postalcode"
},
  "geometry": {"coordinates":[0.22413514284296,51.59101977332868],"type":"Point"}
}