{
  "type": "Feature",
  "properties": {
    "date:inception_lower":"2003-11-01",
    "date:inception_upper":"2003-11-30",
    "iso:country":"GB",
    "wof:name":"RM3 0GT",
    "wof:placetype":"postalcode"
},
  "geometry": {"coordinates":[0.224135,51.59102],"type":"Point"}
}