{
  "type": "Feature",
  "properties": {
    "iso:country":"GB",
    "wof:name":"NG22 9HY",
    "wof:placetype":"postalcode"
},
  "geometry": {"coordinates":[-0.99193663847684,53.20562213514901],"type":"Point"}
}