{
  "type": "Feature",
  "properties": {
    "iso:country": "GB",
    "wof:name": "NG22 9HY",
    "wof:placetype": "postalcode"
  },
  "geometry": {"coordinates":[-0.991937,53.205622],"type":"Point"}
}
