{
  "type": "Feature",
  "properties": {
    "iso:country": "GB",
    "wof:name": "PL6 8BG",
    "wof:placetype": "postalcode"
  },
  "geometry": {"coordinates":[-4.114461,50.418667],"type":"Point"}
}
