{
  "type": "Feature",
  "properties": {
    "date:inception_lower": "1980-01-01",
    "date:inception_upper": "1980-01-01",
    "iso:country": "GB",
    "wof:name": "PL6 8BG",
    "wof:placetype": "postalcode"
  },
  "geometry": {"coordinates":[-4.114461,50.418667],"type":"Point"}
}
