{
  "type": "Feature",
  "properties": {
    "iso:country":"GB",
    "wof:name":"PL6 8BG",
    "wof:placetype":"postalcode"
},
  "geometry": {"coordinates":[-4.11446098325815,50.41866659024197],"type":"Point"}
}