{
  "type": "Feature",
  "properties": {
    "iso:country": "GB",
    "wof:name": "S62 5EJ",
    "wof:placetype": "postalcode"
  },
  "geometry": {"coordinates":[-1.330776,53.46719],"type":"Point"}
}
