{
  "type": "Feature",
  "properties": {
    "iso:country":"GB",
    "wof:name":"M33 5JG",
    "wof:placetype":"postalcode"
},
  "geometry": {"coordinates":[-2.35369799171855,53.42916833633067],"type":"Point"}
}