{
  "type": "Feature",
  "properties": {
    "iso:country":"GB",
    "wof:name":"LS16 7SH",
    "wof:placetype":"postalcode"
},
  "geometry": {"coordinates":[-1.61002231094869,53.85974695014389],"type":"Point"}
}