{
  "type": "Feature",
  "properties": {
    "iso:country":"GB",
    "wof:name":"SG5 2QR",
    "wof:placetype":"postalcode"
},
  "geometry": {"coordinates":[-0.2926092193972,51.95688096376351],"type":"Point"}
}