{
  "type": "Feature",
  "properties": {
    "iso:country":"GB",
    "wof:name":"TR18 4NY",
    "wof:placetype":"postalcode"
},
  "geometry": {"coordinates":[-5.54856817346441,50.11139518591566],"type":"Point"}
}