{
  "type": "Feature",
  "properties": {
    "date:inception_lower": "1980-01-01",
    "date:inception_upper": "1980-01-01",
    "iso:country": "GB",
    "wof:name": "TR18 4NY",
    "wof:placetype": "postalcode"
  },
  "geometry": {"coordinates":[-5.548568,50.111395],"type":"Point"}
}
