{
  "type": "Feature",
  "properties": {
    "iso:country":"GB",
    "wof:name":"RM15 5AN",
    "wof:placetype":"postalcode"
},
  "geometry": {"coordinates":[0.28328012394748,51.51314655255916],"type":"Point"}
}