{
  "type": "Feature",
  "properties": {
    "iso:country": "GB",
    "wof:name": "SS2 4UE",
    "wof:placetype": "postalcode"
  },
  "geometry": {"coordinates":[0.739033,51.543893],"type":"Point"}
}
