{
  "type": "Feature",
  "properties": {
    "iso:country": "GB",
    "wof:name": "BD17 7AJ",
    "wof:placetype": "postalcode"
  },
  "geometry": {"coordinates":[-1.768265,53.838244],"type":"Point"}
}
