{
  "type": "Feature",
  "properties": {
    "iso:country":"GB",
    "wof:name":"BD17 7AJ",
    "wof:placetype":"postalcode"
},
  "geometry": {"coordinates":[-1.76826457331094,53.83824396806864],"type":"Point"}
}