{
  "type": "Feature",
  "properties": {
    "date:inception_lower":"2008-03-01",
    "date:inception_upper":"2008-03-31",
    "iso:country":"GB",
    "wof:name":"BD17 7AJ",
    "wof:placetype":"postalcode"
},
  "geometry": {"coordinates":[-1.768265,53.838244],"type":"Point"}
}