{
  "type": "Feature",
  "properties": {
    "iso:country": "GB",
    "wof:name": "SL1 5HP",
    "wof:placetype": "postalcode"
  },
  "geometry": {"coordinates":[-0.642694,51.517832],"type":"Point"}
}
