{
  "type": "Feature",
  "properties": {
    "date:inception_lower": "1999-12-01",
    "date:inception_upper": "1999-12-01",
    "iso:country": "GB",
    "wof:name": "SL1 5HP",
    "wof:placetype": "postalcode"
  },
  "geometry": {"coordinates":[-0.642694,51.517832],"type":"Point"}
}
