{
  "type": "Feature",
  "properties": {
    "iso:country":"GB",
    "wof:name":"SK17 8DG",
    "wof:placetype":"postalcode"
},
  "geometry": {"coordinates":[-1.89096388564997,53.30122291710227],"type":"Point"}
}