{
  "type": "Feature",
  "properties": {
    "iso:country": "GB",
    "wof:name": "SK17 8DG",
    "wof:placetype": "postalcode"
  },
  "geometry": {"coordinates":[-1.890964,53.301223],"type":"Point"}
}
