{
  "type": "Feature",
  "properties": {
    "date:inception_lower":"2014-11-01",
    "date:inception_upper":"2014-11-30",
    "iso:country":"GB",
    "wof:name":"G4 0QG",
    "wof:placetype":"postalcode"
},
  "geometry": {"coordinates":[-4.238813,55.862682],"type":"Point"}
}