{
  "type": "Feature",
  "properties": {
    "iso:country":"GB",
    "wof:name":"SY3 5BY",
    "wof:placetype":"postalcode"
},
  "geometry": {"coordinates":[-2.81251372180137,52.71538787883325],"type":"Point"}
}