{
  "type": "Feature",
  "properties": {
    "iso:country":"GB",
    "wof:name":"SG6 2ES",
    "wof:placetype":"postalcode"
},
  "geometry": {"coordinates":[-0.21908917378869,51.97253454294453],"type":"Point"}
}