{
  "type": "Feature",
  "properties": {
    "iso:country":"GB",
    "wof:name":"S9 2XB",
    "wof:placetype":"postalcode"
},
  "geometry": {"coordinates":[-1.42520341864283,53.39967317332367],"type":"Point"}
}