{
  "type": "Feature",
  "properties": {
    "iso:country":"GB",
    "wof:name":"SW11 1DB",
    "wof:placetype":"postalcode"
},
  "geometry": {"coordinates":[-0.16988145381149,51.45757037735343],"type":"Point"}
}