{
  "type": "Feature",
  "properties": {
    "iso:country":"GB",
    "wof:name":"TN9 1PE",
    "wof:placetype":"postalcode"
},
  "geometry": {"coordinates":[0.28099194809632,51.19721323980478],"type":"Point"}
}