{
  "type": "Feature",
  "properties": {
    "iso:country": "GB",
    "wof:name": "TN9 1PE",
    "wof:placetype": "postalcode"
  },
  "geometry": {"coordinates":[0.280992,51.197213],"type":"Point"}
}
