{
  "type": "Feature",
  "properties": {
    "iso:country":"GB",
    "wof:name":"ME19 4UA",
    "wof:placetype":"postalcode"
},
  "geometry": {"coordinates":[0.39433421697684,51.27645662550022],"type":"Point"}
}