{
  "type": "Feature",
  "properties": {
    "date:inception_lower":"2005-08-01",
    "date:inception_upper":"2005-08-31",
    "iso:country":"GB",
    "wof:name":"ME19 4UA",
    "wof:placetype":"postalcode"
},
  "geometry": {"coordinates":[0.394334,51.276457],"type":"Point"}
}