{
  "type": "Feature",
  "properties": {
    "date:inception_lower": "1980-01-01",
    "date:inception_upper": "1980-01-01",
    "iso:country": "GB",
    "wof:name": "EH20 9PQ",
    "wof:placetype": "postalcode"
  },
  "geometry": {"coordinates":[-3.175713,55.874472],"type":"Point"}
}
