{
  "type": "Feature",
  "properties": {
    "iso:country":"GB",
    "wof:name":"EH20 9PQ",
    "wof:placetype":"postalcode"
},
  "geometry": {"coordinates":[-3.17571312652474,55.87447229056414],"type":"Point"}
}