{
  "type": "Feature",
  "properties": {
    "iso:country":"GB",
    "wof:name":"AL6 0QT",
    "wof:placetype":"postalcode"
},
  "geometry": {"coordinates":[-0.19355820145173,51.84124154496136],"type":"Point"}
}