{
  "type": "Feature",
  "properties": {
    "iso:country":"GB",
    "wof:name":"OX16 0RH",
    "wof:placetype":"postalcode"
},
  "geometry": {"coordinates":[-1.3568042525966,52.0646830629059],"type":"Point"}
}