{
  "type": "Feature",
  "properties": {
    "iso:country":"GB",
    "wof:name":"TR3 7DQ",
    "wof:placetype":"postalcode"
},
  "geometry": {"coordinates":[-5.17277390475128,50.18719953987492],"type":"Point"}
}