{
  "type": "Feature",
  "properties": {
    "date:inception_lower": "1980-01-01",
    "date:inception_upper": "1980-01-01",
    "iso:country": "GB",
    "wof:name": "EX20 1HX",
    "wof:placetype": "postalcode"
  },
  "geometry": {"coordinates":[-4.003287,50.735711],"type":"Point"}
}
