{
  "type": "Feature",
  "properties": {
    "iso:country":"GB",
    "wof:name":"EX20 1HX",
    "wof:placetype":"postalcode"
},
  "geometry": {"coordinates":[-4.00328671458814,50.73571097972441],"type":"Point"}
}