{
  "type": "Feature",
  "properties": {
    "date:inception_lower": "2021-06-01",
    "date:inception_upper": "2021-06-01",
    "iso:country": "GB",
    "wof:name": "NG14 7HQ",
    "wof:placetype": "postalcode"
  },
  "geometry": {"coordinates":[-0.965605,53.037198],"type":"Point"}
}
