{
  "type": "Feature",
  "properties": {
    "iso:country":"GB",
    "wof:name":"PL12 6JW",
    "wof:placetype":"postalcode"
},
  "geometry": {"coordinates":[-4.21277531862575,50.40894024465909],"type":"Point"}
}