{
  "type": "Feature",
  "properties": {
    "date:inception_lower": "1980-01-01",
    "date:inception_upper": "1980-01-01",
    "iso:country": "GB",
    "wof:name": "DT8 3PB",
    "wof:placetype": "postalcode"
  },
  "geometry": {"coordinates":[-2.66073,50.796969],"type":"Point"}
}
