{
  "type": "Feature",
  "properties": {
    "iso:country":"GB",
    "wof:name":"DT8 3PB",
    "wof:placetype":"postalcode"
},
  "geometry": {"coordinates":[-2.66072980693229,50.79696867318963],"type":"Point"}
}