{
  "type": "Feature",
  "properties": {
    "iso:country":"GB",
    "wof:name":"CR7 8SB",
    "wof:placetype":"postalcode"
},
  "geometry": {"coordinates":[-0.09241614268729,51.39698379161609],"type":"Point"}
}