{
  "type": "Feature",
  "properties": {
    "date:inception_lower": "1980-01-01",
    "date:inception_upper": "1980-01-01",
    "iso:country": "GB",
    "wof:name": "TA7 8NN",
    "wof:placetype": "postalcode"
  },
  "geometry": {"coordinates":[-2.879647,51.190625],"type":"Point"}
}
