{
  "type": "Feature",
  "properties": {
    "iso:country": "GB",
    "wof:name": "PO20 0QG",
    "wof:placetype": "postalcode"
  },
  "geometry": {"coordinates":[-0.791781,50.733269],"type":"Point"}
}
