{
  "type": "Feature",
  "properties": {
    "iso:country":"GB",
    "wof:name":"BH12 3BT",
    "wof:placetype":"postalcode"
},
  "geometry": {"coordinates":[-1.94754877996913,50.73292277697315],"type":"Point"}
}