{
  "type": "Feature",
  "properties": {
    "iso:country":"GB",
    "wof:name":"TR26 1SH",
    "wof:placetype":"postalcode"
},
  "geometry": {"coordinates":[-5.48228410513117,50.21170946330268],"type":"Point"}
}