{
  "type": "Feature",
  "properties": {
    "iso:country": "GB",
    "wof:name": "TR26 1SH",
    "wof:placetype": "postalcode"
  },
  "geometry": {"coordinates":[-5.482284,50.211709],"type":"Point"}
}
