{
  "type": "Feature",
  "properties": {
    "iso:country": "GB",
    "wof:name": "LS27 8FG",
    "wof:placetype": "postalcode"
  },
  "geometry": {"coordinates":[-1.579977,53.749342],"type":"Point"}
}
