{
  "type": "Feature",
  "properties": {
    "iso:country":"GB",
    "wof:name":"SP11 6DD",
    "wof:placetype":"postalcode"
},
  "geometry": {"coordinates":[-1.38907477057357,51.24480829400987],"type":"Point"}
}