{
  "type": "Feature",
  "properties": {
    "date:inception_lower": "1980-01-01",
    "date:inception_upper": "1980-01-01",
    "iso:country": "GB",
    "wof:name": "NE9 5TR",
    "wof:placetype": "postalcode"
  },
  "geometry": {"coordinates":[-1.596005,54.940402],"type":"Point"}
}
