{
  "type": "Feature",
  "properties": {
    "iso:country": "GB",
    "wof:name": "NE9 5TR",
    "wof:placetype": "postalcode"
  },
  "geometry": {"coordinates":[-1.596005,54.940402],"type":"Point"}
}
