{
  "type": "Feature",
  "properties": {
    "iso:country":"GB",
    "wof:name":"M34 3TE",
    "wof:placetype":"postalcode"
},
  "geometry": {"coordinates":[-2.1076411623544,53.46362951580974],"type":"Point"}
}