{
  "type": "Feature",
  "properties": {
    "date:inception_lower": "1980-01-01",
    "date:inception_upper": "1980-01-01",
    "iso:country": "GB",
    "wof:name": "G14 0HR",
    "wof:placetype": "postalcode"
  },
  "geometry": {"coordinates":[-4.370696,55.885049],"type":"Point"}
}
