{
  "type": "Feature",
  "properties": {
    "iso:country": "GB",
    "wof:name": "YO30 2DG",
    "wof:placetype": "postalcode"
  },
  "geometry": {"coordinates":[-1.219723,54.032552],"type":"Point"}
}
