{
  "type": "Feature",
  "properties": {
    "date:inception_lower":"2010-08-01",
    "date:inception_upper":"2010-08-31",
    "iso:country":"GB",
    "wof:name":"CV3 1PH",
    "wof:placetype":"postalcode"
},
  "geometry": {"coordinates":[-1.485998,52.401334],"type":"Point"}
}