{
  "type": "Feature",
  "properties": {
    "iso:country":"GB",
    "wof:name":"CV3 1PH",
    "wof:placetype":"postalcode"
},
  "geometry": {"coordinates":[-1.48599796131384,52.40133414956016],"type":"Point"}
}