{
  "type": "Feature",
  "properties": {
    "date:inception_lower":"2007-01-01",
    "date:inception_upper":"2007-01-31",
    "iso:country":"GB",
    "wof:name":"M20 2UR",
    "wof:placetype":"postalcode"
},
  "geometry": {"coordinates":[-2.251224,53.426974],"type":"Point"}
}