{
  "type": "Feature",
  "properties": {
    "iso:country":"GB",
    "wof:name":"ST18 9PN",
    "wof:placetype":"postalcode"
},
  "geometry": {"coordinates":[-2.16039415264202,52.79575214406459],"type":"Point"}
}