{
  "type": "Feature",
  "properties": {
    "iso:country":"GB",
    "wof:name":"OX2 7XH",
    "wof:placetype":"postalcode"
},
  "geometry": {"coordinates":[-1.26156920443908,51.77441721969225],"type":"Point"}
}