{
  "type": "Feature",
  "properties": {
    "iso:country": "GB",
    "wof:name": "CR3 6JT",
    "wof:placetype": "postalcode"
  },
  "geometry": {"coordinates":[-0.07771,51.292003],"type":"Point"}
}
