{
  "type": "Feature",
  "properties": {
    "iso:country": "GB",
    "wof:name": "CR3 6JT",
    "wof:placetype": "postalcode"
  },
  "geometry": {"coordinates":[-0.07788,51.29206],"type":"Point"}
}
