{
  "type": "Feature",
  "properties": {
    "date:inception_lower":"1992-08-01",
    "date:inception_upper":"1992-08-31",
    "iso:country":"GB",
    "wof:name":"DE6 3LF",
    "wof:placetype":"postalcode"
},
  "geometry": {"coordinates":[-1.587218,53.048401],"type":"Point"}
}