{
  "type": "Feature",
  "properties": {
    "iso:country": "GB",
    "wof:name": "DE6 3LF",
    "wof:placetype": "postalcode"
  },
  "geometry": {"coordinates":[-1.587218,53.048401],"type":"Point"}
}
