{
  "type": "Feature",
  "properties": {
    "iso:country":"GB",
    "wof:name":"DE6 3LF",
    "wof:placetype":"postalcode"
},
  "geometry": {"coordinates":[-1.58721762130095,53.04840079993654],"type":"Point"}
}