{
  "type": "Feature",
  "properties": {
    "iso:country": "GB",
    "wof:name": "GL53 7ES",
    "wof:placetype": "postalcode"
  },
  "geometry": {"coordinates":[-2.068652,51.889173],"type":"Point"}
}
