{
  "type": "Feature",
  "properties": {
    "date:inception_lower":"2014-06-01",
    "date:inception_upper":"2014-06-30",
    "iso:country":"GB",
    "wof:name":"GL53 7ES",
    "wof:placetype":"postalcode"
},
  "geometry": {"coordinates":[-2.068652,51.889173],"type":"Point"}
}