{
  "type": "Feature",
  "properties": {
    "iso:country":"GB",
    "wof:name":"DN9 3LN",
    "wof:placetype":"postalcode"
},
  "geometry": {"coordinates":[-1.01364208350356,53.48832858295489],"type":"Point"}
}