{
  "type": "Feature",
  "properties": {
    "date:inception_lower":"1980-01-01",
    "date:inception_upper":"1980-01-31",
    "iso:country":"GB",
    "wof:name":"WN7 4EP",
    "wof:placetype":"postalcode"
},
  "geometry": {"coordinates":[-2.529313,53.497758],"type":"Point"}
}