{
  "type": "Feature",
  "properties": {
    "iso:country":"GB",
    "wof:name":"RG14 2LZ",
    "wof:placetype":"postalcode"
},
  "geometry": {"coordinates":[-1.30503130387532,51.4122629107766],"type":"Point"}
}