{
  "type": "Feature",
  "properties": {
    "iso:country":"GB",
    "wof:name":"BL3 4HB",
    "wof:placetype":"postalcode"
},
  "geometry": {"coordinates":[-2.46009655698408,53.56777674654491],"type":"Point"}
}