{
  "type": "Feature",
  "properties": {
    "iso:country":"GB",
    "wof:name":"G5 8NX",
    "wof:placetype":"postalcode"
},
  "geometry": {"coordinates":[-4.26947580257425,55.85028863633951],"type":"Point"}
}