{
  "type": "Feature",
  "properties": {
    "iso:country":"GB",
    "wof:name":"PR9 8DZ",
    "wof:placetype":"postalcode"
},
  "geometry": {"coordinates":[-2.88754354964494,53.696456730414],"type":"Point"}
}