{
  "type": "Feature",
  "properties": {
    "iso:country":"GB",
    "wof:name":"S35 0HA",
    "wof:placetype":"postalcode"
},
  "geometry": {"coordinates":[-1.53614873411845,53.4331885990403],"type":"Point"}
}