{
  "type": "Feature",
  "properties": {
    "date:inception_lower": "2015-08-01",
    "date:inception_upper": "2015-08-01",
    "iso:country": "GB",
    "wof:name": "RH12 3UT",
    "wof:placetype": "postalcode"
  },
  "geometry": {"coordinates":[-0.361879,51.062639],"type":"Point"}
}
