{
  "type": "Feature",
  "properties": {
    "iso:country":"GB",
    "wof:name":"RH12 3UT",
    "wof:placetype":"postalcode"
},
  "geometry": {"coordinates":[-0.36184949742117,51.06266593526585],"type":"Point"}
}