{
  "type": "Feature",
  "properties": {
    "date:inception_lower": "1983-03-01",
    "date:inception_upper": "1983-03-01",
    "iso:country": "GB",
    "wof:name": "SW8 4AL",
    "wof:placetype": "postalcode"
  },
  "geometry": {"coordinates":[-0.143901,51.476776],"type":"Point"}
}
