{
  "type": "Feature",
  "properties": {
    "iso:country":"GB",
    "wof:name":"SW8 4AL",
    "wof:placetype":"postalcode"
},
  "geometry": {"coordinates":[-0.14361708842921,51.47659037140254],"type":"Point"}
}