{
  "type": "Feature",
  "properties": {
    "date:inception_lower": "2001-12-01",
    "date:inception_upper": "2001-12-01",
    "iso:country": "GB",
    "wof:name": "TS10 2TY",
    "wof:placetype": "postalcode"
  },
  "geometry": {"coordinates":[-1.053783,54.592367],"type":"Point"}
}
