{
  "type": "Feature",
  "properties": {
    "iso:country":"GB",
    "wof:name":"LL14 1BU",
    "wof:placetype":"postalcode"
},
  "geometry": {"coordinates":[-3.0577551062727,53.0140716557008],"type":"Point"}
}