{
  "type": "Feature",
  "properties": {
    "date:inception_lower": "2017-04-01",
    "date:inception_upper": "2017-04-01",
    "iso:country": "GB",
    "wof:name": "S63 6GH",
    "wof:placetype": "postalcode"
  },
  "geometry": {"coordinates":[-1.36056,53.50321],"type":"Point"}
}
