{
  "type": "Feature",
  "properties": {
    "iso:country": "GB",
    "wof:name": "DA12 5DF",
    "wof:placetype": "postalcode"
  },
  "geometry": {"coordinates":[0.381132,51.417788],"type":"Point"}
}
