{
  "type": "Feature",
  "properties": {
    "iso:country": "GB",
    "wof:name": "CF81 8QN",
    "wof:placetype": "postalcode"
  },
  "geometry": {"coordinates":[-3.238986,51.684504],"type":"Point"}
}
