{
  "type": "Feature",
  "properties": {
    "iso:country": "GB",
    "wof:name": "G62 6HU",
    "wof:placetype": "postalcode"
  },
  "geometry": {"coordinates":[-4.309524,55.937936],"type":"Point"}
}
