{
  "type": "Feature",
  "properties": {
    "iso:country":"GB",
    "wof:name":"G62 6HU",
    "wof:placetype":"postalcode"
},
  "geometry": {"coordinates":[-4.30952393084987,55.93793560452006],"type":"Point"}
}