{
  "type": "Feature",
  "properties": {
    "iso:country":"GB",
    "wof:name":"LS11 0AJ",
    "wof:placetype":"postalcode"
},
  "geometry": {"coordinates":[-1.5616634168529,53.78200474837923],"type":"Point"}
}