{
  "type": "Feature",
  "properties": {
    "iso:country":"GB",
    "wof:name":"LS14 2AW",
    "wof:placetype":"postalcode"
},
  "geometry": {"coordinates":[-1.45046254824123,53.83001957968191],"type":"Point"}
}