{
  "type": "Feature",
  "properties": {
    "iso:country": "GB",
    "wof:name": "GU14 6NX",
    "wof:placetype": "postalcode"
  },
  "geometry": {"coordinates":[-0.740593,51.281416],"type":"Point"}
}
