{
  "type": "Feature",
  "properties": {
    "iso:country":"GB",
    "wof:name":"BD23 1BE",
    "wof:placetype":"postalcode"
},
  "geometry": {"coordinates":[-2.00375936929205,53.96573439056657],"type":"Point"}
}