{
  "type": "Feature",
  "properties": {
    "iso:country": "GB",
    "wof:name": "GL7 3FX",
    "wof:placetype": "postalcode"
  },
  "geometry": {"coordinates":[-1.725636,51.698259],"type":"Point"}
}
