{
  "type": "Feature",
  "properties": {
    "iso:country":"GB",
    "wof:name":"S41 8QT",
    "wof:placetype":"postalcode"
},
  "geometry": {"coordinates":[-1.44308715676384,53.25537996960799],"type":"Point"}
}