{
  "type": "Feature",
  "properties": {
    "iso:country":"GB",
    "wof:name":"TA11 7NN",
    "wof:placetype":"postalcode"
},
  "geometry": {"coordinates":[-2.72522606895695,51.05352812253207],"type":"Point"}
}