{
  "type": "Feature",
  "properties": {
    "date:inception_lower": "1980-01-01",
    "date:inception_upper": "1980-01-01",
    "iso:country": "GB",
    "wof:name": "TA11 7NN",
    "wof:placetype": "postalcode"
  },
  "geometry": {"coordinates":[-2.726418,51.05373],"type":"Point"}
}
