{
  "type": "Feature",
  "properties": {
    "date:inception_lower": "1980-01-01",
    "date:inception_upper": "1980-01-01",
    "iso:country": "GB",
    "wof:name": "NE1 3RE",
    "wof:placetype": "postalcode"
  },
  "geometry": {"coordinates":[-1.609296,54.968301],"type":"Point"}
}
