{
  "type": "Feature",
  "properties": {
    "iso:country": "GB",
    "wof:name": "KY7 6NX",
    "wof:placetype": "postalcode"
  },
  "geometry": {"coordinates":[-3.153254,56.213287],"type":"Point"}
}
