{
  "type": "Feature",
  "properties": {
    "iso:country":"GB",
    "wof:name":"LA4 6LY",
    "wof:placetype":"postalcode"
},
  "geometry": {"coordinates":[-2.83280047301637,54.06649528312553],"type":"Point"}
}