{
  "type": "Feature",
  "properties": {
    "date:inception_lower": "1980-01-01",
    "date:inception_upper": "1980-01-01",
    "iso:country": "GB",
    "wof:name": "LA4 6LY",
    "wof:placetype": "postalcode"
  },
  "geometry": {"coordinates":[-2.832798,54.066506],"type":"Point"}
}
