{
  "type": "Feature",
  "properties": {
    "date:inception_lower": "1980-01-01",
    "date:inception_upper": "1980-01-01",
    "iso:country": "GB",
    "wof:name": "NE44 6AL",
    "wof:placetype": "postalcode"
  },
  "geometry": {"coordinates":[-1.980706,54.944836],"type":"Point"}
}
