{
  "type": "Feature",
  "properties": {
    "iso:country": "GB",
    "wof:name": "NE44 6AL",
    "wof:placetype": "postalcode"
  },
  "geometry": {"coordinates":[-1.980706,54.944836],"type":"Point"}
}
