{
  "type": "Feature",
  "properties": {
    "iso:country":"GB",
    "wof:name":"NE44 6AL",
    "wof:placetype":"postalcode"
},
  "geometry": {"coordinates":[-1.98070565983737,54.94483614338744],"type":"Point"}
}