{
  "type": "Feature",
  "properties": {
    "iso:country":"GB",
    "wof:name":"MK45 2TG",
    "wof:placetype":"postalcode"
},
  "geometry": {"coordinates":[-0.49418506851008,52.02561969802917],"type":"Point"}
}