{
  "type": "Feature",
  "properties": {
    "iso:country":"GB",
    "wof:name":"MK8 8EQ",
    "wof:placetype":"postalcode"
},
  "geometry": {"coordinates":[-0.79888203419893,52.03874915714732],"type":"Point"}
}