{
  "type": "Feature",
  "properties": {
    "date:inception_lower": "1983-07-01",
    "date:inception_upper": "1983-07-01",
    "iso:country": "GB",
    "wof:name": "MK8 8EQ",
    "wof:placetype": "postalcode"
  },
  "geometry": {"coordinates":[-0.798882,52.038749],"type":"Point"}
}
