{
  "type": "Feature",
  "properties": {
    "iso:country":"GB",
    "wof:name":"TW18 2FD",
    "wof:placetype":"postalcode"
},
  "geometry": {"coordinates":[-0.50412034960251,51.43225909394734],"type":"Point"}
}