{
  "type": "Feature",
  "properties": {
    "date:inception_lower": "1999-06-01",
    "date:inception_upper": "1999-06-01",
    "iso:country": "GB",
    "wof:name": "TW18 2FD",
    "wof:placetype": "postalcode"
  },
  "geometry": {"coordinates":[-0.504187,51.432242],"type":"Point"}
}
