{
  "type": "Feature",
  "properties": {
    "date:inception_lower": "1987-04-01",
    "date:inception_upper": "1987-04-01",
    "iso:country": "GB",
    "wof:name": "BH21 1QX",
    "wof:placetype": "postalcode"
  },
  "geometry": {"coordinates":[-1.982978,50.7967],"type":"Point"}
}
