{
  "type": "Feature",
  "properties": {
    "date:inception_lower": "1995-07-01",
    "date:inception_upper": "1995-07-01",
    "iso:country": "GB",
    "wof:name": "WR5 2PL",
    "wof:placetype": "postalcode"
  },
  "geometry": {"coordinates":[-2.196851,52.163873],"type":"Point"}
}
