{
  "type": "Feature",
  "properties": {
    "iso:country": "GB",
    "wof:name": "WR5 2PL",
    "wof:placetype": "postalcode"
  },
  "geometry": {"coordinates":[-2.196851,52.163873],"type":"Point"}
}
