{
  "type": "Feature",
  "properties": {
    "iso:country":"GB",
    "wof:name":"IP26 5LJ",
    "wof:placetype":"postalcode"
},
  "geometry": {"coordinates":[0.58220289026422,52.54366025058132],"type":"Point"}
}