{
  "type": "Feature",
  "properties": {
    "date:inception_lower": "1980-01-01",
    "date:inception_upper": "1980-01-01",
    "iso:country": "GB",
    "wof:name": "TW18 4EN",
    "wof:placetype": "postalcode"
  },
  "geometry": {"coordinates":[-0.514717,51.434201],"type":"Point"}
}
