{
  "type": "Feature",
  "properties": {
    "iso:country": "GB",
    "wof:name": "RH20 4EN",
    "wof:placetype": "postalcode"
  },
  "geometry": {"coordinates":[-0.452903,50.914255],"type":"Point"}
}
