{
  "type": "Feature",
  "properties": {
    "iso:country":"GB",
    "wof:name":"RH20 4EN",
    "wof:placetype":"postalcode"
},
  "geometry": {"coordinates":[-0.45290333841447,50.91425522093529],"type":"Point"}
}