{
  "type": "Feature",
  "properties": {
    "iso:country":"GB",
    "wof:name":"BS16 9JE",
    "wof:placetype":"postalcode"
},
  "geometry": {"coordinates":[-2.48622537080199,51.48173822846707],"type":"Point"}
}