{
  "type": "Feature",
  "properties": {
    "iso:country":"GB",
    "wof:name":"DY12 1LJ",
    "wof:placetype":"postalcode"
},
  "geometry": {"coordinates":[-2.29161295830505,52.38225783106964],"type":"Point"}
}