{
  "type": "Feature",
  "properties": {
    "date:inception_lower":"2004-03-01",
    "date:inception_upper":"2004-03-31",
    "iso:country":"GB",
    "wof:name":"DN37 0RL",
    "wof:placetype":"postalcode"
},
  "geometry": {"coordinates":[-0.10959,53.499498],"type":"Point"}
}