{
  "type": "Feature",
  "properties": {
    "iso:country": "GB",
    "wof:name": "DN37 0RL",
    "wof:placetype": "postalcode"
  },
  "geometry": {"coordinates":[-0.10959,53.499498],"type":"Point"}
}
