{
  "type": "Feature",
  "properties": {
    "iso:country":"GB",
    "wof:name":"CM19 4QH",
    "wof:placetype":"postalcode"
},
  "geometry": {"coordinates":[0.08665353049452,51.74719205761664],"type":"Point"}
}