{
  "type": "Feature",
  "properties": {
    "iso:country":"GB",
    "wof:name":"S43 3AN",
    "wof:placetype":"postalcode"
},
  "geometry": {"coordinates":[-1.32693623202388,53.27540173019772],"type":"Point"}
}