{
  "type": "Feature",
  "properties": {
    "iso:country": "GB",
    "wof:name": "MK45 3HQ",
    "wof:placetype": "postalcode"
  },
  "geometry": {"coordinates":[-0.394487,52.064693],"type":"Point"}
}
