{
  "type": "Feature",
  "properties": {
    "date:inception_lower": "1994-05-01",
    "date:inception_upper": "1994-05-01",
    "iso:country": "GB",
    "wof:name": "MK45 3HQ",
    "wof:placetype": "postalcode"
  },
  "geometry": {"coordinates":[-0.394487,52.064693],"type":"Point"}
}
