{
  "type": "Feature",
  "properties": {
    "date:inception_lower": "2023-01-01",
    "date:inception_upper": "2023-01-01",
    "iso:country": "GB",
    "wof:name": "ST19 9FL",
    "wof:placetype": "postalcode"
  },
  "geometry": {"coordinates":[-2.215776,52.713596],"type":"Point"}
}
