{
  "type": "Feature",
  "properties": {
    "iso:country":"GB",
    "wof:name":"NG8 6FH",
    "wof:placetype":"postalcode"
},
  "geometry": {"coordinates":[-1.21256486700144,52.97739250380754],"type":"Point"}
}