{
  "type": "Feature",
  "properties": {
    "iso:country":"GB",
    "wof:name":"CH4 9EL",
    "wof:placetype":"postalcode"
},
  "geometry": {"coordinates":[-2.9299793802497,53.12960157936966],"type":"Point"}
}