{
  "type": "Feature",
  "properties": {
    "iso:country": "GB",
    "wof:name": "CH4 9EL",
    "wof:placetype": "postalcode"
  },
  "geometry": {"coordinates":[-2.929979,53.129602],"type":"Point"}
}
