{
  "type": "Feature",
  "properties": {
    "iso:country": "GB",
    "wof:name": "PO41 0AB",
    "wof:placetype": "postalcode"
  },
  "geometry": {"coordinates":[-1.465282,50.70957],"type":"Point"}
}
