{
  "type": "Feature",
  "properties": {
    "iso:country":"GB",
    "wof:name":"PO41 0AB",
    "wof:placetype":"postalcode"
},
  "geometry": {"coordinates":[-1.4652821439591,50.70956953857553],"type":"Point"}
}