{
  "type": "Feature",
  "properties": {
    "iso:country": "GB",
    "wof:name": "IP14 5FS",
    "wof:placetype": "postalcode"
  },
  "geometry": {"coordinates":[1.012444,52.191003],"type":"Point"}
}
