{
  "type": "Feature",
  "properties": {
    "iso:country":"GB",
    "wof:name":"CA14 3PU",
    "wof:placetype":"postalcode"
},
  "geometry": {"coordinates":[-3.54705331604595,54.6321902450086],"type":"Point"}
}