{
  "type": "Feature",
  "properties": {
    "date:inception_lower":"1999-06-01",
    "date:inception_upper":"1999-06-30",
    "iso:country":"GB",
    "wof:name":"NP25 5QA",
    "wof:placetype":"postalcode"
},
  "geometry": {"coordinates":[-2.752444,51.829612],"type":"Point"}
}