{
  "type": "Feature",
  "properties": {
    "iso:country":"GB",
    "wof:name":"NP25 5QA",
    "wof:placetype":"postalcode"
},
  "geometry": {"coordinates":[-2.75244416646676,51.82961177166923],"type":"Point"}
}