{
  "type": "Feature",
  "properties": {
    "iso:country":"GB",
    "wof:name":"W1J 7EZ",
    "wof:placetype":"postalcode"
},
  "geometry": {"coordinates":[-0.15057755220797,51.50458618833392],"type":"Point"}
}