{
  "type": "Feature",
  "properties": {
    "date:inception_lower": "2007-11-01",
    "date:inception_upper": "2007-11-01",
    "iso:country": "GB",
    "wof:name": "RG2 0GX",
    "wof:placetype": "postalcode"
  },
  "geometry": {"coordinates":[-0.975258,51.431209],"type":"Point"}
}
