{
  "type": "Feature",
  "properties": {
    "iso:country":"GB",
    "wof:name":"RG2 0GX",
    "wof:placetype":"postalcode"
},
  "geometry": {"coordinates":[-0.97525848536977,51.43120913053167],"type":"Point"}
}