{
  "type": "Feature",
  "properties": {
    "iso:country": "GB",
    "wof:name": "BS37 8SA",
    "wof:placetype": "postalcode"
  },
  "geometry": {"coordinates":[-2.427696,51.528839],"type":"Point"}
}
