{
  "type": "Feature",
  "properties": {
    "iso:country":"GB",
    "wof:name":"PA16 7NU",
    "wof:placetype":"postalcode"
},
  "geometry": {"coordinates":[-4.79464161673743,55.94635168652534],"type":"Point"}
}