{
  "type": "Feature",
  "properties": {
    "date:inception_lower": "2009-06-01",
    "date:inception_upper": "2009-06-01",
    "iso:country": "GB",
    "wof:name": "PA16 7NU",
    "wof:placetype": "postalcode"
  },
  "geometry": {"coordinates":[-4.794642,55.946352],"type":"Point"}
}
