{
  "type": "Feature",
  "properties": {
    "iso:country":"GB",
    "wof:name":"ME7 1NY",
    "wof:placetype":"postalcode"
},
  "geometry": {"coordinates":[0.55053638242683,51.39476895369714],"type":"Point"}
}