{
  "type": "Feature",
  "properties": {
    "iso:country": "GB",
    "wof:name": "NN6 8JE",
    "wof:placetype": "postalcode"
  },
  "geometry": {"coordinates":[-0.953819,52.324191],"type":"Point"}
}
