{
  "type": "Feature",
  "properties": {
    "iso:country": "GB",
    "wof:name": "IG8 9LA",
    "wof:placetype": "postalcode"
  },
  "geometry": {"coordinates":[0.018737,51.607619],"type":"Point"}
}
