{
  "type": "Feature",
  "properties": {
    "iso:country":"GB",
    "wof:name":"IG8 9LA",
    "wof:placetype":"postalcode"
},
  "geometry": {"coordinates":[0.01873719222346,51.60761926703619],"type":"Point"}
}