{
  "type": "Feature",
  "properties": {
    "date:inception_lower": "1980-01-01",
    "date:inception_upper": "1980-01-01",
    "iso:country": "GB",
    "wof:name": "BD18 2PP",
    "wof:placetype": "postalcode"
  },
  "geometry": {"coordinates":[-1.754762,53.837076],"type":"Point"}
}
