{
  "type": "Feature",
  "properties": {
    "date:inception_lower": "1980-01-01",
    "date:inception_upper": "1980-01-01",
    "iso:country": "GB",
    "wof:name": "GU29 0PN",
    "wof:placetype": "postalcode"
  },
  "geometry": {"coordinates":[-0.779426,51.017614],"type":"Point"}
}
