{
  "type": "Feature",
  "properties": {
    "iso:country": "GB",
    "wof:name": "DE15 9QP",
    "wof:placetype": "postalcode"
  },
  "geometry": {"coordinates":[-1.621758,52.787906],"type":"Point"}
}
