{
  "type": "Feature",
  "properties": {
    "date:inception_lower":"2007-11-01",
    "date:inception_upper":"2007-11-30",
    "iso:country":"GB",
    "wof:name":"LE67 3AS",
    "wof:placetype":"postalcode"
},
  "geometry": {"coordinates":[-1.370255,52.720467],"type":"Point"}
}