{
  "type": "Feature",
  "properties": {
    "iso:country":"GB",
    "wof:name":"B63 1BJ",
    "wof:placetype":"postalcode"
},
  "geometry": {"coordinates":[-2.07643016531799,52.44438199413545],"type":"Point"}
}