{
  "type": "Feature",
  "properties": {
    "date:inception_lower": "1980-01-01",
    "date:inception_upper": "1980-01-01",
    "iso:country": "GB",
    "wof:name": "RM10 7EJ",
    "wof:placetype": "postalcode"
  },
  "geometry": {"coordinates":[0.160014,51.555293],"type":"Point"}
}
