{
  "type": "Feature",
  "properties": {
    "iso:country":"GB",
    "wof:name":"WF3 3FF",
    "wof:placetype":"postalcode"
},
  "geometry": {"coordinates":[-1.52012183086108,53.7344694614474],"type":"Point"}
}