{
  "type": "Feature",
  "properties": {
    "iso:country":"GB",
    "wof:name":"DA7 4PX",
    "wof:placetype":"postalcode"
},
  "geometry": {"coordinates":[0.13502255048727,51.46702720766437],"type":"Point"}
}