{
  "type": "Feature",
  "properties": {
    "iso:country":"GB",
    "wof:name":"DN3 1BG",
    "wof:placetype":"postalcode"
},
  "geometry": {"coordinates":[-1.07019765099181,53.57825535079951],"type":"Point"}
}