{
  "type": "Feature",
  "properties": {
    "iso:country":"GB",
    "wof:name":"S36 4GW",
    "wof:placetype":"postalcode"
},
  "geometry": {"coordinates":[-1.64511978581156,53.49311966873064],"type":"Point"}
}