{
  "type": "Feature",
  "properties": {
    "date:inception_lower": "1997-06-01",
    "date:inception_upper": "1997-06-01",
    "iso:country": "GB",
    "wof:name": "S36 4GW",
    "wof:placetype": "postalcode"
  },
  "geometry": {"coordinates":[-1.64512,53.49312],"type":"Point"}
}
