{
  "type": "Feature",
  "properties": {
    "iso:country":"GB",
    "wof:name":"CV21 1DP",
    "wof:placetype":"postalcode"
},
  "geometry": {"coordinates":[-1.27145653603546,52.3866228974942],"type":"Point"}
}