{
  "type": "Feature",
  "properties": {
    "iso:country":"GB",
    "wof:name":"NG16 5PB",
    "wof:placetype":"postalcode"
},
  "geometry": {"coordinates":[-1.35302277479755,53.05696777658918],"type":"Point"}
}