{
  "type": "Feature",
  "properties": {
    "iso:country": "GB",
    "wof:name": "NG16 5PB",
    "wof:placetype": "postalcode"
  },
  "geometry": {"coordinates":[-1.353023,53.056968],"type":"Point"}
}
