{
  "type": "Feature",
  "properties": {
    "iso:country": "GB",
    "wof:name": "WR5 3RF",
    "wof:placetype": "postalcode"
  },
  "geometry": {"coordinates":[-2.2073,52.172423],"type":"Point"}
}
