{
  "type": "Feature",
  "properties": {
    "date:inception_lower": "1983-07-01",
    "date:inception_upper": "1983-07-01",
    "iso:country": "GB",
    "wof:name": "WR5 3RF",
    "wof:placetype": "postalcode"
  },
  "geometry": {"coordinates":[-2.2073,52.172423],"type":"Point"}
}
