{
  "type": "Feature",
  "properties": {
    "iso:country":"GB",
    "wof:name":"LE2 9GH",
    "wof:placetype":"postalcode"
},
  "geometry": {"coordinates":[-1.15644420489928,52.58874911023725],"type":"Point"}
}