{
  "type": "Feature",
  "properties": {
    "date:inception_lower": "2000-12-01",
    "date:inception_upper": "2000-12-01",
    "iso:country": "GB",
    "wof:name": "LE2 9GH",
    "wof:placetype": "postalcode"
  },
  "geometry": {"coordinates":[-1.156444,52.588749],"type":"Point"}
}
