{
  "type": "Feature",
  "properties": {
    "iso:country":"GB",
    "wof:name":"M16 7UH",
    "wof:placetype":"postalcode"
},
  "geometry": {"coordinates":[-2.25304576446675,53.4574953231722],"type":"Point"}
}