{
  "type": "Feature",
  "properties": {
    "iso:country":"GB",
    "wof:name":"B32 2ED",
    "wof:placetype":"postalcode"
},
  "geometry": {"coordinates":[-1.97621640637335,52.46093713082975],"type":"Point"}
}