{
  "type": "Feature",
  "properties": {
    "iso:country": "GB",
    "wof:name": "NE24 4TU",
    "wof:placetype": "postalcode"
  },
  "geometry": {"coordinates":[-1.537467,55.103704],"type":"Point"}
}
