{
  "type": "Feature",
  "properties": {
    "iso:country":"GB",
    "wof:name":"NG11 9FY",
    "wof:placetype":"postalcode"
},
  "geometry": {"coordinates":[-1.18732178697588,52.89394387341252],"type":"Point"}
}