{
  "type": "Feature",
  "properties": {
    "date:inception_lower": "1980-01-01",
    "date:inception_upper": "1980-01-01",
    "iso:country": "GB",
    "wof:name": "G21 3AU",
    "wof:placetype": "postalcode"
  },
  "geometry": {"coordinates":[-4.230158,55.89155],"type":"Point"}
}
