{
  "type": "Feature",
  "properties": {
    "iso:country":"GB",
    "wof:name":"DN35 0NH",
    "wof:placetype":"postalcode"
},
  "geometry": {"coordinates":[-0.009915673214,53.53826498134116],"type":"Point"}
}