{
  "type": "Feature",
  "properties": {
    "iso:country": "GB",
    "wof:name": "DN35 0NH",
    "wof:placetype": "postalcode"
  },
  "geometry": {"coordinates":[-0.009916,53.538265],"type":"Point"}
}
