{
  "type": "Feature",
  "properties": {
    "iso:country":"GB",
    "wof:name":"WS3 3HL",
    "wof:placetype":"postalcode"
},
  "geometry": {"coordinates":[-2.00226096478551,52.6159787129877],"type":"Point"}
}