{
  "type": "Feature",
  "properties": {
    "iso:country":"GB",
    "wof:name":"SS9 3JR",
    "wof:placetype":"postalcode"
},
  "geometry": {"coordinates":[0.66314644477888,51.54851889587542],"type":"Point"}
}