{
  "type": "Feature",
  "properties": {
    "iso:country":"GB",
    "wof:name":"N1C 4AE",
    "wof:placetype":"postalcode"
},
  "geometry": {"coordinates":[-0.12363856735613,51.53844674410667],"type":"Point"}
}