{
  "type": "Feature",
  "properties": {
    "date:inception_lower":"1980-01-01",
    "date:inception_upper":"1980-01-31",
    "iso:country":"GB",
    "wof:name":"CH2 1ES",
    "wof:placetype":"postalcode"
},
  "geometry": {"coordinates":[-2.88867,53.218632],"type":"Point"}
}