{
  "type": "Feature",
  "properties": {
    "iso:country":"GB",
    "wof:name":"CH2 1ES",
    "wof:placetype":"postalcode"
},
  "geometry": {"coordinates":[-2.88866958279028,53.21863160084365],"type":"Point"}
}