{
  "type": "Feature",
  "properties": {
    "iso:country": "GB",
    "wof:name": "WA10 5HW",
    "wof:placetype": "postalcode"
  },
  "geometry": {"coordinates":[-2.786158,53.458807],"type":"Point"}
}
