{
  "type": "Feature",
  "properties": {
    "iso:country":"GB",
    "wof:name":"WA10 5HW",
    "wof:placetype":"postalcode"
},
  "geometry": {"coordinates":[-2.78615784885553,53.4588072118278],"type":"Point"}
}