{
  "type": "Feature",
  "properties": {
    "date:inception_lower": "2021-01-01",
    "date:inception_upper": "2021-01-01",
    "iso:country": "GB",
    "wof:name": "EH15 1BL",
    "wof:placetype": "postalcode"
  },
  "geometry": {"coordinates":[-3.119629,55.954278],"type":"Point"}
}
