{
  "type": "Feature",
  "properties": {
    "iso:country": "GB",
    "wof:name": "LS12 4LW",
    "wof:placetype": "postalcode"
  },
  "geometry": {"coordinates":[-1.592012,53.790201],"type":"Point"}
}
