{
  "type": "Feature",
  "properties": {
    "iso:country":"GB",
    "wof:name":"LS12 4LW",
    "wof:placetype":"postalcode"
},
  "geometry": {"coordinates":[-1.59201210190078,53.79020101851923],"type":"Point"}
}