{
  "type": "Feature",
  "properties": {
    "date:inception_lower": "1980-01-01",
    "date:inception_upper": "1980-01-01",
    "iso:country": "GB",
    "wof:name": "CA4 9PW",
    "wof:placetype": "postalcode"
  },
  "geometry": {"coordinates":[-2.772217,54.810595],"type":"Point"}
}
