{
  "type": "Feature",
  "properties": {
    "date:inception_lower": "1980-01-01",
    "date:inception_upper": "1980-01-01",
    "iso:country": "GB",
    "wof:name": "KA6 5BY",
    "wof:placetype": "postalcode"
  },
  "geometry": {"coordinates":[-4.53354,55.49189],"type":"Point"}
}
