{
  "type": "Feature",
  "properties": {
    "iso:country":"GB",
    "wof:name":"KA6 5BY",
    "wof:placetype":"postalcode"
},
  "geometry": {"coordinates":[-4.53354041105679,55.49188953244469],"type":"Point"}
}