{
  "type": "Feature",
  "properties": {
    "iso:country":"GB",
    "wof:name":"PE19 7JU",
    "wof:placetype":"postalcode"
},
  "geometry": {"coordinates":[-0.28460155859012,52.22186214499305],"type":"Point"}
}