{
  "type": "Feature",
  "properties": {
    "iso:country": "GB",
    "wof:name": "SY21 9LP",
    "wof:placetype": "postalcode"
  },
  "geometry": {"coordinates":[-3.132912,52.705648],"type":"Point"}
}
