{
  "type": "Feature",
  "properties": {
    "iso:country":"GB",
    "wof:name":"WV1 1NT",
    "wof:placetype":"postalcode"
},
  "geometry": {"coordinates":[-2.12540637264631,52.59388714301016],"type":"Point"}
}