{
  "type": "Feature",
  "properties": {
    "iso:country":"GB",
    "wof:name":"TN27 8RB",
    "wof:placetype":"postalcode"
},
  "geometry": {"coordinates":[0.71834951174061,51.15187974662182],"type":"Point"}
}