{
  "type": "Feature",
  "properties": {
    "date:inception_lower": "1980-01-01",
    "date:inception_upper": "1980-01-01",
    "iso:country": "GB",
    "wof:name": "TN27 8RB",
    "wof:placetype": "postalcode"
  },
  "geometry": {"coordinates":[0.71835,51.15188],"type":"Point"}
}
