{
  "type": "Feature",
  "properties": {
    "iso:country":"GB",
    "wof:name":"LE5 6DW",
    "wof:placetype":"postalcode"
},
  "geometry": {"coordinates":[-1.07304059893598,52.62252187666061],"type":"Point"}
}