{
  "type": "Feature",
  "properties": {
    "iso:country":"GB",
    "wof:name":"SE26 5NR",
    "wof:placetype":"postalcode"
},
  "geometry": {"coordinates":[-0.05216583606492,51.42063801098931],"type":"Point"}
}