{
  "type": "Feature",
  "properties": {
    "iso:country":"GB",
    "wof:name":"TW8 8EZ",
    "wof:placetype":"postalcode"
},
  "geometry": {"coordinates":[-0.31052203519272,51.48151489833832],"type":"Point"}
}