{
  "type": "Feature",
  "properties": {
    "iso:country":"GB",
    "wof:name":"SR5 2RU",
    "wof:placetype":"postalcode"
},
  "geometry": {"coordinates":[-1.39617938543705,54.92132285865647],"type":"Point"}
}