{
  "type": "Feature",
  "properties": {
    "iso:country":"GB",
    "wof:name":"AL9 5DZ",
    "wof:placetype":"postalcode"
},
  "geometry": {"coordinates":[-0.21160857433148,51.77071423602947],"type":"Point"}
}