{
  "type": "Feature",
  "properties": {
    "iso:country":"GB",
    "wof:name":"GU22 7ER",
    "wof:placetype":"postalcode"
},
  "geometry": {"coordinates":[-0.54600278407391,51.32052628245303],"type":"Point"}
}