{
  "type": "Feature",
  "properties": {
    "iso:country":"GB",
    "wof:name":"KT3 3DG",
    "wof:placetype":"postalcode"
},
  "geometry": {"coordinates":[-0.26132817127192,51.40680578453157],"type":"Point"}
}