{
  "type": "Feature",
  "properties": {
    "date:inception_lower": "1983-03-01",
    "date:inception_upper": "1983-03-01",
    "iso:country": "GB",
    "wof:name": "HP12 3HF",
    "wof:placetype": "postalcode"
  },
  "geometry": {"coordinates":[-0.771,51.628938],"type":"Point"}
}
