{
  "type": "Feature",
  "properties": {
    "iso:country":"GB",
    "wof:name":"HP12 3HF",
    "wof:placetype":"postalcode"
},
  "geometry": {"coordinates":[-0.7710001859949,51.62893773327013],"type":"Point"}
}