{
  "type": "Feature",
  "properties": {
    "iso:country": "GB",
    "wof:name": "HP18 0FE",
    "wof:placetype": "postalcode"
  },
  "geometry": {"coordinates":[-0.857976,51.833157],"type":"Point"}
}
