{
  "type": "Feature",
  "properties": {
    "iso:country": "GB",
    "wof:name": "BN16 4FQ",
    "wof:placetype": "postalcode"
  },
  "geometry": {"coordinates":[-0.481891,50.823806],"type":"Point"}
}
