{
  "type": "Feature",
  "properties": {
    "iso:country":"GB",
    "wof:name":"PL10 1PN",
    "wof:placetype":"postalcode"
},
  "geometry": {"coordinates":[-4.20347418328233,50.33129689650004],"type":"Point"}
}