{
  "type": "Feature",
  "properties": {
    "date:inception_lower":"1980-01-01",
    "date:inception_upper":"1980-01-31",
    "iso:country":"GB",
    "wof:name":"WF13 3BT",
    "wof:placetype":"postalcode"
},
  "geometry": {"coordinates":[-1.662335,53.680576],"type":"Point"}
}