{
  "type": "Feature",
  "properties": {
    "iso:country":"GB",
    "wof:name":"WF13 3BT",
    "wof:placetype":"postalcode"
},
  "geometry": {"coordinates":[-1.66233534936886,53.68057597061764],"type":"Point"}
}