{
  "type": "Feature",
  "properties": {
    "iso:country": "GB",
    "wof:name": "YO8 9JE",
    "wof:placetype": "postalcode"
  },
  "geometry": {"coordinates":[-1.167031,53.767843],"type":"Point"}
}
