{
  "type": "Feature",
  "properties": {
    "iso:country":"GB",
    "wof:name":"YO8 9JE",
    "wof:placetype":"postalcode"
},
  "geometry": {"coordinates":[-1.16705458547074,53.767941352243],"type":"Point"}
}