{
  "type": "Feature",
  "properties": {
    "iso:country":"GB",
    "wof:name":"GL7 4DB",
    "wof:placetype":"postalcode"
},
  "geometry": {"coordinates":[-1.78681260496282,51.70677078811308],"type":"Point"}
}