{
  "type": "Feature",
  "properties": {
    "iso:country":"GB",
    "wof:name":"HS3 3DZ",
    "wof:placetype":"postalcode"
},
  "geometry": {"coordinates":[-6.80539354621816,57.86754601634981],"type":"Point"}
}