{
  "type": "Feature",
  "properties": {
    "iso:country": "GB",
    "wof:name": "CA6 5SS",
    "wof:placetype": "postalcode"
  },
  "geometry": {"coordinates":[-2.950267,54.983985],"type":"Point"}
}
