{
  "type": "Feature",
  "properties": {
    "date:inception_lower": "2023-06-01",
    "date:inception_upper": "2023-06-01",
    "iso:country": "GB",
    "wof:name": "YO25 6UQ",
    "wof:placetype": "postalcode"
  },
  "geometry": {"coordinates":[-0.445086,54.005915],"type":"Point"}
}
