{
  "type": "Feature",
  "properties": {
    "iso:country":"GB",
    "wof:name":"WF2 8FF",
    "wof:placetype":"postalcode"
},
  "geometry": {"coordinates":[-1.52409625405307,53.67243083645077],"type":"Point"}
}