{
  "type": "Feature",
  "properties": {
    "iso:country": "GB",
    "wof:name": "WF2 8FF",
    "wof:placetype": "postalcode"
  },
  "geometry": {"coordinates":[-1.506628,53.67652],"type":"Point"}
}
