{
  "type": "Feature",
  "properties": {
    "date:inception_lower":"2015-11-01",
    "date:inception_upper":"2015-11-30",
    "iso:country":"GB",
    "wof:name":"WF2 8FF",
    "wof:placetype":"postalcode"
},
  "geometry": {"coordinates":[-1.506628,53.67652],"type":"Point"}
}