{
  "type": "Feature",
  "properties": {
    "date:inception_lower":"1980-01-01",
    "date:inception_upper":"1980-01-31",
    "iso:country":"GB",
    "wof:name":"DH3 4EN",
    "wof:placetype":"postalcode"
},
  "geometry": {"coordinates":[-1.563433,54.818811],"type":"Point"}
}