{
  "type": "Feature",
  "properties": {
    "iso:country": "GB",
    "wof:name": "DH3 4EN",
    "wof:placetype": "postalcode"
  },
  "geometry": {"coordinates":[-1.563433,54.818811],"type":"Point"}
}
