{
  "type": "Feature",
  "properties": {
    "iso:country":"GB",
    "wof:name":"DH3 4EN",
    "wof:placetype":"postalcode"
},
  "geometry": {"coordinates":[-1.56343275406416,54.81881110343339],"type":"Point"}
}