{
  "type": "Feature",
  "properties": {
    "iso:country":"GB",
    "wof:name":"DH1 4GE",
    "wof:placetype":"postalcode"
},
  "geometry": {"coordinates":[-1.59085535534859,54.78473080799222],"type":"Point"}
}