{
  "type": "Feature",
  "properties": {
    "iso:country":"GB",
    "wof:name":"PR5 4LB",
    "wof:placetype":"postalcode"
},
  "geometry": {"coordinates":[-2.6762238235258,53.74319122738913],"type":"Point"}
}