{
  "type": "Feature",
  "properties": {
    "iso:country":"GB",
    "wof:name":"M32 9DH",
    "wof:placetype":"postalcode"
},
  "geometry": {"coordinates":[-2.32614889235078,53.44588458567453],"type":"Point"}
}