{
  "type": "Feature",
  "properties": {
    "date:inception_lower": "1980-01-01",
    "date:inception_upper": "1980-01-01",
    "iso:country": "GB",
    "wof:name": "M32 9DH",
    "wof:placetype": "postalcode"
  },
  "geometry": {"coordinates":[-2.326149,53.445885],"type":"Point"}
}
