{
  "type": "Feature",
  "properties": {
    "iso:country": "GB",
    "wof:name": "DT11 8UQ",
    "wof:placetype": "postalcode"
  },
  "geometry": {"coordinates":[-2.135248,50.883346],"type":"Point"}
}
