{
  "type": "Feature",
  "properties": {
    "date:inception_lower": "1990-02-01",
    "date:inception_upper": "1990-02-01",
    "iso:country": "GB",
    "wof:name": "BD23 1PG",
    "wof:placetype": "postalcode"
  },
  "geometry": {"coordinates":[-2.024578,53.96051],"type":"Point"}
}
