{
  "type": "Feature",
  "properties": {
    "iso:country":"GB",
    "wof:name":"BD23 1PG",
    "wof:placetype":"postalcode"
},
  "geometry": {"coordinates":[-2.02457774919578,53.96051003295543],"type":"Point"}
}