{
  "type": "Feature",
  "properties": {
    "iso:country": "GB",
    "wof:name": "NP16 6NB",
    "wof:placetype": "postalcode"
  },
  "geometry": {"coordinates":[-2.749473,51.688109],"type":"Point"}
}
