{
  "type": "Feature",
  "properties": {
    "date:inception_lower": "1999-06-01",
    "date:inception_upper": "1999-06-01",
    "iso:country": "GB",
    "wof:name": "NP16 6NB",
    "wof:placetype": "postalcode"
  },
  "geometry": {"coordinates":[-2.749473,51.688109],"type":"Point"}
}
