{
  "type": "Feature",
  "properties": {
    "iso:country":"GB",
    "wof:name":"SO51 7PA",
    "wof:placetype":"postalcode"
},
  "geometry": {"coordinates":[-1.47208520300311,50.99871068763056],"type":"Point"}
}