{
  "type": "Feature",
  "properties": {
    "date:inception_lower": "2021-04-01",
    "date:inception_upper": "2021-04-01",
    "iso:country": "GB",
    "wof:name": "GU12 5RU",
    "wof:placetype": "postalcode"
  },
  "geometry": {"coordinates":[-0.72369,51.275018],"type":"Point"}
}
