{
  "type": "Feature",
  "properties": {
    "iso:country": "GB",
    "wof:name": "NR32 1UY",
    "wof:placetype": "postalcode"
  },
  "geometry": {"coordinates":[1.755859,52.489046],"type":"Point"}
}
