{
  "type": "Feature",
  "properties": {
    "iso:country":"GB",
    "wof:name":"NR32 1UY",
    "wof:placetype":"postalcode"
},
  "geometry": {"coordinates":[1.75585879549748,52.48904635413938],"type":"Point"}
}