{
  "type": "Feature",
  "properties": {
    "date:inception_lower": "1980-01-01",
    "date:inception_upper": "1980-01-01",
    "iso:country": "GB",
    "wof:name": "NR32 1UY",
    "wof:placetype": "postalcode"
  },
  "geometry": {"coordinates":[1.755884,52.489072],"type":"Point"}
}
