{
  "type": "Feature",
  "properties": {
    "iso:country":"GB",
    "wof:name":"BL2 3QX",
    "wof:placetype":"postalcode"
},
  "geometry": {"coordinates":[-2.39254374063114,53.59727468778024],"type":"Point"}
}