{
  "type": "Feature",
  "properties": {
    "iso:country":"GB",
    "wof:name":"L36 6BN",
    "wof:placetype":"postalcode"
},
  "geometry": {"coordinates":[-2.81727593457433,53.40715560170977],"type":"Point"}
}