{
  "type": "Feature",
  "properties": {
    "date:inception_lower":"1980-01-01",
    "date:inception_upper":"1980-01-31",
    "iso:country":"GB",
    "wof:name":"L36 6BN",
    "wof:placetype":"postalcode"
},
  "geometry": {"coordinates":[-2.817276,53.407156],"type":"Point"}
}