{
  "type": "Feature",
  "properties": {
    "date:inception_lower": "2024-07-01",
    "date:inception_upper": "2024-07-01",
    "iso:country": "GB",
    "wof:name": "ME1 3ZL",
    "wof:placetype": "postalcode"
  },
  "geometry": {"coordinates":[0.455538,51.3405],"type":"Point"}
}
