{
  "type": "Feature",
  "properties": {
    "date:inception_lower": "1980-01-01",
    "date:inception_upper": "1980-01-01",
    "iso:country": "GB",
    "wof:name": "RM12 5HH",
    "wof:placetype": "postalcode"
  },
  "geometry": {"coordinates":[0.200393,51.539471],"type":"Point"}
}
