{
  "type": "Feature",
  "properties": {
    "iso:country":"GB",
    "wof:name":"RM12 5HH",
    "wof:placetype":"postalcode"
},
  "geometry": {"coordinates":[0.20039284057674,51.53947064101195],"type":"Point"}
}