{
  "type": "Feature",
  "properties": {
    "iso:country":"GB",
    "wof:name":"CH43 9XW",
    "wof:placetype":"postalcode"
},
  "geometry": {"coordinates":[-3.08357954900865,53.39234293271347],"type":"Point"}
}