{
  "type": "Feature",
  "properties": {
    "date:inception_lower": "1980-01-01",
    "date:inception_upper": "1980-01-01",
    "iso:country": "GB",
    "wof:name": "RM7 0YH",
    "wof:placetype": "postalcode"
  },
  "geometry": {"coordinates":[0.179825,51.557834],"type":"Point"}
}
