{
  "type": "Feature",
  "properties": {
    "iso:country": "GB",
    "wof:name": "RM7 0YH",
    "wof:placetype": "postalcode"
  },
  "geometry": {"coordinates":[0.179711,51.557825],"type":"Point"}
}
