{
  "type": "Feature",
  "properties": {
    "iso:country":"GB",
    "wof:name":"NR6 5PQ",
    "wof:placetype":"postalcode"
},
  "geometry": {"coordinates":[1.26496740447355,52.66151792988301],"type":"Point"}
}