{
  "type": "Feature",
  "properties": {
    "iso:country": "GB",
    "wof:name": "NR6 5PQ",
    "wof:placetype": "postalcode"
  },
  "geometry": {"coordinates":[1.264967,52.661518],"type":"Point"}
}
