{
  "type": "Feature",
  "properties": {
    "date:inception_lower": "1980-01-01",
    "date:inception_upper": "1980-01-01",
    "iso:country": "GB",
    "wof:name": "NR6 5PQ",
    "wof:placetype": "postalcode"
  },
  "geometry": {"coordinates":[1.264967,52.661518],"type":"Point"}
}
