{
  "type": "Feature",
  "properties": {
    "iso:country": "GB",
    "wof:name": "S81 8UH",
    "wof:placetype": "postalcode"
  },
  "geometry": {"coordinates":[-1.14404,53.324208],"type":"Point"}
}
