{
  "type": "Feature",
  "properties": {
    "iso:country":"GB",
    "wof:name":"NE3 5BT",
    "wof:placetype":"postalcode"
},
  "geometry": {"coordinates":[-1.61612333725529,55.01270773955835],"type":"Point"}
}