{
  "type": "Feature",
  "properties": {
    "date:inception_lower":"1980-01-01",
    "date:inception_upper":"1980-01-31",
    "iso:country":"GB",
    "wof:name":"NE48 3BL",
    "wof:placetype":"postalcode"
},
  "geometry": {"coordinates":[-2.284032,55.118279],"type":"Point"}
}