{
  "type": "Feature",
  "properties": {
    "iso:country":"GB",
    "wof:name":"KT16 0ER",
    "wof:placetype":"postalcode"
},
  "geometry": {"coordinates":[-0.56744801034373,51.36135490609626],"type":"Point"}
}