{
  "type": "Feature",
  "properties": {
    "iso:country":"GB",
    "wof:name":"S72 7JX",
    "wof:placetype":"postalcode"
},
  "geometry": {"coordinates":[-1.372050856811,53.5733256955024],"type":"Point"}
}