{
  "type": "Feature",
  "properties": {
    "iso:country":"GB",
    "wof:name":"NW10 0EU",
    "wof:placetype":"postalcode"
},
  "geometry": {"coordinates":[-0.25582427098448,51.56262556212963],"type":"Point"}
}