{
  "type": "Feature",
  "properties": {
    "iso:country":"GB",
    "wof:name":"G21 3PE",
    "wof:placetype":"postalcode"
},
  "geometry": {"coordinates":[-4.19887772223545,55.89780176645002],"type":"Point"}
}