{
  "type": "Feature",
  "properties": {
    "iso:country":"GB",
    "wof:name":"CA7 9LB",
    "wof:placetype":"postalcode"
},
  "geometry": {"coordinates":[-3.15623922372089,54.81574847936032],"type":"Point"}
}