{
  "type": "Feature",
  "properties": {
    "date:inception_lower": "1980-01-01",
    "date:inception_upper": "1980-01-01",
    "iso:country": "GB",
    "wof:name": "ST9 0BP",
    "wof:placetype": "postalcode"
  },
  "geometry": {"coordinates":[-2.076578,53.035454],"type":"Point"}
}
