{
  "type": "Feature",
  "properties": {
    "date:inception_lower":"1980-01-01",
    "date:inception_upper":"1980-01-31",
    "iso:country":"GB",
    "wof:name":"ST9 0BP",
    "wof:placetype":"postalcode"
},
  "geometry": {"coordinates":[-2.076565,53.035428],"type":"Point"}
}