{
  "type": "Feature",
  "properties": {
    "iso:country":"GB",
    "wof:name":"LL40 1UU",
    "wof:placetype":"postalcode"
},
  "geometry": {"coordinates":[-3.89019784326382,52.74275987397562],"type":"Point"}
}