{
  "type": "Feature",
  "properties": {
    "date:inception_lower": "1980-01-01",
    "date:inception_upper": "1980-01-01",
    "iso:country": "GB",
    "wof:name": "LL40 1UU",
    "wof:placetype": "postalcode"
  },
  "geometry": {"coordinates":[-3.890198,52.74276],"type":"Point"}
}
