{
  "type": "Feature",
  "properties": {
    "date:inception_lower":"1980-01-01",
    "date:inception_upper":"1980-01-31",
    "iso:country":"GB",
    "wof:name":"W12 9BL",
    "wof:placetype":"postalcode"
},
  "geometry": {"coordinates":[-0.243371,51.502766],"type":"Point"}
}