{
  "type": "Feature",
  "properties": {
    "iso:country": "GB",
    "wof:name": "B23 6EL",
    "wof:placetype": "postalcode"
  },
  "geometry": {"coordinates":[-1.846307,52.523293],"type":"Point"}
}
