{
  "type": "Feature",
  "properties": {
    "iso:country":"GB",
    "wof:name":"B23 6EL",
    "wof:placetype":"postalcode"
},
  "geometry": {"coordinates":[-1.84630679493567,52.52329313640485],"type":"Point"}
}