{
  "type": "Feature",
  "properties": {
    "iso:country": "GB",
    "wof:name": "CB24 9XR",
    "wof:placetype": "postalcode"
  },
  "geometry": {"coordinates":[0.108688,52.257365],"type":"Point"}
}
