{
  "type": "Feature",
  "properties": {
    "date:inception_lower":"1980-01-01",
    "date:inception_upper":"1980-01-31",
    "iso:country":"GB",
    "wof:name":"PA16 7AP",
    "wof:placetype":"postalcode"
},
  "geometry": {"coordinates":[-4.793836,55.952285],"type":"Point"}
}