{
  "type": "Feature",
  "properties": {
    "iso:country":"GB",
    "wof:name":"PA16 7AP",
    "wof:placetype":"postalcode"
},
  "geometry": {"coordinates":[-4.79383572961733,55.95228456399644],"type":"Point"}
}