{
  "type": "Feature",
  "properties": {
    "date:inception_lower": "1991-01-01",
    "date:inception_upper": "1991-01-01",
    "iso:country": "GB",
    "wof:name": "RH10 7RR",
    "wof:placetype": "postalcode"
  },
  "geometry": {"coordinates":[-0.144836,51.114469],"type":"Point"}
}
