{
  "type": "Feature",
  "properties": {
    "iso:country":"GB",
    "wof:name":"RH10 7RR",
    "wof:placetype":"postalcode"
},
  "geometry": {"coordinates":[-0.14483651062451,51.11446949666099],"type":"Point"}
}