{
  "type": "Feature",
  "properties": {
    "iso:country":"GB",
    "wof:name":"LD6 5LB",
    "wof:placetype":"postalcode"
},
  "geometry": {"coordinates":[-3.51522651038224,52.30575740895881],"type":"Point"}
}