{
  "type": "Feature",
  "properties": {
    "iso:country":"GB",
    "wof:name":"NG1 1HW",
    "wof:placetype":"postalcode"
},
  "geometry": {"coordinates":[-1.14257035158874,52.95091082411775],"type":"Point"}
}