{
  "type": "Feature",
  "properties": {
    "iso:country":"GB",
    "wof:name":"SR4 6SJ",
    "wof:placetype":"postalcode"
},
  "geometry": {"coordinates":[-1.43031818836987,54.91015569364328],"type":"Point"}
}