{
  "type": "Feature",
  "properties": {
    "date:inception_lower": "1981-06-01",
    "date:inception_upper": "1981-06-01",
    "iso:country": "GB",
    "wof:name": "SR4 6SJ",
    "wof:placetype": "postalcode"
  },
  "geometry": {"coordinates":[-1.429159,54.909269],"type":"Point"}
}
