{
  "type": "Feature",
  "properties": {
    "date:inception_lower":"2018-07-01",
    "date:inception_upper":"2018-07-31",
    "iso:country":"GB",
    "wof:name":"BH23 9GX",
    "wof:placetype":"postalcode"
},
  "geometry": {"coordinates":[-1.782094,50.739933],"type":"Point"}
}