{
  "type": "Feature",
  "properties": {
    "date:inception_lower": "2003-10-01",
    "date:inception_upper": "2003-10-01",
    "iso:country": "GB",
    "wof:name": "W2 6DN",
    "wof:placetype": "postalcode"
  },
  "geometry": {"coordinates":[-0.179972,51.519794],"type":"Point"}
}
