{
  "type": "Feature",
  "properties": {
    "iso:country":"GB",
    "wof:name":"W2 6DN",
    "wof:placetype":"postalcode"
},
  "geometry": {"coordinates":[-0.17997162404241,51.5197936611544],"type":"Point"}
}