{
  "type": "Feature",
  "properties": {
    "iso:country":"GB",
    "wof:name":"TN17 1LY",
    "wof:placetype":"postalcode"
},
  "geometry": {"coordinates":[0.47667700180505,51.12719196387608],"type":"Point"}
}