{
  "type": "Feature",
  "properties": {
    "iso:country":"GB",
    "wof:name":"B76 9QD",
    "wof:placetype":"postalcode"
},
  "geometry": {"coordinates":[-1.74687965919712,52.54905834117304],"type":"Point"}
}