{
  "type": "Feature",
  "properties": {
    "iso:country": "GB",
    "wof:name": "B76 9QD",
    "wof:placetype": "postalcode"
  },
  "geometry": {"coordinates":[-1.74688,52.549058],"type":"Point"}
}
