{
  "type": "Feature",
  "properties": {
    "iso:country":"GB",
    "wof:name":"IG11 7AZ",
    "wof:placetype":"postalcode"
},
  "geometry": {"coordinates":[0.07363845880056,51.53419004661264],"type":"Point"}
}