{
  "type": "Feature",
  "properties": {
    "iso:country": "GB",
    "wof:name": "IG11 7AZ",
    "wof:placetype": "postalcode"
  },
  "geometry": {"coordinates":[0.073639,51.53419],"type":"Point"}
}
