{
  "type": "Feature",
  "properties": {
    "iso:country":"GB",
    "wof:name":"SN7 8RL",
    "wof:placetype":"postalcode"
},
  "geometry": {"coordinates":[-1.45189634496313,51.68719155084527],"type":"Point"}
}