{
  "type": "Feature",
  "properties": {
    "iso:country": "GB",
    "wof:name": "SN7 8RL",
    "wof:placetype": "postalcode"
  },
  "geometry": {"coordinates":[-1.451896,51.687192],"type":"Point"}
}
