{
  "type": "Feature",
  "properties": {
    "date:inception_lower": "1980-01-01",
    "date:inception_upper": "1980-01-01",
    "iso:country": "GB",
    "wof:name": "HP3 9UJ",
    "wof:placetype": "postalcode"
  },
  "geometry": {"coordinates":[-0.44812,51.739312],"type":"Point"}
}
