{
  "type": "Feature",
  "properties": {
    "iso:country":"GB",
    "wof:name":"CW3 0HG",
    "wof:placetype":"postalcode"
},
  "geometry": {"coordinates":[-2.50519340354747,52.99407992059052],"type":"Point"}
}