{
  "type": "Feature",
  "properties": {
    "iso:country": "GB",
    "wof:name": "CW3 0HG",
    "wof:placetype": "postalcode"
  },
  "geometry": {"coordinates":[-2.505223,52.994024],"type":"Point"}
}
