{
  "type": "Feature",
  "properties": {
    "date:inception_lower": "2008-12-01",
    "date:inception_upper": "2008-12-01",
    "iso:country": "GB",
    "wof:name": "CO4 5TZ",
    "wof:placetype": "postalcode"
  },
  "geometry": {"coordinates":[0.91789,51.923933],"type":"Point"}
}
