{
  "type": "Feature",
  "properties": {
    "iso:country": "GB",
    "wof:name": "CO4 5TZ",
    "wof:placetype": "postalcode"
  },
  "geometry": {"coordinates":[0.91789,51.923933],"type":"Point"}
}
