{
  "type": "Feature",
  "properties": {
    "iso:country":"GB",
    "wof:name":"CO4 5TZ",
    "wof:placetype":"postalcode"
},
  "geometry": {"coordinates":[0.91785885137388,51.92392114311999],"type":"Point"}
}