{
  "type": "Feature",
  "properties": {
    "date:inception_lower":"1984-02-01",
    "date:inception_upper":"1984-02-29",
    "iso:country":"GB",
    "wof:name":"NE25 0PG",
    "wof:placetype":"postalcode"
},
  "geometry": {"coordinates":[-1.519022,55.064465],"type":"Point"}
}