{
  "type": "Feature",
  "properties": {
    "iso:country":"GB",
    "wof:name":"CF38 2JL",
    "wof:placetype":"postalcode"
},
  "geometry": {"coordinates":[-3.3590054512587,51.54910759816015],"type":"Point"}
}