{
  "type": "Feature",
  "properties": {
    "date:inception_lower": "1994-05-01",
    "date:inception_upper": "1994-05-01",
    "iso:country": "GB",
    "wof:name": "CF38 2JL",
    "wof:placetype": "postalcode"
  },
  "geometry": {"coordinates":[-3.359005,51.549108],"type":"Point"}
}
