{
  "type": "Feature",
  "properties": {
    "iso:country":"GB",
    "wof:name":"TS26 8DS",
    "wof:placetype":"postalcode"
},
  "geometry": {"coordinates":[-1.22189608874703,54.68602161352054],"type":"Point"}
}