{
  "type": "Feature",
  "properties": {
    "iso:country": "GB",
    "wof:name": "TS26 8DS",
    "wof:placetype": "postalcode"
  },
  "geometry": {"coordinates":[-1.221896,54.686022],"type":"Point"}
}
