{
  "type": "Feature",
  "properties": {
    "date:inception_lower": "1980-01-01",
    "date:inception_upper": "1980-01-01",
    "iso:country": "GB",
    "wof:name": "TS26 8DS",
    "wof:placetype": "postalcode"
  },
  "geometry": {"coordinates":[-1.221896,54.686022],"type":"Point"}
}
