{
  "type": "Feature",
  "properties": {
    "iso:country":"GB",
    "wof:name":"EX23 8QX",
    "wof:placetype":"postalcode"
},
  "geometry": {"coordinates":[-4.54426445896841,50.82912125194063],"type":"Point"}
}