{
  "type": "Feature",
  "properties": {
    "iso:country":"GB",
    "wof:name":"EX6 7JD",
    "wof:placetype":"postalcode"
},
  "geometry": {"coordinates":[-3.66047755439005,50.66338636731156],"type":"Point"}
}