{
  "type": "Feature",
  "properties": {
    "iso:country": "GB",
    "wof:name": "EX6 7JD",
    "wof:placetype": "postalcode"
  },
  "geometry": {"coordinates":[-3.660662,50.663356],"type":"Point"}
}
