{
  "type": "Feature",
  "properties": {
    "iso:country":"GB",
    "wof:name":"TS9 6PP",
    "wof:placetype":"postalcode"
},
  "geometry": {"coordinates":[-1.16143939871339,54.49796830044955],"type":"Point"}
}