{
  "type": "Feature",
  "properties": {
    "iso:country":"GB",
    "wof:name":"CF44 8PD",
    "wof:placetype":"postalcode"
},
  "geometry": {"coordinates":[-3.45565460412527,51.72337138130234],"type":"Point"}
}