{
  "type": "Feature",
  "properties": {
    "iso:country": "GB",
    "wof:name": "CF44 8PD",
    "wof:placetype": "postalcode"
  },
  "geometry": {"coordinates":[-3.455655,51.723371],"type":"Point"}
}
