{
  "type": "Feature",
  "properties": {
    "date:inception_lower": "1980-01-01",
    "date:inception_upper": "1980-01-01",
    "iso:country": "GB",
    "wof:name": "KT21 2UD",
    "wof:placetype": "postalcode"
  },
  "geometry": {"coordinates":[-0.296912,51.304633],"type":"Point"}
}
