{
  "type": "Feature",
  "properties": {
    "iso:country":"GB",
    "wof:name":"KT21 2UD",
    "wof:placetype":"postalcode"
},
  "geometry": {"coordinates":[-0.29691172206105,51.30463329563631],"type":"Point"}
}