{
  "type": "Feature",
  "properties": {
    "date:inception_lower": "1985-04-01",
    "date:inception_upper": "1985-04-01",
    "iso:country": "GB",
    "wof:name": "B26 3HG",
    "wof:placetype": "postalcode"
  },
  "geometry": {"coordinates":[-1.786649,52.455452],"type":"Point"}
}
