{
  "type": "Feature",
  "properties": {
    "iso:country": "GB",
    "wof:name": "NE42 5BS",
    "wof:placetype": "postalcode"
  },
  "geometry": {"coordinates":[-1.83284,54.955029],"type":"Point"}
}
