{
  "type": "Feature",
  "properties": {
    "iso:country":"GB",
    "wof:name":"SY7 0HP",
    "wof:placetype":"postalcode"
},
  "geometry": {"coordinates":[-2.97599107233077,52.42638859195831],"type":"Point"}
}