{
  "type": "Feature",
  "properties": {
    "iso:country":"GB",
    "wof:name":"B66 3BS",
    "wof:placetype":"postalcode"
},
  "geometry": {"coordinates":[-1.967833243096,52.49342489150305],"type":"Point"}
}