{
  "type": "Feature",
  "properties": {
    "date:inception_lower": "1980-01-01",
    "date:inception_upper": "1980-01-01",
    "iso:country": "GB",
    "wof:name": "SN14 8QS",
    "wof:placetype": "postalcode"
  },
  "geometry": {"coordinates":[-2.265583,51.44048],"type":"Point"}
}
