{
  "type": "Feature",
  "properties": {
    "iso:country": "GB",
    "wof:name": "IV55 8ZE",
    "wof:placetype": "postalcode"
  },
  "geometry": {"coordinates":[-6.526152,57.40589],"type":"Point"}
}
