{
  "type": "Feature",
  "properties": {
    "iso:country":"GB",
    "wof:name":"IV55 8ZE",
    "wof:placetype":"postalcode"
},
  "geometry": {"coordinates":[-6.52615203922751,57.40588955681626],"type":"Point"}
}