{
  "type": "Feature",
  "properties": {
    "iso:country":"GB",
    "wof:name":"DY3 2NX",
    "wof:placetype":"postalcode"
},
  "geometry": {"coordinates":[-2.12577737213942,52.51735617409826],"type":"Point"}
}