{
  "type": "Feature",
  "properties": {
    "iso:country":"GB",
    "wof:name":"SW6 5AU",
    "wof:placetype":"postalcode"
},
  "geometry": {"coordinates":[-0.20720787161605,51.47662668918457],"type":"Point"}
}