{
  "type": "Feature",
  "properties": {
    "iso:country": "GB",
    "wof:name": "SW6 5AU",
    "wof:placetype": "postalcode"
  },
  "geometry": {"coordinates":[-0.207102,51.476527],"type":"Point"}
}
