{
  "type": "Feature",
  "properties": {
    "iso:country":"GB",
    "wof:name":"L39 8SF",
    "wof:placetype":"postalcode"
},
  "geometry": {"coordinates":[-2.96353223993925,53.60500413933577],"type":"Point"}
}