{
  "type": "Feature",
  "properties": {
    "date:inception_lower": "2002-06-01",
    "date:inception_upper": "2002-06-01",
    "iso:country": "GB",
    "wof:name": "IP14 5QW",
    "wof:placetype": "postalcode"
  },
  "geometry": {"coordinates":[1.015339,52.18556],"type":"Point"}
}
