{
  "type": "Feature",
  "properties": {
    "iso:country":"GB",
    "wof:name":"IP14 5QW",
    "wof:placetype":"postalcode"
},
  "geometry": {"coordinates":[1.0150096811579,52.18568626595759],"type":"Point"}
}