{
  "type": "Feature",
  "properties": {
    "iso:country": "GB",
    "wof:name": "IP14 5QW",
    "wof:placetype": "postalcode"
  },
  "geometry": {"coordinates":[1.01501,52.185686],"type":"Point"}
}
