{
  "type": "Feature",
  "properties": {
    "date:inception_lower":"2002-06-01",
    "date:inception_upper":"2002-06-30",
    "iso:country":"GB",
    "wof:name":"IP14 5QW",
    "wof:placetype":"postalcode"
},
  "geometry": {"coordinates":[1.01501,52.185686],"type":"Point"}
}