{
  "type": "Feature",
  "properties": {
    "iso:country":"GB",
    "wof:name":"NR35 2PE",
    "wof:placetype":"postalcode"
},
  "geometry": {"coordinates":[1.45216086605666,52.46702589103581],"type":"Point"}
}