{
  "type": "Feature",
  "properties": {
    "date:inception_lower": "1980-01-01",
    "date:inception_upper": "1980-01-01",
    "iso:country": "GB",
    "wof:name": "NR35 2PE",
    "wof:placetype": "postalcode"
  },
  "geometry": {"coordinates":[1.452161,52.467026],"type":"Point"}
}
