{
  "type": "Feature",
  "properties": {
    "iso:country":"GB",
    "wof:name":"DN22 8AN",
    "wof:placetype":"postalcode"
},
  "geometry": {"coordinates":[-0.96777405480676,53.27153998530505],"type":"Point"}
}