{
  "type": "Feature",
  "properties": {
    "iso:country": "GB",
    "wof:name": "DN22 8AN",
    "wof:placetype": "postalcode"
  },
  "geometry": {"coordinates":[-0.967603,53.271757],"type":"Point"}
}
