{
  "type": "Feature",
  "properties": {
    "iso:country":"GB",
    "wof:name":"GL1 3BB",
    "wof:placetype":"postalcode"
},
  "geometry": {"coordinates":[-2.24052693232767,51.87486730179072],"type":"Point"}
}