{
  "type": "Feature",
  "properties": {
    "iso:country":"GB",
    "wof:name":"TA5 1HZ",
    "wof:placetype":"postalcode"
},
  "geometry": {"coordinates":[-3.1216284005129,51.14877263472184],"type":"Point"}
}