{
  "type": "Feature",
  "properties": {
    "date:inception_lower": "1980-01-01",
    "date:inception_upper": "1980-01-01",
    "iso:country": "GB",
    "wof:name": "TA5 1HZ",
    "wof:placetype": "postalcode"
  },
  "geometry": {"coordinates":[-3.122736,51.149244],"type":"Point"}
}
