{
  "type": "Feature",
  "properties": {
    "iso:country": "GB",
    "wof:name": "TA5 1HZ",
    "wof:placetype": "postalcode"
  },
  "geometry": {"coordinates":[-3.121628,51.148773],"type":"Point"}
}
