{
  "type": "Feature",
  "properties": {
    "iso:country": "GB",
    "wof:name": "WV10 0LS",
    "wof:placetype": "postalcode"
  },
  "geometry": {"coordinates":[-2.102613,52.593648],"type":"Point"}
}
