{
  "type": "Feature",
  "properties": {
    "date:inception_lower": "2020-01-01",
    "date:inception_upper": "2020-01-01",
    "iso:country": "GB",
    "wof:name": "TS24 0GH",
    "wof:placetype": "postalcode"
  },
  "geometry": {"coordinates":[-1.219135,54.710243],"type":"Point"}
}
