{
  "type": "Feature",
  "properties": {
    "iso:country": "GB",
    "wof:name": "TS24 0GH",
    "wof:placetype": "postalcode"
  },
  "geometry": {"coordinates":[-1.219135,54.710243],"type":"Point"}
}
