{
  "type": "Feature",
  "properties": {
    "date:inception_lower": "1980-01-01",
    "date:inception_upper": "1980-01-01",
    "iso:country": "GB",
    "wof:name": "TW7 4QF",
    "wof:placetype": "postalcode"
  },
  "geometry": {"coordinates":[-0.349623,51.482314],"type":"Point"}
}
