{
  "type": "Feature",
  "properties": {
    "iso:country":"GB",
    "wof:name":"TW7 4QF",
    "wof:placetype":"postalcode"
},
  "geometry": {"coordinates":[-0.34962257935072,51.48231449223186],"type":"Point"}
}