{
  "type": "Feature",
  "properties": {
    "iso:country":"GB",
    "wof:name":"YO51 9QU",
    "wof:placetype":"postalcode"
},
  "geometry": {"coordinates":[-1.35042311227404,54.05987102021263],"type":"Point"}
}