{
  "type": "Feature",
  "properties": {
    "date:inception_lower": "1980-01-01",
    "date:inception_upper": "1980-01-01",
    "iso:country": "GB",
    "wof:name": "NG5 5JG",
    "wof:placetype": "postalcode"
  },
  "geometry": {"coordinates":[-1.159748,52.995388],"type":"Point"}
}
