{
  "type": "Feature",
  "properties": {
    "date:inception_lower": "1980-01-01",
    "date:inception_upper": "1980-01-01",
    "iso:country": "GB",
    "wof:name": "NR29 4JD",
    "wof:placetype": "postalcode"
  },
  "geometry": {"coordinates":[1.702816,52.701871],"type":"Point"}
}
