{
  "type": "Feature",
  "properties": {
    "date:inception_lower":"1990-07-01",
    "date:inception_upper":"1990-07-31",
    "iso:country":"GB",
    "wof:name":"N12 8TG",
    "wof:placetype":"postalcode"
},
  "geometry": {"coordinates":[-0.183602,51.617948],"type":"Point"}
}