{
  "type": "Feature",
  "properties": {
    "date:inception_lower":"1981-06-01",
    "date:inception_upper":"1981-06-30",
    "iso:country":"GB",
    "wof:name":"SA43 1PQ",
    "wof:placetype":"postalcode"
},
  "geometry": {"coordinates":[-4.651041,52.093169],"type":"Point"}
}