{
  "type": "Feature",
  "properties": {
    "iso:country":"GB",
    "wof:name":"SA43 1PQ",
    "wof:placetype":"postalcode"
},
  "geometry": {"coordinates":[-4.65104137032651,52.09316871642257],"type":"Point"}
}