{
  "type": "Feature",
  "properties": {
    "date:inception_lower": "2004-09-01",
    "date:inception_upper": "2004-09-01",
    "iso:country": "GB",
    "wof:name": "G53 7WP",
    "wof:placetype": "postalcode"
  },
  "geometry": {"coordinates":[-4.370127,55.83427],"type":"Point"}
}
