{
  "type": "Feature",
  "properties": {
    "iso:country": "GB",
    "wof:name": "G53 7WP",
    "wof:placetype": "postalcode"
  },
  "geometry": {"coordinates":[-4.370127,55.83427],"type":"Point"}
}
