{
  "type": "Feature",
  "properties": {
    "iso:country":"GB",
    "wof:name":"BA8 0DF",
    "wof:placetype":"postalcode"
},
  "geometry": {"coordinates":[-2.44382767641526,51.00541570568703],"type":"Point"}
}