{
  "type": "Feature",
  "properties": {
    "iso:country": "GB",
    "wof:name": "BA8 0DF",
    "wof:placetype": "postalcode"
  },
  "geometry": {"coordinates":[-2.443828,51.005416],"type":"Point"}
}
