{
  "type": "Feature",
  "properties": {
    "iso:country": "GB",
    "wof:name": "TA7 9AZ",
    "wof:placetype": "postalcode"
  },
  "geometry": {"coordinates":[-2.905633,51.140223],"type":"Point"}
}
