{
  "type": "Feature",
  "properties": {
    "iso:country":"GB",
    "wof:name":"TA7 9AZ",
    "wof:placetype":"postalcode"
},
  "geometry": {"coordinates":[-2.90563330615568,51.14022299360378],"type":"Point"}
}