{
  "type": "Feature",
  "properties": {
    "date:inception_lower": "2009-02-01",
    "date:inception_upper": "2009-02-01",
    "iso:country": "GB",
    "wof:name": "TA7 9AZ",
    "wof:placetype": "postalcode"
  },
  "geometry": {"coordinates":[-2.905626,51.140218],"type":"Point"}
}
