{
  "type": "Feature",
  "properties": {
    "date:inception_lower":"2009-02-01",
    "date:inception_upper":"2009-02-28",
    "iso:country":"GB",
    "wof:name":"TA7 9AZ",
    "wof:placetype":"postalcode"
},
  "geometry": {"coordinates":[-2.905633,51.140223],"type":"Point"}
}