{
  "type": "Feature",
  "properties": {
    "iso:country":"GB",
    "wof:name":"EX4 4LP",
    "wof:placetype":"postalcode"
},
  "geometry": {"coordinates":[-3.5338724740562,50.72955030750001],"type":"Point"}
}