{
  "type": "Feature",
  "properties": {
    "iso:country":"GB",
    "wof:name":"BN16 1PN",
    "wof:placetype":"postalcode"
},
  "geometry": {"coordinates":[-0.47763744103654,50.80398323766937],"type":"Point"}
}