{
  "type": "Feature",
  "properties": {
    "iso:country": "GB",
    "wof:name": "W6 9TD",
    "wof:placetype": "postalcode"
  },
  "geometry": {"coordinates":[-0.240016,51.49037],"type":"Point"}
}
