{
  "type": "Feature",
  "properties": {
    "date:inception_lower": "1995-07-01",
    "date:inception_upper": "1995-07-01",
    "iso:country": "GB",
    "wof:name": "CM7 1HL",
    "wof:placetype": "postalcode"
  },
  "geometry": {"coordinates":[0.553038,51.868428],"type":"Point"}
}
