{
  "type": "Feature",
  "properties": {
    "iso:country": "GB",
    "wof:name": "CM7 1HL",
    "wof:placetype": "postalcode"
  },
  "geometry": {"coordinates":[0.553038,51.868428],"type":"Point"}
}
