{
  "type": "Feature",
  "properties": {
    "iso:country":"GB",
    "wof:name":"YO25 5NW",
    "wof:placetype":"postalcode"
},
  "geometry": {"coordinates":[-0.42099822951249,53.99940626454177],"type":"Point"}
}