{
  "type": "Feature",
  "properties": {
    "iso:country":"GB",
    "wof:name":"SG19 3AT",
    "wof:placetype":"postalcode"
},
  "geometry": {"coordinates":[-0.1462656726777,52.18633067048501],"type":"Point"}
}