{
  "type": "Feature",
  "properties": {
    "iso:country": "GB",
    "wof:name": "SG19 3AT",
    "wof:placetype": "postalcode"
  },
  "geometry": {"coordinates":[-0.146266,52.186331],"type":"Point"}
}
