{
  "type": "Feature",
  "properties": {
    "date:inception_lower": "1980-01-01",
    "date:inception_upper": "1980-01-01",
    "iso:country": "GB",
    "wof:name": "DT5 2DJ",
    "wof:placetype": "postalcode"
  },
  "geometry": {"coordinates":[-2.443621,50.531466],"type":"Point"}
}
