{
  "type": "Feature",
  "properties": {
    "date:inception_lower": "2019-06-01",
    "date:inception_upper": "2019-06-01",
    "iso:country": "GB",
    "wof:name": "NN17 3NB",
    "wof:placetype": "postalcode"
  },
  "geometry": {"coordinates":[-0.623229,52.492865],"type":"Point"}
}
