{
  "type": "Feature",
  "properties": {
    "date:inception_lower":"1980-01-01",
    "date:inception_upper":"1980-01-31",
    "iso:country":"GB",
    "wof:name":"N22 5DX",
    "wof:placetype":"postalcode"
},
  "geometry": {"coordinates":[-0.096801,51.600332],"type":"Point"}
}