{
  "type": "Feature",
  "properties": {
    "date:inception_lower":"1980-01-01",
    "date:inception_upper":"1980-01-31",
    "iso:country":"GB",
    "wof:name":"NN8 2HH",
    "wof:placetype":"postalcode"
},
  "geometry": {"coordinates":[-0.70929,52.290953],"type":"Point"}
}