{
  "type": "Feature",
  "properties": {
    "iso:country":"GB",
    "wof:name":"NN8 2HH",
    "wof:placetype":"postalcode"
},
  "geometry": {"coordinates":[-0.70929026554953,52.29095265547045],"type":"Point"}
}