{
  "type": "Feature",
  "properties": {
    "iso:country": "GB",
    "wof:name": "NN8 2HH",
    "wof:placetype": "postalcode"
  },
  "geometry": {"coordinates":[-0.70929,52.290953],"type":"Point"}
}
