{
  "type": "Feature",
  "properties": {
    "iso:country":"GB",
    "wof:name":"FY8 4BE",
    "wof:placetype":"postalcode"
},
  "geometry": {"coordinates":[-2.9956998746322,53.75032813744939],"type":"Point"}
}