{
  "type": "Feature",
  "properties": {
    "iso:country":"GB",
    "wof:name":"B9 5NU",
    "wof:placetype":"postalcode"
},
  "geometry": {"coordinates":[-1.84432989870903,52.48206273079812],"type":"Point"}
}