{
  "type": "Feature",
  "properties": {
    "iso:country":"GB",
    "wof:name":"GL7 3SB",
    "wof:placetype":"postalcode"
},
  "geometry": {"coordinates":[-1.69264380835605,51.70264225722637],"type":"Point"}
}