{
  "type": "Feature",
  "properties": {
    "date:inception_lower":"1986-07-01",
    "date:inception_upper":"1986-07-31",
    "iso:country":"GB",
    "wof:name":"GL7 3SB",
    "wof:placetype":"postalcode"
},
  "geometry": {"coordinates":[-1.692644,51.702642],"type":"Point"}
}