{
  "type": "Feature",
  "properties": {
    "iso:country":"GB",
    "wof:name":"TF4 3AS",
    "wof:placetype":"postalcode"
},
  "geometry": {"coordinates":[-2.47676809234374,52.66083931633266],"type":"Point"}
}