{
  "type": "Feature",
  "properties": {
    "iso:country":"GB",
    "wof:name":"OX2 9GP",
    "wof:placetype":"postalcode"
},
  "geometry": {"coordinates":[-1.29425853237971,51.7405501751403],"type":"Point"}
}