{
  "type": "Feature",
  "properties": {
    "date:inception_lower": "2012-10-01",
    "date:inception_upper": "2012-10-01",
    "iso:country": "GB",
    "wof:name": "OX2 9GP",
    "wof:placetype": "postalcode"
  },
  "geometry": {"coordinates":[-1.294258,51.74055],"type":"Point"}
}
