{
  "type": "Feature",
  "properties": {
    "iso:country": "GB",
    "wof:name": "OX2 9GP",
    "wof:placetype": "postalcode"
  },
  "geometry": {"coordinates":[-1.294258,51.74055],"type":"Point"}
}
