{
  "type": "Feature",
  "properties": {
    "iso:country":"GB",
    "wof:name":"CH2 2AA",
    "wof:placetype":"postalcode"
},
  "geometry": {"coordinates":[-2.89328173004979,53.20348634601034],"type":"Point"}
}