{
  "type": "Feature",
  "properties": {
    "iso:country":"GB",
    "wof:name":"BH15 2JS",
    "wof:placetype":"postalcode"
},
  "geometry": {"coordinates":[-1.96678115186698,50.72685975482479],"type":"Point"}
}