{
  "type": "Feature",
  "properties": {
    "date:inception_lower":"1980-01-01",
    "date:inception_upper":"1980-01-31",
    "iso:country":"GB",
    "wof:name":"ME7 1DU",
    "wof:placetype":"postalcode"
},
  "geometry": {"coordinates":[0.551714,51.39138],"type":"Point"}
}