{
  "type": "Feature",
  "properties": {
    "iso:country": "GB",
    "wof:name": "ME7 1DU",
    "wof:placetype": "postalcode"
  },
  "geometry": {"coordinates":[0.551809,51.391288],"type":"Point"}
}
