{
  "type": "Feature",
  "properties": {
    "iso:country":"GB",
    "wof:name":"TW18 3JJ",
    "wof:placetype":"postalcode"
},
  "geometry": {"coordinates":[-0.51527901691621,51.43151971028882],"type":"Point"}
}