{
  "type": "Feature",
  "properties": {
    "date:inception_lower": "1980-01-01",
    "date:inception_upper": "1980-01-01",
    "iso:country": "GB",
    "wof:name": "CV1 1NG",
    "wof:placetype": "postalcode"
  },
  "geometry": {"coordinates":[-1.511193,52.407788],"type":"Point"}
}
