{
  "type": "Feature",
  "properties": {
    "iso:country": "GB",
    "wof:name": "NG16 6BT",
    "wof:placetype": "postalcode"
  },
  "geometry": {"coordinates":[-1.299871,53.070196],"type":"Point"}
}
