{
  "type": "Feature",
  "properties": {
    "iso:country": "GB",
    "wof:name": "RM20 3JP",
    "wof:placetype": "postalcode"
  },
  "geometry": {"coordinates":[0.276666,51.477905],"type":"Point"}
}
