{
  "type": "Feature",
  "properties": {
    "date:inception_lower":"1995-07-01",
    "date:inception_upper":"1995-07-31",
    "iso:country":"GB",
    "wof:name":"RM20 3JP",
    "wof:placetype":"postalcode"
},
  "geometry": {"coordinates":[0.276666,51.477905],"type":"Point"}
}