{
  "type": "Feature",
  "properties": {
    "iso:country":"GB",
    "wof:name":"RM20 3JP",
    "wof:placetype":"postalcode"
},
  "geometry": {"coordinates":[0.27666602888958,51.47790544001832],"type":"Point"}
}