{
  "type": "Feature",
  "properties": {
    "iso:country": "GB",
    "wof:name": "G73 4RL",
    "wof:placetype": "postalcode"
  },
  "geometry": {"coordinates":[-4.19579,55.809727],"type":"Point"}
}
