{
  "type": "Feature",
  "properties": {
    "date:inception_lower": "1980-01-01",
    "date:inception_upper": "1980-01-01",
    "iso:country": "GB",
    "wof:name": "IP1 2HP",
    "wof:placetype": "postalcode"
  },
  "geometry": {"coordinates":[1.141218,52.059131],"type":"Point"}
}
