{
  "type": "Feature",
  "properties": {
    "iso:country":"GB",
    "wof:name":"IP1 2HP",
    "wof:placetype":"postalcode"
},
  "geometry": {"coordinates":[1.14121755274623,52.05913052461896],"type":"Point"}
}