{
  "type": "Feature",
  "properties": {
    "iso:country":"GB",
    "wof:name":"YO18 8JQ",
    "wof:placetype":"postalcode"
},
  "geometry": {"coordinates":[-0.77125837713867,54.29144778614398],"type":"Point"}
}