{
  "type": "Feature",
  "properties": {
    "date:inception_lower":"2010-10-01",
    "date:inception_upper":"2010-10-31",
    "iso:country":"GB",
    "wof:name":"YO18 8JQ",
    "wof:placetype":"postalcode"
},
  "geometry": {"coordinates":[-0.771258,54.291448],"type":"Point"}
}