{
  "type": "Feature",
  "properties": {
    "iso:country": "GB",
    "wof:name": "YO18 8JQ",
    "wof:placetype": "postalcode"
  },
  "geometry": {"coordinates":[-0.771258,54.291448],"type":"Point"}
}
