{
  "type": "Feature",
  "properties": {
    "iso:country":"GB",
    "wof:name":"B72 1BN",
    "wof:placetype":"postalcode"
},
  "geometry": {"coordinates":[-1.81598406233279,52.53519751661464],"type":"Point"}
}