{
  "type": "Feature",
  "properties": {
    "iso:country":"GB",
    "wof:name":"YO25 3YF",
    "wof:placetype":"postalcode"
},
  "geometry": {"coordinates":[-0.40001569494332,54.14261433005529],"type":"Point"}
}