{
  "type": "Feature",
  "properties": {
    "iso:country": "GB",
    "wof:name": "TR27 6JR",
    "wof:placetype": "postalcode"
  },
  "geometry": {"coordinates":[-5.437203,50.165768],"type":"Point"}
}
