{
  "type": "Feature",
  "properties": {
    "date:inception_lower":"1980-01-01",
    "date:inception_upper":"1980-01-31",
    "iso:country":"GB",
    "wof:name":"TR27 6JR",
    "wof:placetype":"postalcode"
},
  "geometry": {"coordinates":[-5.437203,50.165768],"type":"Point"}
}