{
  "type": "Feature",
  "properties": {
    "iso:country":"GB",
    "wof:name":"NE28 8DA",
    "wof:placetype":"postalcode"
},
  "geometry": {"coordinates":[-1.54333185345369,55.00029812297979],"type":"Point"}
}