{
  "type": "Feature",
  "properties": {
    "date:inception_lower": "1980-01-01",
    "date:inception_upper": "1980-01-01",
    "iso:country": "GB",
    "wof:name": "FK15 9JD",
    "wof:placetype": "postalcode"
  },
  "geometry": {"coordinates":[-3.979325,56.1899],"type":"Point"}
}
