{
  "type": "Feature",
  "properties": {
    "iso:country": "GB",
    "wof:name": "FK15 9JD",
    "wof:placetype": "postalcode"
  },
  "geometry": {"coordinates":[-3.979325,56.1899],"type":"Point"}
}
