{
  "type": "Feature",
  "properties": {
    "iso:country": "GB",
    "wof:name": "BH10 7JN",
    "wof:placetype": "postalcode"
  },
  "geometry": {"coordinates":[-1.899803,50.770103],"type":"Point"}
}
