{
  "type": "Feature",
  "properties": {
    "iso:country":"GB",
    "wof:name":"BH10 7JN",
    "wof:placetype":"postalcode"
},
  "geometry": {"coordinates":[-1.89980318386572,50.7701031181446],"type":"Point"}
}