{
  "type": "Feature",
  "properties": {
    "iso:country": "GB",
    "wof:name": "WD25 9DZ",
    "wof:placetype": "postalcode"
  },
  "geometry": {"coordinates":[-0.382907,51.681091],"type":"Point"}
}
