{
  "type": "Feature",
  "properties": {
    "date:inception_lower":"1983-03-01",
    "date:inception_upper":"1983-03-31",
    "iso:country":"GB",
    "wof:name":"SW9 8TN",
    "wof:placetype":"postalcode"
},
  "geometry": {"coordinates":[-0.108436,51.462323],"type":"Point"}
}