{
  "type": "Feature",
  "properties": {
    "iso:country": "GB",
    "wof:name": "SW9 8TN",
    "wof:placetype": "postalcode"
  },
  "geometry": {"coordinates":[-0.108436,51.462323],"type":"Point"}
}
