{
  "type": "Feature",
  "properties": {
    "iso:country":"GB",
    "wof:name":"SW9 8TN",
    "wof:placetype":"postalcode"
},
  "geometry": {"coordinates":[-0.10843641974148,51.46232337103424],"type":"Point"}
}