{
  "type": "Feature",
  "properties": {
    "iso:country": "GB",
    "wof:name": "LA2 0PL",
    "wof:placetype": "postalcode"
  },
  "geometry": {"coordinates":[-2.775577,54.009122],"type":"Point"}
}
