{
  "type": "Feature",
  "properties": {
    "iso:country": "GB",
    "wof:name": "SN13 0BQ",
    "wof:placetype": "postalcode"
  },
  "geometry": {"coordinates":[-2.187148,51.433854],"type":"Point"}
}
