{
  "type": "Feature",
  "properties": {
    "iso:country":"GB",
    "wof:name":"SN13 0BQ",
    "wof:placetype":"postalcode"
},
  "geometry": {"coordinates":[-2.18714763999437,51.43385434998547],"type":"Point"}
}