{
  "type": "Feature",
  "properties": {
    "iso:country":"GB",
    "wof:name":"TQ12 2JE",
    "wof:placetype":"postalcode"
},
  "geometry": {"coordinates":[-3.59977752344107,50.52720109490762],"type":"Point"}
}