{
  "type": "Feature",
  "properties": {
    "iso:country": "GB",
    "wof:name": "TQ12 2JE",
    "wof:placetype": "postalcode"
  },
  "geometry": {"coordinates":[-3.599805,50.527134],"type":"Point"}
}
