{
  "type": "Feature",
  "properties": {
    "iso:country": "GB",
    "wof:name": "BS15 9JB",
    "wof:placetype": "postalcode"
  },
  "geometry": {"coordinates":[-2.480182,51.460264],"type":"Point"}
}
