{
  "type": "Feature",
  "properties": {
    "iso:country":"GB",
    "wof:name":"BS15 9JB",
    "wof:placetype":"postalcode"
},
  "geometry": {"coordinates":[-2.48018195555228,51.46026427607904],"type":"Point"}
}