{
  "type": "Feature",
  "properties": {
    "iso:country": "GB",
    "wof:name": "CF40 1BW",
    "wof:placetype": "postalcode"
  },
  "geometry": {"coordinates":[-3.456618,51.622219],"type":"Point"}
}
