{
  "type": "Feature",
  "properties": {
    "date:inception_lower":"1980-01-01",
    "date:inception_upper":"1980-01-31",
    "iso:country":"GB",
    "wof:name":"SE2 0DZ",
    "wof:placetype":"postalcode"
},
  "geometry": {"coordinates":[0.137295,51.482678],"type":"Point"}
}