{
  "type": "Feature",
  "properties": {
    "iso:country":"GB",
    "wof:name":"SE2 0DZ",
    "wof:placetype":"postalcode"
},
  "geometry": {"coordinates":[0.13729466224242,51.48267841510154],"type":"Point"}
}