{
  "type": "Feature",
  "properties": {
    "iso:country":"GB",
    "wof:name":"TN9 1PB",
    "wof:placetype":"postalcode"
},
  "geometry": {"coordinates":[0.28557045770299,51.20180046407351],"type":"Point"}
}