{
  "type": "Feature",
  "properties": {
    "date:inception_lower": "1980-01-01",
    "date:inception_upper": "1980-01-01",
    "iso:country": "GB",
    "wof:name": "TN9 1PB",
    "wof:placetype": "postalcode"
  },
  "geometry": {"coordinates":[0.28557,51.2018],"type":"Point"}
}
