{
  "type": "Feature",
  "properties": {
    "iso:country":"GB",
    "wof:name":"S6 2PD",
    "wof:placetype":"postalcode"
},
  "geometry": {"coordinates":[-1.50197197787202,53.40179761307373],"type":"Point"}
}