{
  "type": "Feature",
  "properties": {
    "iso:country":"GB",
    "wof:name":"WF17 9QB",
    "wof:placetype":"postalcode"
},
  "geometry": {"coordinates":[-1.65730306697558,53.73541630029722],"type":"Point"}
}