{
  "type": "Feature",
  "properties": {
    "iso:country":"GB",
    "wof:name":"E17 3NU",
    "wof:placetype":"postalcode"
},
  "geometry": {"coordinates":[-0.00173249831296,51.58579390240295],"type":"Point"}
}