{
  "type": "Feature",
  "properties": {
    "iso:country":"GB",
    "wof:name":"AB53 8EA",
    "wof:placetype":"postalcode"
},
  "geometry": {"coordinates":[-2.37491199886966,57.51672257657633],"type":"Point"}
}