{
  "type": "Feature",
  "properties": {
    "iso:country": "GB",
    "wof:name": "AB53 8EA",
    "wof:placetype": "postalcode"
  },
  "geometry": {"coordinates":[-2.374912,57.516723],"type":"Point"}
}
