{
  "type": "Feature",
  "properties": {
    "iso:country": "GB",
    "wof:name": "PE13 4UL",
    "wof:placetype": "postalcode"
  },
  "geometry": {"coordinates":[0.122133,52.638628],"type":"Point"}
}
