{
  "type": "Feature",
  "properties": {
    "iso:country":"GB",
    "wof:name":"GU30 7DL",
    "wof:placetype":"postalcode"
},
  "geometry": {"coordinates":[-0.80939660679493,51.07224454343175],"type":"Point"}
}