{
  "type": "Feature",
  "properties": {
    "iso:country": "GB",
    "wof:name": "CF3 6US",
    "wof:placetype": "postalcode"
  },
  "geometry": {"coordinates":[-3.081396,51.551521],"type":"Point"}
}
