{
  "type": "Feature",
  "properties": {
    "date:inception_lower": "1999-06-01",
    "date:inception_upper": "1999-06-01",
    "iso:country": "GB",
    "wof:name": "CF3 6US",
    "wof:placetype": "postalcode"
  },
  "geometry": {"coordinates":[-3.081396,51.551521],"type":"Point"}
}
