{
  "type": "Feature",
  "properties": {
    "iso:country":"GB",
    "wof:name":"CF3 6US",
    "wof:placetype":"postalcode"
},
  "geometry": {"coordinates":[-3.08138816308186,51.55151877588147],"type":"Point"}
}