{
  "type": "Feature",
  "properties": {
    "date:inception_lower": "1980-01-01",
    "date:inception_upper": "1980-01-01",
    "iso:country": "GB",
    "wof:name": "DL8 2NH",
    "wof:placetype": "postalcode"
  },
  "geometry": {"coordinates":[-1.512082,54.224541],"type":"Point"}
}
