{
  "type": "Feature",
  "properties": {
    "iso:country":"GB",
    "wof:name":"DL8 2NH",
    "wof:placetype":"postalcode"
},
  "geometry": {"coordinates":[-1.51199120071895,54.2244415232272],"type":"Point"}
}