{
  "type": "Feature",
  "properties": {
    "iso:country":"GB",
    "wof:name":"CW8 2TR",
    "wof:placetype":"postalcode"
},
  "geometry": {"coordinates":[-2.62005642335807,53.25322297791787],"type":"Point"}
}