{
  "type": "Feature",
  "properties": {
    "iso:country":"GB",
    "wof:name":"CT7 0QD",
    "wof:placetype":"postalcode"
},
  "geometry": {"coordinates":[1.24783265236499,51.35119538239942],"type":"Point"}
}