{
  "type": "Feature",
  "properties": {
    "date:inception_lower": "1980-01-01",
    "date:inception_upper": "1980-01-01",
    "iso:country": "GB",
    "wof:name": "CT7 0QD",
    "wof:placetype": "postalcode"
  },
  "geometry": {"coordinates":[1.247872,51.351156],"type":"Point"}
}
