{
  "type": "Feature",
  "properties": {
    "iso:country": "GB",
    "wof:name": "OX29 5RR",
    "wof:placetype": "postalcode"
  },
  "geometry": {"coordinates":[-1.404104,51.75202],"type":"Point"}
}
