{
  "type": "Feature",
  "properties": {
    "iso:country":"GB",
    "wof:name":"PE19 5SZ",
    "wof:placetype":"postalcode"
},
  "geometry": {"coordinates":[-0.2541740102819,52.29176421009954],"type":"Point"}
}