{
  "type": "Feature",
  "properties": {
    "iso:country":"GB",
    "wof:name":"RH2 0JA",
    "wof:placetype":"postalcode"
},
  "geometry": {"coordinates":[-0.18368461425484,51.24624118941716],"type":"Point"}
}