{
  "type": "Feature",
  "properties": {
    "date:inception_lower": "1984-10-01",
    "date:inception_upper": "1984-10-01",
    "iso:country": "GB",
    "wof:name": "OL11 4DZ",
    "wof:placetype": "postalcode"
  },
  "geometry": {"coordinates":[-2.187766,53.612117],"type":"Point"}
}
