{
  "type": "Feature",
  "properties": {
    "iso:country":"GB",
    "wof:name":"OL11 4DZ",
    "wof:placetype":"postalcode"
},
  "geometry": {"coordinates":[-2.18776630535338,53.61211691800447],"type":"Point"}
}