{
  "type": "Feature",
  "properties": {
    "iso:country": "GB",
    "wof:name": "L40 5BU",
    "wof:placetype": "postalcode"
  },
  "geometry": {"coordinates":[-2.832726,53.596483],"type":"Point"}
}
