{
  "type": "Feature",
  "properties": {
    "iso:country":"GB",
    "wof:name":"BB2 5NU",
    "wof:placetype":"postalcode"
},
  "geometry": {"coordinates":[-2.52880254621174,53.72882352285396],"type":"Point"}
}