{
  "type": "Feature",
  "properties": {
    "iso:country": "GB",
    "wof:name": "BN5 9RE",
    "wof:placetype": "postalcode"
  },
  "geometry": {"coordinates":[-0.29983,50.931938],"type":"Point"}
}
