{
  "type": "Feature",
  "properties": {
    "date:inception_lower": "1980-01-01",
    "date:inception_upper": "1980-01-01",
    "iso:country": "GB",
    "wof:name": "DH3 4EX",
    "wof:placetype": "postalcode"
  },
  "geometry": {"coordinates":[-1.548044,54.843449],"type":"Point"}
}
