{
  "type": "Feature",
  "properties": {
    "iso:country":"GB",
    "wof:name":"DH3 4EX",
    "wof:placetype":"postalcode"
},
  "geometry": {"coordinates":[-1.55154081005886,54.84431639168184],"type":"Point"}
}