{
  "type": "Feature",
  "properties": {
    "iso:country":"GB",
    "wof:name":"TW14 8DA",
    "wof:placetype":"postalcode"
},
  "geometry": {"coordinates":[-0.42752635879684,51.45413311624658],"type":"Point"}
}