{
  "type": "Feature",
  "properties": {
    "iso:country":"GB",
    "wof:name":"KA3 5PW",
    "wof:placetype":"postalcode"
},
  "geometry": {"coordinates":[-4.50676211196539,55.68289599192754],"type":"Point"}
}