{
  "type": "Feature",
  "properties": {
    "iso:country": "GB",
    "wof:name": "LU7 9EX",
    "wof:placetype": "postalcode"
  },
  "geometry": {"coordinates":[-0.632796,51.835792],"type":"Point"}
}
