{
  "type": "Feature",
  "properties": {
    "iso:country":"GB",
    "wof:name":"LU7 9EX",
    "wof:placetype":"postalcode"
},
  "geometry": {"coordinates":[-0.63282188236077,51.83578392414137],"type":"Point"}
}