{
  "type": "Feature",
  "properties": {
    "iso:country": "GB",
    "wof:name": "SL4 2RT",
    "wof:placetype": "postalcode"
  },
  "geometry": {"coordinates":[-0.582316,51.46125],"type":"Point"}
}
