{
  "type": "Feature",
  "properties": {
    "iso:country":"GB",
    "wof:name":"S71 4FF",
    "wof:placetype":"postalcode"
},
  "geometry": {"coordinates":[-1.45718566738633,53.60453630334847],"type":"Point"}
}