{
  "type": "Feature",
  "properties": {
    "iso:country":"GB",
    "wof:name":"RG2 0TD",
    "wof:placetype":"postalcode"
},
  "geometry": {"coordinates":[-0.97432316885417,51.41965535591437],"type":"Point"}
}