{
  "type": "Feature",
  "properties": {
    "iso:country":"GB",
    "wof:name":"EX8 1AU",
    "wof:placetype":"postalcode"
},
  "geometry": {"coordinates":[-3.41658995113587,50.6185646967168],"type":"Point"}
}