{
  "type": "Feature",
  "properties": {
    "date:inception_lower":"1984-10-01",
    "date:inception_upper":"1984-10-31",
    "iso:country":"GB",
    "wof:name":"PE32 1DP",
    "wof:placetype":"postalcode"
},
  "geometry": {"coordinates":[0.553356,52.779343],"type":"Point"}
}