{
  "type": "Feature",
  "properties": {
    "date:inception_lower": "1984-10-01",
    "date:inception_upper": "1984-10-01",
    "iso:country": "GB",
    "wof:name": "PE32 1DP",
    "wof:placetype": "postalcode"
  },
  "geometry": {"coordinates":[0.552781,52.779401],"type":"Point"}
}
