{
  "type": "Feature",
  "properties": {
    "iso:country": "GB",
    "wof:name": "NP18 3PT",
    "wof:placetype": "postalcode"
  },
  "geometry": {"coordinates":[-2.957508,51.617353],"type":"Point"}
}
