{
  "type": "Feature",
  "properties": {
    "date:inception_lower":"1999-06-01",
    "date:inception_upper":"1999-06-30",
    "iso:country":"GB",
    "wof:name":"NP18 3PT",
    "wof:placetype":"postalcode"
},
  "geometry": {"coordinates":[-2.957508,51.617353],"type":"Point"}
}