{
  "type": "Feature",
  "properties": {
    "iso:country":"GB",
    "wof:name":"NP18 3PT",
    "wof:placetype":"postalcode"
},
  "geometry": {"coordinates":[-2.95750819218521,51.61735297276487],"type":"Point"}
}