{
  "type": "Feature",
  "properties": {
    "date:inception_lower": "1980-01-01",
    "date:inception_upper": "1980-01-01",
    "iso:country": "GB",
    "wof:name": "GU15 2RX",
    "wof:placetype": "postalcode"
  },
  "geometry": {"coordinates":[-0.757597,51.319743],"type":"Point"}
}
