{
  "type": "Feature",
  "properties": {
    "iso:country":"GB",
    "wof:name":"WA3 6AJ",
    "wof:placetype":"postalcode"
},
  "geometry": {"coordinates":[-2.5329095012757,53.42026925826286],"type":"Point"}
}