{
  "type": "Feature",
  "properties": {
    "iso:country":"GB",
    "wof:name":"BN27 2LX",
    "wof:placetype":"postalcode"
},
  "geometry": {"coordinates":[0.26870003454785,50.85999219176173],"type":"Point"}
}