{
  "type": "Feature",
  "properties": {
    "iso:country":"GB",
    "wof:name":"SN13 9LX",
    "wof:placetype":"postalcode"
},
  "geometry": {"coordinates":[-2.20039922406159,51.43117990112741],"type":"Point"}
}