{
  "type": "Feature",
  "properties": {
    "iso:country":"GB",
    "wof:name":"NR8 5GR",
    "wof:placetype":"postalcode"
},
  "geometry": {"coordinates":[1.18575156532975,52.66769575528448],"type":"Point"}
}