{
  "type": "Feature",
  "properties": {
    "date:inception_lower": "2014-01-01",
    "date:inception_upper": "2014-01-01",
    "iso:country": "GB",
    "wof:name": "NR8 5GR",
    "wof:placetype": "postalcode"
  },
  "geometry": {"coordinates":[1.185752,52.667696],"type":"Point"}
}
