{
  "type": "Feature",
  "properties": {
    "date:inception_lower": "1980-01-01",
    "date:inception_upper": "1980-01-01",
    "iso:country": "GB",
    "wof:name": "SS2 6LA",
    "wof:placetype": "postalcode"
  },
  "geometry": {"coordinates":[0.708619,51.55103],"type":"Point"}
}
