{
  "type": "Feature",
  "properties": {
    "date:inception_lower": "1980-01-01",
    "date:inception_upper": "1980-01-01",
    "iso:country": "GB",
    "wof:name": "OL15 0HF",
    "wof:placetype": "postalcode"
  },
  "geometry": {"coordinates":[-2.091355,53.643553],"type":"Point"}
}
