{
  "type": "Feature",
  "properties": {
    "date:inception_lower": "1980-01-01",
    "date:inception_upper": "1980-01-01",
    "iso:country": "GB",
    "wof:name": "DN14 8RN",
    "wof:placetype": "postalcode"
  },
  "geometry": {"coordinates":[-0.967114,53.700311],"type":"Point"}
}
