{
  "type": "Feature",
  "properties": {
    "date:inception_lower": "2009-08-01",
    "date:inception_upper": "2009-08-01",
    "iso:country": "GB",
    "wof:name": "TW6 2GE",
    "wof:placetype": "postalcode"
  },
  "geometry": {"coordinates":[-0.421554,51.467712],"type":"Point"}
}
