{
  "type": "Feature",
  "properties": {
    "iso:country":"GB",
    "wof:name":"LE4 5HG",
    "wof:placetype":"postalcode"
},
  "geometry": {"coordinates":[-1.12517710460936,52.64895325672686],"type":"Point"}
}