{
  "type": "Feature",
  "properties": {
    "iso:country":"GB",
    "wof:name":"TS7 0HY",
    "wof:placetype":"postalcode"
},
  "geometry": {"coordinates":[-1.18089098165761,54.52826257213662],"type":"Point"}
}