{
  "type": "Feature",
  "properties": {
    "iso:country": "GB",
    "wof:name": "TS7 0HY",
    "wof:placetype": "postalcode"
  },
  "geometry": {"coordinates":[-1.180891,54.528263],"type":"Point"}
}
