{
  "type": "Feature",
  "properties": {
    "iso:country":"GB",
    "wof:name":"WD23 1FT",
    "wof:placetype":"postalcode"
},
  "geometry": {"coordinates":[-0.35509976049618,51.64052839436876],"type":"Point"}
}