{
  "type": "Feature",
  "properties": {
    "iso:country": "GB",
    "wof:name": "DD11 3FE",
    "wof:placetype": "postalcode"
  },
  "geometry": {"coordinates":[-2.614838,56.564558],"type":"Point"}
}
