{
  "type": "Feature",
  "properties": {
    "iso:country":"GB",
    "wof:name":"TQ6 9QZ",
    "wof:placetype":"postalcode"
},
  "geometry": {"coordinates":[-3.57849213914095,50.35042277389707],"type":"Point"}
}