{
  "type": "Feature",
  "properties": {
    "iso:country": "GB",
    "wof:name": "TQ6 9QZ",
    "wof:placetype": "postalcode"
  },
  "geometry": {"coordinates":[-3.578494,50.350397],"type":"Point"}
}
