{
  "type": "Feature",
  "properties": {
    "iso:country":"GB",
    "wof:name":"HA6 1AD",
    "wof:placetype":"postalcode"
},
  "geometry": {"coordinates":[-0.42285904864778,51.61153249005472],"type":"Point"}
}