{
  "type": "Feature",
  "properties": {
    "iso:country": "GB",
    "wof:name": "EN10 7BU",
    "wof:placetype": "postalcode"
  },
  "geometry": {"coordinates":[-0.022223,51.740694],"type":"Point"}
}
