{
  "type": "Feature",
  "properties": {
    "iso:country": "GB",
    "wof:name": "AB39 2QT",
    "wof:placetype": "postalcode"
  },
  "geometry": {"coordinates":[-2.219971,56.966107],"type":"Point"}
}
