{
  "type": "Feature",
  "properties": {
    "iso:country":"GB",
    "wof:name":"DT2 8JB",
    "wof:placetype":"postalcode"
},
  "geometry": {"coordinates":[-2.32922330119337,50.68679495023197],"type":"Point"}
}