{
  "type": "Feature",
  "properties": {
    "iso:country": "GB",
    "wof:name": "DT2 8JB",
    "wof:placetype": "postalcode"
  },
  "geometry": {"coordinates":[-2.329223,50.686795],"type":"Point"}
}
