{
  "type": "Feature",
  "properties": {
    "iso:country":"GB",
    "wof:name":"NR21 7LW",
    "wof:placetype":"postalcode"
},
  "geometry": {"coordinates":[0.8331395270344,52.82221692796575],"type":"Point"}
}