{
  "type": "Feature",
  "properties": {
    "date:inception_lower":"1980-01-01",
    "date:inception_upper":"1980-01-31",
    "iso:country":"GB",
    "wof:name":"NR21 7LW",
    "wof:placetype":"postalcode"
},
  "geometry": {"coordinates":[0.833174,52.822269],"type":"Point"}
}