{
  "type": "Feature",
  "properties": {
    "iso:country":"GB",
    "wof:name":"DA14 4LY",
    "wof:placetype":"postalcode"
},
  "geometry": {"coordinates":[0.11967457802238,51.43285388774798],"type":"Point"}
}