{
  "type": "Feature",
  "properties": {
    "date:inception_lower":"1980-01-01",
    "date:inception_upper":"1980-01-31",
    "iso:country":"GB",
    "wof:name":"OX2 6BN",
    "wof:placetype":"postalcode"
},
  "geometry": {"coordinates":[-1.267042,51.758672],"type":"Point"}
}