{
  "type": "Feature",
  "properties": {
    "iso:country":"GB",
    "wof:name":"FY2 0RX",
    "wof:placetype":"postalcode"
},
  "geometry": {"coordinates":[-3.03659910670177,53.84196861109733],"type":"Point"}
}