{
  "type": "Feature",
  "properties": {
    "date:inception_lower": "1980-01-01",
    "date:inception_upper": "1980-01-01",
    "iso:country": "GB",
    "wof:name": "LS19 7TL",
    "wof:placetype": "postalcode"
  },
  "geometry": {"coordinates":[-1.677419,53.862122],"type":"Point"}
}
