{
  "type": "Feature",
  "properties": {
    "iso:country":"GB",
    "wof:name":"LS19 7TL",
    "wof:placetype":"postalcode"
},
  "geometry": {"coordinates":[-1.67741953694591,53.86212194964699],"type":"Point"}
}