{
  "type": "Feature",
  "properties": {
    "iso:country": "GB",
    "wof:name": "SO19 6QD",
    "wof:placetype": "postalcode"
  },
  "geometry": {"coordinates":[-1.33147,50.91393],"type":"Point"}
}
