{
  "type": "Feature",
  "properties": {
    "date:inception_lower":"1980-01-01",
    "date:inception_upper":"1980-01-31",
    "iso:country":"GB",
    "wof:name":"CW5 5LS",
    "wof:placetype":"postalcode"
},
  "geometry": {"coordinates":[-2.523569,53.069627],"type":"Point"}
}