{
  "type": "Feature",
  "properties": {
    "iso:country":"GB",
    "wof:name":"TS4 3NG",
    "wof:placetype":"postalcode"
},
  "geometry": {"coordinates":[-1.21559393975039,54.54449859059378],"type":"Point"}
}