{
  "type": "Feature",
  "properties": {
    "date:inception_lower": "1997-12-01",
    "date:inception_upper": "1997-12-01",
    "iso:country": "GB",
    "wof:name": "TQ9 5BS",
    "wof:placetype": "postalcode"
  },
  "geometry": {"coordinates":[-3.676061,50.431873],"type":"Point"}
}
