{
  "type": "Feature",
  "properties": {
    "iso:country":"GB",
    "wof:name":"TQ9 5BS",
    "wof:placetype":"postalcode"
},
  "geometry": {"coordinates":[-3.67606075446544,50.43187283995709],"type":"Point"}
}