{
  "type": "Feature",
  "properties": {
    "iso:country":"GB",
    "wof:name":"S5 9QB",
    "wof:placetype":"postalcode"
},
  "geometry": {"coordinates":[-1.48883443147702,53.43001138788144],"type":"Point"}
}