{
  "type": "Feature",
  "properties": {
    "iso:country":"GB",
    "wof:name":"HX6 2JN",
    "wof:placetype":"postalcode"
},
  "geometry": {"coordinates":[-1.90633924062271,53.71494488265643],"type":"Point"}
}