{
  "type": "Feature",
  "properties": {
    "iso:country":"GB",
    "wof:name":"ML6 7AW",
    "wof:placetype":"postalcode"
},
  "geometry": {"coordinates":[-3.95503440774859,55.86638260278945],"type":"Point"}
}