{
  "type": "Feature",
  "properties": {
    "iso:country":"GB",
    "wof:name":"CT2 7UZ",
    "wof:placetype":"postalcode"
},
  "geometry": {"coordinates":[1.06010061265681,51.29657503440762],"type":"Point"}
}