{
  "type": "Feature",
  "properties": {
    "date:inception_lower":"1984-02-01",
    "date:inception_upper":"1984-02-29",
    "iso:country":"GB",
    "wof:name":"CT2 7UZ",
    "wof:placetype":"postalcode"
},
  "geometry": {"coordinates":[1.060101,51.296575],"type":"Point"}
}