{
  "type": "Feature",
  "properties": {
    "iso:country":"GB",
    "wof:name":"OX4 1LU",
    "wof:placetype":"postalcode"
},
  "geometry": {"coordinates":[-1.22815030857452,51.74701308960842],"type":"Point"}
}