{
  "type": "Feature",
  "properties": {
    "date:inception_lower": "1980-01-01",
    "date:inception_upper": "1980-01-01",
    "iso:country": "GB",
    "wof:name": "WS11 1EJ",
    "wof:placetype": "postalcode"
  },
  "geometry": {"coordinates":[-2.041372,52.685892],"type":"Point"}
}
