{
  "type": "Feature",
  "properties": {
    "iso:country":"GB",
    "wof:name":"WS11 1EJ",
    "wof:placetype":"postalcode"
},
  "geometry": {"coordinates":[-2.04140791272433,52.68586630658611],"type":"Point"}
}