{
  "type": "Feature",
  "properties": {
    "iso:country":"GB",
    "wof:name":"CV34 6WL",
    "wof:placetype":"postalcode"
},
  "geometry": {"coordinates":[-1.55139075340482,52.26913789661808],"type":"Point"}
}