{
  "type": "Feature",
  "properties": {
    "iso:country": "GB",
    "wof:name": "B12 8RT",
    "wof:placetype": "postalcode"
  },
  "geometry": {"coordinates":[-1.874626,52.453519],"type":"Point"}
}
