{
  "type": "Feature",
  "properties": {
    "date:inception_lower": "1980-01-01",
    "date:inception_upper": "1980-01-01",
    "iso:country": "GB",
    "wof:name": "B12 8RT",
    "wof:placetype": "postalcode"
  },
  "geometry": {"coordinates":[-1.874626,52.453519],"type":"Point"}
}
