{
  "type": "Feature",
  "properties": {
    "iso:country":"GB",
    "wof:name":"NG2 7YF",
    "wof:placetype":"postalcode"
},
  "geometry": {"coordinates":[-1.15058372246273,52.93161390370838],"type":"Point"}
}