{
  "type": "Feature",
  "properties": {
    "iso:country":"GB",
    "wof:name":"GU12 4HZ",
    "wof:placetype":"postalcode"
},
  "geometry": {"coordinates":[-0.75135789995461,51.24186611292004],"type":"Point"}
}