{
  "type": "Feature",
  "properties": {
    "iso:country": "GB",
    "wof:name": "IP14 5UU",
    "wof:placetype": "postalcode"
  },
  "geometry": {"coordinates":[1.016104,52.188024],"type":"Point"}
}
