{
  "type": "Feature",
  "properties": {
    "iso:country":"GB",
    "wof:name":"IP14 5UU",
    "wof:placetype":"postalcode"
},
  "geometry": {"coordinates":[1.01610438135025,52.18802355507501],"type":"Point"}
}