{
  "type": "Feature",
  "properties": {
    "iso:country": "GB",
    "wof:name": "BD7 3BP",
    "wof:placetype": "postalcode"
  },
  "geometry": {"coordinates":[-1.775314,53.784518],"type":"Point"}
}
