{
  "type": "Feature",
  "properties": {
    "iso:country":"GB",
    "wof:name":"BD7 3BP",
    "wof:placetype":"postalcode"
},
  "geometry": {"coordinates":[-1.77531411599428,53.78451837390864],"type":"Point"}
}