{
  "type": "Feature",
  "properties": {
    "date:inception_lower":"1980-01-01",
    "date:inception_upper":"1980-01-31",
    "iso:country":"GB",
    "wof:name":"BD7 3BP",
    "wof:placetype":"postalcode"
},
  "geometry": {"coordinates":[-1.775314,53.784518],"type":"Point"}
}