{
  "type": "Feature",
  "properties": {
    "iso:country":"GB",
    "wof:name":"AB11 6JD",
    "wof:placetype":"postalcode"
},
  "geometry": {"coordinates":[-2.10098701067774,57.13946080893129],"type":"Point"}
}