{
  "type": "Feature",
  "properties": {
    "iso:country":"GB",
    "wof:name":"E16 3LT",
    "wof:placetype":"postalcode"
},
  "geometry": {"coordinates":[0.03568690663036,51.5144593782422],"type":"Point"}
}