{
  "type": "Feature",
  "properties": {
    "iso:country": "GB",
    "wof:name": "L11 2AL",
    "wof:placetype": "postalcode"
  },
  "geometry": {"coordinates":[-2.917293,53.444766],"type":"Point"}
}
