{
  "type": "Feature",
  "properties": {
    "iso:country":"GB",
    "wof:name":"WA11 9QY",
    "wof:placetype":"postalcode"
},
  "geometry": {"coordinates":[-2.70596050939995,53.46436875990652],"type":"Point"}
}