{
  "type": "Feature",
  "properties": {
    "iso:country": "GB",
    "wof:name": "WA11 9QY",
    "wof:placetype": "postalcode"
  },
  "geometry": {"coordinates":[-2.70596,53.464369],"type":"Point"}
}
