{
  "type": "Feature",
  "properties": {
    "iso:country":"GB",
    "wof:name":"TN19 7AW",
    "wof:placetype":"postalcode"
},
  "geometry": {"coordinates":[0.44024085772573,51.00962631531002],"type":"Point"}
}