{
  "type": "Feature",
  "properties": {
    "iso:country": "GB",
    "wof:name": "TN19 7AW",
    "wof:placetype": "postalcode"
  },
  "geometry": {"coordinates":[0.440241,51.009626],"type":"Point"}
}
