{
  "type": "Feature",
  "properties": {
    "date:inception_lower": "1980-01-01",
    "date:inception_upper": "1980-01-01",
    "iso:country": "GB",
    "wof:name": "WA4 2DL",
    "wof:placetype": "postalcode"
  },
  "geometry": {"coordinates":[-2.56927,53.372344],"type":"Point"}
}
