{
  "type": "Feature",
  "properties": {
    "iso:country":"GB",
    "wof:name":"CO7 9BU",
    "wof:placetype":"postalcode"
},
  "geometry": {"coordinates":[0.95938121094723,51.85438766310548],"type":"Point"}
}