{
  "type": "Feature",
  "properties": {
    "iso:country": "GB",
    "wof:name": "CO7 9BU",
    "wof:placetype": "postalcode"
  },
  "geometry": {"coordinates":[0.959411,51.854398],"type":"Point"}
}
