{
  "type": "Feature",
  "properties": {
    "iso:country":"GB",
    "wof:name":"BN2 1QE",
    "wof:placetype":"postalcode"
},
  "geometry": {"coordinates":[-0.13016427523519,50.82111801968037],"type":"Point"}
}