{
  "type": "Feature",
  "properties": {
    "date:inception_lower":"1980-01-01",
    "date:inception_upper":"1980-01-31",
    "iso:country":"GB",
    "wof:name":"CA25 5AF",
    "wof:placetype":"postalcode"
},
  "geometry": {"coordinates":[-3.515934,54.522294],"type":"Point"}
}