{
  "type": "Feature",
  "properties": {
    "iso:country":"GB",
    "wof:name":"BL6 6BS",
    "wof:placetype":"postalcode"
},
  "geometry": {"coordinates":[-2.54019710812085,53.59843367522225],"type":"Point"}
}