{
  "type": "Feature",
  "properties": {
    "date:inception_lower": "1996-06-01",
    "date:inception_upper": "1996-06-01",
    "iso:country": "GB",
    "wof:name": "GU47 0XN",
    "wof:placetype": "postalcode"
  },
  "geometry": {"coordinates":[-0.781872,51.348107],"type":"Point"}
}
