{
  "type": "Feature",
  "properties": {
    "iso:country":"GB",
    "wof:name":"NG19 6JN",
    "wof:placetype":"postalcode"
},
  "geometry": {"coordinates":[-1.22692993585885,53.14868786893575],"type":"Point"}
}