{
  "type": "Feature",
  "properties": {
    "iso:country": "GB",
    "wof:name": "NG19 6JN",
    "wof:placetype": "postalcode"
  },
  "geometry": {"coordinates":[-1.22693,53.148688],"type":"Point"}
}
