{
  "type": "Feature",
  "properties": {
    "iso:country": "GB",
    "wof:name": "EH11 4QD",
    "wof:placetype": "postalcode"
  },
  "geometry": {"coordinates":[-3.286547,55.919653],"type":"Point"}
}
