{
  "type": "Feature",
  "properties": {
    "iso:country":"GB",
    "wof:name":"IP6 9QX",
    "wof:placetype":"postalcode"
},
  "geometry": {"coordinates":[1.12303451913921,52.14578387556768],"type":"Point"}
}