{
  "type": "Feature",
  "properties": {
    "date:inception_lower": "1995-12-01",
    "date:inception_upper": "1995-12-01",
    "iso:country": "GB",
    "wof:name": "E3 3PF",
    "wof:placetype": "postalcode"
  },
  "geometry": {"coordinates":[-0.016967,51.523311],"type":"Point"}
}
