{
  "type": "Feature",
  "properties": {
    "date:inception_lower": "1997-12-01",
    "date:inception_upper": "1997-12-01",
    "iso:country": "GB",
    "wof:name": "SS4 1GE",
    "wof:placetype": "postalcode"
  },
  "geometry": {"coordinates":[0.688375,51.595214],"type":"Point"}
}
