{
  "type": "Feature",
  "properties": {
    "iso:country": "GB",
    "wof:name": "SS4 1GE",
    "wof:placetype": "postalcode"
  },
  "geometry": {"coordinates":[0.688375,51.595214],"type":"Point"}
}
