{
  "type": "Feature",
  "properties": {
    "iso:country":"GB",
    "wof:name":"SS4 1GE",
    "wof:placetype":"postalcode"
},
  "geometry": {"coordinates":[0.68837530505517,51.59521361671896],"type":"Point"}
}