{
  "type": "Feature",
  "properties": {
    "iso:country":"GB",
    "wof:name":"HU12 0PF",
    "wof:placetype":"postalcode"
},
  "geometry": {"coordinates":[-0.01264629665165,53.68312765831847],"type":"Point"}
}