{
  "type": "Feature",
  "properties": {
    "date:inception_lower":"1990-02-01",
    "date:inception_upper":"1990-02-28",
    "iso:country":"GB",
    "wof:name":"HU12 0PF",
    "wof:placetype":"postalcode"
},
  "geometry": {"coordinates":[-0.012646,53.683128],"type":"Point"}
}