{
  "type": "Feature",
  "properties": {
    "iso:country":"GB",
    "wof:name":"DH9 7LJ",
    "wof:placetype":"postalcode"
},
  "geometry": {"coordinates":[-1.71260158956379,54.86425062428855],"type":"Point"}
}