{
  "type": "Feature",
  "properties": {
    "iso:country":"GB",
    "wof:name":"SA3 5TA",
    "wof:placetype":"postalcode"
},
  "geometry": {"coordinates":[-4.00408981627823,51.5766120387586],"type":"Point"}
}