{
  "type": "Feature",
  "properties": {
    "iso:country": "GB",
    "wof:name": "SA3 5TA",
    "wof:placetype": "postalcode"
  },
  "geometry": {"coordinates":[-4.00409,51.576612],"type":"Point"}
}
