{
  "type": "Feature",
  "properties": {
    "iso:country":"GB",
    "wof:name":"SA9 2DJ",
    "wof:placetype":"postalcode"
},
  "geometry": {"coordinates":[-3.7962679174559,51.75317735090341],"type":"Point"}
}