{
  "type": "Feature",
  "properties": {
    "iso:country":"GB",
    "wof:name":"EH52 6UP",
    "wof:placetype":"postalcode"
},
  "geometry": {"coordinates":[-3.46840066047791,55.95916513500602],"type":"Point"}
}