{
  "type": "Feature",
  "properties": {
    "date:inception_lower": "1981-03-01",
    "date:inception_upper": "1981-03-01",
    "iso:country": "GB",
    "wof:name": "EH52 6UP",
    "wof:placetype": "postalcode"
  },
  "geometry": {"coordinates":[-3.468401,55.959165],"type":"Point"}
}
