{
  "type": "Feature",
  "properties": {
    "date:inception_lower": "1980-01-01",
    "date:inception_upper": "1980-01-01",
    "iso:country": "GB",
    "wof:name": "DE4 4HE",
    "wof:placetype": "postalcode"
  },
  "geometry": {"coordinates":[-1.612575,53.089845],"type":"Point"}
}
