{
  "type": "Feature",
  "properties": {
    "iso:country":"GB",
    "wof:name":"DE4 4HE",
    "wof:placetype":"postalcode"
},
  "geometry": {"coordinates":[-1.60968741197499,53.09415027210021],"type":"Point"}
}