{
  "type": "Feature",
  "properties": {
    "iso:country": "GB",
    "wof:name": "PO22 9NS",
    "wof:placetype": "postalcode"
  },
  "geometry": {"coordinates":[-0.673419,50.812381],"type":"Point"}
}
