{
  "type": "Feature",
  "properties": {
    "date:inception_lower":"1980-01-01",
    "date:inception_upper":"1980-01-31",
    "iso:country":"GB",
    "wof:name":"PO22 9NS",
    "wof:placetype":"postalcode"
},
  "geometry": {"coordinates":[-0.673419,50.812381],"type":"Point"}
}