{
  "type": "Feature",
  "properties": {
    "iso:country":"GB",
    "wof:name":"M34 2FB",
    "wof:placetype":"postalcode"
},
  "geometry": {"coordinates":[-2.12098646295923,53.44782396351899],"type":"Point"}
}