{
  "type": "Feature",
  "properties": {
    "date:inception_lower": "1980-01-01",
    "date:inception_upper": "1980-01-01",
    "iso:country": "GB",
    "wof:name": "M34 2FB",
    "wof:placetype": "postalcode"
  },
  "geometry": {"coordinates":[-2.120986,53.447824],"type":"Point"}
}
