{
  "type": "Feature",
  "properties": {
    "iso:country":"GB",
    "wof:name":"LU2 7DP",
    "wof:placetype":"postalcode"
},
  "geometry": {"coordinates":[-0.41729362299853,51.8992962878667],"type":"Point"}
}