{
  "type": "Feature",
  "properties": {
    "iso:country":"GB",
    "wof:name":"KT1 1ET",
    "wof:placetype":"postalcode"
},
  "geometry": {"coordinates":[-0.30619954622139,51.40883874207349],"type":"Point"}
}