{
  "type": "Feature",
  "properties": {
    "iso:country":"GB",
    "wof:name":"LA7 7BX",
    "wof:placetype":"postalcode"
},
  "geometry": {"coordinates":[-2.7735477984042,54.24316628684472],"type":"Point"}
}