{
  "type": "Feature",
  "properties": {
    "date:inception_lower": "1996-12-01",
    "date:inception_upper": "1996-12-01",
    "iso:country": "GB",
    "wof:name": "LA7 7BX",
    "wof:placetype": "postalcode"
  },
  "geometry": {"coordinates":[-2.773486,54.243168],"type":"Point"}
}
