{
  "type": "Feature",
  "properties": {
    "iso:country":"GB",
    "wof:name":"DY1 2LR",
    "wof:placetype":"postalcode"
},
  "geometry": {"coordinates":[-2.11348134596551,52.50373092751526],"type":"Point"}
}