{
  "type": "Feature",
  "properties": {
    "date:inception_lower": "2018-01-01",
    "date:inception_upper": "2018-01-01",
    "iso:country": "GB",
    "wof:name": "NE24 3UX",
    "wof:placetype": "postalcode"
  },
  "geometry": {"coordinates":[-1.500768,55.11445],"type":"Point"}
}
