{
  "type": "Feature",
  "properties": {
    "iso:country": "GB",
    "wof:name": "LN6 7BU",
    "wof:placetype": "postalcode"
  },
  "geometry": {"coordinates":[-0.554528,53.228286],"type":"Point"}
}
