{
  "type": "Feature",
  "properties": {
    "iso:country":"GB",
    "wof:name":"TQ9 5FW",
    "wof:placetype":"postalcode"
},
  "geometry": {"coordinates":[-3.71308003119848,50.43346505235162],"type":"Point"}
}