{
  "type": "Feature",
  "properties": {
    "date:inception_lower": "1995-07-01",
    "date:inception_upper": "1995-07-01",
    "iso:country": "GB",
    "wof:name": "TQ9 5FW",
    "wof:placetype": "postalcode"
  },
  "geometry": {"coordinates":[-3.71308,50.433465],"type":"Point"}
}
