{
  "type": "Feature",
  "properties": {
    "iso:country": "GB",
    "wof:name": "AB42 2XW",
    "wof:placetype": "postalcode"
  },
  "geometry": {"coordinates":[-1.797167,57.501281],"type":"Point"}
}
