{
  "type": "Feature",
  "properties": {
    "iso:country":"GB",
    "wof:name":"SW4 7PW",
    "wof:placetype":"postalcode"
},
  "geometry": {"coordinates":[-0.12719311136387,51.4620040077376],"type":"Point"}
}