{
  "type": "Feature",
  "properties": {
    "iso:country": "GB",
    "wof:name": "SW4 7PW",
    "wof:placetype": "postalcode"
  },
  "geometry": {"coordinates":[-0.127193,51.462004],"type":"Point"}
}
