{
  "type": "Feature",
  "properties": {
    "iso:country":"GB",
    "wof:name":"WF9 3QS",
    "wof:placetype":"postalcode"
},
  "geometry": {"coordinates":[-1.31713256937354,53.58984237247201],"type":"Point"}
}