{
  "type": "Feature",
  "properties": {
    "iso:country": "GB",
    "wof:name": "WF9 3QS",
    "wof:placetype": "postalcode"
  },
  "geometry": {"coordinates":[-1.317133,53.589842],"type":"Point"}
}
