{
  "type": "Feature",
  "properties": {
    "date:inception_lower": "2022-11-01",
    "date:inception_upper": "2022-11-01",
    "iso:country": "GB",
    "wof:name": "OX18 4EZ",
    "wof:placetype": "postalcode"
  },
  "geometry": {"coordinates":[-1.633797,51.797076],"type":"Point"}
}
