{
  "type": "Feature",
  "properties": {
    "iso:country": "GB",
    "wof:name": "SY6 6LN",
    "wof:placetype": "postalcode"
  },
  "geometry": {"coordinates":[-2.819862,52.567108],"type":"Point"}
}
