{
  "type": "Feature",
  "properties": {
    "iso:country": "GB",
    "wof:name": "SY6 6LN",
    "wof:placetype": "postalcode"
  },
  "geometry": {"coordinates":[-2.815854,52.568951],"type":"Point"}
}
