{
  "type": "Feature",
  "properties": {
    "iso:country":"GB",
    "wof:name":"SY6 6LN",
    "wof:placetype":"postalcode"
},
  "geometry": {"coordinates":[-2.81585264774882,52.56893664591301],"type":"Point"}
}