{
  "type": "Feature",
  "properties": {
    "iso:country":"GB",
    "wof:name":"WR6 5DG",
    "wof:placetype":"postalcode"
},
  "geometry": {"coordinates":[-2.41262184169582,52.17656709132383],"type":"Point"}
}