{
  "type": "Feature",
  "properties": {
    "iso:country":"GB",
    "wof:name":"WV1 1JS",
    "wof:placetype":"postalcode"
},
  "geometry": {"coordinates":[-2.12550730196977,52.58789084332339],"type":"Point"}
}