{
  "type": "Feature",
  "properties": {
    "iso:country": "GB",
    "wof:name": "CF62 3ZR",
    "wof:placetype": "postalcode"
  },
  "geometry": {"coordinates":[-3.392443,51.39754],"type":"Point"}
}
