{
  "type": "Feature",
  "properties": {
    "iso:country":"GB",
    "wof:name":"CF62 3ZR",
    "wof:placetype":"postalcode"
},
  "geometry": {"coordinates":[-3.39244296878103,51.39754028865923],"type":"Point"}
}