{
  "type": "Feature",
  "properties": {
    "iso:country":"GB",
    "wof:name":"CO5 0FE",
    "wof:placetype":"postalcode"
},
  "geometry": {"coordinates":[0.75824905248892,51.81522887279412],"type":"Point"}
}