{
  "type": "Feature",
  "properties": {
    "date:inception_lower": "1992-08-01",
    "date:inception_upper": "1992-08-01",
    "iso:country": "GB",
    "wof:name": "DE55 6GN",
    "wof:placetype": "postalcode"
  },
  "geometry": {"coordinates":[-1.41828,53.133658],"type":"Point"}
}
