{
  "type": "Feature",
  "properties": {
    "date:inception_lower": "2021-06-01",
    "date:inception_upper": "2021-06-01",
    "iso:country": "GB",
    "wof:name": "GL51 4AF",
    "wof:placetype": "postalcode"
  },
  "geometry": {"coordinates":[-2.129441,51.863792],"type":"Point"}
}
