{
  "type": "Feature",
  "properties": {
    "iso:country":"GB",
    "wof:name":"NW6 1HD",
    "wof:placetype":"postalcode"
},
  "geometry": {"coordinates":[-0.20225255168389,51.55317535714761],"type":"Point"}
}