{
  "type": "Feature",
  "properties": {
    "date:inception_lower": "1980-01-01",
    "date:inception_upper": "1980-01-01",
    "iso:country": "GB",
    "wof:name": "B92 7QB",
    "wof:placetype": "postalcode"
  },
  "geometry": {"coordinates":[-1.799294,52.45462],"type":"Point"}
}
