{
  "type": "Feature",
  "properties": {
    "iso:country": "GB",
    "wof:name": "B92 7QB",
    "wof:placetype": "postalcode"
  },
  "geometry": {"coordinates":[-1.799294,52.45462],"type":"Point"}
}
