{
  "type": "Feature",
  "properties": {
    "iso:country": "GB",
    "wof:name": "N15 3BB",
    "wof:placetype": "postalcode"
  },
  "geometry": {"coordinates":[-0.093649,51.583195],"type":"Point"}
}
