{
  "type": "Feature",
  "properties": {
    "iso:country":"GB",
    "wof:name":"EC4A 2AT",
    "wof:placetype":"postalcode"
},
  "geometry": {"coordinates":[-0.11035630652081,51.51410660540274],"type":"Point"}
}