{
  "type": "Feature",
  "properties": {
    "date:inception_lower": "2002-06-01",
    "date:inception_upper": "2002-06-01",
    "iso:country": "GB",
    "wof:name": "EC4A 2AT",
    "wof:placetype": "postalcode"
  },
  "geometry": {"coordinates":[-0.110356,51.514107],"type":"Point"}
}
