{
  "type": "Feature",
  "properties": {
    "iso:country": "GB",
    "wof:name": "WF10 1FH",
    "wof:placetype": "postalcode"
  },
  "geometry": {"coordinates":[-1.360974,53.728226],"type":"Point"}
}
