{
  "type": "Feature",
  "properties": {
    "iso:country": "GB",
    "wof:name": "L4 9RS",
    "wof:placetype": "postalcode"
  },
  "geometry": {"coordinates":[-2.936117,53.442211],"type":"Point"}
}
