{
  "type": "Feature",
  "properties": {
    "date:inception_lower": "1980-01-01",
    "date:inception_upper": "1980-01-01",
    "iso:country": "GB",
    "wof:name": "PL26 8BZ",
    "wof:placetype": "postalcode"
  },
  "geometry": {"coordinates":[-4.886935,50.39006],"type":"Point"}
}
