{
  "type": "Feature",
  "properties": {
    "iso:country":"GB",
    "wof:name":"PL26 8BZ",
    "wof:placetype":"postalcode"
},
  "geometry": {"coordinates":[-4.88693475468814,50.39006034382663],"type":"Point"}
}