{
  "type": "Feature",
  "properties": {
    "date:inception_lower": "1980-01-01",
    "date:inception_upper": "1980-01-01",
    "iso:country": "GB",
    "wof:name": "NG6 8GT",
    "wof:placetype": "postalcode"
  },
  "geometry": {"coordinates":[-1.197075,53.004609],"type":"Point"}
}
