{
  "type": "Feature",
  "properties": {
    "iso:country":"GB",
    "wof:name":"EH52 6QL",
    "wof:placetype":"postalcode"
},
  "geometry": {"coordinates":[-3.45800573647165,55.98219340078715],"type":"Point"}
}