{
  "type": "Feature",
  "properties": {
    "iso:country": "GB",
    "wof:name": "EH52 6QL",
    "wof:placetype": "postalcode"
  },
  "geometry": {"coordinates":[-3.457851,55.982406],"type":"Point"}
}
