{
  "type": "Feature",
  "properties": {
    "date:inception_lower":"1991-07-01",
    "date:inception_upper":"1991-07-31",
    "iso:country":"GB",
    "wof:name":"EH52 6QL",
    "wof:placetype":"postalcode"
},
  "geometry": {"coordinates":[-3.457851,55.982406],"type":"Point"}
}