{
  "type": "Feature",
  "properties": {
    "iso:country":"GB",
    "wof:name":"LN1 2YF",
    "wof:placetype":"postalcode"
},
  "geometry": {"coordinates":[-0.65907894470339,53.26664377563788],"type":"Point"}
}