{
  "type": "Feature",
  "properties": {
    "date:inception_lower":"2014-12-01",
    "date:inception_upper":"2014-12-31",
    "iso:country":"GB",
    "wof:name":"LN1 2YF",
    "wof:placetype":"postalcode"
},
  "geometry": {"coordinates":[-0.659107,53.266719],"type":"Point"}
}