{
  "type": "Feature",
  "properties": {
    "iso:country":"GB",
    "wof:name":"CR0 7QU",
    "wof:placetype":"postalcode"
},
  "geometry": {"coordinates":[-0.04302921451584,51.38804887902858],"type":"Point"}
}