{
  "type": "Feature",
  "properties": {
    "iso:country":"GB",
    "wof:name":"GL54 2BL",
    "wof:placetype":"postalcode"
},
  "geometry": {"coordinates":[-1.75718666748472,51.88287458464215],"type":"Point"}
}