{
  "type": "Feature",
  "properties": {
    "date:inception_lower": "1980-01-01",
    "date:inception_upper": "1980-01-01",
    "iso:country": "GB",
    "wof:name": "KA8 9EJ",
    "wof:placetype": "postalcode"
  },
  "geometry": {"coordinates":[-4.61502,55.479101],"type":"Point"}
}
