{
  "type": "Feature",
  "properties": {
    "iso:country": "GB",
    "wof:name": "KA8 9EJ",
    "wof:placetype": "postalcode"
  },
  "geometry": {"coordinates":[-4.61502,55.479101],"type":"Point"}
}
