{
  "type": "Feature",
  "properties": {
    "iso:country":"GB",
    "wof:name":"KA8 9EJ",
    "wof:placetype":"postalcode"
},
  "geometry": {"coordinates":[-4.61501981797541,55.47910127328469],"type":"Point"}
}