{
  "type": "Feature",
  "properties": {
    "iso:country": "GB",
    "wof:name": "SA61 2BW",
    "wof:placetype": "postalcode"
  },
  "geometry": {"coordinates":[-4.970403,51.801281],"type":"Point"}
}
