{
  "type": "Feature",
  "properties": {
    "iso:country":"GB",
    "wof:name":"AL5 4BW",
    "wof:placetype":"postalcode"
},
  "geometry": {"coordinates":[-0.36521701720116,51.823925714778],"type":"Point"}
}