{
  "type": "Feature",
  "properties": {
    "date:inception_lower": "1983-07-01",
    "date:inception_upper": "1983-07-01",
    "iso:country": "GB",
    "wof:name": "AL5 4BW",
    "wof:placetype": "postalcode"
  },
  "geometry": {"coordinates":[-0.365217,51.823926],"type":"Point"}
}
