{
  "type": "Feature",
  "properties": {
    "iso:country":"GB",
    "wof:name":"WN5 7XR",
    "wof:placetype":"postalcode"
},
  "geometry": {"coordinates":[-2.70280297426481,53.50390138158787],"type":"Point"}
}