{
  "type": "Feature",
  "properties": {
    "iso:country":"GB",
    "wof:name":"PL15 9DU",
    "wof:placetype":"postalcode"
},
  "geometry": {"coordinates":[-4.35930933036807,50.6368923784651],"type":"Point"}
}