{
  "type": "Feature",
  "properties": {
    "iso:country": "GB",
    "wof:name": "IP12 4DY",
    "wof:placetype": "postalcode"
  },
  "geometry": {"coordinates":[1.301502,52.089814],"type":"Point"}
}
