{
  "type": "Feature",
  "properties": {
    "iso:country":"GB",
    "wof:name":"IP12 4DY",
    "wof:placetype":"postalcode"
},
  "geometry": {"coordinates":[1.30150225921296,52.08981378720293],"type":"Point"}
}