{
  "type": "Feature",
  "properties": {
    "iso:country":"GB",
    "wof:name":"MK17 0HE",
    "wof:placetype":"postalcode"
},
  "geometry": {"coordinates":[-0.91663181265976,52.01072346431091],"type":"Point"}
}