{
  "type": "Feature",
  "properties": {
    "iso:country":"GB",
    "wof:name":"SA3 4RB",
    "wof:placetype":"postalcode"
},
  "geometry": {"coordinates":[-4.01787414988508,51.57110606961161],"type":"Point"}
}