{
  "type": "Feature",
  "properties": {
    "date:inception_lower":"1980-01-01",
    "date:inception_upper":"1980-01-31",
    "iso:country":"GB",
    "wof:name":"SA3 4RB",
    "wof:placetype":"postalcode"
},
  "geometry": {"coordinates":[-4.017874,51.571106],"type":"Point"}
}