{
  "type": "Feature",
  "properties": {
    "iso:country": "GB",
    "wof:name": "GL12 7EY",
    "wof:placetype": "postalcode"
  },
  "geometry": {"coordinates":[-2.350819,51.635552],"type":"Point"}
}
