{
  "type": "Feature",
  "properties": {
    "iso:country":"GB",
    "wof:name":"GL12 7EY",
    "wof:placetype":"postalcode"
},
  "geometry": {"coordinates":[-2.35081907074706,51.63555227129588],"type":"Point"}
}