{
  "type": "Feature",
  "properties": {
    "iso:country":"GB",
    "wof:name":"KT15 3NY",
    "wof:placetype":"postalcode"
},
  "geometry": {"coordinates":[-0.50214957676003,51.34774218307123],"type":"Point"}
}