{
  "type": "Feature",
  "properties": {
    "iso:country": "GB",
    "wof:name": "DY9 8JT",
    "wof:placetype": "postalcode"
  },
  "geometry": {"coordinates":[-2.116846,52.458469],"type":"Point"}
}
