{
  "type": "Feature",
  "properties": {
    "iso:country": "GB",
    "wof:name": "PR6 9PE",
    "wof:placetype": "postalcode"
  },
  "geometry": {"coordinates":[-2.593184,53.620699],"type":"Point"}
}
