{
  "type": "Feature",
  "properties": {
    "iso:country":"GB",
    "wof:name":"PR6 9PE",
    "wof:placetype":"postalcode"
},
  "geometry": {"coordinates":[-2.59318389961607,53.62069853291369],"type":"Point"}
}