{
  "type": "Feature",
  "properties": {
    "iso:country": "GB",
    "wof:name": "IG6 2HR",
    "wof:placetype": "postalcode"
  },
  "geometry": {"coordinates":[0.08019,51.59785],"type":"Point"}
}
