{
  "type": "Feature",
  "properties": {
    "iso:country": "GB",
    "wof:name": "DN15 9PU",
    "wof:placetype": "postalcode"
  },
  "geometry": {"coordinates":[-0.599712,53.655171],"type":"Point"}
}
