{
  "type": "Feature",
  "properties": {
    "iso:country":"GB",
    "wof:name":"DN15 9PU",
    "wof:placetype":"postalcode"
},
  "geometry": {"coordinates":[-0.59960258749263,53.65511351078271],"type":"Point"}
}