{
  "type": "Feature",
  "properties": {
    "iso:country":"GB",
    "wof:name":"SA4 9AN",
    "wof:placetype":"postalcode"
},
  "geometry": {"coordinates":[-3.99921003464596,51.67153045247917],"type":"Point"}
}