{
  "type": "Feature",
  "properties": {
    "date:inception_lower": "2002-06-01",
    "date:inception_upper": "2002-06-01",
    "iso:country": "GB",
    "wof:name": "SA4 9AN",
    "wof:placetype": "postalcode"
  },
  "geometry": {"coordinates":[-3.99921,51.67153],"type":"Point"}
}
