{
  "type": "Feature",
  "properties": {
    "date:inception_lower": "2024-01-01",
    "date:inception_upper": "2024-01-01",
    "iso:country": "GB",
    "wof:name": "DL9 4DA",
    "wof:placetype": "postalcode"
  },
  "geometry": {"coordinates":[-1.676427,54.382561],"type":"Point"}
}
