{
  "type": "Feature",
  "properties": {
    "iso:country":"GB",
    "wof:name":"NP10 8LQ",
    "wof:placetype":"postalcode"
},
  "geometry": {"coordinates":[-3.0559182940523,51.57771885999311],"type":"Point"}
}