{
  "type": "Feature",
  "properties": {
    "iso:country":"GB",
    "wof:name":"NP22 5QX",
    "wof:placetype":"postalcode"
},
  "geometry": {"coordinates":[-3.30154513771757,51.77557792995787],"type":"Point"}
}