{
  "type": "Feature",
  "properties": {
    "iso:country":"GB",
    "wof:name":"BS8 1AT",
    "wof:placetype":"postalcode"
},
  "geometry": {"coordinates":[-2.6099297136829,51.45718817113985],"type":"Point"}
}