{
  "type": "Feature",
  "properties": {
    "iso:country": "GB",
    "wof:name": "BS8 1AT",
    "wof:placetype": "postalcode"
  },
  "geometry": {"coordinates":[-2.60993,51.457188],"type":"Point"}
}
