{
  "type": "Feature",
  "properties": {
    "iso:country":"GB",
    "wof:name":"TW15 2HQ",
    "wof:placetype":"postalcode"
},
  "geometry": {"coordinates":[-0.45503291295835,51.43617254062009],"type":"Point"}
}