{
  "type": "Feature",
  "properties": {
    "iso:country":"GB",
    "wof:name":"IP3 8QH",
    "wof:placetype":"postalcode"
},
  "geometry": {"coordinates":[1.20923901123316,52.04833818163917],"type":"Point"}
}