{
  "type": "Feature",
  "properties": {
    "iso:country":"GB",
    "wof:name":"SN25 1QZ",
    "wof:placetype":"postalcode"
},
  "geometry": {"coordinates":[-1.8137777544151,51.59975788390583],"type":"Point"}
}