{
  "type": "Feature",
  "properties": {
    "iso:country":"GB",
    "wof:name":"L25 5JL",
    "wof:placetype":"postalcode"
},
  "geometry": {"coordinates":[-2.86726645971376,53.37626771390295],"type":"Point"}
}