{
  "type": "Feature",
  "properties": {
    "iso:country":"GB",
    "wof:name":"L40 0SS",
    "wof:placetype":"postalcode"
},
  "geometry": {"coordinates":[-2.84061240668695,53.60700960380534],"type":"Point"}
}