{
  "type": "Feature",
  "properties": {
    "iso:country": "GB",
    "wof:name": "L40 0SS",
    "wof:placetype": "postalcode"
  },
  "geometry": {"coordinates":[-2.840612,53.60701],"type":"Point"}
}
