{
  "type": "Feature",
  "properties": {
    "date:inception_lower": "1980-01-01",
    "date:inception_upper": "1980-01-01",
    "iso:country": "GB",
    "wof:name": "CT21 4DZ",
    "wof:placetype": "postalcode"
  },
  "geometry": {"coordinates":[1.068345,51.070781],"type":"Point"}
}
