{
  "type": "Feature",
  "properties": {
    "date:inception_lower": "2019-06-01",
    "date:inception_upper": "2019-06-01",
    "iso:country": "GB",
    "wof:name": "AB12 3ZF",
    "wof:placetype": "postalcode"
  },
  "geometry": {"coordinates":[-2.098352,57.102204],"type":"Point"}
}
