{
  "type": "Feature",
  "properties": {
    "iso:country":"GB",
    "wof:name":"TN11 8QS",
    "wof:placetype":"postalcode"
},
  "geometry": {"coordinates":[0.2174269203999,51.1954856872664],"type":"Point"}
}