{
  "type": "Feature",
  "properties": {
    "iso:country":"GB",
    "wof:name":"RH14 0HS",
    "wof:placetype":"postalcode"
},
  "geometry": {"coordinates":[-0.54049375060536,50.99868421725645],"type":"Point"}
}