{
  "type": "Feature",
  "properties": {
    "date:inception_lower": "1980-01-01",
    "date:inception_upper": "1980-01-01",
    "iso:country": "GB",
    "wof:name": "RH14 0HS",
    "wof:placetype": "postalcode"
  },
  "geometry": {"coordinates":[-0.540494,50.998684],"type":"Point"}
}
