{
  "type": "Feature",
  "properties": {
    "date:inception_lower": "1980-01-01",
    "date:inception_upper": "1980-01-01",
    "iso:country": "GB",
    "wof:name": "NG19 7AB",
    "wof:placetype": "postalcode"
  },
  "geometry": {"coordinates":[-1.201012,53.148184],"type":"Point"}
}
