{
  "type": "Feature",
  "properties": {
    "iso:country":"GB",
    "wof:name":"TN12 0LT",
    "wof:placetype":"postalcode"
},
  "geometry": {"coordinates":[0.5490619524197,51.16103586041944],"type":"Point"}
}