{
  "type": "Feature",
  "properties": {
    "iso:country": "GB",
    "wof:name": "TN12 0LT",
    "wof:placetype": "postalcode"
  },
  "geometry": {"coordinates":[0.549062,51.161036],"type":"Point"}
}
