{
  "type": "Feature",
  "properties": {
    "iso:country":"GB",
    "wof:name":"HP19 9DL",
    "wof:placetype":"postalcode"
},
  "geometry": {"coordinates":[-0.83441440202871,51.82756004652523],"type":"Point"}
}