{
  "type": "Feature",
  "properties": {
    "iso:country": "GB",
    "wof:name": "HP19 9DL",
    "wof:placetype": "postalcode"
  },
  "geometry": {"coordinates":[-0.834414,51.82756],"type":"Point"}
}
