{
  "type": "Feature",
  "properties": {
    "date:inception_lower": "2009-06-01",
    "date:inception_upper": "2009-06-01",
    "iso:country": "GB",
    "wof:name": "HP19 9DL",
    "wof:placetype": "postalcode"
  },
  "geometry": {"coordinates":[-0.834414,51.82756],"type":"Point"}
}
