{
  "type": "Feature",
  "properties": {
    "iso:country": "GB",
    "wof:name": "HU9 4DN",
    "wof:placetype": "postalcode"
  },
  "geometry": {"coordinates":[-0.265598,53.769517],"type":"Point"}
}
