{
  "type": "Feature",
  "properties": {
    "date:inception_lower": "1980-01-01",
    "date:inception_upper": "1980-01-01",
    "iso:country": "GB",
    "wof:name": "SN16 9PY",
    "wof:placetype": "postalcode"
  },
  "geometry": {"coordinates":[-1.99265,51.622107],"type":"Point"}
}
