{
  "type": "Feature",
  "properties": {
    "iso:country":"GB",
    "wof:name":"SN16 9PY",
    "wof:placetype":"postalcode"
},
  "geometry": {"coordinates":[-1.99255621116322,51.62263492978242],"type":"Point"}
}