{
  "type": "Feature",
  "properties": {
    "iso:country":"GB",
    "wof:name":"NN5 6EP",
    "wof:placetype":"postalcode"
},
  "geometry": {"coordinates":[-0.96434610856851,52.25221523535954],"type":"Point"}
}