{
  "type": "Feature",
  "properties": {
    "date:inception_lower": "1986-07-01",
    "date:inception_upper": "1986-07-01",
    "iso:country": "GB",
    "wof:name": "NN5 6EP",
    "wof:placetype": "postalcode"
  },
  "geometry": {"coordinates":[-0.964346,52.252215],"type":"Point"}
}
