{
  "type": "Feature",
  "properties": {
    "iso:country":"GB",
    "wof:name":"TR8 5PE",
    "wof:placetype":"postalcode"
},
  "geometry": {"coordinates":[-5.13739845948274,50.38628513535968],"type":"Point"}
}