{
  "type": "Feature",
  "properties": {
    "date:inception_lower":"1992-01-01",
    "date:inception_upper":"1992-01-31",
    "iso:country":"GB",
    "wof:name":"TR8 5PE",
    "wof:placetype":"postalcode"
},
  "geometry": {"coordinates":[-5.137398,50.386285],"type":"Point"}
}