{
  "type": "Feature",
  "properties": {
    "iso:country": "GB",
    "wof:name": "TR8 5PE",
    "wof:placetype": "postalcode"
  },
  "geometry": {"coordinates":[-5.137398,50.386285],"type":"Point"}
}
