{
  "type": "Feature",
  "properties": {
    "date:inception_lower": "1994-05-01",
    "date:inception_upper": "1994-05-01",
    "iso:country": "GB",
    "wof:name": "KT8 2TJ",
    "wof:placetype": "postalcode"
  },
  "geometry": {"coordinates":[-0.380971,51.404734],"type":"Point"}
}
