{
  "type": "Feature",
  "properties": {
    "iso:country":"GB",
    "wof:name":"ST5 6AL",
    "wof:placetype":"postalcode"
},
  "geometry": {"coordinates":[-2.30508853533227,53.02100157830976],"type":"Point"}
}