{
  "type": "Feature",
  "properties": {
    "date:inception_lower":"1980-01-01",
    "date:inception_upper":"1980-01-31",
    "iso:country":"GB",
    "wof:name":"RM17 6EL",
    "wof:placetype":"postalcode"
},
  "geometry": {"coordinates":[0.32332,51.477458],"type":"Point"}
}