{
  "type": "Feature",
  "properties": {
    "iso:country":"GB",
    "wof:name":"TW16 5PN",
    "wof:placetype":"postalcode"
},
  "geometry": {"coordinates":[-0.39699854445196,51.40892881570293],"type":"Point"}
}