{
  "type": "Feature",
  "properties": {
    "iso:country":"GB",
    "wof:name":"LL16 4LN",
    "wof:placetype":"postalcode"
},
  "geometry": {"coordinates":[-3.30105265436857,53.16107557145593],"type":"Point"}
}