{
  "type": "Feature",
  "properties": {
    "iso:country": "GB",
    "wof:name": "LL16 4LN",
    "wof:placetype": "postalcode"
  },
  "geometry": {"coordinates":[-3.301053,53.161076],"type":"Point"}
}
