{
  "type": "Feature",
  "properties": {
    "date:inception_lower":"1983-07-01",
    "date:inception_upper":"1983-07-31",
    "iso:country":"GB",
    "wof:name":"LL16 4LN",
    "wof:placetype":"postalcode"
},
  "geometry": {"coordinates":[-3.301053,53.161076],"type":"Point"}
}