{
  "type": "Feature",
  "properties": {
    "iso:country":"GB",
    "wof:name":"SY20 9AY",
    "wof:placetype":"postalcode"
},
  "geometry": {"coordinates":[-3.85660701896641,52.61672577046367],"type":"Point"}
}