{
  "type": "Feature",
  "properties": {
    "date:inception_lower": "1980-01-01",
    "date:inception_upper": "1980-01-01",
    "iso:country": "GB",
    "wof:name": "SY20 9AY",
    "wof:placetype": "postalcode"
  },
  "geometry": {"coordinates":[-3.856607,52.616726],"type":"Point"}
}
