{
  "type": "Feature",
  "properties": {
    "iso:country":"GB",
    "wof:name":"UB10 8QX",
    "wof:placetype":"postalcode"
},
  "geometry": {"coordinates":[-0.44366948074259,51.56341483131722],"type":"Point"}
}