{
  "type": "Feature",
  "properties": {
    "date:inception_lower": "2020-10-01",
    "date:inception_upper": "2020-10-01",
    "iso:country": "GB",
    "wof:name": "LN2 4ZH",
    "wof:placetype": "postalcode"
  },
  "geometry": {"coordinates":[-0.493989,53.241152],"type":"Point"}
}
