{
  "type": "Feature",
  "properties": {
    "date:inception_lower": "2001-06-01",
    "date:inception_upper": "2001-06-01",
    "iso:country": "GB",
    "wof:name": "CT18 7QZ",
    "wof:placetype": "postalcode"
  },
  "geometry": {"coordinates":[1.152042,51.110747],"type":"Point"}
}
