{
  "type": "Feature",
  "properties": {
    "iso:country":"GB",
    "wof:name":"CT18 7QZ",
    "wof:placetype":"postalcode"
},
  "geometry": {"coordinates":[1.15204165561103,51.11074741479187],"type":"Point"}
}