{
  "type": "Feature",
  "properties": {
    "iso:country":"GB",
    "wof:name":"BN2 6TJ",
    "wof:placetype":"postalcode"
},
  "geometry": {"coordinates":[-0.06038506314254,50.8306360584346],"type":"Point"}
}