{
  "type": "Feature",
  "properties": {
    "iso:country":"GB",
    "wof:name":"KW17 2HQ",
    "wof:placetype":"postalcode"
},
  "geometry": {"coordinates":[-3.09157769941511,59.03077169256326],"type":"Point"}
}