{
  "type": "Feature",
  "properties": {
    "iso:country": "GB",
    "wof:name": "KW17 2HQ",
    "wof:placetype": "postalcode"
  },
  "geometry": {"coordinates":[-3.091586,59.030764],"type":"Point"}
}
