{
  "type": "Feature",
  "properties": {
    "iso:country":"GB",
    "wof:name":"PL5 2LX",
    "wof:placetype":"postalcode"
},
  "geometry": {"coordinates":[-4.16500555701599,50.41078390847019],"type":"Point"}
}