{
  "type": "Feature",
  "properties": {
    "iso:country":"GB",
    "wof:name":"S43 1AA",
    "wof:placetype":"postalcode"
},
  "geometry": {"coordinates":[-1.40101483221483,53.25521207660272],"type":"Point"}
}