{
  "type": "Feature",
  "properties": {
    "iso:country": "GB",
    "wof:name": "SR5 1EQ",
    "wof:placetype": "postalcode"
  },
  "geometry": {"coordinates":[-1.38593,54.916122],"type":"Point"}
}
