{
  "type": "Feature",
  "properties": {
    "iso:country":"GB",
    "wof:name":"SR5 1EQ",
    "wof:placetype":"postalcode"
},
  "geometry": {"coordinates":[-1.38593001648634,54.91612229714927],"type":"Point"}
}