{
  "type": "Feature",
  "properties": {
    "iso:country":"GB",
    "wof:name":"SA17 5TL",
    "wof:placetype":"postalcode"
},
  "geometry": {"coordinates":[-4.35842182793432,51.77519722035466],"type":"Point"}
}