{
  "type": "Feature",
  "properties": {
    "date:inception_lower": "1980-01-01",
    "date:inception_upper": "1980-01-01",
    "iso:country": "GB",
    "wof:name": "S5 7SQ",
    "wof:placetype": "postalcode"
  },
  "geometry": {"coordinates":[-1.45995,53.42423],"type":"Point"}
}
