{
  "type": "Feature",
  "properties": {
    "date:inception_lower": "2015-10-01",
    "date:inception_upper": "2015-10-01",
    "iso:country": "GB",
    "wof:name": "SE10 0SN",
    "wof:placetype": "postalcode"
  },
  "geometry": {"coordinates":[0.011924,51.496228],"type":"Point"}
}
