{
  "type": "Feature",
  "properties": {
    "iso:country":"GB",
    "wof:name":"WA8 6AS",
    "wof:placetype":"postalcode"
},
  "geometry": {"coordinates":[-2.73046221196587,53.3639879230285],"type":"Point"}
}