{
  "type": "Feature",
  "properties": {
    "iso:country": "GB",
    "wof:name": "DL17 0LW",
    "wof:placetype": "postalcode"
  },
  "geometry": {"coordinates":[-1.565719,54.653321],"type":"Point"}
}
