{
  "type": "Feature",
  "properties": {
    "date:inception_lower": "1980-01-01",
    "date:inception_upper": "1980-01-01",
    "iso:country": "GB",
    "wof:name": "DL17 0LW",
    "wof:placetype": "postalcode"
  },
  "geometry": {"coordinates":[-1.565719,54.653321],"type":"Point"}
}
