{
  "type": "Feature",
  "properties": {
    "iso:country":"GB",
    "wof:name":"BH21 2US",
    "wof:placetype":"postalcode"
},
  "geometry": {"coordinates":[-1.94230178682472,50.80588623048643],"type":"Point"}
}