{
  "type": "Feature",
  "properties": {
    "iso:country":"GB",
    "wof:name":"SG13 7QY",
    "wof:placetype":"postalcode"
},
  "geometry": {"coordinates":[-0.0419699291497,51.78714624656966],"type":"Point"}
}