{
  "type": "Feature",
  "properties": {
    "iso:country":"GB",
    "wof:name":"NE46 3PQ",
    "wof:placetype":"postalcode"
},
  "geometry": {"coordinates":[-2.09968090732914,54.97211466960984],"type":"Point"}
}