{
  "type": "Feature",
  "properties": {
    "iso:country": "GB",
    "wof:name": "NE46 3PQ",
    "wof:placetype": "postalcode"
  },
  "geometry": {"coordinates":[-2.099721,54.972085],"type":"Point"}
}
