{
  "type": "Feature",
  "properties": {
    "iso:country": "GB",
    "wof:name": "SE17 1FE",
    "wof:placetype": "postalcode"
  },
  "geometry": {"coordinates":[-0.096218,51.491713],"type":"Point"}
}
