{
  "type": "Feature",
  "properties": {
    "iso:country": "GB",
    "wof:name": "LL21 0HP",
    "wof:placetype": "postalcode"
  },
  "geometry": {"coordinates":[-3.402419,52.962146],"type":"Point"}
}
