{
  "type": "Feature",
  "properties": {
    "date:inception_lower":"1980-01-01",
    "date:inception_upper":"1980-01-31",
    "iso:country":"GB",
    "wof:name":"LL21 0HP",
    "wof:placetype":"postalcode"
},
  "geometry": {"coordinates":[-3.402419,52.962146],"type":"Point"}
}