{
  "type": "Feature",
  "properties": {
    "iso:country":"GB",
    "wof:name":"LS12 5QT",
    "wof:placetype":"postalcode"
},
  "geometry": {"coordinates":[-1.61301999368877,53.78854490168047],"type":"Point"}
}