{
  "type": "Feature",
  "properties": {
    "date:inception_lower":"1980-01-01",
    "date:inception_upper":"1980-01-31",
    "iso:country":"GB",
    "wof:name":"YO22 5NB",
    "wof:placetype":"postalcode"
},
  "geometry": {"coordinates":[-0.718629,54.403491],"type":"Point"}
}