{
  "type": "Feature",
  "properties": {
    "iso:country":"GB",
    "wof:name":"YO22 5NB",
    "wof:placetype":"postalcode"
},
  "geometry": {"coordinates":[-0.71862901776702,54.40349095604413],"type":"Point"}
}