{
  "type": "Feature",
  "properties": {
    "date:inception_lower": "1980-01-01",
    "date:inception_upper": "1980-01-01",
    "iso:country": "GB",
    "wof:name": "B17 9NJ",
    "wof:placetype": "postalcode"
  },
  "geometry": {"coordinates":[-1.94615,52.459651],"type":"Point"}
}
