{
  "type": "Feature",
  "properties": {
    "date:inception_lower": "1980-01-01",
    "date:inception_upper": "1980-01-01",
    "iso:country": "GB",
    "wof:name": "IG11 8LA",
    "wof:placetype": "postalcode"
  },
  "geometry": {"coordinates":[0.07425,51.541348],"type":"Point"}
}
