{
  "type": "Feature",
  "properties": {
    "iso:country":"GB",
    "wof:name":"IG11 8LA",
    "wof:placetype":"postalcode"
},
  "geometry": {"coordinates":[0.07433294966663,51.54121907778779],"type":"Point"}
}