{
  "type": "Feature",
  "properties": {
    "iso:country":"GB",
    "wof:name":"YO42 2WD",
    "wof:placetype":"postalcode"
},
  "geometry": {"coordinates":[-0.77452951194046,53.93201004730763],"type":"Point"}
}