{
  "type": "Feature",
  "properties": {
    "date:inception_lower":"1994-12-01",
    "date:inception_upper":"1994-12-31",
    "iso:country":"GB",
    "wof:name":"PR1 5DQ",
    "wof:placetype":"postalcode"
},
  "geometry": {"coordinates":[-2.686638,53.76349],"type":"Point"}
}