{
  "type": "Feature",
  "properties": {
    "date:inception_lower": "1994-12-01",
    "date:inception_upper": "1994-12-01",
    "iso:country": "GB",
    "wof:name": "PR1 5DQ",
    "wof:placetype": "postalcode"
  },
  "geometry": {"coordinates":[-2.68523,53.762903],"type":"Point"}
}
