{
  "type": "Feature",
  "properties": {
    "iso:country": "GB",
    "wof:name": "G64 4AW",
    "wof:placetype": "postalcode"
  },
  "geometry": {"coordinates":[-4.245197,55.93757],"type":"Point"}
}
