{
  "type": "Feature",
  "properties": {
    "iso:country":"GB",
    "wof:name":"G64 4AW",
    "wof:placetype":"postalcode"
},
  "geometry": {"coordinates":[-4.2451965930042,55.93757042522504],"type":"Point"}
}