{
  "type": "Feature",
  "properties": {
    "iso:country":"GB",
    "wof:name":"DH8 9RP",
    "wof:placetype":"postalcode"
},
  "geometry": {"coordinates":[-1.9484600793176,54.90303168476277],"type":"Point"}
}