{
  "type": "Feature",
  "properties": {
    "iso:country": "GB",
    "wof:name": "DH8 9RP",
    "wof:placetype": "postalcode"
  },
  "geometry": {"coordinates":[-1.948469,54.903039],"type":"Point"}
}
