{
  "type": "Feature",
  "properties": {
    "iso:country":"GB",
    "wof:name":"PE12 7HS",
    "wof:placetype":"postalcode"
},
  "geometry": {"coordinates":[-0.00198250948348,52.80106936709254],"type":"Point"}
}