{
  "type": "Feature",
  "properties": {
    "iso:country":"GB",
    "wof:name":"S61 4HZ",
    "wof:placetype":"postalcode"
},
  "geometry": {"coordinates":[-1.38485282227824,53.45380869785912],"type":"Point"}
}