{
  "type": "Feature",
  "properties": {
    "iso:country":"GB",
    "wof:name":"ST14 8TG",
    "wof:placetype":"postalcode"
},
  "geometry": {"coordinates":[-1.87970198421098,52.89096206043437],"type":"Point"}
}