{
  "type": "Feature",
  "properties": {
    "iso:country": "GB",
    "wof:name": "ST14 8TG",
    "wof:placetype": "postalcode"
  },
  "geometry": {"coordinates":[-1.879702,52.890962],"type":"Point"}
}
