{
  "type": "Feature",
  "properties": {
    "date:inception_lower": "1991-09-01",
    "date:inception_upper": "1991-09-01",
    "iso:country": "GB",
    "wof:name": "ST14 8TG",
    "wof:placetype": "postalcode"
  },
  "geometry": {"coordinates":[-1.879702,52.890962],"type":"Point"}
}
