{
  "type": "Feature",
  "properties": {
    "date:inception_lower": "2023-07-01",
    "date:inception_upper": "2023-07-01",
    "iso:country": "GB",
    "wof:name": "L12 2BF",
    "wof:placetype": "postalcode"
  },
  "geometry": {"coordinates":[-2.901419,53.421137],"type":"Point"}
}
