{
  "type": "Feature",
  "properties": {
    "date:inception_lower":"1998-12-01",
    "date:inception_upper":"1998-12-31",
    "iso:country":"GB",
    "wof:name":"KY13 0QF",
    "wof:placetype":"postalcode"
},
  "geometry": {"coordinates":[-3.596118,56.168251],"type":"Point"}
}