{
  "type": "Feature",
  "properties": {
    "iso:country":"GB",
    "wof:name":"KY13 0QF",
    "wof:placetype":"postalcode"
},
  "geometry": {"coordinates":[-3.59611778512875,56.16825115315248],"type":"Point"}
}