{
  "type": "Feature",
  "properties": {
    "date:inception_lower":"2014-12-01",
    "date:inception_upper":"2014-12-31",
    "iso:country":"GB",
    "wof:name":"SN25 2PT",
    "wof:placetype":"postalcode"
},
  "geometry": {"coordinates":[-1.819415,51.609758],"type":"Point"}
}