{
  "type": "Feature",
  "properties": {
    "iso:country":"GB",
    "wof:name":"LS12 2PB",
    "wof:placetype":"postalcode"
},
  "geometry": {"coordinates":[-1.58658849761078,53.80148939613934],"type":"Point"}
}