{
  "type": "Feature",
  "properties": {
    "date:inception_lower": "1980-01-01",
    "date:inception_upper": "1980-01-01",
    "iso:country": "GB",
    "wof:name": "PR1 8JR",
    "wof:placetype": "postalcode"
  },
  "geometry": {"coordinates":[-2.707808,53.74957],"type":"Point"}
}
