{
  "type": "Feature",
  "properties": {
    "iso:country":"GB",
    "wof:name":"SA65 9HE",
    "wof:placetype":"postalcode"
},
  "geometry": {"coordinates":[-4.9758481558414,51.99376579633729],"type":"Point"}
}