{
  "type": "Feature",
  "properties": {
    "date:inception_lower": "2017-05-01",
    "date:inception_upper": "2017-05-01",
    "iso:country": "GB",
    "wof:name": "B93 0FF",
    "wof:placetype": "postalcode"
  },
  "geometry": {"coordinates":[-1.740136,52.37824],"type":"Point"}
}
