{
  "type": "Feature",
  "properties": {
    "iso:country":"GB",
    "wof:name":"PE13 1BD",
    "wof:placetype":"postalcode"
},
  "geometry": {"coordinates":[0.16111935199231,52.665562305058],"type":"Point"}
}