{
  "type": "Feature",
  "properties": {
    "iso:country":"GB",
    "wof:name":"CM23 4PD",
    "wof:placetype":"postalcode"
},
  "geometry": {"coordinates":[0.13702174621015,51.87163264599983],"type":"Point"}
}