{
  "type": "Feature",
  "properties": {
    "date:inception_lower": "1991-09-01",
    "date:inception_upper": "1991-09-01",
    "iso:country": "GB",
    "wof:name": "CM23 4PD",
    "wof:placetype": "postalcode"
  },
  "geometry": {"coordinates":[0.137022,51.871633],"type":"Point"}
}
