{
  "type": "Feature",
  "properties": {
    "iso:country": "GB",
    "wof:name": "CM23 4PD",
    "wof:placetype": "postalcode"
  },
  "geometry": {"coordinates":[0.137022,51.871633],"type":"Point"}
}
