{
  "type": "Feature",
  "properties": {
    "iso:country":"GB",
    "wof:name":"BH12 2NF",
    "wof:placetype":"postalcode"
},
  "geometry": {"coordinates":[-1.93918893049086,50.73276586107397],"type":"Point"}
}