{
  "type": "Feature",
  "properties": {
    "iso:country": "GB",
    "wof:name": "OX26 2JL",
    "wof:placetype": "postalcode"
  },
  "geometry": {"coordinates":[-1.163874,51.899442],"type":"Point"}
}
