{
  "type": "Feature",
  "properties": {
    "iso:country":"GB",
    "wof:name":"DH1 5BT",
    "wof:placetype":"postalcode"
},
  "geometry": {"coordinates":[-1.5900272205186,54.79897168209032],"type":"Point"}
}