{
  "type": "Feature",
  "properties": {
    "date:inception_lower": "2007-12-01",
    "date:inception_upper": "2007-12-01",
    "iso:country": "GB",
    "wof:name": "DH1 5BT",
    "wof:placetype": "postalcode"
  },
  "geometry": {"coordinates":[-1.589977,54.798927],"type":"Point"}
}
