{
  "type": "Feature",
  "properties": {
    "iso:country": "GB",
    "wof:name": "DH1 5BT",
    "wof:placetype": "postalcode"
  },
  "geometry": {"coordinates":[-1.590027,54.798972],"type":"Point"}
}
