{
  "type": "Feature",
  "properties": {
    "iso:country":"GB",
    "wof:name":"ML11 9JU",
    "wof:placetype":"postalcode"
},
  "geometry": {"coordinates":[-3.82311401761717,55.6729476851468],"type":"Point"}
}