{
  "type": "Feature",
  "properties": {
    "date:inception_lower": "2020-09-01",
    "date:inception_upper": "2020-09-01",
    "iso:country": "GB",
    "wof:name": "HG3 3DY",
    "wof:placetype": "postalcode"
  },
  "geometry": {"coordinates":[-1.625483,54.035909],"type":"Point"}
}
