{
  "type": "Feature",
  "properties": {
    "iso:country":"GB",
    "wof:name":"GL55 6TJ",
    "wof:placetype":"postalcode"
},
  "geometry": {"coordinates":[-1.76323062642468,52.09293732992171],"type":"Point"}
}