{
  "type": "Feature",
  "properties": {
    "iso:country":"GB",
    "wof:name":"SR7 7BE",
    "wof:placetype":"postalcode"
},
  "geometry": {"coordinates":[-1.33593886842637,54.8407860055194],"type":"Point"}
}