{
  "type": "Feature",
  "properties": {
    "iso:country":"GB",
    "wof:name":"YO24 3FF",
    "wof:placetype":"postalcode"
},
  "geometry": {"coordinates":[-1.12556254576384,53.95531012686726],"type":"Point"}
}