{
  "type": "Feature",
  "properties": {
    "iso:country": "GB",
    "wof:name": "YO24 3FF",
    "wof:placetype": "postalcode"
  },
  "geometry": {"coordinates":[-1.125562,53.95531],"type":"Point"}
}
