{
  "type": "Feature",
  "properties": {
    "iso:country":"GB",
    "wof:name":"CF44 9LX",
    "wof:placetype":"postalcode"
},
  "geometry": {"coordinates":[-3.56210350136227,51.73989791142913],"type":"Point"}
}