{
  "type": "Feature",
  "properties": {
    "iso:country": "GB",
    "wof:name": "CF44 9LX",
    "wof:placetype": "postalcode"
  },
  "geometry": {"coordinates":[-3.562103,51.739898],"type":"Point"}
}
