{
  "type": "Feature",
  "properties": {
    "date:inception_lower":"2000-10-01",
    "date:inception_upper":"2000-10-31",
    "iso:country":"GB",
    "wof:name":"OX26 5DE",
    "wof:placetype":"postalcode"
},
  "geometry": {"coordinates":[-1.118993,51.895032],"type":"Point"}
}