{
  "type": "Feature",
  "properties": {
    "iso:country":"GB",
    "wof:name":"OX26 5DE",
    "wof:placetype":"postalcode"
},
  "geometry": {"coordinates":[-1.11899263863004,51.89503249281353],"type":"Point"}
}