{
  "type": "Feature",
  "properties": {
    "date:inception_lower": "2017-03-01",
    "date:inception_upper": "2017-03-01",
    "iso:country": "GB",
    "wof:name": "SP9 7SX",
    "wof:placetype": "postalcode"
  },
  "geometry": {"coordinates":[-1.661043,51.228148],"type":"Point"}
}
