{
  "type": "Feature",
  "properties": {
    "iso:country":"GB",
    "wof:name":"GL7 2NJ",
    "wof:placetype":"postalcode"
},
  "geometry": {"coordinates":[-1.9801288221058,51.73407030704099],"type":"Point"}
}