{
  "type": "Feature",
  "properties": {
    "date:inception_lower": "2009-11-01",
    "date:inception_upper": "2009-11-01",
    "iso:country": "GB",
    "wof:name": "GL7 2NJ",
    "wof:placetype": "postalcode"
  },
  "geometry": {"coordinates":[-1.980129,51.73407],"type":"Point"}
}
