{
  "type": "Feature",
  "properties": {
    "iso:country":"GB",
    "wof:name":"LA22 0AX",
    "wof:placetype":"postalcode"
},
  "geometry": {"coordinates":[-2.95716292923281,54.42755742055481],"type":"Point"}
}