{
  "type": "Feature",
  "properties": {
    "iso:country":"GB",
    "wof:name":"AB15 8AS",
    "wof:placetype":"postalcode"
},
  "geometry": {"coordinates":[-2.1705031765115,57.12966579751309],"type":"Point"}
}