{
  "type": "Feature",
  "properties": {
    "iso:country":"GB",
    "wof:name":"LA5 0UG",
    "wof:placetype":"postalcode"
},
  "geometry": {"coordinates":[-2.81021235683158,54.17292076135055],"type":"Point"}
}