{
  "type": "Feature",
  "properties": {
    "iso:country": "GB",
    "wof:name": "PE11 3ZJ",
    "wof:placetype": "postalcode"
  },
  "geometry": {"coordinates":[-0.175695,52.779799],"type":"Point"}
}
