{
  "type": "Feature",
  "properties": {
    "iso:country":"GB",
    "wof:name":"PE11 3ZJ",
    "wof:placetype":"postalcode"
},
  "geometry": {"coordinates":[-0.17569515681011,52.77979017403809],"type":"Point"}
}