{
  "type": "Feature",
  "properties": {
    "iso:country": "GB",
    "wof:name": "LD3 7PG",
    "wof:placetype": "postalcode"
  },
  "geometry": {"coordinates":[-3.385401,51.94963],"type":"Point"}
}
