{
  "type": "Feature",
  "properties": {
    "iso:country":"GB",
    "wof:name":"LD3 7PG",
    "wof:placetype":"postalcode"
},
  "geometry": {"coordinates":[-3.38540086176026,51.94963043492195],"type":"Point"}
}