{
  "type": "Feature",
  "properties": {
    "iso:country":"GB",
    "wof:name":"BD16 4EP",
    "wof:placetype":"postalcode"
},
  "geometry": {"coordinates":[-1.83163732010951,53.85623539250295],"type":"Point"}
}