{
  "type": "Feature",
  "properties": {
    "iso:country": "GB",
    "wof:name": "BH25 5PP",
    "wof:placetype": "postalcode"
  },
  "geometry": {"coordinates":[-1.64116,50.737482],"type":"Point"}
}
