{
  "type": "Feature",
  "properties": {
    "iso:country":"GB",
    "wof:name":"SL4 4AJ",
    "wof:placetype":"postalcode"
},
  "geometry": {"coordinates":[-0.63956970083309,51.46883447575144],"type":"Point"}
}