{
  "type": "Feature",
  "properties": {
    "date:inception_lower": "1994-09-01",
    "date:inception_upper": "1994-09-01",
    "iso:country": "GB",
    "wof:name": "FK1 1DL",
    "wof:placetype": "postalcode"
  },
  "geometry": {"coordinates":[-3.788933,55.998233],"type":"Point"}
}
