{
  "type": "Feature",
  "properties": {
    "iso:country":"GB",
    "wof:name":"FK1 1DL",
    "wof:placetype":"postalcode"
},
  "geometry": {"coordinates":[-3.78893321938832,55.9982330936022],"type":"Point"}
}