{
  "type": "Feature",
  "properties": {
    "iso:country":"GB",
    "wof:name":"NE39 1PN",
    "wof:placetype":"postalcode"
},
  "geometry": {"coordinates":[-1.74303997161517,54.91888385774477],"type":"Point"}
}