{
  "type": "Feature",
  "properties": {
    "iso:country":"GB",
    "wof:name":"NR33 8SB",
    "wof:placetype":"postalcode"
},
  "geometry": {"coordinates":[1.70402866661499,52.456205220519],"type":"Point"}
}