{
  "type": "Feature",
  "properties": {
    "iso:country":"GB",
    "wof:name":"KT6 5BJ",
    "wof:placetype":"postalcode"
},
  "geometry": {"coordinates":[-0.30173088708833,51.38158076453494],"type":"Point"}
}