{
  "type": "Feature",
  "properties": {
    "iso:country": "GB",
    "wof:name": "RM17 6TP",
    "wof:placetype": "postalcode"
  },
  "geometry": {"coordinates":[0.342969,51.474189],"type":"Point"}
}
