{
  "type": "Feature",
  "properties": {
    "iso:country":"GB",
    "wof:name":"RM17 6TP",
    "wof:placetype":"postalcode"
},
  "geometry": {"coordinates":[0.3429686852763,51.47418886752994],"type":"Point"}
}