{
  "type": "Feature",
  "properties": {
    "date:inception_lower": "1984-10-01",
    "date:inception_upper": "1984-10-01",
    "iso:country": "GB",
    "wof:name": "RM17 6TP",
    "wof:placetype": "postalcode"
  },
  "geometry": {"coordinates":[0.342969,51.474189],"type":"Point"}
}
