{
  "type": "Feature",
  "properties": {
    "iso:country":"GB",
    "wof:name":"TW8 0EG",
    "wof:placetype":"postalcode"
},
  "geometry": {"coordinates":[-0.28862537899357,51.48898478851786],"type":"Point"}
}