{
  "type": "Feature",
  "properties": {
    "iso:country":"GB",
    "wof:name":"HR2 8QY",
    "wof:placetype":"postalcode"
},
  "geometry": {"coordinates":[-2.75989526413122,51.89032567891613],"type":"Point"}
}