{
  "type": "Feature",
  "properties": {
    "iso:country":"GB",
    "wof:name":"TA4 3HL",
    "wof:placetype":"postalcode"
},
  "geometry": {"coordinates":[-3.2164278366787,51.07351090045469],"type":"Point"}
}