{
  "type": "Feature",
  "properties": {
    "date:inception_lower": "2004-11-01",
    "date:inception_upper": "2004-11-01",
    "iso:country": "GB",
    "wof:name": "TA4 3HL",
    "wof:placetype": "postalcode"
  },
  "geometry": {"coordinates":[-3.216428,51.073511],"type":"Point"}
}
