{
  "type": "Feature",
  "properties": {
    "date:inception_lower": "1991-01-01",
    "date:inception_upper": "1991-01-01",
    "iso:country": "GB",
    "wof:name": "CR0 0XJ",
    "wof:placetype": "postalcode"
  },
  "geometry": {"coordinates":[-0.099602,51.369978],"type":"Point"}
}
