{
  "type": "Feature",
  "properties": {
    "iso:country":"GB",
    "wof:name":"CR0 0XJ",
    "wof:placetype":"postalcode"
},
  "geometry": {"coordinates":[-0.09960163773715,51.36997846832302],"type":"Point"}
}