{
  "type": "Feature",
  "properties": {
    "date:inception_lower":"1994-05-01",
    "date:inception_upper":"1994-05-31",
    "iso:country":"GB",
    "wof:name":"M27 4ET",
    "wof:placetype":"postalcode"
},
  "geometry": {"coordinates":[-2.330998,53.517599],"type":"Point"}
}