{
  "type": "Feature",
  "properties": {
    "iso:country":"GB",
    "wof:name":"M27 4ET",
    "wof:placetype":"postalcode"
},
  "geometry": {"coordinates":[-2.33099802022928,53.51759928352769],"type":"Point"}
}