{
  "type": "Feature",
  "properties": {
    "iso:country":"GB",
    "wof:name":"RM14 3HS",
    "wof:placetype":"postalcode"
},
  "geometry": {"coordinates":[0.26001466323744,51.55616105505394],"type":"Point"}
}