{
  "type": "Feature",
  "properties": {
    "date:inception_lower": "1980-01-01",
    "date:inception_upper": "1980-01-01",
    "iso:country": "GB",
    "wof:name": "KA8 9RL",
    "wof:placetype": "postalcode"
  },
  "geometry": {"coordinates":[-4.599573,55.472869],"type":"Point"}
}
