{
  "type": "Feature",
  "properties": {
    "iso:country":"GB",
    "wof:name":"KA8 9RL",
    "wof:placetype":"postalcode"
},
  "geometry": {"coordinates":[-4.59957346902092,55.47286865040997],"type":"Point"}
}