{
  "type": "Feature",
  "properties": {
    "iso:country":"GB",
    "wof:name":"PE33 9AX",
    "wof:placetype":"postalcode"
},
  "geometry": {"coordinates":[0.47944724389357,52.58370549304713],"type":"Point"}
}