{
  "type": "Feature",
  "properties": {
    "date:inception_lower": "2020-11-01",
    "date:inception_upper": "2020-11-01",
    "iso:country": "GB",
    "wof:name": "ME13 7FZ",
    "wof:placetype": "postalcode"
  },
  "geometry": {"coordinates":[0.869238,51.317991],"type":"Point"}
}
