{
  "type": "Feature",
  "properties": {
    "date:inception_lower":"1986-01-01",
    "date:inception_upper":"1986-01-31",
    "iso:country":"GB",
    "wof:name":"SO52 9EW",
    "wof:placetype":"postalcode"
},
  "geometry": {"coordinates":[-1.443397,50.975054],"type":"Point"}
}