{
  "type": "Feature",
  "properties": {
    "date:inception_lower": "2003-03-01",
    "date:inception_upper": "2003-03-01",
    "iso:country": "GB",
    "wof:name": "WS7 1AG",
    "wof:placetype": "postalcode"
  },
  "geometry": {"coordinates":[-1.933982,52.683896],"type":"Point"}
}
