{
  "type": "Feature",
  "properties": {
    "iso:country":"GB",
    "wof:name":"WS7 1AG",
    "wof:placetype":"postalcode"
},
  "geometry": {"coordinates":[-1.93398234483412,52.68389565260824],"type":"Point"}
}