{
  "type": "Feature",
  "properties": {
    "date:inception_lower": "2007-03-01",
    "date:inception_upper": "2007-03-01",
    "iso:country": "GB",
    "wof:name": "CW6 0EN",
    "wof:placetype": "postalcode"
  },
  "geometry": {"coordinates":[-2.73163,53.176774],"type":"Point"}
}
