{
  "type": "Feature",
  "properties": {
    "iso:country":"GB",
    "wof:name":"CW6 0EN",
    "wof:placetype":"postalcode"
},
  "geometry": {"coordinates":[-2.73158611650191,53.17678591105601],"type":"Point"}
}