{
  "type": "Feature",
  "properties": {
    "iso:country": "GB",
    "wof:name": "ME13 0RX",
    "wof:placetype": "postalcode"
  },
  "geometry": {"coordinates":[0.838934,51.288391],"type":"Point"}
}
