{
  "type": "Feature",
  "properties": {
    "date:inception_lower": "1980-01-01",
    "date:inception_upper": "1980-01-01",
    "iso:country": "GB",
    "wof:name": "ME13 0RX",
    "wof:placetype": "postalcode"
  },
  "geometry": {"coordinates":[0.838934,51.288391],"type":"Point"}
}
