{
  "type": "Feature",
  "properties": {
    "iso:country":"GB",
    "wof:name":"BL0 9BD",
    "wof:placetype":"postalcode"
},
  "geometry": {"coordinates":[-2.31769913932747,53.64680656106405],"type":"Point"}
}