{
  "type": "Feature",
  "properties": {
    "date:inception_lower": "1994-05-01",
    "date:inception_upper": "1994-05-01",
    "iso:country": "GB",
    "wof:name": "MK45 5HT",
    "wof:placetype": "postalcode"
  },
  "geometry": {"coordinates":[-0.469824,52.002288],"type":"Point"}
}
