{
  "type": "Feature",
  "properties": {
    "iso:country":"GB",
    "wof:name":"N15 6PU",
    "wof:placetype":"postalcode"
},
  "geometry": {"coordinates":[-0.08056533479313,51.57580621685393],"type":"Point"}
}