{
  "type": "Feature",
  "properties": {
    "iso:country":"GB",
    "wof:name":"LD6 5PB",
    "wof:placetype":"postalcode"
},
  "geometry": {"coordinates":[-3.46752991500513,52.30049773002484],"type":"Point"}
}