{
  "type": "Feature",
  "properties": {
    "date:inception_lower": "1980-01-01",
    "date:inception_upper": "1980-01-01",
    "iso:country": "GB",
    "wof:name": "LD6 5PB",
    "wof:placetype": "postalcode"
  },
  "geometry": {"coordinates":[-3.466895,52.300176],"type":"Point"}
}
