{
  "type": "Feature",
  "properties": {
    "iso:country": "GB",
    "wof:name": "LD6 5PB",
    "wof:placetype": "postalcode"
  },
  "geometry": {"coordinates":[-3.467281,52.300315],"type":"Point"}
}
