{
  "type": "Feature",
  "properties": {
    "iso:country":"GB",
    "wof:name":"CF44 9RP",
    "wof:placetype":"postalcode"
},
  "geometry": {"coordinates":[-3.51354439354267,51.73742234771643],"type":"Point"}
}