{
  "type": "Feature",
  "properties": {
    "date:inception_lower": "1980-01-01",
    "date:inception_upper": "1980-01-01",
    "iso:country": "GB",
    "wof:name": "CF44 9RP",
    "wof:placetype": "postalcode"
  },
  "geometry": {"coordinates":[-3.513544,51.737422],"type":"Point"}
}
