{
  "type": "Feature",
  "properties": {
    "iso:country":"GB",
    "wof:name":"KT6 4EG",
    "wof:placetype":"postalcode"
},
  "geometry": {"coordinates":[-0.31079052803098,51.39272753332119],"type":"Point"}
}