{
  "type": "Feature",
  "properties": {
    "date:inception_lower":"1980-01-01",
    "date:inception_upper":"1980-01-31",
    "iso:country":"GB",
    "wof:name":"CV2 3JS",
    "wof:placetype":"postalcode"
},
  "geometry": {"coordinates":[-1.471995,52.424395],"type":"Point"}
}