{
  "type": "Feature",
  "properties": {
    "date:inception_lower": "1980-01-01",
    "date:inception_upper": "1980-01-01",
    "iso:country": "GB",
    "wof:name": "CV2 3JS",
    "wof:placetype": "postalcode"
  },
  "geometry": {"coordinates":[-1.471796,52.424394],"type":"Point"}
}
