{
  "type": "Feature",
  "properties": {
    "iso:country":"GB",
    "wof:name":"CV2 3JS",
    "wof:placetype":"postalcode"
},
  "geometry": {"coordinates":[-1.47199478675627,52.42439515685763],"type":"Point"}
}