{
  "type": "Feature",
  "properties": {
    "iso:country":"GB",
    "wof:name":"NG11 7HG",
    "wof:placetype":"postalcode"
},
  "geometry": {"coordinates":[-1.16173758067134,52.91950327016445],"type":"Point"}
}