{
  "type": "Feature",
  "properties": {
    "iso:country": "GB",
    "wof:name": "NG11 7HG",
    "wof:placetype": "postalcode"
  },
  "geometry": {"coordinates":[-1.161738,52.919503],"type":"Point"}
}
