{
  "type": "Feature",
  "properties": {
    "date:inception_lower":"1980-01-01",
    "date:inception_upper":"1980-01-31",
    "iso:country":"GB",
    "wof:name":"TS3 0LG",
    "wof:placetype":"postalcode"
},
  "geometry": {"coordinates":[-1.191131,54.551159],"type":"Point"}
}