{
  "type": "Feature",
  "properties": {
    "date:inception_lower": "1980-01-01",
    "date:inception_upper": "1980-01-01",
    "iso:country": "GB",
    "wof:name": "CT16 2JF",
    "wof:placetype": "postalcode"
  },
  "geometry": {"coordinates":[1.304756,51.145151],"type":"Point"}
}
