{
  "type": "Feature",
  "properties": {
    "iso:country":"GB",
    "wof:name":"BA2 0AS",
    "wof:placetype":"postalcode"
},
  "geometry": {"coordinates":[-2.48987576009107,51.34254992796362],"type":"Point"}
}