{
  "type": "Feature",
  "properties": {
    "date:inception_lower":"2001-06-01",
    "date:inception_upper":"2001-06-30",
    "iso:country":"GB",
    "wof:name":"BA2 0AS",
    "wof:placetype":"postalcode"
},
  "geometry": {"coordinates":[-2.489876,51.34255],"type":"Point"}
}