{
  "type": "Feature",
  "properties": {
    "date:inception_lower": "2005-03-01",
    "date:inception_upper": "2005-03-01",
    "iso:country": "GB",
    "wof:name": "SW8 3BZ",
    "wof:placetype": "postalcode"
  },
  "geometry": {"coordinates":[-0.140694,51.469585],"type":"Point"}
}
