{
  "type": "Feature",
  "properties": {
    "iso:country":"GB",
    "wof:name":"SW8 3BZ",
    "wof:placetype":"postalcode"
},
  "geometry": {"coordinates":[-0.14071946664555,51.4695842169105],"type":"Point"}
}