{
  "type": "Feature",
  "properties": {
    "iso:country": "GB",
    "wof:name": "TN15 9JA",
    "wof:placetype": "postalcode"
  },
  "geometry": {"coordinates":[0.293515,51.291354],"type":"Point"}
}
