{
  "type": "Feature",
  "properties": {
    "iso:country":"GB",
    "wof:name":"SE16 4AF",
    "wof:placetype":"postalcode"
},
  "geometry": {"coordinates":[-0.06853574205652,51.49696890111315],"type":"Point"}
}