{
  "type": "Feature",
  "properties": {
    "iso:country":"GB",
    "wof:name":"CV10 8AX",
    "wof:placetype":"postalcode"
},
  "geometry": {"coordinates":[-1.49168478851911,52.52419011668123],"type":"Point"}
}