{
  "type": "Feature",
  "properties": {
    "iso:country":"GB",
    "wof:name":"MK6 2HP",
    "wof:placetype":"postalcode"
},
  "geometry": {"coordinates":[-0.75157810256384,52.03223345851862],"type":"Point"}
}