{
  "type": "Feature",
  "properties": {
    "iso:country": "GB",
    "wof:name": "ML4 2RR",
    "wof:placetype": "postalcode"
  },
  "geometry": {"coordinates":[-3.989039,55.81188],"type":"Point"}
}
