{
  "type": "Feature",
  "properties": {
    "iso:country":"GB",
    "wof:name":"ML4 2RR",
    "wof:placetype":"postalcode"
},
  "geometry": {"coordinates":[-3.98903893422832,55.81188013838631],"type":"Point"}
}