{
  "type": "Feature",
  "properties": {
    "date:inception_lower": "2014-07-01",
    "date:inception_upper": "2014-07-01",
    "iso:country": "GB",
    "wof:name": "OL8 1HY",
    "wof:placetype": "postalcode"
  },
  "geometry": {"coordinates":[-2.117926,53.533737],"type":"Point"}
}
