{
  "type": "Feature",
  "properties": {
    "iso:country": "GB",
    "wof:name": "OL8 1HY",
    "wof:placetype": "postalcode"
  },
  "geometry": {"coordinates":[-2.117926,53.533737],"type":"Point"}
}
