{
  "type": "Feature",
  "properties": {
    "iso:country":"GB",
    "wof:name":"BN41 2DP",
    "wof:placetype":"postalcode"
},
  "geometry": {"coordinates":[-0.20810712857196,50.84417714864576],"type":"Point"}
}