{
  "type": "Feature",
  "properties": {
    "date:inception_lower":"1980-01-01",
    "date:inception_upper":"1980-01-31",
    "iso:country":"GB",
    "wof:name":"SL3 7PG",
    "wof:placetype":"postalcode"
},
  "geometry": {"coordinates":[-0.575774,51.501716],"type":"Point"}
}