{
  "type": "Feature",
  "properties": {
    "iso:country":"GB",
    "wof:name":"SL3 7PG",
    "wof:placetype":"postalcode"
},
  "geometry": {"coordinates":[-0.57577354921809,51.50171650480287],"type":"Point"}
}