{
  "type": "Feature",
  "properties": {
    "iso:country":"GB",
    "wof:name":"E9 7PG",
    "wof:placetype":"postalcode"
},
  "geometry": {"coordinates":[-0.05257643771439,51.54114639684981],"type":"Point"}
}