{
  "type": "Feature",
  "properties": {
    "iso:country":"GB",
    "wof:name":"SW3 6HY",
    "wof:placetype":"postalcode"
},
  "geometry": {"coordinates":[-0.17585585853058,51.48895746432196],"type":"Point"}
}