{
  "type": "Feature",
  "properties": {
    "iso:country":"GB",
    "wof:name":"G3 8GN",
    "wof:placetype":"postalcode"
},
  "geometry": {"coordinates":[-4.27251183881063,55.86124226813291],"type":"Point"}
}