{
  "type": "Feature",
  "properties": {
    "iso:country":"GB",
    "wof:name":"SE26 5RR",
    "wof:placetype":"postalcode"
},
  "geometry": {"coordinates":[-0.04260103191858,51.42535271719539],"type":"Point"}
}