{
  "type": "Feature",
  "properties": {
    "iso:country":"GB",
    "wof:name":"ML6 8DD",
    "wof:placetype":"postalcode"
},
  "geometry": {"coordinates":[-3.95246742872436,55.86140872726234],"type":"Point"}
}