{
  "type": "Feature",
  "properties": {
    "date:inception_lower": "1980-01-01",
    "date:inception_upper": "1980-01-01",
    "iso:country": "GB",
    "wof:name": "WF9 2ND",
    "wof:placetype": "postalcode"
  },
  "geometry": {"coordinates":[-1.314347,53.58197],"type":"Point"}
}
