{
  "type": "Feature",
  "properties": {
    "iso:country":"GB",
    "wof:name":"WF9 2ND",
    "wof:placetype":"postalcode"
},
  "geometry": {"coordinates":[-1.31434450671803,53.58195253947513],"type":"Point"}
}