{
  "type": "Feature",
  "properties": {
    "date:inception_lower": "2016-11-01",
    "date:inception_upper": "2016-11-01",
    "iso:country": "GB",
    "wof:name": "G21 3RQ",
    "wof:placetype": "postalcode"
  },
  "geometry": {"coordinates":[-4.202215,55.89709],"type":"Point"}
}
