{
  "type": "Feature",
  "properties": {
    "iso:country":"GB",
    "wof:name":"BS4 2AB",
    "wof:placetype":"postalcode"
},
  "geometry": {"coordinates":[-2.57791491098696,51.44083275490291],"type":"Point"}
}