{
  "type": "Feature",
  "properties": {
    "date:inception_lower": "1988-03-01",
    "date:inception_upper": "1988-03-01",
    "iso:country": "GB",
    "wof:name": "DL8 3UZ",
    "wof:placetype": "postalcode"
  },
  "geometry": {"coordinates":[-2.1945,54.306231],"type":"Point"}
}
