{
  "type": "Feature",
  "properties": {
    "date:inception_lower":"1988-03-01",
    "date:inception_upper":"1988-03-31",
    "iso:country":"GB",
    "wof:name":"DL8 3UZ",
    "wof:placetype":"postalcode"
},
  "geometry": {"coordinates":[-2.194341,54.305833],"type":"Point"}
}