{
  "type": "Feature",
  "properties": {
    "iso:country":"GB",
    "wof:name":"DL8 3UZ",
    "wof:placetype":"postalcode"
},
  "geometry": {"coordinates":[-2.19400435023838,54.30613933636641],"type":"Point"}
}