{
  "type": "Feature",
  "properties": {
    "iso:country": "GB",
    "wof:name": "CO10 9FS",
    "wof:placetype": "postalcode"
  },
  "geometry": {"coordinates":[0.729207,52.078901],"type":"Point"}
}
