{
  "type": "Feature",
  "properties": {
    "iso:country":"GB",
    "wof:name":"N1 3BH",
    "wof:placetype":"postalcode"
},
  "geometry": {"coordinates":[-0.08809609127246,51.54112816072676],"type":"Point"}
}