{
  "type": "Feature",
  "properties": {
    "iso:country": "GB",
    "wof:name": "N1 3BH",
    "wof:placetype": "postalcode"
  },
  "geometry": {"coordinates":[-0.088096,51.541128],"type":"Point"}
}
