{
  "type": "Feature",
  "properties": {
    "iso:country":"GB",
    "wof:name":"LN11 8RF",
    "wof:placetype":"postalcode"
},
  "geometry": {"coordinates":[0.03325651118244,53.26529771936673],"type":"Point"}
}