{
  "type": "Feature",
  "properties": {
    "iso:country":"GB",
    "wof:name":"WA10 3PA",
    "wof:placetype":"postalcode"
},
  "geometry": {"coordinates":[-2.76938585611066,53.43414350981583],"type":"Point"}
}