{
  "type": "Feature",
  "properties": {
    "date:inception_lower": "1980-01-01",
    "date:inception_upper": "1980-01-01",
    "iso:country": "GB",
    "wof:name": "WA10 3PA",
    "wof:placetype": "postalcode"
  },
  "geometry": {"coordinates":[-2.769689,53.434319],"type":"Point"}
}
