{
  "type": "Feature",
  "properties": {
    "iso:country":"GB",
    "wof:name":"DY8 1LH",
    "wof:placetype":"postalcode"
},
  "geometry": {"coordinates":[-2.1342267367214,52.45632306855953],"type":"Point"}
}