{
  "type": "Feature",
  "properties": {
    "date:inception_lower": "1985-10-01",
    "date:inception_upper": "1985-10-01",
    "iso:country": "GB",
    "wof:name": "DY8 1LH",
    "wof:placetype": "postalcode"
  },
  "geometry": {"coordinates":[-2.13425,52.456346],"type":"Point"}
}
