{
  "type": "Feature",
  "properties": {
    "iso:country": "GB",
    "wof:name": "TN39 4FJ",
    "wof:placetype": "postalcode"
  },
  "geometry": {"coordinates":[0.473528,50.854287],"type":"Point"}
}
