{
  "type": "Feature",
  "properties": {
    "date:inception_lower": "2016-11-01",
    "date:inception_upper": "2016-11-01",
    "iso:country": "GB",
    "wof:name": "TN39 4FJ",
    "wof:placetype": "postalcode"
  },
  "geometry": {"coordinates":[0.473528,50.854287],"type":"Point"}
}
