{
  "type": "Feature",
  "properties": {
    "iso:country":"GB",
    "wof:name":"N1 2LU",
    "wof:placetype":"postalcode"
},
  "geometry": {"coordinates":[-0.09730508307428,51.54645757108987],"type":"Point"}
}