{
  "type": "Feature",
  "properties": {
    "date:inception_lower":"1980-01-01",
    "date:inception_upper":"1980-01-31",
    "iso:country":"GB",
    "wof:name":"WC1N 1LT",
    "wof:placetype":"postalcode"
},
  "geometry": {"coordinates":[-0.123033,51.523375],"type":"Point"}
}