{
  "type": "Feature",
  "properties": {
    "iso:country":"GB",
    "wof:name":"WC1N 1LT",
    "wof:placetype":"postalcode"
},
  "geometry": {"coordinates":[-0.12303289953912,51.52337461367763],"type":"Point"}
}