{
  "type": "Feature",
  "properties": {
    "date:inception_lower":"1981-06-01",
    "date:inception_upper":"1981-06-30",
    "iso:country":"GB",
    "wof:name":"OX12 0QH",
    "wof:placetype":"postalcode"
},
  "geometry": {"coordinates":[-1.430663,51.609702],"type":"Point"}
}