{
  "type": "Feature",
  "properties": {
    "iso:country": "GB",
    "wof:name": "MK40 4EP",
    "wof:placetype": "postalcode"
  },
  "geometry": {"coordinates":[-0.487638,52.136237],"type":"Point"}
}
