{
  "type": "Feature",
  "properties": {
    "iso:country":"GB",
    "wof:name":"MK40 4EP",
    "wof:placetype":"postalcode"
},
  "geometry": {"coordinates":[-0.48763780620138,52.13623712789789],"type":"Point"}
}