{
  "type": "Feature",
  "properties": {
    "iso:country":"GB",
    "wof:name":"DT4 0TG",
    "wof:placetype":"postalcode"
},
  "geometry": {"coordinates":[-2.47928545849478,50.62259594607069],"type":"Point"}
}