{
  "type": "Feature",
  "properties": {
    "date:inception_lower": "1980-01-01",
    "date:inception_upper": "1980-01-01",
    "iso:country": "GB",
    "wof:name": "NE61 1JG",
    "wof:placetype": "postalcode"
  },
  "geometry": {"coordinates":[-1.68896,55.172499],"type":"Point"}
}
