{
  "type": "Feature",
  "properties": {
    "iso:country":"GB",
    "wof:name":"BS30 6RB",
    "wof:placetype":"postalcode"
},
  "geometry": {"coordinates":[-2.47462868478847,51.43694467388818],"type":"Point"}
}