{
  "type": "Feature",
  "properties": {
    "iso:country":"GB",
    "wof:name":"KA30 8QA",
    "wof:placetype":"postalcode"
},
  "geometry": {"coordinates":[-4.87228266019751,55.80545943406909],"type":"Point"}
}