{
  "type": "Feature",
  "properties": {
    "date:inception_lower":"1980-01-01",
    "date:inception_upper":"1980-01-31",
    "iso:country":"GB",
    "wof:name":"KA30 8QA",
    "wof:placetype":"postalcode"
},
  "geometry": {"coordinates":[-4.872283,55.805459],"type":"Point"}
}