{
  "type": "Feature",
  "properties": {
    "date:inception_lower": "1980-01-01",
    "date:inception_upper": "1980-01-01",
    "iso:country": "GB",
    "wof:name": "L7 1PH",
    "wof:placetype": "postalcode"
  },
  "geometry": {"coordinates":[-2.954086,53.40498],"type":"Point"}
}
