{
  "type": "Feature",
  "properties": {
    "date:inception_lower": "1980-01-01",
    "date:inception_upper": "1980-01-01",
    "iso:country": "GB",
    "wof:name": "SK15 2RQ",
    "wof:placetype": "postalcode"
  },
  "geometry": {"coordinates":[-2.040551,53.476039],"type":"Point"}
}
