{
  "type": "Feature",
  "properties": {
    "iso:country":"GB",
    "wof:name":"SK15 2RQ",
    "wof:placetype":"postalcode"
},
  "geometry": {"coordinates":[-2.04055081295568,53.47603937378206],"type":"Point"}
}