{
  "type": "Feature",
  "properties": {
    "iso:country": "GB",
    "wof:name": "AB32 7DB",
    "wof:placetype": "postalcode"
  },
  "geometry": {"coordinates":[-2.404928,57.169357],"type":"Point"}
}
