{
  "type": "Feature",
  "properties": {
    "iso:country":"GB",
    "wof:name":"NR13 4HX",
    "wof:placetype":"postalcode"
},
  "geometry": {"coordinates":[1.45501100612421,52.6140863728589],"type":"Point"}
}