{
  "type": "Feature",
  "properties": {
    "date:inception_lower": "2013-05-01",
    "date:inception_upper": "2013-05-01",
    "iso:country": "GB",
    "wof:name": "W7 2QN",
    "wof:placetype": "postalcode"
  },
  "geometry": {"coordinates":[-0.33763,51.501218],"type":"Point"}
}
