{
  "type": "Feature",
  "properties": {
    "iso:country":"GB",
    "wof:name":"SE6 1RF",
    "wof:placetype":"postalcode"
},
  "geometry": {"coordinates":[-0.00154135090189,51.43867950791144],"type":"Point"}
}