{
  "type": "Feature",
  "properties": {
    "date:inception_lower": "2017-10-01",
    "date:inception_upper": "2017-10-01",
    "iso:country": "GB",
    "wof:name": "CV23 9FP",
    "wof:placetype": "postalcode"
  },
  "geometry": {"coordinates":[-1.304245,52.376975],"type":"Point"}
}
