{
  "type": "Feature",
  "properties": {
    "date:inception_lower": "2006-09-01",
    "date:inception_upper": "2006-09-01",
    "iso:country": "GB",
    "wof:name": "CB21 6AY",
    "wof:placetype": "postalcode"
  },
  "geometry": {"coordinates":[0.245188,52.108275],"type":"Point"}
}
