{
  "type": "Feature",
  "properties": {
    "iso:country":"GB",
    "wof:name":"AL1 2LD",
    "wof:placetype":"postalcode"
},
  "geometry": {"coordinates":[-0.33854509867149,51.73713963624324],"type":"Point"}
}