{
  "type": "Feature",
  "properties": {
    "iso:country": "GB",
    "wof:name": "AL1 2LD",
    "wof:placetype": "postalcode"
  },
  "geometry": {"coordinates":[-0.338545,51.73714],"type":"Point"}
}
