{
  "type": "Feature",
  "properties": {
    "iso:country":"GB",
    "wof:name":"FY2 9QD",
    "wof:placetype":"postalcode"
},
  "geometry": {"coordinates":[-3.05280799080611,53.84347230790911],"type":"Point"}
}