{
  "type": "Feature",
  "properties": {
    "iso:country": "GB",
    "wof:name": "FY2 9QD",
    "wof:placetype": "postalcode"
  },
  "geometry": {"coordinates":[-3.052808,53.843472],"type":"Point"}
}
