{
  "type": "Feature",
  "properties": {
    "iso:country":"GB",
    "wof:name":"BR2 8BY",
    "wof:placetype":"postalcode"
},
  "geometry": {"coordinates":[0.06149150340916,51.38327076088603],"type":"Point"}
}