{
  "type": "Feature",
  "properties": {
    "iso:country":"GB",
    "wof:name":"HD1 3AJ",
    "wof:placetype":"postalcode"
},
  "geometry": {"coordinates":[-1.7740046568042,53.64379818496237],"type":"Point"}
}