{
  "type": "Feature",
  "properties": {
    "iso:country": "GB",
    "wof:name": "NE63 9QS",
    "wof:placetype": "postalcode"
  },
  "geometry": {"coordinates":[-1.553382,55.172015],"type":"Point"}
}
