{
  "type": "Feature",
  "properties": {
    "date:inception_lower":"1995-07-01",
    "date:inception_upper":"1995-07-31",
    "iso:country":"GB",
    "wof:name":"RG42 1PG",
    "wof:placetype":"postalcode"
},
  "geometry": {"coordinates":[-0.777275,51.421533],"type":"Point"}
}