{
  "type": "Feature",
  "properties": {
    "date:inception_lower":"1980-01-01",
    "date:inception_upper":"1980-01-31",
    "iso:country":"GB",
    "wof:name":"KT6 5EU",
    "wof:placetype":"postalcode"
},
  "geometry": {"coordinates":[-0.314904,51.38678],"type":"Point"}
}