{
  "type": "Feature",
  "properties": {
    "iso:country": "GB",
    "wof:name": "KT6 5EU",
    "wof:placetype": "postalcode"
  },
  "geometry": {"coordinates":[-0.314904,51.38678],"type":"Point"}
}
