{
  "type": "Feature",
  "properties": {
    "iso:country": "GB",
    "wof:name": "KT6 5EU",
    "wof:placetype": "postalcode"
  },
  "geometry": {"coordinates":[-0.314772,51.386633],"type":"Point"}
}
