{
  "type": "Feature",
  "properties": {
    "iso:country":"GB",
    "wof:name":"KT6 5EU",
    "wof:placetype":"postalcode"
},
  "geometry": {"coordinates":[-0.31490434502483,51.38677977876124],"type":"Point"}
}