{
  "type": "Feature",
  "properties": {
    "date:inception_lower":"1980-01-01",
    "date:inception_upper":"1980-01-31",
    "iso:country":"GB",
    "wof:name":"TS5 4NU",
    "wof:placetype":"postalcode"
},
  "geometry": {"coordinates":[-1.261048,54.561204],"type":"Point"}
}