{
  "type": "Feature",
  "properties": {
    "iso:country":"GB",
    "wof:name":"TS5 4NU",
    "wof:placetype":"postalcode"
},
  "geometry": {"coordinates":[-1.26104795963358,54.56120403749599],"type":"Point"}
}