{
  "type": "Feature",
  "properties": {
    "date:inception_lower": "2002-07-01",
    "date:inception_upper": "2002-07-01",
    "iso:country": "GB",
    "wof:name": "G63 9BD",
    "wof:placetype": "postalcode"
  },
  "geometry": {"coordinates":[-4.305124,55.985139],"type":"Point"}
}
