{
  "type": "Feature",
  "properties": {
    "date:inception_lower": "1994-05-01",
    "date:inception_upper": "1994-05-01",
    "iso:country": "GB",
    "wof:name": "M41 8UB",
    "wof:placetype": "postalcode"
  },
  "geometry": {"coordinates":[-2.386767,53.449533],"type":"Point"}
}
