{
  "type": "Feature",
  "properties": {
    "iso:country":"GB",
    "wof:name":"M41 8UB",
    "wof:placetype":"postalcode"
},
  "geometry": {"coordinates":[-2.38676754591917,53.44953270897722],"type":"Point"}
}