{
  "type": "Feature",
  "properties": {
    "date:inception_lower":"1994-05-01",
    "date:inception_upper":"1994-05-31",
    "iso:country":"GB",
    "wof:name":"M19 1NW",
    "wof:placetype":"postalcode"
},
  "geometry": {"coordinates":[-2.199122,53.429877],"type":"Point"}
}