{
  "type": "Feature",
  "properties": {
    "iso:country":"GB",
    "wof:name":"M19 1NW",
    "wof:placetype":"postalcode"
},
  "geometry": {"coordinates":[-2.19912175900456,53.42987691834049],"type":"Point"}
}