{
  "type": "Feature",
  "properties": {
    "iso:country":"GB",
    "wof:name":"W1W 6SE",
    "wof:placetype":"postalcode"
},
  "geometry": {"coordinates":[-0.14079454206468,51.51943101309504],"type":"Point"}
}