{
  "type": "Feature",
  "properties": {
    "iso:country":"GB",
    "wof:name":"DH6 4SG",
    "wof:placetype":"postalcode"
},
  "geometry": {"coordinates":[-1.50235074917528,54.71233641968399],"type":"Point"}
}