{
  "type": "Feature",
  "properties": {
    "iso:country":"GB",
    "wof:name":"KY6 1NA",
    "wof:placetype":"postalcode"
},
  "geometry": {"coordinates":[-3.19712609968902,56.19984136980683],"type":"Point"}
}