{
  "type": "Feature",
  "properties": {
    "date:inception_lower": "1980-01-01",
    "date:inception_upper": "1980-01-01",
    "iso:country": "GB",
    "wof:name": "KY6 1NA",
    "wof:placetype": "postalcode"
  },
  "geometry": {"coordinates":[-3.197126,56.199841],"type":"Point"}
}
