{
  "type": "Feature",
  "properties": {
    "date:inception_lower": "1980-01-01",
    "date:inception_upper": "1980-01-01",
    "iso:country": "GB",
    "wof:name": "G84 8RP",
    "wof:placetype": "postalcode"
  },
  "geometry": {"coordinates":[-4.782657,56.018595],"type":"Point"}
}
