{
  "type": "Feature",
  "properties": {
    "iso:country":"GB",
    "wof:name":"G84 8RP",
    "wof:placetype":"postalcode"
},
  "geometry": {"coordinates":[-4.78241275401032,56.01832224506565],"type":"Point"}
}