{
  "type": "Feature",
  "properties": {
    "iso:country":"GB",
    "wof:name":"NN17 1HX",
    "wof:placetype":"postalcode"
},
  "geometry": {"coordinates":[-0.7018113505187,52.49735954669048],"type":"Point"}
}