{
  "type": "Feature",
  "properties": {
    "iso:country":"GB",
    "wof:name":"PE28 2UU",
    "wof:placetype":"postalcode"
},
  "geometry": {"coordinates":[-0.06283367564349,52.40954456369163],"type":"Point"}
}