{
  "type": "Feature",
  "properties": {
    "iso:country": "GB",
    "wof:name": "NR3 2RZ",
    "wof:placetype": "postalcode"
  },
  "geometry": {"coordinates":[1.280353,52.651479],"type":"Point"}
}
