{
  "type": "Feature",
  "properties": {
    "iso:country": "GB",
    "wof:name": "CM3 2DW",
    "wof:placetype": "postalcode"
  },
  "geometry": {"coordinates":[0.59255,51.77542],"type":"Point"}
}
