{
  "type": "Feature",
  "properties": {
    "iso:country":"GB",
    "wof:name":"CM3 2DW",
    "wof:placetype":"postalcode"
},
  "geometry": {"coordinates":[0.59255036621769,51.77541962844717],"type":"Point"}
}