{
  "type": "Feature",
  "properties": {
    "iso:country": "GB",
    "wof:name": "WD19 5ET",
    "wof:placetype": "postalcode"
  },
  "geometry": {"coordinates":[-0.380489,51.625595],"type":"Point"}
}
