{
  "type": "Feature",
  "properties": {
    "iso:country":"GB",
    "wof:name":"WD19 5ET",
    "wof:placetype":"postalcode"
},
  "geometry": {"coordinates":[-0.38048912922302,51.62559477471461],"type":"Point"}
}