{
  "type": "Feature",
  "properties": {
    "iso:country":"GB",
    "wof:name":"LS5 3QR",
    "wof:placetype":"postalcode"
},
  "geometry": {"coordinates":[-1.611378467425,53.82822162403578],"type":"Point"}
}