{
  "type": "Feature",
  "properties": {
    "iso:country":"GB",
    "wof:name":"B92 7QP",
    "wof:placetype":"postalcode"
},
  "geometry": {"coordinates":[-1.79484566905485,52.44910198712832],"type":"Point"}
}