{
  "type": "Feature",
  "properties": {
    "iso:country": "GB",
    "wof:name": "B92 7QP",
    "wof:placetype": "postalcode"
  },
  "geometry": {"coordinates":[-1.794846,52.449102],"type":"Point"}
}
