{
  "type": "Feature",
  "properties": {
    "iso:country":"GB",
    "wof:name":"OL3 5AB",
    "wof:placetype":"postalcode"
},
  "geometry": {"coordinates":[-2.01407554219091,53.55586230890412],"type":"Point"}
}