{
  "type": "Feature",
  "properties": {
    "iso:country":"GB",
    "wof:name":"ST17 4TS",
    "wof:placetype":"postalcode"
},
  "geometry": {"coordinates":[-2.09503271588063,52.79419553148374],"type":"Point"}
}