{
  "type": "Feature",
  "properties": {
    "iso:country": "GB",
    "wof:name": "RG9 1QB",
    "wof:placetype": "postalcode"
  },
  "geometry": {"coordinates":[-0.913194,51.526656],"type":"Point"}
}
