{
  "type": "Feature",
  "properties": {
    "iso:country":"GB",
    "wof:name":"RG9 1QB",
    "wof:placetype":"postalcode"
},
  "geometry": {"coordinates":[-0.91319406568474,51.52665634003822],"type":"Point"}
}