{
  "type": "Feature",
  "properties": {
    "iso:country":"GB",
    "wof:name":"M14 7BS",
    "wof:placetype":"postalcode"
},
  "geometry": {"coordinates":[-2.23269696576107,53.44876395515297],"type":"Point"}
}