{
  "type": "Feature",
  "properties": {
    "date:inception_lower": "1980-01-01",
    "date:inception_upper": "1980-01-01",
    "iso:country": "GB",
    "wof:name": "M14 7BS",
    "wof:placetype": "postalcode"
  },
  "geometry": {"coordinates":[-2.232697,53.448764],"type":"Point"}
}
