{
  "type": "Feature",
  "properties": {
    "iso:country":"GB",
    "wof:name":"PR2 9PP",
    "wof:placetype":"postalcode"
},
  "geometry": {"coordinates":[-2.68313982030047,53.79562504822376],"type":"Point"}
}