{
  "type": "Feature",
  "properties": {
    "iso:country":"GB",
    "wof:name":"SL9 9QJ",
    "wof:placetype":"postalcode"
},
  "geometry": {"coordinates":[-0.55588791616308,51.60748934064661],"type":"Point"}
}