{
  "type": "Feature",
  "properties": {
    "iso:country":"GB",
    "wof:name":"TN26 1NF",
    "wof:placetype":"postalcode"
},
  "geometry": {"coordinates":[0.85758851056381,51.110737340565],"type":"Point"}
}