{
  "type": "Feature",
  "properties": {
    "date:inception_lower": "1980-01-01",
    "date:inception_upper": "1980-01-01",
    "iso:country": "GB",
    "wof:name": "TN26 1NF",
    "wof:placetype": "postalcode"
  },
  "geometry": {"coordinates":[0.857589,51.110737],"type":"Point"}
}
