{
  "type": "Feature",
  "properties": {
    "iso:country": "GB",
    "wof:name": "TN26 1NF",
    "wof:placetype": "postalcode"
  },
  "geometry": {"coordinates":[0.857589,51.110737],"type":"Point"}
}
