{
  "type": "Feature",
  "properties": {
    "iso:country": "GB",
    "wof:name": "ME16 0GW",
    "wof:placetype": "postalcode"
  },
  "geometry": {"coordinates":[0.516393,51.275506],"type":"Point"}
}
