{
  "type": "Feature",
  "properties": {
    "iso:country":"GB",
    "wof:name":"ME16 0GW",
    "wof:placetype":"postalcode"
},
  "geometry": {"coordinates":[0.51639302254009,51.27550561502518],"type":"Point"}
}