{
  "type": "Feature",
  "properties": {
    "iso:country":"GB",
    "wof:name":"PO34 5ED",
    "wof:placetype":"postalcode"
},
  "geometry": {"coordinates":[-1.11661029738971,50.71253073769069],"type":"Point"}
}