{
  "type": "Feature",
  "properties": {
    "iso:country":"GB",
    "wof:name":"LS13 2PQ",
    "wof:placetype":"postalcode"
},
  "geometry": {"coordinates":[-1.6299131247797,53.81966072414894],"type":"Point"}
}