{
  "type": "Feature",
  "properties": {
    "iso:country":"GB",
    "wof:name":"WV15 6DE",
    "wof:placetype":"postalcode"
},
  "geometry": {"coordinates":[-2.41369713220285,52.52942014169567],"type":"Point"}
}