{
  "type": "Feature",
  "properties": {
    "date:inception_lower":"1980-01-01",
    "date:inception_upper":"1980-01-31",
    "iso:country":"GB",
    "wof:name":"B90 1LE",
    "wof:placetype":"postalcode"
},
  "geometry": {"coordinates":[-1.863007,52.408826],"type":"Point"}
}