{
  "type": "Feature",
  "properties": {
    "iso:country": "GB",
    "wof:name": "S63 6LR",
    "wof:placetype": "postalcode"
  },
  "geometry": {"coordinates":[-1.384814,53.502356],"type":"Point"}
}
