{
  "type": "Feature",
  "properties": {
    "date:inception_lower":"2000-12-01",
    "date:inception_upper":"2000-12-31",
    "iso:country":"GB",
    "wof:name":"S63 6LR",
    "wof:placetype":"postalcode"
},
  "geometry": {"coordinates":[-1.384814,53.502356],"type":"Point"}
}