{
  "type": "Feature",
  "properties": {
    "date:inception_lower":"1980-01-01",
    "date:inception_upper":"1980-01-31",
    "iso:country":"GB",
    "wof:name":"MK41 7PX",
    "wof:placetype":"postalcode"
},
  "geometry": {"coordinates":[-0.478345,52.150369],"type":"Point"}
}