{
  "type": "Feature",
  "properties": {
    "iso:country": "GB",
    "wof:name": "LE3 2EN",
    "wof:placetype": "postalcode"
  },
  "geometry": {"coordinates":[-1.160004,52.614872],"type":"Point"}
}
