{
  "type": "Feature",
  "properties": {
    "iso:country": "GB",
    "wof:name": "HX3 5QY",
    "wof:placetype": "postalcode"
  },
  "geometry": {"coordinates":[-1.881333,53.738481],"type":"Point"}
}
