{
  "type": "Feature",
  "properties": {
    "iso:country":"GB",
    "wof:name":"HX3 5QY",
    "wof:placetype":"postalcode"
},
  "geometry": {"coordinates":[-1.88133316473424,53.73848050929458],"type":"Point"}
}