{
  "type": "Feature",
  "properties": {
    "iso:country":"GB",
    "wof:name":"CA14 4DG",
    "wof:placetype":"postalcode"
},
  "geometry": {"coordinates":[-3.53847427927287,54.64090984720722],"type":"Point"}
}