{
  "type": "Feature",
  "properties": {
    "iso:country":"GB",
    "wof:name":"GU21 4JJ",
    "wof:placetype":"postalcode"
},
  "geometry": {"coordinates":[-0.56385298139205,51.33162725197752],"type":"Point"}
}