{
  "type": "Feature",
  "properties": {
    "date:inception_lower":"1980-01-01",
    "date:inception_upper":"1980-01-31",
    "iso:country":"GB",
    "wof:name":"GU21 4JJ",
    "wof:placetype":"postalcode"
},
  "geometry": {"coordinates":[-0.563853,51.331627],"type":"Point"}
}