{
  "type": "Feature",
  "properties": {
    "date:inception_lower": "1980-01-01",
    "date:inception_upper": "1980-01-01",
    "iso:country": "GB",
    "wof:name": "NG3 3PW",
    "wof:placetype": "postalcode"
  },
  "geometry": {"coordinates":[-1.132122,52.96502],"type":"Point"}
}
