{
  "type": "Feature",
  "properties": {
    "iso:country":"GB",
    "wof:name":"NG3 3PW",
    "wof:placetype":"postalcode"
},
  "geometry": {"coordinates":[-1.13212221411084,52.96502045925849],"type":"Point"}
}