{
  "type": "Feature",
  "properties": {
    "date:inception_lower": "1980-01-01",
    "date:inception_upper": "1980-01-01",
    "iso:country": "GB",
    "wof:name": "BB2 6BN",
    "wof:placetype": "postalcode"
  },
  "geometry": {"coordinates":[-2.49957,53.74973],"type":"Point"}
}
