{
  "type": "Feature",
  "properties": {
    "iso:country": "GB",
    "wof:name": "S41 7QU",
    "wof:placetype": "postalcode"
  },
  "geometry": {"coordinates":[-1.450026,53.251889],"type":"Point"}
}
