{
  "type": "Feature",
  "properties": {
    "iso:country": "GB",
    "wof:name": "HP17 8UG",
    "wof:placetype": "postalcode"
  },
  "geometry": {"coordinates":[-0.88829,51.793537],"type":"Point"}
}
