{
  "type": "Feature",
  "properties": {
    "date:inception_lower":"1992-08-01",
    "date:inception_upper":"1992-08-31",
    "iso:country":"GB",
    "wof:name":"MK5 6JR",
    "wof:placetype":"postalcode"
},
  "geometry": {"coordinates":[-0.79424,52.022149],"type":"Point"}
}