{
  "type": "Feature",
  "properties": {
    "iso:country":"GB",
    "wof:name":"AL10 9BH",
    "wof:placetype":"postalcode"
},
  "geometry": {"coordinates":[-0.23479315655645,51.78199900339973],"type":"Point"}
}