{
  "type": "Feature",
  "properties": {
    "iso:country": "GB",
    "wof:name": "ME10 4SN",
    "wof:placetype": "postalcode"
  },
  "geometry": {"coordinates":[0.749169,51.33758],"type":"Point"}
}
