{
  "type": "Feature",
  "properties": {
    "iso:country": "GB",
    "wof:name": "M11 4FP",
    "wof:placetype": "postalcode"
  },
  "geometry": {"coordinates":[-2.18563,53.487074],"type":"Point"}
}
