{
  "type": "Feature",
  "properties": {
    "iso:country":"GB",
    "wof:name":"M11 4FP",
    "wof:placetype":"postalcode"
},
  "geometry": {"coordinates":[-2.18563046202845,53.48707440951299],"type":"Point"}
}