{
  "type": "Feature",
  "properties": {
    "iso:country": "GB",
    "wof:name": "ME4 9FG",
    "wof:placetype": "postalcode"
  },
  "geometry": {"coordinates":[0.525547,51.380606],"type":"Point"}
}
