{
  "type": "Feature",
  "properties": {
    "iso:country": "GB",
    "wof:name": "AB56 5PF",
    "wof:placetype": "postalcode"
  },
  "geometry": {"coordinates":[-3.011275,57.662075],"type":"Point"}
}
