{
  "type": "Feature",
  "properties": {
    "date:inception_lower":"1996-06-01",
    "date:inception_upper":"1996-06-30",
    "iso:country":"GB",
    "wof:name":"AB56 5PF",
    "wof:placetype":"postalcode"
},
  "geometry": {"coordinates":[-3.011275,57.662075],"type":"Point"}
}