{
  "type": "Feature",
  "properties": {
    "iso:country":"GB",
    "wof:name":"AB56 5PF",
    "wof:placetype":"postalcode"
},
  "geometry": {"coordinates":[-3.01127476131634,57.66207461433015],"type":"Point"}
}