{
  "type": "Feature",
  "properties": {
    "iso:country":"GB",
    "wof:name":"WC1N 1JG",
    "wof:placetype":"postalcode"
},
  "geometry": {"coordinates":[-0.12565295386901,51.52451359604559],"type":"Point"}
}