{
  "type": "Feature",
  "properties": {
    "iso:country":"GB",
    "wof:name":"PO34 5LR",
    "wof:placetype":"postalcode"
},
  "geometry": {"coordinates":[-1.1152514583352,50.71474168102204],"type":"Point"}
}