{
  "type": "Feature",
  "properties": {
    "iso:country": "GB",
    "wof:name": "SR1 1BL",
    "wof:placetype": "postalcode"
  },
  "geometry": {"coordinates":[-1.378944,54.906795],"type":"Point"}
}
