{
  "type": "Feature",
  "properties": {
    "iso:country":"GB",
    "wof:name":"SR1 1BL",
    "wof:placetype":"postalcode"
},
  "geometry": {"coordinates":[-1.37894437583212,54.90679481326847],"type":"Point"}
}