{
  "type": "Feature",
  "properties": {
    "date:inception_lower": "1980-01-01",
    "date:inception_upper": "1980-01-01",
    "iso:country": "GB",
    "wof:name": "SG17 5LH",
    "wof:placetype": "postalcode"
  },
  "geometry": {"coordinates":[-0.33628,52.030223],"type":"Point"}
}
