{
  "type": "Feature",
  "properties": {
    "date:inception_lower": "2022-02-01",
    "date:inception_upper": "2022-02-01",
    "iso:country": "GB",
    "wof:name": "BN13 3ZA",
    "wof:placetype": "postalcode"
  },
  "geometry": {"coordinates":[-0.428352,50.838639],"type":"Point"}
}
