{
  "type": "Feature",
  "properties": {
    "iso:country":"GB",
    "wof:name":"CB4 2SU",
    "wof:placetype":"postalcode"
},
  "geometry": {"coordinates":[0.12639599760901,52.23148298772367],"type":"Point"}
}