{
  "type": "Feature",
  "properties": {
    "iso:country":"GB",
    "wof:name":"G32 0TT",
    "wof:placetype":"postalcode"
},
  "geometry": {"coordinates":[-4.14252410548923,55.85048052408213],"type":"Point"}
}