{
  "type": "Feature",
  "properties": {
    "date:inception_lower": "1994-05-01",
    "date:inception_upper": "1994-05-01",
    "iso:country": "GB",
    "wof:name": "M30 7GY",
    "wof:placetype": "postalcode"
  },
  "geometry": {"coordinates":[-2.37082,53.480378],"type":"Point"}
}
