{
  "type": "Feature",
  "properties": {
    "date:inception_lower":"2012-05-01",
    "date:inception_upper":"2012-05-31",
    "iso:country":"GB",
    "wof:name":"E14 7GL",
    "wof:placetype":"postalcode"
},
  "geometry": {"coordinates":[-0.033358,51.512645],"type":"Point"}
}