{
  "type": "Feature",
  "properties": {
    "date:inception_lower":"1980-01-01",
    "date:inception_upper":"1980-01-31",
    "iso:country":"GB",
    "wof:name":"M19 2FE",
    "wof:placetype":"postalcode"
},
  "geometry": {"coordinates":[-2.196722,53.44802],"type":"Point"}
}