{
  "type": "Feature",
  "properties": {
    "date:inception_lower": "1985-04-01",
    "date:inception_upper": "1985-04-01",
    "iso:country": "GB",
    "wof:name": "PO1 5JU",
    "wof:placetype": "postalcode"
  },
  "geometry": {"coordinates":[-1.076428,50.806195],"type":"Point"}
}
