{
  "type": "Feature",
  "properties": {
    "iso:country": "GB",
    "wof:name": "BL0 9HJ",
    "wof:placetype": "postalcode"
  },
  "geometry": {"coordinates":[-2.325258,53.644207],"type":"Point"}
}
