{
  "type": "Feature",
  "properties": {
    "iso:country":"GB",
    "wof:name":"BL0 9HJ",
    "wof:placetype":"postalcode"
},
  "geometry": {"coordinates":[-2.32525799245624,53.64420662765936],"type":"Point"}
}