{
  "type": "Feature",
  "properties": {
    "date:inception_lower":"2003-07-01",
    "date:inception_upper":"2003-07-31",
    "iso:country":"GB",
    "wof:name":"WF2 0WG",
    "wof:placetype":"postalcode"
},
  "geometry": {"coordinates":[-1.532661,53.69596],"type":"Point"}
}