{
  "type": "Feature",
  "properties": {
    "iso:country": "GB",
    "wof:name": "BS8 2UR",
    "wof:placetype": "postalcode"
  },
  "geometry": {"coordinates":[-2.614527,51.46835],"type":"Point"}
}
