{
  "type": "Feature",
  "properties": {
    "iso:country": "GB",
    "wof:name": "PO30 5LU",
    "wof:placetype": "postalcode"
  },
  "geometry": {"coordinates":[-1.322471,50.700624],"type":"Point"}
}
