{
  "type": "Feature",
  "properties": {
    "date:inception_lower": "1980-01-01",
    "date:inception_upper": "1980-01-01",
    "iso:country": "GB",
    "wof:name": "LE5 2NB",
    "wof:placetype": "postalcode"
  },
  "geometry": {"coordinates":[-1.049295,52.635774],"type":"Point"}
}
