{
  "type": "Feature",
  "properties": {
    "iso:country":"GB",
    "wof:name":"NG22 0PX",
    "wof:placetype":"postalcode"
},
  "geometry": {"coordinates":[-0.87314468070557,53.22508083834754],"type":"Point"}
}