{
  "type": "Feature",
  "properties": {
    "iso:country": "GB",
    "wof:name": "G71 8LL",
    "wof:placetype": "postalcode"
  },
  "geometry": {"coordinates":[-4.070165,55.807728],"type":"Point"}
}
