{
  "type": "Feature",
  "properties": {
    "iso:country":"GB",
    "wof:name":"PE1 4QA",
    "wof:placetype":"postalcode"
},
  "geometry": {"coordinates":[-0.23121965083168,52.60046496888409],"type":"Point"}
}