{
  "type": "Feature",
  "properties": {
    "iso:country":"GB",
    "wof:name":"DY3 3DP",
    "wof:placetype":"postalcode"
},
  "geometry": {"coordinates":[-2.14470781566374,52.52894046090744],"type":"Point"}
}