{
  "type": "Feature",
  "properties": {
    "date:inception_lower": "1993-01-01",
    "date:inception_upper": "1993-01-01",
    "iso:country": "GB",
    "wof:name": "SA33 4LF",
    "wof:placetype": "postalcode"
  },
  "geometry": {"coordinates":[-4.506317,51.8489],"type":"Point"}
}
