{
  "type": "Feature",
  "properties": {
    "iso:country":"GB",
    "wof:name":"SA33 4LF",
    "wof:placetype":"postalcode"
},
  "geometry": {"coordinates":[-4.50631660100246,51.84889956573165],"type":"Point"}
}