{
  "type": "Feature",
  "properties": {
    "iso:country": "GB",
    "wof:name": "SA33 4LF",
    "wof:placetype": "postalcode"
  },
  "geometry": {"coordinates":[-4.506317,51.8489],"type":"Point"}
}
