{
  "type": "Feature",
  "properties": {
    "date:inception_lower": "2018-02-01",
    "date:inception_upper": "2018-02-01",
    "iso:country": "GB",
    "wof:name": "BN25 1FA",
    "wof:placetype": "postalcode"
  },
  "geometry": {"coordinates":[0.102623,50.773638],"type":"Point"}
}
