{
  "type": "Feature",
  "properties": {
    "iso:country": "GB",
    "wof:name": "BN25 1FA",
    "wof:placetype": "postalcode"
  },
  "geometry": {"coordinates":[0.102623,50.773638],"type":"Point"}
}
