{
  "type": "Feature",
  "properties": {
    "iso:country":"GB",
    "wof:name":"CH5 4QL",
    "wof:placetype":"postalcode"
},
  "geometry": {"coordinates":[-3.05411953719058,53.2144330528342],"type":"Point"}
}