{
  "type": "Feature",
  "properties": {
    "iso:country":"GB",
    "wof:name":"PR6 8LQ",
    "wof:placetype":"postalcode"
},
  "geometry": {"coordinates":[-2.61027140305023,53.68065463089417],"type":"Point"}
}