{
  "type": "Feature",
  "properties": {
    "iso:country": "GB",
    "wof:name": "DL6 2QP",
    "wof:placetype": "postalcode"
  },
  "geometry": {"coordinates":[-1.425889,54.3589],"type":"Point"}
}
