{
  "type": "Feature",
  "properties": {
    "date:inception_lower":"1980-01-01",
    "date:inception_upper":"1980-01-31",
    "iso:country":"GB",
    "wof:name":"DL6 2QP",
    "wof:placetype":"postalcode"
},
  "geometry": {"coordinates":[-1.425889,54.3589],"type":"Point"}
}