{
  "type": "Feature",
  "properties": {
    "iso:country":"GB",
    "wof:name":"DL6 2QP",
    "wof:placetype":"postalcode"
},
  "geometry": {"coordinates":[-1.42588858546364,54.35889960291152],"type":"Point"}
}