{
  "type": "Feature",
  "properties": {
    "iso:country":"GB",
    "wof:name":"IV3 5BD",
    "wof:placetype":"postalcode"
},
  "geometry": {"coordinates":[-4.24635858708841,57.46917246769687],"type":"Point"}
}