{
  "type": "Feature",
  "properties": {
    "iso:country":"GB",
    "wof:name":"TW7 5JB",
    "wof:placetype":"postalcode"
},
  "geometry": {"coordinates":[-0.32979808733826,51.48212374154667],"type":"Point"}
}