{
  "type": "Feature",
  "properties": {
    "iso:country": "GB",
    "wof:name": "SS0 0ND",
    "wof:placetype": "postalcode"
  },
  "geometry": {"coordinates":[0.682769,51.559628],"type":"Point"}
}
