{
  "type": "Feature",
  "properties": {
    "iso:country":"GB",
    "wof:name":"SS0 0ND",
    "wof:placetype":"postalcode"
},
  "geometry": {"coordinates":[0.68276920176151,51.55962843238891],"type":"Point"}
}