{
  "type": "Feature",
  "properties": {
    "iso:country": "GB",
    "wof:name": "TN9 2QP",
    "wof:placetype": "postalcode"
  },
  "geometry": {"coordinates":[0.254543,51.184668],"type":"Point"}
}
