{
  "type": "Feature",
  "properties": {
    "iso:country":"GB",
    "wof:name":"EX39 5TQ",
    "wof:placetype":"postalcode"
},
  "geometry": {"coordinates":[-4.39911147293274,50.99806496230691],"type":"Point"}
}