{
  "type": "Feature",
  "properties": {
    "iso:country": "GB",
    "wof:name": "EX39 5TQ",
    "wof:placetype": "postalcode"
  },
  "geometry": {"coordinates":[-4.399111,50.998065],"type":"Point"}
}
