{
  "type": "Feature",
  "properties": {
    "iso:country":"GB",
    "wof:name":"NE29 6PQ",
    "wof:placetype":"postalcode"
},
  "geometry": {"coordinates":[-1.44604171311496,55.00774830149653],"type":"Point"}
}