{
  "type": "Feature",
  "properties": {
    "iso:country": "GB",
    "wof:name": "NE29 6PQ",
    "wof:placetype": "postalcode"
  },
  "geometry": {"coordinates":[-1.446042,55.007748],"type":"Point"}
}
