{
  "type": "Feature",
  "properties": {
    "iso:country":"GB",
    "wof:name":"NR13 3JG",
    "wof:placetype":"postalcode"
},
  "geometry": {"coordinates":[1.5127834233546,52.59708628107043],"type":"Point"}
}