{
  "type": "Feature",
  "properties": {
    "iso:country": "GB",
    "wof:name": "NR13 3JG",
    "wof:placetype": "postalcode"
  },
  "geometry": {"coordinates":[1.512478,52.593084],"type":"Point"}
}
