{
  "type": "Feature",
  "properties": {
    "date:inception_lower":"1980-01-01",
    "date:inception_upper":"1980-01-31",
    "iso:country":"GB",
    "wof:name":"NR13 3JG",
    "wof:placetype":"postalcode"
},
  "geometry": {"coordinates":[1.512478,52.593084],"type":"Point"}
}