{
  "type": "Feature",
  "properties": {
    "iso:country":"GB",
    "wof:name":"OX9 3TT",
    "wof:placetype":"postalcode"
},
  "geometry": {"coordinates":[-0.97090078651158,51.75001498449589],"type":"Point"}
}