{
  "type": "Feature",
  "properties": {
    "iso:country":"GB",
    "wof:name":"S75 3DX",
    "wof:placetype":"postalcode"
},
  "geometry": {"coordinates":[-1.48465874215388,53.49651783502485],"type":"Point"}
}