{
  "type": "Feature",
  "properties": {
    "iso:country":"GB",
    "wof:name":"SE5 8PT",
    "wof:placetype":"postalcode"
},
  "geometry": {"coordinates":[-0.07868754941293,51.47379083244266],"type":"Point"}
}