{
  "type": "Feature",
  "properties": {
    "date:inception_lower": "1998-06-01",
    "date:inception_upper": "1998-06-01",
    "iso:country": "GB",
    "wof:name": "SA7 9NH",
    "wof:placetype": "postalcode"
  },
  "geometry": {"coordinates":[-3.867931,51.663001],"type":"Point"}
}
