{
  "type": "Feature",
  "properties": {
    "iso:country": "GB",
    "wof:name": "SA7 9NH",
    "wof:placetype": "postalcode"
  },
  "geometry": {"coordinates":[-3.867931,51.663001],"type":"Point"}
}
