{
  "type": "Feature",
  "properties": {
    "iso:country":"GB",
    "wof:name":"SA7 9NH",
    "wof:placetype":"postalcode"
},
  "geometry": {"coordinates":[-3.86793094124261,51.6630006284627],"type":"Point"}
}