{
  "type": "Feature",
  "properties": {
    "iso:country":"GB",
    "wof:name":"B77 2HL",
    "wof:placetype":"postalcode"
},
  "geometry": {"coordinates":[-1.66081223655069,52.61826278788054],"type":"Point"}
}