{
  "type": "Feature",
  "properties": {
    "iso:country": "GB",
    "wof:name": "CV37 6GJ",
    "wof:placetype": "postalcode"
  },
  "geometry": {"coordinates":[-1.705172,52.191792],"type":"Point"}
}
