{
  "type": "Feature",
  "properties": {
    "iso:country":"GB",
    "wof:name":"TN38 0RE",
    "wof:placetype":"postalcode"
},
  "geometry": {"coordinates":[0.55259816969546,50.85892869413181],"type":"Point"}
}