{
  "type": "Feature",
  "properties": {
    "iso:country":"GB",
    "wof:name":"WV14 6AG",
    "wof:placetype":"postalcode"
},
  "geometry": {"coordinates":[-2.07789895904714,52.56759687948756],"type":"Point"}
}