{
  "type": "Feature",
  "properties": {
    "date:inception_lower":"2008-06-01",
    "date:inception_upper":"2008-06-30",
    "iso:country":"GB",
    "wof:name":"S71 4PT",
    "wof:placetype":"postalcode"
},
  "geometry": {"coordinates":[-1.461205,53.596267],"type":"Point"}
}