{
  "type": "Feature",
  "properties": {
    "iso:country": "GB",
    "wof:name": "S71 4PT",
    "wof:placetype": "postalcode"
  },
  "geometry": {"coordinates":[-1.461205,53.596267],"type":"Point"}
}
