{
  "type": "Feature",
  "properties": {
    "iso:country": "GB",
    "wof:name": "YO18 7PS",
    "wof:placetype": "postalcode"
  },
  "geometry": {"coordinates":[-0.655372,54.234719],"type":"Point"}
}
