{
  "type": "Feature",
  "properties": {
    "iso:country":"GB",
    "wof:name":"YO18 7PS",
    "wof:placetype":"postalcode"
},
  "geometry": {"coordinates":[-0.65537180695052,54.23471944648671],"type":"Point"}
}