{
  "type": "Feature",
  "properties": {
    "iso:country":"GB",
    "wof:name":"RG20 8LR",
    "wof:placetype":"postalcode"
},
  "geometry": {"coordinates":[-1.39813829211359,51.41082656548424],"type":"Point"}
}