{
  "type": "Feature",
  "properties": {
    "iso:country":"GB",
    "wof:name":"CM17 0LG",
    "wof:placetype":"postalcode"
},
  "geometry": {"coordinates":[0.15352705462284,51.78468034429262],"type":"Point"}
}