{
  "type": "Feature",
  "properties": {
    "iso:country":"GB",
    "wof:name":"TQ6 9QD",
    "wof:placetype":"postalcode"
},
  "geometry": {"coordinates":[-3.58072842350009,50.35215518772065],"type":"Point"}
}