{
  "type": "Feature",
  "properties": {
    "date:inception_lower":"2001-12-01",
    "date:inception_upper":"2001-12-31",
    "iso:country":"GB",
    "wof:name":"TQ6 9QD",
    "wof:placetype":"postalcode"
},
  "geometry": {"coordinates":[-3.580728,50.352155],"type":"Point"}
}