{
  "type": "Feature",
  "properties": {
    "iso:country": "GB",
    "wof:name": "TQ6 9QD",
    "wof:placetype": "postalcode"
  },
  "geometry": {"coordinates":[-3.580728,50.352155],"type":"Point"}
}
