{
  "type": "Feature",
  "properties": {
    "date:inception_lower":"1980-01-01",
    "date:inception_upper":"1980-01-31",
    "iso:country":"GB",
    "wof:name":"BS16 6DU",
    "wof:placetype":"postalcode"
},
  "geometry": {"coordinates":[-2.505829,51.495179],"type":"Point"}
}