{
  "type": "Feature",
  "properties": {
    "iso:country":"GB",
    "wof:name":"BS16 6DU",
    "wof:placetype":"postalcode"
},
  "geometry": {"coordinates":[-2.50582925451636,51.49517857720774],"type":"Point"}
}