{
  "type": "Feature",
  "properties": {
    "iso:country": "GB",
    "wof:name": "EH41 3DE",
    "wof:placetype": "postalcode"
  },
  "geometry": {"coordinates":[-2.807677,55.954778],"type":"Point"}
}
