{
  "type": "Feature",
  "properties": {
    "iso:country":"GB",
    "wof:name":"NE23 7LU",
    "wof:placetype":"postalcode"
},
  "geometry": {"coordinates":[-1.5902218393221,55.05013167492275],"type":"Point"}
}