{
  "type": "Feature",
  "properties": {
    "iso:country": "GB",
    "wof:name": "CW2 5FA",
    "wof:placetype": "postalcode"
  },
  "geometry": {"coordinates":[-2.440772,53.062796],"type":"Point"}
}
