{
  "type": "Feature",
  "properties": {
    "date:inception_lower": "1980-01-01",
    "date:inception_upper": "1980-01-01",
    "iso:country": "GB",
    "wof:name": "B76 9AX",
    "wof:placetype": "postalcode"
  },
  "geometry": {"coordinates":[-1.768932,52.531276],"type":"Point"}
}
