{
  "type": "Feature",
  "properties": {
    "iso:country": "GB",
    "wof:name": "B76 9AX",
    "wof:placetype": "postalcode"
  },
  "geometry": {"coordinates":[-1.768932,52.531276],"type":"Point"}
}
