{
  "type": "Feature",
  "properties": {
    "iso:country": "GB",
    "wof:name": "ME16 9EJ",
    "wof:placetype": "postalcode"
  },
  "geometry": {"coordinates":[0.47302,51.263506],"type":"Point"}
}
