{
  "type": "Feature",
  "properties": {
    "date:inception_lower": "1980-01-01",
    "date:inception_upper": "1980-01-01",
    "iso:country": "GB",
    "wof:name": "N16 0NL",
    "wof:placetype": "postalcode"
  },
  "geometry": {"coordinates":[-0.077859,51.561284],"type":"Point"}
}
