{
  "type": "Feature",
  "properties": {
    "iso:country": "GB",
    "wof:name": "EH22 2NP",
    "wof:placetype": "postalcode"
  },
  "geometry": {"coordinates":[-3.020809,55.905403],"type":"Point"}
}
