{
  "type": "Feature",
  "properties": {
    "iso:country":"GB",
    "wof:name":"BS15 4DT",
    "wof:placetype":"postalcode"
},
  "geometry": {"coordinates":[-2.49506058450176,51.46516573105622],"type":"Point"}
}