{
  "type": "Feature",
  "properties": {
    "date:inception_lower": "1980-01-01",
    "date:inception_upper": "1980-01-01",
    "iso:country": "GB",
    "wof:name": "NG22 9ES",
    "wof:placetype": "postalcode"
  },
  "geometry": {"coordinates":[-1.051896,53.224128],"type":"Point"}
}
