{
  "type": "Feature",
  "properties": {
    "iso:country":"GB",
    "wof:name":"SW15 6EW",
    "wof:placetype":"postalcode"
},
  "geometry": {"coordinates":[-0.22060393647715,51.45839615637991],"type":"Point"}
}