{
  "type": "Feature",
  "properties": {
    "iso:country":"GB",
    "wof:name":"LD2 3LR",
    "wof:placetype":"postalcode"
},
  "geometry": {"coordinates":[-3.54792665037691,52.15316687791361],"type":"Point"}
}