{
  "type": "Feature",
  "properties": {
    "iso:country": "GB",
    "wof:name": "LD2 3LR",
    "wof:placetype": "postalcode"
  },
  "geometry": {"coordinates":[-3.547927,52.153167],"type":"Point"}
}
