{
  "type": "Feature",
  "properties": {
    "iso:country":"GB",
    "wof:name":"EN9 1UQ",
    "wof:placetype":"postalcode"
},
  "geometry": {"coordinates":[0.01414423461356,51.68327124662501],"type":"Point"}
}