{
  "type": "Feature",
  "properties": {
    "iso:country":"GB",
    "wof:name":"GU14 6ND",
    "wof:placetype":"postalcode"
},
  "geometry": {"coordinates":[-0.74854625643645,51.28000838491745],"type":"Point"}
}