{
  "type": "Feature",
  "properties": {
    "iso:country": "GB",
    "wof:name": "GU14 6ND",
    "wof:placetype": "postalcode"
  },
  "geometry": {"coordinates":[-0.748546,51.280008],"type":"Point"}
}
