{
  "type": "Feature",
  "properties": {
    "date:inception_lower":"2003-06-01",
    "date:inception_upper":"2003-06-30",
    "iso:country":"GB",
    "wof:name":"LN2 3WU",
    "wof:placetype":"postalcode"
},
  "geometry": {"coordinates":[-0.481134,53.299039],"type":"Point"}
}