{
  "type": "Feature",
  "properties": {
    "iso:country":"GB",
    "wof:name":"LN2 3WU",
    "wof:placetype":"postalcode"
},
  "geometry": {"coordinates":[-0.48113355139651,53.29903913129063],"type":"Point"}
}