{
  "type": "Feature",
  "properties": {
    "iso:country":"GB",
    "wof:name":"BD7 1RH",
    "wof:placetype":"postalcode"
},
  "geometry": {"coordinates":[-1.76752717285818,53.78747857424653],"type":"Point"}
}