{
  "type": "Feature",
  "properties": {
    "iso:country":"GB",
    "wof:name":"LN6 7JQ",
    "wof:placetype":"postalcode"
},
  "geometry": {"coordinates":[-0.57164120094556,53.20563191558242],"type":"Point"}
}