{
  "type": "Feature",
  "properties": {
    "iso:country": "GB",
    "wof:name": "LN6 7JQ",
    "wof:placetype": "postalcode"
  },
  "geometry": {"coordinates":[-0.571626,53.205645],"type":"Point"}
}
