{
  "type": "Feature",
  "properties": {
    "iso:country":"GB",
    "wof:name":"E6 1HY",
    "wof:placetype":"postalcode"
},
  "geometry": {"coordinates":[0.05202427084478,51.53386872886256],"type":"Point"}
}