{
  "type": "Feature",
  "properties": {
    "iso:country":"GB",
    "wof:name":"E13 8QR",
    "wof:placetype":"postalcode"
},
  "geometry": {"coordinates":[0.02872101440705,51.52279041842987],"type":"Point"}
}