{
  "type": "Feature",
  "properties": {
    "date:inception_lower": "1980-01-01",
    "date:inception_upper": "1980-01-01",
    "iso:country": "GB",
    "wof:name": "CF45 3ST",
    "wof:placetype": "postalcode"
  },
  "geometry": {"coordinates":[-3.360053,51.668759],"type":"Point"}
}
