{
  "type": "Feature",
  "properties": {
    "iso:country":"GB",
    "wof:name":"TN29 9DA",
    "wof:placetype":"postalcode"
},
  "geometry": {"coordinates":[0.90443686996473,50.94875881499847],"type":"Point"}
}