{
  "type": "Feature",
  "properties": {
    "iso:country":"GB",
    "wof:name":"BN1 6DJ",
    "wof:placetype":"postalcode"
},
  "geometry": {"coordinates":[-0.1374603423726,50.83792658856825],"type":"Point"}
}