{
  "type": "Feature",
  "properties": {
    "iso:country": "GB",
    "wof:name": "WF11 9LW",
    "wof:placetype": "postalcode"
  },
  "geometry": {"coordinates":[-1.206584,53.741775],"type":"Point"}
}
