{
  "type": "Feature",
  "properties": {
    "iso:country":"GB",
    "wof:name":"IP4 5AY",
    "wof:placetype":"postalcode"
},
  "geometry": {"coordinates":[1.17956667626107,52.056527298908],"type":"Point"}
}