{
  "type": "Feature",
  "properties": {
    "iso:country":"GB",
    "wof:name":"BD5 7BJ",
    "wof:placetype":"postalcode"
},
  "geometry": {"coordinates":[-1.75626340239752,53.77728181497159],"type":"Point"}
}