{
  "type": "Feature",
  "properties": {
    "iso:country":"GB",
    "wof:name":"EH16 4EY",
    "wof:placetype":"postalcode"
},
  "geometry": {"coordinates":[-3.12344822353617,55.92810052160021],"type":"Point"}
}