{
  "type": "Feature",
  "properties": {
    "iso:country":"GB",
    "wof:name":"GL7 2JR",
    "wof:placetype":"postalcode"
},
  "geometry": {"coordinates":[-1.97852095318104,51.73522088889204],"type":"Point"}
}