{
  "type": "Feature",
  "properties": {
    "iso:country": "GB",
    "wof:name": "GL7 2JR",
    "wof:placetype": "postalcode"
  },
  "geometry": {"coordinates":[-1.978512,51.735226],"type":"Point"}
}
