{
  "type": "Feature",
  "properties": {
    "date:inception_lower": "1980-01-01",
    "date:inception_upper": "1980-01-01",
    "iso:country": "GB",
    "wof:name": "GL7 2JR",
    "wof:placetype": "postalcode"
  },
  "geometry": {"coordinates":[-1.978512,51.735226],"type":"Point"}
}
