{
  "type": "Feature",
  "properties": {
    "iso:country":"GB",
    "wof:name":"GL52 6YG",
    "wof:placetype":"postalcode"
},
  "geometry": {"coordinates":[-2.04894563095591,51.88582050725865],"type":"Point"}
}