{
  "type": "Feature",
  "properties": {
    "iso:country": "GB",
    "wof:name": "GL52 6YG",
    "wof:placetype": "postalcode"
  },
  "geometry": {"coordinates":[-2.048946,51.885821],"type":"Point"}
}
