{
  "type": "Feature",
  "properties": {
    "date:inception_lower": "1980-01-01",
    "date:inception_upper": "1980-01-01",
    "iso:country": "GB",
    "wof:name": "GL52 6YG",
    "wof:placetype": "postalcode"
  },
  "geometry": {"coordinates":[-2.049272,51.885783],"type":"Point"}
}
