{
  "type": "Feature",
  "properties": {
    "iso:country":"GB",
    "wof:name":"DT6 6AP",
    "wof:placetype":"postalcode"
},
  "geometry": {"coordinates":[-2.78168208049392,50.72233599465945],"type":"Point"}
}