{
  "type": "Feature",
  "properties": {
    "iso:country": "GB",
    "wof:name": "CH63 3HD",
    "wof:placetype": "postalcode"
  },
  "geometry": {"coordinates":[-3.01043,53.345738],"type":"Point"}
}
