{
  "type": "Feature",
  "properties": {
    "date:inception_lower": "1980-01-01",
    "date:inception_upper": "1980-01-01",
    "iso:country": "GB",
    "wof:name": "DN5 8SG",
    "wof:placetype": "postalcode"
  },
  "geometry": {"coordinates":[-1.172092,53.540002],"type":"Point"}
}
