{
  "type": "Feature",
  "properties": {
    "iso:country": "GB",
    "wof:name": "IG3 9XQ",
    "wof:placetype": "postalcode"
  },
  "geometry": {"coordinates":[0.103158,51.562729],"type":"Point"}
}
