{
  "type": "Feature",
  "properties": {
    "date:inception_lower": "1980-01-01",
    "date:inception_upper": "1980-01-01",
    "iso:country": "GB",
    "wof:name": "IG3 9XQ",
    "wof:placetype": "postalcode"
  },
  "geometry": {"coordinates":[0.103158,51.562729],"type":"Point"}
}
