{
  "type": "Feature",
  "properties": {
    "iso:country":"GB",
    "wof:name":"ST18 9QL",
    "wof:placetype":"postalcode"
},
  "geometry": {"coordinates":[-2.20742070837207,52.83289554243851],"type":"Point"}
}