{
  "type": "Feature",
  "properties": {
    "date:inception_lower": "1991-09-01",
    "date:inception_upper": "1991-09-01",
    "iso:country": "GB",
    "wof:name": "ST18 9QL",
    "wof:placetype": "postalcode"
  },
  "geometry": {"coordinates":[-2.207939,52.832652],"type":"Point"}
}
