{
  "type": "Feature",
  "properties": {
    "iso:country": "GB",
    "wof:name": "ST15 0GT",
    "wof:placetype": "postalcode"
  },
  "geometry": {"coordinates":[-2.199644,52.897713],"type":"Point"}
}
