{
  "type": "Feature",
  "properties": {
    "iso:country":"GB",
    "wof:name":"ST15 0GT",
    "wof:placetype":"postalcode"
},
  "geometry": {"coordinates":[-2.19964372228619,52.89771336374088],"type":"Point"}
}