{
  "type": "Feature",
  "properties": {
    "iso:country": "GB",
    "wof:name": "HP22 0AP",
    "wof:placetype": "postalcode"
  },
  "geometry": {"coordinates":[-0.733014,51.803294],"type":"Point"}
}
