{
  "type": "Feature",
  "properties": {
    "date:inception_lower": "2023-10-01",
    "date:inception_upper": "2023-10-01",
    "iso:country": "GB",
    "wof:name": "CV37 9YJ",
    "wof:placetype": "postalcode"
  },
  "geometry": {"coordinates":[-1.730297,52.186463],"type":"Point"}
}
