{
  "type": "Feature",
  "properties": {
    "iso:country":"GB",
    "wof:name":"AL6 9BS",
    "wof:placetype":"postalcode"
},
  "geometry": {"coordinates":[-0.26713413364264,51.84333766787061],"type":"Point"}
}