{
  "type": "Feature",
  "properties": {
    "date:inception_lower": "1980-01-01",
    "date:inception_upper": "1980-01-01",
    "iso:country": "GB",
    "wof:name": "AL6 9BS",
    "wof:placetype": "postalcode"
  },
  "geometry": {"coordinates":[-0.265576,51.84361],"type":"Point"}
}
