{
  "type": "Feature",
  "properties": {
    "iso:country":"GB",
    "wof:name":"BD15 9AZ",
    "wof:placetype":"postalcode"
},
  "geometry": {"coordinates":[-1.83253880604054,53.80931974017551],"type":"Point"}
}