{
  "type": "Feature",
  "properties": {
    "iso:country":"GB",
    "wof:name":"NP11 4LX",
    "wof:placetype":"postalcode"
},
  "geometry": {"coordinates":[-3.15070953764071,51.66474826391913],"type":"Point"}
}