{
  "type": "Feature",
  "properties": {
    "iso:country": "GB",
    "wof:name": "NP11 4LX",
    "wof:placetype": "postalcode"
  },
  "geometry": {"coordinates":[-3.150709,51.664748],"type":"Point"}
}
