{
  "type": "Feature",
  "properties": {
    "date:inception_lower": "1990-07-01",
    "date:inception_upper": "1990-07-01",
    "iso:country": "GB",
    "wof:name": "L33 1ZG",
    "wof:placetype": "postalcode"
  },
  "geometry": {"coordinates":[-2.886891,53.495917],"type":"Point"}
}
