{
  "type": "Feature",
  "properties": {
    "iso:country":"GB",
    "wof:name":"L33 1ZG",
    "wof:placetype":"postalcode"
},
  "geometry": {"coordinates":[-2.88689140504154,53.49591740824561],"type":"Point"}
}