{
  "type": "Feature",
  "properties": {
    "date:inception_lower": "1980-01-01",
    "date:inception_upper": "1980-01-01",
    "iso:country": "GB",
    "wof:name": "N8 0NS",
    "wof:placetype": "postalcode"
  },
  "geometry": {"coordinates":[-0.102846,51.586249],"type":"Point"}
}
