{
  "type": "Feature",
  "properties": {
    "date:inception_lower": "1998-12-01",
    "date:inception_upper": "1998-12-01",
    "iso:country": "GB",
    "wof:name": "KY13 8EP",
    "wof:placetype": "postalcode"
  },
  "geometry": {"coordinates":[-3.420485,56.203964],"type":"Point"}
}
