{
  "type": "Feature",
  "properties": {
    "iso:country":"GB",
    "wof:name":"KY13 8EP",
    "wof:placetype":"postalcode"
},
  "geometry": {"coordinates":[-3.42048478762691,56.20396440572412],"type":"Point"}
}