{
  "type": "Feature",
  "properties": {
    "iso:country":"GB",
    "wof:name":"TA24 8AE",
    "wof:placetype":"postalcode"
},
  "geometry": {"coordinates":[-3.4911307853078,51.20248484249206],"type":"Point"}
}