{
  "type": "Feature",
  "properties": {
    "iso:country":"GB",
    "wof:name":"CF5 4GY",
    "wof:placetype":"postalcode"
},
  "geometry": {"coordinates":[-3.24653683997439,51.47725235429242],"type":"Point"}
}