{
  "type": "Feature",
  "properties": {
    "date:inception_lower": "1998-06-01",
    "date:inception_upper": "1998-06-01",
    "iso:country": "GB",
    "wof:name": "M46 9TZ",
    "wof:placetype": "postalcode"
  },
  "geometry": {"coordinates":[-2.472082,53.529484],"type":"Point"}
}
