{
  "type": "Feature",
  "properties": {
    "iso:country":"GB",
    "wof:name":"M46 9TZ",
    "wof:placetype":"postalcode"
},
  "geometry": {"coordinates":[-2.47208166378206,53.52948429132185],"type":"Point"}
}