{
  "type": "Feature",
  "properties": {
    "date:inception_lower":"2001-12-01",
    "date:inception_upper":"2001-12-31",
    "iso:country":"GB",
    "wof:name":"SE10 0QR",
    "wof:placetype":"postalcode"
},
  "geometry": {"coordinates":[0.013371,51.492435],"type":"Point"}
}