{
  "type": "Feature",
  "properties": {
    "iso:country":"GB",
    "wof:name":"SE10 0QR",
    "wof:placetype":"postalcode"
},
  "geometry": {"coordinates":[0.01337057845341,51.49243479167006],"type":"Point"}
}