{
  "type": "Feature",
  "properties": {
    "iso:country": "GB",
    "wof:name": "SO21 3FU",
    "wof:placetype": "postalcode"
  },
  "geometry": {"coordinates":[-1.378672,51.164072],"type":"Point"}
}
