{
  "type": "Feature",
  "properties": {
    "iso:country":"GB",
    "wof:name":"RG9 5AR",
    "wof:placetype":"postalcode"
},
  "geometry": {"coordinates":[-0.9927521030532,51.58082183998614],"type":"Point"}
}