{
  "type": "Feature",
  "properties": {
    "iso:country": "GB",
    "wof:name": "G40 3HP",
    "wof:placetype": "postalcode"
  },
  "geometry": {"coordinates":[-4.204092,55.846175],"type":"Point"}
}
