{
  "type": "Feature",
  "properties": {
    "date:inception_lower":"2007-01-01",
    "date:inception_upper":"2007-01-31",
    "iso:country":"GB",
    "wof:name":"TS1 2XH",
    "wof:placetype":"postalcode"
},
  "geometry": {"coordinates":[-1.244942,54.575852],"type":"Point"}
}