{
  "type": "Feature",
  "properties": {
    "iso:country": "GB",
    "wof:name": "WA8 5AA",
    "wof:placetype": "postalcode"
  },
  "geometry": {"coordinates":[-2.724125,53.389957],"type":"Point"}
}
