{
  "type": "Feature",
  "properties": {
    "date:inception_lower":"1980-01-01",
    "date:inception_upper":"1980-01-31",
    "iso:country":"GB",
    "wof:name":"NE34 7SG",
    "wof:placetype":"postalcode"
},
  "geometry": {"coordinates":[-1.399197,54.978518],"type":"Point"}
}