{
  "type": "Feature",
  "properties": {
    "iso:country":"GB",
    "wof:name":"NE34 7SG",
    "wof:placetype":"postalcode"
},
  "geometry": {"coordinates":[-1.39919658248827,54.97851824306373],"type":"Point"}
}