{
  "type": "Feature",
  "properties": {
    "date:inception_lower": "2005-03-01",
    "date:inception_upper": "2005-03-01",
    "iso:country": "GB",
    "wof:name": "CH64 1TU",
    "wof:placetype": "postalcode"
  },
  "geometry": {"coordinates":[-3.007652,53.294234],"type":"Point"}
}
