{
  "type": "Feature",
  "properties": {
    "iso:country":"GB",
    "wof:name":"CH64 1TU",
    "wof:placetype":"postalcode"
},
  "geometry": {"coordinates":[-3.00754826313255,53.29423735783661],"type":"Point"}
}