{
  "type": "Feature",
  "properties": {
    "date:inception_lower":"1995-01-01",
    "date:inception_upper":"1995-01-31",
    "iso:country":"GB",
    "wof:name":"IP14 5BE",
    "wof:placetype":"postalcode"
},
  "geometry": {"coordinates":[1.018458,52.184537],"type":"Point"}
}