{
  "type": "Feature",
  "properties": {
    "iso:country":"GB",
    "wof:name":"OX16 9TY",
    "wof:placetype":"postalcode"
},
  "geometry": {"coordinates":[-1.32509985228424,52.04765717018677],"type":"Point"}
}