{
  "type": "Feature",
  "properties": {
    "date:inception_lower":"1980-01-01",
    "date:inception_upper":"1980-01-31",
    "iso:country":"GB",
    "wof:name":"CM3 4HN",
    "wof:placetype":"postalcode"
},
  "geometry": {"coordinates":[0.592949,51.677888],"type":"Point"}
}