{
  "type": "Feature",
  "properties": {
    "iso:country":"GB",
    "wof:name":"CM3 4HN",
    "wof:placetype":"postalcode"
},
  "geometry": {"coordinates":[0.59294864103677,51.67788802032775],"type":"Point"}
}