{
  "type": "Feature",
  "properties": {
    "iso:country": "GB",
    "wof:name": "CM3 4HN",
    "wof:placetype": "postalcode"
  },
  "geometry": {"coordinates":[0.592949,51.677888],"type":"Point"}
}
