{
  "type": "Feature",
  "properties": {
    "iso:country": "GB",
    "wof:name": "NE12 8AF",
    "wof:placetype": "postalcode"
  },
  "geometry": {"coordinates":[-1.566179,55.01263],"type":"Point"}
}
