{
  "type": "Feature",
  "properties": {
    "iso:country": "GB",
    "wof:name": "SW19 4NG",
    "wof:placetype": "postalcode"
  },
  "geometry": {"coordinates":[-0.218467,51.419857],"type":"Point"}
}
