{
  "type": "Feature",
  "properties": {
    "iso:country":"GB",
    "wof:name":"SW19 4NG",
    "wof:placetype":"postalcode"
},
  "geometry": {"coordinates":[-0.2189285588643,51.42007156556477],"type":"Point"}
}