{
  "type": "Feature",
  "properties": {
    "iso:country":"GB",
    "wof:name":"RM8 2DB",
    "wof:placetype":"postalcode"
},
  "geometry": {"coordinates":[0.11253940430226,51.55220984322791],"type":"Point"}
}