{
  "type": "Feature",
  "properties": {
    "iso:country": "GB",
    "wof:name": "SA15 4RF",
    "wof:placetype": "postalcode"
  },
  "geometry": {"coordinates":[-4.213467,51.706625],"type":"Point"}
}
