{
  "type": "Feature",
  "properties": {
    "iso:country":"GB",
    "wof:name":"SA15 4RF",
    "wof:placetype":"postalcode"
},
  "geometry": {"coordinates":[-4.21346662140055,51.70662475731215],"type":"Point"}
}