{
  "type": "Feature",
  "properties": {
    "iso:country":"GB",
    "wof:name":"LU7 2PS",
    "wof:placetype":"postalcode"
},
  "geometry": {"coordinates":[-0.68282282867175,51.91333920999782],"type":"Point"}
}