{
  "type": "Feature",
  "properties": {
    "iso:country": "GB",
    "wof:name": "NE12 8GA",
    "wof:placetype": "postalcode"
  },
  "geometry": {"coordinates":[-1.591024,55.011296],"type":"Point"}
}
