{
  "type": "Feature",
  "properties": {
    "date:inception_lower":"2003-08-01",
    "date:inception_upper":"2003-08-31",
    "iso:country":"GB",
    "wof:name":"NE12 8GA",
    "wof:placetype":"postalcode"
},
  "geometry": {"coordinates":[-1.591024,55.011296],"type":"Point"}
}