{
  "type": "Feature",
  "properties": {
    "date:inception_lower":"2010-10-01",
    "date:inception_upper":"2010-10-31",
    "iso:country":"GB",
    "wof:name":"SO22 6FE",
    "wof:placetype":"postalcode"
},
  "geometry": {"coordinates":[-1.350495,51.086771],"type":"Point"}
}