{
  "type": "Feature",
  "properties": {
    "iso:country": "GB",
    "wof:name": "SO22 6FE",
    "wof:placetype": "postalcode"
  },
  "geometry": {"coordinates":[-1.350495,51.086771],"type":"Point"}
}
