{
  "type": "Feature",
  "properties": {
    "iso:country": "GB",
    "wof:name": "NR29 5BT",
    "wof:placetype": "postalcode"
  },
  "geometry": {"coordinates":[1.556108,52.733396],"type":"Point"}
}
