{
  "type": "Feature",
  "properties": {
    "iso:country": "GB",
    "wof:name": "CV22 5QW",
    "wof:placetype": "postalcode"
  },
  "geometry": {"coordinates":[-1.235019,52.355968],"type":"Point"}
}
