{
  "type": "Feature",
  "properties": {
    "iso:country": "GB",
    "wof:name": "LL44 2HD",
    "wof:placetype": "postalcode"
  },
  "geometry": {"coordinates":[-4.115408,52.788478],"type":"Point"}
}
