{
  "type": "Feature",
  "properties": {
    "iso:country": "GB",
    "wof:name": "ST15 0EL",
    "wof:placetype": "postalcode"
  },
  "geometry": {"coordinates":[-2.143812,52.894055],"type":"Point"}
}
