{
  "type": "Feature",
  "properties": {
    "iso:country":"GB",
    "wof:name":"ST15 0EL",
    "wof:placetype":"postalcode"
},
  "geometry": {"coordinates":[-2.14381239825408,52.8940546333914],"type":"Point"}
}