{
  "type": "Feature",
  "properties": {
    "date:inception_lower": "2005-09-01",
    "date:inception_upper": "2005-09-01",
    "iso:country": "GB",
    "wof:name": "AL3 7QN",
    "wof:placetype": "postalcode"
  },
  "geometry": {"coordinates":[-0.419165,51.815032],"type":"Point"}
}
