{
  "type": "Feature",
  "properties": {
    "iso:country":"GB",
    "wof:name":"SG17 5EU",
    "wof:placetype":"postalcode"
},
  "geometry": {"coordinates":[-0.30165499279751,52.04058016617351],"type":"Point"}
}