{
  "type": "Feature",
  "properties": {
    "iso:country":"GB",
    "wof:name":"RG21 4LB",
    "wof:placetype":"postalcode"
},
  "geometry": {"coordinates":[-1.08020430485814,51.26224830948406],"type":"Point"}
}