{
  "type": "Feature",
  "properties": {
    "iso:country":"GB",
    "wof:name":"WF10 4QU",
    "wof:placetype":"postalcode"
},
  "geometry": {"coordinates":[-1.3251961325385,53.71709134394578],"type":"Point"}
}