{
  "type": "Feature",
  "properties": {
    "iso:country": "GB",
    "wof:name": "CA6 4JH",
    "wof:placetype": "postalcode"
  },
  "geometry": {"coordinates":[-2.91875,54.937542],"type":"Point"}
}
