{
  "type": "Feature",
  "properties": {
    "iso:country":"GB",
    "wof:name":"CA6 4JH",
    "wof:placetype":"postalcode"
},
  "geometry": {"coordinates":[-2.91846375147074,54.93744833723827],"type":"Point"}
}