{
  "type": "Feature",
  "properties": {
    "iso:country":"GB",
    "wof:name":"DL2 1PN",
    "wof:placetype":"postalcode"
},
  "geometry": {"coordinates":[-1.46695834663011,54.49324782206453],"type":"Point"}
}