{
  "type": "Feature",
  "properties": {
    "iso:country":"GB",
    "wof:name":"ST11 9JA",
    "wof:placetype":"postalcode"
},
  "geometry": {"coordinates":[-2.08129141481063,52.97168241062745],"type":"Point"}
}