{
  "type": "Feature",
  "properties": {
    "iso:country": "GB",
    "wof:name": "PL26 6LY",
    "wof:placetype": "postalcode"
  },
  "geometry": {"coordinates":[-4.856604,50.239244],"type":"Point"}
}
