{
  "type": "Feature",
  "properties": {
    "date:inception_lower": "1991-09-01",
    "date:inception_upper": "1991-09-01",
    "iso:country": "GB",
    "wof:name": "DA9 9QA",
    "wof:placetype": "postalcode"
  },
  "geometry": {"coordinates":[0.272867,51.450442],"type":"Point"}
}
