{
  "type": "Feature",
  "properties": {
    "iso:country":"GB",
    "wof:name":"DA9 9QA",
    "wof:placetype":"postalcode"
},
  "geometry": {"coordinates":[0.27286689437037,51.45044229615382],"type":"Point"}
}