{
  "type": "Feature",
  "properties": {
    "iso:country":"GB",
    "wof:name":"G13 3NW",
    "wof:placetype":"postalcode"
},
  "geometry": {"coordinates":[-4.34459609948965,55.89454578517812],"type":"Point"}
}