{
  "type": "Feature",
  "properties": {
    "iso:country":"GB",
    "wof:name":"HD5 0QA",
    "wof:placetype":"postalcode"
},
  "geometry": {"coordinates":[-1.73232221801853,53.66677606315762],"type":"Point"}
}