{
  "type": "Feature",
  "properties": {
    "iso:country":"GB",
    "wof:name":"RG12 9QG",
    "wof:placetype":"postalcode"
},
  "geometry": {"coordinates":[-0.73358240913755,51.40590896886745],"type":"Point"}
}