{
  "type": "Feature",
  "properties": {
    "iso:country":"GB",
    "wof:name":"NR30 2DJ",
    "wof:placetype":"postalcode"
},
  "geometry": {"coordinates":[1.73646898055476,52.6094812613637],"type":"Point"}
}