{
  "type": "Feature",
  "properties": {
    "iso:country": "GB",
    "wof:name": "NR30 2DJ",
    "wof:placetype": "postalcode"
  },
  "geometry": {"coordinates":[1.736474,52.609463],"type":"Point"}
}
