{
  "type": "Feature",
  "properties": {
    "date:inception_lower":"1980-01-01",
    "date:inception_upper":"1980-01-31",
    "iso:country":"GB",
    "wof:name":"NR30 2DJ",
    "wof:placetype":"postalcode"
},
  "geometry": {"coordinates":[1.736474,52.609463],"type":"Point"}
}