{
  "type": "Feature",
  "properties": {
    "iso:country": "GB",
    "wof:name": "WR10 3JB",
    "wof:placetype": "postalcode"
  },
  "geometry": {"coordinates":[-2.041251,52.059103],"type":"Point"}
}
