{
  "type": "Feature",
  "properties": {
    "iso:country":"GB",
    "wof:name":"WR10 3JB",
    "wof:placetype":"postalcode"
},
  "geometry": {"coordinates":[-2.04159529019927,52.05919172570702],"type":"Point"}
}