{
  "type": "Feature",
  "properties": {
    "date:inception_lower":"1980-01-01",
    "date:inception_upper":"1980-01-31",
    "iso:country":"GB",
    "wof:name":"WR10 3JB",
    "wof:placetype":"postalcode"
},
  "geometry": {"coordinates":[-2.041251,52.059103],"type":"Point"}
}