{
  "type": "Feature",
  "properties": {
    "iso:country":"GB",
    "wof:name":"LL18 2DU",
    "wof:placetype":"postalcode"
},
  "geometry": {"coordinates":[-3.48823453756293,53.31626511997201],"type":"Point"}
}