{
  "type": "Feature",
  "properties": {
    "iso:country":"GB",
    "wof:name":"S2 3SQ",
    "wof:placetype":"postalcode"
},
  "geometry": {"coordinates":[-1.45400847703156,53.36528269317454],"type":"Point"}
}