{
  "type": "Feature",
  "properties": {
    "date:inception_lower":"2006-04-01",
    "date:inception_upper":"2006-04-30",
    "iso:country":"GB",
    "wof:name":"GL14 3JL",
    "wof:placetype":"postalcode"
},
  "geometry": {"coordinates":[-2.478628,51.827988],"type":"Point"}
}