{
  "type": "Feature",
  "properties": {
    "iso:country": "GB",
    "wof:name": "GL14 3JL",
    "wof:placetype": "postalcode"
  },
  "geometry": {"coordinates":[-2.478628,51.827988],"type":"Point"}
}
