{
  "type": "Feature",
  "properties": {
    "iso:country":"GB",
    "wof:name":"GL14 3JL",
    "wof:placetype":"postalcode"
},
  "geometry": {"coordinates":[-2.47862829726223,51.82798837761771],"type":"Point"}
}