{
  "type": "Feature",
  "properties": {
    "iso:country":"GB",
    "wof:name":"BR3 3RU",
    "wof:placetype":"postalcode"
},
  "geometry": {"coordinates":[-0.04020917010509,51.38980030125079],"type":"Point"}
}