{
  "type": "Feature",
  "properties": {
    "iso:country":"GB",
    "wof:name":"GL12 8AA",
    "wof:placetype":"postalcode"
},
  "geometry": {"coordinates":[-2.43074468557786,51.62261734091253],"type":"Point"}
}