{
  "type": "Feature",
  "properties": {
    "iso:country": "GB",
    "wof:name": "GL12 8AA",
    "wof:placetype": "postalcode"
  },
  "geometry": {"coordinates":[-2.430745,51.622617],"type":"Point"}
}
