{
  "type": "Feature",
  "properties": {
    "iso:country":"GB",
    "wof:name":"PE3 9DY",
    "wof:placetype":"postalcode"
},
  "geometry": {"coordinates":[-0.26206044030458,52.58195981565849],"type":"Point"}
}