{
  "type": "Feature",
  "properties": {
    "iso:country": "GB",
    "wof:name": "S8 7BT",
    "wof:placetype": "postalcode"
  },
  "geometry": {"coordinates":[-1.489507,53.331085],"type":"Point"}
}
