{
  "type": "Feature",
  "properties": {
    "date:inception_lower":"1980-01-01",
    "date:inception_upper":"1980-01-31",
    "iso:country":"GB",
    "wof:name":"RG7 4NN",
    "wof:placetype":"postalcode"
},
  "geometry": {"coordinates":[-1.119793,51.389573],"type":"Point"}
}