{
  "type": "Feature",
  "properties": {
    "iso:country": "GB",
    "wof:name": "RG7 4NN",
    "wof:placetype": "postalcode"
  },
  "geometry": {"coordinates":[-1.119793,51.389573],"type":"Point"}
}
