{
  "type": "Feature",
  "properties": {
    "iso:country": "GB",
    "wof:name": "EX16 8PB",
    "wof:placetype": "postalcode"
  },
  "geometry": {"coordinates":[-3.695348,50.909287],"type":"Point"}
}
