{
  "type": "Feature",
  "properties": {
    "iso:country":"GB",
    "wof:name":"EX16 8PB",
    "wof:placetype":"postalcode"
},
  "geometry": {"coordinates":[-3.695330430113,50.90929334131952],"type":"Point"}
}