{
  "type": "Feature",
  "properties": {
    "date:inception_lower": "1980-01-01",
    "date:inception_upper": "1980-01-01",
    "iso:country": "GB",
    "wof:name": "PL24 2DU",
    "wof:placetype": "postalcode"
  },
  "geometry": {"coordinates":[-4.720297,50.350679],"type":"Point"}
}
