{
  "type": "Feature",
  "properties": {
    "iso:country":"GB",
    "wof:name":"PL24 2DU",
    "wof:placetype":"postalcode"
},
  "geometry": {"coordinates":[-4.72029710676057,50.35067851931034],"type":"Point"}
}