{
  "type": "Feature",
  "properties": {
    "iso:country":"GB",
    "wof:name":"DN11 8LA",
    "wof:placetype":"postalcode"
},
  "geometry": {"coordinates":[-1.07073551381024,53.41025064755588],"type":"Point"}
}