{
  "type": "Feature",
  "properties": {
    "iso:country": "GB",
    "wof:name": "IP1 4NT",
    "wof:placetype": "postalcode"
  },
  "geometry": {"coordinates":[1.151781,52.077771],"type":"Point"}
}
