{
  "type": "Feature",
  "properties": {
    "date:inception_lower":"1980-01-01",
    "date:inception_upper":"1980-01-31",
    "iso:country":"GB",
    "wof:name":"EC1M 4BS",
    "wof:placetype":"postalcode"
},
  "geometry": {"coordinates":[-0.102713,51.52151],"type":"Point"}
}