{
  "type": "Feature",
  "properties": {
    "iso:country": "GB",
    "wof:name": "RH10 3GT",
    "wof:placetype": "postalcode"
  },
  "geometry": {"coordinates":[-0.141293,51.138709],"type":"Point"}
}
