{
  "type": "Feature",
  "properties": {
    "date:inception_lower": "2019-10-01",
    "date:inception_upper": "2019-10-01",
    "iso:country": "GB",
    "wof:name": "RH10 3GT",
    "wof:placetype": "postalcode"
  },
  "geometry": {"coordinates":[-0.141093,51.138715],"type":"Point"}
}
