{
  "type": "Feature",
  "properties": {
    "iso:country": "GB",
    "wof:name": "RH10 3GT",
    "wof:placetype": "postalcode"
  },
  "geometry": {"coordinates":[-0.141093,51.138715],"type":"Point"}
}
