{
  "type": "Feature",
  "properties": {
    "iso:country": "GB",
    "wof:name": "LL30 3HB",
    "wof:placetype": "postalcode"
  },
  "geometry": {"coordinates":[-3.774389,53.314329],"type":"Point"}
}
