{
  "type": "Feature",
  "properties": {
    "iso:country":"GB",
    "wof:name":"CT20 1SJ",
    "wof:placetype":"postalcode"
},
  "geometry": {"coordinates":[1.18304881055558,51.0801782009851],"type":"Point"}
}