{
  "type": "Feature",
  "properties": {
    "date:inception_lower":"1980-01-01",
    "date:inception_upper":"1980-01-31",
    "iso:country":"GB",
    "wof:name":"PE7 2BJ",
    "wof:placetype":"postalcode"
},
  "geometry": {"coordinates":[-0.070454,52.560534],"type":"Point"}
}