{
  "type": "Feature",
  "properties": {
    "iso:country":"GB",
    "wof:name":"PE7 2BJ",
    "wof:placetype":"postalcode"
},
  "geometry": {"coordinates":[-0.07045437182476,52.56053360600981],"type":"Point"}
}