{
  "type": "Feature",
  "properties": {
    "iso:country": "GB",
    "wof:name": "OX27 7JF",
    "wof:placetype": "postalcode"
  },
  "geometry": {"coordinates":[-1.240443,51.979351],"type":"Point"}
}
