{
  "type": "Feature",
  "properties": {
    "iso:country":"GB",
    "wof:name":"OX27 7JF",
    "wof:placetype":"postalcode"
},
  "geometry": {"coordinates":[-1.24044273773624,51.97935099567672],"type":"Point"}
}