{
  "type": "Feature",
  "properties": {
    "iso:country":"GB",
    "wof:name":"DL6 1PS",
    "wof:placetype":"postalcode"
},
  "geometry": {"coordinates":[-1.43211177038485,54.33275809109071],"type":"Point"}
}