{
  "type": "Feature",
  "properties": {
    "iso:country":"GB",
    "wof:name":"YO21 1LD",
    "wof:placetype":"postalcode"
},
  "geometry": {"coordinates":[-0.62770225676903,54.4814860240516],"type":"Point"}
}