{
  "type": "Feature",
  "properties": {
    "iso:country":"GB",
    "wof:name":"SA6 5HB",
    "wof:placetype":"postalcode"
},
  "geometry": {"coordinates":[-3.89628006441959,51.69781402751389],"type":"Point"}
}