{
  "type": "Feature",
  "properties": {
    "date:inception_lower": "1980-01-01",
    "date:inception_upper": "1980-01-01",
    "iso:country": "GB",
    "wof:name": "SA6 5HB",
    "wof:placetype": "postalcode"
  },
  "geometry": {"coordinates":[-3.896234,51.697752],"type":"Point"}
}
