{
  "type": "Feature",
  "properties": {
    "date:inception_lower":"1980-01-01",
    "date:inception_upper":"1980-01-31",
    "iso:country":"GB",
    "wof:name":"EX8 3JX",
    "wof:placetype":"postalcode"
},
  "geometry": {"coordinates":[-3.405065,50.630746],"type":"Point"}
}