{
  "type": "Feature",
  "properties": {
    "date:inception_lower": "1980-01-01",
    "date:inception_upper": "1980-01-01",
    "iso:country": "GB",
    "wof:name": "NE30 3AA",
    "wof:placetype": "postalcode"
  },
  "geometry": {"coordinates":[-1.439606,55.029762],"type":"Point"}
}
