{
  "type": "Feature",
  "properties": {
    "iso:country":"GB",
    "wof:name":"NE30 3AA",
    "wof:placetype":"postalcode"
},
  "geometry": {"coordinates":[-1.43960578910477,55.02976217416597],"type":"Point"}
}