{
  "type": "Feature",
  "properties": {
    "iso:country":"GB",
    "wof:name":"IP3 8UH",
    "wof:placetype":"postalcode"
},
  "geometry": {"coordinates":[1.22314154287279,52.03274939700683],"type":"Point"}
}