{
  "type": "Feature",
  "properties": {
    "iso:country": "GB",
    "wof:name": "IP3 8UH",
    "wof:placetype": "postalcode"
  },
  "geometry": {"coordinates":[1.223142,52.032749],"type":"Point"}
}
