{
  "type": "Feature",
  "properties": {
    "iso:country": "GB",
    "wof:name": "NN3 8QF",
    "wof:placetype": "postalcode"
  },
  "geometry": {"coordinates":[-0.816333,52.265848],"type":"Point"}
}
