{
  "type": "Feature",
  "properties": {
    "date:inception_lower": "1980-01-01",
    "date:inception_upper": "1980-01-01",
    "iso:country": "GB",
    "wof:name": "SG2 7AZ",
    "wof:placetype": "postalcode"
  },
  "geometry": {"coordinates":[-0.076263,51.911705],"type":"Point"}
}
