{
  "type": "Feature",
  "properties": {
    "date:inception_lower":"1999-12-01",
    "date:inception_upper":"1999-12-31",
    "iso:country":"GB",
    "wof:name":"BN3 1WB",
    "wof:placetype":"postalcode"
},
  "geometry": {"coordinates":[-0.160555,50.824164],"type":"Point"}
}