{
  "type": "Feature",
  "properties": {
    "iso:country": "GB",
    "wof:name": "BN3 1WB",
    "wof:placetype": "postalcode"
  },
  "geometry": {"coordinates":[-0.160555,50.824164],"type":"Point"}
}
