{
  "type": "Feature",
  "properties": {
    "iso:country":"GB",
    "wof:name":"B9 4AH",
    "wof:placetype":"postalcode"
},
  "geometry": {"coordinates":[-1.88093793072369,52.47578520541609],"type":"Point"}
}