{
  "type": "Feature",
  "properties": {
    "iso:country": "GB",
    "wof:name": "CB1 9AT",
    "wof:placetype": "postalcode"
  },
  "geometry": {"coordinates":[0.195837,52.211841],"type":"Point"}
}
