{
  "type": "Feature",
  "properties": {
    "date:inception_lower":"2006-09-01",
    "date:inception_upper":"2006-09-30",
    "iso:country":"GB",
    "wof:name":"CB1 9AT",
    "wof:placetype":"postalcode"
},
  "geometry": {"coordinates":[0.195837,52.211841],"type":"Point"}
}