{
  "type": "Feature",
  "properties": {
    "iso:country":"GB",
    "wof:name":"HP6 6PY",
    "wof:placetype":"postalcode"
},
  "geometry": {"coordinates":[-0.57068189269788,51.67210625228122],"type":"Point"}
}