{
  "type": "Feature",
  "properties": {
    "iso:country": "GB",
    "wof:name": "HP6 6PY",
    "wof:placetype": "postalcode"
  },
  "geometry": {"coordinates":[-0.570682,51.672106],"type":"Point"}
}
