{
  "type": "Feature",
  "properties": {
    "iso:country":"GB",
    "wof:name":"TF1 7GZ",
    "wof:placetype":"postalcode"
},
  "geometry": {"coordinates":[-2.45838955524575,52.72428931327541],"type":"Point"}
}