{
  "type": "Feature",
  "properties": {
    "iso:country": "GB",
    "wof:name": "TF1 7GZ",
    "wof:placetype": "postalcode"
  },
  "geometry": {"coordinates":[-2.45839,52.724289],"type":"Point"}
}
