{
  "type": "Feature",
  "properties": {
    "iso:country": "GB",
    "wof:name": "BN12 6FL",
    "wof:placetype": "postalcode"
  },
  "geometry": {"coordinates":[-0.456189,50.819279],"type":"Point"}
}
