{
  "type": "Feature",
  "properties": {
    "iso:country":"GB",
    "wof:name":"IV19 1BB",
    "wof:placetype":"postalcode"
},
  "geometry": {"coordinates":[-4.05228481665159,57.8102725412505],"type":"Point"}
}