{
  "type": "Feature",
  "properties": {
    "date:inception_lower": "1980-01-01",
    "date:inception_upper": "1980-01-01",
    "iso:country": "GB",
    "wof:name": "IV19 1BB",
    "wof:placetype": "postalcode"
  },
  "geometry": {"coordinates":[-4.052285,57.810273],"type":"Point"}
}
