{
  "type": "Feature",
  "properties": {
    "iso:country":"GB",
    "wof:name":"BA14 0EB",
    "wof:placetype":"postalcode"
},
  "geometry": {"coordinates":[-2.22618304545747,51.3073174835141],"type":"Point"}
}