{
  "type": "Feature",
  "properties": {
    "iso:country": "GB",
    "wof:name": "NP19 0NB",
    "wof:placetype": "postalcode"
  },
  "geometry": {"coordinates":[-2.97727,51.582242],"type":"Point"}
}
