{
  "type": "Feature",
  "properties": {
    "date:inception_lower":"2009-04-01",
    "date:inception_upper":"2009-04-30",
    "iso:country":"GB",
    "wof:name":"NP19 0NB",
    "wof:placetype":"postalcode"
},
  "geometry": {"coordinates":[-2.97727,51.582242],"type":"Point"}
}