{
  "type": "Feature",
  "properties": {
    "iso:country":"GB",
    "wof:name":"NP19 0NB",
    "wof:placetype":"postalcode"
},
  "geometry": {"coordinates":[-2.97726331199108,51.58220380287097],"type":"Point"}
}