{
  "type": "Feature",
  "properties": {
    "iso:country": "GB",
    "wof:name": "SW19 8DU",
    "wof:placetype": "postalcode"
  },
  "geometry": {"coordinates":[-0.197553,51.437442],"type":"Point"}
}
