{
  "type": "Feature",
  "properties": {
    "iso:country":"GB",
    "wof:name":"CV35 8XF",
    "wof:placetype":"postalcode"
},
  "geometry": {"coordinates":[-1.66528203304136,52.28489781611385],"type":"Point"}
}