{
  "type": "Feature",
  "properties": {
    "date:inception_lower":"1980-01-01",
    "date:inception_upper":"1980-01-31",
    "iso:country":"GB",
    "wof:name":"G13 3EW",
    "wof:placetype":"postalcode"
},
  "geometry": {"coordinates":[-4.36109,55.88722],"type":"Point"}
}