{
  "type": "Feature",
  "properties": {
    "iso:country":"GB",
    "wof:name":"DY1 3TD",
    "wof:placetype":"postalcode"
},
  "geometry": {"coordinates":[-2.10895061002926,52.52427713993946],"type":"Point"}
}