{
  "type": "Feature",
  "properties": {
    "iso:country": "GB",
    "wof:name": "DY1 3TD",
    "wof:placetype": "postalcode"
  },
  "geometry": {"coordinates":[-2.108951,52.524277],"type":"Point"}
}
