{
  "type": "Feature",
  "properties": {
    "iso:country":"GB",
    "wof:name":"PA14 6XP",
    "wof:placetype":"postalcode"
},
  "geometry": {"coordinates":[-4.58991506110225,55.9259305175122],"type":"Point"}
}