{
  "type": "Feature",
  "properties": {
    "iso:country":"GB",
    "wof:name":"LS17 5JW",
    "wof:placetype":"postalcode"
},
  "geometry": {"coordinates":[-1.56203120987002,53.8487150868144],"type":"Point"}
}