{
  "type": "Feature",
  "properties": {
    "iso:country": "GB",
    "wof:name": "BD18 2BB",
    "wof:placetype": "postalcode"
  },
  "geometry": {"coordinates":[-1.776929,53.826342],"type":"Point"}
}
