{
  "type": "Feature",
  "properties": {
    "iso:country":"GB",
    "wof:name":"BD18 2BB",
    "wof:placetype":"postalcode"
},
  "geometry": {"coordinates":[-1.77692889058026,53.82634238286892],"type":"Point"}
}