{
  "type": "Feature",
  "properties": {
    "date:inception_lower": "2015-04-01",
    "date:inception_upper": "2015-04-01",
    "iso:country": "GB",
    "wof:name": "SN2 2GA",
    "wof:placetype": "postalcode"
  },
  "geometry": {"coordinates":[-1.796353,51.564574],"type":"Point"}
}
