{
  "type": "Feature",
  "properties": {
    "iso:country":"GB",
    "wof:name":"SA3 4TP",
    "wof:placetype":"postalcode"
},
  "geometry": {"coordinates":[-4.0156477328559,51.5778618277317],"type":"Point"}
}