{
  "type": "Feature",
  "properties": {
    "date:inception_lower":"1983-07-01",
    "date:inception_upper":"1983-07-31",
    "iso:country":"GB",
    "wof:name":"SA3 4TP",
    "wof:placetype":"postalcode"
},
  "geometry": {"coordinates":[-4.015648,51.577862],"type":"Point"}
}