{
  "type": "Feature",
  "properties": {
    "iso:country": "GB",
    "wof:name": "SA3 4TP",
    "wof:placetype": "postalcode"
  },
  "geometry": {"coordinates":[-4.015648,51.577862],"type":"Point"}
}
