{
  "type": "Feature",
  "properties": {
    "iso:country":"GB",
    "wof:name":"EN2 0HH",
    "wof:placetype":"postalcode"
},
  "geometry": {"coordinates":[-0.08395489893011,51.66913101788536],"type":"Point"}
}