{
  "type": "Feature",
  "properties": {
    "iso:country":"GB",
    "wof:name":"PO30 4LH",
    "wof:placetype":"postalcode"
},
  "geometry": {"coordinates":[-1.34879105841475,50.71285322659137],"type":"Point"}
}