{
  "type": "Feature",
  "properties": {
    "iso:country":"GB",
    "wof:name":"SW15 2SZ",
    "wof:placetype":"postalcode"
},
  "geometry": {"coordinates":[-0.21075680600568,51.45916352449229],"type":"Point"}
}