{
  "type": "Feature",
  "properties": {
    "date:inception_lower": "1981-09-01",
    "date:inception_upper": "1981-09-01",
    "iso:country": "GB",
    "wof:name": "BD23 1UG",
    "wof:placetype": "postalcode"
  },
  "geometry": {"coordinates":[-2.02964,53.964023],"type":"Point"}
}
