{
  "type": "Feature",
  "properties": {
    "iso:country": "GB",
    "wof:name": "DH9 9TA",
    "wof:placetype": "postalcode"
  },
  "geometry": {"coordinates":[-1.725724,54.886522],"type":"Point"}
}
