{
  "type": "Feature",
  "properties": {
    "date:inception_lower": "1980-01-01",
    "date:inception_upper": "1980-01-01",
    "iso:country": "GB",
    "wof:name": "AL5 4QX",
    "wof:placetype": "postalcode"
  },
  "geometry": {"coordinates":[-0.342773,51.82264],"type":"Point"}
}
