{
  "type": "Feature",
  "properties": {
    "iso:country":"GB",
    "wof:name":"AL5 4QX",
    "wof:placetype":"postalcode"
},
  "geometry": {"coordinates":[-0.34277267367082,51.82264046417685],"type":"Point"}
}