{
  "type": "Feature",
  "properties": {
    "iso:country":"GB",
    "wof:name":"PO9 2RW",
    "wof:placetype":"postalcode"
},
  "geometry": {"coordinates":[-0.97381144878287,50.85120959032213],"type":"Point"}
}