{
  "type": "Feature",
  "properties": {
    "iso:country": "GB",
    "wof:name": "PO9 2RW",
    "wof:placetype": "postalcode"
  },
  "geometry": {"coordinates":[-0.973811,50.85121],"type":"Point"}
}
