{
  "type": "Feature",
  "properties": {
    "iso:country":"GB",
    "wof:name":"PA5 8PN",
    "wof:placetype":"postalcode"
},
  "geometry": {"coordinates":[-4.52957891323856,55.82838784626637],"type":"Point"}
}