{
  "type": "Feature",
  "properties": {
    "iso:country":"GB",
    "wof:name":"LS10 4DF",
    "wof:placetype":"postalcode"
},
  "geometry": {"coordinates":[-1.53918903976506,53.74582435169773],"type":"Point"}
}