{
  "type": "Feature",
  "properties": {
    "date:inception_lower": "2003-11-01",
    "date:inception_upper": "2003-11-01",
    "iso:country": "GB",
    "wof:name": "LE5 1DU",
    "wof:placetype": "postalcode"
  },
  "geometry": {"coordinates":[-1.076791,52.646465],"type":"Point"}
}
