{
  "type": "Feature",
  "properties": {
    "date:inception_lower": "2023-11-01",
    "date:inception_upper": "2023-11-01",
    "iso:country": "GB",
    "wof:name": "B49 5FR",
    "wof:placetype": "postalcode"
  },
  "geometry": {"coordinates":[-1.880726,52.218014],"type":"Point"}
}
