{
  "type": "Feature",
  "properties": {
    "iso:country":"GB",
    "wof:name":"UB8 2TQ",
    "wof:placetype":"postalcode"
},
  "geometry": {"coordinates":[-0.48409414954248,51.54521345171211],"type":"Point"}
}