{
  "type": "Feature",
  "properties": {
    "date:inception_lower":"1980-01-01",
    "date:inception_upper":"1980-01-31",
    "iso:country":"GB",
    "wof:name":"UB8 2TQ",
    "wof:placetype":"postalcode"
},
  "geometry": {"coordinates":[-0.484094,51.545213],"type":"Point"}
}