{
  "type": "Feature",
  "properties": {
    "iso:country":"GB",
    "wof:name":"BS31 2NH",
    "wof:placetype":"postalcode"
},
  "geometry": {"coordinates":[-2.50624715161896,51.40936079414132],"type":"Point"}
}