{
  "type": "Feature",
  "properties": {
    "iso:country": "GB",
    "wof:name": "BL9 0AS",
    "wof:placetype": "postalcode"
  },
  "geometry": {"coordinates":[-2.296701,53.593118],"type":"Point"}
}
