{
  "type": "Feature",
  "properties": {
    "date:inception_lower": "2017-08-01",
    "date:inception_upper": "2017-08-01",
    "iso:country": "GB",
    "wof:name": "BL9 0AS",
    "wof:placetype": "postalcode"
  },
  "geometry": {"coordinates":[-2.296701,53.593118],"type":"Point"}
}
