{
  "type": "Feature",
  "properties": {
    "iso:country":"GB",
    "wof:name":"BL9 0AS",
    "wof:placetype":"postalcode"
},
  "geometry": {"coordinates":[-2.29670319806458,53.59310169634954],"type":"Point"}
}