{
  "type": "Feature",
  "properties": {
    "iso:country":"GB",
    "wof:name":"TN17 1BJ",
    "wof:placetype":"postalcode"
},
  "geometry": {"coordinates":[0.46106396495438,51.11472353863695],"type":"Point"}
}