{
  "type": "Feature",
  "properties": {
    "iso:country":"GB",
    "wof:name":"BH14 9AH",
    "wof:placetype":"postalcode"
},
  "geometry": {"coordinates":[-1.92620578542636,50.72617577173277],"type":"Point"}
}