{
  "type": "Feature",
  "properties": {
    "iso:country": "GB",
    "wof:name": "CM19 5GH",
    "wof:placetype": "postalcode"
  },
  "geometry": {"coordinates":[0.066244,51.769194],"type":"Point"}
}
