{
  "type": "Feature",
  "properties": {
    "iso:country":"GB",
    "wof:name":"HU3 6TB",
    "wof:placetype":"postalcode"
},
  "geometry": {"coordinates":[-0.38189515335904,53.74565000118773],"type":"Point"}
}