{
  "type": "Feature",
  "properties": {
    "date:inception_lower": "1980-01-01",
    "date:inception_upper": "1980-01-01",
    "iso:country": "GB",
    "wof:name": "LA2 0HE",
    "wof:placetype": "postalcode"
  },
  "geometry": {"coordinates":[-2.786582,53.961522],"type":"Point"}
}
