{
  "type": "Feature",
  "properties": {
    "iso:country":"GB",
    "wof:name":"LA2 0HE",
    "wof:placetype":"postalcode"
},
  "geometry": {"coordinates":[-2.78658160131417,53.96152232750092],"type":"Point"}
}