{
  "type": "Feature",
  "properties": {
    "iso:country":"GB",
    "wof:name":"PH2 6JT",
    "wof:placetype":"postalcode"
},
  "geometry": {"coordinates":[-3.40420240272383,56.41976063899109],"type":"Point"}
}