{
  "type": "Feature",
  "properties": {
    "date:inception_lower": "1980-01-01",
    "date:inception_upper": "1980-01-01",
    "iso:country": "GB",
    "wof:name": "PH2 6JT",
    "wof:placetype": "postalcode"
  },
  "geometry": {"coordinates":[-3.404202,56.419761],"type":"Point"}
}
