{
  "type": "Feature",
  "properties": {
    "iso:country":"GB",
    "wof:name":"NE48 2SQ",
    "wof:placetype":"postalcode"
},
  "geometry": {"coordinates":[-2.16561094311537,55.17463331094082],"type":"Point"}
}