{
  "type": "Feature",
  "properties": {
    "iso:country": "GB",
    "wof:name": "BB11 5EH",
    "wof:placetype": "postalcode"
  },
  "geometry": {"coordinates":[-2.270937,53.785356],"type":"Point"}
}
