{
  "type": "Feature",
  "properties": {
    "date:inception_lower": "2020-09-01",
    "date:inception_upper": "2020-09-01",
    "iso:country": "GB",
    "wof:name": "BS2 2EY",
    "wof:placetype": "postalcode"
  },
  "geometry": {"coordinates":[-2.575336,51.458764],"type":"Point"}
}
