{
  "type": "Feature",
  "properties": {
    "date:inception_lower": "1990-07-01",
    "date:inception_upper": "1990-07-01",
    "iso:country": "GB",
    "wof:name": "DE1 1QB",
    "wof:placetype": "postalcode"
  },
  "geometry": {"coordinates":[-1.482093,52.91503],"type":"Point"}
}
