{
  "type": "Feature",
  "properties": {
    "iso:country":"GB",
    "wof:name":"DE1 1QB",
    "wof:placetype":"postalcode"
},
  "geometry": {"coordinates":[-1.48221639136986,52.91494886194766],"type":"Point"}
}