{
  "type": "Feature",
  "properties": {
    "iso:country":"GB",
    "wof:name":"BS20 0PA",
    "wof:placetype":"postalcode"
},
  "geometry": {"coordinates":[-2.69778622956943,51.47809820514094],"type":"Point"}
}