{
  "type": "Feature",
  "properties": {
    "date:inception_lower": "2002-10-01",
    "date:inception_upper": "2002-10-01",
    "iso:country": "GB",
    "wof:name": "NE12 8LZ",
    "wof:placetype": "postalcode"
  },
  "geometry": {"coordinates":[-1.58751,55.013953],"type":"Point"}
}
