{
  "type": "Feature",
  "properties": {
    "iso:country":"GB",
    "wof:name":"NP10 8QE",
    "wof:placetype":"postalcode"
},
  "geometry": {"coordinates":[-3.01682327888069,51.55505446347159],"type":"Point"}
}