{
  "type": "Feature",
  "properties": {
    "iso:country":"GB",
    "wof:name":"HG4 2RH",
    "wof:placetype":"postalcode"
},
  "geometry": {"coordinates":[-1.54981795702735,54.14086146865957],"type":"Point"}
}