{
  "type": "Feature",
  "properties": {
    "iso:country":"GB",
    "wof:name":"NG31 6LL",
    "wof:placetype":"postalcode"
},
  "geometry": {"coordinates":[-0.6541434345298,52.90964239202037],"type":"Point"}
}