{
  "type": "Feature",
  "properties": {
    "date:inception_lower":"1990-02-01",
    "date:inception_upper":"1990-02-28",
    "iso:country":"GB",
    "wof:name":"SP10 3UP",
    "wof:placetype":"postalcode"
},
  "geometry": {"coordinates":[-1.500363,51.205043],"type":"Point"}
}