{
  "type": "Feature",
  "properties": {
    "iso:country":"GB",
    "wof:name":"SP10 3UP",
    "wof:placetype":"postalcode"
},
  "geometry": {"coordinates":[-1.50036322256482,51.20504297681789],"type":"Point"}
}