{
  "type": "Feature",
  "properties": {
    "iso:country": "GB",
    "wof:name": "SP10 3UP",
    "wof:placetype": "postalcode"
  },
  "geometry": {"coordinates":[-1.500363,51.205043],"type":"Point"}
}
