{
  "type": "Feature",
  "properties": {
    "date:inception_lower": "1980-01-01",
    "date:inception_upper": "1980-01-01",
    "iso:country": "GB",
    "wof:name": "DL12 8QW",
    "wof:placetype": "postalcode"
  },
  "geometry": {"coordinates":[-1.923217,54.562886],"type":"Point"}
}
