{
  "type": "Feature",
  "properties": {
    "iso:country":"GB",
    "wof:name":"DL12 8QW",
    "wof:placetype":"postalcode"
},
  "geometry": {"coordinates":[-1.92321662536762,54.56288629996012],"type":"Point"}
}