{
  "type": "Feature",
  "properties": {
    "iso:country":"GB",
    "wof:name":"GU22 8UH",
    "wof:placetype":"postalcode"
},
  "geometry": {"coordinates":[-0.50520722032273,51.32834869927719],"type":"Point"}
}