{
  "type": "Feature",
  "properties": {
    "iso:country": "GB",
    "wof:name": "PO9 3RE",
    "wof:placetype": "postalcode"
  },
  "geometry": {"coordinates":[-1.012251,50.859347],"type":"Point"}
}
