{
  "type": "Feature",
  "properties": {
    "iso:country":"GB",
    "wof:name":"PO9 3RE",
    "wof:placetype":"postalcode"
},
  "geometry": {"coordinates":[-1.01225104951146,50.8593468776718],"type":"Point"}
}