{
  "type": "Feature",
  "properties": {
    "date:inception_lower": "1980-01-01",
    "date:inception_upper": "1980-01-01",
    "iso:country": "GB",
    "wof:name": "PO9 3RE",
    "wof:placetype": "postalcode"
  },
  "geometry": {"coordinates":[-1.012251,50.859347],"type":"Point"}
}
