{
  "type": "Feature",
  "properties": {
    "iso:country":"GB",
    "wof:name":"DY7 6EU",
    "wof:placetype":"postalcode"
},
  "geometry": {"coordinates":[-2.23022974813286,52.44961224613095],"type":"Point"}
}