{
  "type": "Feature",
  "properties": {
    "iso:country":"GB",
    "wof:name":"SA3 5RF",
    "wof:placetype":"postalcode"
},
  "geometry": {"coordinates":[-4.01738361696074,51.58186067638999],"type":"Point"}
}