{
  "type": "Feature",
  "properties": {
    "iso:country": "GB",
    "wof:name": "DN17 4AF",
    "wof:placetype": "postalcode"
  },
  "geometry": {"coordinates":[-0.710991,53.659915],"type":"Point"}
}
