{
  "type": "Feature",
  "properties": {
    "iso:country":"GB",
    "wof:name":"DN17 4AF",
    "wof:placetype":"postalcode"
},
  "geometry": {"coordinates":[-0.71099140588728,53.65991494681073],"type":"Point"}
}