{
  "type": "Feature",
  "properties": {
    "iso:country":"GB",
    "wof:name":"DH2 2UH",
    "wof:placetype":"postalcode"
},
  "geometry": {"coordinates":[-1.59830674454054,54.85501211600623],"type":"Point"}
}