{
  "type": "Feature",
  "properties": {
    "date:inception_lower": "1994-12-01",
    "date:inception_upper": "1994-12-01",
    "iso:country": "GB",
    "wof:name": "DH2 2UH",
    "wof:placetype": "postalcode"
  },
  "geometry": {"coordinates":[-1.598307,54.855012],"type":"Point"}
}
