{
  "type": "Feature",
  "properties": {
    "iso:country": "GB",
    "wof:name": "IP19 0DD",
    "wof:placetype": "postalcode"
  },
  "geometry": {"coordinates":[1.389098,52.306867],"type":"Point"}
}
