{
  "type": "Feature",
  "properties": {
    "date:inception_lower": "1980-01-01",
    "date:inception_upper": "1980-01-01",
    "iso:country": "GB",
    "wof:name": "CM9 6LH",
    "wof:placetype": "postalcode"
  },
  "geometry": {"coordinates":[0.652324,51.73195],"type":"Point"}
}
