{
  "type": "Feature",
  "properties": {
    "iso:country":"GB",
    "wof:name":"CM9 6LH",
    "wof:placetype":"postalcode"
},
  "geometry": {"coordinates":[0.65229551993767,51.73194350550384],"type":"Point"}
}