{
  "type": "Feature",
  "properties": {
    "date:inception_lower":"1980-01-01",
    "date:inception_upper":"1980-01-31",
    "iso:country":"GB",
    "wof:name":"EX38 7JR",
    "wof:placetype":"postalcode"
},
  "geometry": {"coordinates":[-4.04477,50.952505],"type":"Point"}
}