{
  "type": "Feature",
  "properties": {
    "iso:country":"GB",
    "wof:name":"EX38 7JR",
    "wof:placetype":"postalcode"
},
  "geometry": {"coordinates":[-4.04474675428104,50.95251104074809],"type":"Point"}
}