{
  "type": "Feature",
  "properties": {
    "iso:country":"GB",
    "wof:name":"DN15 6SS",
    "wof:placetype":"postalcode"
},
  "geometry": {"coordinates":[-0.64504310526913,53.59279448516814],"type":"Point"}
}