{
  "type": "Feature",
  "properties": {
    "iso:country":"GB",
    "wof:name":"SK4 4BD",
    "wof:placetype":"postalcode"
},
  "geometry": {"coordinates":[-2.18800123705739,53.42344119769708],"type":"Point"}
}