{
  "type": "Feature",
  "properties": {
    "iso:country":"GB",
    "wof:name":"IP25 7DU",
    "wof:placetype":"postalcode"
},
  "geometry": {"coordinates":[0.77274880184638,52.63126985693528],"type":"Point"}
}