{
  "type": "Feature",
  "properties": {
    "date:inception_lower": "2008-03-01",
    "date:inception_upper": "2008-03-01",
    "iso:country": "GB",
    "wof:name": "RG14 7FN",
    "wof:placetype": "postalcode"
  },
  "geometry": {"coordinates":[-1.327171,51.385039],"type":"Point"}
}
