{
  "type": "Feature",
  "properties": {
    "iso:country":"GB",
    "wof:name":"RG14 7FN",
    "wof:placetype":"postalcode"
},
  "geometry": {"coordinates":[-1.32717141292092,51.38503911887868],"type":"Point"}
}