{
  "type": "Feature",
  "properties": {
    "iso:country":"GB",
    "wof:name":"S60 4DS",
    "wof:placetype":"postalcode"
},
  "geometry": {"coordinates":[-1.32770139403461,53.40816195745922],"type":"Point"}
}