{
  "type": "Feature",
  "properties": {
    "date:inception_lower": "1980-01-01",
    "date:inception_upper": "1980-01-01",
    "iso:country": "GB",
    "wof:name": "LE12 8DN",
    "wof:placetype": "postalcode"
  },
  "geometry": {"coordinates":[-1.170676,52.747252],"type":"Point"}
}
