{
  "type": "Feature",
  "properties": {
    "iso:country":"GB",
    "wof:name":"TN26 3PR",
    "wof:placetype":"postalcode"
},
  "geometry": {"coordinates":[0.80108921543603,51.10526062823265],"type":"Point"}
}