{
  "type": "Feature",
  "properties": {
    "date:inception_lower":"1980-01-01",
    "date:inception_upper":"1980-01-31",
    "iso:country":"GB",
    "wof:name":"TN26 3PR",
    "wof:placetype":"postalcode"
},
  "geometry": {"coordinates":[0.801089,51.105261],"type":"Point"}
}