{
  "type": "Feature",
  "properties": {
    "iso:country": "GB",
    "wof:name": "LA9 4RA",
    "wof:placetype": "postalcode"
  },
  "geometry": {"coordinates":[-2.746744,54.329912],"type":"Point"}
}
