{
  "type": "Feature",
  "properties": {
    "iso:country": "GB",
    "wof:name": "HP5 2RY",
    "wof:placetype": "postalcode"
  },
  "geometry": {"coordinates":[-0.63659,51.718613],"type":"Point"}
}
