{
  "type": "Feature",
  "properties": {
    "iso:country":"GB",
    "wof:name":"HP5 2RY",
    "wof:placetype":"postalcode"
},
  "geometry": {"coordinates":[-0.63658981203377,51.71861276189722],"type":"Point"}
}