{
  "type": "Feature",
  "properties": {
    "iso:country":"GB",
    "wof:name":"LS13 4QR",
    "wof:placetype":"postalcode"
},
  "geometry": {"coordinates":[-1.64678907954743,53.79794265091145],"type":"Point"}
}