{
  "type": "Feature",
  "properties": {
    "date:inception_lower":"1990-02-01",
    "date:inception_upper":"1990-02-28",
    "iso:country":"GB",
    "wof:name":"LS13 4QR",
    "wof:placetype":"postalcode"
},
  "geometry": {"coordinates":[-1.646789,53.797943],"type":"Point"}
}