{
  "type": "Feature",
  "properties": {
    "iso:country":"GB",
    "wof:name":"RG28 7EG",
    "wof:placetype":"postalcode"
},
  "geometry": {"coordinates":[-1.33568397462346,51.23458143207264],"type":"Point"}
}