{
  "type": "Feature",
  "properties": {
    "iso:country": "GB",
    "wof:name": "RG28 7EG",
    "wof:placetype": "postalcode"
  },
  "geometry": {"coordinates":[-1.335684,51.234581],"type":"Point"}
}
