{
  "type": "Feature",
  "properties": {
    "iso:country":"GB",
    "wof:name":"ST9 9NG",
    "wof:placetype":"postalcode"
},
  "geometry": {"coordinates":[-2.12900024153026,53.06118997920255],"type":"Point"}
}