{
  "type": "Feature",
  "properties": {
    "iso:country":"GB",
    "wof:name":"L17 4JE",
    "wof:placetype":"postalcode"
},
  "geometry": {"coordinates":[-2.93923781802074,53.37551623506097],"type":"Point"}
}