{
  "type": "Feature",
  "properties": {
    "iso:country": "GB",
    "wof:name": "L17 4JE",
    "wof:placetype": "postalcode"
  },
  "geometry": {"coordinates":[-2.939238,53.375516],"type":"Point"}
}
