{
  "type": "Feature",
  "properties": {
    "iso:country":"GB",
    "wof:name":"CR2 7DB",
    "wof:placetype":"postalcode"
},
  "geometry": {"coordinates":[-0.09308411569744,51.35844275415007],"type":"Point"}
}