{
  "type": "Feature",
  "properties": {
    "iso:country":"GB",
    "wof:name":"TS24 9PW",
    "wof:placetype":"postalcode"
},
  "geometry": {"coordinates":[-1.23555693331142,54.71188286095735],"type":"Point"}
}