{
  "type": "Feature",
  "properties": {
    "iso:country": "GB",
    "wof:name": "KT23 4EQ",
    "wof:placetype": "postalcode"
  },
  "geometry": {"coordinates":[-0.371574,51.280192],"type":"Point"}
}
