{
  "type": "Feature",
  "properties": {
    "iso:country": "GB",
    "wof:name": "EX32 8AU",
    "wof:placetype": "postalcode"
  },
  "geometry": {"coordinates":[-4.040743,51.081463],"type":"Point"}
}
