{
  "type": "Feature",
  "properties": {
    "iso:country":"GB",
    "wof:name":"CF44 9TT",
    "wof:placetype":"postalcode"
},
  "geometry": {"coordinates":[-3.5101821672459,51.74213236943157],"type":"Point"}
}