{
  "type": "Feature",
  "properties": {
    "iso:country": "GB",
    "wof:name": "HP23 5QL",
    "wof:placetype": "postalcode"
  },
  "geometry": {"coordinates":[-0.624511,51.800809],"type":"Point"}
}
