{
  "type": "Feature",
  "properties": {
    "iso:country":"GB",
    "wof:name":"B66 4HA",
    "wof:placetype":"postalcode"
},
  "geometry": {"coordinates":[-1.97021472329249,52.47822350546606],"type":"Point"}
}