{
  "type": "Feature",
  "properties": {
    "iso:country": "GB",
    "wof:name": "B77 2DG",
    "wof:placetype": "postalcode"
  },
  "geometry": {"coordinates":[-1.655818,52.622312],"type":"Point"}
}
