{
  "type": "Feature",
  "properties": {
    "iso:country":"GB",
    "wof:name":"B77 2DG",
    "wof:placetype":"postalcode"
},
  "geometry": {"coordinates":[-1.6558176127848,52.62231177708625],"type":"Point"}
}