{
  "type": "Feature",
  "properties": {
    "iso:country":"GB",
    "wof:name":"ME9 8GA",
    "wof:placetype":"postalcode"
},
  "geometry": {"coordinates":[0.72529111685364,51.31338648252195],"type":"Point"}
}