{
  "type": "Feature",
  "properties": {
    "date:inception_lower": "1999-06-01",
    "date:inception_upper": "1999-06-01",
    "iso:country": "GB",
    "wof:name": "ME9 8GA",
    "wof:placetype": "postalcode"
  },
  "geometry": {"coordinates":[0.725291,51.313386],"type":"Point"}
}
