{
  "type": "Feature",
  "properties": {
    "date:inception_lower": "1999-06-01",
    "date:inception_upper": "1999-06-01",
    "iso:country": "GB",
    "wof:name": "DL7 9UH",
    "wof:placetype": "postalcode"
  },
  "geometry": {"coordinates":[-1.565141,54.306621],"type":"Point"}
}
