{
  "type": "Feature",
  "properties": {
    "iso:country":"GB",
    "wof:name":"DL7 9UH",
    "wof:placetype":"postalcode"
},
  "geometry": {"coordinates":[-1.56527179943249,54.30653795368682],"type":"Point"}
}