{
  "type": "Feature",
  "properties": {
    "iso:country": "GB",
    "wof:name": "DL7 9UH",
    "wof:placetype": "postalcode"
  },
  "geometry": {"coordinates":[-1.565141,54.306621],"type":"Point"}
}
