{
  "type": "Feature",
  "properties": {
    "iso:country":"GB",
    "wof:name":"SA1 5AJ",
    "wof:placetype":"postalcode"
},
  "geometry": {"coordinates":[-3.94345570226572,51.62385358347954],"type":"Point"}
}