{
  "type": "Feature",
  "properties": {
    "date:inception_lower": "2007-09-01",
    "date:inception_upper": "2007-09-01",
    "iso:country": "GB",
    "wof:name": "SA1 5AJ",
    "wof:placetype": "postalcode"
  },
  "geometry": {"coordinates":[-3.943456,51.623854],"type":"Point"}
}
