{
  "type": "Feature",
  "properties": {
    "iso:country": "GB",
    "wof:name": "TD9 0RN",
    "wof:placetype": "postalcode"
  },
  "geometry": {"coordinates":[-2.811189,55.178301],"type":"Point"}
}
