{
  "type": "Feature",
  "properties": {
    "iso:country":"GB",
    "wof:name":"WS3 3BD",
    "wof:placetype":"postalcode"
},
  "geometry": {"coordinates":[-1.99190666742036,52.62021265189195],"type":"Point"}
}