{
  "type": "Feature",
  "properties": {
    "date:inception_lower": "1980-01-01",
    "date:inception_upper": "1980-01-01",
    "iso:country": "GB",
    "wof:name": "OX12 9EN",
    "wof:placetype": "postalcode"
  },
  "geometry": {"coordinates":[-1.424656,51.594738],"type":"Point"}
}
