{
  "type": "Feature",
  "properties": {
    "iso:country":"GB",
    "wof:name":"OX12 9EN",
    "wof:placetype":"postalcode"
},
  "geometry": {"coordinates":[-1.42465650105599,51.59473818347507],"type":"Point"}
}