{
  "type": "Feature",
  "properties": {
    "iso:country": "GB",
    "wof:name": "CB5 8RG",
    "wof:placetype": "postalcode"
  },
  "geometry": {"coordinates":[0.163366,52.211164],"type":"Point"}
}
