{
  "type": "Feature",
  "properties": {
    "iso:country":"GB",
    "wof:name":"CB5 8RG",
    "wof:placetype":"postalcode"
},
  "geometry": {"coordinates":[0.16336609092467,52.21116359405503],"type":"Point"}
}