{
  "type": "Feature",
  "properties": {
    "iso:country":"GB",
    "wof:name":"TQ2 8BU",
    "wof:placetype":"postalcode"
},
  "geometry": {"coordinates":[-3.53175341562751,50.49174602381844],"type":"Point"}
}