{
  "type": "Feature",
  "properties": {
    "date:inception_lower": "1980-01-01",
    "date:inception_upper": "1980-01-01",
    "iso:country": "GB",
    "wof:name": "RM6 4ED",
    "wof:placetype": "postalcode"
  },
  "geometry": {"coordinates":[0.125818,51.568768],"type":"Point"}
}
