{
  "type": "Feature",
  "properties": {
    "iso:country":"GB",
    "wof:name":"RM6 4ED",
    "wof:placetype":"postalcode"
},
  "geometry": {"coordinates":[0.12581790754205,51.56876846903691],"type":"Point"}
}