{
  "type": "Feature",
  "properties": {
    "iso:country":"GB",
    "wof:name":"SO21 1TJ",
    "wof:placetype":"postalcode"
},
  "geometry": {"coordinates":[-1.30926507534971,50.99058707088356],"type":"Point"}
}