{
  "type": "Feature",
  "properties": {
    "iso:country":"GB",
    "wof:name":"S63 7PX",
    "wof:placetype":"postalcode"
},
  "geometry": {"coordinates":[-1.34200253309442,53.50299986922916],"type":"Point"}
}