{
  "type": "Feature",
  "properties": {
    "iso:country":"GB",
    "wof:name":"SE2 0XJ",
    "wof:placetype":"postalcode"
},
  "geometry": {"coordinates":[0.10259527817892,51.48512237983489],"type":"Point"}
}