{
  "type": "Feature",
  "properties": {
    "iso:country":"GB",
    "wof:name":"M27 5XA",
    "wof:placetype":"postalcode"
},
  "geometry": {"coordinates":[-2.33152388903222,53.50769257525774],"type":"Point"}
}