{
  "type": "Feature",
  "properties": {
    "iso:country": "GB",
    "wof:name": "RG42 5RT",
    "wof:placetype": "postalcode"
  },
  "geometry": {"coordinates":[-0.750694,51.435883],"type":"Point"}
}
