{
  "type": "Feature",
  "properties": {
    "iso:country":"GB",
    "wof:name":"RG42 5RT",
    "wof:placetype":"postalcode"
},
  "geometry": {"coordinates":[-0.75069407248229,51.43588328519539],"type":"Point"}
}