{
  "type": "Feature",
  "properties": {
    "iso:country": "GB",
    "wof:name": "G77 6TJ",
    "wof:placetype": "postalcode"
  },
  "geometry": {"coordinates":[-4.339778,55.774607],"type":"Point"}
}
