{
  "type": "Feature",
  "properties": {
    "iso:country":"GB",
    "wof:name":"G77 6TJ",
    "wof:placetype":"postalcode"
},
  "geometry": {"coordinates":[-4.339778260142,55.7746069346351],"type":"Point"}
}