{
  "type": "Feature",
  "properties": {
    "date:inception_lower":"1980-01-01",
    "date:inception_upper":"1980-01-31",
    "iso:country":"GB",
    "wof:name":"B32 1DN",
    "wof:placetype":"postalcode"
},
  "geometry": {"coordinates":[-2.006941,52.461682],"type":"Point"}
}