{
  "type": "Feature",
  "properties": {
    "iso:country": "GB",
    "wof:name": "B32 1DN",
    "wof:placetype": "postalcode"
  },
  "geometry": {"coordinates":[-2.006941,52.461682],"type":"Point"}
}
