{
  "type": "Feature",
  "properties": {
    "date:inception_lower":"1980-01-01",
    "date:inception_upper":"1980-01-31",
    "iso:country":"GB",
    "wof:name":"GL1 1NN",
    "wof:placetype":"postalcode"
},
  "geometry": {"coordinates":[-2.243593,51.864369],"type":"Point"}
}