{
  "type": "Feature",
  "properties": {
    "iso:country": "GB",
    "wof:name": "GL1 1NN",
    "wof:placetype": "postalcode"
  },
  "geometry": {"coordinates":[-2.243593,51.864369],"type":"Point"}
}
