{
  "type": "Feature",
  "properties": {
    "iso:country":"GB",
    "wof:name":"GL1 1NN",
    "wof:placetype":"postalcode"
},
  "geometry": {"coordinates":[-2.24359316406632,51.86436859124031],"type":"Point"}
}