{
  "type": "Feature",
  "properties": {
    "iso:country":"GB",
    "wof:name":"TF3 1YZ",
    "wof:placetype":"postalcode"
},
  "geometry": {"coordinates":[-2.43060381684362,52.66025200556275],"type":"Point"}
}