{
  "type": "Feature",
  "properties": {
    "date:inception_lower":"1980-01-01",
    "date:inception_upper":"1980-01-31",
    "iso:country":"GB",
    "wof:name":"LL53 8TD",
    "wof:placetype":"postalcode"
},
  "geometry": {"coordinates":[-4.578553,52.867765],"type":"Point"}
}