{
  "type": "Feature",
  "properties": {
    "iso:country": "GB",
    "wof:name": "LL53 8TD",
    "wof:placetype": "postalcode"
  },
  "geometry": {"coordinates":[-4.578553,52.867765],"type":"Point"}
}
