{
  "type": "Feature",
  "properties": {
    "iso:country":"GB",
    "wof:name":"LL53 8TD",
    "wof:placetype":"postalcode"
},
  "geometry": {"coordinates":[-4.57855336436728,52.8677651129926],"type":"Point"}
}