{
  "type": "Feature",
  "properties": {
    "date:inception_lower": "1980-01-01",
    "date:inception_upper": "1980-01-01",
    "iso:country": "GB",
    "wof:name": "PH8 0AH",
    "wof:placetype": "postalcode"
  },
  "geometry": {"coordinates":[-3.585611,56.565372],"type":"Point"}
}
