{
  "type": "Feature",
  "properties": {
    "date:inception_lower":"2014-09-01",
    "date:inception_upper":"2014-09-30",
    "iso:country":"GB",
    "wof:name":"LE8 6PD",
    "wof:placetype":"postalcode"
},
  "geometry": {"coordinates":[-1.172653,52.55809],"type":"Point"}
}