{
  "type": "Feature",
  "properties": {
    "iso:country": "GB",
    "wof:name": "LE8 6PD",
    "wof:placetype": "postalcode"
  },
  "geometry": {"coordinates":[-1.172653,52.55809],"type":"Point"}
}
