{
  "type": "Feature",
  "properties": {
    "date:inception_lower": "2021-07-01",
    "date:inception_upper": "2021-07-01",
    "iso:country": "GB",
    "wof:name": "DL6 2FS",
    "wof:placetype": "postalcode"
  },
  "geometry": {"coordinates":[-1.439836,54.35238],"type":"Point"}
}
