{
  "type": "Feature",
  "properties": {
    "iso:country":"GB",
    "wof:name":"HD3 3TA",
    "wof:placetype":"postalcode"
},
  "geometry": {"coordinates":[-1.84424439324092,53.65807539079152],"type":"Point"}
}