{
  "type": "Feature",
  "properties": {
    "iso:country": "GB",
    "wof:name": "HD3 3TA",
    "wof:placetype": "postalcode"
  },
  "geometry": {"coordinates":[-1.844244,53.658075],"type":"Point"}
}
