{
  "type": "Feature",
  "properties": {
    "iso:country": "GB",
    "wof:name": "TA7 0JQ",
    "wof:placetype": "postalcode"
  },
  "geometry": {"coordinates":[-2.904248,51.072225],"type":"Point"}
}
