{
  "type": "Feature",
  "properties": {
    "iso:country":"GB",
    "wof:name":"PR1 9DF",
    "wof:placetype":"postalcode"
},
  "geometry": {"coordinates":[-2.71982556131481,53.73313101036783],"type":"Point"}
}