{
  "type": "Feature",
  "properties": {
    "iso:country": "GB",
    "wof:name": "RG42 5QS",
    "wof:placetype": "postalcode"
  },
  "geometry": {"coordinates":[-0.765856,51.466304],"type":"Point"}
}
