{
  "type": "Feature",
  "properties": {
    "iso:country":"GB",
    "wof:name":"RG42 5QS",
    "wof:placetype":"postalcode"
},
  "geometry": {"coordinates":[-0.76776318275307,51.46451461724487],"type":"Point"}
}