{
  "type": "Feature",
  "properties": {
    "date:inception_lower": "2019-02-01",
    "date:inception_upper": "2019-02-01",
    "iso:country": "GB",
    "wof:name": "GL15 5FT",
    "wof:placetype": "postalcode"
  },
  "geometry": {"coordinates":[-2.51649,51.73054],"type":"Point"}
}
