{
  "type": "Feature",
  "properties": {
    "iso:country":"GB",
    "wof:name":"IP4 3LG",
    "wof:placetype":"postalcode"
},
  "geometry": {"coordinates":[1.19443705338,52.06515478991259],"type":"Point"}
}