{
  "type": "Feature",
  "properties": {
    "iso:country": "GB",
    "wof:name": "IP4 3LG",
    "wof:placetype": "postalcode"
  },
  "geometry": {"coordinates":[1.194588,52.065013],"type":"Point"}
}
