{
  "type": "Feature",
  "properties": {
    "iso:country":"GB",
    "wof:name":"TN32 5EG",
    "wof:placetype":"postalcode"
},
  "geometry": {"coordinates":[0.46738392134227,50.98327930889644],"type":"Point"}
}