{
  "type": "Feature",
  "properties": {
    "date:inception_lower": "1990-02-01",
    "date:inception_upper": "1990-02-01",
    "iso:country": "GB",
    "wof:name": "TN32 5EG",
    "wof:placetype": "postalcode"
  },
  "geometry": {"coordinates":[0.467384,50.983279],"type":"Point"}
}
