{
  "type": "Feature",
  "properties": {
    "iso:country":"GB",
    "wof:name":"CM22 7DL",
    "wof:placetype":"postalcode"
},
  "geometry": {"coordinates":[0.19794257488073,51.81787698593599],"type":"Point"}
}