{
  "type": "Feature",
  "properties": {
    "iso:country":"GB",
    "wof:name":"SK6 1QH",
    "wof:placetype":"postalcode"
},
  "geometry": {"coordinates":[-2.10364651018017,53.42531510725588],"type":"Point"}
}