{
  "type": "Feature",
  "properties": {
    "date:inception_lower":"1994-12-01",
    "date:inception_upper":"1994-12-31",
    "iso:country":"GB",
    "wof:name":"SO40 2NZ",
    "wof:placetype":"postalcode"
},
  "geometry": {"coordinates":[-1.565643,50.924963],"type":"Point"}
}