{
  "type": "Feature",
  "properties": {
    "iso:country": "GB",
    "wof:name": "SO40 2NZ",
    "wof:placetype": "postalcode"
  },
  "geometry": {"coordinates":[-1.565662,50.924955],"type":"Point"}
}
