{
  "type": "Feature",
  "properties": {
    "iso:country":"GB",
    "wof:name":"ML10 6SR",
    "wof:placetype":"postalcode"
},
  "geometry": {"coordinates":[-4.09909006234492,55.71239496110667],"type":"Point"}
}