{
  "type": "Feature",
  "properties": {
    "iso:country":"GB",
    "wof:name":"TF11 8UB",
    "wof:placetype":"postalcode"
},
  "geometry": {"coordinates":[-2.36681540367224,52.67350183337575],"type":"Point"}
}