{
  "type": "Feature",
  "properties": {
    "date:inception_lower":"1990-02-01",
    "date:inception_upper":"1990-02-28",
    "iso:country":"GB",
    "wof:name":"TF11 8UB",
    "wof:placetype":"postalcode"
},
  "geometry": {"coordinates":[-2.366815,52.673502],"type":"Point"}
}