{
  "type": "Feature",
  "properties": {
    "iso:country": "GB",
    "wof:name": "TF11 8UB",
    "wof:placetype": "postalcode"
  },
  "geometry": {"coordinates":[-2.366815,52.673502],"type":"Point"}
}
