{
  "type": "Feature",
  "properties": {
    "date:inception_lower": "1980-01-01",
    "date:inception_upper": "1980-01-01",
    "iso:country": "GB",
    "wof:name": "LN12 2BS",
    "wof:placetype": "postalcode"
  },
  "geometry": {"coordinates":[0.265711,53.33581],"type":"Point"}
}
