{
  "type": "Feature",
  "properties": {
    "iso:country":"GB",
    "wof:name":"KY1 4EB",
    "wof:placetype":"postalcode"
},
  "geometry": {"coordinates":[-3.14747054049751,56.1638057344954],"type":"Point"}
}