{
  "type": "Feature",
  "properties": {
    "iso:country": "GB",
    "wof:name": "KY1 4EB",
    "wof:placetype": "postalcode"
  },
  "geometry": {"coordinates":[-3.14747,56.163806],"type":"Point"}
}
