{
  "type": "Feature",
  "properties": {
    "iso:country":"GB",
    "wof:name":"DN7 6LY",
    "wof:placetype":"postalcode"
},
  "geometry": {"coordinates":[-0.98458046606558,53.57300219691191],"type":"Point"}
}