{
  "type": "Feature",
  "properties": {
    "iso:country": "GB",
    "wof:name": "ST6 5AW",
    "wof:placetype": "postalcode"
  },
  "geometry": {"coordinates":[-2.212135,53.059659],"type":"Point"}
}
