{
  "type": "Feature",
  "properties": {
    "iso:country":"GB",
    "wof:name":"PA13 4LX",
    "wof:placetype":"postalcode"
},
  "geometry": {"coordinates":[-4.63532570921088,55.88951673143794],"type":"Point"}
}