{
  "type": "Feature",
  "properties": {
    "iso:country":"GB",
    "wof:name":"CW7 2JU",
    "wof:placetype":"postalcode"
},
  "geometry": {"coordinates":[-2.54364839799504,53.18844417958726],"type":"Point"}
}