{
  "type": "Feature",
  "properties": {
    "iso:country": "GB",
    "wof:name": "TQ14 8TA",
    "wof:placetype": "postalcode"
  },
  "geometry": {"coordinates":[-3.49167,50.548045],"type":"Point"}
}
