{
  "type": "Feature",
  "properties": {
    "iso:country": "GB",
    "wof:name": "NP22 5QG",
    "wof:placetype": "postalcode"
  },
  "geometry": {"coordinates":[-3.295228,51.776673],"type":"Point"}
}
