{
  "type": "Feature",
  "properties": {
    "iso:country":"GB",
    "wof:name":"NP22 5QG",
    "wof:placetype":"postalcode"
},
  "geometry": {"coordinates":[-3.29522785649937,51.77667276038383],"type":"Point"}
}