{
  "type": "Feature",
  "properties": {
    "iso:country":"GB",
    "wof:name":"CH8 8HP",
    "wof:placetype":"postalcode"
},
  "geometry": {"coordinates":[-3.19832731084084,53.24102679434618],"type":"Point"}
}