{
  "type": "Feature",
  "properties": {
    "date:inception_lower": "1980-01-01",
    "date:inception_upper": "1980-01-01",
    "iso:country": "GB",
    "wof:name": "SN3 2JH",
    "wof:placetype": "postalcode"
  },
  "geometry": {"coordinates":[-1.755236,51.551224],"type":"Point"}
}
