{
  "type": "Feature",
  "properties": {
    "iso:country": "GB",
    "wof:name": "SN3 2JH",
    "wof:placetype": "postalcode"
  },
  "geometry": {"coordinates":[-1.755118,51.55125],"type":"Point"}
}
