{
  "type": "Feature",
  "properties": {
    "date:inception_lower": "2022-09-01",
    "date:inception_upper": "2022-09-01",
    "iso:country": "GB",
    "wof:name": "SA3 4DG",
    "wof:placetype": "postalcode"
  },
  "geometry": {"coordinates":[-4.010608,51.568862],"type":"Point"}
}
