{
  "type": "Feature",
  "properties": {
    "date:inception_lower": "2009-09-01",
    "date:inception_upper": "2009-09-01",
    "iso:country": "GB",
    "wof:name": "RG30 4HZ",
    "wof:placetype": "postalcode"
  },
  "geometry": {"coordinates":[-1.027602,51.449675],"type":"Point"}
}
