{
  "type": "Feature",
  "properties": {
    "iso:country": "GB",
    "wof:name": "RG30 4HZ",
    "wof:placetype": "postalcode"
  },
  "geometry": {"coordinates":[-1.027602,51.449675],"type":"Point"}
}
