{
  "type": "Feature",
  "properties": {
    "iso:country":"GB",
    "wof:name":"RG30 4HZ",
    "wof:placetype":"postalcode"
},
  "geometry": {"coordinates":[-1.02760190718945,51.44967455416447],"type":"Point"}
}