{
  "type": "Feature",
  "properties": {
    "iso:country":"GB",
    "wof:name":"WV3 9NT",
    "wof:placetype":"postalcode"
},
  "geometry": {"coordinates":[-2.14847083062711,52.586884343413],"type":"Point"}
}