{
  "type": "Feature",
  "properties": {
    "date:inception_lower":"1980-01-01",
    "date:inception_upper":"1980-01-31",
    "iso:country":"GB",
    "wof:name":"KA18 1LF",
    "wof:placetype":"postalcode"
},
  "geometry": {"coordinates":[-4.262164,55.454424],"type":"Point"}
}