{
  "type": "Feature",
  "properties": {
    "iso:country":"GB",
    "wof:name":"TS1 4SS",
    "wof:placetype":"postalcode"
},
  "geometry": {"coordinates":[-1.25546682187933,54.56876389543228],"type":"Point"}
}