{
  "type": "Feature",
  "properties": {
    "date:inception_lower": "1980-01-01",
    "date:inception_upper": "1980-01-01",
    "iso:country": "GB",
    "wof:name": "OX17 1NL",
    "wof:placetype": "postalcode"
  },
  "geometry": {"coordinates":[-1.319544,52.115796],"type":"Point"}
}
