{
  "type": "Feature",
  "properties": {
    "iso:country":"GB",
    "wof:name":"CO5 9XG",
    "wof:placetype":"postalcode"
},
  "geometry": {"coordinates":[0.78609469007549,51.83309862012729],"type":"Point"}
}