{
  "type": "Feature",
  "properties": {
    "iso:country":"GB",
    "wof:name":"SG19 1AT",
    "wof:placetype":"postalcode"
},
  "geometry": {"coordinates":[-0.28248389733493,52.12452614081172],"type":"Point"}
}