{
  "type": "Feature",
  "properties": {
    "date:inception_lower": "1980-01-01",
    "date:inception_upper": "1980-01-01",
    "iso:country": "GB",
    "wof:name": "DN12 3EQ",
    "wof:placetype": "postalcode"
  },
  "geometry": {"coordinates":[-1.221762,53.48599],"type":"Point"}
}
