{
  "type": "Feature",
  "properties": {
    "iso:country": "GB",
    "wof:name": "DN12 3EQ",
    "wof:placetype": "postalcode"
  },
  "geometry": {"coordinates":[-1.221762,53.48599],"type":"Point"}
}
