{
  "type": "Feature",
  "properties": {
    "iso:country":"GB",
    "wof:name":"OX16 2BL",
    "wof:placetype":"postalcode"
},
  "geometry": {"coordinates":[-1.34358350699913,52.06499680457273],"type":"Point"}
}