{
  "type": "Feature",
  "properties": {
    "date:inception_lower": "2005-06-01",
    "date:inception_upper": "2005-06-01",
    "iso:country": "GB",
    "wof:name": "OX16 2BL",
    "wof:placetype": "postalcode"
  },
  "geometry": {"coordinates":[-1.343583,52.064997],"type":"Point"}
}
