{
  "type": "Feature",
  "properties": {
    "iso:country":"GB",
    "wof:name":"HU18 1HH",
    "wof:placetype":"postalcode"
},
  "geometry": {"coordinates":[-0.17139940317123,53.916718728612],"type":"Point"}
}