{
  "type": "Feature",
  "properties": {
    "date:inception_lower": "1980-01-01",
    "date:inception_upper": "1980-01-01",
    "iso:country": "GB",
    "wof:name": "SW19 7QJ",
    "wof:placetype": "postalcode"
  },
  "geometry": {"coordinates":[-0.206446,51.424818],"type":"Point"}
}
