{
  "type": "Feature",
  "properties": {
    "iso:country":"GB",
    "wof:name":"SW19 7QJ",
    "wof:placetype":"postalcode"
},
  "geometry": {"coordinates":[-0.20644565618507,51.42481812038144],"type":"Point"}
}