{
  "type": "Feature",
  "properties": {
    "iso:country": "GB",
    "wof:name": "DL16 7UH",
    "wof:placetype": "postalcode"
  },
  "geometry": {"coordinates":[-1.603839,54.697145],"type":"Point"}
}
