{
  "type": "Feature",
  "properties": {
    "iso:country": "GB",
    "wof:name": "HP13 7EQ",
    "wof:placetype": "postalcode"
  },
  "geometry": {"coordinates":[-0.714597,51.6185],"type":"Point"}
}
