{
  "type": "Feature",
  "properties": {
    "iso:country":"GB",
    "wof:name":"NG3 5PG",
    "wof:placetype":"postalcode"
},
  "geometry": {"coordinates":[-1.12948396862011,52.97257931841838],"type":"Point"}
}