{
  "type": "Feature",
  "properties": {
    "iso:country":"GB",
    "wof:name":"RG45 7LR",
    "wof:placetype":"postalcode"
},
  "geometry": {"coordinates":[-0.80101102011093,51.36799712427294],"type":"Point"}
}