{
  "type": "Feature",
  "properties": {
    "iso:country":"GB",
    "wof:name":"MK10 9QT",
    "wof:placetype":"postalcode"
},
  "geometry": {"coordinates":[-0.69324424982829,52.04105975252424],"type":"Point"}
}