{
  "type": "Feature",
  "properties": {
    "date:inception_lower": "2008-03-01",
    "date:inception_upper": "2008-03-01",
    "iso:country": "GB",
    "wof:name": "MK10 9QT",
    "wof:placetype": "postalcode"
  },
  "geometry": {"coordinates":[-0.693244,52.04106],"type":"Point"}
}
