{
  "type": "Feature",
  "properties": {
    "iso:country": "GB",
    "wof:name": "WN3 6TE",
    "wof:placetype": "postalcode"
  },
  "geometry": {"coordinates":[-2.663677,53.52017],"type":"Point"}
}
