{
  "type": "Feature",
  "properties": {
    "iso:country":"GB",
    "wof:name":"N13 6AF",
    "wof:placetype":"postalcode"
},
  "geometry": {"coordinates":[-0.10154467880629,51.61400566970608],"type":"Point"}
}