{
  "type": "Feature",
  "properties": {
    "date:inception_lower":"2014-12-01",
    "date:inception_upper":"2014-12-31",
    "iso:country":"GB",
    "wof:name":"N13 6AF",
    "wof:placetype":"postalcode"
},
  "geometry": {"coordinates":[-0.101457,51.61404],"type":"Point"}
}