{
  "type": "Feature",
  "properties": {
    "iso:country":"GB",
    "wof:name":"BA2 3BE",
    "wof:placetype":"postalcode"
},
  "geometry": {"coordinates":[-2.36957265291875,51.37910223843959],"type":"Point"}
}