{
  "type": "Feature",
  "properties": {
    "iso:country":"GB",
    "wof:name":"SY18 6AJ",
    "wof:placetype":"postalcode"
},
  "geometry": {"coordinates":[-3.54656217068518,52.44632921238773],"type":"Point"}
}