{
  "type": "Feature",
  "properties": {
    "iso:country":"GB",
    "wof:name":"GU14 9BX",
    "wof:placetype":"postalcode"
},
  "geometry": {"coordinates":[-0.77068946808162,51.31417959759015],"type":"Point"}
}