{
  "type": "Feature",
  "properties": {
    "date:inception_lower": "2017-08-01",
    "date:inception_upper": "2017-08-01",
    "iso:country": "GB",
    "wof:name": "S20 5FJ",
    "wof:placetype": "postalcode"
  },
  "geometry": {"coordinates":[-1.360391,53.328765],"type":"Point"}
}
