{
  "type": "Feature",
  "properties": {
    "iso:country": "GB",
    "wof:name": "SA67 8BN",
    "wof:placetype": "postalcode"
  },
  "geometry": {"coordinates":[-4.73776,51.770821],"type":"Point"}
}
