{
  "type": "Feature",
  "properties": {
    "iso:country": "GB",
    "wof:name": "SG5 3SW",
    "wof:placetype": "postalcode"
  },
  "geometry": {"coordinates":[-0.304217,51.985579],"type":"Point"}
}
