{
  "type": "Feature",
  "properties": {
    "iso:country": "GB",
    "wof:name": "CF5 1LX",
    "wof:placetype": "postalcode"
  },
  "geometry": {"coordinates":[-3.207158,51.480155],"type":"Point"}
}
