{
  "type": "Feature",
  "properties": {
    "iso:country":"GB",
    "wof:name":"B79 7SQ",
    "wof:placetype":"postalcode"
},
  "geometry": {"coordinates":[-1.71751089950087,52.63975311069373],"type":"Point"}
}