{
  "type": "Feature",
  "properties": {
    "iso:country":"GB",
    "wof:name":"OX29 4TJ",
    "wof:placetype":"postalcode"
},
  "geometry": {"coordinates":[-1.37858706368241,51.77255821021504],"type":"Point"}
}