{
  "type": "Feature",
  "properties": {
    "iso:country":"GB",
    "wof:name":"HX6 2TT",
    "wof:placetype":"postalcode"
},
  "geometry": {"coordinates":[-1.91894729695974,53.71405523844818],"type":"Point"}
}