{
  "type": "Feature",
  "properties": {
    "iso:country":"GB",
    "wof:name":"EH6 6DG",
    "wof:placetype":"postalcode"
},
  "geometry": {"coordinates":[-3.17352829155802,55.97416917272292],"type":"Point"}
}