{
  "type": "Feature",
  "properties": {
    "iso:country": "GB",
    "wof:name": "PE11 3NT",
    "wof:placetype": "postalcode"
  },
  "geometry": {"coordinates":[-0.175126,52.790912],"type":"Point"}
}
