{
  "type": "Feature",
  "properties": {
    "iso:country":"GB",
    "wof:name":"PE11 3NT",
    "wof:placetype":"postalcode"
},
  "geometry": {"coordinates":[-0.17512605469275,52.79091192264088],"type":"Point"}
}