{
  "type": "Feature",
  "properties": {
    "iso:country": "GB",
    "wof:name": "SA41 3UX",
    "wof:placetype": "postalcode"
  },
  "geometry": {"coordinates":[-4.760265,52.025505],"type":"Point"}
}
