{
  "type": "Feature",
  "properties": {
    "date:inception_lower": "1982-03-01",
    "date:inception_upper": "1982-03-01",
    "iso:country": "GB",
    "wof:name": "ML3 9EX",
    "wof:placetype": "postalcode"
  },
  "geometry": {"coordinates":[-4.092309,55.767764],"type":"Point"}
}
