{
  "type": "Feature",
  "properties": {
    "iso:country": "GB",
    "wof:name": "PL14 5FH",
    "wof:placetype": "postalcode"
  },
  "geometry": {"coordinates":[-4.430161,50.53655],"type":"Point"}
}
