{
  "type": "Feature",
  "properties": {
    "date:inception_lower": "2016-10-01",
    "date:inception_upper": "2016-10-01",
    "iso:country": "GB",
    "wof:name": "CV23 8ER",
    "wof:placetype": "postalcode"
  },
  "geometry": {"coordinates":[-1.37671,52.314383],"type":"Point"}
}
