{
  "type": "Feature",
  "properties": {
    "iso:country":"GB",
    "wof:name":"L20 0BY",
    "wof:placetype":"postalcode"
},
  "geometry": {"coordinates":[-2.97413972128578,53.46099958500015],"type":"Point"}
}