{
  "type": "Feature",
  "properties": {
    "iso:country":"GB",
    "wof:name":"KY11 1PH",
    "wof:placetype":"postalcode"
},
  "geometry": {"coordinates":[-3.38747517641131,56.03118862855125],"type":"Point"}
}