{
  "type": "Feature",
  "properties": {
    "iso:country":"GB",
    "wof:name":"WN5 8PL",
    "wof:placetype":"postalcode"
},
  "geometry": {"coordinates":[-2.70156182454548,53.54649649312416],"type":"Point"}
}