{
  "type": "Feature",
  "properties": {
    "iso:country":"GB",
    "wof:name":"NR28 9NU",
    "wof:placetype":"postalcode"
},
  "geometry": {"coordinates":[1.48200089234498,52.82357528539633],"type":"Point"}
}