{
  "type": "Feature",
  "properties": {
    "iso:country": "GB",
    "wof:name": "NR28 9NU",
    "wof:placetype": "postalcode"
  },
  "geometry": {"coordinates":[1.482001,52.823575],"type":"Point"}
}
