{
  "type": "Feature",
  "properties": {
    "iso:country":"GB",
    "wof:name":"LU4 0XA",
    "wof:placetype":"postalcode"
},
  "geometry": {"coordinates":[-0.4784868822619,51.89967173319239],"type":"Point"}
}