{
  "type": "Feature",
  "properties": {
    "date:inception_lower":"2013-08-01",
    "date:inception_upper":"2013-08-31",
    "iso:country":"GB",
    "wof:name":"SW9 6FW",
    "wof:placetype":"postalcode"
},
  "geometry": {"coordinates":[-0.111426,51.477074],"type":"Point"}
}