{
  "type": "Feature",
  "properties": {
    "iso:country":"GB",
    "wof:name":"SW9 6FW",
    "wof:placetype":"postalcode"
},
  "geometry": {"coordinates":[-0.11142638461882,51.47707447523065],"type":"Point"}
}