{
  "type": "Feature",
  "properties": {
    "iso:country":"GB",
    "wof:name":"E9 7PH",
    "wof:placetype":"postalcode"
},
  "geometry": {"coordinates":[-0.0523753301378,51.54214123357112],"type":"Point"}
}