{
  "type": "Feature",
  "properties": {
    "iso:country":"GB",
    "wof:name":"AL5 3DD",
    "wof:placetype":"postalcode"
},
  "geometry": {"coordinates":[-0.37003263642967,51.8259887391574],"type":"Point"}
}