{
  "type": "Feature",
  "properties": {
    "date:inception_lower": "1980-01-01",
    "date:inception_upper": "1980-01-01",
    "iso:country": "GB",
    "wof:name": "G42 8TR",
    "wof:placetype": "postalcode"
  },
  "geometry": {"coordinates":[-4.250259,55.833754],"type":"Point"}
}
