{
  "type": "Feature",
  "properties": {
    "iso:country":"GB",
    "wof:name":"G42 8TR",
    "wof:placetype":"postalcode"
},
  "geometry": {"coordinates":[-4.25025902800894,55.83375427073091],"type":"Point"}
}