{
  "type": "Feature",
  "properties": {
    "iso:country":"GB",
    "wof:name":"CV5 9BS",
    "wof:placetype":"postalcode"
},
  "geometry": {"coordinates":[-1.56603303704324,52.42337498645988],"type":"Point"}
}