{
  "type": "Feature",
  "properties": {
    "iso:country":"GB",
    "wof:name":"HU5 1LH",
    "wof:placetype":"postalcode"
},
  "geometry": {"coordinates":[-0.3502553171036,53.76245083782975],"type":"Point"}
}