{
  "type": "Feature",
  "properties": {
    "date:inception_lower": "1980-01-01",
    "date:inception_upper": "1980-01-01",
    "iso:country": "GB",
    "wof:name": "EN5 5AA",
    "wof:placetype": "postalcode"
  },
  "geometry": {"coordinates":[-0.188312,51.648037],"type":"Point"}
}
