{
  "type": "Feature",
  "properties": {
    "date:inception_lower": "1980-01-01",
    "date:inception_upper": "1980-01-01",
    "iso:country": "GB",
    "wof:name": "PR5 6GD",
    "wof:placetype": "postalcode"
  },
  "geometry": {"coordinates":[-2.66218,53.735475],"type":"Point"}
}
