{
  "type": "Feature",
  "properties": {
    "iso:country":"GB",
    "wof:name":"CV1 2LJ",
    "wof:placetype":"postalcode"
},
  "geometry": {"coordinates":[-1.51074996923766,52.40394736973498],"type":"Point"}
}