{
  "type": "Feature",
  "properties": {
    "iso:country":"GB",
    "wof:name":"SS13 2JH",
    "wof:placetype":"postalcode"
},
  "geometry": {"coordinates":[0.53150623203546,51.57086889973784],"type":"Point"}
}