{
  "type": "Feature",
  "properties": {
    "iso:country":"GB",
    "wof:name":"CV2 4JW",
    "wof:placetype":"postalcode"
},
  "geometry": {"coordinates":[-1.47531184044887,52.41378356009704],"type":"Point"}
}