{
  "type": "Feature",
  "properties": {
    "iso:country":"GB",
    "wof:name":"GU28 9LN",
    "wof:placetype":"postalcode"
},
  "geometry": {"coordinates":[-0.59668764812657,51.04446237959576],"type":"Point"}
}