{
  "type": "Feature",
  "properties": {
    "iso:country": "GB",
    "wof:name": "GU28 9LN",
    "wof:placetype": "postalcode"
  },
  "geometry": {"coordinates":[-0.596688,51.044462],"type":"Point"}
}
