{
  "type": "Feature",
  "properties": {
    "iso:country":"GB",
    "wof:name":"RM12 5PU",
    "wof:placetype":"postalcode"
},
  "geometry": {"coordinates":[0.2039532041241,51.54152612098569],"type":"Point"}
}