{
  "type": "Feature",
  "properties": {
    "date:inception_lower":"1980-01-01",
    "date:inception_upper":"1980-01-31",
    "iso:country":"GB",
    "wof:name":"RM12 5PU",
    "wof:placetype":"postalcode"
},
  "geometry": {"coordinates":[0.203953,51.541526],"type":"Point"}
}