{
  "type": "Feature",
  "properties": {
    "date:inception_lower": "1995-07-01",
    "date:inception_upper": "1995-07-01",
    "iso:country": "GB",
    "wof:name": "L1 5DG",
    "wof:placetype": "postalcode"
  },
  "geometry": {"coordinates":[-2.978477,53.39939],"type":"Point"}
}
