{
  "type": "Feature",
  "properties": {
    "iso:country": "GB",
    "wof:name": "WR9 0WR",
    "wof:placetype": "postalcode"
  },
  "geometry": {"coordinates":[-2.154615,52.275386],"type":"Point"}
}
