{
  "type": "Feature",
  "properties": {
    "iso:country":"GB",
    "wof:name":"NP19 9EW",
    "wof:placetype":"postalcode"
},
  "geometry": {"coordinates":[-2.94478113742464,51.59499514739085],"type":"Point"}
}