{
  "type": "Feature",
  "properties": {
    "iso:country":"GB",
    "wof:name":"KT19 0JB",
    "wof:placetype":"postalcode"
},
  "geometry": {"coordinates":[-0.26560566307416,51.36746383427663],"type":"Point"}
}