{
  "type": "Feature",
  "properties": {
    "date:inception_lower": "1980-01-01",
    "date:inception_upper": "1980-01-01",
    "iso:country": "GB",
    "wof:name": "SK17 0PS",
    "wof:placetype": "postalcode"
  },
  "geometry": {"coordinates":[-1.850819,53.177736],"type":"Point"}
}
