{
  "type": "Feature",
  "properties": {
    "iso:country": "GB",
    "wof:name": "CF44 9LS",
    "wof:placetype": "postalcode"
  },
  "geometry": {"coordinates":[-3.49126,51.732276],"type":"Point"}
}
