{
  "type": "Feature",
  "properties": {
    "iso:country":"GB",
    "wof:name":"G13 1RF",
    "wof:placetype":"postalcode"
},
  "geometry": {"coordinates":[-4.32215956851543,55.89649009023783],"type":"Point"}
}