{
  "type": "Feature",
  "properties": {
    "date:inception_lower": "1980-01-01",
    "date:inception_upper": "1980-01-01",
    "iso:country": "GB",
    "wof:name": "KT22 7HT",
    "wof:placetype": "postalcode"
  },
  "geometry": {"coordinates":[-0.326914,51.299147],"type":"Point"}
}
