{
  "type": "Feature",
  "properties": {
    "date:inception_lower": "1994-05-01",
    "date:inception_upper": "1994-05-01",
    "iso:country": "GB",
    "wof:name": "LE4 9DJ",
    "wof:placetype": "postalcode"
  },
  "geometry": {"coordinates":[-1.098238,52.650765],"type":"Point"}
}
