{
  "type": "Feature",
  "properties": {
    "iso:country":"GB",
    "wof:name":"LE4 9DJ",
    "wof:placetype":"postalcode"
},
  "geometry": {"coordinates":[-1.09823796740696,52.65076513189913],"type":"Point"}
}