{
  "type": "Feature",
  "properties": {
    "iso:country":"GB",
    "wof:name":"S25 2SP",
    "wof:placetype":"postalcode"
},
  "geometry": {"coordinates":[-1.20041557346642,53.36680223994608],"type":"Point"}
}