{
  "type": "Feature",
  "properties": {
    "date:inception_lower": "1997-06-01",
    "date:inception_upper": "1997-06-01",
    "iso:country": "GB",
    "wof:name": "S25 2SP",
    "wof:placetype": "postalcode"
  },
  "geometry": {"coordinates":[-1.200416,53.366802],"type":"Point"}
}
