{
  "type": "Feature",
  "properties": {
    "date:inception_lower": "1980-01-01",
    "date:inception_upper": "1980-01-01",
    "iso:country": "GB",
    "wof:name": "GL6 6UA",
    "wof:placetype": "postalcode"
  },
  "geometry": {"coordinates":[-2.17175,51.795499],"type":"Point"}
}
