{
  "type": "Feature",
  "properties": {
    "iso:country": "GB",
    "wof:name": "GL6 6UA",
    "wof:placetype": "postalcode"
  },
  "geometry": {"coordinates":[-2.17175,51.795499],"type":"Point"}
}
