{
  "type": "Feature",
  "properties": {
    "iso:country":"GB",
    "wof:name":"GL6 6UA",
    "wof:placetype":"postalcode"
},
  "geometry": {"coordinates":[-2.17175032227349,51.79549889352601],"type":"Point"}
}