{
  "type": "Feature",
  "properties": {
    "date:inception_lower":"1980-01-01",
    "date:inception_upper":"1980-01-31",
    "iso:country":"GB",
    "wof:name":"LE14 4SD",
    "wof:placetype":"postalcode"
},
  "geometry": {"coordinates":[-0.852127,52.777312],"type":"Point"}
}