{
  "type": "Feature",
  "properties": {
    "iso:country": "GB",
    "wof:name": "LE14 4SD",
    "wof:placetype": "postalcode"
  },
  "geometry": {"coordinates":[-0.852127,52.777312],"type":"Point"}
}
