{
  "type": "Feature",
  "properties": {
    "iso:country":"GB",
    "wof:name":"LE14 4SD",
    "wof:placetype":"postalcode"
},
  "geometry": {"coordinates":[-0.84475223487008,52.78092651734784],"type":"Point"}
}