{
  "type": "Feature",
  "properties": {
    "iso:country":"GB",
    "wof:name":"CM7 1DL",
    "wof:placetype":"postalcode"
},
  "geometry": {"coordinates":[0.55656554927568,51.87017668860941],"type":"Point"}
}