{
  "type": "Feature",
  "properties": {
    "iso:country":"GB",
    "wof:name":"BH17 8SS",
    "wof:placetype":"postalcode"
},
  "geometry": {"coordinates":[-1.95178051534632,50.7516652500345],"type":"Point"}
}