{
  "type": "Feature",
  "properties": {
    "iso:country":"GB",
    "wof:name":"TF8 7JU",
    "wof:placetype":"postalcode"
},
  "geometry": {"coordinates":[-2.48142717650068,52.62602997898322],"type":"Point"}
}