{
  "type": "Feature",
  "properties": {
    "iso:country":"GB",
    "wof:name":"E10 7JR",
    "wof:placetype":"postalcode"
},
  "geometry": {"coordinates":[-0.02513077001791,51.56851063129639],"type":"Point"}
}