{
  "type": "Feature",
  "properties": {
    "date:inception_lower": "1980-01-01",
    "date:inception_upper": "1980-01-01",
    "iso:country": "GB",
    "wof:name": "DY1 3SB",
    "wof:placetype": "postalcode"
  },
  "geometry": {"coordinates":[-2.09646,52.527947],"type":"Point"}
}
