{
  "type": "Feature",
  "properties": {
    "iso:country":"GB",
    "wof:name":"NP15 1LJ",
    "wof:placetype":"postalcode"
},
  "geometry": {"coordinates":[-2.8792474541853,51.68357611928835],"type":"Point"}
}