{
  "type": "Feature",
  "properties": {
    "iso:country": "GB",
    "wof:name": "DN5 0JY",
    "wof:placetype": "postalcode"
  },
  "geometry": {"coordinates":[-1.152843,53.556379],"type":"Point"}
}
