{
  "type": "Feature",
  "properties": {
    "date:inception_lower": "1994-12-01",
    "date:inception_upper": "1994-12-01",
    "iso:country": "GB",
    "wof:name": "DN5 0JY",
    "wof:placetype": "postalcode"
  },
  "geometry": {"coordinates":[-1.152843,53.556379],"type":"Point"}
}
