{
  "type": "Feature",
  "properties": {
    "iso:country":"GB",
    "wof:name":"DN5 0JY",
    "wof:placetype":"postalcode"
},
  "geometry": {"coordinates":[-1.15284303500837,53.55637948607017],"type":"Point"}
}