{
  "type": "Feature",
  "properties": {
    "iso:country":"GB",
    "wof:name":"ME17 3EX",
    "wof:placetype":"postalcode"
},
  "geometry": {"coordinates":[0.55530759354533,51.2025950843509],"type":"Point"}
}