{
  "type": "Feature",
  "properties": {
    "iso:country":"GB",
    "wof:name":"LS20 8BW",
    "wof:placetype":"postalcode"
},
  "geometry": {"coordinates":[-1.71492061362899,53.87475489729447],"type":"Point"}
}