{
  "type": "Feature",
  "properties": {
    "iso:country":"GB",
    "wof:name":"FY5 3EG",
    "wof:placetype":"postalcode"
},
  "geometry": {"coordinates":[-3.04076639231327,53.87087490690489],"type":"Point"}
}