{
  "type": "Feature",
  "properties": {
    "iso:country":"GB",
    "wof:name":"ML2 9DY",
    "wof:placetype":"postalcode"
},
  "geometry": {"coordinates":[-3.88716443382569,55.78835013985],"type":"Point"}
}