{
  "type": "Feature",
  "properties": {
    "iso:country": "GB",
    "wof:name": "LE67 9WL",
    "wof:placetype": "postalcode"
  },
  "geometry": {"coordinates":[-1.278763,52.684293],"type":"Point"}
}
