{
  "type": "Feature",
  "properties": {
    "iso:country":"GB",
    "wof:name":"LE67 9WL",
    "wof:placetype":"postalcode"
},
  "geometry": {"coordinates":[-1.27876321914481,52.68429252768937],"type":"Point"}
}