{
  "type": "Feature",
  "properties": {
    "iso:country":"GB",
    "wof:name":"SP10 3UA",
    "wof:placetype":"postalcode"
},
  "geometry": {"coordinates":[-1.49888433640268,51.20678110292511],"type":"Point"}
}