{
  "type": "Feature",
  "properties": {
    "iso:country": "GB",
    "wof:name": "SP10 3UA",
    "wof:placetype": "postalcode"
  },
  "geometry": {"coordinates":[-1.498884,51.206781],"type":"Point"}
}
