{
  "type": "Feature",
  "properties": {
    "date:inception_lower": "2017-03-01",
    "date:inception_upper": "2017-03-01",
    "iso:country": "GB",
    "wof:name": "SA72 9AR",
    "wof:placetype": "postalcode"
  },
  "geometry": {"coordinates":[-4.941597,51.693673],"type":"Point"}
}
