{
  "type": "Feature",
  "properties": {
    "date:inception_lower":"1995-07-01",
    "date:inception_upper":"1995-07-31",
    "iso:country":"GB",
    "wof:name":"RG31 4SL",
    "wof:placetype":"postalcode"
},
  "geometry": {"coordinates":[-1.05575,51.451091],"type":"Point"}
}