{
  "type": "Feature",
  "properties": {
    "iso:country":"GB",
    "wof:name":"TS7 9AH",
    "wof:placetype":"postalcode"
},
  "geometry": {"coordinates":[-1.18200651409122,54.54898547846517],"type":"Point"}
}