{
  "type": "Feature",
  "properties": {
    "iso:country":"GB",
    "wof:name":"NE16 6QJ",
    "wof:placetype":"postalcode"
},
  "geometry": {"coordinates":[-1.73161227826219,54.90599077946541],"type":"Point"}
}