{
  "type": "Feature",
  "properties": {
    "iso:country":"GB",
    "wof:name":"G53 7ZY",
    "wof:placetype":"postalcode"
},
  "geometry": {"coordinates":[-4.34428038101498,55.8001811506703],"type":"Point"}
}