{
  "type": "Feature",
  "properties": {
    "date:inception_lower":"2015-02-01",
    "date:inception_upper":"2015-02-28",
    "iso:country":"GB",
    "wof:name":"G53 7ZY",
    "wof:placetype":"postalcode"
},
  "geometry": {"coordinates":[-4.344374,55.800112],"type":"Point"}
}