{
  "type": "Feature",
  "properties": {
    "date:inception_lower": "1980-01-01",
    "date:inception_upper": "1980-01-01",
    "iso:country": "GB",
    "wof:name": "BL2 4JB",
    "wof:placetype": "postalcode"
  },
  "geometry": {"coordinates":[-2.375473,53.597608],"type":"Point"}
}
