{
  "type": "Feature",
  "properties": {
    "iso:country":"GB",
    "wof:name":"BL2 4JB",
    "wof:placetype":"postalcode"
},
  "geometry": {"coordinates":[-2.37547259729717,53.59760814373207],"type":"Point"}
}