{
  "type": "Feature",
  "properties": {
    "iso:country":"GB",
    "wof:name":"CW10 0PL",
    "wof:placetype":"postalcode"
},
  "geometry": {"coordinates":[-2.45103931787556,53.186943272885],"type":"Point"}
}