{
  "type": "Feature",
  "properties": {
    "iso:country": "GB",
    "wof:name": "S35 4JF",
    "wof:placetype": "postalcode"
  },
  "geometry": {"coordinates":[-1.499799,53.471675],"type":"Point"}
}
