{
  "type": "Feature",
  "properties": {
    "iso:country":"GB",
    "wof:name":"EN9 2HJ",
    "wof:placetype":"postalcode"
},
  "geometry": {"coordinates":[0.01221493685995,51.73403058294435],"type":"Point"}
}