{
  "type": "Feature",
  "properties": {
    "iso:country":"GB",
    "wof:name":"SO32 1EY",
    "wof:placetype":"postalcode"
},
  "geometry": {"coordinates":[-1.21436686803887,50.95461134243986],"type":"Point"}
}