{
  "type": "Feature",
  "properties": {
    "iso:country":"GB",
    "wof:name":"NW4 1EN",
    "wof:placetype":"postalcode"
},
  "geometry": {"coordinates":[-0.21525703348441,51.59534113100494],"type":"Point"}
}