{
  "type": "Feature",
  "properties": {
    "date:inception_lower": "1980-01-01",
    "date:inception_upper": "1980-01-01",
    "iso:country": "GB",
    "wof:name": "NW4 1EN",
    "wof:placetype": "postalcode"
  },
  "geometry": {"coordinates":[-0.215186,51.595398],"type":"Point"}
}
