{
  "type": "Feature",
  "properties": {
    "iso:country":"GB",
    "wof:name":"GU16 7JW",
    "wof:placetype":"postalcode"
},
  "geometry": {"coordinates":[-0.7410740639627,51.31522286119623],"type":"Point"}
}