{
  "type": "Feature",
  "properties": {
    "iso:country":"GB",
    "wof:name":"PR25 3NQ",
    "wof:placetype":"postalcode"
},
  "geometry": {"coordinates":[-2.69018554442141,53.69953649884577],"type":"Point"}
}