{
  "type": "Feature",
  "properties": {
    "date:inception_lower": "2001-06-01",
    "date:inception_upper": "2001-06-01",
    "iso:country": "GB",
    "wof:name": "PR25 3NQ",
    "wof:placetype": "postalcode"
  },
  "geometry": {"coordinates":[-2.690087,53.700245],"type":"Point"}
}
