{
  "type": "Feature",
  "properties": {
    "iso:country": "GB",
    "wof:name": "PR25 3NQ",
    "wof:placetype": "postalcode"
  },
  "geometry": {"coordinates":[-2.690087,53.700245],"type":"Point"}
}
