{
  "type": "Feature",
  "properties": {
    "iso:country":"GB",
    "wof:name":"IP33 3EA",
    "wof:placetype":"postalcode"
},
  "geometry": {"coordinates":[0.70270058298468,52.24681982754178],"type":"Point"}
}