{
  "type": "Feature",
  "properties": {
    "date:inception_lower":"1980-01-01",
    "date:inception_upper":"1980-01-31",
    "iso:country":"GB",
    "wof:name":"IP33 3EA",
    "wof:placetype":"postalcode"
},
  "geometry": {"coordinates":[0.702701,52.24682],"type":"Point"}
}