{
  "type": "Feature",
  "properties": {
    "iso:country":"GB",
    "wof:name":"AL2 1QX",
    "wof:placetype":"postalcode"
},
  "geometry": {"coordinates":[-0.28937520073387,51.71912450124633],"type":"Point"}
}