{
  "type": "Feature",
  "properties": {
    "iso:country":"GB",
    "wof:name":"SO18 6AT",
    "wof:placetype":"postalcode"
},
  "geometry": {"coordinates":[-1.35473835644432,50.91906945000015],"type":"Point"}
}