{
  "type": "Feature",
  "properties": {
    "date:inception_lower":"1980-01-01",
    "date:inception_upper":"1980-01-31",
    "iso:country":"GB",
    "wof:name":"PL12 4NU",
    "wof:placetype":"postalcode"
},
  "geometry": {"coordinates":[-4.222704,50.403048],"type":"Point"}
}