{
  "type": "Feature",
  "properties": {
    "iso:country":"GB",
    "wof:name":"PL12 4NU",
    "wof:placetype":"postalcode"
},
  "geometry": {"coordinates":[-4.2227037012876,50.40304841356207],"type":"Point"}
}