{
  "type": "Feature",
  "properties": {
    "iso:country":"GB",
    "wof:name":"SP6 2DF",
    "wof:placetype":"postalcode"
},
  "geometry": {"coordinates":[-1.78397218794229,50.97064888191423],"type":"Point"}
}