{
  "type": "Feature",
  "properties": {
    "date:inception_lower": "1980-01-01",
    "date:inception_upper": "1980-01-01",
    "iso:country": "GB",
    "wof:name": "SP6 2DF",
    "wof:placetype": "postalcode"
  },
  "geometry": {"coordinates":[-1.783964,50.970498],"type":"Point"}
}
