{
  "type": "Feature",
  "properties": {
    "iso:country": "GB",
    "wof:name": "SP6 2DF",
    "wof:placetype": "postalcode"
  },
  "geometry": {"coordinates":[-1.783964,50.970498],"type":"Point"}
}
