{
  "type": "Feature",
  "properties": {
    "iso:country":"GB",
    "wof:name":"CV6 2NS",
    "wof:placetype":"postalcode"
},
  "geometry": {"coordinates":[-1.52972738774665,52.44394047146486],"type":"Point"}
}