{
  "type": "Feature",
  "properties": {
    "iso:country": "GB",
    "wof:name": "CV6 2NS",
    "wof:placetype": "postalcode"
  },
  "geometry": {"coordinates":[-1.529727,52.44394],"type":"Point"}
}
