{
  "type": "Feature",
  "properties": {
    "date:inception_lower": "1980-01-01",
    "date:inception_upper": "1980-01-01",
    "iso:country": "GB",
    "wof:name": "SN12 6NP",
    "wof:placetype": "postalcode"
  },
  "geometry": {"coordinates":[-2.083849,51.348994],"type":"Point"}
}
