{
  "type": "Feature",
  "properties": {
    "iso:country":"GB",
    "wof:name":"SN12 6NP",
    "wof:placetype":"postalcode"
},
  "geometry": {"coordinates":[-2.08384893572438,51.34899404472599],"type":"Point"}
}