{
  "type": "Feature",
  "properties": {
    "iso:country":"GB",
    "wof:name":"AB43 8SW",
    "wof:placetype":"postalcode"
},
  "geometry": {"coordinates":[-1.92093323946591,57.59899555975518],"type":"Point"}
}