{
  "type": "Feature",
  "properties": {
    "iso:country":"GB",
    "wof:name":"CM2 7RU",
    "wof:placetype":"postalcode"
},
  "geometry": {"coordinates":[0.53179864244873,51.72138264307213],"type":"Point"}
}