{
  "type": "Feature",
  "properties": {
    "date:inception_lower":"1980-01-01",
    "date:inception_upper":"1980-01-31",
    "iso:country":"GB",
    "wof:name":"CM2 7RU",
    "wof:placetype":"postalcode"
},
  "geometry": {"coordinates":[0.531799,51.721383],"type":"Point"}
}