{
  "type": "Feature",
  "properties": {
    "iso:country": "GB",
    "wof:name": "PL26 7SW",
    "wof:placetype": "postalcode"
  },
  "geometry": {"coordinates":[-4.900526,50.370922],"type":"Point"}
}
