{
  "type": "Feature",
  "properties": {
    "iso:country":"GB",
    "wof:name":"DA4 9JD",
    "wof:placetype":"postalcode"
},
  "geometry": {"coordinates":[0.23487356391579,51.41279940332404],"type":"Point"}
}