{
  "type": "Feature",
  "properties": {
    "date:inception_lower": "2007-02-01",
    "date:inception_upper": "2007-02-01",
    "iso:country": "GB",
    "wof:name": "DA4 9JD",
    "wof:placetype": "postalcode"
  },
  "geometry": {"coordinates":[0.234874,51.412799],"type":"Point"}
}
