{
  "type": "Feature",
  "properties": {
    "iso:country":"GB",
    "wof:name":"SE4 1TX",
    "wof:placetype":"postalcode"
},
  "geometry": {"coordinates":[-0.02982557892144,51.46284517471103],"type":"Point"}
}