{
  "type": "Feature",
  "properties": {
    "date:inception_lower": "2002-10-01",
    "date:inception_upper": "2002-10-01",
    "iso:country": "GB",
    "wof:name": "NN4 6JN",
    "wof:placetype": "postalcode"
  },
  "geometry": {"coordinates":[-0.882094,52.200784],"type":"Point"}
}
