{
  "type": "Feature",
  "properties": {
    "iso:country": "GB",
    "wof:name": "NR33 0HJ",
    "wof:placetype": "postalcode"
  },
  "geometry": {"coordinates":[1.743598,52.468055],"type":"Point"}
}
