{
  "type": "Feature",
  "properties": {
    "date:inception_lower": "1980-01-01",
    "date:inception_upper": "1980-01-01",
    "iso:country": "GB",
    "wof:name": "B77 4JD",
    "wof:placetype": "postalcode"
  },
  "geometry": {"coordinates":[-1.642977,52.613653],"type":"Point"}
}
