{
  "type": "Feature",
  "properties": {
    "iso:country": "GB",
    "wof:name": "BN2 5TE",
    "wof:placetype": "postalcode"
  },
  "geometry": {"coordinates":[-0.107704,50.815831],"type":"Point"}
}
