{
  "type": "Feature",
  "properties": {
    "iso:country":"GB",
    "wof:name":"BN2 5TE",
    "wof:placetype":"postalcode"
},
  "geometry": {"coordinates":[-0.10785158899772,50.81569491425472],"type":"Point"}
}