{
  "type": "Feature",
  "properties": {
    "iso:country":"GB",
    "wof:name":"BS20 8NX",
    "wof:placetype":"postalcode"
},
  "geometry": {"coordinates":[-2.78999477126593,51.48108279286814],"type":"Point"}
}