{
  "type": "Feature",
  "properties": {
    "iso:country":"GB",
    "wof:name":"EX2 7NF",
    "wof:placetype":"postalcode"
},
  "geometry": {"coordinates":[-3.47348652573858,50.72201954420316],"type":"Point"}
}