{
  "type": "Feature",
  "properties": {
    "iso:country": "GB",
    "wof:name": "CT1 2LN",
    "wof:placetype": "postalcode"
  },
  "geometry": {"coordinates":[1.073788,51.275322],"type":"Point"}
}
