{
  "type": "Feature",
  "properties": {
    "iso:country":"GB",
    "wof:name":"EN8 7RQ",
    "wof:placetype":"postalcode"
},
  "geometry": {"coordinates":[-0.02545824231817,51.68241501801015],"type":"Point"}
}