{
  "type": "Feature",
  "properties": {
    "date:inception_lower": "1981-09-01",
    "date:inception_upper": "1981-09-01",
    "iso:country": "GB",
    "wof:name": "PE4 6NA",
    "wof:placetype": "postalcode"
  },
  "geometry": {"coordinates":[-0.27273,52.621461],"type":"Point"}
}
