{
  "type": "Feature",
  "properties": {
    "iso:country":"GB",
    "wof:name":"PE4 6NA",
    "wof:placetype":"postalcode"
},
  "geometry": {"coordinates":[-0.27237977433802,52.62131088468681],"type":"Point"}
}