{
  "type": "Feature",
  "properties": {
    "iso:country": "GB",
    "wof:name": "BS11 9QF",
    "wof:placetype": "postalcode"
  },
  "geometry": {"coordinates":[-2.68671,51.48943],"type":"Point"}
}
