{
  "type": "Feature",
  "properties": {
    "date:inception_lower": "1999-06-01",
    "date:inception_upper": "1999-06-01",
    "iso:country": "GB",
    "wof:name": "CH47 5BB",
    "wof:placetype": "postalcode"
  },
  "geometry": {"coordinates":[-3.166099,53.402559],"type":"Point"}
}
