{
  "type": "Feature",
  "properties": {
    "date:inception_lower": "1980-01-01",
    "date:inception_upper": "1980-01-01",
    "iso:country": "GB",
    "wof:name": "SS2 4PZ",
    "wof:placetype": "postalcode"
  },
  "geometry": {"coordinates":[0.733038,51.551201],"type":"Point"}
}
