{
  "type": "Feature",
  "properties": {
    "iso:country":"GB",
    "wof:name":"SS2 4PZ",
    "wof:placetype":"postalcode"
},
  "geometry": {"coordinates":[0.7330381210772,51.55120086742261],"type":"Point"}
}