{
  "type": "Feature",
  "properties": {
    "iso:country": "GB",
    "wof:name": "RM13 9LA",
    "wof:placetype": "postalcode"
  },
  "geometry": {"coordinates":[0.209774,51.526228],"type":"Point"}
}
