{
  "type": "Feature",
  "properties": {
    "iso:country":"GB",
    "wof:name":"RM13 9LA",
    "wof:placetype":"postalcode"
},
  "geometry": {"coordinates":[0.20977392734915,51.52622756739698],"type":"Point"}
}