{
  "type": "Feature",
  "properties": {
    "date:inception_lower": "1980-01-01",
    "date:inception_upper": "1980-01-01",
    "iso:country": "GB",
    "wof:name": "LA18 4EU",
    "wof:placetype": "postalcode"
  },
  "geometry": {"coordinates":[-3.289711,54.196432],"type":"Point"}
}
