{
  "type": "Feature",
  "properties": {
    "iso:country":"GB",
    "wof:name":"LA18 4EU",
    "wof:placetype":"postalcode"
},
  "geometry": {"coordinates":[-3.28971104441811,54.1964316437024],"type":"Point"}
}