{
  "type": "Feature",
  "properties": {
    "date:inception_lower":"1980-01-01",
    "date:inception_upper":"1980-01-31",
    "iso:country":"GB",
    "wof:name":"KA13 7JX",
    "wof:placetype":"postalcode"
},
  "geometry": {"coordinates":[-4.68139,55.654871],"type":"Point"}
}