{
  "type": "Feature",
  "properties": {
    "iso:country":"GB",
    "wof:name":"KA13 7JX",
    "wof:placetype":"postalcode"
},
  "geometry": {"coordinates":[-4.68139025663363,55.65487110156734],"type":"Point"}
}