{
  "type": "Feature",
  "properties": {
    "iso:country": "GB",
    "wof:name": "KA13 7JX",
    "wof:placetype": "postalcode"
  },
  "geometry": {"coordinates":[-4.68139,55.654871],"type":"Point"}
}
