{
  "type": "Feature",
  "properties": {
    "date:inception_lower":"2016-04-01",
    "date:inception_upper":"2016-04-30",
    "iso:country":"GB",
    "wof:name":"G71 7FH",
    "wof:placetype":"postalcode"
},
  "geometry": {"coordinates":[-4.069979,55.817981],"type":"Point"}
}