{
  "type": "Feature",
  "properties": {
    "date:inception_lower": "1980-01-01",
    "date:inception_upper": "1980-01-01",
    "iso:country": "GB",
    "wof:name": "RM2 5NS",
    "wof:placetype": "postalcode"
  },
  "geometry": {"coordinates":[0.195687,51.588833],"type":"Point"}
}
