{
  "type": "Feature",
  "properties": {
    "iso:country": "GB",
    "wof:name": "RM2 5NS",
    "wof:placetype": "postalcode"
  },
  "geometry": {"coordinates":[0.195687,51.588833],"type":"Point"}
}
