{
  "type": "Feature",
  "properties": {
    "iso:country":"GB",
    "wof:name":"KA3 2RL",
    "wof:placetype":"postalcode"
},
  "geometry": {"coordinates":[-4.53173114290421,55.63895152235589],"type":"Point"}
}