{
  "type": "Feature",
  "properties": {
    "iso:country":"GB",
    "wof:name":"DH8 5XE",
    "wof:placetype":"postalcode"
},
  "geometry": {"coordinates":[-1.84164646416648,54.86472077462858],"type":"Point"}
}