{
  "type": "Feature",
  "properties": {
    "date:inception_lower":"1996-06-01",
    "date:inception_upper":"1996-06-30",
    "iso:country":"GB",
    "wof:name":"W3 8RN",
    "wof:placetype":"postalcode"
},
  "geometry": {"coordinates":[-0.272977,51.502846],"type":"Point"}
}