{
  "type": "Feature",
  "properties": {
    "iso:country":"GB",
    "wof:name":"W3 8RN",
    "wof:placetype":"postalcode"
},
  "geometry": {"coordinates":[-0.27297721630461,51.50284645548439],"type":"Point"}
}