{
  "type": "Feature",
  "properties": {
    "iso:country":"GB",
    "wof:name":"DN39 6XF",
    "wof:placetype":"postalcode"
},
  "geometry": {"coordinates":[-0.33672201027978,53.65030303757226],"type":"Point"}
}