{
  "type": "Feature",
  "properties": {
    "iso:country": "GB",
    "wof:name": "DN39 6XF",
    "wof:placetype": "postalcode"
  },
  "geometry": {"coordinates":[-0.336722,53.650303],"type":"Point"}
}
