{
  "type": "Feature",
  "properties": {
    "iso:country":"GB",
    "wof:name":"PE36 5EG",
    "wof:placetype":"postalcode"
},
  "geometry": {"coordinates":[0.48825649694647,52.93171001110557],"type":"Point"}
}