{
  "type": "Feature",
  "properties": {
    "date:inception_lower": "1984-02-01",
    "date:inception_upper": "1984-02-01",
    "iso:country": "GB",
    "wof:name": "PE36 5EG",
    "wof:placetype": "postalcode"
  },
  "geometry": {"coordinates":[0.488257,52.93171],"type":"Point"}
}
