{
  "type": "Feature",
  "properties": {
    "date:inception_lower":"1980-01-01",
    "date:inception_upper":"1980-01-31",
    "iso:country":"GB",
    "wof:name":"OX11 0RY",
    "wof:placetype":"postalcode"
},
  "geometry": {"coordinates":[-1.294629,51.566722],"type":"Point"}
}