{
  "type": "Feature",
  "properties": {
    "iso:country":"GB",
    "wof:name":"OX11 0RY",
    "wof:placetype":"postalcode"
},
  "geometry": {"coordinates":[-1.29462929403457,51.56672199643954],"type":"Point"}
}