{
  "type": "Feature",
  "properties": {
    "iso:country":"GB",
    "wof:name":"MK16 0AN",
    "wof:placetype":"postalcode"
},
  "geometry": {"coordinates":[-0.73053547222098,52.08292548085748],"type":"Point"}
}