{
  "type": "Feature",
  "properties": {
    "iso:country": "GB",
    "wof:name": "MK16 0AN",
    "wof:placetype": "postalcode"
  },
  "geometry": {"coordinates":[-0.730535,52.082925],"type":"Point"}
}
