{
  "type": "Feature",
  "properties": {
    "date:inception_lower": "1980-01-01",
    "date:inception_upper": "1980-01-01",
    "iso:country": "GB",
    "wof:name": "MK16 0AN",
    "wof:placetype": "postalcode"
  },
  "geometry": {"coordinates":[-0.730535,52.082925],"type":"Point"}
}
