{
  "type": "Feature",
  "properties": {
    "date:inception_lower": "1990-07-01",
    "date:inception_upper": "1990-07-01",
    "iso:country": "GB",
    "wof:name": "TR11 2UB",
    "wof:placetype": "postalcode"
  },
  "geometry": {"coordinates":[-5.072262,50.157816],"type":"Point"}
}
