{
  "type": "Feature",
  "properties": {
    "iso:country":"GB",
    "wof:name":"SG13 8HE",
    "wof:placetype":"postalcode"
},
  "geometry": {"coordinates":[-0.08576751252219,51.78726512407891],"type":"Point"}
}