{
  "type": "Feature",
  "properties": {
    "date:inception_lower": "1986-07-01",
    "date:inception_upper": "1986-07-01",
    "iso:country": "GB",
    "wof:name": "CT9 3YG",
    "wof:placetype": "postalcode"
  },
  "geometry": {"coordinates":[1.42626,51.385084],"type":"Point"}
}
