{
  "type": "Feature",
  "properties": {
    "iso:country": "GB",
    "wof:name": "LL54 6DE",
    "wof:placetype": "postalcode"
  },
  "geometry": {"coordinates":[-4.280881,53.045474],"type":"Point"}
}
