{
  "type": "Feature",
  "properties": {
    "iso:country":"GB",
    "wof:name":"LL54 6DE",
    "wof:placetype":"postalcode"
},
  "geometry": {"coordinates":[-4.28088117393004,53.04547383752538],"type":"Point"}
}