{
  "type": "Feature",
  "properties": {
    "iso:country":"GB",
    "wof:name":"LE12 5TE",
    "wof:placetype":"postalcode"
},
  "geometry": {"coordinates":[-1.16015289351669,52.77830955559524],"type":"Point"}
}