{
  "type": "Feature",
  "properties": {
    "date:inception_lower": "1980-01-01",
    "date:inception_upper": "1980-01-01",
    "iso:country": "GB",
    "wof:name": "G33 6HW",
    "wof:placetype": "postalcode"
  },
  "geometry": {"coordinates":[-4.136652,55.89542],"type":"Point"}
}
