{
  "type": "Feature",
  "properties": {
    "iso:country":"GB",
    "wof:name":"HU19 2JT",
    "wof:placetype":"postalcode"
},
  "geometry": {"coordinates":[0.03531754095319,53.72781036677504],"type":"Point"}
}