{
  "type": "Feature",
  "properties": {
    "iso:country":"GB",
    "wof:name":"SA6 8EY",
    "wof:placetype":"postalcode"
},
  "geometry": {"coordinates":[-3.92389982263467,51.65846384488341],"type":"Point"}
}