{
  "type": "Feature",
  "properties": {
    "iso:country": "GB",
    "wof:name": "SA6 8EY",
    "wof:placetype": "postalcode"
  },
  "geometry": {"coordinates":[-3.92363,51.659193],"type":"Point"}
}
