{
  "type": "Feature",
  "properties": {
    "date:inception_lower": "1996-06-01",
    "date:inception_upper": "1996-06-01",
    "iso:country": "GB",
    "wof:name": "AB55 6RY",
    "wof:placetype": "postalcode"
  },
  "geometry": {"coordinates":[-2.874354,57.55187],"type":"Point"}
}
