{
  "type": "Feature",
  "properties": {
    "iso:country":"GB",
    "wof:name":"AB55 6RY",
    "wof:placetype":"postalcode"
},
  "geometry": {"coordinates":[-2.8743540416791,57.55187027133579],"type":"Point"}
}