{
  "type": "Feature",
  "properties": {
    "iso:country": "GB",
    "wof:name": "HP22 6LF",
    "wof:placetype": "postalcode"
  },
  "geometry": {"coordinates":[-0.742358,51.763489],"type":"Point"}
}
