{
  "type": "Feature",
  "properties": {
    "date:inception_lower":"1988-03-01",
    "date:inception_upper":"1988-03-31",
    "iso:country":"GB",
    "wof:name":"HP22 6LF",
    "wof:placetype":"postalcode"
},
  "geometry": {"coordinates":[-0.742358,51.763489],"type":"Point"}
}