{
  "type": "Feature",
  "properties": {
    "iso:country":"GB",
    "wof:name":"SW9 9RJ",
    "wof:placetype":"postalcode"
},
  "geometry": {"coordinates":[-0.12188299608828,51.46651427834153],"type":"Point"}
}