{
  "type": "Feature",
  "properties": {
    "date:inception_lower": "1980-01-01",
    "date:inception_upper": "1980-01-01",
    "iso:country": "GB",
    "wof:name": "KA1 1QD",
    "wof:placetype": "postalcode"
  },
  "geometry": {"coordinates":[-4.497253,55.607902],"type":"Point"}
}
