{
  "type": "Feature",
  "properties": {
    "iso:country":"GB",
    "wof:name":"KA1 1QD",
    "wof:placetype":"postalcode"
},
  "geometry": {"coordinates":[-4.49734348640194,55.60775714066403],"type":"Point"}
}