{
  "type": "Feature",
  "properties": {
    "date:inception_lower": "2019-06-01",
    "date:inception_upper": "2019-06-01",
    "iso:country": "GB",
    "wof:name": "SG5 2EA",
    "wof:placetype": "postalcode"
  },
  "geometry": {"coordinates":[-0.290605,51.95115],"type":"Point"}
}
