{
  "type": "Feature",
  "properties": {
    "iso:country": "GB",
    "wof:name": "HR6 0BL",
    "wof:placetype": "postalcode"
  },
  "geometry": {"coordinates":[-2.79077,52.284658],"type":"Point"}
}
