{
  "type": "Feature",
  "properties": {
    "iso:country":"GB",
    "wof:name":"HR6 0BL",
    "wof:placetype":"postalcode"
},
  "geometry": {"coordinates":[-2.79087243169974,52.2846454260673],"type":"Point"}
}