{
  "type": "Feature",
  "properties": {
    "iso:country":"GB",
    "wof:name":"N19 5NQ",
    "wof:placetype":"postalcode"
},
  "geometry": {"coordinates":[-0.14017852928413,51.56850211854839],"type":"Point"}
}