{
  "type": "Feature",
  "properties": {
    "date:inception_lower": "2017-04-01",
    "date:inception_upper": "2017-04-01",
    "iso:country": "GB",
    "wof:name": "BR8 9BP",
    "wof:placetype": "postalcode"
  },
  "geometry": {"coordinates":[0.17493,51.395825],"type":"Point"}
}
