{
  "type": "Feature",
  "properties": {
    "iso:country":"GB",
    "wof:name":"HA4 8UB",
    "wof:placetype":"postalcode"
},
  "geometry": {"coordinates":[-0.40443231206407,51.57438885819732],"type":"Point"}
}