{
  "type": "Feature",
  "properties": {
    "iso:country":"GB",
    "wof:name":"SW1H 9AP",
    "wof:placetype":"postalcode"
},
  "geometry": {"coordinates":[-0.13427840926411,51.50040728757052],"type":"Point"}
}