{
  "type": "Feature",
  "properties": {
    "iso:country":"GB",
    "wof:name":"NG1 4BU",
    "wof:placetype":"postalcode"
},
  "geometry": {"coordinates":[-1.15207736799381,52.95643563743375],"type":"Point"}
}