{
  "type": "Feature",
  "properties": {
    "date:inception_lower": "1980-01-01",
    "date:inception_upper": "1980-01-01",
    "iso:country": "GB",
    "wof:name": "B73 5EA",
    "wof:placetype": "postalcode"
  },
  "geometry": {"coordinates":[-1.844226,52.549181],"type":"Point"}
}
