{
  "type": "Feature",
  "properties": {
    "iso:country":"GB",
    "wof:name":"B73 5EA",
    "wof:placetype":"postalcode"
},
  "geometry": {"coordinates":[-1.84422565062458,52.54918127595518],"type":"Point"}
}