{
  "type": "Feature",
  "properties": {
    "iso:country": "GB",
    "wof:name": "DN11 0YB",
    "wof:placetype": "postalcode"
  },
  "geometry": {"coordinates":[-1.066452,53.480807],"type":"Point"}
}
