{
  "type": "Feature",
  "properties": {
    "iso:country":"GB",
    "wof:name":"BA1 2TA",
    "wof:placetype":"postalcode"
},
  "geometry": {"coordinates":[-2.36879482494785,51.38958000188433],"type":"Point"}
}