{
  "type": "Feature",
  "properties": {
    "iso:country": "GB",
    "wof:name": "BA1 2TA",
    "wof:placetype": "postalcode"
  },
  "geometry": {"coordinates":[-2.368795,51.38958],"type":"Point"}
}
