{
  "type": "Feature",
  "properties": {
    "date:inception_lower":"1980-01-01",
    "date:inception_upper":"1980-01-31",
    "iso:country":"GB",
    "wof:name":"KA6 7DL",
    "wof:placetype":"postalcode"
},
  "geometry": {"coordinates":[-4.460599,55.430881],"type":"Point"}
}