{
  "type": "Feature",
  "properties": {
    "iso:country":"GB",
    "wof:name":"KA6 7DL",
    "wof:placetype":"postalcode"
},
  "geometry": {"coordinates":[-4.46059875405168,55.43088135120293],"type":"Point"}
}