{
  "type": "Feature",
  "properties": {
    "iso:country": "GB",
    "wof:name": "KA6 7DL",
    "wof:placetype": "postalcode"
  },
  "geometry": {"coordinates":[-4.460599,55.430881],"type":"Point"}
}
