{
  "type": "Feature",
  "properties": {
    "iso:country":"GB",
    "wof:name":"N9 8ER",
    "wof:placetype":"postalcode"
},
  "geometry": {"coordinates":[-0.04102401526611,51.63480000817352],"type":"Point"}
}