{
  "type": "Feature",
  "properties": {
    "iso:country": "GB",
    "wof:name": "FK14 7HQ",
    "wof:placetype": "postalcode"
  },
  "geometry": {"coordinates":[-3.685932,56.163275],"type":"Point"}
}
