{
  "type": "Feature",
  "properties": {
    "date:inception_lower": "1980-01-01",
    "date:inception_upper": "1980-01-01",
    "iso:country": "GB",
    "wof:name": "FK14 7HQ",
    "wof:placetype": "postalcode"
  },
  "geometry": {"coordinates":[-3.685932,56.163275],"type":"Point"}
}
