{
  "type": "Feature",
  "properties": {
    "iso:country":"GB",
    "wof:name":"E2 0NU",
    "wof:placetype":"postalcode"
},
  "geometry": {"coordinates":[-0.05307100619285,51.52989589745103],"type":"Point"}
}