{
  "type": "Feature",
  "properties": {
    "date:inception_lower": "2002-10-01",
    "date:inception_upper": "2002-10-01",
    "iso:country": "GB",
    "wof:name": "B45 8EZ",
    "wof:placetype": "postalcode"
  },
  "geometry": {"coordinates":[-2.012138,52.373282],"type":"Point"}
}
