{
  "type": "Feature",
  "properties": {
    "iso:country":"GB",
    "wof:name":"B45 8EZ",
    "wof:placetype":"postalcode"
},
  "geometry": {"coordinates":[-2.01226471478834,52.37327678764827],"type":"Point"}
}