{
  "type": "Feature",
  "properties": {
    "iso:country": "GB",
    "wof:name": "B45 8EZ",
    "wof:placetype": "postalcode"
  },
  "geometry": {"coordinates":[-2.012265,52.373277],"type":"Point"}
}
