{
  "type": "Feature",
  "properties": {
    "iso:country":"GB",
    "wof:name":"LS16 5RT",
    "wof:placetype":"postalcode"
},
  "geometry": {"coordinates":[-1.59061729884786,53.83057937668021],"type":"Point"}
}