{
  "type": "Feature",
  "properties": {
    "date:inception_lower": "2002-08-01",
    "date:inception_upper": "2002-08-01",
    "iso:country": "GB",
    "wof:name": "LS16 5RT",
    "wof:placetype": "postalcode"
  },
  "geometry": {"coordinates":[-1.590651,53.830613],"type":"Point"}
}
