{
  "type": "Feature",
  "properties": {
    "date:inception_lower":"2002-08-01",
    "date:inception_upper":"2002-08-31",
    "iso:country":"GB",
    "wof:name":"LS16 5RT",
    "wof:placetype":"postalcode"
},
  "geometry": {"coordinates":[-1.590617,53.830579],"type":"Point"}
}