{
  "type": "Feature",
  "properties": {
    "iso:country":"GB",
    "wof:name":"KT23 4EJ",
    "wof:placetype":"postalcode"
},
  "geometry": {"coordinates":[-0.39089311515511,51.27059466870344],"type":"Point"}
}