{
  "type": "Feature",
  "properties": {
    "date:inception_lower": "1980-01-01",
    "date:inception_upper": "1980-01-01",
    "iso:country": "GB",
    "wof:name": "KT23 4EJ",
    "wof:placetype": "postalcode"
  },
  "geometry": {"coordinates":[-0.390893,51.270595],"type":"Point"}
}
