{
  "type": "Feature",
  "properties": {
    "iso:country":"GB",
    "wof:name":"SS11 8XP",
    "wof:placetype":"postalcode"
},
  "geometry": {"coordinates":[0.5475739559366,51.60553215244153],"type":"Point"}
}