{
  "type": "Feature",
  "properties": {
    "iso:country":"GB",
    "wof:name":"E15 1QE",
    "wof:placetype":"postalcode"
},
  "geometry": {"coordinates":[-0.00060870755117,51.54693571790196],"type":"Point"}
}