{
  "type": "Feature",
  "properties": {
    "date:inception_lower": "2018-04-01",
    "date:inception_upper": "2018-04-01",
    "iso:country": "GB",
    "wof:name": "NR20 3FW",
    "wof:placetype": "postalcode"
  },
  "geometry": {"coordinates":[0.970242,52.682494],"type":"Point"}
}
