{
  "type": "Feature",
  "properties": {
    "iso:country": "GB",
    "wof:name": "DN15 6AS",
    "wof:placetype": "postalcode"
  },
  "geometry": {"coordinates":[-0.651379,53.598469],"type":"Point"}
}
