{
  "type": "Feature",
  "properties": {
    "iso:country":"GB",
    "wof:name":"TN6 2NF",
    "wof:placetype":"postalcode"
},
  "geometry": {"coordinates":[0.1816501174125,51.04487998788658],"type":"Point"}
}