{
  "type": "Feature",
  "properties": {
    "iso:country": "GB",
    "wof:name": "IP30 0PW",
    "wof:placetype": "postalcode"
  },
  "geometry": {"coordinates":[0.84848,52.177281],"type":"Point"}
}
