{
  "type": "Feature",
  "properties": {
    "iso:country":"GB",
    "wof:name":"L20 4EH",
    "wof:placetype":"postalcode"
},
  "geometry": {"coordinates":[-2.99995769345221,53.45402661370915],"type":"Point"}
}