{
  "type": "Feature",
  "properties": {
    "iso:country":"GB",
    "wof:name":"AB51 8ZH",
    "wof:placetype":"postalcode"
},
  "geometry": {"coordinates":[-2.46507831385831,57.41094776250867],"type":"Point"}
}