{
  "type": "Feature",
  "properties": {
    "iso:country": "GB",
    "wof:name": "SS3 0BL",
    "wof:placetype": "postalcode"
  },
  "geometry": {"coordinates":[0.802225,51.551866],"type":"Point"}
}
