{
  "type": "Feature",
  "properties": {
    "iso:country":"GB",
    "wof:name":"SS3 0BL",
    "wof:placetype":"postalcode"
},
  "geometry": {"coordinates":[0.80217939555405,51.55185352070048],"type":"Point"}
}