{
  "type": "Feature",
  "properties": {
    "date:inception_lower":"1980-01-01",
    "date:inception_upper":"1980-01-31",
    "iso:country":"GB",
    "wof:name":"SK15 3EQ",
    "wof:placetype":"postalcode"
},
  "geometry": {"coordinates":[-2.033764,53.486783],"type":"Point"}
}