{
  "type": "Feature",
  "properties": {
    "iso:country": "GB",
    "wof:name": "NR32 1PH",
    "wof:placetype": "postalcode"
  },
  "geometry": {"coordinates":[1.751754,52.477879],"type":"Point"}
}
