{
  "type": "Feature",
  "properties": {
    "date:inception_lower": "1980-01-01",
    "date:inception_upper": "1980-01-01",
    "iso:country": "GB",
    "wof:name": "DG11 3EY",
    "wof:placetype": "postalcode"
  },
  "geometry": {"coordinates":[-3.181266,55.087231],"type":"Point"}
}
