{
  "type": "Feature",
  "properties": {
    "iso:country": "GB",
    "wof:name": "DG11 3EY",
    "wof:placetype": "postalcode"
  },
  "geometry": {"coordinates":[-3.180551,55.087435],"type":"Point"}
}
