{
  "type": "Feature",
  "properties": {
    "iso:country":"GB",
    "wof:name":"DG11 3EY",
    "wof:placetype":"postalcode"
},
  "geometry": {"coordinates":[-3.18054915231152,55.08743028903063],"type":"Point"}
}