{
  "type": "Feature",
  "properties": {
    "date:inception_lower": "2020-10-01",
    "date:inception_upper": "2020-10-01",
    "iso:country": "GB",
    "wof:name": "CA9 3XZ",
    "wof:placetype": "postalcode"
  },
  "geometry": {"coordinates":[-2.438213,54.81216],"type":"Point"}
}
