{
  "type": "Feature",
  "properties": {
    "date:inception_lower": "2020-02-01",
    "date:inception_upper": "2020-02-01",
    "iso:country": "GB",
    "wof:name": "DL14 7AH",
    "wof:placetype": "postalcode"
  },
  "geometry": {"coordinates":[-1.675493,54.662994],"type":"Point"}
}
