{
  "type": "Feature",
  "properties": {
    "iso:country":"GB",
    "wof:name":"WA3 4PE",
    "wof:placetype":"postalcode"
},
  "geometry": {"coordinates":[-2.53194183802374,53.45363031736743],"type":"Point"}
}