{
  "type": "Feature",
  "properties": {
    "date:inception_lower": "2014-02-01",
    "date:inception_upper": "2014-02-01",
    "iso:country": "GB",
    "wof:name": "PL15 8WH",
    "wof:placetype": "postalcode"
  },
  "geometry": {"coordinates":[-4.366826,50.640626],"type":"Point"}
}
