{
  "type": "Feature",
  "properties": {
    "iso:country":"GB",
    "wof:name":"PL15 8WH",
    "wof:placetype":"postalcode"
},
  "geometry": {"coordinates":[-4.36676741069538,50.64064456264407],"type":"Point"}
}