{
  "type": "Feature",
  "properties": {
    "date:inception_lower": "1997-12-01",
    "date:inception_upper": "1997-12-01",
    "iso:country": "GB",
    "wof:name": "BS20 7TQ",
    "wof:placetype": "postalcode"
  },
  "geometry": {"coordinates":[-2.722517,51.475645],"type":"Point"}
}
