{
  "type": "Feature",
  "properties": {
    "iso:country": "GB",
    "wof:name": "B96 6EA",
    "wof:placetype": "postalcode"
  },
  "geometry": {"coordinates":[-1.937331,52.263419],"type":"Point"}
}
