{
  "type": "Feature",
  "properties": {
    "date:inception_lower": "2005-07-01",
    "date:inception_upper": "2005-07-01",
    "iso:country": "GB",
    "wof:name": "TN20 6PH",
    "wof:placetype": "postalcode"
  },
  "geometry": {"coordinates":[0.262208,51.02159],"type":"Point"}
}
