{
  "type": "Feature",
  "properties": {
    "iso:country": "GB",
    "wof:name": "SY22 5HA",
    "wof:placetype": "postalcode"
  },
  "geometry": {"coordinates":[-3.280312,52.791522],"type":"Point"}
}
