{
  "type": "Feature",
  "properties": {
    "iso:country":"GB",
    "wof:name":"PR5 0UD",
    "wof:placetype":"postalcode"
},
  "geometry": {"coordinates":[-2.62250281169057,53.76363389960571],"type":"Point"}
}