{
  "type": "Feature",
  "properties": {
    "iso:country": "GB",
    "wof:name": "TR14 0FR",
    "wof:placetype": "postalcode"
  },
  "geometry": {"coordinates":[-5.282088,50.233387],"type":"Point"}
}
