{
  "type": "Feature",
  "properties": {
    "date:inception_lower":"1980-01-01",
    "date:inception_upper":"1980-01-31",
    "iso:country":"GB",
    "wof:name":"LE15 8RX",
    "wof:placetype":"postalcode"
},
  "geometry": {"coordinates":[-0.682824,52.617999],"type":"Point"}
}