{
  "type": "Feature",
  "properties": {
    "iso:country":"GB",
    "wof:name":"YO24 4HN",
    "wof:placetype":"postalcode"
},
  "geometry": {"coordinates":[-1.11823531136715,53.95228154419785],"type":"Point"}
}