{
  "type": "Feature",
  "properties": {
    "iso:country": "GB",
    "wof:name": "G83 9AU",
    "wof:placetype": "postalcode"
  },
  "geometry": {"coordinates":[-4.568239,55.98638],"type":"Point"}
}
