{
  "type": "Feature",
  "properties": {
    "iso:country":"GB",
    "wof:name":"LS15 9EW",
    "wof:placetype":"postalcode"
},
  "geometry": {"coordinates":[-1.44001762854657,53.79178101700283],"type":"Point"}
}