{
  "type": "Feature",
  "properties": {
    "date:inception_lower": "1985-04-01",
    "date:inception_upper": "1985-04-01",
    "iso:country": "GB",
    "wof:name": "LS15 9EW",
    "wof:placetype": "postalcode"
  },
  "geometry": {"coordinates":[-1.440018,53.791781],"type":"Point"}
}
