{
  "type": "Feature",
  "properties": {
    "iso:country":"GB",
    "wof:name":"LS12 5TN",
    "wof:placetype":"postalcode"
},
  "geometry": {"coordinates":[-1.62121631844824,53.77843254849952],"type":"Point"}
}