{
  "type": "Feature",
  "properties": {
    "iso:country":"GB",
    "wof:name":"KT3 5PF",
    "wof:placetype":"postalcode"
},
  "geometry": {"coordinates":[-0.25969794314327,51.38611673433969],"type":"Point"}
}