{
  "type": "Feature",
  "properties": {
    "iso:country": "GB",
    "wof:name": "RG26 3SE",
    "wof:placetype": "postalcode"
  },
  "geometry": {"coordinates":[-1.130608,51.35044],"type":"Point"}
}
