{
  "type": "Feature",
  "properties": {
    "iso:country":"GB",
    "wof:name":"HP7 9QW",
    "wof:placetype":"postalcode"
},
  "geometry": {"coordinates":[-0.57129199557378,51.66604417901588],"type":"Point"}
}