{
  "type": "Feature",
  "properties": {
    "iso:country": "GB",
    "wof:name": "GU34 1GN",
    "wof:placetype": "postalcode"
  },
  "geometry": {"coordinates":[-0.989723,51.150401],"type":"Point"}
}
