{
  "type": "Feature",
  "properties": {
    "date:inception_lower": "2019-05-01",
    "date:inception_upper": "2019-05-01",
    "iso:country": "GB",
    "wof:name": "GU34 1GN",
    "wof:placetype": "postalcode"
  },
  "geometry": {"coordinates":[-0.991126,51.150332],"type":"Point"}
}
