{
  "type": "Feature",
  "properties": {
    "date:inception_lower": "2016-01-01",
    "date:inception_upper": "2016-01-01",
    "iso:country": "GB",
    "wof:name": "SA63 4WA",
    "wof:placetype": "postalcode"
  },
  "geometry": {"coordinates":[-4.880711,51.850452],"type":"Point"}
}
