{
  "type": "Feature",
  "properties": {
    "iso:country": "GB",
    "wof:name": "SA63 4WA",
    "wof:placetype": "postalcode"
  },
  "geometry": {"coordinates":[-4.880704,51.850344],"type":"Point"}
}
