{
  "type": "Feature",
  "properties": {
    "iso:country":"GB",
    "wof:name":"SA63 4WA",
    "wof:placetype":"postalcode"
},
  "geometry": {"coordinates":[-4.8807401878031,51.85045522544247],"type":"Point"}
}