{
  "type": "Feature",
  "properties": {
    "iso:country":"GB",
    "wof:name":"BS34 7AD",
    "wof:placetype":"postalcode"
},
  "geometry": {"coordinates":[-2.57326970307083,51.51217694690727],"type":"Point"}
}