{
  "type": "Feature",
  "properties": {
    "date:inception_lower": "1997-12-01",
    "date:inception_upper": "1997-12-01",
    "iso:country": "GB",
    "wof:name": "BS34 7AD",
    "wof:placetype": "postalcode"
  },
  "geometry": {"coordinates":[-2.57327,51.512177],"type":"Point"}
}
