{
  "type": "Feature",
  "properties": {
    "iso:country":"GB",
    "wof:name":"N1 1BH",
    "wof:placetype":"postalcode"
},
  "geometry": {"coordinates":[-0.11400363894936,51.54094502844067],"type":"Point"}
}