{
  "type": "Feature",
  "properties": {
    "date:inception_lower":"1982-03-01",
    "date:inception_upper":"1982-03-31",
    "iso:country":"GB",
    "wof:name":"CV11 6UB",
    "wof:placetype":"postalcode"
},
  "geometry": {"coordinates":[-1.425052,52.504809],"type":"Point"}
}