{
  "type": "Feature",
  "properties": {
    "iso:country": "GB",
    "wof:name": "CV11 6UB",
    "wof:placetype": "postalcode"
  },
  "geometry": {"coordinates":[-1.425052,52.504809],"type":"Point"}
}
