{
  "type": "Feature",
  "properties": {
    "iso:country": "GB",
    "wof:name": "EH12 8TL",
    "wof:placetype": "postalcode"
  },
  "geometry": {"coordinates":[-3.297638,55.953193],"type":"Point"}
}
