{
  "type": "Feature",
  "properties": {
    "iso:country": "GB",
    "wof:name": "LE17 4AT",
    "wof:placetype": "postalcode"
  },
  "geometry": {"coordinates":[-1.199854,52.454981],"type":"Point"}
}
