{
  "type": "Feature",
  "properties": {
    "iso:country":"GB",
    "wof:name":"BA2 1HF",
    "wof:placetype":"postalcode"
},
  "geometry": {"coordinates":[-2.38966146022477,51.36919119949717],"type":"Point"}
}