{
  "type": "Feature",
  "properties": {
    "date:inception_lower": "2017-10-01",
    "date:inception_upper": "2017-10-01",
    "iso:country": "GB",
    "wof:name": "TN12 9GF",
    "wof:placetype": "postalcode"
  },
  "geometry": {"coordinates":[0.495151,51.170256],"type":"Point"}
}
