{
  "type": "Feature",
  "properties": {
    "iso:country": "GB",
    "wof:name": "CO4 3AR",
    "wof:placetype": "postalcode"
  },
  "geometry": {"coordinates":[0.925229,51.892755],"type":"Point"}
}
