{
  "type": "Feature",
  "properties": {
    "iso:country": "GB",
    "wof:name": "HP1 1GN",
    "wof:placetype": "postalcode"
  },
  "geometry": {"coordinates":[-0.471873,51.751095],"type":"Point"}
}
