{
  "type": "Feature",
  "properties": {
    "iso:country":"GB",
    "wof:name":"HP1 1GN",
    "wof:placetype":"postalcode"
},
  "geometry": {"coordinates":[-0.47189534205796,51.75107918284336],"type":"Point"}
}