{
  "type": "Feature",
  "properties": {
    "date:inception_lower":"2015-08-01",
    "date:inception_upper":"2015-08-31",
    "iso:country":"GB",
    "wof:name":"HP1 1GN",
    "wof:placetype":"postalcode"
},
  "geometry": {"coordinates":[-0.471873,51.751095],"type":"Point"}
}