{
  "type": "Feature",
  "properties": {
    "iso:country": "GB",
    "wof:name": "SN1 2PN",
    "wof:placetype": "postalcode"
  },
  "geometry": {"coordinates":[-1.757878,51.571972],"type":"Point"}
}
