{
  "type": "Feature",
  "properties": {
    "iso:country":"GB",
    "wof:name":"BH9 3JL",
    "wof:placetype":"postalcode"
},
  "geometry": {"coordinates":[-1.86740615497757,50.75787688748784],"type":"Point"}
}