{
  "type": "Feature",
  "properties": {
    "iso:country":"GB",
    "wof:name":"HP4 3LH",
    "wof:placetype":"postalcode"
},
  "geometry": {"coordinates":[-0.58005583678387,51.76168803164771],"type":"Point"}
}