{
  "type": "Feature",
  "properties": {
    "iso:country":"GB",
    "wof:name":"TQ3 3LG",
    "wof:placetype":"postalcode"
},
  "geometry": {"coordinates":[-3.57565055043071,50.43479631291346],"type":"Point"}
}