{
  "type": "Feature",
  "properties": {
    "iso:country":"GB",
    "wof:name":"DY1 2TD",
    "wof:placetype":"postalcode"
},
  "geometry": {"coordinates":[-2.09871496954483,52.51467593757356],"type":"Point"}
}