{
  "type": "Feature",
  "properties": {
    "iso:country":"GB",
    "wof:name":"WS6 7HU",
    "wof:placetype":"postalcode"
},
  "geometry": {"coordinates":[-2.0446789112489,52.65868935531687],"type":"Point"}
}