{
  "type": "Feature",
  "properties": {
    "iso:country":"GB",
    "wof:name":"KT16 0NP",
    "wof:placetype":"postalcode"
},
  "geometry": {"coordinates":[-0.53678881102689,51.3638355893593],"type":"Point"}
}