{
  "type": "Feature",
  "properties": {
    "iso:country": "GB",
    "wof:name": "KT16 0NP",
    "wof:placetype": "postalcode"
  },
  "geometry": {"coordinates":[-0.536789,51.363836],"type":"Point"}
}
