{
  "type": "Feature",
  "properties": {
    "iso:country":"GB",
    "wof:name":"NW10 8SG",
    "wof:placetype":"postalcode"
},
  "geometry": {"coordinates":[-0.25096540675506,51.53884945364478],"type":"Point"}
}