{
  "type": "Feature",
  "properties": {
    "iso:country":"GB",
    "wof:name":"FY4 3LX",
    "wof:placetype":"postalcode"
},
  "geometry": {"coordinates":[-3.02552202664804,53.78796286025901],"type":"Point"}
}