{
  "type": "Feature",
  "properties": {
    "iso:country":"GB",
    "wof:name":"UB6 0LN",
    "wof:placetype":"postalcode"
},
  "geometry": {"coordinates":[-0.32923811203349,51.55534001224829],"type":"Point"}
}