{
  "type": "Feature",
  "properties": {
    "iso:country":"GB",
    "wof:name":"SL3 0FE",
    "wof:placetype":"postalcode"
},
  "geometry": {"coordinates":[-0.50563967364013,51.48576412213526],"type":"Point"}
}