{
  "type": "Feature",
  "properties": {
    "date:inception_lower":"2009-03-01",
    "date:inception_upper":"2009-03-31",
    "iso:country":"GB",
    "wof:name":"SL3 0FE",
    "wof:placetype":"postalcode"
},
  "geometry": {"coordinates":[-0.50564,51.485764],"type":"Point"}
}