{
  "type": "Feature",
  "properties": {
    "iso:country":"GB",
    "wof:name":"TS25 5PY",
    "wof:placetype":"postalcode"
},
  "geometry": {"coordinates":[-1.23197037126313,54.67331547352723],"type":"Point"}
}