{
  "type": "Feature",
  "properties": {
    "iso:country":"GB",
    "wof:name":"B23 7BY",
    "wof:placetype":"postalcode"
},
  "geometry": {"coordinates":[-1.86419728100639,52.5287808301764],"type":"Point"}
}