{
  "type": "Feature",
  "properties": {
    "iso:country":"GB",
    "wof:name":"SW19 6BJ",
    "wof:placetype":"postalcode"
},
  "geometry": {"coordinates":[-0.21883087913922,51.44588763702941],"type":"Point"}
}