{
  "type": "Feature",
  "properties": {
    "iso:country": "GB",
    "wof:name": "EX17 6QL",
    "wof:placetype": "postalcode"
  },
  "geometry": {"coordinates":[-3.803974,50.862509],"type":"Point"}
}
