{
  "type": "Feature",
  "properties": {
    "iso:country":"GB",
    "wof:name":"HA4 9PS",
    "wof:placetype":"postalcode"
},
  "geometry": {"coordinates":[-0.39124315987514,51.57191580589338],"type":"Point"}
}