{
  "type": "Feature",
  "properties": {
    "date:inception_lower":"1980-01-01",
    "date:inception_upper":"1980-01-31",
    "iso:country":"GB",
    "wof:name":"HA4 9PS",
    "wof:placetype":"postalcode"
},
  "geometry": {"coordinates":[-0.391243,51.571916],"type":"Point"}
}