{
  "type": "Feature",
  "properties": {
    "iso:country":"GB",
    "wof:name":"BB10 3QX",
    "wof:placetype":"postalcode"
},
  "geometry": {"coordinates":[-2.17062681589681,53.8142399330811],"type":"Point"}
}