{
  "type": "Feature",
  "properties": {
    "iso:country":"GB",
    "wof:name":"CW1 5UA",
    "wof:placetype":"postalcode"
},
  "geometry": {"coordinates":[-2.3924865041377,53.10402937101043],"type":"Point"}
}