{
  "type": "Feature",
  "properties": {
    "iso:country":"GB",
    "wof:name":"IP1 6NT",
    "wof:placetype":"postalcode"
},
  "geometry": {"coordinates":[1.13926144752142,52.08261174569512],"type":"Point"}
}