{
  "type": "Feature",
  "properties": {
    "iso:country":"GB",
    "wof:name":"PO20 2HB",
    "wof:placetype":"postalcode"
},
  "geometry": {"coordinates":[-0.71857010677234,50.84923505666082],"type":"Point"}
}