{
  "type": "Feature",
  "properties": {
    "iso:country": "GB",
    "wof:name": "PO20 2HB",
    "wof:placetype": "postalcode"
  },
  "geometry": {"coordinates":[-0.71857,50.849235],"type":"Point"}
}
