{
  "type": "Feature",
  "properties": {
    "iso:country": "GB",
    "wof:name": "BB7 9DH",
    "wof:placetype": "postalcode"
  },
  "geometry": {"coordinates":[-2.392945,53.840241],"type":"Point"}
}
