{
  "type": "Feature",
  "properties": {
    "date:inception_lower": "1980-01-01",
    "date:inception_upper": "1980-01-01",
    "iso:country": "GB",
    "wof:name": "NW2 1NJ",
    "wof:placetype": "postalcode"
  },
  "geometry": {"coordinates":[-0.215081,51.564845],"type":"Point"}
}
