{
  "type": "Feature",
  "properties": {
    "iso:country":"GB",
    "wof:name":"NW2 1NJ",
    "wof:placetype":"postalcode"
},
  "geometry": {"coordinates":[-0.21508070221214,51.56484545960799],"type":"Point"}
}