{
  "type": "Feature",
  "properties": {
    "iso:country": "GB",
    "wof:name": "AB43 9PZ",
    "wof:placetype": "postalcode"
  },
  "geometry": {"coordinates":[-2.022643,57.684071],"type":"Point"}
}
