{
  "type": "Feature",
  "properties": {
    "iso:country":"GB",
    "wof:name":"PL26 8AW",
    "wof:placetype":"postalcode"
},
  "geometry": {"coordinates":[-4.88134726799868,50.3821481967015],"type":"Point"}
}