{
  "type": "Feature",
  "properties": {
    "iso:country": "GB",
    "wof:name": "TN27 8ND",
    "wof:placetype": "postalcode"
  },
  "geometry": {"coordinates":[0.694372,51.150987],"type":"Point"}
}
