{
  "type": "Feature",
  "properties": {
    "date:inception_lower": "1980-01-01",
    "date:inception_upper": "1980-01-01",
    "iso:country": "GB",
    "wof:name": "WV16 5BA",
    "wof:placetype": "postalcode"
  },
  "geometry": {"coordinates":[-2.43424,52.536278],"type":"Point"}
}
