{
  "type": "Feature",
  "properties": {
    "date:inception_lower": "1995-01-01",
    "date:inception_upper": "1995-01-01",
    "iso:country": "GB",
    "wof:name": "L35 7LX",
    "wof:placetype": "postalcode"
  },
  "geometry": {"coordinates":[-2.783696,53.426554],"type":"Point"}
}
