{
  "type": "Feature",
  "properties": {
    "iso:country": "GB",
    "wof:name": "PO19 7HB",
    "wof:placetype": "postalcode"
  },
  "geometry": {"coordinates":[-0.762892,50.840612],"type":"Point"}
}
