{
  "type": "Feature",
  "properties": {
    "iso:country":"GB",
    "wof:name":"PO19 7HB",
    "wof:placetype":"postalcode"
},
  "geometry": {"coordinates":[-0.7628919383778,50.84061243907772],"type":"Point"}
}