{
  "type": "Feature",
  "properties": {
    "date:inception_lower": "1994-12-01",
    "date:inception_upper": "1994-12-01",
    "iso:country": "GB",
    "wof:name": "SO19 9HS",
    "wof:placetype": "postalcode"
  },
  "geometry": {"coordinates":[-1.353422,50.891851],"type":"Point"}
}
