{
  "type": "Feature",
  "properties": {
    "iso:country": "GB",
    "wof:name": "SO19 9HS",
    "wof:placetype": "postalcode"
  },
  "geometry": {"coordinates":[-1.353422,50.891851],"type":"Point"}
}
