{
  "type": "Feature",
  "properties": {
    "date:inception_lower":"1993-08-01",
    "date:inception_upper":"1993-08-31",
    "iso:country":"GB",
    "wof:name":"NN11 3BY",
    "wof:placetype":"postalcode"
},
  "geometry": {"coordinates":[-1.19404,52.219231],"type":"Point"}
}