{
  "type": "Feature",
  "properties": {
    "iso:country": "GB",
    "wof:name": "NN11 3BY",
    "wof:placetype": "postalcode"
  },
  "geometry": {"coordinates":[-1.19404,52.219231],"type":"Point"}
}
