{
  "type": "Feature",
  "properties": {
    "date:inception_lower": "1980-01-01",
    "date:inception_upper": "1980-01-01",
    "iso:country": "GB",
    "wof:name": "EX22 7AA",
    "wof:placetype": "postalcode"
  },
  "geometry": {"coordinates":[-4.244543,50.825445],"type":"Point"}
}
