{
  "type": "Feature",
  "properties": {
    "iso:country":"GB",
    "wof:name":"EX22 7AA",
    "wof:placetype":"postalcode"
},
  "geometry": {"coordinates":[-4.24454254820076,50.82544504568824],"type":"Point"}
}