{
  "type": "Feature",
  "properties": {
    "iso:country": "GB",
    "wof:name": "EX22 7AA",
    "wof:placetype": "postalcode"
  },
  "geometry": {"coordinates":[-4.244543,50.825445],"type":"Point"}
}
