{
  "type": "Feature",
  "properties": {
    "iso:country":"GB",
    "wof:name":"MK41 0FL",
    "wof:placetype":"postalcode"
},
  "geometry": {"coordinates":[-0.41626047136498,52.15638482658574],"type":"Point"}
}