{
  "type": "Feature",
  "properties": {
    "date:inception_lower": "2014-03-01",
    "date:inception_upper": "2014-03-01",
    "iso:country": "GB",
    "wof:name": "MK41 0FL",
    "wof:placetype": "postalcode"
  },
  "geometry": {"coordinates":[-0.41626,52.156385],"type":"Point"}
}
