{
  "type": "Feature",
  "properties": {
    "iso:country":"GB",
    "wof:name":"DN34 4TS",
    "wof:placetype":"postalcode"
},
  "geometry": {"coordinates":[-0.09716166744937,53.56073040866978],"type":"Point"}
}