{
  "type": "Feature",
  "properties": {
    "iso:country": "GB",
    "wof:name": "DN34 4TS",
    "wof:placetype": "postalcode"
  },
  "geometry": {"coordinates":[-0.097162,53.56073],"type":"Point"}
}
