{
  "type": "Feature",
  "properties": {
    "date:inception_lower":"1997-06-01",
    "date:inception_upper":"1997-06-30",
    "iso:country":"GB",
    "wof:name":"LS4 2BE",
    "wof:placetype":"postalcode"
},
  "geometry": {"coordinates":[-1.578625,53.803799],"type":"Point"}
}