{
  "type": "Feature",
  "properties": {
    "iso:country":"GB",
    "wof:name":"LS4 2BE",
    "wof:placetype":"postalcode"
},
  "geometry": {"coordinates":[-1.57862456662761,53.80379858383255],"type":"Point"}
}