{
  "type": "Feature",
  "properties": {
    "iso:country": "GB",
    "wof:name": "LS4 2BE",
    "wof:placetype": "postalcode"
  },
  "geometry": {"coordinates":[-1.578625,53.803799],"type":"Point"}
}
