{
  "type": "Feature",
  "properties": {
    "date:inception_lower": "2023-05-01",
    "date:inception_upper": "2023-05-01",
    "iso:country": "GB",
    "wof:name": "TN23 3UR",
    "wof:placetype": "postalcode"
  },
  "geometry": {"coordinates":[0.843655,51.125315],"type":"Point"}
}
