{
  "type": "Feature",
  "properties": {
    "iso:country": "GB",
    "wof:name": "TA4 3DZ",
    "wof:placetype": "postalcode"
  },
  "geometry": {"coordinates":[-3.177662,51.085418],"type":"Point"}
}
