{
  "type": "Feature",
  "properties": {
    "iso:country":"GB",
    "wof:name":"TA4 3DZ",
    "wof:placetype":"postalcode"
},
  "geometry": {"coordinates":[-3.1776622947673,51.08541839697572],"type":"Point"}
}