{
  "type": "Feature",
  "properties": {
    "iso:country":"GB",
    "wof:name":"DL4 1DR",
    "wof:placetype":"postalcode"
},
  "geometry": {"coordinates":[-1.64505396758832,54.6342312600306],"type":"Point"}
}