{
  "type": "Feature",
  "properties": {
    "iso:country": "GB",
    "wof:name": "HR3 5EH",
    "wof:placetype": "postalcode"
  },
  "geometry": {"coordinates":[-3.124563,52.070932],"type":"Point"}
}
