{
  "type": "Feature",
  "properties": {
    "iso:country":"GB",
    "wof:name":"HR3 5EH",
    "wof:placetype":"postalcode"
},
  "geometry": {"coordinates":[-3.12456319763729,52.07093211707153],"type":"Point"}
}