{
  "type": "Feature",
  "properties": {
    "date:inception_lower": "1981-09-01",
    "date:inception_upper": "1981-09-01",
    "iso:country": "GB",
    "wof:name": "HR3 5EH",
    "wof:placetype": "postalcode"
  },
  "geometry": {"coordinates":[-3.124563,52.070932],"type":"Point"}
}
