{
  "type": "Feature",
  "properties": {
    "iso:country":"GB",
    "wof:name":"NG31 9UL",
    "wof:placetype":"postalcode"
},
  "geometry": {"coordinates":[-0.6081165404695,52.92039456966945],"type":"Point"}
}