{
  "type": "Feature",
  "properties": {
    "iso:country":"GB",
    "wof:name":"SE19 2UE",
    "wof:placetype":"postalcode"
},
  "geometry": {"coordinates":[-0.08380190506971,51.41597974337633],"type":"Point"}
}