{
  "type": "Feature",
  "properties": {
    "iso:country": "GB",
    "wof:name": "SE19 2UE",
    "wof:placetype": "postalcode"
  },
  "geometry": {"coordinates":[-0.083802,51.41598],"type":"Point"}
}
