{
  "type": "Feature",
  "properties": {
    "date:inception_lower": "1980-01-01",
    "date:inception_upper": "1980-01-01",
    "iso:country": "GB",
    "wof:name": "RM12 6RT",
    "wof:placetype": "postalcode"
  },
  "geometry": {"coordinates":[0.21487,51.549837],"type":"Point"}
}
