{
  "type": "Feature",
  "properties": {
    "iso:country":"GB",
    "wof:name":"BB18 6RJ",
    "wof:placetype":"postalcode"
},
  "geometry": {"coordinates":[-2.13581737733268,53.91753701100839],"type":"Point"}
}