{
  "type": "Feature",
  "properties": {
    "iso:country":"GB",
    "wof:name":"UB8 1LE",
    "wof:placetype":"postalcode"
},
  "geometry": {"coordinates":[-0.47415181646307,51.54409545003978],"type":"Point"}
}