{
  "type": "Feature",
  "properties": {
    "iso:country":"GB",
    "wof:name":"DY1 3NG",
    "wof:placetype":"postalcode"
},
  "geometry": {"coordinates":[-2.10209991711333,52.52552386793692],"type":"Point"}
}