{
  "type": "Feature",
  "properties": {
    "iso:country":"GB",
    "wof:name":"TR18 4PF",
    "wof:placetype":"postalcode"
},
  "geometry": {"coordinates":[-5.54732862531073,50.11014658619506],"type":"Point"}
}