{
  "type": "Feature",
  "properties": {
    "iso:country":"GB",
    "wof:name":"EN2 0HQ",
    "wof:placetype":"postalcode"
},
  "geometry": {"coordinates":[-0.08370935622371,51.66706776095542],"type":"Point"}
}