{
  "type": "Feature",
  "properties": {
    "iso:country":"GB",
    "wof:name":"CH61 5XX",
    "wof:placetype":"postalcode"
},
  "geometry": {"coordinates":[-3.0954886661115,53.34077174514581],"type":"Point"}
}