{
  "type": "Feature",
  "properties": {
    "iso:country": "GB",
    "wof:name": "DL1 4BJ",
    "wof:placetype": "postalcode"
  },
  "geometry": {"coordinates":[-1.540828,54.51831],"type":"Point"}
}
