{
  "type": "Feature",
  "properties": {
    "iso:country":"GB",
    "wof:name":"DL1 4BJ",
    "wof:placetype":"postalcode"
},
  "geometry": {"coordinates":[-1.54082846243426,54.5183099093662],"type":"Point"}
}