{
  "type": "Feature",
  "properties": {
    "date:inception_lower": "1980-01-01",
    "date:inception_upper": "1980-01-01",
    "iso:country": "GB",
    "wof:name": "DL1 4BJ",
    "wof:placetype": "postalcode"
  },
  "geometry": {"coordinates":[-1.540828,54.51831],"type":"Point"}
}
