{
  "type": "Feature",
  "properties": {
    "iso:country": "GB",
    "wof:name": "KY12 8PZ",
    "wof:placetype": "postalcode"
  },
  "geometry": {"coordinates":[-3.507688,56.064804],"type":"Point"}
}
