{
  "type": "Feature",
  "properties": {
    "iso:country":"GB",
    "wof:name":"ST6 4HB",
    "wof:placetype":"postalcode"
},
  "geometry": {"coordinates":[-2.20154442171511,53.05390677574301],"type":"Point"}
}