{
  "type": "Feature",
  "properties": {
    "iso:country": "GB",
    "wof:name": "NR33 7NP",
    "wof:placetype": "postalcode"
  },
  "geometry": {"coordinates":[1.718276,52.447122],"type":"Point"}
}
