{
  "type": "Feature",
  "properties": {
    "date:inception_lower": "1980-01-01",
    "date:inception_upper": "1980-01-01",
    "iso:country": "GB",
    "wof:name": "SM1 3DZ",
    "wof:placetype": "postalcode"
  },
  "geometry": {"coordinates":[-0.186099,51.375963],"type":"Point"}
}
