{
  "type": "Feature",
  "properties": {
    "date:inception_lower":"1998-12-01",
    "date:inception_upper":"1998-12-31",
    "iso:country":"GB",
    "wof:name":"TF2 9UZ",
    "wof:placetype":"postalcode"
},
  "geometry": {"coordinates":[-2.435638,52.698107],"type":"Point"}
}