{
  "type": "Feature",
  "properties": {
    "iso:country": "GB",
    "wof:name": "TF2 9UZ",
    "wof:placetype": "postalcode"
  },
  "geometry": {"coordinates":[-2.435638,52.698107],"type":"Point"}
}
