{
  "type": "Feature",
  "properties": {
    "iso:country":"GB",
    "wof:name":"TF2 9UZ",
    "wof:placetype":"postalcode"
},
  "geometry": {"coordinates":[-2.43563767672166,52.69810729761875],"type":"Point"}
}