{
  "type": "Feature",
  "properties": {
    "date:inception_lower":"1980-01-01",
    "date:inception_upper":"1980-01-31",
    "iso:country":"GB",
    "wof:name":"CA18 1RN",
    "wof:placetype":"postalcode"
},
  "geometry": {"coordinates":[-3.364612,54.346219],"type":"Point"}
}