{
  "type": "Feature",
  "properties": {
    "iso:country": "GB",
    "wof:name": "RG29 1EW",
    "wof:placetype": "postalcode"
  },
  "geometry": {"coordinates":[-0.952251,51.259528],"type":"Point"}
}
