{
  "type": "Feature",
  "properties": {
    "iso:country": "GB",
    "wof:name": "WN4 0BD",
    "wof:placetype": "postalcode"
  },
  "geometry": {"coordinates":[-2.655205,53.500909],"type":"Point"}
}
