{
  "type": "Feature",
  "properties": {
    "iso:country":"GB",
    "wof:name":"WN4 0BD",
    "wof:placetype":"postalcode"
},
  "geometry": {"coordinates":[-2.65520455188156,53.50090899430511],"type":"Point"}
}