{
  "type": "Feature",
  "properties": {
    "date:inception_lower": "1980-01-01",
    "date:inception_upper": "1980-01-01",
    "iso:country": "GB",
    "wof:name": "LE12 5RB",
    "wof:placetype": "postalcode"
  },
  "geometry": {"coordinates":[-1.254598,52.830658],"type":"Point"}
}
