{
  "type": "Feature",
  "properties": {
    "iso:country":"GB",
    "wof:name":"LE12 5RB",
    "wof:placetype":"postalcode"
},
  "geometry": {"coordinates":[-1.25459774334625,52.83065781740537],"type":"Point"}
}