{
  "type": "Feature",
  "properties": {
    "date:inception_lower": "1991-09-01",
    "date:inception_upper": "1991-09-01",
    "iso:country": "GB",
    "wof:name": "FY5 3HT",
    "wof:placetype": "postalcode"
  },
  "geometry": {"coordinates":[-3.035133,53.866933],"type":"Point"}
}
