{
  "type": "Feature",
  "properties": {
    "iso:country":"GB",
    "wof:name":"FY5 3HT",
    "wof:placetype":"postalcode"
},
  "geometry": {"coordinates":[-3.03513297986897,53.86693283527809],"type":"Point"}
}