{
  "type": "Feature",
  "properties": {
    "date:inception_lower": "2001-12-01",
    "date:inception_upper": "2001-12-01",
    "iso:country": "GB",
    "wof:name": "BS34 8RE",
    "wof:placetype": "postalcode"
  },
  "geometry": {"coordinates":[-2.533953,51.515411],"type":"Point"}
}
