{
  "type": "Feature",
  "properties": {
    "iso:country":"GB",
    "wof:name":"CB6 3RW",
    "wof:placetype":"postalcode"
},
  "geometry": {"coordinates":[0.17855168428209,52.35115768087198],"type":"Point"}
}