{
  "type": "Feature",
  "properties": {
    "iso:country":"GB",
    "wof:name":"HU6 9TN",
    "wof:placetype":"postalcode"
},
  "geometry": {"coordinates":[-0.3866304397944,53.78670401385789],"type":"Point"}
}