{
  "type": "Feature",
  "properties": {
    "iso:country":"GB",
    "wof:name":"W3 7DH",
    "wof:placetype":"postalcode"
},
  "geometry": {"coordinates":[-0.24970008072262,51.51469507177769],"type":"Point"}
}