{
  "type": "Feature",
  "properties": {
    "date:inception_lower": "1980-01-01",
    "date:inception_upper": "1980-01-01",
    "iso:country": "GB",
    "wof:name": "TN38 9HE",
    "wof:placetype": "postalcode"
  },
  "geometry": {"coordinates":[0.546052,50.880658],"type":"Point"}
}
