{
  "type": "Feature",
  "properties": {
    "iso:country":"GB",
    "wof:name":"TN38 9HE",
    "wof:placetype":"postalcode"
},
  "geometry": {"coordinates":[0.54605168115411,50.88065793533667],"type":"Point"}
}