{
  "type": "Feature",
  "properties": {
    "iso:country": "GB",
    "wof:name": "EH27 8BH",
    "wof:placetype": "postalcode"
  },
  "geometry": {"coordinates":[-3.413654,55.88853],"type":"Point"}
}
