{
  "type": "Feature",
  "properties": {
    "iso:country":"GB",
    "wof:name":"EH27 8BH",
    "wof:placetype":"postalcode"
},
  "geometry": {"coordinates":[-3.41365431411213,55.88853001405845],"type":"Point"}
}