{
  "type": "Feature",
  "properties": {
    "iso:country":"GB",
    "wof:name":"LE15 6DD",
    "wof:placetype":"postalcode"
},
  "geometry": {"coordinates":[-0.7182785005288,52.6750361537133],"type":"Point"}
}