{
  "type": "Feature",
  "properties": {
    "date:inception_lower": "1984-02-01",
    "date:inception_upper": "1984-02-01",
    "iso:country": "GB",
    "wof:name": "LE15 6DD",
    "wof:placetype": "postalcode"
  },
  "geometry": {"coordinates":[-0.718278,52.675036],"type":"Point"}
}
