{
  "type": "Feature",
  "properties": {
    "iso:country": "GB",
    "wof:name": "CO11 2JB",
    "wof:placetype": "postalcode"
  },
  "geometry": {"coordinates":[1.043438,51.935983],"type":"Point"}
}
