{
  "type": "Feature",
  "properties": {
    "iso:country":"GB",
    "wof:name":"CO11 2JB",
    "wof:placetype":"postalcode"
},
  "geometry": {"coordinates":[1.04343781541179,51.93598344676295],"type":"Point"}
}