{
  "type": "Feature",
  "properties": {
    "iso:country":"GB",
    "wof:name":"EN8 0PH",
    "wof:placetype":"postalcode"
},
  "geometry": {"coordinates":[-0.03143141451705,51.71611981929809],"type":"Point"}
}