{
  "type": "Feature",
  "properties": {
    "iso:country":"GB",
    "wof:name":"AB51 0NN",
    "wof:placetype":"postalcode"
},
  "geometry": {"coordinates":[-2.31987826317924,57.3378137110443],"type":"Point"}
}