{
  "type": "Feature",
  "properties": {
    "date:inception_lower": "2009-11-01",
    "date:inception_upper": "2009-11-01",
    "iso:country": "GB",
    "wof:name": "HR3 5DH",
    "wof:placetype": "postalcode"
  },
  "geometry": {"coordinates":[-3.125781,52.076432],"type":"Point"}
}
