{
  "type": "Feature",
  "properties": {
    "iso:country": "GB",
    "wof:name": "HR3 5DH",
    "wof:placetype": "postalcode"
  },
  "geometry": {"coordinates":[-3.125781,52.076432],"type":"Point"}
}
