{
  "type": "Feature",
  "properties": {
    "iso:country":"GB",
    "wof:name":"HR3 5DH",
    "wof:placetype":"postalcode"
},
  "geometry": {"coordinates":[-3.12578121884401,52.07643197126139],"type":"Point"}
}