{
  "type": "Feature",
  "properties": {
    "date:inception_lower": "2016-05-01",
    "date:inception_upper": "2016-05-01",
    "iso:country": "GB",
    "wof:name": "PO11 9FP",
    "wof:placetype": "postalcode"
  },
  "geometry": {"coordinates":[-0.971434,50.789964],"type":"Point"}
}
