{
  "type": "Feature",
  "properties": {
    "date:inception_lower": "2023-05-01",
    "date:inception_upper": "2023-05-01",
    "iso:country": "GB",
    "wof:name": "SR8 9BY",
    "wof:placetype": "postalcode"
  },
  "geometry": {"coordinates":[-1.3333,54.757951],"type":"Point"}
}
