{
  "type": "Feature",
  "properties": {
    "iso:country": "GB",
    "wof:name": "SG9 9GU",
    "wof:placetype": "postalcode"
  },
  "geometry": {"coordinates":[-0.008017,51.937968],"type":"Point"}
}
