{
  "type": "Feature",
  "properties": {
    "iso:country":"GB",
    "wof:name":"TQ9 7PF",
    "wof:placetype":"postalcode"
},
  "geometry": {"coordinates":[-3.78061268787074,50.41279903516142],"type":"Point"}
}