{
  "type": "Feature",
  "properties": {
    "iso:country":"GB",
    "wof:name":"PH1 1HS",
    "wof:placetype":"postalcode"
},
  "geometry": {"coordinates":[-3.476795536403,56.39083869006853],"type":"Point"}
}