{
  "type": "Feature",
  "properties": {
    "iso:country":"GB",
    "wof:name":"IV30 8HN",
    "wof:placetype":"postalcode"
},
  "geometry": {"coordinates":[-3.21145651624477,57.63806442490607],"type":"Point"}
}