{
  "type": "Feature",
  "properties": {
    "iso:country":"GB",
    "wof:name":"E12 5QU",
    "wof:placetype":"postalcode"
},
  "geometry": {"coordinates":[0.06321140556872,51.55072267074036],"type":"Point"}
}