{
  "type": "Feature",
  "properties": {
    "date:inception_lower": "2020-02-01",
    "date:inception_upper": "2020-02-01",
    "iso:country": "GB",
    "wof:name": "GL5 3AS",
    "wof:placetype": "postalcode"
  },
  "geometry": {"coordinates":[-2.239685,51.739065],"type":"Point"}
}
