{
  "type": "Feature",
  "properties": {
    "iso:country":"GB",
    "wof:name":"LL19 9TD",
    "wof:placetype":"postalcode"
},
  "geometry": {"coordinates":[-3.34805712261474,53.33772656197935],"type":"Point"}
}