{
  "type": "Feature",
  "properties": {
    "iso:country": "GB",
    "wof:name": "DE21 6FD",
    "wof:placetype": "postalcode"
  },
  "geometry": {"coordinates":[-1.452552,52.933505],"type":"Point"}
}
