{
  "type": "Feature",
  "properties": {
    "iso:country":"GB",
    "wof:name":"BN23 7RY",
    "wof:placetype":"postalcode"
},
  "geometry": {"coordinates":[0.30009319190828,50.80082684013342],"type":"Point"}
}