{
  "type": "Feature",
  "properties": {
    "iso:country":"GB",
    "wof:name":"CV21 1JP",
    "wof:placetype":"postalcode"
},
  "geometry": {"coordinates":[-1.24413797192813,52.38683801166935],"type":"Point"}
}