{
  "type": "Feature",
  "properties": {
    "date:inception_lower": "2021-12-01",
    "date:inception_upper": "2021-12-01",
    "iso:country": "GB",
    "wof:name": "CW11 3EB",
    "wof:placetype": "postalcode"
  },
  "geometry": {"coordinates":[-2.401918,53.162434],"type":"Point"}
}
