{
  "type": "Feature",
  "properties": {
    "iso:country": "GB",
    "wof:name": "DY12 2DH",
    "wof:placetype": "postalcode"
  },
  "geometry": {"coordinates":[-2.31449,52.374288],"type":"Point"}
}
