{
  "type": "Feature",
  "properties": {
    "iso:country":"GB",
    "wof:name":"BB9 6QU",
    "wof:placetype":"postalcode"
},
  "geometry": {"coordinates":[-2.22234804572899,53.85284810485047],"type":"Point"}
}