{
  "type": "Feature",
  "properties": {
    "iso:country": "GB",
    "wof:name": "BB9 6QU",
    "wof:placetype": "postalcode"
  },
  "geometry": {"coordinates":[-2.222348,53.852848],"type":"Point"}
}
