{
  "type": "Feature",
  "properties": {
    "iso:country":"GB",
    "wof:name":"IP4 1DY",
    "wof:placetype":"postalcode"
},
  "geometry": {"coordinates":[1.15848927494276,52.05473815721832],"type":"Point"}
}