{
  "type": "Feature",
  "properties": {
    "date:inception_lower":"1991-01-01",
    "date:inception_upper":"1991-01-31",
    "iso:country":"GB",
    "wof:name":"IP4 1DY",
    "wof:placetype":"postalcode"
},
  "geometry": {"coordinates":[1.158489,52.054738],"type":"Point"}
}