{
  "type": "Feature",
  "properties": {
    "iso:country":"GB",
    "wof:name":"CM7 9NB",
    "wof:placetype":"postalcode"
},
  "geometry": {"coordinates":[0.56551979974579,51.88328236479347],"type":"Point"}
}