{
  "type": "Feature",
  "properties": {
    "iso:country": "GB",
    "wof:name": "CM7 9NB",
    "wof:placetype": "postalcode"
  },
  "geometry": {"coordinates":[0.56552,51.883282],"type":"Point"}
}
