{
  "type": "Feature",
  "properties": {
    "iso:country": "GB",
    "wof:name": "IP25 6RP",
    "wof:placetype": "postalcode"
  },
  "geometry": {"coordinates":[0.839979,52.573958],"type":"Point"}
}
