{
  "type": "Feature",
  "properties": {
    "iso:country":"GB",
    "wof:name":"IP25 6RP",
    "wof:placetype":"postalcode"
},
  "geometry": {"coordinates":[0.83997851209071,52.5739578402349],"type":"Point"}
}