{
  "type": "Feature",
  "properties": {
    "date:inception_lower":"2008-08-01",
    "date:inception_upper":"2008-08-31",
    "iso:country":"GB",
    "wof:name":"IP25 6RP",
    "wof:placetype":"postalcode"
},
  "geometry": {"coordinates":[0.839979,52.573958],"type":"Point"}
}