{
  "type": "Feature",
  "properties": {
    "date:inception_lower": "2017-12-01",
    "date:inception_upper": "2017-12-01",
    "iso:country": "GB",
    "wof:name": "S8 8BS",
    "wof:placetype": "postalcode"
  },
  "geometry": {"coordinates":[-1.467152,53.327113],"type":"Point"}
}
