{
  "type": "Feature",
  "properties": {
    "iso:country":"GB",
    "wof:name":"NW8 6PJ",
    "wof:placetype":"postalcode"
},
  "geometry": {"coordinates":[-0.17171207184973,51.53455671164138],"type":"Point"}
}