{
  "type": "Feature",
  "properties": {
    "iso:country":"GB",
    "wof:name":"SM7 1AW",
    "wof:placetype":"postalcode"
},
  "geometry": {"coordinates":[-0.21238695518728,51.31929952430922],"type":"Point"}
}