{
  "type": "Feature",
  "properties": {
    "date:inception_lower":"2008-02-01",
    "date:inception_upper":"2008-02-29",
    "iso:country":"GB",
    "wof:name":"SM7 1AW",
    "wof:placetype":"postalcode"
},
  "geometry": {"coordinates":[-0.212387,51.3193],"type":"Point"}
}