{
  "type": "Feature",
  "properties": {
    "iso:country": "GB",
    "wof:name": "NE15 0DB",
    "wof:placetype": "postalcode"
  },
  "geometry": {"coordinates":[-1.800968,54.991098],"type":"Point"}
}
