{
  "type": "Feature",
  "properties": {
    "iso:country":"GB",
    "wof:name":"NE15 0DB",
    "wof:placetype":"postalcode"
},
  "geometry": {"coordinates":[-1.80096850597254,54.99109797748845],"type":"Point"}
}