{
  "type": "Feature",
  "properties": {
    "iso:country":"GB",
    "wof:name":"G42 7HF",
    "wof:placetype":"postalcode"
},
  "geometry": {"coordinates":[-4.25172761223287,55.83871543786001],"type":"Point"}
}