{
  "type": "Feature",
  "properties": {
    "date:inception_lower": "1999-06-01",
    "date:inception_upper": "1999-06-01",
    "iso:country": "GB",
    "wof:name": "G42 7HF",
    "wof:placetype": "postalcode"
  },
  "geometry": {"coordinates":[-4.251728,55.838715],"type":"Point"}
}
