{
  "type": "Feature",
  "properties": {
    "iso:country":"GB",
    "wof:name":"SS14 1SJ",
    "wof:placetype":"postalcode"
},
  "geometry": {"coordinates":[0.48606045723171,51.56689452898696],"type":"Point"}
}