{
  "type": "Feature",
  "properties": {
    "date:inception_lower":"1980-01-01",
    "date:inception_upper":"1980-01-31",
    "iso:country":"GB",
    "wof:name":"SS14 1SJ",
    "wof:placetype":"postalcode"
},
  "geometry": {"coordinates":[0.48606,51.566895],"type":"Point"}
}