{
  "type": "Feature",
  "properties": {
    "iso:country":"GB",
    "wof:name":"GL17 0XY",
    "wof:placetype":"postalcode"
},
  "geometry": {"coordinates":[-2.45515255957557,51.86563700774394],"type":"Point"}
}