{
  "type": "Feature",
  "properties": {
    "date:inception_lower": "2011-07-01",
    "date:inception_upper": "2011-07-01",
    "iso:country": "GB",
    "wof:name": "GL17 0XY",
    "wof:placetype": "postalcode"
  },
  "geometry": {"coordinates":[-2.455153,51.865672],"type":"Point"}
}
