{
  "type": "Feature",
  "properties": {
    "date:inception_lower": "1981-09-01",
    "date:inception_upper": "1981-09-01",
    "iso:country": "GB",
    "wof:name": "TN15 9BJ",
    "wof:placetype": "postalcode"
  },
  "geometry": {"coordinates":[0.280058,51.274206],"type":"Point"}
}
