{
  "type": "Feature",
  "properties": {
    "iso:country":"GB",
    "wof:name":"TN15 9BJ",
    "wof:placetype":"postalcode"
},
  "geometry": {"coordinates":[0.28005791837948,51.2742059995406],"type":"Point"}
}