{
  "type": "Feature",
  "properties": {
    "iso:country": "GB",
    "wof:name": "GL50 1TB",
    "wof:placetype": "postalcode"
  },
  "geometry": {"coordinates":[-2.077277,51.893861],"type":"Point"}
}
