{
  "type": "Feature",
  "properties": {
    "iso:country":"GB",
    "wof:name":"N18 1AJ",
    "wof:placetype":"postalcode"
},
  "geometry": {"coordinates":[-0.09581117254811,51.6119164837138],"type":"Point"}
}