{
  "type": "Feature",
  "properties": {
    "iso:country": "GB",
    "wof:name": "ST4 6LF",
    "wof:placetype": "postalcode"
  },
  "geometry": {"coordinates":[-2.206164,52.987127],"type":"Point"}
}
