{
  "type": "Feature",
  "properties": {
    "iso:country":"GB",
    "wof:name":"ST4 6LF",
    "wof:placetype":"postalcode"
},
  "geometry": {"coordinates":[-2.20616362402012,52.98712745104201],"type":"Point"}
}