{
  "type": "Feature",
  "properties": {
    "date:inception_lower": "1980-01-01",
    "date:inception_upper": "1980-01-01",
    "iso:country": "GB",
    "wof:name": "NN16 9PE",
    "wof:placetype": "postalcode"
  },
  "geometry": {"coordinates":[-0.713465,52.407932],"type":"Point"}
}
