{
  "type": "Feature",
  "properties": {
    "iso:country":"GB",
    "wof:name":"DL10 4LU",
    "wof:placetype":"postalcode"
},
  "geometry": {"coordinates":[-1.73457511141686,54.40373957576126],"type":"Point"}
}