{
  "type": "Feature",
  "properties": {
    "date:inception_lower": "1991-01-01",
    "date:inception_upper": "1991-01-01",
    "iso:country": "GB",
    "wof:name": "DL10 4LU",
    "wof:placetype": "postalcode"
  },
  "geometry": {"coordinates":[-1.734575,54.40374],"type":"Point"}
}
