{
  "type": "Feature",
  "properties": {
    "iso:country":"GB",
    "wof:name":"S72 8QW",
    "wof:placetype":"postalcode"
},
  "geometry": {"coordinates":[-1.39818742969867,53.59275812176572],"type":"Point"}
}