{
  "type": "Feature",
  "properties": {
    "iso:country":"GB",
    "wof:name":"CW4 7DN",
    "wof:placetype":"postalcode"
},
  "geometry": {"coordinates":[-2.3615351302481,53.19793650781805],"type":"Point"}
}