{
  "type": "Feature",
  "properties": {
    "iso:country": "GB",
    "wof:name": "CW4 7DN",
    "wof:placetype": "postalcode"
  },
  "geometry": {"coordinates":[-2.361535,53.197937],"type":"Point"}
}
