{
  "type": "Feature",
  "properties": {
    "iso:country":"GB",
    "wof:name":"WC1A 1JB",
    "wof:placetype":"postalcode"
},
  "geometry": {"coordinates":[-0.12789927628225,51.51719359552774],"type":"Point"}
}