{
  "type": "Feature",
  "properties": {
    "date:inception_lower":"1980-01-01",
    "date:inception_upper":"1980-01-31",
    "iso:country":"GB",
    "wof:name":"WC1A 1JB",
    "wof:placetype":"postalcode"
},
  "geometry": {"coordinates":[-0.127899,51.517194],"type":"Point"}
}