{
  "type": "Feature",
  "properties": {
    "date:inception_lower":"1991-09-01",
    "date:inception_upper":"1991-09-30",
    "iso:country":"GB",
    "wof:name":"B7 5JX",
    "wof:placetype":"postalcode"
},
  "geometry": {"coordinates":[-1.864948,52.505039],"type":"Point"}
}