{
  "type": "Feature",
  "properties": {
    "iso:country":"GB",
    "wof:name":"TW9 3LQ",
    "wof:placetype":"postalcode"
},
  "geometry": {"coordinates":[-0.29124093567671,51.4752735721294],"type":"Point"}
}