{
  "type": "Feature",
  "properties": {
    "iso:country": "GB",
    "wof:name": "TW9 3LQ",
    "wof:placetype": "postalcode"
  },
  "geometry": {"coordinates":[-0.291241,51.475274],"type":"Point"}
}
