{
  "type": "Feature",
  "properties": {
    "iso:country":"GB",
    "wof:name":"NP13 2EQ",
    "wof:placetype":"postalcode"
},
  "geometry": {"coordinates":[-3.1395060880378,51.71667599898591],"type":"Point"}
}