{
  "type": "Feature",
  "properties": {
    "date:inception_lower": "1999-06-01",
    "date:inception_upper": "1999-06-01",
    "iso:country": "GB",
    "wof:name": "NP13 2EQ",
    "wof:placetype": "postalcode"
  },
  "geometry": {"coordinates":[-3.139514,51.716679],"type":"Point"}
}
