{
  "type": "Feature",
  "properties": {
    "iso:country":"GB",
    "wof:name":"TF2 9LN",
    "wof:placetype":"postalcode"
},
  "geometry": {"coordinates":[-2.43127006982821,52.69336772602906],"type":"Point"}
}