{
  "type": "Feature",
  "properties": {
    "date:inception_lower": "1980-01-01",
    "date:inception_upper": "1980-01-01",
    "iso:country": "GB",
    "wof:name": "TF2 9LN",
    "wof:placetype": "postalcode"
  },
  "geometry": {"coordinates":[-2.43127,52.693368],"type":"Point"}
}
