{
  "type": "Feature",
  "properties": {
    "iso:country":"GB",
    "wof:name":"KA11 1QE",
    "wof:placetype":"postalcode"
},
  "geometry": {"coordinates":[-4.6306139207211,55.62979584924685],"type":"Point"}
}