{
  "type": "Feature",
  "properties": {
    "date:inception_lower":"1985-05-01",
    "date:inception_upper":"1985-05-31",
    "iso:country":"GB",
    "wof:name":"KA11 1QE",
    "wof:placetype":"postalcode"
},
  "geometry": {"coordinates":[-4.630614,55.629796],"type":"Point"}
}