{
  "type": "Feature",
  "properties": {
    "iso:country":"GB",
    "wof:name":"CF37 3DL",
    "wof:placetype":"postalcode"
},
  "geometry": {"coordinates":[-3.33440402287022,51.62606381761955],"type":"Point"}
}