{
  "type": "Feature",
  "properties": {
    "date:inception_lower": "1980-01-01",
    "date:inception_upper": "1980-01-01",
    "iso:country": "GB",
    "wof:name": "KT10 0BJ",
    "wof:placetype": "postalcode"
  },
  "geometry": {"coordinates":[-0.330341,51.374115],"type":"Point"}
}
