{
  "type": "Feature",
  "properties": {
    "iso:country":"GB",
    "wof:name":"WF13 1DU",
    "wof:placetype":"postalcode"
},
  "geometry": {"coordinates":[-1.62917622136815,53.69303446004604],"type":"Point"}
}