{
  "type": "Feature",
  "properties": {
    "date:inception_lower":"1980-01-01",
    "date:inception_upper":"1980-01-31",
    "iso:country":"GB",
    "wof:name":"WF13 1DU",
    "wof:placetype":"postalcode"
},
  "geometry": {"coordinates":[-1.629176,53.693034],"type":"Point"}
}