{
  "type": "Feature",
  "properties": {
    "iso:country": "GB",
    "wof:name": "DN8 5PH",
    "wof:placetype": "postalcode"
  },
  "geometry": {"coordinates":[-0.951095,53.608578],"type":"Point"}
}
