{
  "type": "Feature",
  "properties": {
    "iso:country":"GB",
    "wof:name":"BB18 6AT",
    "wof:placetype":"postalcode"
},
  "geometry": {"coordinates":[-2.18386530627745,53.91695166490996],"type":"Point"}
}