{
  "type": "Feature",
  "properties": {
    "iso:country":"GB",
    "wof:name":"YO26 8AA",
    "wof:placetype":"postalcode"
},
  "geometry": {"coordinates":[-1.30174305149786,54.00554571497766],"type":"Point"}
}