{
  "type": "Feature",
  "properties": {
    "iso:country": "GB",
    "wof:name": "YO26 8AA",
    "wof:placetype": "postalcode"
  },
  "geometry": {"coordinates":[-1.301743,54.005546],"type":"Point"}
}
