{
  "type": "Feature",
  "properties": {
    "date:inception_lower": "1980-01-01",
    "date:inception_upper": "1980-01-01",
    "iso:country": "GB",
    "wof:name": "HR4 8ST",
    "wof:placetype": "postalcode"
  },
  "geometry": {"coordinates":[-2.867756,52.155891],"type":"Point"}
}
