{
  "type": "Feature",
  "properties": {
    "iso:country": "GB",
    "wof:name": "HR4 8ST",
    "wof:placetype": "postalcode"
  },
  "geometry": {"coordinates":[-2.869651,52.155598],"type":"Point"}
}
