{
  "type": "Feature",
  "properties": {
    "iso:country":"GB",
    "wof:name":"HR4 8ST",
    "wof:placetype":"postalcode"
},
  "geometry": {"coordinates":[-2.8696494145292,52.15558855976533],"type":"Point"}
}