{
  "type": "Feature",
  "properties": {
    "date:inception_lower": "1980-01-01",
    "date:inception_upper": "1980-01-01",
    "iso:country": "GB",
    "wof:name": "WV15 5DE",
    "wof:placetype": "postalcode"
  },
  "geometry": {"coordinates":[-2.407792,52.53351],"type":"Point"}
}
