{
  "type": "Feature",
  "properties": {
    "iso:country": "GB",
    "wof:name": "LA8 0JJ",
    "wof:placetype": "postalcode"
  },
  "geometry": {"coordinates":[-2.745146,54.277318],"type":"Point"}
}
