{
  "type": "Feature",
  "properties": {
    "iso:country":"GB",
    "wof:name":"LA8 0JJ",
    "wof:placetype":"postalcode"
},
  "geometry": {"coordinates":[-2.74514584709362,54.27731801581434],"type":"Point"}
}