{
  "type": "Feature",
  "properties": {
    "date:inception_lower":"1980-01-01",
    "date:inception_upper":"1980-01-31",
    "iso:country":"GB",
    "wof:name":"LA8 0JJ",
    "wof:placetype":"postalcode"
},
  "geometry": {"coordinates":[-2.745146,54.277318],"type":"Point"}
}