{
  "type": "Feature",
  "properties": {
    "iso:country":"GB",
    "wof:name":"NN8 1JT",
    "wof:placetype":"postalcode"
},
  "geometry": {"coordinates":[-0.68600133715076,52.303516786818],"type":"Point"}
}