{
  "type": "Feature",
  "properties": {
    "date:inception_lower": "1980-01-01",
    "date:inception_upper": "1980-01-01",
    "iso:country": "GB",
    "wof:name": "LL18 6AU",
    "wof:placetype": "postalcode"
  },
  "geometry": {"coordinates":[-3.412128,53.296335],"type":"Point"}
}
