{
  "type": "Feature",
  "properties": {
    "iso:country":"GB",
    "wof:name":"TW8 9PP",
    "wof:placetype":"postalcode"
},
  "geometry": {"coordinates":[-0.30616306808011,51.49226982924358],"type":"Point"}
}