{
  "type": "Feature",
  "properties": {
    "iso:country":"GB",
    "wof:name":"NW10 9PX",
    "wof:placetype":"postalcode"
},
  "geometry": {"coordinates":[-0.25395788279119,51.54279670480754],"type":"Point"}
}