{
  "type": "Feature",
  "properties": {
    "date:inception_lower": "1980-01-01",
    "date:inception_upper": "1980-01-01",
    "iso:country": "GB",
    "wof:name": "NW10 9PX",
    "wof:placetype": "postalcode"
  },
  "geometry": {"coordinates":[-0.254002,51.54277],"type":"Point"}
}
