{
  "type": "Feature",
  "properties": {
    "date:inception_lower": "1981-06-01",
    "date:inception_upper": "1981-06-01",
    "iso:country": "GB",
    "wof:name": "M2 2AS",
    "wof:placetype": "postalcode"
  },
  "geometry": {"coordinates":[-2.24152,53.480503],"type":"Point"}
}
