{
  "type": "Feature",
  "properties": {
    "iso:country":"GB",
    "wof:name":"M2 2AS",
    "wof:placetype":"postalcode"
},
  "geometry": {"coordinates":[-2.24151995981168,53.48050273358462],"type":"Point"}
}