{
  "type": "Feature",
  "properties": {
    "iso:country":"GB",
    "wof:name":"PO4 0LT",
    "wof:placetype":"postalcode"
},
  "geometry": {"coordinates":[-1.07577073886251,50.78769127094687],"type":"Point"}
}