{
  "type": "Feature",
  "properties": {
    "iso:country": "GB",
    "wof:name": "GL51 0RP",
    "wof:placetype": "postalcode"
  },
  "geometry": {"coordinates":[-2.118481,51.907241],"type":"Point"}
}
