{
  "type": "Feature",
  "properties": {
    "iso:country":"GB",
    "wof:name":"GL51 0RP",
    "wof:placetype":"postalcode"
},
  "geometry": {"coordinates":[-2.11848055799556,51.90724105474181],"type":"Point"}
}