{
  "type": "Feature",
  "properties": {
    "iso:country": "GB",
    "wof:name": "NG19 9PJ",
    "wof:placetype": "postalcode"
  },
  "geometry": {"coordinates":[-1.175632,53.168048],"type":"Point"}
}
