{
  "type": "Feature",
  "properties": {
    "iso:country":"GB",
    "wof:name":"FY3 9AT",
    "wof:placetype":"postalcode"
},
  "geometry": {"coordinates":[-3.03355442376265,53.81646796841915],"type":"Point"}
}