{
  "type": "Feature",
  "properties": {
    "iso:country":"GB",
    "wof:name":"BH7 6HX",
    "wof:placetype":"postalcode"
},
  "geometry": {"coordinates":[-1.83606997128147,50.7307782684428],"type":"Point"}
}