{
  "type": "Feature",
  "properties": {
    "date:inception_lower":"1980-01-01",
    "date:inception_upper":"1980-01-31",
    "iso:country":"GB",
    "wof:name":"BH7 6HX",
    "wof:placetype":"postalcode"
},
  "geometry": {"coordinates":[-1.83607,50.730778],"type":"Point"}
}