{
  "type": "Feature",
  "properties": {
    "iso:country":"GB",
    "wof:name":"TS3 7LP",
    "wof:placetype":"postalcode"
},
  "geometry": {"coordinates":[-1.20518484563352,54.55593417093706],"type":"Point"}
}