{
  "type": "Feature",
  "properties": {
    "iso:country":"GB",
    "wof:name":"N7 0ST",
    "wof:placetype":"postalcode"
},
  "geometry": {"coordinates":[-0.12116240952722,51.55585252803813],"type":"Point"}
}