{
  "type": "Feature",
  "properties": {
    "iso:country": "GB",
    "wof:name": "PE11 4JU",
    "wof:placetype": "postalcode"
  },
  "geometry": {"coordinates":[-0.270069,52.84986],"type":"Point"}
}
