{
  "type": "Feature",
  "properties": {
    "iso:country":"GB",
    "wof:name":"G43 2DB",
    "wof:placetype":"postalcode"
},
  "geometry": {"coordinates":[-4.28908835101471,55.82056279669744],"type":"Point"}
}