{
  "type": "Feature",
  "properties": {
    "iso:country": "GB",
    "wof:name": "G43 2DB",
    "wof:placetype": "postalcode"
  },
  "geometry": {"coordinates":[-4.28885,55.820576],"type":"Point"}
}
