{
  "type": "Feature",
  "properties": {
    "date:inception_lower": "1980-01-01",
    "date:inception_upper": "1980-01-01",
    "iso:country": "GB",
    "wof:name": "G43 2DB",
    "wof:placetype": "postalcode"
  },
  "geometry": {"coordinates":[-4.288895,55.82049],"type":"Point"}
}
