{
  "type": "Feature",
  "properties": {
    "iso:country":"GB",
    "wof:name":"GU16 8SA",
    "wof:placetype":"postalcode"
},
  "geometry": {"coordinates":[-0.72715690058444,51.32347119192008],"type":"Point"}
}