{
  "type": "Feature",
  "properties": {
    "iso:country":"GB",
    "wof:name":"PE27 6DN",
    "wof:placetype":"postalcode"
},
  "geometry": {"coordinates":[-0.08023192317395,52.32982286147318],"type":"Point"}
}