{
  "type": "Feature",
  "properties": {
    "iso:country":"GB",
    "wof:name":"CT14 7SB",
    "wof:placetype":"postalcode"
},
  "geometry": {"coordinates":[1.39701497368172,51.21081740285778],"type":"Point"}
}