{
  "type": "Feature",
  "properties": {
    "date:inception_lower": "1999-06-01",
    "date:inception_upper": "1999-06-01",
    "iso:country": "GB",
    "wof:name": "CH66 2YZ",
    "wof:placetype": "postalcode"
  },
  "geometry": {"coordinates":[-2.92565,53.259727],"type":"Point"}
}
