{
  "type": "Feature",
  "properties": {
    "iso:country":"GB",
    "wof:name":"CH66 2YZ",
    "wof:placetype":"postalcode"
},
  "geometry": {"coordinates":[-2.92564988407323,53.25972700894337],"type":"Point"}
}