{
  "type": "Feature",
  "properties": {
    "iso:country":"GB",
    "wof:name":"PL19 9BL",
    "wof:placetype":"postalcode"
},
  "geometry": {"coordinates":[-4.14279171885097,50.54064949636405],"type":"Point"}
}