{
  "type": "Feature",
  "properties": {
    "iso:country":"GB",
    "wof:name":"EH51 9HF",
    "wof:placetype":"postalcode"
},
  "geometry": {"coordinates":[-3.60771950532201,56.01680556124658],"type":"Point"}
}