{
  "type": "Feature",
  "properties": {
    "date:inception_lower": "1981-03-01",
    "date:inception_upper": "1981-03-01",
    "iso:country": "GB",
    "wof:name": "EH51 9HF",
    "wof:placetype": "postalcode"
  },
  "geometry": {"coordinates":[-3.607907,56.016817],"type":"Point"}
}
