{
  "type": "Feature",
  "properties": {
    "iso:country":"GB",
    "wof:name":"CR0 3DY",
    "wof:placetype":"postalcode"
},
  "geometry": {"coordinates":[-0.13074244586028,51.38566816512537],"type":"Point"}
}