{
  "type": "Feature",
  "properties": {
    "iso:country":"GB",
    "wof:name":"DN14 8QG",
    "wof:placetype":"postalcode"
},
  "geometry": {"coordinates":[-0.9630246801831,53.6978312816021],"type":"Point"}
}