{
  "type": "Feature",
  "properties": {
    "iso:country":"GB",
    "wof:name":"NE49 0JN",
    "wof:placetype":"postalcode"
},
  "geometry": {"coordinates":[-2.54162408226564,54.9451038753737],"type":"Point"}
}