{
  "type": "Feature",
  "properties": {
    "iso:country": "GB",
    "wof:name": "NE49 0JN",
    "wof:placetype": "postalcode"
  },
  "geometry": {"coordinates":[-2.541624,54.945104],"type":"Point"}
}
