{
  "type": "Feature",
  "properties": {
    "iso:country":"GB",
    "wof:name":"EX33 1NA",
    "wof:placetype":"postalcode"
},
  "geometry": {"coordinates":[-4.22264126052856,51.13012933101788],"type":"Point"}
}