{
  "type": "Feature",
  "properties": {
    "date:inception_lower":"2006-05-01",
    "date:inception_upper":"2006-05-31",
    "iso:country":"GB",
    "wof:name":"BD17 7LW",
    "wof:placetype":"postalcode"
},
  "geometry": {"coordinates":[-1.767071,53.839797],"type":"Point"}
}