{
  "type": "Feature",
  "properties": {
    "iso:country":"GB",
    "wof:name":"BD17 7LW",
    "wof:placetype":"postalcode"
},
  "geometry": {"coordinates":[-1.76707064998005,53.83979656828518],"type":"Point"}
}