{
  "type": "Feature",
  "properties": {
    "iso:country":"GB",
    "wof:name":"PL15 9TE",
    "wof:placetype":"postalcode"
},
  "geometry": {"coordinates":[-4.35988832798107,50.63659282939594],"type":"Point"}
}