{
  "type": "Feature",
  "properties": {
    "date:inception_lower": "1990-07-01",
    "date:inception_upper": "1990-07-01",
    "iso:country": "GB",
    "wof:name": "PL15 9TE",
    "wof:placetype": "postalcode"
  },
  "geometry": {"coordinates":[-4.359888,50.636593],"type":"Point"}
}
