{
  "type": "Feature",
  "properties": {
    "iso:country":"GB",
    "wof:name":"SO14 3EG",
    "wof:placetype":"postalcode"
},
  "geometry": {"coordinates":[-1.39936658279909,50.89911932775424],"type":"Point"}
}