{
  "type": "Feature",
  "properties": {
    "iso:country": "GB",
    "wof:name": "SO14 3EG",
    "wof:placetype": "postalcode"
  },
  "geometry": {"coordinates":[-1.399357,50.899128],"type":"Point"}
}
