{
  "type": "Feature",
  "properties": {
    "iso:country":"GB",
    "wof:name":"HA2 0NH",
    "wof:placetype":"postalcode"
},
  "geometry": {"coordinates":[-0.34935358348023,51.56311522169072],"type":"Point"}
}