{
  "type": "Feature",
  "properties": {
    "iso:country":"GB",
    "wof:name":"SE22 0NL",
    "wof:placetype":"postalcode"
},
  "geometry": {"coordinates":[-0.05938589066494,51.45357217120416],"type":"Point"}
}