{
  "type": "Feature",
  "properties": {
    "date:inception_lower":"1980-01-01",
    "date:inception_upper":"1980-01-31",
    "iso:country":"GB",
    "wof:name":"SE22 0NL",
    "wof:placetype":"postalcode"
},
  "geometry": {"coordinates":[-0.059386,51.453572],"type":"Point"}
}