{
  "type": "Feature",
  "properties": {
    "date:inception_lower": "2021-11-01",
    "date:inception_upper": "2021-11-01",
    "iso:country": "GB",
    "wof:name": "SR3 2PP",
    "wof:placetype": "postalcode"
  },
  "geometry": {"coordinates":[-1.42639,54.869204],"type":"Point"}
}
