{
  "type": "Feature",
  "properties": {
    "iso:country": "GB",
    "wof:name": "SA4 0XP",
    "wof:placetype": "postalcode"
  },
  "geometry": {"coordinates":[-4.053523,51.712255],"type":"Point"}
}
