{
  "type": "Feature",
  "properties": {
    "iso:country":"GB",
    "wof:name":"SA4 0XP",
    "wof:placetype":"postalcode"
},
  "geometry": {"coordinates":[-4.0535233449547,51.71225526277674],"type":"Point"}
}