{
  "type": "Feature",
  "properties": {
    "date:inception_lower":"2002-06-01",
    "date:inception_upper":"2002-06-30",
    "iso:country":"GB",
    "wof:name":"SA4 0XP",
    "wof:placetype":"postalcode"
},
  "geometry": {"coordinates":[-4.053523,51.712255],"type":"Point"}
}