{
  "type": "Feature",
  "properties": {
    "iso:country": "GB",
    "wof:name": "CA7 4RU",
    "wof:placetype": "postalcode"
  },
  "geometry": {"coordinates":[-3.292146,54.844509],"type":"Point"}
}
