{
  "type": "Feature",
  "properties": {
    "iso:country":"GB",
    "wof:name":"TQ1 3TP",
    "wof:placetype":"postalcode"
},
  "geometry": {"coordinates":[-3.51023225410041,50.47073939218532],"type":"Point"}
}