{
  "type": "Feature",
  "properties": {
    "iso:country": "GB",
    "wof:name": "TQ1 3TP",
    "wof:placetype": "postalcode"
  },
  "geometry": {"coordinates":[-3.510232,50.470739],"type":"Point"}
}
