{
  "type": "Feature",
  "properties": {
    "iso:country": "GB",
    "wof:name": "B76 2XA",
    "wof:placetype": "postalcode"
  },
  "geometry": {"coordinates":[-1.797134,52.556419],"type":"Point"}
}
