{
  "type": "Feature",
  "properties": {
    "date:inception_lower": "1980-01-01",
    "date:inception_upper": "1980-01-01",
    "iso:country": "GB",
    "wof:name": "HR2 7AE",
    "wof:placetype": "postalcode"
  },
  "geometry": {"coordinates":[-2.728659,52.04674],"type":"Point"}
}
