{
  "type": "Feature",
  "properties": {
    "iso:country":"GB",
    "wof:name":"HR2 7AE",
    "wof:placetype":"postalcode"
},
  "geometry": {"coordinates":[-2.72865876831015,52.0467404827814],"type":"Point"}
}