{
  "type": "Feature",
  "properties": {
    "iso:country": "GB",
    "wof:name": "HU11 4BS",
    "wof:placetype": "postalcode"
  },
  "geometry": {"coordinates":[-0.256977,53.777266],"type":"Point"}
}
