{
  "type": "Feature",
  "properties": {
    "date:inception_lower": "1994-12-01",
    "date:inception_upper": "1994-12-01",
    "iso:country": "GB",
    "wof:name": "SO31 6QS",
    "wof:placetype": "postalcode"
  },
  "geometry": {"coordinates":[-1.260958,50.867913],"type":"Point"}
}
