{
  "type": "Feature",
  "properties": {
    "iso:country": "GB",
    "wof:name": "NP10 8AW",
    "wof:placetype": "postalcode"
  },
  "geometry": {"coordinates":[-3.028244,51.557455],"type":"Point"}
}
