{
  "type": "Feature",
  "properties": {
    "date:inception_lower": "2015-10-01",
    "date:inception_upper": "2015-10-01",
    "iso:country": "GB",
    "wof:name": "NP10 8AW",
    "wof:placetype": "postalcode"
  },
  "geometry": {"coordinates":[-3.028244,51.557455],"type":"Point"}
}
