{
  "type": "Feature",
  "properties": {
    "date:inception_lower": "2005-06-01",
    "date:inception_upper": "2005-06-01",
    "iso:country": "GB",
    "wof:name": "HP14 4HA",
    "wof:placetype": "postalcode"
  },
  "geometry": {"coordinates":[-0.807966,51.66498],"type":"Point"}
}
