{
  "type": "Feature",
  "properties": {
    "iso:country":"GB",
    "wof:name":"HP14 4HA",
    "wof:placetype":"postalcode"
},
  "geometry": {"coordinates":[-0.80796616575651,51.66497979357697],"type":"Point"}
}