{
  "type": "Feature",
  "properties": {
    "iso:country": "GB",
    "wof:name": "B5 7ED",
    "wof:placetype": "postalcode"
  },
  "geometry": {"coordinates":[-1.899761,52.463564],"type":"Point"}
}
