{
  "type": "Feature",
  "properties": {
    "iso:country":"GB",
    "wof:name":"HU17 8RF",
    "wof:placetype":"postalcode"
},
  "geometry": {"coordinates":[-0.55073508350099,53.82498861724422],"type":"Point"}
}