{
  "type": "Feature",
  "properties": {
    "iso:country":"GB",
    "wof:name":"B68 9AT",
    "wof:placetype":"postalcode"
},
  "geometry": {"coordinates":[-1.9956421532093,52.47891934453651],"type":"Point"}
}