{
  "type": "Feature",
  "properties": {
    "date:inception_lower": "1980-01-01",
    "date:inception_upper": "1980-01-01",
    "iso:country": "GB",
    "wof:name": "M34 2DT",
    "wof:placetype": "postalcode"
  },
  "geometry": {"coordinates":[-2.124419,53.447847],"type":"Point"}
}
