{
  "type": "Feature",
  "properties": {
    "iso:country":"GB",
    "wof:name":"ME7 3RR",
    "wof:placetype":"postalcode"
},
  "geometry": {"coordinates":[0.5776227032771,51.35387543400849],"type":"Point"}
}