{
  "type": "Feature",
  "properties": {
    "iso:country": "GB",
    "wof:name": "ST1 6EQ",
    "wof:placetype": "postalcode"
  },
  "geometry": {"coordinates":[-2.16766,53.045267],"type":"Point"}
}
