{
  "type": "Feature",
  "properties": {
    "iso:country":"GB",
    "wof:name":"ST1 6EQ",
    "wof:placetype":"postalcode"
},
  "geometry": {"coordinates":[-2.16765963505754,53.04526696302493],"type":"Point"}
}