{
  "type": "Feature",
  "properties": {
    "date:inception_lower": "2023-05-01",
    "date:inception_upper": "2023-05-01",
    "iso:country": "GB",
    "wof:name": "GU9 8FR",
    "wof:placetype": "postalcode"
  },
  "geometry": {"coordinates":[-0.794479,51.207785],"type":"Point"}
}
