{
  "type": "Feature",
  "properties": {
    "date:inception_lower": "2022-06-01",
    "date:inception_upper": "2022-06-01",
    "iso:country": "GB",
    "wof:name": "OX14 1RW",
    "wof:placetype": "postalcode"
  },
  "geometry": {"coordinates":[-1.290514,51.686287],"type":"Point"}
}
