{
  "type": "Feature",
  "properties": {
    "iso:country": "GB",
    "wof:name": "BD12 0TQ",
    "wof:placetype": "postalcode"
  },
  "geometry": {"coordinates":[-1.765635,53.756619],"type":"Point"}
}
