{
  "type": "Feature",
  "properties": {
    "iso:country":"GB",
    "wof:name":"BD12 0TQ",
    "wof:placetype":"postalcode"
},
  "geometry": {"coordinates":[-1.76563472216845,53.75661903348379],"type":"Point"}
}