{
  "type": "Feature",
  "properties": {
    "iso:country": "GB",
    "wof:name": "L35 9LQ",
    "wof:placetype": "postalcode"
  },
  "geometry": {"coordinates":[-2.772992,53.41554],"type":"Point"}
}
