{
  "type": "Feature",
  "properties": {
    "date:inception_lower":"1980-01-01",
    "date:inception_upper":"1980-01-31",
    "iso:country":"GB",
    "wof:name":"SW1P 2EU",
    "wof:placetype":"postalcode"
},
  "geometry": {"coordinates":[-0.133066,51.496575],"type":"Point"}
}