{
  "type": "Feature",
  "properties": {
    "iso:country":"GB",
    "wof:name":"UB5 5DE",
    "wof:placetype":"postalcode"
},
  "geometry": {"coordinates":[-0.37906125642716,51.54440294076597],"type":"Point"}
}