{
  "type": "Feature",
  "properties": {
    "iso:country": "GB",
    "wof:name": "YO42 1AH",
    "wof:placetype": "postalcode"
  },
  "geometry": {"coordinates":[-0.768196,53.925977],"type":"Point"}
}
