{
  "type": "Feature",
  "properties": {
    "iso:country":"GB",
    "wof:name":"NP20 3HG",
    "wof:placetype":"postalcode"
},
  "geometry": {"coordinates":[-3.01479553937674,51.57670600743457],"type":"Point"}
}