{
  "type": "Feature",
  "properties": {
    "iso:country": "GB",
    "wof:name": "L25 8QQ",
    "wof:placetype": "postalcode"
  },
  "geometry": {"coordinates":[-2.859258,53.370456],"type":"Point"}
}
