{
  "type": "Feature",
  "properties": {
    "iso:country": "GB",
    "wof:name": "GL10 2PU",
    "wof:placetype": "postalcode"
  },
  "geometry": {"coordinates":[-2.286049,51.755581],"type":"Point"}
}
