{
  "type": "Feature",
  "properties": {
    "iso:country":"GB",
    "wof:name":"DN3 3FF",
    "wof:placetype":"postalcode"
},
  "geometry": {"coordinates":[-1.03356989703917,53.53791153444624],"type":"Point"}
}