{
  "type": "Feature",
  "properties": {
    "iso:country": "GB",
    "wof:name": "RH16 4RE",
    "wof:placetype": "postalcode"
  },
  "geometry": {"coordinates":[-0.102828,50.986047],"type":"Point"}
}
