{
  "type": "Feature",
  "properties": {
    "iso:country":"GB",
    "wof:name":"S66 8LG",
    "wof:placetype":"postalcode"
},
  "geometry": {"coordinates":[-1.2015432233432,53.42303482816114],"type":"Point"}
}