{
  "type": "Feature",
  "properties": {
    "iso:country":"GB",
    "wof:name":"EH21 7EU",
    "wof:placetype":"postalcode"
},
  "geometry": {"coordinates":[-3.04545240461814,55.93982126673776],"type":"Point"}
}