{
  "type": "Feature",
  "properties": {
    "iso:country":"GB",
    "wof:name":"BR1 3TJ",
    "wof:placetype":"postalcode"
},
  "geometry": {"coordinates":[0.02253141252591,51.40903991150319],"type":"Point"}
}