{
  "type": "Feature",
  "properties": {
    "date:inception_lower":"1980-01-01",
    "date:inception_upper":"1980-01-31",
    "iso:country":"GB",
    "wof:name":"DN14 9JA",
    "wof:placetype":"postalcode"
},
  "geometry": {"coordinates":[-1.02624,53.692988],"type":"Point"}
}