{
  "type": "Feature",
  "properties": {
    "iso:country": "GB",
    "wof:name": "DN14 9JA",
    "wof:placetype": "postalcode"
  },
  "geometry": {"coordinates":[-1.026211,53.692925],"type":"Point"}
}
