{
  "type": "Feature",
  "properties": {
    "iso:country": "GB",
    "wof:name": "BD23 2PF",
    "wof:placetype": "postalcode"
  },
  "geometry": {"coordinates":[-2.017853,53.952287],"type":"Point"}
}
