{
  "type": "Feature",
  "properties": {
    "iso:country": "GB",
    "wof:name": "TS25 3PL",
    "wof:placetype": "postalcode"
  },
  "geometry": {"coordinates":[-1.241449,54.658908],"type":"Point"}
}
