{
  "type": "Feature",
  "properties": {
    "iso:country":"GB",
    "wof:name":"GL54 3LX",
    "wof:placetype":"postalcode"
},
  "geometry": {"coordinates":[-1.80353738847285,51.8281612825494],"type":"Point"}
}