{
  "type": "Feature",
  "properties": {
    "date:inception_lower": "1980-01-01",
    "date:inception_upper": "1980-01-01",
    "iso:country": "GB",
    "wof:name": "GL54 3LX",
    "wof:placetype": "postalcode"
  },
  "geometry": {"coordinates":[-1.803537,51.828161],"type":"Point"}
}
