{
  "type": "Feature",
  "properties": {
    "iso:country":"GB",
    "wof:name":"CO10 7QF",
    "wof:placetype":"postalcode"
},
  "geometry": {"coordinates":[0.67694478386435,52.10728940996422],"type":"Point"}
}