{
  "type": "Feature",
  "properties": {
    "iso:country": "GB",
    "wof:name": "CO10 7QF",
    "wof:placetype": "postalcode"
  },
  "geometry": {"coordinates":[0.676944,52.107268],"type":"Point"}
}
