{
  "type": "Feature",
  "properties": {
    "date:inception_lower": "1980-01-01",
    "date:inception_upper": "1980-01-01",
    "iso:country": "GB",
    "wof:name": "CO10 7QF",
    "wof:placetype": "postalcode"
  },
  "geometry": {"coordinates":[0.677104,52.108245],"type":"Point"}
}
