{
  "type": "Feature",
  "properties": {
    "iso:country":"GB",
    "wof:name":"TQ14 8SL",
    "wof:placetype":"postalcode"
},
  "geometry": {"coordinates":[-3.49459754667684,50.54689207759543],"type":"Point"}
}