{
  "type": "Feature",
  "properties": {
    "iso:country": "GB",
    "wof:name": "PA11 3TN",
    "wof:placetype": "postalcode"
  },
  "geometry": {"coordinates":[-4.616846,55.868276],"type":"Point"}
}
