{
  "type": "Feature",
  "properties": {
    "date:inception_lower":"2012-11-01",
    "date:inception_upper":"2012-11-30",
    "iso:country":"GB",
    "wof:name":"PA11 3TN",
    "wof:placetype":"postalcode"
},
  "geometry": {"coordinates":[-4.616846,55.868276],"type":"Point"}
}