{
  "type": "Feature",
  "properties": {
    "iso:country":"GB",
    "wof:name":"PA11 3TN",
    "wof:placetype":"postalcode"
},
  "geometry": {"coordinates":[-4.61684580349501,55.86827624562275],"type":"Point"}
}