{
  "type": "Feature",
  "properties": {
    "iso:country":"GB",
    "wof:name":"RH13 9TH",
    "wof:placetype":"postalcode"
},
  "geometry": {"coordinates":[-0.35500575078236,51.0218048032875],"type":"Point"}
}