{
  "type": "Feature",
  "properties": {
    "iso:country": "GB",
    "wof:name": "DA14 5AT",
    "wof:placetype": "postalcode"
  },
  "geometry": {"coordinates":[0.150904,51.412222],"type":"Point"}
}
