{
  "type": "Feature",
  "properties": {
    "iso:country":"GB",
    "wof:name":"B11 3PH",
    "wof:placetype":"postalcode"
},
  "geometry": {"coordinates":[-1.83512927218398,52.44591052128303],"type":"Point"}
}