{
  "type": "Feature",
  "properties": {
    "iso:country": "GB",
    "wof:name": "NE29 8DQ",
    "wof:placetype": "postalcode"
  },
  "geometry": {"coordinates":[-1.481849,55.022167],"type":"Point"}
}
