{
  "type": "Feature",
  "properties": {
    "iso:country":"GB",
    "wof:name":"NE29 8DQ",
    "wof:placetype":"postalcode"
},
  "geometry": {"coordinates":[-1.48184876738962,55.02216715467354],"type":"Point"}
}