{
  "type": "Feature",
  "properties": {
    "iso:country":"GB",
    "wof:name":"WA12 9HS",
    "wof:placetype":"postalcode"
},
  "geometry": {"coordinates":[-2.65121764616375,53.4542259802642],"type":"Point"}
}