{
  "type": "Feature",
  "properties": {
    "date:inception_lower":"1980-01-01",
    "date:inception_upper":"1980-01-31",
    "iso:country":"GB",
    "wof:name":"WA12 9HS",
    "wof:placetype":"postalcode"
},
  "geometry": {"coordinates":[-2.651218,53.454226],"type":"Point"}
}