{
  "type": "Feature",
  "properties": {
    "iso:country": "GB",
    "wof:name": "WA12 9HS",
    "wof:placetype": "postalcode"
  },
  "geometry": {"coordinates":[-2.651218,53.454226],"type":"Point"}
}
