{
  "type": "Feature",
  "properties": {
    "iso:country":"GB",
    "wof:name":"DN3 2DZ",
    "wof:placetype":"postalcode"
},
  "geometry": {"coordinates":[-1.0567202047366,53.53775476824972],"type":"Point"}
}