{
  "type": "Feature",
  "properties": {
    "iso:country": "GB",
    "wof:name": "DN3 2DZ",
    "wof:placetype": "postalcode"
  },
  "geometry": {"coordinates":[-1.05672,53.537755],"type":"Point"}
}
