{
  "type": "Feature",
  "properties": {
    "iso:country": "GB",
    "wof:name": "RG4 9SS",
    "wof:placetype": "postalcode"
  },
  "geometry": {"coordinates":[-0.978974,51.520018],"type":"Point"}
}
