{
  "type": "Feature",
  "properties": {
    "iso:country":"GB",
    "wof:name":"BA9 8NH",
    "wof:placetype":"postalcode"
},
  "geometry": {"coordinates":[-2.33006412812184,51.08362019066868],"type":"Point"}
}