{
  "type": "Feature",
  "properties": {
    "date:inception_lower":"1980-01-01",
    "date:inception_upper":"1980-01-31",
    "iso:country":"GB",
    "wof:name":"BA9 8NH",
    "wof:placetype":"postalcode"
},
  "geometry": {"coordinates":[-2.330064,51.08362],"type":"Point"}
}