{
  "type": "Feature",
  "properties": {
    "iso:country": "GB",
    "wof:name": "BA9 8NH",
    "wof:placetype": "postalcode"
  },
  "geometry": {"coordinates":[-2.330064,51.08362],"type":"Point"}
}
