{
  "type": "Feature",
  "properties": {
    "iso:country":"GB",
    "wof:name":"WA2 8TR",
    "wof:placetype":"postalcode"
},
  "geometry": {"coordinates":[-2.59416551449778,53.42452836265845],"type":"Point"}
}