{
  "type": "Feature",
  "properties": {
    "date:inception_lower": "1990-07-01",
    "date:inception_upper": "1990-07-01",
    "iso:country": "GB",
    "wof:name": "WA2 8TR",
    "wof:placetype": "postalcode"
  },
  "geometry": {"coordinates":[-2.594165,53.424528],"type":"Point"}
}
