{
  "type": "Feature",
  "properties": {
    "date:inception_lower": "1980-01-01",
    "date:inception_upper": "1980-01-01",
    "iso:country": "GB",
    "wof:name": "SW9 9NG",
    "wof:placetype": "postalcode"
  },
  "geometry": {"coordinates":[-0.127002,51.464573],"type":"Point"}
}
