{
  "type": "Feature",
  "properties": {
    "date:inception_lower": "1985-04-01",
    "date:inception_upper": "1985-04-01",
    "iso:country": "GB",
    "wof:name": "TN17 4LJ",
    "wof:placetype": "postalcode"
  },
  "geometry": {"coordinates":[0.632755,51.051018],"type":"Point"}
}
