{
  "type": "Feature",
  "properties": {
    "iso:country":"GB",
    "wof:name":"TN17 4LJ",
    "wof:placetype":"postalcode"
},
  "geometry": {"coordinates":[0.63275526580406,51.05101841013232],"type":"Point"}
}