{
  "type": "Feature",
  "properties": {
    "iso:country": "GB",
    "wof:name": "TN17 4LJ",
    "wof:placetype": "postalcode"
  },
  "geometry": {"coordinates":[0.632755,51.051018],"type":"Point"}
}
