{
  "type": "Feature",
  "properties": {
    "date:inception_lower": "2014-09-01",
    "date:inception_upper": "2014-09-01",
    "iso:country": "GB",
    "wof:name": "HP12 3AG",
    "wof:placetype": "postalcode"
  },
  "geometry": {"coordinates":[-0.774359,51.636202],"type":"Point"}
}
