{
  "type": "Feature",
  "properties": {
    "iso:country":"GB",
    "wof:name":"BN9 0QH",
    "wof:placetype":"postalcode"
},
  "geometry": {"coordinates":[0.05998122845592,50.80417286657363],"type":"Point"}
}