{
  "type": "Feature",
  "properties": {
    "iso:country":"GB",
    "wof:name":"LL11 2RH",
    "wof:placetype":"postalcode"
},
  "geometry": {"coordinates":[-2.99757367512273,53.06095060209214],"type":"Point"}
}