{
  "type": "Feature",
  "properties": {
    "date:inception_lower": "2022-07-01",
    "date:inception_upper": "2022-07-01",
    "iso:country": "GB",
    "wof:name": "WS11 1BQ",
    "wof:placetype": "postalcode"
  },
  "geometry": {"coordinates":[-2.027634,52.692503],"type":"Point"}
}
