{
  "type": "Feature",
  "properties": {
    "iso:country":"GB",
    "wof:name":"LN11 9JY",
    "wof:placetype":"postalcode"
},
  "geometry": {"coordinates":[-0.0087760094636,53.36524142048393],"type":"Point"}
}