{
  "type": "Feature",
  "properties": {
    "iso:country": "GB",
    "wof:name": "CR0 8XN",
    "wof:placetype": "postalcode"
  },
  "geometry": {"coordinates":[-0.049583,51.379255],"type":"Point"}
}
