{
  "type": "Feature",
  "properties": {
    "iso:country":"GB",
    "wof:name":"DN36 4NX",
    "wof:placetype":"postalcode"
},
  "geometry": {"coordinates":[-0.06895610855675,53.52128037975807],"type":"Point"}
}