{
  "type": "Feature",
  "properties": {
    "date:inception_lower": "1980-01-01",
    "date:inception_upper": "1980-01-01",
    "iso:country": "GB",
    "wof:name": "DN36 4NX",
    "wof:placetype": "postalcode"
  },
  "geometry": {"coordinates":[-0.068956,53.52128],"type":"Point"}
}
