{
  "type": "Feature",
  "properties": {
    "iso:country":"GB",
    "wof:name":"PO38 3NY",
    "wof:placetype":"postalcode"
},
  "geometry": {"coordinates":[-1.28230731309203,50.6487485884665],"type":"Point"}
}