{
  "type": "Feature",
  "properties": {
    "date:inception_lower": "1980-01-01",
    "date:inception_upper": "1980-01-01",
    "iso:country": "GB",
    "wof:name": "L7 6AE",
    "wof:placetype": "postalcode"
  },
  "geometry": {"coordinates":[-2.943704,53.399417],"type":"Point"}
}
