{
  "type": "Feature",
  "properties": {
    "iso:country": "GB",
    "wof:name": "MK42 9RP",
    "wof:placetype": "postalcode"
  },
  "geometry": {"coordinates":[-0.477586,52.117334],"type":"Point"}
}
