{
  "type": "Feature",
  "properties": {
    "iso:country":"GB",
    "wof:name":"EX11 1UB",
    "wof:placetype":"postalcode"
},
  "geometry": {"coordinates":[-3.31563503014015,50.73663344170477],"type":"Point"}
}