{
  "type": "Feature",
  "properties": {
    "iso:country":"GB",
    "wof:name":"BA11 1JZ",
    "wof:placetype":"postalcode"
},
  "geometry": {"coordinates":[-2.32092718694258,51.22572867481569],"type":"Point"}
}