{
  "type": "Feature",
  "properties": {
    "iso:country":"GB",
    "wof:name":"NE32 5QL",
    "wof:placetype":"postalcode"
},
  "geometry": {"coordinates":[-1.49247504138948,54.964690703393],"type":"Point"}
}