{
  "type": "Feature",
  "properties": {
    "iso:country":"GB",
    "wof:name":"N16 6RX",
    "wof:placetype":"postalcode"
},
  "geometry": {"coordinates":[-0.07241054496566,51.56968353634294],"type":"Point"}
}