{
  "type": "Feature",
  "properties": {
    "iso:country":"GB",
    "wof:name":"LL30 3PY",
    "wof:placetype":"postalcode"
},
  "geometry": {"coordinates":[-3.77198205276147,53.32036958097619],"type":"Point"}
}