{
  "type": "Feature",
  "properties": {
    "date:inception_lower": "1986-07-01",
    "date:inception_upper": "1986-07-01",
    "iso:country": "GB",
    "wof:name": "CV35 9TL",
    "wof:placetype": "postalcode"
  },
  "geometry": {"coordinates":[-1.599831,52.188362],"type":"Point"}
}
