{
  "type": "Feature",
  "properties": {
    "iso:country": "GB",
    "wof:name": "CV35 9TL",
    "wof:placetype": "postalcode"
  },
  "geometry": {"coordinates":[-1.599831,52.188362],"type":"Point"}
}
