{
  "type": "Feature",
  "properties": {
    "iso:country":"GB",
    "wof:name":"CV35 9TL",
    "wof:placetype":"postalcode"
},
  "geometry": {"coordinates":[-1.59983137753063,52.18836234955609],"type":"Point"}
}