{
  "type": "Feature",
  "properties": {
    "date:inception_lower": "2018-08-01",
    "date:inception_upper": "2018-08-01",
    "iso:country": "GB",
    "wof:name": "CM24 8XR",
    "wof:placetype": "postalcode"
  },
  "geometry": {"coordinates":[0.196675,51.911719],"type":"Point"}
}
