{
  "type": "Feature",
  "properties": {
    "iso:country": "GB",
    "wof:name": "CM24 8XR",
    "wof:placetype": "postalcode"
  },
  "geometry": {"coordinates":[0.196733,51.911718],"type":"Point"}
}
