{
  "type": "Feature",
  "properties": {
    "date:inception_lower": "1984-02-01",
    "date:inception_upper": "1984-02-01",
    "iso:country": "GB",
    "wof:name": "ST11 9JN",
    "wof:placetype": "postalcode"
  },
  "geometry": {"coordinates":[-2.055612,52.965656],"type":"Point"}
}
