{
  "type": "Feature",
  "properties": {
    "iso:country":"GB",
    "wof:name":"ST11 9JN",
    "wof:placetype":"postalcode"
},
  "geometry": {"coordinates":[-2.05561216612581,52.96565650181994],"type":"Point"}
}