{
  "type": "Feature",
  "properties": {
    "iso:country": "GB",
    "wof:name": "ST11 9JN",
    "wof:placetype": "postalcode"
  },
  "geometry": {"coordinates":[-2.055612,52.965656],"type":"Point"}
}
