{
  "type": "Feature",
  "properties": {
    "date:inception_lower": "1990-07-01",
    "date:inception_upper": "1990-07-01",
    "iso:country": "GB",
    "wof:name": "MK17 0BB",
    "wof:placetype": "postalcode"
  },
  "geometry": {"coordinates":[-0.764967,51.975361],"type":"Point"}
}
