{
  "type": "Feature",
  "properties": {
    "date:inception_lower":"1994-05-01",
    "date:inception_upper":"1994-05-31",
    "iso:country":"GB",
    "wof:name":"M28 2RY",
    "wof:placetype":"postalcode"
},
  "geometry": {"coordinates":[-2.387615,53.507874],"type":"Point"}
}