{
  "type": "Feature",
  "properties": {
    "iso:country":"GB",
    "wof:name":"M28 2RY",
    "wof:placetype":"postalcode"
},
  "geometry": {"coordinates":[-2.38761546225444,53.5078742969202],"type":"Point"}
}