{
  "type": "Feature",
  "properties": {
    "iso:country":"GB",
    "wof:name":"EN1 4NW",
    "wof:placetype":"postalcode"
},
  "geometry": {"coordinates":[-0.05559049239153,51.67397931136724],"type":"Point"}
}