{
  "type": "Feature",
  "properties": {
    "iso:country":"GB",
    "wof:name":"B75 7LQ",
    "wof:placetype":"postalcode"
},
  "geometry": {"coordinates":[-1.78580639531473,52.56241309923127],"type":"Point"}
}