{
  "type": "Feature",
  "properties": {
    "iso:country": "GB",
    "wof:name": "EX5 4EF",
    "wof:placetype": "postalcode"
  },
  "geometry": {"coordinates":[-3.508841,50.764114],"type":"Point"}
}
