{
  "type": "Feature",
  "properties": {
    "iso:country":"GB",
    "wof:name":"EX5 4EF",
    "wof:placetype":"postalcode"
},
  "geometry": {"coordinates":[-3.50884061885449,50.76411432033117],"type":"Point"}
}