{
  "type": "Feature",
  "properties": {
    "date:inception_lower":"1980-01-01",
    "date:inception_upper":"1980-01-31",
    "iso:country":"GB",
    "wof:name":"EX5 4EF",
    "wof:placetype":"postalcode"
},
  "geometry": {"coordinates":[-3.508841,50.764114],"type":"Point"}
}