{
  "type": "Feature",
  "properties": {
    "date:inception_lower":"1980-01-01",
    "date:inception_upper":"1980-01-31",
    "iso:country":"GB",
    "wof:name":"RH20 3NT",
    "wof:placetype":"postalcode"
},
  "geometry": {"coordinates":[-0.440441,50.925331],"type":"Point"}
}