{
  "type": "Feature",
  "properties": {
    "iso:country":"GB",
    "wof:name":"RH20 3NT",
    "wof:placetype":"postalcode"
},
  "geometry": {"coordinates":[-0.44044134074656,50.92533072924844],"type":"Point"}
}