{
  "type": "Feature",
  "properties": {
    "iso:country": "GB",
    "wof:name": "RH20 3NT",
    "wof:placetype": "postalcode"
  },
  "geometry": {"coordinates":[-0.440441,50.925331],"type":"Point"}
}
