{
  "type": "Feature",
  "properties": {
    "iso:country":"GB",
    "wof:name":"SW15 5BS",
    "wof:placetype":"postalcode"
},
  "geometry": {"coordinates":[-0.23588060650689,51.45343835834489],"type":"Point"}
}