{
  "type": "Feature",
  "properties": {
    "iso:country":"GB",
    "wof:name":"SE18 3JA",
    "wof:placetype":"postalcode"
},
  "geometry": {"coordinates":[0.0697368673475,51.46658829932088],"type":"Point"}
}