{
  "type": "Feature",
  "properties": {
    "date:inception_lower": "1980-01-01",
    "date:inception_upper": "1980-01-01",
    "iso:country": "GB",
    "wof:name": "SE18 3JA",
    "wof:placetype": "postalcode"
  },
  "geometry": {"coordinates":[0.06902,51.467978],"type":"Point"}
}
