{
  "type": "Feature",
  "properties": {
    "iso:country":"GB",
    "wof:name":"B27 7PU",
    "wof:placetype":"postalcode"
},
  "geometry": {"coordinates":[-1.83358599800758,52.44158416241753],"type":"Point"}
}