{
  "type": "Feature",
  "properties": {
    "date:inception_lower": "1986-06-01",
    "date:inception_upper": "1986-06-01",
    "iso:country": "GB",
    "wof:name": "EH7 5AN",
    "wof:placetype": "postalcode"
  },
  "geometry": {"coordinates":[-3.172363,55.956847],"type":"Point"}
}
