{
  "type": "Feature",
  "properties": {
    "iso:country":"GB",
    "wof:name":"M28 7UQ",
    "wof:placetype":"postalcode"
},
  "geometry": {"coordinates":[-2.4093538945279,53.51527119719934],"type":"Point"}
}