{
  "type": "Feature",
  "properties": {
    "iso:country":"GB",
    "wof:name":"CF38 1DL",
    "wof:placetype":"postalcode"
},
  "geometry": {"coordinates":[-3.32090550046608,51.57066481480314],"type":"Point"}
}