{
  "type": "Feature",
  "properties": {
    "iso:country": "GB",
    "wof:name": "WA8 6DH",
    "wof:placetype": "postalcode"
  },
  "geometry": {"coordinates":[-2.729165,53.361918],"type":"Point"}
}
