{
  "type": "Feature",
  "properties": {
    "iso:country":"GB",
    "wof:name":"WA8 6DH",
    "wof:placetype":"postalcode"
},
  "geometry": {"coordinates":[-2.72926929591384,53.36189183558273],"type":"Point"}
}