{
  "type": "Feature",
  "properties": {
    "date:inception_lower": "2013-01-01",
    "date:inception_upper": "2013-01-01",
    "iso:country": "GB",
    "wof:name": "N7 8DE",
    "wof:placetype": "postalcode"
  },
  "geometry": {"coordinates":[-0.116159,51.54847],"type":"Point"}
}
