{
  "type": "Feature",
  "properties": {
    "iso:country":"GB",
    "wof:name":"N7 8DE",
    "wof:placetype":"postalcode"
},
  "geometry": {"coordinates":[-0.11615881266172,51.54847040156488],"type":"Point"}
}