{
  "type": "Feature",
  "properties": {
    "iso:country":"GB",
    "wof:name":"L36 2LD",
    "wof:placetype":"postalcode"
},
  "geometry": {"coordinates":[-2.85385967500039,53.4191602967944],"type":"Point"}
}