{
  "type": "Feature",
  "properties": {
    "iso:country": "GB",
    "wof:name": "L36 2LD",
    "wof:placetype": "postalcode"
  },
  "geometry": {"coordinates":[-2.85386,53.41916],"type":"Point"}
}
