{
  "type": "Feature",
  "properties": {
    "date:inception_lower": "1980-01-01",
    "date:inception_upper": "1980-01-01",
    "iso:country": "GB",
    "wof:name": "L36 2LD",
    "wof:placetype": "postalcode"
  },
  "geometry": {"coordinates":[-2.85386,53.41916],"type":"Point"}
}
