{
  "type": "Feature",
  "properties": {
    "iso:country": "GB",
    "wof:name": "CV34 5EQ",
    "wof:placetype": "postalcode"
  },
  "geometry": {"coordinates":[-1.591706,52.289746],"type":"Point"}
}
