{
  "type": "Feature",
  "properties": {
    "iso:country":"GB",
    "wof:name":"MK40 1RW",
    "wof:placetype":"postalcode"
},
  "geometry": {"coordinates":[-0.46531017622354,52.13498662476735],"type":"Point"}
}