{
  "type": "Feature",
  "properties": {
    "date:inception_lower": "1998-12-01",
    "date:inception_upper": "1998-12-01",
    "iso:country": "GB",
    "wof:name": "IV2 6AL",
    "wof:placetype": "postalcode"
  },
  "geometry": {"coordinates":[-4.239448,57.37856],"type":"Point"}
}
