{
  "type": "Feature",
  "properties": {
    "iso:country":"GB",
    "wof:name":"IV2 6AL",
    "wof:placetype":"postalcode"
},
  "geometry": {"coordinates":[-4.23944854556417,57.37855990375258],"type":"Point"}
}