{
  "type": "Feature",
  "properties": {
    "date:inception_lower": "1980-01-01",
    "date:inception_upper": "1980-01-01",
    "iso:country": "GB",
    "wof:name": "SY8 2DX",
    "wof:placetype": "postalcode"
  },
  "geometry": {"coordinates":[-2.686111,52.383075],"type":"Point"}
}
