{
  "type": "Feature",
  "properties": {
    "iso:country": "GB",
    "wof:name": "SY8 2DX",
    "wof:placetype": "postalcode"
  },
  "geometry": {"coordinates":[-2.686126,52.383093],"type":"Point"}
}
