{
  "type": "Feature",
  "properties": {
    "iso:country":"GB",
    "wof:name":"SY8 2DX",
    "wof:placetype":"postalcode"
},
  "geometry": {"coordinates":[-2.68612740462056,52.38307965455233],"type":"Point"}
}