{
  "type": "Feature",
  "properties": {
    "iso:country":"GB",
    "wof:name":"RH20 3PJ",
    "wof:placetype":"postalcode"
},
  "geometry": {"coordinates":[-0.44602579110954,50.92214071259792],"type":"Point"}
}