{
  "type": "Feature",
  "properties": {
    "iso:country":"GB",
    "wof:name":"SG14 3HB",
    "wof:placetype":"postalcode"
},
  "geometry": {"coordinates":[-0.08023240551617,51.8045927325696],"type":"Point"}
}