{
  "type": "Feature",
  "properties": {
    "iso:country":"GB",
    "wof:name":"DE6 3JJ",
    "wof:placetype":"postalcode"
},
  "geometry": {"coordinates":[-1.60599243977053,53.04904870993124],"type":"Point"}
}