{
  "type": "Feature",
  "properties": {
    "iso:country": "GB",
    "wof:name": "DE6 3JJ",
    "wof:placetype": "postalcode"
  },
  "geometry": {"coordinates":[-1.605992,53.049049],"type":"Point"}
}
