{
  "type": "Feature",
  "properties": {
    "iso:country":"GB",
    "wof:name":"BS20 6YY",
    "wof:placetype":"postalcode"
},
  "geometry": {"coordinates":[-2.7629587364343,51.48070437557035],"type":"Point"}
}