{
  "type": "Feature",
  "properties": {
    "iso:country":"GB",
    "wof:name":"IP6 0NA",
    "wof:placetype":"postalcode"
},
  "geometry": {"coordinates":[1.09017113917586,52.11433579075497],"type":"Point"}
}