{
  "type": "Feature",
  "properties": {
    "date:inception_lower":"2013-04-01",
    "date:inception_upper":"2013-04-30",
    "iso:country":"GB",
    "wof:name":"BA12 8FN",
    "wof:placetype":"postalcode"
},
  "geometry": {"coordinates":[-2.20404,51.205319],"type":"Point"}
}