{
  "type": "Feature",
  "properties": {
    "iso:country":"GB",
    "wof:name":"BA12 8FN",
    "wof:placetype":"postalcode"
},
  "geometry": {"coordinates":[-2.20403966946659,51.20531866209196],"type":"Point"}
}