{
  "type": "Feature",
  "properties": {
    "iso:country":"GB",
    "wof:name":"RG2 8AE",
    "wof:placetype":"postalcode"
},
  "geometry": {"coordinates":[-0.96360359953441,51.42498320764986],"type":"Point"}
}