{
  "type": "Feature",
  "properties": {
    "iso:country": "GB",
    "wof:name": "RG2 8AE",
    "wof:placetype": "postalcode"
  },
  "geometry": {"coordinates":[-0.963604,51.424983],"type":"Point"}
}
