{
  "type": "Feature",
  "properties": {
    "date:inception_lower":"1993-01-01",
    "date:inception_upper":"1993-01-31",
    "iso:country":"GB",
    "wof:name":"SR3 2TU",
    "wof:placetype":"postalcode"
},
  "geometry": {"coordinates":[-1.404951,54.859701],"type":"Point"}
}