{
  "type": "Feature",
  "properties": {
    "iso:country": "GB",
    "wof:name": "L31 8DR",
    "wof:placetype": "postalcode"
  },
  "geometry": {"coordinates":[-2.952218,53.519226],"type":"Point"}
}
