{
  "type": "Feature",
  "properties": {
    "date:inception_lower": "1980-01-01",
    "date:inception_upper": "1980-01-01",
    "iso:country": "GB",
    "wof:name": "L31 8DR",
    "wof:placetype": "postalcode"
  },
  "geometry": {"coordinates":[-2.952218,53.519226],"type":"Point"}
}
