{
  "type": "Feature",
  "properties": {
    "iso:country":"GB",
    "wof:name":"L31 8DR",
    "wof:placetype":"postalcode"
},
  "geometry": {"coordinates":[-2.95221799352043,53.51922590553521],"type":"Point"}
}