{
  "type": "Feature",
  "properties": {
    "iso:country":"GB",
    "wof:name":"LE7 7GL",
    "wof:placetype":"postalcode"
},
  "geometry": {"coordinates":[-1.17453414368943,52.66216285352714],"type":"Point"}
}