{
  "type": "Feature",
  "properties": {
    "date:inception_lower": "2002-06-01",
    "date:inception_upper": "2002-06-01",
    "iso:country": "GB",
    "wof:name": "PE15 9BX",
    "wof:placetype": "postalcode"
  },
  "geometry": {"coordinates":[0.091596,52.549338],"type":"Point"}
}
