{
  "type": "Feature",
  "properties": {
    "iso:country": "GB",
    "wof:name": "NR11 8JD",
    "wof:placetype": "postalcode"
  },
  "geometry": {"coordinates":[1.417193,52.884759],"type":"Point"}
}
