{
  "type": "Feature",
  "properties": {
    "date:inception_lower":"1991-01-01",
    "date:inception_upper":"1991-01-31",
    "iso:country":"GB",
    "wof:name":"NR11 8JD",
    "wof:placetype":"postalcode"
},
  "geometry": {"coordinates":[1.417193,52.884759],"type":"Point"}
}