{
  "type": "Feature",
  "properties": {
    "iso:country":"GB",
    "wof:name":"SA6 5BX",
    "wof:placetype":"postalcode"
},
  "geometry": {"coordinates":[-3.89980977089496,51.69502331784939],"type":"Point"}
}