{
  "type": "Feature",
  "properties": {
    "iso:country":"GB",
    "wof:name":"HP22 6PA",
    "wof:placetype":"postalcode"
},
  "geometry": {"coordinates":[-0.73570257762178,51.76661203071702],"type":"Point"}
}