{
  "type": "Feature",
  "properties": {
    "iso:country":"GB",
    "wof:name":"IP17 1UA",
    "wof:placetype":"postalcode"
},
  "geometry": {"coordinates":[1.55870484337529,52.19488223781705],"type":"Point"}
}