{
  "type": "Feature",
  "properties": {
    "iso:country":"GB",
    "wof:name":"BN17 6LN",
    "wof:placetype":"postalcode"
},
  "geometry": {"coordinates":[-0.54294568712627,50.81869352988019],"type":"Point"}
}