{
  "type": "Feature",
  "properties": {
    "date:inception_lower": "1980-01-01",
    "date:inception_upper": "1980-01-01",
    "iso:country": "GB",
    "wof:name": "BN17 6LN",
    "wof:placetype": "postalcode"
  },
  "geometry": {"coordinates":[-0.542946,50.818694],"type":"Point"}
}
