{
  "type": "Feature",
  "properties": {
    "iso:country": "GB",
    "wof:name": "BN17 6LN",
    "wof:placetype": "postalcode"
  },
  "geometry": {"coordinates":[-0.542946,50.818694],"type":"Point"}
}
