{
  "type": "Feature",
  "properties": {
    "date:inception_lower": "2023-04-01",
    "date:inception_upper": "2023-04-01",
    "iso:country": "GB",
    "wof:name": "WR10 1FJ",
    "wof:placetype": "postalcode"
  },
  "geometry": {"coordinates":[-2.079294,52.126173],"type":"Point"}
}
