{
  "type": "Feature",
  "properties": {
    "iso:country": "GB",
    "wof:name": "CV31 2JY",
    "wof:placetype": "postalcode"
  },
  "geometry": {"coordinates":[-1.532018,52.266339],"type":"Point"}
}
