{
  "type": "Feature",
  "properties": {
    "date:inception_lower": "1980-01-01",
    "date:inception_upper": "1980-01-01",
    "iso:country": "GB",
    "wof:name": "BB10 4TA",
    "wof:placetype": "postalcode"
  },
  "geometry": {"coordinates":[-2.172292,53.742627],"type":"Point"}
}
