{
  "type": "Feature",
  "properties": {
    "date:inception_lower": "2001-12-01",
    "date:inception_upper": "2001-12-01",
    "iso:country": "GB",
    "wof:name": "DD2 3BA",
    "wof:placetype": "postalcode"
  },
  "geometry": {"coordinates":[-3.008373,56.486888],"type":"Point"}
}
