{
  "type": "Feature",
  "properties": {
    "iso:country":"GB",
    "wof:name":"DD2 3BA",
    "wof:placetype":"postalcode"
},
  "geometry": {"coordinates":[-3.00837317621004,56.48688820444347],"type":"Point"}
}