{
  "type": "Feature",
  "properties": {
    "iso:country":"GB",
    "wof:name":"NE13 6NG",
    "wof:placetype":"postalcode"
},
  "geometry": {"coordinates":[-1.62472102760864,55.05321723899205],"type":"Point"}
}