{
  "type": "Feature",
  "properties": {
    "date:inception_lower":"1980-01-01",
    "date:inception_upper":"1980-01-31",
    "iso:country":"GB",
    "wof:name":"NE13 6NG",
    "wof:placetype":"postalcode"
},
  "geometry": {"coordinates":[-1.624721,55.053217],"type":"Point"}
}