{
  "type": "Feature",
  "properties": {
    "iso:country":"GB",
    "wof:name":"RH20 4HR",
    "wof:placetype":"postalcode"
},
  "geometry": {"coordinates":[-0.48032998813361,50.92037993391505],"type":"Point"}
}