{
  "type": "Feature",
  "properties": {
    "date:inception_lower": "1980-01-01",
    "date:inception_upper": "1980-01-01",
    "iso:country": "GB",
    "wof:name": "RH20 4HR",
    "wof:placetype": "postalcode"
  },
  "geometry": {"coordinates":[-0.480335,50.920364],"type":"Point"}
}
