{
  "type": "Feature",
  "properties": {
    "iso:country":"GB",
    "wof:name":"PE6 8QN",
    "wof:placetype":"postalcode"
},
  "geometry": {"coordinates":[-0.30232743966093,52.67811577396086],"type":"Point"}
}