{
  "type": "Feature",
  "properties": {
    "iso:country": "GB",
    "wof:name": "PE6 8QN",
    "wof:placetype": "postalcode"
  },
  "geometry": {"coordinates":[-0.302327,52.678116],"type":"Point"}
}
