{
  "type": "Feature",
  "properties": {
    "date:inception_lower": "1981-06-01",
    "date:inception_upper": "1981-06-01",
    "iso:country": "GB",
    "wof:name": "PE6 8QN",
    "wof:placetype": "postalcode"
  },
  "geometry": {"coordinates":[-0.302327,52.678116],"type":"Point"}
}
