{
  "type": "Feature",
  "properties": {
    "iso:country":"GB",
    "wof:name":"B75 5EF",
    "wof:placetype":"postalcode"
},
  "geometry": {"coordinates":[-1.82781226986928,52.59060169974654],"type":"Point"}
}