{
  "type": "Feature",
  "properties": {
    "iso:country":"GB",
    "wof:name":"SR8 5DB",
    "wof:placetype":"postalcode"
},
  "geometry": {"coordinates":[-1.33108797262039,54.76213514826838],"type":"Point"}
}