{
  "type": "Feature",
  "properties": {
    "iso:country": "GB",
    "wof:name": "DA9 9NT",
    "wof:placetype": "postalcode"
  },
  "geometry": {"coordinates":[0.284882,51.452682],"type":"Point"}
}
