{
  "type": "Feature",
  "properties": {
    "iso:country":"GB",
    "wof:name":"DA9 9NT",
    "wof:placetype":"postalcode"
},
  "geometry": {"coordinates":[0.28488180796434,51.45268179420913],"type":"Point"}
}