{
  "type": "Feature",
  "properties": {
    "iso:country":"GB",
    "wof:name":"WA12 0DU",
    "wof:placetype":"postalcode"
},
  "geometry": {"coordinates":[-2.61593344154967,53.4573074998584],"type":"Point"}
}