{
  "type": "Feature",
  "properties": {
    "iso:country": "GB",
    "wof:name": "WA12 0DU",
    "wof:placetype": "postalcode"
  },
  "geometry": {"coordinates":[-2.615933,53.457307],"type":"Point"}
}
