{
  "type": "Feature",
  "properties": {
    "date:inception_lower":"2004-03-01",
    "date:inception_upper":"2004-03-31",
    "iso:country":"GB",
    "wof:name":"WF2 7AX",
    "wof:placetype":"postalcode"
},
  "geometry": {"coordinates":[-1.506121,53.667909],"type":"Point"}
}