{
  "type": "Feature",
  "properties": {
    "iso:country": "GB",
    "wof:name": "ML2 9AG",
    "wof:placetype": "postalcode"
  },
  "geometry": {"coordinates":[-3.867159,55.786589],"type":"Point"}
}
