{
  "type": "Feature",
  "properties": {
    "iso:country":"GB",
    "wof:name":"TS10 2AT",
    "wof:placetype":"postalcode"
},
  "geometry": {"coordinates":[-1.06411872687762,54.61407908544504],"type":"Point"}
}