{
  "type": "Feature",
  "properties": {
    "iso:country":"GB",
    "wof:name":"RM7 0QR",
    "wof:placetype":"postalcode"
},
  "geometry": {"coordinates":[0.17380622283224,51.56591073347904],"type":"Point"}
}