{
  "type": "Feature",
  "properties": {
    "iso:country":"GB",
    "wof:name":"WN2 4JE",
    "wof:placetype":"postalcode"
},
  "geometry": {"coordinates":[-2.56059915476704,53.53475563032104],"type":"Point"}
}