{
  "type": "Feature",
  "properties": {
    "iso:country": "GB",
    "wof:name": "PO20 8SE",
    "wof:placetype": "postalcode"
  },
  "geometry": {"coordinates":[-0.858432,50.766136],"type":"Point"}
}
