{
  "type": "Feature",
  "properties": {
    "iso:country":"GB",
    "wof:name":"PO20 8SE",
    "wof:placetype":"postalcode"
},
  "geometry": {"coordinates":[-0.85843210994166,50.76613561192768],"type":"Point"}
}