{
  "type": "Feature",
  "properties": {
    "iso:country":"GB",
    "wof:name":"RM9 4RD",
    "wof:placetype":"postalcode"
},
  "geometry": {"coordinates":[0.11246733430168,51.53477414876212],"type":"Point"}
}