{
  "type": "Feature",
  "properties": {
    "iso:country":"GB",
    "wof:name":"LS24 8DG",
    "wof:placetype":"postalcode"
},
  "geometry": {"coordinates":[-1.23789056331655,53.92109370396278],"type":"Point"}
}