{
  "type": "Feature",
  "properties": {
    "iso:country":"GB",
    "wof:name":"CT8 8NE",
    "wof:placetype":"postalcode"
},
  "geometry": {"coordinates":[1.33390746931886,51.37751425225062],"type":"Point"}
}