{
  "type": "Feature",
  "properties": {
    "iso:country": "GB",
    "wof:name": "CT8 8NE",
    "wof:placetype": "postalcode"
  },
  "geometry": {"coordinates":[1.333908,51.377514],"type":"Point"}
}
