{
  "type": "Feature",
  "properties": {
    "date:inception_lower": "2022-12-01",
    "date:inception_upper": "2022-12-01",
    "iso:country": "GB",
    "wof:name": "PE7 8TX",
    "wof:placetype": "postalcode"
  },
  "geometry": {"coordinates":[-0.266903,52.526485],"type":"Point"}
}
