{
  "type": "Feature",
  "properties": {
    "iso:country":"GB",
    "wof:name":"SW9 6QH",
    "wof:placetype":"postalcode"
},
  "geometry": {"coordinates":[-0.10873662650161,51.47247187430474],"type":"Point"}
}