{
  "type": "Feature",
  "properties": {
    "iso:country":"GB",
    "wof:name":"L25 7UN",
    "wof:placetype":"postalcode"
},
  "geometry": {"coordinates":[-2.87158744110447,53.36188095656664],"type":"Point"}
}