{
  "type": "Feature",
  "properties": {
    "date:inception_lower":"1980-01-01",
    "date:inception_upper":"1980-01-31",
    "iso:country":"GB",
    "wof:name":"SP5 1BL",
    "wof:placetype":"postalcode"
},
  "geometry": {"coordinates":[-1.693697,51.104386],"type":"Point"}
}