{
  "type": "Feature",
  "properties": {
    "iso:country": "GB",
    "wof:name": "SP5 1BL",
    "wof:placetype": "postalcode"
  },
  "geometry": {"coordinates":[-1.693697,51.104386],"type":"Point"}
}
