{
  "type": "Feature",
  "properties": {
    "iso:country":"GB",
    "wof:name":"SP5 1BL",
    "wof:placetype":"postalcode"
},
  "geometry": {"coordinates":[-1.69369660308162,51.10438615830039],"type":"Point"}
}