{
  "type": "Feature",
  "properties": {
    "iso:country": "GB",
    "wof:name": "EN6 4EJ",
    "wof:placetype": "postalcode"
  },
  "geometry": {"coordinates":[-0.11888,51.713785],"type":"Point"}
}
