{
  "type": "Feature",
  "properties": {
    "iso:country":"GB",
    "wof:name":"SG4 0BX",
    "wof:placetype":"postalcode"
},
  "geometry": {"coordinates":[-0.26048244406438,51.95855971568877],"type":"Point"}
}