{
  "type": "Feature",
  "properties": {
    "iso:country":"GB",
    "wof:name":"TS4 2QN",
    "wof:placetype":"postalcode"
},
  "geometry": {"coordinates":[-1.21780067640891,54.56247807350557],"type":"Point"}
}