{
  "type": "Feature",
  "properties": {
    "date:inception_lower": "1980-01-01",
    "date:inception_upper": "1980-01-01",
    "iso:country": "GB",
    "wof:name": "KT19 9HZ",
    "wof:placetype": "postalcode"
  },
  "geometry": {"coordinates":[-0.283719,51.362524],"type":"Point"}
}
