{
  "type": "Feature",
  "properties": {
    "date:inception_lower": "2021-11-01",
    "date:inception_upper": "2021-11-01",
    "iso:country": "GB",
    "wof:name": "G78 1FL",
    "wof:placetype": "postalcode"
  },
  "geometry": {"coordinates":[-4.394327,55.813799],"type":"Point"}
}
