{
  "type": "Feature",
  "properties": {
    "iso:country": "GB",
    "wof:name": "CO4 3QZ",
    "wof:placetype": "postalcode"
  },
  "geometry": {"coordinates":[0.930323,51.888833],"type":"Point"}
}
