{
  "type": "Feature",
  "properties": {
    "date:inception_lower":"1980-01-01",
    "date:inception_upper":"1980-01-31",
    "iso:country":"GB",
    "wof:name":"CO4 3QZ",
    "wof:placetype":"postalcode"
},
  "geometry": {"coordinates":[0.930323,51.888833],"type":"Point"}
}