{
  "type": "Feature",
  "properties": {
    "iso:country":"GB",
    "wof:name":"CT9 1UH",
    "wof:placetype":"postalcode"
},
  "geometry": {"coordinates":[1.38023142541665,51.38744761141861],"type":"Point"}
}