{
  "type": "Feature",
  "properties": {
    "iso:country":"GB",
    "wof:name":"SG17 5AL",
    "wof:placetype":"postalcode"
},
  "geometry": {"coordinates":[-0.32911534691884,52.0361533018886],"type":"Point"}
}