{
  "type": "Feature",
  "properties": {
    "iso:country":"GB",
    "wof:name":"SA1 1EJ",
    "wof:placetype":"postalcode"
},
  "geometry": {"coordinates":[-3.940007996368,51.61923455056103],"type":"Point"}
}