{
  "type": "Feature",
  "properties": {
    "iso:country": "GB",
    "wof:name": "SA1 1EJ",
    "wof:placetype": "postalcode"
  },
  "geometry": {"coordinates":[-3.940008,51.619235],"type":"Point"}
}
