{
  "type": "Feature",
  "properties": {
    "date:inception_lower":"2000-12-01",
    "date:inception_upper":"2000-12-31",
    "iso:country":"GB",
    "wof:name":"SA1 1EJ",
    "wof:placetype":"postalcode"
},
  "geometry": {"coordinates":[-3.940008,51.619235],"type":"Point"}
}