{
  "type": "Feature",
  "properties": {
    "iso:country":"GB",
    "wof:name":"PO21 2UX",
    "wof:placetype":"postalcode"
},
  "geometry": {"coordinates":[-0.68873128246651,50.78865959160167],"type":"Point"}
}