{
  "type": "Feature",
  "properties": {
    "iso:country":"GB",
    "wof:name":"SR7 9SS",
    "wof:placetype":"postalcode"
},
  "geometry": {"coordinates":[-1.40618069136804,54.81947407710256],"type":"Point"}
}