{
  "type": "Feature",
  "properties": {
    "date:inception_lower": "1980-01-01",
    "date:inception_upper": "1980-01-01",
    "iso:country": "GB",
    "wof:name": "SR7 9SS",
    "wof:placetype": "postalcode"
  },
  "geometry": {"coordinates":[-1.406181,54.819474],"type":"Point"}
}
