{
  "type": "Feature",
  "properties": {
    "iso:country":"GB",
    "wof:name":"B90 1AZ",
    "wof:placetype":"postalcode"
},
  "geometry": {"coordinates":[-1.85128277567654,52.40683418200671],"type":"Point"}
}