{
  "type": "Feature",
  "properties": {
    "iso:country": "GB",
    "wof:name": "FK4 1QF",
    "wof:placetype": "postalcode"
  },
  "geometry": {"coordinates":[-3.910603,55.998357],"type":"Point"}
}
