{
  "type": "Feature",
  "properties": {
    "iso:country":"GB",
    "wof:name":"NN3 8NE",
    "wof:placetype":"postalcode"
},
  "geometry": {"coordinates":[-0.83369810782082,52.26417752871075],"type":"Point"}
}