{
  "type": "Feature",
  "properties": {
    "iso:country": "GB",
    "wof:name": "DE11 9RY",
    "wof:placetype": "postalcode"
  },
  "geometry": {"coordinates":[-1.580649,52.765419],"type":"Point"}
}
