{
  "type": "Feature",
  "properties": {
    "iso:country":"GB",
    "wof:name":"DE11 9RY",
    "wof:placetype":"postalcode"
},
  "geometry": {"coordinates":[-1.58064909641283,52.76541939911749],"type":"Point"}
}