{
  "type": "Feature",
  "properties": {
    "iso:country":"GB",
    "wof:name":"DG2 8RB",
    "wof:placetype":"postalcode"
},
  "geometry": {"coordinates":[-3.83310206549496,55.03613285480847],"type":"Point"}
}