{
  "type": "Feature",
  "properties": {
    "iso:country": "GB",
    "wof:name": "DG2 8RB",
    "wof:placetype": "postalcode"
  },
  "geometry": {"coordinates":[-3.833102,55.036133],"type":"Point"}
}
