{
  "type": "Feature",
  "properties": {
    "date:inception_lower": "2018-07-01",
    "date:inception_upper": "2018-07-01",
    "iso:country": "GB",
    "wof:name": "BD16 1FH",
    "wof:placetype": "postalcode"
  },
  "geometry": {"coordinates":[-1.865265,53.833571],"type":"Point"}
}
