{
  "type": "Feature",
  "properties": {
    "iso:country": "GB",
    "wof:name": "HA2 8UU",
    "wof:placetype": "postalcode"
  },
  "geometry": {"coordinates":[-0.352001,51.566102],"type":"Point"}
}
