{
  "type": "Feature",
  "properties": {
    "date:inception_lower": "1990-07-01",
    "date:inception_upper": "1990-07-01",
    "iso:country": "GB",
    "wof:name": "HP14 3RF",
    "wof:placetype": "postalcode"
  },
  "geometry": {"coordinates":[-0.892823,51.658306],"type":"Point"}
}
