{
  "type": "Feature",
  "properties": {
    "iso:country": "GB",
    "wof:name": "DN7 4QD",
    "wof:placetype": "postalcode"
  },
  "geometry": {"coordinates":[-1.033537,53.56254],"type":"Point"}
}
