{
  "type": "Feature",
  "properties": {
    "iso:country":"GB",
    "wof:name":"TD12 4SP",
    "wof:placetype":"postalcode"
},
  "geometry": {"coordinates":[-2.17002771206279,55.63121104011142],"type":"Point"}
}