{
  "type": "Feature",
  "properties": {
    "iso:country": "GB",
    "wof:name": "TD12 4SP",
    "wof:placetype": "postalcode"
  },
  "geometry": {"coordinates":[-2.170028,55.631211],"type":"Point"}
}
