{
  "type": "Feature",
  "properties": {
    "date:inception_lower":"1980-01-01",
    "date:inception_upper":"1980-01-31",
    "iso:country":"GB",
    "wof:name":"TD12 4SP",
    "wof:placetype":"postalcode"
},
  "geometry": {"coordinates":[-2.170028,55.631211],"type":"Point"}
}