{
  "type": "Feature",
  "properties": {
    "iso:country": "GB",
    "wof:name": "BD14 6ES",
    "wof:placetype": "postalcode"
  },
  "geometry": {"coordinates":[-1.814543,53.781952],"type":"Point"}
}
