{
  "type": "Feature",
  "properties": {
    "iso:country":"GB",
    "wof:name":"BD14 6ES",
    "wof:placetype":"postalcode"
},
  "geometry": {"coordinates":[-1.81454263817638,53.78195189216105],"type":"Point"}
}