{
  "type": "Feature",
  "properties": {
    "date:inception_lower":"1991-09-01",
    "date:inception_upper":"1991-09-30",
    "iso:country":"GB",
    "wof:name":"BH31 6AT",
    "wof:placetype":"postalcode"
},
  "geometry": {"coordinates":[-1.855022,50.870539],"type":"Point"}
}