{
  "type": "Feature",
  "properties": {
    "iso:country":"GB",
    "wof:name":"BH31 6AT",
    "wof:placetype":"postalcode"
},
  "geometry": {"coordinates":[-1.85502206837632,50.87053859023121],"type":"Point"}
}