{
  "type": "Feature",
  "properties": {
    "iso:country":"GB",
    "wof:name":"IV6 7TP",
    "wof:placetype":"postalcode"
},
  "geometry": {"coordinates":[-4.45820036152102,57.51643010760986],"type":"Point"}
}