{
  "type": "Feature",
  "properties": {
    "iso:country": "GB",
    "wof:name": "S21 1FB",
    "wof:placetype": "postalcode"
  },
  "geometry": {"coordinates":[-1.318538,53.316937],"type":"Point"}
}
