{
  "type": "Feature",
  "properties": {
    "iso:country":"GB",
    "wof:name":"BA1 1QE",
    "wof:placetype":"postalcode"
},
  "geometry": {"coordinates":[-2.35979877588128,51.3804904225729],"type":"Point"}
}