{
  "type": "Feature",
  "properties": {
    "date:inception_lower":"2007-09-01",
    "date:inception_upper":"2007-09-30",
    "iso:country":"GB",
    "wof:name":"WF12 8DN",
    "wof:placetype":"postalcode"
},
  "geometry": {"coordinates":[-1.605681,53.687699],"type":"Point"}
}