{
  "type": "Feature",
  "properties": {
    "date:inception_lower":"1992-01-01",
    "date:inception_upper":"1992-01-31",
    "iso:country":"GB",
    "wof:name":"PE2 5EP",
    "wof:placetype":"postalcode"
},
  "geometry": {"coordinates":[-0.289865,52.553207],"type":"Point"}
}