{
  "type": "Feature",
  "properties": {
    "date:inception_lower": "2004-06-01",
    "date:inception_upper": "2004-06-01",
    "iso:country": "GB",
    "wof:name": "ST4 5BT",
    "wof:placetype": "postalcode"
  },
  "geometry": {"coordinates":[-2.190348,52.994894],"type":"Point"}
}
