{
  "type": "Feature",
  "properties": {
    "date:inception_lower":"1980-01-01",
    "date:inception_upper":"1980-01-31",
    "iso:country":"GB",
    "wof:name":"TW15 2TL",
    "wof:placetype":"postalcode"
},
  "geometry": {"coordinates":[-0.460746,51.433577],"type":"Point"}
}