{
  "type": "Feature",
  "properties": {
    "iso:country":"GB",
    "wof:name":"TW15 2TL",
    "wof:placetype":"postalcode"
},
  "geometry": {"coordinates":[-0.46074555525561,51.4335769788912],"type":"Point"}
}