{
  "type": "Feature",
  "properties": {
    "iso:country":"GB",
    "wof:name":"CM9 5JE",
    "wof:placetype":"postalcode"
},
  "geometry": {"coordinates":[0.68533123826938,51.7248435103981],"type":"Point"}
}