{
  "type": "Feature",
  "properties": {
    "iso:country": "GB",
    "wof:name": "CM9 5JE",
    "wof:placetype": "postalcode"
  },
  "geometry": {"coordinates":[0.685331,51.724844],"type":"Point"}
}
