{
  "type": "Feature",
  "properties": {
    "date:inception_lower": "2001-12-01",
    "date:inception_upper": "2001-12-01",
    "iso:country": "GB",
    "wof:name": "HD7 4QJ",
    "wof:placetype": "postalcode"
  },
  "geometry": {"coordinates":[-1.854793,53.639726],"type":"Point"}
}
