{
  "type": "Feature",
  "properties": {
    "iso:country": "GB",
    "wof:name": "HD7 4QJ",
    "wof:placetype": "postalcode"
  },
  "geometry": {"coordinates":[-1.854793,53.639726],"type":"Point"}
}
