{
  "type": "Feature",
  "properties": {
    "iso:country": "GB",
    "wof:name": "PL18 9AA",
    "wof:placetype": "postalcode"
  },
  "geometry": {"coordinates":[-4.210467,50.508586],"type":"Point"}
}
