{
  "type": "Feature",
  "properties": {
    "date:inception_lower":"1980-01-01",
    "date:inception_upper":"1980-01-31",
    "iso:country":"GB",
    "wof:name":"PL18 9AA",
    "wof:placetype":"postalcode"
},
  "geometry": {"coordinates":[-4.210467,50.508586],"type":"Point"}
}