{
  "type": "Feature",
  "properties": {
    "iso:country":"GB",
    "wof:name":"BS23 3DX",
    "wof:placetype":"postalcode"
},
  "geometry": {"coordinates":[-2.96526211734602,51.34925364189365],"type":"Point"}
}