{
  "type": "Feature",
  "properties": {
    "iso:country":"GB",
    "wof:name":"NG1 7FF",
    "wof:placetype":"postalcode"
},
  "geometry": {"coordinates":[-1.14833764073274,52.94902852263291],"type":"Point"}
}