{
  "type": "Feature",
  "properties": {
    "date:inception_lower": "2017-11-01",
    "date:inception_upper": "2017-11-01",
    "iso:country": "GB",
    "wof:name": "CM17 9SS",
    "wof:placetype": "postalcode"
  },
  "geometry": {"coordinates":[0.152301,51.747678],"type":"Point"}
}
