{
  "type": "Feature",
  "properties": {
    "date:inception_lower": "1988-03-01",
    "date:inception_upper": "1988-03-01",
    "iso:country": "GB",
    "wof:name": "SK3 8UU",
    "wof:placetype": "postalcode"
  },
  "geometry": {"coordinates":[-2.161786,53.387364],"type":"Point"}
}
