{
  "type": "Feature",
  "properties": {
    "iso:country":"GB",
    "wof:name":"HS2 0NW",
    "wof:placetype":"postalcode"
},
  "geometry": {"coordinates":[-6.20548833003997,58.34343857742852],"type":"Point"}
}