{
  "type": "Feature",
  "properties": {
    "iso:country":"GB",
    "wof:name":"NN3 9AZ",
    "wof:placetype":"postalcode"
},
  "geometry": {"coordinates":[-0.81325998812201,52.25198020469752],"type":"Point"}
}