{
  "type": "Feature",
  "properties": {
    "iso:country": "GB",
    "wof:name": "NN3 9AZ",
    "wof:placetype": "postalcode"
  },
  "geometry": {"coordinates":[-0.81326,52.25198],"type":"Point"}
}
