{
  "type": "Feature",
  "properties": {
    "iso:country": "GB",
    "wof:name": "S8 8GG",
    "wof:placetype": "postalcode"
  },
  "geometry": {"coordinates":[-1.474109,53.329139],"type":"Point"}
}
