{
  "type": "Feature",
  "properties": {
    "iso:country":"GB",
    "wof:name":"NG5 4EJ",
    "wof:placetype":"postalcode"
},
  "geometry": {"coordinates":[-1.14693548561504,52.978692781894],"type":"Point"}
}