{
  "type": "Feature",
  "properties": {
    "date:inception_lower": "2005-09-01",
    "date:inception_upper": "2005-09-01",
    "iso:country": "GB",
    "wof:name": "PA1 1UB",
    "wof:placetype": "postalcode"
  },
  "geometry": {"coordinates":[-4.421922,55.841503],"type":"Point"}
}
