{
  "type": "Feature",
  "properties": {
    "iso:country": "GB",
    "wof:name": "PR2 6DB",
    "wof:placetype": "postalcode"
  },
  "geometry": {"coordinates":[-2.666205,53.773142],"type":"Point"}
}
