{
  "type": "Feature",
  "properties": {
    "iso:country": "GB",
    "wof:name": "TR8 5RJ",
    "wof:placetype": "postalcode"
  },
  "geometry": {"coordinates":[-5.105843,50.405052],"type":"Point"}
}
