{
  "type": "Feature",
  "properties": {
    "iso:country":"GB",
    "wof:name":"TR8 5RJ",
    "wof:placetype":"postalcode"
},
  "geometry": {"coordinates":[-5.10584276420548,50.40505214575941],"type":"Point"}
}