{
  "type": "Feature",
  "properties": {
    "iso:country":"GB",
    "wof:name":"SN9 6AF",
    "wof:placetype":"postalcode"
},
  "geometry": {"coordinates":[-1.80024437847092,51.29053388120636],"type":"Point"}
}