{
  "type": "Feature",
  "properties": {
    "iso:country": "GB",
    "wof:name": "SN9 6AF",
    "wof:placetype": "postalcode"
  },
  "geometry": {"coordinates":[-1.800244,51.290534],"type":"Point"}
}
