{
  "type": "Feature",
  "properties": {
    "iso:country":"GB",
    "wof:name":"HR1 1TD",
    "wof:placetype":"postalcode"
},
  "geometry": {"coordinates":[-2.6913760538345,52.04972536944193],"type":"Point"}
}