{
  "type": "Feature",
  "properties": {
    "date:inception_lower":"1992-08-01",
    "date:inception_upper":"1992-08-31",
    "iso:country":"GB",
    "wof:name":"HR1 1TD",
    "wof:placetype":"postalcode"
},
  "geometry": {"coordinates":[-2.691376,52.049725],"type":"Point"}
}