{
  "type": "Feature",
  "properties": {
    "iso:country":"GB",
    "wof:name":"LL29 8SS",
    "wof:placetype":"postalcode"
},
  "geometry": {"coordinates":[-3.65679783277158,53.28085218140193],"type":"Point"}
}