{
  "type": "Feature",
  "properties": {
    "date:inception_lower":"1980-01-01",
    "date:inception_upper":"1980-01-31",
    "iso:country":"GB",
    "wof:name":"E10 6HA",
    "wof:placetype":"postalcode"
},
  "geometry": {"coordinates":[-0.007612,51.572495],"type":"Point"}
}