{
  "type": "Feature",
  "properties": {
    "iso:country":"GB",
    "wof:name":"IG3 8UE",
    "wof:placetype":"postalcode"
},
  "geometry": {"coordinates":[0.10758575485751,51.56737078816139],"type":"Point"}
}