{
  "type": "Feature",
  "properties": {
    "iso:country":"GB",
    "wof:name":"DD11 1NB",
    "wof:placetype":"postalcode"
},
  "geometry": {"coordinates":[-2.58225619560355,56.55821123783375],"type":"Point"}
}