{
  "type": "Feature",
  "properties": {
    "iso:country": "GB",
    "wof:name": "ME10 3NX",
    "wof:placetype": "postalcode"
  },
  "geometry": {"coordinates":[0.758496,51.341057],"type":"Point"}
}
