{
  "type": "Feature",
  "properties": {
    "date:inception_lower": "1980-01-01",
    "date:inception_upper": "1980-01-01",
    "iso:country": "GB",
    "wof:name": "EX15 3LA",
    "wof:placetype": "postalcode"
  },
  "geometry": {"coordinates":[-3.279725,50.912218],"type":"Point"}
}
