{
  "type": "Feature",
  "properties": {
    "date:inception_lower":"1980-01-01",
    "date:inception_upper":"1980-01-31",
    "iso:country":"GB",
    "wof:name":"MK41 6BY",
    "wof:placetype":"postalcode"
},
  "geometry": {"coordinates":[-0.499682,52.163931],"type":"Point"}
}