{
  "type": "Feature",
  "properties": {
    "iso:country": "GB",
    "wof:name": "WS15 2UB",
    "wof:placetype": "postalcode"
  },
  "geometry": {"coordinates":[-1.977023,52.752457],"type":"Point"}
}
