{
  "type": "Feature",
  "properties": {
    "iso:country": "GB",
    "wof:name": "FK2 7FY",
    "wof:placetype": "postalcode"
  },
  "geometry": {"coordinates":[-3.80566,56.011455],"type":"Point"}
}
