{
  "type": "Feature",
  "properties": {
    "iso:country":"GB",
    "wof:name":"BS41 9LS",
    "wof:placetype":"postalcode"
},
  "geometry": {"coordinates":[-2.64887268253983,51.43355572719047],"type":"Point"}
}