{
  "type": "Feature",
  "properties": {
    "date:inception_lower":"1980-01-01",
    "date:inception_upper":"1980-01-31",
    "iso:country":"GB",
    "wof:name":"HA5 1SN",
    "wof:placetype":"postalcode"
},
  "geometry": {"coordinates":[-0.394161,51.583295],"type":"Point"}
}