{
  "type": "Feature",
  "properties": {
    "iso:country": "GB",
    "wof:name": "IP7 6RQ",
    "wof:placetype": "postalcode"
  },
  "geometry": {"coordinates":[1.004198,52.084755],"type":"Point"}
}
