{
  "type": "Feature",
  "properties": {
    "iso:country":"GB",
    "wof:name":"DE1 2BA",
    "wof:placetype":"postalcode"
},
  "geometry": {"coordinates":[-1.47549478685838,52.92108611718857],"type":"Point"}
}