{
  "type": "Feature",
  "properties": {
    "date:inception_lower": "1980-01-01",
    "date:inception_upper": "1980-01-01",
    "iso:country": "GB",
    "wof:name": "GU34 3EH",
    "wof:placetype": "postalcode"
  },
  "geometry": {"coordinates":[-0.984966,51.111794],"type":"Point"}
}
