{
  "type": "Feature",
  "properties": {
    "iso:country": "GB",
    "wof:name": "GU34 3EH",
    "wof:placetype": "postalcode"
  },
  "geometry": {"coordinates":[-0.984966,51.111794],"type":"Point"}
}
