{
  "type": "Feature",
  "properties": {
    "iso:country":"GB",
    "wof:name":"GU34 3EH",
    "wof:placetype":"postalcode"
},
  "geometry": {"coordinates":[-0.98496606111602,51.11179450011002],"type":"Point"}
}