{
  "type": "Feature",
  "properties": {
    "iso:country": "GB",
    "wof:name": "L13 2AU",
    "wof:placetype": "postalcode"
  },
  "geometry": {"coordinates":[-2.923569,53.413453],"type":"Point"}
}
