{
  "type": "Feature",
  "properties": {
    "iso:country":"GB",
    "wof:name":"L13 2AU",
    "wof:placetype":"postalcode"
},
  "geometry": {"coordinates":[-2.92355542256472,53.41350887255543],"type":"Point"}
}