{
  "type": "Feature",
  "properties": {
    "iso:country": "GB",
    "wof:name": "DN2 6QE",
    "wof:placetype": "postalcode"
  },
  "geometry": {"coordinates":[-1.093111,53.533722],"type":"Point"}
}
