{
  "type": "Feature",
  "properties": {
    "date:inception_lower": "1980-01-01",
    "date:inception_upper": "1980-01-01",
    "iso:country": "GB",
    "wof:name": "PH33 7HR",
    "wof:placetype": "postalcode"
  },
  "geometry": {"coordinates":[-5.099644,56.840577],"type":"Point"}
}
