{
  "type": "Feature",
  "properties": {
    "iso:country":"GB",
    "wof:name":"PH33 7HR",
    "wof:placetype":"postalcode"
},
  "geometry": {"coordinates":[-5.09964455366886,56.84057734757549],"type":"Point"}
}