{
  "type": "Feature",
  "properties": {
    "iso:country":"GB",
    "wof:name":"GU52 8EH",
    "wof:placetype":"postalcode"
},
  "geometry": {"coordinates":[-0.82625159714903,51.26393462924187],"type":"Point"}
}