{
  "type": "Feature",
  "properties": {
    "iso:country":"GB",
    "wof:name":"RG17 0EZ",
    "wof:placetype":"postalcode"
},
  "geometry": {"coordinates":[-1.50724052878335,51.42019255298177],"type":"Point"}
}