{
  "type": "Feature",
  "properties": {
    "iso:country":"GB",
    "wof:name":"DT11 8GY",
    "wof:placetype":"postalcode"
},
  "geometry": {"coordinates":[-2.09760614262106,50.89665628735339],"type":"Point"}
}