{
  "type": "Feature",
  "properties": {
    "iso:country":"GB",
    "wof:name":"NG3 7BJ",
    "wof:placetype":"postalcode"
},
  "geometry": {"coordinates":[-1.11224248706588,52.96153858571311],"type":"Point"}
}