{
  "type": "Feature",
  "properties": {
    "iso:country":"GB",
    "wof:name":"S44 6BT",
    "wof:placetype":"postalcode"
},
  "geometry": {"coordinates":[-1.31856356263004,53.23324093201482],"type":"Point"}
}