{
  "type": "Feature",
  "properties": {
    "iso:country": "GB",
    "wof:name": "S44 6BT",
    "wof:placetype": "postalcode"
  },
  "geometry": {"coordinates":[-1.318548,53.233241],"type":"Point"}
}
