{
  "type": "Feature",
  "properties": {
    "date:inception_lower": "1980-01-01",
    "date:inception_upper": "1980-01-01",
    "iso:country": "GB",
    "wof:name": "S44 6BT",
    "wof:placetype": "postalcode"
  },
  "geometry": {"coordinates":[-1.318548,53.233241],"type":"Point"}
}
