{
  "type": "Feature",
  "properties": {
    "iso:country":"GB",
    "wof:name":"BD9 4QP",
    "wof:placetype":"postalcode"
},
  "geometry": {"coordinates":[-1.77740800499444,53.81045258555644],"type":"Point"}
}