{
  "type": "Feature",
  "properties": {
    "iso:country":"GB",
    "wof:name":"BH24 2PT",
    "wof:placetype":"postalcode"
},
  "geometry": {"coordinates":[-1.83335644378936,50.84074464936176],"type":"Point"}
}