{
  "type": "Feature",
  "properties": {
    "date:inception_lower":"2007-01-01",
    "date:inception_upper":"2007-01-31",
    "iso:country":"GB",
    "wof:name":"BH24 2PT",
    "wof:placetype":"postalcode"
},
  "geometry": {"coordinates":[-1.833356,50.840745],"type":"Point"}
}