{
  "type": "Feature",
  "properties": {
    "iso:country": "GB",
    "wof:name": "CV47 2UN",
    "wof:placetype": "postalcode"
  },
  "geometry": {"coordinates":[-1.444775,52.165088],"type":"Point"}
}
