{
  "type": "Feature",
  "properties": {
    "iso:country": "GB",
    "wof:name": "ML2 9FD",
    "wof:placetype": "postalcode"
  },
  "geometry": {"coordinates":[-3.871777,55.790428],"type":"Point"}
}
