{
  "type": "Feature",
  "properties": {
    "iso:country":"GB",
    "wof:name":"B67 5JL",
    "wof:placetype":"postalcode"
},
  "geometry": {"coordinates":[-1.97874050530075,52.47639137331564],"type":"Point"}
}