{
  "type": "Feature",
  "properties": {
    "date:inception_lower": "1980-01-01",
    "date:inception_upper": "1980-01-01",
    "iso:country": "GB",
    "wof:name": "SA46 0AY",
    "wof:placetype": "postalcode"
  },
  "geometry": {"coordinates":[-4.261222,52.241501],"type":"Point"}
}
