{
  "type": "Feature",
  "properties": {
    "date:inception_lower": "1980-01-01",
    "date:inception_upper": "1980-01-01",
    "iso:country": "GB",
    "wof:name": "B70 7SW",
    "wof:placetype": "postalcode"
  },
  "geometry": {"coordinates":[-1.997201,52.510672],"type":"Point"}
}
