{
  "type": "Feature",
  "properties": {
    "iso:country":"GB",
    "wof:name":"LE5 3FJ",
    "wof:placetype":"postalcode"
},
  "geometry": {"coordinates":[-1.11063183751354,52.63877622406137],"type":"Point"}
}