{
  "type": "Feature",
  "properties": {
    "iso:country": "GB",
    "wof:name": "DE15 0EL",
    "wof:placetype": "postalcode"
  },
  "geometry": {"coordinates":[-1.592519,52.803666],"type":"Point"}
}
