{
  "type": "Feature",
  "properties": {
    "iso:country": "GB",
    "wof:name": "LE16 8PX",
    "wof:placetype": "postalcode"
  },
  "geometry": {"coordinates":[-0.813833,52.482245],"type":"Point"}
}
