{
  "type": "Feature",
  "properties": {
    "iso:country": "GB",
    "wof:name": "NG34 7SP",
    "wof:placetype": "postalcode"
  },
  "geometry": {"coordinates":[-0.411055,52.987543],"type":"Point"}
}
