{
  "type": "Feature",
  "properties": {
    "date:inception_lower":"2001-06-01",
    "date:inception_upper":"2001-06-30",
    "iso:country":"GB",
    "wof:name":"NG34 7SP",
    "wof:placetype":"postalcode"
},
  "geometry": {"coordinates":[-0.411055,52.987543],"type":"Point"}
}