{
  "type": "Feature",
  "properties": {
    "iso:country":"GB",
    "wof:name":"LN5 9NT",
    "wof:placetype":"postalcode"
},
  "geometry": {"coordinates":[-0.5385999069464,53.16809483574609],"type":"Point"}
}