{
  "type": "Feature",
  "properties": {
    "iso:country": "GB",
    "wof:name": "LN5 9NT",
    "wof:placetype": "postalcode"
  },
  "geometry": {"coordinates":[-0.538923,53.168642],"type":"Point"}
}
