{
  "type": "Feature",
  "properties": {
    "iso:country":"GB",
    "wof:name":"M44 6RA",
    "wof:placetype":"postalcode"
},
  "geometry": {"coordinates":[-2.42079067150124,53.43821790331889],"type":"Point"}
}