{
  "type": "Feature",
  "properties": {
    "iso:country": "GB",
    "wof:name": "M44 6RA",
    "wof:placetype": "postalcode"
  },
  "geometry": {"coordinates":[-2.420791,53.438218],"type":"Point"}
}
