{
  "type": "Feature",
  "properties": {
    "date:inception_lower":"2000-06-01",
    "date:inception_upper":"2000-06-30",
    "iso:country":"GB",
    "wof:name":"M44 6RA",
    "wof:placetype":"postalcode"
},
  "geometry": {"coordinates":[-2.420791,53.438218],"type":"Point"}
}