{
  "type": "Feature",
  "properties": {
    "iso:country":"GB",
    "wof:name":"CT4 6RN",
    "wof:placetype":"postalcode"
},
  "geometry": {"coordinates":[1.17680699843044,51.17591967929782],"type":"Point"}
}