{
  "type": "Feature",
  "properties": {
    "iso:country": "GB",
    "wof:name": "SY6 6FB",
    "wof:placetype": "postalcode"
  },
  "geometry": {"coordinates":[-2.800008,52.479041],"type":"Point"}
}
