{
  "type": "Feature",
  "properties": {
    "date:inception_lower": "1980-01-01",
    "date:inception_upper": "1980-01-01",
    "iso:country": "GB",
    "wof:name": "TA7 8HA",
    "wof:placetype": "postalcode"
  },
  "geometry": {"coordinates":[-2.93868,51.166202],"type":"Point"}
}
