{
  "type": "Feature",
  "properties": {
    "iso:country":"GB",
    "wof:name":"TA7 8HA",
    "wof:placetype":"postalcode"
},
  "geometry": {"coordinates":[-2.93867992822458,51.16620175970083],"type":"Point"}
}