{
  "type": "Feature",
  "properties": {
    "iso:country": "GB",
    "wof:name": "DE22 2TZ",
    "wof:placetype": "postalcode"
  },
  "geometry": {"coordinates":[-1.474976,52.956592],"type":"Point"}
}
