{
  "type": "Feature",
  "properties": {
    "date:inception_lower": "1992-08-01",
    "date:inception_upper": "1992-08-01",
    "iso:country": "GB",
    "wof:name": "DE22 2TZ",
    "wof:placetype": "postalcode"
  },
  "geometry": {"coordinates":[-1.474976,52.956592],"type":"Point"}
}
