{
  "type": "Feature",
  "properties": {
    "date:inception_lower": "2021-06-01",
    "date:inception_upper": "2021-06-01",
    "iso:country": "GB",
    "wof:name": "TR26 2QZ",
    "wof:placetype": "postalcode"
  },
  "geometry": {"coordinates":[-5.471174,50.192747],"type":"Point"}
}
