{
  "type": "Feature",
  "properties": {
    "iso:country":"GB",
    "wof:name":"GL20 7JG",
    "wof:placetype":"postalcode"
},
  "geometry": {"coordinates":[-2.07679413362056,52.03631980624246],"type":"Point"}
}