{
  "type": "Feature",
  "properties": {
    "iso:country": "GB",
    "wof:name": "GL20 7JG",
    "wof:placetype": "postalcode"
  },
  "geometry": {"coordinates":[-2.076794,52.03632],"type":"Point"}
}
