{
  "type": "Feature",
  "properties": {
    "iso:country":"GB",
    "wof:name":"BS3 1LP",
    "wof:placetype":"postalcode"
},
  "geometry": {"coordinates":[-2.61020364768263,51.44319573146126],"type":"Point"}
}