{
  "type": "Feature",
  "properties": {
    "iso:country":"GB",
    "wof:name":"PO18 8ND",
    "wof:placetype":"postalcode"
},
  "geometry": {"coordinates":[-0.85822003097862,50.83308571113983],"type":"Point"}
}