{
  "type": "Feature",
  "properties": {
    "iso:country":"GB",
    "wof:name":"GL51 3EW",
    "wof:placetype":"postalcode"
},
  "geometry": {"coordinates":[-2.10838422359402,51.88572669632639],"type":"Point"}
}