{
  "type": "Feature",
  "properties": {
    "iso:country":"GB",
    "wof:name":"E8 4LX",
    "wof:placetype":"postalcode"
},
  "geometry": {"coordinates":[-0.06857664561491,51.53927068945229],"type":"Point"}
}