{
  "type": "Feature",
  "properties": {
    "iso:country":"GB",
    "wof:name":"TW1 1NG",
    "wof:placetype":"postalcode"
},
  "geometry": {"coordinates":[-0.3244816187395,51.45938713757442],"type":"Point"}
}