{
  "type": "Feature",
  "properties": {
    "date:inception_lower": "1980-01-01",
    "date:inception_upper": "1980-01-01",
    "iso:country": "GB",
    "wof:name": "LS11 6HR",
    "wof:placetype": "postalcode"
  },
  "geometry": {"coordinates":[-1.548162,53.774423],"type":"Point"}
}
