{
  "type": "Feature",
  "properties": {
    "iso:country": "GB",
    "wof:name": "CT14 6RN",
    "wof:placetype": "postalcode"
  },
  "geometry": {"coordinates":[1.398729,51.236215],"type":"Point"}
}
