{
  "type": "Feature",
  "properties": {
    "iso:country":"GB",
    "wof:name":"GU1 2DE",
    "wof:placetype":"postalcode"
},
  "geometry": {"coordinates":[-0.55046907663061,51.2393350680895],"type":"Point"}
}