{
  "type": "Feature",
  "properties": {
    "iso:country":"GB",
    "wof:name":"M24 1ES",
    "wof:placetype":"postalcode"
},
  "geometry": {"coordinates":[-2.19273603831893,53.54179350551298],"type":"Point"}
}