{
  "type": "Feature",
  "properties": {
    "iso:country":"GB",
    "wof:name":"SK14 3NX",
    "wof:placetype":"postalcode"
},
  "geometry": {"coordinates":[-2.0363676985431,53.44732258680146],"type":"Point"}
}