{
  "type": "Feature",
  "properties": {
    "iso:country":"GB",
    "wof:name":"MK45 3WL",
    "wof:placetype":"postalcode"
},
  "geometry": {"coordinates":[-0.44767233968148,52.07448682770686],"type":"Point"}
}