{
  "type": "Feature",
  "properties": {
    "iso:country": "GB",
    "wof:name": "WR11 2AJ",
    "wof:placetype": "postalcode"
  },
  "geometry": {"coordinates":[-1.948666,52.077133],"type":"Point"}
}
