{
  "type": "Feature",
  "properties": {
    "date:inception_lower": "1983-01-01",
    "date:inception_upper": "1983-01-01",
    "iso:country": "GB",
    "wof:name": "SY4 2EL",
    "wof:placetype": "postalcode"
  },
  "geometry": {"coordinates":[-2.851105,52.787617],"type":"Point"}
}
