{
  "type": "Feature",
  "properties": {
    "iso:country":"GB",
    "wof:name":"SY4 2EL",
    "wof:placetype":"postalcode"
},
  "geometry": {"coordinates":[-2.85122555674293,52.78759203930753],"type":"Point"}
}