{
  "type": "Feature",
  "properties": {
    "iso:country":"GB",
    "wof:name":"M33 2DU",
    "wof:placetype":"postalcode"
},
  "geometry": {"coordinates":[-2.30816741496349,53.42238237783904],"type":"Point"}
}