{
  "type": "Feature",
  "properties": {
    "date:inception_lower":"1996-06-01",
    "date:inception_upper":"1996-06-30",
    "iso:country":"GB",
    "wof:name":"AB54 8RW",
    "wof:placetype":"postalcode"
},
  "geometry": {"coordinates":[-2.798749,57.446787],"type":"Point"}
}