{
  "type": "Feature",
  "properties": {
    "iso:country":"GB",
    "wof:name":"TR7 1RS",
    "wof:placetype":"postalcode"
},
  "geometry": {"coordinates":[-5.07652134246425,50.41218290026162],"type":"Point"}
}