{
  "type": "Feature",
  "properties": {
    "iso:country":"GB",
    "wof:name":"SY23 5BZ",
    "wof:placetype":"postalcode"
},
  "geometry": {"coordinates":[-4.14587656189097,52.28682538776057],"type":"Point"}
}