{
  "type": "Feature",
  "properties": {
    "date:inception_lower": "1998-06-01",
    "date:inception_upper": "1998-06-01",
    "iso:country": "GB",
    "wof:name": "LE67 2JD",
    "wof:placetype": "postalcode"
  },
  "geometry": {"coordinates":[-1.377285,52.707136],"type":"Point"}
}
