{
  "type": "Feature",
  "properties": {
    "iso:country":"GB",
    "wof:name":"PE31 7HR",
    "wof:placetype":"postalcode"
},
  "geometry": {"coordinates":[0.48779210174564,52.90675007647312],"type":"Point"}
}