{
  "type": "Feature",
  "properties": {
    "iso:country": "GB",
    "wof:name": "SG18 0JE",
    "wof:placetype": "postalcode"
  },
  "geometry": {"coordinates":[-0.265531,52.087071],"type":"Point"}
}
