{
  "type": "Feature",
  "properties": {
    "iso:country": "GB",
    "wof:name": "SL9 7DW",
    "wof:placetype": "postalcode"
  },
  "geometry": {"coordinates":[-0.554117,51.579592],"type":"Point"}
}
