{
  "type": "Feature",
  "properties": {
    "iso:country": "GB",
    "wof:name": "L19 9AY",
    "wof:placetype": "postalcode"
  },
  "geometry": {"coordinates":[-2.903145,53.363372],"type":"Point"}
}
