{
  "type": "Feature",
  "properties": {
    "date:inception_lower": "1980-01-01",
    "date:inception_upper": "1980-01-01",
    "iso:country": "GB",
    "wof:name": "L19 9AY",
    "wof:placetype": "postalcode"
  },
  "geometry": {"coordinates":[-2.903145,53.363372],"type":"Point"}
}
