{
  "type": "Feature",
  "properties": {
    "iso:country": "GB",
    "wof:name": "HP10 8PE",
    "wof:placetype": "postalcode"
  },
  "geometry": {"coordinates":[-0.677243,51.621661],"type":"Point"}
}
