{
  "type": "Feature",
  "properties": {
    "iso:country":"GB",
    "wof:name":"HP10 8PE",
    "wof:placetype":"postalcode"
},
  "geometry": {"coordinates":[-0.67724347430383,51.62166075727673],"type":"Point"}
}