{
  "type": "Feature",
  "properties": {
    "iso:country":"GB",
    "wof:name":"BS32 4QE",
    "wof:placetype":"postalcode"
},
  "geometry": {"coordinates":[-2.5626735707729,51.54803248671097],"type":"Point"}
}