{
  "type": "Feature",
  "properties": {
    "iso:country":"GB",
    "wof:name":"DL16 7HW",
    "wof:placetype":"postalcode"
},
  "geometry": {"coordinates":[-1.59624365138404,54.67761924415115],"type":"Point"}
}