{
  "type": "Feature",
  "properties": {
    "iso:country": "GB",
    "wof:name": "TA6 4WU",
    "wof:placetype": "postalcode"
  },
  "geometry": {"coordinates":[-2.986617,51.14619],"type":"Point"}
}
