{
  "type": "Feature",
  "properties": {
    "date:inception_lower": "2019-09-01",
    "date:inception_upper": "2019-09-01",
    "iso:country": "GB",
    "wof:name": "TA6 4WU",
    "wof:placetype": "postalcode"
  },
  "geometry": {"coordinates":[-2.986631,51.14619],"type":"Point"}
}
