{
  "type": "Feature",
  "properties": {
    "iso:country":"GB",
    "wof:name":"SM7 3RB",
    "wof:placetype":"postalcode"
},
  "geometry": {"coordinates":[-0.19448912662883,51.33104820352538],"type":"Point"}
}