{
  "type": "Feature",
  "properties": {
    "iso:country": "GB",
    "wof:name": "SM7 3RB",
    "wof:placetype": "postalcode"
  },
  "geometry": {"coordinates":[-0.194489,51.331048],"type":"Point"}
}
