{
  "type": "Feature",
  "properties": {
    "date:inception_lower": "1980-01-01",
    "date:inception_upper": "1980-01-01",
    "iso:country": "GB",
    "wof:name": "SG18 0EQ",
    "wof:placetype": "postalcode"
  },
  "geometry": {"coordinates":[-0.26384,52.096038],"type":"Point"}
}
