{
  "type": "Feature",
  "properties": {
    "iso:country": "GB",
    "wof:name": "SG18 0EQ",
    "wof:placetype": "postalcode"
  },
  "geometry": {"coordinates":[-0.26384,52.096038],"type":"Point"}
}
