{
  "type": "Feature",
  "properties": {
    "iso:country":"GB",
    "wof:name":"MK2 3AH",
    "wof:placetype":"postalcode"
},
  "geometry": {"coordinates":[-0.72539240946129,51.98880429031256],"type":"Point"}
}