{
  "type": "Feature",
  "properties": {
    "iso:country":"GB",
    "wof:name":"OX20 1DU",
    "wof:placetype":"postalcode"
},
  "geometry": {"coordinates":[-1.36476260278755,51.87459621895656],"type":"Point"}
}