{
  "type": "Feature",
  "properties": {
    "iso:country": "GB",
    "wof:name": "DT3 5ES",
    "wof:placetype": "postalcode"
  },
  "geometry": {"coordinates":[-2.462748,50.628598],"type":"Point"}
}
