{
  "type": "Feature",
  "properties": {
    "date:inception_lower":"1980-01-01",
    "date:inception_upper":"1980-01-31",
    "iso:country":"GB",
    "wof:name":"DT3 5ES",
    "wof:placetype":"postalcode"
},
  "geometry": {"coordinates":[-2.462748,50.628598],"type":"Point"}
}