{
  "type": "Feature",
  "properties": {
    "iso:country":"GB",
    "wof:name":"DT6 3AL",
    "wof:placetype":"postalcode"
},
  "geometry": {"coordinates":[-2.75878964911937,50.73817073845792],"type":"Point"}
}