{
  "type": "Feature",
  "properties": {
    "iso:country": "GB",
    "wof:name": "DY3 3DH",
    "wof:placetype": "postalcode"
  },
  "geometry": {"coordinates":[-2.149103,52.526936],"type":"Point"}
}
