{
  "type": "Feature",
  "properties": {
    "iso:country": "GB",
    "wof:name": "EC4N 5AE",
    "wof:placetype": "postalcode"
  },
  "geometry": {"coordinates":[-0.090267,51.511733],"type":"Point"}
}
