{
  "type": "Feature",
  "properties": {
    "date:inception_lower": "2015-06-01",
    "date:inception_upper": "2015-06-01",
    "iso:country": "GB",
    "wof:name": "EC4N 5AE",
    "wof:placetype": "postalcode"
  },
  "geometry": {"coordinates":[-0.090267,51.511733],"type":"Point"}
}
