{
  "type": "Feature",
  "properties": {
    "iso:country":"GB",
    "wof:name":"EC4N 5AE",
    "wof:placetype":"postalcode"
},
  "geometry": {"coordinates":[-0.09044964187635,51.51176985953053],"type":"Point"}
}