{
  "type": "Feature",
  "properties": {
    "date:inception_lower": "2016-07-01",
    "date:inception_upper": "2016-07-01",
    "iso:country": "GB",
    "wof:name": "NW9 0AZ",
    "wof:placetype": "postalcode"
  },
  "geometry": {"coordinates":[-0.262043,51.594398],"type":"Point"}
}
