{
  "type": "Feature",
  "properties": {
    "iso:country":"GB",
    "wof:name":"LS24 8DZ",
    "wof:placetype":"postalcode"
},
  "geometry": {"coordinates":[-1.24082080223483,53.89133490591269],"type":"Point"}
}