{
  "type": "Feature",
  "properties": {
    "iso:country":"GB",
    "wof:name":"G72 8UZ",
    "wof:placetype":"postalcode"
},
  "geometry": {"coordinates":[-4.14269322053179,55.80884865781759],"type":"Point"}
}