{
  "type": "Feature",
  "properties": {
    "iso:country":"GB",
    "wof:name":"SO51 6ZR",
    "wof:placetype":"postalcode"
},
  "geometry": {"coordinates":[-1.61578318631147,50.99916336777748],"type":"Point"}
}