{
  "type": "Feature",
  "properties": {
    "iso:country": "GB",
    "wof:name": "M6 5LT",
    "wof:placetype": "postalcode"
  },
  "geometry": {"coordinates":[-2.2942,53.487315],"type":"Point"}
}
