{
  "type": "Feature",
  "properties": {
    "iso:country":"GB",
    "wof:name":"M6 5LT",
    "wof:placetype":"postalcode"
},
  "geometry": {"coordinates":[-2.29420053749745,53.48731465638162],"type":"Point"}
}