{
  "type": "Feature",
  "properties": {
    "iso:country": "GB",
    "wof:name": "RG14 1HL",
    "wof:placetype": "postalcode"
  },
  "geometry": {"coordinates":[-1.325932,51.403852],"type":"Point"}
}
