{
  "type": "Feature",
  "properties": {
    "iso:country":"GB",
    "wof:name":"RG14 1HL",
    "wof:placetype":"postalcode"
},
  "geometry": {"coordinates":[-1.3259322924706,51.40385176202248],"type":"Point"}
}