{
  "type": "Feature",
  "properties": {
    "date:inception_lower": "2006-05-01",
    "date:inception_upper": "2006-05-01",
    "iso:country": "GB",
    "wof:name": "RG14 1HL",
    "wof:placetype": "postalcode"
  },
  "geometry": {"coordinates":[-1.325932,51.403852],"type":"Point"}
}
