{
  "type": "Feature",
  "properties": {
    "iso:country": "GB",
    "wof:name": "WN8 8DQ",
    "wof:placetype": "postalcode"
  },
  "geometry": {"coordinates":[-2.797031,53.547957],"type":"Point"}
}
