{
  "type": "Feature",
  "properties": {
    "iso:country":"GB",
    "wof:name":"WN8 8DQ",
    "wof:placetype":"postalcode"
},
  "geometry": {"coordinates":[-2.79703115659048,53.54795653163247],"type":"Point"}
}