{
  "type": "Feature",
  "properties": {
    "date:inception_lower":"1980-01-01",
    "date:inception_upper":"1980-01-31",
    "iso:country":"GB",
    "wof:name":"WN8 8DQ",
    "wof:placetype":"postalcode"
},
  "geometry": {"coordinates":[-2.797031,53.547957],"type":"Point"}
}