{
  "type": "Feature",
  "properties": {
    "iso:country":"GB",
    "wof:name":"WA7 2EW",
    "wof:placetype":"postalcode"
},
  "geometry": {"coordinates":[-2.70185450461298,53.33317513723693],"type":"Point"}
}