{
  "type": "Feature",
  "properties": {
    "iso:country": "GB",
    "wof:name": "WA7 2EW",
    "wof:placetype": "postalcode"
  },
  "geometry": {"coordinates":[-2.701854,53.333175],"type":"Point"}
}
