{
  "type": "Feature",
  "properties": {
    "iso:country":"GB",
    "wof:name":"NE24 4HQ",
    "wof:placetype":"postalcode"
},
  "geometry": {"coordinates":[-1.5691888544077,55.10671663108226],"type":"Point"}
}