{
  "type": "Feature",
  "properties": {
    "date:inception_lower": "1980-01-01",
    "date:inception_upper": "1980-01-01",
    "iso:country": "GB",
    "wof:name": "NE24 4HQ",
    "wof:placetype": "postalcode"
  },
  "geometry": {"coordinates":[-1.569313,55.106723],"type":"Point"}
}
