{
  "type": "Feature",
  "properties": {
    "iso:country":"GB",
    "wof:name":"IP2 9PJ",
    "wof:placetype":"postalcode"
},
  "geometry": {"coordinates":[1.11633009197975,52.04347694752511],"type":"Point"}
}