{
  "type": "Feature",
  "properties": {
    "iso:country":"GB",
    "wof:name":"ML2 9AW",
    "wof:placetype":"postalcode"
},
  "geometry": {"coordinates":[-3.8723357192199,55.78578205775146],"type":"Point"}
}