{
  "type": "Feature",
  "properties": {
    "iso:country": "GB",
    "wof:name": "BS23 2TD",
    "wof:placetype": "postalcode"
  },
  "geometry": {"coordinates":[-2.966438,51.353263],"type":"Point"}
}
