{
  "type": "Feature",
  "properties": {
    "iso:country":"GB",
    "wof:name":"BS23 2TD",
    "wof:placetype":"postalcode"
},
  "geometry": {"coordinates":[-2.96643780378338,51.35326335816352],"type":"Point"}
}