{
  "type": "Feature",
  "properties": {
    "iso:country":"GB",
    "wof:name":"WV1 4PQ",
    "wof:placetype":"postalcode"
},
  "geometry": {"coordinates":[-2.14111008646477,52.59285359382375],"type":"Point"}
}