{
  "type": "Feature",
  "properties": {
    "iso:country": "GB",
    "wof:name": "WV1 4PQ",
    "wof:placetype": "postalcode"
  },
  "geometry": {"coordinates":[-2.141075,52.592905],"type":"Point"}
}
