{
  "type": "Feature",
  "properties": {
    "iso:country":"GB",
    "wof:name":"SA73 1SU",
    "wof:placetype":"postalcode"
},
  "geometry": {"coordinates":[-4.94640608630276,51.71073633277058],"type":"Point"}
}