{
  "type": "Feature",
  "properties": {
    "iso:country": "GB",
    "wof:name": "CH66 1SZ",
    "wof:placetype": "postalcode"
  },
  "geometry": {"coordinates":[-2.924865,53.289368],"type":"Point"}
}
