{
  "type": "Feature",
  "properties": {
    "iso:country": "GB",
    "wof:name": "NG15 9HS",
    "wof:placetype": "postalcode"
  },
  "geometry": {"coordinates":[-1.164026,53.073149],"type":"Point"}
}
