{
  "type": "Feature",
  "properties": {
    "iso:country":"GB",
    "wof:name":"N12 9UE",
    "wof:placetype":"postalcode"
},
  "geometry": {"coordinates":[-0.16913198392884,51.61605944721572],"type":"Point"}
}