{
  "type": "Feature",
  "properties": {
    "iso:country":"GB",
    "wof:name":"L19 2JJ",
    "wof:placetype":"postalcode"
},
  "geometry": {"coordinates":[-2.9044656454222,53.35689010647869],"type":"Point"}
}