{
  "type": "Feature",
  "properties": {
    "iso:country":"GB",
    "wof:name":"FK1 4PE",
    "wof:placetype":"postalcode"
},
  "geometry": {"coordinates":[-3.81691307596856,56.00057369149894],"type":"Point"}
}