{
  "type": "Feature",
  "properties": {
    "date:inception_lower": "1980-01-01",
    "date:inception_upper": "1980-01-01",
    "iso:country": "GB",
    "wof:name": "FK1 4PE",
    "wof:placetype": "postalcode"
  },
  "geometry": {"coordinates":[-3.816913,56.000574],"type":"Point"}
}
