{
  "type": "Feature",
  "properties": {
    "iso:country":"GB",
    "wof:name":"B68 9NY",
    "wof:placetype":"postalcode"
},
  "geometry": {"coordinates":[-1.99527314740092,52.48793625363809],"type":"Point"}
}