{
  "type": "Feature",
  "properties": {
    "iso:country":"GB",
    "wof:name":"BR4 9LR",
    "wof:placetype":"postalcode"
},
  "geometry": {"coordinates":[-0.01535709160368,51.37154018472663],"type":"Point"}
}