{
  "type": "Feature",
  "properties": {
    "iso:country":"GB",
    "wof:name":"RG5 3DH",
    "wof:placetype":"postalcode"
},
  "geometry": {"coordinates":[-0.91313902495158,51.45323745005532],"type":"Point"}
}