{
  "type": "Feature",
  "properties": {
    "date:inception_lower": "2024-01-01",
    "date:inception_upper": "2024-01-01",
    "iso:country": "GB",
    "wof:name": "SA4 9HS",
    "wof:placetype": "postalcode"
  },
  "geometry": {"coordinates":[-4.000584,51.66716],"type":"Point"}
}
