{
  "type": "Feature",
  "properties": {
    "iso:country": "GB",
    "wof:name": "NE68 7WH",
    "wof:placetype": "postalcode"
  },
  "geometry": {"coordinates":[-1.665525,55.578667],"type":"Point"}
}
