{
  "type": "Feature",
  "properties": {
    "iso:country": "GB",
    "wof:name": "CB23 1LF",
    "wof:placetype": "postalcode"
  },
  "geometry": {"coordinates":[0.056049,52.148485],"type":"Point"}
}
