{
  "type": "Feature",
  "properties": {
    "iso:country":"GB",
    "wof:name":"CB23 1LF",
    "wof:placetype":"postalcode"
},
  "geometry": {"coordinates":[0.05604885646729,52.148485120042],"type":"Point"}
}