{
  "type": "Feature",
  "properties": {
    "iso:country": "GB",
    "wof:name": "EX34 7AG",
    "wof:placetype": "postalcode"
  },
  "geometry": {"coordinates":[-4.19648,51.173064],"type":"Point"}
}
