{
  "type": "Feature",
  "properties": {
    "date:inception_lower": "2019-05-01",
    "date:inception_upper": "2019-05-01",
    "iso:country": "GB",
    "wof:name": "LS27 0FX",
    "wof:placetype": "postalcode"
  },
  "geometry": {"coordinates":[-1.61916,53.737734],"type":"Point"}
}
