{
  "type": "Feature",
  "properties": {
    "iso:country":"GB",
    "wof:name":"LN5 9AD",
    "wof:placetype":"postalcode"
},
  "geometry": {"coordinates":[-0.54977339203477,53.19475998691055],"type":"Point"}
}