{
  "type": "Feature",
  "properties": {
    "date:inception_lower": "1992-08-01",
    "date:inception_upper": "1992-08-01",
    "iso:country": "GB",
    "wof:name": "LN5 9AD",
    "wof:placetype": "postalcode"
  },
  "geometry": {"coordinates":[-0.549397,53.193906],"type":"Point"}
}
