{
  "type": "Feature",
  "properties": {
    "iso:country": "GB",
    "wof:name": "LN5 9AD",
    "wof:placetype": "postalcode"
  },
  "geometry": {"coordinates":[-0.549773,53.19476],"type":"Point"}
}
