{
  "type": "Feature",
  "properties": {
    "iso:country":"GB",
    "wof:name":"SK13 7PY",
    "wof:placetype":"postalcode"
},
  "geometry": {"coordinates":[-1.92894954537148,53.45054308646951],"type":"Point"}
}