{
  "type": "Feature",
  "properties": {
    "date:inception_lower": "1997-12-01",
    "date:inception_upper": "1997-12-01",
    "iso:country": "GB",
    "wof:name": "SK13 7PY",
    "wof:placetype": "postalcode"
  },
  "geometry": {"coordinates":[-1.928949,53.450543],"type":"Point"}
}
