{
  "type": "Feature",
  "properties": {
    "date:inception_lower": "1999-06-01",
    "date:inception_upper": "1999-06-01",
    "iso:country": "GB",
    "wof:name": "BR1 5PL",
    "wof:placetype": "postalcode"
  },
  "geometry": {"coordinates":[-0.000191,51.429403],"type":"Point"}
}
