{
  "type": "Feature",
  "properties": {
    "iso:country":"GB",
    "wof:name":"BR1 5PL",
    "wof:placetype":"postalcode"
},
  "geometry": {"coordinates":[-0.00019109675144,51.42940290637803],"type":"Point"}
}