{
  "type": "Feature",
  "properties": {
    "date:inception_lower": "1980-01-01",
    "date:inception_upper": "1980-01-01",
    "iso:country": "GB",
    "wof:name": "WF8 1QG",
    "wof:placetype": "postalcode"
  },
  "geometry": {"coordinates":[-1.30515,53.694048],"type":"Point"}
}
