{
  "type": "Feature",
  "properties": {
    "iso:country":"GB",
    "wof:name":"SA16 0RH",
    "wof:placetype":"postalcode"
},
  "geometry": {"coordinates":[-4.24384463659091,51.68988824010516],"type":"Point"}
}