{
  "type": "Feature",
  "properties": {
    "date:inception_lower": "1980-01-01",
    "date:inception_upper": "1980-01-01",
    "iso:country": "GB",
    "wof:name": "SA16 0RH",
    "wof:placetype": "postalcode"
  },
  "geometry": {"coordinates":[-4.24387,51.689825],"type":"Point"}
}
