{
  "type": "Feature",
  "properties": {
    "iso:country":"GB",
    "wof:name":"SP11 0JR",
    "wof:placetype":"postalcode"
},
  "geometry": {"coordinates":[-1.48937420035895,51.30044482519597],"type":"Point"}
}