{
  "type": "Feature",
  "properties": {
    "iso:country": "GB",
    "wof:name": "SP11 0JR",
    "wof:placetype": "postalcode"
  },
  "geometry": {"coordinates":[-1.48936,51.300442],"type":"Point"}
}
