{
  "type": "Feature",
  "properties": {
    "iso:country":"GB",
    "wof:name":"TN13 3XL",
    "wof:placetype":"postalcode"
},
  "geometry": {"coordinates":[0.20039462741477,51.28015545111022],"type":"Point"}
}