{
  "type": "Feature",
  "properties": {
    "iso:country":"GB",
    "wof:name":"EC1M 6DU",
    "wof:placetype":"postalcode"
},
  "geometry": {"coordinates":[-0.10316876404451,51.520249396018],"type":"Point"}
}