{
  "type": "Feature",
  "properties": {
    "date:inception_lower":"1998-12-01",
    "date:inception_upper":"1998-12-31",
    "iso:country":"GB",
    "wof:name":"EC1M 6DU",
    "wof:placetype":"postalcode"
},
  "geometry": {"coordinates":[-0.103169,51.520249],"type":"Point"}
}