{
  "type": "Feature",
  "properties": {
    "date:inception_lower": "1991-09-01",
    "date:inception_upper": "1991-09-01",
    "iso:country": "GB",
    "wof:name": "TN2 4XW",
    "wof:placetype": "postalcode"
  },
  "geometry": {"coordinates":[0.296006,51.142507],"type":"Point"}
}
