{
  "type": "Feature",
  "properties": {
    "iso:country": "GB",
    "wof:name": "TN2 4XW",
    "wof:placetype": "postalcode"
  },
  "geometry": {"coordinates":[0.296006,51.142507],"type":"Point"}
}
