{
  "type": "Feature",
  "properties": {
    "iso:country":"GB",
    "wof:name":"TN2 4XW",
    "wof:placetype":"postalcode"
},
  "geometry": {"coordinates":[0.29586367673922,51.14248455542253],"type":"Point"}
}