{
  "type": "Feature",
  "properties": {
    "iso:country":"GB",
    "wof:name":"L17 4LL",
    "wof:placetype":"postalcode"
},
  "geometry": {"coordinates":[-2.94302156041586,53.38144606299085],"type":"Point"}
}