{
  "type": "Feature",
  "properties": {
    "iso:country":"GB",
    "wof:name":"NG16 1BY",
    "wof:placetype":"postalcode"
},
  "geometry": {"coordinates":[-1.23619687400879,52.99868970065771],"type":"Point"}
}