{
  "type": "Feature",
  "properties": {
    "iso:country":"GB",
    "wof:name":"SN15 3FU",
    "wof:placetype":"postalcode"
},
  "geometry": {"coordinates":[-2.11070454112383,51.44600031916871],"type":"Point"}
}