{
  "type": "Feature",
  "properties": {
    "iso:country":"GB",
    "wof:name":"W9 3DT",
    "wof:placetype":"postalcode"
},
  "geometry": {"coordinates":[-0.20201130810023,51.52746239003649],"type":"Point"}
}