{
  "type": "Feature",
  "properties": {
    "date:inception_lower": "1981-06-01",
    "date:inception_upper": "1981-06-01",
    "iso:country": "GB",
    "wof:name": "NG24 4BP",
    "wof:placetype": "postalcode"
  },
  "geometry": {"coordinates":[-0.803978,53.070327],"type":"Point"}
}
