{
  "type": "Feature",
  "properties": {
    "iso:country":"GB",
    "wof:name":"DT2 7HP",
    "wof:placetype":"postalcode"
},
  "geometry": {"coordinates":[-2.26769712174363,50.73801318094115],"type":"Point"}
}