{
  "type": "Feature",
  "properties": {
    "iso:country": "GB",
    "wof:name": "KA9 2RX",
    "wof:placetype": "postalcode"
  },
  "geometry": {"coordinates":[-4.585845,55.50027],"type":"Point"}
}
