{
  "type": "Feature",
  "properties": {
    "iso:country":"GB",
    "wof:name":"BL3 5AU",
    "wof:placetype":"postalcode"
},
  "geometry": {"coordinates":[-2.44151246718046,53.57243089196839],"type":"Point"}
}