{
  "type": "Feature",
  "properties": {
    "iso:country": "GB",
    "wof:name": "WD17 2BU",
    "wof:placetype": "postalcode"
  },
  "geometry": {"coordinates":[-0.396721,51.65547],"type":"Point"}
}
