{
  "type": "Feature",
  "properties": {
    "iso:country": "GB",
    "wof:name": "BD5 8EH",
    "wof:placetype": "postalcode"
  },
  "geometry": {"coordinates":[-1.752722,53.773059],"type":"Point"}
}
