{
  "type": "Feature",
  "properties": {
    "iso:country": "GB",
    "wof:name": "LL49 9PW",
    "wof:placetype": "postalcode"
  },
  "geometry": {"coordinates":[-4.141221,52.933281],"type":"Point"}
}
