{
  "type": "Feature",
  "properties": {
    "date:inception_lower": "1980-01-01",
    "date:inception_upper": "1980-01-01",
    "iso:country": "GB",
    "wof:name": "LL49 9PW",
    "wof:placetype": "postalcode"
  },
  "geometry": {"coordinates":[-4.142041,52.933626],"type":"Point"}
}
