{
  "type": "Feature",
  "properties": {
    "iso:country":"GB",
    "wof:name":"LL49 9PW",
    "wof:placetype":"postalcode"
},
  "geometry": {"coordinates":[-4.14121346596281,52.93326616034583],"type":"Point"}
}