{
  "type": "Feature",
  "properties": {
    "iso:country": "GB",
    "wof:name": "CW6 9AP",
    "wof:placetype": "postalcode"
  },
  "geometry": {"coordinates":[-2.636168,53.165244],"type":"Point"}
}
