{
  "type": "Feature",
  "properties": {
    "date:inception_lower": "1980-01-01",
    "date:inception_upper": "1980-01-01",
    "iso:country": "GB",
    "wof:name": "L12 0HH",
    "wof:placetype": "postalcode"
  },
  "geometry": {"coordinates":[-2.90251,53.44345],"type":"Point"}
}
