{
  "type": "Feature",
  "properties": {
    "iso:country":"GB",
    "wof:name":"PE22 9BN",
    "wof:placetype":"postalcode"
},
  "geometry": {"coordinates":[0.12776689474822,53.04110219870024],"type":"Point"}
}