{
  "type": "Feature",
  "properties": {
    "iso:country":"GB",
    "wof:name":"MK3 7SU",
    "wof:placetype":"postalcode"
},
  "geometry": {"coordinates":[-0.75691137387057,52.00706959493161],"type":"Point"}
}