{
  "type": "Feature",
  "properties": {
    "iso:country": "GB",
    "wof:name": "MK3 7SU",
    "wof:placetype": "postalcode"
  },
  "geometry": {"coordinates":[-0.756911,52.00707],"type":"Point"}
}
