{
  "type": "Feature",
  "properties": {
    "iso:country":"GB",
    "wof:name":"PE28 5NN",
    "wof:placetype":"postalcode"
},
  "geometry": {"coordinates":[-0.35686767340533,52.43250045550952],"type":"Point"}
}