{
  "type": "Feature",
  "properties": {
    "date:inception_lower": "1980-01-01",
    "date:inception_upper": "1980-01-01",
    "iso:country": "GB",
    "wof:name": "DG13 0EQ",
    "wof:placetype": "postalcode"
  },
  "geometry": {"coordinates":[-2.989775,55.145273],"type":"Point"}
}
