{
  "type": "Feature",
  "properties": {
    "iso:country":"GB",
    "wof:name":"DG13 0EQ",
    "wof:placetype":"postalcode"
},
  "geometry": {"coordinates":[-2.98977246871622,55.14526871047629],"type":"Point"}
}