{
  "type": "Feature",
  "properties": {
    "date:inception_lower": "1980-01-01",
    "date:inception_upper": "1980-01-01",
    "iso:country": "GB",
    "wof:name": "SS7 5DE",
    "wof:placetype": "postalcode"
  },
  "geometry": {"coordinates":[0.549765,51.551309],"type":"Point"}
}
