{
  "type": "Feature",
  "properties": {
    "date:inception_lower": "1980-01-01",
    "date:inception_upper": "1980-01-01",
    "iso:country": "GB",
    "wof:name": "GL55 6NP",
    "wof:placetype": "postalcode"
  },
  "geometry": {"coordinates":[-1.725214,52.058466],"type":"Point"}
}
