{
  "type": "Feature",
  "properties": {
    "iso:country":"GB",
    "wof:name":"EH9 1HQ",
    "wof:placetype":"postalcode"
},
  "geometry": {"coordinates":[-3.19351154576802,55.93778379972068],"type":"Point"}
}