{
  "type": "Feature",
  "properties": {
    "iso:country":"GB",
    "wof:name":"TQ6 9RE",
    "wof:placetype":"postalcode"
},
  "geometry": {"coordinates":[-3.57874358413782,50.34995167785502],"type":"Point"}
}