{
  "type": "Feature",
  "properties": {
    "date:inception_lower": "2015-06-01",
    "date:inception_upper": "2015-06-01",
    "iso:country": "GB",
    "wof:name": "SE10 0GQ",
    "wof:placetype": "postalcode"
  },
  "geometry": {"coordinates":[0.013777,51.496421],"type":"Point"}
}
