{
  "type": "Feature",
  "properties": {
    "date:inception_lower": "1980-01-01",
    "date:inception_upper": "1980-01-01",
    "iso:country": "GB",
    "wof:name": "BS7 8NA",
    "wof:placetype": "postalcode"
  },
  "geometry": {"coordinates":[-2.601257,51.480665],"type":"Point"}
}
