{
  "type": "Feature",
  "properties": {
    "date:inception_lower": "1999-12-01",
    "date:inception_upper": "1999-12-01",
    "iso:country": "GB",
    "wof:name": "OX18 4XU",
    "wof:placetype": "postalcode"
  },
  "geometry": {"coordinates":[-1.593071,51.757626],"type":"Point"}
}
