{
  "type": "Feature",
  "properties": {
    "iso:country":"GB",
    "wof:name":"RH16 4AF",
    "wof:placetype":"postalcode"
},
  "geometry": {"coordinates":[-0.10980159777036,50.99782446233619],"type":"Point"}
}