{
  "type": "Feature",
  "properties": {
    "iso:country": "GB",
    "wof:name": "B98 7QN",
    "wof:placetype": "postalcode"
  },
  "geometry": {"coordinates":[-1.921142,52.291365],"type":"Point"}
}
