{
  "type": "Feature",
  "properties": {
    "iso:country":"GB",
    "wof:name":"B98 7QN",
    "wof:placetype":"postalcode"
},
  "geometry": {"coordinates":[-1.92125256172261,52.29131483945662],"type":"Point"}
}