{
  "type": "Feature",
  "properties": {
    "iso:country": "GB",
    "wof:name": "SK6 4ES",
    "wof:placetype": "postalcode"
  },
  "geometry": {"coordinates":[-2.076239,53.414577],"type":"Point"}
}
