{
  "type": "Feature",
  "properties": {
    "iso:country": "GB",
    "wof:name": "NP11 7FE",
    "wof:placetype": "postalcode"
  },
  "geometry": {"coordinates":[-3.1141,51.635879],"type":"Point"}
}
