{
  "type": "Feature",
  "properties": {
    "date:inception_lower": "2010-10-01",
    "date:inception_upper": "2010-10-01",
    "iso:country": "GB",
    "wof:name": "NP11 7FE",
    "wof:placetype": "postalcode"
  },
  "geometry": {"coordinates":[-3.1141,51.635879],"type":"Point"}
}
