{
  "type": "Feature",
  "properties": {
    "iso:country":"GB",
    "wof:name":"NP11 7FE",
    "wof:placetype":"postalcode"
},
  "geometry": {"coordinates":[-3.11409967516861,51.63587856857176],"type":"Point"}
}