{
  "type": "Feature",
  "properties": {
    "iso:country":"GB",
    "wof:name":"BN20 9QB",
    "wof:placetype":"postalcode"
},
  "geometry": {"coordinates":[0.24886424165365,50.81039717789649],"type":"Point"}
}