{
  "type": "Feature",
  "properties": {
    "iso:country": "GB",
    "wof:name": "DN5 7HD",
    "wof:placetype": "postalcode"
  },
  "geometry": {"coordinates":[-1.275206,53.522011],"type":"Point"}
}
