{
  "type": "Feature",
  "properties": {
    "date:inception_lower": "2022-11-01",
    "date:inception_upper": "2022-11-01",
    "iso:country": "GB",
    "wof:name": "SP4 7ZE",
    "wof:placetype": "postalcode"
  },
  "geometry": {"coordinates":[-1.774382,51.160522],"type":"Point"}
}
