{
  "type": "Feature",
  "properties": {
    "iso:country":"GB",
    "wof:name":"OX1 4LF",
    "wof:placetype":"postalcode"
},
  "geometry": {"coordinates":[-1.25779390758093,51.74478530430356],"type":"Point"}
}