{
  "type": "Feature",
  "properties": {
    "iso:country":"GB",
    "wof:name":"WF11 9EF",
    "wof:placetype":"postalcode"
},
  "geometry": {"coordinates":[-1.26626904777935,53.73608790388221],"type":"Point"}
}