{
  "type": "Feature",
  "properties": {
    "iso:country":"GB",
    "wof:name":"HA5 2AJ",
    "wof:placetype":"postalcode"
},
  "geometry": {"coordinates":[-0.3968266362067,51.59778164466923],"type":"Point"}
}