{
  "type": "Feature",
  "properties": {
    "iso:country":"GB",
    "wof:name":"PH7 4EL",
    "wof:placetype":"postalcode"
},
  "geometry": {"coordinates":[-3.84818323595537,56.37120226117464],"type":"Point"}
}