{
  "type": "Feature",
  "properties": {
    "iso:country":"GB",
    "wof:name":"WR6 6LG",
    "wof:placetype":"postalcode"
},
  "geometry": {"coordinates":[-2.31264591589737,52.28166641366169],"type":"Point"}
}