{
  "type": "Feature",
  "properties": {
    "iso:country":"GB",
    "wof:name":"NG34 9TQ",
    "wof:placetype":"postalcode"
},
  "geometry": {"coordinates":[-0.34349128173429,53.05494574946617],"type":"Point"}
}