{
  "type": "Feature",
  "properties": {
    "iso:country": "GB",
    "wof:name": "NG34 9TQ",
    "wof:placetype": "postalcode"
  },
  "geometry": {"coordinates":[-0.343491,53.054946],"type":"Point"}
}
