{
  "type": "Feature",
  "properties": {
    "date:inception_lower": "1980-01-01",
    "date:inception_upper": "1980-01-01",
    "iso:country": "GB",
    "wof:name": "NG34 9TQ",
    "wof:placetype": "postalcode"
  },
  "geometry": {"coordinates":[-0.343491,53.054946],"type":"Point"}
}
