{
  "type": "Feature",
  "properties": {
    "date:inception_lower": "1994-12-01",
    "date:inception_upper": "1994-12-01",
    "iso:country": "GB",
    "wof:name": "SO17 1SA",
    "wof:placetype": "postalcode"
  },
  "geometry": {"coordinates":[-1.390957,50.927888],"type":"Point"}
}
