{
  "type": "Feature",
  "properties": {
    "iso:country":"GB",
    "wof:name":"OX18 4US",
    "wof:placetype":"postalcode"
},
  "geometry": {"coordinates":[-1.69880021579641,51.82153835966471],"type":"Point"}
}