{
  "type": "Feature",
  "properties": {
    "date:inception_lower": "1991-09-01",
    "date:inception_upper": "1991-09-01",
    "iso:country": "GB",
    "wof:name": "OX18 4US",
    "wof:placetype": "postalcode"
  },
  "geometry": {"coordinates":[-1.69777,51.821884],"type":"Point"}
}
