{
  "type": "Feature",
  "properties": {
    "iso:country":"GB",
    "wof:name":"CF31 4DD",
    "wof:placetype":"postalcode"
},
  "geometry": {"coordinates":[-3.60246056587087,51.50926515763544],"type":"Point"}
}