{
  "type": "Feature",
  "properties": {
    "iso:country":"GB",
    "wof:name":"HX2 7SY",
    "wof:placetype":"postalcode"
},
  "geometry": {"coordinates":[-1.92640327635016,53.7393704241152],"type":"Point"}
}