{
  "type": "Feature",
  "properties": {
    "iso:country": "GB",
    "wof:name": "PE4 5EG",
    "wof:placetype": "postalcode"
  },
  "geometry": {"coordinates":[-0.279351,52.628506],"type":"Point"}
}
