{
  "type": "Feature",
  "properties": {
    "iso:country":"GB",
    "wof:name":"PE4 5EG",
    "wof:placetype":"postalcode"
},
  "geometry": {"coordinates":[-0.27935123541959,52.62850609315882],"type":"Point"}
}