{
  "type": "Feature",
  "properties": {
    "iso:country": "GB",
    "wof:name": "EH7 4FJ",
    "wof:placetype": "postalcode"
  },
  "geometry": {"coordinates":[-3.18073,55.962764],"type":"Point"}
}
