{
  "type": "Feature",
  "properties": {
    "iso:country": "GB",
    "wof:name": "DN7 5TF",
    "wof:placetype": "postalcode"
  },
  "geometry": {"coordinates":[-1.048912,53.621548],"type":"Point"}
}
