{
  "type": "Feature",
  "properties": {
    "iso:country":"GB",
    "wof:name":"DN7 5TF",
    "wof:placetype":"postalcode"
},
  "geometry": {"coordinates":[-1.04891163874648,53.62154804117861],"type":"Point"}
}