{
  "type": "Feature",
  "properties": {
    "date:inception_lower": "2022-11-01",
    "date:inception_upper": "2022-11-01",
    "iso:country": "GB",
    "wof:name": "ME14 9BU",
    "wof:placetype": "postalcode"
  },
  "geometry": {"coordinates":[0.563687,51.237694],"type":"Point"}
}
