{
  "type": "Feature",
  "properties": {
    "iso:country": "GB",
    "wof:name": "S72 9DL",
    "wof:placetype": "postalcode"
  },
  "geometry": {"coordinates":[-1.389619,53.606494],"type":"Point"}
}
