{
  "type": "Feature",
  "properties": {
    "iso:country":"GB",
    "wof:name":"S72 9DL",
    "wof:placetype":"postalcode"
},
  "geometry": {"coordinates":[-1.3896195032853,53.60649396693584],"type":"Point"}
}