{
  "type": "Feature",
  "properties": {
    "iso:country": "GB",
    "wof:name": "NG32 2LZ",
    "wof:placetype": "postalcode"
  },
  "geometry": {"coordinates":[-0.616407,52.945412],"type":"Point"}
}
