{
  "type": "Feature",
  "properties": {
    "iso:country":"GB",
    "wof:name":"NG32 2LZ",
    "wof:placetype":"postalcode"
},
  "geometry": {"coordinates":[-0.61640713831363,52.94541162128512],"type":"Point"}
}