{
  "type": "Feature",
  "properties": {
    "date:inception_lower":"1995-01-01",
    "date:inception_upper":"1995-01-31",
    "iso:country":"GB",
    "wof:name":"NG32 2LZ",
    "wof:placetype":"postalcode"
},
  "geometry": {"coordinates":[-0.616407,52.945412],"type":"Point"}
}