{
  "type": "Feature",
  "properties": {
    "iso:country":"GB",
    "wof:name":"TF11 9PQ",
    "wof:placetype":"postalcode"
},
  "geometry": {"coordinates":[-2.40853270040661,52.67002112323621],"type":"Point"}
}