{
  "type": "Feature",
  "properties": {
    "date:inception_lower":"1980-01-01",
    "date:inception_upper":"1980-01-31",
    "iso:country":"GB",
    "wof:name":"SA68 0PG",
    "wof:placetype":"postalcode"
},
  "geometry": {"coordinates":[-4.768783,51.745755],"type":"Point"}
}