{
  "type": "Feature",
  "properties": {
    "iso:country":"GB",
    "wof:name":"SA68 0PG",
    "wof:placetype":"postalcode"
},
  "geometry": {"coordinates":[-4.76878346959362,51.74575479710249],"type":"Point"}
}