{
  "type": "Feature",
  "properties": {
    "iso:country": "GB",
    "wof:name": "SA11 3UD",
    "wof:placetype": "postalcode"
  },
  "geometry": {"coordinates":[-3.79327,51.65368],"type":"Point"}
}
