{
  "type": "Feature",
  "properties": {
    "iso:country":"GB",
    "wof:name":"SA11 3UD",
    "wof:placetype":"postalcode"
},
  "geometry": {"coordinates":[-3.79327002124349,51.65367984334785],"type":"Point"}
}