{
  "type": "Feature",
  "properties": {
    "iso:country": "GB",
    "wof:name": "SP11 6EQ",
    "wof:placetype": "postalcode"
  },
  "geometry": {"coordinates":[-1.407747,51.255548],"type":"Point"}
}
