{
  "type": "Feature",
  "properties": {
    "iso:country":"GB",
    "wof:name":"SP11 6EQ",
    "wof:placetype":"postalcode"
},
  "geometry": {"coordinates":[-1.40786339511164,51.25545236330245],"type":"Point"}
}