{
  "type": "Feature",
  "properties": {
    "date:inception_lower": "2000-10-01",
    "date:inception_upper": "2000-10-01",
    "iso:country": "GB",
    "wof:name": "WD24 6RT",
    "wof:placetype": "postalcode"
  },
  "geometry": {"coordinates":[-0.397339,51.680812],"type":"Point"}
}
