{
  "type": "Feature",
  "properties": {
    "iso:country":"GB",
    "wof:name":"BN22 8NN",
    "wof:placetype":"postalcode"
},
  "geometry": {"coordinates":[0.29563590510972,50.78140667053553],"type":"Point"}
}