{
  "type": "Feature",
  "properties": {
    "date:inception_lower": "1980-01-01",
    "date:inception_upper": "1980-01-01",
    "iso:country": "GB",
    "wof:name": "NG17 8GF",
    "wof:placetype": "postalcode"
  },
  "geometry": {"coordinates":[-1.265103,53.103975],"type":"Point"}
}
