{
  "type": "Feature",
  "properties": {
    "iso:country":"GB",
    "wof:name":"LU1 5EB",
    "wof:placetype":"postalcode"
},
  "geometry": {"coordinates":[-0.42305232187256,51.87513203826609],"type":"Point"}
}