{
  "type": "Feature",
  "properties": {
    "iso:country":"GB",
    "wof:name":"OX10 8FN",
    "wof:placetype":"postalcode"
},
  "geometry": {"coordinates":[-1.11566455942205,51.60046953228397],"type":"Point"}
}