{
  "type": "Feature",
  "properties": {
    "iso:country": "GB",
    "wof:name": "OX10 8FN",
    "wof:placetype": "postalcode"
  },
  "geometry": {"coordinates":[-1.115665,51.60047],"type":"Point"}
}
