{
  "type": "Feature",
  "properties": {
    "iso:country": "GB",
    "wof:name": "RM12 5AG",
    "wof:placetype": "postalcode"
  },
  "geometry": {"coordinates":[0.204611,51.537836],"type":"Point"}
}
