{
  "type": "Feature",
  "properties": {
    "iso:country":"GB",
    "wof:name":"RM12 5AG",
    "wof:placetype":"postalcode"
},
  "geometry": {"coordinates":[0.20461127982646,51.53783565640418],"type":"Point"}
}