{
  "type": "Feature",
  "properties": {
    "iso:country":"GB",
    "wof:name":"DD9 7TZ",
    "wof:placetype":"postalcode"
},
  "geometry": {"coordinates":[-2.64399793553711,56.78868556643593],"type":"Point"}
}