{
  "type": "Feature",
  "properties": {
    "iso:country":"GB",
    "wof:name":"TR11 3HL",
    "wof:placetype":"postalcode"
},
  "geometry": {"coordinates":[-5.06606930305307,50.15162851024785],"type":"Point"}
}