{
  "type": "Feature",
  "properties": {
    "date:inception_lower": "1980-01-01",
    "date:inception_upper": "1980-01-01",
    "iso:country": "GB",
    "wof:name": "TR11 3HL",
    "wof:placetype": "postalcode"
  },
  "geometry": {"coordinates":[-5.066069,50.151629],"type":"Point"}
}
