{
  "type": "Feature",
  "properties": {
    "iso:country":"GB",
    "wof:name":"SR5 4JG",
    "wof:placetype":"postalcode"
},
  "geometry": {"coordinates":[-1.45118979196586,54.92950957415323],"type":"Point"}
}