{
  "type": "Feature",
  "properties": {
    "iso:country": "GB",
    "wof:name": "SR5 4JG",
    "wof:placetype": "postalcode"
  },
  "geometry": {"coordinates":[-1.45119,54.92951],"type":"Point"}
}
