{
  "type": "Feature",
  "properties": {
    "iso:country":"GB",
    "wof:name":"KA21 6GP",
    "wof:placetype":"postalcode"
},
  "geometry": {"coordinates":[-4.78753938635382,55.65187491884172],"type":"Point"}
}