{
  "type": "Feature",
  "properties": {
    "iso:country": "GB",
    "wof:name": "KA21 6GP",
    "wof:placetype": "postalcode"
  },
  "geometry": {"coordinates":[-4.787539,55.651875],"type":"Point"}
}
