{
  "type": "Feature",
  "properties": {
    "date:inception_lower": "2007-05-01",
    "date:inception_upper": "2007-05-01",
    "iso:country": "GB",
    "wof:name": "KA21 6GP",
    "wof:placetype": "postalcode"
  },
  "geometry": {"coordinates":[-4.787539,55.651875],"type":"Point"}
}
