{
  "type": "Feature",
  "properties": {
    "iso:country":"GB",
    "wof:name":"AB43 6JS",
    "wof:placetype":"postalcode"
},
  "geometry": {"coordinates":[-2.19813073445433,57.59644817309934],"type":"Point"}
}