{
  "type": "Feature",
  "properties": {
    "iso:country":"GB",
    "wof:name":"SO16 9NL",
    "wof:placetype":"postalcode"
},
  "geometry": {"coordinates":[-1.45673568639211,50.93289711961886],"type":"Point"}
}