{
  "type": "Feature",
  "properties": {
    "iso:country": "GB",
    "wof:name": "MK17 8EL",
    "wof:placetype": "postalcode"
  },
  "geometry": {"coordinates":[-0.631856,52.01017],"type":"Point"}
}
