{
  "type": "Feature",
  "properties": {
    "date:inception_lower":"1999-12-01",
    "date:inception_upper":"1999-12-31",
    "iso:country":"GB",
    "wof:name":"LS7 4RE",
    "wof:placetype":"postalcode"
},
  "geometry": {"coordinates":[-1.531111,53.819001],"type":"Point"}
}