{
  "type": "Feature",
  "properties": {
    "iso:country":"GB",
    "wof:name":"AL3 4DG",
    "wof:placetype":"postalcode"
},
  "geometry": {"coordinates":[-0.34148739415514,51.75289914553173],"type":"Point"}
}