{
  "type": "Feature",
  "properties": {
    "date:inception_lower": "2024-01-01",
    "date:inception_upper": "2024-01-01",
    "iso:country": "GB",
    "wof:name": "DT10 1GF",
    "wof:placetype": "postalcode"
  },
  "geometry": {"coordinates":[-2.299465,50.935314],"type":"Point"}
}
