{
  "type": "Feature",
  "properties": {
    "iso:country":"GB",
    "wof:name":"SE11 4DS",
    "wof:placetype":"postalcode"
},
  "geometry": {"coordinates":[-0.11067778199028,51.4878715003919],"type":"Point"}
}